Workbook

Sheet December, 2021
B3: STAFF PAYROLL FOR THE MONTH OF DECEMBER, 2021
E4: ='[1]FEB 08'!E8/'[1]FEB 08'!M8 -> 0.22 | H4: ='[1]FEB 08'!F8/'[1]FEB 08'!Q8 -> 0.3
B5: STAFF NAME | T5: DEDUCTIONS | Z5: NET SALARY
C6: DESIGNATION | D6: SALARY | E6: BASIC | L6: MOTOR/ | M6: RESEARCH | N6: HARDSHIP | O6: LEAVE | P6: OUT FIT | Q6: LEGISLATIVE | R6: GROSS | Y6: NOVEMBER,2021 | Z6: DECEMBER,2021
D7: LEVEL | E7: SALARY | F7: SALARY/ALLOWCE AREARS | G7: RENT | H7: UTILITY | I7: DOMESTIC | J7: ENTERT. | K7: FURNIT. | L7: FUEL | M7: ALLOWANCE | N7: ALLOWANCE | O7: ALLCE | P7: ALLCE | Q7: DUTY ALLCE | R7: SALARY | S7: AUCTION | T7: COOP SOCIETY | U7: COOP. LOAN RECOVERY | V7: NHF DEDUCTION | W7: PAYE | X7: TOTAL
A8: S/N | B8: DG OFFICE | E8: N | H8: N | R8: N | W8: N
A9: 1 | B9: PROF. ABUBAKAR O. SULAIMAN | C9: DIRECTOR GENERAL | D9: CONSOL | E9: 160488.75 | G9: 320977.5 | H9: 48146.63 | I9: 120366.57 | J9: 72219.94 | K9: 0 | L9: 120366.57 | M9: =250000 -> 250000 | O9: 16048.88 | P9: 25000 | Q9: 25235 | R9: =Q9+P9+O9+N9+M9+L9+K9+J9+I9+H9+G9+F9+E9 -> 1158849.8 | W9: 113176.97 | X9: =W9+V9+U9+T9+S9 -> 113176.97 | Y9: 1045672.9 | Z9: =R9-X9 -> 1045672.9
A10: 2 | B10: DR ADEYEMI AKEEB FAJINGBESI | C10: DIR. SPECIAL DUTIES, DG OFFICE | D10: 17(9) | E10: 81740.02 | G10: =E10*300% -> 245220.06 | H10: =E10*7.5% -> 6130.5015 | I10: 80244.38 | J10: =E10*50% -> 40870.01 | K10: =E10*350% -> 286090.07 | L10: =E10*100% -> 81740.02 | M10: =200000 -> 200000 | O10: =E10*10% -> 8174.002 | P10: 20000 | Q10: 0 | R10: =Q10+P10+O10+N10+M10+L10+K10+J10+I10+H10+G10+F10+E10 -> 1050209.1 | T10: 200000 | U10: =59722.22 -> 59722.22 | V10: ='[2]Jan 2021'!$H$35 -> 2043.5005 | W10: 52776.63 | X10: =W10+V10+U10+T10+S10 -> 314542.35 | Y10: 735666.71 | Z10: =R10-X10 -> 735666.71
A11: 3 | B11: SARAFADEEN ALABELEWE | C11: SA- ADMIN | D11: 16(9) | E11: =42653.17 -> 42653.17 | G11: =E11*300% -> 127959.51 | H11: =E11*7.5% -> 3198.9877 | I11: 40122.19 | J11: =E11*50% -> 21326.585 | K11: =E11*350% -> 149286.1 | L11: =E11*100% -> 42653.17 | N11: =90000 -> 90000 | O11: =E11*10% -> 4265.317 | P11: 20000 | R11: =Q11+P11+O11+N11+M11+L11+K11+J11+I11+H11+G11+F11+E11 -> 541465.02 | T11: =100000 -> 100000 | U11: =201736.11 -> 201736.11 | W11: 21618.09 | X11: =W11+V11+U11+T11+S11 -> 323354.2 | Y11: 218110.82 | Z11: =R11-X11 -> 218110.82
A12: 4 | B12: DR JAKE DABANG DAN AZUMI | C12: DEPUTY DIRECTOR TRAINING | D12: 16(7) | E12: =39662.25 -> 39662.25 | G12: =E12*300% -> 118986.75 | H12: =E12*7.5% -> 2974.6687 | I12: 40122.19 | J12: =E12*50% -> 19831.125 | K12: =E12*350% -> 138817.88 | L12: =E12*100% -> 39662.25 | M12: =180000 -> 180000 | O12: =E12*10% -> 3966.225 | P12: 20000 | Q12: 150000 | R12: =Q12+P12+O12+N12+M12+L12+K12+J12+I12+H12+G12+F12+E12 -> 754023.33 | V12: ='[2]Jan 2021'!$H$27 -> 991.55625 | W12: =21618.09 -> 21618.09 | X12: =W12+V12+U12+T12+S12 -> 22609.646 | Y12: 731413.69 | Z12: =R12-X12 -> 731413.69
A13: 5 | B13: DR ABDULSALAM NASIRU NAEEM | C13: SA ACADEMICS | D13: 16(7) | E13: =39662.25 -> 39662.25 | G13: =E13*300% -> 118986.75 | H13: =E13*7.5% -> 2974.6687 | I13: 40122.19 | J13: =E13*50% -> 19831.125 | K13: =E13*350% -> 138817.88 | L13: =E13*100% -> 39662.25 | M13: =180000 -> 180000 | O13: =E13*10% -> 3966.225 | P13: 20000 | Q13: =100000 -> 100000 | R13: =Q13+P13+O13+N13+M13+L13+K13+J13+I13+H13+G13+F13+E13 -> 704023.33 | W13: =21618.09 -> 21618.09 | X13: =W13+V13+U13+T13+S13 -> 21618.09 | Y13: 682405.24 | Z13: =R13-X13 -> 682405.24
A14: 6 | B14: RAHEEM USMAN AYIGORO | C14: SA-INFRASTRUCTURE | D14: 16 (7) | E14: =39662.25 -> 39662.25 | G14: =E14*300% -> 118986.75 | H14: =E14*7.5% -> 2974.6687 | I14: 40122.19 | J14: =E14*50% -> 19831.125 | K14: =E14*350% -> 138817.88 | L14: =E14*100% -> 39662.25 | N14: =90000 -> 90000 | O14: =E14*10% -> 3966.225 | P14: 20000 | Q14: 0 | R14: =Q14+P14+O14+N14+M14+L14+K14+J14+I14+H14+G14+F14+E14 -> 514023.33 | W14: =21618.09 -> 21618.09 | X14: =W14+V14+U14+T14+S14 -> 21618.09 | Y14: 492405.24 | Z14: =R14-X14 -> 492405.24
A15: 7 | B15: AKINSANMI ADEJOKE OLUKEMI | C15: HEAD INFORMATION/PROTOCOL | D15: 15(9) | E15: 33507.5 | G15: =E15*300% -> 100522.5 | H15: =E15*7.5% -> 2513.0625 | I15: 40122.19 | J15: =E15*50% -> 16753.75 | K15: =E15*350% -> 117276.25 | L15: =E15*100% -> 33507.5 | N15: =80000 -> 80000 | O15: =E15*10% -> 3350.75 | P15: 20000 | Q15: =100000 -> 100000 | R15: =Q15+P15+O15+N15+M15+L15+K15+J15+I15+H15+G15+F15+E15 -> 547553.5 | T15: =0 -> 0 | U15: 0 | V15: =837.69 -> 837.69 | W15: 15548.33 | X15: =W15+V15+U15+T15+S15 -> 16386.02 | Y15: 531167.48 | Z15: =R15-X15 -> 531167.48
A16: 8 | B16: DR IKEME ARTHUR J.O | C16: SNR RESEARCH FELLOW | D16: 15(9) | E16: =33507.5 -> 33507.5 | G16: =E16*300% -> 100522.5 | H16: =E16*7.5% -> 2513.0625 | I16: 40122.19 | J16: =E16*50% -> 16753.75 | K16: =E16*350% -> 117276.25 | L16: =E16*100% -> 33507.5 | N16: =80000 -> 80000 | O16: =E16*10% -> 3350.75 | P16: 20000 | Q16: 0 | R16: =Q16+P16+O16+N16+M16+L16+K16+J16+I16+H16+G16+F16+E16 -> 447553.5 | T16: =50000 -> 50000 | U16: =160416.67 -> 160416.67 | V16: ='[3]DECEMBER 2019'!$H$38 -> 837.6875 | W16: 15548.33 | X16: =W16+V16+U16+T16+S16 -> 226802.69 | Y16: 220750.82 | Z16: =R16-X16 -> 220750.82
A17: 9 | B17: MOSHOOD M. OLALERE | C17: MANAGER ADMIN DG's OFFICE | D17: 15(9) | E17: =33507.5 -> 33507.5 | G17: =E17*300% -> 100522.5 | H17: =E17*7.5% -> 2513.0625 | I17: 40122.19 | J17: =E17*50% -> 16753.75 | K17: =E17*350% -> 117276.25 | L17: =E17*100% -> 33507.5 | N17: =80000 -> 80000 | O17: =E17*10% -> 3350.75 | P17: 20000 | Q17: 0 | R17: =Q17+P17+O17+N17+M17+L17+K17+J17+I17+H17+G17+F17+E17 -> 447553.5 | T17: =20000 -> 20000 | U17: =179017.51 -> 179017.51 | V17: ='[3]DECEMBER 2019'!$H$35 -> 837.6875 | W17: 15548.33 | X17: =W17+V17+U17+T17+S17 -> 215403.53 | Y17: 232149.97 | Z17: =R17-X17 -> 232149.97
A18: 10 | B18: ANDRAWUS MUSA | C18: ASST. DIRECTOR, STORE | D18: 15(8) | E18: =32263.2 -> 32263.2 | G18: =E18*300% -> 96789.6 | H18: =E18*7.5% -> 2419.74 | I18: =40122.19 -> 40122.19 | J18: =E18*50% -> 16131.6 | K18: =E18*350% -> 112921.2 | L18: =E18*100% -> 32263.2 | N18: =80000 -> 80000 | O18: =E18*10% -> 3226.32 | P18: 20000 | Q18: 0 | R18: =SUM(E18:Q18) -> 436137.05 | T18: =50000 -> 50000 | U18: =90000 -> 90000 | V18: ='[2]Jan 2021'!$H$29 -> 806.58 | W18: =15548.33 -> 15548.33 | X18: =W18+V18+U18+T18+S18 -> 156354.91 | Y18: 279782.14 | Z18: =R18-X18 -> 279782.14
A19: 11 | B19: AYOBOLU OLAJIDE OLUFUNSHO | C19: ASST.DIR., INFORMATION | D19: 15 (7) | E19: 31018.84 | G19: =E19*300% -> 93056.52 | H19: =E19*7.5% -> 2326.413 | I19: 40122.19 | J19: =E19*50% -> 15509.42 | K19: =E19*350% -> 108565.94 | L19: =E19*100% -> 31018.84 | N19: =80000 -> 80000 | O19: =E19*10% -> 3101.884 | P19: 20000 | Q19: 0 | R19: =Q19+P19+O19+N19+M19+L19+K19+J19+I19+H19+G19+F19+E19 -> 424720.05 | T19: =25000 -> 25000 | U19: =52500 -> 52500 | W19: 15548.33 | X19: =W19+V19+U19+T19+S19 -> 93048.33 | Y19: 331671.72 | Z19: =R19-X19 -> 331671.72
A20: 12 | B20: HUSSEIN EGYE MUSA | C20: CHIEF PROTOCOL OFFICER | D20: 14(8) | E20: =25854.1 -> 25854.1 | G20: =E20*300% -> 77562.3 | H20: =E20*7.5% -> 1939.0575 | J20: =E20*50% -> 12927.05 | K20: =E20*350% -> 90489.35 | L20: =E20*100% -> 25854.1 | N20: =70000 -> 70000 | O20: =E20*10% -> 2585.41 | P20: 20000 | Q20: 50000 | R20: =Q20+P20+O20+N20+M20+L20+K20+J20+I20+H20+G20+F20+E20 -> 377211.37 | T20: 50000 | U20: =150000 -> 150000 | V20: 0 | W20: 7709.76 | X20: =W20+V20+U20+T20+S20 -> 207709.76 | Y20: 169501.61 | Z20: =R20-X20 -> 169501.61
A21: 13 | B21: DONALD E. MKPANAM | C21: CHIEF ICT OFFICER | D21: 14(8) | E21: =25854.1 -> 25854.1 | G21: =E21*300% -> 77562.3 | H21: =E21*7.5% -> 1939.0575 | J21: =E21*50% -> 12927.05 | K21: =E21*350% -> 90489.35 | L21: =E21*100% -> 25854.1 | N21: =70000 -> 70000 | O21: =E21*10% -> 2585.41 | P21: 20000 | Q21: 0 | R21: =Q21+P21+O21+N21+M21+L21+K21+J21+I21+H21+G21+F21+E21 -> 327211.37 | V21: ='[2]Jan 2021'!$H$28 -> 658.4825 | W21: 7709.76 | X21: =W21+V21+U21+T21+S21 -> 8368.2425 | Y21: 318843.12 | Z21: =R21-X21 -> 318843.12
A22: 14 | B22: JOY HARUNA MAKERI | C22: RESEARCH FELLOW 1 TRAINING | D22: 14(8) | E22: =25854.1 -> 25854.1 | G22: =E22*300% -> 77562.3 | H22: =E22*7.5% -> 1939.0575 | J22: =E22*50% -> 12927.05 | K22: =E22*350% -> 90489.35 | L22: =E22*100% -> 25854.1 | M22: =140000 -> 140000 | O22: =E22*10% -> 2585.41 | P22: 20000 | Q22: =50000+100000 -> 150000 | R22: =Q22+P22+O22+N22+M22+L22+K22+J22+I22+H22+G22+F22+E22 -> 547211.37 | W22: =7709.76 -> 7709.76 | X22: =W22+V22+U22+T22+S22 -> 7709.76 | Y22: 539501.61 | Z22: =R22-X22 -> 539501.61
A23: 15 | B23: ALI ABDULLAHI | C23: ASST. CHIEF ICT OFFICER | D23: 13(11) | E23: =26339.3 -> 26339.3 | G23: =E23*300% -> 79017.9 | H23: =E23*7.5% -> 1975.4475 | I23: 0 | J23: =E23*50% -> 13169.65 | K23: =E23*350% -> 92187.55 | L23: =E23*100% -> 26339.3 | N23: =70000 -> 70000 | O23: =E23*10% -> 2633.93 | P23: 15000 | Q23: =0 -> 0 | R23: =Q23+P23+O23+N23+M23+L23+K23+J23+I23+H23+G23+F23+E23 -> 326663.08 | W23: =7709.76 -> 7709.76 | X23: =W23+V23+U23+T23+S23 -> 7709.76 | Y23: 318953.32 | Z23: =R23-X23 -> 318953.32
A24: 16 | B24: MARIAM MOHAMMED BELLO | C24: PA- SPECIAL DUTIES | D24: 13 (7) | E24: =23074.99 -> 23074.99 | G24: =E24*300% -> 69224.97 | H24: =E24*7.5% -> 1730.6243 | I24: 0 | J24: =E24*50% -> 11537.495 | K24: =E24*350% -> 80762.465 | L24: =E24*100% -> 23074.99 | N24: =70000 -> 70000 | O24: =E24*10% -> 2307.499 | P24: 15000 | Q24: =100000+100000 -> 200000 | R24: =Q24+P24+O24+N24+M24+L24+K24+J24+I24+H24+G24+F24+E24 -> 496713.03 | W24: =7709.76 -> 7709.76 | X24: =W24+V24+U24+T24+S24 -> 7709.76 | Y24: 489003.27 | Z24: =R24-X24 -> 489003.27
A25: 17 | B25: PERCY TERFA GBAHABO | C25: HEAD, NILDS LIAISON OFFICE | D25: 13(7) | E25: =23074.99 -> 23074.99 | G25: =E25*300% -> 69224.97 | H25: =E25*7.5% -> 1730.6243 | I25: 0 | J25: =E25*50% -> 11537.495 | K25: =E25*350% -> 80762.465 | L25: =E25*100% -> 23074.99 | M25: =120000 -> 120000 | O25: =E25*10% -> 2307.499 | P25: 15000 | Q25: 0 | R25: =Q25+P25+O25+N25+M25+L25+K25+J25+I25+H25+G25+F25+E25 -> 346713.03 | T25: =10000 -> 10000 | U25: =98464.26 -> 98464.26 | W25: =7709.76 -> 7709.76 | X25: =W25+V25+U25+T25+S25 -> 116174.02 | Y25: 230539.01 | Z25: =R25-X25 -> 230539.01
A26: 18 | B26: ADUGBA RICHARD TERSEER | C26: INFORMATION OFFICER | D26: 10(9) | E26: =18281.64 -> 18281.64 | G26: =E26*300% -> 54844.92 | H26: =E26*7.5% -> 1371.123 | J26: =E26*50% -> 9140.82 | K26: =E26*350% -> 63985.74 | L26: =E26*100% -> 18281.64 | N26: =60000 -> 60000 | O26: =E26*10% -> 1828.164 | P26: 10000 | R26: =Q26+P26+O26+N26+M26+L26+K26+J26+I26+H26+G26+F26+E26 -> 237734.05 | T26: =20000 -> 20000 | U26: =111833.33 -> 111833.33 | W26: 3369.51 | X26: =W26+V26+U26+T26+S26 -> 135202.84 | Y26: 102531.21 | Z26: =R26-X26 -> 102531.21
A27: 19 | B27: CHRISTIAN MADUABUCHI ODO | C27: PRINCIPAL ICT OFFICER | D27: 12(7) | E27: =20749 -> 20749 | G27: =E27*300% -> 62247 | H27: =E27*7.5% -> 1556.175 | J27: =E27*50% -> 10374.5 | K27: =E27*350% -> 72621.5 | L27: =E27*100% -> 20749 | N27: =60000 -> 60000 | O27: =E27*10% -> 2074.9 | P27: 15000 | R27: =Q27+P27+O27+N27+M27+L27+K27+J27+I27+H27+G27+F27+E27 -> 265372.07 | T27: =20000 -> 20000 | U27: =82500 -> 82500 | V27: ='[2]Jan 2021'!$H$47 -> 481.92375 | W27: 3369.51 | X27: =W27+V27+U27+T27+S27 -> 106351.43 | Y27: 159020.64 | Z27: =R27-X27 -> 159020.64
A28: 20 | B28: HASSANA AHMED IBRAHIM | C28: PA- TO DG | D28: 10(8) | E28: =17784 -> 17784 | G28: =E28*300% -> 53352 | H28: =E28*7.5% -> 1333.8 | J28: =E28*50% -> 8892 | K28: =E28*350% -> 62244 | L28: =E28*100% -> 17784 | M28: =100000 -> 100000 | O28: =E28*10% -> 1778.4 | P28: 10000 | Q28: =100000 -> 100000 | R28: =Q28+P28+O28+N28+M28+L28+K28+J28+I28+H28+G28+F28+E28 -> 373168.2 | T28: =30000 -> 30000 | V28: ='[2]Jan 2021'!$H$55 -> 444.6 | W28: 3369.51 | X28: =W28+V28+U28+T28+S28 -> 33814.11 | Y28: 339354.09 | Z28: =R28-X28 -> 339354.09
A29: 21 | B29: VICTOR ASUKWO | C29: ICT OFFICER | D29: 8 (9) | E29: =13112.16 -> 13112.16 | G29: =E29*300% -> 39336.48 | H29: =E29*7.5% -> 983.412 | J29: =E29*50% -> 6556.08 | K29: =E29*350% -> 45892.56 | L29: =E29*100% -> 13112.16 | N29: =50000 -> 50000 | O29: =E29*10% -> 1311.216 | P29: 10000 | R29: =Q29+P29+O29+N29+M29+L29+K29+J29+I29+H29+G29+F29+E29 -> 180304.07 | W29: 1484.37 | X29: =W29+V29+U29+T29+S29 -> 1484.37 | Y29: 178819.7 | Z29: =R29-X29 -> 178819.7
A30: 22 | B30: SULEIMAN ABUBAKAR SODEEQ | C30: ASST. ADMIN. OFFICER | D30: 8(7) | E30: =12351.94 -> 12351.94 | G30: =E30*300% -> 37055.82 | H30: =E30*7.5% -> 926.3955 | J30: =E30*50% -> 6175.97 | K30: =E30*350% -> 43231.79 | L30: =E30*100% -> 12351.94 | N30: =50000 -> 50000 | O30: =E30*10% -> 1235.194 | P30: 10000 | R30: =Q30+P30+O30+N30+M30+L30+K30+J30+I30+H30+G30+F30+E30 -> 173329.05 | W30: =1484.37 -> 1484.37 | X30: =W30+V30+U30+T30+S30 -> 1484.37 | Y30: 171844.68 | Z30: =R30-X30 -> 171844.68
A31: 23 | B31: YAKUB OLUWATOYIN USMAN | C31: ASST. ADMIN. OFFICER | D31: 10(7) | E31: =17286.33 -> 17286.33 | G31: =E31*300% -> 51858.99 | H31: =E31*7.5% -> 1296.4748 | J31: =E31*50% -> 8643.165 | K31: =E31*350% -> 60502.155 | L31: =E31*100% -> 17286.33 | N31: =60000 -> 60000 | O31: =E31*10% -> 1728.633 | P31: 10000 | R31: =Q31+P31+O31+N31+M31+L31+K31+J31+I31+H31+G31+F31+E31 -> 228602.08 | T31: =10000 -> 10000 | U31: =34333.33 -> 34333.33 | W31: =1484.37 -> 1484.37 | X31: =W31+V31+U31+T31+S31 -> 45817.7 | Y31: 182784.38 | Z31: =R31-X31 -> 182784.38
A32: 24 | B32: ANTHONY EDET | C32: ASST. MGR M&E | D32: 13(8) | E32: =23891.12 -> 23891.12 | G32: =E32*300% -> 71673.36 | H32: =E32*7.5% -> 1791.834 | I32: 0 | J32: =E32*50% -> 11945.56 | K32: =E32*350% -> 83618.92 | L32: =E32*100% -> 23891.12 | N32: =70000 -> 70000 | O32: =E32*10% -> 2389.112 | P32: 15000 | Q32: 0 | R32: =Q32+P32+O32+N32+M32+L32+K32+J32+I32+H32+G32+F32+E32 -> 304201.03 | T32: 20000 | U32: =68750 -> 68750 | V32: ='[2]Jan 2021'!$H$39 -> 597.278 | W32: =7709.76 -> 7709.76 | X32: =W32+V32+U32+T32+S32 -> 97057.038 | Y32: 207143.99 | Z32: =R32-X32 -> 207143.99
A33: 25 | B33: EGUATU U. ONYEJELEM | C33: OFFICER M&E | D33: 10(9) | E33: =18281.64 -> 18281.64 | G33: =E33*300% -> 54844.92 | H33: =E33*7.5% -> 1371.123 | J33: =E33*50% -> 9140.82 | K33: =E33*350% -> 63985.74 | L33: =E33*100% -> 18281.64 | N33: =60000 -> 60000 | O33: =E33*10% -> 1828.164 | P33: 10000 | R33: =Q33+P33+O33+N33+M33+L33+K33+J33+I33+H33+G33+F33+E33 -> 237734.05 | T33: =20000 -> 20000 | U33: =87500+43750 -> 131250 | W33: 3369.51 | X33: =W33+V33+U33+T33+S33 -> 154619.51 | Y33: 83114.537 | Z33: =R33-X33 -> 83114.537
A34: 26 | B34: ODEH SUZIE | C34: ADMIN. OFFICER, LIASION OFFICE | D34: 10(8) | E34: =17784 -> 17784 | G34: =E34*300% -> 53352 | H34: =E34*7.5% -> 1333.8 | J34: =E34*50% -> 8892 | K34: =E34*350% -> 62244 | L34: =E34*100% -> 17784 | N34: 60000 | O34: =E34*10% -> 1778.4 | P34: 10000 | R34: =Q34+P34+O34+N34+M34+L34+K34+J34+I34+H34+G34+F34+E34 -> 233168.2 | T34: =30000 -> 30000 | V34: =0 -> 0 | W34: 3369.51 | X34: =W34+V34+U34+T34+S34 -> 33369.51 | Y34: 199798.69 | Z34: =R34-X34 -> 199798.69
A35: 27 | B35: IJEOMA NKOLIKWA | C35: ASSISTANT STORES OFFICER | D35: 8(9) | E35: =13112.16 -> 13112.16 | G35: =E35*300% -> 39336.48 | H35: =E35*7.5% -> 983.412 | J35: =E35*50% -> 6556.08 | K35: =E35*350% -> 45892.56 | L35: =E35*100% -> 13112.16 | N35: =50000 -> 50000 | O35: =E35*10% -> 1311.216 | P35: 10000 | R35: =SUM(E35:Q35) -> 180304.07 | T35: =10000 -> 10000 | W35: 1484.37 | X35: =W35+V35+U35+T35+S35 -> 11484.37 | Y35: 168819.7 | Z35: =R35-X35 -> 168819.7
A36: 28 | B36: ABDULRAHMAN A SULAIMAN | C36: ASSISTANT STORES OFFICER | D36: 8 (8) | E36: =12732 -> 12732 | G36: =E36*300% -> 38196 | H36: =E36*7.5% -> 954.9 | J36: =E36*50% -> 6366 | K36: =E36*350% -> 44562 | L36: =E36*100% -> 12732 | N36: =50000 -> 50000 | O36: =E36*10% -> 1273.2 | P36: 10000 | R36: =SUM(E36:Q36) -> 176816.1 | T36: =20000 -> 20000 | U36: =10000 -> 10000 | W36: =(1484.37) -> 1484.37 | X36: =W36+V36+U36+T36+S36 -> 31484.37 | Y36: 145331.73 | Z36: =R36-X36 -> 145331.73
A37: 29 | B37: TASSNEEM IBRAHIM | C37: ASSIST. INFORMATION | D37: 8(8) | E37: =12732 -> 12732 | G37: =E37*300% -> 38196 | H37: =E37*7.5% -> 954.9 | J37: =E37*50% -> 6366 | K37: =E37*350% -> 44562 | L37: =E37*100% -> 12732 | N37: =50000 -> 50000 | O37: =E37*10% -> 1273.2 | P37: 10000 | R37: =Q37+P37+O37+N37+M37+L37+K37+J37+I37+H37+G37+F37+E37 -> 176816.1 | T37: =50000 -> 50000 | U37: =17166.67 -> 17166.67 | V37: =0 -> 0 | W37: =1484.37 -> 1484.37 | X37: =W37+V37+U37+T37+S37 -> 68651.04 | Y37: 108165.06 | Z37: =R37-X37 -> 108165.06
A38: 30 | B38: JIMOH ADEBAYO ZAKA | C38: ASST. OFFICER/COMM | D38: 8(7) | E38: =12351.94 -> 12351.94 | G38: =E38*300% -> 37055.82 | H38: =E38*7.5% -> 926.3955 | J38: =E38*50% -> 6175.97 | K38: =E38*350% -> 43231.79 | L38: =E38*100% -> 12351.94 | N38: =50000 -> 50000 | O38: =E38*10% -> 1235.194 | P38: 10000 | R38: =Q38+P38+O38+N38+M38+L38+K38+J38+I38+H38+G38+F38+E38 -> 173329.05 | T38: =50000 -> 50000 | V38: =0 -> 0 | W38: =1484.37 -> 1484.37 | X38: =W38+V38+U38+T38+S38 -> 51484.37 | Y38: 121844.68 | Z38: =R38-X38 -> 121844.68
B39: TOTAL | C39: 30 | E39: =SUM(E9:E38) -> 928174.74 | F39: =SUM(F9:F38) -> 0 | G39: =SUM(G9:G38) -> 2624035.5 | H39: =SUM(H9:H38) -> 105723.08 | I39: =SUM(I9:I38) -> 561710.66 | J39: =SUM(J9:J38) -> 456062.93 | K39: =SUM(K9:K38) -> 2686901 | L39: =SUM(L9:L38) -> 888052.56 | ... R39: =SUM(R9:R38) -> 12388713 | T39: =SUM(T9:T38) -> 785000 | U39: =SUM(U9:U38) -> 1447690.1 | V39: =SUM(V9:V38) -> 8536.986 | W39: =SUM(W9:W38) -> 411374.07 | X39: =SUM(X9:X38) -> 2652601.2 | Y39: 9736111.7 | Z39: =SUM(Z9:Z38) -> 9736111.7
B41: INTERNAL AUDIT
A42: 1 | B42: OSANAIYE DAVID AKINYEMI | C42: DIRECTOR INTERNAL AUDIT | D42: 17(7) | E42: =76339.3 -> 76339.3 | G42: =E42*300% -> 229017.9 | H42: =E42*7.5% -> 5725.4475 | I42: 80244.38 | J42: =E42*50% -> 38169.65 | K42: =E42*350% -> 267187.55 | L42: =E42*100% -> 76339.3 | N42: =100000 -> 100000 | O42: =E42*10% -> 7633.93 | P42: 20000 | R42: =SUM(E42:Q42) -> 900657.46 | W42: =(52776.63) -> 52776.63 | X42: =W42+V42+U42+T42+S42 -> 52776.63 | Y42: 847880.83 | Z42: =R42-X42 -> 847880.83
C43: 1 | E43: =SUM(E42:E42) -> 76339.3 | F43: =SUM(F42:F42) -> 0 | G43: =SUM(G42:G42) -> 229017.9 | H43: =SUM(H42:H42) -> 5725.4475 | I43: =SUM(I42:I42) -> 80244.38 | J43: =SUM(J42:J42) -> 38169.65 | K43: =SUM(K42:K42) -> 267187.55 | L43: =SUM(L42:L42) -> 76339.3 | N43: =SUM(N42:N42) -> 100000 | O43: =SUM(O42:O42) -> 7633.93 | P43: =SUM(P42:P42) -> 20000 | Q43: =SUM(Q42:Q42) -> 0 | R43: =SUM(R42:R42) -> 900657.46 | T43: =SUM(T42:T42) -> 0 | U43: =SUM(U42:U42) -> 0 | V43: =SUM(V42:V42) -> 0 | W43: =SUM(W42:W42) -> 52776.63 | X43: =SUM(X42:X42) -> 52776.63 | Y43: 847880.83 | Z43: =SUM(Z42:Z42) -> 847880.83
B45: LEG. SUPPORT SEVICES
A46: 1 | B46: PROF. EDOBA BRIGHT OMOREGBE | C46: AG. DLSS | D46: 17(9) | E46: =81740.02 -> 81740.02 | G46: =E46*300% -> 245220.06 | H46: =E46*7.5% -> 6130.5015 | I46: 80244.38 | J46: =E46*50% -> 40870.01 | K46: =E46*350% -> 286090.07 | L46: =E46*100% -> 81740.02 | M46: =200000 -> 200000 | O46: =E46*10% -> 8174.002 | P46: 20000 | R46: =SUM(E46:Q46) -> 1050209.1 | T46: =200000 -> 200000 | U46: =52500*2 -> 105000 | W46: =52776.63 -> 52776.63 | X46: =W46+V46+U46+T46+S46 -> 357776.63 | Y46: 744932.43 | Z46: =R46-X46 -> 692432.43
A47: 2 | B47: DR CLINTON JAJA | C47: SENIOR RESEARCH FELLOW | D47: 15(9) | E47: =33507.5 -> 33507.5 | G47: =E47*300% -> 100522.5 | H47: =E47*7.5% -> 2513.0625 | I47: 40122.19 | J47: =E47*50% -> 16753.75 | K47: =E47*350% -> 117276.25 | L47: =E47*100% -> 33507.5 | M47: =160000 -> 160000 | O47: =E47*10% -> 3350.75 | P47: 20000 | Q47: 0 | R47: =SUM(E47:Q47) -> 527553.5 | T47: 50000 | U47: =0 -> 0 | W47: 15548.33 | X47: =W47+V47+U47+T47+S47 -> 65548.33 | Y47: 462005.17 | Z47: =R47-X47 -> 462005.17
A48: 3 | B48: BETHEL UZOMA IHUGBA | C48: SNR RESEARCH FELLOW | D48: 15(9) | E48: =33507.5 -> 33507.5 | G48: =E48*300% -> 100522.5 | H48: =E48*7.5% -> 2513.0625 | I48: 40122.19 | J48: =E48*50% -> 16753.75 | K48: =E48*350% -> 117276.25 | L48: =E48*100% -> 33507.5 | M48: =160000 -> 160000 | O48: =E48*10% -> 3350.75 | P48: 20000 | R48: =SUM(E48:Q48) -> 527553.5 | T48: =80000+23000 -> 103000 | U48: =246905.96 -> 246905.96 | W48: 15548.33 | X48: =W48+V48+U48+T48+S48 -> 365454.29 | Y48: 162099.21 | Z48: =R48-X48 -> 162099.21
A49: 4 | B49: OGUCHE SAMUEL | C49: SNR RESEARCH FELLOW | D49: 15(7) | E49: =31018.84 -> 31018.84 | G49: =E49*300% -> 93056.52 | H49: =E49*7.5% -> 2326.413 | I49: 40122.19 | J49: =E49*50% -> 15509.42 | K49: =E49*350% -> 108565.94 | L49: =E49*100% -> 31018.84 | M49: =160000 -> 160000 | O49: =E49*10% -> 3101.884 | P49: 20000 | R49: =SUM(E49:Q49) -> 504720.05 | T49: =30000 -> 30000 | U49: =176288.88 -> 176288.88 | W49: =15548.33 -> 15548.33 | X49: =W49+V49+U49+T49+S49 -> 221837.21 | Y49: 282882.84 | Z49: =R49-X49 -> 282882.84
A50: 5 | B50: IBRAHIM USMAN | C50: RESEARCH FELLOW I | D50: 14(11) | E50: =28489.81 -> 28489.81 | G50: =E50*300% -> 85469.43 | H50: =E50*7.5% -> 2136.7357 | I50: 0 | J50: =E50*50% -> 14244.905 | K50: =E50*350% -> 99714.335 | L50: =E50*100% -> 28489.81 | M50: =140000 -> 140000 | O50: =E50*10% -> 2848.981 | P50: 20000 | Q50: 0 | R50: =SUM(E50:Q50) -> 421394.01 | V50: ='[2]Jan 2021'!$H$24 -> 712.24525 | W50: 7709.76 | X50: =W50+V50+U50+T50+S50 -> 8422.0053 | Y50: 412972 | Z50: =R50-X50 -> 412972
A51: 6 | B51: DR MOHAMMED O. AMALI | C51: RESEARCH FELLOW I | D51: 14(8) | E51: =25854.1 -> 25854.1 | G51: =E51*300% -> 77562.3 | H51: =E51*7.5% -> 1939.0575 | J51: =E51*50% -> 12927.05 | K51: =E51*350% -> 90489.35 | L51: =E51*100% -> 25854.1 | M51: =140000 -> 140000 | O51: =E51*10% -> 2585.41 | P51: 20000 | R51: =SUM(E51:Q51) -> 397211.37 | T51: =15000 -> 15000 | U51: =133333.34 -> 133333.34 | W51: 7709.76 | X51: =W51+V51+U51+T51+S51 -> 156043.1 | Y51: 241168.27 | Z51: =R51-X51 -> 241168.27
A52: 7 | B52: YAHAYA SHAMSU | C52: RESEARCH FELLOW 1 | D52: 14(8) | E52: =25854.1 -> 25854.1 | G52: =E52*300% -> 77562.3 | H52: =E52*7.5% -> 1939.0575 | J52: =E52*50% -> 12927.05 | K52: =E52*350% -> 90489.35 | L52: =E52*100% -> 25854.1 | M52: =140000 -> 140000 | O52: =E52*10% -> 2585.41 | P52: 20000 | R52: =SUM(E52:Q52) -> 397211.37 | V52: 0 | W52: 7709.76 | X52: =W52+V52+U52+T52+S52 -> 7709.76 | Y52: 389501.61 | Z52: =R52-X52 -> 389501.61
A53: 8 | B53: OFORDEME ADAOBI JULIA | C53: RESEARCH FELLOW 11 | D53: 13(9) | E53: =24741.26 -> 24741.26 | G53: =E53*300% -> 74223.78 | H53: =E53*7.5% -> 1855.5945 | I53: 0 | J53: =E53*50% -> 12370.63 | K53: =E53*350% -> 86594.41 | L53: =E53*100% -> 24741.26 | M53: =120000 -> 120000 | O53: =E53*10% -> 2474.126 | P53: 15000 | Q53: 0 | R53: =SUM(E53:Q53) -> 362001.06 | W53: 7709.76 | X53: =W53+V53+U53+T53+S53 -> 7709.76 | Y53: 354291.3 | Z53: =R53-X53 -> 354291.3
A54: 9 | B54: IKPEAZU CHINEDU ANITA | C54: RESEARCH FELLOW 1 | D54: 14(8) | E54: =25854.1 -> 25854.1 | G54: =E54*300% -> 77562.3 | H54: =E54*7.5% -> 1939.0575 | I54: 0 | J54: =E54*50% -> 12927.05 | K54: =E54*350% -> 90489.35 | L54: =E54*100% -> 25854.1 | M54: 140000 | O54: =E54*10% -> 2585.41 | P54: 20000 | Q54: 0 | R54: =SUM(E54:Q54) -> 397211.37 | W54: 7709.76 | X54: =W54+V54+U54+T54+S54 -> 7709.76 | Y54: 389501.61 | Z54: =R54-X54 -> 389501.61
A55: 10 | B55: DORIS DAKDA AARON | C55: RESEARCH FELLOW II | D55: 13(8) | E55: =23891.12 -> 23891.12 | G55: =E55*300% -> 71673.36 | H55: =E55*7.5% -> 1791.834 | J55: =E55*50% -> 11945.56 | K55: =E55*350% -> 83618.92 | L55: =E55*100% -> 23891.12 | M55: =120000 -> 120000 | O55: =E55*10% -> 2389.112 | P55: 15000 | R55: =SUM(E55:Q55) -> 354201.03 | T55: =50000+10000 -> 60000 | U55: =91666.67 -> 91666.67 | V55: ='[2]Jan 2021'!$H$48 -> 597.278 | W55: =7709.76 -> 7709.76 | X55: =W55+V55+U55+T55+S55 -> 159973.71 | Y55: 194227.32 | Z55: =R55-X55 -> 194227.32
B56: TOTAL | C56: 10 | E56: =SUM(E46:E55) -> 334458.35 | F56: =SUM(F46:F55) -> 0 | G56: =SUM(G46:G55) -> 1003375.1 | H56: =SUM(H46:H55) -> 25084.376 | I56: =SUM(I46:I55) -> 200610.95 | J56: =SUM(J46:J55) -> 167229.17 | K56: =SUM(K46:K55) -> 1170604.2 | L56: =SUM(L46:L55) -> 334458.35 | M56: =SUM(M46:M55) -> 1480000 | O56: =SUM(O46:O55) -> 33445.835 | P56: =SUM(P46:P55) -> 190000 | Q56: =SUM(Q46:Q55) -> 0 | R56: =SUM(R46:R55) -> 4939266.3 | T56: =SUM(T46:T55) -> 458000 | U56: =SUM(U46:U55) -> 753194.85 | V56: =SUM(V46:V55) -> 1309.5233 | W56: =SUM(W46:W55) -> 145680.18 | X56: =SUM(X46:X55) -> 1358184.6 | Y56: 3633581.8 | Z56: =SUM(Z46:Z55) -> 3581081.8
B58: LEGAL SERVICES
A59: 1 | B59: DR SHUIBU DANWANKA | C59: DIRECTOR LEGAL SERVICES | D59: 17(9) | E59: =81740.02 -> 81740.02 | G59: =E59*300% -> 245220.06 | H59: =E59*7.5% -> 6130.5015 | I59: 80244.38 | J59: =E59*50% -> 40870.01 | K59: =E59*350% -> 286090.07 | L59: =E59*100% -> 81740.02 | M59: =200000 -> 200000 | O59: =E59*10% -> 8174.002 | P59: 20000 | Q59: 0 | R59: =SUM(E59:Q59) -> 1050209.1 | V59: 0 | W59: 52776.63 | X59: =W59+V59+U59+T59+S59 -> 52776.63 | Y59: 997432.43 | Z59: =R59-X59 -> 997432.43
A60: 2 | B60: ABDULSALAM BAKO | C60: MANAGER, LEGAL SERVICES | D60: 15 (7) | E60: 31018.84 | G60: =E60*300% -> 93056.52 | H60: =E60*7.5% -> 2326.413 | I60: 40122.19 | J60: =E60*50% -> 15509.42 | K60: =E60*350% -> 108565.94 | L60: =E60*100% -> 31018.84 | N60: =80000 -> 80000 | O60: =E60*10% -> 3101.884 | P60: 20000 | Q60: 0 | R60: =SUM(E60:Q60) -> 424720.05 | T60: =50000 -> 50000 | U60: =95000 -> 95000 | V60: 0 | W60: =15548.33 -> 15548.33 | X60: =W60+V60+U60+T60+S60 -> 160548.33 | Y60: 264171.72 | Z60: =R60-X60 -> 264171.72
B61: TOTAL | C61: 2 | E61: =SUM(E59:E60) -> 112758.86 | G61: =SUM(G59:G60) -> 338276.58 | H61: =SUM(H59:H60) -> 8456.9145 | I61: =SUM(I59:I60) -> 120366.57 | J61: =SUM(J59:J60) -> 56379.43 | K61: =SUM(K59:K60) -> 394656.01 | L61: =SUM(L59:L60) -> 112758.86 | M61: =SUM(M59:M60) -> 200000 | N61: =SUM(N59:N60) -> 80000 | ... R61: =SUM(R59:R60) -> 1474929.1 | T61: =SUM(T59:T60) -> 50000 | U61: =SUM(U60) -> 95000 | V61: =SUM(V59:V60) -> 0 | W61: =SUM(W59:W60) -> 68324.96 | X61: =SUM(X59:X60) -> 213324.96 | Y61: 1261604.2 | Z61: =SUM(Z59:Z60) -> 1261604.2
B63: DEMOCRACY AND GOVERNANCE
A64: 1 | B64: DR. ADEWALE ADEREMI | C64: DIRECTOR, DEMOCRATIC STUDIES | D64: 17(8) | E64: =79039.64 -> 79039.64 | G64: =E64*300% -> 237118.92 | H64: =E64*7.5% -> 5927.973 | I64: =80244.38 -> 80244.38 | J64: =E64*50% -> 39519.82 | K64: =E64*350% -> 276638.74 | L64: =E64*100% -> 79039.64 | M64: =200000 -> 200000 | O64: =E64*10% -> 7903.964 | P64: 20000 | Q64: 0 | R64: =SUM(E64:Q64) -> 1025433.1 | T64: =100000+100000 -> 200000 | W64: =52776.63 -> 52776.63 | X64: =W64+V64+U64+T64+S64 -> 252776.63 | Y64: 772656.45 | Z64: =R64-X64 -> 772656.45
A65: 2 | B65: NDANUSA MOHAMMED MANZUMA | C65: SNR RESEARCH FELLOW | D65: 15 (7) | E65: 31018.84 | G65: =E65*300% -> 93056.52 | H65: =E65*7.5% -> 2326.413 | I65: 40122.19 | J65: =E65*50% -> 15509.42 | K65: =E65*350% -> 108565.94 | L65: =E65*100% -> 31018.84 | M65: =160000 -> 160000 | O65: =E65*10% -> 3101.884 | P65: 20000 | Q65: 0 | R65: =SUM(E65:Q65) -> 504720.05 | T65: =100000 -> 100000 | U65: =131250 -> 131250 | V65: 0 | W65: =15548.33 -> 15548.33 | X65: =W65+V65+U65+T65+S65 -> 246798.33 | Y65: 257921.72 | Z65: =R65-X65 -> 257921.72
A66: 3 | B66: EMILY EDOISA IKHIDE | C66: RESEARCH FELLOW II | D66: 13(10) | E66: =25523.45 -> 25523.45 | G66: =E66*300% -> 76570.35 | H66: =E66*7.5% -> 1914.2587 | J66: =E66*50% -> 12761.725 | K66: =E66*350% -> 89332.075 | L66: =E66*100% -> 25523.45 | M66: =120000 -> 120000 | O66: =E66*10% -> 2552.345 | P66: 15000 | R66: =SUM(E66:Q66) -> 369177.65 | T66: =50000 -> 50000 | U66: =45833.33 -> 45833.33 | W66: 7709.76 | X66: =W66+V66+U66+T66+S66 -> 103543.09 | Y66: 265634.56 | Z66: =R66-X66 -> 265634.56
A67: 4 | B67: EJALONIBU GANIYU LAYI | C67: RESEARCH FELLOW 11 | D67: 13(8) | E67: =23891.12 -> 23891.12 | G67: =E67*300% -> 71673.36 | H67: =E67*7.5% -> 1791.834 | J67: =E67*50% -> 11945.56 | K67: =E67*350% -> 83618.92 | L67: =E67*100% -> 23891.12 | M67: =120000 -> 120000 | O67: =E67*10% -> 2389.112 | P67: 15000 | R67: =SUM(E67:Q67) -> 354201.03 | T67: =110000 -> 110000 | W67: =7709.76 -> 7709.76 | X67: =W67+V67+U67+T67+S67 -> 117709.76 | Y67: 236491.27 | Z67: =R67-X67 -> 236491.27
A68: 5 | B68: LONA POLIT BONKAT | C68: RESEARCH FELLOW 11 | D68: 13(7) | E68: =23074.99 -> 23074.99 | G68: =E68*300% -> 69224.97 | H68: =E68*7.5% -> 1730.6243 | I68: 0 | J68: =E68*50% -> 11537.495 | K68: =E68*350% -> 80762.465 | L68: =E68*100% -> 23074.99 | M68: =120000 -> 120000 | O68: =E68*10% -> 2307.499 | P68: 15000 | Q68: 0 | R68: =SUM(E68:Q68) -> 346713.03 | T68: =20000 -> 20000 | U68: =119444.44 -> 119444.44 | V68: =0 -> 0 | W68: 7709.76 | X68: =W68+V68+U68+T68+S68 -> 147154.2 | Y68: 199558.83 | Z68: =R68-X68 -> 199558.83
A69: 6 | B69: YUNUSA ABDULLAHI | C69: RESEARCH FELLOW 1 | D69: 14(8) | E69: =25854.1 -> 25854.1 | G69: =E69*300% -> 77562.3 | H69: =E69*7.5% -> 1939.0575 | J69: =E69*50% -> 12927.05 | K69: =E69*350% -> 90489.35 | L69: =E69*100% -> 25854.1 | M69: =140000 -> 140000 | O69: =E69*10% -> 2585.41 | P69: 20000 | R69: =SUM(E69:Q69) -> 397211.37 | T69: =10000 -> 10000 | U69: =54585.66 -> 54585.66 | W69: =7709.76 -> 7709.76 | X69: =W69+V69+U69+T69+S69 -> 72295.42 | Y69: 324915.95 | Z69: =R69-X69 -> 324915.95
A70: 7 | B70: UDEFUNA NNADOZIE PATRICK | C70: RESEARCH OFFICER | D70: 10(13) | E70: =19774.62 -> 19774.62 | G70: =E70*300% -> 59323.86 | H70: =E70*7.5% -> 1483.0965 | I70: 0 | J70: =E70*50% -> 9887.31 | K70: =E70*350% -> 69211.17 | L70: =E70*100% -> 19774.62 | M70: =100000 -> 100000 | O70: =E70*10% -> 1977.462 | P70: 10000 | Q70: 0 | R70: =SUM(E70:Q70) -> 291432.14 | T70: =10000 -> 10000 | U70: =131771.66 -> 131771.66 | W70: 3369.51 | X70: =W70+V70+U70+T70+S70 -> 145141.17 | Y70: 146290.97 | Z70: =R70-X70 -> 146290.97
A71: 8 | B71: OSOLAFIA MUHAMMAD EGYE | C71: RESEARCH OFFICER | D71: 12(7) | E71: =20749 -> 20749 | G71: =E71*300% -> 62247 | H71: =E71*7.5% -> 1556.175 | I71: 0 | J71: =E71*50% -> 10374.5 | K71: =E71*350% -> 72621.5 | L71: =E71*100% -> 20749 | M71: =110000 -> 110000 | O71: =E71*10% -> 2074.9 | P71: 15000 | Q71: 0 | R71: =SUM(E71:Q71) -> 315372.08 | T71: =10000+20000 -> 30000 | U71: =130000 -> 130000 | V71: ='[2]Jan 2021'!$H$43 -> 481.92375 | W71: =3369.51 -> 3369.51 | X71: =W71+V71+U71+T71+S71 -> 163851.43 | Y71: 151520.64 | Z71: =R71-X71 -> 151520.64
A72: 9 | B72: HAUWA PATE SADIQ | C72: PROGRAMME OFFICER | D72: 10(9) | E72: =18281.64 -> 18281.64 | G72: =E72*300% -> 54844.92 | H72: =E72*7.5% -> 1371.123 | J72: =E72*50% -> 9140.82 | K72: =E72*350% -> 63985.74 | L72: =E72*100% -> 18281.64 | M72: =100000 -> 100000 | O72: =E72*10% -> 1828.164 | P72: 10000 | R72: =SUM(E72:Q72) -> 277734.05 | T72: =70000+20000 -> 90000 | W72: 3369.51 | X72: =W72+V72+U72+T72+S72 -> 93369.51 | Y72: 152864.54 | Z72: =R72-X72 -> 184364.54
A73: 10 | B73: ABAYOMI KAYODE QUADRI | C73: RESEARCH OFFICER | D73: 10(7) | E73: =17286.33 -> 17286.33 | G73: =E73*300% -> 51858.99 | H73: =E73*7.5% -> 1296.4748 | J73: =E73*50% -> 8643.165 | K73: =E73*350% -> 60502.155 | L73: =E73*100% -> 17286.33 | M73: =100000 -> 100000 | O73: =E73*10% -> 1728.633 | P73: 10000 | R73: =SUM(E73:Q73) -> 268602.08 | T73: =50000 -> 50000 | U73: 0 | W73: 3369.51 | X73: =W73+V73+U73+T73+S73 -> 53369.51 | Y73: 215232.57 | Z73: =R73-X73 -> 215232.57
A74: 11 | B74: NNANDI LIVINUS ATURE | C74: RESEARCH ASSISTANT | D74: 8(7) | E74: =12351.94 -> 12351.94 | G74: =E74*300% -> 37055.82 | H74: =E74*7.5% -> 926.3955 | J74: =E74*50% -> 6175.97 | K74: =E74*350% -> 43231.79 | L74: =E74*100% -> 12351.94 | M74: =100000 -> 100000 | O74: =E74*10% -> 1235.194 | P74: 10000 | R74: =SUM(E74:Q74) -> 223329.05 | T74: =100000 -> 100000 | W74: 1484.37 | X74: =W74+V74+U74+T74+S74 -> 101484.37 | Y74: 121844.68 | Z74: =R74-X74 -> 121844.68
A75: 12 | B75: LUCKY AGWOM | C75: RESEARCH ASSISTANT | D75: 8(7) | E75: =12351.94 -> 12351.94 | G75: =E75*300% -> 37055.82 | H75: =E75*7.5% -> 926.3955 | J75: =E75*50% -> 6175.97 | K75: =E75*350% -> 43231.79 | L75: =E75*100% -> 12351.94 | M75: =100000 -> 100000 | O75: =E75*10% -> 1235.194 | P75: 10000 | R75: =SUM(E75:Q75) -> 223329.05 | W75: 1484.37 | X75: =W75+V75+U75+T75+S75 -> 1484.37 | Y75: 221844.68 | Z75: =R75-X75 -> 221844.68
B76: TOTAL | C76: 12 | E76: =SUM(E64:E75) -> 309197.61 | F76: =SUM(F64:F75) -> 0 | G76: =SUM(G64:G75) -> 927592.83 | H76: =SUM(H64:H75) -> 23189.821 | I76: =SUM(I64:I75) -> 120366.57 | J76: =SUM(J64:J75) -> 154598.8 | K76: =SUM(K64:K75) -> 1082191.6 | L76: =SUM(L64:L75) -> 309197.61 | M76: =SUM(M64:M75) -> 1470000 | O76: =SUM(O64:O75) -> 30919.761 | P76: =SUM(P64:P75) -> 170000 | Q76: =SUM(Q64:Q75) -> 0 | R76: =SUM(R64:R75) -> 4597254.6 | T76: =SUM(T64:T75) -> 770000 | U76: =SUM(U64:U75) -> 612885.09 | V76: =SUM(V64:V75) -> 481.92375 | W76: =SUM(W64:W75) -> 115610.78 | X76: =SUM(X64:X75) -> 1498977.8 | Y76: 3066776.8 | Z76: =SUM(Z64:Z75) -> 3098276.8
B78: STUDIES
A79: 1 | B79: DR ASIMIYU G. ABIOLA | C79: DIRECTOR POST GRADUATE | D79: 17(9) | E79: =81740.02 -> 81740.02 | G79: =E79*300% -> 245220.06 | H79: =E79*7.5% -> 6130.5015 | I79: 80244.38 | J79: =E79*50% -> 40870.01 | K79: =E79*350% -> 286090.07 | L79: =E79*100% -> 81740.02 | M79: =200000 -> 200000 | O79: =E79*10% -> 8174.002 | P79: 20000 | Q79: 0 | R79: =SUM(E79:Q79) -> 1050209.1 | T79: 250000 | U79: =0 -> 0 | V79: 0 | W79: 52776.63 | X79: =W79+V79+U79+T79+S79 -> 302776.63 | Y79: 747432.43 | Z79: =R79-X79 -> 747432.43
A80: 2 | B80: USMAN WALI | C80: SENIOR RESEARCH FELLOW | D80: 15 (7) | E80: 31018.84 | G80: =E80*300% -> 93056.52 | H80: =E80*7.5% -> 2326.413 | I80: 40122.19 | J80: =E80*50% -> 15509.42 | K80: =E80*350% -> 108565.94 | L80: =E80*100% -> 31018.84 | M80: =160000 -> 160000 | O80: =E80*10% -> 3101.884 | P80: 20000 | Q80: 0 | R80: =SUM(E80:Q80) -> 504720.05 | V80: 0 | W80: =15548.33 -> 15548.33 | X80: =W80+V80+U80+T80+S80 -> 15548.33 | Y80: 489171.72 | Z80: =R80-X80 -> 489171.72
A81: 3 | B81: MOSHOOD TOSHO AMUDA | C81: MANAGER, EXAMS & RECORDS | D81: 15 (7) | E81: 31018.84 | G81: =E81*300% -> 93056.52 | H81: =E81*7.5% -> 2326.413 | I81: 40122.19 | J81: =E81*50% -> 15509.42 | K81: =E81*350% -> 108565.94 | L81: =E81*100% -> 31018.84 | M81: =160000 -> 160000 | O81: =E81*10% -> 3101.884 | P81: 20000 | Q81: 0 | R81: =SUM(E81:Q81) -> 504720.05 | V81: 0 | W81: =15548.33 -> 15548.33 | X81: =W81+V81+U81+T81+S81 -> 15548.33 | Y81: 489171.72 | Z81: =R81-X81 -> 489171.72
A82: 4 | B82: UZODINMA EMMANUEL EZENWA | C82: RESEARCH FELLOW II | D82: 13(8) | E82: =23891.12 -> 23891.12 | G82: =E82*300% -> 71673.36 | H82: =E82*7.5% -> 1791.834 | I82: 0 | J82: =E82*50% -> 11945.56 | K82: =E82*350% -> 83618.92 | L82: =E82*100% -> 23891.12 | M82: =120000 -> 120000 | O82: =E82*10% -> 2389.112 | P82: 15000 | Q82: 0 | R82: =SUM(E82:Q82) -> 354201.03 | T82: =0 -> 0 | U82: =0 -> 0 | V82: ='[2]Jan 2021'!$H$44 -> 597.278 | W82: =7709.76 -> 7709.76 | X82: =W82+V82+U82+T82+S82 -> 8307.038 | Y82: 345893.99 | Z82: =R82-X82 -> 345893.99
A83: 5 | B83: IGWE STACY | C83: PROGRAMME OFFICER | D83: 10(7) | E83: =17286.33 -> 17286.33 | G83: =E83*300% -> 51858.99 | H83: =E83*7.5% -> 1296.4748 | J83: =E83*50% -> 8643.165 | K83: =E83*350% -> 60502.155 | L83: =E83*100% -> 17286.33 | M83: =100000 -> 100000 | O83: =E83*10% -> 1728.633 | P83: 10000 | R83: =SUM(E83:Q83) -> 268602.08 | T83: =50000 -> 50000 | U83: =50000 -> 50000 | W83: 3369.51 | X83: =W83+V83+U83+T83+S83 -> 103369.51 | Y83: 165232.57 | Z83: =R83-X83 -> 165232.57
A84: 6 | B84: DARE SHEU MAGBON | C84: ASSIST. PG | D84: 8(8) | E84: =12732 -> 12732 | G84: =E84*300% -> 38196 | H84: =E84*7.5% -> 954.9 | J84: =E84*50% -> 6366 | K84: =E84*350% -> 44562 | L84: =E84*100% -> 12732 | M84: =100000 -> 100000 | O84: =E84*10% -> 1273.2 | P84: 10000 | R84: =SUM(E84:Q84) -> 226816.1 | T84: =3000+20000 -> 23000 | U84: 0 | W84: 1484.37 | X84: =W84+V84+U84+T84+S84 -> 24484.37 | Y84: 202331.73 | Z84: =R84-X84 -> 202331.73
A85: 7 | B85: MOHAMMED BELLO | C85: RESEARCH ASSITANT PG | D85: 8(7) | E85: =12351.94 -> 12351.94 | G85: =E85*300% -> 37055.82 | H85: =E85*7.5% -> 926.3955 | J85: =E85*50% -> 6175.97 | K85: =E85*350% -> 43231.79 | L85: =E85*100% -> 12351.94 | M85: =100000 -> 100000 | O85: =E85*10% -> 1235.194 | P85: 10000 | R85: =SUM(E85:Q85) -> 223329.05 | T85: =0 -> 0 | U85: =26666.67 -> 26666.67 | W85: 1484.37 | X85: =W85+V85+U85+T85+S85 -> 28151.04 | Y85: 195178.01 | Z85: =R85-X85 -> 195178.01
B86: TOTAL | C86: 7 | E86: =SUM(E79:E85) -> 210039.09 | G86: =SUM(G79:G85) -> 630117.27 | H86: =SUM(H79:H85) -> 15752.932 | I86: =SUM(I79:I85) -> 160488.76 | J86: =SUM(J79:J85) -> 105019.55 | K86: =SUM(K79:K85) -> 735136.82 | L86: =SUM(L79:L85) -> 210039.09 | M86: =SUM(M79:M85) -> 940000 | O86: =SUM(O79:O85) -> 21003.909 | P86: =SUM(P79:P85) -> 105000 | Q86: =SUM(Q79:Q85) -> 0 | R86: =SUM(R79:R85) -> 3132597.4 | T86: =SUM(T79:T85) -> 323000 | U86: =SUM(U79:U85) -> 76666.67 | V86: =SUM(V79:V85) -> 597.278 | W86: =SUM(W79:W85) -> 97921.3 | X86: =SUM(X79:X85) -> 498185.25 | Y86: 2634412.2 | Z86: =SUM(Z79:Z85) -> 2634412.2
B88: ECONOMIC DEV. AND SOCIAL RESEARCH
A89: 1 | B89: DR ASEMOTA OMOROGBE JOSEPH | C89: Ag. DEPUTY DIRECTOR, ECO & SOC DEV DEPT | D89: 16(7) | E89: =39662.25 -> 39662.25 | G89: =E89*300% -> 118986.75 | H89: =E89*7.5% -> 2974.6687 | I89: 40122.19 | J89: =E89*50% -> 19831.125 | K89: =E89*350% -> 138817.88 | L89: =E89*100% -> 39662.25 | M89: =180000 -> 180000 | O89: =E89*10% -> 3966.225 | P89: 20000 | R89: =SUM(E89:Q89) -> 604023.33 | W89: =21618.09 -> 21618.09 | X89: =W89+V89+U89+T89+S89 -> 21618.09 | Y89: 582405.24 | Z89: =R89-X89 -> 582405.24
A90: 2 | B90: TERFA WILLIAMS ABRAHAM | C90: SNR RESEARCH FELLOW | D90: 15(8) | E90: =32263.2 -> 32263.2 | G90: =E90*300% -> 96789.6 | H90: =E90*7.5% -> 2419.74 | I90: =40122.19 -> 40122.19 | J90: =E90*50% -> 16131.6 | K90: =E90*350% -> 112921.2 | L90: =E90*100% -> 32263.2 | M90: =160000 -> 160000 | O90: =E90*10% -> 3226.32 | P90: 20000 | R90: =SUM(E90:Q90) -> 516137.05 | W90: =15548.33 -> 15548.33 | X90: =W90+V90+U90+T90+S90 -> 15548.33 | Y90: 500588.72 | Z90: =R90-X90 -> 500588.72
A91: 3 | B91: DR AUGUSTINE C. OSIGWE | C91: SNR RESEARCH FELLOW | D91: 15(8) | E91: =32263.2 -> 32263.2 | G91: =E91*300% -> 96789.6 | H91: =E91*7.5% -> 2419.74 | I91: =40122.19 -> 40122.19 | J91: =E91*50% -> 16131.6 | K91: =E91*350% -> 112921.2 | L91: =E91*100% -> 32263.2 | M91: =160000 -> 160000 | O91: =E91*10% -> 3226.32 | P91: 20000 | R91: =SUM(E91:Q91) -> 516137.05 | T91: =20000 -> 20000 | U91: =68750 -> 68750 | V91: ='[2]Jan 2021'!$H$38 -> 806.58 | W91: =15548.33 -> 15548.33 | X91: =W91+V91+U91+T91+S91 -> 105104.91 | Y91: 411032.14 | Z91: =R91-X91 -> 411032.14
A92: 4 | B92: JUMARE FADILA | C92: RESEARCH FELLOW I | D92: 14(8) | E92: =25854.1 -> 25854.1 | G92: =E92*300% -> 77562.3 | H92: =E92*7.5% -> 1939.0575 | I92: 0 | J92: =E92*50% -> 12927.05 | K92: =E92*350% -> 90489.35 | L92: =E92*100% -> 25854.1 | M92: 140000 | O92: =E92*10% -> 2585.41 | P92: 20000 | Q92: 0 | R92: =SUM(E92:Q92) -> 397211.37 | T92: =50000 -> 50000 | W92: =7709.76 -> 7709.76 | X92: =W92+V92+U92+T92+S92 -> 57709.76 | Y92: 339501.61 | Z92: =R92-X92 -> 339501.61
A93: 5 | B93: NGARA CHRISTOPHER OCHANJA | C93: RESEARCH FELLOW 1 | D93: 14(9) | E93: =26732.65 -> 26732.65 | G93: =E93*300% -> 80197.95 | H93: =E93*7.5% -> 2004.9488 | J93: =E93*50% -> 13366.325 | K93: =E93*350% -> 93564.275 | L93: =E93*100% -> 26732.65 | M93: 140000 | O93: =E93*10% -> 2673.265 | P93: 20000 | Q93: 0 | R93: =SUM(E93:Q93) -> 405272.06 | T93: =20000 -> 20000 | U93: =163103.59 -> 163103.59 | V93: ='[2]Jan 2021'!$H$46 -> 668.31625 | W93: =7709.76 -> 7709.76 | X93: =W93+V93+U93+T93+S93 -> 191481.67 | Y93: 213790.4 | Z93: =R93-X93 -> 213790.4
A94: 6 | B94: OMOJU OLUWASOLA EMMANUEL | C94: RESEARCH FELLOW I | D94: 14(8) | E94: =25854.1 -> 25854.1 | G94: =E94*300% -> 77562.3 | H94: =E94*7.5% -> 1939.0575 | J94: =E94*50% -> 12927.05 | K94: =E94*350% -> 90489.35 | L94: =E94*100% -> 25854.1 | M94: 140000 | O94: =E94*10% -> 2585.41 | P94: 20000 | R94: =SUM(E94:Q94) -> 397211.37 | T94: =50000 -> 50000 | U94: =(500000*1.03)/6 -> 85833.333 | W94: =7709.76 -> 7709.76 | X94: =W94+V94+U94+T94+S94 -> 143543.09 | Y94: 339501.61 | Z94: =R94-X94 -> 253668.27
A95: 7 | B95: RIFKATU NGHARGBU | C95: RESEARCH FELLOW 1 | D95: 14(7) | E95: =24975.81 -> 24975.81 | G95: =E95*300% -> 74927.43 | H95: =E95*7.5% -> 1873.1858 | I95: 0 | J95: =E95*50% -> 12487.905 | K95: =E95*350% -> 87415.335 | L95: =E95*100% -> 24975.81 | M95: 140000 | O95: =E95*10% -> 2497.581 | P95: 20000 | Q95: `12333 | R95: =SUM(E95:Q95) -> 389153.06 | T95: =100000 -> 100000 | U95: =68666.67 -> 68666.67 | W95: =7709.76 -> 7709.76 | X95: =W95+V95+U95+T95+S95 -> 176376.43 | Y95: 212776.63 | Z95: =R95-X95 -> 212776.63
A96: 8 | B96: IBE EZECHI CYRIACUS | C96: RESEARCH FELLOW II | D96: 13(8) | E96: =23891.12 -> 23891.12 | G96: =E96*300% -> 71673.36 | H96: =E96*7.5% -> 1791.834 | I96: 0 | J96: =E96*50% -> 11945.56 | K96: =E96*350% -> 83618.92 | L96: =E96*100% -> 23891.12 | M96: =120000 -> 120000 | O96: =E96*10% -> 2389.112 | P96: 15000 | Q96: 0 | R96: =SUM(E96:Q96) -> 354201.03 | T96: =20000 -> 20000 | U96: =68666.67 -> 68666.67 | W96: =7709.76 -> 7709.76 | X96: =W96+V96+U96+T96+S96 -> 96376.43 | Y96: 257824.6 | Z96: =R96-X96 -> 257824.6
A97: 9 | B97: OSIKHEN LEO IGBANOI | C97: RESEARCH FELLOW 11 | D97: 13(7) | E97: =23074.99 -> 23074.99 | G97: =E97*300% -> 69224.97 | H97: =E97*7.5% -> 1730.6243 | I97: 0 | J97: =E97*50% -> 11537.495 | K97: =E97*350% -> 80762.465 | L97: =E97*100% -> 23074.99 | M97: =120000 -> 120000 | O97: =E97*10% -> 2307.499 | P97: 15000 | Q97: 0 | R97: =SUM(E97:Q97) -> 346713.03 | T97: =25000 -> 25000 | U97: =94262.15 -> 94262.15 | W97: =7709.76 -> 7709.76 | X97: =W97+V97+U97+T97+S97 -> 126971.91 | Y97: 219741.12 | Z97: =R97-X97 -> 219741.12
A98: 10 | B98: OKUNGBOWA OSARETIN GODSPOWER | C98: RESEARCH FELLOW 11 | D98: 13(7) | E98: =23074.99 -> 23074.99 | G98: =E98*300% -> 69224.97 | H98: =E98*7.5% -> 1730.6243 | I98: 0 | J98: =E98*50% -> 11537.495 | K98: =E98*350% -> 80762.465 | L98: =E98*100% -> 23074.99 | M98: =120000 -> 120000 | O98: =E98*10% -> 2307.499 | P98: 15000 | Q98: 0 | R98: =SUM(E98:Q98) -> 346713.03 | T98: =100000 -> 100000 | W98: =7709.76 -> 7709.76 | X98: =W98+V98+U98+T98+S98 -> 107709.76 | Y98: 239003.27 | Z98: =R98-X98 -> 239003.27
B99: TOTAL | C99: 10 | E99: =SUM(E89:E98) -> 277646.41 | G99: =SUM(G89:G98) -> 832939.23 | H99: =SUM(H89:H98) -> 20823.481 | I99: =SUM(I89:I98) -> 120366.57 | J99: =SUM(J89:J98) -> 138823.2 | K99: =SUM(K89:K98) -> 971762.43 | L99: =SUM(L89:L98) -> 277646.41 | M99: =SUM(M89:M98) -> 1420000 | O99: =SUM(O89:O98) -> 27764.641 | P99: =SUM(P89:P98) -> 185000 | Q99: =SUM(Q89:Q98) -> 0 | R99: =SUM(R89:R98) -> 4272772.4 | T99: =SUM(T89:T98) -> 385000 | U99: =SUM(U89:U98) -> 549282.41 | V99: =SUM(V89:V98) -> 1474.8963 | W99: =SUM(W89:W98) -> 106683.07 | X99: =SUM(X89:X98) -> 1042440.4 | Y99: 3316165.3 | Z99: =SUM(Z89:Z98) -> 3230332
B101: TRAINING AND INTERNATIONAL COOP
A102: 1 | B102: REKIYA IBRAHIM ATTAH | C102: DEPUTY DIRECTOR TRAINING | D102: 16(7) | E102: =39662.25 -> 39662.25 | G102: =E102*300% -> 118986.75 | H102: =E102*7.5% -> 2974.6687 | I102: 40122.19 | J102: =E102*50% -> 19831.125 | K102: =E102*350% -> 138817.88 | L102: =E102*100% -> 39662.25 | N102: =90000 -> 90000 | O102: =E102*10% -> 3966.225 | P102: 20000 | R102: =SUM(E102:Q102) -> 514023.33 | U102: =0 -> 0 | W102: =21618.09 -> 21618.09 | X102: =W102+V102+U102+T102+S102 -> 21618.09 | Y102: 492405.24 | Z102: =R102-X102 -> 492405.24
A103: 2 | B103: DR FRANCIS NDUM OJIE | C103: CHIEF TRAINING OFFICER | D103: 14(8) | E103: =25854.1 -> 25854.1 | G103: =E103*300% -> 77562.3 | H103: =E103*7.5% -> 1939.0575 | J103: =E103*50% -> 12927.05 | K103: =E103*350% -> 90489.35 | L103: =E103*100% -> 25854.1 | N103: =70000 -> 70000 | O103: =E103*10% -> 2585.41 | P103: 20000 | R103: =SUM(E103:Q103) -> 327211.37 | V103: =646.35 -> 646.35 | W103: =7709.76 -> 7709.76 | X103: =W103+V103+U103+T103+S103 -> 8356.11 | Y103: 318855.26 | Z103: =R103-X103 -> 318855.26
A104: 3 | B104: ABUBAKAR MOHAMMED BASHIR | C104: ASST. CHIEF TRAINING OFFICER | D104: 13(7) | E104: =23074.99 -> 23074.99 | G104: =E104*300% -> 69224.97 | H104: =E104*7.5% -> 1730.6243 | I104: 0 | J104: =E104*50% -> 11537.495 | K104: =E104*350% -> 80762.465 | L104: =E104*100% -> 23074.99 | N104: 70000 | O104: =E104*10% -> 2307.499 | P104: 15000 | Q104: 0 | R104: =SUM(E104:Q104) -> 296713.03 | W104: =7709.76 -> 7709.76 | X104: =W104+V104+U104+T104+S104 -> 7709.76 | Y104: 289003.27 | Z104: =R104-X104 -> 289003.27
A105: 4 | B105: OKECHUKWU UCHENNA HULDA | C105: TRAINING OFFICER | D105: 10(9) | E105: =18281.64 -> 18281.64 | G105: =E105*300% -> 54844.92 | H105: =E105*7.5% -> 1371.123 | J105: =E105*50% -> 9140.82 | K105: =E105*350% -> 63985.74 | L105: =E105*100% -> 18281.64 | N105: =60000 -> 60000 | O105: =E105*10% -> 1828.164 | P105: 10000 | R105: =SUM(E105:Q105) -> 237734.05 | T105: =5000 -> 5000 | U105: =64806.29 -> 64806.29 | W105: 3369.51 | X105: =W105+V105+U105+T105+S105 -> 73175.8 | Y105: 164558.25 | Z105: =R105-X105 -> 164558.25
B106: TOTAL | C106: 4 | E106: =SUM(E102:E105) -> 106872.98 | G106: =SUM(G102:G105) -> 320618.94 | H106: =SUM(H102:H105) -> 8015.4735 | I106: =SUM(I102:I105) -> 40122.19 | J106: =SUM(J102:J105) -> 53436.49 | K106: =SUM(K102:K105) -> 374055.43 | L106: =SUM(L102:L105) -> 106872.98 | N106: =SUM(N102:N105) -> 290000 | O106: =SUM(O102:O105) -> 10687.298 | P106: =SUM(P102:P105) -> 65000 | Q106: =SUM(Q102:Q105) -> 0 | R106: =SUM(R102:R105) -> 1375681.8 | T106: =SUM(T102:T105) -> 5000 | U106: =SUM(U102:U105) -> 64806.29 | V106: =SUM(V102:V105) -> 646.35 | W106: =SUM(W102:W105) -> 40407.12 | X106: =SUM(X102:X105) -> 110859.76 | Y106: 1264822 | Z106: =SUM(Z102:Z105) -> 1264822
B108: LIBRARY AND DOCUMENTATION
A109: 1 | B109: DR MAIMUNA IZAH | C109: INSITUTE LIBRARIAN | D109: 17(8) | E109: =79039.64 -> 79039.64 | G109: =E109*300% -> 237118.92 | H109: =E109*7.5% -> 5927.973 | I109: 80244.38 | J109: =E109*50% -> 39519.82 | K109: =E109*350% -> 276638.74 | L109: =E109*100% -> 79039.64 | M109: =200000 -> 200000 | O109: =E109*10% -> 7903.964 | P109: 20000 | Q109: 0 | R109: =SUM(E109:Q109) -> 1025433.1 | T109: =100000 -> 100000 | U109: 0 | V109: 0 | W109: =52776.63 -> 52776.63 | X109: =W109+V109+U109+T109+S109 -> 152776.63 | Y109: 872656.45 | Z109: =R109-X109 -> 872656.45
A110: 2 | B110: CATHERINE E. IKOKOH | C110: SNR RESEARCH FELLOW DOCU | D110: 15(9) | E110: =33507.5 -> 33507.5 | G110: =E110*300% -> 100522.5 | H110: =E110*7.5% -> 2513.0625 | I110: 40122.19 | J110: =E110*50% -> 16753.75 | K110: =E110*350% -> 117276.25 | L110: =E110*100% -> 33507.5 | M110: =160000 -> 160000 | O110: =E110*10% -> 3350.75 | P110: 20000 | Q110: 0 | R110: =SUM(E110:Q110) -> 527553.5 | T110: 40000 | U110: =131250 -> 131250 | V110: ='[2]Jan 2021'!$H$33 -> 837.6875 | W110: 15548.33 | X110: =15548.33+837.69+131250+40000 -> 187636.02 | Y110: 339917.48 | Z110: =R110-X110 -> 339917.48
...

Sheet MEMO1
A2: NATIONAL INSTITUTE FOR LEGISLATIVE AND DEMOCRATIC STUDIES
B3: INTERNAL MEMO
A4: INTERNAL MEMO
A6: FROM : DEPUTY DIRECTOR, FINANCE AND ACCOUNTS
A7: THRU: DIRECTOR, FINANCE AND ACCOUNTS
A8: TO: DG
A9: 29TH JANUARY , 2021
A11: SUBJECT: PAYROLL FOR THE MONTH OF JANUARY, 2021
A12: Find below the details of NILDS Staff Payroll for the month of January, 2021
A14: TO: | C14: DIRECTOR, GENERAL
A15: THRU: | C15: DIRECTOR, FINANCE AND ACCOUNT
A16: FROM: | C16: DEPUTY DIRECTOR, FINANCE AND ACCOUNTS
A17: DATE: | C17: 13TH DECEMBER, 2021
A18: SUBJECT: PAYROLL FOR THE MONTH OF DECEMBER, 2021
A19: Find below the details of NILDS Staff Payroll for the month of December, 2021
A20: GROSS SALARY FOR DECEMBER, 2021 | H20: ='December, 2021'!R188 -> 51639317
A21: DEDUCTIONS
A22: COOP SOCIETY DEDUCTIONS | G22: ='December, 2021'!T188 -> 4849500
A23: COOP LOAN RECOVERY | G23: ='December, 2021'!U188 -> 6686064
A24: PAYE DEDUCTIONS | G24: ='December, 2021'!W188 -> 1514721.3
A25: NHF DEDUCTIONS | G25: ='December, 2021'!V188 -> 26068.025
A26: TOTAL DEDUCTIONS FOR DECEMBER, 2021 | H26: =G22+G23+G24+G25 -> 13076353
A27: NET PAY AS PER DECEMBER, 2021 PAYROLL | H27: =H20-H26 -> 38562964
A28: NET PAY AS PER NOVEMBER, 2021 PAYROLL | H28: ='December, 2021'!Y188 -> 39568935
A29: NET INCREASE/ (DECREASE) IN PAY FOR DECEMBER, 2021 | H29: =H27-H28-1.08 -> -1005971.7
A30: ANALYSED AS FOLLOWS:
A31: Effect of Cooperative adjustment for December 2021 | H31: =143971.73+22000 -> 165971.73
A32: Effect of removal of 1st 28 days to Sunday Adeyi and 2 other drivers (Tanimu & Abdullahi) in November, 2021 | H32: =280000*3 -> 840000
H33: =SUM(H31:H32) -> 1005971.7
E34: NOVEMBER, 2021 | G34: DECEMBER, 2021
E35: No. of Staff | F35: N | G35: No. of Staff | H35: N
A36: 1 | B36: Director General's Office | E36: 30 | F36: ='December, 2021'!Y39 -> 9736111.7 | G36: 30 | H36: ='December, 2021'!Z39 -> 9736111.7
A37: 2 | B37: Internal Audit | E37: 2 | F37: ='December, 2021'!Y43 -> 847880.83 | G37: 1 | H37: ='December, 2021'!Z43 -> 847880.83
A38: 3 | B38: Legis. Support Services | E38: 10 | F38: ='December, 2021'!Y56 -> 3633581.8 | G38: 10 | H38: ='December, 2021'!Z56 -> 3581081.8
A39: 4 | B39: Legal Services | E39: 2 | F39: ='December, 2021'!Y61 -> 1261604.2 | G39: 2 | H39: ='December, 2021'!Z61 -> 1261604.2
A40: 5 | B40: Democracy and Governance | E40: 12 | F40: ='December, 2021'!Y76 -> 3066776.8 | G40: 12 | H40: ='December, 2021'!Z76 -> 3098276.8
A41: 6 | B41: Studies | E41: =7 -> 7 | F41: ='December, 2021'!Y86 -> 2634412.2 | G41: =7 -> 7 | H41: ='December, 2021'!Z86 -> 2634412.2
A42: 7 | B42: Economic Dev. & Social Research | E42: 10 | F42: ='December, 2021'!Y99 -> 3316165.3 | G42: 10 | H42: ='December, 2021'!Z99 -> 3230332
A43: 8 | B43: Training & International | E43: 4 | F43: ='December, 2021'!Y106 -> 1264822 | G43: 4 | H43: ='December, 2021'!Z106 -> 1264822
A44: 9 | B44: Library & Documentation | E44: 8 | F44: ='December, 2021'!Y117 -> 2497780.6 | G44: 8 | H44: ='December, 2021'!Z117 -> 2497780.6
A45: 10 | B45: Finance and Accounts | E45: 9 | F45: ='December, 2021'!Y129 -> 2792106.4 | G45: 9 | H45: ='December, 2021'!Z129 -> 2792106.4
A46: 11 | B46: Admin & HR | E46: 55 | F46: ='December, 2021'!Y187 -> 8517692.7 | G46: 55 | H46: ='December, 2021'!Z187 -> 7618555.4
E47: =SUM(E36:E46) -> 149 | F47: =SUM(F36:F46) -> 39568935 | G47: =SUM(G36:G46) -> 148 | H47: =SUM(H36:H46) -> 38562964
A48: The Director General is requested to consider and approve payment of N38,562,963.95 to Guaranty Trust Bank being December 2021 Salary, N11,535,564.01 being NILDS Coop Society deductions for December, 2021 N1,514,721.30 being PAYE Tax Deductions from Staff Salary for the month of December, 2021 and N26,068.02 being NHF deductions from staff for December, 2021 .
A51: KABIR M SULAIMAN
A52: Deputy Director, Finance and Accounts
C156: =10000 -> 10000

Sheet 13 month
B3: SCHEDULE OF 13TH MONTH SALARY FOR 3 STAFF FOR YEAR, 2021
F4: ='[1]FEB 08'!E8/'[1]FEB 08'!M8 -> 0.22 | I4: ='[1]FEB 08'!F8/'[1]FEB 08'!Q8 -> 0.3
B5: STAFF NAME | U5: DEDUCTIONS
D6: DESIGNATION | E6: SALARY | F6: BASIC | M6: MOTOR/ | N6: RESEARCH | O6: HARDSHIP | P6: LEAVE | Q6: OUT FIT | R6: LEGISLATIVE | S6: GROSS | Z6: NOVEMBER,2021 | AA6: N
E7: LEVEL | F7: SALARY | G7: SALARY/ALLOWCE AREARS | H7: RENT | I7: UTILITY | J7: DOMESTIC | K7: ENTERT. | L7: FURNIT. | M7: FUEL | N7: ALLOWANCE | O7: ALLOWANCE | P7: ALLCE | Q7: ALLCE | R7: DUTY ALLCE | S7: SALARY | T7: AUCTION | U7: COOP SOCIETY | V7: COOP. LOAN RECOVERY | W7: NHF DEDUCTION | X7: PAYE | Y7: TOTAL
A8: S/N | B8: DG OFFICE | F8: N | I8: N | S8: N | X8: N
B9: LEG. SUPPORT SEVICES
A10: 1 | B10: BETHEL UZOMA IHUGBA | D10: SNR RESEARCH FELLOW | E10: 15(9) | F10: =33507.5 -> 33507.5 | H10: =F10*300% -> 100522.5 | I10: =F10*7.5% -> 2513.0625 | J10: 40122.19 | K10: =F10*50% -> 16753.75 | L10: =F10*350% -> 117276.25 | M10: =F10*100% -> 33507.5 | N10: =160000 -> 160000 | P10: =F10*10% -> 3350.75 | Q10: 20000 | S10: =SUM(F10:R10) -> 527553.5 | Y10: =X10+W10+V10+U10+T10 -> 0 | Z10: 162099.21 | AA10: =S10-Y10 -> 527553.5
B11: TOTAL | D11: 1 | F11: =SUM(F10:F10) -> 33507.5 | G11: =SUM(G10:G10) -> 0 | H11: =SUM(H10:H10) -> 100522.5 | I11: =SUM(I10:I10) -> 2513.0625 | J11: =SUM(J10:J10) -> 40122.19 | K11: =SUM(K10:K10) -> 16753.75 | L11: =SUM(L10:L10) -> 117276.25 | M11: =SUM(M10:M10) -> 33507.5 | N11: =SUM(N10:N10) -> 160000 | P11: =SUM(P10:P10) -> 3350.75 | Q11: =SUM(Q10:Q10) -> 20000 | R11: =SUM(R10:R10) -> 0 | S11: =SUM(S10:S10) -> 527553.5 | W11: =SUM(W10:W10) -> 0 | Y11: =SUM(Y10:Y10) -> 0 | Z11: 3633581.8 | AA11: =SUM(AA10:AA10) -> 527553.5
B13: FINANCE & ACCOUNT
A14: 2 | B14: TONDO IORWUESE EDWARD | D14: ASST. DIRECTOR, ACCOUNTS | E14: 15(8) | F14: =32263.2 -> 32263.2 | H14: =F14*300% -> 96789.6 | I14: =F14*7.5% -> 2419.74 | J14: =40122.19 -> 40122.19 | K14: =F14*50% -> 16131.6 | L14: =F14*350% -> 112921.2 | M14: =F14*100% -> 32263.2 | O14: =80000 -> 80000 | P14: =F14*10% -> 3226.32 | Q14: 20000 | R14: =100000 -> 100000 | S14: =SUM(F14:R14) -> 536137.05 | Y14: =X14+W14+V14+U14+T14 -> 0 | Z14: 339782.14 | AA14: =S14-Y14 -> 536137.05
B15: TOTAL | D15: 1 | F15: =SUM(F14:F14) -> 32263.2 | H15: =SUM(H14:H14) -> 96789.6 | I15: =SUM(I14:I14) -> 2419.74 | J15: =SUM(J14:J14) -> 40122.19 | K15: =SUM(K14:K14) -> 16131.6 | L15: =SUM(L14:L14) -> 112921.2 | M15: =SUM(M14:M14) -> 32263.2 | O15: =SUM(O14:O14) -> 80000 | P15: =SUM(P14:P14) -> 3226.32 | Q15: =SUM(Q14:Q14) -> 20000 | R15: =SUM(R14:R14) -> 100000 | S15: =SUM(S14:S14) -> 536137.05 | Y15: =SUM(Y14:Y14) -> 0 | Z15: 2792106.4 | AA15: =SUM(AA14:AA14) -> 536137.05
B17: ADMINISTRATION & HUMAN RESOURCE
A18: 3 | B18: SALAMATU YAKUBU | D18: CHIEF ADMIN OFFICER | E18: 14(8) | F18: =25854.1 -> 25854.1 | H18: =F18*300% -> 77562.3 | I18: =F18*7.5% -> 1939.0575 | J18: 0 | K18: =F18*50% -> 12927.05 | L18: =F18*350% -> 90489.35 | M18: =F18*100% -> 25854.1 | O18: 70000 | P18: =F18*10% -> 2585.41 | Q18: 20000 | R18: 0 | S18: =SUM(F18:R18) -> 327211.37 | Y18: =X18+W18+V18+U18+T18 -> 0 | Z18: 185530.19 | AA18: =S18-Y18 -> 327211.37
B19: TOTAL | D19: 1 | F19: =SUM(F18:F18) -> 25854.1 | G19: =SUM(G18:G18) -> 0 | H19: =SUM(H18:H18) -> 77562.3 | I19: =SUM(I18:I18) -> 1939.0575 | J19: =SUM(J18:J18) -> 0 | K19: =SUM(K18:K18) -> 12927.05 | L19: =SUM(L18:L18) -> 90489.35 | M19: =SUM(M18:M18) -> 25854.1 | O19: =SUM(O18:O18) -> 70000 | P19: =SUM(P18:P18) -> 2585.41 | Q19: =SUM(Q18:Q18) -> 20000 | R19: =SUM(R18:R18) -> 0 | S19: =SUM(S18:S18) -> 327211.37 | U19: =SUM(U18:U18) -> 0 | V19: =SUM(V18:V18) -> 0 | Y19: =SUM(Y18:Y18) -> 0 | Z19: 8517692.7 | AA19: =SUM(AA18:AA18) -> 327211.37
B20: GRAND TOTAL | D20: 3 | F20: =SUM(F19,F15,F11) -> 91624.8 | G20: =SUM(G19,G11) -> 0 | H20: =SUM(H19,H15,H11) -> 274874.4 | I20: =SUM(I19,I15,I11) -> 6871.86 | J20: =SUM(J19,J15,J11) -> 80244.38 | K20: =SUM(K19,K15,K11) -> 45812.4 | L20: =SUM(L19,L15,L11) -> 320686.8 | M20: =SUM(M19,M15,M11) -> 91624.8 | N20: =SUM(N11) -> 160000 | O20: =SUM(O19,O15) -> 150000 | P20: =SUM(P19,P15,P11) -> 9162.48 | Q20: =SUM(Q19,Q15,Q11) -> 60000 | R20: =SUM(R19,R15,R11) -> 100000 | S20: =SUM(S19,S15,S11) -> 1390901.9 | U20: =SUM(U19,U15,U11) -> 0 | V20: =SUM(V19,V15,V11) -> 0 | W20: =SUM(W19,W15,W11) -> 0 | X20: =SUM(X19,X15,X11) -> 0 | Y20: =SUM(Y19,Y15,Y11) -> 0 | Z20: =SUM(Z10:Z19) -> 15630792 | AA20: =SUM(AA19,AA15,AA11) -> 1390901.9
K22: SIGNATURE | P22: DATE

Sheet Sheet3
A2: Research /Hardshi allowances
A4: 1 | B4: Fajingbesi | C4: =100000 -> 100000
A5: 2 | B5: Joy | C5: 50000
A6: 3 | B6: Maryam | C6: 100000
A7: 4 | B7: Terfa Gbahabo | C7: =50000 -> 50000
A8: 5 | B8: Hassana | C8: =140000 -> 140000
A9: 6 | B9: Yakub | C9: =10000 -> 10000
C10: =SUM(C4:C9) -> 450000
B11: Arears
A12: 1 | B12: Yakub | C12: =45283 -> 45283
A13: 2 | B13: Abdullahi | C13: =35436 -> 35436
C14: =SUM(C11:C13) -> 80719
B16: Late Staff
B17: Bashir Auwal | C17: =33074.51 -> 33074.51
B18: Chukwuka Edmond | C18: =148722.77 -> 148722.77
C19: =SUM(C17:C18) -> 181797.28
B21: Dr. Eze
B22: Director Salary | C22: =925433.08 -> 925433.08
B23: DD | C23: =451465+90000 -> 541465
B24: DIFF. | C24: =C22-C23 -> 383968.08
B25: Portion for 12 days | C25: =C24*12/31 -> 148632.81

Sheet Promotion
B3: STAFF PAYROLL FOR THE MONTH OF SEPTEMBER, 2021
F4: ='[1]FEB 08'!E8/'[1]FEB 08'!M8 -> 0.22 | I4: ='[1]FEB 08'!F8/'[1]FEB 08'!Q8 -> 0.3
B5: EFFECT OF PROMOTION | U5: DEDUCTIONS | AA5: NET SALARY
D6: DESIGNATION | E6: OLD SALARY | F6: BASIC | M6: MOTOR/ | N6: RESEARCH | O6: HARDSHIP | P6: LEAVE | Q6: OUT FIT | R6: LEGISLATIVE | S6: OLD GROSS | Z6: AUGUST,2021 | AA6: SEPTEMBER,2021 | AB6: NEW SALARY | AC6: NEWGROSS
E7: LEVEL | F7: SALARY | G7: SALARY/ALLOWCE AREARS | H7: RENT | I7: UTILITY | J7: DOMESTIC | K7: ENTERT. | L7: FURNIT. | M7: FUEL | N7: ALLOWANCE | O7: ALLOWANCE | P7: ALLCE | Q7: ALLCE | R7: DUTY ALLCE | S7: SALARY | T7: AUCTION | U7: COOP SOCIETY | V7: COOP. LOAN RECOVERY | W7: NHF DEDUCTION | X7: PAYE | Y7: TOTAL | AB7: GRADE LEVEL | AC7: SALARY | AD7: DIFFERENCE | AE7: AREARS FOR AUGUST | AF7: TOTAL DIFFERENCE | AG7: OLD PAYE | AH7: NEW PAYE | AI7: DIFF
A8: S/N | B8: DG OFFICE | F8: N | I8: N | S8: N | X8: N
A9: 1 | B9: HUSSEIN EGYE MUSA | D9: AM PROTOCOL | E9: 13(10) | F9: =25523.45 -> 25523.45 | H9: =F9*300% -> 76570.35 | I9: =F9*7.5% -> 1914.2587 | K9: =F9*50% -> 12761.725 | L9: =F9*350% -> 89332.075 | M9: =F9*100% -> 25523.45 | O9: =70000 -> 70000 | P9: =F9*10% -> 2552.345 | Q9: 15000 | R9: 50000 | S9: =R9+Q9+P9+O9+N9+M9+L9+K9+J9+I9+H9+G9+F9 -> 369177.65 | U9: 50000 | V9: =150000 -> 150000 | W9: 0 | X9: 7709.76 | Y9: =X9+W9+V9+U9+T9 -> 207709.76 | Z9: 160467.89 | AA9: =S9-Y9 -> 161467.89 | AB9: 14 (8) | AC9: =257211+70000+50000 -> 377211 | AD9: =AC9-S9 -> 8033.3463 | AE9: =23/31*AD9 -> 5960.2246 | AF9: =AD9+AE9 -> 13993.571 | AG9: 7709.76 | AH9: 7709.76 | AI9: =AH9-AG9 -> 0 | AK9: =AC9+AE9 -> 383171.22
A10: 2 | B10: DONALD E. MKPANAM | D10: AM ICT | E10: 13(11) | F10: 26339.3 | H10: =F10*300% -> 79017.9 | I10: =F10*7.5% -> 1975.4475 | K10: =F10*50% -> 13169.65 | L10: =F10*350% -> 92187.55 | M10: =F10*100% -> 26339.3 | O10: =70000 -> 70000 | P10: =F10*10% -> 2633.93 | Q10: 15000 | R10: 0 | S10: =R10+Q10+P10+O10+N10+M10+L10+K10+J10+I10+H10+G10+F10 -> 326663.08 | W10: ='[2]Jan 2021'!$H$28 -> 658.4825 | X10: 7709.76 | Y10: =X10+W10+V10+U10+T10 -> 8368.2425 | Z10: 318294.83 | AA10: =S10-Y10 -> 318294.83 | AB10: 14 (8) | AC10: =257211+70000 -> 327211 | AD10: =AC10-S10 -> 547.9225 | AE10: =23/31*AD10 -> 406.52315 | AF10: =AD10+AE10 -> 954.44565 | AG10: 7709.76 | AH10: 7709.76 | AI10: =AH10-AG10 -> 0 | AK10: =AC10+AE10 -> 327617.52
A11: 3 | B11: JOY HARUNA MAKERI | D11: AM TRAINING | E11: 13(10) | F11: =25523.45 -> 25523.45 | H11: =F11*300% -> 76570.35 | I11: =F11*7.5% -> 1914.2587 | K11: =F11*50% -> 12761.725 | L11: =F11*350% -> 89332.075 | M11: =F11*100% -> 25523.45 | N11: =120000 -> 120000 | P11: =F11*10% -> 2552.345 | Q11: 15000 | R11: =50000+100000 -> 150000 | S11: =R11+Q11+P11+O11+N11+M11+L11+K11+J11+I11+H11+G11+F11 -> 519177.65 | X11: =7709.76 -> 7709.76 | Y11: =X11+W11+V11+U11+T11 -> 7709.76 | Z11: 546467.89 | AA11: =S11-Y11 -> 511467.89 | AB11: 14 (8) | AC11: =257211+140000+150000 -> 547211 | AD11: =AC11-S11 -> 28033.346 | AE11: =23/31*AD11 -> 20798.934 | AF11: =AD11+AE11 -> 48832.281 | AG11: 7709.76 | AH11: 7709.76 | AI11: =AH11-AG11 -> 0
A12: 4 | B12: CHRISTIAN MADUABUCHI ODO | D12: ICT OFFICER | E12: 10(11) | S12: 246866.02 | AB12: 12(7) | AC12: =205372+60000 -> 265372 | AD12: =AC12-S12 -> 18505.984 | AE12: =23/31*AD12 -> 13730.246 | AF12: =AD12+AE12 -> 32236.23 | AG12: =3369.51 -> 3369.51 | AH12: =3369.51 -> 3369.51 | AI12: =AH12-AG12 -> 0
B13: TOTAL | D13: 4 | F13: =SUM(F9:F11) -> 77386.2 | G13: =SUM(G9:G11) -> 0 | H13: =SUM(H9:H11) -> 232158.6 | I13: =SUM(I9:I11) -> 5803.965 | J13: =SUM(J9:J11) -> 0 | K13: =SUM(K9:K11) -> 38693.1 | L13: =SUM(L9:L11) -> 270851.7 | M13: =SUM(M9:M11) -> 77386.2 | ... S13: =SUM(S9:S11) -> 1215018.4 | U13: =SUM(U9:U11) -> 50000 | V13: =SUM(V9:V11) -> 150000 | W13: =SUM(W9:W11) -> 658.4825 | X13: =SUM(X9:X11) -> 23129.28 | Y13: =SUM(Y9:Y11) -> 223787.76 | Z13: 9309597.9 | AA13: =SUM(AA9:AA11) -> 991230.62 | AC13: =SUM(AC9:AC12) -> 1517005 | AD13: =SUM(AD9:AD12) -> 55120.599 | AE13: =SUM(AE9:AE12) -> 40895.928 | AF13: =SUM(AF9:AF12) -> 96016.527 | AG13: =SUM(AG9:AG12) -> 26498.79 | AH13: =SUM(AH9:AH12) -> 26498.79 | AI13: =SUM(AI9:AI12) -> 0
B15: INTERNAL AUDIT
C16: TOTAL | F16: =SUM(#REF!) -> #REF! | H16: =SUM(#REF!) -> #REF! | I16: =SUM(#REF!) -> #REF! | J16: =SUM(#REF!) -> #REF! | K16: =SUM(#REF!) -> #REF! | L16: =SUM(#REF!) -> #REF! | M16: =SUM(#REF!) -> #REF! | N16: =SUM(#REF!) -> #REF! | O16: =SUM(#REF!) -> #REF! | P16: =SUM(#REF!) -> #REF! | U16: =SUM(#REF!) -> #REF! | V16: =SUM(#REF!) -> #REF! | W16: =SUM(#REF!) -> #REF! | X16: =SUM(#REF!) -> #REF! | Y16: =SUM(#REF!) -> #REF! | Z16: 478180.46 | AA16: =SUM(#REF!) -> #REF!
B17: LEG. SUPPORT SEVICES
A18: 1 | B18: OGUCHE SAMUEL | D18: RESEARCH FELLOW I | E18: 14(11) | F18: 28489.81 | H18: =F18*300% -> 85469.43 | I18: =F18*7.5% -> 2136.7357 | K18: =F18*50% -> 14244.905 | L18: =F18*350% -> 99714.335 | M18: =F18*100% -> 28489.81 | N18: =140000 -> 140000 | P18: =F18*10% -> 2848.981 | Q18: 20000 | S18: =SUM(F18:R18) -> 421394.01 | U18: =30000 -> 30000 | V18: =0 -> 0 | X18: 7709.76 | Y18: =X18+W18+V18+U18+T18 -> 37709.76 | Z18: 383684.25 | AA18: =S18-Y18 -> 383684.25 | AB18: 15(7) | AC18: =344720+160000 -> 504720 | AD18: =AC18-S18 -> 83325.993 | AE18: =23/31*AD18 -> 61822.511 | AF18: =AE18+AD18 -> 145148.5 | AG18: 7709.76 | AH18: 15548.33 | AI18: =AH18-AG18 -> 7838.57
A19: 2 | B19: YAHAYA SHAMSU | D19: RESEARCH FELLOW 11 | E19: 13(11) | F19: =26339.3 -> 26339.3 | H19: =F19*300% -> 79017.9 | I19: =F19*7.5% -> 1975.4475 | K19: =F19*50% -> 13169.65 | L19: =F19*350% -> 92187.55 | M19: =F19*100% -> 26339.3 | N19: =120000 -> 120000 | P19: =F19*10% -> 2633.93 | Q19: 15000 | S19: =SUM(F19:R19) -> 376663.08 | W19: 0 | X19: 7709.76 | Y19: =X19+W19+V19+U19+T19 -> 7709.76 | Z19: 368953.32 | AA19: =S19-Y19 -> 368953.32 | AB19: 14(8) | AC19: =257211+140000 -> 397211 | AD19: =AC19-S19 -> 20547.923 | AE19: =23/31*AD19 -> 15245.233 | AF19: =AE19+AD19 -> 35793.155 | AG19: 7709.76 | AH19: 7709.76 | AI19: =AH19-AG19 -> 0
B20: TOTAL | D20: 2 | F20: =SUM(F18:F19) -> 54829.11 | H20: =SUM(H18:H19) -> 164487.33 | I20: =SUM(I18:I19) -> 4112.1833 | J20: =SUM(J18:J19) -> 0 | K20: =SUM(K18:K19) -> 27414.555 | L20: =SUM(L18:L19) -> 191901.89 | M20: =SUM(M18:M19) -> 54829.11 | N20: =SUM(N18:N19) -> 260000 | P20: =SUM(P18:P19) -> 5482.911 | Q20: =SUM(Q18:Q19) -> 35000 | R20: =SUM(R18:R19) -> 0 | S20: =SUM(S18:S19) -> 798057.08 | U20: =SUM(U18:U19) -> 30000 | V20: =SUM(V18:V19) -> 0 | W20: =SUM(W18:W19) -> 0 | X20: =SUM(X18:X19) -> 15419.52 | Y20: =SUM(Y18:Y19) -> 45419.52 | Z20: 3862557.6 | AA20: =SUM(AA18:AA19) -> 752637.56 | AC20: =SUM(AC18:AC19) -> 901931 | AD20: =SUM(AD18:AD19) -> 103873.92 | AE20: =SUM(AE18:AE19) -> 77067.744 | AF20: =SUM(AF18:AF19) -> 180941.66 | AG20: =SUM(AG18:AG19) -> 15419.52 | AH20: =SUM(AH18:AH19) -> 23258.09 | AI20: =SUM(AI18:AI19) -> 7838.57
B22: LEGAL SERVICES
B23: TOTAL | F23: =SUM(#REF!) -> #REF! | H23: =SUM(#REF!) -> #REF! | I23: =SUM(#REF!) -> #REF! | J23: =SUM(#REF!) -> #REF! | K23: =SUM(#REF!) -> #REF! | L23: =SUM(#REF!) -> #REF! | M23: =SUM(#REF!) -> #REF! | N23: =SUM(#REF!) -> #REF! | O23: =SUM(#REF!) -> #REF! | ... R23: =SUM(#REF!) -> #REF! | S23: =0 -> 0 | U23: =SUM(#REF!) -> #REF! | W23: =SUM(#REF!) -> #REF! | X23: =SUM(#REF!) -> #REF! | Y23: =SUM(#REF!) -> #REF! | Z23: 931604.15 | AA23: =SUM(#REF!) -> #REF!
B25: DEMOCRACY AND GOVERNANCE
A26: 1 | B26: YUNUSA ABDULLAHI | D26: RESEARCH FELLOW 11 | E26: 13(11) | F26: =26339.3 -> 26339.3 | H26: =F26*300% -> 79017.9 | I26: =F26*7.5% -> 1975.4475 | K26: =F26*50% -> 13169.65 | L26: =F26*350% -> 92187.55 | M26: =F26*100% -> 26339.3 | N26: =120000 -> 120000 | P26: =F26*10% -> 2633.93 | Q26: 15000 | S26: =SUM(F26:R26) -> 376663.08 | U26: =10000 -> 10000 | V26: =54585.66 -> 54585.66 | X26: =7709.76 -> 7709.76 | Y26: =X26+W26+V26+U26+T26 -> 72295.42 | Z26: 303367.66 | AA26: =S26-Y26 -> 304367.66 | AB26: 14(8) | AC26: =257211+140000 -> 397211 | AD26: =AC26-S26 -> 20547.923 | AE26: =23/31*AD26 -> 15245.233 | AF26: =AE26+AD26 -> 35793.155 | AG26: 7709.76 | AH26: 7709.76 | AI26: =AH26-AG26 -> 0
A27: 2 | B27: OSOLAFIA MUHAMMAD EGYE | D27: RESEARCH OFFICER | E27: 10(11) | F27: =19276.95 -> 19276.95 | H27: =F27*300% -> 57830.85 | I27: =F27*7.5% -> 1445.7713 | J27: 0 | K27: =F27*50% -> 9638.475 | L27: =F27*350% -> 67469.325 | M27: =F27*100% -> 19276.95 | N27: =100000 -> 100000 | P27: =F27*10% -> 1927.695 | Q27: 10000 | R27: 0 | S27: =SUM(F27:R27) -> 286866.02 | U27: =20000 -> 20000 | V27: =100000 -> 100000 | W27: ='[2]Jan 2021'!$H$43 -> 481.92375 | X27: =3369.51 -> 3369.51 | Y27: =X27+W27+V27+U27+T27 -> 123851.43 | Z27: 163014.58 | AA27: =S27-Y27 -> 163014.58 | AB27: 12(7) | AC27: =205372+110000 -> 315372 | AD27: =AC27-S27 -> 28505.984 | AE27: =23/31*AD27 -> 21149.601 | AF27: =AE27+AD27 -> 49655.585 | AG27: =3369.51 -> 3369.51 | AH27: =3369.51 -> 3369.51 | AI27: =AH27-AG27 -> 0 | AK27: =AC27+AE27 -> 336521.6
B28: TOTAL | D28: 2 | F28: =SUM(F26:F27) -> 45616.25 | H28: =SUM(H26:H27) -> 136848.75 | I28: =SUM(I26:I27) -> 3421.2188 | J28: =SUM(J26:J27) -> 0 | K28: =SUM(K26:K27) -> 22808.125 | L28: =SUM(L26:L27) -> 159656.88 | M28: =SUM(M26:M27) -> 45616.25 | N28: =SUM(N26:N27) -> 220000 | P28: =SUM(P26:P27) -> 4561.625 | Q28: =SUM(Q26:Q27) -> 25000 | R28: =SUM(R26:R27) -> 0 | S28: =SUM(S26:S27) -> 663529.09 | U28: =SUM(U26:U27) -> 30000 | V28: =SUM(V26:V27) -> 154585.66 | W28: =SUM(W26:W27) -> 481.92375 | X28: =SUM(X26:X27) -> 11079.27 | Y28: =SUM(Y26:Y27) -> 196146.85 | Z28: 3477220.9 | AA28: =SUM(AA26:AA27) -> 467382.24 | AC28: =SUM(AC26:AC27) -> 712583 | AD28: =SUM(AD26:AD27) -> 49053.906 | AE28: =SUM(AE26:AE27) -> 36394.834 | AF28: =SUM(AF26:AF27) -> 85448.74 | AG28: =SUM(AG26:AG27) -> 11079.27 | AH28: =SUM(AH26:AH27) -> 11079.27 | AI28: =SUM(AI26:AI27) -> 0
B30: STUDIES
B31: TOTAL | F31: =SUM(#REF!) -> #REF! | H31: =SUM(#REF!) -> #REF! | I31: =SUM(#REF!) -> #REF! | J31: =SUM(#REF!) -> #REF! | K31: =SUM(#REF!) -> #REF! | L31: =SUM(#REF!) -> #REF! | M31: =SUM(#REF!) -> #REF! | N31: =SUM(#REF!) -> #REF! | P31: =SUM(#REF!) -> #REF! | Q31: =SUM(#REF!) -> #REF! | R31: =SUM(#REF!) -> #REF! | S31: =0 -> 0 | U31: =SUM(#REF!) -> #REF! | V31: =SUM(#REF!) -> #REF! | W31: =SUM(#REF!) -> #REF! | X31: =SUM(#REF!) -> #REF! | Y31: =SUM(#REF!) -> #REF! | Z31: 3200748.9 | AA31: =SUM(#REF!) -> #REF!
B33: ECONOMIC DEV. AND SOCIAL RESEARCH
B34: TOTAL | F34: =SUM(#REF!) -> #REF! | G34: =SUM(#REF!) -> #REF! | H34: =SUM(#REF!) -> #REF! | I34: =SUM(#REF!) -> #REF! | J34: =SUM(#REF!) -> #REF! | K34: =SUM(#REF!) -> #REF! | L34: =SUM(#REF!) -> #REF! | M34: =SUM(#REF!) -> #REF! | N34: =SUM(#REF!) -> #REF! | P34: =SUM(#REF!) -> #REF! | Q34: =SUM(#REF!) -> #REF! | R34: =SUM(#REF!) -> #REF! | S34: =0 -> 0 | U34: =SUM(#REF!) -> #REF! | V34: =SUM(#REF!) -> #REF! | W34: =SUM(#REF!) -> #REF! | X34: =SUM(#REF!) -> #REF! | Y34: =SUM(#REF!) -> #REF! | Z34: 3494235.1 | AA34: =SUM(#REF!) -> #REF!
B36: TRAINING AND INTERNATIONAL COOP
B37: TOTAL | F37: =SUM(#REF!) -> #REF! | H37: =SUM(#REF!) -> #REF! | I37: =SUM(#REF!) -> #REF! | J37: =SUM(#REF!) -> #REF! | K37: =SUM(#REF!) -> #REF! | L37: =SUM(#REF!) -> #REF! | M37: =SUM(#REF!) -> #REF! | N37: =SUM(#REF!) -> #REF! | O37: =SUM(#REF!) -> #REF! | ... R37: =SUM(#REF!) -> #REF! | S37: =0 -> 0 | U37: =SUM(#REF!) -> #REF! | V37: =SUM(#REF!) -> #REF! | W37: =SUM(#REF!) -> #REF! | X37: =SUM(#REF!) -> #REF! | Y37: =SUM(#REF!) -> #REF! | Z37: 547219.79 | AA37: =SUM(#REF!) -> #REF!
B39: LIBRARY AND DOCUMENTATION
B40: TOTAL | F40: =SUM(#REF!) -> #REF! | H40: =SUM(#REF!) -> #REF! | I40: =SUM(#REF!) -> #REF! | J40: =SUM(#REF!) -> #REF! | K40: =SUM(#REF!) -> #REF! | L40: =SUM(#REF!) -> #REF! | M40: =SUM(#REF!) -> #REF! | N40: =SUM(#REF!) -> #REF! | P40: =SUM(#REF!) -> #REF! | Q40: =SUM(#REF!) -> #REF! | R40: =SUM(#REF!) -> #REF! | S40: =0 -> 0 | U40: =SUM(#REF!) -> #REF! | V40: =SUM(#REF!) -> #REF! | W40: =SUM(#REF!) -> #REF! | X40: =SUM(#REF!) -> #REF! | Y40: =SUM(#REF!) -> #REF! | Z40: 2082060.7 | AA40: =SUM(#REF!) -> #REF!
B42: FINANCE & ACCOUNT
B43: TOTAL | F43: =SUM(#REF!) -> #REF! | H43: =SUM(#REF!) -> #REF! | I43: =SUM(#REF!) -> #REF! | J43: =SUM(#REF!) -> #REF! | K43: =SUM(#REF!) -> #REF! | L43: =SUM(#REF!) -> #REF! | M43: =SUM(#REF!) -> #REF! | O43: =SUM(#REF!) -> #REF! | P43: =SUM(#REF!) -> #REF! | Q43: =SUM(#REF!) -> #REF! | R43: =SUM(#REF!) -> #REF! | S43: =0 -> 0 | U43: =SUM(#REF!) -> #REF! | V43: =SUM(#REF!) -> #REF! | W43: =SUM(#REF!) -> #REF! | X43: =SUM(#REF!) -> #REF! | Y43: =SUM(#REF!) -> #REF! | Z43: 2761365 | AA43: =SUM(#REF!) -> #REF!
B45: ADMINISTRATION & HUMAN RESOURCE
A46: 1 | B46: SIMON YAKUBU WAKAWA | D46: ASST. MANAGER , ASSETS & MAINT. | E46: 13(10) | F46: =25523.45 -> 25523.45 | H46: =F46*300% -> 76570.35 | I46: =F46*7.5% -> 1914.2587 | J46: 0 | K46: =F46*50% -> 12761.725 | L46: =F46*350% -> 89332.075 | M46: =F46*100% -> 25523.45 | O46: 70000 | P46: =F46*10% -> 2552.345 | Q46: 15000 | S46: =SUM(F46:R46) -> 319177.65 | U46: 30000 | V46: =52500 -> 52500 | W46: ='[2]Jan 2021'!$H$49 -> 638.08625 | X46: 7709.76 | Y46: =X46+W46+V46+U46+T46 -> 90847.846 | Z46: 223329.81 | AA46: =S46-Y46 -> 228329.81 | AB46: 14 (8) | AC46: =257211+70000 -> 327211 | AD46: =AC46-S46 -> 8033.3463 | AE46: =23/31*AD46 -> 5960.2246 | AF46: =AE46+AD46 -> 13993.571 | AG46: 7709.76 | AH46: 7709.76 | AI46: =AH46-AG46 -> 0
A47: 2 | B47: SALAMATU YAKUBU | D47: PRINCIPAL CONF. SECRETARY | E47: 13(10) | F47: =25523.45 -> 25523.45 | H47: =F47*300% -> 76570.35 | I47: =F47*7.5% -> 1914.2587 | J47: 0 | K47: =F47*50% -> 12761.725 | L47: =F47*350% -> 89332.075 | M47: =F47*100% -> 25523.45 | O47: 70000 | P47: =F47*10% -> 2552.345 | Q47: 15000 | R47: 0 | S47: =SUM(F47:R47) -> 319177.65 | U47: =0 -> 0 | V47: =0 -> 0 | W47: ='[2]Jan 2021'!$H$53 -> 638.08625 | X47: 7709.76 | Y47: =X47+W47+V47+U47+T47 -> 8347.8463 | Z47: 308829.81 | AA47: =S47-Y47 -> 310829.81 | AB47: 14 (8) | AC47: =257211+70000 -> 327211 | AD47: =AC47-S47 -> 8033.3463 | AE47: =23/31*AD47 -> 5960.2246 | AF47: =AE47+AD47 -> 13993.571 | AG47: 7709.76 | AH47: 7709.76 | AI47: =AH47-AG47 -> 0
A48: 3 | B48: USMAN WAZIRI | D48: PRINCIPAL CONF. SECRETARY | E48: 13(10) | F48: =25523.45 -> 25523.45 | H48: =F48*300% -> 76570.35 | I48: =F48*7.5% -> 1914.2587 | J48: 0 | K48: =F48*50% -> 12761.725 | L48: =F48*350% -> 89332.075 | M48: =F48*100% -> 25523.45 | O48: 70000 | P48: =F48*10% -> 2552.345 | Q48: 15000 | R48: 0 | S48: =SUM(F48:R48) -> 319177.65 | U48: =3000 -> 3000 | V48: =50000 -> 50000 | X48: 7709.76 | Y48: =X48+W48+V48+U48+T48 -> 60709.76 | Z48: 258467.89 | AA48: =S48-Y48 -> 258467.89 | AB48: 14 (8) | AC48: =257211+70000 -> 327211 | AD48: =AC48-S48 -> 8033.3463 | AE48: =23/31*AD48 -> 5960.2246 | AF48: =AE48+AD48 -> 13993.571 | AG48: 7709.76 | AH48: 7709.76 | AI48: =AH48-AG48 -> 0
A49: 4 | B49: EROMOSELE OMONIGBO | D49: PERSONNEL OFFICER | E49: 10(11) | F49: =19276.95 -> 19276.95 | H49: =F49*300% -> 57830.85 | I49: =F49*7.5% -> 1445.7713 | J49: 0 | K49: =F49*50% -> 9638.475 | L49: =F49*350% -> 67469.325 | M49: =F49*100% -> 19276.95 | O49: =60000 -> 60000 | P49: =F49*10% -> 1927.695 | Q49: 10000 | R49: 0 | S49: =SUM(F49:R49) -> 246866.02 | U49: 10000 | V49: =0 -> 0 | W49: ='[2]Jan 2021'!$H$41 -> 481.92375 | X49: =3369.51 -> 3369.51 | Y49: =X49+W49+V49+U49+T49 -> 13851.434 | Z49: 233014.58 | AA49: =S49-Y49 -> 233014.58 | AB49: 12(7) | AC49: =205372+60000 -> 265372 | AD49: =AC49-S49 -> 18505.984 | AE49: =23/31*AD49 -> 13730.246 | AF49: =AE49+AD49 -> 32236.23 | AG49: =3369.51 -> 3369.51 | AH49: =3369.51 -> 3369.51 | AI49: =AH49-AG49 -> 0
A50: 5 | B50: OGUNYOMI ROTIMI | D50: PERSONNEL OFFICER | E50: 10(10) | F50: =18779.3 -> 18779.3 | H50: =F50*300% -> 56337.9 | I50: =F50*7.5% -> 1408.4475 | J50: 0 | K50: =F50*50% -> 9389.65 | L50: =F50*350% -> 65727.55 | M50: =F50*100% -> 18779.3 | O50: =60000 -> 60000 | P50: =F50*10% -> 1877.93 | Q50: 10000 | R50: 0 | S50: =SUM(F50:R50) -> 242300.08 | V50: =50000 -> 50000 | X50: 3369.51 | Y50: =X50+W50+V50+U50+T50 -> 53369.51 | Z50: 188930.57 | AA50: =S50-Y50 -> 188930.57 | AB50: 12(7) | AC50: =205372+60000 -> 265372 | AD50: =AC50-S50 -> 23071.923 | AE50: =23/31*AD50 -> 17117.878 | AF50: =AE50+AD50 -> 40189.8 | AG50: =3369.51 -> 3369.51 | AH50: =3369.51 -> 3369.51 | AI50: =AH50-AG50 -> 0
A51: 6 | B51: OMOUDU QUEEN PRISCILLA | D51: SECRETARY | E51: 10(11) | F51: =19276.95 -> 19276.95 | H51: =F51*300% -> 57830.85 | I51: =F51*7.5% -> 1445.7713 | K51: =F51*50% -> 9638.475 | L51: =F51*350% -> 67469.325 | M51: =F51*100% -> 19276.95 | O51: =60000 -> 60000 | P51: =F51*10% -> 1927.695 | Q51: 10000 | S51: =SUM(F51:R51) -> 246866.02 | U51: =20000+10000 -> 30000 | X51: 3369.51 | Y51: =X51+W51+V51+U51+T51 -> 33369.51 | Z51: 213496.51 | AA51: =S51-Y51 -> 213496.51 | AB51: 12(7) | AC51: =205372+60000 -> 265372 | AD51: =AC51-S51 -> 18505.984 | AE51: =23/31*AD51 -> 13730.246 | AF51: =AE51+AD51 -> 32236.23 | AG51: =3369.51 -> 3369.51 | AH51: =3369.51 -> 3369.51 | AI51: =AH51-AG51 -> 0
A52: 7 | B52: YUSIF SADIQ SANI | D52: CONFIDENTIAL SECRETARY | E52: 8(10) | F52: =13492.21 -> 13492.21 | H52: =F52*300% -> 40476.63 | I52: =F52*7.5% -> 1011.9157 | K52: =F52*50% -> 6746.105 | L52: =F52*350% -> 47222.735 | M52: =F52*100% -> 13492.21 | O52: =50000 -> 50000 | P52: =F52*10% -> 1349.221 | Q52: 10000 | S52: =SUM(F52:R52) -> 183791.03 | U52: =10000 -> 10000 | V52: 0 | X52: 1484.37 | Y52: =X52+W52+V52+U52+T52 -> 11484.37 | Z52: 172306.66 | AA52: =S52-Y52 -> 172306.66 | AB52: 10 (7) | AC52: =168602+60000 -> 228602 | AD52: =AC52-S52 -> 44810.973 | AE52: =23/31*AD52 -> 33246.851 | AF52: =AE52+AD52 -> 78057.824 | AG52: =3369.51 -> 3369.51 | AH52: =3369.51 -> 3369.51 | AI52: =AH52-AG52 -> 0
A53: 8 | B53: STELLA NGOZI PAUL | D53: CONFIDENTIAL SECRETARY | E53: 8(10) | F53: =13492.21 -> 13492.21 | H53: =F53*300% -> 40476.63 | I53: =F53*7.5% -> 1011.9157 | K53: =F53*50% -> 6746.105 | L53: =F53*350% -> 47222.735 | M53: =F53*100% -> 13492.21 | O53: =50000 -> 50000 | P53: =F53*10% -> 1349.221 | Q53: 10000 | S53: =SUM(F53:R53) -> 183791.03 | U53: =10000+30000 -> 40000 | V53: =7500 -> 7500 | W53: ='[2]Jan 2021'!$H$37 -> 337.30525 | X53: 1484.37 | Y53: =X53+W53+V53+U53+T53 -> 49321.675 | Z53: 134469.35 | AA53: =S53-Y53 -> 134469.35 | AB53: 10 (7) | AC53: =168602+60000 -> 228602 | AD53: =AC53-S53 -> 44810.973 | AE53: =23/31*AD53 -> 33246.851 | AF53: =AE53+AD53 -> 78057.824 | AG53: =3369.51 -> 3369.51 | AH53: =3369.51 -> 3369.51 | AI53: =AH53-AG53 -> 0
A54: 9 | B54: OWOEYE TOSIN KAYODE | D54: CONFIDENTIAL SECRETARY | E54: 8(10) | F54: =13492.21 -> 13492.21 | H54: =F54*300% -> 40476.63 | I54: =F54*7.5% -> 1011.9157 | K54: =F54*50% -> 6746.105 | L54: =F54*350% -> 47222.735 | M54: =F54*100% -> 13492.21 | O54: =50000 -> 50000 | P54: =F54*10% -> 1349.221 | Q54: 10000 | S54: =SUM(F54:R54) -> 183791.03 | X54: 1484.37 | Y54: =X54+W54+V54+U54+T54 -> 1484.37 | Z54: 182306.66 | AA54: =S54-Y54 -> 182306.66 | AB54: 10 (7) | AC54: =168602+60000 -> 228602 | AD54: =AC54-S54 -> 44810.973 | AE54: =23/31*AD54 -> 33246.851 | AF54: =AE54+AD54 -> 78057.824 | AG54: =3369.51 -> 3369.51 | AH54: =3369.51 -> 3369.51 | AI54: =AH54-AG54 -> 0
A55: 10 | B55: IBRAHIM ZAKARI AHMAD | D55: DRIVER | E55: 4(10) | F55: =4836.3 -> 4836.3 | H55: =F55*300% -> 14508.9 | I55: =F55*7.5% -> 362.7225 | K55: =F55*50% -> 2418.15 | L55: =F55*350% -> 16927.05 | M55: =F55*100% -> 4836.3 | O55: =15000 -> 15000 | P55: =F55*10% -> 483.63 | Q55: 5000 | R55: =7000 -> 7000 | S55: =SUM(F55:R55) -> 71373.052 | U55: =5000+3000 -> 8000 | V55: =15000 -> 15000 | X55: 236.04 | Y55: =X55+W55+V55+U55+T55 -> 23236.04 | Z55: 47137.012 | AA55: =S55-Y55 -> 48137.012 | AB55: 5 (7) | AC55: =48538+7000+20000 -> 75538 | AD55: =AC55-S55 -> 4164.9475 | AE55: =23/31*AD55 -> 3090.1223 | AF55: =AE55+AD55 -> 7255.0698 | AG55: 236.04 | AH55: 236.04 | AI55: =AH55-AG55 -> 0
A56: 11 | B56: SHEDRACK NASARA M. | D56: DRIVER | E56: 4(10) | F56: =4836.3 -> 4836.3 | H56: =F56*300% -> 14508.9 | I56: =F56*7.5% -> 362.7225 | K56: =F56*50% -> 2418.15 | L56: =F56*350% -> 16927.05 | M56: =F56*100% -> 4836.3 | O56: =15000 -> 15000 | P56: =F56*10% -> 483.63 | Q56: 5000 | R56: =4000 -> 4000 | S56: =SUM(F56:R56) -> 68373.052 | U56: =10000+3000+5000 -> 18000 | V56: =25555.56 -> 25555.56 | X56: 236.04 | Y56: =X56+W56+V56+U56+T56 -> 43791.6 | Z56: 24581.452 | AA56: =S56-Y56 -> 24581.452 | AB56: 5 (7) | AC56: =48538+4000+20000 -> 72538 | AD56: =AC56-S56 -> 4164.9475 | AE56: =23/31*AD56 -> 3090.1223 | AF56: =AE56+AD56 -> 7255.0698 | AG56: 236.04 | AH56: 236.04 | AI56: =AH56-AG56 -> 0
A57: 12 | B57: IBRAHIM ALIYU | D57: DRIVER | E57: 4(10) | F57: =4836.3 -> 4836.3 | H57: =F57*300% -> 14508.9 | I57: =F57*7.5% -> 362.7225 | K57: =F57*50% -> 2418.15 | L57: =F57*350% -> 16927.05 | M57: =F57*100% -> 4836.3 | O57: =15000 -> 15000 | P57: =F57*10% -> 483.63 | Q57: 5000 | R57: =7000 -> 7000 | S57: =SUM(F57:R57) -> 71373.052 | U57: =5000+3000 -> 8000 | V57: =30087.22 -> 30087.22 | X57: 236.04 | Y57: =X57+W57+V57+U57+T57 -> 38323.26 | Z57: 33049.792 | AA57: =S57-Y57 -> 33049.792 | AB57: 5 (7) | AC57: =48538+7000+20000 -> 75538 | AD57: =AC57-S57 -> 4164.9475 | AE57: =23/31*AD57 -> 3090.1223 | AF57: =AE57+AD57 -> 7255.0698 | AG57: 236.04 | AH57: 236.04 | AI57: =AH57-AG57 -> 0
A58: 13 | B58: ABUBAKAR AMINU DOLE | D58: DRIVER | E58: 4(10) | F58: =4836.3 -> 4836.3 | H58: =F58*300% -> 14508.9 | I58: =F58*7.5% -> 362.7225 | K58: =F58*50% -> 2418.15 | L58: =F58*350% -> 16927.05 | M58: =F58*100% -> 4836.3 | O58: =15000 -> 15000 | P58: =F58*10% -> 483.63 | Q58: 5000 | R58: =4000 -> 4000 | S58: =SUM(F58:R58) -> 68373.052 | U58: =10000+3000 -> 13000 | V58: =8416.67 -> 8416.67 | X58: 236.04 | Y58: =X58+W58+V58+U58+T58 -> 21652.71 | Z58: 46720.342 | AA58: =S58-Y58 -> 46720.342 | AB58: 5 (7) | AC58: =48538+4000+20000 -> 72538 | AD58: =AC58-S58 -> 4164.9475 | AE58: =23/31*AD58 -> 3090.1223 | AF58: =AE58+AD58 -> 7255.0698 | AG58: 236.04 | AH58: 236.04 | AI58: =AH58-AG58 -> 0
A59: 14 | B59: DARAMOLA SANJO SAMSON | D59: DRIVER | E59: 4(10) | F59: =4836.3 -> 4836.3 | H59: =F59*300% -> 14508.9 | I59: =F59*7.5% -> 362.7225 | K59: =F59*50% -> 2418.15 | L59: =F59*350% -> 16927.05 | M59: =F59*100% -> 4836.3 | O59: =15000 -> 15000 | P59: =F59*10% -> 483.63 | Q59: 5000 | R59: =7000 -> 7000 | S59: =SUM(F59:R59) -> 71373.052 | U59: =5000 -> 5000 | V59: =3550.56 -> 3550.56 | X59: 236.04 | Y59: =X59+W59+V59+U59+T59 -> 8786.6 | Z59: 62586.452 | AA59: =S59-Y59 -> 62586.452 | AB59: 5 (7) | AC59: =48538+7000+20000 -> 75538 | AD59: =AC59-S59 -> 4164.9475 | AE59: =23/31*AD59 -> 3090.1223 | AF59: =AE59+AD59 -> 7255.0698 | AG59: 236.04 | AH59: 236.04 | AI59: =AH59-AG59 -> 0
B60: TOTAL | D60: 14 | F60: =SUM(F46:F59) -> 198561.68 | H60: =SUM(H46:H59) -> 595685.04 | I60: =SUM(I46:I59) -> 14892.126 | J60: =SUM(J46:J59) -> 0 | K60: =SUM(K46:K59) -> 99280.84 | L60: =SUM(L46:L59) -> 694965.88 | M60: =SUM(M46:M59) -> 198561.68 | N60: =SUM(N46:N59) -> 0 | O60: =SUM(O46:O59) -> 615000 | ... S60: =SUM(S46:S59) -> 2595803.4 | U60: =SUM(U46:U59) -> 175000 | V60: =SUM(V46:V59) -> 242610.01 | W60: =SUM(W46:W59) -> 2095.4015 | X60: =SUM(X46:X59) -> 38871.12 | Y60: =SUM(Y46:Y59) -> 458576.53 | Z60: 6521425.5 | AA60: =SUM(AA46:AA59) -> 2137226.9 | AC60: =SUM(AC46:AC59) -> 2835245 | AD60: =SUM(AD46:AD59) -> 239441.59 | AE60: =SUM(AE46:AE59) -> 177650.21 | AF60: =SUM(AF46:AF59) -> 417091.79 | AG60: =SUM(AG46:AG59) -> 44526.54 | AH60: =SUM(AH46:AH59) -> 44526.54 | AI60: =SUM(AI46:AI59) -> 0
B61: GRAND TOTAL | D61: =D13+D16+D20+D23+D28+D31+D34+D37+D40+D43+D60 -> 22 | F61: =F13+F16+F20+F23+F28+F31+F34+F37+F40+F43+F60 -> #REF! | G61: =G13+G16+G20+G23+G28+G31+G34+G37+G40+G43+G60 -> #REF! | H61: =H13+H16+H20+H23+H28+H31+H34+H37+H40+H43+H60 -> #REF! | I61: =I13+I16+I20+I23+I28+I31+I34+I37+I40+I43+I60 -> #REF! | J61: =J13+J16+J20+J23+J28+J31+J34+J37+J40+J43+J60 -> #REF! | K61: =K13+K16+K20+K23+K28+K31+K34+K37+K40+K43+K60 -> #REF! | L61: =L13+L16+L20+L23+L28+L31+L34+L37+L40+L43+L60 -> #REF! | M61: =M13+M16+M20+M23+M28+M31+M34+M37+M40+M43+M60 -> #REF! | ... AA61: =AA13+AA16+AA20+AA23+AA28+AA31+AA34+AA37+AA40+AA43+AA60 -> #REF! | AC61: =AC13+AC20+AC28+AC60 -> 5966764 | AD61: =AD13+AD20+AD28+AD60 -> 447490.01 | AE61: =AE13+AE20+AE28+AE60 -> 332008.71 | AF61: =AD61+AE61 -> 779498.72 | AG61: =AG13+AG20+AG28+AG60 -> 97524.12 | AH61: =AH13+AH20+AH28+AH60 -> 105362.69 | AI61: =AI13+AI20+AI28+AI60 -> 7838.57
B63: Net effect of staff promotiton | K63: SIGNATURE | P63: DATE | AI63: =-AF61+AI61 -> -771660.15
AE65: ='December, 2021'!F188-Promotion!AE61 -> -332008.71

Sheet Library
D2: DESIGNATION | E2: GRADE LEVEL | F2: SALARY | G2: SALARY/ALLOWCE AREARS | H2: RENT | I2: UTILITY | J2: DOMESTIC | K2: ENTERT. | L2: FURNIT. | M2: FUEL | N2: ALLOWANCE | O2: ALLOWANCE | P2: ALLCE | Q2: ALLCE | R2: DUTY ALLCE | S2: GROSS SALARY | T2: AUCTION | U2: COOP SOCIETY | V2: COOP. LOAN RECOVERY | W2: NHF DEDUCTION | X2: PAYE | Y2: TOTAL | AB2: SHIFT DUTY ALLOWANCES (11% of GROSS)
B3: LIBRARY AND DOCUMENTATION
A4: 1 | B4: ALIYU SANNI ABUBAKAR | D4: RESEARCH FELLOW 11 DATA & DOCU | E4: 13(11) | F4: =26339.3 -> 26339.3 | H4: =F4*300% -> 79017.9 | I4: =F4*7.5% -> 1975.4475 | J4: 0 | K4: =F4*50% -> 13169.65 | L4: =F4*350% -> 92187.55 | M4: =F4*100% -> 26339.3 | N4: =120000 -> 120000 | P4: =F4*10% -> 2633.93 | Q4: 15000 | R4: 0 | S4: =SUM(F4:R4) -> 376663.08 | U4: 30000 | V4: =43750 -> 43750 | W4: ='[2]Jan 2021'!$H$36 -> 658.4825 | X4: =7709.76 -> 7709.76 | Y4: =X4+W4+V4+U4+T4 -> 82118.242 | Z4: 294544.83 | AA4: =S4-Y4 -> 294544.83 | AB4: =S4*0.11 -> 41432.939
A5: 2 | B5: CHINAKO N. ASOGWA | D5: RESEARCH FELLOW 11 DATA & DOCU | E5: 13(9) | F5: =24741.26 -> 24741.26 | H5: =F5*300% -> 74223.78 | I5: =F5*7.5% -> 1855.5945 | J5: 0 | K5: =F5*50% -> 12370.63 | L5: =F5*350% -> 86594.41 | M5: =F5*100% -> 24741.26 | N5: =120000 -> 120000 | P5: =F5*10% -> 2474.126 | Q5: 15000 | S5: =SUM(F5:R5) -> 362001.06 | U5: =50000 -> 50000 | V5: =68750+45833.33 -> 114583.33 | X5: =7709.76 -> 7709.76 | Y5: =X5+W5+V5+U5+T5 -> 172293.09 | Z5: 235541.3 | AA5: =S5-Y5 -> 189707.97 | AB5: =S5*0.11 -> 39820.117
A6: 3 | B6: AMOS ABA | D6: LIBRARY ASSISTANT | E6: 8(9) | F6: =13112.16 -> 13112.16 | H6: =F6*300% -> 39336.48 | I6: =F6*7.5% -> 983.412 | K6: =F6*50% -> 6556.08 | L6: =F6*350% -> 45892.56 | M6: =F6*100% -> 13112.16 | N6: =100000 -> 100000 | P6: =F6*10% -> 1311.216 | Q6: 10000 | S6: =SUM(F6:R6) -> 230304.07 | U6: 20000 | V6: =50000 -> 50000 | X6: 1484.37 | Y6: =X6+W6+V6+U6+T6 -> 71484.37 | Z6: 158819.7 | AA6: =S6-Y6 -> 158819.7 | AB6: =S6*0.11 -> 25333.447
A7: 4 | B7: TITILAYO DANIEL MARVELLOUS | D7: LIBRARY ASSISTANT | E7: 8(8) | F7: =12732 -> 12732 | H7: =F7*300% -> 38196 | I7: =F7*7.5% -> 954.9 | K7: =F7*50% -> 6366 | L7: =F7*350% -> 44562 | M7: =F7*100% -> 12732 | N7: =100000 -> 100000 | P7: =F7*10% -> 1273.2 | Q7: 10000 | S7: =SUM(F7:R7) -> 226816.1 | U7: =25000 -> 25000 | V7: 0 | X7: 1484.37 | Y7: =X7+W7+V7+U7+T7 -> 26484.37 | Z7: 200580.91 | AA7: =S7-Y7 -> 200331.73 | AB7: =S7*0.11 -> 24949.771
A8: 5 | B8: ENENCHE JEREMIAH AGADA | D8: LIBRARY ASSISTANT | E8: 8(7) | F8: =12351.94 -> 12351.94 | H8: =F8*300% -> 37055.82 | I8: =F8*7.5% -> 926.3955 | K8: =F8*50% -> 6175.97 | L8: =F8*350% -> 43231.79 | M8: =F8*100% -> 12351.94 | N8: =100000 -> 100000 | P8: =F8*10% -> 1235.194 | Q8: 10000 | S8: =SUM(F8:R8) -> 223329.05 | X8: 1484.37 | Y8: =X8+W8+V8+U8+T8 -> 1484.37 | AA8: =S8-Y8 -> 221844.68 | AB8: =S8*0.11 -> 24566.195
A9: 6 | B9: ABBAS ZAINAB | D9: LIBRARY ASSISTANT | E9: 8(7) | F9: =12351.94 -> 12351.94 | H9: =F9*300% -> 37055.82 | I9: =F9*7.5% -> 926.3955 | K9: =F9*50% -> 6175.97 | L9: =F9*350% -> 43231.79 | M9: =F9*100% -> 12351.94 | N9: =100000 -> 100000 | P9: =F9*10% -> 1235.194 | Q9: 10000 | S9: =SUM(F9:R9) -> 223329.05 | X9: 1484.37 | Y9: =X9+W9+V9+U9+T9 -> 1484.37 | AA9: =S9-Y9 -> 221844.68 | AB9: =S9*0.11 -> 24566.195
B10: TOTAL | D10: 6 | F10: =SUM(F4:F9) -> 101628.6 | H10: =SUM(H4:H9) -> 304885.8 | I10: =SUM(I4:I9) -> 7622.145 | J10: =SUM(J4:J9) -> 0 | K10: =SUM(K4:K9) -> 50814.3 | L10: =SUM(L4:L9) -> 355700.1 | M10: =SUM(M4:M9) -> 101628.6 | N10: =SUM(N4:N9) -> 640000 | P10: =SUM(P4:P9) -> 10162.86 | Q10: =SUM(Q4:Q9) -> 70000 | R10: =SUM(R4:R9) -> 0 | S10: =SUM(S4:S9) -> 1642442.4 | U10: =SUM(U4:U9) -> 125000 | V10: =SUM(V4:V9) -> 208333.33 | W10: =SUM(W4:W9) -> 658.4825 | X10: =SUM(X4:X9) -> 21357 | Y10: =SUM(Y4:Y9) -> 355348.81 | Z10: =SUM(Z4:Z9) -> 889486.74 | AA10: =SUM(AA4:AA9) -> 1287093.6 | AB10: =SUM(AB4:AB9) -> 180668.66

Sheet New staff
B3: STAFF PAYROLL FOR THE MONTH OF SEPTEMBER, 2021
F4: ='[1]FEB 08'!E8/'[1]FEB 08'!M8 -> 0.22 | I4: ='[1]FEB 08'!F8/'[1]FEB 08'!Q8 -> 0.3
B5: EFFECT OF ADDITION OF NEW STAFF | S5: DEDUCTIONS | Y5: NET SALARY
D6: DESIGNATION | E6: SALARY | F6: BASIC | M6: MOTOR/ | N6: OLD | O6: LEAVE | P6: OUT FIT | Q6: LEGISLATIVE | R6: GROSS | X6: JUNE,2021 | Y6: JULY,2021 | Z6: NEW
E7: LEVEL | F7: SALARY | G7: SALARY/ALLOWCE AREARS | H7: RENT | I7: UTILITY | J7: DOMESTIC | K7: ENTERT. | L7: FURNIT. | M7: FUEL | N7: SALARY | O7: ALLCE | P7: ALLCE | Q7: DUTY ALLCE | R7: SALARY | S7: COOP SOCIETY | T7: COOP. LOAN RECOVERY | U7: NHF DEDUCTION | V7: PAYE | W7: TOTAL | Z7: SALARY | AA7: DIFFERENCE | AB7: OLD TAX | AC7: NEW TAX | AD7: DIFFERENCE
A8: S/N | B8: DG OFFICE | F8: N | I8: N | R8: N | V8: N
A9: 1 | B9: JIMOH ADEBAYO ZAKA | D9: ASST. OFFICER INF/COMM | E9: 8(7) | Z9: =123329+50000 -> 173329 | AA9: =Z9-N9 -> 173329 | AC9: =1484.37 -> 1484.37 | AD9: =AC9-AB9 -> 1484.37
B10: TOTAL | D10: 1 | F10: =SUM(F9:F9) -> 0 | H10: =SUM(H9:H9) -> 0 | I10: =SUM(I9:I9) -> 0 | J10: =SUM(J9:J9) -> 0 | K10: =SUM(K9:K9) -> 0 | L10: =SUM(L9:L9) -> 0 | M10: =SUM(M9:M9) -> 0 | N10: =SUM(N9:N9) -> 0 | O10: =SUM(O9:O9) -> 0 | ... W10: =SUM(W9:W9) -> 0 | X10: 7468053.9 | Y10: =SUM(Y9:Y9) -> 0 | Z10: =SUM(Z9) -> 173329 | AA10: =SUM(AA9) -> 173329 | AC10: =SUM(AC9) -> 1484.37 | AD10: =SUM(AD9) -> 1484.37
B12: INTERNAL AUDIT
A13: 1 | B13: OSANAIYE DAVID AKINYEMI | D13: DIRECTOR INTERNAL AUDIT | E13: 17 (7) | Z13: =(800657+100000)*18/30 -> 540394.2 | AA13: =Z13-N13 -> 540394.2 | AC13: =('December, 2021'!W46)*18/30 -> 31665.978 | AD13: =AC13-AB13 -> 31665.978
B14: NWOSU EZE MATTHEW | D14: DEPUTY DIRECTOR IA | E14: 16 (9) | AB14: 52776.63 | AC14: 21618.09 | AD14: =AC14-AB14 -> -31158.54
C15: TOTAL | D15: 1 | F15: =SUM(F13:F13) -> 0 | H15: =SUM(H13:H13) -> 0 | I15: =SUM(I13:I13) -> 0 | J15: =SUM(J13:J13) -> 0 | K15: =SUM(K13:K13) -> 0 | L15: =SUM(L13:L13) -> 0 | M15: =SUM(M13:M13) -> 0 | N15: =SUM(N13:N13) -> 0 | O15: =SUM(O13:O13) -> 0 | ... W15: =SUM(W13:W13) -> 0 | X15: 383180.46 | Y15: =SUM(Y13:Y13) -> 0 | Z15: =SUM(Z13:Z14) -> 540394.2 | AA15: =SUM(AA13:AA14) -> 540394.2 | AB15: =SUM(AB13:AB14) -> 52776.63 | AC15: =SUM(AC13:AC14) -> 53284.068 | AD15: =SUM(AD13:AD14) -> 507.438
B17: LEG. SUPPORT SEVICES
B18: TOTAL | D18: 0 | F18: =SUM(#REF!) -> #REF! | H18: =SUM(#REF!) -> #REF! | I18: =SUM(#REF!) -> #REF! | J18: =SUM(#REF!) -> #REF! | K18: =SUM(#REF!) -> #REF! | L18: =SUM(#REF!) -> #REF! | M18: =SUM(#REF!) -> #REF!
B20: LEGAL SERVICES
A21: 1 | B21: ENECHE JERIMIAH AGADA | D21: LIBRARY ASSISTANT | E21: 8 (7) | N21: =0 -> 0 | Z21: =123329+100000 -> 223329 | AA21: =Z21-N21 -> 223329 | AC21: =1484.37 -> 1484.37 | AD21: =AC21-AB21 -> 1484.37
A22: 2 | B22: ABBAS ZAINAB | D22: LIBRARY ASSISTANT | E22: 8 (7) | N22: =0 -> 0 | Z22: =123329+100000 -> 223329 | AA22: =Z22-N22 -> 223329 | AC22: =1484.37 -> 1484.37 | AD22: =AC22-AB22 -> 1484.37
B23: TOTAL | D23: 2 | F23: =SUM(F21:F22) -> 0 | H23: =SUM(H21:H22) -> 0 | I23: =SUM(I21:I22) -> 0 | J23: =SUM(J21:J22) -> 0 | K23: =SUM(K21:K22) -> 0 | L23: =SUM(L21:L22) -> 0 | M23: =SUM(M21:M22) -> 0 | N23: =SUM(N21:N22) -> 0 | O23: =SUM(O21:O22) -> 0 | ... S23: =SUM(S21:S22) -> 0 | U23: =SUM(U21:U22) -> 0 | V23: =SUM(V21:V22) -> 0 | W23: =SUM(W21:W22) -> 0 | X23: 1126604.2 | Y23: =SUM(Y21:Y22) -> 0 | Z23: =SUM(Z21:Z22) -> 446658 | AA23: =SUM(AA21:AA22) -> 446658 | AC23: =SUM(AC21:AC22) -> 2968.74 | AD23: =SUM(AD21:AD22) -> 2968.74
B25: DEMOCRATIC STUDIES
B26: TOTAL | F26: =SUM(#REF!) -> #REF! | H26: =SUM(#REF!) -> #REF! | I26: =SUM(#REF!) -> #REF! | J26: =SUM(#REF!) -> #REF! | K26: =SUM(#REF!) -> #REF! | L26: =SUM(#REF!) -> #REF! | M26: =SUM(#REF!) -> #REF!
B28: STUDIES
B29: TOTAL | F29: =SUM(#REF!) -> #REF! | H29: =SUM(#REF!) -> #REF! | I29: =SUM(#REF!) -> #REF! | J29: =SUM(#REF!) -> #REF! | K29: =SUM(#REF!) -> #REF! | L29: =SUM(#REF!) -> #REF! | M29: =SUM(#REF!) -> #REF!
B31: ECONOMIC AND SOCIAL DEV.
B32: TOTAL | D32: 0 | F32: =SUM(#REF!) -> #REF! | H32: =SUM(#REF!) -> #REF! | I32: =SUM(#REF!) -> #REF! | J32: =SUM(#REF!) -> #REF! | K32: =SUM(#REF!) -> #REF! | L32: =SUM(#REF!) -> #REF! | M32: =SUM(#REF!) -> #REF!
B34: TRAINING AND INTERNATIONAL COOP
A35: 1 | B35: REKIYA IBRAHIM ATTAH | D35: DEPUTY DIRECTOR TRAINING | E35: 16 (7) | N35: =0 -> 0 | Z35: =(424023+90000)*21/30 -> 359816.1 | AA35: =Z35-N35 -> 359816.1 | AC35: =21618.09 -> 21618.09 | AD35: =AC35-AB35 -> 21618.09
A36: 2 | B36: ABUBAKAR MOHAMMED BASHIR | D36: ASST. CHIEF TRAINING OFFICER | E36: 13 (7) | Z36: =226713+70000 -> 296713 | AA36: =Z36-N36 -> 296713 | AC36: ='December, 2021'!W92 -> 7709.76 | AD36: =AC36-AB36 -> 7709.76
B37: TOTAL | D37: 2 | F37: =SUM(F35:F36) -> 0 | H37: =SUM(H35:H36) -> 0 | I37: =SUM(I35:I36) -> 0 | J37: =SUM(J35:J36) -> 0 | K37: =SUM(K35:K36) -> 0 | L37: =SUM(L35:L36) -> 0 | M37: =SUM(M35:M36) -> 0 | N37: =SUM(N35:N36) -> 0 | O37: =SUM(O35:O36) -> 0 | ... W37: =SUM(W35:W36) -> 0 | X37: 1259979.1 | Y37: =SUM(Y35:Y36) -> 0 | Z37: =SUM(Z35:Z36) -> 656529.1 | AA37: =SUM(AA35:AA36) -> 656529.1 | AC37: =SUM(AC35:AC36) -> 29327.85 | AD37: =SUM(AD35:AD36) -> 29327.85
B39: LIBRARY AND DOCUMENTATION
B40: TOTAL | F40: =SUM(#REF!) -> #REF! | H40: =SUM(#REF!) -> #REF! | I40: =SUM(#REF!) -> #REF! | J40: =SUM(#REF!) -> #REF! | K40: =SUM(#REF!) -> #REF! | L40: =SUM(#REF!) -> #REF! | M40: =SUM(#REF!) -> #REF!
B42: FINANCE & ACCOUNT
A43: 1 | B43: ARAOYE GANIYAT TITILOLA | D43: ASST. DIRECTOR Accounts | E43: 15 (7) | N43: =0 -> 0 | Z43: =(344720+80000)*18/30 -> 254832 | AA43: =Z43-N43 -> 254832 | AC43: =('December, 2021'!W90)*18/30 -> 9328.998 | AD43: =AC43-AB43 -> 9328.998
A44: 2 | B44: SALMAN RABBIAT BOLATITO | D44: ASST. CHIEF | E44: 13 (7) | Z44: =226713+70000 -> 296713 | AA44: =Z44-N44 -> 296713 | AC44: =AC36 -> 7709.76 | AD44: =AC44-AB44 -> 7709.76
B45: TOTAL | D45: 2 | F45: =SUM(F43:F44) -> 0 | H45: =SUM(H43:H44) -> 0 | I45: =SUM(I43:I44) -> 0 | J45: =SUM(J43:J44) -> 0 | K45: =SUM(K43:K44) -> 0 | L45: =SUM(L43:L44) -> 0 | M45: =SUM(M43:M44) -> 0 | N45: =SUM(N43:N44) -> 0 | O45: =SUM(O43:O44) -> 0 | ... W45: =SUM(W43:W44) -> 0 | X45: 2217865 | Y45: =SUM(Y43:Y44) -> 0 | Z45: =SUM(Z43:Z44) -> 551545 | AA45: =SUM(AA43:AA44) -> 551545 | AC45: =SUM(AC43:AC44) -> 17038.758 | AD45: =SUM(AD43:AD44) -> 17038.758
B47: ADMINISTRATION & HUMAN RESOURCE
A48: 1 | B48: PRISCILLA NKECHI CHUKWU | D48: ASST. DIRECTOR HR | E48: 15 (9) | N48: =0 -> 0 | Z48: =367553+80000 -> 447553 | AA48: =Z48-N48 -> 447553 | AC48: ='December, 2021'!W135 -> 15548.33 | AD48: =AC48-AB48 -> 15548.33
A49: 2 | B49: OLOLADE ABRU IDOWU | D49: CONFIDENTIAL SECRETARY | E49: 8(7) | Z49: =123329+50000 -> 173329 | AA49: =Z49-N49 -> 173329 | AC49: =1484.37 -> 1484.37 | AD49: =AC49-AB49 -> 1484.37
B50: TOTAL | D50: 2 | F50: =SUM(#REF!) -> #REF! | H50: =SUM(#REF!) -> #REF! | I50: =SUM(#REF!) -> #REF! | J50: =SUM(#REF!) -> #REF! | K50: =SUM(#REF!) -> #REF! | L50: =SUM(#REF!) -> #REF! | M50: =SUM(#REF!) -> #REF! | Z50: =SUM(Z48:Z49) -> 620882 | AA50: =SUM(AA48:AA49) -> 620882 | AC50: =SUM(AC48:AC49) -> 17032.7 | AD50: =SUM(AD48:AD49) -> 17032.7
B51: GRAND TOTAL | D51: =D10+D15+D18+D23+D26+D29+D32+D37+D40+D45+D50 -> 10 | F51: =F10+F15+F18+F23+F26+F29+F32+F37+F40+F45+F50 -> #REF! | G51: =G10+G15+G18+G23+G26+G29+G32+G37+G40+G45+G50 -> 0 | H51: =H10+H15+H18+H23+H26+H29+H32+H37+H40+H45+H50 -> #REF! | I51: =I10+I15+I18+I23+I26+I29+I32+I37+I40+I45+I50 -> #REF! | J51: =J10+J15+J18+J23+J26+J29+J32+J37+J40+J45+J50 -> #REF! | K51: =K10+K15+K18+K23+K26+K29+K32+K37+K40+K45+K50 -> #REF! | L51: =L10+L15+L18+L23+L26+L29+L32+L37+L40+L45+L50 -> #REF! | M51: =M10+M15+M18+M23+M26+M29+M32+M37+M40+M45+M50 -> #REF! | ... AA51: =AA10+AA15+AA18+AA23+AA26+AA29+AA32+AA37+AA40+AA45+AA50 -> 2989337.3 | AC51: =AC50+AC45+AC37+AC23+AC15+AC10 -> 121136.49 | AD51: =AD50+AD45+AD37+AD23+AD15+AD10 -> 68359.856
C53: SULEIMAN ABUBAKAR SODEEQ | AB53: =1235.19 -> 1235.19 | AC53: =1484.37 -> 1484.37 | AD53: =AC53-AB53 -> 249.18
C54: YAKUB OLUWATOYIN USMAN | AB54: =1235.19 -> 1235.19 | AC54: =1484.37 -> 1484.37 | AD54: =AC54-AB54 -> 249.18
C55: TASSNEEM IBRAHIM | AB55: =1235.19 -> 1235.19 | AC55: =1484.37 -> 1484.37 | AD55: =AC55-AB55 -> 249.18
C56: TITILAYO DANIEL MARVELLOUS | AB56: =1235.19 -> 1235.19 | AC56: =1484.37 -> 1484.37 | AD56: =AC56-AB56 -> 249.18
C57: DARE SHEU MAGBON | AB57: =1235.19 -> 1235.19 | AC57: =1484.37 -> 1484.37 | AD57: =AC57-AB57 -> 249.18
C58: MOHAMMED BELLO | AB58: =1235.19 -> 1235.19 | AC58: =1484.37 -> 1484.37 | AD58: =AC58-AB58 -> 249.18
C59: NNANDI LIVINUS ATURE | AB59: =1235.19 -> 1235.19 | AC59: =1484.37 -> 1484.37 | AD59: =AC59-AB59 -> 249.18
C60: LUCKY AGWOM | AB60: =1235.19 -> 1235.19 | AC60: =1484.37 -> 1484.37 | AD60: =AC60-AB60 -> 249.18
C61: JONATHAN GABRIEL | AC61: 236.04 | AD61: =AC61-AB61 -> 236.04
AD62: =SUM(AD53:AD61) -> 2229.48
D63: GRAND TOTAL | AD63: =AD51+AD62 -> 70589.336
C64: Net Effect of enrollment of new staff and tax adjustment | AD64: =-AA51+AD63 -> -2918748

Sheet New staff (2)
B3: STAFF PAYROLL FOR THE MONTH OF SEPTEMBER, 2021
F4: ='[1]FEB 08'!E8/'[1]FEB 08'!M8 -> 0.22 | I4: ='[1]FEB 08'!F8/'[1]FEB 08'!Q8 -> 0.3
B5: EFFECT OF ADDITION OF NEW STAFF | S5: DEDUCTIONS | Y5: NET SALARY
D6: DESIGNATION | E6: SALARY | F6: BASIC | M6: MOTOR/ | N6: OLD | O6: LEAVE | P6: OUT FIT | Q6: LEGISLATIVE | R6: GROSS | X6: JUNE,2021 | Y6: JULY,2021 | Z6: NEW
E7: LEVEL | F7: SALARY | G7: SALARY/ALLOWCE AREARS | H7: RENT | I7: UTILITY | J7: DOMESTIC | K7: ENTERT. | L7: FURNIT. | M7: FUEL | N7: SALARY | O7: ALLCE | P7: ALLCE | Q7: DUTY ALLCE | R7: SALARY | S7: COOP SOCIETY | T7: COOP. LOAN RECOVERY | U7: NHF DEDUCTION | V7: PAYE | W7: TOTAL | Z7: SALARY | AA7: DIFFERENCE | AB7: OLD TAX | AC7: NEW TAX | AD7: DIFFERENCE
B8: INTERNAL AUDIT
A9: 1 | B9: OSANAIYE DAVID AKINYEMI | D9: DIRECTOR INTERNAL AUDIT | E9: 17 (7) | N9: 540394.2 | Z9: =(800657+100000) -> 900657 | AA9: =Z9-N9 -> 360262.8 | AB9: 31665.978 | AC9: =('December, 2021'!W46) -> 52776.63 | AD9: =AC9-AB9 -> 21110.652
C10: TOTAL | D10: 1 | F10: =SUM(F9:F9) -> 0 | H10: =SUM(H9:H9) -> 0 | I10: =SUM(I9:I9) -> 0 | J10: =SUM(J9:J9) -> 0 | K10: =SUM(K9:K9) -> 0 | L10: =SUM(L9:L9) -> 0 | M10: =SUM(M9:M9) -> 0 | N10: 540394.2 | O10: =SUM(O9:O9) -> 0 | P10: =SUM(P9:P9) -> 0 | Q10: =SUM(Q9:Q9) -> 0 | R10: =SUM(R9:R9) -> 0 | S10: =SUM(S9:S9) -> 0 | T10: =SUM(T9:T9) -> 0 | U10: =SUM(U9:U9) -> 0 | V10: =SUM(V9:V9) -> 0 | W10: =SUM(W9:W9) -> 0 | X10: 383180.46 | Y10: =SUM(Y9:Y9) -> 0 | Z10: =SUM(Z9:Z9) -> 900657 | AA10: =SUM(AA9:AA9) -> 360262.8 | AB10: 53284.068 | AC10: =SUM(AC9:AC9) -> 52776.63 | AD10: =SUM(AD9:AD9) -> 21110.652
B12: TRAINING AND INTERNATIONAL COOP
A13: 1 | B13: REKIYA IBRAHIM ATTAH | D13: DEPUTY DIRECTOR TRAINING | E13: 16 (7) | N13: 359816.1 | Z13: =(424023+90000) -> 514023 | AA13: =Z13-N13 -> 154206.9 | AB13: 21618.09 | AC13: =21618.09 -> 21618.09 | AD13: =AC13-AB13 -> 0
B14: TOTAL | D14: 2 | F14: =SUM(F13:F13) -> 0 | H14: =SUM(H13:H13) -> 0 | I14: =SUM(I13:I13) -> 0 | J14: =SUM(J13:J13) -> 0 | K14: =SUM(K13:K13) -> 0 | L14: =SUM(L13:L13) -> 0 | M14: =SUM(M13:M13) -> 0 | N14: 359816.1 | O14: =SUM(O13:O13) -> 0 | P14: =SUM(P13:P13) -> 0 | Q14: =SUM(Q13:Q13) -> 0 | R14: =SUM(R13:R13) -> 0 | S14: =SUM(S13:S13) -> 0 | T14: =SUM(T13:T13) -> 0 | U14: =SUM(U13:U13) -> 0 | V14: =SUM(V13:V13) -> 0 | W14: =SUM(W13:W13) -> 0 | X14: 1259979.1 | Y14: =SUM(Y13:Y13) -> 0 | Z14: =SUM(Z13:Z13) -> 514023 | AA14: =SUM(AA13:AA13) -> 154206.9 | AB14: 21618.09 | AC14: =SUM(AC13:AC13) -> 21618.09 | AD14: =SUM(AD13:AD13) -> 0
B15: FINANCE & ACCOUNT
A16: 1 | B16: ARAOYE GANIYAT TITILOLA | D16: ASST. DIRECTOR Accounts | E16: 15 (7) | N16: 254832 | Z16: =(344720+80000) -> 424720 | AA16: =Z16-N16 -> 169888 | AB16: 9328.998 | AC16: =('December, 2021'!W90) -> 15548.33 | AD16: =AC16-AB16 -> 6219.332
B17: TOTAL | D17: 2 | F17: =SUM(F16:F16) -> 0 | H17: =SUM(H16:H16) -> 0 | I17: =SUM(I16:I16) -> 0 | J17: =SUM(J16:J16) -> 0 | K17: =SUM(K16:K16) -> 0 | L17: =SUM(L16:L16) -> 0 | M17: =SUM(M16:M16) -> 0 | N17: 254832 | O17: =SUM(O16:O16) -> 0 | P17: =SUM(P16:P16) -> 0 | Q17: =SUM(Q16:Q16) -> 0 | R17: =SUM(R16:R16) -> 0 | S17: =SUM(S16:S16) -> 0 | T17: =SUM(T16:T16) -> 0 | U17: =SUM(U16:U16) -> 0 | V17: =SUM(V16:V16) -> 0 | W17: =SUM(W16:W16) -> 0 | X17: 2217865 | Y17: =SUM(Y16:Y16) -> 0 | Z17: =SUM(Z16:Z16) -> 424720 | AA17: =SUM(AA16:AA16) -> 169888 | AB17: 9328.998 | AC17: =SUM(AC16:AC16) -> 15548.33 | AD17: =SUM(AD16:AD16) -> 6219.332
B18: GRAND TOTAL | N18: =N10+N14+N17 -> 1155042.3 | O18: =O10+O14+O17 -> 0 | P18: =P10+P14+P17 -> 0 | Q18: =Q10+Q14+Q17 -> 0 | R18: =R10+R14+R17 -> 0 | S18: =S10+S14+S17 -> 0 | T18: =T10+T14+T17 -> 0 | U18: =U10+U14+U17 -> 0 | ... AD18: =AD10+AD14+AD17 -> 27329.984
B19: NET DIFFERENCE | AD19: =-AA18+AD18 -> -657027.72

Sheet Adj Hardship
B3: STAFF PAYROLL FOR THE MONTH OF JULY, 2021
F4: ='[1]FEB 08'!E8/'[1]FEB 08'!M8 -> 0.22 | I4: ='[1]FEB 08'!F8/'[1]FEB 08'!Q8 -> 0.3
B5: STAFF NAME | S5: DEDUCTIONS | Y5: NET SALARY
D6: DESIGNATION | E6: SALARY | F6: BASIC | M6: MOTOR/ | N6: RESEARCH | O6: LEAVE | P6: OUT FIT | Q6: LEGISLATIVE | R6: GROSS | X6: JUNE,2021 | Y6: JULY,2021 | Z6: NEW RESEARCH/
E7: LEVEL | F7: SALARY | G7: SALARY/ALLOWCE AREARS | H7: RENT | I7: UTILITY | J7: DOMESTIC | K7: ENTERT. | L7: FURNIT. | M7: FUEL | N7: ALLOWANCE | O7: ALLCE | P7: ALLCE | Q7: DUTY ALLCE | R7: SALARY | S7: COOP SOCIETY | T7: COOP. LOAN RECOVERY | U7: NHF DEDUCTION | V7: PAYE | W7: TOTAL | Z7: HARDSHIP ALLOWANCE | AA7: DIFFERENCE
A8: S/N | B8: DG OFFICE | F8: N | I8: N | R8: N | V8: N
A9: 1 | B9: PROF. ABUBAKAR O. SULAIMAN | D9: DIRECTOR GENERAL | E9: CONSOL | F9: 160488.75 | H9: 320977.5 | I9: 48146.63 | J9: 120366.57 | K9: 72219.94 | L9: 0 | M9: 120366.57 | N9: =100000 -> 100000 | O9: 16048.88 | P9: 25000 | Q9: 25235 | R9: =SUM(F9:Q9) -> 1008849.8 | V9: 113176.97 | W9: =S9+T9+U9+V9 -> 113176.97 | X9: 895672.87 | Y9: =R9-W9 -> 895672.87 | Z9: =250000 -> 250000 | AA9: =Z9-N9 -> 150000
A10: 2 | B10: DR ADEYEMI AKEEB FAJINGBESI | D10: DIR. SPECIAL DUTIES, DG OFFICE | E10: 17(9) | F10: 81740.02 | H10: =F10*300% -> 245220.06 | I10: =F10*7.5% -> 6130.5015 | J10: 80244.38 | K10: =F10*50% -> 40870.01 | L10: =F10*350% -> 286090.07 | M10: =F10*100% -> 81740.02 | N10: =100000 -> 100000 | O10: =F10*10% -> 8174.002 | P10: 20000 | Q10: 0 | R10: =SUM(F10:Q10) -> 950209.06 | S10: 200000 | T10: =59722.22 -> 59722.22 | U10: ='[2]Jan 2021'!$H$35 -> 2043.5005 | V10: 52776.63 | W10: =SUM(S10:V10) -> 314542.35 | X10: 635666.71 | Y10: =R10-W10 -> 635666.71 | Z10: =100000 -> 100000 | AA10: =Z10-N10 -> 0
A11: 3 | B11: SARAFADEEN ALABELEWE | D11: SA ADMINISTRATION | E11: 16(9) | F11: =42653.17 -> 42653.17 | H11: =F11*300% -> 127959.51 | I11: =F11*7.5% -> 3198.9877 | J11: 40122.19 | K11: =F11*50% -> 21326.585 | L11: =F11*350% -> 149286.1 | M11: =F11*100% -> 42653.17 | O11: =F11*10% -> 4265.317 | P11: 20000 | R11: =SUM(F11:Q11) -> 451465.02 | S11: =100000 -> 100000 | T11: =137500 -> 137500 | V11: 21618.09 | W11: =S11+T11+U11+V11 -> 259118.09 | X11: 192346.93 | Y11: =R11-W11 -> 192346.93 | Z11: =90000 -> 90000 | AA11: =Z11-N11 -> 90000
A12: 4 | B12: DR JAKE DABANG DAN AZUMI | D12: DEPUTY DIRECTOR TRAINING | E12: 16(7) | F12: =39662.25 -> 39662.25 | H12: =F12*300% -> 118986.75 | I12: =F12*7.5% -> 2974.6687 | J12: 40122.19 | K12: =F12*50% -> 19831.125 | L12: =F12*350% -> 138817.88 | M12: =F12*100% -> 39662.25 | N12: =100000 -> 100000 | O12: =F12*10% -> 3966.225 | P12: 20000 | Q12: 150000 | R12: =SUM(F12:Q12) -> 674023.33 | U12: ='[2]Jan 2021'!$H$27 -> 991.55625 | V12: =21618.09 -> 21618.09 | W12: =SUM(S12:V12) -> 22609.646 | X12: 651413.69 | Y12: =R12-W12 -> 651413.69 | Z12: =180000 -> 180000 | AA12: =Z12-N12 -> 80000
A13: 5 | B13: DR ABDULSALAM NASIRU NAEEM | D13: SA ACADEMICS | E13: 16(7) | F13: =39662.25 -> 39662.25 | H13: =F13*300% -> 118986.75 | I13: =F13*7.5% -> 2974.6687 | J13: 40122.19 | K13: =F13*50% -> 19831.125 | L13: =F13*350% -> 138817.88 | M13: =F13*100% -> 39662.25 | N13: =100000 -> 100000 | O13: =F13*10% -> 3966.225 | P13: 20000 | Q13: =100000 -> 100000 | R13: =SUM(F13:Q13) -> 624023.33 | V13: =21618.09 -> 21618.09 | W13: =S13+T13+U13+V13 -> 21618.09 | X13: 602405.24 | Y13: =R13-W13 -> 602405.24 | Z13: =180000 -> 180000 | AA13: =Z13-N13 -> 80000
A14: 6 | B14: RAHEEM USMAN AYIGORO | D14: SA-INFRASTRUCTURE | E14: 16 (7) | F14: =39662.25 -> 39662.25 | H14: =F14*300% -> 118986.75 | I14: =F14*7.5% -> 2974.6687 | J14: 40122.19 | K14: =F14*50% -> 19831.125 | L14: =F14*350% -> 138817.88 | M14: =F14*100% -> 39662.25 | O14: =F14*10% -> 3966.225 | P14: 20000 | Q14: 0 | R14: =SUM(F14:Q14) -> 424023.33 | V14: =21618.09 -> 21618.09 | W14: =S14+T14+U14+V14 -> 21618.09 | X14: 402405.24 | Y14: =R14-W14 -> 402405.24 | Z14: =90000 -> 90000 | AA14: =Z14-N14 -> 90000
A15: 7 | B15: AKINSANMI ADEJOKE OLUKEMI | D15: HEAD INFORMATION/PROTOCOL | E15: 15(9) | F15: 33507.5 | H15: =F15*300% -> 100522.5 | I15: =F15*7.5% -> 2513.0625 | J15: 40122.19 | K15: =F15*50% -> 16753.75 | L15: =F15*350% -> 117276.25 | M15: =F15*100% -> 33507.5 | O15: =F15*10% -> 3350.75 | P15: 20000 | Q15: =100000 -> 100000 | R15: =SUM(F15:Q15) -> 467553.5 | S15: =0 -> 0 | T15: 0 | U15: =837.69 -> 837.69 | V15: 15548.33 | W15: =S15+T15+U15+V15 -> 16386.02 | X15: 451167.48 | Y15: =R15-W15 -> 451167.48 | Z15: =80000 -> 80000 | AA15: =Z15-N15 -> 80000
A16: 8 | B16: DR IKEME ARTHUR J.O | D16: SNR RESEARCH FELLOW | E16: 15(9) | F16: =33507.5 -> 33507.5 | H16: =F16*300% -> 100522.5 | I16: =F16*7.5% -> 2513.0625 | J16: 40122.19 | K16: =F16*50% -> 16753.75 | L16: =F16*350% -> 117276.25 | M16: =F16*100% -> 33507.5 | N16: =100000 -> 100000 | O16: =F16*10% -> 3350.75 | P16: 20000 | Q16: 0 | R16: =SUM(F16:Q16) -> 467553.5 | S16: 50000 | T16: =212642 -> 212642 | U16: ='[3]DECEMBER 2019'!$H$38 -> 837.6875 | V16: 15548.33 | W16: =SUM(S16:V16) -> 279028.02 | X16: 188525.48 | Y16: =R16-W16 -> 188525.48 | Z16: =80000 -> 80000 | AA16: =Z16-N16 -> -20000
A17: 9 | B17: MOSHOOD M. OLALERE | D17: MANAGER ADMIN DG's OFFICE | E17: 15(9) | F17: =33507.5 -> 33507.5 | H17: =F17*300% -> 100522.5 | I17: =F17*7.5% -> 2513.0625 | J17: 40122.19 | K17: =F17*50% -> 16753.75 | L17: =F17*350% -> 117276.25 | M17: =F17*100% -> 33507.5 | O17: =F17*10% -> 3350.75 | P17: 20000 | Q17: 0 | R17: =SUM(F17:Q17) -> 367553.5 | S17: =5000 -> 5000 | T17: =179017.51 -> 179017.51 | U17: ='[3]DECEMBER 2019'!$H$35 -> 837.6875 | V17: 15548.33 | W17: =S17+T17+U17+V17 -> 200403.53 | X17: 167149.98 | Y17: =R17-W17 -> 167149.98 | Z17: =80000 -> 80000 | AA17: =Z17-N17 -> 80000
A18: 10 | B18: AYOBOLU OLAJIDE OLUFUNSHO | D18: MANAGER, INFORMATION | E18: 15 (7) | F18: 31018.84 | H18: =F18*300% -> 93056.52 | I18: =F18*7.5% -> 2326.413 | J18: 40122.19 | K18: =F18*50% -> 15509.42 | L18: =F18*350% -> 108565.94 | M18: =F18*100% -> 31018.84 | O18: =F18*10% -> 3101.884 | P18: 20000 | Q18: 0 | R18: =SUM(F18:Q18) -> 344720.05 | S18: =25000 -> 25000 | T18: =52500 -> 52500 | V18: 15548.33 | W18: =S18+T18+U18+V18 -> 93048.33 | X18: 251671.72 | Y18: =R18-W18 -> 251671.72 | Z18: =80000 -> 80000 | AA18: =Z18-N18 -> 80000
A19: 11 | B19: HUSSEIN EGYE MUSA | D19: AM PROTOCOL | E19: 13(10) | F19: =25523.45 -> 25523.45 | H19: =F19*300% -> 76570.35 | I19: =F19*7.5% -> 1914.2587 | K19: =F19*50% -> 12761.725 | L19: =F19*350% -> 89332.075 | M19: =F19*100% -> 25523.45 | O19: =F19*10% -> 2552.345 | P19: 15000 | Q19: 50000 | R19: =SUM(F19:Q19) -> 299177.65 | S19: 50000 | T19: =0 -> 0 | U19: 0 | V19: 7709.76 | W19: =S19+T19+U19+V19 -> 57709.76 | X19: 241467.89 | Y19: =R19-W19 -> 241467.89 | Z19: =70000 -> 70000 | AA19: =Z19-N19 -> 70000
A20: 12 | B20: DONALD E. MKPANAM | D20: AM ICT | E20: 13(11) | F20: 26339.3 | H20: =F20*300% -> 79017.9 | I20: =F20*7.5% -> 1975.4475 | K20: =F20*50% -> 13169.65 | L20: =F20*350% -> 92187.55 | M20: =F20*100% -> 26339.3 | N20: =100000 -> 100000 | O20: =F20*10% -> 2633.93 | P20: 15000 | Q20: 0 | R20: =SUM(F20:Q20) -> 356663.08 | U20: ='[2]Jan 2021'!$H$28 -> 658.4825 | V20: 7709.76 | W20: =S20+T20+U20+V20 -> 8368.2425 | X20: 348294.83 | Y20: =R20-W20 -> 348294.83 | Z20: =70000 -> 70000 | AA20: =Z20-N20 -> -30000
A21: 13 | B21: JOY HARUNA MAKERI | D21: AM TRAINING | E21: 13(10) | F21: =25523.45 -> 25523.45 | H21: =F21*300% -> 76570.35 | I21: =F21*7.5% -> 1914.2587 | K21: =F21*50% -> 12761.725 | L21: =F21*350% -> 89332.075 | M21: =F21*100% -> 25523.45 | N21: 100000 | O21: =F21*10% -> 2552.345 | P21: 15000 | Q21: =50000+100000 -> 150000 | R21: =SUM(F21:Q21) -> 499177.65 | V21: =7709.76 -> 7709.76 | W21: =SUM(S21:V21) -> 7709.76 | X21: 491467.89 | Y21: =R21-W21 -> 491467.89 | Z21: =70000 -> 70000 | AA21: =Z21-N21 -> -30000
A22: 14 | B22: ALI ABDULLAHI | D22: AM ICT | E22: 13(11) | F22: =26339.3 -> 26339.3 | H22: =F22*300% -> 79017.9 | I22: =F22*7.5% -> 1975.4475 | J22: 0 | K22: =F22*50% -> 13169.65 | L22: =F22*350% -> 92187.55 | M22: =F22*100% -> 26339.3 | N22: =100000 -> 100000 | O22: =F22*10% -> 2633.93 | P22: 15000 | Q22: =0 -> 0 | R22: =SUM(F22:Q22) -> 356663.08 | V22: =7709.76 -> 7709.76 | W22: =S22+T22+U22+V22 -> 7709.76 | X22: 348953.32 | Y22: =R22-W22 -> 348953.32 | Z22: =70000 -> 70000 | AA22: =Z22-N22 -> -30000
A23: 15 | B23: MARIAM MOHAMMED BELLO | D23: PA- SPECIAL DUTIES | E23: 13 (7) | F23: =23074.99 -> 23074.99 | H23: =F23*300% -> 69224.97 | I23: =F23*7.5% -> 1730.6243 | J23: 0 | K23: =F23*50% -> 11537.495 | L23: =F23*350% -> 80762.465 | M23: =F23*100% -> 23074.99 | N23: =0 -> 0 | O23: =F23*10% -> 2307.499 | P23: 15000 | Q23: =100000 -> 100000 | R23: =SUM(F23:Q23) -> 326713.03 | V23: =7709.76 -> 7709.76 | W23: =S23+T23+U23+V23 -> 7709.76 | X23: 319003.27 | Y23: =R23-W23 -> 319003.27 | Z23: =70000 -> 70000 | AA23: =Z23-N23 -> 70000
A24: 16 | B24: PERCY TERFA GBAHABO | D24: RESEARCH FELLOW 11 | E24: 13(7) | F24: =23074.99 -> 23074.99 | H24: =F24*300% -> 69224.97 | I24: =F24*7.5% -> 1730.6243 | J24: 0 | K24: =F24*50% -> 11537.495 | L24: =F24*350% -> 80762.465 | M24: =F24*100% -> 23074.99 | N24: =100000 -> 100000 | O24: =F24*10% -> 2307.499 | P24: 15000 | Q24: 0 | R24: =SUM(F24:Q24) -> 326713.03 | S24: =10000 -> 10000 | T24: =131666.67 -> 131666.67 | V24: =7709.76 -> 7709.76 | W24: =SUM(S24:V24) -> 149376.43 | X24: 177336.6 | Y24: =R24-W24 -> 177336.6 | Z24: =70000 -> 70000 | AA24: =Z24-N24 -> -30000
A25: 17 | B25: ADUGBA RICHARD TERSEER | D25: INFORMATION OFFICER | E25: 10(9) | F25: =18281.64 -> 18281.64 | H25: =F25*300% -> 54844.92 | I25: =F25*7.5% -> 1371.123 | K25: =F25*50% -> 9140.82 | L25: =F25*350% -> 63985.74 | M25: =F25*100% -> 18281.64 | O25: =F25*10% -> 1828.164 | P25: 10000 | R25: =SUM(F25:Q25) -> 177734.05 | S25: =20000 -> 20000 | T25: =111833.33 -> 111833.33 | V25: 3369.51 | W25: =S25+T25+U25+V25 -> 135202.84 | X25: 42531.207 | Y25: =R25-W25 -> 42531.207 | Z25: =60000 -> 60000 | AA25: =Z25-N25 -> 60000
A26: 18 | B26: CHRISTIAN MADUABUCHI ODO | D26: ICT OFFICER | E26: 10(11) | F26: =19276.95 -> 19276.95 | H26: =F26*300% -> 57830.85 | I26: =F26*7.5% -> 1445.7713 | K26: =F26*50% -> 9638.475 | L26: =F26*350% -> 67469.325 | M26: =F26*100% -> 19276.95 | N26: =100000 -> 100000 | O26: =F26*10% -> 1927.695 | P26: 10000 | R26: =SUM(F26:Q26) -> 286866.02 | S26: =20000 -> 20000 | T26: =82500 -> 82500 | U26: ='[2]Jan 2021'!$H$47 -> 481.92375 | V26: 3369.51 | W26: =S26+T26+U26+V26 -> 106351.43 | X26: 180514.58 | Y26: =R26-W26 -> 180514.58 | Z26: =60000 -> 60000 | AA26: =Z26-N26 -> -40000
A27: 19 | B27: HASSANA AHMED IBRAHIM | D27: TRAINING OFFICER | E27: 10(8) | F27: =17784 -> 17784 | H27: =F27*300% -> 53352 | I27: =F27*7.5% -> 1333.8 | K27: =F27*50% -> 8892 | L27: =F27*350% -> 62244 | M27: =F27*100% -> 17784 | O27: =F27*10% -> 1778.4 | P27: 10000 | R27: =SUM(F27:Q27) -> 173168.2 | S27: =30000 -> 30000 | U27: ='[2]Jan 2021'!$H$55 -> 444.6 | V27: 3369.51 | W27: =SUM(S27:V27) -> 33814.11 | X27: 239354.09 | Y27: =R27-W27 -> 139354.09 | Z27: =60000 -> 60000 | AA27: =Z27-N27 -> 60000
A28: 20 | B28: VICTOR ASUKWO | D28: ICT OFFICER | E28: 8 (9) | F28: =13112.16 -> 13112.16 | H28: =F28*300% -> 39336.48 | I28: =F28*7.5% -> 983.412 | K28: =F28*50% -> 6556.08 | L28: =F28*350% -> 45892.56 | M28: =F28*100% -> 13112.16 | N28: =100000 -> 100000 | O28: =F28*10% -> 1311.216 | P28: 10000 | R28: =SUM(F28:Q28) -> 230304.07 | S28: =10000 -> 10000 | V28: 1484.37 | W28: =S28+T28+U28+V28 -> 11484.37 | X28: 218819.7 | Y28: =R28-W28 -> 218819.7 | Z28: =50000 -> 50000 | AA28: =Z28-N28 -> -50000
A29: 21 | B29: SULEIMAN ABUBAKAR SODEEQ | D29: ASST. ADMIN. OFFICER | E29: 8(7) | F29: =12351.94 -> 12351.94 | H29: =F29*300% -> 37055.82 | I29: =F29*7.5% -> 926.3955 | K29: =F29*50% -> 6175.97 | L29: =F29*350% -> 43231.79 | M29: =F29*100% -> 12351.94 | O29: =F29*10% -> 1235.194 | P29: 10000 | R29: =SUM(F29:Q29) -> 123329.05 | V29: =1235.19 -> 1235.19 | W29: =SUM(S29:V29) -> 1235.19 | X29: 122093.86 | Y29: =R29-W29 -> 122093.86 | Z29: =50000 -> 50000 | AA29: =Z29-N29 -> 50000
A30: 22 | B30: YAKUB OLUWATOYIN USMAN | D30: ASST. ADMIN. OFFICER | E30: 8(7) | F30: =12351.94 -> 12351.94 | H30: =F30*300% -> 37055.82 | I30: =F30*7.5% -> 926.3955 | K30: =F30*50% -> 6175.97 | L30: =F30*350% -> 43231.79 | M30: =F30*100% -> 12351.94 | O30: =F30*10% -> 1235.194 | P30: 10000 | R30: =SUM(F30:Q30) -> 123329.05 | S30: =10000 -> 10000 | V30: =1235.19 -> 1235.19 | W30: =SUM(S30:V30) -> 11235.19 | X30: 112093.86 | Y30: =R30-W30 -> 112093.86 | Z30: =50000 -> 50000 | AA30: =Z30-N30 -> 50000
A31: 23 | B31: ANTHONY EDET | D31: ASST. MGR M&E | E31: 13(8) | F31: =23891.12 -> 23891.12 | H31: =F31*300% -> 71673.36 | I31: =F31*7.5% -> 1791.834 | J31: 0 | K31: =F31*50% -> 11945.56 | L31: =F31*350% -> 83618.92 | M31: =F31*100% -> 23891.12 | N31: =100000 -> 100000 | O31: =F31*10% -> 2389.112 | P31: 15000 | Q31: 0 | R31: =SUM(F31:Q31) -> 334201.03 | S31: 20000 | U31: ='[2]Jan 2021'!$H$39 -> 597.278 | V31: =7709.76 -> 7709.76 | W31: =SUM(S31:V31) -> 28307.038 | X31: 305893.99 | Y31: =R31-W31 -> 305893.99 | Z31: =70000 -> 70000 | AA31: =Z31-N31 -> -30000
A32: 24 | B32: EGUATU U. ONYEJELEM | D32: OFFICER M&E | E32: 10(9) | F32: =18281.64 -> 18281.64 | H32: =F32*300% -> 54844.92 | I32: =F32*7.5% -> 1371.123 | K32: =F32*50% -> 9140.82 | L32: =F32*350% -> 63985.74 | M32: =F32*100% -> 18281.64 | N32: =100000 -> 100000 | O32: =F32*10% -> 1828.164 | P32: 10000 | R32: =SUM(F32:Q32) -> 277734.05 | S32: =20000 -> 20000 | T32: =87500+43750 -> 131250 | V32: 3369.51 | W32: =SUM(S32:V32) -> 154619.51 | X32: 123114.54 | Y32: =R32-W32 -> 123114.54 | Z32: =60000 -> 60000 | AA32: =Z32-N32 -> -40000
A33: 25 | B33: ODEH SUZIE | D33: ADMIN. OFFICER, LIASION OFFICE | E33: 10(8) | F33: =17784 -> 17784 | H33: =F33*300% -> 53352 | I33: =F33*7.5% -> 1333.8 | K33: =F33*50% -> 8892 | L33: =F33*350% -> 62244 | M33: =F33*100% -> 17784 | O33: =F33*10% -> 1778.4 | P33: 10000 | R33: =SUM(F33:Q33) -> 173168.2 | S33: =30000 -> 30000 | U33: =0 -> 0 | V33: 3369.51 | W33: =S33+T33+U33+V33 -> 33369.51 | X33: 139798.69 | Y33: =R33-W33 -> 139798.69 | Z33: 60000 | AA33: =Z33-N33 -> 60000
A34: 26 | B34: TASSNEEM IBRAHIM | D34: ASSIST. INFORMATION | E34: 8(8) | F34: =12732 -> 12732 | H34: =F34*300% -> 38196 | I34: =F34*7.5% -> 954.9 | K34: =F34*50% -> 6366 | L34: =F34*350% -> 44562 | M34: =F34*100% -> 12732 | O34: =F34*10% -> 1273.2 | P34: 10000 | R34: =SUM(F34:Q34) -> 126816.1 | S34: =50000 -> 50000 | T34: =40000 -> 40000 | U34: =0 -> 0 | V34: =1235.19 -> 1235.19 | W34: =S34+T34+U34+V34 -> 91235.19 | X34: 35580.91 | Y34: =R34-W34 -> 35580.91 | Z34: =50000 -> 50000 | AA34: =Z34-N34 -> 50000
B35: TOTAL | D35: 26 | F35: =SUM(F9:F34) -> 851132.9 | H35: =SUM(H9:H34) -> 2392909.9 | I35: =SUM(I9:I34) -> 99944.941 | J35: =SUM(J9:J34) -> 521588.47 | K35: =SUM(K9:K34) -> 417542.01 | L35: =SUM(L9:L34) -> 2417254.5 | M35: =SUM(M9:M34) -> 811010.72 | N35: =SUM(N9:N34) -> 1300000 | O35: =SUM(O9:O34) -> 85113.295 | ... W35: =SUM(W9:W34) -> 2186987.2 | X35: 7468053.9 | Y35: =SUM(Y9:Y34) -> 7784744.6 | Z35: =SUM(Z9:Z34) -> 2200000 | AA35: =SUM(AA9:AA34) -> 900000
B37: INTERNAL AUDIT
A38: 1 | B38: NWOSU MATHEW EZE | D38: Ag. DIRECTOR INT. AUDIT | E38: 17(8) | F38: =79039.64 -> 79039.64 | H38: =F38*300% -> 237118.92 | I38: =F38*7.5% -> 5927.973 | J38: =80244.38 -> 80244.38 | K38: =F38*50% -> 39519.82 | L38: =F38*350% -> 276638.74 | M38: =F38*100% -> 79039.64 | O38: =F38*10% -> 7903.964 | P38: 20000 | Q38: 0 | R38: =SUM(F38:Q38) -> 825433.08 | S38: =100000 -> 100000 | T38: =287500 -> 287500 | U38: ='[2]Jan 2021'!$H$23 -> 1975.991 | V38: =52776.63 -> 52776.63 | W38: =S38+T38+U38+V38 -> 442252.62 | X38: 383180.46 | Y38: =R38-W38 -> 383180.46 | Z38: =100000 -> 100000 | AA38: =Z38-N38 -> 100000
C39: TOTAL | D39: 1 | F39: =SUM(F38:F38) -> 79039.64 | H39: =SUM(H38:H38) -> 237118.92 | I39: =SUM(I38:I38) -> 5927.973 | J39: =SUM(J38:J38) -> 80244.38 | K39: =SUM(K38:K38) -> 39519.82 | L39: =SUM(L38:L38) -> 276638.74 | M39: =SUM(M38:M38) -> 79039.64 | N39: =SUM(N38:N38) -> 0 | O39: =SUM(O38:O38) -> 7903.964 | ... W39: =SUM(W38:W38) -> 442252.62 | X39: 383180.46 | Y39: =SUM(Y38:Y38) -> 383180.46 | Z39: =SUM(Z38) -> 100000 | AA39: =SUM(AA38) -> 100000
B41: LEG. SUPPORT SEVICES
A42: 1 | B42: PROF. EDOBA BRIGHT OMOREGBE | D42: AG. DLSS | E42: 17(9) | F42: =81740.02 -> 81740.02 | H42: =F42*300% -> 245220.06 | I42: =F42*7.5% -> 6130.5015 | J42: 80244.38 | K42: =F42*50% -> 40870.01 | L42: =F42*350% -> 286090.07 | M42: =F42*100% -> 81740.02 | N42: 100000 | O42: =F42*10% -> 8174.002 | P42: 20000 | R42: =SUM(F42:Q42) -> 950209.06 | S42: =100000 -> 100000 | V42: =52776.63 -> 52776.63 | W42: =V42+S42+T42+U42 -> 152776.63 | X42: 797432.43 | Y42: =R42-W42 -> 797432.43 | Z42: =200000 -> 200000 | AA42: =Z42-N42 -> 100000
A43: 2 | B43: DR CLINTON JAJA | D43: SENIOR RESEARCH FELLOW | E43: 15(9) | F43: =33507.5 -> 33507.5 | H43: =F43*300% -> 100522.5 | I43: =F43*7.5% -> 2513.0625 | J43: 40122.19 | K43: =F43*50% -> 16753.75 | L43: =F43*350% -> 117276.25 | M43: =F43*100% -> 33507.5 | N43: 100000 | O43: =F43*10% -> 3350.75 | P43: 20000 | Q43: 0 | R43: =SUM(F43:Q43) -> 467553.5 | S43: 50000 | T43: =240909.11 -> 240909.11 | V43: 15548.33 | W43: =SUM(S43:V43) -> 306457.44 | X43: 161096.06 | Y43: =R43-W43 -> 161096.06 | Z43: =160000 -> 160000 | AA43: =Z43-N43 -> 60000
A44: 3 | B44: BETHEL UZOMA IHUGBA | D44: SNR RESEARCH FELLOW | E44: 15(9) | F44: =33507.5 -> 33507.5 | H44: =F44*300% -> 100522.5 | I44: =F44*7.5% -> 2513.0625 | J44: 40122.19 | K44: =F44*50% -> 16753.75 | L44: =F44*350% -> 117276.25 | M44: =F44*100% -> 33507.5 | N44: 100000 | O44: =F44*10% -> 3350.75 | P44: 20000 | R44: =SUM(F44:Q44) -> 467553.5 | S44: =30000+13000 -> 43000 | T44: =246905.96 -> 246905.96 | V44: 15548.33 | W44: =V44+S44+T44+U44 -> 305454.29 | X44: 162099.21 | Y44: =R44-W44 -> 162099.21 | Z44: =160000 -> 160000 | AA44: =Z44-N44 -> 60000
A45: 4 | B45: OGUCHE SAMUEL | D45: RESEARCH FELLOW I | E45: 14(11) | F45: 28489.81 | H45: =F45*300% -> 85469.43 | I45: =F45*7.5% -> 2136.7357 | K45: =F45*50% -> 14244.905 | L45: =F45*350% -> 99714.335 | M45: =F45*100% -> 28489.81 | N45: 100000 | O45: =F45*10% -> 2848.981 | P45: 20000 | R45: =SUM(F45:Q45) -> 381394.01 | S45: =30000 -> 30000 | T45: =179165.6+26250 -> 205415.6 | V45: 7709.76 | W45: =SUM(S45:V45) -> 243125.36 | X45: 138268.65 | Y45: =R45-W45 -> 138268.65 | Z45: =140000 -> 140000 | AA45: =Z45-N45 -> 40000
A46: 5 | B46: IBRAHIM USMAN | D46: RESEARCH FELLOW I | E46: 14(11) | F46: =28489.81 -> 28489.81 | H46: =F46*300% -> 85469.43 | I46: =F46*7.5% -> 2136.7357 | J46: 0 | K46: =F46*50% -> 14244.905 | L46: =F46*350% -> 99714.335 | M46: =F46*100% -> 28489.81 | N46: 100000 | O46: =F46*10% -> 2848.981 | P46: 20000 | Q46: 0 | R46: =SUM(F46:Q46) -> 381394.01 | U46: ='[2]Jan 2021'!$H$24 -> 712.24525 | V46: 7709.76 | W46: =V46+S46+T46+U46 -> 8422.0053 | X46: 372972 | Y46: =R46-W46 -> 372972 | Z46: =140000 -> 140000 | AA46: =Z46-N46 -> 40000
A47: 6 | B47: DR MOHAMMED O. AMALI | D47: RESEARCH FELLOW I | E47: 14(8) | F47: =25854.1 -> 25854.1 | H47: =F47*300% -> 77562.3 | I47: =F47*7.5% -> 1939.0575 | K47: =F47*50% -> 12927.05 | L47: =F47*350% -> 90489.35 | M47: =F47*100% -> 25854.1 | N47: 100000 | O47: =F47*10% -> 2585.41 | P47: 20000 | R47: =SUM(F47:Q47) -> 357211.37 | S47: =15000 -> 15000 | T47: =106666.67 -> 106666.67 | V47: 7709.76 | W47: =V47+S47+T47+U47 -> 129376.43 | X47: 227834.94 | Y47: =R47-W47 -> 227834.94 | Z47: =140000 -> 140000 | AA47: =Z47-N47 -> 40000
A48: 7 | B48: YAHAYA SHAMSU | D48: RESEARCH FELLOW 11 | E48: 13(11) | F48: =26339.3 -> 26339.3 | H48: =F48*300% -> 79017.9 | I48: =F48*7.5% -> 1975.4475 | K48: =F48*50% -> 13169.65 | L48: =F48*350% -> 92187.55 | M48: =F48*100% -> 26339.3 | N48: 100000 | O48: =F48*10% -> 2633.93 | P48: 15000 | R48: =SUM(F48:Q48) -> 356663.08 | U48: 0 | V48: 7709.76 | W48: =V48+T48+S48+U48 -> 7709.76 | X48: 348953.32 | Y48: =R48-W48 -> 348953.32 | Z48: =120000 -> 120000 | AA48: =Z48-N48 -> 20000
A49: 8 | B49: OFORDEME ADAOBI JULIA | D49: RESEARCH FELLOW 11 | E49: 13(9) | F49: =24741.26 -> 24741.26 | H49: =F49*300% -> 74223.78 | I49: =F49*7.5% -> 1855.5945 | J49: 0 | K49: =F49*50% -> 12370.63 | L49: =F49*350% -> 86594.41 | M49: =F49*100% -> 24741.26 | N49: 100000 | O49: =F49*10% -> 2474.126 | P49: 15000 | Q49: 0 | R49: =SUM(F49:Q49) -> 342001.06 | V49: 7709.76 | W49: =V49+S49+T49+U49 -> 7709.76 | X49: 334291.3 | Y49: =R49-W49 -> 334291.3 | Z49: =120000 -> 120000 | AA49: =Z49-N49 -> 20000
A50: 9 | B50: IKPEAZU CHINEDU ANITA | D50: RESEARCH FELLOW II | E50: 14(8) | F50: =25854.1 -> 25854.1 | H50: =F50*300% -> 77562.3 | I50: =F50*7.5% -> 1939.0575 | J50: 0 | K50: =F50*50% -> 12927.05 | L50: =F50*350% -> 90489.35 | M50: =F50*100% -> 25854.1 | N50: 100000 | O50: =F50*10% -> 2585.41 | P50: 20000 | Q50: 0 | R50: =SUM(F50:Q50) -> 357211.37 | V50: 7709.76 | W50: =V50+S50+T50+U50 -> 7709.76 | X50: 349501.61 | Y50: =R50-W50 -> 349501.61 | Z50: 140000 | AA50: =Z50-N50 -> 40000
A51: 10 | B51: ONYEAKU CHUKWUKA EDMOND | D51: RESEARCH FELLOW II | E51: 13(10) | F51: =25523.45 -> 25523.45 | H51: =F51*300% -> 76570.35 | I51: =F51*7.5% -> 1914.2587 | J51: =J22 -> 0 | K51: =F51*50% -> 12761.725 | L51: =F51*350% -> 89332.075 | M51: =F51*100% -> 25523.45 | N51: 100000 | O51: =F51*10% -> 2552.345 | P51: 15000 | Q51: 0 | R51: =SUM(F51:Q51) -> 349177.65 | S51: =30000 -> 30000 | T51: =182107.04 -> 182107.04 | U51: ='[2]Jan 2021'!$H$42 -> 638.08625 | V51: 7709.76 | W51: =V51+S51+T51+U51 -> 220454.89 | X51: 128722.77 | Y51: =R51-W51 -> 128722.77 | Z51: =120000 -> 120000 | AA51: =Z51-N51 -> 20000
A52: 11 | B52: DORIS DAKDA AARON | D52: RESEARCH FELLOW II | E52: 13(8) | F52: =23891.12 -> 23891.12 | H52: =F52*300% -> 71673.36 | I52: =F52*7.5% -> 1791.834 | K52: =F52*50% -> 11945.56 | L52: =F52*350% -> 83618.92 | M52: =F52*100% -> 23891.12 | N52: 100000 | O52: =F52*10% -> 2389.112 | P52: 15000 | R52: =SUM(F52:Q52) -> 334201.03 | S52: =100000+10000 -> 110000 | U52: ='[2]Jan 2021'!$H$48 -> 597.278 | V52: =7709.76 -> 7709.76 | W52: =V52+S52+T52+U52 -> 118307.04 | X52: 215893.99 | Y52: =R52-W52 -> 215893.99 | Z52: =120000 -> 120000 | AA52: =Z52-N52 -> 20000
B53: TOTAL | D53: 11 | F53: =SUM(F42:F52) -> 357937.97 | H53: =SUM(H42:H52) -> 1073813.9 | I53: =SUM(I42:I52) -> 26845.348 | J53: =SUM(J42:J52) -> 160488.76 | K53: =SUM(K42:K52) -> 178968.98 | L53: =SUM(L42:L52) -> 1252782.9 | M53: =SUM(M42:M52) -> 357937.97 | N53: =SUM(N42:N52) -> 1100000 | O53: =SUM(O42:O52) -> 35793.797 | ... W53: =SUM(W42:W52) -> 1507503.4 | X53: 3237066.3 | Y53: =SUM(Y42:Y52) -> 3237066.3 | Z53: =SUM(Z42:Z52) -> 1560000 | AA53: =SUM(AA42:AA52) -> 460000
B55: LEGAL SERVICES
A56: 1 | B56: DR SHUIBU DANWANKA | D56: DIRECTOR LEGAL SERVICES | E56: 17(9) | F56: =81740.02 -> 81740.02 | H56: =F56*300% -> 245220.06 | I56: =F56*7.5% -> 6130.5015 | J56: 80244.38 | K56: =F56*50% -> 40870.01 | L56: =F56*350% -> 286090.07 | M56: =F56*100% -> 81740.02 | N56: =100000 -> 100000 | O56: =F56*10% -> 8174.002 | P56: 20000 | Q56: 0 | R56: =SUM(F56:Q56) -> 950209.06 | U56: 0 | V56: 52776.63 | W56: =S56+T56+U56+V56 -> 52776.63 | X56: 897432.43 | Y56: =R56-W56 -> 897432.43 | Z56: =200000 -> 200000 | AA56: =Z56-N56 -> 100000
A57: 2 | B57: ABDULSALAM BAKO | D57: MANAGER, LEGAL SERVICES | E57: 15 (7) | F57: 31018.84 | H57: =F57*300% -> 93056.52 | I57: =F57*7.5% -> 2326.413 | J57: 40122.19 | K57: =F57*50% -> 15509.42 | L57: =F57*350% -> 108565.94 | M57: =F57*100% -> 31018.84 | O57: =F57*10% -> 3101.884 | P57: 20000 | Q57: 0 | R57: =SUM(F57:Q57) -> 344720.05 | S57: =100000 -> 100000 | U57: 0 | V57: =15548.33 -> 15548.33 | W57: =S57+T57+U57+V57 -> 115548.33 | X57: 229171.72 | Y57: =R57-W57 -> 229171.72 | Z57: =80000 -> 80000 | AA57: =Z57-N57 -> 80000
B58: TOTAL | D58: 2 | F58: =SUM(F56:F57) -> 112758.86 | H58: =SUM(H56:H57) -> 338276.58 | I58: =SUM(I56:I57) -> 8456.9145 | J58: =SUM(J56:J57) -> 120366.57 | K58: =SUM(K56:K57) -> 56379.43 | L58: =SUM(L56:L57) -> 394656.01 | M58: =SUM(M56:M57) -> 112758.86 | N58: =SUM(N56:N57) -> 100000 | O58: =SUM(O56:O57) -> 11275.886 | ... S58: =SUM(S56:S57) -> 100000 | U58: =SUM(U56:U57) -> 0 | V58: =SUM(V56:V57) -> 68324.96 | W58: =SUM(W56:W57) -> 168324.96 | X58: 1126604.2 | Y58: =SUM(Y56:Y57) -> 1126604.2 | Z58: =SUM(Z56:Z57) -> 280000 | AA58: =SUM(AA56:AA57) -> 180000
B60: DEMOCRATIC STUDIES
A61: 1 | B61: DR. ADEWALE ADEREMI | D61: DIRECTOR, DEMOCRATIC STUDIES | E61: 17(8) | F61: =79039.64 -> 79039.64 | H61: =F61*300% -> 237118.92 | I61: =F61*7.5% -> 5927.973 | J61: =80244.38 -> 80244.38 | K61: =F61*50% -> 39519.82 | L61: =F61*350% -> 276638.74 | M61: =F61*100% -> 79039.64 | N61: =100000 -> 100000 | O61: =F61*10% -> 7903.964 | P61: 20000 | Q61: 0 | R61: =SUM(F61:Q61) -> 925433.08 | S61: =100000 -> 100000 | V61: =52776.63 -> 52776.63 | W61: =S61+T61+U61+V61 -> 152776.63 | X61: 772656.45 | Y61: =R61-W61 -> 772656.45 | Z61: =200000 -> 200000 | AA61: =Z61-N61 -> 100000
A62: 2 | B62: NDANUSA MOHAMMED MANZUMA | D62: SNR RESEARCH FELLOW | E62: 15 (7) | F62: 31018.84 | H62: =F62*300% -> 93056.52 | I62: =F62*7.5% -> 2326.413 | J62: 40122.19 | K62: =F62*50% -> 15509.42 | L62: =F62*350% -> 108565.94 | M62: =F62*100% -> 31018.84 | O62: =F62*10% -> 3101.884 | P62: 20000 | Q62: 0 | R62: =SUM(F62:Q62) -> 344720.05 | S62: =100000 -> 100000 | T62: =131250 -> 131250 | U62: 0 | V62: =15548.33 -> 15548.33 | W62: =S62+T62+U62+V62 -> 246798.33 | X62: 97921.717 | Y62: =R62-W62 -> 97921.717 | Z62: =160000 -> 160000 | AA62: =Z62-N62 -> 160000
A63: 3 | B63: EMILY EDOISA IKHIDE | D63: RESEARCH FELLOW II | E63: 13(10) | F63: =25523.45 -> 25523.45 | H63: =F63*300% -> 76570.35 | I63: =F63*7.5% -> 1914.2587 | K63: =F63*50% -> 12761.725 | L63: =F63*350% -> 89332.075 | M63: =F63*100% -> 25523.45 | N63: =100000 -> 100000 | O63: =F63*10% -> 2552.345 | P63: 15000 | R63: =SUM(F63:Q63) -> 349177.65 | S63: =50000 -> 50000 | T63: =45833.33 -> 45833.33 | V63: 7709.76 | W63: =SUM(S63:V63) -> 103543.09 | X63: 245634.56 | Y63: =R63-W63 -> 245634.56 | Z63: =120000 -> 120000 | AA63: =Z63-N63 -> 20000
A64: 4 | B64: EJALONIBU GANIYU LAYI | D64: RESEARCH FELLOW 11 | E64: 13(8) | F64: =23891.12 -> 23891.12 | H64: =F64*300% -> 71673.36 | I64: =F64*7.5% -> 1791.834 | K64: =F64*50% -> 11945.56 | L64: =F64*350% -> 83618.92 | M64: =F64*100% -> 23891.12 | N64: =100000 -> 100000 | O64: =F64*10% -> 2389.112 | P64: 15000 | R64: =SUM(F64:Q64) -> 334201.03 | S64: =110000 -> 110000 | V64: =7709.76 -> 7709.76 | W64: =S64+T64+U64+V64 -> 117709.76 | X64: 216491.27 | Y64: =R64-W64 -> 216491.27 | Z64: =120000 -> 120000 | AA64: =Z64-N64 -> 20000
A65: 5 | B65: LONA POLIT BONKAT | D65: RESEARCH FELLOW 11 | E65: 13(7) | F65: =23074.99 -> 23074.99 | H65: =F65*300% -> 69224.97 | I65: =F65*7.5% -> 1730.6243 | J65: 0 | K65: =F65*50% -> 11537.495 | L65: =F65*350% -> 80762.465 | M65: =F65*100% -> 23074.99 | N65: =100000 -> 100000 | O65: =F65*10% -> 2307.499 | P65: 15000 | Q65: 0 | R65: =SUM(F65:Q65) -> 326713.03 | S65: =20000 -> 20000 | T65: =119444.44 -> 119444.44 | U65: =0 -> 0 | V65: 7709.76 | W65: =SUM(S65:V65) -> 147154.2 | X65: 179558.83 | Y65: =R65-W65 -> 179558.83 | Z65: =120000 -> 120000 | AA65: =Z65-N65 -> 20000
A66: 6 | B66: YUNUSA ABDULLAHI | D66: RESEARCH FELLOW 11 | E66: 13(10) | F66: =25523.45 -> 25523.45 | H66: =F66*300% -> 76570.35 | I66: =F66*7.5% -> 1914.2587 | K66: =F66*50% -> 12761.725 | L66: =F66*350% -> 89332.075 | M66: =F66*100% -> 25523.45 | O66: =F66*10% -> 2552.345 | P66: 15000 | R66: =SUM(F66:Q66) -> 249177.65 | S66: =10000 -> 10000 | T66: =54585.66 -> 54585.66 | V66: =7709.76 -> 7709.76 | W66: =SUM(S66:V66) -> 72295.42 | X66: 176882.23 | Y66: =R66-W66 -> 176882.23 | Z66: =120000 -> 120000 | AA66: =Z66-N66 -> 120000
A67: 7 | B67: UDEFUNA NNADOZIE PATRICK | D67: RESEARCH OFFICER | E67: 10(13) | F67: =19774.62 -> 19774.62 | H67: =F67*300% -> 59323.86 | I67: =F67*7.5% -> 1483.0965 | J67: 0 | K67: =F67*50% -> 9887.31 | L67: =F67*350% -> 69211.17 | M67: =F67*100% -> 19774.62 | N67: =100000 -> 100000 | O67: =F67*10% -> 1977.462 | P67: 10000 | Q67: 0 | R67: =SUM(F67:Q67) -> 291432.14 | S67: =10000 -> 10000 | T67: =131771.66 -> 131771.66 | V67: 3369.51 | W67: =SUM(S67:V67) -> 145141.17 | X67: 146290.97 | Y67: =R67-W67 -> 146290.97 | Z67: =100000 -> 100000 | AA67: =Z67-N67 -> 0
A68: 8 | B68: OSOLAFIA MUHAMMAD EGYE | D68: RESEARCH OFFICER | E68: 10(11) | F68: =19276.95 -> 19276.95 | H68: =F68*300% -> 57830.85 | I68: =F68*7.5% -> 1445.7713 | J68: 0 | K68: =F68*50% -> 9638.475 | L68: =F68*350% -> 67469.325 | M68: =F68*100% -> 19276.95 | N68: =100000 -> 100000 | O68: =F68*10% -> 1927.695 | P68: 10000 | Q68: 0 | R68: =SUM(F68:Q68) -> 286866.02 | S68: =20000 -> 20000 | T68: =100000 -> 100000 | U68: ='[2]Jan 2021'!$H$43 -> 481.92375 | V68: =3369.51 -> 3369.51 | W68: =S68+T68+U68+V68 -> 123851.43 | X68: 163014.58 | Y68: =R68-W68 -> 163014.58 | Z68: =100000 -> 100000 | AA68: =Z68-N68 -> 0
A69: 9 | B69: HAUWA PATE SADIQ | D69: PROGRAMME OFFICER | E69: 10(9) | F69: =18281.64 -> 18281.64 | H69: =F69*300% -> 54844.92 | I69: =F69*7.5% -> 1371.123 | K69: =F69*50% -> 9140.82 | L69: =F69*350% -> 63985.74 | M69: =F69*100% -> 18281.64 | N69: =100000 -> 100000 | O69: =F69*10% -> 1828.164 | P69: 10000 | R69: =SUM(F69:Q69) -> 277734.05 | S69: =70000+20000 -> 90000 | T69: =31500 -> 31500 | V69: 3369.51 | W69: =SUM(S69:V69) -> 124869.51 | X69: 152864.54 | Y69: =R69-W69 -> 152864.54 | Z69: =100000 -> 100000 | AA69: =Z69-N69 -> 0
A70: 10 | B70: ABAYOMI KAYODE QUADRI | D70: RESEARCH OFFICER | E70: 10(7) | F70: =17286.33 -> 17286.33 | H70: =F70*300% -> 51858.99 | I70: =F70*7.5% -> 1296.4748 | K70: =F70*50% -> 8643.165 | L70: =F70*350% -> 60502.155 | M70: =F70*100% -> 17286.33 | N70: =100000 -> 100000 | O70: =F70*10% -> 1728.633 | P70: 10000 | R70: =SUM(F70:Q70) -> 268602.08 | S70: =50000 -> 50000 | T70: 0 | V70: 3369.51 | W70: =SUM(S70:V70) -> 53369.51 | X70: 215232.57 | Y70: =R70-W70 -> 215232.57 | Z70: =100000 -> 100000 | AA70: =Z70-N70 -> 0
A71: 11 | B71: NNANDI LIVINUS ATURE | D71: RESEARCH ASSISTANT | E71: 8(7) | F71: =12351.94 -> 12351.94 | H71: =F71*300% -> 37055.82 | I71: =F71*7.5% -> 926.3955 | K71: =F71*50% -> 6175.97 | L71: =F71*350% -> 43231.79 | M71: =F71*100% -> 12351.94 | N71: =100000 -> 100000 | O71: =F71*10% -> 1235.194 | P71: 10000 | R71: =SUM(F71:Q71) -> 223329.05 | S71: =100000 -> 100000 | V71: =1235.19 -> 1235.19 | W71: =SUM(S71:V71) -> 101235.19 | X71: 122093.86 | Y71: =R71-W71 -> 122093.86 | Z71: =100000 -> 100000 | AA71: =Z71-N71 -> 0
A72: 12 | B72: LUCKY AGWOM | D72: RESEARCH ASSISTANT | E72: 8(7) | F72: =12351.94 -> 12351.94 | H72: =F72*300% -> 37055.82 | I72: =F72*7.5% -> 926.3955 | K72: =F72*50% -> 6175.97 | L72: =F72*350% -> 43231.79 | M72: =F72*100% -> 12351.94 | N72: =100000 -> 100000 | O72: =F72*10% -> 1235.194 | P72: 10000 | R72: =SUM(F72:Q72) -> 223329.05 | V72: =1235.19 -> 1235.19 | W72: =SUM(S72:V72) -> 1235.19 | X72: 222093.86 | Y72: =R72-W72 -> 222093.86 | Z72: =100000 -> 100000 | AA72: =Z72-N72 -> 0
B73: TOTAL | D73: 12 | F73: =SUM(F61:F72) -> 307394.91 | H73: =SUM(H61:H72) -> 922184.73 | I73: =SUM(I61:I72) -> 23054.618 | J73: =SUM(J61:J72) -> 120366.57 | K73: =SUM(K61:K72) -> 153697.46 | L73: =SUM(L61:L72) -> 1075882.2 | M73: =SUM(M61:M72) -> 307394.91 | N73: =SUM(N61:N72) -> 1000000 | O73: =SUM(O61:O72) -> 30739.491 | ... AA73: =SUM(AA61:AA72) -> 440000
B75: STUDIES
A76: 1 | B76: DR ASIMIYU G. ABIOLA | D76: DIRECTOR POST GRADUATE | E76: 17(9) | F76: =81740.02 -> 81740.02 | H76: =F76*300% -> 245220.06 | I76: =F76*7.5% -> 6130.5015 | J76: 80244.38 | K76: =F76*50% -> 40870.01 | L76: =F76*350% -> 286090.07 | M76: =F76*100% -> 81740.02 | N76: =100000 -> 100000 | O76: =F76*10% -> 8174.002 | P76: 20000 | Q76: 0 | R76: =SUM(F76:Q76) -> 950209.06 | S76: 150000 | T76: =0 -> 0 | U76: 0 | V76: 52776.63 | W76: =SUM(S76:V76) -> 202776.63 | X76: 747432.43 | Y76: =R76-W76 -> 747432.43 | Z76: =200000 -> 200000 | AA76: =Z76-N76 -> 100000
A77: 2 | B77: USMAN WALI | D77: SENIOR RESEARCH FELLOW | E77: 15 (7) | F77: 31018.84 | H77: =F77*300% -> 93056.52 | I77: =F77*7.5% -> 2326.413 | J77: 40122.19 | K77: =F77*50% -> 15509.42 | L77: =F77*350% -> 108565.94 | M77: =F77*100% -> 31018.84 | O77: =F77*10% -> 3101.884 | P77: 20000 | Q77: 0 | R77: =SUM(F77:Q77) -> 344720.05 | U77: 0 | V77: =15548.33 -> 15548.33 | W77: =S77+T77+U77+V77 -> 15548.33 | X77: 329171.72 | Y77: =R77-W77 -> 329171.72 | Z77: =160000 -> 160000 | AA77: =Z77-N77 -> 160000
A78: 3 | B78: MOSHOOD TOSHO AMUDA | D78: MANAGER, EXAMS & RECORDS | E78: 15 (7) | F78: 31018.84 | H78: =F78*300% -> 93056.52 | I78: =F78*7.5% -> 2326.413 | J78: 40122.19 | K78: =F78*50% -> 15509.42 | L78: =F78*350% -> 108565.94 | M78: =F78*100% -> 31018.84 | N78: =100000 -> 100000 | O78: =F78*10% -> 3101.884 | P78: 20000 | Q78: 0 | R78: =SUM(F78:Q78) -> 444720.05 | U78: 0 | V78: =15548.33 -> 15548.33 | W78: =S78+T78+U78+V78 -> 15548.33 | X78: 429171.72 | Y78: =R78-W78 -> 429171.72 | Z78: =160000 -> 160000 | AA78: =Z78-N78 -> 60000
A79: 4 | B79: CHIOMA UWAZURUIKE | D79: MANAGER, PROGRAMME | E79: 15 (7) | F79: 31018.84 | H79: =F79*300% -> 93056.52 | I79: =F79*7.5% -> 2326.413 | J79: 40122.19 | K79: =F79*50% -> 15509.42 | L79: =F79*350% -> 108565.94 | M79: =F79*100% -> 31018.84 | O79: =F79*10% -> 3101.884 | P79: 20000 | Q79: 0 | R79: =SUM(F79:Q79) -> 344720.05 | U79: 0 | V79: =15548.33 -> 15548.33 | W79: =S79+T79+U79+V79 -> 15548.33 | X79: 329171.72 | Y79: =R79-W79 -> 329171.72 | Z79: =160000 -> 160000 | AA79: =Z79-N79 -> 160000
A80: 5 | B80: UZODINMA EMMANUEL EZENWA | D80: RESEARCH FELLOW II | E80: 13(8) | F80: =23891.12 -> 23891.12 | H80: =F80*300% -> 71673.36 | I80: =F80*7.5% -> 1791.834 | J80: 0 | K80: =F80*50% -> 11945.56 | L80: =F80*350% -> 83618.92 | M80: =F80*100% -> 23891.12 | N80: =100000 -> 100000 | O80: =F80*10% -> 2389.112 | P80: 15000 | Q80: 0 | R80: =SUM(F80:Q80) -> 334201.03 | S80: =0 -> 0 | T80: =0 -> 0 | U80: ='[2]Jan 2021'!$H$44 -> 597.278 | V80: =7709.76 -> 7709.76 | W80: =S80+T80+U80+V80 -> 8307.038 | X80: 325893.99 | Y80: =R80-W80 -> 325893.99 | Z80: =120000 -> 120000 | AA80: =Z80-N80 -> 20000
A81: 6 | B81: IGWE STACY | D81: PROGRAMME OFFICER | E81: 10(7) | F81: =17286.33 -> 17286.33 | H81: =F81*300% -> 51858.99 | I81: =F81*7.5% -> 1296.4748 | K81: =F81*50% -> 8643.165 | L81: =F81*350% -> 60502.155 | M81: =F81*100% -> 17286.33 | N81: =100000 -> 100000 | O81: =F81*10% -> 1728.633 | P81: 10000 | R81: =SUM(F81:Q81) -> 268602.08 | S81: =50000 -> 50000 | T81: 0 | V81: 3369.51 | W81: =SUM(S81:V81) -> 53369.51 | X81: 215232.57 | Y81: =R81-W81 -> 215232.57 | Z81: =100000 -> 100000 | AA81: =Z81-N81 -> 0
A82: 7 | B82: DARE SHEU MAGBON | D82: ASSIST. PG | E82: 8(8) | F82: =12732 -> 12732 | H82: =F82*300% -> 38196 | I82: =F82*7.5% -> 954.9 | K82: =F82*50% -> 6366 | L82: =F82*350% -> 44562 | M82: =F82*100% -> 12732 | O82: =F82*10% -> 1273.2 | P82: 10000 | R82: =SUM(F82:Q82) -> 126816.1 | S82: =3000+20000 -> 23000 | T82: 0 | V82: =1235.19 -> 1235.19 | W82: =SUM(S82:V82) -> 24235.19 | X82: 102580.91 | Y82: =R82-W82 -> 102580.91 | Z82: =100000 -> 100000 | AA82: =Z82-N82 -> 100000
A83: 8 | B83: MOHAMMED BELLO | D83: RESEARCH ASSITANT PG | E83: 8(7) | F83: =12351.94 -> 12351.94 | H83: =F83*300% -> 37055.82 | I83: =F83*7.5% -> 926.3955 | K83: =F83*50% -> 6175.97 | L83: =F83*350% -> 43231.79 | M83: =F83*100% -> 12351.94 | N83: =100000 -> 100000 | O83: =F83*10% -> 1235.194 | P83: 10000 | R83: =SUM(F83:Q83) -> 223329.05 | S83: =0 -> 0 | T83: 0 | V83: =1235.19 -> 1235.19 | W83: =SUM(S83:V83) -> 1235.19 | X83: 222093.86 | Y83: =R83-W83 -> 222093.86 | Z83: =100000 -> 100000 | AA83: =Z83-N83 -> 0
B84: TOTAL | D84: 8 | F84: =SUM(F76:F83) -> 241057.93 | H84: =SUM(H76:H83) -> 723173.79 | I84: =SUM(I76:I83) -> 18079.345 | J84: =SUM(J76:J83) -> 200610.95 | K84: =SUM(K76:K83) -> 120528.96 | L84: =SUM(L76:L83) -> 843702.76 | M84: =SUM(M76:M83) -> 241057.93 | N84: =SUM(N76:N83) -> 500000 | O84: =SUM(O76:O83) -> 24105.793 | ... W84: =SUM(W76:W83) -> 336568.55 | X84: 2700748.9 | Y84: =SUM(Y76:Y83) -> 2700748.9 | Z84: =SUM(Z76:Z83) -> 1100000 | AA84: =SUM(AA76:AA83) -> 600000
B86: ECONOMIC AND SOCIAL DEV.
A87: 1 | B87: DR ASEMOTA OMOROGBE JOSEPH | D87: Ag. DEPUTY DIRECTOR, ECO & SOC DEV DEPT | E87: 16(7) | F87: =39662.25 -> 39662.25 | H87: =F87*300% -> 118986.75 | I87: =F87*7.5% -> 2974.6687 | J87: 40122.19 | K87: =F87*50% -> 19831.125 | L87: =F87*350% -> 138817.88 | M87: =F87*100% -> 39662.25 | N87: =100000 -> 100000 | O87: =F87*10% -> 3966.225 | P87: 20000 | R87: =SUM(F87:Q87) -> 524023.33 | V87: =21618.09 -> 21618.09 | W87: =SUM(S87:V87) -> 21618.09 | X87: 502405.24 | Y87: =R87-W87 -> 502405.24 | Z87: =180000 -> 180000 | AA87: =Z87-N87 -> 80000
A88: 2 | B88: TERFA WILLIAMS ABRAHAM | D88: SNR RESEARCH FELLOW | E88: 15(8) | F88: =32263.2 -> 32263.2 | H88: =F88*300% -> 96789.6 | I88: =F88*7.5% -> 2419.74 | J88: =40122.19 -> 40122.19 | K88: =F88*50% -> 16131.6 | L88: =F88*350% -> 112921.2 | M88: =F88*100% -> 32263.2 | N88: =100000 -> 100000 | O88: =F88*10% -> 3226.32 | P88: 20000 | R88: =SUM(F88:Q88) -> 456137.05 | V88: =15548.33 -> 15548.33 | W88: =SUM(S88:V88) -> 15548.33 | X88: 440588.72 | Y88: =R88-W88 -> 440588.72 | Z88: =160000 -> 160000 | AA88: =Z88-N88 -> 60000
A89: 3 | B89: DR AUGUSTINE C. OSIGWE | D89: SNR RESEARCH FELLOW | E89: 15(8) | F89: =32263.2 -> 32263.2 | H89: =F89*300% -> 96789.6 | I89: =F89*7.5% -> 2419.74 | J89: =40122.19 -> 40122.19 | K89: =F89*50% -> 16131.6 | L89: =F89*350% -> 112921.2 | M89: =F89*100% -> 32263.2 | N89: =100000 -> 100000 | O89: =F89*10% -> 3226.32 | P89: 20000 | R89: =SUM(F89:Q89) -> 456137.05 | S89: =20000 -> 20000 | T89: =68750 -> 68750 | U89: ='[2]Jan 2021'!$H$38 -> 806.58 | V89: =15548.33 -> 15548.33 | W89: =SUM(S89:V89) -> 105104.91 | X89: 351032.14 | Y89: =R89-W89 -> 351032.14 | Z89: =160000 -> 160000 | AA89: =Z89-N89 -> 60000
A90: 4 | B90: JUMARE FADILA | D90: RESEARCH FELLOW I | E90: 14(8) | F90: =25854.1 -> 25854.1 | H90: =F90*300% -> 77562.3 | I90: =F90*7.5% -> 1939.0575 | J90: 0 | K90: =F90*50% -> 12927.05 | L90: =F90*350% -> 90489.35 | M90: =F90*100% -> 25854.1 | N90: =100000 -> 100000 | O90: =F90*10% -> 2585.41 | P90: 20000 | Q90: 0 | R90: =SUM(F90:Q90) -> 357211.37 | S90: 5000 | V90: =7709.76 -> 7709.76 | W90: =SUM(S90:V90) -> 12709.76 | X90: 344501.61 | Y90: =R90-W90 -> 344501.61 | Z90: 140000 | AA90: =Z90-N90 -> 40000
A91: 5 | B91: NGARA CHRISTOPHER OCHANJA | D91: RESEARCH FELLOW 1 | E91: 14(9) | F91: =26732.65 -> 26732.65 | H91: =F91*300% -> 80197.95 | I91: =F91*7.5% -> 2004.9488 | K91: =F91*50% -> 13366.325 | L91: =F91*350% -> 93564.275 | M91: =F91*100% -> 26732.65 | N91: =100000 -> 100000 | O91: =F91*10% -> 2673.265 | P91: 20000 | Q91: 0 | R91: =SUM(F91:Q91) -> 365272.06 | S91: =20000 -> 20000 | T91: =163103.59 -> 163103.59 | U91: ='[2]Jan 2021'!$H$46 -> 668.31625 | V91: =7709.76 -> 7709.76 | W91: =S91+T91+U91+V91 -> 191481.67 | X91: 173790.4 | Y91: =R91-W91 -> 173790.4 | Z91: 140000 | AA91: =Z91-N91 -> 40000
A92: 6 | B92: OMOJU OLUWASOLA EMMANUEL | D92: RESEARCH FELLOW I | E92: 14(8) | F92: =25854.1 -> 25854.1 | H92: =F92*300% -> 77562.3 | I92: =F92*7.5% -> 1939.0575 | K92: =F92*50% -> 12927.05 | L92: =F92*350% -> 90489.35 | M92: =F92*100% -> 25854.1 | N92: =100000 -> 100000 | O92: =F92*10% -> 2585.41 | P92: 20000 | R92: =SUM(F92:Q92) -> 357211.37 | S92: =50000 -> 50000 | T92: =87500 -> 87500 | V92: =7709.76 -> 7709.76 | W92: =SUM(S92:V92) -> 145209.76 | X92: 212001.61 | Y92: =R92-W92 -> 212001.61 | Z92: 140000 | AA92: =Z92-N92 -> 40000
A93: 7 | B93: ONYIMADU C. ONYEBUCHI | D93: RESEARCH FELLOW I | E93: 14(8) | F93: =25854.1 -> 25854.1 | H93: =F93*300% -> 77562.3 | I93: =F93*7.5% -> 1939.0575 | K93: =F93*50% -> 12927.05 | L93: =F93*350% -> 90489.35 | M93: =F93*100% -> 25854.1 | N93: =100000 -> 100000 | O93: =F93*10% -> 2585.41 | P93: 20000 | R93: =SUM(F93:Q93) -> 357211.37 | S93: =50000 -> 50000 | U93: ='[2]Jan 2021'!$H$50 -> 646.3525 | V93: 7709.76 | W93: =SUM(S93:V93) -> 58356.113 | X93: 298855.26 | Y93: =R93-W93 -> 298855.26 | Z93: 140000 | AA93: =Z93-N93 -> 40000
A94: 8 | B94: RIFKATU NGHARGBU | D94: RESEARCH FELLOW 1 | E94: 14(7) | F94: =24975.81 -> 24975.81 | H94: =F94*300% -> 74927.43 | I94: =F94*7.5% -> 1873.1858 | J94: 0 | K94: =F94*50% -> 12487.905 | L94: =F94*350% -> 87415.335 | M94: =F94*100% -> 24975.81 | N94: =100000 -> 100000 | O94: =F94*10% -> 2497.581 | P94: 20000 | Q94: 0 | R94: =SUM(F94:Q94) -> 349153.06 | S94: =100000 -> 100000 | T94: =68666.67 -> 68666.67 | V94: =7709.76 -> 7709.76 | W94: =SUM(S94:V94) -> 176376.43 | X94: 172776.63 | Y94: =R94-W94 -> 172776.63 | Z94: 140000 | AA94: =Z94-N94 -> 40000
A95: 9 | B95: IBE EZECHI CYRIACUS | D95: RESEARCH FELLOW II | E95: 13(8) | F95: =23891.12 -> 23891.12 | H95: =F95*300% -> 71673.36 | I95: =F95*7.5% -> 1791.834 | J95: 0 | K95: =F95*50% -> 11945.56 | L95: =F95*350% -> 83618.92 | M95: =F95*100% -> 23891.12 | N95: =100000 -> 100000 | O95: =F95*10% -> 2389.112 | P95: 15000 | Q95: 0 | R95: =SUM(F95:Q95) -> 334201.03 | S95: =50000 -> 50000 | V95: =7709.76 -> 7709.76 | W95: =SUM(S95:V95) -> 57709.76 | X95: 276491.27 | Y95: =R95-W95 -> 276491.27 | Z95: =120000 -> 120000 | AA95: =Z95-N95 -> 20000
A96: 10 | B96: OSIKHEN LEO IGBANOI | D96: RESEARCH FELLOW 11 | E96: 13(7) | F96: =23074.99 -> 23074.99 | H96: =F96*300% -> 69224.97 | I96: =F96*7.5% -> 1730.6243 | J96: 0 | K96: =F96*50% -> 11537.495 | L96: =F96*350% -> 80762.465 | M96: =F96*100% -> 23074.99 | N96: =100000 -> 100000 | O96: =F96*10% -> 2307.499 | P96: 15000 | Q96: 0 | R96: =SUM(F96:Q96) -> 326713.03 | S96: =25000 -> 25000 | T96: =94262.15 -> 94262.15 | V96: =7709.76 -> 7709.76 | W96: =SUM(S96:V96) -> 126971.91 | X96: 199741.12 | Y96: =R96-W96 -> 199741.12 | Z96: =120000 -> 120000 | AA96: =Z96-N96 -> 20000
A97: 11 | B97: OKUNGBOWA OSARETIN GODSPOWER | D97: RESEARCH FELLOW 11 | E97: 13(7) | F97: =23074.99 -> 23074.99 | H97: =F97*300% -> 69224.97 | I97: =F97*7.5% -> 1730.6243 | J97: 0 | K97: =F97*50% -> 11537.495 | L97: =F97*350% -> 80762.465 | M97: =F97*100% -> 23074.99 | N97: =100000 -> 100000 | O97: =F97*10% -> 2307.499 | P97: 15000 | Q97: 0 | R97: =SUM(F97:Q97) -> 326713.03 | S97: =70000 -> 70000 | V97: =7709.76 -> 7709.76 | W97: =SUM(S97:V97) -> 77709.76 | X97: 249003.27 | Y97: =R97-W97 -> 249003.27 | Z97: =120000 -> 120000 | AA97: =Z97-N97 -> 20000
B98: TOTAL | D98: 11 | F98: =SUM(F87:F97) -> 303500.51 | H98: =SUM(H87:H97) -> 910501.53 | I98: =SUM(I87:I97) -> 22762.538 | J98: =SUM(J87:J97) -> 120366.57 | K98: =SUM(K87:K97) -> 151750.26 | L98: =SUM(L87:L97) -> 1062251.8 | M98: =SUM(M87:M97) -> 303500.51 | N98: =SUM(N87:N97) -> 1100000 | O98: =SUM(O87:O97) -> 30350.051 | ... W98: =SUM(W87:W97) -> 988796.49 | X98: 3398523.9 | Y98: =SUM(Y87:Y97) -> 3221187.3 | Z98: =SUM(Z87:Z97) -> 1560000 | AA98: =SUM(AA87:AA97) -> 460000
B100: TRAINING AND INTERNATIONAL COOP
A101: 1 | B101: DR FRANCIS NDUM OJIE | D101: ASST. MANAGER, TRAINING | E101: 14(8) | F101: =25854.1 -> 25854.1 | H101: =F101*300% -> 77562.3 | I101: =F101*7.5% -> 1939.0575 | K101: =F101*50% -> 12927.05 | L101: =F101*350% -> 90489.35 | M101: =F101*100% -> 25854.1 | N101: 100000 | O101: =F101*10% -> 2585.41 | P101: 20000 | R101: =SUM(F101:Q101) -> 357211.37 | U101: =646.35 -> 646.35 | V101: =7709.76 -> 7709.76 | W101: =SUM(S101:V101) -> 8356.11 | X101: 348855.26 | Y101: =R101-W101 -> 348855.26 | Z101: =70000 -> 70000 | AA101: =Z101-N101 -> -30000
A102: 2 | B102: OKECHUKWU UCHENNA HULDA | D102: TRAINING OFFICER | E102: 10(9) | F102: =18281.64 -> 18281.64 | H102: =F102*300% -> 54844.92 | I102: =F102*7.5% -> 1371.123 | K102: =F102*50% -> 9140.82 | L102: =F102*350% -> 63985.74 | M102: =F102*100% -> 18281.64 | N102: =100000 -> 100000 | O102: =F102*10% -> 1828.164 | P102: 10000 | R102: =SUM(F102:Q102) -> 277734.05 | S102: =5000 -> 5000 | T102: =0 -> 0 | V102: 3369.51 | W102: =SUM(S102:V102) -> 8369.51 | X102: 269364.54 | Y102: =R102-W102 -> 269364.54 | Z102: =60000 -> 60000 | AA102: =Z102-N102 -> -40000
B103: TOTAL | D103: 2 | F103: =SUM(F101:F102) -> 44135.74 | H103: =SUM(H101:H102) -> 132407.22 | I103: =SUM(I101:I102) -> 3310.1805 | J103: =SUM(J101:J102) -> 0 | K103: =SUM(K101:K102) -> 22067.87 | L103: =SUM(L101:L102) -> 154475.09 | M103: =SUM(M101:M102) -> 44135.74 | N103: =SUM(N101:N102) -> 200000 | O103: =SUM(O101:O102) -> 4413.574 | ... W103: =SUM(W101:W102) -> 16725.62 | X103: 1259979.1 | Y103: =SUM(Y101:Y102) -> 618219.79 | Z103: =SUM(Z101:Z102) -> 130000 | AA103: =SUM(AA101:AA102) -> -70000
B105: LIBRARY AND DOCUMENTATION
A106: 1 | B106: DR MAIMUNA IZAH | D106: INSITUTE LIBRARIAN | E106: 17(8) | F106: =79039.64 -> 79039.64 | H106: =F106*300% -> 237118.92 | I106: =F106*7.5% -> 5927.973 | J106: 80244.38 | K106: =F106*50% -> 39519.82 | L106: =F106*350% -> 276638.74 | M106: =F106*100% -> 79039.64 | N106: =100000 -> 100000 | O106: =F106*10% -> 7903.964 | P106: 20000 | Q106: 0 | R106: =SUM(F106:Q106) -> 925433.08 | S106: =100000 -> 100000 | T106: 0 | U106: 0 | V106: =52776.63 -> 52776.63 | W106: =SUM(S106:V106) -> 152776.63 | X106: 772656.45 | Y106: =R106-W106 -> 772656.45 | Z106: =200000 -> 200000 | AA106: =Z106-N106 -> 100000
A107: 2 | B107: CATHERINE E. IKOKOH | D107: SNR RESEARCH FELLOW DOCU | E107: 15(9) | F107: =33507.5 -> 33507.5 | H107: =F107*300% -> 100522.5 | I107: =F107*7.5% -> 2513.0625 | J107: 40122.19 | K107: =F107*50% -> 16753.75 | L107: =F107*350% -> 117276.25 | M107: =F107*100% -> 33507.5 | N107: =100000 -> 100000 | O107: =F107*10% -> 3350.75 | P107: 20000 | Q107: 0 | R107: =SUM(F107:Q107) -> 467553.5 | S107: 40000 | T107: =131250 -> 131250 | U107: ='[2]Jan 2021'!$H$33 -> 837.6875 | V107: 15548.33 | W107: =SUM(S107:V107) -> 187636.02 | X107: 279917.48 | Y107: =R107-W107 -> 279917.48 | Z107: =160000 -> 160000 | AA107: =Z107-N107 -> 60000
A108: 3 | B108: ALIYU SANNI ABUBAKAR | D108: RESEARCH FELLOW 11 DATA & DOCU | E108: 13(11) | F108: =26339.3 -> 26339.3 | H108: =F108*300% -> 79017.9 | I108: =F108*7.5% -> 1975.4475 | J108: 0 | K108: =F108*50% -> 13169.65 | L108: =F108*350% -> 92187.55 | M108: =F108*100% -> 26339.3 | N108: =100000 -> 100000 | O108: =F108*10% -> 2633.93 | P108: 15000 | Q108: 0 | R108: =SUM(F108:Q108) -> 356663.08 | S108: 30000 | T108: =0 -> 0 | U108: ='[2]Jan 2021'!$H$36 -> 658.4825 | V108: =7709.76 -> 7709.76 | W108: =SUM(S108:V108) -> 38368.243 | X108: 318294.83 | Y108: =R108-W108 -> 318294.83 | Z108: =120000 -> 120000 | AA108: =Z108-N108 -> 20000
A109: 4 | B109: CHINAKO N. ASOGWA | D109: RESEARCH FELLOW 11 DATA & DOCU | E109: 13(9) | F109: =24741.26 -> 24741.26 | H109: =F109*300% -> 74223.78 | I109: =F109*7.5% -> 1855.5945 | J109: 0 | K109: =F109*50% -> 12370.63 | L109: =F109*350% -> 86594.41 | M109: =F109*100% -> 24741.26 | N109: =100000 -> 100000 | O109: =F109*10% -> 2474.126 | P109: 15000 | R109: =SUM(F109:Q109) -> 342001.06 | S109: =50000 -> 50000 | T109: =68750 -> 68750 | V109: =7709.76 -> 7709.76 | W109: =SUM(S109:V109) -> 126459.76 | X109: 215541.3 | Y109: =R109-W109 -> 215541.3 | Z109: =120000 -> 120000 | AA109: =Z109-N109 -> 20000
A110: 5 | B110: TITILAYO DANIEL MARVELLOUS | D110: LIBRARY ASSISTANT | E110: 8(8) | F110: =12732 -> 12732 | H110: =F110*300% -> 38196 | I110: =F110*7.5% -> 954.9 | K110: =F110*50% -> 6366 | L110: =F110*350% -> 44562 | M110: =F110*100% -> 12732 | N110: =100000 -> 100000 | O110: =F110*10% -> 1273.2 | P110: 10000 | R110: =SUM(F110:Q110) -> 226816.1 | S110: =25000 -> 25000 | T110: 0 | V110: =1235.19 -> 1235.19 | W110: =SUM(S110:V110) -> 26235.19 | X110: 200580.91 | Y110: =R110-W110 -> 200580.91 | Z110: =100000 -> 100000 | AA110: =Z110-N110 -> 0
...

Sheet Welfare 2
B3: WELFARE FOR JULY, 2021
F4: ='[1]FEB 08'!E8/'[1]FEB 08'!M8 -> 0.22 | I4: ='[1]FEB 08'!F8/'[1]FEB 08'!Q8 -> 0.3
B5: STAFF NAME | S5: DEDUCTIONS | Y5: WELFARE
D6: DESIGNATION | E6: SALARY | F6: BASIC | M6: MOTOR/ | N6: RESEARCH | O6: LEAVE | P6: OUT FIT | Q6: LEGISLATIVE | R6: GROSS | X6: JUNE,2021 | Y6: JULY,2021
E7: LEVEL | F7: SALARY | G7: SALARY/ALLOWCE AREARS | H7: RENT | I7: UTILITY | J7: DOMESTIC | K7: ENTERT. | L7: FURNIT. | M7: FUEL | N7: ALLOWANCE | O7: ALLCE | P7: ALLCE | Q7: DUTY ALLCE | R7: SALARY | S7: COOP SOCIETY | T7: COOP. LOAN RECOVERY | U7: NHF DEDUCTION | V7: PAYE | W7: TOTAL
A8: S/N | B8: DG OFFICE | F8: N | I8: N | R8: N | V8: N
A9: 1 | B9: PROF. ABUBAKAR O. SULAIMAN | D9: DIRECTOR GENERAL | E9: CONSOL | F9: 160488.75 | H9: 320977.5 | I9: 48146.63 | J9: 120366.57 | K9: 72219.94 | L9: 0 | M9: 120366.57 | N9: =100000 -> 100000 | O9: 16048.88 | P9: 25000 | Q9: 25235 | R9: =SUM(F9:Q9) -> 1008849.8 | V9: 113176.97 | W9: =S9+T9+U9+V9 -> 113176.97 | X9: 895672.87 | Y9: =300000 -> 300000
A10: 2 | B10: DR ADEYEMI AKEEB FAJINGBESI | D10: DIR. SPECIAL DUTIES, DG OFFICE | E10: 17(9) | F10: 81740.02 | H10: =F10*300% -> 245220.06 | I10: =F10*7.5% -> 6130.5015 | J10: 80244.38 | K10: =F10*50% -> 40870.01 | L10: =F10*350% -> 286090.07 | M10: =F10*100% -> 81740.02 | N10: =100000 -> 100000 | O10: =F10*10% -> 8174.002 | P10: 20000 | Q10: 0 | R10: =SUM(F10:Q10) -> 950209.06 | S10: 200000 | T10: =59722.22 -> 59722.22 | U10: ='[2]Jan 2021'!$H$35 -> 2043.5005 | V10: 52776.63 | W10: =SUM(S10:V10) -> 314542.35 | X10: 635666.71 | Y10: =150000 -> 150000
A11: 3 | B11: SARAFADEEN ALABELEWE | D11: SA ADMINISTRATION | E11: 16(9) | F11: =42653.17 -> 42653.17 | H11: =F11*300% -> 127959.51 | I11: =F11*7.5% -> 3198.9877 | J11: 40122.19 | K11: =F11*50% -> 21326.585 | L11: =F11*350% -> 149286.1 | M11: =F11*100% -> 42653.17 | O11: =F11*10% -> 4265.317 | P11: 20000 | R11: =SUM(F11:Q11) -> 451465.02 | S11: =100000 -> 100000 | T11: =137500 -> 137500 | V11: 21618.09 | W11: =S11+T11+U11+V11 -> 259118.09 | X11: 192346.93 | Y11: =70000 -> 70000
A12: 4 | B12: DR JAKE DABANG DAN AZUMI | D12: DEPUTY DIRECTOR TRAINING | E12: 16(7) | F12: =39662.25 -> 39662.25 | H12: =F12*300% -> 118986.75 | I12: =F12*7.5% -> 2974.6687 | J12: 40122.19 | K12: =F12*50% -> 19831.125 | L12: =F12*350% -> 138817.88 | M12: =F12*100% -> 39662.25 | N12: =100000 -> 100000 | O12: =F12*10% -> 3966.225 | P12: 20000 | Q12: 150000 | R12: =SUM(F12:Q12) -> 674023.33 | U12: ='[2]Jan 2021'!$H$27 -> 991.55625 | V12: =21618.09 -> 21618.09 | W12: =SUM(S12:V12) -> 22609.646 | X12: 651413.69 | Y12: =70000 -> 70000
A13: 5 | B13: DR ABDULSALAM NASIRU NAEEM | D13: SA ACADEMICS | E13: 16(7) | F13: =39662.25 -> 39662.25 | H13: =F13*300% -> 118986.75 | I13: =F13*7.5% -> 2974.6687 | J13: 40122.19 | K13: =F13*50% -> 19831.125 | L13: =F13*350% -> 138817.88 | M13: =F13*100% -> 39662.25 | N13: =100000 -> 100000 | O13: =F13*10% -> 3966.225 | P13: 20000 | Q13: =100000 -> 100000 | R13: =SUM(F13:Q13) -> 624023.33 | V13: =21618.09 -> 21618.09 | W13: =S13+T13+U13+V13 -> 21618.09 | X13: 602405.24 | Y13: =70000 -> 70000
A14: 6 | B14: RAHEEM USMAN AYIGORO | D14: SA-INFRASTRUCTURE | E14: 16 (7) | F14: =39662.25 -> 39662.25 | H14: =F14*300% -> 118986.75 | I14: =F14*7.5% -> 2974.6687 | J14: 40122.19 | K14: =F14*50% -> 19831.125 | L14: =F14*350% -> 138817.88 | M14: =F14*100% -> 39662.25 | O14: =F14*10% -> 3966.225 | P14: 20000 | Q14: 0 | R14: =SUM(F14:Q14) -> 424023.33 | V14: =21618.09 -> 21618.09 | W14: =S14+T14+U14+V14 -> 21618.09 | X14: 402405.24 | Y14: =70000 -> 70000
A15: 7 | B15: AKINSANMI ADEJOKE OLUKEMI | D15: HEAD INFORMATION/PROTOCOL | E15: 15(9) | F15: 33507.5 | H15: =F15*300% -> 100522.5 | I15: =F15*7.5% -> 2513.0625 | J15: 40122.19 | K15: =F15*50% -> 16753.75 | L15: =F15*350% -> 117276.25 | M15: =F15*100% -> 33507.5 | O15: =F15*10% -> 3350.75 | P15: 20000 | Q15: =100000 -> 100000 | R15: =SUM(F15:Q15) -> 467553.5 | S15: =0 -> 0 | T15: 0 | U15: =837.69 -> 837.69 | V15: 15548.33 | W15: =S15+T15+U15+V15 -> 16386.02 | X15: 451167.48 | Y15: =70000 -> 70000
A16: 8 | B16: DR IKEME ARTHUR J.O | D16: SNR RESEARCH FELLOW | E16: 15(9) | F16: =33507.5 -> 33507.5 | H16: =F16*300% -> 100522.5 | I16: =F16*7.5% -> 2513.0625 | J16: 40122.19 | K16: =F16*50% -> 16753.75 | L16: =F16*350% -> 117276.25 | M16: =F16*100% -> 33507.5 | N16: =100000 -> 100000 | O16: =F16*10% -> 3350.75 | P16: 20000 | Q16: 0 | R16: =SUM(F16:Q16) -> 467553.5 | S16: 50000 | T16: =212642 -> 212642 | U16: ='[3]DECEMBER 2019'!$H$38 -> 837.6875 | V16: 15548.33 | W16: =SUM(S16:V16) -> 279028.02 | X16: 188525.48 | Y16: =70000 -> 70000
A17: 9 | B17: MOSHOOD M. OLALERE | D17: MANAGER ADMIN DG's OFFICE | E17: 15(9) | F17: =33507.5 -> 33507.5 | H17: =F17*300% -> 100522.5 | I17: =F17*7.5% -> 2513.0625 | J17: 40122.19 | K17: =F17*50% -> 16753.75 | L17: =F17*350% -> 117276.25 | M17: =F17*100% -> 33507.5 | O17: =F17*10% -> 3350.75 | P17: 20000 | Q17: 0 | R17: =SUM(F17:Q17) -> 367553.5 | S17: =5000 -> 5000 | T17: =179017.51 -> 179017.51 | U17: ='[3]DECEMBER 2019'!$H$35 -> 837.6875 | V17: 15548.33 | W17: =S17+T17+U17+V17 -> 200403.53 | X17: 167149.98 | Y17: =70000 -> 70000
A18: 10 | B18: AYOBOLU OLAJIDE OLUFUNSHO | D18: MANAGER, INFORMATION | E18: 15 (7) | F18: 31018.84 | H18: =F18*300% -> 93056.52 | I18: =F18*7.5% -> 2326.413 | J18: 40122.19 | K18: =F18*50% -> 15509.42 | L18: =F18*350% -> 108565.94 | M18: =F18*100% -> 31018.84 | O18: =F18*10% -> 3101.884 | P18: 20000 | Q18: 0 | R18: =SUM(F18:Q18) -> 344720.05 | S18: =25000 -> 25000 | T18: =52500 -> 52500 | V18: 15548.33 | W18: =S18+T18+U18+V18 -> 93048.33 | X18: 251671.72 | Y18: =70000 -> 70000
A19: 11 | B19: HUSSEIN EGYE MUSA | D19: AM PROTOCOL | E19: 13(10) | F19: =25523.45 -> 25523.45 | H19: =F19*300% -> 76570.35 | I19: =F19*7.5% -> 1914.2587 | K19: =F19*50% -> 12761.725 | L19: =F19*350% -> 89332.075 | M19: =F19*100% -> 25523.45 | O19: =F19*10% -> 2552.345 | P19: 15000 | Q19: 50000 | R19: =SUM(F19:Q19) -> 299177.65 | S19: 50000 | T19: =0 -> 0 | U19: 0 | V19: 7709.76 | W19: =S19+T19+U19+V19 -> 57709.76 | X19: 241467.89 | Y19: 50000
A20: 12 | B20: DONALD E. MKPANAM | D20: AM ICT | E20: 13(11) | F20: 26339.3 | H20: =F20*300% -> 79017.9 | I20: =F20*7.5% -> 1975.4475 | K20: =F20*50% -> 13169.65 | L20: =F20*350% -> 92187.55 | M20: =F20*100% -> 26339.3 | N20: =100000 -> 100000 | O20: =F20*10% -> 2633.93 | P20: 15000 | Q20: 0 | R20: =SUM(F20:Q20) -> 356663.08 | U20: ='[2]Jan 2021'!$H$28 -> 658.4825 | V20: 7709.76 | W20: =S20+T20+U20+V20 -> 8368.2425 | X20: 348294.83 | Y20: 50000
A21: 13 | B21: JOY HARUNA MAKERI | D21: AM TRAINING | E21: 13(10) | F21: =25523.45 -> 25523.45 | H21: =F21*300% -> 76570.35 | I21: =F21*7.5% -> 1914.2587 | K21: =F21*50% -> 12761.725 | L21: =F21*350% -> 89332.075 | M21: =F21*100% -> 25523.45 | N21: 100000 | O21: =F21*10% -> 2552.345 | P21: 15000 | Q21: =50000+100000 -> 150000 | R21: =SUM(F21:Q21) -> 499177.65 | V21: =7709.76 -> 7709.76 | W21: =SUM(S21:V21) -> 7709.76 | X21: 491467.89 | Y21: 50000
A22: 14 | B22: ALI ABDULLAHI | D22: AM ICT | E22: 13(11) | F22: =26339.3 -> 26339.3 | H22: =F22*300% -> 79017.9 | I22: =F22*7.5% -> 1975.4475 | J22: 0 | K22: =F22*50% -> 13169.65 | L22: =F22*350% -> 92187.55 | M22: =F22*100% -> 26339.3 | N22: =100000 -> 100000 | O22: =F22*10% -> 2633.93 | P22: 15000 | Q22: =0 -> 0 | R22: =SUM(F22:Q22) -> 356663.08 | V22: =7709.76 -> 7709.76 | W22: =S22+T22+U22+V22 -> 7709.76 | X22: 348953.32 | Y22: 50000
A23: 15 | B23: MARIAM MOHAMMED BELLO | D23: PA- SPECIAL DUTIES | E23: 13 (7) | F23: =23074.99 -> 23074.99 | H23: =F23*300% -> 69224.97 | I23: =F23*7.5% -> 1730.6243 | J23: 0 | K23: =F23*50% -> 11537.495 | L23: =F23*350% -> 80762.465 | M23: =F23*100% -> 23074.99 | N23: =100000+100000+100000 -> 300000 | O23: =F23*10% -> 2307.499 | P23: 15000 | Q23: =100000 -> 100000 | R23: =SUM(F23:Q23) -> 626713.03 | V23: =7709.76 -> 7709.76 | W23: =S23+T23+U23+V23 -> 7709.76 | X23: 319003.27 | Y23: 50000
A24: 16 | B24: ADUGBA RICHARD TERSEER | D24: INFORMATION OFFICER | E24: 10(9) | F24: =18281.64 -> 18281.64 | H24: =F24*300% -> 54844.92 | I24: =F24*7.5% -> 1371.123 | K24: =F24*50% -> 9140.82 | L24: =F24*350% -> 63985.74 | M24: =F24*100% -> 18281.64 | O24: =F24*10% -> 1828.164 | P24: 10000 | R24: =SUM(F24:Q24) -> 177734.05 | S24: =20000 -> 20000 | T24: =111833.33 -> 111833.33 | V24: 3369.51 | W24: =S24+T24+U24+V24 -> 135202.84 | X24: 42531.207 | Y24: 30000
A25: 17 | B25: CHRISTIAN MADUABUCHI ODO | D25: ICT OFFICER | E25: 10(11) | F25: =19276.95 -> 19276.95 | H25: =F25*300% -> 57830.85 | I25: =F25*7.5% -> 1445.7713 | K25: =F25*50% -> 9638.475 | L25: =F25*350% -> 67469.325 | M25: =F25*100% -> 19276.95 | N25: =100000 -> 100000 | O25: =F25*10% -> 1927.695 | P25: 10000 | R25: =SUM(F25:Q25) -> 286866.02 | S25: =20000 -> 20000 | T25: =82500 -> 82500 | U25: ='[2]Jan 2021'!$H$47 -> 481.92375 | V25: 3369.51 | W25: =S25+T25+U25+V25 -> 106351.43 | X25: 180514.58 | Y25: 30000
A26: 18 | B26: VICTOR ASUKWO | D26: ICT OFFICER | E26: 8 (9) | F26: =13112.16 -> 13112.16 | H26: =F26*300% -> 39336.48 | I26: =F26*7.5% -> 983.412 | K26: =F26*50% -> 6556.08 | L26: =F26*350% -> 45892.56 | M26: =F26*100% -> 13112.16 | N26: =100000 -> 100000 | O26: =F26*10% -> 1311.216 | P26: 10000 | R26: =SUM(F26:Q26) -> 230304.07 | S26: =10000 -> 10000 | V26: 1484.37 | W26: =S26+T26+U26+V26 -> 11484.37 | X26: 218819.7 | Y26: 30000
A27: 19 | B27: SULEIMAN ABUBAKAR SODEEQ | D27: ASST. ADMIN. OFFICER | E27: 8(7) | F27: =12351.94 -> 12351.94 | H27: =F27*300% -> 37055.82 | I27: =F27*7.5% -> 926.3955 | K27: =F27*50% -> 6175.97 | L27: =F27*350% -> 43231.79 | M27: =F27*100% -> 12351.94 | O27: =F27*10% -> 1235.194 | P27: 10000 | R27: =SUM(F27:Q27) -> 123329.05 | V27: =1235.19 -> 1235.19 | W27: =SUM(S27:V27) -> 1235.19 | X27: 122093.86 | Y27: 30000
A28: 20 | B28: YAKUB OLUWATOYIN USMAN | D28: ASST. ADMIN. OFFICER | E28: 8(7) | F28: =12351.94 -> 12351.94 | H28: =F28*300% -> 37055.82 | I28: =F28*7.5% -> 926.3955 | K28: =F28*50% -> 6175.97 | L28: =F28*350% -> 43231.79 | M28: =F28*100% -> 12351.94 | O28: =F28*10% -> 1235.194 | P28: 10000 | R28: =SUM(F28:Q28) -> 123329.05 | S28: =10000 -> 10000 | V28: =1235.19 -> 1235.19 | W28: =SUM(S28:V28) -> 11235.19 | X28: 112093.86 | Y28: 30000
A29: 21 | B29: ANTHONY EDET | D29: ASST. MGR M&E | E29: 13(8) | F29: =23891.12 -> 23891.12 | H29: =F29*300% -> 71673.36 | I29: =F29*7.5% -> 1791.834 | J29: 0 | K29: =F29*50% -> 11945.56 | L29: =F29*350% -> 83618.92 | M29: =F29*100% -> 23891.12 | N29: =100000 -> 100000 | O29: =F29*10% -> 2389.112 | P29: 15000 | Q29: 0 | R29: =SUM(F29:Q29) -> 334201.03 | S29: 20000 | U29: ='[2]Jan 2021'!$H$39 -> 597.278 | V29: =7709.76 -> 7709.76 | W29: =SUM(S29:V29) -> 28307.038 | X29: 305893.99 | Y29: 50000
A30: 22 | B30: EGUATU U. ONYEJELEM | D30: OFFICER M&E | E30: 10(9) | F30: =18281.64 -> 18281.64 | H30: =F30*300% -> 54844.92 | I30: =F30*7.5% -> 1371.123 | K30: =F30*50% -> 9140.82 | L30: =F30*350% -> 63985.74 | M30: =F30*100% -> 18281.64 | N30: =100000 -> 100000 | O30: =F30*10% -> 1828.164 | P30: 10000 | R30: =SUM(F30:Q30) -> 277734.05 | S30: =20000 -> 20000 | T30: =87500+43750 -> 131250 | V30: 3369.51 | W30: =SUM(S30:V30) -> 154619.51 | X30: 123114.54 | Y30: 30000
A31: 23 | B31: ODEH SUZIE | D31: ADMIN. OFFICER, LIASION OFFICE | E31: 10(8) | F31: =17784 -> 17784 | H31: =F31*300% -> 53352 | I31: =F31*7.5% -> 1333.8 | K31: =F31*50% -> 8892 | L31: =F31*350% -> 62244 | M31: =F31*100% -> 17784 | O31: =F31*10% -> 1778.4 | P31: 10000 | R31: =SUM(F31:Q31) -> 173168.2 | S31: =30000 -> 30000 | U31: =0 -> 0 | V31: 3369.51 | W31: =S31+T31+U31+V31 -> 33369.51 | X31: 139798.69 | Y31: 30000
A32: 24 | B32: TESSNEEM IBRAHIM | D32: ASSIST. INFORMATION | E32: 8(8) | F32: =12732 -> 12732 | H32: =F32*300% -> 38196 | I32: =F32*7.5% -> 954.9 | K32: =F32*50% -> 6366 | L32: =F32*350% -> 44562 | M32: =F32*100% -> 12732 | O32: =F32*10% -> 1273.2 | P32: 10000 | R32: =SUM(F32:Q32) -> 126816.1 | S32: =50000 -> 50000 | T32: =40000 -> 40000 | U32: =0 -> 0 | V32: =1235.19 -> 1235.19 | W32: =S32+T32+U32+V32 -> 91235.19 | X32: 35580.91 | Y32: 30000
B33: TOTAL | D33: 24 | F33: =SUM(F9:F32) -> 810273.91 | H33: =SUM(H9:H32) -> 2270333 | I33: =SUM(I9:I32) -> 96880.517 | J33: =SUM(J9:J32) -> 521588.47 | K33: =SUM(K9:K32) -> 397112.52 | L33: =SUM(L9:L32) -> 2274248.1 | M33: =SUM(M9:M32) -> 770151.73 | N33: =SUM(N9:N32) -> 1500000 | O33: =SUM(O9:O32) -> 81027.396 | ... W33: =SUM(W9:W32) -> 2003796.7 | X33: 7468053.9 | Y33: =SUM(Y9:Y32) -> 1550000
B35: INTERNAL AUDIT
A36: 1 | B36: NWOSU MATHEW EZE | D36: Ag. DIRECTOR INT. AUDIT | E36: 17(8) | F36: =79039.64 -> 79039.64 | H36: =F36*300% -> 237118.92 | I36: =F36*7.5% -> 5927.973 | J36: =80244.38 -> 80244.38 | K36: =F36*50% -> 39519.82 | L36: =F36*350% -> 276638.74 | M36: =F36*100% -> 79039.64 | O36: =F36*10% -> 7903.964 | P36: 20000 | Q36: 0 | R36: =SUM(F36:Q36) -> 825433.08 | S36: =100000 -> 100000 | T36: =287500 -> 287500 | U36: ='[2]Jan 2021'!$H$23 -> 1975.991 | V36: =52776.63 -> 52776.63 | W36: =S36+T36+U36+V36 -> 442252.62 | X36: 383180.46 | Y36: 150000
C37: TOTAL | D37: 1 | F37: =SUM(F36:F36) -> 79039.64 | H37: =SUM(H36:H36) -> 237118.92 | I37: =SUM(I36:I36) -> 5927.973 | J37: =SUM(J36:J36) -> 80244.38 | K37: =SUM(K36:K36) -> 39519.82 | L37: =SUM(L36:L36) -> 276638.74 | M37: =SUM(M36:M36) -> 79039.64 | N37: =SUM(N36:N36) -> 0 | O37: =SUM(O36:O36) -> 7903.964 | ... W37: =SUM(W36:W36) -> 442252.62 | X37: 383180.46 | Y37: =SUM(Y36:Y36) -> 150000
B39: LEG. SUPPORT SEVICES
A40: 1 | B40: PROF. EDOBA BRIGHT OMOREGBE | D40: AG. DLSS | E40: 17(9) | F40: =81740.02 -> 81740.02 | H40: =F40*300% -> 245220.06 | I40: =F40*7.5% -> 6130.5015 | J40: 80244.38 | K40: =F40*50% -> 40870.01 | L40: =F40*350% -> 286090.07 | M40: =F40*100% -> 81740.02 | N40: 100000 | O40: =F40*10% -> 8174.002 | P40: 20000 | R40: =SUM(F40:Q40) -> 950209.06 | S40: =100000 -> 100000 | V40: =52776.63 -> 52776.63 | W40: =V40+S40+T40+U40 -> 152776.63 | X40: 797432.43 | Y40: 150000
A41: 2 | B41: DR CLINTON JAJA | D41: SENIOR RESEARCH FELLOW | E41: 15(9) | F41: =33507.5 -> 33507.5 | H41: =F41*300% -> 100522.5 | I41: =F41*7.5% -> 2513.0625 | J41: 40122.19 | K41: =F41*50% -> 16753.75 | L41: =F41*350% -> 117276.25 | M41: =F41*100% -> 33507.5 | N41: 100000 | O41: =F41*10% -> 3350.75 | P41: 20000 | Q41: 0 | R41: =SUM(F41:Q41) -> 467553.5 | S41: 50000 | T41: =240909.11 -> 240909.11 | V41: 15548.33 | W41: =SUM(S41:V41) -> 306457.44 | X41: 161096.06 | Y41: =70000 -> 70000
A42: 3 | B42: BETHEL UZOMA IHUGBA | D42: SNR RESEARCH FELLOW | E42: 15(9) | F42: =33507.5 -> 33507.5 | H42: =F42*300% -> 100522.5 | I42: =F42*7.5% -> 2513.0625 | J42: 40122.19 | K42: =F42*50% -> 16753.75 | L42: =F42*350% -> 117276.25 | M42: =F42*100% -> 33507.5 | N42: 100000 | O42: =F42*10% -> 3350.75 | P42: 20000 | R42: =SUM(F42:Q42) -> 467553.5 | S42: =30000+13000 -> 43000 | T42: =246905.96 -> 246905.96 | V42: 15548.33 | W42: =V42+S42+T42+U42 -> 305454.29 | X42: 162099.21 | Y42: =70000 -> 70000
A43: 4 | B43: OGUCHE SAMUEL | D43: RESEARCH FELLOW I | E43: 14(11) | F43: 28489.81 | H43: =F43*300% -> 85469.43 | I43: =F43*7.5% -> 2136.7357 | K43: =F43*50% -> 14244.905 | L43: =F43*350% -> 99714.335 | M43: =F43*100% -> 28489.81 | N43: 100000 | O43: =F43*10% -> 2848.981 | P43: 20000 | R43: =SUM(F43:Q43) -> 381394.01 | S43: =30000 -> 30000 | T43: =179165.6+26250 -> 205415.6 | V43: 7709.76 | W43: =SUM(S43:V43) -> 243125.36 | X43: 138268.65 | Y43: 50000
A44: 5 | B44: IBRAHIM USMAN | D44: RESEARCH FELLOW I | E44: 14(11) | F44: =28489.81 -> 28489.81 | H44: =F44*300% -> 85469.43 | I44: =F44*7.5% -> 2136.7357 | J44: 0 | K44: =F44*50% -> 14244.905 | L44: =F44*350% -> 99714.335 | M44: =F44*100% -> 28489.81 | N44: 100000 | O44: =F44*10% -> 2848.981 | P44: 20000 | Q44: 0 | R44: =SUM(F44:Q44) -> 381394.01 | U44: ='[2]Jan 2021'!$H$24 -> 712.24525 | V44: 7709.76 | W44: =V44+S44+T44+U44 -> 8422.0053 | X44: 372972 | Y44: 50000
A45: 6 | B45: DR MOHAMMED O. AMALI | D45: RESEARCH FELLOW I | E45: 14(8) | F45: =25854.1 -> 25854.1 | H45: =F45*300% -> 77562.3 | I45: =F45*7.5% -> 1939.0575 | K45: =F45*50% -> 12927.05 | L45: =F45*350% -> 90489.35 | M45: =F45*100% -> 25854.1 | N45: 100000 | O45: =F45*10% -> 2585.41 | P45: 20000 | R45: =SUM(F45:Q45) -> 357211.37 | S45: =15000 -> 15000 | T45: =106666.67 -> 106666.67 | V45: 7709.76 | W45: =V45+S45+T45+U45 -> 129376.43 | X45: 227834.94 | Y45: 50000
A46: 7 | B46: YAHAYA SHAMSU | D46: RESEARCH FELLOW 11 | E46: 13(11) | F46: =26339.3 -> 26339.3 | H46: =F46*300% -> 79017.9 | I46: =F46*7.5% -> 1975.4475 | K46: =F46*50% -> 13169.65 | L46: =F46*350% -> 92187.55 | M46: =F46*100% -> 26339.3 | N46: 100000 | O46: =F46*10% -> 2633.93 | P46: 15000 | R46: =SUM(F46:Q46) -> 356663.08 | U46: 0 | V46: 7709.76 | W46: =V46+T46+S46+U46 -> 7709.76 | X46: 348953.32 | Y46: 50000
A47: 8 | B47: OFORDEME ADAOBI JULIA | D47: RESEARCH FELLOW 11 | E47: 13(9) | F47: =24741.26 -> 24741.26 | H47: =F47*300% -> 74223.78 | I47: =F47*7.5% -> 1855.5945 | J47: 0 | K47: =F47*50% -> 12370.63 | L47: =F47*350% -> 86594.41 | M47: =F47*100% -> 24741.26 | N47: 100000 | O47: =F47*10% -> 2474.126 | P47: 15000 | Q47: 0 | R47: =SUM(F47:Q47) -> 342001.06 | V47: 7709.76 | W47: =V47+S47+T47+U47 -> 7709.76 | X47: 334291.3 | Y47: 50000
A48: 9 | B48: IKPEAZU CHINEDU ANITA | D48: RESEARCH FELLOW II | E48: 14(8) | F48: =25854.1 -> 25854.1 | H48: =F48*300% -> 77562.3 | I48: =F48*7.5% -> 1939.0575 | J48: 0 | K48: =F48*50% -> 12927.05 | L48: =F48*350% -> 90489.35 | M48: =F48*100% -> 25854.1 | N48: 100000 | O48: =F48*10% -> 2585.41 | P48: 20000 | Q48: 0 | R48: =SUM(F48:Q48) -> 357211.37 | V48: 7709.76 | W48: =V48+S48+T48+U48 -> 7709.76 | X48: 349501.61 | Y48: 50000
A49: 10 | B49: ONYEAKU CHUKWUKA EDMOND | D49: RESEARCH FELLOW II | E49: 13(10) | F49: =25523.45 -> 25523.45 | H49: =F49*300% -> 76570.35 | I49: =F49*7.5% -> 1914.2587 | J49: =J22 -> 0 | K49: =F49*50% -> 12761.725 | L49: =F49*350% -> 89332.075 | M49: =F49*100% -> 25523.45 | N49: 100000 | O49: =F49*10% -> 2552.345 | P49: 15000 | Q49: 0 | R49: =SUM(F49:Q49) -> 349177.65 | S49: =30000 -> 30000 | T49: =182107.04 -> 182107.04 | U49: ='[2]Jan 2021'!$H$42 -> 638.08625 | V49: 7709.76 | W49: =V49+S49+T49+U49 -> 220454.89 | X49: 128722.77 | Y49: 50000
A50: 11 | B50: DORIS DAKDA AARON | D50: RESEARCH FELLOW II | E50: 13(8) | F50: =23891.12 -> 23891.12 | H50: =F50*300% -> 71673.36 | I50: =F50*7.5% -> 1791.834 | K50: =F50*50% -> 11945.56 | L50: =F50*350% -> 83618.92 | M50: =F50*100% -> 23891.12 | N50: 100000 | O50: =F50*10% -> 2389.112 | P50: 15000 | R50: =SUM(F50:Q50) -> 334201.03 | S50: =100000+10000 -> 110000 | U50: ='[2]Jan 2021'!$H$48 -> 597.278 | V50: =7709.76 -> 7709.76 | W50: =V50+S50+T50+U50 -> 118307.04 | X50: 215893.99 | Y50: 50000
B51: TOTAL | D51: 11 | F51: =SUM(F40:F50) -> 357937.97 | H51: =SUM(H40:H50) -> 1073813.9 | I51: =SUM(I40:I50) -> 26845.348 | J51: =SUM(J40:J50) -> 160488.76 | K51: =SUM(K40:K50) -> 178968.98 | L51: =SUM(L40:L50) -> 1252782.9 | M51: =SUM(M40:M50) -> 357937.97 | N51: =SUM(N40:N50) -> 1100000 | O51: =SUM(O40:O50) -> 35793.797 | ... W51: =SUM(W40:W50) -> 1507503.4 | X51: 3237066.3 | Y51: =SUM(Y40:Y50) -> 690000
B53: LEGAL SERVICES
A54: 1 | B54: DR SHUIBU DANWANKA | D54: DIRECTOR LEGAL SERVICES | E54: 17(9) | F54: =81740.02 -> 81740.02 | H54: =F54*300% -> 245220.06 | I54: =F54*7.5% -> 6130.5015 | J54: 80244.38 | K54: =F54*50% -> 40870.01 | L54: =F54*350% -> 286090.07 | M54: =F54*100% -> 81740.02 | N54: =100000 -> 100000 | O54: =F54*10% -> 8174.002 | P54: 20000 | Q54: 0 | R54: =SUM(F54:Q54) -> 950209.06 | U54: 0 | V54: 52776.63 | W54: =S54+T54+U54+V54 -> 52776.63 | X54: 897432.43 | Y54: 150000
A55: 2 | B55: ABDULSALAM BAKO | D55: MANAGER, LEGAL SERVICES | E55: 15 (7) | F55: 31018.84 | H55: =F55*300% -> 93056.52 | I55: =F55*7.5% -> 2326.413 | J55: 40122.19 | K55: =F55*50% -> 15509.42 | L55: =F55*350% -> 108565.94 | M55: =F55*100% -> 31018.84 | O55: =F55*10% -> 3101.884 | P55: 20000 | Q55: 0 | R55: =SUM(F55:Q55) -> 344720.05 | S55: =100000 -> 100000 | U55: 0 | V55: =15548.33 -> 15548.33 | W55: =S55+T55+U55+V55 -> 115548.33 | X55: 229171.72 | Y55: =70000 -> 70000
B56: TOTAL | D56: 2 | F56: =SUM(F54:F55) -> 112758.86 | H56: =SUM(H54:H55) -> 338276.58 | I56: =SUM(I54:I55) -> 8456.9145 | J56: =SUM(J54:J55) -> 120366.57 | K56: =SUM(K54:K55) -> 56379.43 | L56: =SUM(L54:L55) -> 394656.01 | M56: =SUM(M54:M55) -> 112758.86 | N56: =SUM(N54:N55) -> 100000 | O56: =SUM(O54:O55) -> 11275.886 | ... S56: =SUM(S54:S55) -> 100000 | U56: =SUM(U54:U55) -> 0 | V56: =SUM(V54:V55) -> 68324.96 | W56: =SUM(W54:W55) -> 168324.96 | X56: 1126604.2 | Y56: =SUM(Y54:Y55) -> 220000
B58: DEMOCRATIC STUDIES
A59: 1 | B59: DR. ADEWALE ADEREMI | D59: DIRECTOR, DEMOCRATIC STUDIES | E59: 17(8) | F59: =79039.64 -> 79039.64 | H59: =F59*300% -> 237118.92 | I59: =F59*7.5% -> 5927.973 | J59: =80244.38 -> 80244.38 | K59: =F59*50% -> 39519.82 | L59: =F59*350% -> 276638.74 | M59: =F59*100% -> 79039.64 | N59: =100000 -> 100000 | O59: =F59*10% -> 7903.964 | P59: 20000 | Q59: 0 | R59: =SUM(F59:Q59) -> 925433.08 | S59: =100000 -> 100000 | V59: =52776.63 -> 52776.63 | W59: =S59+T59+U59+V59 -> 152776.63 | X59: 772656.45 | Y59: 150000
A60: 2 | B60: NDANUSA MOHAMMED MANZUMA | D60: SNR RESEARCH FELLOW | E60: 15 (7) | F60: 31018.84 | H60: =F60*300% -> 93056.52 | I60: =F60*7.5% -> 2326.413 | J60: 40122.19 | K60: =F60*50% -> 15509.42 | L60: =F60*350% -> 108565.94 | M60: =F60*100% -> 31018.84 | O60: =F60*10% -> 3101.884 | P60: 20000 | Q60: 0 | R60: =SUM(F60:Q60) -> 344720.05 | S60: =100000 -> 100000 | T60: =131250 -> 131250 | U60: 0 | V60: =15548.33 -> 15548.33 | W60: =S60+T60+U60+V60 -> 246798.33 | X60: 97921.717 | Y60: =70000 -> 70000
A61: 3 | B61: EMILY EDOISA IKHIDE | D61: RESEARCH FELLOW II | E61: 13(10) | F61: =25523.45 -> 25523.45 | H61: =F61*300% -> 76570.35 | I61: =F61*7.5% -> 1914.2587 | K61: =F61*50% -> 12761.725 | L61: =F61*350% -> 89332.075 | M61: =F61*100% -> 25523.45 | N61: =100000 -> 100000 | O61: =F61*10% -> 2552.345 | P61: 15000 | R61: =SUM(F61:Q61) -> 349177.65 | S61: =50000 -> 50000 | T61: =45833.33 -> 45833.33 | V61: 7709.76 | W61: =SUM(S61:V61) -> 103543.09 | X61: 245634.56 | Y61: 50000
A62: 4 | B62: EJALONIBU GANIYU LAYI | D62: RESEARCH FELLOW 11 | E62: 13(8) | F62: =23891.12 -> 23891.12 | H62: =F62*300% -> 71673.36 | I62: =F62*7.5% -> 1791.834 | K62: =F62*50% -> 11945.56 | L62: =F62*350% -> 83618.92 | M62: =F62*100% -> 23891.12 | N62: =100000 -> 100000 | O62: =F62*10% -> 2389.112 | P62: 15000 | R62: =SUM(F62:Q62) -> 334201.03 | S62: =110000 -> 110000 | V62: =7709.76 -> 7709.76 | W62: =S62+T62+U62+V62 -> 117709.76 | X62: 216491.27 | Y62: 50000
A63: 5 | B63: LONA POLIT BONKAT | D63: RESEARCH FELLOW 11 | E63: 13(7) | F63: =23074.99 -> 23074.99 | H63: =F63*300% -> 69224.97 | I63: =F63*7.5% -> 1730.6243 | J63: 0 | K63: =F63*50% -> 11537.495 | L63: =F63*350% -> 80762.465 | M63: =F63*100% -> 23074.99 | N63: =100000 -> 100000 | O63: =F63*10% -> 2307.499 | P63: 15000 | Q63: 0 | R63: =SUM(F63:Q63) -> 326713.03 | S63: =20000 -> 20000 | T63: =119444.44 -> 119444.44 | U63: =0 -> 0 | V63: 7709.76 | W63: =SUM(S63:V63) -> 147154.2 | X63: 179558.83 | Y63: 50000
A64: 6 | B64: YUNUSA ABDULLAHI | D64: RESEARCH FELLOW 11 | E64: 13(10) | F64: =25523.45 -> 25523.45 | H64: =F64*300% -> 76570.35 | I64: =F64*7.5% -> 1914.2587 | K64: =F64*50% -> 12761.725 | L64: =F64*350% -> 89332.075 | M64: =F64*100% -> 25523.45 | N64: =100000 -> 100000 | O64: =F64*10% -> 2552.345 | P64: 15000 | R64: =SUM(F64:Q64) -> 349177.65 | S64: =10000 -> 10000 | T64: =54585.66 -> 54585.66 | V64: =7709.76 -> 7709.76 | W64: =SUM(S64:V64) -> 72295.42 | X64: 176882.23 | Y64: 50000
A65: 7 | B65: UDEFUNA NNADOZIE PATRICK | D65: RESEARCH OFFICER | E65: 10(13) | F65: =19774.62 -> 19774.62 | H65: =F65*300% -> 59323.86 | I65: =F65*7.5% -> 1483.0965 | J65: 0 | K65: =F65*50% -> 9887.31 | L65: =F65*350% -> 69211.17 | M65: =F65*100% -> 19774.62 | N65: =100000 -> 100000 | O65: =F65*10% -> 1977.462 | P65: 10000 | Q65: 0 | R65: =SUM(F65:Q65) -> 291432.14 | S65: =10000 -> 10000 | T65: =131771.66 -> 131771.66 | V65: 3369.51 | W65: =SUM(S65:V65) -> 145141.17 | X65: 146290.97 | Y65: 30000
A66: 8 | B66: OSOLAFIA MUHAMMAD EGYE | D66: PERSONNEL OFFICER | E66: 10(11) | F66: =19276.95 -> 19276.95 | H66: =F66*300% -> 57830.85 | I66: =F66*7.5% -> 1445.7713 | J66: 0 | K66: =F66*50% -> 9638.475 | L66: =F66*350% -> 67469.325 | M66: =F66*100% -> 19276.95 | N66: =100000 -> 100000 | O66: =F66*10% -> 1927.695 | P66: 10000 | Q66: 0 | R66: =SUM(F66:Q66) -> 286866.02 | S66: =20000 -> 20000 | T66: =100000 -> 100000 | U66: ='[2]Jan 2021'!$H$43 -> 481.92375 | V66: =3369.51 -> 3369.51 | W66: =S66+T66+U66+V66 -> 123851.43 | X66: 163014.58 | Y66: 30000
A67: 9 | B67: HAUWA PATE SADIQ | D67: PROGRAMME OFFICER | E67: 10(9) | F67: =18281.64 -> 18281.64 | H67: =F67*300% -> 54844.92 | I67: =F67*7.5% -> 1371.123 | K67: =F67*50% -> 9140.82 | L67: =F67*350% -> 63985.74 | M67: =F67*100% -> 18281.64 | N67: =100000 -> 100000 | O67: =F67*10% -> 1828.164 | P67: 10000 | R67: =SUM(F67:Q67) -> 277734.05 | S67: =70000+20000 -> 90000 | T67: =31500 -> 31500 | V67: 3369.51 | W67: =SUM(S67:V67) -> 124869.51 | X67: 152864.54 | Y67: 30000
A68: 10 | B68: ABAYOMI KAYODE QUADRI | D68: RESEARCH OFFICER | E68: 10(7) | F68: =17286.33 -> 17286.33 | H68: =F68*300% -> 51858.99 | I68: =F68*7.5% -> 1296.4748 | K68: =F68*50% -> 8643.165 | L68: =F68*350% -> 60502.155 | M68: =F68*100% -> 17286.33 | N68: =100000 -> 100000 | O68: =F68*10% -> 1728.633 | P68: 10000 | R68: =SUM(F68:Q68) -> 268602.08 | S68: =50000 -> 50000 | T68: 0 | V68: 3369.51 | W68: =SUM(S68:V68) -> 53369.51 | X68: 215232.57 | Y68: 30000
A69: 11 | B69: NNANDI LIVINUS ATURE | D69: RESEARCH ASSISTANT | E69: 8(7) | F69: =12351.94 -> 12351.94 | H69: =F69*300% -> 37055.82 | I69: =F69*7.5% -> 926.3955 | K69: =F69*50% -> 6175.97 | L69: =F69*350% -> 43231.79 | M69: =F69*100% -> 12351.94 | N69: =100000 -> 100000 | O69: =F69*10% -> 1235.194 | P69: 10000 | R69: =SUM(F69:Q69) -> 223329.05 | S69: =100000 -> 100000 | V69: =1235.19 -> 1235.19 | W69: =SUM(S69:V69) -> 101235.19 | X69: 122093.86 | Y69: 30000
A70: 12 | B70: LUCKY AGWOM | D70: RESEARCH ASSISTANT | E70: 8(7) | F70: =12351.94 -> 12351.94 | H70: =F70*300% -> 37055.82 | I70: =F70*7.5% -> 926.3955 | K70: =F70*50% -> 6175.97 | L70: =F70*350% -> 43231.79 | M70: =F70*100% -> 12351.94 | N70: =100000 -> 100000 | O70: =F70*10% -> 1235.194 | P70: 10000 | R70: =SUM(F70:Q70) -> 223329.05 | V70: =1235.19 -> 1235.19 | W70: =SUM(S70:V70) -> 1235.19 | X70: 222093.86 | Y70: 30000
B71: TOTAL | D71: 12 | F71: =SUM(F59:F70) -> 307394.91 | H71: =SUM(H59:H70) -> 922184.73 | I71: =SUM(I59:I70) -> 23054.618 | J71: =SUM(J59:J70) -> 120366.57 | K71: =SUM(K59:K70) -> 153697.46 | L71: =SUM(L59:L70) -> 1075882.2 | M71: =SUM(M59:M70) -> 307394.91 | N71: =SUM(N59:N70) -> 1100000 | O71: =SUM(O59:O70) -> 30739.491 | ... Y71: =SUM(Y59:Y70) -> 600000
B73: POST GRADUATE SCHOOL
A74: 1 | B74: DR ASIMIYU G. ABIOLA | D74: DIRECTOR POST GRADUATE | E74: 17(9) | F74: =81740.02 -> 81740.02 | H74: =F74*300% -> 245220.06 | I74: =F74*7.5% -> 6130.5015 | J74: 80244.38 | K74: =F74*50% -> 40870.01 | L74: =F74*350% -> 286090.07 | M74: =F74*100% -> 81740.02 | N74: =100000 -> 100000 | O74: =F74*10% -> 8174.002 | P74: 20000 | Q74: 0 | R74: =SUM(F74:Q74) -> 950209.06 | S74: 150000 | T74: =0 -> 0 | U74: 0 | V74: 52776.63 | W74: =SUM(S74:V74) -> 202776.63 | X74: 747432.43 | Y74: 150000
A75: 2 | B75: USMAN WALI | D75: DEPUTY DIRECTOR, PG | E75: 15 (7) | F75: 31018.84 | H75: =F75*300% -> 93056.52 | I75: =F75*7.5% -> 2326.413 | J75: 40122.19 | K75: =F75*50% -> 15509.42 | L75: =F75*350% -> 108565.94 | M75: =F75*100% -> 31018.84 | O75: =F75*10% -> 3101.884 | P75: 20000 | Q75: 0 | R75: =SUM(F75:Q75) -> 344720.05 | U75: 0 | V75: =15548.33 -> 15548.33 | W75: =S75+T75+U75+V75 -> 15548.33 | X75: 329171.72 | Y75: =70000 -> 70000
A76: 3 | B76: MOSHOOD TOSHO AMUDA | D76: MANAGER, EXAMS & RECORDS | E76: 15 (7) | F76: 31018.84 | H76: =F76*300% -> 93056.52 | I76: =F76*7.5% -> 2326.413 | J76: 40122.19 | K76: =F76*50% -> 15509.42 | L76: =F76*350% -> 108565.94 | M76: =F76*100% -> 31018.84 | N76: =100000 -> 100000 | O76: =F76*10% -> 3101.884 | P76: 20000 | Q76: 0 | R76: =SUM(F76:Q76) -> 444720.05 | U76: 0 | V76: =15548.33 -> 15548.33 | W76: =S76+T76+U76+V76 -> 15548.33 | X76: 429171.72 | Y76: =70000 -> 70000
A77: 4 | B77: CHIOMA UWAZURUIKE | D77: MANAGER, PROGRAMME | E77: 15 (7) | F77: 31018.84 | H77: =F77*300% -> 93056.52 | I77: =F77*7.5% -> 2326.413 | J77: 40122.19 | K77: =F77*50% -> 15509.42 | L77: =F77*350% -> 108565.94 | M77: =F77*100% -> 31018.84 | O77: =F77*10% -> 3101.884 | P77: 20000 | Q77: 0 | R77: =SUM(F77:Q77) -> 344720.05 | U77: 0 | V77: =15548.33 -> 15548.33 | W77: =S77+T77+U77+V77 -> 15548.33 | X77: 329171.72 | Y77: =70000 -> 70000
A78: 5 | B78: UZODINMA EMMANUEL EZENWA | D78: RESEARCH FELLOW II | E78: 13(8) | F78: =23891.12 -> 23891.12 | H78: =F78*300% -> 71673.36 | I78: =F78*7.5% -> 1791.834 | J78: 0 | K78: =F78*50% -> 11945.56 | L78: =F78*350% -> 83618.92 | M78: =F78*100% -> 23891.12 | N78: =100000 -> 100000 | O78: =F78*10% -> 2389.112 | P78: 15000 | Q78: 0 | R78: =SUM(F78:Q78) -> 334201.03 | S78: =0 -> 0 | T78: =0 -> 0 | U78: ='[2]Jan 2021'!$H$44 -> 597.278 | V78: =7709.76 -> 7709.76 | W78: =S78+T78+U78+V78 -> 8307.038 | X78: 325893.99 | Y78: 50000
A79: 6 | B79: IGWE STACY | D79: PROGRAMME OFFICER | E79: 10(7) | F79: =17286.33 -> 17286.33 | H79: =F79*300% -> 51858.99 | I79: =F79*7.5% -> 1296.4748 | K79: =F79*50% -> 8643.165 | L79: =F79*350% -> 60502.155 | M79: =F79*100% -> 17286.33 | N79: =100000 -> 100000 | O79: =F79*10% -> 1728.633 | P79: 10000 | R79: =SUM(F79:Q79) -> 268602.08 | S79: =50000 -> 50000 | T79: 0 | V79: 3369.51 | W79: =SUM(S79:V79) -> 53369.51 | X79: 215232.57 | Y79: 30000
A80: 7 | B80: DARE SHEU MAGBON | D80: ASSISTANT OFFICER PG | E80: 8(8) | F80: =12732 -> 12732 | H80: =F80*300% -> 38196 | I80: =F80*7.5% -> 954.9 | K80: =F80*50% -> 6366 | L80: =F80*350% -> 44562 | M80: =F80*100% -> 12732 | O80: =F80*10% -> 1273.2 | P80: 10000 | R80: =SUM(F80:Q80) -> 126816.1 | S80: =3000+20000 -> 23000 | T80: 0 | V80: =1235.19 -> 1235.19 | W80: =SUM(S80:V80) -> 24235.19 | X80: 102580.91 | Y80: 30000
A81: 8 | B81: MOHAMMED BELLO | D81: RESEARCH ASSITANT PG | E81: 8(7) | F81: =12351.94 -> 12351.94 | H81: =F81*300% -> 37055.82 | I81: =F81*7.5% -> 926.3955 | K81: =F81*50% -> 6175.97 | L81: =F81*350% -> 43231.79 | M81: =F81*100% -> 12351.94 | N81: =100000 -> 100000 | O81: =F81*10% -> 1235.194 | P81: 10000 | R81: =SUM(F81:Q81) -> 223329.05 | S81: =0 -> 0 | T81: 0 | V81: =1235.19 -> 1235.19 | W81: =SUM(S81:V81) -> 1235.19 | X81: 222093.86 | Y81: 30000
B82: TOTAL | D82: 8 | F82: =SUM(F74:F81) -> 241057.93 | H82: =SUM(H74:H81) -> 723173.79 | I82: =SUM(I74:I81) -> 18079.345 | J82: =SUM(J74:J81) -> 200610.95 | K82: =SUM(K74:K81) -> 120528.96 | L82: =SUM(L74:L81) -> 843702.76 | M82: =SUM(M74:M81) -> 241057.93 | N82: =SUM(N74:N81) -> 500000 | O82: =SUM(O74:O81) -> 24105.793 | ... W82: =SUM(W74:W81) -> 336568.55 | X82: 2700748.9 | Y82: =SUM(Y74:Y81) -> 500000
B84: ECONOMIC AND SOCIAL DEV.
A85: 1 | B85: DR ASEMOTA OMOROGBE JOSEPH | D85: Ag. DEPUTY DIRECTOR, ECO & SOC DEV DEPT | E85: 16(7) | F85: =39662.25 -> 39662.25 | H85: =F85*300% -> 118986.75 | I85: =F85*7.5% -> 2974.6687 | J85: 40122.19 | K85: =F85*50% -> 19831.125 | L85: =F85*350% -> 138817.88 | M85: =F85*100% -> 39662.25 | N85: =100000 -> 100000 | O85: =F85*10% -> 3966.225 | P85: 20000 | R85: =SUM(F85:Q85) -> 524023.33 | V85: =21618.09 -> 21618.09 | W85: =SUM(S85:V85) -> 21618.09 | X85: 502405.24 | Y85: =70000 -> 70000
A86: 2 | B86: TERFA WILLIAMS ABRAHAM | D86: SNR RESEARCH FELLOW | E86: 15(8) | F86: =32263.2 -> 32263.2 | H86: =F86*300% -> 96789.6 | I86: =F86*7.5% -> 2419.74 | J86: =40122.19 -> 40122.19 | K86: =F86*50% -> 16131.6 | L86: =F86*350% -> 112921.2 | M86: =F86*100% -> 32263.2 | N86: =100000 -> 100000 | O86: =F86*10% -> 3226.32 | P86: 20000 | R86: =SUM(F86:Q86) -> 456137.05 | V86: =15548.33 -> 15548.33 | W86: =SUM(S86:V86) -> 15548.33 | X86: 440588.72 | Y86: =70000 -> 70000
A87: 3 | B87: DR AUGUSTINE C. OSIGWE | D87: SNR RESEARCH FELLOW | E87: 15(8) | F87: =32263.2 -> 32263.2 | H87: =F87*300% -> 96789.6 | I87: =F87*7.5% -> 2419.74 | J87: =40122.19 -> 40122.19 | K87: =F87*50% -> 16131.6 | L87: =F87*350% -> 112921.2 | M87: =F87*100% -> 32263.2 | N87: =100000 -> 100000 | O87: =F87*10% -> 3226.32 | P87: 20000 | R87: =SUM(F87:Q87) -> 456137.05 | S87: =20000 -> 20000 | T87: =68750 -> 68750 | U87: ='[2]Jan 2021'!$H$38 -> 806.58 | V87: =15548.33 -> 15548.33 | W87: =SUM(S87:V87) -> 105104.91 | X87: 351032.14 | Y87: =70000 -> 70000
A88: 4 | B88: JUMARE FADILA | D88: RESEARCH FELLOW I | E88: 14(8) | F88: =25854.1 -> 25854.1 | H88: =F88*300% -> 77562.3 | I88: =F88*7.5% -> 1939.0575 | J88: 0 | K88: =F88*50% -> 12927.05 | L88: =F88*350% -> 90489.35 | M88: =F88*100% -> 25854.1 | N88: =100000 -> 100000 | O88: =F88*10% -> 2585.41 | P88: 20000 | Q88: 0 | R88: =SUM(F88:Q88) -> 357211.37 | S88: 5000 | V88: =7709.76 -> 7709.76 | W88: =SUM(S88:V88) -> 12709.76 | X88: 344501.61 | Y88: 50000
A89: 5 | B89: NGARA CHRISTOPHER OCHANJA | D89: RESEARCH FELLOW 1 | E89: 14(9) | F89: =26732.65 -> 26732.65 | H89: =F89*300% -> 80197.95 | I89: =F89*7.5% -> 2004.9488 | K89: =F89*50% -> 13366.325 | L89: =F89*350% -> 93564.275 | M89: =F89*100% -> 26732.65 | N89: =100000 -> 100000 | O89: =F89*10% -> 2673.265 | P89: 20000 | Q89: 0 | R89: =SUM(F89:Q89) -> 365272.06 | S89: =20000 -> 20000 | T89: =163103.59 -> 163103.59 | U89: ='[2]Jan 2021'!$H$46 -> 668.31625 | V89: =7709.76 -> 7709.76 | W89: =S89+T89+U89+V89 -> 191481.67 | X89: 173790.4 | Y89: 50000
A90: 6 | B90: OMOJU OLUWASOLA EMMANUEL | D90: RESEARCH FELLOW I | E90: 14(8) | F90: =25854.1 -> 25854.1 | H90: =F90*300% -> 77562.3 | I90: =F90*7.5% -> 1939.0575 | K90: =F90*50% -> 12927.05 | L90: =F90*350% -> 90489.35 | M90: =F90*100% -> 25854.1 | N90: =100000 -> 100000 | O90: =F90*10% -> 2585.41 | P90: 20000 | R90: =SUM(F90:Q90) -> 357211.37 | S90: =50000 -> 50000 | T90: =87500 -> 87500 | V90: =7709.76 -> 7709.76 | W90: =SUM(S90:V90) -> 145209.76 | X90: 212001.61 | Y90: 50000
A91: 7 | B91: ONYIMADU C. ONYEBUCHI | D91: RESEARCH FELLOW I | E91: 14(8) | F91: =25854.1 -> 25854.1 | H91: =F91*300% -> 77562.3 | I91: =F91*7.5% -> 1939.0575 | K91: =F91*50% -> 12927.05 | L91: =F91*350% -> 90489.35 | M91: =F91*100% -> 25854.1 | N91: =100000 -> 100000 | O91: =F91*10% -> 2585.41 | P91: 20000 | R91: =SUM(F91:Q91) -> 357211.37 | S91: =50000 -> 50000 | U91: ='[2]Jan 2021'!$H$50 -> 646.3525 | V91: 7709.76 | W91: =SUM(S91:V91) -> 58356.113 | X91: 298855.26 | Y91: 50000
A92: 8 | B92: RIFKATU NGHARGBU | D92: RESEARCH FELLOW 1 | E92: 14(7) | F92: =24975.81 -> 24975.81 | H92: =F92*300% -> 74927.43 | I92: =F92*7.5% -> 1873.1858 | J92: 0 | K92: =F92*50% -> 12487.905 | L92: =F92*350% -> 87415.335 | M92: =F92*100% -> 24975.81 | N92: =100000 -> 100000 | O92: =F92*10% -> 2497.581 | P92: 20000 | Q92: 0 | R92: =SUM(F92:Q92) -> 349153.06 | S92: =100000 -> 100000 | T92: =68666.67 -> 68666.67 | V92: =7709.76 -> 7709.76 | W92: =SUM(S92:V92) -> 176376.43 | X92: 172776.63 | Y92: 50000
A93: 9 | B93: IBE EZECHI CYRIACUS | D93: RESEARCH FELLOW II | E93: 13(8) | F93: =23891.12 -> 23891.12 | H93: =F93*300% -> 71673.36 | I93: =F93*7.5% -> 1791.834 | J93: 0 | K93: =F93*50% -> 11945.56 | L93: =F93*350% -> 83618.92 | M93: =F93*100% -> 23891.12 | N93: =100000 -> 100000 | O93: =F93*10% -> 2389.112 | P93: 15000 | Q93: 0 | R93: =SUM(F93:Q93) -> 334201.03 | S93: =50000 -> 50000 | V93: =7709.76 -> 7709.76 | W93: =SUM(S93:V93) -> 57709.76 | X93: 276491.27 | Y93: 50000
A94: 10 | B94: PERCY TERFA GBAHABO | D94: RESEARCH FELLOW 11 | E94: 13(7) | F94: =23074.99 -> 23074.99 | H94: =F94*300% -> 69224.97 | I94: =F94*7.5% -> 1730.6243 | J94: 0 | K94: =F94*50% -> 11537.495 | L94: =F94*350% -> 80762.465 | M94: =F94*100% -> 23074.99 | N94: =100000 -> 100000 | O94: =F94*10% -> 2307.499 | P94: 15000 | Q94: 0 | R94: =SUM(F94:Q94) -> 326713.03 | S94: =10000 -> 10000 | T94: =131666.67 -> 131666.67 | V94: =7709.76 -> 7709.76 | W94: =SUM(S94:V94) -> 149376.43 | X94: 177336.6 | Y94: 50000
A95: 11 | B95: OSIKHEN LEO IGBANOI | D95: RESEARCH FELLOW 11 | E95: 13(7) | F95: =23074.99 -> 23074.99 | H95: =F95*300% -> 69224.97 | I95: =F95*7.5% -> 1730.6243 | J95: 0 | K95: =F95*50% -> 11537.495 | L95: =F95*350% -> 80762.465 | M95: =F95*100% -> 23074.99 | N95: =100000 -> 100000 | O95: =F95*10% -> 2307.499 | P95: 15000 | Q95: 0 | R95: =SUM(F95:Q95) -> 326713.03 | S95: =25000 -> 25000 | T95: =94262.15 -> 94262.15 | V95: =7709.76 -> 7709.76 | W95: =SUM(S95:V95) -> 126971.91 | X95: 199741.12 | Y95: 50000
A96: 12 | B96: OKUNGBOWA OSARETIN GODSPOWER | D96: RESEARCH FELLOW 11 | E96: 13(7) | F96: =23074.99 -> 23074.99 | H96: =F96*300% -> 69224.97 | I96: =F96*7.5% -> 1730.6243 | J96: 0 | K96: =F96*50% -> 11537.495 | L96: =F96*350% -> 80762.465 | M96: =F96*100% -> 23074.99 | N96: =100000 -> 100000 | O96: =F96*10% -> 2307.499 | P96: 15000 | Q96: 0 | R96: =SUM(F96:Q96) -> 326713.03 | S96: =70000 -> 70000 | V96: =7709.76 -> 7709.76 | W96: =SUM(S96:V96) -> 77709.76 | X96: 249003.27 | Y96: 50000
B97: TOTAL | D97: 12 | F97: =SUM(F85:F96) -> 326575.5 | H97: =SUM(H85:H96) -> 979726.5 | I97: =SUM(I85:I96) -> 24493.162 | J97: =SUM(J85:J96) -> 120366.57 | K97: =SUM(K85:K96) -> 163287.75 | L97: =SUM(L85:L96) -> 1143014.2 | M97: =SUM(M85:M96) -> 326575.5 | N97: =SUM(N85:N96) -> 1200000 | O97: =SUM(O85:O96) -> 32657.55 | ... W97: =SUM(W85:W96) -> 1138172.9 | X97: 3398523.9 | Y97: =SUM(Y85:Y96) -> 660000
B99: TRAINING AND INTERNATIONAL COOP
A100: 1 | B100: MRS AMINA U IBRAHIM | D100: DEPUTY DIRECTOR TRAINING | E100: 16 (7) | F100: =39662.25 -> 39662.25 | H100: =F100*300% -> 118986.75 | I100: =F100*7.5% -> 2974.6687 | J100: 40122.19 | K100: =F100*50% -> 19831.125 | L100: =F100*350% -> 138817.88 | M100: =F100*100% -> 39662.25 | O100: =F100*10% -> 3966.225 | P100: 20000 | Q100: 0 | R100: =SUM(F100:Q100) -> 424023.33 | V100: =21618.09 -> 21618.09 | W100: =S100+T100+U100+V100 -> 21618.09 | X100: 402405.24 | Y100: =70000 -> 70000
A101: 2 | B101: DR FRANCIS NDUM OJIE | D101: ASST. MANAGER, TRAINING | E101: 14(8) | F101: =25854.1 -> 25854.1 | H101: =F101*300% -> 77562.3 | I101: =F101*7.5% -> 1939.0575 | K101: =F101*50% -> 12927.05 | L101: =F101*350% -> 90489.35 | M101: =F101*100% -> 25854.1 | N101: 100000 | O101: =F101*10% -> 2585.41 | P101: 20000 | R101: =SUM(F101:Q101) -> 357211.37 | U101: =646.35 -> 646.35 | V101: =7709.76 -> 7709.76 | W101: =SUM(S101:V101) -> 8356.11 | X101: 348855.26 | Y101: 50000
A102: 3 | B102: OKECHUKWU UCHENNA HULDA | D102: TRAINING OFFICER | E102: 10(9) | F102: =18281.64 -> 18281.64 | H102: =F102*300% -> 54844.92 | I102: =F102*7.5% -> 1371.123 | K102: =F102*50% -> 9140.82 | L102: =F102*350% -> 63985.74 | M102: =F102*100% -> 18281.64 | N102: =100000 -> 100000 | O102: =F102*10% -> 1828.164 | P102: 10000 | R102: =SUM(F102:Q102) -> 277734.05 | S102: =5000 -> 5000 | T102: =0 -> 0 | V102: 3369.51 | W102: =SUM(S102:V102) -> 8369.51 | X102: 269364.54 | Y102: 30000
A103: 4 | B103: HASSANA AHMED IBRAHIM | D103: TRAINING OFFICER | E103: 10(8) | F103: =17784 -> 17784 | H103: =F103*300% -> 53352 | I103: =F103*7.5% -> 1333.8 | K103: =F103*50% -> 8892 | L103: =F103*350% -> 62244 | M103: =F103*100% -> 17784 | N103: 100000 | O103: =F103*10% -> 1778.4 | P103: 10000 | R103: =SUM(F103:Q103) -> 273168.2 | S103: =30000 -> 30000 | U103: ='[2]Jan 2021'!$H$55 -> 444.6 | V103: 3369.51 | W103: =SUM(S103:V103) -> 33814.11 | X103: 239354.09 | Y103: 30000
B104: TOTAL | D104: 4 | F104: =SUM(F100:F103) -> 101581.99 | H104: =SUM(H100:H103) -> 304745.97 | I104: =SUM(I100:I103) -> 7618.6492 | J104: =SUM(J100:J103) -> 40122.19 | K104: =SUM(K100:K103) -> 50790.995 | L104: =SUM(L100:L103) -> 355536.96 | M104: =SUM(M100:M103) -> 101581.99 | N104: =SUM(N100:N103) -> 300000 | O104: =SUM(O100:O103) -> 10158.199 | ... W104: =SUM(W100:W103) -> 72157.82 | X104: 1259979.1 | Y104: =SUM(Y100:Y103) -> 180000
B106: LIBRARY AND DOCUMENTATION
A107: 1 | B107: DR MAIMUNA IZAH | D107: INSITUTE LIBRARIAN | E107: 17(8) | F107: =79039.64 -> 79039.64 | H107: =F107*300% -> 237118.92 | I107: =F107*7.5% -> 5927.973 | J107: 80244.38 | K107: =F107*50% -> 39519.82 | L107: =F107*350% -> 276638.74 | M107: =F107*100% -> 79039.64 | N107: =100000 -> 100000 | O107: =F107*10% -> 7903.964 | P107: 20000 | Q107: 0 | R107: =SUM(F107:Q107) -> 925433.08 | S107: =100000 -> 100000 | T107: 0 | U107: 0 | V107: =52776.63 -> 52776.63 | W107: =SUM(S107:V107) -> 152776.63 | X107: 772656.45 | Y107: 150000
A108: 2 | B108: CATHERINE E. IKOKOH | D108: SNR RESEARCH FELLOW DOCU | E108: 15(9) | F108: =33507.5 -> 33507.5 | H108: =F108*300% -> 100522.5 | I108: =F108*7.5% -> 2513.0625 | J108: 40122.19 | K108: =F108*50% -> 16753.75 | L108: =F108*350% -> 117276.25 | M108: =F108*100% -> 33507.5 | N108: =100000 -> 100000 | O108: =F108*10% -> 3350.75 | P108: 20000 | Q108: 0 | R108: =SUM(F108:Q108) -> 467553.5 | S108: 40000 | T108: =131250 -> 131250 | U108: ='[2]Jan 2021'!$H$33 -> 837.6875 | V108: 15548.33 | W108: =SUM(S108:V108) -> 187636.02 | X108: 279917.48 | Y108: =70000 -> 70000
A109: 3 | B109: ALIYU SANNI ABUBAKAR | D109: RESEARCH FELLOW 11 DATA & DOCU | E109: 13(11) | F109: =26339.3 -> 26339.3 | H109: =F109*300% -> 79017.9 | I109: =F109*7.5% -> 1975.4475 | J109: 0 | K109: =F109*50% -> 13169.65 | L109: =F109*350% -> 92187.55 | M109: =F109*100% -> 26339.3 | N109: =100000 -> 100000 | O109: =F109*10% -> 2633.93 | P109: 15000 | Q109: 0 | R109: =SUM(F109:Q109) -> 356663.08 | S109: 30000 | T109: =0 -> 0 | U109: ='[2]Jan 2021'!$H$36 -> 658.4825 | V109: =7709.76 -> 7709.76 | W109: =SUM(S109:V109) -> 38368.243 | X109: 318294.83 | Y109: 50000
A110: 4 | B110: CHINAKO N. ASOGWA | D110: RESEARCH FELLOW 11 DATA & DOCU | E110: 13(9) | F110: =24741.26 -> 24741.26 | H110: =F110*300% -> 74223.78 | I110: =F110*7.5% -> 1855.5945 | J110: 0 | K110: =F110*50% -> 12370.63 | L110: =F110*350% -> 86594.41 | M110: =F110*100% -> 24741.26 | N110: =100000 -> 100000 | O110: =F110*10% -> 2474.126 | P110: 15000 | R110: =SUM(F110:Q110) -> 342001.06 | S110: =50000 -> 50000 | T110: =68750 -> 68750 | V110: =7709.76 -> 7709.76 | W110: =SUM(S110:V110) -> 126459.76 | X110: 215541.3 | Y110: 50000
...

Sheet ADjustment
B3: STAFF PAYROLL FOR THE MONTH OF JUNE, 2021
F4: ='[1]FEB 08'!E8/'[1]FEB 08'!M8 -> 0.22 | I4: ='[1]FEB 08'!F8/'[1]FEB 08'!Q8 -> 0.3
B5: STAFF NAME | S5: DEDUCTIONS | Y5: NET SALARY
D6: DESIGNATION | E6: SALARY | F6: BASIC | M6: MOTOR/ | N6: RESEARCH | O6: LEAVE | P6: OUT FIT | Q6: LEGISLATIVE | R6: GROSS | X6: APRIL,2021 | Y6: MAY,2021 | Z6: PROPOSED | AA6: DIFFERENCE
E7: LEVEL | F7: SALARY | G7: SALARY/ALLOWCE AREARS | H7: RENT | I7: UTILITY | J7: DOMESTIC | K7: ENTERT. | L7: FURNIT. | M7: FUEL | N7: ALLOWANCE | O7: ALLCE | P7: ALLCE | Q7: DUTY ALLCE | R7: SALARY | S7: COOP SOCIETY | T7: COOP. LOAN RECOVERY | U7: NHF DEDUCTION | V7: PAYE | W7: TOTAL | Z7: ALLOWANCES
A8: S/N | B8: DG OFFICE | F8: N | I8: N | R8: N | V8: N
A9: 1 | B9: PROF. ABUBAKAR O. SULAIMAN | D9: DIRECTOR GENERAL | E9: CONSOL | F9: 160488.75 | H9: 320977.5 | I9: 48146.63 | J9: 120366.57 | K9: 72219.94 | L9: 0 | M9: 120366.57 | N9: =100000 -> 100000 | O9: 16048.88 | P9: 25000 | Q9: 25235 | R9: =SUM(F9:Q9) -> 1008849.8 | V9: 113176.97 | W9: =S9+T9+U9+V9 -> 113176.97 | X9: 895672.87 | Y9: =R9-W9 -> 895672.87 | Z9: =200000 -> 200000
A10: 2 | B10: DR ADEYEMI AKEEB FAJINGBESI | D10: DIR. SPECIAL DUTIES, DG OFFICE | E10: 17(9) | F10: 81740.02 | H10: =F10*300% -> 245220.06 | I10: =F10*7.5% -> 6130.5015 | J10: 80244.38 | K10: =F10*50% -> 40870.01 | L10: =F10*350% -> 286090.07 | M10: =F10*100% -> 81740.02 | N10: =100000 -> 100000 | O10: =F10*10% -> 8174.002 | P10: 20000 | Q10: 0 | R10: =SUM(F10:Q10) -> 950209.06 | S10: 200000 | T10: =59722.22 -> 59722.22 | U10: ='[2]Jan 2021'!$H$35 -> 2043.5005 | V10: 52776.63 | W10: =SUM(S10:V10) -> 314542.35 | X10: 635666.71 | Y10: =R10-W10 -> 635666.71 | Z10: =100000 -> 100000
A11: 3 | B11: SARAFADEEN ALABELEWE | D11: SA ADMINISTRATION | E11: 16(9) | F11: =42653.17 -> 42653.17 | H11: =F11*300% -> 127959.51 | I11: =F11*7.5% -> 3198.9877 | J11: 40122.19 | K11: =F11*50% -> 21326.585 | L11: =F11*350% -> 149286.1 | M11: =F11*100% -> 42653.17 | O11: =F11*10% -> 4265.317 | P11: 20000 | R11: =SUM(F11:Q11) -> 451465.02 | S11: =100000 -> 100000 | T11: =137500 -> 137500 | V11: 21618.09 | W11: =S11+T11+U11+V11 -> 259118.09 | X11: 192346.93 | Y11: =R11-W11 -> 192346.93 | Z11: =100000 -> 100000
A12: 4 | B12: DR JAKE DABANG DAN AZUMI | D12: DEPUTY DIRECTOR TRAINING | E12: 16(7) | F12: =39662.25 -> 39662.25 | H12: =F12*300% -> 118986.75 | I12: =F12*7.5% -> 2974.6687 | J12: 40122.19 | K12: =F12*50% -> 19831.125 | L12: =F12*350% -> 138817.88 | M12: =F12*100% -> 39662.25 | N12: =100000 -> 100000 | O12: =F12*10% -> 3966.225 | P12: 20000 | Q12: 150000 | R12: =SUM(F12:Q12) -> 674023.33 | U12: ='[2]Jan 2021'!$H$27 -> 991.55625 | V12: =21618.09 -> 21618.09 | W12: =SUM(S12:V12) -> 22609.646 | X12: 651413.69 | Y12: =R12-W12 -> 651413.69 | Z12: 100000
A13: 5 | B13: DR ABDULSALAM NASIRU NAEEM | D13: SA ACADEMICS | E13: 16(7) | F13: =39662.25 -> 39662.25 | H13: =F13*300% -> 118986.75 | I13: =F13*7.5% -> 2974.6687 | J13: 40122.19 | K13: =F13*50% -> 19831.125 | L13: =F13*350% -> 138817.88 | M13: =F13*100% -> 39662.25 | N13: =100000 -> 100000 | O13: =F13*10% -> 3966.225 | P13: 20000 | Q13: =100000 -> 100000 | R13: =SUM(F13:Q13) -> 624023.33 | V13: =21618.09 -> 21618.09 | W13: =S13+T13+U13+V13 -> 21618.09 | X13: 602405.24 | Y13: =R13-W13 -> 602405.24 | Z13: 100000
A14: 6 | B14: RAHEEM USMAN AYIGORO | D14: SA-INFRASTRUCTURE | E14: 16 (7) | F14: =39662.25 -> 39662.25 | H14: =F14*300% -> 118986.75 | I14: =F14*7.5% -> 2974.6687 | J14: 40122.19 | K14: =F14*50% -> 19831.125 | L14: =F14*350% -> 138817.88 | M14: =F14*100% -> 39662.25 | O14: =F14*10% -> 3966.225 | P14: 20000 | Q14: 0 | R14: =SUM(F14:Q14) -> 424023.33 | V14: =21618.09 -> 21618.09 | W14: =S14+T14+U14+V14 -> 21618.09 | X14: 402405.24 | Y14: =R14-W14 -> 402405.24 | Z14: 100000
A15: 7 | B15: AKINSANMI ADEJOKE OLUKEMI | D15: HEAD INFORMATION/PROTOCOL | E15: 15(9) | F15: 33507.5 | H15: =F15*300% -> 100522.5 | I15: =F15*7.5% -> 2513.0625 | J15: 40122.19 | K15: =F15*50% -> 16753.75 | L15: =F15*350% -> 117276.25 | M15: =F15*100% -> 33507.5 | O15: =F15*10% -> 3350.75 | P15: 20000 | Q15: =100000 -> 100000 | R15: =SUM(F15:Q15) -> 467553.5 | S15: =0 -> 0 | T15: 0 | U15: =837.69 -> 837.69 | V15: 15548.33 | W15: =S15+T15+U15+V15 -> 16386.02 | X15: 451167.48 | Y15: =R15-W15 -> 451167.48 | Z15: 80000
A16: 8 | B16: DR IKEME ARTHUR J.O | D16: SNR RESEARCH FELLOW | E16: 15(9) | F16: =33507.5 -> 33507.5 | H16: =F16*300% -> 100522.5 | I16: =F16*7.5% -> 2513.0625 | J16: 40122.19 | K16: =F16*50% -> 16753.75 | L16: =F16*350% -> 117276.25 | M16: =F16*100% -> 33507.5 | N16: =100000 -> 100000 | O16: =F16*10% -> 3350.75 | P16: 20000 | Q16: 0 | R16: =SUM(F16:Q16) -> 467553.5 | S16: 50000 | T16: =212642 -> 212642 | U16: ='[3]DECEMBER 2019'!$H$38 -> 837.6875 | V16: 15548.33 | W16: =SUM(S16:V16) -> 279028.02 | X16: 188525.48 | Y16: =R16-W16 -> 188525.48 | Z16: 80000
A17: 9 | B17: MOSHOOD M. OLALERE | D17: MANAGER ADMIN DG's OFFICE | E17: 15(9) | F17: =33507.5 -> 33507.5 | H17: =F17*300% -> 100522.5 | I17: =F17*7.5% -> 2513.0625 | J17: 40122.19 | K17: =F17*50% -> 16753.75 | L17: =F17*350% -> 117276.25 | M17: =F17*100% -> 33507.5 | O17: =F17*10% -> 3350.75 | P17: 20000 | Q17: 0 | R17: =SUM(F17:Q17) -> 367553.5 | S17: =5000 -> 5000 | T17: =179017.51 -> 179017.51 | U17: ='[3]DECEMBER 2019'!$H$35 -> 837.6875 | V17: 15548.33 | W17: =S17+T17+U17+V17 -> 200403.53 | X17: 167149.98 | Y17: =R17-W17 -> 167149.98 | Z17: 80000
A18: 10 | B18: AYOBOLU OLAJIDE OLUFUNSHO | D18: MANAGER, INFORMATION | E18: 15 (7) | F18: 31018.84 | H18: =F18*300% -> 93056.52 | I18: =F18*7.5% -> 2326.413 | J18: 40122.19 | K18: =F18*50% -> 15509.42 | L18: =F18*350% -> 108565.94 | M18: =F18*100% -> 31018.84 | O18: =F18*10% -> 3101.884 | P18: 20000 | Q18: 0 | R18: =SUM(F18:Q18) -> 344720.05 | S18: =25000 -> 25000 | T18: =52500 -> 52500 | V18: 15548.33 | W18: =S18+T18+U18+V18 -> 93048.33 | X18: 251671.72 | Y18: =R18-W18 -> 251671.72 | Z18: 80000
A19: 11 | B19: HUSSEIN EGYE MUSA | D19: AM PROTOCOL | E19: 13(10) | F19: =25523.45 -> 25523.45 | H19: =F19*300% -> 76570.35 | I19: =F19*7.5% -> 1914.2587 | K19: =F19*50% -> 12761.725 | L19: =F19*350% -> 89332.075 | M19: =F19*100% -> 25523.45 | O19: =F19*10% -> 2552.345 | P19: 15000 | Q19: 50000 | R19: =SUM(F19:Q19) -> 299177.65 | S19: 50000 | T19: =0 -> 0 | U19: 0 | V19: 7709.76 | W19: =S19+T19+U19+V19 -> 57709.76 | X19: 281467.89 | Y19: =R19-W19 -> 241467.89 | Z19: 80000
A20: 12 | B20: DONALD E. MKPANAM | D20: AM ICT | E20: 13(11) | F20: 26339.3 | H20: =F20*300% -> 79017.9 | I20: =F20*7.5% -> 1975.4475 | K20: =F20*50% -> 13169.65 | L20: =F20*350% -> 92187.55 | M20: =F20*100% -> 26339.3 | N20: =100000 -> 100000 | O20: =F20*10% -> 2633.93 | P20: 15000 | Q20: 0 | R20: =SUM(F20:Q20) -> 356663.08 | U20: ='[2]Jan 2021'!$H$28 -> 658.4825 | V20: 7709.76 | W20: =S20+T20+U20+V20 -> 8368.2425 | X20: 348294.83 | Y20: =R20-W20 -> 348294.83 | Z20: 80000
A21: 13 | B21: JOY HARUNA MAKERI | D21: AM TRAINING | E21: 13(10) | F21: =25523.45 -> 25523.45 | H21: =F21*300% -> 76570.35 | I21: =F21*7.5% -> 1914.2587 | K21: =F21*50% -> 12761.725 | L21: =F21*350% -> 89332.075 | M21: =F21*100% -> 25523.45 | N21: 100000 | O21: =F21*10% -> 2552.345 | P21: 15000 | Q21: =50000+100000 -> 150000 | R21: =SUM(F21:Q21) -> 499177.65 | V21: =7709.76 -> 7709.76 | W21: =SUM(S21:V21) -> 7709.76 | X21: 491467.89 | Y21: =R21-W21 -> 491467.89 | Z21: 80000
A22: 14 | B22: ALI ABDULLAHI | D22: AM ICT | E22: 13(11) | F22: =26339.3 -> 26339.3 | H22: =F22*300% -> 79017.9 | I22: =F22*7.5% -> 1975.4475 | J22: 0 | K22: =F22*50% -> 13169.65 | L22: =F22*350% -> 92187.55 | M22: =F22*100% -> 26339.3 | N22: =100000 -> 100000 | O22: =F22*10% -> 2633.93 | P22: 15000 | Q22: =0 -> 0 | R22: =SUM(F22:Q22) -> 356663.08 | V22: =7709.76 -> 7709.76 | W22: =S22+T22+U22+V22 -> 7709.76 | X22: 348953.32 | Y22: =R22-W22 -> 348953.32 | Z22: 80000
A23: 15 | B23: MARIAM MOHAMMED BELLO | D23: PA- SPECIAL DUTIES | E23: 13 (7) | F23: =23074.99 -> 23074.99 | H23: =F23*300% -> 69224.97 | I23: =F23*7.5% -> 1730.6243 | J23: 0 | K23: =F23*50% -> 11537.495 | L23: =F23*350% -> 80762.465 | M23: =F23*100% -> 23074.99 | O23: =F23*10% -> 2307.499 | P23: 15000 | Q23: =100000 -> 100000 | R23: =SUM(F23:Q23) -> 326713.03 | V23: =7709.76 -> 7709.76 | W23: =S23+T23+U23+V23 -> 7709.76 | X23: 319003.27 | Y23: =R23-W23 -> 319003.27 | Z23: 80000
A24: 16 | B24: ADUGBA RICHARD TERSEER | D24: INFORMATION OFFICER | E24: 10(9) | F24: =18281.64 -> 18281.64 | H24: =F24*300% -> 54844.92 | I24: =F24*7.5% -> 1371.123 | K24: =F24*50% -> 9140.82 | L24: =F24*350% -> 63985.74 | M24: =F24*100% -> 18281.64 | O24: =F24*10% -> 1828.164 | P24: 10000 | R24: =SUM(F24:Q24) -> 177734.05 | S24: =20000 -> 20000 | T24: =111833.33 -> 111833.33 | V24: 3369.51 | W24: =S24+T24+U24+V24 -> 135202.84 | X24: 42531.207 | Y24: =R24-W24 -> 42531.207 | Z24: 50000
A25: 17 | B25: CHRISTIAN MADUABUCHI ODO | D25: ICT OFFICER | E25: 10(11) | F25: =19276.95 -> 19276.95 | H25: =F25*300% -> 57830.85 | I25: =F25*7.5% -> 1445.7713 | K25: =F25*50% -> 9638.475 | L25: =F25*350% -> 67469.325 | M25: =F25*100% -> 19276.95 | N25: =100000 -> 100000 | O25: =F25*10% -> 1927.695 | P25: 10000 | R25: =SUM(F25:Q25) -> 286866.02 | S25: =20000 -> 20000 | T25: =82500 -> 82500 | U25: ='[2]Jan 2021'!$H$47 -> 481.92375 | V25: 3369.51 | W25: =S25+T25+U25+V25 -> 106351.43 | X25: 180514.58 | Y25: =R25-W25 -> 180514.58 | Z25: 50000
A26: 18 | B26: VICTOR ASUKWO | D26: ICT OFFICER | E26: 8 (9) | F26: =13112.16 -> 13112.16 | H26: =F26*300% -> 39336.48 | I26: =F26*7.5% -> 983.412 | K26: =F26*50% -> 6556.08 | L26: =F26*350% -> 45892.56 | M26: =F26*100% -> 13112.16 | N26: =100000 -> 100000 | O26: =F26*10% -> 1311.216 | P26: 10000 | R26: =SUM(F26:Q26) -> 230304.07 | S26: =10000 -> 10000 | V26: 1484.37 | W26: =S26+T26+U26+V26 -> 11484.37 | X26: 218819.7 | Y26: =R26-W26 -> 218819.7 | Z26: 50000
A27: 19 | B27: SULEIMAN ABUBAKAR SODEEQ | D27: ASST. ADMIN. OFFICER | E27: 8(7) | F27: =12351.94 -> 12351.94 | H27: =F27*300% -> 37055.82 | I27: =F27*7.5% -> 926.3955 | K27: =F27*50% -> 6175.97 | L27: =F27*350% -> 43231.79 | M27: =F27*100% -> 12351.94 | O27: =F27*10% -> 1235.194 | P27: 10000 | R27: =SUM(F27:Q27) -> 123329.05 | V27: =1235.19 -> 1235.19 | W27: =SUM(S27:V27) -> 1235.19 | X27: 122093.86 | Y27: =R27-W27 -> 122093.86 | Z27: =50000 -> 50000
A28: 20 | B28: YAKUB OLUWATOYIN USMAN | D28: ASST. ADMIN. OFFICER | E28: 8(7) | F28: =12351.94 -> 12351.94 | H28: =F28*300% -> 37055.82 | I28: =F28*7.5% -> 926.3955 | K28: =F28*50% -> 6175.97 | L28: =F28*350% -> 43231.79 | M28: =F28*100% -> 12351.94 | O28: =F28*10% -> 1235.194 | P28: 10000 | R28: =SUM(F28:Q28) -> 123329.05 | S28: =10000 -> 10000 | V28: =1235.19 -> 1235.19 | W28: =SUM(S28:V28) -> 11235.19 | X28: 112093.86 | Y28: =R28-W28 -> 112093.86 | Z28: =50000 -> 50000
A29: 21 | B29: ANTHONY EDET | D29: ASST. MGR M&E | E29: 13(8) | F29: =23891.12 -> 23891.12 | H29: =F29*300% -> 71673.36 | I29: =F29*7.5% -> 1791.834 | J29: 0 | K29: =F29*50% -> 11945.56 | L29: =F29*350% -> 83618.92 | M29: =F29*100% -> 23891.12 | N29: =100000 -> 100000 | O29: =F29*10% -> 2389.112 | P29: 15000 | Q29: 0 | R29: =SUM(F29:Q29) -> 334201.03 | S29: 10000 | U29: ='[2]Jan 2021'!$H$39 -> 597.278 | V29: =7709.76 -> 7709.76 | W29: =SUM(S29:V29) -> 18307.038 | X29: 315893.99 | Y29: =R29-W29 -> 315893.99 | Z29: 80000
A30: 22 | B30: EGUATU U. ONYEJELEM | D30: OFFICER M&E | E30: 10(9) | F30: =18281.64 -> 18281.64 | H30: =F30*300% -> 54844.92 | I30: =F30*7.5% -> 1371.123 | K30: =F30*50% -> 9140.82 | L30: =F30*350% -> 63985.74 | M30: =F30*100% -> 18281.64 | N30: =100000 -> 100000 | O30: =F30*10% -> 1828.164 | P30: 10000 | R30: =SUM(F30:Q30) -> 277734.05 | S30: =20000 -> 20000 | T30: =87500+43750 -> 131250 | V30: 3369.51 | W30: =SUM(S30:V30) -> 154619.51 | X30: 123114.54 | Y30: =R30-W30 -> 123114.54 | Z30: =50000 -> 50000
A31: 23 | B31: ODEH SUZIE | D31: ADMIN. OFFICER, LIASION OFFICE | E31: 10(8) | F31: =17784 -> 17784 | H31: =F31*300% -> 53352 | I31: =F31*7.5% -> 1333.8 | K31: =F31*50% -> 8892 | L31: =F31*350% -> 62244 | M31: =F31*100% -> 17784 | O31: =F31*10% -> 1778.4 | P31: 10000 | R31: =SUM(F31:Q31) -> 173168.2 | S31: =30000+20000 -> 50000 | U31: =0 -> 0 | V31: 3369.51 | W31: =S31+T31+U31+V31 -> 53369.51 | X31: 119798.69 | Y31: =R31-W31 -> 119798.69 | Z31: =50000 -> 50000
A32: 24 | B32: TESSNEEM IBRAHIM | D32: ASSIST. INFORMATION | E32: 8(8) | F32: =12732 -> 12732 | H32: =F32*300% -> 38196 | I32: =F32*7.5% -> 954.9 | K32: =F32*50% -> 6366 | L32: =F32*350% -> 44562 | M32: =F32*100% -> 12732 | O32: =F32*10% -> 1273.2 | P32: 10000 | R32: =SUM(F32:Q32) -> 126816.1 | S32: =10000 -> 10000 | U32: =0 -> 0 | V32: =1235.19 -> 1235.19 | W32: =S32+T32+U32+V32 -> 11235.19 | X32: 115580.91 | Y32: =R32-W32 -> 115580.91 | Z32: =50000 -> 50000
B33: TOTAL | D33: 24 | F33: =SUM(F9:F32) -> 810273.91 | H33: =SUM(H9:H32) -> 2270333 | I33: =SUM(I9:I32) -> 96880.517 | J33: =SUM(J9:J32) -> 521588.47 | K33: =SUM(K9:K32) -> 397112.52 | L33: =SUM(L9:L32) -> 2274248.1 | M33: =SUM(M9:M32) -> 770151.73 | N33: =SUM(N9:N32) -> 1200000 | O33: =SUM(O9:O32) -> 81027.396 | ... W33: =SUM(W9:W32) -> 1933796.7 | X33: 7578053.9 | Y33: =SUM(Y9:Y32) -> 7538053.9 | Z33: =SUM(Z9:Z32) -> 1900000
B35: INTERNAL AUDIT
A36: 1 | B36: NWOSU MATHEW EZE | D36: Ag. DIRECTOR INT. AUDIT | E36: 17(8) | F36: =79039.64 -> 79039.64 | H36: =F36*300% -> 237118.92 | I36: =F36*7.5% -> 5927.973 | J36: =80244.38 -> 80244.38 | K36: =F36*50% -> 39519.82 | L36: =F36*350% -> 276638.74 | M36: =F36*100% -> 79039.64 | O36: =F36*10% -> 7903.964 | P36: 20000 | Q36: 0 | R36: =SUM(F36:Q36) -> 825433.08 | S36: =100000 -> 100000 | T36: =287500 -> 287500 | U36: ='[2]Jan 2021'!$H$23 -> 1975.991 | V36: =52776.63 -> 52776.63 | W36: =S36+T36+U36+V36 -> 442252.62 | X36: 383180.46 | Y36: =R36-W36 -> 383180.46 | Z36: =100000 -> 100000
