Workbook

Sheet April 2012
W1: Page 1 of 2
A3: STAFF PAYROLL FOR THE MONTH OF april 2012.
F4: ='[1]FEB 08'!E8/'[1]FEB 08'!M8 -> 0.22 | J4: ='[1]FEB 08'!F8/'[1]FEB 08'!Q8 -> 0.3
A5: STAFF NAME | V5: NET SALARY | W5: NET SALARY
D6: DESIGNATION | E6: SALARY | F6: BASIC | G6: 28 DAYS ALCE | H6: 40969 | N6: PERSONAL | O6: MOTOR/ | P6: RESEARCH | Q6: LEAVE | R6: OUT FIT | S6: LEGISLATIVE | T6: GROSS | W6: April
E7: LEVEL | F7: SALARY | G7: IN LIEU | H7: AREARS | I7: RENT | J7: UTILITY | K7: DOMESTIC | L7: ENTERT. | M7: FURNIT. | N7: ASSISTANT | O7: FUEL | P7: ALLOWANCE | Q7: ALLCE | R7: ALLCE | S7: DUTY ALLCE | T7: SALARY | U7: PAYE
A8: DG OFFICE | F8: N | J8: N | T8: N | U8: N | W8: N
A9: DR LADI HAMALAI | D9: DG | E9: CONSOL | F9: 160488.75 | G9: 0 | I9: 320977.5 | J9: 48146.63 | K9: 120366.57 | L9: 72219.94 | M9: 481466.25 | N9: 40122.19 | O9: 120366.57 | P9: 150000 | Q9: 16048.88 | R9: 25000 | S9: 25235 | T9: =SUM(F9:S9) -> 1580438.3 | U9: 0 | V9: =T9-U9 -> 1580438.3 | W9: 1880438.3
A10: PROF. OFFORNZE AMUCHEAZI | D10: LEGAL ADVISER | E10: 16(7) | F10: =F21 -> 39662.25 | G10: 0 | I10: =I21 -> 118986.75 | J10: =J21 -> 2974.6687 | K10: =K21 -> 40122.19 | L10: =F10*50% -> 19831.125 | M10: =F10*350% -> 138817.88 | N10: 0 | O10: =F10*100% -> 39662.25 | P10: 0 | Q10: =F10*10% -> 3966.225 | R10: 20000 | S10: 0 | T10: =SUM(F10:S10) -> 424023.33 | U10: 0 | V10: =T10-U10 -> 424023.33 | W10: =T10-U10 -> 424023.33
A11: MOHAMMED ISIAKA YAKUBU | D11: SPECIAL ASSISTANT | E11: 16(7) | F11: =F10 -> 39662.25 | G11: 0 | I11: =I10 -> 118986.75 | J11: =J10 -> 2974.6687 | K11: 40122.19 | L11: 19831.13 | M11: 138817.88 | N11: 0 | O11: 39662.25 | P11: 0 | Q11: 3966.23 | R11: =R10 -> 20000 | S11: 0 | T11: 424023.33 | U11: 0 | V11: =T11-U11 -> 424023.33 | W11: 424023.33
A12: RICHARD KWALMI | D12: MICT | E12: 15(7) | F12: 31018.9 | G12: 0 | I12: =F12*300% -> 93056.7 | J12: =F12*7.5% -> 2326.4175 | K12: =K9/3 -> 40122.19 | L12: =F12*50% -> 15509.45 | M12: =F12*350% -> 108566.15 | N12: 0 | O12: =F12*100% -> 31018.9 | P12: 0 | Q12: =F12*10% -> 3101.89 | R12: 20000 | S12: 0 | T12: =SUM(F12:S12) -> 344720.6 | U12: 0 | V12: =T12-U12 -> 344720.6 | W12: =T12-U12 -> 344720.6
A13: KENNETH OKEREAFOR | D13: AM MICT | E13: 13(7) | F13: 23891.12 | G13: 252000 | I13: =F13*300% -> 71673.36 | J13: =F13*7.5% -> 1791.834 | K13: 0 | L13: =F13*50% -> 11945.56 | M13: =F13*350% -> 83618.92 | N13: 0 | O13: =F13*100% -> 23891.12 | P13: 0 | Q13: =F13*10% -> 2389.112 | R13: 15000 | S13: 0 | T13: =SUM(F13:S13) -> 486201.03 | U13: 0 | V13: =T13-U13 -> 486201.03 | W13: 0
A14: ABDULSALAM MUSTAFA | D14: ICT OFFICER | E14: 10(10) | F14: 18234.42 | G14: 0 | I14: =F14*300% -> 54703.26 | J14: =F14*7.5% -> 1367.5815 | K14: 0 | L14: =F14*50% -> 9117.21 | M14: =F14*350% -> 63820.47 | N14: 0 | O14: =F14*100% -> 18234.42 | P14: 0 | Q14: =F14*10% -> 1823.442 | R14: 15000 | S14: 0 | T14: =SUM(F14:S14) -> 182300.8 | U14: 0 | V14: =T14-U14 -> 182300.8 | W14: =T14-U14 -> 182300.8
A15: ALI ABDULLAHI | D15: 1CT ASSISTANT | E15: 8(7) | F15: 12351.94 | G15: 0 | I15: =F15*300% -> 37055.82 | J15: =F15*7.5% -> 926.3955 | K15: 0 | L15: =F15*50% -> 6175.97 | M15: =F15*350% -> 43231.79 | N15: 0 | O15: =F15*100% -> 12351.94 | P15: 0 | Q15: =F15*10% -> 1235.194 | R15: 10000 | S15: 0 | T15: =SUM(F15:S15) -> 123329.05 | V15: =T15-U16 -> 123329.05 | W15: 105890.22
A16: MKPANAM DONALD EFFIONG | D16: ICT ASSISTANT | E16: 8(7) | F16: 12351.94 | G16: 252000 | I16: =F16*300% -> 37055.82 | J16: =F16*7.5% -> 926.3955 | L16: =F16*50% -> 6175.97 | M16: =F16*350% -> 43231.79 | O16: =F16*100% -> 12351.94 | P16: 0 | Q16: =F16*10% -> 1235.194 | R16: 10000 | S16: 0 | T16: =SUM(F16:S16) -> 375329.05 | U16: 0 | V16: =T16-U17 -> 375329.05 | W16: 0
A17: TOTAL | D17: 8 | F17: =SUM(F9:F16) -> 337661.57 | G17: =SUM(G9:G16) -> 504000 | H17: =SUM(H9:H16) -> 0 | I17: =SUM(I9:I16) -> 852495.96 | J17: =SUM(J9:J16) -> 61434.591 | K17: =SUM(K9:K16) -> 240733.14 | L17: =SUM(L9:L16) -> 160806.36 | M17: =SUM(M9:M16) -> 1101571.1 | ... W17: =SUM(W9:W16) -> 3361396.6
G18: 0
A20: LEG. SUPPORT SEVICES
A21: DR SHUIBU DANWANKA | D21: DD | E21: 16(7) | F21: 39662.25 | G21: 0 | I21: =F21*300% -> 118986.75 | J21: =F21*7.5% -> 2974.6687 | K21: =K12 -> 40122.19 | L21: =F21*50% -> 19831.125 | M21: =F21*350% -> 138817.88 | N21: 0 | O21: =F21*100% -> 39662.25 | P21: 100000 | Q21: =F21*10% -> 3966.225 | R21: 20000 | S21: 0 | T21: =SUM(F21:S21) -> 524023.33 | U21: 0 | V21: =T21-U21 -> 524023.33 | W21: 724023.33
A22: TOTAL | D22: 1 | F22: =SUM(F21) -> 39662.25 | G22: 0 | H22: 0 | I22: =SUM(I21) -> 118986.75 | J22: =SUM(J21) -> 2974.6687 | K22: =SUM(K21) -> 40122.19 | L22: =SUM(L21) -> 19831.125 | M22: =SUM(M21) -> 138817.88 | N22: =SUM(N21) -> 0 | O22: =SUM(O21) -> 39662.25 | P22: =SUM(P21) -> 100000 | ... W22: =SUM(W21) -> 724023.33
A24: RESEARCH & TRAINING
A25: DR ASIMIYU G. ABIOLA | D25: DD RESEARCH | E25: 16(7) | F25: =F21 -> 39662.25 | G25: 0 | I25: =I21 -> 118986.75 | J25: =J21 -> 2974.6687 | K25: =K21 -> 40122.19 | L25: =L21 -> 19831.125 | M25: =F25*350% -> 138817.88 | N25: 0 | O25: =F25*100% -> 39662.25 | P25: =P21 -> 100000 | Q25: =F25*10% -> 3966.225 | R25: 20000 | S25: 0 | T25: =SUM(F25:S25) -> 524023.33 | U25: 0 | V25: =T25-U25 -> 524023.33 | W25: 724023.33
A26: SOLOMON A. BENJAMIN | D26: DD TRAINING | E26: 16(7) | F26: =F22 -> 39662.25 | G26: 0 | I26: =I22 -> 118986.75 | J26: =J22 -> 2974.6687 | K26: =K22 -> 40122.19 | L26: =L22 -> 19831.125 | M26: =F26*350% -> 138817.88 | N26: 0 | O26: =F26*100% -> 39662.25 | P26: =P22 -> 100000 | Q26: =F26*10% -> 3966.225 | R26: 20000 | S26: 0 | T26: =SUM(F26:S26) -> 524023.33 | U26: =U22 -> 0 | V26: =T26-U26 -> 524023.33 | W26: 724023.33
A27: DR PATTERSON EKEOCHA | D27: SRF | E27: 15(9) | F27: 33507.5 | G27: 0 | I27: =F27*300% -> 100522.5 | J27: =F27*7.5% -> 2513.0625 | K27: =K12 -> 40122.19 | L27: =F27*50% -> 16753.75 | M27: =F27*350% -> 117276.25 | N27: 0 | O27: =F27*100% -> 33507.5 | P27: 100000 | Q27: =F27*10% -> 3350.75 | R27: 20000 | S27: 0 | T27: =SUM(F27:S27) -> 467553.5 | U27: 0 | V27: =T27-U27 -> 467553.5 | W27: 667553.5
A28: CATHERINE E. IKOKOH | D28: RESEARCH FELLOW 1 | E28: 13(7) | F28: 23891.12 | G28: 252000 | H28: 131762 | I28: =F28*300% -> 71673.36 | J28: =F28*7.5% -> 1791.834 | K28: =K13 -> 0 | L28: =F28*50% -> 11945.56 | M28: =F28*350% -> 83618.92 | N28: 0 | O28: =F28*100% -> 23891.12 | P28: 80000 | Q28: =F28*10% -> 2389.112 | R28: 15000 | S28: 0 | T28: =SUM(F28:S28) -> 697963.03 | U28: 0 | V28: =T28-U28 -> 697963.03 | W28: 0
A29: ALIYU SANNI ABUBAKAR | D29: DATA & DOCU. OFFICER | E29: 10(7) | F29: 17286.33 | G29: 252000 | I29: =F29*300% -> 51858.99 | J29: =F29*7.5% -> 1296.4748 | K29: =K13 -> 0 | L29: =F29*50% -> 8643.165 | M29: =F29*350% -> 60502.155 | N29: 0 | O29: =F29*100% -> 17286.33 | P29: 40000 | Q29: =F29*10% -> 1728.633 | R29: 10000 | S29: 0 | T29: =SUM(F29:S29) -> 460602.08 | V29: 0 | W29: 0
A30: TOTAL | D30: 5 | F30: =SUM(F25:F29) -> 154009.45 | G30: =SUM(G25:G29) -> 504000 | H30: =SUM(H25:H29) -> 131762 | I30: =SUM(I25:I29) -> 462028.35 | J30: =SUM(J25:J29) -> 11550.709 | K30: =SUM(K25:K29) -> 120366.57 | L30: =SUM(L25:L29) -> 77004.725 | M30: =SUM(M25:M29) -> 539033.07 | ... W30: =SUM(W25:W29) -> 2115600.2
A32: FINANCE & ADMIN.
A33: DR KABIR AHMED | D33: DFA | E33: 17(7) | F33: ='17.7'!E4 -> 76339.3 | G33: 0 | I33: =F33*300% -> 229017.9 | J33: =F33*7.5% -> 5725.4475 | K33: ='17.7'!E7 -> 80244.38 | L33: =F33*50% -> 38169.65 | M33: =F33*350% -> 267187.55 | N33: 0 | O33: =F33*100% -> 76339.3 | P33: 0 | Q33: =F33*10% -> 7633.93 | R33: 20000 | S33: 0 | T33: =SUM(F33:S33) -> 800657.46 | U33: 0 | V33: =T33-U33 -> 800657.46 | W33: 712778.05
A34: IBRAHIM M. MSHELIA | D34: DD F&A | E34: 16(7) | F34: 39662.25 | G34: 0 | I34: =F34*300% -> 118986.75 | J34: =F34*7.5% -> 2974.6687 | K34: =K26 -> 40122.19 | L34: =F34*50% -> 19831.125 | M34: =F34*350% -> 138817.88 | N34: 0 | O34: =F34*100% -> 39662.25 | P34: 0 | Q34: =F34*10% -> 3966.225 | R34: 20000 | S34: 0 | T34: =SUM(F34:S34) -> 424023.33 | U34: 0 | V34: =T34-U34 -> 424023.33 | W34: =T34-U34 -> 424023.33
A35: AMINU BELLO DUKKU | D35: DD ADMIN/HR | E35: 16(7) | F35: 39662.25 | G35: 0 | I35: =F35*300% -> 118986.75 | J35: =F35*7.5% -> 2974.6687 | K35: =K27 -> 40122.19 | L35: =F35*50% -> 19831.125 | M35: =F35*350% -> 138817.88 | N35: 0 | O35: =F35*100% -> 39662.25 | P35: 0 | Q35: =F35*10% -> 3966.225 | R35: 20000 | S35: 0 | T35: =SUM(F35:S35) -> 424023.33 | U35: 0 | V35: =T35-U35 -> 424023.33 | W35: =T35-U35 -> 424023.33
A36: KABIR MUHAMMAD SULAIMAN | D36: MANAGER ADMIN&HR | E36: 15(7) | F36: 31018.9 | G36: 364000 | I36: =F36*300% -> 93056.7 | J36: =F36*7.5% -> 2326.4175 | K36: =K35 -> 40122.19 | L36: =F36*50% -> 15509.45 | M36: =F36*350% -> 108566.15 | N36: 0 | O36: =F36*100% -> 31018.9 | P36: 0 | Q36: =F36*10% -> 3101.89 | R36: 20000 | S36: 0 | T36: =SUM(F36:S36) -> 708720.6 | U36: 0 | V36: =T36-U36 -> 708720.6 | W36: 0
A37: PRISCILLA AGWU | D37: MANAGER PROCUREMENT | E37: 15(7) | F37: 31018.9 | G37: 364000 | I37: =F37*300% -> 93056.7 | J37: =F37*7.5% -> 2326.4175 | K37: =K36 -> 40122.19 | L37: =F37*50% -> 15509.45 | M37: =F37*350% -> 108566.15 | N37: 0 | O37: =F37*100% -> 31018.9 | P37: 0 | Q37: =F37*10% -> 3101.89 | R37: 20000 | S37: 0 | T37: =SUM(F37:S37) -> 708720.6 | U37: 0 | V37: =T37-U37 -> 708720.6 | W37: 0
A38: NWOSU MATHEW EZE | D38: MANAGER INT. AUDIT | E38: 15(7) | F38: 31018.9 | G38: 364000 | I38: =F38*300% -> 93056.7 | J38: =F38*7.5% -> 2326.4175 | K38: =K37 -> 40122.19 | L38: =F38*50% -> 15509.45 | M38: =F38*350% -> 108566.15 | N38: 0 | O38: =F38*100% -> 31018.9 | P38: 0 | Q38: =F38*10% -> 3101.89 | R38: 20000 | S38: 0 | T38: =SUM(F38:S38) -> 708720.6 | U38: 0 | V38: =T38-U38 -> 708720.6 | W38: 0
A39: MAGAJI BALA | D39: MANGER ACCOUNTS | E39: 15(7) | F39: 31018.9 | G39: 364000 | I39: =F39*300% -> 93056.7 | J39: =F39*7.5% -> 2326.4175 | K39: =K38 -> 40122.19 | L39: =F39*50% -> 15509.45 | M39: =F39*350% -> 108566.15 | N39: 0 | O39: =F39*100% -> 31018.9 | P39: 0 | Q39: =F39*10% -> 3101.89 | R39: 20000 | S39: 0 | T39: =SUM(F39:S39) -> 708720.6 | U39: 0 | V39: =T39-U39 -> 708720.6 | W39: 0
A40: RAHILA AMOS | D40: OFFICER ACCTS | E40: 10(11) | F40: 18732 | G40: 0 | I40: =F40*300% -> 56196 | J40: =F40*7.5% -> 1404.9 | K40: 0 | L40: =F40*50% -> 9366 | M40: =F40*350% -> 65562 | N40: 0 | O40: =F40*100% -> 18732 | P40: 0 | Q40: =F40*10% -> 1873.2 | R40: 15000 | S40: 0 | T40: =SUM(F40:S40) -> 186866.1 | U40: 0 | V40: =T40-U40 -> 186866.1 | W40: =T40-U40 -> 186866.1
A41: HUSSEIN MUSA AGYE | D41: PROTOCOL OFFICER | E41: 10(7) | F41: 17286.33 | G41: 0 | I41: =F41*300% -> 51858.99 | J41: =F41*7.5% -> 1296.4748 | K41: 0 | L41: =F41*50% -> 8643.165 | M41: =F41*350% -> 60502.155 | N41: 0 | O41: =F41*100% -> 17286.33 | P41: 0 | Q41: =F41*10% -> 1728.633 | R41: 10000 | S41: 0 | T41: =SUM(F41:S41) -> 168602.08 | U41: 0 | V41: =T41-U41 -> 168602.08 | W41: 420602.08
A42: ABDULLAHI YUNUSA | D42: PERSONNEL OFFICER | E42: 10(7) | F42: 17286.33 | G42: 252000 | I42: =F42*300% -> 51858.99 | J42: =F42*7.5% -> 1296.4748 | K42: 0 | L42: =F42*50% -> 8643.165 | M42: =F42*350% -> 60502.155 | N42: 0 | O42: =F42*100% -> 17286.33 | P42: 0 | Q42: =F42*10% -> 1728.633 | R42: 10000 | S42: 0 | T42: =SUM(F42:S42) -> 420602.08 | U42: 0 | V42: =T42-U42 -> 420602.08 | W42: 0
A43: PATIENCE AMUDA BOSAH | D43: PERSONNEL OFFICER | E43: 10(7) | F43: 17286.33 | G43: 252000 | I43: =F43*300% -> 51858.99 | J43: =F43*7.5% -> 1296.4748 | K43: 0 | L43: =F43*50% -> 8643.165 | M43: =F43*350% -> 60502.155 | N43: 0 | O43: =F43*100% -> 17286.33 | P43: 0 | Q43: =F43*10% -> 1728.633 | R43: 10000 | S43: 0 | T43: =SUM(F43:S43) -> 420602.08 | U43: 0 | V43: =T43-U43 -> 420602.08 | W43: 0
A44: MARUF ABDULSALAM | D44: ASSET& MAINT. OFFICER | E44: 10(7) | F44: 17286.33 | G44: 252000 | I44: =F44*300% -> 51858.99 | J44: =F44*7.5% -> 1296.4748 | K44: 0 | L44: =F44*50% -> 8643.165 | M44: =F44*350% -> 60502.155 | N44: 0 | O44: =F44*100% -> 17286.33 | P44: 0 | Q44: =F44*10% -> 1728.633 | R44: 10000 | S44: 0 | T44: =SUM(F44:S44) -> 420602.08 | U44: 0 | V44: =T44-U44 -> 420602.08 | W44: 0
A45: SALIHU LIMAN MAIRAFI | D45: PROCUREMENT OFFICER | E45: 10(7) | F45: 17286.33 | G45: 252000 | I45: =F45*300% -> 51858.99 | J45: =F45*7.5% -> 1296.4748 | K45: 0 | L45: =F45*50% -> 8643.165 | M45: =F45*350% -> 60502.155 | N45: 0 | O45: =F45*100% -> 17286.33 | P45: 0 | Q45: =F45*10% -> 1728.633 | R45: 10000 | S45: 0 | T45: =SUM(F45:S45) -> 420602.08 | U45: 0 | V45: =T45-U45 -> 420602.08 | W45: 0
A46: ANDRAWUS MUSA | D46: STORE OFFICER | E46: 10(7) | F46: 17286.33 | G46: 252000 | I46: =F46*300% -> 51858.99 | J46: =F46*7.5% -> 1296.4748 | K46: 0 | L46: =F46*50% -> 8643.165 | M46: =F46*350% -> 60502.155 | N46: 0 | O46: =F46*100% -> 17286.33 | P46: 0 | Q46: =F46*10% -> 1728.633 | R46: 10000 | S46: 0 | T46: =SUM(F46:S46) -> 420602.08 | U46: 0 | V46: =T46-U46 -> 420602.08 | W46: 0
A47: IBE EZECHI CYRIACUS | D47: PERSONNEL ASSISTANT | E47: 8(7) | F47: 12351.94 | G47: 252000 | I47: =F47*300% -> 37055.82 | J47: =F47*7.5% -> 926.3955 | K47: 0 | L47: =F47*50% -> 6175.97 | M47: =F47*350% -> 43231.79 | N47: 0 | O47: =F47*100% -> 12351.94 | P47: 0 | Q47: =F47*10% -> 1235.194 | R47: 10000 | S47: 0 | T47: =SUM(F47:S47) -> 375329.05 | U47: 0 | V47: =T47-U47 -> 375329.05 | W47: 0
A48: MUHAMMED AGEDE YAHAYA | D48: PERSONNEL ASSISTANT | E48: 8(7) | F48: 12351.94 | G48: 252000 | I48: =F48*300% -> 37055.82 | J48: =F48*7.5% -> 926.3955 | K48: 0 | L48: =F48*50% -> 6175.97 | M48: =F48*350% -> 43231.79 | N48: 0 | O48: =F48*100% -> 12351.94 | P48: 0 | Q48: =F48*10% -> 1235.194 | R48: 10000 | S48: 0 | T48: =SUM(F48:S48) -> 375329.05 | U48: 0 | V48: =T48-U48 -> 375329.05 | W48: 0
A49: EROMOSELE OMONIGBO | D49: PERSONNEL ASSISTANT | E49: 8(7) | F49: 12351.94 | G49: 252000 | I49: =F49*300% -> 37055.82 | J49: =F49*7.5% -> 926.3955 | K49: 0 | L49: =F49*50% -> 6175.97 | M49: =F49*350% -> 43231.79 | N49: 0 | O49: =F49*100% -> 12351.94 | P49: 0 | Q49: =F49*10% -> 1235.194 | R49: 10000 | S49: 0 | T49: =SUM(F49:S49) -> 375329.05 | U49: 0 | V49: =T49-U49 -> 375329.05 | W49: 0
A50: OGUNYOMI ROTIMI | D50: PERSONNEL ASSISTANT | E50: 8(7) | F50: 12351.94 | G50: 252000 | I50: =F50*300% -> 37055.82 | J50: =F50*7.5% -> 926.3955 | K50: 0 | L50: =F50*50% -> 6175.97 | M50: =F50*350% -> 43231.79 | N50: 0 | O50: =F50*100% -> 12351.94 | P50: 0 | Q50: =F50*10% -> 1235.194 | R50: 10000 | S50: 0 | T50: =SUM(F50:S50) -> 375329.05 | U50: 0 | V50: =T50-U50 -> 375329.05 | W50: 0
A51: CYNTHIA CHINENYE OKENMUO | D51: PERSONNEL ASSISTANT | E51: 8(7) | F51: =12351.94*19/30 -> 7822.8953 | G51: 252000 | I51: =F51*300% -> 23468.686 | J51: =F51*7.5% -> 586.71715 | K51: 0 | L51: =F51*50% -> 3911.4477 | M51: =F51*350% -> 27380.134 | N51: 0 | O51: =F51*100% -> 7822.8953 | P51: 0 | Q51: =F51*10% -> 782.28953 | R51: =10000*19/30 -> 6333.3333 | S51: 0 | T51: =SUM(F51:S51) -> 330108.4 | U51: 0 | V51: =T51-U51 -> 330108.4 | W51: 0
A52: SHEHU ABDULLAHI | D52: ACCOUNT ASSISTANT | E52: 8(7) | F52: 12351.94 | G52: 252000 | I52: =F52*300% -> 37055.82 | J52: =F52*7.5% -> 926.3955 | K52: 0 | L52: =F52*50% -> 6175.97 | M52: =F52*350% -> 43231.79 | N52: 0 | O52: =F52*100% -> 12351.94 | P52: 0 | Q52: =F52*10% -> 1235.194 | R52: 10000 | S52: 0 | T52: =SUM(F52:S52) -> 375329.05 | U52: 0 | V52: =T52-U52 -> 375329.05
A53: JESSICA IDAKULA | D53: ACCOUNT ASSISTANT | E53: 8(7) | F53: 12351.94 | G53: 252000 | I53: =F53*300% -> 37055.82 | J53: =F53*7.5% -> 926.3955 | K53: 0 | L53: =F53*50% -> 6175.97 | M53: =F53*350% -> 43231.79 | N53: 0 | O53: =F53*100% -> 12351.94 | P53: 0 | Q53: =F53*10% -> 1235.194 | R53: 10000 | S53: 0 | T53: =SUM(F53:S53) -> 375329.05 | U53: 0 | V53: =T53-U53 -> 375329.05
A54: SIMON YAKUBU WAKAWA | D54: ASSET& MAINT. ASST. | E54: 8(7) | F54: 12351.94 | G54: 252000 | I54: =F54*300% -> 37055.82 | J54: =F54*7.5% -> 926.3955 | K54: 0 | L54: =F54*50% -> 6175.97 | M54: =F54*350% -> 43231.79 | N54: 0 | O54: =F54*100% -> 12351.94 | P54: 0 | Q54: =F54*10% -> 1235.194 | R54: 10000 | S54: 0 | T54: =SUM(F54:S54) -> 375329.05 | U54: 0 | V54: =T54-U54 -> 375329.05 | W54: 0
A55: MARGARET LEONIE DUREKE | D55: PROCUREMENT ASSIST | E55: 8(7) | F55: 12351.94 | G55: 252000 | I55: =F55*300% -> 37055.82 | J55: =F55*7.5% -> 926.3955 | K55: 0 | L55: =F55*50% -> 6175.97 | M55: =F55*350% -> 43231.79 | N55: 0 | O55: =F55*100% -> 12351.94 | P55: 0 | Q55: =F55*10% -> 1235.194 | R55: 10000 | S55: 0 | T55: =SUM(F55:S55) -> 375329.05 | U55: 0 | V55: =T55-U55 -> 375329.05 | W55: 0
A56: BASHIRU ABBA WALI | D56: ASSIT. INT. AUDIT | E56: 8(7) | F56: 12351.94 | G56: 252000 | I56: =F56*300% -> 37055.82 | J56: =F56*7.5% -> 926.3955 | K56: 0 | L56: =F56*50% -> 6175.97 | M56: =F56*350% -> 43231.79 | N56: 0 | O56: =F56*100% -> 12351.94 | P56: 0 | Q56: =F56*10% -> 1235.194 | R56: 10000 | S56: 0 | T56: =SUM(F56:S56) -> 375329.05 | U56: 0 | V56: =T56-U56 -> 375329.05
A57: USMAN WAZIRI | D57: SEC. FINANCE | E57: 8(9) | F57: =F58 -> 13112.2 | G57: 0 | I57: =F57*300% -> 39336.6 | J57: =F57*7.5% -> 983.415 | K57: 0 | L57: =F57*50% -> 6556.1 | M57: =F57*350% -> 45892.7 | N57: 0 | O57: =F57*100% -> 13112.2 | P57: 0 | Q57: =F57*10% -> 1311.22 | R57: 10000 | S57: 0 | T57: =SUM(F57:S57) -> 130304.44 | U57: 0 | V57: =T57-U57 -> 130304.44 | W57: =T57-U57 -> 130304.44
A58: SALAMATU YAKUBU | D58: SECRETARY | E58: 8(9) | F58: =F60 -> 13112.2 | G58: 0 | I58: =F58*300% -> 39336.6 | J58: =F58*7.5% -> 983.415 | K58: 0 | L58: =F58*50% -> 6556.1 | M58: =F58*350% -> 45892.7 | N58: 0 | O58: =F58*100% -> 13112.2 | P58: 0 | Q58: =F58*10% -> 1311.22 | R58: =R60 -> 10000 | S58: =S60 -> 0 | T58: =SUM(F58:S58) -> 130304.44 | U58: 0 | V58: =T58-U58 -> 130304.44 | W58: =T58-U58 -> 130304.44
A59: IDAHOSA JANE CECILIA | D59: SECRETARY | E59: 8/(9) | F59: 13112.2 | G59: 0 | I59: =F59*300% -> 39336.6 | J59: =F59*7.5% -> 983.415 | K59: 0 | L59: =F59*50% -> 6556.1 | M59: =F59*350% -> 45892.7 | N59: 0 | O59: =F59*100% -> 13112.2 | P59: 0 | Q59: =F59*10% -> 1311.22 | R59: 10000 | S59: 0 | T59: =SUM(F59:S59) -> 130304.44 | U59: 0 | V59: =T59-U59 -> 130304.44 | W59: =T59-U59 -> 130304.44
A60: ESTHER WAMINAJE | D60: SECRETARY | E60: 8(9) | F60: =F59 -> 13112.2 | G60: 0 | I60: =F60*300% -> 39336.6 | J60: =F60*7.5% -> 983.415 | K60: 0 | L60: =F60*50% -> 6556.1 | M60: =F60*350% -> 45892.7 | N60: 0 | O60: =F60*100% -> 13112.2 | P60: 0 | Q60: =F60*10% -> 1311.22 | R60: 10000 | S60: 0 | T60: =SUM(F60:S60) -> 130304.44 | U60: 0 | V60: =T60-U60 -> 130304.44 | W60: =T60-U60 -> 130304.44
A61: ANTHONY EDET | D61: RECEPTIONIST | E61: 8(7) | F61: =F15 -> 12351.94 | G61: 0 | I61: =F61*300% -> 37055.82 | J61: =F61*7.5% -> 926.3955 | K61: 0 | L61: =F61*50% -> 6175.97 | M61: =F61*350% -> 43231.79 | N61: 0 | O61: =F61*100% -> 12351.94 | P61: 0 | Q61: =F61*10% -> 1235.194 | R61: 10000 | S61: 0 | T61: =SUM(F61:S61) -> 123329.05 | U61: 0 | V61: =T61-U61 -> 123329.05 | W61: 105890.22
A62: OLATUNJI OYEDELE YUSUF | D62: DRIVER | E62: 4(10) | F62: 4542.35 | G62: 0 | I62: =F62*300% -> 13627.05 | J62: =F62*7.5% -> 340.67625 | K62: 0 | L62: =F62*50% -> 2271.175 | M62: =F62*350% -> 15898.225 | N62: 0 | O62: =F62*100% -> 4542.35 | P62: 0 | Q62: =F62*10% -> 454.235 | R62: 5000 | S62: 0 | T62: =SUM(F62:S62) -> 46676.061 | U62: 0 | V62: =T62-U62 -> 46676.061 | W62: =T62-U62 -> 46676.061
A63: TASIU MOHAMMED | D63: DRIVER | E63: 4(10) | F63: 4542.35 | G63: 0 | I63: =F63*300% -> 13627.05 | J63: =F63*7.5% -> 340.67625 | K63: 0 | L63: =F63*50% -> 2271.175 | M63: =F63*350% -> 15898.225 | N63: 0 | O63: =F63*100% -> 4542.35 | P63: 0 | Q63: =F63*10% -> 454.235 | R63: 5000 | S63: 0 | T63: =SUM(F63:S63) -> 46676.061 | U63: 0 | V63: =T63-U63 -> 46676.061 | W63: =T63-U63 -> 46676.061
A64: JAFARU MUSA | D64: DRIVER | E64: 4(10) | F64: =F69 -> 4542.35 | G64: 0 | I64: =F64*300% -> 13627.05 | J64: =F64*7.5% -> 340.67625 | K64: 0 | L64: =F64*50% -> 2271.175 | M64: =F64*350% -> 15898.225 | N64: 0 | O64: =F64*100% -> 4542.35 | P64: 0 | Q64: =F64*10% -> 454.235 | R64: 5000 | S64: 0 | T64: =SUM(F64:S64) -> 46676.061 | U64: 0 | V64: =T64-U64 -> 46676.061 | W64: =T64-U64 -> 46676.061
A65: NAMADI IDRIS UMAR | D65: DRIVER | E65: 4(10) | F65: =F64 -> 4542.35 | G65: 0 | I65: =F65*300% -> 13627.05 | J65: =F65*7.5% -> 340.67625 | K65: 0 | L65: =F65*50% -> 2271.175 | M65: =F65*350% -> 15898.225 | N65: 0 | O65: =F65*100% -> 4542.35 | P65: 0 | Q65: =F65*10% -> 454.235 | R65: 5000 | S65: 0 | T65: =SUM(F65:S65) -> 46676.061 | U65: 0 | V65: =T65-U65 -> 46676.061 | W65: =T65-U65 -> 46676.061
A66: DANJUMA KAGADAMA | D66: DRIVER | E66: 4(10) | F66: =F65 -> 4542.35 | G66: 0 | I66: =F66*300% -> 13627.05 | J66: =F66*7.5% -> 340.67625 | K66: 0 | L66: =F66*50% -> 2271.175 | M66: =F66*350% -> 15898.225 | N66: 0 | O66: =F66*100% -> 4542.35 | P66: 0 | Q66: =F66*10% -> 454.235 | R66: 5000 | S66: 0 | T66: =SUM(F66:S66) -> 46676.061 | U66: 0 | V66: =T66-U66 -> 46676.061 | W66: =T66-U66 -> 46676.061
A67: MOHAMMED SIAKA | D67: DRIVER | E67: 4(10) | F67: =F66 -> 4542.35 | G67: 0 | I67: =F67*300% -> 13627.05 | J67: =F67*7.5% -> 340.67625 | K67: 0 | L67: =F67*50% -> 2271.175 | M67: =F67*350% -> 15898.225 | N67: 0 | O67: =F67*100% -> 4542.35 | P67: 0 | Q67: =F67*10% -> 454.235 | R67: 5000 | S67: 0 | T67: =SUM(F67:S67) -> 46676.061 | U67: 0 | V67: =T67-U67 -> 46676.061 | W67: =T67-U67 -> 46676.061
A68: ALFRED ISABU | D68: DRIVER | E68: 4(10) | F68: =F67 -> 4542.35 | G68: 0 | I68: =F68*300% -> 13627.05 | J68: =F68*7.5% -> 340.67625 | K68: 0 | L68: =F68*50% -> 2271.175 | M68: =F68*350% -> 15898.225 | N68: 0 | O68: =F68*100% -> 4542.35 | P68: 0 | Q68: =F68*10% -> 454.235 | R68: 5000 | S68: 0 | T68: =SUM(F68:S68) -> 46676.061 | U68: 0 | V68: =T68-U68 -> 46676.061 | W68: =T68-U68 -> 46676.061
A69: USMAN YAHAYA | D69: DRIVER | E69: 4(10) | F69: 4542.35 | G69: 0 | I69: =F69*300% -> 13627.05 | J69: =F69*7.5% -> 340.67625 | K69: 0 | L69: =F69*50% -> 2271.175 | M69: =F69*350% -> 15898.225 | N69: 0 | O69: =F69*100% -> 4542.35 | P69: 0 | Q69: =F69*10% -> 454.235 | R69: 5000 | S69: 0 | T69: =SUM(F69:S69) -> 46676.061 | U69: 0 | V69: =T69-U69 -> 46676.061 | W69: =T69-U69 -> 46676.061
A70: ALIYU YAKUBU | D70: DRIVER | E70: 3(8) | F70: 3904.5 | G70: 0 | I70: =F70*300% -> 11713.5 | J70: =F70*7.5% -> 292.8375 | K70: 0 | L70: =F70*50% -> 1952.25 | M70: =F70*350% -> 13665.75 | N70: 0 | O70: =F70*100% -> 3904.5 | P70: 0 | Q70: =F70*10% -> 390.45 | R70: 5000 | S70: 0 | T70: =SUM(F70:S70) -> 40823.787 | U70: 0 | V70: =T70-U70 -> 40823.787 | W70: =T70-U70 -> 40823.787
A71: ABDULLAHI HARUNA | D71: DRIVER | E71: 3(8) | F71: 3904.5 | G71: 0 | I71: =F71*300% -> 11713.5 | J71: =F71*7.5% -> 292.8375 | K71: 0 | L71: =F71*50% -> 1952.25 | M71: =F71*350% -> 13665.75 | N71: 0 | O71: =F71*100% -> 3904.5 | P71: 0 | Q71: =F71*10% -> 390.45 | R71: 5000 | S71: 0 | T71: =SUM(F71:S71) -> 40823.787 | U71: 0 | V71: =T71-U71 -> 40823.787 | W71: =T71-U71 -> 40823.787
A72: ABDULWAHAB DAHIRU | D72: DISPATCH CLERK | F72: 90000 | G72: 0 | I72: 0 | J72: 0 | K72: 0 | L72: 0 | M72: 0 | N72: 0 | O72: 0 | P72: 0 | Q72: 0 | R72: 0 | S72: 0 | T72: =F72 -> 90000 | U72: 0 | V72: =T72-U72 -> 90000 | W72: =T72-U72 -> 90000
A73: GIDEON B. LAMIDO | D73: DISPATCH CLERK | F73: 90000 | G73: 0 | I73: 0 | J73: 0 | K73: 0 | L73: 0 | M73: 0 | N73: 0 | O73: 0 | P73: 0 | Q73: 0 | R73: 0 | S73: 0 | T73: =F73 -> 90000 | U73: 0 | V73: =T73-U73 -> 90000 | W73: =T73-U73 -> 90000
A74: JOHN JAMBU ASIGAN | D74: STEWARD | F74: 45000 | G74: 0 | I74: 0 | J74: 0 | K74: 0 | L74: 0 | M74: 0 | N74: 0 | O74: 0 | P74: 0 | Q74: 0 | R74: 0 | S74: 0 | T74: =F74 -> 45000 | U74: 0 | V74: =T74-U74 -> 45000 | W74: =T74-U74 -> 45000
A75: AYUBA SULE | D75: STEWARD | F75: 45000 | G75: 0 | I75: 0 | J75: 0 | K75: 0 | L75: 0 | M75: 0 | N75: 0 | O75: 0 | P75: 0 | Q75: 0 | R75: 0 | S75: 0 | T75: =F75 -> 45000 | U75: 0 | V75: =T75-U75 -> 45000 | W75: =T75-U75 -> 45000
A76: EWELIKWA IJEOMA NKOLIKWA | D76: STEWARD | F76: 45000 | G76: 0 | I76: 0 | J76: 0 | K76: 0 | L76: 0 | M76: 0 | N76: 0 | O76: 0 | P76: 0 | Q76: 0 | R76: 0 | S76: 0 | T76: =F76 -> 45000 | U76: 0 | V76: =T76-U76 -> 45000 | W76: =T76-U76 -> 45000
A77: IDREES MAHMOUD | D77: NYSC | F77: 15000 | G77: 0 | I77: 0 | J77: 0 | K77: 0 | L77: 0 | M77: 0 | N77: 0 | O77: 0 | P77: 0 | Q77: 0 | R77: 0 | S77: 0 | T77: =F77 -> 15000 | U77: 0 | V77: =T77-U77 -> 15000 | W77: =T77-U77 -> 15000
A78: BONAHI JULIET KEFAS | D78: NYSC | F78: 15000 | G78: 0 | I78: 0 | J78: 0 | K78: 0 | L78: 0 | M78: 0 | N78: 0 | O78: 0 | P78: 0 | Q78: 0 | R78: 0 | S78: 0 | T78: =F78 -> 15000 | U78: 0 | V78: =T78-U78 -> 15000 | W78: =T78-U78 -> 15000
A79: MMODU IFEOMA A. | D79: NYSC | F79: 15000 | G79: 0 | I79: 0 | J79: 0 | K79: 0 | L79: 0 | M79: 0 | N79: 0 | O79: 0 | P79: 0 | Q79: 0 | R79: 0 | S79: 0 | T79: =F79 -> 15000 | U79: 0 | V79: =T79-U79 -> 15000 | W79: =T79-U79 -> 15000
A80: ADANMA ABALUNAM | D80: NYSC | F80: 15000 | G80: 0 | I80: 0 | J80: 0 | K80: 0 | L80: 0 | M80: 0 | N80: 0 | O80: 0 | P80: 0 | Q80: 0 | R80: 0 | S80: 0 | T80: =F80 -> 15000 | U80: 0 | V80: =T80-U80 -> 15000 | W80: =T80-U80 -> 15000
A81: TOTAL | D81: 48 | F81: =SUM(F33:F80) -> 1005128.3 | G81: =SUM(G33:G80) -> 5236000 | H81: =SUM(H33:H80) -> 0 | I81: =SUM(I33:I80) -> 1890384.8 | J81: =SUM(J33:J80) -> 47259.621 | K81: =SUM(K33:K80) -> 320977.52 | L81: =SUM(L33:L80) -> 315064.14 | M81: =SUM(M33:M80) -> 2205449 | ... W81: =SUM(W33:W80) -> 3625456.9
A82: GRAND TOTAL | F82: =F17+F22+F30+F81 -> 1536461.5 | G82: =G17+G22+G30+G81 -> 6244000 | H82: =H17+H22+H30+H81 -> 131762 | I82: =I17+I22+I30+I81 -> 3323895.9 | J82: =J17+J22+J30+J81 -> 123219.59 | K82: =K17+K22+K30+K81 -> 722199.42 | L82: =L17+L22+L30+L81 -> 572706.34 | M82: =M17+M22+M30+M81 -> 3984871 | ... W82: =W17+W22+W30+W81 -> 9826477
D84: PREPARED BY: | L84: SIGNATURE | Q84: DATE

Sheet MEMO
A1: NATIONAL INSTITUTE FOR LEGISLATIVE STUDIES
A4: INTERNAL MEMO
A7: FROM : DEPUTY DIRCTOR FINANCE & ACCOUNTS
A8: THROUGH: DIRECTOR, FINANCE & ADMIN.
A9: TO: DIRECTOR GENERAL
A10: DATE: 20TH APRIL, 2012
A12: Subject: Payroll for the Month of April, 2012.
A14: Find below the details of NILS Staff Payroll for the month of April, 2012:
E16: APRIL, 2012 | G16: MARCH, 2012
E17: No of | F17: Amount | G17: No of | H17: Amount
E18: Staff | F18: N | G18: Staff | H18: N
A19: 1 | B19: Director General's Office | E19: ='April 2012'!D17 -> 8 | F19: ='April 2012'!V17 -> 3940365.5 | G19: 1 | H19: ='April 2012'!W17 -> 3361396.6
A20: 2 | B20: Leg. Support Services | E20: ='April 2012'!D22 -> 1 | F20: ='April 2012'!V22 -> 524023.33 | G20: 1 | H20: ='April 2012'!W22 -> 724023.33
A21: 3 | B21: Research & Training | E21: ='April 2012'!D30 -> 5 | F21: ='April 2012'!V30 -> 2213563.2 | G21: 3 | H21: ='April 2012'!W30 -> 2115600.2
A22: 4 | B22: Finance/ Admin & HR | E22: ='April 2012'!D81 -> 48 | F22: ='April 2012'!V81 -> 12124738 | G22: 28 | H22: ='April 2012'!W81 -> 3625456.9
E23: 62 | F23: =SUM(F19:F22) -> 18802690 | G23: =SUM(G19:G22) -> 33 | H23: =SUM(H19:H22) -> 9826477
A25: VARIATION IN APRIL, 2012 OVER MARCH,2012 PAYROLL
A27: NET PAY AS PER APRIL, 2012 PAYROLL | H27: =F23 -> 18802690
A28: NET PAY AS PER MARCH, 2012 PAYROLL | H28: =H23 -> 9826477
A29: NET INCREASE IN PAY FOR MARCH, 2012. | H29: =H27-H28 -> 8976212.8
A32: The net Salary Increase is reconciled as follows:
A33: Net Salary for the month of MARCH, 2012 | H33: =H23 -> 9826477
A34: Appendix A: Payment of Salary to Newly Recruited Staff | G34: =4422057.81-208602.08 -> 4213455.7
A35: Appendix B: 28 Days allowance in Lieu of Accomdation to New Staff | G35: =6244000-252000 -> 5992000
A36: Salary Adjustment for 2 Office Assistants | G36: 34877.66
A37: Effect of Payment of Full Salary to DFA in April | G37: 451879.41
A38: Reducing effect of 28 days allowance in Lieu for March | G38: -616000
A39: Reducing Effect of Research allowance arears in March | G39: -1100000 | H39: =SUM(G34:G39) -> 8976212.8
H40: =H33+H39 -> 18802690
A42: Net Salary for the month of APRIL, 2012 | H42: ='April 2012'!V82 -> 18802690
A44: The Director General is requested to consider and approve payment of N18,802,689.78
A45: being April, 2012 Net Salary Payable to NILS Staff.
A48: Mshelia Madu Ibrahim
A49: Deputy Director, Finance & Accounts

Sheet 17.7
A1: SALARY DETAILS OF NILS DIRECTORS
A2: GRADE LEVEL 17 STEP 7
D3: ANNUALLY | E3: MONTHLY
A4: Basic Salary | D4: =E4*12 -> 916071.6 | E4: =sUMMARY!F3 -> 76339.3
A5: Rent Subsidy | D5: =E5*12 -> 2748214.8 | E5: =sUMMARY!H3 -> 229017.9
A6: Utility | D6: =E6*12 -> 68705.37 | E6: =sUMMARY!I3 -> 5725.4475
A7: Domestic Staff Allowance | D7: =E7*12 -> 962932.56 | E7: =sUMMARY!J3 -> 80244.38
A8: Entertainment Allowance | D8: =E8*12 -> 458035.8 | E8: =sUMMARY!K3 -> 38169.65
A9: Furniture Allowance | D9: =E9*12 -> 3206250.6 | E9: =sUMMARY!L3 -> 267187.55
A10: Motor Fuel Allowance | D10: =E10*12 -> 916071.6 | E10: =sUMMARY!N3 -> 76339.3
A11: Leave Allowance | D11: =E11*12 -> 91607.16 | E11: =sUMMARY!O3 -> 7633.93
A12: Outfit Allowance | D12: =E12*12 -> 240000 | E12: =sUMMARY!P3 -> 20000
A13: GROSS SALARY | D13: =E13*12 -> 9607889.5 | E13: =SUM(E4:E12) -> 800657.46

Sheet 16.7
A1: SALARY DETAILS OF NILS DEPUTY DIRECTORS
A2: GRADE LEVEL 16 STEP 7
D3: ANNUALLY | E3: MONTHLY
A4: Basic Salary | D4: =E4*12 -> 475947 | E4: ='April 2012'!F10 -> 39662.25
A5: Rent Subsidy | D5: =E5*12 -> 1427841 | E5: ='April 2012'!I10 -> 118986.75
A6: Utility | D6: =E6*12 -> 35696.025 | E6: ='April 2012'!J10 -> 2974.6687
A7: Domestic Staff Allowance | D7: =E7*12 -> 481466.28 | E7: ='April 2012'!K10 -> 40122.19
A8: Entertainment Allowance | D8: =E8*12 -> 237973.5 | E8: ='April 2012'!L10 -> 19831.125
A9: Furniture Allowance | D9: =E9*12 -> 1665814.5 | E9: ='April 2012'!M10 -> 138817.88
A10: Motor Fuel Allowance | D10: =E10*12 -> 475947 | E10: ='April 2012'!O10 -> 39662.25
A11: Leave Allowance | D11: =E11*12 -> 47594.7 | E11: ='April 2012'!Q10 -> 3966.225
A12: Outfit Allowance | D12: =E12*12 -> 240000 | E12: =sUMMARY!P3 -> 20000
A13: GROSS SALARY | D13: =E13*12 -> 5088280 | E13: =SUM(E4:E12) -> 424023.33

Sheet 15.9
A1: SALARY DETAILS OF NILS SENIOR RESEARCH FELLOWS
A2: GRADE LEVEL 15 STEP 9
D3: ANNUALLY | E3: MONTHLY
A4: Basic Salary | D4: =E4*12 -> 402090 | E4: ='April 2012'!F27 -> 33507.5
A5: Rent Subsidy | D5: =E5*12 -> 1206270 | E5: ='April 2012'!I27 -> 100522.5
A6: Utility | D6: =E6*12 -> 30156.75 | E6: ='April 2012'!J27 -> 2513.0625
A7: Domestic Staff Allowance | D7: =E7*12 -> 481466.28 | E7: ='April 2012'!K27 -> 40122.19
A8: Entertainment Allowance | D8: =E8*12 -> 201045 | E8: ='April 2012'!L27 -> 16753.75
A9: Furniture Allowance | D9: =E9*12 -> 1407315 | E9: ='April 2012'!M27 -> 117276.25
A10: Motor Fuel Allowance | D10: =E10*12 -> 402090 | E10: ='April 2012'!O27 -> 33507.5
A11: Research Allowance | D11: =E11*12 -> 1200000 | E11: 100000
A12: Leave Allowance | D12: =E12*12 -> 40209 | E12: ='April 2012'!Q27 -> 3350.75
A13: Outfit Allowance | D13: =E13*12 -> 240000 | E13: ='April 2012'!R27 -> 20000
A14: GROSS SALARY | D14: =E14*12 -> 5610642 | E14: =SUM(E4:E13) -> 467553.5

Sheet 13.7
A1: SALARY DETAILS OF NILS ASSISTANT MANAGER
A2: GRADE LEVEL 13 STEP 7
D3: ANNUALLY | E3: MONTHLY
A4: Basic Salary | D4: =E4*12 -> 286693.44 | E4: =sUMMARY!F5 -> 23891.12
A5: Rent Subsidy | D5: =E5*12 -> 860080.32 | E5: =sUMMARY!H5 -> 71673.36
A6: Utility | D6: =E6*12 -> 21502.008 | E6: =sUMMARY!I5 -> 1791.834
A7: Domestic Staff Allowance | D7: =E7*12 -> 0 | E7: =sUMMARY!J5 -> 0
A8: Entertainment Allowance | D8: =E8*12 -> 143346.72 | E8: =sUMMARY!K5 -> 11945.56
A9: Furniture Allowance | D9: =E9*12 -> 1003427 | E9: =sUMMARY!L5 -> 83618.92
A10: Motor Fuel Allowance | D10: =E10*12 -> 286693.44 | E10: =sUMMARY!N5 -> 23891.12
A11: Research Allowance | D11: =E11*12 -> 0 | E11: 0
A12: Leave Allowance | D12: =E12*12 -> 28669.344 | E12: =sUMMARY!O5 -> 2389.112
A13: Outfit Allowance | D13: =E13*12 -> 180000 | E13: =sUMMARY!P5 -> 15000
A14: GROSS SALARY | D14: =E14*12 -> 2810412.3 | E14: =SUM(E4:E13) -> 234201.03

Sheet 12.7
D3: ANNUALLY | E3: MONTHLY
A4: Basic Salary | D4: =E4*12 -> 255527.52 | E4: =sUMMARY!F6 -> 21293.96
A5: Rent Subsidy | D5: =E5*12 -> 766582.56 | E5: =sUMMARY!H6 -> 63881.88
A6: Utility | D6: =E6*12 -> 19164.564 | E6: =sUMMARY!I6 -> 1597.047
A7: Domestic Staff Allowance | D7: =E7*12 -> 0 | E7: =sUMMARY!J5 -> 0
A8: Entertainment Allowance | D8: =E8*12 -> 127763.76 | E8: =sUMMARY!K6 -> 10646.98
A9: Furniture Allowance | D9: =E9*12 -> 894346.32 | E9: =sUMMARY!L6 -> 74528.86
A10: Motor Fuel Allowance | D10: =E10*12 -> 255527.52 | E10: =sUMMARY!N6 -> 21293.96
A11: Leave Allowance | D11: =E11*12 -> 25552.752 | E11: =sUMMARY!O6 -> 2129.396
A12: Outfit Allowance | D12: =E12*12 -> 120000 | E12: =sUMMARY!P6 -> 10000
A13: GROSS SALARY | D13: =E13*12 -> 2464465 | E13: =SUM(E4:E12) -> 205372.08

Sheet 10.7
A1: SALARY DETAILS OF NILS RESEARCH OFFICERS
A2: GRADE LEVEL 10 STEP 7
D3: ANNUALLY | E3: MONTHLY
A4: Basic Salary | D4: =E4*12 -> 207435.96 | E4: =sUMMARY!F7 -> 17286.33
A5: Rent Subsidy | D5: =E5*12 -> 622307.88 | E5: =sUMMARY!H7 -> 51858.99
A6: Utility | D6: =E6*12 -> 15557.697 | E6: =sUMMARY!I7 -> 1296.4748
A7: Domestic Staff Allowance | D7: =E7*12 -> 0 | E7: =sUMMARY!J5 -> 0
A8: Entertainment Allowance | D8: =E8*12 -> 103717.98 | E8: =sUMMARY!K7 -> 8643.165
A9: Furniture Allowance | D9: =E9*12 -> 726025.86 | E9: =sUMMARY!L7 -> 60502.155
A10: Motor Fuel Allowance | D10: =E10*12 -> 207435.96 | E10: =sUMMARY!N7 -> 17286.33
A11: Research Allowance | D11: =E11*12 -> 480000 | E11: 40000
A12: Leave Allowance | D12: =E12*12 -> 20743.596 | E12: =sUMMARY!O7 -> 1728.633
A13: Outfit Allowance | D13: =E13*12 -> 120000 | E13: =sUMMARY!P6 -> 10000
A14: GROSS SALARY | D14: =E14*12 -> 2503224.9 | E14: =SUM(E4:E13) -> 208602.08

Sheet 9.7
A1: SALARY DETAILS OF NILS RESEARCH ASSISTANTS
A2: GRADE LEVEL 9 STEP 7
D3: ANNUALLY | E3: MONTHLY
A4: Basic Salary | D4: =E4*12 -> 176833.68 | E4: =sUMMARY!F8 -> 14736.14
A5: Rent Subsidy | D5: =E5*12 -> 530501.04 | E5: =sUMMARY!H8 -> 44208.42
A6: Utility | D6: =E6*12 -> 13262.526 | E6: =sUMMARY!I8 -> 1105.2105
A7: Domestic Staff Allowance | D7: =E7*12 -> 0 | E7: =sUMMARY!J5 -> 0
A8: Entertainment Allowance | D8: =E8*12 -> 88416.84 | E8: =sUMMARY!K8 -> 7368.07
A9: Furniture Allowance | D9: =E9*12 -> 618917.88 | E9: =sUMMARY!L8 -> 51576.49
A10: Motor Fuel Allowance | D10: =E10*12 -> 176833.68 | E10: =sUMMARY!N8 -> 14736.14
A11: Research Assistants | D11: =E11*12 -> 480000 | E11: 40000
A12: Leave Allowance | D12: =E12*12 -> 17683.368 | E12: =sUMMARY!O8 -> 1473.614
A13: Outfit Allowance | D13: =E13*12 -> 120000 | E13: =sUMMARY!P6 -> 10000
A14: GROSS SALARY | D14: =E14*12 -> 2222449 | E14: =SUM(E4:E13) -> 185204.08

Sheet 8.7
D3: ANNUALLY | E3: MONTHLY
A4: Basic Salary | D4: =E4*12 -> 148223.28 | E4: =sUMMARY!F9 -> 12351.94
A5: Rent Subsidy | D5: =E5*12 -> 444669.84 | E5: =sUMMARY!H9 -> 37055.82
A6: Utility | D6: =E6*12 -> 11116.746 | E6: =sUMMARY!I9 -> 926.3955
A7: Domestic Staff Allowance | D7: =E7*12 -> 0 | E7: =sUMMARY!J5 -> 0
A8: Entertainment Allowance | D8: =E8*12 -> 74111.64 | E8: =sUMMARY!K9 -> 6175.97
A9: Furniture Allowance | D9: =E9*12 -> 518781.48 | E9: =sUMMARY!L9 -> 43231.79
A10: Motor Fuel Allowance | D10: =E10*12 -> 148223.28 | E10: =sUMMARY!N9 -> 12351.94
A11: Leave Allowance | D11: =E11*12 -> 14822.328 | E11: =sUMMARY!O9 -> 1235.194
A12: Outfit Allowance | D12: =E12*12 -> 120000 | E12: =sUMMARY!P6 -> 10000
A13: GROSS SALARY | D13: =E13*12 -> 1479948.6 | E13: =SUM(E4:E12) -> 123329.05

Sheet sUMMARY
F1: BASIC | G1: 28 DAYS ALCE | M1: PERSONAL | N1: MOTOR/ | O1: RESEARCH | P1: LEAVE | Q1: OUT FIT | R1: LEGISLATIVE | S1: GROSS | U1: MAR.2012 | V1: FEB. 2012
F2: SALARY | G2: IN LIEU | H2: RENT | I2: UTILITY | J2: DOMESTIC | K2: ENTERT. | L2: FURNIT. | M2: ASSISTANT | N2: FUEL | O2: ALLOWANCE | P2: ALLCE | Q2: ALLCE | R2: DUTY ALLCE | S2: SALARY | T2: PAYE
A3: DIRECTOR | E3: 17/7 | F3: 76339.3 | H3: =F3*300% -> 229017.9 | I3: =F3*7.5% -> 5725.4475 | J3: 80244.38 | K3: =F3*50% -> 38169.65 | L3: =F3*350% -> 267187.55 | M3: 0 | N3: =F3*100% -> 76339.3 | O3: =F3*10% -> 7633.93 | P3: 20000 | Q3: 0 | R3: =SUM(F3:Q3) -> 800657.46
A4: RESEARCH FELLOW I | E4: 14(7) | F4: 24975.81 | G4: 0 | H4: =F4*300% -> 74927.43 | I4: =F4*7.5% -> 1873.1858 | J4: 0 | K4: =F4*50% -> 12487.905 | L4: =F4*350% -> 87415.335 | M4: 0 | N4: =F4*100% -> 24975.81 | O4: 100000 | P4: =F4*10% -> 2497.581 | Q4: 20000 | R4: 0 | S4: =SUM(F4:R4) -> 349153.06 | T4: 0 | U4: =S4-T4 -> 349153.06 | V4: 344720.6
A5: RESEARCH FELLOW II | E5: 13/7 | F5: 23891.12 | H5: =F5*300% -> 71673.36 | I5: =F5*7.5% -> 1791.834 | J5: 0 | K5: =F5*50% -> 11945.56 | L5: =F5*350% -> 83618.92 | M5: 0 | N5: =F5*100% -> 23891.12 | O5: =F5*10% -> 2389.112 | P5: 15000 | Q5: 0 | R5: =SUM(F5:Q5) -> 234201.03
A6: RESEARCH FELLOW | E6: 12/7 | F6: 21293.96 | H6: =F6*300% -> 63881.88 | I6: =F6*7.5% -> 1597.047 | J6: 0 | K6: =F6*50% -> 10646.98 | L6: =F6*350% -> 74528.86 | M6: 0 | N6: =F6*100% -> 21293.96 | O6: =F6*10% -> 2129.396 | P6: 10000 | Q6: 0 | R6: =SUM(F6:Q6) -> 205372.08
A7: RESEARCH OFFICER | E7: 10/7 | F7: 17286.33 | H7: =F7*300% -> 51858.99 | I7: =F7*7.5% -> 1296.4748 | J7: 0 | K7: =F7*50% -> 8643.165 | L7: =F7*350% -> 60502.155 | M7: 0 | N7: =F7*100% -> 17286.33 | O7: =F7*10% -> 1728.633 | P7: 10000 | Q7: 0 | R7: =SUM(F7:Q7) -> 168602.08
A8: RESEARCH ASSISTANTS | E8: 9/7 | F8: 14736.14 | H8: =F8*300% -> 44208.42 | I8: =F8*7.5% -> 1105.2105 | J8: 0 | K8: =F8*50% -> 7368.07 | L8: =F8*350% -> 51576.49 | M8: 0 | N8: =F8*100% -> 14736.14 | O8: =F8*10% -> 1473.614 | P8: 10000 | Q8: 0 | R8: =SUM(F8:Q8) -> 145204.08
E9: 8/7 | F9: 12351.94 | H9: =F9*300% -> 37055.82 | I9: =F9*7.5% -> 926.3955 | J9: 0 | K9: =F9*50% -> 6175.97 | L9: =F9*350% -> 43231.79 | M9: 0 | N9: =F9*100% -> 12351.94 | O9: =F9*10% -> 1235.194 | P9: 10000 | Q9: 0 | R9: =SUM(F9:Q9) -> 123329.05

Sheet 14.7
A1: SALARY DETAILS OF NILS RESEARCH FELLOW I
A2: GRADE LEVEL 14 STEP 7
D3: ANNUALLY | E3: MONTHLY
A4: Basic Salary | D4: =E4*12 -> 299709.72 | E4: =sUMMARY!F4 -> 24975.81
A5: Rent Subsidy | D5: =E5*12 -> 899129.16 | E5: =sUMMARY!H4 -> 74927.43
A6: Utility | D6: =E6*12 -> 22478.229 | E6: =sUMMARY!I4 -> 1873.1858
A7: Domestic Staff Allowance | D7: =E7*12 -> 0 | E7: =sUMMARY!J5 -> 0
A8: Entertainment Allowance | D8: =E8*12 -> 149854.86 | E8: =sUMMARY!K4 -> 12487.905
A9: Furniture Allowance | D9: =E9*12 -> 1048984 | E9: =sUMMARY!L4 -> 87415.335
A10: Motor Fuel Allowance | D10: =E10*12 -> 299709.72 | E10: =sUMMARY!N4 -> 24975.81
A11: Research Allowance | D11: =E11*12 -> 1200000 | E11: =sUMMARY!O4 -> 100000
A12: Leave Allowance | D12: =E12*12 -> 29970.972 | E12: =sUMMARY!P4 -> 2497.581
A13: Outfit Allowance | D13: =E13*12 -> 240000 | E13: =sUMMARY!Q4 -> 20000
A14: GROSS SALARY | D14: =E14*12 -> 4189836.7 | E14: =SUM(E4:E13) -> 349153.06

Sheet Sheet2
A1: LIST OF STAFF THAT HAVE ASSUMED DUTY
A2: STAFF NAME
D3: DESIGNATION | E3: SALARY
E4: LEVEL
A5: DG OFFICE
A6: DR LADI HAMALAI | D6: DG | E6: CONSOL
A7: PROF. OFFORNZE AMUCHEAZI | D7: LEGAL ADVISER | E7: 16(7)
A8: MOHAMMED ISIAKA YAKUBU | D8: SPECIAL ASSISTANT | E8: 16(7)
A9: RICHARD KWALMI | D9: DSM | E9: 15(7)
A10: ABDULSALAM MUSTAFA | D10: ICT OFFICER | E10: 10(10)
A11: ALI ABDULLAHI | D11: 1CT ASSISTANT | E11: 8(2)
A13: LEG. SUPPORT SEVICES
A14: DR SHUIBU DANWANKA | D14: DD | E14: 16(7)
A16: RESEARCH & TRAINING
A17: DR ASIMIYU G. ABIOLA | D17: DD RESEARCH | E17: 16(7)
A18: SOLOMON A. BENJAMIN | D18: DD TRAINING | E18: 16(7)
A19: DR PATTERSON EKEOCHA | D19: SRF | E19: 15(9)
A21: FINANCE & ADMIN.
A22: DR KABIR AHMED | D22: DFA | E22: 17(7)
A23: IBRAHIM M. MSHELIA | D23: DD F&A | E23: 16(7)
A24: AMINU BELLO DUKKU | D24: DD ADMIN/HR | E24: 16(7)
A25: RAHILA AMOS | D25: OFFICER ACCTS | E25: 10(11)
A26: HUSSEIN MUSA AGYE | D26: PROTOCOL OFFICER | E26: 10(&)
A27: USMAN WAZIRI | D27: SEC. FINANCE | E27: 8(9)
A28: SALAMATU YAKUBU | D28: SECRETARY | E28: 8(9)
A29: IDAHOSA JANE CECILIA | D29: SECRETARY | E29: 8/(9)
A30: ESTHER WAMINAJE | D30: SECRETARY | E30: 8(9)
A31: ANTHONY EDET | D31: RECEPTIONIST | E31: 8(2)
A32: OLATUNJI OYEDELE YUSUF | D32: DRIVER | E32: 4(10)
A33: TASIU MOHAMMED | D33: DRIVER | E33: 4(10)
... A41: ABDULLAHI HARUNA | D41: DRIVER | E41: 3(8)
A42: ABDULWAHAB DAHIRU | D42: DISPATCH CLERK
A43: GIDEON B. LAMIDO | D43: DISPATCH CLERK
A44: JOHN JAMBU ASIGAN | D44: STEWARD
A45: AYUBA SULE | D45: STEWARD
A46: EWELIKWA IJEOMA NKOLIKWA | D46: STEWARD

Sheet 5.7
A1: SALARY DETAILS OF NILS SENIOR MOTOR DRIVER-MECHANIC
A2: GRADE LEVEL 5 STEP 7
D3: ANNUALLY | E3: MONTHLY
A4: Basic Salary | D4: =E4*12 -> #REF! | E4: ='April 2012'!#REF! -> #REF!
A5: Rent Subsidy | D5: =E5*12 -> #REF! | E5: ='April 2012'!#REF! -> #REF!
A6: Utility | D6: =E6*12 -> #REF! | E6: ='April 2012'!#REF! -> #REF!
A7: Domestic Staff Allowance | D7: =E7*12 -> 0 | E7: =sUMMARY!J5 -> 0
A8: Entertainment Allowance | D8: =E8*12 -> #REF! | E8: ='April 2012'!#REF! -> #REF!
A9: Furniture Allowance | D9: =E9*12 -> #REF! | E9: ='April 2012'!#REF! -> #REF!
A10: Motor Fuel Allowance | D10: =E10*12 -> #REF! | E10: ='April 2012'!#REF! -> #REF!
A11: Research Allowance | D11: =E11*12 -> 0 | E11: 0
A12: Leave Allowance | D12: =E12*12 -> #REF! | E12: ='April 2012'!#REF! -> #REF!
A13: Outfit Allowance | D13: =E13*12 -> #REF! | E13: ='April 2012'!#REF! -> #REF!
A14: GROSS SALARY | D14: =E14*12 -> #REF! | E14: =SUM(E4:E13) -> #REF!
