Workbook

Sheet JANUARY 2024
A1: CONTRACT/SABBATICAL AND NYSC SALARY FOR THE MONTH OF JANUARY
A3: S/N | B3: STAFF NAME | C3: DESIGNATION | D3: BASIC ALLOWANCE | E3: LEGISLATIVE ALLOWCE | F3: GROSS | G3: DEDUCTIONS | K3: JANUARY 2024 NET SALARY
G4: COOP CONTR | H4: COOP LOAN RECOVERY | I4: PAYE TAX | J4: TOTAL DEDUCTION | K4: N
A5: 1 | B5: Takwasa A. Galadima | C5: Nass Deployed | D5: =136027.8 -> 136027.8 | E5: =60000 -> 60000 | F5: =D5+E5 -> 196027.8 | G5: =30000 -> 30000 | I5: ='[1]August 2022 '!$AD$6 -> 20099.337 | J5: =G5+H5+I5 -> 50099.337 | K5: =F5-J5 -> 145928.46
A6: 2 | B6: Saratu Adamu Attajiri | C6: Office Assistant | D6: 90000 | E6: 30000 | F6: =D6+E6 -> 120000 | G6: 10000 | H6: 40000 | I6: 8900 | J6: =G6+H6+I6 -> 58900 | K6: =F6-J6 -> 61100
A7: 3 | B7: Aboaman Innocent | C7: Casual | D7: 45000 | E7: 15000 | F7: =D7+E7 -> 60000 | G7: =10000 -> 10000 | H7: =10000+10000 -> 20000 | I7: 2446.6667 | J7: =G7+H7+I7 -> 32446.667 | K7: =F7-J7 -> 27553.333
A8: 4 | B8: Kusai E. Richard | C8: Plumber | D8: 45000 | E8: 15000 | F8: =D8+E8 -> 60000 | G8: =10000 -> 10000 | H8: =20000 -> 20000 | I8: 2446.6667 | J8: =G8+H8+I8 -> 32446.667 | K8: =F8-J8 -> 27553.333
A9: 5 | B9: Bulus Ishaya | C9: Gardener | D9: 45000 | E9: 15000 | F9: =D9+E9 -> 60000 | G9: 0 | H9: 0 | I9: 2446.6667 | J9: =G9+H9+I9 -> 2446.6667 | K9: =F9-J9 -> 57553.333
A10: 6 | B10: Alhamdu Iliya | C10: Casual-Gardner | D10: =50000 -> 50000 | E10: 15000 | F10: =D10+E10 -> 65000 | G10: =5000+5000+5000 -> 15000 | H10: =14350 -> 14350 | I10: 2886.6667 | J10: =G10+H10+I10 -> 32236.667 | K10: =F10-J10 -> 32763.333
A11: 7 | B11: Salihu Hassan | C11: Casual-Gardner | D11: =50000 -> 50000 | E11: 15000 | F11: =D11+E11 -> 65000 | G11: =5000 -> 5000 | H11: 0 | I11: 2886.6667 | J11: =G11+H11+I11 -> 7886.6667 | K11: =F11-J11 -> 57113.333
A12: 8 | B12: Ishaya Moro James | C12: Gardener | D12: =60000 -> 60000 | E12: 20000 | F12: =D12+E12 -> 80000 | G12: =10000 -> 10000 | H12: =17500 -> 17500 | I12: 4206.6667 | J12: =G12+H12+I12 -> 31706.667 | K12: =F12-J12 -> 48293.333
A13: 9 | B13: Enobong Sambo | C13: Retainership | D13: =70000 -> 70000 | E13: 20000 | F13: =D13+E13 -> 90000 | G13: =0 -> 0 | H13: 0 | I13: 5300 | J13: =G13+H13+I13 -> 5300 | K13: =F13-J13 -> 84700
A14: 10 | B14: Masarr Sarr | C14: Casual | D14: =90000 -> 90000 | E14: 30000 | F14: =D14+E14 -> 120000 | G14: =0 -> 0 | H14: 0 | I14: 8900 | J14: =G14+H14+I14 -> 8900 | K14: =F14-J14 -> 111100
A15: 11 | B15: Said Idris Abduljalil | C15: Secondment | D15: =105352.17 -> 105352.17 | E15: =(60000+50000) -> 110000 | F15: =D15+E15 -> 215352.17 | G15: =0 -> 0 | H15: 0 | I15: 23345.831 | J15: =G15+H15+I15 -> 23345.831 | K15: =F15-J15 -> 192006.34
A16: 12 | B16: Prof. Peter Siyan | C16: Sabbatical | D16: =502746.92 -> 502746.92 | E16: 180000 | F16: =D16+E16 -> 682746.92 | G16: =0 -> 0 | H16: 0 | I16: 109754.08 | J16: =G16+H16+I16 -> 109754.08 | K16: =F16-J16 -> 572992.84
A17: 13 | B17: Pro. Francis Onyekwere Ozoh | C17: Sabbatical | D17: =555351.17 -> 555351.17 | E17: 180000 | F17: =D17+E17 -> 735351.17 | G17: =0 -> 0 | H17: 0 | I17: =(119693.26) -> 119693.26 | J17: =G17+H17+I17 -> 119693.26 | K17: =F17-J17 -> 615657.91
A18: 14 | B18: Prof. Zubairu Kwambo Dagona | C18: Contract Staff | D18: =800656.58 -> 800656.58 | E18: 200000 | F18: =D18+E18 -> 1000656.6 | G18: =0 -> 0 | H18: 0 | I18: =(170631.89) -> 170631.89 | J18: =G18+H18+I18 -> 170631.89 | K18: =F18-J18 -> 830024.69
A19: 15 | B19: Abdulkareem Toyeeb | C19: NYSC | D19: 25000 | E19: 0 | F19: =D19+E19 -> 25000 | G19: =0 -> 0 | H19: 0 | J19: =G19+H19+I19 -> 0 | K19: =F19-J19 -> 25000
A20: 16 | B20: Akeh Blessing | C20: NYSC | D20: 25000 | E20: 0 | F20: =D20+E20 -> 25000 | G20: =0 -> 0 | H20: 0 | J20: =G20+H20+I20 -> 0 | K20: =F20-J20 -> 25000
A21: 17 | B21: Fasasi Ahmed Olalekan | C21: NYSC | D21: 25000 | E21: 0 | F21: =D21+E21 -> 25000 | G21: =0 -> 0 | H21: 0 | J21: =G21+H21+I21 -> 0 | K21: =F21-J21 -> 25000
A22: 18 | B22: Nwabueze Joy Oluchi | C22: NYSC | D22: 25000 | E22: 0 | F22: =D22+E22 -> 25000 | G22: =0 -> 0 | H22: 0 | J22: =G22+H22+I22 -> 0 | K22: =F22-J22 -> 25000
A23: 19 | B23: Muhammad Kudu Abubakar | C23: Ag. Gen Manager | D23: =424023.33 -> 424023.33 | E23: 90000 | F23: =D23+E23 -> 514023.33 | G23: =0 -> 0 | H23: 0 | I23: =77198.31 -> 77198.31 | J23: =G23+H23+I23 -> 77198.31 | K23: =F23-J23 -> 436825.02
A24: 20 | B24: Prof. Mohammed Mustapha Namadi | C24: Sabbatical | D24: =496425.42 -> 496425.42 | E24: 180000 | F24: =D24+E24 -> 676425.42 | G24: =0 -> 0 | H24: 0 | I24: =108540.35 -> 108540.35 | J24: =G24+H24+I24 -> 108540.35 | K24: =F24-J24 -> 567885.07
A25: 21 | B25: Ibrahim Kaltume Onawo | C25: NYSC (Arrears) | D25: =25000+7500 -> 32500 | E25: 0 | F25: =D25+E25 -> 32500 | G25: =0 -> 0 | H25: 0 | J25: =G25+H25+I25 -> 0 | K25: =F25-J25 -> 32500
A26: 22 | B26: Hassan Mahmud Adewole | C26: NYSC | D26: 25000 | E26: 0 | F26: =D26+E26 -> 25000 | G26: =0 -> 0 | H26: 0 | J26: =G26+H26+I26 -> 0 | K26: =F26-J26 -> 25000
A27: 23 | B27: Nwanganga Chidozie | C27: House Keeper | D27: 60000 | E27: 20000 | F27: =D27+E27 -> 80000 | G27: =0 -> 0 | H27: 0 | I27: =4206.67 -> 4206.67 | J27: =G27+H27+I27 -> 4206.67 | K27: =F27-J27 -> 75793.33
A28: 24 | B28: Mary Shadrach | C28: Cleaner | D28: 55000 | E28: 15000 | F28: =D28+E28 -> 70000 | G28: =0 -> 0 | H28: 0 | I28: =3326.67 -> 3326.67 | J28: =G28+H28+I28 -> 3326.67 | K28: =F28-J28 -> 66673.33
A29: 25 | B29: Akinboboye Oluwatosin Ifedayo | C29: NYSC | D29: 25000 | E29: 0 | F29: =D29+E29 -> 25000 | G29: =0 -> 0 | H29: 0 | J29: =G29+H29+I29 -> 0 | K29: =F29-J29 -> 25000
A30: 26 | B30: Abdulrahim Abdullahi | C30: NYSC | D30: 25000 | F30: =D30+E30 -> 25000 | G30: =0 -> 0 | H30: 0 | J30: =G30+H30+I30 -> 0 | K30: =F30-J30 -> 25000
A31: 27 | B31: Julie G. Sanda | C31: Sabbatical | D31: 410900.75 | E31: 160000 | F31: =D31+E31 -> 570900.75 | G31: =0 -> 0 | H31: 0 | I31: =88279.61 -> 88279.61 | J31: =G31+H31+I31 -> 88279.61 | K31: =F31-J31 -> 482621.14
A32: 28 | B32: Rahimat Suberu Onize | C32: Contract Staff | D32: =123329.05 -> 123329.05 | E32: 50000 | F32: =D32+E32 -> 173329.05 | G32: 20000 | H32: 0 | I32: 16512.68 | J32: =G32+H32+I32 -> 36512.68 | K32: =F32-J32 -> 136816.37
A33: 29 | B33: Ikip Lebo | C33: Contract Staff | D33: =226713 -> 226713 | E33: =70000 -> 70000 | F33: =D33+E33 -> 296713 | G33: =20000 -> 20000 | H33: 0 | I33: =37014.45 -> 37014.45 | J33: =G33+H33+I33 -> 57014.45 | K33: =F33-J33 -> 239698.55
A34: 30 | B34: Yusuf Yusuf Dayyabu | C34: Contract Staff | D34: =145204 -> 145204 | E34: =60000 -> 60000 | F34: =D34+E34 -> 205204 | G34: =0 -> 0 | H34: 0 | I34: 21640.953 | J34: =G34+H34+I34 -> 21640.953 | K34: =F34-J34 -> 183563.05
A35: 31 | B35: Musa Mustapha Adekola | C35: Casual Staff | D35: =90000 -> 90000 | E35: =30000 -> 30000 | F35: =D35+E35 -> 120000 | G35: =0 -> 0 | H35: 0 | I35: =8600 -> 8600 | J35: =G35+H35+I35 -> 8600 | K35: =F35-J35 -> 111400
A36: 32 | B36: Ramatu Ibrahim Abdulrahim | C36: Contract Staff | D36: =123329.05 -> 123329.05 | E36: =50000 -> 50000 | F36: =D36+E36 -> 173329.05 | G36: =50000 -> 50000 | H36: 0 | I36: 16512.68 | J36: =G36+H36+I36 -> 66512.68 | K36: =F36-J36 -> 106816.37
A37: 33 | B37: Rasheedat Daibu | C37: Contract Staff | D37: =168602 -> 168602 | E37: =60000 -> 60000 | F37: =D37+E37 -> 228602 | G37: =0 -> 0 | H37: 0 | I37: =25571.8 -> 25571.8 | J37: =G37+H37+I37 -> 25571.8 | K37: =F37-J37 -> 203030.2
A38: 34 | B38: Ladan Abdulmushin Tawfiq | C38: Contract Staff | D38: 145204 | E38: 60000 | F38: =D38+E38 -> 205204 | G38: =0 -> 0 | H38: 0 | I38: =21640.95 -> 21640.95 | J38: =G38+H38+I38 -> 21640.95 | K38: =F38-J38 -> 183563.05
A39: 35 | B39: Dr. Alabi Adesina Muhydeen | C39: Contract Staff | D39: =226713 -> 226713 | E39: =120000 -> 120000 | F39: =D39+E39 -> 346713 | G39: =0 -> 0 | H39: 0 | I39: =45414.45 -> 45414.45 | J39: =G39+H39+I39 -> 45414.45 | K39: =F39-J39 -> 301298.55
A40: 36 | B40: Lukman Abdullahi Opobiyi | C40: NYSC | D40: 25000 | F40: =D40+E40 -> 25000 | G40: =0 -> 0 | H40: 0 | J40: =G40+H40+I40 -> 0 | K40: =F40-J40 -> 25000
A41: 37 | B41: Zainab Bakare | C41: Contract Staff | D41: =123329.05 -> 123329.05 | E41: =50000 -> 50000 | F41: =D41+E41 -> 173329.05 | G41: =0 -> 0 | H41: 0 | I41: 16512.68 | J41: =G41+H41+I41 -> 16512.68 | K41: =F41-J41 -> 156816.37
A42: 38 | B42: Desmond Cibueze Domendu | C42: Contract Staff | D42: =123329.05 -> 123329.05 | E42: =100000 -> 100000 | F42: =D42+E42 -> 223329.05 | G42: =0 -> 0 | H42: 0 | I42: =28687.49 -> 28687.49 | J42: =G42+H42+I42 -> 28687.49 | K42: =F42-J42 -> 194641.56
A43: 39 | B43: Blessing Ojone Jibrin | C43: Contract Staff | D43: =123329.05 -> 123329.05 | E43: =100000 -> 100000 | F43: =D43+E43 -> 223329.05 | G43: =0 -> 0 | H43: 0 | I43: =28687.49 -> 28687.49 | J43: =G43+H43+I43 -> 28687.49 | K43: =F43-J43 -> 194641.56
A44: 40 | B44: Chicha Ebweyi Joshua | C44: Contract Staff | D44: =123329.05 -> 123329.05 | E44: =100000 -> 100000 | F44: =D44+E44 -> 223329.05 | G44: =0 -> 0 | H44: 0 | I44: =28687.49 -> 28687.49 | J44: =G44+H44+I44 -> 28687.49 | K44: =F44-J44 -> 194641.56
A45: 41 | B45: Amal Zoaka | C45: NYSC | D45: 25000 | F45: =D45+E45 -> 25000 | G45: =0 -> 0 | H45: 0 | J45: =G45+H45+I45 -> 0 | K45: =F45-J45 -> 25000
A46: 42 | B46: Olufemi Emmanuel Oyegoke | C46: Contract Staff | D46: =145204 -> 145204 | E46: =60000 -> 60000 | F46: =D46+E46 -> 205204 | G46: =0 -> 0 | H46: 0 | I46: =21640.95 -> 21640.95 | J46: =G46+H46+I46 -> 21640.95 | K46: =F46-J46 -> 183563.05
A47: 43 | B47: Ngalabak Shugge | C47: Contract Staff | D47: =123329.05 -> 123329.05 | E47: =50000 -> 50000 | F47: =D47+E47 -> 173329.05 | G47: =0 -> 0 | H47: 0 | I47: =16512.68 -> 16512.68 | J47: =G47+H47+I47 -> 16512.68 | K47: =F47-J47 -> 156816.37
A48: 44 | B48: Prof. Shedrack Best Gaya | C48: Sabbatical | D48: =555351.17 -> 555351.17 | E48: 180000 | F48: =D48+E48 -> 735351.17 | G48: =0 -> 0 | H48: 0 | I48: =(119693.26) -> 119693.26 | J48: =G48+H48+I48 -> 119693.26 | K48: =F48-J48 -> 615657.91
A49: 45 | B49: Dr. Hadiza Saidu | C49: Contract | D49: ='[2]SALARY STRUCTURE'!$H$18 -> 344720.17 | E49: =160000 -> 160000 | F49: =D49+E49 -> 504720.17 | G49: =0 -> 0 | H49: 0 | I49: =75436.17 -> 75436.17 | J49: =G49+H49+I49 -> 75436.17 | K49: =F49-J49 -> 429284
A50: 46 | B50: Idris Muhammad Jamiu | C50: NYSC | D50: 25000 | E50: 0 | F50: =D50+E50 -> 25000 | G50: =0 -> 0 | H50: 0 | I50: 0 | J50: =G50+H50+I50 -> 0 | K50: =F50-J50 -> 25000
A51: 47 | B51: Dosumu Taiwo Oluomo | C51: NYSC | D51: 25000 | E51: 0 | F51: =D51+E51 -> 25000 | G51: =0 -> 0 | H51: 0 | I51: 0 | J51: =G51+H51+I51 -> 0 | K51: =F51-J51 -> 25000
A52: 48 | B52: Olarenwaju Abduhameed Olaitan | C52: NYSC | D52: 25000 | E52: 0 | F52: =D52+E52 -> 25000 | G52: =0 -> 0 | H52: 0 | I52: 0 | J52: =G52+H52+I52 -> 0 | K52: =F52-J52 -> 25000
A53: 49 | B53: Galadima Yakubu Takwasa | C53: NYSC | D53: 25000 | E53: 0 | F53: =D53+E53 -> 25000 | G53: =0 -> 0 | H53: 0 | I53: 0 | J53: =G53+H53+I53 -> 0 | K53: =F53-J53 -> 25000
A54: 50 | B54: Dangana Faith | C54: NYSC | D54: 25000 | E54: 0 | F54: =D54+E54 -> 25000 | G54: =0 -> 0 | H54: 0 | I54: 0 | J54: =G54+H54+I54 -> 0 | K54: =F54-J54 -> 25000
A55: 51 | B55: Bankole Bunmi Khadijah | C55: NYSC | D55: 25000 | E55: 0 | F55: =D55+E55 -> 25000 | G55: =0 -> 0 | H55: 0 | I55: 0 | J55: =G55+H55+I55 -> 0 | K55: =F55-J55 -> 25000
A56: 52 | B56: Shittu Deborah Damilola | C56: NYSC | D56: 25000 | E56: 0 | F56: =D56+E56 -> 25000 | G56: =0 -> 0 | H56: 0 | I56: 0 | J56: =G56+H56+I56 -> 0 | K56: =F56-J56 -> 25000
B57: TOTAL | D57: =SUM(D5:D56) -> 7434998.8 | E57: =SUM(E5:E56) -> 2670000 | F57: =SUM(F5:F56) -> 10104999 | G57: =SUM(G5:G56) -> 180000 | H57: =SUM(H5:H56) -> 111850 | I57: =SUM(I5:I56) -> 1294262.2 | J57: =SUM(J5:J56) -> 1586112.2 | K57: =SUM(K5:K56) -> 8518886.6
M139: =60000 -> 60000

Sheet JANUARY 2024 2
A1: CONSULTANCY FEES FOR THE MONTH OF JANUARY 2024
A3: S/N | B3: STAFF NAME | C3: DESIGNATION | D3: TOTAL/GROSS FEES | E3: DEDUCTIONS | I3: NET PAYMENT JANUARY 2024
E4: COOP CONTR | F4: COOP LOAN RECOVERY | G4: WITHOLDING TAX | H4: TOTAL DEDUCTION | I4: N
A5: 1 | B5: Dr. Mohammed Etudaiye | C5: Consultant | D5: =300000 -> 300000 | G5: =D5*0.05 -> 15000 | H5: =E5+F5+G5 -> 15000 | I5: =D5-H5 -> 285000
A6: 2 | B6: Barr. James G Bathna | C6: Consultancy | D6: =300000 -> 300000 | G6: =D6*0.05 -> 15000 | H6: =E6+F6+G6 -> 15000 | I6: =D6-H6 -> 285000
A7: 3 | B7: Dr. John Niyi Olanrewaju | C7: Consultancy | D7: =500000 -> 500000 | E7: =25000 -> 25000 | F7: 60640 | G7: =D7*0.05 -> 25000 | H7: =E7+F7+G7 -> 110640 | I7: =D7-H7 -> 389360
A8: 4 | B8: Dr. Shehu Wahab L | C8: Consultant | D8: 300000 | G8: =D8*0.05 -> 15000 | H8: =E8+F8+G8 -> 15000 | I8: =D8-H8 -> 285000
A9: 5 | B9: Moshood Tsoho Amuda | C9: Consultancy | D9: =500000 -> 500000 | G9: =D9*0.05 -> 25000 | H9: =E9+F9+G9 -> 25000 | I9: =D9-H9 -> 475000
A10: 6 | B10: Inya Joephine Ode | C10: Consultant | D10: =300000 -> 300000 | G10: =D10*0.05 -> 15000 | H10: =E10+F10+G10 -> 15000 | I10: =D10-H10 -> 285000
A11: 7 | B11: Prof Charles U. Ilebune | C11: Consultant | D11: =300000 -> 300000 | G11: =D11*0.05 -> 15000 | H11: =E11+F11+G11 -> 15000 | I11: =D11-H11 -> 285000
A12: 8 | B12: Prof. Maryam Adepeju Abdulraheem-Mustapha | C12: Consultant | D12: =300000*0.77 -> 231000 | G12: =D12*0.05 -> 11550 | H12: =E12+F12+G12 -> 11550 | I12: =D12-H12 -> 219450
A13: 9 | B13: Victoria Stephanie David | C13: Consultancy | D13: =150000 -> 150000 | G13: =D13*0.05 -> 7500 | H13: =E13+F13+G13 -> 7500 | I13: =D13-H13 -> 142500
A14: 10 | B14: Kindness Oluwakemi M | C14: Consultancy | D14: =200000 -> 200000 | G14: =D14*0.05 -> 10000 | H14: =E14+F14+G14 -> 10000 | I14: =D14-H14 -> 190000
A15: 11 | B15: Danladi Idris Daniel | C15: Consultancy | D15: =200000 -> 200000 | G15: =D15*0.05 -> 10000 | H15: =E15+F15+G15 -> 10000 | I15: =D15-H15 -> 190000
A16: 12 | B16: Ufomba Patricia Osinachi | C16: Consultancy | D16: =150000 -> 150000 | G16: =D16*0.05 -> 7500 | H16: =E16+F16+G16 -> 7500 | I16: =D16-H16 -> 142500
A17: 13 | B17: Anayo Akwitti | C17: Consultancy | D17: =200000 -> 200000 | G17: =D17*0.05 -> 10000 | H17: =E17+F17+G17 -> 10000 | I17: =D17-H17 -> 190000
A18: 14 | B18: Otene Oche Jonah | C18: Consultancy (Arrears) | D18: =200000+20000 -> 220000 | G18: =D18*0.05 -> 11000 | H18: =E18+F18+G18 -> 11000 | I18: =D18-H18 -> 209000
A19: 15 | B19: Julian Chinyere Osamoto | C19: Consultancy | D19: =150000 -> 150000 | G19: =D19*0.05 -> 7500 | H19: =E19+F19+G19 -> 7500 | I19: =D19-H19 -> 142500
A20: 16 | B20: Faith Onyebujoh | C20: Consultancy | D20: =200000 -> 200000 | G20: =D20*0.05 -> 10000 | H20: =E20+F20+G20 -> 10000 | I20: =D20-H20 -> 190000
A21: 17 | B21: Dr. Dare Fatai | C21: Consultancy | D21: 300000 | G21: =D21*0.05 -> 15000 | H21: =E21+F21+G21 -> 15000 | I21: =D21-H21 -> 285000
A22: 18 | B22: Alkadriyar Abdullahi Abdullahi | C22: Consultancy | D22: =150000 -> 150000 | G22: =D22*0.05 -> 7500 | H22: =E22+F22+G22 -> 7500 | I22: =D22-H22 -> 142500
A23: 19 | B23: Benjamin Ubiri | C23: Consultancy | D23: 200000 | G23: =D23*0.05 -> 10000 | H23: =E23+F23+G23 -> 10000 | I23: =D23-H23 -> 190000
A24: 20 | B24: Mugisat Abdulganiyyu | C24: Consultancy | D24: 150000 | G24: =D24*0.05 -> 7500 | H24: =E24+F24+G24 -> 7500 | I24: =D24-H24 -> 142500
A25: 21 | B25: Sofiat Adepeju Adenekan | C25: Consultancy | D25: 150000 | G25: =D25*0.05 -> 7500 | H25: =E25+F25+G25 -> 7500 | I25: =D25-H25 -> 142500
A26: 22 | B26: Echianu Chinedu Chikadibia | C26: Consultancy | D26: 150000 | G26: =D26*0.05 -> 7500 | H26: =E26+F26+G26 -> 7500 | I26: =D26-H26 -> 142500
B27: TOTAL | D27: =SUM(D5:D26) -> 5301000 | E27: =SUM(E5:E26) -> 25000 | F27: =SUM(F5:F26) -> 60640 | G27: =SUM(G5:G26) -> 265050 | H27: =SUM(H5:H26) -> 350690 | I27: =SUM(I5:I26) -> 4950310
K109: =60000 -> 60000

Sheet ENHANCED WELFARE 2024
A1: NATIONAL INSTITUTE FOR LEGISLATIVE AND DEMOCRATIC STUDIES
A2: STAFF ENHANCED WELFARE SCHEDULE 2024
A3: STAFF ENHANCED WELFARE SCHEDULE 2024
A4: S/N | B4: STAFF NAME | C4: DESIGNATION | D4: AMOUNT
D5: N
A6: 1 | B6: Takwasa A. Galadima | C6: NASS Deployed | D6: 500000
A7: 2 | B7: Saratu Adamu Attajiri | C7: Office Assistant | D7: 300000
A8: 3 | B8: Aboaman Innocent | C8: Casual | D8: 100000
A9: 4 | B9: Kusai E. Richard | C9: Plumber | D9: 100000
A10: 5 | B10: Bulus Ishaya | C10: Gardener | D10: 100000
A11: 6 | B11: Alhamdu Iliya | C11: Casual-Gardner | D11: 100000
A12: 7 | B12: Salihu Hassan | C12: Casual-Gardner | D12: 100000
A13: 8 | B13: Ishaya Moro James | C13: Gardener | D13: 100000
A14: 9 | B14: Dr. John Niyi Olanrewaju | C14: Contract | D14: 500000
A15: 10 | B15: Enobong Sambo | C15: Retainership | D15: 100000
A16: 11 | B16: Masarr Sarr | C16: Casual | D16: 300000
A17: 12 | B17: Said Idris Abduljalil | C17: Secondment | D17: 300000
... A39: 35 | B39: Godwin Etim | C39: Sergent at Arms | D39: 100000
B40: TOTAL | D40: =SUM(D6:D39) -> 9750000
F122: =60000 -> 60000

Sheet ENHANCED WELFARE 2024 2
A1: NATIONAL INSTITUTE FOR LEGISLATIVE AND DEMOCRATIC STUDIES
A2: STAFF ENHANCED WELFARE SCHEDULE 2024
A3: STAFF ENHANCED WELFARE SCHEDULE 2024
A4: S/N | B4: STAFF NAME | C4: DESIGNATION | D4: AMOUNT
D5: N
A6: 1 | B6: Victoria Stephanie David | C6: Consultancy | D6: 100000
A7: 2 | B7: Kindness Oluwakemi M | C7: Consultancy | D7: 100000
A8: 3 | B8: Danladi Idris Daniel | C8: Consultancy | D8: 100000
A9: 4 | B9: Ufomba Patricia Osinachi | C9: Consultancy | D9: 100000
A10: 5 | B10: Anayo Akwitti | C10: Consultancy | D10: 100000
A11: 6 | B11: Otene Oche Jonah | C11: Consultancy | D11: 100000
A12: 7 | B12: Julian Chinyere Osamoto | C12: Consultancy | D12: 100000
A13: 8 | B13: Faith Onyebujoh | C13: Consultancy | D13: 100000
A14: 9 | B14: Dr. Dare Fatai | C14: Consultancy | D14: 100000
A15: 10 | B15: Alkadriyar Abdullahi Abdullahi | C15: Consultancy | D15: 100000
A16: 11 | B16: Benjamin Ubiri | C16: Consultancy | D16: 100000
A17: 12 | B17: Mugisat Abdulganiyyu | C17: Consultancy | D17: 100000
... A23: 18 | B23: Moshood Tsoho Amuda | C23: Consultancy | D23: 100000
B24: TOTAL | D24: =SUM(D6:D23) -> 1800000
F106: =60000 -> 60000

Sheet JANUARY 2024 (2)
A1: CONTRACT/SABBATICAL AND NYSC SALARY FOR THE MONTH OF JANUARY
A3: S/N | B3: STAFF NAME | C3: DESIGNATION | D3: BASIC ALLOWANCE | E3: LEGISLATIVE ALLOWCE | F3: GROSS | G3: DEDUCTIONS | K3: JANUARY 2024 NET SALARY
G4: COOP CONTR | H4: COOP LOAN RECOVERY | I4: PAYE TAX | J4: TOTAL DEDUCTION | K4: N
A5: 1 | B5: Takwasa A. Galadima | C5: Nass Deployed | D5: =136027.8 -> 136027.8 | E5: =60000 -> 60000 | F5: =D5+E5 -> 196027.8 | G5: =30000 -> 30000 | I5: ='[1]August 2022 '!$AD$6 -> 20099.337 | J5: =G5+H5+I5 -> 50099.337 | K5: =F5-J5 -> 145928.46
A6: 2 | B6: Saratu Adamu Attajiri | C6: Office Assistant | D6: 90000 | E6: 30000 | F6: =D6+E6 -> 120000 | G6: 10000 | H6: 40000 | I6: 8900 | J6: =G6+H6+I6 -> 58900 | K6: =F6-J6 -> 61100
A7: 3 | B7: Aboaman Innocent | C7: Casual | D7: 45000 | E7: 15000 | F7: =D7+E7 -> 60000 | G7: =10000 -> 10000 | H7: =10000+10000 -> 20000 | I7: 2446.6667 | J7: =G7+H7+I7 -> 32446.667 | K7: =F7-J7 -> 27553.333
A8: 4 | B8: Kusai E. Richard | C8: Plumber | D8: 45000 | E8: 15000 | F8: =D8+E8 -> 60000 | G8: =10000 -> 10000 | H8: =20000 -> 20000 | I8: 2446.6667 | J8: =G8+H8+I8 -> 32446.667 | K8: =F8-J8 -> 27553.333
A9: 5 | B9: Bulus Ishaya | C9: Gardener | D9: 45000 | E9: 15000 | F9: =D9+E9 -> 60000 | G9: 0 | H9: 0 | I9: 2446.6667 | J9: =G9+H9+I9 -> 2446.6667 | K9: =F9-J9 -> 57553.333
A10: 6 | B10: Alhamdu Iliya | C10: Casual-Gardner | D10: =50000 -> 50000 | E10: 15000 | F10: =D10+E10 -> 65000 | G10: =5000+5000+5000 -> 15000 | H10: =14350 -> 14350 | I10: 2886.6667 | J10: =G10+H10+I10 -> 32236.667 | K10: =F10-J10 -> 32763.333
A11: 7 | B11: Salihu Hassan | C11: Casual-Gardner | D11: =50000 -> 50000 | E11: 15000 | F11: =D11+E11 -> 65000 | G11: =5000 -> 5000 | H11: 0 | I11: 2886.6667 | J11: =G11+H11+I11 -> 7886.6667 | K11: =F11-J11 -> 57113.333
A12: 8 | B12: Ishaya Moro James | C12: Gardener | D12: =60000 -> 60000 | E12: 20000 | F12: =D12+E12 -> 80000 | G12: =10000 -> 10000 | H12: =17500 -> 17500 | I12: 4206.6667 | J12: =G12+H12+I12 -> 31706.667 | K12: =F12-J12 -> 48293.333
A13: 9 | B13: Enobong Sambo | C13: Retainership | D13: =70000 -> 70000 | E13: 20000 | F13: =D13+E13 -> 90000 | G13: =0 -> 0 | H13: 0 | I13: 5300 | J13: =G13+H13+I13 -> 5300 | K13: =F13-J13 -> 84700
A14: 10 | B14: Masarr Sarr | C14: Casual | D14: =90000 -> 90000 | E14: 30000 | F14: =D14+E14 -> 120000 | G14: =0 -> 0 | H14: 0 | I14: 8900 | J14: =G14+H14+I14 -> 8900 | K14: =F14-J14 -> 111100
A15: 11 | B15: Said Idris Abduljalil | C15: Secondment | D15: =105352.17 -> 105352.17 | E15: =(60000+50000) -> 110000 | F15: =D15+E15 -> 215352.17 | G15: =0 -> 0 | H15: 0 | I15: 23345.831 | J15: =G15+H15+I15 -> 23345.831 | K15: =F15-J15 -> 192006.34
A16: 12 | B16: Prof. Peter Siyan | C16: Sabbatical | D16: =502746.92 -> 502746.92 | E16: 180000 | F16: =D16+E16 -> 682746.92 | G16: =0 -> 0 | H16: 0 | I16: 109754.08 | J16: =G16+H16+I16 -> 109754.08 | K16: =F16-J16 -> 572992.84
A17: 13 | B17: Pro. Francis Onyekwere Ozoh | C17: Sabbatical | D17: =555351.17 -> 555351.17 | E17: 180000 | F17: =D17+E17 -> 735351.17 | G17: =0 -> 0 | H17: 0 | I17: =(119693.26) -> 119693.26 | J17: =G17+H17+I17 -> 119693.26 | K17: =F17-J17 -> 615657.91
A18: 14 | B18: Prof. Zubairu Kwambo Dagona | C18: Contract Staff | D18: =800656.58 -> 800656.58 | E18: 200000 | F18: =D18+E18 -> 1000656.6 | G18: =0 -> 0 | H18: 0 | I18: =(170631.89) -> 170631.89 | J18: =G18+H18+I18 -> 170631.89 | K18: =F18-J18 -> 830024.69
A19: 15 | B19: Abdulkareem Toyeeb | C19: NYSC | D19: 25000 | E19: 0 | F19: =D19+E19 -> 25000 | G19: =0 -> 0 | H19: 0 | J19: =G19+H19+I19 -> 0 | K19: =F19-J19 -> 25000
A20: 16 | B20: Akeh Blessing | C20: NYSC | D20: 25000 | E20: 0 | F20: =D20+E20 -> 25000 | G20: =0 -> 0 | H20: 0 | J20: =G20+H20+I20 -> 0 | K20: =F20-J20 -> 25000
A21: 17 | B21: Fasasi Ahmed Olalekan | C21: NYSC | D21: 25000 | E21: 0 | F21: =D21+E21 -> 25000 | G21: =0 -> 0 | H21: 0 | J21: =G21+H21+I21 -> 0 | K21: =F21-J21 -> 25000
A22: 18 | B22: Nwabueze Joy Oluchi | C22: NYSC | D22: 25000 | E22: 0 | F22: =D22+E22 -> 25000 | G22: =0 -> 0 | H22: 0 | J22: =G22+H22+I22 -> 0 | K22: =F22-J22 -> 25000
A23: 19 | B23: Muhammad Kudu Abubakar | C23: Ag. Gen Manager | D23: =424023.33 -> 424023.33 | E23: 90000 | F23: =D23+E23 -> 514023.33 | G23: =0 -> 0 | H23: 0 | I23: =77198.31 -> 77198.31 | J23: =G23+H23+I23 -> 77198.31 | K23: =F23-J23 -> 436825.02
A24: 20 | B24: Prof. Mohammed Mustapha Namadi | C24: Sabbatical | D24: =496425.42 -> 496425.42 | E24: 180000 | F24: =D24+E24 -> 676425.42 | G24: =0 -> 0 | H24: 0 | I24: =108540.35 -> 108540.35 | J24: =G24+H24+I24 -> 108540.35 | K24: =F24-J24 -> 567885.07
A25: 21 | B25: Ibrahim Kaltume Onawo | C25: NYSC (Arrears) | D25: =25000+7500 -> 32500 | E25: 0 | F25: =D25+E25 -> 32500 | G25: =0 -> 0 | H25: 0 | J25: =G25+H25+I25 -> 0 | K25: =F25-J25 -> 32500
A26: 22 | B26: Hassan Mahmud Adewole | C26: NYSC | D26: 25000 | E26: 0 | F26: =D26+E26 -> 25000 | G26: =0 -> 0 | H26: 0 | J26: =G26+H26+I26 -> 0 | K26: =F26-J26 -> 25000
A27: 23 | B27: Nwanganga Chidozie | C27: House Keeper | D27: 60000 | E27: 20000 | F27: =D27+E27 -> 80000 | G27: =0 -> 0 | H27: 0 | I27: =4206.67 -> 4206.67 | J27: =G27+H27+I27 -> 4206.67 | K27: =F27-J27 -> 75793.33
A28: 24 | B28: Mary Shadrach | C28: Cleaner | D28: 55000 | E28: 15000 | F28: =D28+E28 -> 70000 | G28: =0 -> 0 | H28: 0 | I28: =3326.67 -> 3326.67 | J28: =G28+H28+I28 -> 3326.67 | K28: =F28-J28 -> 66673.33
A29: 25 | B29: Akinboboye Oluwatosin Ifedayo | C29: NYSC | D29: 25000 | E29: 0 | F29: =D29+E29 -> 25000 | G29: =0 -> 0 | H29: 0 | J29: =G29+H29+I29 -> 0 | K29: =F29-J29 -> 25000
A30: 26 | B30: Abdulrahim Abdullahi | C30: NYSC | D30: 25000 | F30: =D30+E30 -> 25000 | G30: =0 -> 0 | H30: 0 | J30: =G30+H30+I30 -> 0 | K30: =F30-J30 -> 25000
A31: 27 | B31: Julie G. Sanda | C31: Sabbatical | D31: 410900.75 | E31: 160000 | F31: =D31+E31 -> 570900.75 | G31: =0 -> 0 | H31: 0 | I31: =88279.61 -> 88279.61 | J31: =G31+H31+I31 -> 88279.61 | K31: =F31-J31 -> 482621.14
A32: 28 | B32: Rahimat Suberu Onize | C32: Contract Staff | D32: =123329.05 -> 123329.05 | E32: 50000 | F32: =D32+E32 -> 173329.05 | G32: 20000 | H32: 0 | I32: 16512.68 | J32: =G32+H32+I32 -> 36512.68 | K32: =F32-J32 -> 136816.37
A33: 29 | B33: Ikip Lebo | C33: Contract Staff | D33: =226713 -> 226713 | E33: =70000 -> 70000 | F33: =D33+E33 -> 296713 | G33: =20000 -> 20000 | H33: 0 | I33: =37014.45 -> 37014.45 | J33: =G33+H33+I33 -> 57014.45 | K33: =F33-J33 -> 239698.55
A34: 30 | B34: Yusuf Yusuf Dayyabu | C34: Contract Staff | D34: =145204 -> 145204 | E34: =60000 -> 60000 | F34: =D34+E34 -> 205204 | G34: =0 -> 0 | H34: 0 | I34: 21640.953 | J34: =G34+H34+I34 -> 21640.953 | K34: =F34-J34 -> 183563.05
A35: 31 | B35: Musa Mustapha Adekola | C35: Casual Staff | D35: =90000 -> 90000 | E35: =30000 -> 30000 | F35: =D35+E35 -> 120000 | G35: =0 -> 0 | H35: 0 | I35: =8600 -> 8600 | J35: =G35+H35+I35 -> 8600 | K35: =F35-J35 -> 111400
A36: 32 | B36: Ramatu Ibrahim Abdulrahim | C36: Contract Staff | D36: =123329.05 -> 123329.05 | E36: =50000 -> 50000 | F36: =D36+E36 -> 173329.05 | G36: =50000 -> 50000 | H36: 0 | I36: 16512.68 | J36: =G36+H36+I36 -> 66512.68 | K36: =F36-J36 -> 106816.37
A37: 33 | B37: Rasheedat Daibu | C37: Contract Staff | D37: =168602 -> 168602 | E37: =60000 -> 60000 | F37: =D37+E37 -> 228602 | G37: =0 -> 0 | H37: 0 | I37: =25571.8 -> 25571.8 | J37: =G37+H37+I37 -> 25571.8 | K37: =F37-J37 -> 203030.2
A38: 34 | B38: Ladan Abdulmushin Tawfiq | C38: Contract Staff | D38: 145204 | E38: 60000 | F38: =D38+E38 -> 205204 | G38: =0 -> 0 | H38: 0 | I38: =21640.95 -> 21640.95 | J38: =G38+H38+I38 -> 21640.95 | K38: =F38-J38 -> 183563.05
A39: 35 | B39: Dr. Alabi Adesina Muhydeen | C39: Contract Staff | D39: =226713 -> 226713 | E39: =120000 -> 120000 | F39: =D39+E39 -> 346713 | G39: =0 -> 0 | H39: 0 | I39: =45414.45 -> 45414.45 | J39: =G39+H39+I39 -> 45414.45 | K39: =F39-J39 -> 301298.55
A40: 36 | B40: Lukman Abdullahi Opobiyi | C40: NYSC | D40: 25000 | F40: =D40+E40 -> 25000 | G40: =0 -> 0 | H40: 0 | J40: =G40+H40+I40 -> 0 | K40: =F40-J40 -> 25000
A41: 37 | B41: Zainab Bakare | C41: Contract Staff | D41: =123329.05 -> 123329.05 | E41: =50000 -> 50000 | F41: =D41+E41 -> 173329.05 | G41: =0 -> 0 | H41: 0 | I41: 16512.68 | J41: =G41+H41+I41 -> 16512.68 | K41: =F41-J41 -> 156816.37
A42: 38 | B42: Desmond Cibueze Domendu | C42: Contract Staff | D42: =123329.05 -> 123329.05 | E42: =100000 -> 100000 | F42: =D42+E42 -> 223329.05 | G42: =0 -> 0 | H42: 0 | I42: =28687.49 -> 28687.49 | J42: =G42+H42+I42 -> 28687.49 | K42: =F42-J42 -> 194641.56
A43: 39 | B43: Blessing Ojone Jibrin | C43: Contract Staff | D43: =123329.05 -> 123329.05 | E43: =100000 -> 100000 | F43: =D43+E43 -> 223329.05 | G43: =0 -> 0 | H43: 0 | I43: =28687.49 -> 28687.49 | J43: =G43+H43+I43 -> 28687.49 | K43: =F43-J43 -> 194641.56
A44: 40 | B44: Chicha Ebweyi Joshua | C44: Contract Staff | D44: =123329.05 -> 123329.05 | E44: =100000 -> 100000 | F44: =D44+E44 -> 223329.05 | G44: =0 -> 0 | H44: 0 | I44: =28687.49 -> 28687.49 | J44: =G44+H44+I44 -> 28687.49 | K44: =F44-J44 -> 194641.56
A45: 41 | B45: Amal Zoaka | C45: NYSC | D45: 25000 | F45: =D45+E45 -> 25000 | G45: =0 -> 0 | H45: 0 | J45: =G45+H45+I45 -> 0 | K45: =F45-J45 -> 25000
A46: 42 | B46: Olufemi Emmanuel Oyegoke | C46: Contract Staff | D46: =145204 -> 145204 | E46: =60000 -> 60000 | F46: =D46+E46 -> 205204 | G46: =0 -> 0 | H46: 0 | I46: =21640.95 -> 21640.95 | J46: =G46+H46+I46 -> 21640.95 | K46: =F46-J46 -> 183563.05
A47: 43 | B47: Ngalabak Shugge | C47: Contract Staff | D47: =123329.05 -> 123329.05 | E47: =50000 -> 50000 | F47: =D47+E47 -> 173329.05 | G47: =0 -> 0 | H47: 0 | I47: =16512.68 -> 16512.68 | J47: =G47+H47+I47 -> 16512.68 | K47: =F47-J47 -> 156816.37
A48: 44 | B48: Prof. Shedrack Best Gaya | C48: Sabbatical | D48: =555351.17 -> 555351.17 | E48: 180000 | F48: =D48+E48 -> 735351.17 | G48: =0 -> 0 | H48: 0 | I48: =(119693.26) -> 119693.26 | J48: =G48+H48+I48 -> 119693.26 | K48: =F48-J48 -> 615657.91
A49: 45 | B49: Dr. Hadiza Saidu | C49: Contract | D49: ='[2]SALARY STRUCTURE'!$H$18 -> 344720.17 | E49: =160000 -> 160000 | F49: =D49+E49 -> 504720.17 | G49: =0 -> 0 | H49: 0 | I49: =75436.17 -> 75436.17 | J49: =G49+H49+I49 -> 75436.17 | K49: =F49-J49 -> 429284
A50: 46 | B50: Idris Muhammad Jamiu | C50: NYSC | D50: 25000 | E50: 0 | F50: =D50+E50 -> 25000 | G50: =0 -> 0 | H50: 0 | I50: 0 | J50: =G50+H50+I50 -> 0 | K50: =F50-J50 -> 25000
A51: 47 | B51: Dosumu Taiwo Oluomo | C51: NYSC | D51: 25000 | E51: 0 | F51: =D51+E51 -> 25000 | G51: =0 -> 0 | H51: 0 | I51: 0 | J51: =G51+H51+I51 -> 0 | K51: =F51-J51 -> 25000
A52: 48 | B52: Olarenwaju Abduhameed Olaitan | C52: NYSC | D52: 25000 | E52: 0 | F52: =D52+E52 -> 25000 | G52: =0 -> 0 | H52: 0 | I52: 0 | J52: =G52+H52+I52 -> 0 | K52: =F52-J52 -> 25000
A53: 49 | B53: Galadima Yakubu Takwasa | C53: NYSC | D53: 25000 | E53: 0 | F53: =D53+E53 -> 25000 | G53: =0 -> 0 | H53: 0 | I53: 0 | J53: =G53+H53+I53 -> 0 | K53: =F53-J53 -> 25000
A54: 50 | B54: Dangana Faith | C54: NYSC | D54: 25000 | E54: 0 | F54: =D54+E54 -> 25000 | G54: =0 -> 0 | H54: 0 | I54: 0 | J54: =G54+H54+I54 -> 0 | K54: =F54-J54 -> 25000
A55: 51 | B55: Bankole Bunmi Khadijah | C55: NYSC | D55: 25000 | E55: 0 | F55: =D55+E55 -> 25000 | G55: =0 -> 0 | H55: 0 | I55: 0 | J55: =G55+H55+I55 -> 0 | K55: =F55-J55 -> 25000
A56: 52 | B56: Shittu Deborah Damilola | C56: NYSC | D56: 25000 | E56: 0 | F56: =D56+E56 -> 25000 | G56: =0 -> 0 | H56: 0 | I56: 0 | J56: =G56+H56+I56 -> 0 | K56: =F56-J56 -> 25000
B57: TOTAL | D57: =SUM(D5:D56) -> 7434998.8 | E57: =SUM(E5:E56) -> 2670000 | F57: =SUM(F5:F56) -> 10104999 | G57: =SUM(G5:G56) -> 180000 | H57: =SUM(H5:H56) -> 111850 | I57: =SUM(I5:I56) -> 1294262.2 | J57: =SUM(J5:J56) -> 1586112.2 | K57: =SUM(K5:K56) -> 8518886.6
M139: =60000 -> 60000

Sheet Sheet32

Sheet CHRISTMAS WELFARE 1
A1: CONTRACT/SABBATICAL AND CONSULTANT CHRISTMAS WELFARE DECEMBER 2023
A3: S/N | B3: STAFF NAME | C3: DESIGNATION | D3: AMOUNT (N)
A4: 1 | B4: Dr. Mohammed Etudaiye | C4: Consultant | D4: 90000
A5: 2 | B5: Takwasa A. Galadima | C5: Nass Deployed | D5: 90000
A6: 3 | B6: Saratu Adamu Attajiri | C6: Office Assistant | D6: 54000
A7: 4 | B7: Aboaman Innocent | C7: Casual | D7: 36000
A8: 5 | B8: Kusai E. Richard | C8: Plumber | D8: 36000
A9: 6 | B9: Bulus Ishaya | C9: Gardener | D9: 36000
A10: 7 | B10: Alhamdu Iliya | C10: Casual-Gardner | D10: 36000
A11: 8 | B11: Salihu Hassan | C11: Casual-Gardner | D11: 36000
A12: 9 | B12: Ishaya Moro James | C12: Gardener | D12: 36000
A13: 10 | B13: Barr. James G Bathna | C13: Consultancy | D13: 90000
A14: 11 | B14: Dr. John Niyi Olanrewaju | C14: Consultancy | D14: 90000
A15: 12 | B15: Dr. Shehu Wahab L | C15: Consultant | D15: 90000
... A71: 68 | B71: Shittu Deborah Damilola | C71: NYSC | D71: 18000
B72: TOTAL | D72: =SUM(D4:D71) -> 3861000
F154: =60000 -> 60000

Sheet CHRISTMAS WELFARE 2
A1: CONSULTANCY WELFARE SCHEDULE DECEMBER 2023
A3: S/N | B3: STAFF NAME | C3: DESIGNATION | D3: AMOUNT (N)
A4: 1 | B4: Victoria Stephanie David | C4: Consultancy | D4: 54000
A5: 2 | B5: Kindness Oluwakemi M | C5: Consultancy | D5: 54000
A6: 3 | B6: Danladi Idris Daniel | C6: Consultancy | D6: 54000
A7: 4 | B7: Ufomba Patricia Osinachi | C7: Consultancy | D7: 54000
A8: 5 | B8: Anayo Akwitti | C8: Consultancy | D8: 54000
A9: 6 | B9: Otene Oche Jonah | C9: Consultancy | D9: 54000
A10: 7 | B10: Julian Chinyere Osamoto | C10: Consultancy | D10: 54000
A11: 8 | B11: Faith Onyebujoh | C11: Consultancy | D11: 54000
A12: 9 | B12: Dr. Dare Fatai | C12: Consultancy | D12: 90000
A13: 10 | B13: Alkadriyar Abdullahi Abdullahi | C13: Consultancy | D13: 54000
A14: 11 | B14: Benjamin Ubiri | C14: Consultancy | D14: 54000
A15: 12 | B15: Mugisat Abdulganiyyu | C15: Consultancy | D15: 54000
... A18: 15 | B18: Godwin Etim | C18: Sergearnt at Arms | D18: 54000
B19: TOTAL | D19: =SUM(D4:D18) -> 846000
E101: =60000 -> 60000

Sheet HALF SALARY
A1: CONTRACT/SABBATICAL AND CONSULTANT HALF SALARY FOR THE MONTH OF DECEMBER 2023
A3: S/N | B3: STAFF NAME | C3: DESIGNATION | D3: TOTAL SALARY | E3: HALF SALARY DECEMBER 2023
E4: N
A5: 1 | B5: Dr. Mohammed Etudaiye | C5: Consultant | D5: 300000 | E5: =D5/2 -> 150000
A6: 2 | B6: Takwasa A. Galadima | C6: Nass Deployed | D6: 196027.8 | E6: =D6/2 -> 98013.9
A7: 3 | B7: Saratu Adamu Attajiri | C7: Office Assistant | D7: 120000 | E7: =D7/2 -> 60000
A8: 4 | B8: Aboaman Innocent | C8: Casual | D8: 60000 | E8: =D8/2 -> 30000
A9: 5 | B9: Kusai E. Richard | C9: Plumber | D9: 60000 | E9: =D9/2 -> 30000
A10: 6 | B10: Bulus Ishaya | C10: Gardener | D10: 60000 | E10: =D10/2 -> 30000
A11: 7 | B11: Alhamdu Iliya | C11: Casual-Gardner | D11: 65000 | E11: =D11/2 -> 32500
A12: 8 | B12: Salihu Hassan | C12: Casual-Gardner | D12: 65000 | E12: =D12/2 -> 32500
A13: 9 | B13: Ishaya Moro James | C13: Gardener | D13: 80000 | E13: =D13/2 -> 40000
A14: 10 | B14: Barr. James G Bathna | C14: Consultancy | D14: 300000 | E14: =D14/2 -> 150000
A15: 11 | B15: Dr. John Niyi Olanrewaju | C15: Consultancy | D15: 500000 | E15: =D15/2 -> 250000
A16: 12 | B16: Dr. Shehu Wahab L | C16: Consultant | D16: 300000 | E16: =D16/2 -> 150000
... A60: 68 | B60: Shittu Deborah Damilola | C60: NYSC | D60: 15000 | E60: =D60/2 -> 7500
B61: TOTAL | D61: 13498810 | E61: =SUM(E5:E60) -> 6659405.1
G143: =60000 -> 60000

Sheet HALF PAYMT (3)
A1: CONSULTANCY FEES FOR THE MONTH OF DECEMBER 2023
A3: S/N | B3: STAFF NAME | C3: DESIGNATION | D3: TOTAL/GROSS FEES | E3: HALF PAYMENT DECEMBER 2023
E4: N
A5: 1 | B5: Victoria Stephanie David | C5: Consultancy | D5: =150000 -> 150000 | E5: =D5/2 -> 75000
A6: 2 | B6: Kindness Oluwakemi M | C6: Consultancy | D6: =200000 -> 200000 | E6: =D6/2 -> 100000
A7: 3 | B7: Danladi Idris Daniel | C7: Consultancy | D7: =200000 -> 200000 | E7: =D7/2 -> 100000
A8: 4 | B8: Ufomba Patricia Osinachi | C8: Consultancy | D8: =150000 -> 150000 | E8: =D8/2 -> 75000
A9: 5 | B9: Anayo Akwitti | C9: Consultancy | D9: =200000 -> 200000 | E9: =D9/2 -> 100000
A10: 6 | B10: Otene Oche Jonah | C10: Consultancy | D10: =200000 -> 200000 | E10: =D10/2 -> 100000
A11: 7 | B11: Julian Chinyere Osamoto | C11: Consultancy | D11: =150000 -> 150000 | E11: =D11/2 -> 75000
A12: 8 | B12: Faith Onyebujoh | C12: Consultancy | D12: =200000 -> 200000 | E12: =D12/2 -> 100000
A13: 9 | B13: Dr. Dare Fatai | C13: Consultancy | D13: 300000 | E13: =D13/2 -> 150000
A14: 10 | B14: Alkadriyar Abdullahi Abdullahi | C14: Consultancy | D14: =150000 -> 150000 | E14: =D14/2 -> 75000
A15: 11 | B15: Benjamin Ubiri | C15: Consultancy | D15: 200000 | E15: =D15/2 -> 100000
A16: 12 | B16: Mugisat Abdulganiyyu | C16: Consultancy | D16: 150000 | E16: =D16/2 -> 75000
A17: 13 | B17: Echianu Chinedu Chikadibia | C17: Consultancy | D17: 150000 | E17: =D17/2 -> 75000
B18: TOTAL | D18: =SUM(D5:D17) -> 2400000 | E18: =SUM(E5:E17) -> 1200000
G100: =60000 -> 60000

Sheet Sheet28

Sheet Tenure 
B1: TENURE OF CONTRACT , SABBATICAL AND NYSC STAFF
B2: TENURE OF CONTRACT AND SABBATICAL STAFF
B4: STAFF NAME | C4: DESIGNATION | D4: START DATE | E4: EXPIRY DATE | F4: FIRST RENEWAL | G4: EXPIRY DATE
A5: 1 | B5: Prof. Edoba B. Omoregie | C5: Sabbatical | D5: 18th December, 2020 | E5: 18th December, 2021 | F5: 44478 | G5: 44842
A6: 2 | B6: Dr. Shehu Yahaya | C6: Consultant | D6: 25th February 2021 | E6: 25th February 2022
A7: 3 | B7: Prof. Attahiru Muhammadu Jega | C7: Consultant | D7: 7th September, 2020 | E7: 6th September, 2021
A8: 4 | B8: Prof. Alabi O Mojeed | C8: Sabbatical | D8: 11th August, 2020 | E8: 10th August, 2021
A9: 7 | B9: Abayomi Kolapo Quadri | D9: 1st June, 2021 | E9: 1st June, 2022 | F9: 44706 | G9: 45070
A10: 8 | B10: Takwasa A. Galadima | C10: Nass Deployed
A11: 12 | B11: Saratu Adamu Attajiri | C11: Office Assistant
A12: 13 | B12: Moshood Tosho Amuda | C12: Manager, Exams & Records | D12: 1st July, 2020 | E12: 30th June 2021
A13: 14 | B13: Maryam Muhammed Bello | C13: PA Special Duties | D13: 2nd August, 2019 | E13: 31st July, 2020
A14: 18 | B14: Aboaman Innocent | C14: Steward
A15: 19 | B15: Adanhou V. Alfred | C15: Steward
A16: 20 | B16: Kusai E. Richard | C16: Plumber
A17: 21 | B17: Enenche Jeremiah Agada | C17: Casual | D17: 4th September, 2020
A18: 22 | B18: Yahaya Adamu Abdulhamid | C18: Casual | D18: 30th November, 2020
A19: 23 | B19: Bulus Ishaya | C19: Gardener
A20: 24 | B20: Mohammed Etudaiye | C20: Consultant | D20: 1st February, 2021 | E20: 31st January, 2022 | F20: 44593 | G20: 44957
A21: 25 | B21: Prof. Jide Oladipo | C21: Sabbatical | D21: 26th August 2020 | E21: 25th August, 2021
A22: 26 | B22: Prof. Yusuf I. Arowosaiye | C22: Sabbatical | D22: 1st September, 2020 | E22: 31st August, 2021
A23: 27 | B23: Ndanusa Mohammed Manzuma -Ndaaba | C23: Mgr. Admin-Contract | D23: 2nd September, 2020 | E23: 1st September, 2021 | F23: 44835 | G23: 45170
A24: 28 | B24: Zainab Abbas | C24: Casual | D24: 4th September, 2020
A25: 29 | B25: Dr. Usman Wali | C25: SNR- Ast. PG Cood-Contract | D25: 17th August, 2020 | E25: 16th August 2021 | F25: 44845 | G25: 45209
A26: 30 | B26: Ayobolu Olajide Olufunsho | C26: Internal Editor- Contract | D26: 14th October, 2020 | E26: 13th October, 2021 | F26: 44835 | G26: 45170
A27: 31 | B27: Jimoh Munirat Olaide | C27: Casual | D27: 16th October, 2020 | E27: Contract Service
A28: 32 | B28: Dr. Olanrewaju John | C28: Contract | D28: 22nd May, 2020 | E28: 21st May 2021 | F28: 44739 | G28: 45103
A29: 33 | B29: Massarr Sarr | C29: Casual | D29: 24th November, 2020
A30: 34 | B30: Tessneem Ibrahim | C30: Permanent Staff | D30: 18th November, 2020
A31: 35 | B31: Dr. Olajide O Akanji | C31: Sabbatical | D31: 16th November, 2020
A32: 36 | B32: Prof. Shola Jeremiah Omotola | C32: Consultant | D32: 8th August 2020 | E32: 7th August 2021
A33: 37 | B33: Enobong Peter Sambo | C33: Retainership | D33: 9th October, 2020
A34: 38 | B34: Mr. Shehu Wahab | C34: Consultant | D34: 7th September, 2020 | E34: 6th September 2021 | F34: 1st November 2021 | G34: 31st October 2022
A35: 39 | B35: Abru Ololade Idowu | C35: Contract | D35: 5th October, 2020 | E35: 4th October, 2021
A36: 40 | B36: Adeojo Bolaji Joy | C36: NYSC | D36: 21st September, 2020
A37: 41 | B37: Jimoh Adebayo Zaka | C37: Casual | D37: 4th September, 2020
A38: 42 | B38: Abu Joan | C38: NYSC | D38: 1st September, 2020
A39: 43 | B39: Abdulsalam Iyabo Jariatu | C39: NYSC | D39: 1st September, 2020
A40: 44 | B40: Michael Daksiri Yahra | C40: NYSC | D40: 27th July, 2020
A41: 45 | B41: Dr Chris Itsede | C41: Consultant | D41: 1st July, 2020 | E41: 30th June 2021
A42: 46 | B42: James G Bathna | C42: Sabbatical | D42: 11th May, 2021 | E42: 11th May 2022 | F42: 44682 | G42: 45017
A43: 47 | B43: Amina Ummukhair Ibrahim | C43: Contract | D43: 29th March 2021 | E43: 29th May 2022 | F43: Not Renewed
A44: 48 | B44: Adewale Aderemi | C44: Contract | D44: 10th March 2020 | E44: 9th March 2021
A45: 49 | B45: Olima James Enyi | C45: Casual | D45: 10th february 2020
A46: 50 | B46: Ishaya Moro James | C46: Gardner | D46: 3rd February, 2020
A47: 51 | B47: Salihu Hassan | C47: Casual | D47: 18th december, 2019
A48: 52 | B48: Sholagberu Taiye Sofiat | C48: Casual
A49: 53 | B49: Mohammed Danjuma Hassan | C49: Consultant | D49: 29th June, 2021 | E49: 28th June, 2022
A50: 54 | B50: Okolo Ujunwa Pascaline | C50: NYSC | D50: 5th July, 2021
A51: 55 | B51: Adeokun Temiloluwa Ruth | C51: NYSC | D51: 1st July 2021
A52: 56 | B52: Prof Peter Siyan | C52: Consultant | D52: 9th June, 2021 | E52: 9th June, 2022 | F52: 44662 | G52: 45026
A53: 57 | B53: Siyan-Peter Rejoice | C53: NYSC | D53: 24th June 2021
A54: 58 | B54: Umar Yahaya Halima | C54: NYSC | D54: 24th June 2021
A55: 59 | B55: Yakubu Lina Lessi | C55: NYSC | D55: 9th June, 2021
A56: 60 | B56: Kasimu Hauwa Temitope | C56: NYSC | D56: 3rd March 2021
A57: 61 | B57: Dr. Abubakar Muhammad S | C57: Sabbatical | D57: 2nd February 2021 | E57: 1st February 2022
A58: 62 | B58: Dr. Abubakar Mohammed Bashir | C58: Secondment- Fed Min of Finance | D58: 17th March 2021 | E58: 17th March 2023
A59: 66 | B59: Prof. Echezona Roseline Ifeoma | C59: Sabbatical | D59: 1st February, 2021 | E59: 31st January, 2022
A60: 67 | B60: Dr. Abubakar Muhammad Saidu | C60: Sabbatical | D60: 1st February, 2021 | E60: 31st January, 2022
A61: 68 | B61: Dr Ali Arazeem Abdullahi | C61: Sabbatical | D61: 2nd February, 2021 | E61: 1st December 2022
A62: 69 | B62: Etti Hawanat Oyenike | C62: Contract Staff | D62: 44818 | E62: 45182
A63: 70 | B63: Lawal-Gambari Bilkis Sitou | C63: Contract Staff | D63: 44819 | E63: 45183
A64: 71 | B64: Olaniyan Taiwo Abimbola | C64: Contract Staff | D64: 44819 | E64: 45183
A65: 72 | B65: Sulaimon Aminat Jumoke | C65: Contract Staff | D65: 44823 | E65: 45187
A66: 73 | B66: CHRISTABEL UKOH | C66: CONFIDENTIAL SECRETARY | D66: 28th October 2021 | E66: 27th October 2022
A67: 74 | B67: Gunat Nansat Mark | C67: Contract | D67: 44782 | E67: 45177
A68: 75 | B68: Salihu Abubakar Musa | C68: NYSC | E68: 44835
A69: 76 | B69: Yahya Zaiyad Alhaji | C69: NYSC | E69: 44835
A70: 77 | B70: Sogaolu O Oreoluwa | C70: NYSC | E70: 44835
A71: 78 | B71: Nkwere Ozioma Philippa | C71: NYSC | E71: 44835
A72: 79 | B72: Mustapha Rafiu Ayobanji | C72: Contract | D72: 44826 | E72: 45190
A73: 80 | B73: Idris Ibrahim | C73: Contract | D73: 44826 | E73: 45190
A74: 81 | B74: Ahmad Aisha Suleiman | C74: NYSC | D74: 44839 | E74: 45203
A75: 82 | B75: Magaji Bala | C75: Contract Staff | D75: 44827 | E75: 45191
A76: 83 | B76: Osanaiye David Akinyemi | C76: Secondment | D76: 44452 | E76: 45181
A77: 84 | B77: Araoye Ganiyat Titilola | C77: Contract Staff | D77: 44452 | E77: 44816
A78: 85 | B78: Rekiya Ibrahim Attah | C78: Contract Staff | D78: 44449 | E78: 44813
A79: 86 | B79: Said Idris Abduljalil | C79: Secondment | D79: 44417 | E79: 45146
A80: 87 | B80: Salman Rabiat Bolatito | C80: Secondment | D80: 44403 | E80: 45132
A81: 88 | B81: Dr Abubakar Mohammed Bashir | C81: Secondment | D81: 44272 | E81: 45001
A82: 89 | B82: Aishatu O. Usman | C82: Sabbatical | D82: 44845 | E82: 45209
A83: 90 | B83: Mustapha Raheemat Adebola | C83: NYSC | D83: 44763 | E83: 45092
A84: 91 | B84: Sulaiman ( Dada) Oluwatosin Mutiat | C84: NYSC | D84: 44762 | E84: 45092
A85: 92 | B85: Omirinde Mariam | C85: NYSC | D85: 44762 | E85: 15/06/2023or Feb 2023
A86: 93 | B86: Maryam Musa Sada | C86: Contract | D86: 44714 | E86: 45078
A87: 94 | B87: Abdullahi Ahmad Usman | C87: Contract | D87: 45078 | E87: 45077
A88: 95 | B88: Papka (Dibal) Rosemighty Ishaku | C88: NYSC | D88: 44682 | E88: 45017 | F88: 45003
A89: 96 | B89: Ajibade Saheed Olabanji | C89: NYSC | D89: 44696 | E89: 14/04/2023 or Jan 2023
A90: 97 | B90: Farooq Onikijipa Afeez | C90: Contract | D90: 44670 | E90: 45034
A91: 98 | B91: Jibrin Blessing Ojone | C91: NYSC | D91: 44675 | E91: 44986
A92: 99 | B92: Jamila Abdul | C92: Contract | D92: 44670 | E92: 45034
A93: 100 | B93: Dr. Festus Osagu | C93: Contract | D93: 44670 | E93: 45034
A94: 101 | B94: Yusuf Ibrahim | C94: Contract | D94: 44673 | E94: 45037
A95: 102 | B95: Shafiu Yahya Mikail | C95: Contract | D95: 44670 | E95: 45034
A96: 103 | B96: Hassan Yerima | C96: Contract | D96: 44670 | E96: 45034
A97: 104 | B97: Zainab Akinde | C97: Contract | D97: 44670 | E97: 45034
A98: 105 | B98: Isere Richard Kantee | C98: Contract | D98: 44676 | E98: 45040
A99: 106 | B99: Haruna Musa | C99: Contract | D99: 44670 | E99: 45034
A100: 107 | B100: Moyaki Micheal Olumide | C100: NYSC | D100: 45041 | E100: 44986
A101: 108 | B101: Muhammed Khadijat | C101: NYSC | D101: 44671 | E101: March or Feb 2023
...

Sheet Half Salary Allowance
A1: CONTRACT/SABBATICAL AND CONSULTANT HALF SALARY ALLOWANCE FOR THE MONTH OF DECEMBER 2022
A3: S/N | B3: STAFF NAME | C3: DESIGNATION | D3: BASIC ALLOWANCE | E3: LEGISLATIVE ALLOWCE | F3: GROSS | G3: NET SALARY DECEMBER 22
G4: N
A5: 1 | B5: Dr. Mohammed Etudaiye | C5: Consultant | D5: =300000 -> 300000 | E5: =0 -> 0 | F5: =D5+E5 -> 300000 | G5: =F5/2 -> 150000
A6: 2 | B6: Takwasa A. Galadima | C6: Nass Deployed | D6: =136027.8 -> 136027.8 | E6: =60000 -> 60000 | F6: =D6+E6 -> 196027.8 | G6: =F6/2 -> 98013.9
A7: 3 | B7: Saratu Adamu Attajiri | C7: Office Assistant | D7: 90000 | E7: 30000 | F7: =D7+E7 -> 120000 | G7: =F7/2 -> 60000
A8: 4 | B8: Aboaman Innocent | C8: Casual | D8: 45000 | E8: 15000 | F8: =D8+E8 -> 60000 | G8: =F8/2 -> 30000
A9: 5 | B9: Kusai E. Richard | C9: Plumber | D9: 45000 | E9: 15000 | F9: =D9+E9 -> 60000 | G9: =F9/2 -> 30000
A10: 6 | B10: Bulus Ishaya | C10: Gardener | D10: 45000 | E10: 15000 | F10: =D10+E10 -> 60000 | G10: =F10/2 -> 30000
A11: 7 | B11: Sholagberu T Sofiat | C11: Casual | D11: =90000 -> 90000 | E11: 30000 | F11: =D11+E11 -> 120000 | G11: =F11/2 -> 60000
A12: 8 | B12: Alhamdu Iliya | C12: Casual-Gardner | D12: =50000 -> 50000 | E12: 15000 | F12: =D12+E12 -> 65000 | G12: =F12/2 -> 32500
A13: 9 | B13: Salihu Hassan | C13: Casual-Gardner | D13: =50000 -> 50000 | E13: 15000 | F13: =D13+E13 -> 65000 | G13: =F13/2 -> 32500
A14: 10 | B14: Ishaya Moro James | C14: Gardener | D14: =60000 -> 60000 | E14: 20000 | F14: =D14+E14 -> 80000 | G14: =F14/2 -> 40000
A15: 11 | B15: James G Bathna | C15: Sabbatical | D15: =300000 -> 300000 | F15: =D15+E15 -> 300000 | G15: =F15/2 -> 150000
A16: 12 | B16: Dr. John Niyi Olanrewaju | C16: Consultancy | D16: =500000 -> 500000 | E16: =0 -> 0 | F16: =D16+E16 -> 500000 | G16: =F16/2 -> 250000
A17: 13 | B17: Mr. Shehu Wahab L | C17: Consultant | D17: 300000 | E17: 0 | F17: =D17+E17 -> 300000 | G17: =F17/2 -> 150000
A18: 14 | B18: Enobong Sambo | C18: Retainership | D18: =70000 -> 70000 | E18: 20000 | F18: =D18+E18 -> 90000 | G18: =F18/2 -> 45000
A19: 15 | B19: Masarr Sarr | C19: Casual | D19: =90000 -> 90000 | E19: 30000 | F19: =D19+E19 -> 120000 | G19: =F19/2 -> 60000
A20: 16 | B20: Aleke Friday Onyantu | C20: Casual | D20: =90000 -> 90000 | E20: =30000 -> 30000 | F20: =D20+E20 -> 120000 | G20: =F20/2 -> 60000
A21: 17 | B21: Ode Ijoko Michael | C21: Casual | D21: =90000 -> 90000 | E21: =30000 -> 30000 | F21: =D21+E21 -> 120000 | G21: =F21/2 -> 60000
A22: 18 | B22: Said Idris Abduljalil | C22: Secondment | D22: =105352.17 -> 105352.17 | E22: =(60000+50000) -> 110000 | F22: =D22+E22 -> 215352.17 | G22: =F22/2 -> 107676.08
A23: 19 | B23: Giwa Sidika Ajoke | C23: Casual(DGs GH) | D23: =90000 -> 90000 | E23: =30000 -> 30000 | F23: =D23+E23 -> 120000 | G23: =F23/2 -> 60000
A24: 20 | B24: Muhammed Khadijah Grema | C24: NYSC | D24: 15000 | E24: 0 | F24: =D24+E24 -> 15000 | G24: =F24/2 -> 7500
A25: 21 | B25: Rasheed Mariam Folashade | C25: Casual | D25: 90000 | E25: =30000 -> 30000 | F25: =D25+E25 -> 120000 | G25: =F25/2 -> 60000
A26: 22 | B26: Hadiza Saidu | C26: Sabbatical | D26: =399385.82 -> 399385.82 | E26: =160000 -> 160000 | F26: =D26+E26 -> 559385.82 | G26: =F26/2 -> 279692.91
A27: 23 | B27: Adebayo Warith Bolaji | C27: NYSC | D27: =15000 -> 15000 | E27: 0 | F27: =D27+E27 -> 15000 | G27: =F27/2 -> 7500
A28: 24 | B28: Moyaki Michael Olumide | C28: NYSC | D28: 15000 | F28: =D28+E28 -> 15000 | G28: =F28/2 -> 7500
A29: 25 | B29: Jibrin Blessing Ojone | C29: NYSC | D29: 15000 | F29: =D29+E29 -> 15000 | G29: =F29/2 -> 7500
A30: 26 | B30: Ajibade Saheed Olabanji | C30: NYSC | D30: 15000 | F30: =D30+E30 -> 15000 | G30: =F30/2 -> 7500
A31: 27 | B31: Suleiman Oluwatosin Mutiat | C31: NYSC | D31: 15000 | F31: =D31+E31 -> 15000 | G31: =F31/2 -> 7500
A32: 28 | B32: Omirinde Mariam | C32: NYSC | D32: 15000 | F32: =D32+E32 -> 15000 | G32: =F32/2 -> 7500
A33: 29 | B33: Mustapha Raheemat Adebola | C33: NYSC | D33: 15000 | F33: =D33+E33 -> 15000 | G33: =F33/2 -> 7500
A34: 30 | B34: Rosemighty Papki Ishaku | C34: NYSC | D34: 15000 | F34: =D34+E34 -> 15000 | G34: =F34/2 -> 7500
A35: 31 | B35: Etti Hawanat Oyenike | C35: Contract Staff | D35: =123329.05 -> 123329.05 | E35: 50000 | F35: =D35+E35 -> 173329.05 | G35: =F35/2 -> 86664.525
A36: 32 | B36: Lawal-Gambari Bilkis Sitou | C36: Contract Staff | D36: ='[3]Nils Salary Structure'!$H$36 -> 168601.58 | E36: 100000 | F36: =D36+E36 -> 268601.58 | G36: =F36/2 -> 134300.79
A37: 33 | B37: Olaniyan Taiwo Abimbola | C37: Contract Staff | D37: ='[3]Nils Salary Structure'!$H$35 -> 145203.67 | E37: 100000 | F37: =D37+E37 -> 245203.67 | G37: =F37/2 -> 122601.83
A38: 34 | B38: Sulaimon Aminat Jumoke | C38: Contract Staff | D38: =123329.05 -> 123329.05 | E38: 50000 | F38: =D38+E38 -> 173329.05 | G38: =F38/2 -> 86664.525
A39: 35 | B39: Mustapha Rafiu Ayobanji | C39: Contract Staff | D39: ='[4]October 2022'!$R$108-60000 -> 244895.91 | E39: 60000 | F39: =D39+E39 -> 304895.91 | G39: =F39/2 -> 152447.96
A40: 36 | B40: Idris Ibrahim | C40: Contract Staff | D40: =205372.08 -> 205372.08 | E40: 110000 | F40: =D40+E40 -> 315372.08 | G40: =F40/2 -> 157686.04
A41: 37 | B41: Aishatu O. Usman | C41: Sabbatical | D41: 328759.88 | E41: 160000 | F41: =D41+E41 -> 488759.88 | G41: =F41/2 -> 244379.94
A42: 38 | B42: Maryam Musa Sada | C42: Contract Staff | D42: =268602.07775-100000 -> 168602.08 | E42: 100000 | F42: =D42+E42 -> 268602.08 | G42: =F42/2 -> 134301.04
A43: 39 | B43: Garba Rofiat Kehinde | C43: NYSC | D43: 15000 | F43: =D43+E43 -> 15000 | G43: =F43/2 -> 7500
A44: 40 | B44: Ogah Friday David | C44: NYSC | D44: 15000 | F44: =D44+E44 -> 15000 | G44: =F44/2 -> 7500
A45: 41 | B45: Ismail Fauzyat | C45: NYSC | D45: 15000 | F45: =D45+E45 -> 15000 | G45: =F45/2 -> 7500
A46: 42 | B46: Owolabi Olawale Adebayo | C46: NYSC | D46: 15000 | F46: =D46+E46 -> 15000 | G46: =F46/2 -> 7500
A47: 43 | B47: Sale Angbo Likita | C47: NYSC | D47: 15000 | F47: =D47+E47 -> 15000 | G47: =F47/2 -> 7500
A48: 44 | B48: Mariam Adepeju Abdulraheem-Mustapha | C48: Sabbatical | D48: =373267.83*0.77 -> 287416.23 | E48: =160000*0.77 -> 123200 | F48: =D48+E48 -> 410616.23 | G48: =F48/2 -> 205308.11
B49: TOTAL | D49: =SUM(D5:D48) -> 5041275.3 | E49: =SUM(E5:E48) -> 1508200 | F49: =SUM(F5:F48) -> 6549475.3 | G49: =SUM(G5:G48) -> 3274737.7
A51: PREPARED BY: RAHILA N. HABU
G52: =242808.11 -> 242808.11
I133: =60000 -> 60000

Sheet Chrismas  Welfare (3)
A1: CONTRACT/SABBATICAL AND CONSULTANT STAFF WELFARE DECEMBER 2022
A3: S/N | B3: STAFF NAME | C3: DESIGNATION | D3: AMOUNT
A5: 1 | B5: Takwasa A. Galadima | C5: Nass Deployed | D5: 75000 | E5: =SUM(D5:D5) -> 75000
A6: 2 | B6: Saratu Adamu Attajiri | C6: Office Assistant | D6: 45000 | E6: =SUM(D6:D6) -> 45000
A7: 3 | B7: Aboaman Innocent | C7: Casual | D7: 30000 | E7: =SUM(D7:D7) -> 30000
A8: 4 | B8: Kusai E. Richard | C8: Plumber | D8: 30000 | E8: =SUM(D8:D8) -> 30000
A9: 5 | B9: Bulus Ishaya | C9: Gardener | D9: 30000 | E9: =SUM(D9:D9) -> 30000
A10: 6 | B10: Sholagberu T Sofiat | C10: Casual | D10: 45000 | E10: =SUM(D10:D10) -> 45000
A11: 7 | B11: Alhamdu Iliya | C11: Casual-Gardner | D11: 30000 | E11: =SUM(D11:D11) -> 30000
A12: 8 | B12: Salihu Hassan | C12: Casual-Gardner | D12: 30000 | E12: =SUM(D12:D12) -> 30000
A13: 9 | B13: Ishaya Moro James | C13: Gardener | D13: 30000 | E13: =SUM(D13:D13) -> 30000
A14: 10 | B14: James G Bathna | C14: Sabbatical | D14: 75000 | E14: =SUM(D14:D14) -> 75000
A15: 11 | B15: John Niyi Olanrewaju | C15: Consultant | D15: =105000 -> 105000
A16: 12 | B16: Enobong Sambo | C16: Retainership | D16: =25000*1.5 -> 37500 | E16: =SUM(D16:D16) -> 37500
A17: 13 | B17: Masarr Sarr | C17: Casual | D17: 45000 | E17: =SUM(D17:D17) -> 45000
A18: 14 | B18: Aleke Friday Onyantu | C18: Casual | D18: 45000 | E18: =SUM(D18:D18) -> 45000
A19: 15 | B19: Ode Ijoko Michael | C19: Casual | D19: 45000 | E19: =SUM(D19:D19) -> 45000
A20: 16 | B20: Said Idris Abduljalil | C20: Secondment | D20: 45000 | E20: =SUM(D20:D20) -> 45000
A21: 17 | B21: Giwa Sidika Ajoke | C21: Casual(DGs GH) | D21: 45000 | E21: =SUM(D21:D21) -> 45000
A22: 18 | B22: Abdullahi Ali Arazeem | C22: Sabbatical
A23: 19 | B23: Muhammed Khadijat | C23: NYSC | D23: 15000 | E23: =SUM(D23:D23) -> 15000
A24: 20 | B24: Rasheed Mariam Folashade | C24: Casual | D24: 45000 | E24: =SUM(D24:D24) -> 45000
A25: 21 | B25: Hadiza Saidu | C25: Sabbatical | D25: 105000 | E25: =SUM(D25:D25) -> 105000
A26: 22 | B26: Adebayo Warith Bolaji | C26: NYSC | D26: 15000 | E26: =SUM(D26:D26) -> 15000
A27: 23 | B27: Moyaki Michael Olumide | C27: NYSC | D27: 15000 | E27: =SUM(D27:D27) -> 15000
A28: 24 | B28: Jibrin Blessing Ojone | C28: NYSC | D28: 15000 | E28: =SUM(D28:D28) -> 15000
A29: 25 | B29: Ajibade Saheed Olabanji | C29: NYSC | D29: 15000 | E29: =SUM(D29:D29) -> 15000
A30: 26 | B30: Suleiman Oluwatosin Mutiat | C30: NYSC | D30: 15000
A31: 27 | B31: Omirinde Mariam | C31: NYSC | D31: 15000
A32: 28 | B32: Mustapha Raheemat Adebola | C32: NYSC | D32: 15000
A33: 29 | B33: Rosemighty Papki Ishaku | C33: NYSC | D33: 15000
A34: 30 | B34: Etti Hawanat Oyenike | C34: Contract Staff | D34: 45000
A35: 31 | B35: Lawal-Gambari Bilkis Sitou | C35: Contract Staff | D35: 45000
A36: 32 | B36: Olaniyan Taiwo Abimbola | C36: Contract Staff | D36: 45000
A37: 33 | B37: Sulaimon Aminat Jumoke | C37: Contract Staff | D37: 45000 | E37: =#REF!-#REF! -> #REF!
A38: 34 | B38: Mustapha Rafiu Ayobanji | C38: Contract Staff | D38: 45000
A39: 35 | B39: Idris Ibrahim | C39: Contract Staff | D39: 45000
A40: 36 | B40: Aishatu O. Usman | C40: Sabbatical | D40: 75000
A41: 37 | B41: Gunat Nansat Mark | C41: Contract Staff | D41: 45000
A42: 38 | B42: Suleima Abubakar Sodeeq | C42: Contract Staff | D42: 45000
A43: 39 | B43: Haruna Jibrin A. | C43: Contract Staff | D43: 45000
A44: 40 | B44: Haruna Musa | C44: Contract Staff | D44: 45000
A45: 41 | B45: Yahaya Adamu Abdulhamid | C45: Contract Staff | D45: 45000
A46: 42 | B46: Elizabeth Ogechukwu Onyeaku | C46: Contract Staff | D46: 45000
A47: 43 | B47: Maryam Musa Sada | C47: Contract Staff | D47: 45000
A48: 44 | B48: Magaji Bala | C48: Contract Staff | D48: 150000
A49: 45 | B49: Adejoh Emmanuel | C49: Sergearnt at Arms | D49: 45000
A50: 46 | B50: Godwin Etim | C50: Sergearnt at Arms | D50: 45000
B51: TOTAL | D51: =SUM(D5:D50) -> 1972500 | E51: =SUM(E5:E37) -> #REF!

Sheet Chrismas  Welfare (4)
A1: CONTRACT/SABBATICAL AND CONSULTANT STAFF WELFARE DECEMBER 2022
A3: S/N | B3: STAFF NAME | C3: DESIGNATION | D3: AMOUNT
A5: 1 | B5: Takwasa A. Galadima | C5: Nass Deployed | D5: =50000 -> 50000 | E5: =SUM(D5:D5) -> 50000
A6: 2 | B6: Saratu Adamu Attajiri | C6: Office Assistant | D6: 30000 | E6: =SUM(D6:D6) -> 30000
A7: 3 | B7: Aboaman Innocent | C7: Casual | D7: 20000 | E7: =SUM(D7:D7) -> 20000
A8: 4 | B8: Kusai E. Richard | C8: Plumber | D8: 20000 | E8: =SUM(D8:D8) -> 20000
A9: 5 | B9: Bulus Ishaya | C9: Gardener | D9: 20000 | E9: =SUM(D9:D9) -> 20000
A10: 6 | B10: Sholagberu T Sofiat | C10: Casual | D10: 30000 | E10: =SUM(D10:D10) -> 30000
A11: 7 | B11: Alhamdu Iliya | C11: Casual-Gardner | D11: 20000 | E11: =SUM(D11:D11) -> 20000
A12: 8 | B12: Salihu Hassan | C12: Casual-Gardner | D12: 20000 | E12: =SUM(D12:D12) -> 20000
A13: 9 | B13: Ishaya Moro James | C13: Gardener | D13: 20000 | E13: =SUM(D13:D13) -> 20000
A14: 10 | B14: James G Bathna | C14: Sabbatical | D14: 50000 | E14: =SUM(D14:D14) -> 50000
A15: 11 | B15: John Niyi Olanrewaju | C15: Consultant | D15: =70000 -> 70000
A16: 12 | B16: Enobong Sambo | C16: Retainership | D16: 25000 | E16: =SUM(D16:D16) -> 25000
A17: 13 | B17: Masarr Sarr | C17: Casual | D17: 30000 | E17: =SUM(D17:D17) -> 30000
A18: 14 | B18: Aleke Friday Onyantu | C18: Casual | D18: 30000 | E18: =SUM(D18:D18) -> 30000
A19: 15 | B19: Ode Ijoko Michael | C19: Casual | D19: 30000 | E19: =SUM(D19:D19) -> 30000
A20: 16 | B20: Said Idris Abduljalil | C20: Secondment | D20: 30000 | E20: =SUM(D20:D20) -> 30000
A21: 17 | B21: Giwa Sidika Ajoke | C21: Casual(DGs GH) | D21: 30000 | E21: =SUM(D21:D21) -> 30000
A22: 18 | B22: Abdullahi Ali Arazeem | C22: Sabbatical | D22: 70000
A23: 19 | B23: Muhammed Khadijat | C23: NYSC | D23: 10000 | E23: =SUM(D23:D23) -> 10000
A24: 20 | B24: Rasheed Mariam Folashade | C24: Casual | D24: 30000 | E24: =SUM(D24:D24) -> 30000
A25: 21 | B25: Hadiza Saidu | C25: Sabbatical | D25: 70000 | E25: =SUM(D25:D25) -> 70000
A26: 22 | B26: Adebayo Warith Bolaji | C26: NYSC | D26: =10000 -> 10000 | E26: =SUM(D26:D26) -> 10000
A27: 23 | B27: Moyaki Michael Olumide | C27: NYSC | D27: =10000 -> 10000 | E27: =SUM(D27:D27) -> 10000
A28: 24 | B28: Jibrin Blessing Ojone | C28: NYSC | D28: =10000 -> 10000 | E28: =SUM(D28:D28) -> 10000
A29: 25 | B29: Ajibade Saheed Olabanji | C29: NYSC | D29: =10000 -> 10000 | E29: =SUM(D29:D29) -> 10000
A30: 26 | B30: Suleiman Oluwatosin Mutiat | C30: NYSC | D30: =10000 -> 10000
A31: 27 | B31: Omirinde Mariam | C31: NYSC | D31: =10000 -> 10000
A32: 28 | B32: Mustapha Raheemat Adebola | C32: NYSC | D32: =10000 -> 10000
A33: 29 | B33: Rosemighty Papki Ishaku | C33: NYSC | D33: =10000 -> 10000
A34: 30 | B34: Etti Hawanat Oyenike | C34: Contract Staff | D34: 30000
A35: 31 | B35: Lawal-Gambari Bilkis Sitou | C35: Contract Staff | D35: 30000
A36: 32 | B36: Olaniyan Taiwo Abimbola | C36: Contract Staff | D36: 30000
A37: 33 | B37: Sulaimon Aminat Jumoke | C37: Contract Staff | D37: 30000 | E37: =#REF!-#REF! -> #REF!
A38: 34 | B38: Mustapha Rafiu Ayobanji | C38: Contract Staff | D38: 30000
A39: 35 | B39: Idris Ibrahim | C39: Contract Staff | D39: 30000
A40: 36 | B40: Aishatu O. Usman | C40: Sabbatical | D40: 50000
A41: 37 | B41: Gunat Nansat Mark | C41: Contract Staff | D41: 30000
A42: 38 | B42: Suleima Abubakar Sodeeq | C42: Contract Staff | D42: 30000
A43: 39 | B43: Haruna Jibrin A. | C43: Contract Staff | D43: 30000
A44: 40 | B44: Haruna Musa | C44: Contract Staff | D44: 30000
A45: 41 | B45: Yahaya Adamu Abdulhamid | C45: Contract Staff | D45: 30000
A46: 42 | B46: Elizabeth Ogechukwu Onyeaku | C46: Contract Staff | D46: 30000
A47: 43 | B47: Maryam Musa Sada | C47: Contract Staff | D47: 30000
A48: 44 | B48: Magaji Bala | C48: Contract Staff | D48: 70000
A49: 45 | B49: Adejoh Emmanuel | C49: Sergearnt at Arms | D49: 30000
A50: 46 | B50: Godwin Etim | C50: Sergearnt at Arms | D50: 30000
B51: TOTAL | D51: =SUM(D5:D50) -> 1355000 | E51: =SUM(E5:E37) -> #REF!

Sheet Sallah Welfare June 2023 
A1: CONTRACT/SABBATICAL AND CONSULTANT WELFARE JUNE 2023
A2: S/N | B2: STAFF NAME | C2: DESIGNATION | D2: WELFARE AMOUNT
D3: N
A4: 1 | B4: Dr. Mohammed Etudaiye | C4: Consultant | D4: 75000
A5: 2 | B5: Takwasa A. Galadima | C5: Nass Deployed | D5: 75000
A6: 3 | B6: Saratu Adamu Attajiri | C6: Office Assistant | D6: 45000
A7: 4 | B7: Aboaman Innocent | C7: Casual | D7: 30000
A8: 5 | B8: Kusai E. Richard | C8: Plumber | D8: 30000
A9: 6 | B9: Bulus Ishaya | C9: Gardener | D9: 30000
A10: 7 | B10: Alhamdu Iliya | C10: Casual-Gardner | D10: 30000
A11: 8 | B11: Salihu Hassan | C11: Casual-Gardner | D11: 30000
A12: 9 | B12: Ishaya Moro James | C12: Gardener | D12: 30000
A13: 10 | B13: James G Bathna | C13: Sabbatical | D13: 75000
A14: 11 | B14: Dr. John Niyi Olanrewaju | C14: Consultancy | D14: 75000
A15: 12 | B15: Mr. Shehu Wahab L | C15: Consultant | D15: 75000
... A59: 56 | B59: Francis Onyekwere Ozoh | C59: Sabbatical | D59: 75000
A60: 57 | B60: Prof. Zubairu Kwambo Dagona | C60: Contract Staff | D60: =225000 -> 225000
A61: 58 | B61: Atofarati Umar Faruq | C61: NYSC | D61: 15000
A62: 59 | B62: Ogbormeh Micheal Ikenchukwu | C62: NYSC | D62: 15000
A63: 60 | B63: Abdullahi Sekinat Ayomide | C63: NYSC | D63: 15000
A64: 61 | B64: Mustapha Ola Sulyman | C64: NYSC | D64: 15000
A65: 62 | B65: Muhammad Kudu Abubakar | C65: Ag. Gen Manager | D65: 150000
A66: 63 | B66: Prof. Mohammed Mustapha Namadi | C66: Sabbatical | D66: 75000
A67: 64 | B67: Ibrahim Kaltume Onawo | C67: NYSC | D67: 15000
A68: 65 | B68: Hassan Mahmud Adewole | C68: NYSC | D68: 15000
A69: 66 | B69: Nwanganga Chidozie | C69: House Keeper | D69: 45000
A70: 67 | B70: Mary Shadrach | C70: Cleaner | D70: 45000
A71: 68 | B71: Suberu Rahimat Onize | C71: Intern | D71: 45000
A72: 69 | B72: Akinboboye Oluwatosin Ifedayo | C72: NYSC | D72: 15000
B73: TOTAL | D73: =SUM(D4:D72) -> 2842500
F158: =60000 -> 60000

Sheet Sallah Welfare June 2023 Latest
A1: CONTRACT/SABBATICAL AND CONSULTANT WELFARE JUNE 2023
A2: S/N | B2: STAFF NAME | C2: DESIGNATION | D2: WELFARE AMOUNT
D3: N
A4: 1 | B4: Dr. Mohammed Etudaiye | C4: Consultant | D4: 90000
A5: 2 | B5: Takwasa A. Galadima | C5: Nass Deployed | D5: 90000
A6: 3 | B6: Saratu Adamu Attajiri | C6: Office Assistant | D6: 54000
A7: 4 | B7: Aboaman Innocent | C7: Casual | D7: 36000
A8: 5 | B8: Kusai E. Richard | C8: Plumber | D8: 36000
A9: 6 | B9: Bulus Ishaya | C9: Gardener | D9: 36000
A10: 7 | B10: Alhamdu Iliya | C10: Casual-Gardner | D10: 36000
A11: 8 | B11: Salihu Hassan | C11: Casual-Gardner | D11: 36000
A12: 9 | B12: Ishaya Moro James | C12: Gardener | D12: 36000
A13: 10 | B13: James G Bathna | C13: Sabbatical | D13: 90000
A14: 11 | B14: Dr. John Niyi Olanrewaju | C14: Consultancy | D14: 90000
A15: 12 | B15: Mr. Shehu Wahab L | C15: Consultant | D15: 90000
... A66: 63 | B66: Akinboboye Oluwatosin Ifedayo | C66: NYSC | D66: 18000
B67: TOTAL | D67: =SUM(D4:D66) -> 3159000
F152: =60000 -> 60000

Sheet Sheet27

Sheet Sallah Welfare April 2023
A1: CONTRACT/SABBATICAL AND CONSULTANT WELFARE APRIL 2023
A3: S/N | B3: STAFF NAME | C3: DESIGNATION | D3: WELFARE AMOUNT
D4: N
A5: 1 | B5: Dr. Mohammed Etudaiye | C5: Consultant | D5: 75000
A6: 2 | B6: Takwasa A. Galadima | C6: Nass Deployed | D6: 75000
A7: 3 | B7: Saratu Adamu Attajiri | C7: Office Assistant | D7: 45000
A8: 4 | B8: Aboaman Innocent | C8: Casual | D8: 30000
A9: 5 | B9: Kusai E. Richard | C9: Plumber | D9: 30000
A10: 6 | B10: Bulus Ishaya | C10: Gardener | D10: 30000
A11: 8 | B11: Alhamdu Iliya | C11: Casual-Gardner | D11: 30000
A12: 9 | B12: Salihu Hassan | C12: Casual-Gardner | D12: 30000
A13: 10 | B13: Ishaya Moro James | C13: Gardener | D13: 30000
A14: 11 | B14: James G Bathna | C14: Sabbatical | D14: 75000
A15: 12 | B15: Dr. John Niyi Olanrewaju | C15: Consultancy | D15: 75000
A16: 13 | B16: Mr. Shehu Wahab L | C16: Consultant | D16: 75000
... A61: 62 | B61: Francis Onyekwere Ozoh | C61: Sabbatical | D61: 75000
B62: TOTAL | D62: =SUM(D5:D61) -> 2197500
A67: PREPARED BY: RAHILA N. HABU
F149: =60000 -> 60000

Sheet March (2)
A1: CONTRACT/SABBATICAL AND CONSULTANT SALARY FOR THE MONTH OF MARCH 2023
A3: S/N | B3: STAFF NAME | C3: DESIGNATION | D3: BASIC ALLOWANCE | E3: LEGISLATIVE ALLOWCE | F3: GROSS | G3: DEDUCTIONS | K3: NET SALARY MARCH 2023
G4: COOP CONTR | H4: COOP LOAN RECOVERY | I4: PAYE TAX | J4: TOTAL DEDUCTION | K4: N
A5: 1 | B5: Dr. Mohammed Etudaiye | C5: Consultant | D5: =300000 -> 300000 | E5: =0 -> 0 | F5: =D5+E5 -> 300000 | I5: 37566.667 | J5: =G5+H5+I5 -> 37566.667 | K5: =F5-J5 -> 262433.33
A6: 2 | B6: Takwasa A. Galadima | C6: Nass Deployed | D6: =136027.8 -> 136027.8 | E6: =60000 -> 60000 | F6: =D6+E6 -> 196027.8 | G6: =30000 -> 30000 | I6: ='[1]August 2022 '!$AD$6 -> 20099.337 | J6: =G6+H6+I6 -> 50099.337 | K6: =F6-J6 -> 145928.46
A7: 3 | B7: Saratu Adamu Attajiri | C7: Office Assistant | D7: 90000 | E7: 30000 | F7: =D7+E7 -> 120000 | G7: 10000 | H7: =20000 -> 20000 | I7: 8900 | J7: =G7+H7+I7 -> 38900 | K7: =F7-J7 -> 81100
A8: 4 | B8: Aboaman Innocent | C8: Casual | D8: 45000 | E8: 15000 | F8: =D8+E8 -> 60000 | G8: =10000 -> 10000 | H8: =10000+10000 -> 20000 | I8: 2446.6667 | J8: =G8+H8+I8 -> 32446.667 | K8: =F8-J8 -> 27553.333
A9: 5 | B9: Kusai E. Richard | C9: Plumber | D9: 45000 | E9: 15000 | F9: =D9+E9 -> 60000 | G9: =10000 -> 10000 | H9: =20000 -> 20000 | I9: 2446.6667 | J9: =G9+H9+I9 -> 32446.667 | K9: =F9-J9 -> 27553.333
A10: 6 | B10: Bulus Ishaya | C10: Gardener | D10: 45000 | E10: 15000 | F10: =D10+E10 -> 60000 | I10: 2446.6667 | J10: =G10+H10+I10 -> 2446.6667 | K10: =F10-J10 -> 57553.333
A11: 8 | B11: Alhamdu Iliya | C11: Casual-Gardner | D11: =50000 -> 50000 | E11: 15000 | F11: =D11+E11 -> 65000 | G11: =5000+5000+5000 -> 15000 | H11: =14350 -> 14350 | I11: 2886.6667 | J11: =G11+H11+I11 -> 32236.667 | K11: =F11-J11 -> 32763.333
A12: 9 | B12: Salihu Hassan | C12: Casual-Gardner | D12: =50000 -> 50000 | E12: 15000 | F12: =D12+E12 -> 65000 | G12: =5000 -> 5000 | H12: 10500 | I12: 2886.6667 | J12: =G12+H12+I12 -> 18386.667 | K12: =F12-J12 -> 46613.333
A13: 10 | B13: Ishaya Moro James | C13: Gardener | D13: =60000 -> 60000 | E13: 20000 | F13: =D13+E13 -> 80000 | G13: =10000 -> 10000 | H13: =17500 -> 17500 | I13: 4206.6667 | J13: =G13+H13+I13 -> 31706.667 | K13: =F13-J13 -> 48293.333
A14: 11 | B14: James G Bathna | C14: Sabbatical | D14: =300000 -> 300000 | F14: =D14+E14 -> 300000 | I14: 37566.667 | J14: =G14+H14+I14 -> 37566.667 | K14: =F14-J14 -> 262433.33
A15: 12 | B15: Dr. John Niyi Olanrewaju | C15: Consultancy | D15: =500000 -> 500000 | E15: =0 -> 0 | F15: =D15+E15 -> 500000 | G15: 25000 | H15: 60640 | I15: 74666.667 | J15: =G15+H15+I15 -> 160306.67 | K15: =F15-J15 -> 339693.33
A16: 13 | B16: Mr. Shehu Wahab L | C16: Consultant | D16: 300000 | E16: 0 | F16: =D16+E16 -> 300000 | I16: 37566.667 | J16: =G16+H16+I16 -> 37566.667 | K16: =F16-J16 -> 262433.33
A17: 14 | B17: Enobong Sambo | C17: Retainership | D17: =70000 -> 70000 | E17: 20000 | F17: =D17+E17 -> 90000 | G17: =0 -> 0 | I17: 5300 | J17: =G17+H17+I17 -> 5300 | K17: =F17-J17 -> 84700
A18: 15 | B18: Masarr Sarr | C18: Casual | D18: =90000 -> 90000 | E18: 30000 | F18: =D18+E18 -> 120000 | I18: 8900 | J18: =G18+H18+I18 -> 8900 | K18: =F18-J18 -> 111100
A19: 16 | B19: Aleke Friday Onyantu | C19: Casual | D19: =90000 -> 90000 | E19: =30000 -> 30000 | F19: =D19+E19 -> 120000 | I19: 8900 | J19: =G19+H19+I19 -> 8900 | K19: =F19-J19 -> 111100
A20: 17 | B20: Ode Ijoko Michael | C20: Casual | D20: =90000 -> 90000 | E20: =30000 -> 30000 | F20: =D20+E20 -> 120000 | I20: 8900 | J20: =G20+H20+I20 -> 8900 | K20: =F20-J20 -> 111100
A21: 18 | B21: Said Idris Abduljalil | C21: Secondment | D21: =105352.17 -> 105352.17 | E21: =(60000+50000) -> 110000 | F21: =D21+E21 -> 215352.17 | I21: 23345.831 | J21: =G21+H21+I21 -> 23345.831 | K21: =F21-J21 -> 192006.34
A22: 19 | B22: Giwa Sidika Ajoke | C22: Casual (DGs GH) | D22: =90000 -> 90000 | E22: =30000 -> 30000 | F22: =D22+E22 -> 120000 | I22: 8900 | J22: =G22+H22+I22 -> 8900 | K22: =F22-J22 -> 111100
A23: 21 | B23: Rasheed Mariam Folashade | C23: Casual | D23: 90000 | E23: =30000 -> 30000 | F23: =D23+E23 -> 120000 | I23: 8900 | J23: =G23+H23+I23 -> 8900 | K23: =F23-J23 -> 111100
A24: 22 | B24: Hadiza Saidu | C24: Sabbatical | D24: =399385.82 -> 399385.82 | E24: =160000 -> 160000 | F24: =D24+E24 -> 559385.82 | I24: 86068.744 | J24: =G24+H24+I24 -> 86068.744 | K24: =F24-J24 -> 473317.08
A25: 24 | B25: Moyaki Michael Olumide | C25: NYSC | D25: 15000 | F25: =D25+E25 -> 15000 | I25: 0 | J25: =G25+H25+I25 -> 0 | K25: =F25-J25 -> 15000
A26: 25 | B26: Jibrin Blessing Ojone | C26: NYSC | D26: 15000 | F26: =D26+E26 -> 15000 | I26: 0 | J26: =G26+H26+I26 -> 0 | K26: =F26-J26 -> 15000
A27: 27 | B27: Suleiman Oluwatosin Mutiat | C27: NYSC | D27: 15000 | F27: =D27+E27 -> 15000 | I27: 0 | J27: =G27+H27+I27 -> 0 | K27: =F27-J27 -> 15000
A28: 29 | B28: Mustapha Raheemat Adebola | C28: NYSC | D28: 15000 | F28: =D28+E28 -> 15000 | I28: 0 | J28: =G28+H28+I28 -> 0 | K28: =F28-J28 -> 15000
A29: 30 | B29: Rosemighty Papki Ishaku | C29: NYSC | D29: 15000 | F29: =D29+E29 -> 15000 | I29: 0 | J29: =G29+H29+I29 -> 0 | K29: =F29-J29 -> 15000
A30: 31 | B30: Etti Hawanat Oyenike | C30: Contract Staff | D30: =123329.05 -> 123329.05 | E30: 50000 | F30: =D30+E30 -> 173329.05 | I30: =16512.68 -> 16512.68 | J30: =G30+H30+I30 -> 16512.68 | K30: =F30-J30 -> 156816.37
A31: 32 | B31: Lawal-Gambari Bilkis Sitou | C31: Contract Staff | D31: ='[3]Nils Salary Structure'!$H$36 -> 168601.58 | E31: 100000 | F31: =D31+E31 -> 268601.58 | I31: =32291.82 -> 32291.82 | J31: =G31+H31+I31 -> 32291.82 | K31: =F31-J31 -> 236309.76
A32: 33 | B32: Olaniyan Taiwo Abimbola | C32: Contract Staff | D32: ='[3]Nils Salary Structure'!$H$35 -> 145203.67 | E32: 100000 | F32: =D32+E32 -> 245203.67 | I32: =21640.95 -> 21640.95 | J32: =G32+H32+I32 -> 21640.95 | K32: =F32-J32 -> 223562.72
A33: 34 | B33: Sulaimon Aminat Jumoke | C33: Contract Staff | D33: =123329.05 -> 123329.05 | E33: 50000 | F33: =D33+E33 -> 173329.05 | G33: 20000 | I33: =I30 -> 16512.68 | J33: =G33+H33+I33 -> 36512.68 | K33: =F33-J33 -> 136816.37
A34: 35 | B34: Mustapha Rafiu Ayobanji | C34: Contract Staff | D34: ='[4]October 2022'!$R$108-60000 -> 244895.91 | E34: 60000 | F34: =D34+E34 -> 304895.91 | I34: =31749.1368366667 -> 31749.137 | J34: =G34+H34+I34 -> 31749.137 | K34: =F34-J34 -> 273146.78
A35: 36 | B35: Idris Ibrahim | C35: Contract Staff | D35: =205372.08 -> 205372.08 | E35: 110000 | F35: =D35+E35 -> 315372.08 | I35: ='Arrears in Nov'!B4 -> 40149.18 | J35: =G35+H35+I35 -> 40149.18 | K35: =F35-J35 -> 275222.9
A36: 37 | B36: Aishatu O. Usman | C36: Sabbatical | D36: 328759.88 | E36: 160000 | F36: =D36+E36 -> 488759.88 | I36: =72508.5636266667 -> 72508.564 | J36: =G36+H36+I36 -> 72508.564 | K36: =F36-J36 -> 416251.32
A37: 38 | B37: Maryam Musa Sada | C37: Contract Staff | D37: =268602.07775-100000 -> 168602.08 | E37: 100000 | F37: =D37+E37 -> 268602.08 | I37: 32291.82 | J37: =G37+H37+I37 -> 32291.82 | K37: =F37-J37 -> 236310.26
A38: 39 | B38: Garba Rofiat Kehinde | C38: NYSC | D38: 15000 | F38: =D38+E38 -> 15000 | I38: 0 | J38: =G38+H38+I38 -> 0 | K38: =F38-J38 -> 15000
A39: 40 | B39: Ogah Friday David | C39: NYSC | D39: 15000 | F39: =D39+E39 -> 15000 | I39: 0 | J39: =G39+H39+I39 -> 0 | K39: =F39-J39 -> 15000
A40: 41 | B40: Ismail Fauzyat | C40: NYSC | D40: 15000 | F40: =D40+E40 -> 15000 | I40: 0 | J40: =G40+H40+I40 -> 0 | K40: =F40-J40 -> 15000
A41: 42 | B41: Owolabi Olawale Adebayo | C41: NYSC | D41: 15000 | F41: =D41+E41 -> 15000 | I41: 0 | J41: =G41+H41+I41 -> 0 | K41: =F41-J41 -> 15000
A42: 43 | B42: Sale Angbo Likita | C42: NYSC | D42: 15000 | F42: =D42+E42 -> 15000 | I42: 0 | J42: =G42+H42+I42 -> 0 | K42: =F42-J42 -> 15000
A43: 44 | B43: Mariam Adepeju Abdulraheem-Mustapha | C43: Sabbatical | D43: =385939.33 -> 385939.33 | E43: =160000 -> 160000 | F43: =D43+E43 -> 545939.33 | I43: =83487.02 -> 83487.02 | J43: =G43+H43+I43 -> 83487.02 | K43: =F43-J43 -> 462452.31
A44: 45 | B44: Peter Siyan | C44: Sabbatical | D44: =502746.92 -> 502746.92 | E44: 180000 | F44: =D44+E44 -> 682746.92 | H44: ='Arrears in Nov'!G10 -> 0 | I44: 109754.08 | J44: =G44+H44+I44 -> 109754.08 | K44: =F44-J44 -> 572992.84
A45: 46 | B45: Anyanyo Uchechukwu Nathan | C45: NYSC | D45: 15000 | F45: =D45+E45 -> 15000 | I45: 0 | J45: =G45+H45+I45 -> 0 | K45: =F45-J45 -> 15000
A46: 47 | B46: Ajagbonna Ibukun Victor | C46: NYSC | D46: 15000 | F46: =D46+E46 -> 15000 | I46: 0 | J46: =G46+H46+I46 -> 0 | K46: =F46-J46 -> 15000
A47: 48 | B47: Augustine Azibaolanary Thomas | C47: NYSC | D47: 15000 | F47: =D47+E47 -> 15000 | I47: 0 | J47: =G47+H47+I47 -> 0 | K47: =F47-J47 -> 15000
A48: 49 | B48: Ekeh Patience Nkechi | C48: NYSC | D48: 15000 | F48: =D48+E48 -> 15000 | I48: 0 | J48: =G48+H48+I48 -> 0 | K48: =F48-J48 -> 15000
A49: 50 | B49: Muhammad Mustapha | C49: NYSC | D49: 15000 | F49: =D49+E49 -> 15000 | I49: 0 | J49: =G49+H49+I49 -> 0 | K49: =F49-J49 -> 15000
A50: 51 | B50: Idris Hafsat Aminu | C50: NYSC | D50: 15000 | F50: =D50+E50 -> 15000 | I50: 0 | J50: =G50+H50+I50 -> 0 | K50: =F50-J50 -> 15000
A51: 52 | B51: Adefajo O. Ibrahim | C51: NYSC | D51: 15000 | F51: =D51+E51 -> 15000 | I51: 0 | J51: 0 | K51: =F51-J51 -> 15000
A52: 53 | B52: Ibok Rhoda Nsa | C52: NYSC | D52: 15000 | F52: =D52+E52 -> 15000 | I52: 0 | J52: 0 | K52: =F52-J52 -> 15000
A53: 54 | B53: Dung Juliana Zakka | C53: NYSC | D53: 15000 | F53: 15000 | I53: 0 | J53: 0 | K53: 15000
A54: 55 | B54: Odomadehi Iyinmekhumen Olufeyikemi | C54: NYSC | D54: 15000 | F54: 15000 | I54: 0 | J54: 0 | K54: 15000
A55: 56 | B55: Mbat Brian Dominic | C55: NYSC | D55: 15000 | F55: 15000 | I55: 0 | J55: 0 | K55: 15000
A56: 57 | B56: Oyinlola Aishah Temitope | C56: NYSC | D56: 15000 | F56: 15000 | I56: 0 | J56: 0 | K56: 15000
A57: 58 | B57: Jibril Muhammed Amees | C57: NYSC | D57: 15000 | F57: 15000 | I57: 0 | J57: 0 | K57: 15000
A58: 59 | B58: Sholagberu Taiye Sofia | C58: 1st 28 days | D58: 560000 | E58: 0 | F58: =D58+E58 -> 560000 | K58: =F58 -> 560000
A59: 60 | B59: Shafiu Yahaya Mikail | C59: 1st 28 days | D59: =25000*28 -> 700000 | E59: 0 | F59: =D59+E59 -> 700000 | K59: =F59 -> 700000
A60: 61 | B60: Isere Richard Kantee | C60: 1st 28 days | D60: 560000 | E60: 0 | F60: =D60+E60 -> 560000 | K60: =F60 -> 560000
A61: 62 | B61: Abdul Jamila | C61: 1st 28 days | D61: 560000 | E61: 0 | F61: =D61+E61 -> 560000 | K61: =F61 -> 560000
A62: 63 | B62: Haruna Musa | C62: 1st 28 days | D62: 560000 | E62: 0 | F62: =D62+E62 -> 560000 | K62: =F62 -> 560000
A63: 64 | B63: Hassan Yerima | C63: 1st 28 days | D63: =25000*28 -> 700000 | F63: =D63+E63 -> 700000 | K63: =F63 -> 700000
A64: 65 | B64: Enenche Jeremiah Agada | C64: 1st 28 days | D64: 560000 | E64: 0 | F64: =D64+E64 -> 560000 | K64: =F64 -> 560000
A65: 66 | B65: Farooq Onikijipa Afeez | C65: 1st 28 days | D65: 560000 | E65: 0 | F65: =D65+E65 -> 560000 | K65: =F65 -> 560000
B66: TOTAL | D66: =SUM(D5:D65) -> 10447545 | E66: =SUM(E5:E65) -> 1695000 | F66: =SUM(F5:F65) -> 12142545 | G66: =SUM(G5:G65) -> 135000 | H66: =SUM(H5:H65) -> 162990 | I66: =SUM(I5:I65) -> 849798.51 | J66: =SUM(J5:J65) -> 1147788.5 | K66: =SUM(K5:K65) -> 10994757
A71: PREPARED BY: RAHILA N. HABU
M153: =60000 -> 60000

Sheet Sheet26

Sheet Arrears in Nov
A2: Idris Ibrahim | B2: New Placement | C2: 40 days old grade | D2: 40 days New placement | E2: diffrence | F2: Total Salary in November
B3: 315372.08 | C3: 346583.33 | D3: 406931.72 | E3: =D3-C3 -> 60348.39 | F3: =B3+E3 -> 375720.47
B4: 40149.18 | C4: 41666.865 | D4: 51805.394 | E4: =D4-C4 -> 10138.529 | F4: =B4+E4 -> 50287.709
B5: 275222.9 | C5: 304916.46 | D5: 355126.32 | E5: =D5-C5 -> 50209.861 | F5: =B5+E5 -> 325432.76
A7: Emily | B7: Diff for 1 month | C7: No of Month | D7: Total
B8: ='[5]Promotion Arrear'!$H$17 -> 8607 | C8: =7.73 -> 7.73 | D8: =B8*C8 -> 66532.11
A9: Research Allowance | B9: 20000 | C9: =7.73 -> 7.73 | D9: =B9*C9 -> 154600
B10: Total Arrears | D10: =SUM(D8:D9) -> 221132.11

Sheet Salah Welfare
G5: DEDUCTIONS | K5: WELFARE
A6: S/N | B6: STAFF NAME | C6: DESIGNATION | D6: GROSS | E6: LEGISLATIVE | F6: GROSS | K6: 44743
G7: COOP CONTR | H7: COOP LOAN | I7: TAX | J7: TOTAL DEDUCTION | K7: N
A8: 1 | B8: Takwasa A. Galadima | C8: Nass Deployed | D8: 114649.42 | E8: =60000 -> 60000 | F8: =D8+E8 -> 174649.42 | G8: =30000 -> 30000 | I8: 0 | J8: =G8+H8+I8 -> 30000 | K8: 30000
A9: 2 | B9: Saratu Adamu Attajiri | C9: Office Assistant | D9: 90000 | E9: 30000 | F9: =D9+E9 -> 120000 | G9: 50000 | H9: =20000 -> 20000 | I9: 0 | J9: =G9+H9+I9 -> 70000 | K9: 30000
A10: 3 | B10: Aboaman Innocent | C10: Casual | D10: 45000 | E10: 15000 | F10: =D10+E10 -> 60000 | G10: =10000 -> 10000 | H10: =10000+10000 -> 20000 | I10: 0 | J10: =G10+H10+I10 -> 30000 | K10: 20000
A11: 4 | B11: Kusai E. Richard | C11: Plumber | D11: 45000 | E11: 15000 | F11: =D11+E11 -> 60000 | G11: =10000 -> 10000 | H11: =20000 -> 20000 | I11: 0 | J11: =G11+H11+I11 -> 30000 | K11: 20000
A12: 5 | B12: Ayuba Sule | C12: Contract | D12: =96825 -> 96825 | E12: 30000 | F12: =D12+E12 -> 126825 | G12: =10000+5000 -> 15000 | H12: =32000 -> 32000 | I12: 0 | J12: =G12+H12+I12 -> 47000 | K12: 30000
A13: 6 | B13: Bulus Ishaya | C13: Gardener | D13: 45000 | E13: 15000 | F13: =D13+E13 -> 60000 | J13: =G13+H13+I13 -> 0 | K13: 20000
A14: 7 | B14: Sholagberu T Sofiat | C14: Casual | D14: =90000 -> 90000 | E14: 30000 | F14: =D14+E14 -> 120000 | G14: =30000 -> 30000 | H14: =0 -> 0 | J14: =G14+H14+I14 -> 30000 | K14: 30000
A15: 8 | B15: Jimoh Munirat Olaide | C15: Casual | D15: =90000 -> 90000 | E15: 30000 | F15: =D15+E15 -> 120000 | G15: =50000 -> 50000 | H15: =10000 -> 10000 | J15: =G15+H15+I15 -> 60000 | K15: 30000
A16: 9 | B16: Alhamdu Iliya | C16: Casual-Gardner | D16: =50000 -> 50000 | E16: 15000 | F16: =D16+E16 -> 65000 | G16: =5000+5000 -> 10000 | H16: =14350 -> 14350 | J16: =G16+H16+I16 -> 24350 | K16: 20000
A17: 10 | B17: Salihu Hassan | C17: Casual-Gardner | D17: =50000 -> 50000 | E17: 15000 | F17: =D17+E17 -> 65000 | G17: =5000 -> 5000 | J17: =G17+H17+I17 -> 5000 | K17: 20000
A18: 11 | B18: Ishaya Moro James | C18: Gardener | D18: =60000 -> 60000 | E18: 20000 | F18: =D18+E18 -> 80000 | G18: =10000 -> 10000 | J18: =G18+H18+I18 -> 10000 | K18: 20000
A19: 12 | B19: John Niyi Olanrewaju | C19: Consultant | K19: =70000 -> 70000
A20: 13 | B20: Enobong Sambo | C20: Retainership | D20: =70000 -> 70000 | E20: 20000 | F20: =D20+E20 -> 90000 | G20: =0 -> 0 | J20: =G20+H20+I20 -> 0 | K20: 20000
A21: 14 | B21: Masarr Sarr | C21: Casual | D21: =90000 -> 90000 | E21: 30000 | F21: =(D21+E21) -> 120000 | J21: =G21+H21+I21 -> 0 | K21: 30000
A22: 15 | B22: Yahaya Adamu Abdulhamid | C22: Casual | D22: =90000 -> 90000 | E22: 30000 | F22: =D22+E22 -> 120000 | J22: =G22+H22+I22 -> 0 | K22: 30000
A23: 16 | B23: Frances Edna Hananiya | C23: Casual | D23: =90000 -> 90000 | E23: 30000 | F23: =D23+E23 -> 120000 | J23: =G23+H23+I23 -> 0 | K23: 30000
A24: 17 | B24: Hazeem Hussain | C24: Casual | D24: =90000 -> 90000 | E24: =30000 -> 30000 | F24: =(D24+E24) -> 120000 | G24: =3000 -> 3000 | H24: =25000 -> 25000 | J24: =G24+H24 -> 28000 | K24: 30000
A25: 18 | B25: Aleke Friday Onyantu | C25: Casual | D25: =90000 -> 90000 | E25: =30000 -> 30000 | F25: =(D25+E25) -> 120000 | J25: =G25+H25+I25 -> 0 | K25: 30000
A26: 19 | B26: Ode Ijoko Michael | C26: Casual | D26: =90000 -> 90000 | E26: =30000 -> 30000 | F26: =(D26+E26) -> 120000 | J26: =G26+H26+I26 -> 0 | K26: 30000
A27: 20 | B27: Haruna Jibril Ameh | C27: Casual | D27: =90000 -> 90000 | E27: =30000 -> 30000 | F27: =D27+E27 -> 120000 | J27: =G27+H27+I27 -> 0 | K27: 30000
A28: 21 | B28: Akwawo Michele Kennedy | C28: NYSC | D28: =15000 -> 15000 | F28: =D28+E28 -> 15000 | J28: =G28+H28+I28 -> 0 | K28: 10000
A29: 22 | B29: Schicha Ebweyi Joshua | C29: NYSC | D29: =15000 -> 15000 | F29: 15000 | J29: =G29+H29+I29 -> 0 | K29: 10000
A30: 23 | B30: Abdullahi Ali Arazeem | C30: Sabbatical | D30: =373287.83 -> 373287.83 | E30: =160000 -> 160000 | F30: =D30+E30 -> 533287.83 | I30: =15548.33 -> 15548.33 | J30: =G30+H30+I30 -> 15548.33 | K30: =70000 -> 70000
A31: 24 | B31: Moyosore Maryaam Ajoke | C31: NYSC | D31: 15000 | E31: 0 | F31: 15000 | J31: =G31+H31+I31 -> 0 | K31: 10000
A32: 25 | B32: Demokun Friday Martin | C32: NYSC | D32: 15000 | F32: 15000 | J32: =G32+H32+I32 -> 0 | K32: 10000
A33: 26 | B33: Said Idris Abduljalil | C33: Secondment | D33: =105352.17 -> 105352.17 | E33: =(60000+50000) -> 110000 | F33: =D33+E33 -> 215352.17 | I33: =4771.84 -> 4771.84 | J33: =G33+H33+I33 -> 4771.84 | K33: 30000
A34: 27 | B34: Giwa Sidika Ajoke | C34: Casual | D34: =90000 -> 90000 | E34: =30000 -> 30000 | F34: =D34+E34 -> 120000 | K34: 30000
A35: 28 | B35: Gunat Nansat Mark | C35: NYSC | D35: =15000 -> 15000 | E35: 0 | F35: =D35+E35 -> 15000 | K35: 10000
A36: 29 | B36: Sogaolu O Oreoluwa | C36: NYSC | D36: =15000 -> 15000 | F36: =D36+E36 -> 15000 | K36: 10000
A37: 30 | B37: Yahya Zaiyad Alhaji | C37: NYSC | D37: =15000 -> 15000 | F37: =D37+E37 -> 15000 | K37: 10000
A38: 31 | B38: Nkwere Ozioma Philippa | C38: NYSC | D38: =15000 -> 15000 | F38: =D38+E38 -> 15000 | K38: 10000
A39: 32 | B39: Salihu Abubakar Musa | C39: NYSC | D39: =15000 -> 15000 | F39: =D39+E39 -> 15000 | K39: 10000
A40: 33 | B40: Oladele Zainab Ayomide | C40: NYSC | D40: =15000 -> 15000 | E40: =0 -> 0 | F40: =D40+E40 -> 15000 | K40: 10000
A41: 34 | B41: Ibyeenegh Bosua Keziah | C41: NYSC | D41: =15000 -> 15000 | E41: =0 -> 0 | F41: =D41+E41 -> 15000 | K41: 10000
A42: 35 | B42: Muhammed Khadijah Grema | C42: NYSC | D42: 15000 | E42: 0 | F42: 15000 | K42: 10000
A43: 36 | B43: Salahudden Hameedah | C43: NYSC | D43: 15000 | E43: 0 | F43: 15000 | K43: 10000
A44: 37 | B44: Domendu Desmond Chibueze | C44: NYSC | D44: 15000 | E44: 0 | F44: 15000 | K44: 10000
A45: 38 | B45: Abdulraheem Ramatu Ibrahim | C45: NYSC | D45: 15000 | E45: 0 | F45: 15000 | K45: 10000
A46: 39 | B46: Rasheed Mariam Folashade | C46: Casual | D46: 90000 | E46: =30000+76451.61+76451.61 -> 182903.22 | F46: =D46+E46 -> 272903.22 | K46: 30000
A47: 40 | B47: Yusuff Kehinde Paul | C47: NYSC | D47: =15000 -> 15000 | E47: 0 | F47: =15000 -> 15000 | K47: 10000
A48: 41 | B48: Victor Jarumi | C48: NYSC | D48: 15000 | E48: 0 | F48: 15000 | K48: 10000
A49: 42 | B49: Ntuka Ogochukwu Emmanuel | C49: NYSC | D49: 15000 | F49: =D49+E49 -> 15000 | K49: 10000
A50: 43 | B50: Zubair Fareedah Olamide | C50: NYSC | D50: 15000 | F50: =D50+E50 -> 15000 | K50: 10000
A51: 44 | B51: Sojinu Ayobami Sebasi | C51: NYSC | D51: 15000 | F51: =D51+E51 -> 15000 | K51: 10000
A52: 45 | B52: Ogunmiluyi Adetutu Winifred | C52: NYSC | D52: 15000 | F52: =D52+E52 -> 15000 | K52: 10000
A53: 46 | B53: Ajileye O Elisha | C53: NYSC | D53: 15000 | F53: =D53+E53 -> 15000 | K53: 10000
A54: 47 | B54: Oaikhienan James Ehidiamen | C54: NYSC | D54: 15000 | F54: =D54+E54 -> 15000 | K54: 10000
A55: 48 | B55: Hadiza Saidu | C55: Sabbatical | D55: =399385.82 -> 399385.82 | E55: =160000 -> 160000 | F55: =D55+E55 -> 559385.82 | I55: 15548.33 | J55: 15548.33 | K55: 50000
A56: 49 | B56: Adebayo Warith Bolaji | C56: NYSC | D56: =15000 -> 15000 | E56: 0 | F56: 15000 | K56: 10000
A57: 50 | B57: Muhammed Khadijat | C57: NYSC | D57: 15000 | F57: 15000 | K57: 10000
A58: 51 | B58: Moyaki Michael Olumide | C58: NYSC | K58: 10000
A59: 52 | B59: Jibrin Blessing Ojone | C59: NYSC | D59: 15000 | F59: 15000 | K59: 10000
A60: 53 | B60: Ajibade Saheed Olabanji | C60: NYSC | D60: 15000 | F60: 15000 | K60: 10000
A61: 54 | B61: Adejoh Emmanuel | C61: Sergearnt at Arms | K61: =30000 -> 30000
A62: 55 | B62: Godwin Etim | C62: Sergearnt at Arms | K62: =30000 -> 30000
B63: TOTAL | D63: =SUM(D8:D57) -> 2909500.2 | E63: =SUM(E8:E57) -> 1147903.2 | F63: =SUM(F8:F57) -> 4057403.5 | G63: =SUM(G8:G57) -> 223000 | H63: =SUM(H8:H57) -> 141350 | I63: =SUM(I8:I57) -> 35868.5 | J63: =SUM(J8:J57) -> 400218.5 | K63: =SUM(K8:K62) -> 1120000
D64: TONDO, IORWUESE EDWRAD | G64: =H63+G63 -> 364350

Sheet Enhanced Welfare2
A3: CONTRACT/SABBATICAL AND CONSULTANT SALARY FOR THE MONTH OF JANUARY 2022
G5: DEDUCTIONS | K5: WELFARE
A6: S/N | B6: STAFF NAME | C6: DESIGNATION | D6: GROSS | E6: LEGISLATIVE | F6: GROSS | K6: N
A7: 1 | B7: Takwasa A. Galadima | C7: Nass Deployed | D7: 114649.42 | E7: =60000 -> 60000 | F7: =D7+E7 -> 174649.42 | G7: =30000 -> 30000 | I7: 0 | J7: =G7+H7+I7 -> 30000 | K7: =300000 -> 300000
A8: 2 | B8: Abdullahi Ali Arazeem | C8: Sabbatical | D8: =373287.83 -> 373287.83 | E8: =160000 -> 160000 | F8: =D8+E8 -> 533287.83 | I8: =15548.33 -> 15548.33 | J8: =G8+H8+I8 -> 15548.33 | K8: =250000 -> 250000
A9: 3 | B9: Said Idris Abduljalil | C9: Secondment | D9: =105352.17 -> 105352.17 | E9: =(60000+50000) -> 110000 | F9: =D9+E9 -> 215352.17 | I9: =4771.84 -> 4771.84 | J9: =G9+H9+I9 -> 4771.84 | K9: =300000 -> 300000
A10: 4 | B10: Onyeaku Ogechukwu Elizabeth | C10: Contract | K10: =300000 -> 300000
D11: =SUM(D7:D9) -> 593289.42 | E11: =SUM(E7:E9) -> 330000 | F11: =SUM(F7:F9) -> 923289.42 | G11: =SUM(G7:G9) -> 30000 | H11: =SUM(H7:H9) -> 0 | I11: =SUM(I7:I9) -> 20320.17 | J11: =SUM(J7:J9) -> 50320.17 | K11: =SUM(K7:K10) -> 1150000
C12: PREPARED BY: | D12: TONDO, IORWUESE EDWRAD | G12: =H11+G11 -> 30000
G13: =436350-G12 -> 406350

Sheet Enhanced Welfare 2023
A1: CONTRACT, CASUAL AND NASS DEPLOYED STAFF ENHANCED WELFARE FOR 2023
A3: S/N | B3: STAFF NAME | C3: DESIGNATION | D3: AMOUNT
A4: 1 | B4: Takwasa A. Galadima | C4: Nass Deployed | D4: 500000
A5: 2 | B5: Saratu Adamu Attajiri | C5: Office Assistant | D5: 300000
A6: 3 | B6: Aboaman Innocent | C6: Casual | D6: 100000
A7: 4 | B7: Kusai E. Richard | C7: Plumber | D7: 100000
A8: 5 | B8: Bulus Ishaya | C8: Gardener | D8: 100000
A9: 6 | B9: Sholagberu T Sofiat | C9: Casual | D9: 300000
A10: 7 | B10: Alhamdu Iliya | C10: Casual-Gardner | D10: 100000
A11: 8 | B11: Salihu Hassan | C11: Casual-Gardner | D11: 100000
A12: 9 | B12: Ishaya Moro James | C12: Gardener | D12: 100000
A13: 10 | B13: John Niyi Olanrewaju | C13: Consultant | D13: 250000
A14: 11 | B14: Enobong Sambo | C14: Retainership | D14: 100000
A15: 12 | B15: Masarr Sarr | C15: Casual | D15: 300000
... A26: 23 | B26: Idris Ibrahim | C26: Contract Staff | D26: 400000
B27: TOTAL | D27: =SUM(D4:D26) -> 5850000

Sheet Enhanced Welfare 2023 (2)
A1: CONTRACT/SABBATICAL AND CONSULTANT STAFF WELFARE FOR 2023
A3: S/N | B3: STAFF NAME | C3: DESIGNATION | D3: AMOUNT
A5: 1 | B5: Takwasa A. Galadima | C5: Nass Deployed | D5: 500000 | E5: =SUM(D5:D5) -> 500000
A6: 2 | B6: Saratu Adamu Attajiri | C6: Office Assistant | D6: 300000 | E6: =SUM(D6:D6) -> 300000
A7: 3 | B7: Aboaman Innocent | C7: Casual | D7: 100000 | E7: =SUM(D7:D7) -> 100000
A8: 4 | B8: Kusai E. Richard | C8: Plumber | D8: 100000 | E8: =SUM(D8:D8) -> 100000
A9: 5 | B9: Bulus Ishaya | C9: Gardener | D9: 100000 | E9: =SUM(D9:D9) -> 100000
A10: 6 | B10: Sholagberu T Sofiat | C10: Casual | D10: 300000 | E10: =SUM(D10:D10) -> 300000
A11: 7 | B11: Alhamdu Iliya | C11: Casual-Gardner | D11: 100000 | E11: =SUM(D11:D11) -> 100000
A12: 8 | B12: Salihu Hassan | C12: Casual-Gardner | D12: 100000 | E12: =SUM(D12:D12) -> 100000
A13: 9 | B13: Ishaya Moro James | C13: Gardener | D13: 100000 | E13: =SUM(D13:D13) -> 100000
A14: 10 | B14: James G Bathna | C14: Sabbatical | D14: 0 | E14: =SUM(D14:D14) -> 0
A15: 11 | B15: John Niyi Olanrewaju | C15: Consultant | D15: 250000
A16: 12 | B16: Enobong Sambo | C16: Retainership | D16: 100000 | E16: =SUM(D16:D16) -> 100000
A17: 13 | B17: Masarr Sarr | C17: Casual | D17: 300000 | E17: =SUM(D17:D17) -> 300000
A18: 14 | B18: Aleke Friday Onyantu | C18: Casual | D18: 300000 | E18: =SUM(D18:D18) -> 300000
A19: 15 | B19: Ode Ijoko Michael | C19: Casual | D19: 300000 | E19: =SUM(D19:D19) -> 300000
A20: 16 | B20: Said Idris Abduljalil | C20: Secondment | D20: 300000 | E20: =SUM(D20:D20) -> 300000
A21: 17 | B21: Giwa Sidika Ajoke | C21: Casual(DGs GH) | D21: 300000 | E21: =SUM(D21:D21) -> 300000
A22: 20 | B22: Rasheed Mariam Folashade | C22: Casual | D22: 300000 | E22: =SUM(D22:D22) -> 300000
A23: 21 | B23: Hadiza Saidu | C23: Sabbatical | D23: 0 | E23: =SUM(D23:D23) -> 0
A24: 30 | B24: Etti Hawanat Oyenike | C24: Contract Staff | D24: 300000
A25: 31 | B25: Lawal-Gambari Bilkis Sitou | C25: Contract Staff | D25: 300000
A26: 32 | B26: Olaniyan Taiwo Abimbola | C26: Contract Staff | D26: 300000
A27: 33 | B27: Sulaimon Aminat Jumoke | C27: Contract Staff | D27: 300000 | E27: =#REF!-#REF! -> #REF!
A28: 34 | B28: Mustapha Rafiu Ayobanji | C28: Contract Staff | D28: 300000
A29: 35 | B29: Idris Ibrahim | C29: Contract Staff | D29: 400000
A30: 36 | B30: Aishatu O. Usman | C30: Sabbatical | D30: 0
A31: 37 | B31: Mariam Adepeju Abdulraheem-Mustapha | C31: Sabbatical | D31: 0
A32: 38 | B32: Siyan Peter | C32: Sabbatical | D32: 0
B33: TOTAL | D33: =SUM(D5:D32) -> 5750000 | E33: =SUM(E5:E27) -> #REF!

Sheet Sheet31

Sheet Enhanced Welfare2 8 and below
A3: CONTRACT/SABBATICAL AND CONSULTANT SALARY FOR THE MONTH OF JANUARY 2022
G5: DEDUCTIONS | K5: WELFARE
A6: S/N | B6: STAFF NAME | C6: DESIGNATION | D6: GROSS | E6: LEGISLATIVE | F6: GROSS | K6: N
A7: 1 | B7: Saratu Adamu Attajiri | C7: Office Assistant | D7: 90000 | E7: 30000 | F7: =D7+E7 -> 120000 | G7: 50000 | H7: =20000 -> 20000 | I7: 0 | J7: =G7+H7+I7 -> 70000 | K7: =300000 -> 300000
A8: 2 | B8: Aboaman Innocent | C8: Casual | D8: 45000 | E8: 15000 | F8: =D8+E8 -> 60000 | G8: =10000 -> 10000 | H8: =10000 -> 10000 | I8: 0 | J8: =G8+H8+I8 -> 20000 | K8: =100000 -> 100000
A9: 3 | B9: Kusai E. Richard | C9: Plumber | D9: 45000 | E9: 15000 | F9: =D9+E9 -> 60000 | G9: =10000 -> 10000 | H9: =20000 -> 20000 | I9: 0 | J9: =G9+H9+I9 -> 30000 | K9: =100000 -> 100000
A10: 4 | B10: Ayuba Sule | C10: Contract | D10: =96825 -> 96825 | E10: 30000 | F10: =D10+E10 -> 126825 | G10: =10000+5000 -> 15000 | H10: =32000 -> 32000 | I10: 0 | J10: =G10+H10+I10 -> 47000 | K10: =300000 -> 300000
A11: 5 | B11: Bulus Ishaya | C11: Gardener | D11: 45000 | E11: 15000 | F11: =D11+E11 -> 60000 | J11: =G11+H11+I11 -> 0 | K11: =100000 -> 100000
A12: 6 | B12: Sholagberu T Sofiat | C12: Casual | D12: =90000 -> 90000 | E12: 30000 | F12: =D12+E12 -> 120000 | G12: =30000 -> 30000 | H12: =20000 -> 20000 | J12: =G12+H12+I12 -> 50000 | K12: =300000 -> 300000
A13: 7 | B13: Jimoh Munirat Olaide | C13: Casual | D13: =90000 -> 90000 | E13: 30000 | F13: =D13+E13 -> 120000 | G13: =50000 -> 50000 | H13: =10000 -> 10000 | J13: =G13+H13+I13 -> 60000 | K13: =300000 -> 300000
A14: 8 | B14: Alhamdu Iliya | C14: Casual-Gardner | D14: =50000 -> 50000 | E14: 15000 | F14: =D14+E14 -> 65000 | G14: =5000+5000 -> 10000 | H14: =14350 -> 14350 | J14: =G14+H14+I14 -> 24350 | K14: =100000 -> 100000
A15: 9 | B15: Salihu Hassan | C15: Casual-Gardner | D15: =50000 -> 50000 | E15: 15000 | F15: =D15+E15 -> 65000 | G15: =5000 -> 5000 | J15: =G15+H15+I15 -> 5000 | K15: =100000 -> 100000
A16: 10 | B16: Ishaya Moro James | C16: Gardener | D16: =60000 -> 60000 | E16: 20000 | F16: =D16+E16 -> 80000 | G16: =10000+2000 -> 12000 | J16: =G16+H16+I16 -> 12000 | K16: =100000 -> 100000
A17: 11 | B17: Enobong Sambo | C17: Retainership | D17: =70000 -> 70000 | E17: 20000 | F17: =D17+E17 -> 90000 | G17: =10000 -> 10000 | J17: =G17+H17+I17 -> 10000 | K17: =100000 -> 100000
A18: 12 | B18: Masarr Sarr | C18: Casual | D18: =90000 -> 90000 | E18: 30000 | F18: =(D18+E18) -> 120000 | J18: =G18+H18+I18 -> 0 | K18: 300000
A19: 13 | B19: Yahaya Adamu Abdulhamid | C19: Casual | D19: =90000 -> 90000 | E19: 30000 | F19: =D19+E19 -> 120000 | J19: =G19+H19+I19 -> 0 | K19: 300000
A20: 14 | B20: Frances Edna Hananiya | C20: Casual | D20: =90000 -> 90000 | E20: 30000 | F20: =D20+E20 -> 120000 | J20: =G20+H20+I20 -> 0 | K20: 300000
A21: 15 | B21: Hazeem Hussain | C21: Casual | D21: =90000 -> 90000 | E21: =30000 -> 30000 | F21: =(D21+E21) -> 120000 | G21: =3000 -> 3000 | H21: =25000 -> 25000 | J21: =G21+H21 -> 28000 | K21: 300000
A22: 16 | B22: Aleke Friday Onyantu | C22: Casual | D22: =90000 -> 90000 | E22: =30000 -> 30000 | F22: =(D22+E22) -> 120000 | J22: =G22+H22+I22 -> 0 | K22: 300000
A23: 17 | B23: Ode Ijoko Michael | C23: Casual | D23: =90000 -> 90000 | E23: =30000 -> 30000 | F23: =(D23+E23) -> 120000 | J23: =G23+H23+I23 -> 0 | K23: 300000
A24: 18 | B24: Haruna Jibril Ameh | C24: Casual | D24: =90000 -> 90000 | E24: =30000 -> 30000 | F24: =D24+E24 -> 120000 | J24: =G24+H24+I24 -> 0 | K24: 300000
A25: 19 | B25: Giwa Sidika Ajoke | C25: Casual | D25: =90000 -> 90000 | E25: =30000 -> 30000 | F25: =D25+E25 -> 120000 | K25: 300000
A26: 20 | B26: Rasheed Mariam Folashade | C26: Casual | D26: 90000 | E26: 0 | F26: =90000*15/31 -> 43548.387 | K26: =300000 -> 300000
A27: 21 | B27: Adejoh Emmanuel | C27: Reception | K27: =300000 -> 300000
A28: 22 | B28: Godwin Etim | C28: Reception | K28: 300000
D29: =SUM(D7:D26) -> 1541825 | E29: =SUM(E7:E26) -> 475000 | F29: =SUM(F7:F26) -> 1970373.4 | G29: =SUM(G7:G26) -> 205000 | H29: =SUM(H7:H26) -> 151350 | I29: =SUM(I7:I26) -> 0 | J29: =SUM(J7:J26) -> 356350 | K29: =SUM(K7:K28) -> 5200000
C30: PREPARED BY: | D30: TONDO, IORWUESE EDWRAD | G30: =H29+G29 -> 356350
G31: =436350-G30 -> 80000

Sheet July 2021 Welfare
B3: CONTRACT/SABBATICAL AND CONSULTANT EL-KABIR WELFARE JULY 2021
G5: DEDUCTIONS | L5: Welfare
A6: S/N | B6: STAFF NAME | C6: DESIGNATION | D6: GROSS | E6: LEGISLATIVE | F6: GROSS | L6: 44378
A7: 1 | B7: Takwasa A. Galadima | C7: Nass Deployed | D7: 114649.42 | E7: =0 -> 0 | F7: =D7+E7 -> 114649.42 | G7: =30000 -> 30000 | H7: =43750 -> 43750 | J7: 0 | K7: =G7+H7+J7 -> 73750 | L7: =30000 -> 30000
A8: 2 | B8: Saratu Adamu Attajiri | C8: Office Assistant | D8: 90000 | F8: =D8+E8 -> 90000 | G8: 20000 | H8: =20000 -> 20000 | J8: 0 | K8: =G8+H8+J8 -> 40000 | L8: =30000 -> 30000
A9: 3 | B9: Aboaman Innocent | C9: Steward | D9: 45000 | F9: =D9+E9 -> 45000 | G9: =10000 -> 10000 | J9: 0 | K9: =G9+H9+J9 -> 10000 | L9: 20000
A10: 4 | B10: Kusai E. Richard | C10: Plumber | D10: 45000 | F10: =D10+E10 -> 45000 | G10: =10000 -> 10000 | H10: =20000 -> 20000 | J10: 0 | K10: =G10+H10+J10 -> 30000 | L10: 20000
A11: 5 | B11: Ayuba Sule | C11: Contract | D11: =96825 -> 96825 | E11: =0 -> 0 | F11: =D11+E11 -> 96825 | G11: =10000+3000 -> 13000 | H11: =32000 -> 32000 | J11: 0 | K11: =G11+H11+J11 -> 45000 | L11: 30000
A12: 6 | B12: Bulus Ishaya | C12: Gardener | D12: 45000 | F12: =D12+E12 -> 45000 | K12: =G12+H12+J12 -> 0 | L12: 20000
A13: 7 | B13: Sholagberu T Sofiat | C13: Casual | D13: =90000 -> 90000 | F13: =D13+E13 -> 90000 | G13: =30000 -> 30000 | H13: =20000 -> 20000 | K13: =G13+H13+J13 -> 50000 | L13: =30000 -> 30000
A14: 8 | B14: Ezenwajiobi Chidinma Charity | C14: Casual | D14: =90000 -> 90000 | F14: =D14+E14 -> 90000 | G14: =50000 -> 50000 | K14: =G14+H14+J14 -> 50000 | L14: =30000 -> 30000
A15: 9 | B15: Prof. Yusuf I Arowosaiye | C15: Sabbatical | D15: =422590.63 -> 422590.63 | F15: =(D15+E15) -> 422590.63 | J15: =(15548.33)+(13/31*15548.33) -> 22068.597 | K15: =G15+H15+J15 -> 22068.597 | L15: 70000
A16: 10 | B16: Prof. Jide Oladipo | C16: Sabbatical | D16: =407042.3 -> 407042.3 | F16: =D16+E16 -> 407042.3 | J16: =15548.33 -> 15548.33 | K16: =G16+H16+J16 -> 15548.33 | L16: 70000
A17: 11 | B17: Jimoh Munirat Olaide | C17: Casual | D17: =90000 -> 90000 | F17: =D17+E17 -> 90000 | G17: =50000 -> 50000 | K17: =G17+H17+J17 -> 50000 | L17: =30000 -> 30000
A18: 12 | B18: Alhamdu Iliya | C18: Casual-Gardner | D18: =50000 -> 50000 | F18: =D18+E18 -> 50000 | G18: =5000+3000 -> 8000 | H18: =7350+8750 -> 16100 | K18: =G18+H18+J18 -> 24100 | L18: =30000 -> 30000
A19: 13 | B19: Salihu Hassan | C19: Casual-Gardner | D19: =50000 -> 50000 | F19: =D19+E19 -> 50000 | G19: =5000 -> 5000 | K19: =G19+H19+J19 -> 5000 | L19: =30000 -> 30000
A20: 14 | B20: Ishaya Moro James | C20: Gardener | D20: =60000 -> 60000 | F20: =D20+E20 -> 60000 | K20: =G20+H20+J20 -> 0 | L20: =30000 -> 30000
A21: 15 | B21: James G Bathna | C21: Sabbatical | D21: =444720 -> 444720 | E21: =0 -> 0 | F21: =D21+E21 -> 444720 | J21: =15548.33 -> 15548.33 | K21: =G21+H21+J21 -> 15548.33 | L21: 70000
A22: 16 | B22: Jimoh Adebayo Zaka | C22: Casual | D22: =90000 -> 90000 | F22: =D22+E22 -> 90000 | G22: =0 -> 0 | H22: =0 -> 0 | K22: =G22+H22+J22 -> 0 | L22: =30000 -> 30000
A23: 17 | B23: Abbas Zainab | C23: Casual | D23: =90000 -> 90000 | F23: =D23+E23 -> 90000 | G23: =0 -> 0 | H23: =0 -> 0 | K23: =G23+H23+J23 -> 0 | L23: =30000 -> 30000
A24: 18 | B24: Enenche Jeremiah Agada | C24: Casual | D24: =90000 -> 90000 | F24: =D24+E24 -> 90000 | G24: =0 -> 0 | H24: =0 -> 0 | K24: =G24+H24+J24 -> 0 | L24: =30000 -> 30000
A25: 19 | B25: Abru Idowu Ololade | C25: Contract | D25: =123329 -> 123329 | F25: =D25+E25 -> 123329 | G25: =70000 -> 70000 | J25: =1235.19 -> 1235.19 | K25: =G25+H25+J25 -> 71235.19 | L25: =30000 -> 30000
A26: 20 | B26: Dr. Olajide O Akanji | C26: Sabbatical | D26: =153161.33+34243.25+99537.5 -> 286942.08 | E26: =100000 -> 100000 | F26: =(D26+E26) -> 386942.08 | J26: =15548.33 -> 15548.33 | K26: =G26+H26+I26+J26 -> 15548.33 | L26: 50000
A27: 21 | B27: Masarr Sarr | C27: Casual | D27: =90000 -> 90000 | F27: =(D27+E27) -> 90000 | L27: =30000 -> 30000
A28: 22 | B28: Abdullahi Adamu | C28: Casual | D28: =90000 -> 90000 | F28: =D28+E28 -> 90000 | L28: =30000 -> 30000
A29: 23 | B29: William Osamwenyobo Ugiagbe | C29: NYSC | D29: =15000 -> 15000 | E29: 0 | F29: =D29+E29 -> 15000 | L29: 10000
A30: 24 | B30: Abubakar Mohammed Saidu | C30: Sabbatical | D30: =299997.17 -> 299997.17 | E30: =100000 -> 100000 | F30: =D30+E30 -> 399997.17 | J30: =15548.33 -> 15548.33 | K30: =G30+H30+I30+J30 -> 15548.33 | L30: 50000
A31: 25 | B31: Prof. Echezona Roseline Ifeoma | C31: Sabbatical | D31: =424023 -> 424023 | E31: =100000 -> 100000 | F31: =D31+E31 -> 524023 | J31: =21618.09 -> 21618.09 | K31: =G31+H31+I31+J31 -> 21618.09 | L31: 70000
A32: 26 | B32: Frances Edna Hananiya | C32: Casual | D32: =90000 -> 90000 | F32: =D32+E32 -> 90000 | L32: =30000 -> 30000
A33: 27 | B33: Nwosu Chidinma Favour | C33: NYSC | D33: =15000 -> 15000 | F33: 15000 | L33: 10000
A34: 28 | B34: Bashir Aisha | C34: NYSC | D34: =15000 -> 15000 | F34: =D34+E34 -> 15000 | L34: 10000
A35: 29 | B35: Stephen Uzoma | C35: NYSC | D35: 15000 | E35: 0 | F35: =D35+E35 -> 15000 | L35: 10000
A36: 30 | B36: Dr. Abubakar Mohammed Bashir | C36: Secondment | D36: =226713 -> 226713 | F36: =(D36+E36) -> 226713 | J36: =7709.76 -> 7709.76 | K36: =G36+H36+I36+J36 -> 7709.76 | L36: 50000
A37: 31 | B37: Kasimu Hauwa Temitope | C37: NYSC | D37: =15000 -> 15000 | F37: =(D37+E37) -> 15000 | L37: 10000
A38: 32 | B38: Siyan- Peter Rejoice | C38: NYSC | D38: =15000 -> 15000 | F38: =(D38+E38) -> 15000 | L38: 10000
A39: 33 | B39: Umar Yahaya Halima | C39: NYSC | D39: =15000 -> 15000 | F39: =(D39+E39) -> 15000 | L39: 10000
A40: 34 | B40: Adepkun Temiloluwa | C40: NYSC | D40: =15000 -> 15000 | F40: =(D40+E40) -> 15000 | L40: 10000
A41: 35 | B41: Okolo Ujunwa Pascaline | C41: NYSC | D41: =15000 -> 15000 | F41: =(D41+E41) -> 15000 | L41: 10000
A42: 36 | B42: Suberu Rahimat Onize | C42: NYSC | D42: =15000 -> 15000 | F42: =(D42+E42) -> 15000 | L42: 10000
B43: TOTAL | D43: =SUM(D7:D42) -> 4191831.6 | E43: =SUM(E7:E42) -> 300000 | F43: =SUM(F7:F42) -> 4491831.6 | G43: =SUM(G7:G42) -> 296000 | H43: =SUM(H7:H42) -> 151850 | J43: =SUM(J7:J42) -> 114824.96 | K43: =SUM(K7:K42) -> 562674.96 | L43: =SUM(L7:L42) -> 1070000
B44: GRAND TOTAL | D44: TONDO, IORWUESE EDWRAD | H44: =H43+G43 -> 447850 | L44: ='[6]Welfare 2'!$Y$180+L43 -> 8260000

Sheet Housing 2021
B3: OVERHEAD ALLOWANCES FOR THE MONTH OF JANUARY, 2021
G5: DEDUCTIONS | L5: NET SALARY
A6: S/N | B6: STAFF NAME | C6: DESIGNATION | D6: GROSS | E6: LEGISLATIVE | F6: GROSS | L6: 44197
A7: 1 | B7: Percy Terfa Gbahabo | C7: Contract | D7: =314201.03 -> 314201.03 | E7: =50000 -> 50000 | F7: =D7+E7 -> 364201.03 | G7: =10000 -> 10000 | H7: =131666.67 -> 131666.67 | J7: =7709.76 -> 7709.76 | K7: =G7+H7+J7 -> 149376.43 | L7: =500000 -> 500000
A8: 2 | B8: Rifkatu Nghargbu | C8: Contract | D8: =349153.06 -> 349153.06 | E8: =50000 -> 50000 | F8: =D8+E8 -> 399153.06 | G8: =50000 -> 50000 | J8: =7709.76 -> 7709.76 | K8: =G8+H8+J8 -> 57709.76 | L8: =500000 -> 500000
A9: 3 | B9: Osikhen Leo Igbanoi | C9: Contract | D9: =314201.03 -> 314201.03 | E9: =50000 -> 50000 | F9: =D9+E9 -> 364201.03 | G9: =25000 -> 25000 | H9: =94262.15 -> 94262.15 | J9: =7709.76 -> 7709.76 | K9: =G9+H9+J9 -> 126971.91 | L9: =500000 -> 500000
A10: 4 | B10: Bashar Aminu | C10: Foreign Affairs Deployed | D10: 101161.25 | E10: =50000 -> 50000 | F10: =D10+E10 -> 151161.25 | K10: =G10+H10+J10 -> 0 | L10: =500000 -> 500000
A11: 5 | B11: Okungbowa Osaretin Godspower | C11: Contract | D11: =326713 -> 326713 | E11: =50000 -> 50000 | F11: =D11+E11 -> 376713 | G11: =70000 -> 70000 | H11: =0 -> 0 | J11: =7709.76 -> 7709.76 | K11: =G11+H11+J11 -> 77709.76 | L11: =250000 -> 250000
A12: 6 | B12: Dr. Lona Polit Bonkat | C12: Contract | D12: =326713 -> 326713 | E12: =50000 -> 50000 | F12: =D12+E12 -> 376713 | G12: =110000 -> 110000 | J12: =7709.76 -> 7709.76 | K12: =G12+H12+J12 -> 117709.76 | L12: =500000 -> 500000
A13: 7 | B13: Igwe Stacy | C13: Contract | D13: =168602.08 -> 168602.08 | E13: =150000 -> 150000 | F13: =D13+E13 -> 318602.08 | G13: =50000 -> 50000 | J13: 3369.51 | K13: =G13+H13+J13 -> 53369.51 | L13: =300000 -> 300000
A14: 8 | B14: Abayomi Kayode Quadri | C14: Contract | D14: =168602.08 -> 168602.08 | E14: =150000 -> 150000 | F14: =D14+E14 -> 318602.08 | J14: 3369.51 | K14: =G14+H14+J14 -> 3369.51 | L14: =300000 -> 300000
A15: 9 | B15: Chioma Uwazurike | C15: Contract Manager PG | D15: 329171.72 | E15: =150000 -> 150000 | F15: =D15+E15 -> 479171.72 | J15: =15548.33 -> 15548.33 | K15: =G15+H15+J15 -> 15548.33 | L15: =700000 -> 700000
A16: 10 | B16: Takwasa A. Galadima | C16: Nass Deployed | D16: 114649.42 | E16: =0 -> 0 | F16: =D16+E16 -> 114649.42 | G16: =30000 -> 30000 | H16: =43750 -> 43750 | J16: 0 | K16: =G16+H16+J16 -> 73750 | L16: 300000
A17: 11 | B17: Daniel Titilayo Mervellous | C17: Library Assistant | D17: =123329 -> 123329 | E17: =150000 -> 150000 | F17: =D17+E17 -> 273329 | J17: =1235.19 -> 1235.19 | K17: =G17+H17+J17 -> 1235.19 | L17: 300000
A18: 12 | B18: Saratu Adamu Attajiri | C18: Office Assistant | D18: 90000 | E18: =25000 -> 25000 | F18: =D18+E18 -> 115000 | G18: 20000 | H18: =20000+50000 -> 70000 | J18: 0 | K18: =G18+H18+J18 -> 90000 | L18: =300000 -> 300000
A19: 13 | B19: Moshood Tosho Amuda | C19: Manager, Exams & Records | D19: =344720 -> 344720 | E19: =150000 -> 150000 | F19: =D19+E19 -> 494720 | J19: =15548.33 -> 15548.33 | K19: =G19+H19+J19 -> 15548.33 | L19: =700000 -> 700000
A20: 14 | B20: Maryam Mohammed Bello | C20: PA Special Duties | D20: =226713.03 -> 226713.03 | E20: =100000+100000 -> 200000 | F20: =D20+E20 -> 426713.03 | J20: =7709.76 -> 7709.76 | K20: =G20+H20+J20 -> 7709.76 | L20: 500000
A21: 15 | B21: Dare Sheu Magbon | C21: Administrative Assistant | D21: =123329 -> 123329 | E21: =100000 -> 100000 | F21: =D21+E21 -> 223329 | G21: =23000 -> 23000 | J21: =1235.19 -> 1235.19 | K21: =G21+H21+J21 -> 24235.19 | L21: 300000
A22: 16 | B22: Mr. Nandi Livinus Ature | C22: Research Assistant | D22: =123329 -> 123329 | E22: =150000 -> 150000 | F22: =D22+E22 -> 273329 | J22: =1235.19 -> 1235.19 | K22: =G22+H22+J22 -> 1235.19 | L22: 300000
A23: 17 | B23: Lucky Agwom | C23: Research Assistant | D23: =123329 -> 123329 | E23: =150000 -> 150000 | F23: =D23+E23 -> 273329 | J23: =1235.19 -> 1235.19 | K23: =G23+H23+J23 -> 1235.19 | L23: 300000
A24: 18 | B24: Mohammed Bello | C24: Research Assistant | D24: =123329 -> 123329 | E24: =150000 -> 150000 | F24: =D24+E24 -> 273329 | J24: =1235.19 -> 1235.19 | K24: =G24+H24+J24 -> 1235.19 | L24: 300000
A25: 19 | B25: Aboaman Innocent | C25: Steward | D25: 45000 | E25: =25000 -> 25000 | F25: =D25+E25 -> 70000 | J25: 0 | K25: =G25+H25+J25 -> 0 | L25: 100000
A26: 20 | B26: Kusai E. Richard | C26: Plumber | D26: 45000 | E26: =25000 -> 25000 | F26: =D26+E26 -> 70000 | G26: =10000 -> 10000 | H26: =13750 -> 13750 | J26: 0 | K26: =G26+H26+J26 -> 23750 | L26: 100000
A27: 21 | B27: Ayuba Sule | C27: Contract | D27: =96825 -> 96825 | E27: =25000 -> 25000 | F27: =D27+E27 -> 121825 | G27: =10000+2000 -> 12000 | H27: =18155.56+50000 -> 68155.56 | J27: 0 | K27: =G27+H27+J27 -> 80155.56 | L27: 300000
A28: 22 | B28: Bulus Ishaya | C28: Gardener | D28: 45000 | E28: =25000 -> 25000 | F28: =D28+E28 -> 70000 | K28: =G28+H28+J28 -> 0 | L28: 100000
A29: 23 | B29: Sholagberu T Sofiat | C29: Casual | D29: =90000 -> 90000 | E29: =25000 -> 25000 | F29: =D29+E29 -> 115000 | G29: =30000 -> 30000 | H29: =20000 -> 20000 | K29: =G29+H29+J29 -> 50000 | L29: 300000
A30: 24 | B30: Ezenwajiobi Chidinma Charity | C30: Casual | D30: =90000 -> 90000 | E30: =25000 -> 25000 | F30: =D30+E30 -> 115000 | G30: =35000 -> 35000 | K30: =G30+H30+J30 -> 35000 | L30: 300000
A31: 25 | B31: Prof. Yusuf I Arowosaiye | C31: Sabbatical | D31: =422590.63 -> 422590.63 | F31: =(D31+E31) -> 422590.63 | J31: =(15548.33)+(13/31*15548.33) -> 22068.597 | K31: =G31+H31+J31 -> 22068.597 | L31: =350000 -> 350000
A32: 26 | B32: Prof. Jide Oladipo | C32: Sabbatical | D32: =407042.3 -> 407042.3 | F32: =D32+E32 -> 407042.3 | J32: =15548.33 -> 15548.33 | K32: =G32+H32+J32 -> 15548.33 | L32: =350000 -> 350000
A33: 27 | B33: Ndanusa Mohammed Manzuma -Ndaaba | C33: Contract | D33: =344720 -> 344720 | E33: =100000+100000 -> 200000 | F33: =D33+E33 -> 544720 | G33: =100000 -> 100000 | H33: =0 -> 0 | J33: =15548.33 -> 15548.33 | K33: =G33+H33+J33 -> 115548.33 | L33: 700000
A34: 28 | B34: Dr. Usman Wali | C34: Contract | D34: =344720 -> 344720 | E34: =150000 -> 150000 | F34: =D34+E34 -> 494720 | J34: =15548.33 -> 15548.33 | K34: =G34+H34+J34 -> 15548.33 | L34: 700000
A35: 29 | B35: Ayobolu Olajide Olufunsho | C35: Contract | D35: =344720 -> 344720 | E35: =100000 -> 100000 | F35: =D35+E35 -> 444720 | G35: =25000 -> 25000 | J35: =15548.33 -> 15548.33 | K35: =G35+H35+J35 -> 40548.33 | L35: 700000
A36: 30 | B36: Jimoh Munirat Olaide | C36: Casual | D36: =90000 -> 90000 | E36: =25000 -> 25000 | F36: =D36+E36 -> 115000 | G36: =50000 -> 50000 | K36: =G36+H36+J36 -> 50000 | L36: 300000
A37: 31 | B37: Alhamdu Iliya | C37: Casual-Gardner | D37: =50000 -> 50000 | E37: =25000 -> 25000 | F37: =D37+E37 -> 75000 | G37: =5000+2000 -> 7000 | H37: =7350 -> 7350 | K37: =G37+H37+J37 -> 14350 | L37: 100000
A38: 32 | B38: Salihu Hassan | C38: Casual-Gardner | D38: =50000 -> 50000 | E38: =25000 -> 25000 | F38: =D38+E38 -> 75000 | K38: =G38+H38+J38 -> 0 | L38: 100000
A39: 33 | B39: Ishaya Moro James | C39: Gardener | D39: =60000 -> 60000 | E39: =25000 -> 25000 | F39: =D39+E39 -> 85000 | K39: =G39+H39+J39 -> 0 | L39: 100000
A40: 34 | B40: Olima James Enyi | C40: Steward | D40: =60000 -> 60000 | E40: =25000 -> 25000 | F40: =(D40+E40) -> 85000 | K40: =G40+H40+J40 -> 0 | L40: 100000
A41: 35 | B41: James G Bathna | C41: Sabbatical | D41: =444720 -> 444720 | E41: =0 -> 0 | F41: =D41+E41 -> 444720 | J41: =15548.33 -> 15548.33 | K41: =G41+H41+J41 -> 15548.33 | L41: =700000 -> 700000
A42: 36 | B42: Dr. John Niyi Olanrewaju | C42: Consultancy | D42: =500000 -> 500000 | E42: =0 -> 0 | F42: =D42+E42 -> 500000 | J42: =0.05*D42 -> 25000 | K42: =G42+H42+J42 -> 25000 | L42: =700000 -> 700000
A43: 37 | B43: Mrs Amina Ibrahim | C43: Contract | D43: =524023.33 -> 524023.33 | F43: =D43+E43 -> 524023.33 | J43: =21618.09 -> 21618.09 | K43: =G43+H43+J43 -> 21618.09 | L43: =700000 -> 700000
A44: 38 | B44: Jimoh Adebayo Zaka | C44: Casual | D44: =90000 -> 90000 | E44: =25000 -> 25000 | F44: =D44+E44 -> 115000 | G44: =0 -> 0 | H44: =0 -> 0 | K44: =G44+H44+J44 -> 0 | L44: 300000
A45: 39 | B45: Abbas Zainab | C45: Casual | D45: =90000 -> 90000 | E45: =25000 -> 25000 | F45: =D45+E45 -> 115000 | G45: =0 -> 0 | H45: =0 -> 0 | K45: =G45+H45+J45 -> 0 | L45: 300000
A46: 40 | B46: Enenche Jeremiah Agada | C46: Casual | D46: =90000 -> 90000 | E46: =25000 -> 25000 | F46: =D46+E46 -> 115000 | G46: =0 -> 0 | H46: =0 -> 0 | K46: =G46+H46+J46 -> 0 | L46: 300000
A47: 41 | B47: Abru Idowu Ololade | C47: Contract | D47: =123329 -> 123329 | E47: =100000 -> 100000 | F47: =D47+E47 -> 223329 | G47: =70000 -> 70000 | J47: =1235.19 -> 1235.19 | K47: =G47+H47+J47 -> 71235.19 | L47: 300000
A48: 42 | B48: Tessneem Ibrahim | C48: Assistant Information | D48: =123329 -> 123329 | E48: =100000 -> 100000 | F48: =(D48+E48) -> 223329 | J48: =1235.19 -> 1235.19 | K48: =G48+H48+I48+J48 -> 1235.19 | L48: 300000
A49: 43 | B49: Dr. Olajide O Akanji | C49: Sabbatical | D49: =153161.33+34243.25+99537.5 -> 286942.08 | E49: =150000 -> 150000 | F49: =(D49+E49) -> 436942.08 | J49: =15548.33 -> 15548.33 | K49: =G49+H49+I49+J49 -> 15548.33 | L49: =350000 -> 350000
A50: 44 | B50: Masarr Sarr | C50: Casual | D50: =90000 -> 90000 | E50: =25000 -> 25000 | F50: =(D50+E50) -> 115000 | L50: 300000
A51: 45 | B51: Abdulsalam Bako | C51: Contract | D51: =344720 -> 344720 | E51: 100000 | F51: =(D51+E51) -> 444720 | J51: =15548.33 -> 15548.33 | K51: =G51+H51+J51 -> 15548.33 | L51: 700000
A52: 46 | B52: Yusuf Abdullahi | C52: Driver | D52: =44538 -> 44538 | E52: =25000 -> 25000 | F52: =D52+E52 -> 69538 | J52: =236.04 -> 236.04 | K52: =G52+H52+I52+J52 -> 236.04 | L52: 100000
A53: 47 | B53: Abdullahi Adamu | C53: Casual | D53: =90000 -> 90000 | E53: =25000+25000 -> 50000 | F53: =D53+E53 -> 140000 | L53: 300000
A54: 48 | B54: Raheem Usman Ayigoro | C54: SA (Insfrastructure) | D54: =424023 -> 424023 | E54: =100000 -> 100000 | F54: =D54+E54 -> 524023 | J54: =15548.33 -> 15548.33 | K54: =G54+H54+I54+J54 -> 15548.33 | L54: =350000 -> 350000
A55: 49 | B55: Sunday Adejoh | C55: Sergeant at arms | L55: =300000 -> 300000
A56: 50 | B56: Godwin Etim | C56: Sergeant at arms | L56: =300000 -> 300000
A57: 51 | B57: Abubakar Mohammed Saidu | C57: Sabbatical | L57: =350000 -> 350000
D58: =SUM(D7:D52) -> 9128465 | E58: =SUM(E7:E52) -> 3125000 | F58: =SUM(F7:F52) -> 12253465 | G58: =SUM(G7:G52) -> 727000 | H58: =SUM(H7:H52) -> 448934.38 | J58: =SUM(J7:J52) -> 270501.61 | K58: =SUM(K7:K52) -> 1446436 | L58: =SUM(L7:L57) -> 18700000
C59: PREPARED BY: | H59: =H58+G58 -> 1175934.4
L60: =L58-L59 -> 18700000

Sheet Welfare 2020 
B3: OVERHEAD ALLOWANCES FOR THE MONTH OF JULY, 2020
A6: S/N | B6: STAFF NAME | C6: DESIGNATION | D6: AMOUNT
D7: N
A8: 1 | B8: Valentina Tetteh Ayongo | C8: Programme Manager | D8: =70000 -> 70000
A9: 2 | B9: Percy Terfa Gbahabo | C9: Contract | D9: =50000 -> 50000
A10: 3 | B10: Rifkatu Nghargbu | C10: Contract | D10: =50000 -> 50000
A11: 4 | B11: Osikhen Leo Igbanoi | C11: Contract | D11: =50000 -> 50000
A12: 5 | B12: Suzie Orefi Odeh | C12: Admin Officer | D12: =30000 -> 30000
A13: 6 | B13: Dahiru Abdullahi | C13: Nass Deployed | D13: =30000 -> 30000
A14: 7 | B14: Bashar Aminu | C14: Foreign Affairs Deployed | D14: =30000 -> 30000
A15: 8 | B15: Ibrahim Babangishiri | C15: Nass Deployed | D15: =0 -> 0
A16: 9 | B16: Abdulmalik Dahiru | C16: Nass Deployed | D16: =0 -> 0
A17: 10 | B17: Okungbowa Osaretin Godspower | C17: Contract | D17: =50000 -> 50000
A18: 12 | B18: Dr. Lona Polit Bonkat | C18: Contract | D18: =50000 -> 50000
A19: 13 | B19: Igwe Stacy | C19: Contract | D19: =30000 -> 30000
A20: 14 | B20: Abayomi Kayode Quadri | C20: Contract | D20: =30000 -> 30000
A21: 15 | B21: Dr. Ngozi Nwogwugwu | C21: Contract | D21: =70000 -> 70000
A22: 16 | B22: Chioma Uwazurike | C22: Contract Manager PG | D22: =70000 -> 70000
A23: 17 | B23: Takwasa A. Galadima | C23: Nass Deployed | D23: =30000 -> 30000
A24: 18 | B24: Daniel Titilayo Mervellous | C24: Library Assistant | D24: =30000 -> 30000
A25: 22 | B25: Saratu Adamu Attajiri | C25: Office Assistant | D25: =30000 -> 30000
A26: 23 | B26: Moshood Tosho Amuda | C26: Manager, Exams & Records | D26: =70000 -> 70000
A27: 24 | B27: Shiru Bukola Hauwa | C27: Admin. Assistant | D27: =30000 -> 30000
A28: 25 | B28: Dare Sheu Magbon | C28: Administrative Assistant | D28: =30000 -> 30000
A29: 26 | B29: Sulaiman Ayoola Abdulrahman | C29: Administrative Assistant | D29: =30000 -> 30000
A30: 27 | B30: Mr. Nandi Livinus Ature | C30: Research Assistant | D30: =30000 -> 30000
A31: 28 | B31: Lucky Agwom | C31: Research Assistant | D31: =30000 -> 30000
A32: 29 | B32: Mohammed Bello | C32: Research Assistant | D32: =30000 -> 30000
A33: 30 | B33: Aboaman Innocent | C33: Steward | D33: =20000 -> 20000
A34: 32 | B34: Kusai E. Richard | C34: Plumber | D34: =20000 -> 20000
A35: 33 | B35: Ayuba Sule | C35: Gardener | D35: =30000 -> 30000
A36: 34 | B36: Bulus Ishaya | C36: Gardener | D36: =20000 -> 20000
A37: 35 | B37: Sholagberu T Sofiat | C37: Casual | D37: =30000 -> 30000
A38: 36 | B38: Ezenwajiobi Chidinma Charity | C38: Casual | D38: =30000 -> 30000
A39: 37 | B39: Okoli Winnie Ijeoma | C39: NYSC | D39: =10000 -> 10000
A40: 38 | B40: Prof. Yusuf I Arowosaiye | C40: Sabbatical | D40: =70000 -> 70000
A41: 39 | B41: Prof. Jide Oladipo | C41: Sabbatical | D41: =70000 -> 70000
A42: 40 | B42: Ndanusa Mohammed Manzuma -Ndaaba | C42: Contract | D42: =70000 -> 70000
A43: 41 | B43: Zainab Abbas | C43: NYSC | D43: =10000 -> 10000
A44: 42 | B44: Dr. Usman Wali | C44: Contract | D44: =70000 -> 70000
A45: 43 | B45: Ayobolu Olajide Olufunsho | C45: Contract | D45: =70000 -> 70000
A46: 44 | B46: Dr. Abdullahi Yahuza Zainawa | C46: Sabbatical | D46: =70000 -> 70000
A47: 45 | B47: Dr. Usman Ahmad Karofi | C47: Sabbatical | D47: =70000 -> 70000
A48: 46 | B48: Jimoh Munirat Olaide | C48: NYSC | D48: =10000 -> 10000
A49: 47 | B49: Jimoh Olayinka Bashir | C49: NYSC | D49: =10000 -> 10000
A50: 48 | B50: Bott Whitney Zere | C50: NYSC | D50: =10000 -> 10000
A51: 49 | B51: Alhamdu Iliya | C51: Casual-Gardner | D51: =20000 -> 20000
A52: 50 | B52: Salihu Hassan | C52: Casual-Gardner | D52: =20000 -> 20000
A53: 51 | B53: Hananiya, Frances Edna | C53: NYSC | D53: =10000 -> 10000
A54: 52 | B54: Adamu Zainab Sani | C54: NYSC | D54: =10000 -> 10000
A55: 53 | B55: Shehu Suleiman Ibrahim | C55: NYSC | D55: =10000 -> 10000
A56: 54 | B56: Ishaya Moro James | C56: Gardener | D56: =20000 -> 20000
A57: 55 | B57: Olima James Enyi | C57: Steward | D57: =20000 -> 20000
A58: 56 | B58: Okeke Chinemerem | C58: NYSC | D58: =10000 -> 10000
A59: 57 | B59: Odudu Dearest Osadebamwen | C59: NYSC | D59: =10000 -> 10000
D60: =SUM(D8:D59) -> 1770000
C61: GRAND TOTAL | D61: =#REF!+D60 -> #REF!

Sheet Hardship
A3: S/N | B3: STAFF NAME | C3: DESIGNATION | D3: RESEARCH /HARDSHIP ALLOWANCES | E3: EFFECT OF INCREASE OF RESEARCH | F3: EFFECT OF INTRODUCTION OF HARDSHIP | G3: TOTAL EFFECT
A4: 2 | B4: Valentina Tetteh Ayongo | C4: Programme Manager | D4: 100000 | E4: =0 -> 0 | F4: =0 -> 0 | G4: =E4+F4 -> 0
A5: 3 | B5: Percy Terfa Gbahabo | C5: Contract | D5: =50000 -> 50000 | E5: =50000 -> 50000 | F5: =0 -> 0 | G5: =E5+F5 -> 50000
A6: 4 | B6: Rifkatu Nghargbu | C6: Contract | D6: =50000 -> 50000 | E6: =50000 -> 50000 | F6: =0 -> 0 | G6: =E6+F6 -> 50000
A7: 5 | B7: Osikhen Leo Igbanoi | C7: Contract | D7: =50000 -> 50000 | E7: =50000 -> 50000 | F7: =0 -> 0 | G7: =E7+F7 -> 50000
A8: 6 | B8: Suzie Orefi Odeh | C8: Admin Officer | D8: =100000 -> 100000 | E8: =0 -> 0 | F8: =D8 -> 100000 | G8: =E8+F8 -> 100000
A9: 7 | B9: Dahiru Abdullahi | C9: Nass Deployed | D9: 100000 | E9: =0 -> 0 | F9: =D9 -> 100000 | G9: =E9+F9 -> 100000
A10: 8 | B10: Bashar Aminu | C10: Foreign Affairs Deployed | D10: 100000 | E10: =0 -> 0 | F10: =D10 -> 100000 | G10: =E10+F10 -> 100000
A11: 9 | B11: Ibrahim Babangishiri | C11: Nass Deployed | D11: =100000 -> 100000 | F11: =100000 -> 100000 | G11: =E11+F11 -> 100000
A12: 10 | B12: Abdulmalik Dahiru | C12: Nass Deployed | D12: =100000 -> 100000 | F12: =100000 -> 100000 | G12: =E12+F12 -> 100000
A13: 11 | B13: Okungbowa Osaretin Godspower | C13: Contract | D13: =50000 -> 50000 | E13: =50000 -> 50000 | G13: =E13+F13 -> 50000
A14: 14 | B14: Dr. Lona Polit Bonkat | C14: Contract | D14: =50000 -> 50000 | E14: =50000 -> 50000 | G14: =E14+F14 -> 50000
A15: 15 | B15: Igwe Stacy | C15: Contract | D15: =150000 -> 150000 | E15: =50000 -> 50000 | G15: =E15+F15 -> 50000
A16: 16 | B16: Abayomi Kayode Quadri | C16: Contract | D16: =150000 -> 150000 | E16: =50000 -> 50000 | G16: =E16+F16 -> 50000
A17: 17 | B17: Dr. Ngozi Nwogwugwu | C17: Contract | D17: =150000 -> 150000 | E17: =50000 -> 50000 | G17: =E17+F17 -> 50000
A18: 18 | B18: Chioma Uwazurike | C18: Contract Manager PG | D18: =150000 -> 150000 | E18: =50000 -> 50000 | G18: =E18+F18 -> 50000
A19: 19 | B19: Takwasa A. Galadima | C19: Nass Deployed | D19: =100000 -> 100000 | E19: =0 -> 0 | F19: =D19 -> 100000 | G19: =E19+F19 -> 100000
A20: 20 | B20: Daniel Titilayo Mervellous | C20: Library Assistant | D20: =150000 -> 150000 | E20: =50000 -> 50000 | F20: =0 -> 0 | G20: =E20+F20 -> 50000
A21: 24 | B21: Nuradeen Santuraki | C21: ICT Assistant | D21: =100000 -> 100000 | F21: =0 -> 0 | G21: =E21+F21 -> 0
A22: 25 | B22: Saratu Adamu Attajiri | C22: Office Assistant | D22: =25000 -> 25000 | F22: =D22 -> 25000 | G22: =E22+F22 -> 25000
A23: 26 | B23: Moshood Tosho Amuda | C23: Manager, Exams & Records | D23: =100000 -> 100000 | F23: =0 -> 0 | G23: =E23+F23 -> 0
A24: 27 | B24: Shiru Bukola Hauwa | C24: Admin. Assistant | D24: =25000 -> 25000 | F24: =D24 -> 25000 | G24: =E24+F24 -> 25000
A25: 28 | B25: Maryam Mohammed Bello | C25: PA Special Duties | D25: =100000 -> 100000 | F25: =D25 -> 100000 | G25: =E25+F25 -> 100000
A26: 29 | B26: Dare Sheu Magbon | C26: Administrative Assistant | D26: =25000 -> 25000 | F26: =D26 -> 25000 | G26: =E26+F26 -> 25000
A27: 30 | B27: Sulaiman Ayoola Abdulrahman | C27: Administrative Assistant | D27: =25000 -> 25000 | F27: =D27 -> 25000 | G27: =E27+F27 -> 25000
A28: 31 | B28: Mr. Nandi Livinus Ature | C28: Research Assistant | D28: =150000 -> 150000 | E28: =50000 -> 50000 | G28: =E28+F28 -> 50000
A29: 32 | B29: Lucky Agwom | C29: Research Assistant | D29: =150000 -> 150000 | E29: =50000 -> 50000 | G29: =E29+F29 -> 50000
A30: 33 | B30: Mohammed Bello | C30: Research Assistant | D30: =150000 -> 150000 | E30: =50000 -> 50000 | G30: =E30+F30 -> 50000
A31: 34 | B31: Aboaman Innocent | C31: Steward | D31: =25000 -> 25000 | F31: =25000 -> 25000 | G31: =E31+F31 -> 25000
A32: 35 | B32: Yarima Tongriang Dagwa | C32: Steward | D32: =25000 -> 25000 | F32: =25000 -> 25000 | G32: =E32+F32 -> 25000
A33: 36 | B33: Kusai E. Richard | C33: Plumber | D33: =25000 -> 25000 | F33: =25000 -> 25000 | G33: =E33+F33 -> 25000
A34: 37 | B34: Ayuba Sule | C34: Gardener | D34: =25000 -> 25000 | F34: =25000 -> 25000 | G34: =E34+F34 -> 25000
A35: 38 | B35: Bulus Ishaya | C35: Gardener | D35: =25000 -> 25000 | F35: =25000 -> 25000 | G35: =E35+F35 -> 25000
A36: 39 | B36: Sholagberu T Sofiat | C36: Casual | D36: =25000 -> 25000 | F36: =25000 -> 25000 | G36: =E36+F36 -> 25000
A37: 50 | B37: Ndanusa Mohammed Manzuma -Ndaaba | C37: Contract | D37: =100000 -> 100000 | E37: =0 -> 0 | F37: =100000 -> 100000 | G37: =E37+F37 -> 100000
A38: 52 | B38: Dr. Usman Wali | C38: Contract | D38: =150000 -> 150000 | E38: =50000 -> 50000 | G38: =E38+F38 -> 50000
A39: 53 | B39: Ayobolu Olajide Olufunsho | C39: Contract | D39: =100000 -> 100000 | E39: 0 | F39: =0 -> 0 | G39: =E39+F39 -> 0
A40: 60 | B40: Alhamdu Iliya | C40: Casual-Gardner | D40: =25000 -> 25000 | F40: =25000 -> 25000 | G40: =E40+F40 -> 25000
A41: 61 | B41: Salihu Hassan | C41: Casual-Gardner | D41: =25000 -> 25000 | F41: =25000 -> 25000 | G41: =E41+F41 -> 25000
A42: 65 | B42: Ishaya Moro James | C42: Gardener | D42: =25000 -> 25000 | F42: =25000 -> 25000 | G42: =E42+F42 -> 25000
A43: 66 | B43: Olima James Enyi | C43: Steward | D43: =25000 -> 25000 | F43: =25000 -> 25000 | G43: =E43+F43 -> 25000
D44: =SUM(D4:D43) -> 3150000 | E44: =SUM(E4:E43) -> 700000 | F44: =SUM(F4:F43) -> 1150000 | G44: =E44+F44 -> 1850000
C45: PREPARED BY:

Sheet Sheet19

Sheet NYSC
B3: END OF YEAR WELFARE FOR NYSC AND SERGEANT AT ARMS
A6: S/N | B6: STAFF NAME | C6: DESIGNATION | D6: TOTAL
A7: 1 | B7: Enenche Jeremiah Agada | C7: NYSC | D7: =5000 -> 5000
A8: 2 | B8: Omohieme Osedebamhen | C8: NYSC | D8: =5000 -> 5000
A9: 3 | B9: Wampana Hosea | C9: NYSC | D9: =5000 -> 5000
A10: 4 | B10: Idoko Somadina Benedict | C10: NYSC | D10: =5000 -> 5000
A11: 5 | B11: Yahaya Adamu Abdulhamid | C11: NYSC | D11: =5000 -> 5000
A12: 6 | B12: Adakuyi Ede Samson | C12: NYSC | D12: =5000 -> 5000
A13: 7 | B13: Bakari Zainab | C13: NYSC | D13: =5000 -> 5000
A14: 8 | B14: Ezenwajiobi Chidinma Charity | C14: NYSC | D14: =5000 -> 5000
A15: 9 | B15: Stephen Samuel | C15: NYSC | D15: =5000 -> 5000
A16: 10 | B16: Oke Eniola Oluwabukunmi | C16: NYSC | D16: =5000 -> 5000
A17: 11 | B17: Oban Obianuju Sandra | C17: NYSC | D17: =5000 -> 5000
A18: 12 | B18: Okoli Winnie Ijeoma | C18: NYSC | D18: =5000 -> 5000
... A22: 16 | B22: Jimoh Olayinka Bashir | C22: NYSC | D22: =5000 -> 5000
A23: 17 | B23: Emmanuel Adejoh | C23: Sergeant at arms | D23: =20000 -> 20000
A24: 18 | B24: Godwin Etim Nkang | C24: Sergeant at arms | D24: =20000 -> 20000
A25: 19 | B25: Olajide Ayobolu | C25: Internal Editor | D25: =30000 -> 30000
D26: =SUM(D7:D25) -> 150000

Sheet Staff List
A1: S/N | B1: NAMES | D1: DESIGNATION | E1: SCALE
B2: DG OFFICE
A3: 1 | B3: DR LADI HAMALAI | D3: DIRECTOR GENERAL | E3: CONSOL
A4: 2 | B4: NWAJEI KANAYO | D4: COMMUNICATION ADVISER | E4: 16(7)
A5: 3 | B5: DR ABDULHAMID OBA YUSUF | D5: LEGAL ADVISER
A6: 4 | B6: NWOSU MATHEW EZE | D6: MANAGER INT. AUDIT | E6: 15(9)
A7: 5 | B7: DR IKEME ARTHUR J. O | D7: MANAGER M&E | E7: 15(8)
A8: 6 | B8: AKINSANMI ADEJOKE OLUKEMI | D8: AM INFORMATION | E8: 15(7)
A9: 7 | B9: ARCH. TIJO ZARA BORYO | D9: MANAGER, ASSETS/MAINT. | E9: 15(7)
A10: 8 | B10: YAHAYA SHAMSU | D10: AM LEGAL | E10: 13(8)
A11: 9 | B11: TOKUNBO ALFRED ADULOJU | D11: AM LIAISON OFFICE | E11: 13(7)
A12: 10 | B12: NGARA CHRISTOPHER OCHANJA | D12: OFFICER, SPECIAL DUTIES | E12: 13(7)
A13: 11 | B13: JOY HARUNA MAKERI | D13: PA DG | E13: 10(11)
A14: 12 | B14: DONALD E. MKPANAM | D14: AM ICT | E14: 13(10)
A15: 13 | B15: ABUBAKAR LAMIDO TANKO | D15: ICT OFFICER | E15: 10(9)
A16: 14 | B16: HUSSEIN MUSA AGYE | D16: PROTOCOL OFFICER | E16: 13(7)
A17: 15 | B17: BASHIRU ABBA WALI | D17: ASSIT. INT. AUDIT | E17: 10(7)
... A20: 18 | B20: CHRISTIAN MADUABUCHI ODO | D20: ICT ASSISTANT | E20: 10(7)
A21: 19 | B21: Dahiru Abdullahi | D21: Nass Deployed
A22: 20 | B22: Moshood M. Olarele | D22: Nass Deployed
A23: 21 | B23: Ibrahim Babangishiri | D23: Nass Deployed
A24: 22 | B24: Abdulmalik Dahiru | D24: Nass Deployed
A25: 23 | B25: Takwasa A. Galadima | D25: Nass Deployed
C26: TOTAL | D26: 23
B28: LEG. SUPPORT SEVICES
A29: 1 | B29: DR SHUIBU DANWANKA | D29: DD LEG. SP SERVICES | E29: 16(9)
A30: 2 | B30: IBRAHIM USMAN | D30: RESEARCH FELLOW II | E30: 13(11)
A31: 3 | B31: OFORDEME ADAOBI JULIA | D31: RESEARCH OFFICER | E31: 10(11)
A32: 4 | B32: IKPEAZU CHINEDU ANITA | D32: RESEARCH OFFICER | E32: 10(11)
A33: 5 | B33: ONYEAKU CHUKWUKA EDMOND | D33: RESEARCH OFFICER | E33: 10(9)
A34: 6 | B34: Jibirin Ushama Ahmed | D34: Nass Deployed
B35: TOTAL | D35: 6
B37: RESEARCH & TRAINING
A38: 1 | B38: DR ADEYEMI AKEEB FAJINGBESI | D38: DIR. RES. & TRAINING | E38: 17(7)
A39: 2 | B39: DR ASIMIYU G. ABIOLA | D39: DD RESEARCH | E39: 16(9)
A40: 3 | B40: DR KANAYO OGUJIUBA | D40: SRF SOCIAL SECTOR | E40: 15(9)
A41: 4 | B41: DR OLARENWAJU NIYI JOHN | D41: SABATICAL
A42: 5 | B42: JAMES B. BATHNA | D42: SABATICAL
A43: 6 | B43: AMINCI THOMAS | D43: Nass Deployed | E43: 0
A44: 7 | B44: CATHERINE E. IKOKOH | D44: RESEARCH FELLOW1 DOCU | E44: 14(11)
A45: 8 | B45: DR CLINTON JAJA | D45: RESEARCH FELLOW I | E45: 14(9)
A46: 9 | B46: ABDULKADIR I. AHMED | D46: CHIEF LIBRARIAN | E46: 14(9)
A47: 10 | B47: DR ASEMOTA O. JOSEPH | D47: RESEARCH FELLOW I | E47: 14(9)
A48: 11 | B48: DR UMAR AMINU | D48: RESEARCH FELLOW II | E48: 14(10)
A49: 12 | B49: OGUCHE SAMUEL | D49: RESEARCH FELLOW II | E49: 13(10)
A50: 13 | B50: DR JAKE DABANG DAN AZUMI | D50: RESEARCH FELLOW I TRAINING | E50: 14(9)
A51: 14 | B51: TAIWO A. ADEREMI | D51: RESEARCH FELLOW II | E51: 13(10)
A52: 15 | B52: BETHEL UZOMA IHUGBA | D52: RESEARCH FELLOW I | E52: 14(9)
A53: 16 | B53: TERFA WILLIAMS ABRAHAM | D53: RESEARCH FELLOW II | E53: 13(10)
A54: 17 | B54: ABDULSALAM MUSTAFA | D54: ASST. MANAGER, TRAINING | E54: 13(11)
A55: 18 | B55: ALIYU SANNI ABUBAKAR | D55: DATA & DOCU. OFFICER | E55: 13(7)
... A61: 24 | B61: ANTHONY EDET | D61: OFFICER M&E | E61: 10(9)
B62: TOTAL | D62: 24
B64: FINANCE & ADMIN.
A65: 1 | B65: DR KABIR AHMED | D65: DIR. FINANCE & ADMIN | E65: 17(9)
A66: 2 | B66: IBRAHIM M. MSHELIA | D66: DD F&A | E66: 16(9)
A67: 3 | B67: AMINU BELLO DUKKU | D67: DD ADMIN/HR | E67: 16(9)
A68: 4 | B68: KABIR MUHAMMAD SULAIMAN | D68: MANAGER ADMIN&HR | E68: 15(9)
A69: 5 | B69: MAGAJI BALA | D69: MANGER ACCOUNTS | E69: 15(9)
A70: 6 | B70: RAHILA NURUDEEN HABU | D70: ASST. MANAGER, ACCOUNTS | E70: 13(11)
A71: 7 | B71: ABDULLAHI YUNUSA | D71: PERSONNEL OFFICER | E71: 13(7)
A72: 8 | B72: MARUF ABDULSALAM | D72: ASSET& MAINT. OFFICER | E72: 13(7)
A73: 9 | B73: ANDRAWUS MUSA | D73: STORE OFFICER | E73: 13(7)
A74: 10 | B74: TONDO IORWUESE EDWARD | D74: OFFICER ACCOUNTS | E74: 13(7)
A75: 11 | B75: OSOLAFIA MUHAMMAD EGYE | D75: PERSONNEL ASSISTANT | E75: 10(7)
A76: 12 | B76: EROMOSELE OMONIGBO | D76: PERSONNEL ASSISTANT | E76: 10(7)
... A88: 24 | B88: OMOUDU QUEEN PRISCILLA | D88: SECRETARY | E88: 8(12)
A89: 25 | B89: BASSEY NSONGURUA UDOFIA | D89: CONFIDENTIAL SECRETARY
A90: 26 | B90: OLATUNJI OYEDELE YUSUF | D90: SENIOR DRIVER | E90: 5(10)
A91: 27 | B91: TASIU MOHAMMED | D91: SENIOR DRIVER | E91: 5(10)
A92: 28 | B92: NAMADI IDRIS UMAR | D92: SENIOR DRIVER | E92: 5(10)
A93: 29 | B93: DANJUMA KAGADAMA | D93: SENIOR DRIVER | E93: 5(10)
A94: 30 | B94: MOHAMMED SIAKA | D94: SENIOR DRIVER | E94: 5(10)
A95: 31 | B95: ALFRED ISABU | D95: SENIOR DRIVER | E95: 5(10)
A96: 32 | B96: ALIYU YAKUBU | D96: SENIOR DRIVER | E96: 5(10)
A97: 33 | B97: ABDULLAHI HARUNA | D97: SENIOR DRIVER | E97: 5(10)
A98: 35 | B98: OGABO OGAH USMAN | D98: DRIVER | E98: 4(11)
A99: 36 | B99: ETSU UMARU | D99: DRIVER | E99: 4(11)
A100: 37 | B100: MURTALA LAWAL | D100: DRIVER | E100: 4(11)
A101: 38 | B101: EDACHE OGA | D101: DRIVER | E101: 4(11)
... A105: 42 | B105: ABUBAKAR MUSA DANLAMI | D105: DRIVER | E105: 4(10)
A106: 43 | B106: Gideon B. Lamido | D106: Dispatch Clerk
A107: 44 | B107: Ewelikwa Ijeoma Nkolikwa | D107: Dispatch Clerk
A108: 45 | B108: Hussain Hazeem Mohammed | D108: Asst. Secretary
A109: 46 | B109: Saratu Adamu Attajiri | D109: Office Assistant
A110: 47 | B110: Saratu H. Gwalem | D110: Receptionist
A111: 48 | B111: Aboaman Innocent | D111: Steward
A112: 49 | B112: ADANHOU V. ALFRED | D112: Steward
A113: 50 | B113: Kusai E. Richard | D113: Plumber
A114: 51 | B114: Oluma Joseph Oluma | D114: Steward
A115: 52 | B115: HARUNA BELLO | D115: GARDENER
A116: 53 | B116: Salisu Mohammad Adamu | D116: DRIVER
A117: 54 | B117: Ayuba Sule | D117: Gardener
B118: TOTAL | D118: 54

Sheet Sheet6
A1: 1 | B1: DR LADI HAMALAI | C1: DIRECTOR GENERAL | D1: CONSOL
A2: 2 | B2: PROF. OFFORNZE AMUCHEAZI | C2: LEGAL ADVISER | D2: 16(9)
A3: 3 | B3: NWAJEI KANAYO | C3: COMMUNICATION ADVISER | D3: 16(7)
A4: 4 | B4: NWOSU MATHEW EZE | C4: MANAGER INT. AUDIT | D4: 15(9)
A5: 5 | B5: CHIEDO AKALEU | C5: RESEARCH FELLOW II | D5: 15(8)
A6: 6 | B6: AKINSANMI ADEJOKE OLUKEMI | C6: AM INFORMATION | D6: 13(9)
A7: 7 | B7: BEDARI HARI | C7: LEGAL OFFICER | D7: 10(9)
A8: 8 | B8: NGARA CHRISTOPHER OCHANJA | C8: OFFICER, SPECIAL DUTIES | D8: 10(9)
A9: 9 | B9: JOY HARUNA MAKERI | C9: PA DG | D9: 10(9)
A10: 10 | B10: DONALD E. MKPANAM | C10: IT OFFICER | D10: 10(9)
B11: ABUBAKAR LAMIDO | C11: ICT OFFICER | D11: 10(7)
A12: 11 | B12: HUSSEIN MUSA AGYE | C12: PROTOCOL OFFICER | D12: 10(9)
A13: 12 | B13: BASHIRU ABBA WALI | C13: ASSIT. INT. AUDIT | D13: 8(9)
A14: 13 | B14: ALI ABDULLAHI | C14: OFFICER ICT | D14: 10(7)
A15: 14 | B15: UZODINMA EMMANUEL EZENWA | C15: INFORMATION ASST | D15: 8(9)
A16: 15 | B16: CHRISTIAN MADUABUCHI ODO | C16: ICT ASSISTANT | D16: 8(9)
B17: TOTAL | C17: 15
B20: LEG. SUPPORT SEVICES
A21: 1 | B21: PROF OKECHUKWU OKO | C21: DIR. LEG. SP SERVICES | D21: 17(9)
A22: 2 | B22: DR SHUIBU DANWANKA | C22: DD LEG. SP SERVICES | D22: 16(9)
A23: 3 | B23: IBRAHIM USMAN | C23: RESEARCH FELLOW II | D23: 13(9)
A24: 4 | B24: OFORDEME ADAOBI JULIA | C24: RESEARCH OFFICER | D24: 10(9)
A25: 5 | B25: IKPEAZU CHINEDU ANITA | C25: RESEARCH OFFICER | D25: 10(9)
A26: 6 | B26: ONYEAKU CHUKWUKA EDMOND | C26: RESEARCH OFFICER | D26: 10(7)
B27: TOTAL | C27: 6
B29: RESEARCH & TRAINING
A30: 1 | B30: DR ADEYEMI AKEEB FAJINGBESI | C30: DIR. RES. & TRAINING | D30: 17(7)
A31: 2 | B31: DR ASIMIYU G. ABIOLA | C31: DD RESEARCH | D31: 16(9)
A32: 3 | B32: DR KANAYO OGUJIUBA | C32: SRF SOCIAL SECTOR | D32: 15(9)
A33: 4 | B33: DR ADAM GAMBO SALEH | C33: INSTITUTE LIBRARIAN | D33: 15(7)
A34: 5 | B34: DR ANUMUDU CHARLES NNAMDI | C34: SRF I SOCIAL SECTOR | D34: 14(9)
A35: 6 | B35: CATHERINE E. IKOKOH | C35: RESEARCH FELLOW1 DOCU | D35: 14(9)
A36: 7 | C36: RESEARCH FELLOW I | D36: 14(7)
A37: 8 | B37: ABDULKADIR | C37: CHIEF LIBRARIAN | D37: 14(7)
A38: 9 | B38: DR ASEMOTA O. JOSEPH | C38: RESEARCH FELLOW I | D38: 14(7)
A39: 10 | B39: DR UMAR AMINU | C39: RESEARCH FELLOW II | D39: 13(9)
A40: 11 | C40: RESEARCH FELLOW II | D40: 13(8)
A41: 12 | B41: DR JAKE DABANG DAN AZUMI | C41: RESEARCH FELLOW I TRAINING | D41: 14(7)
A42: 13 | B42: TAIWO A. ADEREMI | C42: RESEARCH FELLOW II | D42: 13(7)
A43: 14 | B43: BETHEL UZOMA | C43: RESEARCH FELLOW II | D43: 13(7)
A44: 15 | C44: RESEARCH FELLOW II | D44: 13(7)
A45: 16 | C45: RESEARCH FELLOW II | D45: 13(7)
A46: 17 | B46: ABDULSALAM MUSTAFA | C46: ASST. MANAGER, TRAINING | D46: 13(7)
A47: 18 | B47: ALIYU SANNI ABUBAKAR | C47: DATA & DOCU. OFFICER | D47: 10(9)
A48: 19 | B48: JUMARE FADILA | C48: RESEARCH OFFICER | D48: 10(9)
A49: 20 | B49: CHINAKO N. ASOGWA | C49: LIBRARY OFFICER | D49: 10(9)
A50: 21 | B50: UDEFUNA NNADOZIE PATRICK | C50: RESEARCH OFFICER | D50: 10(7)
A51: 22 | B51: CHARLES I. OBUTTE | C51: RESEARCH ASSISTANT | D51: 9(9)
A52: 23 | B52: OGUNYOMI ROTIMI | C52: RESEARCH ASSISTANT | D52: 9(8)
A53: 24 | B53: IBE EZECHI CYRIACUS | C53: RESEARCH ASSISTANT | D53: 9(8)
A54: 25 | B54: ANTHONY EDET | C54: OFFICER M&E | D54: 10(7)
B55: TOTAL | C55: 25
B57: FINANCE & ADMIN.
A58: 1 | B58: DR KABIR AHMED | C58: DIR. FINANCE & ADMIN | D58: 17(9)
A59: 2 | B59: IBRAHIM M. MSHELIA | C59: DD F&A | D59: 16(9)
A60: 3 | B60: AMINU BELLO DUKKU | C60: DD ADMIN/HR | D60: 16(9)
A61: 4 | B61: KABIR MUHAMMAD SULAIMAN | C61: MANAGER ADMIN&HR | D61: 15(9)
A62: 5 | B62: PRISCILLA CHUKWU | C62: MANAGER ADMIN & HR | D62: 15(9)
A63: 6 | B63: MAGAJI BALA | C63: MANGER ACCOUNTS | D63: 15(9)
A64: 7 | B64: RAHILA NURUDEEN HABU | C64: ASST. MANAGER, ACCOUNTS | D64: 13(9)
A65: 8 | B65: ABDULLAHI YUNUSA | C65: PERSONNEL OFFICER | D65: 10(9)
A66: 9 | B66: MARUF ABDULSALAM | C66: ASSET& MAINT. OFFICER | D66: 10(9)
A67: 10 | B67: ANDRAWUS MUSA | C67: STORE OFFICER | D67: 10(9)
A68: 11 | B68: TONDO IORWUESE EDWARD | C68: OFFICER ACCOUNTS | D68: 10(9)
A69: 12 | B69: MUHAMMED AGEDE YAHAYA | C69: PERSONNEL ASSISTANT | D69: 8(9)
A70: 13 | C70: PERSONNEL ASSISTANT | D70: 8(9)
A71: 14 | B71: SHEHU ABDULLAHI | C71: ACCOUNT ASSISTANT | D71: 8(9)
A72: 15 | B72: YUSUFF ABISOLA GANIYAT | C72: ACCOUNT ASSISTANT | D72: 8(9)
A73: 16 | B73: RAHILA SALIHU | C73: ACCOUNT ASSISTANT | D73: 8(9)
A74: 17 | B74: SIMON YAKUBU WAKAWA | C74: OFFICER, ASSETS & MAINT. | D74: 10(7)
A75: 18 | B75: OKWUOSA UCHECH AMAECHI | C75: ADMIN OFFICER | D75: 10(7)
A76: 19 | B76: h | C76: ADMIN OFFICER | D76: 10(7)
A77: 20 | B77: USMAN WAZIRI | C77: SEN. CONF. SECRETARY | D77: 10(7)
A78: 21 | B78: SALAMATU YAKUBU | C78: SEN. CONF. SECRETARY | D78: 10(7)
A79: 22 | B79: IDAHOSA JANE CECILIA | C79: SECRETARY | D79: 9(8)
A80: 23 | B80: MOHAMMED R. ADAMU | C80: SECRETARY | D80: 8(11)
A81: 24 | C81: SECRETARY | D81: 8(10)
A82: 25 | B82: OLATUNJI OYEDELE YUSUF | C82: SENIOR DRIVER | D82: 5(8)
A83: 26 | B83: TASIU MOHAMMED | C83: SENIOR DRIVER | D83: 5(8)
A84: 27 | B84: NAMADI IDRIS UMAR | C84: SENIOR DRIVER | D84: 5(8)
A85: 28 | B85: DANJUMA KAGADAMA | C85: SENIOR DRIVER | D85: 5(8)
A86: 29 | B86: MOHAMMED SIAKA | C86: SENIOR DRIVER | D86: 5(8)
A87: 30 | B87: ALFRED ISABU | C87: SENIOR DRIVER | D87: 5(8)
A88: 31 | B88: USMAN YAHAYA | C88: SENIOR DRIVER | D88: 5(8)
A89: 32 | B89: ALIYU YAKUBU | C89: SENIOR DRIVER | D89: 5(8)
A90: 33 | B90: ABDULLAHI HARUNA | C90: SENIOR DRIVER | D90: 5(8)
A91: 34 | B91: EJEME PATRICK | C91: DRIVER | D91: 4(9)
A92: 35 | B92: OGABO OGAH USMAN | C92: DRIVER | D92: 4(9)
A93: 36 | B93: ETSU UMARU | C93: DRIVER | D93: 4(9)
... A99: 42 | B99: ABUBAKAR MUSA DANLAMI | C99: DRIVER | D99: 4(8)
C100: 42
B102: CASUAL & SABBATICAL STAFF
A103: 1 | B103: DR AREMU FATAI AYINDE | C103: SABBATICAL
A104: 2 | B104: BENJAMIN SOLOMON AKHERE | C104: SABBATICAL
A105: 3 | B105: PROF. NUHU MOHAMMED JAMO | C105: SABBATICAL
A106: 4 | B106: OLAGUNJU OLALEKAN | C106: EDITOR
A107: 5 | B107: ABDULWAHAB DAHIRU | C107: DISPATCH CLERK
A108: 6 | B108: GIDEON B. LAMIDO | C108: DISPATCH CLERK
A109: 7 | B109: EWELIKWA IJEOMA NKOLIKWA | C109: DISPATCH CLERK
A110: 8 | B110: HUSSAIN HAZEEM MOHAMMED | C110: ASST SECRETARY
...

Sheet Sheet4
A1: S/N | B1: DG OFFICE | C1: RANK | D1: SALARY LEVEL | E1: AMOUNT
A2: 1 | B2: DR LADI HAMALAI | C2: DIRECTOR GENERAL | D2: CONSOL | E2: 250000
A3: 2 | B3: PROF. OFFORNZE AMUCHEAZI | C3: LEGAL ADVISER | D3: 16(9) | E3: 100000
A4: 3 | B4: NWAJEI KANAYO | C4: COMMUNICATION ADVISER | D4: 16(7) | E4: 100000
A5: 4 | B5: NWOSU MATHEW EZE | C5: MANAGER INT. AUDIT | D5: 15(9) | E5: 75000
A6: 5 | B6: CHIEDO AKALEU | C6: RESEARCH FELLOW II | D6: 15(8) | E6: 75000
A7: 6 | B7: AKINSANMI ADEJOKE OLUKEMI | C7: AM INFORMATION | D7: 13(9) | E7: 50000
A8: 7 | B8: BEDARI HARI | C8: LEGAL OFFICER | D8: 10(9) | E8: 30000
A9: 8 | B9: NGARA CHRISTOPHER OCHANJA | C9: OFFICER, SPECIAL DUTIES | D9: 10(9) | E9: 30000
A10: 9 | B10: JOY HARUNA MAKERI | C10: PA DG | D10: 10(9) | E10: 30000
A11: 10 | B11: DONALD E. MKPANAM | C11: IT OFFICER | D11: 10(9) | E11: 30000
A12: 11 | B12: HUSSEIN MUSA AGYE | C12: PROTOCOL OFFICER | D12: 10(9) | E12: 30000
A13: 12 | B13: BASHIRU ABBA WALI | C13: ASSIT. INT. AUDIT | D13: 8(9) | E13: 30000
... A16: 15 | B16: CHRISTIAN MADUABUCHI ODO | C16: ICT ASSISTANT | D16: 8(9) | E16: 30000
B17: TOTAL | E17: =SUM(E2:E16) -> 920000
B20: LEG. SUPPORT SEVICES
A21: 1 | B21: PROF OKECHUKWU OKO | C21: DIR. LEG. SP SERVICES | D21: 17(9) | E21: 200000
A22: 2 | B22: DR SHUIBU DANWANKA | C22: DD LEG. SP SERVICES | D22: 16(9) | E22: 100000
A23: 3 | B23: IBRAHIM USMAN | C23: RESEARCH FELLOW II | D23: 13(9) | E23: 50000
A24: 4 | B24: OFORDEME ADAOBI JULIA | C24: RESEARCH OFFICER | D24: 10(9) | E24: 30000
A25: 5 | B25: IKPEAZU CHINEDU ANITA | C25: RESEARCH OFFICER | D25: 10(9) | E25: 30000
A26: 6 | B26: ONYEAKU CHUKWUKA EDMOND | C26: RESEARCH OFFICER | D26: 10(7) | E26: 30000
B27: TOTAL | E27: =SUM(E21:E26) -> 440000
B29: RESEARCH & TRAINING
A30: 1 | B30: DR ADEYEMI AKEEB FAJINGBESI | C30: DIR. RES. & TRAINING | D30: 17(7) | E30: 200000
A31: 2 | B31: DR ASIMIYU G. ABIOLA | C31: DD RESEARCH | D31: 16(9) | E31: 100000
A32: 3 | B32: DR KANAYO OGUJIUBA | C32: SRF SOCIAL SECTOR | D32: 15(9) | E32: 75000
A33: 4 | B33: DR ADAM GAMBO SALEH | C33: INSTITUTE LIBRARIAN | D33: 15(7) | E33: 75000
A34: 5 | B34: DR ANUMUDU CHARLES NNAMDI | C34: SRF I SOCIAL SECTOR | D34: 14(9) | E34: 50000
A35: 6 | B35: CATHERINE E. IKOKOH | C35: RESEARCH FELLOW1 DOCU | D35: 14(9) | E35: 50000
A36: 7 | B36: DR CLINTON JAJA | C36: RESEARCH FELLOW I | D36: 14(7) | E36: 50000
A37: 8 | B37: ABDULKADIR I. AHMED | C37: CHIEF LIBRARIAN | D37: 14(7) | E37: 50000
A38: 9 | B38: DR ASEMOTA O. JOSEPH | C38: RESEARCH FELLOW I | D38: 14(7) | E38: 50000
A39: 10 | B39: DR UMAR AMINU | C39: RESEARCH FELLOW II | D39: 13(9) | E39: 50000
A40: 11 | B40: OGUCHE SAMUEL | C40: RESEARCH FELLOW II | D40: 13(8) | E40: 50000
A41: 12 | B41: DR JAKE DABANG DAN AZUMI | C41: RESEARCH FELLOW I TRAINING | D41: 14(7) | E41: 50000
... A54: 25 | B54: ANTHONY EDET | C54: OFFICER M&E | D54: 10(7) | E54: 30000
B55: TOTAL | E55: =SUM(E30:E54) -> 1340000
B59: FINANCE & ADMIN.
A60: 1 | B60: DR KABIR AHMED | C60: DIR. FINANCE & ADMIN | D60: 17(9) | E60: 200000
A61: 2 | B61: IBRAHIM M. MSHELIA | C61: DD F&A | D61: 16(9) | E61: 100000
A62: 3 | B62: AMINU BELLO DUKKU | C62: DD ADMIN/HR | D62: 16(9) | E62: 100000
A63: 4 | B63: KABIR MUHAMMAD SULAIMAN | C63: MANAGER ADMIN&HR | D63: 15(9) | E63: 75000
A64: 5 | B64: PRISCILLA CHUKWU | C64: MANAGER ADMIN & HR | D64: 15(9) | E64: 75000
A65: 6 | B65: MAGAJI BALA | C65: MANGER ACCOUNTS | D65: 15(9) | E65: 75000
A66: 7 | B66: RAHILA NURUDEEN HABU | C66: ASST. MANAGER, ACCOUNTS | D66: 13(9) | E66: 50000
A67: 8 | B67: ABDULLAHI YUNUSA | C67: PERSONNEL OFFICER | D67: 10(9) | E67: 30000
A68: 9 | B68: MARUF ABDULSALAM | C68: ASSET& MAINT. OFFICER | D68: 10(9) | E68: 30000
A69: 10 | B69: ANDRAWUS MUSA | C69: STORE OFFICER | D69: 10(9) | E69: 30000
A70: 11 | B70: TONDO IORWUESE EDWARD | C70: OFFICER ACCOUNTS | D70: 10(9) | E70: 30000
A71: 12 | B71: MUHAMMED AGEDE YAHAYA | C71: PERSONNEL ASSISTANT | D71: 8(9) | E71: 30000
... A101: 42 | B101: ABUBAKAR MUSA DANLAMI | C101: DRIVER | D101: 4(8) | E101: 20000
B102: TOTAL | E102: =SUM(E60:E101) -> 1545000
B104: CASUAL & SABBATICAL STAFF
A105: 1 | B105: DR AREMU FATAI AYINDE | C105: SABBATICAL | E105: 75000
A106: 2 | B106: OLAGUNJU OLALEKAN | C106: EDITOR | E106: 50000
A107: 3 | B107: ABDULWAHAB DAHIRU | C107: DISPATCH CLERK | E107: 30000
A108: 4 | B108: GIDEON B. LAMIDO | C108: DISPATCH CLERK | E108: 30000
A109: 5 | B109: EWELIKWA IJEOMA NKOLIKWA | C109: DISPATCH CLERK | E109: 30000
A110: 6 | B110: HUSSAIN HAZEEM MOHAMMED | C110: ASST SECRETARY | E110: 30000
A111: 7 | B111: EGWUATU ONYEJELEM | C111: OFFICER M&E | E111: 30000
A112: 8 | B112: AYUBA SULE | C112: GARDENER | E112: 20000
B113: TOTAL | E113: =SUM(E105:E112) -> 295000
B114: GRAND TOTAL | E114: =E17+E27+E55+E102+E113 -> 4540000

Sheet Sheet5
A1: S/N | B1: DG OFFICE | C1: RANK | D1: SALARY LEVEL | E1: AMOUNT
A2: 1 | B2: DR LADI HAMALAI | C2: DIRECTOR GENERAL | D2: CONSOL | E2: 250000
A3: 2 | B3: PROF. OFFORNZE AMUCHEAZI | C3: LEGAL ADVISER | D3: 16(9) | E3: 100000
A4: 3 | B4: NWAJEI KANAYO | C4: COMMUNICATION ADVISER | D4: 16(7) | E4: 100000
A5: 4 | B5: NWOSU MATHEW EZE | C5: MANAGER INT. AUDIT | D5: 15(9) | E5: 75000
A6: 5 | B6: CHIEDO AKALEU | C6: RESEARCH FELLOW II | D6: 15(8) | E6: 75000
A7: 6 | B7: AKINSANMI ADEJOKE OLUKEMI | C7: AM INFORMATION | D7: 13(9) | E7: 50000
A8: 7 | B8: BEDARI HARI | C8: LEGAL OFFICER | D8: 10(9) | E8: 30000
A9: 8 | B9: NGARA CHRISTOPHER OCHANJA | C9: OFFICER, SPECIAL DUTIES | D9: 10(9) | E9: 30000
A10: 9 | B10: JOY HARUNA MAKERI | C10: PA DG | D10: 10(9) | E10: 30000
A11: 10 | B11: DONALD E. MKPANAM | C11: IT OFFICER | D11: 10(9) | E11: 30000
A12: 11 | B12: HUSSEIN MUSA AGYE | C12: PROTOCOL OFFICER | D12: 10(9) | E12: 30000
A13: 12 | B13: BASHIRU ABBA WALI | C13: ASSIT. INT. AUDIT | D13: 8(9) | E13: 30000
... A16: 15 | B16: CHRISTIAN MADUABUCHI ODO | C16: ICT ASSISTANT | D16: 8(9) | E16: 30000
B17: TOTAL | E17: =SUM(E2:E16) -> 920000
B20: LEG. SUPPORT SEVICES
A21: 1 | B21: PROF OKECHUKWU OKO | C21: DIR. LEG. SP SERVICES | D21: 17(9) | E21: 200000
A22: 2 | B22: DR SHUIBU DANWANKA | C22: DD LEG. SP SERVICES | D22: 16(9) | E22: 100000
A23: 3 | B23: IBRAHIM USMAN | C23: RESEARCH FELLOW II | D23: 13(9) | E23: 50000
A24: 4 | B24: OFORDEME ADAOBI JULIA | C24: RESEARCH OFFICER | D24: 10(9) | E24: 30000
A25: 5 | B25: IKPEAZU CHINEDU ANITA | C25: RESEARCH OFFICER | D25: 10(9) | E25: 30000
A26: 6 | B26: ONYEAKU CHUKWUKA EDMOND | C26: RESEARCH OFFICER | D26: 10(7) | E26: 30000
B27: TOTAL | E27: =SUM(E21:E26) -> 440000
B29: RESEARCH & TRAINING
A30: 1 | B30: DR ADEYEMI AKEEB FAJINGBESI | C30: DIR. RES. & TRAINING | D30: 17(7) | E30: 200000
A31: 2 | B31: DR ASIMIYU G. ABIOLA | C31: DD RESEARCH | D31: 16(9) | E31: 100000
A32: 3 | B32: DR KANAYO OGUJIUBA | C32: SRF SOCIAL SECTOR | D32: 15(9) | E32: 75000
A33: 4 | B33: DR ADAM GAMBO SALEH | C33: INSTITUTE LIBRARIAN | D33: 15(7) | E33: 75000
A34: 5 | B34: DR ANUMUDU CHARLES NNAMDI | C34: SRF I SOCIAL SECTOR | D34: 14(9) | E34: 50000
A35: 6 | B35: CATHERINE E. IKOKOH | C35: RESEARCH FELLOW1 DOCU | D35: 14(9) | E35: 50000
A36: 7 | B36: DR CLINTON JAJA | C36: RESEARCH FELLOW I | D36: 14(7) | E36: 50000
A37: 8 | B37: ABDULKADIR I. AHMED | C37: CHIEF LIBRARIAN | D37: 14(7) | E37: 50000
A38: 9 | B38: DR ASEMOTA O. JOSEPH | C38: RESEARCH FELLOW I | D38: 14(7) | E38: 50000
A39: 10 | B39: DR UMAR AMINU | C39: RESEARCH FELLOW II | D39: 13(9) | E39: 50000
A40: 11 | B40: OGUCHE SAMUEL | C40: RESEARCH FELLOW II | D40: 13(8) | E40: 50000
A41: 12 | B41: DR JAKE DABANG DAN AZUMI | C41: RESEARCH FELLOW I TRAINING | D41: 14(7) | E41: 50000
... A54: 25 | B54: ANTHONY EDET | C54: OFFICER M&E | D54: 10(7) | E54: 30000
B55: TOTAL | E55: =SUM(E30:E54) -> 1340000
B59: FINANCE & ADMIN.
A60: 1 | B60: DR KABIR AHMED | C60: DIR. FINANCE & ADMIN | D60: 17(9) | E60: 200000
A61: 2 | B61: IBRAHIM M. MSHELIA | C61: DD F&A | D61: 16(9) | E61: 100000
A62: 3 | B62: AMINU BELLO DUKKU | C62: DD ADMIN/HR | D62: 16(9) | E62: 100000
A63: 4 | B63: KABIR MUHAMMAD SULAIMAN | C63: MANAGER ADMIN&HR | D63: 15(9) | E63: 75000
A64: 5 | B64: PRISCILLA CHUKWU | C64: MANAGER ADMIN & HR | D64: 15(9) | E64: 75000
A65: 6 | B65: MAGAJI BALA | C65: MANGER ACCOUNTS | D65: 15(9) | E65: 75000
A66: 7 | B66: RAHILA NURUDEEN HABU | C66: ASST. MANAGER, ACCOUNTS | D66: 13(9) | E66: 50000
A67: 8 | B67: ABDULLAHI YUNUSA | C67: PERSONNEL OFFICER | D67: 10(9) | E67: 30000
A68: 9 | B68: MARUF ABDULSALAM | C68: ASSET& MAINT. OFFICER | D68: 10(9) | E68: 30000
A69: 10 | B69: ANDRAWUS MUSA | C69: STORE OFFICER | D69: 10(9) | E69: 30000
A70: 11 | B70: TONDO IORWUESE EDWARD | C70: OFFICER ACCOUNTS | D70: 10(9) | E70: 30000
A71: 12 | B71: MUHAMMED AGEDE YAHAYA | C71: PERSONNEL ASSISTANT | D71: 8(9) | E71: 30000
... A101: 42 | B101: ABUBAKAR MUSA DANLAMI | C101: DRIVER | D101: 4(8) | E101: 20000
B102: TOTAL | E102: =SUM(E60:E101) -> 1545000
B104: CASUAL & SABBATICAL STAFF
A105: 1 | B105: DR AREMU FATAI AYINDE | C105: SABBATICAL | E105: 75000
A106: 2 | B106: OLAGUNJU OLALEKAN | C106: EDITOR | E106: 50000
A107: 3 | B107: ABDULWAHAB DAHIRU | C107: DISPATCH CLERK | E107: 30000
A108: 4 | B108: GIDEON B. LAMIDO | C108: DISPATCH CLERK | E108: 30000
A109: 5 | B109: EWELIKWA IJEOMA NKOLIKWA | C109: DISPATCH CLERK | E109: 30000
A110: 6 | B110: HUSSAIN HAZEEM MOHAMMED | C110: ASST SECRETARY | E110: 30000
A111: 7 | B111: EGWUATU ONYEJELEM | C111: OFFICER M&E | E111: 30000
A112: 8 | B112: AYUBA SULE | C112: GARDENER | E112: 20000
B113: TOTAL | E113: =SUM(E105:E112) -> 295000
B114: GRAND TOTAL | E114: =E17+E27+E55+E102+E113 -> 4540000

Sheet Eid Kabir
A1: S/N | B1: NAMES | D1: DESIGNATION | E1: SCALE | F1: AMOUNT
B2: DIRECTOR GENERAL'S OFFICE
A3: 1 | B3: DR LADI HAMALAI | D3: DIRECTOR GENERAL | E3: CONSOL | F3: 150000
A4: 2 | B4: NWAJEI KANAYO | D4: COMMUNICATION ADVISER | E4: 16(7) | F4: 50000
A5: 3 | B5: NWOSU MATHEW EZE | D5: MANAGER INT. AUDIT | E5: 15(9) | F5: 50000
A6: 4 | B6: AKINSANMI ADEJOKE OLUKEMI | D6: AM INFORMATION | E6: 15(7) | F6: 50000
A7: 5 | B7: ARCH. TIJO ZARA BORYO | D7: MANAGER, ASSETS/MAINT. | E7: 15(7) | F7: 50000
A8: 6 | B8: YAHAYA SHAMSU | D8: AM LEGAL | E8: 13(8) | F8: 30000
A9: 7 | B9: TOKUNBO ALFRED ADULOJU | D9: AM LIAISON OFFICE | E9: 13(7) | F9: 30000
A10: 8 | B10: NGARA CHRISTOPHER OCHANJA | D10: OFFICER, SPECIAL DUTIES | E10: 13(7) | F10: 30000
A11: 9 | B11: DONALD E. MKPANAM | D11: AM ICT | E11: 13(10) | F11: 30000
A12: 10 | B12: JOY HARUNA MAKERI | D12: PA DG | E12: 10(11) | F12: 20000
A13: 11 | B13: ABUBAKAR LAMIDO TANKO | D13: ICT OFFICER | E13: 10(9) | F13: 20000
A14: 12 | B14: BASHIRU ABBA WALI | D14: ASSIT. INT. AUDIT | E14: 10(7) | F14: 20000
... A17: 15 | B17: CHRISTIAN MADUABUCHI ODO | D17: ICT ASSISTANT | E17: 10(7) | F17: 20000
C18: TOTAL | F18: =SUM(F3:F17) -> 590000
B20: LEG. SUPPORT SEVICES
A21: 1 | B21: DR SHUIBU DANWANKA | D21: DD LEG. SP SERVICES | E21: 16(9) | F21: 50000
A22: 2 | B22: IBRAHIM USMAN | D22: RESEARCH FELLOW II | E22: 13(11) | F22: 30000
A23: 3 | B23: OFORDEME ADAOBI JULIA | D23: RESEARCH OFFICER | E23: 10(11) | F23: 20000
A24: 4 | B24: IKPEAZU CHINEDU ANITA | D24: RESEARCH OFFICER | E24: 10(11) | F24: 20000
A25: 5 | B25: ONYEAKU CHUKWUKA EDMOND | D25: RESEARCH OFFICER | E25: 10(9) | F25: 20000
A26: 6 | B26: DORIS DAKDA AARON | D26: RESEARCH OFFICER | E26: 10(7) | F26: 20000
B27: TOTAL | F27: =SUM(F21:F26) -> 160000
B29: DEMOCRATIC STUDIES
A30: 1 | B30: DR IKEME ARTHUR J.O | D30: SNR RESEARCH FELLOW | E30: 15(7) | F30: 50000
A31: 2 | B31: EJALONIBU GANIYU LAYI | D31: RESEARCH OFFICER | E31: 10(7) | F31: 20000
B32: TOTAL | F32: =SUM(F30:F31) -> 70000
B34: RESEARCH & TRAINING
A35: 1 | B35: DR ADEYEMI AKEEB FAJINGBESI | D35: DIR. RES. & TRAINING | E35: 17(7) | F35: 100000
A36: 2 | B36: DR ASIMIYU G. ABIOLA | D36: DD RESEARCH | E36: 16(9) | F36: 50000
A37: 3 | B37: CATHERINE E. IKOKOH | D37: RESEARCH FELLOW1 DOCU | E37: 14(11) | F37: 30000
A38: 4 | B38: DR CLINTON JAJA | D38: RESEARCH FELLOW I | E38: 14(9) | F38: 30000
A39: 5 | B39: ABDULKADIR I. AHMED | D39: CHIEF LIBRARIAN | E39: 14(9) | F39: 30000
A40: 6 | B40: DR ASEMOTA O. JOSEPH | D40: RESEARCH FELLOW I | E40: 14(9) | F40: 30000
A41: 7 | B41: DR UMAR AMINU | D41: RESEARCH FELLOW II | E41: 14(10) | F41: 30000
A42: 8 | B42: OGUCHE SAMUEL | D42: RESEARCH FELLOW II | E42: 13(10) | F42: 30000
A43: 9 | B43: DR JAKE DABANG DAN AZUMI | D43: RESEARCH FELLOW I TRAINING | E43: 14(9) | F43: 30000
A44: 10 | B44: BETHEL UZOMA IHUGBA | D44: RESEARCH FELLOW I | E44: 14(9) | F44: 30000
A45: 11 | B45: TERFA WILLIAMS ABRAHAM | D45: RESEARCH FELLOW II | E45: 13(10) | F45: 30000
A46: 12 | B46: ABDULSALAM MUSTAFA | D46: ASST. MANAGER, TRAINING | E46: 13(11) | F46: 30000
... A56: 22 | B56: ANTHONY EDET | D56: OFFICER M&E | E56: 10(9) | F56: 20000
B57: TOTAL | F57: =SUM(F35:F56) -> 690000
B59: FINANCE & ADMIN.
A60: 1 | B60: DR KABIR AHMED | D60: DIR. FINANCE & ADMIN | E60: 17(9) | F60: 100000
A61: 2 | B61: IBRAHIM M. MSHELIA | D61: DD F&A | E61: 16(9) | F61: 50000
A62: 3 | B62: AMINU BELLO DUKKU | D62: DD ADMIN/HR | E62: 16(9) | F62: 50000
A63: 4 | B63: KABIR MUHAMMAD SULAIMAN | D63: MANAGER ADMIN&HR | E63: 15(9) | F63: 50000
A64: 5 | B64: MAGAJI BALA | D64: MANGER ACCOUNTS | E64: 15(9) | F64: 50000
A65: 6 | B65: RAHILA NURUDEEN HABU | D65: ASST. MANAGER, ACCOUNTS | E65: 13(11) | F65: 30000
A66: 7 | B66: MARUF ABDULSALAM | D66: ASSET& MAINT. OFFICER | E66: 13(7) | F66: 30000
A67: 8 | B67: ANDRAWUS MUSA | D67: STORE OFFICER | E67: 13(7) | F67: 30000
A68: 9 | B68: YUNUSA ABDULLAHI | D68: AM ADMIN & HR | E68: 13(7) | F68: 30000
A69: 10 | B69: TONDO IORWUESE EDWARD | D69: OFFICER ACCOUNTS | E69: 13(7) | F69: 30000
A70: 11 | B70: OSOLAFIA MUHAMMAD EGYE | D70: PERSONNEL ASSISTANT | E70: 10(7) | F70: 20000
A71: 12 | B71: EROMOSELE OMONIGBO | D71: PERSONNEL ASSISTANT | E71: 10(7) | F71: 20000
... A83: 24 | B83: OMOUDU QUEEN PRISCILLA | D83: SECRETARY | E83: 8(12) | F83: 20000
A84: 25 | B84: BASSEY NSONGURUA UDOFIA | D84: CONFIDENTIAL SECRETARY | F84: 20000
A85: 26 | B85: OLATUNJI OYEDELE YUSUF | D85: SENIOR DRIVER | E85: 5(10) | F85: 10000
A86: 27 | B86: TASIU MOHAMMED | D86: SENIOR DRIVER | E86: 5(10) | F86: 10000
A87: 28 | B87: NAMADI IDRIS UMAR | D87: SENIOR DRIVER | E87: 5(10) | F87: 10000
A88: 29 | B88: DANJUMA KAGADAMA | D88: SENIOR DRIVER | E88: 5(10) | F88: 10000
A89: 30 | B89: MOHAMMED SIAKA | D89: SENIOR DRIVER | E89: 5(10) | F89: 10000
A90: 31 | B90: ALFRED ISABU | D90: SENIOR DRIVER | E90: 5(10) | F90: 10000
A91: 32 | B91: ALIYU YAKUBU | D91: SENIOR DRIVER | E91: 5(10) | F91: 10000
A92: 33 | B92: ABDULLAHI HARUNA | D92: SENIOR DRIVER | E92: 5(10) | F92: 10000
A93: 34 | B93: OGABO OGAH USMAN | D93: DRIVER | E93: 4(11) | F93: 10000
A94: 35 | B94: ETSU UMARU | D94: DRIVER | E94: 4(11) | F94: 10000
A95: 36 | B95: MURTALA LAWAL | D95: DRIVER | E95: 4(11) | F95: 10000
A96: 37 | B96: EDACHE OGA | D96: DRIVER | E96: 4(11) | F96: 10000
... A100: 41 | B100: ABUBAKAR MUSA DANLAMI | D100: DRIVER | E100: 4(10) | F100: 10000
A101: 42 | B101: Gideon B. Lamido | D101: Dispatch Clerk | F101: 10000
A102: 43 | B102: Ewelikwa Ijeoma Nkolikwa | D102: Dispatch Clerk | F102: 10000
A103: 44 | B103: Saratu Adamu Attajiri | D103: Office Assistant | F103: 10000
A104: 45 | B104: Saratu H. Gwalem | D104: Receptionist | F104: 10000
A105: 46 | B105: Okechukwu Uchenna Hulda | D105: Admin Assistant | F105: 10000
A106: 47 | B106: Ayuba Sule | D106: Gardener | F106: 10000
B107: TOTAL | F107: =SUM(F60:F106) -> 970000
B108: GRAND TOTAL | F108: =F18+F27+F32+F57+F107 -> 2480000

Sheet MEMO
A1: NATIONAL INSTITUTE FOR LEGISLATIVE STUDIES
A3: INTERNAL MEMO
A5: FROM : DDF
A6: THROUGH: DFA
A7: TO: DG
A8: 2ND MARCH, 2018
A10: Subject: Payroll for the month of February, 2018
A11: Find below the details of NILS Staff Payroll for the month of February, 2018
E13: JANUARY, 2018 | G13: FEBRUARY, 2018
E14: NO OF | F14: AMOUNT | G14: NO OF | H14: AMOUNT
E15: STAFF | F15: N | G15: STAFF | H15: N
A16: 1 | B16: Director General's Office | E16: 20 | F16: =#REF! -> #REF! | G16: 20 | H16: =#REF! -> #REF!
A17: 2 | B17: Legis. Support Services | E17: 12 | F17: =#REF! -> #REF! | G17: 12 | H17: =#REF! -> #REF!
A18: 3 | B18: Legal Services | E18: 2 | F18: =#REF! -> #REF! | G18: 2 | H18: =#REF! -> #REF!
A19: 4 | B19: Democratic Studies | E19: 3 | F19: =#REF! -> #REF! | G19: 3 | H19: =#REF! -> #REF!
A20: 5 | B20: Post Graduate School | E20: 3 | F20: =#REF! -> #REF! | G20: 3 | H20: =#REF! -> #REF!
A21: 6 | B21: Research & Training | E21: 27 | F21: =#REF! -> #REF! | G21: 27 | H21: =#REF! -> #REF!
A22: 7 | B22: Finance/ Admin & HR | E22: 63 | F22: =#REF! -> #REF! | G22: 63 | H22: =#REF! -> #REF!
E23: =SUM(E16:E22) -> 130 | F23: =SUM(F16:F22) -> #REF! | G23: =SUM(G16:G22) -> 130 | H23: =SUM(H16:H22) -> #REF!
A25: VARIATION IN FEBRUARY, 2018 OVER JANUARY, 2018 SALARIES
A27: GROSS SALARY FOR FEBRUARY, 2018 | H27: =#REF! -> #REF!
A28: DEDUCTIONS
A29: COOP SOCIETY DEDUCTIONS | G29: =#REF! -> #REF!
A30: COOP ADVANCE RECOVERY | G30: =#REF! -> #REF!
A31: PAYE DEDUCTIONS | G31: =#REF! -> #REF!
A32: TOTAL DEDUCTIONS FOR FEBRUARY, 2018 | H32: =SUM(G29:G31) -> #REF!
A33: NET PAY AS PER FEBRUARY, 2018 PAYROLL | H33: =H27-H32+1.1 -> #REF!
A34: NET PAY AS PER JANUARY, 2018 PAYROLL | H34: =F23 -> #REF!
A35: NET INCREASE/ (DECREASE) IN PAY FOR FEBRUARY, 2018 | H35: =H33-H34-1.08 -> #REF!
A37: Effect of payment of December Consultancy arears to Sarah Hope Tebira | H37: -50000
A38: Effect of payment of half salary arears to Abdullahi Yunusa for December on suspension resumption | H38: -117100.52
A39: Effect of Payment of 28 days allowance in lieu to new enrolments last in January | H39: -756000
A40: Effect of Correct Salary placement for Ismaheel Driver and December arears | H40: -5000
A41: Effect of Tax adjustments for January 2018 | H41: =-1484.37-236.04-52776.63+7709 -> -46788.04
A42: Effect of enrolment of Owoeye T. Kayode as Confidential Secretary on Payroll | H42: 123329
A43: Effect of enrolment of Aba Amos Terso as Office assistant | H43: 90000
A44: Effect of January arears for Aba Amos Terso | H44: 90000
A45: Effect of Payment of 28 days allowance in lieu to new enrolments | H45: =252000+84000 -> 336000
A46: Effect of enrolment of Daramola Sanjo Samson as Driver on payroll | H46: 42632
A47: Effect of payment of 3 months salary in lie of notice to Blessing Ikanyi on termination | H47: 386459.1
A48: Effect of removal of Dr Hauwa Lamino on resignation | H48: -334201.03
A49: Effect of enrolment of Prof Femi Ajayi DDS on payroll | H49: 900657.46
A50: Effect of Cooperative deductions for February, 2018 | H50: =-340798.04 -> -340798.04
H51: =SUM(H37:H50) -> 319189.93
A53: The Director General is requested to consider and approve payment of N28,676,056.21 to Guaranty Trust Bank being January, 2018 Salary, N4,208,883.00 being NILS Coop Society deductions for January and N912,665.57 being PAYE TAX Deductions from Staff Salary for the month of January, 2018.
A56: Mshelia Madu Ibrahim
A57: Deputy Director, Finance & Accounts

Sheet 17.9
A1: SALARY DETAILS OF NILS DIRECTOR RESEARCH AND TRAINING
A2: GRADE LEVEL 17 STEP 7
D3: ANNUALLY | E3: MONTHLY
A4: Basic Salary | D4: =E4*12 -> 948475.68 | E4: =sUMMARY!F3 -> 79039.64
A5: Rent Subsidy | D5: =E5*12 -> 2845427 | E5: =sUMMARY!H3 -> 237118.92
A6: Utility | D6: =E6*12 -> 71135.676 | E6: =sUMMARY!I3 -> 5927.973
A7: Domestic Staff Allowance | D7: =E7*12 -> 962932.56 | E7: =sUMMARY!J3 -> 80244.38
A8: Entertainment Allowance | D8: =E8*12 -> 474237.84 | E8: =sUMMARY!K3 -> 39519.82
A9: Furniture Allowance | D9: =E9*12 -> 3319664.9 | E9: =sUMMARY!L3 -> 276638.74
A10: Research Allowance | D10: =E10*12 -> 0
A11: Motor Fuel Allowance | D11: =E11*12 -> 948475.68 | E11: =sUMMARY!N3 -> 79039.64
A12: Leave Allowance | D12: =E12*12 -> 94847.568 | E12: =sUMMARY!O3 -> 7903.964
A13: Outfit Allowance | D13: =E13*12 -> 240000 | E13: =sUMMARY!P3 -> 20000
A14: GROSS SALARY | D14: =E14*12 -> 9905196.9 | E14: =SUM(E4:E13) -> 825433.08

Sheet 16.7
A1: SALARY DETAILS OF NILS INSTITUTE LIBRARIAN
A2: GRADE LEVEL 16 STEP 7
D3: ANNUALLY | E3: MONTHLY
A4: Basic Salary | D4: =E4*12 -> #REF! | E4: =#REF! -> #REF!
A5: Rent Subsidy | D5: =E5*12 -> #REF! | E5: =#REF! -> #REF!
A6: Utility | D6: =E6*12 -> #REF! | E6: =#REF! -> #REF!
A7: Domestic Staff Allowance | D7: =E7*12 -> #REF! | E7: =#REF! -> #REF!
A8: Entertainment Allowance | D8: =E8*12 -> #REF! | E8: =#REF! -> #REF!
A9: Furniture Allowance | D9: =E9*12 -> #REF! | E9: =#REF! -> #REF!
A10: Motor Fuel Allowance | D10: =E10*12 -> #REF! | E10: =#REF! -> #REF!
A11: Reasearch Allowance | D11: =E11*12 -> 1200000 | E11: 100000
A12: Leave Allowance | D12: =E12*12 -> #REF! | E12: =#REF! -> #REF!
A13: Outfit Allowance | D13: =E13*12 -> #REF! | E13: =#REF! -> #REF!
A14: GROSS SALARY | D14: =SUM(D4:D13) -> #REF! | E14: =SUM(E4:E13) -> #REF!

Sheet Welfare
B1: CHRISTMAS WELFARE LIST 2017
A2: S/N | B2: NAMES | D2: RANK | E2: SALARY SCALE | F2: AMOUNT
A3: 1 | B3: DR LADI HAMALAI | D3: DIRECTOR GENERAL | E3: CONSOL | F3: 150000
A4: 2 | B4: NWAJEI KANAYO | D4: COMMUNICATION ADVISER | E4: 16(7) | F4: 50000
A5: 3 | B5: NWOSU MATHEW EZE | D5: MANAGER INT. AUDIT | E5: 15(9) | F5: 50000
A6: 4 | B6: AKINSANMI ADEJOKE OLUKEMI | D6: AM INFORMATION | E6: 15(7) | F6: 50000
A7: 5 | B7: MOSHOOD M. OLALERE | D7: NASS DEPLOYED | E7: 15(7) | F7: 50000
A8: 6 | B8: JAMES DAJAN LAMAN | D8: M&E SPECIALIST | E8: 13(7) | F8: 30000
A9: 7 | B9: TOKUNBO ALFRED ADULOJU | D9: AM LIAISON OFFICE | E9: 13(7) | F9: 30000
A10: 8 | B10: JOY HARUNA MAKERI | D10: PA DG | E10: 10(11) | F10: 20000
A11: 9 | B11: DONALD E. MKPANAM | D11: AM ICT | E11: 13(10) | F11: 30000
A12: 10 | B12: ABUBAKAR LAMIDO TANKO | D12: ICT OFFICER | E12: 10(9) | F12: 20000
A13: 11 | B13: BASHIRU ABBA WALI | D13: ASSIT. INT. AUDIT | E13: 10(7) | F13: 20000
A14: 12 | B14: ALI ABDULLAHI | D14: OFFICER ICT | E14: 10(9) | F14: 20000
... A16: 14 | B16: CHRISTIAN MADUABUCHI ODO | D16: ICT OFFICER | E16: 10(7) | F16: 20000
A17: 15 | B17: Adugba Richard Terseer | D17: Nass Deployed | F17: 20000
A18: 16 | B18: Dahiru Abdullahi | D18: Nass Deployed | F18: 20000
A19: 17 | B19: Muhammad Gali T. Bala | D19: Nass Deployed | F19: 20000
A20: 18 | B20: Aminu Abubakar | D20: Nass Deployed | F20: 20000
A21: 19 | B21: Ibrahim Babangishiri | D21: Nass Deployed | F21: 20000
A22: 20 | B22: Abdulmalik Dahiru | D22: Nass Deployed | F22: 20000
C23: TOTAL | D23: 20 | F23: =SUM(F3:F22) -> 680000
B25: LEG. SUPPORT SEVICES
A26: 1 | B26: BETHEL UZOMA IHUGBA | D26: RESEARCH FELLOW I | E26: 14(9) | F26: 30000
A27: 2 | B27: IBRAHIM USMAN | D27: RESEARCH FELLOW II | E27: 13(11) | F27: 30000
A28: 4 | B28: OFORDEME ADAOBI JULIA | D28: RESEARCH OFFICER | E28: 10(11) | F28: 20000
A29: 5 | B29: IKPEAZU CHINEDU ANITA | D29: RESEARCH OFFICER | E29: 10(11) | F29: 20000
A30: 6 | B30: ONYEAKU CHUKWUKA EDMOND | D30: RESEARCH OFFICER | E30: 10(9) | F30: 20000
A31: 7 | B31: DORIS DAKDA AARON | D31: RESEARCH OFFICER | E31: 10(7) | F31: 20000
A32: 8 | B32: NWAFOR ORIZU ONYIYE | D32: RESEARCH OFFICER | E32: 10(7) | F32: 20000
A33: 9 | B33: Jibirin Ushama Ahmed | D33: Nass Deployed | F33: 20000
B34: TOTAL | D34: 9 | F34: =SUM(F26:F33) -> 180000
B36: LEGAL SERVICES
A37: 1 | B37: DR SHUIBU DANWANKA | D37: DIRECTOR LEGAL SERVICES | E37: 17(7) | F37: 100000
A38: 2 | B38: YAHAYA SHAMSU | D38: AM LEGAL | E38: 13(8) | F38: 30000
B39: TOTAL | F39: =SUM(F37:F38) -> 130000
B41: DEMOCRATIC STUDIES
A42: 1 | B42: DR IKEME ARTHUR J.O | D42: SNR RESEARCH FELLOW | E42: 15(7) | F42: 50000
A43: 3 | B43: EJALONIBU GANIYU LAYI | D43: RESEARCH OFFICER | E43: 10(7) | F43: 20000
B44: TOTAL | D44: 2 | F44: =SUM(F42:F43) -> 70000
B46: POST GRADUATE SCHOOL
A47: 1 | B47: DR ASIMIYU G. ABIOLA | D47: DIRECTOR POST GRADUATE | E47: 17(7) | F47: 100000
A48: 2 | B48: DR HAUWA LAMINO ABUBAKAR | D48: ASSISTANT MANAGER, PG | E48: 13(7) | F48: 30000
A49: 3 | B49: Takwasa A. Galadima | D49: Nass Deployed | F49: 20000
B50: TOTAL | F50: =SUM(F47:F49) -> 150000
B52: RESEARCH & TRAINING
A53: 1 | B53: DR ADEYEMI AKEEB FAJINGBESI | D53: DIR. RES. & TRAINING | E53: 17(7) | F53: 100000
A54: 3 | B54: DR OLARENWAJU NIYI JOHN | D54: SABATICAL | E54: 15(7) | F54: 50000
A55: 4 | B55: CATHERINE E. IKOKOH | D55: RESEARCH FELLOW1 DOCU | E55: 15(7) | F55: 50000
A56: 5 | B56: DR CLINTON JAJA | D56: SENIOR RESEARCH FELLOW | E56: 15(7) | F56: 50000
A57: 6 | B57: DR ASEMOTA O. JOSEPH | D57: RESEARCH FELLOW I | E57: 15(7) | F57: 50000
A58: 7 | B58: DR UMAR AMINU | D58: RESEARCH FELLOW I | E58: 14(10) | F58: 30000
A59: 8 | B59: DR YINUSA OLUMUYIWA GANIYU | D59: RESEARCH FELLOW I | E59: 14(7) | F59: 30000
A60: 9 | B60: DR AUGUSTINE C. OSIGWE | D60: RESEARCH FELLOW I | E60: 14(7) | F60: 30000
A61: 10 | B61: DR OLA FALADE | D61: RESEARCH FELLOW I | E61: 14(7) | F61: 30000
A62: 11 | B62: OGUCHE SAMUEL | D62: RESEARCH FELLOW II | E62: 13(10) | F62: 30000
A63: 12 | B63: DR JAKE DABANG DAN AZUMI | D63: SENIOR RESEARCH FELLOW TRAINING | E63: 15(7) | F63: 50000
A64: 13 | B64: TERFA WILLIAMS ABRAHAM | D64: RESEARCH FELLOW I | E64: 14(10) | F64: 30000
... A77: 26 | B77: ANTHONY EDET | D77: OFFICER M&E | E77: 10(9) | F77: 20000
B78: TOTAL | D78: 26 | F78: =SUM(F53:F77) -> 850000
B80: FINANCE & ADMIN.
A81: 1 | B81: DR KABIR AHMED | D81: DIR. FINANCE & ADMIN | E81: 17(9) | F81: 100000
A82: 2 | B82: IBRAHIM M. MSHELIA | D82: DD F&A | E82: 16(9) | F82: 50000
A83: 3 | B83: AMINU BELLO DUKKU | D83: DD ADMIN/HR | E83: 16(9) | F83: 50000
A84: 4 | B84: KABIR MUHAMMAD SULAIMAN | D84: MANAGER ADMIN&HR | E84: 15(9) | F84: 50000
A85: 5 | B85: MAGAJI BALA | D85: MANGER ACCOUNTS | E85: 15(9) | F85: 50000
A86: 6 | B86: ARCH. TIJO ZARA BORYO | D86: MANAGER, ASSETS/MAINT. | E86: 15(7) | F86: 50000
A87: 7 | B87: RAHILA NURUDEEN HABU | D87: ASST. MANAGER, ACCOUNTS | E87: 13(11) | F87: 30000
A88: 8 | B88: ABDULLAHI YUNUSA | D88: PERSONNEL OFFICER | E88: 13(7) | F88: 30000
A89: 9 | B89: MARUF ABDULSALAM | D89: ASSET& MAINT. OFFICER | E89: 13(7) | F89: 30000
A90: 10 | B90: ANDRAWUS MUSA | D90: STORE OFFICER | E90: 13(7) | F90: 30000
A91: 11 | B91: TONDO IORWUESE EDWARD | D91: OFFICER ACCOUNTS | E91: 13(7) | F91: 30000
A92: 12 | B92: OSOLAFIA MUHAMMAD EGYE | D92: PERSONNEL ASSISTANT | E92: 10(7) | F92: 20000
... A124: 44 | B124: ABUBAKAR MUSA DANLAMI | D124: DRIVER | E124: 4(10) | F124: 10000
A125: 45 | B125: Gideon B. Lamido | D125: Dispatch Clerk | F125: 10000
A126: 46 | B126: Ewelikwa Ijeoma Nkolikwa | D126: Dispatch Clerk | F126: 10000
A127: 47 | B127: Saratu Adamu Attajiri | D127: Office Assistant | F127: 10000
A128: 48 | B128: Saratu H. Gwalem | D128: Receptionist | F128: 10000
A129: 49 | B129: Okechukwu Uchenna Hulda | D129: Admin Assistant | F129: 10000
A130: 50 | B130: Aboaman Innocent | D130: Steward | F130: 10000
A131: 51 | B131: ADANHOU V. ALFRED | D131: Steward | F131: 10000
A132: 52 | B132: Kusai E. Richard | D132: Plumber | F132: 10000
A133: 53 | B133: Oluma Joseph Oluma | D133: Steward | F133: 10000
A134: 54 | B134: HARUNA BELLO | D134: GARDENER | F134: 10000
A135: 55 | B135: Salisu Mohammad Adamu | D135: DRIVER | F135: 10000
A136: 56 | B136: Sekyen Sylvanus | D136: Steward | F136: 10000
... A141: 63 | B141: Ayuba Sule | D141: Gardener | F141: 10000
B142: TOTAL | D142: 63 | F142: =SUM(F81:F141) -> 1170000
B143: GRAND TOTAL | F143: =F23+F34+F39+F44+F50+F78+F142 -> 3230000

Sheet Sheet20

Sheet Enhanced Welfare
B1: DIRECTOR GENERAL'S OFFICE
B2: NAMES | D2: RANK | E2: SALARY SCALE | F2: AMOUNT
A3: 1 | B3: DR LADI HAMALAI | D3: DIRECTOR GENERAL | E3: CONSOL | F3: 2000000
A4: 2 | B4: NWAJEI KANAYO | D4: COMMUNICATION ADVISER | E4: 16(7) | F4: 700000
A5: 3 | B5: NWOSU MATHEW EZE | D5: MANAGER INT. AUDIT | E5: 15(9) | F5: 350000
A6: 4 | B6: AKINSANMI ADEJOKE OLUKEMI | D6: AM INFORMATION | E6: 15(7) | F6: 700000
A7: 5 | B7: MOSHOOD M. OLALERE | D7: NASS DEPLOYED | E7: 15(7) | F7: 700000
A8: 7 | B8: TOKUNBO ALFRED ADULOJU | D8: AM LIAISON OFFICE | E8: 13(7) | F8: 500000
C9: TOTAL | D9: 20 | F9: =SUM(F3:F8) -> 4950000
B11: LEG. SUPPORT SEVICES
A12: 1 | B12: BETHEL UZOMA IHUGBA | D12: RESEARCH FELLOW I | E12: 14(9) | F12: 500000
A13: 2 | B13: PROF. MUHAMMED T. LADAN | D13: DLSS | E13: 17(7) | F13: 500000
B14: TOTAL | D14: 9 | F14: =SUM(F12:F13) -> 1000000
B16: LEGAL SERVICES
A17: 1 | B17: DR SHUIBU DANWANKA | D17: DIRECTOR LEGAL SERVICES | E17: 17(7) | F17: 500000
A18: 2 | B18: YAHAYA SHAMSU | D18: AM LEGAL | E18: 13(8) | F18: 500000
B19: TOTAL | D19: 2 | F19: =SUM(F17:F18) -> 1000000
B21: DEMOCRATIC STUDIES
A22: 1 | B22: DR IKEME ARTHUR J.O | D22: SNR RESEARCH FELLOW | E22: 15(7) | F22: 700000
B23: TOTAL | D23: 2 | F23: =SUM(F22:F22) -> 700000
B25: POST GRADUATE SCHOOL
A26: 1 | B26: DR ASIMIYU G. ABIOLA | D26: DIRECTOR POST GRADUATE | E26: 17(7) | F26: 1000000
A27: 2 | B27: DR HAUWA LAMINO ABUBAKAR | D27: ASSISTANT MANAGER, PG | E27: 13(7) | F27: 500000
B28: TOTAL | D28: 3 | F28: =SUM(F26:F27) -> 1500000
B30: RESEARCH & TRAINING
A31: 1 | B31: DR ADEYEMI AKEEB FAJINGBESI | D31: DIR. RES. & TRAINING | E31: 17(7) | F31: 500000
A32: 4 | B32: DR OLARENWAJU NIYI JOHN | D32: SABATICAL | E32: 15(7) | F32: 700000
A33: 5 | B33: CATHERINE E. IKOKOH | D33: RESEARCH FELLOW1 DOCU | E33: 15(7) | F33: 700000
A34: 6 | B34: DR CLINTON JAJA | D34: SENIOR RESEARCH FELLOW | E34: 15(7) | F34: 700000
A35: 7 | B35: DR ASEMOTA O. JOSEPH | D35: RESEARCH FELLOW I | E35: 15(7) | F35: 700000
A36: 9 | B36: DR YINUSA OLUMUYIWA GANIYU | D36: RESEARCH FELLOW I | E36: 14(7) | F36: 500000
A37: 10 | B37: DR AUGUSTINE C. OSIGWE | D37: RESEARCH FELLOW I | E37: 14(7) | F37: 500000
A38: 11 | B38: DR OLA FALADE | D38: RESEARCH FELLOW I | E38: 14(7) | F38: 500000
A39: 13 | B39: DR JAKE DABANG DAN AZUMI | D39: SENIOR RESEARCH FELLOW TRAINING | E39: 15(7) | F39: 700000
A40: 14 | B40: TERFA WILLIAMS ABRAHAM | D40: RESEARCH FELLOW I | E40: 14(10) | F40: 500000
B41: TOTAL | D41: 26 | F41: =SUM(F31:F40) -> 6000000
B43: FINANCE & ADMIN.
A44: 1 | B44: DR KABIR AHMED | D44: DIR. FINANCE & ADMIN | E44: 17(9) | F44: 1000000
A45: 2 | B45: IBRAHIM M. MSHELIA | D45: DD F&A | E45: 16(9) | F45: 350000
A46: 3 | B46: AMINU BELLO DUKKU | D46: DD ADMIN/HR | E46: 16(9) | F46: 350000
A47: 4 | B47: KABIR MUHAMMAD SULAIMAN | D47: MANAGER ADMIN&HR | E47: 15(9) | F47: 700000
A48: 5 | B48: MAGAJI BALA | D48: MANGER ACCOUNTS | E48: 15(9) | F48: 350000
A49: 6 | B49: ARCH. TIJO ZARA BORYO | D49: MANAGER, ASSETS/MAINT. | E49: 15(7) | F49: 700000
A50: 7 | B50: RAHILA NURUDEEN HABU | D50: ASST. MANAGER, ACCOUNTS | E50: 13(11) | F50: 500000
A51: 9 | B51: MARUF ABDULSALAM | D51: ASSET& MAINT. OFFICER | E51: 13(7) | F51: 500000
A52: 10 | B52: ANDRAWUS MUSA | D52: STORE OFFICER | E52: 13(7) | F52: 500000
B53: TOTAL | D53: 63 | F53: =SUM(F44:F52) -> 4950000
B54: GRAND TOTAL | F54: =F9+F14+F19+F23+F28+F41+F53 -> 20100000

Sheet Sheet22

Sheet Sheet23

Sheet Sheet24

Sheet Sheet25

Sheet 15.7.1
A1: SALARY DETAILS OF NILS SENIOR RESEARCH FELLOW
A2: GRADE LEVEL 15 STEP 7
D3: ANNUALLY | E3: MONTHLY
A4: Basic Salary | D4: =E4*12 -> #REF! | E4: =#REF! -> #REF!
A5: Rent Subsidy | D5: =E5*12 -> #REF! | E5: =#REF! -> #REF!
A6: Utility | D6: =E6*12 -> #REF! | E6: =#REF! -> #REF!
A7: Domestic Staff Allowance | D7: =E7*12 -> #REF! | E7: =#REF! -> #REF!
A8: Entertainment Allowance | D8: =E8*12 -> #REF! | E8: =#REF! -> #REF!
A9: Furniture Allowance | D9: =E9*12 -> #REF! | E9: =#REF! -> #REF!
A10: Motor Fuel Allowance | D10: =E10*12 -> #REF! | E10: =#REF! -> #REF!
A11: Research Allowance | D11: =E11*12 -> 0 | E11: 0
A12: Leave Allowance | D12: =E12*12 -> #REF! | E12: =#REF! -> #REF!
A13: Outfit Allowance | D13: =E13*12 -> 240000 | E13: 20000
A14: GROSS SALARY | D14: =E14*12 -> #REF! | E14: =SUM(E4:E13) -> #REF!

Sheet Sheet7

Sheet Sheet8

Sheet Sheet9

Sheet Sheet10

Sheet Sheet11

Sheet Sheet12

Sheet Sheet13

Sheet Sheet14

Sheet Sheet15

Sheet Sheet16

Sheet Sheet17

Sheet Sheet18

Sheet 13.7
A1: SALARY DETAILS OF NILS ASSISTANT MANAGER
A2: GRADE LEVEL 13 STEP 7
D3: ANNUALLY | E3: MONTHLY
A4: Basic Salary | D4: =E4*12 -> #REF! | E4: =#REF! -> #REF!
A5: Rent Subsidy | D5: =E5*12 -> #REF! | E5: =#REF! -> #REF!
A6: Utility | D6: =E6*12 -> #REF! | E6: =#REF! -> #REF!
A7: Domestic Staff Allowance | D7: =E7*12 -> 0 | E7: =sUMMARY!J6 -> 0
A8: Entertainment Allowance | D8: =E8*12 -> #REF! | E8: =#REF! -> #REF!
A9: Furniture Allowance | D9: =E9*12 -> #REF! | E9: =#REF! -> #REF!
A10: Motor Fuel Allowance | D10: =E10*12 -> #REF! | E10: =#REF! -> #REF!
A11: Research Allowance | D11: =E11*12 -> 0 | E11: 0
A12: Leave Allowance | D12: =E12*12 -> #REF! | E12: =#REF! -> #REF!
A13: Outfit Allowance | D13: =E13*12 -> #REF! | E13: =#REF! -> #REF!
A14: GROSS SALARY | D14: =E14*12 -> #REF! | E14: =SUM(E4:E13) -> #REF!

Sheet 12.7
D3: ANNUALLY | E3: MONTHLY
A4: Basic Salary | D4: =E4*12 -> 255527.52 | E4: =sUMMARY!F7 -> 21293.96
A5: Rent Subsidy | D5: =E5*12 -> 766582.56 | E5: =sUMMARY!H7 -> 63881.88
A6: Utility | D6: =E6*12 -> 19164.564 | E6: =sUMMARY!I7 -> 1597.047
A7: Domestic Staff Allowance | D7: =E7*12 -> 0 | E7: =sUMMARY!J6 -> 0
A8: Entertainment Allowance | D8: =E8*12 -> 127763.76 | E8: =sUMMARY!K7 -> 10646.98
A9: Furniture Allowance | D9: =E9*12 -> 894346.32 | E9: =sUMMARY!L7 -> 74528.86
A10: Motor Fuel Allowance | D10: =E10*12 -> 255527.52 | E10: =sUMMARY!N7 -> 21293.96
A11: Leave Allowance | D11: =E11*12 -> 25552.752 | E11: =sUMMARY!O7 -> 2129.396
A12: Outfit Allowance | D12: =E12*12 -> 120000 | E12: =sUMMARY!P7 -> 10000
A13: GROSS SALARY | D13: =E13*12 -> 2464465 | E13: =SUM(E4:E12) -> 205372.08

Sheet 10.7
A1: SALARY DETAILS OF NILS RESEARCH OFFICERS
A2: GRADE LEVEL 10 STEP 7
D3: ANNUALLY | E3: MONTHLY
A4: Basic Salary | D4: =E4*12 -> 207435.96 | E4: =sUMMARY!F8 -> 17286.33
A5: Rent Subsidy | D5: =E5*12 -> 622307.88 | E5: =sUMMARY!H8 -> 51858.99
A6: Utility | D6: =E6*12 -> 15557.697 | E6: =sUMMARY!I8 -> 1296.4748
A7: Domestic Staff Allowance | D7: =E7*12 -> 0 | E7: =sUMMARY!J6 -> 0
A8: Entertainment Allowance | D8: =E8*12 -> 103717.98 | E8: =sUMMARY!K8 -> 8643.165
A9: Furniture Allowance | D9: =E9*12 -> 726025.86 | E9: =sUMMARY!L8 -> 60502.155
A10: Motor Fuel Allowance | D10: =E10*12 -> 207435.96 | E10: =sUMMARY!N8 -> 17286.33
A11: Research Allowance | D11: =E11*12 -> 480000 | E11: 40000
A12: Leave Allowance | D12: =E12*12 -> 20743.596 | E12: =sUMMARY!O8 -> 1728.633
A13: Outfit Allowance | D13: =E13*12 -> 120000 | E13: =sUMMARY!P7 -> 10000
A14: GROSS SALARY | D14: =E14*12 -> 2503224.9 | E14: =SUM(E4:E13) -> 208602.08

Sheet 9.7
A1: SALARY DETAILS OF NILS RESEARCH ASSISTANTS
A2: GRADE LEVEL 9 STEP 7
D3: ANNUALLY | E3: MONTHLY
A4: Basic Salary | D4: =E4*12 -> 176833.68 | E4: =sUMMARY!F9 -> 14736.14
A5: Rent Subsidy | D5: =E5*12 -> 530501.04 | E5: =sUMMARY!H9 -> 44208.42
A6: Utility | D6: =E6*12 -> 13262.526 | E6: =sUMMARY!I9 -> 1105.2105
A7: Domestic Staff Allowance | D7: =E7*12 -> 0 | E7: =sUMMARY!J6 -> 0
A8: Entertainment Allowance | D8: =E8*12 -> 88416.84 | E8: =sUMMARY!K9 -> 7368.07
A9: Furniture Allowance | D9: =E9*12 -> 618917.88 | E9: =sUMMARY!L9 -> 51576.49
A10: Motor Fuel Allowance | D10: =E10*12 -> 176833.68 | E10: =sUMMARY!N9 -> 14736.14
A11: Research Assistants | D11: =E11*12 -> 480000 | E11: 40000
A12: Leave Allowance | D12: =E12*12 -> 17683.368 | E12: =sUMMARY!O9 -> 1473.614
A13: Outfit Allowance | D13: =E13*12 -> 120000 | E13: =sUMMARY!P7 -> 10000
A14: GROSS SALARY | D14: =E14*12 -> 2222449 | E14: =SUM(E4:E13) -> 185204.08

Sheet 8.7
A1: SALARY OF SECRTARY ON SCALE 8 STEP 7
D3: ANNUALLY | E3: MONTHLY
A4: Basic Salary | D4: =E4*12 -> #REF! | E4: =#REF! -> #REF!
A5: Rent Subsidy | D5: =E5*12 -> #REF! | E5: =#REF! -> #REF!
A6: Utility | D6: =E6*12 -> #REF! | E6: =#REF! -> #REF!
A7: Entertainment Allowance | D7: =E7*12 -> #REF! | E7: =#REF! -> #REF!
A8: Furniture Allowance | D8: =E8*12 -> #REF! | E8: =#REF! -> #REF!
A9: Motor Fuel Allowance | D9: =E9*12 -> #REF! | E9: =#REF! -> #REF!
A10: Leave Allowance | D10: =E10*12 -> #REF! | E10: =#REF! -> #REF!
A11: Outfit Allowance | D11: =E11*12 -> #REF! | E11: =#REF! -> #REF!
A12: GROSS SALARY | D12: =E12*12 -> #REF! | E12: =SUM(E4:E11) -> #REF!

Sheet sUMMARY
F1: BASIC | G1: 28 DAYS ALCE | M1: PERSONAL | N1: MOTOR/ | O1: RESEARCH | P1: LEAVE | Q1: OUT FIT | R1: LEGISLATIVE | S1: GROSS | U1: MAR.2012 | V1: FEB. 2012
F2: SALARY | G2: IN LIEU | H2: RENT | I2: UTILITY | J2: DOMESTIC | K2: ENTERT. | L2: FURNIT. | M2: ASSISTANT | N2: FUEL | O2: ALLOWANCE | P2: ALLCE | Q2: ALLCE | R2: DUTY ALLCE | S2: SALARY | T2: PAYE
A3: DIRECTOR | E3: 17/8 | F3: 79039.64 | H3: =F3*300% -> 237118.92 | I3: =F3*7.5% -> 5927.973 | J3: 80244.38 | K3: =F3*50% -> 39519.82 | L3: =F3*350% -> 276638.74 | M3: 0 | N3: =F3*100% -> 79039.64 | O3: =F3*10% -> 7903.964 | P3: 20000 | Q3: 0 | R3: =SUM(F3:Q3) -> 825433.08
A4: DEPUTY DIRECTOR | E4: 16/8 | F4: 36784.71 | H4: =F4*300% -> 110354.13 | I4: =F4*7.5% -> 2758.8532 | J4: 80244.38 | K4: =F4*50% -> 18392.355 | L4: =F4*350% -> 128746.49 | N4: =F4*100% -> 36784.71 | O4: =F4*10% -> 3678.471 | P4: 20000 | Q4: 0 | R4: =SUM(F4:Q4) -> 437744.09
A5: RESEARCH FELLOW I | E5: 14(7) | F5: 24975.81 | G5: 0 | H5: =F5*300% -> 74927.43 | I5: =F5*7.5% -> 1873.1858 | J5: 0 | K5: =F5*50% -> 12487.905 | L5: =F5*350% -> 87415.335 | M5: 0 | N5: =F5*100% -> 24975.81 | O5: 100000 | P5: =F5*10% -> 2497.581 | Q5: 20000 | R5: 0 | S5: =SUM(F5:R5) -> 349153.06 | T5: 0 | U5: =S5-T5 -> 349153.06 | V5: 344720.6
A6: RESEARCH FELLOW II | E6: 13/7 | F6: 23891.12 | H6: =F6*300% -> 71673.36 | I6: =F6*7.5% -> 1791.834 | J6: 0 | K6: =F6*50% -> 11945.56 | L6: =F6*350% -> 83618.92 | M6: 0 | N6: =F6*100% -> 23891.12 | O6: =F6*10% -> 2389.112 | P6: 15000 | Q6: 0 | R6: =SUM(F6:Q6) -> 234201.03
A7: RESEARCH FELLOW | E7: 12/7 | F7: 21293.96 | H7: =F7*300% -> 63881.88 | I7: =F7*7.5% -> 1597.047 | J7: 0 | K7: =F7*50% -> 10646.98 | L7: =F7*350% -> 74528.86 | M7: 0 | N7: =F7*100% -> 21293.96 | O7: =F7*10% -> 2129.396 | P7: 10000 | Q7: 0 | R7: =SUM(F7:Q7) -> 205372.08
A8: RESEARCH OFFICER | E8: 10/7 | F8: 17286.33 | H8: =F8*300% -> 51858.99 | I8: =F8*7.5% -> 1296.4748 | J8: 0 | K8: =F8*50% -> 8643.165 | L8: =F8*350% -> 60502.155 | M8: 0 | N8: =F8*100% -> 17286.33 | O8: =F8*10% -> 1728.633 | P8: 10000 | Q8: 0 | R8: =SUM(F8:Q8) -> 168602.08
A9: RESEARCH ASSISTANTS | E9: 9/7 | F9: 14736.14 | H9: =F9*300% -> 44208.42 | I9: =F9*7.5% -> 1105.2105 | J9: 0 | K9: =F9*50% -> 7368.07 | L9: =F9*350% -> 51576.49 | M9: 0 | N9: =F9*100% -> 14736.14 | O9: =F9*10% -> 1473.614 | P9: 10000 | Q9: 0 | R9: =SUM(F9:Q9) -> 145204.08
E10: 8/7 | F10: 12351.94 | H10: =F10*300% -> 37055.82 | I10: =F10*7.5% -> 926.3955 | J10: 0 | K10: =F10*50% -> 6175.97 | L10: =F10*350% -> 43231.79 | M10: 0 | N10: =F10*100% -> 12351.94 | O10: =F10*10% -> 1235.194 | P10: 10000 | Q10: 0 | R10: =SUM(F10:Q10) -> 123329.05

Sheet 14.7
A1: SALARY DETAILS OF NILS CHIEF LIBRARIAN
A2: GRADE LEVEL 14 STEP 7
D3: ANNUALLY | E3: MONTHLY
A4: Basic Salary | D4: =E4*12 -> 299709.72 | E4: =sUMMARY!F5 -> 24975.81
A5: Rent Subsidy | D5: =E5*12 -> 899129.16 | E5: =sUMMARY!H5 -> 74927.43
A6: Utility | D6: =E6*12 -> 22478.229 | E6: =sUMMARY!I5 -> 1873.1858
A7: Domestic Staff Allowance | D7: =E7*12 -> 0 | E7: =sUMMARY!J6 -> 0
A8: Entertainment Allowance | D8: =E8*12 -> 149854.86 | E8: =sUMMARY!K5 -> 12487.905
A9: Furniture Allowance | D9: =E9*12 -> 1048984 | E9: =sUMMARY!L5 -> 87415.335
A10: Motor Fuel Allowance | D10: =E10*12 -> 299709.72 | E10: =sUMMARY!N5 -> 24975.81
A11: Research Allowance | D11: =E11*12 -> 0 | E11: 0
A12: Leave Allowance | D12: =E12*12 -> 29970.972 | E12: =sUMMARY!P5 -> 2497.581
A13: Outfit Allowance | D13: =E13*12 -> 240000 | E13: =sUMMARY!Q5 -> 20000
A14: GROSS SALARY | D14: =E14*12 -> 2989836.7 | E14: =SUM(E4:E13) -> 249153.06

Sheet Sheet2
A1: LIST OF STAFF THAT HAVE ASSUMED DUTY
A2: STAFF NAME
D3: DESIGNATION | E3: SALARY
E4: LEVEL
A5: DG OFFICE
A6: DR LADI HAMALAI | D6: DG | E6: CONSOL
A7: PROF. OFFORNZE AMUCHEAZI | D7: LEGAL ADVISER | E7: 16(7)
A8: MOHAMMED ISIAKA YAKUBU | D8: SPECIAL ASSISTANT | E8: 16(7)
A9: RICHARD KWALMI | D9: DSM | E9: 15(7)
A10: ABDULSALAM MUSTAFA | D10: ICT OFFICER | E10: 10(10)
A11: ALI ABDULLAHI | D11: 1CT ASSISTANT | E11: 8(2)
A13: LEG. SUPPORT SEVICES
A14: DR SHUIBU DANWANKA | D14: DD | E14: 16(7)
A16: RESEARCH & TRAINING
A17: DR ASIMIYU G. ABIOLA | D17: DD RESEARCH | E17: 16(7)
A18: SOLOMON A. BENJAMIN | D18: DD TRAINING | E18: 16(7)
A19: DR PATTERSON EKEOCHA | D19: SRF | E19: 15(9)
A21: FINANCE & ADMIN.
A22: DR KABIR AHMED | D22: DFA | E22: 17(7)
A23: IBRAHIM M. MSHELIA | D23: DD F&A | E23: 16(7)
A24: AMINU BELLO DUKKU | D24: DD ADMIN/HR | E24: 16(7)
A25: RAHILA AMOS | D25: OFFICER ACCTS | E25: 10(11)
A26: HUSSEIN MUSA AGYE | D26: PROTOCOL OFFICER | E26: 10(&)
A27: USMAN WAZIRI | D27: SEC. FINANCE | E27: 8(9)
A28: SALAMATU YAKUBU | D28: SECRETARY | E28: 8(9)
A29: IDAHOSA JANE CECILIA | D29: SECRETARY | E29: 8/(9)
A30: ESTHER WAMINAJE | D30: SECRETARY | E30: 8(9)
A31: ANTHONY EDET | D31: RECEPTIONIST | E31: 8(2)
A32: OLATUNJI OYEDELE YUSUF | D32: DRIVER | E32: 4(10)
A33: TASIU MOHAMMED | D33: DRIVER | E33: 4(10)
... A41: ABDULLAHI HARUNA | D41: DRIVER | E41: 3(8)
A42: ABDULWAHAB DAHIRU | D42: DISPATCH CLERK
A43: GIDEON B. LAMIDO | D43: DISPATCH CLERK
A44: JOHN JAMBU ASIGAN | D44: STEWARD
A45: AYUBA SULE | D45: STEWARD
A46: EWELIKWA IJEOMA NKOLIKWA | D46: STEWARD

Sheet 15.7
A1: SALARY DETAILS OF NILS LIBRARIAN
A2: GRADE LEVEL 15 STEP 7
B3: ANNUALLY | C3: MONTHLY
A4: Basic Salary | B4: =C4*12 -> 475947 | C4: 39662.25
A5: Rent Subsidy | B5: =C5*12 -> 1427841 | C5: 118986.75
A6: Utility | B6: =C6*12 -> 35696.04 | C6: 2974.67
A7: Domestic Staff Allowance | B7: =C7*12 -> #REF! | C7: =#REF! -> #REF!
A8: Entertainment Allowance | B8: =C8*12 -> 237973.56 | C8: 19831.13
A9: Furniture Allowance | B9: =C9*12 -> 1665814.6 | C9: 138817.88
A10: Motor Fuel Allowance | B10: =C10*12 -> 475947 | C10: 39662.25
A11: Research Allowance | B11: =C11*12 -> 0 | C11: 0
A12: Leave Allowance | B12: =C12*12 -> 47594.76 | C12: 3966.23
A13: Outfit Allowance | B13: =C13*12 -> #REF! | C13: =#REF! -> #REF!
A14: GROSS SALARY | B14: =SUM(B4:B13) -> #REF! | C14: =SUM(C4:C13) -> #REF!

Sheet 5.7
A1: SALARY DETAILS OF NILS SENIOR MOTOR DRIVER-MECHANIC
A2: GRADE LEVEL 5 STEP 7
D3: ANNUALLY | E3: MONTHLY
A4: Basic Salary | D4: =E4*12 -> #REF! | E4: =#REF! -> #REF!
A5: Rent Subsidy | D5: =E5*12 -> #REF! | E5: =#REF! -> #REF!
A6: Utility | D6: =E6*12 -> #REF! | E6: =#REF! -> #REF!
A7: Domestic Staff Allowance | D7: =E7*12 -> 0 | E7: =sUMMARY!J6 -> 0
A8: Entertainment Allowance | D8: =E8*12 -> #REF! | E8: =#REF! -> #REF!
A9: Furniture Allowance | D9: =E9*12 -> #REF! | E9: =#REF! -> #REF!
A10: Motor Fuel Allowance | D10: =E10*12 -> #REF! | E10: =#REF! -> #REF!
A11: Research Allowance | D11: =E11*12 -> 0 | E11: 0
A12: Leave Allowance | D12: =E12*12 -> #REF! | E12: =#REF! -> #REF!
A13: Outfit Allowance | D13: =E13*12 -> #REF! | E13: =#REF! -> #REF!
A14: GROSS SALARY | D14: =E14*12 -> #REF! | E14: =SUM(E4:E13) -> #REF!

Sheet Noninal roll
A2: NOMINAL ROLL AND 2012 PERSONEL COST ESTIMATION
A3: S/NO | B3: DESIGNATION | C3: SALARY LEVEL | D3: NUMBER | E3: ANNUAL SALARY | F3: TOTAL
A5: 1 | B5: DIRECTOR GENERAL | C5: CONS. | D5: 1 | E5: =1580439.5*12 -> 18965274 | F5: =E5*D5 -> 18965274
A6: 2 | B6: DIRECTORS | C6: 17(7) | D6: 4 | E6: 9607889.5 | F6: =E6*D6 -> 38431558
A7: 3 | B7: LEGAL ADVISER | C7: 16(7) | D7: 1 | E7: =424023.33*12 -> 5088280 | F7: =E7*D7 -> 5088280
A8: 4 | B8: SPECIAL ASSISTANT | C8: 16(7) | D8: 2 | E8: =424023.33*12 -> 5088280 | F8: =E8*D8 -> 10176560
A9: 5 | B9: DEUTY DIRECTORS | C9: 16(7) | D9: 10 | E9: 5088280 | F9: =E9*D9 -> 50882800
A10: 6 | B10: SENIOR RESEARCH FELLOWS | C10: 16(7) | D10: 10 | E10: 4136647.2 | F10: =E10*D10 -> 41366472
A11: 7 | B11: MANAGERS | C11: 15(7) | D11: 12 | E11: =344720.6*12 -> 4136647.2 | F11: =E11*D11 -> 49639766
A12: 8 | B12: RESEARCH FELLOW I | C12: 14(7) | D12: 10 | E12: =249153.06*12 -> 2989836.7 | F12: =E12*D12 -> 29898367
A13: 9 | B13: ASSISTANT MANAGERS | C13: 13(7) | D13: 8 | E13: 2810412.4 | F13: =E13*D13 -> 22483299
A14: 10 | B14: OFFICERS | C14: 10(7) | D14: 15 | E14: =168602.08*12 -> 2023225 | F14: =E14*D14 -> 30348374
A15: 11 | B15: OFFICE ASSISTANTS | C15: 8(7) | D15: 20 | E15: =123329.05*12 -> 1479948.6 | F15: =E15*D15 -> 29598972
A16: 12 | B16: SECRETARIES | C16: 8(9) | D16: 15 | E16: =130304.44*12 -> 1563653.3 | F16: =E16*D16 -> 23454799
A17: 13 | B17: DRIVERS | C17: 4(10) | D17: 20 | E17: =46676.06*12 -> 560112.72 | F17: =E17*D17 -> 11202254
D18: =SUM(D9:D17) -> 100 | F18: =SUM(F5:F17) -> 3.6153678e+08

Sheet Welfare List Mgt Staff
A2: STAFF NAME | D2: DESIGNATION | E2: GRADE | F2: AMOUNT | G2: SIGNATURE
F3: 300000
A4: PROF OKECHUKWU OKO | D4: DIR. LEG. SP SERVICES | E4: 17(7) | F4: 150000
A5: DR BADAYI M. SANI | D5: DIR. RES. & TRAINING | E5: 17(7) | F5: 150000
A6: DR KABIR AHMED | D6: DIR. FINANCE & ADMIN | E6: 17(7) | F6: 150000
A7: PROF. OFFORNZE AMUCHEAZI | D7: LEGAL ADVISER | E7: 16(7) | F7: 100000
A8: MOHAMMED ISIAKA YAKUBU | D8: HEAD PUBLICATION | E8: 16(7) | F8: 100000
A9: DR MOBOLAJI HAKEEM | D9: SPECIAL ASSISTANT | E9: 16(7) | F9: 100000
A10: DR SHUIBU DANWANKA | D10: DD LEG. SP SERVICES | E10: 16(7) | F10: 100000
A11: DR ASIMIYU G. ABIOLA | D11: DD RESEARCH | E11: 16(7) | F11: 100000
A12: IBRAHIM M. MSHELIA | D12: DD F&A | E12: 16(7) | F12: 100000
A13: AMINU BELLO DUKKU | D13: DD ADMIN/HR | E13: 16(7) | F13: 100000
A14: RICHARD KWALMI | D14: MICT | E14: 15(7) | F14: 80000
A15: ADAMU ISA ABBA | D15: INFO. MANAGER | E15: 15(7) | F15: 80000
... A22: EDET B. AKPAKPAN | D22: SABATICAL | E22: Sab. | F22: 80000
A23: TOTAL | F23: =SUM(F3:F22) -> 2170000

Sheet Welfare Support Staff
A1: S/N | B1: NAMES | E1: DESIGNATION | F1: GRADE | G1: AMOUNT | H1: SIGNATURE
A2: 1 | B2: AKINSANMI ADEJOKE OLUKEMI | E2: AM INFORMATION | F2: 13(7) | G2: 20000
A3: 2 | B3: FAROUK U. M ILLO | E3: PA DG | F3: 13(7) | G3: 20000
A4: 3 | B4: UMOLU ADAEZE OBIAMAKA | E4: INFO OFFICER | F4: 10(7) | G4: 20000
A5: 4 | B5: TONDO IORWUESE EDWARD | E5: OFFICER INT AUDIT | F5: 10(7) | G5: 20000
A6: 5 | B6: BEDARI HARI | E6: LEGAL OFFICER | F6: 10(7) | G6: 20000
A7: 6 | B7: NGARA CHRISTOPHER OCHANJA | C7: NGARA CHRISTOPHER OCHANJA | E7: OFFICER, SPECIAL DUTIES | F7: 10(7) | G7: 20000
A8: 7 | B8: JOY HARUNA MAKERI | E8: PA DG | F8: 10(7) | G8: 20000
A9: 8 | B9: BASHIRU ABBA WALI | E9: ASSIT. INT. AUDIT | F9: 8(7) | G9: 20000
A10: 9 | B10: ALI ABDULLAHI | E10: 1CT ASSISTANT | F10: 8(7) | G10: 20000
A11: 10 | B11: UZODINMA EMMANUEL EZENWA | E11: INFORMATION ASST | F11: 8(7) | G11: 20000
A12: 11 | B12: IBRAHIM TASSNEEM | E12: INFORMATION ASST | F12: 8(7) | G12: 20000
A13: 12 | B13: GLORIA NDIDI HELG | E13: CONFIDENTIAL SECRETARY | F13: 8(7) | G13: 20000
A14: 13 | B14: CHRISTIAN MADUABUCHI ODO | E14: ICT ASSISTANT | F14: 8(7) | G14: 20000
A15: 14 | B15: IBRAHIM USMAN | E15: RESEARCH FELLOW II | F15: 13(7) | G15: 20000
A16: 15 | B16: OFORDEME ADAOBI JULIA | E16: RESEARCH OFFICER | F16: 10(7) | G16: 20000
A17: 16 | B17: IKPEAZU CHINEDU ANITA | E17: RESEARCH OFFICER | F17: 10(7) | G17: 20000
A18: 17 | B18: ONYEAKU CHUKWUKA EDMOND | E18: RESEARCH ASSISTANT | F18: 9(7) | G18: 20000
A19: 18 | B19: DR ANUMUDU CHARLES NNAMDI | E19: SRF I SOCIAL SECTOR | F19: 14(7) | G19: 20000
... A77: 76 | B77: AYUBA SULE | E77: STEWARD | F77: - | G77: 10000
A78: 77 | B78: EWELIKWA IJEOMA NKOLIKWA | E78: DISPATCH CLERK | F78: 0 | G78: 10000
A79: 78 | B79: JUMMAI AJIYA | E79: STEWARD | F79: 0 | G79: 10000
A80: 79 | B80: HUSSAIN HAZEEM MOHAMMED | E80: DISPATCH CLERK | F80: - | G80: 10000
A81: 80 | B81: ABOMAN INNOCENT | E81: CLEANER | G81: 10000
A82: 81 | B82: AKEUSOLA SEGUN | E82: CLEANER | G82: 10000
A83: 82 | B83: EDACHE OGA | E83: DRIVER | G83: 10000
A84: 83 | B84: ONCHE ENOKELA ONCHE | E84: STEWARD | G84: 10000
G85: =SUM(G2:G84) -> 1390000

Sheet Welfare Deployed Staff
A1: EID EL KABIR TRANSPORT ALLOWANCE TO NILS DEPLOYED STAFF
A2: S/N | C2: DESIGNATION | D2: GRADE | E2: AMOUNT | F2: SIGNATURE
A3: 1 | B3: ARC OJO M.O | C3: DD & HEAD OF BUILDING | D3: 16(7) | E3: 100000
A4: 2 | B4: AMINCI THOMAS | C4: MANAGER LIB. & DOCUM. | D4: 15(7) | E4: 80000
A5: 3 | B5: AMINU F. HAMAJODA | C5: MANAGER INFORMATION | D5: 15(7) | E5: 80000
A6: 4 | B6: DAHIRU M. ABDULLAHI | C6: PROTOCOL OFFICER | D6: 10(7) | E6: 20000
A7: 5 | B7: MOSHOOD M. OLARELE | C7: ADMIN OFFICER | D7: 10(7) | E7: 20000
A8: 6 | B8: IBRAHIM A. BABANGISHIRI | C8: OFFICER INFORMATION | D8: 10(7) | E8: 20000
A9: 7 | B9: JIBRIN USHAMA AHMED | C9: OFFICER LEGAL | D9: 10(7) | E9: 20000
A10: 8 | B10: ENGR. EBI THOMPSON | C10: ASSISTANT CHIEF ENGINEER | D10: 13(7) | E10: 20000
A11: 9 | B11: ADEOGUN MORUF | C11: PRINCIPAL Q.S | D11: 10(7) | E11: 20000
B12: TOTAL | E12: =SUM(E3:E11) -> 380000

Sheet Sheet1
B1: 2013 END OF YEAR STAFF WELFARE TO ASSIST WITH TRANSPORTATION AND LOGISTICS.
E3: DESIGNATION | F3: SALARY | G3: BASIC
F4: LEVEL | G4: SALARY
B5: DG OFFICE | G5: N
A6: 1 | B6: DR LADI HAMALAI | E6: DIRECTOR GENERAL | F6: CONSOL | G6: 400000
A7: 2 | B7: PROF. OFFORNZE AMUCHEAZI | E7: LEGAL ADVISER | F7: 16(7) | G7: 200000
A8: 3 | B8: MOHAMMED ISIAKA YAKUBU | E8: HEAD PUBLICATION | F8: 16(7) | G8: 200000
A9: 4 | B9: DR MOBOLAJI HAKEEM | E9: SPECIAL ASSISTANT | F9: 16(70 | G9: 200000
A10: 5 | B10: RICHARD KWALMI | E10: MICT | F10: 15(7) | G10: 100000
A11: 6 | B11: ADAMU ISA ABBA | E11: INFO. MANAGER | F11: 15(7) | G11: 100000
A12: 7 | B12: NWOSU MATHEW EZE | E12: MANAGER INT. AUDIT | F12: 15(7) | G12: 100000
A13: 8 | B13: PRISCILLA CHUKWU | E13: MANAGER PROCUREMENT | F13: 15(7) | G13: 100000
A14: 9 | B14: DR ANAH O. PAMELA | E14: SRF | F14: 15((7) | G14: 100000
A15: 10 | B15: AKINSANMI ADEJOKE OLUKEMI | E15: AM INFORMATION | F15: 13(7) | G15: 80000
A16: 11 | B16: FAROUK U. M ILLO | E16: PA DG | F16: 13(7) | G16: 80000
A17: 12 | B17: UMOLU ADAEZE OBIAMAKA | E17: INFO OFFICER | F17: 10(7) | G17: 50000
... A19: 14 | B19: BEDARI HARI | E19: LEGAL OFFICER | F19: 10(7) | G19: 50000
A20: 15 | B20: NGARA CHRISTOPHER OCHANJA | C20: NGARA CHRISTOPHER OCHANJA | E20: OFFICER, SPECIAL DUTIES | F20: 10(7) | G20: 50000
A21: 16 | B21: JOY HARUNA MAKERI | C21: JOY HARUNA MAKERI | E21: PA DG | F21: 10(7) | G21: 50000
A22: 17 | B22: DONALD E. MKPANAM | E22: IT OFFICER | F22: 10(7) | G22: 50000
A23: 18 | B23: BASHIRU ABBA WALI | E23: ASSIT. INT. AUDIT | F23: 8(7) | G23: 50000
A24: 19 | B24: ALI ABDULLAHI | E24: 1CT ASSISTANT | F24: 8(7) | G24: 50000
A25: 20 | B25: UZODINMA EMMANUEL EZENWA | E25: INFORMATION ASST | F25: 8(7) | G25: 50000
A26: 21 | B26: IBRAHIM TASSNEEM | E26: INFORMATION ASST | F26: 8(7) | G26: 50000
A27: 22 | B27: GLORIA NDIDI HELG | E27: CONFIDENTIAL SECRETARY | F27: 8(7) | G27: 50000
A28: 23 | B28: CHRISTIAN MADUABUCHI ODO | E28: ICT ASSISTANT | F28: 8(7) | G28: 50000
B29: TOTAL | E29: 23 | G29: =SUM(G6:G28) -> 2260000
B30: LEG. SUPPORT SEVICES
A31: 1 | B31: PROF OKECHUKWU OKO | E31: DIR. LEG. SP SERVICES | F31: 17(7) | G31: 300000
A32: 2 | B32: DR SHUIBU DANWANKA | E32: DD LEG. SP SERVICES | F32: 16(7) | G32: 200000
A33: 3 | B33: IBRAHIM USMAN | E33: RESEARCH FELLOW II | F33: 13(7) | G33: 80000
A34: 4 | B34: OFORDEME ADAOBI JULIA | E34: RESEARCH OFFICER | F34: 10(7) | G34: 50000
A35: 5 | B35: IKPEAZU CHINEDU ANITA | C35: IKPEAZU CHINEDU ANITA | E35: RESEARCH OFFICER | F35: 10(7) | G35: 50000
A36: 6 | B36: ONYEAKU CHUKWUKA EDMOND | E36: RESEARCH ASSISTANT | F36: 9(7) | G36: 50000
B37: TOTAL | E37: 6 | G37: =SUM(G31:G36) -> 730000
A39: 1 | B39: DR BADAYI M. SANI | E39: DIR. RES. & TRAINING | F39: 17(7) | G39: 300000
A40: 2 | B40: DR ASIMIYU G. ABIOLA | E40: DD RESEARCH | F40: 16(7) | G40: 200000
A41: 3 | B41: DR KANAYO OGUJIUBA | E41: SRF SOCIAL SECTOR | F41: 15(9) | G41: 100000
A42: 4 | B42: DR ANUMUDU CHARLES NNAMDI | E42: SRF I SOCIAL SECTOR | F42: 14(7) | G42: 80000
A43: 5 | B43: CATHERINE E. IKOKOH | E43: RESEARCH FELLOW1 DOCU | F43: 14(7) | G43: 80000
A44: 6 | B44: CHIEDO AKALEU | E44: RESEARCH FELLOW II | F44: 13(7) | G44: 80000
A45: 7 | B45: DR UMAR AMINU | E45: RESEARCH FELLOW II | F45: 13(7) | G45: 80000
A46: 8 | B46: DR JAKE DABANG DAN AZUMI | E46: RESEARCH FELLOW II | F46: 13(7) | G46: 80000
A47: 9 | B47: HARRISON O. OKAFOR | E47: RESEARCH FELLOW II | F47: 13(7) | G47: 80000
A48: 10 | B48: ABDULSALAM MUSTAFA | E48: ICT OFFICER | F48: 10(10) | G48: 50000
A49: 11 | B49: ALIYU SANNI ABUBAKAR | C49: ALIYU SANNI ABUBAKAR | E49: DATA & DOCU. OFFICER | F49: 10(7) | G49: 50000
A50: 12 | B50: JUMARE FADILA | E50: RESEARCH OFFICER | F50: 10(7) | G50: 50000
A51: 13 | B51: CHINAKO N. ASOGWA | E51: LIBRARY OFFICER | F51: 10(7) | G51: 50000
A52: 14 | B52: EHIGIAMUSOE UYI KIZITO | E52: RESEARCH ASSISTANT | F52: 9(7) | G52: 50000
A53: 15 | B53: UDEFUNA NNADOZIE PATRICK | E53: RESEARCH ASSISTANT | F53: 9(7) | G53: 50000
A54: 16 | B54: OGBONNAYA UFIEM MAURICE | E54: RESEARCH ASSISTANT | F54: 9(7) | G54: 50000
A55: 17 | B55: CHARLES I. OBUTTE | E55: RESEARCH ASSISTANT | F55: 9(7) | G55: 50000
B56: TOTAL | E56: 17 | G56: =SUM(G39:G55) -> 1480000
A58: 1 | B58: DR KABIR AHMED | E58: DIR. FINANCE & ADMIN | F58: 17(7) | G58: 300000
A59: 2 | B59: IBRAHIM M. MSHELIA | E59: DD F&A | F59: 16(7) | G59: 200000
A60: 3 | B60: AMINU BELLO DUKKU | E60: DD ADMIN/HR | F60: 16(7) | G60: 200000
A61: 4 | B61: KABIR MUHAMMAD SULAIMAN | E61: MANAGER ADMIN&HR | F61: 15(7) | G61: 100000
A62: 5 | B62: MAGAJI BALA | E62: MANGER ACCOUNTS | F62: 15(7) | G62: 100000
A63: 6 | B63: RAHILA AMOS | E63: OFFICER ACCTS | F63: 10(11) | G63: 50000
A64: 7 | B64: HUSSEIN MUSA AGYE | E64: PROTOCOL OFFICER | F64: 10(7) | G64: 50000
A65: 8 | B65: ABDULLAHI YUNUSA | E65: PERSONNEL OFFICER | F65: 10(7) | G65: 50000
A66: 9 | B66: PATIENCE AMUDA BOSAH | E66: PERSONNEL OFFICER | F66: 10(7) | G66: 50000
A67: 10 | B67: MARUF ABDULSALAM | E67: ASSET& MAINT. OFFICER | F67: 10(7) | G67: 50000
A68: 11 | B68: SALIHU LIMAN MAIRAFI | E68: PROCUREMENT OFFICER | F68: 10(7) | G68: 50000
A69: 12 | B69: ANDRAWUS MUSA | E69: STORE OFFICER | F69: 10(7) | G69: 50000
... A100: 43 | B100: MURTALA LAWAL | E100: DRIVER | F100: 4(7) | G100: 20000
A101: 44 | B101: YUGUDA S. IDRIS | C101: YUGUDA S. IDRIS | E101: DRIVER | F101: 4(7) | G101: 20000
B102: TOTAL | E102: 44 | G102: =SUM(G58:G101) -> 2370000
A104: 1 | B104: ABDULWAHAB DAHIRU | E104: DISPATCH CLERK | F104: - | G104: 20000
A105: 2 | B105: GIDEON B. LAMIDO | E105: DISPATCH CLERK | F105: - | G105: 20000
A106: 3 | B106: JOHN JAMBU ASIGAN | E106: STEWARD | F106: - | G106: 20000
A107: 4 | B107: AYUBA SULE | E107: STEWARD | F107: - | G107: 20000
A108: 5 | B108: EWELIKWA IJEOMA NKOLIKWA | E108: DISPATCH CLERK | F108: 0 | G108: 20000
A109: 6 | B109: JUMMAI AJIYA | E109: STEWARD | F109: 0 | G109: 20000
A110: 7 | B110: HUSSAIN HAZEEM MOHAMMED | E110: DISPATCH CLERK | F110: - | G110: 20000
A111: 8 | B111: ABOMAN INNOCENT | E111: CLEANER | G111: 20000
A112: 9 | B112: AKEUSOLA SEGUN | E112: CLEANER | G112: 20000
A113: 10 | B113: EDACHE OGA | E113: DRIVER | G113: 20000
A114: 11 | B114: ONCHE ENOKELA ONCHE | C114: ONCHE ENOKELA ONCHE | E114: STEWARD | G114: 20000
A115: 12 | B115: OKOYE AUGUSTINA CHINENYE | C115: OKOYE AUGUSTINA CHINENYE | E115: NYSC | G115: 20000
A116: 13 | B116: UKPONG INYANG ONOYOM | C116: UKPONG INYANG ONOYOM | E116: NYSC | G116: 20000
A117: 14 | B117: AMARACHI NNAWUCHI | E117: NYSC | G117: 20000
B118: TOTAL | E118: 14 | G118: =SUM(G104:G117) -> 280000
A120: 1 | B120: EDET B. AKPAKPAN | C120: PROF. EDET AKPAKPAN | E120: SABATICAL | G120: 50000
A121: 2 | B121: TERFA W. ABRAHAM | E121: RESEARCH OFFICER | F121: 10(7) | G121: 50000
A122: 3 | B122: DAHIRU M. ABDULLAHI | E122: PROTOCOL OFFICER | F122: 10(7) | G122: 50000
A123: 4 | B123: MOSHOOD M. OLARELE | E123: ADMIN OFFICER | F123: 10(7) | G123: 50000
A124: 5 | B124: AMINCI THOMAS | E124: MANAGER LIB. & DOCUM. | F124: 15(7) | G124: 50000
A125: 6 | B125: AMINU F. HAMAJODA | E125: MANAGER INFORMATION | F125: 15(7) | G125: 50000
A126: 7 | B126: IBRAHIM A. BABANGISHIRI | E126: OFFICER INFORMATION | F126: 10(7) | G126: 50000
A127: 8 | B127: JIBRIN USHAMA AHMED | E127: OFFICER LEGAL | F127: 10(7) | G127: 50000
A128: 9 | B128: ARC OJO M.O | E128: DD & HEAD OF BUILDING | F128: 16(7) | G128: 50000
A129: 10 | B129: ENGR. EBI THOMPSON | E129: ASSISTANT CHIEF ENGINEER | F129: 13(7) | G129: 50000
A130: 11 | B130: IBRAHIM OKPE | E130: AM PROTOCOL | F130: 13(7) | G130: 50000
A131: 12 | B131: ADEOGUN MORUF | E131: PRINCIPAL Q.S | F131: 10(7) | G131: 50000
B132: TOTAL | E132: 12 | G132: =SUM(G120:G131) -> 600000
B133: GRAND TOTAL | G133: =G29+G37+G56+G102+G118 -> 7120000

Sheet Sheet3
A2: New Additions
A3: Maryam Muhammed Bello | B3: PA Special Duties | C3: 30 Days
A4: Shiru Bukola Hauwa | B4: Admin. Assistant | C4: 10 Days
A5: Sulaiman A Abdurahman | B5: Assistant Store Officer | C5: 18 Days
A6: Dare Sheu Magbon | B6: Administrative Assistant | C6: 18 Days
A7: Mr. Nandi Livinus Ature | B7: Research Assistant | C7: 2 months (July & Aug 2019)
A8: Lucky Agwom | B8: Research Assistant | C8: 47 Days
A9: Mohammed Bello | B9: Research Assistant | C9: 18 Days
A10: Yahaya Adamu Abdulhamid | B10: NYSC
A11: Adakuyi Ede Samson | B11: NYSC
A12: Bakari Zainab | B12: NYSC
A13: Ezenwajiobi Chidinma Charity | B13: NYSC
A14: Stephen Samuel | B14: NYSC
A15: Oke Eniola Oluwabukunmi | B15: NYSC
A16: Oban Obianuju Sandra | B16: NYSC
A18: Removals
A19: Uchenna Hulda Okechukwu
A20: Juwairatu Isha Abdulsalam
A21: Gideon Babor Lamidp
A22: Gwalem Saratu
A23: Hauwa Pate Sadiq

Sheet Sheet21

Sheet JUNE 2023 (2)
A1: CONTRACT/SABBATICAL AND CONSULTANT SALARY FOR THE MONTH OF JUNE 2023
A3: S/N | B3: STAFF NAME | C3: DESIGNATION
A5: 1 | B5: Dr. Mohammed Etudaiye | C5: Consultant
A6: 2 | B6: Takwasa A. Galadima | C6: Nass Deployed
A7: 3 | B7: Saratu Adamu Attajiri | C7: Office Assistant
A8: 4 | B8: Aboaman Innocent | C8: Casual
A9: 5 | B9: Kusai E. Richard | C9: Plumber
A10: 6 | B10: Bulus Ishaya | C10: Gardener
A11: 7 | B11: Alhamdu Iliya | C11: Casual-Gardner
A12: 8 | B12: Salihu Hassan | C12: Casual-Gardner
A13: 9 | B13: Ishaya Moro James | C13: Gardener
A14: 10 | B14: Barr. James G Bathna | C14: Sabbatical
A15: 11 | B15: Dr. John Niyi Olanrewaju | C15: Consultancy
A16: 12 | B16: Dr. Shehu Wahab L | C16: Consultant
... A65: 61 | B65: Akinboboye Oluwatosin Ifedayo | C65: NYSC
E147: =60000 -> 60000
