Workbook

Sheet FEBRUARY 2024
A1: NATIONAL INSTITUTE FOR LEGISLATIVE AND DEMOCRATIC STUDIES
A2: STAFF PAYROLL FOR THE MONTH OF FEBRUARY, 2024
E3: ='[1]FEB 08'!E11/'[1]FEB 08'!M11 -> #REF!
B4: STAFF NAME | C4: DESIGNATION | D4: GRADE LEVEL | E4: BASIC SALARY | F4: ALLCE/ AREARS | G4: ALLOWANCE | H4: ALLOWANCE | I4: DUTY ALLCE | J4: GROSS SALARY | K4: AUCTION | L4: COOP CONTR/SPEC SAVINGS | M4: COOP. LOAN RECOVERY | N4: NHF DED. | O4: PAYE | P4: EMPLOYEE PENSIONS | Q4: TOTAL DEDUCTION | R4: JANUARY, 2023 | S4: FEBRUARY, 2024
E5: N | G5: N | H5: N | I5: N | J5: N | K5: N | L5: N | M5: N | N5: N | O5: N | P5: N | Q5: N | R5: N | S5: N
A6: S/N | B6: DG'S OFFICE
A7: 1 | B7: PROF. ABUBAKAR O. SULAIMAN | C7: DIRECTOR GENERAL | D7: CONSOL | E7: 1659751.2 | F7: 627118.15 | G7: =250000 -> 250000 | I7: 25235 | J7: =E7+F7+G7+H7+I7 -> 2562104.3 | O7: 350184.01 | Q7: =O7+N7+M7+L7+K7+P7 -> 350184.01 | R7: 957684 | S7: =J7-Q7 -> 2211920.3
A8: 2 | B8: RAHEEM USMAN AYIGORO | C8: SA-INFRASTRUCTURE | D8: 16 (9) | E8: 762373.17 | F8: 262923.83 | H8: =90000 -> 90000 | I8: 0 | J8: =E8+F8+G8+H8+I8 -> 1115297 | L8: =100000 -> 100000 | O8: 130612.26 | P8: 60989.853 | Q8: =O8+N8+M8+L8+K8+P8 -> 291602.12 | R8: 358837.07 | S8: =J8-Q8 -> 823694.88
A9: 3 | B9: MARIAM MOHAMMED BELLO | C9: SA- SPECIAL DUTIES | D9: 16 (9) | E9: 762373.17 | F9: 251213.78 | H9: =90000 -> 90000 | I9: =100000+100000 -> 200000 | J9: =E9+F9+G9+H9+I9 -> 1303586.9 | O9: 180722.31 | Q9: =O9+N9+M9+L9+K9+P9 -> 180722.31 | R9: 620437.07 | S9: =J9-Q9 -> 1122864.6
A10: 4 | B10: DR IKEME ARTHUR J.O | C10: DEPUTY DIRECTOR, M&E | D10: 16 (9) | E10: 762373.17 | F10: 262923.83 | G10: 180000 | I10: 0 | J10: =E10+F10+G10+H10+I10 -> 1205297 | L10: =50000 -> 50000 | M10: 103000 | N10: 1066.3293 | O10: 147687.53 | P10: 60989.853 | Q10: =O10+N10+M10+L10+K10+P10 -> 362743.71 | R10: 377695.48 | S10: =J10-Q10 -> 842553.29
A11: 5 | B11: MOSHOOD M. OLALERE | C11: DEPUTY DIR. GENERAL SERVICE | D11: 16 (9) | E11: 762373.17 | F11: 262923.83 | H11: =80000+10000 -> 90000 | I11: 150000 | J11: =E11+F11+G11+H11+I11 -> 1265297 | L11: =20000+60000 -> 80000 | M11: ='[2]OCTOBER 2023 '!$D$193 -> 230499.8 | N11: 1066.3293 | O11: 159207.53 | P11: 60989.853 | Q11: =O11+N11+M11+L11+K11+P11 -> 531763.51 | R11: 268675.68 | S11: =J11-Q11 -> 733533.49
A12: 6 | B12: REKIYA IBRAHIM ATTAH | C12: DEPUTY DIRECTOR TRAINING | D12: 16 (9) | E12: 762373.17 | F12: 251213.78 | H12: =90000 -> 90000 | I12: 100000 | J12: =E12+F12+G12+H12+I12 -> 1203586.9 | L12: =50000 -> 50000 | M12: =91666.67 -> 91666.67 | O12: 161522.31 | Q12: =O12+N12+M12+L12+K12+P12 -> 303188.98 | R12: 397970.4 | S12: =J12-Q12 -> 900397.96
A13: 7 | B13: ANDRAWUS MUSA | C13: ASST. DIRECTOR, STORES | D13: 15(9) | E13: 620675.58 | F13: 214056.22 | H13: =80000 -> 80000 | I13: 50000 | J13: =E13+F13+G13+H13+I13 -> 964731.8 | L13: =50000-40000 -> 10000 | M13: =90000+110000 -> 200000 | N13: 837.6875 | O13: 113101.97 | P13: 49654.047 | Q13: =O13+N13+M13+L13+K13+P13 -> 373593.7 | R13: 212679.71 | S13: =J13-Q13 -> 591138.1
A14: 8 | B14: DR FRANCIS NDUM OJIE | C14: AD, TRAINING & IC./SA TO DG | D14: 15(7) | E14: 582118.08 | F14: 200751.53 | G14: 160000 | I14: =100000 -> 100000 | J14: =E14+F14+G14+H14+I14 -> 1042869.6 | N14: 775.496 | O14: 131263.11 | P14: 46569.447 | Q14: =O14+N14+M14+L14+K14+P14 -> 178608.05 | R14: 509327.94 | S14: =J14-Q14 -> 864261.56
A15: 9 | B15: ALI ABDULLAHI | C15: CHIEF ICT OFFICER | D15: 14(11) | E15: 484373.75 | F15: 178220.89 | H15: =70000 -> 70000 | I15: =0 -> 0 | J15: =E15+F15+G15+H15+I15 -> 732594.64 | O15: 77666.446 | P15: 38749.9 | Q15: =O15+N15+M15+L15+K15+P15 -> 116416.35 | R15: 298486.42 | S15: =J15-Q15 -> 616178.29
A16: 10 | B16: EMILY EKHIDE | C16: RESEARCH FELLOW 1 | D16: 14(10) | E16: 470498 | F16: 166536.14 | G16: 140000 | I16: 50000 | J16: =E16+F16+G16+H16+I16 -> 827034.14 | L16: =50000 -> 50000 | O16: 98255.433 | P16: 37639.84 | Q16: =O16+N16+M16+L16+K16+P16 -> 185895.27 | R16: 366666.37 | S16: =J16-Q16 -> 641138.87
A17: 11 | B17: DORIS DAKDA AARON | C17: RESEARCH FELLOW I | D17: 14(8) | E17: 442746.5 | F17: 156712.97 | G17: =140000 -> 140000 | I17: 150000 | J17: =E17+F17+G17+H17+I17 -> 889459.47 | L17: 70000 | O17: 112553.41 | P17: 35419.72 | Q17: =O17+N17+M17+L17+K17+P17 -> 217973.13 | R17: 430544.7 | S17: =J17-Q17 -> 671486.34
A18: 12 | B18: ABDULSALAM S. MUSTAPHA | C18: ASST. MANAGER ICT | D18: 13(11) | E18: 441804.92 | F18: 157040.82 | H18: 70000 | J18: =E18+F18+G18+H18+I18 -> 668845.73 | O18: 70147.087 | P18: 35344.393 | Q18: =O18+N18+M18+L18+K18+P18 -> 105491.48 | R18: 284617.02 | S18: =J18-Q18 -> 563354.25
A19: 13 | B19: PERCY TERFA GBAHABO | C19: HEAD, NILDS LIAISON OFFICE | D19: 13(10) | E19: 428915.92 | F19: 151816.66 | G19: =120000 -> 120000 | I19: 0 | J19: =E19+F19+G19+H19+I19 -> 700732.58 | L19: =50000 -> 50000 | M19: 0 | O19: 77470.374 | P19: 34313.273 | Q19: =O19+N19+M19+L19+K19+P19 -> 161783.65 | R19: 272510.99 | S19: =J19-Q19 -> 538948.93
A20: 14 | B20: HASSANA AHMED IBRAHIM | C20: PA- TO DG | D20: 13 (9) | E20: 416026.92 | F20: 147121.82 | G20: =120000 -> 120000 | I20: =100000 -> 100000 | J20: =E20+F20+G20+H20+I20 -> 783148.74 | L20: =30000-20000 -> 10000 | M20: =95833.33 -> 95833.33 | N20: 618.5315 | O20: 94274.903 | P20: 33282.153 | Q20: =O20+N20+M20+L20+K20+P20 -> 234008.92 | R20: 308882.53 | S20: =J20-Q20 -> 549139.82
A21: 15 | B21: ADUGBA RICHARD TERSEER | C21: PRINCIPAL INFO. OFFICER | D21: 12(9) | E21: 377895.17 | F21: 129717.87 | H21: =60000 -> 60000 | I21: 100000 | J21: =E21+F21+G21+H21+I21 -> 667613.04 | L21: =20000 -> 20000 | M21: =111833.33 -> 111833.33 | O21: 76138.069 | P21: 30231.613 | Q21: =O21+N21+M21+L21+K21+P21 -> 238203.01 | R21: 200205.9 | S21: =J21-Q21 -> 429410.02
A22: 16 | B22: LUCKY AGWOM | C22: RESEARCH ASSISTANT | D22: 12(7) | E22: 353512.5 | F22: 129167.42 | G22: =100000 -> 100000 | I22: 100000 | J22: =E22+F22+G22+H22+I22 -> 682679.92 | L22: 50000 | O22: 79511.115 | P22: 28281 | Q22: =O22+N22+M22+L22+K22+P22 -> 157792.11 | R22: 301705.41 | S22: =J22-Q22 -> 524887.8
A23: 17 | B23: IDRIS IBRAHIM | C23: PRINCIPAL RESEARCH OFFICER | D23: 12(7) | E23: 353512.5 | F23: ='January Arrears'!Q23 -> 126058.49 | G23: 110000 | I23: 0 | J23: =E23+F23+G23+H23+I23 -> 589570.99 | L23: 0 | O23: 62231.115 | P23: 28281 | Q23: =O23+N23+M23+L23+K23+P23 -> 90512.115 | R23: 968705.41 | S23: =J23-Q23 -> 499058.87
A24: 18 | B24: FARUQ ATOFARATI | C24: PA (SPECIAL DUTIES) TO DG | D24: 10(7) | E24: 293029.67 | F24: 105651.98 | H24: =50000+10000 -> 60000 | I24: 100000 | J24: =E24+F24+G24+H24+I24 -> 558681.64 | O24: 61147.427 | P24: 23442.373 | Q24: =O24+N24+M24+L24+K24+P24 -> 84589.8 | R24: 286230.26 | S24: =J24-Q24 -> 474091.84
A25: 19 | B25: ELIZABETH OGECHUKWU ONYEAKU | C25: ICT OFFICER | D25: 9(9) | E25: 270481.67 | F25: 100957.36 | H25: =50000+10000 -> 60000 | J25: =E25+F25+G25+H25+I25 -> 431439.02 | L25: 10000 | M25: =20000 -> 20000 | O25: 39052.313 | P25: 21638.533 | Q25: =O25+N25+M25+L25+K25+P25 -> 90690.846 | R25: 160472 | S25: =J25-Q25 -> 340748.18
A26: 20 | B26: VICTOR ASUKWO | C26: ICT OFFICER | D26: 9(9) | E26: 270481.67 | F26: 100957.36 | H26: =50000+10000 -> 60000 | J26: =E26+F26+G26+H26+I26 -> 431439.02 | O26: 39052.313 | P26: 21638.533 | Q26: =O26+N26+M26+L26+K26+P26 -> 60690.846 | R26: 190472 | S26: =J26-Q26 -> 370748.18
A27: 21 | B27: NNANDI LIVINUS ATURE | C27: RESEARCH ASSISTANT | D27: 9(9) | E27: 270481.67 | F27: 100957.36 | G27: =100000 -> 100000 | J27: =E27+F27+G27+H27+I27 -> 471439.02 | L27: =10000 -> 10000 | M27: =95833.33 -> 95833.33 | O27: 45772.313 | P27: 21638.533 | Q27: =O27+N27+M27+L27+K27+P27 -> 173244.18 | R27: 117918.67 | S27: =J27-Q27 -> 298194.85
A28: 22 | B28: ABDULRAHMAN A SULAIMAN | C28: STORE OFFICER | D28: 9(8) | E28: 263165.33 | F28: 98226.268 | H28: =60000 -> 60000 | J28: =E28+F28+G28+H28+I28 -> 421391.6 | L28: =20000 -> 20000 | M28: =17500 -> 17500 | O28: 37921.501 | P28: 21053.227 | Q28: =O28+N28+M28+L28+K28+P28 -> 96474.727 | R28: 149517.56 | S28: =J28-Q28 -> 324916.87
A29: 23 | B29: DARE SHEU MAGBON | C29: ADMINISTRATION OFFICER | D29: 9(7) | E29: 255849 | F29: 95495.18 | H29: =60000 -> 60000 | J29: =E29+F29+G29+H29+I29 -> 411344.18 | L29: =30000+20000 -> 50000 | M29: 0 | O29: 36790.688 | P29: 20467.92 | Q29: =O29+N29+M29+L29+K29+P29 -> 107258.61 | R29: 133563.13 | S29: =J29-Q29 -> 304085.57
A30: 24 | B30: ABUBAKAR SULAIMAN SODEEQ | C30: ADMINISTRATION OFFICER | D30: 9(7) | E30: 255849 | F30: 95495.18 | H30: =60000 -> 60000 | J30: =E30+F30+G30+H30+I30 -> 411344.18 | M30: 0 | O30: 36790.688 | P30: 20467.92 | Q30: =O30+N30+M30+L30+K30+P30 -> 57258.608 | R30: 183563.13 | S30: =J30-Q30 -> 354085.57
A31: 25 | B31: JIMOH ADEBAYO ZAKA | C31: ASST. OFFICER/COMM | D31: 9(9) | E31: 270481.67 | F31: 104411.79 | H31: =60000 -> 60000 | J31: =E31+F31+G31+H31+I31 -> 434893.46 | L31: =50000 -> 50000 | M31: 50000 | O31: 39052.313 | P31: 21638.533 | Q31: =O31+N31+M31+L31+K31+P31 -> 160690.85 | R31: 87017.565 | S31: =J31-Q31 -> 274202.61
A32: 26 | B32: MOHAMMED BELLO | C32: PROTOCOL ASSISTANT | D32: 8(9) | E32: 230631.92 | F32: 86687.598 | H32: =50000 -> 50000 | J32: =E32+F32+G32+H32+I32 -> 367319.51 | L32: =0 -> 0 | M32: =26666.67 -> 26666.67 | O32: 31213.136 | P32: 18450.553 | Q32: =O32+N32+M32+L32+K32+P32 -> 76330.359 | R32: 136064.51 | S32: =J32-Q32 -> 290989.16
A33: 27 | B33: HARUNA JIBRIL AMEH | C33: ASST. ADMIN. OFFICER | D33: 8(8) | E33: 224459.75 | F33: 87384.217 | H33: 50000 | J33: =E33+F33+G33+H33+I33 -> 361843.97 | L33: 20000 | M33: 0 | O33: 30259.166 | P33: 17956.78 | Q33: =O33+N33+M33+L33+K33+P33 -> 68215.946 | R33: 136816.37 | S33: =J33-Q33 -> 293628.02
B34: TOTAL | C34: 27 | E34: 13048608 | F34: =SUM(F7:F33) -> 4651742.3 | G34: =SUM(G7:G33) -> 1420000 | H34: =SUM(H7:H33) -> 1160000 | I34: =SUM(I7:I33) -> 1225235 | J34: =SUM(J7:J33) -> 21505585 | K34: =SUM(K7:K33) -> 0 | L34: =SUM(L7:L33) -> 700000 | M34: =SUM(M7:M33) -> 1042833.1 | ... Q34: =SUM(Q7:Q33) -> 5055927.2 | R34: 8717267.3 | S34: =SUM(S7:S33) -> 16449658
B36: INTERNAL AUDIT
A37: 1 | B37: OSANAIYE DAVID AKINYEMI | C37: DIRECTOR INTERNAL AUDIT | D37: 17(9) | E37: 1435720 | F37: 495145.5 | H37: =100000 -> 100000 | J37: =SUM(E37:I37) -> 2030865.5 | K37: ='FEBRUARY 2024'!F196 -> 0 | L37: 200000 | M37: 0 | O37: 251472.25 | P37: 114857.6 | Q37: =O37+N37+M37+L37+K37+P37 -> 566329.85 | R37: 589102.26 | S37: =J37-Q37 -> 1464535.6
A38: 2 | B38: JAMILA ABDUL | C38: AUDITOR II | D38: 10(7) | E38: 293029.67 | F38: =150718.948586667+37675.34 -> 188394.29 | H38: =60000 -> 60000 | J38: =SUM(E38:I38) -> 541423.96 | L38: =20000 -> 20000 | N38: 0 | O38: 42537.332 | P38: 23442.373 | Q38: =O38+N38+M38+L38+K38+P38 -> 85979.705 | R38: 139773.39 | S38: =J38-Q38 -> 455444.25
A39: 3 | B39: IJEOMA EWELUKWA | C39: AUDIT OFFICER | D39: 10(8) | E39: 300965.58 | F39: 110371.64 | H39: =50000+10000 -> 60000 | J39: =SUM(E39:I39) -> 471337.22 | L39: =10000 -> 10000 | O39: 43763.907 | P39: 24077.247 | Q39: =O39+N39+M39+L39+K39+P39 -> 77841.154 | R39: 196830.04 | S39: =J39-Q39 -> 393496.07
C40: 3 | E40: 2029715.2 | F40: =SUM(F37:F39) -> 793911.42 | G40: =SUM(G37:G39) -> 0 | H40: =SUM(H37:H39) -> 220000 | I40: =SUM(I37:I39) -> 0 | J40: =SUM(J37:J39) -> 3043626.7 | K40: =SUM(K37:K39) -> 0 | L40: =SUM(L37:L39) -> 230000 | M40: =SUM(M37:M39) -> 0 | N40: 0 | O40: 337773.49 | P40: =SUM(P37:P39) -> 162377.22 | Q40: =SUM(Q37:Q39) -> 730150.71 | R40: 925705.68 | S40: =SUM(S37:S39) -> 2313476
B42: LEG. SUPPORT SEVICES
A43: 1 | B43: PROF. EDOBA BRIGHT OMOREGBE | C43: AG. DLSS | D43: 17(9) | E43: 1435720 | F43: 495145.5 | G43: =200000 -> 200000 | J43: =SUM(E43:I43) -> 2130865.5 | L43: =200000 -> 200000 | M43: =380000 -> 380000 | O43: 270672.25 | P43: 114857.6 | Q43: =O43+N43+M43+L43+K43+P43 -> 965529.85 | R43: 289902.26 | S43: =J43-Q43 -> 1165335.6
A44: 2 | B44: DR CLINTON JAJA | C44: SENIOR RESEARCH FELLOW | D44: 15(9) | E44: 620675.58 | F44: 214056.22 | G44: =160000 -> 160000 | I44: 0 | J44: =SUM(E44:I44) -> 994731.8 | L44: =50000 -> 50000 | M44: =385000 -> 385000 | O44: 119022.8 | P44: 49654.047 | Q44: =O44+N44+M44+L44+K44+P44 -> 603676.85 | R44: 12596.563 | S44: =J44-Q44 -> 391054.95
A45: 3 | B45: BETHEL UZOMA IHUGBA | C45: DEPUTY DIRECTOR, LEGAL RESEARCH | D45: 16(8) | E45: 739203.58 | F45: 254933.51 | G45: =180000 -> 180000 | J45: =SUM(E45:I45) -> 1174137.1 | L45: =80000+23000 -> 103000 | M45: =246905.96 -> 246905.96 | O45: 143799.59 | P45: 59136.287 | Q45: =O45+N45+M45+L45+K45+P45 -> 552841.83 | R45: 170564.52 | S45: =J45-Q45 -> 621295.26
A46: 4 | B46: OGUCHE SAMUEL | C46: SNR RESEARCH FELLOW | D46: 15(9) | E46: 620675.58 | F46: 214056.22 | G46: =160000 -> 160000 | J46: =SUM(E46:I46) -> 994731.8 | L46: =30000 -> 30000 | M46: =176288.88 -> 176288.88 | O46: 119022.8 | P46: 49654.047 | Q46: =O46+N46+M46+L46+K46+P46 -> 374965.73 | R46: 241307.68 | S46: =J46-Q46 -> 619766.07
A47: 5 | B47: IBRAHIM USMAN | C47: SNR RESEARCH FELLOW | D47: 15(9) | E47: 620675.58 | F47: 214056.22 | G47: =140000+20000 -> 160000 | I47: 0 | J47: =SUM(E47:I47) -> 994731.8 | N47: 837.6875 | O47: 118861.97 | P47: 49654.047 | Q47: =O47+N47+M47+L47+K47+P47 -> 169353.7 | R47: 446919.71 | S47: =J47-Q47 -> 825378.1
A48: 6 | B48: DR MOHAMMED O. AMALI | C48: SNR RESEARCH FELLOW | D48: 15(7) | E48: 582118.08 | F48: 200758.95 | G48: =140000+20000 -> 160000 | J48: =SUM(E48:I48) -> 942877.03 | L48: =15000 -> 15000 | M48: =216666.67 -> 216666.67 | O48: 112212 | P48: 46569.447 | Q48: =O48+N48+M48+L48+K48+P48 -> 390448.12 | R48: 197480.46 | S48: =J48-Q48 -> 552428.91
A49: 7 | B49: YAHAYA SHAMSU | C49: RESEARCH FELLOW 1 | D49: 14(10) | E49: 470498 | F49: 166536.14 | G49: =140000 -> 140000 | J49: =SUM(E49:I49) -> 777034.14 | N49: 0 | O49: 88655.433 | P49: 37639.84 | Q49: =O49+N49+M49+L49+K49+P49 -> 126295.27 | R49: 355306.43 | S49: =J49-Q49 -> 650738.87
A50: 8 | B50: BILKIS S. LAWAL-GAMBARI | C50: RESEARCH OFFICER | D50: 10(8) | E50: 300965.58 | F50: 109826.32 | G50: 100000 | J50: =SUM(E50:I50) -> 510791.9 | O50: 51029.227 | P50: 24077.247 | Q50: =O50+N50+M50+L50+K50+P50 -> 75106.474 | R50: 240110.04 | S50: =J50-Q50 -> 435685.43
A51: 9 | B51: ZAINAB AKINDE | C51: RESEARCH OFFICER | D51: 9(8) | E51: 263165.33 | F51: 98226.268 | G51: =100000 -> 100000 | J51: =SUM(E51:I51) -> 461391.6 | O51: 44641.501 | P51: 21053.227 | Q51: =O51+N51+M51+L51+K51+P51 -> 65694.727 | R51: 220297.56 | S51: =J51-Q51 -> 395696.87
A52: 10 | B52: ABDULLAHI AHMAD USMAN | C52: RESEARCH OFFICER | D52: 9(8) | E52: 263165.33 | F52: 97528.738 | G52: =100000 -> 100000 | J52: =SUM(E52:I52) -> 460694.07 | O52: 44641.501 | P52: 21053.227 | Q52: =O52+N52+M52+L52+K52+P52 -> 65694.727 | R52: 220995.09 | S52: =J52-Q52 -> 394999.34
A53: 11 | B53: GUNAT NANSAK MARK | C53: RESEARCH OFFICER | D53: 9(8) | E53: 263165.33 | F53: 98226.268 | G53: =100000 -> 100000 | J53: =SUM(E53:I53) -> 461391.6 | O53: 44641.501 | P53: 21053.227 | Q53: =O53+N53+M53+L53+K53+P53 -> 65694.727 | R53: 220297.56 | S53: =J53-Q53 -> 395696.87
B54: TOTAL | C54: 11 | E54: 6180028 | F54: 2163350.3 | G54: =SUM(G43:G53) -> 1560000 | H54: =SUM(H43:H53) -> 0 | I54: =SUM(I43:I53) -> 0 | J54: =SUM(J43:J53) -> 9903378.3 | K54: =SUM(K43:K53) -> 0 | L54: =SUM(L43:L53) -> 398000 | M54: =SUM(M43:M53) -> 1404861.5 | N54: 837.6875 | O54: 1157200.6 | P54: 494402.24 | Q54: =SUM(Q43:Q53) -> 3455302 | R54: 2615777.9 | S54: =SUM(S43:S53) -> 6448076.3
B56: LEGAL SERVICES
A57: 1 | B57: DR SHUIBU DANWANKA | C57: DIRECTOR LEGAL SERVICES | D57: 17(9) | E57: 1435720 | F57: 495145.5 | G57: =200000 -> 200000 | I57: 0 | J57: =SUM(E57:I57) -> 2130865.5 | L57: 120000 | N57: 0 | O57: 270672.25 | P57: 114857.6 | Q57: =O57+N57+M57+L57+K57+P57 -> 505529.85 | R57: 629902.26 | S57: =J57-Q57 -> 1625335.6
A58: 2 | B58: ABDULSALAM BAKO | C58: MANAGER, LEGAL SERVICES | D58: 15 (9) | E58: 620675.58 | F58: 214056.22 | H58: 80000 | J58: =SUM(E58:I58) -> 914731.8 | L58: 50000 | M58: 145000 | N58: 0 | O58: 103662.8 | P58: 49654.047 | Q58: =O58+N58+M58+L58+K58+P58 -> 348316.85 | R58: 187956.56 | S58: =J58-Q58 -> 566414.95
B59: TOTAL | C59: 2 | E59: 2056395.6 | F59: 709201.71 | G59: =SUM(G57:G58) -> 200000 | H59: =SUM(H57:H58) -> 80000 | I59: =SUM(I57:I58) -> 0 | J59: =SUM(J57:J58) -> 3045597.3 | K59: =SUM(K57:K58) -> 0 | L59: =SUM(L57:L58) -> 170000 | M59: =SUM(M57:M58) -> 145000 | N59: 0 | O59: 374335.05 | P59: 164511.65 | Q59: =SUM(Q57:Q58) -> 853846.7 | R59: 817858.82 | S59: =SUM(S57:S58) -> 2191750.6
B61: DEMOCRACY & GOVERNANCE
A62: 1 | B62: DR. ADEWALE ADEREMI | C62: DIRECTOR, DEMOCRATIC STUDIES | D62: 17(9) | E62: 1435720 | F62: 473092.84 | G62: =200000 -> 200000 | I62: 0 | J62: =SUM(E62:I62) -> 2108812.8 | L62: =100000+100000 -> 200000 | M62: =223611.11 -> 223611.11 | O62: 292724.91 | Q62: =O62+N62+M62+L62+K62+P62 -> 716336.02 | R62: 446291.15 | S62: =J62-Q62 -> 1392476.8
A63: 2 | B63: NDANUSA MOHAMMED MANZUMA | C63: SNR RESEARCH FELLOW | D63: 15(8) | E63: 601396.83 | F63: 207407.36 | G63: =160000 -> 160000 | I63: 0 | J63: =SUM(E63:I63) -> 968804.19 | L63: =100000 -> 100000 | M63: =131250 -> 131250 | O63: 115617.4 | P63: 48111.747 | Q63: =O63+N63+M63+L63+K63+P63 -> 394979.15 | R63: 207122.07 | S63: =J63-Q63 -> 573825.04
A64: 3 | B64: EJALONIBU GANIYU LAYI | C64: RESEARCH FELLOW 1 | D64: 14(8) | E64: 442746.5 | F64: 156712.97 | G64: 140000 | J64: =SUM(E64:I64) -> 739459.47 | L64: =110000 -> 110000 | O64: 83753.408 | P64: 35419.72 | Q64: =O64+N64+M64+L64+K64+P64 -> 229173.13 | R64: 232280.12 | S64: =J64-Q64 -> 510286.34
A65: 4 | B65: LOHNA BONKAT JONATHAN | C65: RESEARCH FELLOW 11 | D65: 13(10) | E65: 428915.92 | F65: 151816.66 | G65: =120000 -> 120000 | I65: 0 | J65: =SUM(E65:I65) -> 700732.58 | L65: =20000+65000 -> 85000 | M65: 0 | N65: 0 | O65: 77470.374 | P65: 34313.273 | Q65: =O65+N65+M65+L65+K65+P65 -> 196783.65 | R65: 234628.88 | S65: =J65-Q65 -> 503948.93
A66: 5 | B66: YUNUSA ABDULLAHI | C66: RESEARCH FELLOW 1 | D66: 14(11) | E66: 484373.75 | F66: 171447.61 | G66: =140000 -> 140000 | J66: =SUM(E66:I66) -> 795821.36 | L66: =10000 -> 10000 | M66: =54585.66 -> 54585.66 | O66: 91106.446 | P66: 38749.9 | Q66: =O66+N66+M66+L66+K66+P66 -> 194442.01 | R66: 310141.68 | S66: =J66-Q66 -> 601379.36
A67: 7 | B67: UDEFUNA NNADOZIE PATRICK | C67: RESEARCH OFFICER | D67: 12(8) | E67: 365703.83 | F67: 130204.12 | G67: =110000 -> 110000 | I67: 0 | J67: =SUM(E67:I67) -> 605907.95 | L67: =10000 -> 10000 | M67: =65885.83 -> 65885.83 | O67: 64384.592 | P67: 29256.307 | Q67: =O67+N67+M67+L67+K67+P67 -> 169526.73 | R67: 205229.29 | S67: =J67-Q67 -> 436381.22
A68: 8 | B68: SHAFIU YAHYA MIKAIL | C68: PRINCIPAL RESEARCH OFFICER | D68: 12(8) | E68: 365703.83 | F68: 130204.12 | G68: =110000 -> 110000 | I68: 0 | J68: =SUM(E68:I68) -> 605907.95 | L68: =52000-2000 -> 50000 | O68: 64384.592 | P68: 29256.307 | Q68: =O68+N68+M68+L68+K68+P68 -> 143640.9 | R68: 231115.12 | S68: =J68-Q68 -> 462267.05
A69: 9 | B69: HASSAN YERIMA | C69: PRINCIPAL RESEARCH OFFICER | D69: 12(8) | E69: 365703.83 | F69: 130204.12 | G69: =110000 -> 110000 | I69: 0 | J69: =SUM(E69:I69) -> 605907.95 | L69: =67000-2000 -> 65000 | O69: 64384.592 | P69: 29256.307 | Q69: =O69+N69+M69+L69+K69+P69 -> 158640.9 | R69: 216115.12 | S69: =J69-Q69 -> 447267.05
A70: 10 | B70: HAUWA PATE SADIQ | C70: PRINCIPAL PROGRAMME OFFICER | D70: 12(9) | E70: 377895.17 | F70: 130188.98 | G70: =110000 -> 110000 | J70: =SUM(E70:I70) -> 618084.15 | L70: =80000+20000 -> 100000 | O70: 66538.069 | P70: 30231.613 | Q70: =O70+N70+M70+L70+K70+P70 -> 196769.68 | R70: 191168.12 | S70: =J70-Q70 -> 421314.47
A71: 11 | B71: KOLAPO Q. ABAYOMI | C71: RESEARCH OFFICER | D71: 10(8) | E71: 300965.58 | F71: 106028.3 | G71: 100000 | J71: =SUM(E71:I71) -> 506993.88 | O71: 51029.227 | P71: 24077.247 | Q71: =O71+N71+M71+L71+K71+P71 -> 75106.474 | R71: 243908.06 | S71: =J71-Q71 -> 431887.4
B72: TOTAL | C72: 12 | E72: 5169125.2 | F72: 1787307.1 | G72: =SUM(G62:G71) -> 1300000 | H72: =SUM(H62:H71) -> 0 | I72: =SUM(I62:I71) -> 0 | J72: =SUM(J62:J71) -> 8256432.3 | K72: =SUM(K62:K71) -> 0 | L72: =SUM(L62:L71) -> 730000 | M72: =SUM(M62:M71) -> 475332.6 | N72: 0 | O72: 971393.61 | P72: 298672.42 | Q72: =SUM(Q62:Q71) -> 2475398.6 | R72: 2517999.6 | S72: =SUM(S62:S71) -> 5781033.7
B74: DEPARTMENT OF STUDIES
A75: 1 | B75: DR ASIMIYU G. ABIOLA | C75: DIRECTOR POST GRADUATE | D75: 17(9) | E75: 1435720 | F75: 495145.5 | G75: =200000 -> 200000 | I75: 0 | J75: =SUM(E75:I75) -> 2130865.5 | L75: 250000 | M75: =0 -> 0 | N75: 0 | O75: 270672.25 | P75: 114857.6 | Q75: =O75+N75+M75+L75+K75+P75 -> 635529.85 | R75: 619902.26 | S75: =J75-Q75 -> 1495335.6
A76: 2 | B76: USMAN WALI | C76: SENIOR RESEARCH FELLOW | D76: 15 (8) | E76: 601396.83 | F76: 198169.9 | G76: =160000 -> 160000 | I76: 0 | J76: =SUM(E76:I76) -> 959566.74 | N76: 0 | O76: 124854.86 | Q76: =O76+N76+M76+L76+K76+P76 -> 124854.86 | R76: 438372.07 | S76: =J76-Q76 -> 834711.88
A77: 3 | B77: AYOBOLU OLAJIDE OLUFUNSHO | C77: ASST.DIR., INFORMATION | D77: 15 (9) | E77: 620675.58 | F77: 204522.64 | G77: 160000 | I77: 0 | J77: =SUM(E77:I77) -> 985198.22 | L77: =50000 -> 50000 | M77: =59583.33 -> 59583.33 | O77: 128556.38 | Q77: =O77+N77+M77+L77+K77+P77 -> 238139.71 | R77: 273373.23 | S77: =J77-Q77 -> 747058.51
A78: 4 | B78: ANTHONY EDET | C78: CHIEF PROGRAMMES OFFICER | D78: 14(9) | E78: 456622.25 | F78: 161624.67 | G78: =140000 -> 140000 | I78: 0 | J78: =SUM(E78:I78) -> 758246.92 | L78: 20000 | M78: =96664.65 -> 96664.65 | N78: 668.31625 | O78: 86076.104 | P78: 36529.78 | Q78: =O78+N78+M78+L78+K78+P78 -> 239938.85 | R78: 231588.51 | S78: =J78-Q78 -> 518308.07
A79: 5 | B79: IGWE STACY | C79: PROGRAMME OFFICER | D79: 10(9) | E79: 308901.5 | F79: 116360.43 | G79: =100000 -> 100000 | J79: =SUM(E79:I79) -> 525261.93 | L79: =50000 -> 50000 | M79: =50000 -> 50000 | O79: 52431.028 | P79: 24712.12 | Q79: =O79+N79+M79+L79+K79+P79 -> 177143.15 | R79: 155661.57 | S79: =J79-Q79 -> 348118.79
A80: 6 | B80: OLANIYAN TAIWO ABINBOLA | C80: PROGRAMME OFFICER | D80: 9(8) | E80: 263165.33 | F80: 98226.268 | G80: 100000 | J80: =SUM(E80:I80) -> 461391.6 | O80: 44641.501 | P80: 21053.227 | Q80: =O80+N80+M80+L80+K80+P80 -> 65694.727 | R80: 220297.56 | S80: =J80-Q80 -> 395696.87
A81: 7 | B81: AMINAT JUMOKE SULAIMON | C81: AST. PROGRAMME OFFICER | D81: 8(8) | E81: 224459.75 | F81: 86834.47 | G81: 100000 | H81: 0 | J81: =SUM(E81:I81) -> 411294.22 | L81: 20000 | M81: 0 | N81: 0 | O81: 38659.166 | P81: 17956.78 | Q81: =O81+N81+M81+L81+K81+P81 -> 76615.946 | R81: 178966.11 | S81: =J81-Q81 -> 334678.27
B82: TOTAL | C82: 7 | E82: 3910941.3 | F82: 1360883.9 | G82: =SUM(G75:G81) -> 960000 | H82: =SUM(H75:H81) -> 0 | I82: =SUM(I75:I81) -> 0 | J82: =SUM(J75:J81) -> 6231825.1 | K82: =SUM(K75:K81) -> 0 | L82: =SUM(L75:L81) -> 390000 | M82: =SUM(M75:M81) -> 206247.98 | N82: =SUM(N75:N81) -> 668.31625 | O82: =SUM(O75:O81) -> 745891.28 | P82: 215109.51 | Q82: =SUM(Q75:Q81) -> 1557917.1 | R82: 2118161.3 | S82: =SUM(S75:S81) -> 4673908
B84: ECON. DEV. & SOC. RESEARCH
A85: 1 | B85: TERFA WILLIAMS ABRAHAM | C85: SNR RESEARCH FELLOW | D85: 15(9) | E85: 620675.58 | F85: 214056.22 | G85: =160000 -> 160000 | I85: 100000 | J85: =SUM(E85:I85) -> 1094731.8 | O85: 138222.8 | P85: 49654.047 | Q85: =O85+N85+M85+L85+K85+P85 -> 187876.85 | R85: 528396.56 | S85: =J85-Q85 -> 906854.95
A86: 2 | B86: DR AUGUSTINE C. OSIGWE | C86: SNR RESEARCH FELLOW | D86: 15(9) | E86: 620675.58 | F86: 214056.22 | G86: =160000 -> 160000 | J86: =SUM(E86:I86) -> 994731.8 | L86: =30000 -> 30000 | M86: 98750 | N86: 837.6875 | O86: 118861.97 | P86: 49654.047 | Q86: =O86+N86+M86+L86+K86+P86 -> 298103.7 | R86: 298969.71 | S86: =J86-Q86 -> 696628.1
A87: 3 | B87: OMOJU OLUWASOLA EMMANUEL | C87: SNR RESEARCH FELLOW | D87: 15(7) | E87: 582118.08 | F87: 200751.53 | G87: 160000 | J87: =SUM(E87:I87) -> 942869.62 | L87: =50000 -> 50000 | M87: =79861.11 -> 79861.11 | O87: 112212 | P87: 46569.447 | Q87: =O87+N87+M87+L87+K87+P87 -> 288642.56 | R87: 294911.17 | S87: =J87-Q87 -> 654227.06
A88: 4 | B88: IBE EZECHI CYRIACUS | C88: RESEARCH FELLOW II | D88: 13(11) | E88: 441804.92 | F88: 156380.73 | G88: =120000 -> 120000 | I88: 0 | J88: =SUM(E88:I88) -> 718185.65 | L88: =50000 -> 50000 | M88: 0 | O88: 79747.087 | P88: 35344.393 | Q88: =O88+N88+M88+L88+K88+P88 -> 165091.48 | R88: 251088.4 | S88: =J88-Q88 -> 553094.17
A89: 5 | B89: OSIKHEN LEO IGBANOI | C89: RESEARCH FELLOW 11 | D89: 13(10) | E89: 428915.92 | F89: 151816.66 | G89: =120000 -> 120000 | I89: 0 | J89: =SUM(E89:I89) -> 700732.58 | L89: 50000 | M89: 0 | O89: 77470.374 | P89: 34313.273 | Q89: =O89+N89+M89+L89+K89+P89 -> 161783.65 | R89: 248191.68 | S89: =J89-Q89 -> 538948.93
A90: 6 | B90: OKUNGBOWA OSARETIN GODSPOWER | C90: RESEARCH FELLOW 1 | D90: 14(7) | E90: 428870.75 | F90: 151799.35 | G90: =140000 -> 140000 | I90: 0 | J90: =SUM(E90:I90) -> 720670.1 | L90: =100000-100000 -> 0 | O90: 81302.396 | P90: 34309.66 | Q90: =O90+N90+M90+L90+K90+P90 -> 115612.06 | R90: 339604.28 | S90: =J90-Q90 -> 605058.04
A91: 7 | B91: YUSUF IBRAHIM | C91: PRINCIPAL RESEARCH OFFICER | D91: 12(8) | E91: 365703.83 | F91: 130204.12 | G91: =110000 -> 110000 | I91: 0 | J91: =SUM(E91:I91) -> 605907.95 | L91: =20000 -> 20000 | M91: 43750 | O91: 64384.592 | P91: 29256.307 | Q91: =O91+N91+M91+L91+K91+P91 -> 157390.9 | R91: 205320.02 | S91: =J91-Q91 -> 448517.05
A92: 8 | B92: MUSTAPHA RAFIU AYOBANJI | C92: RESEARCH FELLOW 11 | D92: 13(7) | E92: 390248.92 | F92: 138323.95 | G92: 120000 | I92: 0 | J92: =SUM(E92:I92) -> 648572.87 | L92: 0 | N92: 576.87475 | O92: 70529.475 | P92: 31219.913 | Q92: =O92+N92+M92+L92+K92+P92 -> 102326.26 | R92: 304894.12 | S92: =J92-Q92 -> 546246.6
A93: 9 | B93: MARYAM MUSA SADA | C93: ASSIT. RESEARCH OFFICER | D93: 10(8) | E93: 300965.58 | F93: 106028.3 | G93: 100000 | J93: =SUM(E93:I93) -> 506993.88 | O93: 51029.227 | P93: 24077.247 | Q93: =O93+N93+M93+L93+K93+P93 -> 75106.474 | R93: 232319.59 | S93: =J93-Q93 -> 431887.4
A94: 10 | B94: CHARITY EZENWAJIOBI | C94: REASEARCH. ASST. | D94: 8(9) | E94: 230631.92 | F94: 66133.388 | G94: =100000 -> 100000 | J94: =SUM(E94:I94) -> 396765.31 | L94: 50000 | N94: 0 | O94: 39613.136 | P94: 18450.553 | Q94: =O94+N94+M94+L94+K94+P94 -> 108063.69 | R94: 171044.28 | S94: =J94-Q94 -> 288701.62
B95: TOTAL | C95: 11 | E95: 4410611.1 | F95: 1529550.5 | G95: =SUM(G85:G94) -> 1290000 | H95: =SUM(H85:H94) -> 0 | I95: =SUM(I85:I94) -> 100000 | J95: =SUM(J85:J94) -> 7330161.6 | K95: =SUM(K85:K94) -> 0 | L95: =SUM(L85:L94) -> 250000 | M95: =SUM(M85:M94) -> 222361.11 | N95: 1414.5622 | O95: 833373.06 | P95: 352848.89 | Q95: =SUM(Q85:Q94) -> 1659997.6 | R95: 2874739.8 | S95: =SUM(S85:S94) -> 5670163.9
B97: TRAINING & INT''L COOP
A98: 1 | B98: AKINSANMI ADEJOKE OLUKEMI | C98: Ag. DIR. TRAINING & IC | D98: 16(9) | E98: 762373.17 | F98: 262923.83 | H98: =80000+10000 -> 90000 | J98: =E98+F98+G98+H98+I98 -> 1115297 | L98: =0 -> 0 | M98: 0 | N98: 1066.3293 | O98: 130407.53 | P98: 60989.853 | Q98: =O98+N98+M98+L98+K98+P98 -> 192463.71 | R98: 457975.48 | S98: =J98-Q98 -> 922833.29
A99: 2 | B99: MOHAMMED R. ADAMU | C99: CHIEF TRAINING OFFICER | D99: 14(9) | E99: 456622.25 | F99: 162078.14 | H99: 70000 | I99: 0 | J99: =E99+F99+G99+H99+I99 -> 688700.39 | L99: =10000 -> 10000 | M99: 175000 | O99: 72764.421 | P99: 36529.78 | Q99: =O99+N99+M99+L99+K99+P99 -> 294294.2 | R99: 67644.112 | S99: =J99-Q99 -> 394406.19
A100: 3 | B100: OKECHUKWU UCHENNA HULDA | C100: PRINCIPALTRAINING OFFICER | D100: 12(9) | E100: 377895.17 | F100: 131388.98 | H100: =60000 -> 60000 | J100: =E100+F100+G100+H100+I100 -> 569284.15 | L100: =5000 -> 5000 | M100: =64806.29 -> 64806.29 | O100: 56938.069 | P100: 30231.613 | Q100: =O100+N100+M100+L100+K100+P100 -> 156975.97 | R100: 171238.34 | S100: =J100-Q100 -> 412308.18
A101: 4 | B101: TASSNEEM IBRAHIM | C101: SENIOR PROGRAMME OFFICER | D101: 10(8) | E101: 300965.58 | F101: 106573.62 | H101: =60000 -> 60000 | J101: =E101+F101+G101+H101+I101 -> 467539.2 | L101: =10000 -> 10000 | M101: =19583.33 -> 19583.33 | O101: 43763.907 | P101: 24077.247 | Q101: =O101+N101+M101+L101+K101+P101 -> 97424.484 | R101: 173181.83 | S101: =J101-Q101 -> 370114.72
B102: TOTAL | C102: 4 | E102: 1897856.2 | F102: 662964.57 | G102: =SUM(G98:G101) -> 0 | H102: =SUM(H98:H101) -> 280000 | I102: =SUM(I98:I101) -> 0 | J102: =SUM(J98:J101) -> 2840820.7 | K102: =SUM(K98:K101) -> 0 | L102: =SUM(L98:L101) -> 25000 | M102: =SUM(M98:M101) -> 259389.62 | N102: 1066.3293 | O102: 303873.92 | P102: 151828.49 | Q102: =SUM(Q98:Q101) -> 741158.37 | R102: 870039.76 | S102: =SUM(S98:S101) -> 2099662.4
B104: LIBRARY & DOCUMENTATION
A105: 1 | B105: DR MAIMUNA IZAH | C105: INSITUTE LIBRARIAN | D105: 17(9) | E105: 1435720 | F105: 495145.5 | G105: =200000 -> 200000 | I105: 0 | J105: =SUM(E105:I105) -> 2130865.5 | L105: =100000 -> 100000 | M105: 0 | N105: 0 | O105: 270672.25 | P105: 114857.6 | Q105: =O105+N105+M105+L105+K105+P105 -> 485529.85 | R105: 769902.26 | S105: =J105-Q105 -> 1645335.6
A106: 2 | B106: CATHERINE E. IKOKOH | C106: SNR RESEARCH FELLOW DOCU | D106: 16(9) | E106: 762373.17 | F106: 262923.83 | G106: =160000+20000 -> 180000 | I106: 0 | J106: =SUM(E106:I106) -> 1205297 | L106: 40000 | M106: =238888.89 -> 238888.89 | N106: 1066.3293 | O106: 147687.53 | P106: 60989.853 | Q106: =O106+N106+M106+L106+K106+P106 -> 488632.6 | R106: 251806.59 | S106: =J106-Q106 -> 716664.4
A107: 3 | B107: ALIYU SANNI ABUBAKAR | C107: RESEARCH FELLOW 11 DATA & DOCU | D107: 13(11) | E107: 441804.92 | F107: 156380.73 | G107: =120000 -> 120000 | I107: 41432.939 | J107: =SUM(E107:I107) -> 759618.58 | L107: 30000 | M107: =61111.11 -> 61111.11 | N107: 658.4825 | O107: 87575.783 | P107: 35344.393 | Q107: =O107+N107+M107+L107+K107+P107 -> 214689.77 | R107: 146146.05 | S107: =J107-Q107 -> 544928.82
A108: 4 | B108: CHINAKO N. ASOGWA | C108: RESEARCH FELLOW 11 DATA & DOCU | D108: 13(11) | E108: 441804.92 | F108: 156380.73 | G108: =120000 -> 120000 | I108: 39820.117 | J108: =SUM(E108:I108) -> 758005.76 | L108: =50000 -> 50000 | M108: =0 -> 0 | O108: 87392.55 | P108: 35344.393 | Q108: =O108+N108+M108+L108+K108+P108 -> 172736.94 | R108: 266575.24 | S108: =J108-Q108 -> 585268.82
...

Sheet MEMO
A2: NATIONAL INSTITUTE FOR LEGISLATIVE AND DEMOCRATIC STUDIES
A3: INTERNAL MEMO
A4: FROM : DEPUTY DIRECTOR, FINANCE AND ACCOUNTS
A5: THRU: DIRECTOR, FINANCE AND ACCOUNTS
A6: TO: DG
A7: 29TH JANUARY , 2021
A9: SUBJECT: PAYROLL FOR THE MONTH OF JANUARY, 2021
A10: Find below the details of NILDS Staff Payroll for the month of January, 2021
A13: TO: | C13: DIRECTOR, GENERAL
A14: THRU: | C14: DIRECTOR, FINANCE AND ACCOUNT
A15: FROM: | C15: DEPUTY DIRECTOR, FINANCE AND ACCOUNTS
A16: DATE: | C16: 29TH FEBRUARY 2024
A18: SUBJECT: PAYROLL FOR THE MONTH OF FEBRUARY 2024
A19: Find below the details of NILDS Staff Payroll for the Month of February 2024: | G19: NGN | H19: NGN
A20: GROSS SALARY FOR FEBRUARY, 2024 | H20: ='FEBRUARY 2024'!J194 -> 1.0195062e+08
A22: DEDUCTIONS
A23: COOP SOCIETY DEDUCTIONS ( CONTR.& SPEC. SAVINGS) | G23: ='FEBRUARY 2024'!L194 -> 5123500
A24: COOP LOAN RECOVERY | G24: ='FEBRUARY 2024'!M194 -> 7075945.7
A25: NHF DEDUCTIONS | G25: ='FEBRUARY 2024'!N194 -> 23031.314
A26: PAYE DEDUCTIONS | G26: ='FEBRUARY 2024'!O194 -> 11302661
A27: PENSION DEDUCTIONS | G27: ='Employee Pensions'!F195 -> 4564480.7
A28: TOTAL DEDUCTIONS FOR FEBRUARY 2024 | H28: =G23+G24+G26+G25+G27 -> 28089619
A29: NET PAY AS PER FEBRUARY, 2024 PAYROLL | H29: =H20-H28 -> 73861003
A30: NET PAY AS PER JANUARY, 2024 PAYROLL | H30: ='FEBRUARY 2024'!R194 -> 33238252
A31: NET INCREASE/ (DECREASE) IN PAY FOR FEBRUARY, 2024 | H31: =H29-H30 -> 40622751
A32: ANALYSED AS FOLLOWS:
A33: Effect of Cooperative Adjustment for February, 2024 | H33: -152000
A34: Effect of Increase in Gross Salary due to change in Salary Scale | H34: -26073904
A35: Effect of Increase in PAYE Tax due to change in Salary Scale | H35: =4073085.37 -> 4073085.4
A36: Effect of 8% Employee Pension deductions in February change in Salary Scale | H36: =4564480.74 -> 4564480.7
A37: Salary Arrears for the Month of January 2024 to all Staff | H37: =-22700818.57 -> -22700819
A38: Effect Regularisation of Taxes of Dr. Augustine Osigwe & 17 others | H38: =-224761.32 -> -224761.32
A39: Effect of Arrears due to over deduction of Tax of Dr. Idris Ibrahim | H39: =-6517.49 -> -6517.49
A40: Net Effect of Arrears ifo Jamila Abdul due to Upgrade in Grade Level | H40: -37675.34
A41: Net Effect of Research Allowance to Ayobolu Olufunso | H41: -64640
H42: =SUM(H33:H41) -> -40622751
E44: JANUARY, 2023 | G44: FEBRUARY, 2024
E45: No. of Staff | F45: N | G45: No. of Staff | H45: N
A46: 1 | B46: Director General's Office | E46: 33 | F46: ='FEBRUARY 2024'!R34 -> 8717267.3 | G46: ='FEBRUARY 2024'!C34 -> 27 | H46: ='FEBRUARY 2024'!S34 -> 16449658
A47: 2 | B47: Internal Audit | E47: 2 | F47: ='FEBRUARY 2024'!R40 -> 925705.68 | G47: ='FEBRUARY 2024'!C40 -> 3 | H47: ='FEBRUARY 2024'!S40 -> 2313476
A48: 3 | B48: Legis. Support Services | E48: 11 | F48: ='FEBRUARY 2024'!R54 -> 2615777.9 | G48: ='FEBRUARY 2024'!C54 -> 11 | H48: ='FEBRUARY 2024'!S54 -> 6448076.3
A49: 4 | B49: Legal Services | E49: 2 | F49: ='FEBRUARY 2024'!R59 -> 817858.82 | G49: ='FEBRUARY 2024'!C59 -> 2 | H49: ='FEBRUARY 2024'!S59 -> 2191750.6
A50: 5 | B50: Democracy and Governance | E50: 13 | F50: ='FEBRUARY 2024'!R72 -> 2517999.6 | G50: ='FEBRUARY 2024'!C72 -> 12 | H50: ='FEBRUARY 2024'!S72 -> 5781033.7
A51: 6 | B51: Studies | E51: 4 | F51: ='FEBRUARY 2024'!R82 -> 2118161.3 | G51: ='FEBRUARY 2024'!C82 -> 7 | H51: ='FEBRUARY 2024'!S82 -> 4673908
A52: 7 | B52: Economic Dev. & Social Research | E52: 12 | F52: ='FEBRUARY 2024'!R95 -> 2874739.8 | G52: ='FEBRUARY 2024'!C95 -> 11 | H52: ='FEBRUARY 2024'!S95 -> 5670163.9
A53: 8 | B53: Training & Int'l Cooperation | E53: 4 | F53: ='FEBRUARY 2024'!R102 -> 870039.76 | G53: ='FEBRUARY 2024'!C102 -> 4 | H53: ='FEBRUARY 2024'!S102 -> 2099662.4
A54: 9 | B54: Library & Documentation | E54: 8 | F54: ='FEBRUARY 2024'!R112 -> 1943184.8 | G54: ='FEBRUARY 2024'!C112 -> 7 | H54: ='FEBRUARY 2024'!S112 -> 4542081.7
A55: 10 | B55: Leg. Center for Security Analysis | E55: 2 | F55: ='FEBRUARY 2024'!R118 -> 732856.3 | G55: ='FEBRUARY 2024'!C118 -> 2 | H55: ='FEBRUARY 2024'!S118 -> 1577913.9
A56: 11 | B56: Finance and Accounts | E56: 9 | F56: ='FEBRUARY 2024'!R131 -> 2223207.6 | G56: ='FEBRUARY 2024'!C131 -> 10 | H56: ='FEBRUARY 2024'!S131 -> 5656464.1
A57: 12 | B57: Admin & Human Resource | E57: 58 | F57: ='FEBRUARY 2024'!R193 -> 6881453.5 | G57: ='FEBRUARY 2024'!C193 -> 59 | H57: ='FEBRUARY 2024'!S193 -> 16456814
E58: =SUM(E46:E57) -> 158 | F58: =SUM(F46:F57) -> 33238252 | G58: 154 | H58: =SUM(H46:H57) -> 73861003
A60: The Director General is requested to consider and approve payment of N73,861,002.93 to Guaranty Trust Bank being February, 2024 Salary, N12,199,445.68 being NILDS Coop Society deductions for February 2024, N11,302,661.13 being PAYE Tax Deductions from Staff Salary for the month of February 2024 and N23,031.31 being NHF deductions from staff for February 2024
A64: RAHILA NURUDEEN HABU
C168: =10000 -> 10000

Sheet January Arrears
A1: NATIONAL INSTITUTE FOR LEGISLATIVE AND DEMOCRATIC STUDIES
A2: COMPUTATION OF JANUARY 2024 ARREARS
E3: ='[1]FEB 08'!E11/'[1]FEB 08'!M11 -> #REF!
B4: STAFF NAME | C4: DESIGNATION | D4: GRADE LEVEL | E4: SALARY | F4: AREARS | G4: RESEARCH ALLOW. | H4: HARDSHIP ALLOW. | I4: DUTY ALLCE | J4: NEW GROSS SALARY | K4: OLD GROSS SALARY | L4: VARIATION IN GROSS SALARY | M4: NEW PAYE TAX | N4: OLD PAYE TAX | O4: VARIATION IN PAYE TAX | Q4: JANUARY 2024 ARREARS
L5: A | O5: B | Q5: (A-B)
A6: S/N | B6: DG'S OFFICE | E6: N | F6: N | G6: N | H6: N | I6: N | J6: N | K6: N | L6: N | M6: N | N6: N | O6: N | Q6: N
A7: 1 | B7: PROF. ABUBAKAR O. SULAIMAN | C7: DIRECTOR GENERAL | D7: CONSOL | E7: 1659751.2 | G7: =250000 -> 250000 | I7: 25235 | J7: =E7+F7+G7+H7+I7 -> 1934986.2 | K7: 1158849.8 | L7: =J7-K7 -> 776136.33 | M7: 350184.01 | N7: 201165.84 | O7: =M7-N7 -> 149018.17 | Q7: =L7-O7 -> 627118.15
A8: 2 | B8: RAHEEM USMAN AYIGORO | C8: SA-INFRASTRUCTURE | D8: 16 (9) | E8: 762373.17 | H8: =90000 -> 90000 | I8: 0 | J8: =E8+F8+G8+H8+I8 -> 852373.17 | K8: 541465.02 | L8: =J8-K8 -> 310908.14 | M8: 130612.26 | N8: 82627.951 | O8: =M8-N8 -> 47984.311 | Q8: =L8-O8 -> 262923.83
A9: 3 | B9: MARIAM MOHAMMED BELLO | C9: SA- SPECIAL DUTIES | D9: 16 (9) | E9: 762373.17 | H9: =90000 -> 90000 | I9: =100000+100000 -> 200000 | J9: =E9+F9+G9+H9+I9 -> 1052373.2 | K9: 741465.02 | L9: =J9-K9 -> 310908.14 | M9: 180722.31 | N9: 121027.95 | O9: =M9-N9 -> 59694.363 | Q9: =L9-O9 -> 251213.78
A10: 4 | B10: DR IKEME ARTHUR J.O | C10: DEPUTY DIRECTOR, M&E | D10: 16 (9) | E10: 762373.17 | G10: 180000 | I10: 0 | J10: =E10+F10+G10+H10+I10 -> 942373.17 | K10: 631465.02 | L10: =J10-K10 -> 310908.14 | M10: 147687.53 | N10: 99703.216 | O10: =M10-N10 -> 47984.311 | Q10: =L10-O10 -> 262923.83
A11: 5 | B11: MOSHOOD M. OLALERE | C11: PPS TO DG | D11: 16 (9) | E11: 762373.17 | H11: =80000+10000 -> 90000 | I11: 150000 | J11: =E11+F11+G11+H11+I11 -> 1002373.2 | K11: 691465.02 | L11: =J11-K11 -> 310908.14 | M11: 159207.53 | N11: 111223.22 | O11: =M11-N11 -> 47984.311 | Q11: =L11-O11 -> 262923.83
A12: 6 | B12: REKIYA IBRAHIM ATTAH | C12: DEPUTY DIRECTOR TRAINING | D12: 16 (9) | E12: 762373.17 | H12: =90000 -> 90000 | I12: 100000 | J12: =E12+F12+G12+H12+I12 -> 952373.17 | K12: 641465.02 | L12: =J12-K12 -> 310908.14 | M12: 161522.31 | N12: 101827.95 | O12: =M12-N12 -> 59694.363 | Q12: =L12-O12 -> 251213.78
A13: 7 | B13: ANDRAWUS MUSA | C13: ASST. DIRECTOR, STORES | D13: 15(9) | E13: 620675.58 | H13: =80000 -> 80000 | I13: 50000 | J13: =E13+F13+G13+H13+I13 -> 750675.58 | K13: 497553.5 | L13: =J13-K13 -> 253122.08 | M13: 113101.97 | N13: 74036.103 | O13: =M13-N13 -> 39065.863 | Q13: =L13-O13 -> 214056.22
A14: 8 | B14: DR FRANCIS NDUM OJIE | C14: AD, TRAINING & IC./SA TO DG | D14: 15(7) | E14: 582118.08 | G14: 160000 | I14: =100000 -> 100000 | J14: =E14+F14+G14+H14+I14 -> 842118.08 | K14: 604729.22 | L14: =J14-K14 -> 237388.86 | M14: 131263.11 | N14: 94625.782 | O14: =M14-N14 -> 36637.328 | Q14: =L14-O14 -> 200751.53
A15: 9 | B15: ALI ABDULLAHI | C15: CHIEF ICT OFFICER | D15: 14(11) | E15: 484373.75 | H15: =70000 -> 70000 | I15: =0 -> 0 | J15: =E15+F15+G15+H15+I15 -> 554373.75 | K15: 343333.04 | L15: =J15-K15 -> 211040.71 | M15: 77666.446 | N15: 44846.617 | O15: =M15-N15 -> 32819.829 | Q15: =L15-O15 -> 178220.89
A16: 10 | B16: EMILY EKHIDE | C16: RESEARCH FELLOW 1 | D16: 14(10) | E16: 470498 | G16: 140000 | I16: 50000 | J16: =E16+F16+G16+H16+I16 -> 660498 | K16: 463333.04 | L16: =J16-K16 -> 197164.96 | M16: 98255.433 | N16: 67626.609 | O16: =M16-N16 -> 30628.824 | Q16: =L16-O16 -> 166536.14
A17: 11 | B17: DORIS DAKDA AARON | C17: RESEARCH FELLOW I | D17: 14(8) | E17: 442746.5 | G17: =140000 -> 140000 | I17: 150000 | J17: =E17+F17+G17+H17+I17 -> 732746.5 | K17: 547211.37 | L17: =J17-K17 -> 185535.13 | M17: 112553.41 | N17: 83731.249 | O17: =M17-N17 -> 28822.159 | Q17: =L17-O17 -> 156712.97
A18: 12 | B18: ABDULSALAM S. MUSTAPHA | C18: ASST. MANAGER ICT | D18: 13(11) | E18: 441804.92 | H18: 70000 | J18: =E18+F18+G18+H18+I18 -> 511804.92 | K18: 326663.08 | L18: =J18-K18 -> 185141.84 | M18: 70147.087 | N18: 42046.064 | O18: =M18-N18 -> 28101.023 | Q18: =L18-O18 -> 157040.82
A19: 13 | B19: PERCY TERFA GBAHABO | C19: HEAD, NILDS LIAISON OFFICE | D19: 13(10) | E19: 428915.92 | G19: =120000 -> 120000 | I19: 0 | J19: =E19+F19+G19+H19+I19 -> 548915.92 | K19: 369177.65 | L19: =J19-K19 -> 179738.26 | M19: 77470.374 | N19: 49548.776 | O19: =M19-N19 -> 27921.598 | Q19: =L19-O19 -> 151816.66
A20: 14 | B20: HASSANA AHMED IBRAHIM | C20: PA- TRAINING | D20: 13 (9) | E20: 416026.92 | G20: =120000 -> 120000 | I20: =100000 -> 100000 | J20: =E20+F20+G20+H20+I20 -> 636026.92 | K20: 462001.06 | L20: =J20-K20 -> 174025.86 | M20: 94274.903 | N20: 67370.87 | O20: =M20-N20 -> 26904.033 | Q20: =L20-O20 -> 147121.82
A21: 15 | B21: ADUGBA RICHARD TERSEER | C21: PRINCIPAL INFO. OFFICER | D21: 12(9) | E21: 377895.17 | H21: =60000 -> 60000 | I21: 100000 | J21: =E21+F21+G21+H21+I21 -> 537895.17 | K21: 384537 | L21: =J21-K21 -> 153358.17 | M21: 76138.069 | N21: 52497.77 | O21: =M21-N21 -> 23640.299 | Q21: =L21-O21 -> 129717.87
A22: 16 | B22: LUCKY AGWOM | C22: PA-TECHNICAL | D22: 12(7) | E22: 353512.5 | G22: =100000 -> 100000 | I22: 100000 | J22: =E22+F22+G22+H22+I22 -> 553512.5 | K22: 400372.08 | L22: =J22-K22 -> 153140.42 | M22: 79511.115 | N22: 55538.105 | O22: =M22-N22 -> 23973.01 | Q22: =L22-O22 -> 129167.42
A23: 17 | B23: IDRIS IBRAHIM | C23: PRINCIPAL RESEARCH OFFICER | D23: 12(7) | E23: 353512.5 | G23: 110000 | I23: 0 | J23: =E23+F23+G23+H23+I23 -> 463512.5 | K23: =1015372.075-700000 -> 315372.07 | L23: =J23-K23 -> 148140.43 | M23: 62231.115 | N23: 40149.175 | O23: =M23-N23 -> 22081.939 | Q23: =L23-O23 -> 126058.49
A24: 18 | B24: FARUQ ATOFARATI | C24: PA (SPECIAL DUTIES) TO DG | D24: 10(7) | E24: 293029.67 | H24: =50000+10000 -> 60000 | I24: 100000 | J24: =E24+F24+G24+H24+I24 -> 453029.67 | K24: 328602.08 | L24: =J24-K24 -> 124427.59 | M24: 61147.427 | N24: 42371.816 | O24: =M24-N24 -> 18775.611 | Q24: =L24-O24 -> 105651.98
A25: 19 | B25: ELIZABETH OGECHUKWU ONYEAKU | C25: ICT OFFICER | D25: 9(9) | E25: 270481.67 | H25: =50000+10000 -> 60000 | J25: =E25+F25+G25+H25+I25 -> 330481.67 | K25: 213508.01 | L25: =J25-K25 -> 116973.66 | M25: 39052.313 | N25: 23036.012 | O25: =M25-N25 -> 16016.301 | Q25: =L25-O25 -> 100957.36
A26: 20 | B26: VICTOR ASUKWO | C26: ICT OFFICER | D26: 9(9) | E26: 270481.67 | H26: =50000+10000 -> 60000 | J26: =E26+F26+G26+H26+I26 -> 330481.67 | K26: 213508.01 | L26: =J26-K26 -> 116973.66 | M26: 39052.313 | N26: 23036.012 | O26: =M26-N26 -> 16016.301 | Q26: =L26-O26 -> 100957.36
A27: 21 | B27: NNANDI LIVINUS ATURE | C27: RESEARCH ASSISTANT | D27: 9(9) | E27: 270481.67 | G27: =100000 -> 100000 | J27: =E27+F27+G27+H27+I27 -> 370481.67 | K27: 253508.01 | L27: =J27-K27 -> 116973.66 | M27: 45772.313 | N27: 29756.012 | O27: =M27-N27 -> 16016.301 | Q27: =L27-O27 -> 100957.36
A28: 22 | B28: ABDULRAHMAN A SULAIMAN | C28: STORE OFFICER | D28: 9(8) | E28: 263165.33 | H28: =60000 -> 60000 | J28: =E28+F28+G28+H28+I28 -> 323165.33 | K28: 209356.05 | L28: =J28-K28 -> 113809.29 | M28: 37921.501 | N28: 22338.483 | O28: =M28-N28 -> 15583.018 | Q28: =L28-O28 -> 98226.268
A29: 23 | B29: DARE SHEU MAGBON | C29: ADMINISTRATION OFFICER | D29: 9(7) | E29: 255849 | H29: =60000 -> 60000 | J29: =E29+F29+G29+H29+I29 -> 315849 | K29: 205204.08 | L29: =J29-K29 -> 110644.92 | M29: 36790.688 | N29: 21640.953 | O29: =M29-N29 -> 15149.735 | Q29: =L29-O29 -> 95495.18
A30: 24 | B30: ABUBAKAR SULAIMAN SODEEQ | C30: ADMINISTRATION OFFICER | D30: 9(7) | E30: 255849 | H30: =60000 -> 60000 | J30: =E30+F30+G30+H30+I30 -> 315849 | K30: 205204.08 | L30: =J30-K30 -> 110644.92 | M30: 36790.688 | N30: 21640.953 | O30: =M30-N30 -> 15149.735 | Q30: =L30-O30 -> 95495.18
A31: 25 | B31: JIMOH ADEBAYO ZAKA | C31: ASST. OFFICER/COMM | D31: 9(9) | E31: 270481.67 | H31: =60000 -> 60000 | J31: =E31+F31+G31+H31+I31 -> 330481.67 | K31: 209356.05 | L31: =J31-K31 -> 121125.62 | M31: 39052.313 | N31: 22338.483 | O31: =M31-N31 -> 16713.83 | Q31: =L31-O31 -> 104411.79
A32: 26 | B32: MOHAMMED BELLO | C32: PROTOCOL ASSISTANT | D32: 8(9) | E32: 230631.92 | H32: =50000 -> 50000 | J32: =E32+F32+G32+H32+I32 -> 280631.92 | K32: 180304.07 | L32: =J32-K32 -> 100327.85 | M32: 31213.136 | N32: 17572.885 | O32: =M32-N32 -> 13640.251 | Q32: =L32-O32 -> 86687.598
A33: 27 | B33: HARUNA JIBRIL AMEH | C33: ASST. ADMIN. OFFICER | D33: 8(8) | E33: 224459.75 | H33: 50000 | J33: =E33+F33+G33+H33+I33 -> 274459.75 | K33: 173329.05 | L33: =J33-K33 -> 101130.7 | M33: 30259.166 | N33: 16512.682 | O33: =M33-N33 -> 13746.483 | Q33: =L33-O33 -> 87384.217
B34: TOTAL | C34: 27 | E34: =SUM(E7:E33) -> 13048608 | F34: =SUM(F7:F33) -> 0 | G34: =SUM(G7:G33) -> 1420000 | H34: =SUM(H7:H33) -> 1160000 | I34: =SUM(I7:I33) -> 1225235 | J34: =SUM(J7:J33) -> 16853843 | K34: =SUM(K7:K33) -> 11312338 | L34: =SUM(L7:L33) -> 5541505.6 | ... O34: =SUM(O7:O33) -> 889763.31 | Q34: =SUM(Q7:Q33) -> 4651742.3
B36: INTERNAL AUDIT
A37: 1 | B37: OSANAIYE DAVID AKINYEMI | C37: DIRECTOR INTERNAL AUDIT | D37: 17(9) | E37: 1435720 | H37: =100000 -> 100000 | J37: =E37+F37+G37+H37+I37 -> 1535720 | K37: 950209.06 | L37: =J37-K37 -> 585510.94 | M37: 251472.25 | N37: 161106.81 | O37: =M37-N37 -> 90365.441 | Q37: =L37-O37 -> 495145.5
A38: 2 | B38: JAMILA ABDUL | C38: SENIOR INTERNAL AUDITOR | D38: 10(7) | E38: 293029.67 | H38: =60000 -> 60000 | J38: =E38+F38+G38+H38+I38 -> 353029.67 | K38: 176816.1 | L38: =J38-K38 -> 176213.57 | M38: 42537.332 | N38: 17042.714 | O38: =M38-N38 -> 25494.618 | Q38: =L38-O38 -> 150718.95
A39: 3 | B39: IJEOMA EWELUKWA | C39: AUDIT OFFICER | D39: 10(8) | E39: 300965.58 | H39: =50000+10000 -> 60000 | J39: =E39+F39+G39+H39+I39 -> 360965.58 | K39: 233169.12 | L39: =J39-K39 -> 127796.47 | M39: 43763.907 | N39: 26339.078 | O39: =M39-N39 -> 17424.829 | Q39: =L39-O39 -> 110371.64
C40: 3 | E40: =SUM(E37:E39) -> 2029715.2 | F40: =SUM(F37:F39) -> 0 | G40: =SUM(G37:G39) -> 0 | H40: =SUM(H37:H39) -> 220000 | I40: =SUM(I37:I39) -> 0 | J40: =SUM(J37:J39) -> 2249715.2 | K40: 1360194.3 | L40: =SUM(L37:L39) -> 889520.97 | M40: =SUM(M37:M39) -> 337773.49 | N40: 204488.6 | O40: =SUM(O37:O39) -> 133284.89 | Q40: =SUM(Q37:Q39) -> 756236.08
B42: LEG. SUPPORT SEVICES
A43: 1 | B43: PROF. EDOBA BRIGHT OMOREGBE | C43: AG. DLSS | D43: 17(9) | E43: 1435720 | G43: =200000 -> 200000 | J43: =E43+F43+G43+H43+I43 -> 1635720 | K43: 1050209.1 | L43: =J43-K43 -> 585510.94 | M43: 270672.25 | N43: 180306.81 | O43: =M43-N43 -> 90365.441 | Q43: =L43-O43 -> 495145.5
A44: 2 | B44: DR CLINTON JAJA | C44: SENIOR RESEARCH FELLOW | D44: 15(9) | E44: 620675.58 | G44: =160000 -> 160000 | I44: 0 | J44: =E44+F44+G44+H44+I44 -> 780675.58 | K44: 527553.5 | L44: =J44-K44 -> 253122.08 | M44: 119022.8 | N44: 79956.939 | O44: =M44-N44 -> 39065.863 | Q44: =L44-O44 -> 214056.22
A45: 3 | B45: BETHEL UZOMA IHUGBA | C45: DEPUTY DIRECTOR, LEGAL RESEARCH | D45: 16(8) | E45: 739203.58 | G45: =180000 -> 180000 | J45: =E45+F45+G45+H45+I45 -> 919203.58 | K45: 617744 | L45: =J45-K45 -> 301459.59 | M45: 143799.59 | N45: 97273.514 | O45: =M45-N45 -> 46526.074 | Q45: =L45-O45 -> 254933.51
A46: 4 | B46: OGUCHE SAMUEL | C46: SNR RESEARCH FELLOW | D46: 15(9) | E46: 620675.58 | G46: =160000 -> 160000 | J46: =E46+F46+G46+H46+I46 -> 780675.58 | K46: 527553.5 | L46: =J46-K46 -> 253122.08 | M46: 119022.8 | N46: 79956.939 | O46: =M46-N46 -> 39065.863 | Q46: =L46-O46 -> 214056.22
A47: 5 | B47: IBRAHIM USMAN | C47: SNR RESEARCH FELLOW | D47: 15(9) | E47: 620675.58 | G47: =140000+20000 -> 160000 | I47: 0 | J47: =E47+F47+G47+H47+I47 -> 780675.58 | K47: 527553.5 | L47: =J47-K47 -> 253122.08 | M47: 118861.97 | N47: 79796.103 | O47: =M47-N47 -> 39065.863 | Q47: =L47-O47 -> 214056.22
A48: 6 | B48: DR MOHAMMED O. AMALI | C48: SNR RESEARCH FELLOW | D48: 15(7) | E48: 582118.08 | G48: =140000+20000 -> 160000 | J48: =E48+F48+G48+H48+I48 -> 742118.08 | K48: 504720.05 | L48: =J48-K48 -> 237398.04 | M48: 112212 | N48: 75572.916 | O48: =M48-N48 -> 36639.089 | Q48: =L48-O48 -> 200758.95
A49: 7 | B49: YAHAYA SHAMSU | C49: RESEARCH FELLOW 1 | D49: 14(10) | E49: 470498 | G49: =140000 -> 140000 | J49: =E49+F49+G49+H49+I49 -> 610498 | K49: 413333.04 | L49: =J49-K49 -> 197164.96 | M49: 88655.433 | N49: 58026.609 | O49: =M49-N49 -> 30628.824 | Q49: =L49-O49 -> 166536.14
A50: 8 | B50: BILKIS S. LAWAL-GAMBARI | C50: RESEARCH OFFICER | D50: 10(8) | E50: 300965.58 | G50: 100000 | J50: =E50+F50+G50+H50+I50 -> 400965.58 | K50: 273169.12 | L50: =J50-K50 -> 127796.47 | M50: 51029.227 | N50: 33059.078 | O50: =M50-N50 -> 17970.149 | Q50: =L50-O50 -> 109826.32
A51: 9 | B51: ZAINAB AKINDE | C51: RESEARCH OFFICER | D51: 9(8) | E51: 263165.33 | G51: =100000 -> 100000 | J51: =E51+F51+G51+H51+I51 -> 363165.33 | K51: 249356.05 | L51: =J51-K51 -> 113809.29 | M51: 44641.501 | N51: 29058.483 | O51: =M51-N51 -> 15583.018 | Q51: =L51-O51 -> 98226.268
A52: 10 | B52: ABDULLAHI AHMAD USMAN | C52: RESEARCH OFFICER | D52: 9(8) | E52: 263165.33 | G52: =100000 -> 100000 | J52: =E52+F52+G52+H52+I52 -> 363165.33 | K52: 249356.05 | L52: =J52-K52 -> 113809.29 | M52: 44641.501 | N52: 28360.953 | O52: =M52-N52 -> 16280.548 | Q52: =L52-O52 -> 97528.738
A53: 11 | B53: GUNAT NANSAK MARK | C53: RESEARCH OFFICER | D53: 9(8) | E53: 263165.33 | G53: =100000 -> 100000 | J53: =E53+F53+G53+H53+I53 -> 363165.33 | K53: 249356.05 | L53: =J53-K53 -> 113809.29 | M53: 44641.501 | N53: 29058.483 | O53: =M53-N53 -> 15583.018 | Q53: =L53-O53 -> 98226.268
B54: TOTAL | C54: 11 | E54: =SUM(E43:E53) -> 6180028 | F54: =SUM(F43:F53) -> 0 | G54: =SUM(G43:G53) -> 1560000 | H54: =SUM(H43:H53) -> 0 | I54: =SUM(I43:I53) -> 0 | J54: =SUM(J43:J53) -> 7740028 | K54: 5189903.9 | L54: =SUM(L43:L53) -> 2550124.1 | M54: =SUM(M43:M53) -> 1157200.6 | N54: 770426.82 | O54: =SUM(O43:O53) -> 386773.75 | Q54: =SUM(Q43:Q53) -> 2163350.3
B56: LEGAL SERVICES
A57: 1 | B57: DR SHUIBU DANWANKA | C57: DIRECTOR LEGAL SERVICES | D57: 17(9) | E57: 1435720 | G57: =200000 -> 200000 | I57: 0 | J57: =E57+F57+G57+H57+I57 -> 1635720 | K57: 1050209.1 | L57: =J57-K57 -> 585510.94 | M57: 270672.25 | N57: 180306.81 | O57: =M57-N57 -> 90365.441 | Q57: =L57-O57 -> 495145.5
A58: 2 | B58: ABDULSALAM BAKO | C58: MANAGER, LEGAL SERVICES | D58: 15 (9) | E58: 620675.58 | H58: 80000 | J58: =E58+F58+G58+H58+I58 -> 700675.58 | K58: 447553.5 | L58: =J58-K58 -> 253122.08 | M58: 103662.8 | N58: 64596.939 | O58: =M58-N58 -> 39065.863 | Q58: =L58-O58 -> 214056.22
B59: TOTAL | C59: 2 | E59: =SUM(E57:E58) -> 2056395.6 | F59: =SUM(F57:F58) -> 0 | G59: =SUM(G57:G58) -> 200000 | H59: =SUM(H57:H58) -> 80000 | I59: =SUM(I57:I58) -> 0 | J59: =SUM(J57:J58) -> 2336395.6 | K59: 1497762.6 | L59: =SUM(L57:L58) -> 838633.02 | M59: =SUM(M57:M58) -> 374335.05 | N59: 244903.75 | O59: =SUM(O57:O58) -> 129431.3 | Q59: =SUM(Q57:Q58) -> 709201.71
B61: DEMOCRACY & GOVERNANCE
A62: 1 | B62: DR. ADEWALE ADEREMI | C62: DIRECTOR, DEMOCRATIC STUDIES | D62: 17(9) | E62: 1435720 | G62: =200000 -> 200000 | I62: 0 | J62: =E62+F62+G62+H62+I62 -> 1635720 | K62: 1050209.1 | L62: =J62-K62 -> 585510.94 | M62: 292724.91 | N62: 180306.81 | O62: =M62-N62 -> 112418.1 | Q62: =L62-O62 -> 473092.84
A63: 2 | B63: NDANUSA MOHAMMED MANZUMA | C63: SNR RESEARCH FELLOW | D63: 15(8) | E63: 601396.83 | G63: =160000 -> 160000 | I63: 0 | J63: =E63+F63+G63+H63+I63 -> 761396.83 | K63: 516137.05 | L63: =J63-K63 -> 245259.78 | M63: 115617.4 | N63: 77764.98 | O63: =M63-N63 -> 37852.423 | Q63: =L63-O63 -> 207407.36
A64: 3 | B64: EJALONIBU GANIYU LAYI | C64: RESEARCH FELLOW 1 | D64: 14(8) | E64: 442746.5 | G64: 140000 | J64: =E64+F64+G64+H64+I64 -> 582746.5 | K64: 397211.37 | L64: =J64-K64 -> 185535.13 | M64: 83753.408 | N64: 54931.249 | O64: =M64-N64 -> 28822.159 | Q64: =L64-O64 -> 156712.97
A65: 4 | B65: LOHNA BONKAT JONATHAN | C65: RESEARCH FELLOW 11 | D65: 13(10) | E65: 428915.92 | G65: =120000 -> 120000 | I65: 0 | J65: =E65+F65+G65+H65+I65 -> 548915.92 | K65: 369177.65 | L65: =J65-K65 -> 179738.26 | M65: 77470.374 | N65: 49548.776 | O65: =M65-N65 -> 27921.598 | Q65: =L65-O65 -> 151816.66
A66: 5 | B66: YUNUSA ABDULLAHI | C66: RESEARCH FELLOW 1 | D66: 14(11) | E66: 484373.75 | G66: =140000 -> 140000 | J66: =E66+F66+G66+H66+I66 -> 624373.75 | K66: 421394.01 | L66: =J66-K66 -> 202979.74 | M66: 91106.446 | N66: 59574.316 | O66: =M66-N66 -> 31532.13 | Q66: =L66-O66 -> 171447.61
A67: 7 | B67: UDEFUNA NNADOZIE PATRICK | C67: RESEARCH OFFICER | D67: 12(8) | E67: 365703.83 | G67: =110000 -> 110000 | I67: 0 | J67: =E67+F67+G67+H67+I67 -> 475703.83 | K67: 322454.07 | L67: =J67-K67 -> 153249.76 | M67: 64384.592 | N67: 41338.951 | O67: =M67-N67 -> 23045.641 | Q67: =L67-O67 -> 130204.12
A68: 8 | B68: SHAFIU YAHYA MIKAIL | C68: PRINCIPAL RESEARCH OFFICER | D68: 12(8) | E68: 365703.83 | G68: =110000 -> 110000 | I68: 0 | J68: =E68+F68+G68+H68+I68 -> 475703.83 | K68: 322454.07 | L68: =J68-K68 -> 153249.76 | M68: 64384.592 | N68: 41338.951 | O68: =M68-N68 -> 23045.641 | Q68: =L68-O68 -> 130204.12
A69: 9 | B69: HASSAN YERIMA | C69: PRINCIPAL RESEARCH OFFICER | D69: 12(8) | E69: 365703.83 | G69: =110000 -> 110000 | I69: 0 | J69: =E69+F69+G69+H69+I69 -> 475703.83 | K69: 322454.07 | L69: =J69-K69 -> 153249.76 | M69: 64384.592 | N69: 41338.951 | O69: =M69-N69 -> 23045.641 | Q69: =L69-O69 -> 130204.12
A70: 10 | B70: HAUWA PATE SADIQ | C70: PRINCIPAL PROGRAMME OFFICER | D70: 12(9) | E70: 377895.17 | G70: =110000 -> 110000 | J70: =E70+F70+G70+H70+I70 -> 487895.17 | K70: 334537 | L70: =J70-K70 -> 153358.17 | M70: 66538.069 | N70: 43368.882 | O70: =M70-N70 -> 23169.186 | Q70: =L70-O70 -> 130188.98
A71: 11 | B71: KOLAPO Q. ABAYOMI | C71: RESEARCH OFFICER | D71: 10(8) | E71: 300965.58 | G71: 100000 | J71: =E71+F71+G71+H71+I71 -> 400965.58 | K71: 277734.05 | L71: =J71-K71 -> 123231.54 | M71: 51029.227 | N71: 33825.987 | O71: =M71-N71 -> 17203.241 | Q71: =L71-O71 -> 106028.3
B72: TOTAL | C72: 12 | E72: =SUM(E62:E71) -> 5169125.2 | F72: =SUM(F62:F71) -> 0 | G72: =SUM(G62:G71) -> 1300000 | H72: =SUM(H62:H71) -> 0 | I72: =SUM(I62:I71) -> 0 | J72: =SUM(J62:J71) -> 6469125.2 | K72: 4333762.4 | L72: =SUM(L62:L71) -> 2135362.8 | M72: =SUM(M62:M71) -> 971393.61 | N72: 623337.85 | O72: =SUM(O62:O71) -> 348055.76 | Q72: =SUM(Q62:Q71) -> 1787307.1
B74: DEPARTMENT OF STUDIES
A75: 1 | B75: DR ASIMIYU G. ABIOLA | C75: DIRECTOR POST GRADUATE | D75: 17(9) | E75: 1435720 | G75: =200000 -> 200000 | I75: 0 | J75: =E75+F75+G75+H75+I75 -> 1635720 | K75: 1050209.1 | L75: =J75-K75 -> 585510.94 | M75: 270672.25 | N75: 180306.81 | O75: =M75-N75 -> 90365.441 | Q75: =L75-O75 -> 495145.5
A76: 2 | B76: USMAN WALI | C76: SENIOR RESEARCH FELLOW | D76: 15 (8) | E76: 601396.83 | G76: =160000 -> 160000 | I76: 0 | J76: =E76+F76+G76+H76+I76 -> 761396.83 | K76: 516137.05 | L76: =J76-K76 -> 245259.78 | M76: 124854.86 | N76: 77764.98 | O76: =M76-N76 -> 47089.878 | Q76: =L76-O76 -> 198169.9
A77: 3 | B77: AYOBOLU OLAJIDE OLUFUNSHO | C77: ASST.DIR., INFORMATION | D77: 15 (9) | E77: 620675.58 | G77: 0 | H77: 80000 | I77: 0 | J77: =E77+F77+G77+H77+I77 -> 700675.58 | K77: 447553.5 | L77: =J77-K77 -> 253122.08 | M77: 113196.38 | N77: 64596.939 | O77: =M77-N77 -> 48599.44 | Q77: =L77-O77 -> 204522.64
A78: 4 | B78: ANTHONY EDET | C78: CHIEF PROGRAMMES OFFICER | D78: 14(9) | E78: 456622.25 | G78: =140000 -> 140000 | I78: 0 | J78: =E78+F78+G78+H78+I78 -> 596622.25 | K78: 405272.06 | L78: =J78-K78 -> 191350.19 | M78: 86076.104 | N78: 56350.586 | O78: =M78-N78 -> 29725.518 | Q78: =L78-O78 -> 161624.67
A79: 5 | B79: IGWE STACY | C79: PROGRAMME OFFICER | D79: 10(9) | E79: 308901.5 | G79: =100000 -> 100000 | J79: =E79+F79+G79+H79+I79 -> 408901.5 | K79: 273169.12 | L79: =J79-K79 -> 135732.38 | M79: 52431.028 | N79: 33059.078 | O79: =M79-N79 -> 19371.949 | Q79: =L79-O79 -> 116360.43
A80: 6 | B80: OLANIYAN TAIWO ABINBOLA | C80: PROGRAMME OFFICER | D80: 9(8) | E80: 263165.33 | G80: 100000 | J80: =E80+F80+G80+H80+I80 -> 363165.33 | K80: 249356.05 | L80: =J80-K80 -> 113809.29 | M80: 44641.501 | N80: 29058.483 | O80: =M80-N80 -> 15583.018 | Q80: =L80-O80 -> 98226.268
A81: 7 | B81: AMINAT JUMOKE SULAIMON | C81: AST. PROGRAMME OFFICER | D81: 8(8) | E81: 224459.75 | G81: 100000 | H81: 0 | J81: =E81+F81+G81+H81+I81 -> 324459.75 | K81: 223717.28 | L81: =J81-K81 -> 100742.47 | M81: 38659.166 | N81: 24751.17 | O81: =M81-N81 -> 13907.995 | Q81: =L81-O81 -> 86834.47
B82: TOTAL | C82: 7 | E82: =SUM(E75:E81) -> 3910941.3 | F82: =SUM(F75:F81) -> 0 | G82: =SUM(G75:G81) -> 800000 | H82: =SUM(H75:H81) -> 80000 | I82: =SUM(I75:I81) -> 0 | J82: =SUM(J75:J81) -> 4790941.2 | K82: 3165414.1 | L82: =SUM(L75:L81) -> 1625527.1 | M82: =SUM(M75:M81) -> 730531.28 | N82: 465888.04 | O82: =SUM(O75:O81) -> 264643.24 | Q82: =SUM(Q75:Q81) -> 1360883.9
B84: ECON. DEV. & SOC. RESEARCH
A85: 1 | B85: TERFA WILLIAMS ABRAHAM | C85: SNR RESEARCH FELLOW | D85: 15(9) | E85: 620675.58 | G85: =160000 -> 160000 | I85: 100000 | J85: =E85+F85+G85+H85+I85 -> 880675.58 | K85: 627553.5 | L85: =J85-K85 -> 253122.08 | M85: 138222.8 | N85: 99156.939 | O85: =M85-N85 -> 39065.863 | Q85: =L85-O85 -> 214056.22
A86: 2 | B86: DR AUGUSTINE C. OSIGWE | C86: SNR RESEARCH FELLOW | D86: 15(9) | E86: 620675.58 | G86: =160000 -> 160000 | J86: =E86+F86+G86+H86+I86 -> 780675.58 | K86: 527553.5 | L86: =J86-K86 -> 253122.08 | M86: 118861.97 | N86: 79796.103 | O86: =M86-N86 -> 39065.863 | Q86: =L86-O86 -> 214056.22
A87: 3 | B87: OMOJU OLUWASOLA EMMANUEL | C87: SNR RESEARCH FELLOW | D87: 15(7) | E87: 582118.08 | G87: 160000 | J87: =E87+F87+G87+H87+I87 -> 742118.08 | K87: 504729.22 | L87: =J87-K87 -> 237388.86 | M87: 112212 | N87: 75574.677 | O87: =M87-N87 -> 36637.328 | Q87: =L87-O87 -> 200751.53
A88: 4 | B88: IBE EZECHI CYRIACUS | C88: RESEARCH FELLOW II | D88: 13(11) | E88: 441804.92 | G88: =120000 -> 120000 | I88: 0 | J88: =E88+F88+G88+H88+I88 -> 561804.92 | K88: 376663.08 | L88: =J88-K88 -> 185141.84 | M88: 79747.087 | N88: 50985.978 | O88: =M88-N88 -> 28761.11 | Q88: =L88-O88 -> 156380.73
A89: 5 | B89: OSIKHEN LEO IGBANOI | C89: RESEARCH FELLOW 11 | D89: 13(10) | E89: 428915.92 | G89: =120000 -> 120000 | I89: 0 | J89: =E89+F89+G89+H89+I89 -> 548915.92 | K89: 369177.65 | L89: =J89-K89 -> 179738.26 | M89: 77470.374 | N89: 49548.776 | O89: =M89-N89 -> 27921.598 | Q89: =L89-O89 -> 151816.66
A90: 6 | B90: OKUNGBOWA OSARETIN GODSPOWER | C90: RESEARCH FELLOW 1 | D90: 14(7) | E90: 428870.75 | G90: =140000 -> 140000 | I90: 0 | J90: =E90+F90+G90+H90+I90 -> 568870.75 | K90: 389153.06 | L90: =J90-K90 -> 179717.69 | M90: 81302.396 | N90: 53384.054 | O90: =M90-N90 -> 27918.342 | Q90: =L90-O90 -> 151799.35
A91: 7 | B91: YUSUF IBRAHIM | C91: PRINCIPAL RESEARCH OFFICER | D91: 12(8) | E91: 365703.83 | G91: =110000 -> 110000 | I91: 0 | J91: =E91+F91+G91+H91+I91 -> 475703.83 | K91: 322454.07 | L91: =J91-K91 -> 153249.76 | M91: 64384.592 | N91: 41338.951 | O91: =M91-N91 -> 23045.641 | Q91: =L91-O91 -> 130204.12
A92: 8 | B92: MUSTAPHA RAFIU AYOBANJI | C92: RESEARCH FELLOW 11 | D92: 13(7) | E92: 390248.92 | G92: 120000 | I92: 0 | J92: =E92+F92+G92+H92+I92 -> 510248.92 | K92: 346713.03 | L92: =J92-K92 -> 163535.88 | M92: 70529.475 | N92: 45317.541 | O92: =M92-N92 -> 25211.934 | Q92: =L92-O92 -> 138323.95
A93: 9 | B93: MARYAM MUSA SADA | C93: ASSIT. RESEARCH OFFICER | D93: 10(8) | E93: 300965.58 | G93: 100000 | J93: =E93+F93+G93+H93+I93 -> 400965.58 | K93: 277734.05 | L93: =J93-K93 -> 123231.54 | M93: 51029.227 | N93: 33825.987 | O93: =M93-N93 -> 17203.241 | Q93: =L93-O93 -> 106028.3
A94: 10 | B94: CHARITY EZENWAJIOBI | C94: REASEARCH. ASST. | D94: 8(9) | E94: 230631.92 | G94: =100000 -> 100000 | J94: =E94+F94+G94+H94+I94 -> 330631.92 | K94: 254870.26 | L94: =J94-K94 -> 75761.653 | M94: 39613.136 | N94: 29984.871 | O94: =M94-N94 -> 9628.2648 | Q94: =L94-O94 -> 66133.388
B95: TOTAL | C95: 11 | E95: =SUM(E85:E94) -> 4410611.1 | F95: =SUM(F85:F94) -> 0 | G95: =SUM(G85:G94) -> 1290000 | H95: =SUM(H85:H94) -> 0 | I95: =SUM(I85:I94) -> 100000 | J95: =SUM(J85:J94) -> 5800611.1 | K95: 3996601.4 | L95: =SUM(L85:L94) -> 1804009.7 | M95: =SUM(M85:M94) -> 833373.06 | N95: 558913.88 | O95: =SUM(O85:O94) -> 274459.18 | Q95: =SUM(Q85:Q94) -> 1529550.5
B97: TRAINING & INT''L COOP
A98: 1 | B98: AKINSANMI ADEJOKE OLUKEMI | C98: Ag. DIR. TRAINING & IC | D98: 16(9) | E98: 762373.17 | H98: =80000+10000 -> 90000 | J98: =E98+F98+G98+H98+I98 -> 852373.17 | K98: 541465.02 | L98: =J98-K98 -> 310908.14 | M98: 130407.53 | N98: 82423.216 | O98: =M98-N98 -> 47984.311 | Q98: =L98-O98 -> 262923.83
A99: 2 | B99: MOHAMMED R. ADAMU | C99: CHIEF TRAINING OFFICER | D99: 14(9) | E99: 456622.25 | H99: 70000 | I99: 0 | J99: =E99+F99+G99+H99+I99 -> 526622.25 | K99: 335272.06 | L99: =J99-K99 -> 191350.19 | M99: 72764.421 | N99: 43492.373 | O99: =M99-N99 -> 29272.048 | Q99: =L99-O99 -> 162078.14
A100: 3 | B100: OKECHUKWU UCHENNA HULDA | C100: PRINCIPALTRAINING OFFICER | D100: 12(9) | E100: 377895.17 | H100: =60000 -> 60000 | J100: =E100+F100+G100+H100+I100 -> 437895.17 | K100: 284537 | L100: =J100-K100 -> 153358.17 | M100: 56938.069 | N100: 34968.882 | O100: =M100-N100 -> 21969.186 | Q100: =L100-O100 -> 131388.98
A101: 4 | B101: TASSNEEM IBRAHIM | C101: SENIOR PROGRAMME OFFICER | D101: 10(8) | E101: 300965.58 | H101: =60000 -> 60000 | J101: =E101+F101+G101+H101+I101 -> 360965.58 | K101: 237734.05 | L101: =J101-K101 -> 123231.54 | M101: 43763.907 | N101: 27105.987 | O101: =M101-N101 -> 16657.921 | Q101: =L101-O101 -> 106573.62
B102: TOTAL | C102: 4 | E102: =SUM(E98:E101) -> 1897856.2 | F102: =SUM(F98:F101) -> 0 | G102: =SUM(G98:G101) -> 0 | H102: =SUM(H98:H101) -> 280000 | I102: =SUM(I98:I101) -> 0 | J102: =SUM(J98:J101) -> 2177856.2 | K102: 1399008.1 | L102: =SUM(L98:L101) -> 778848.03 | M102: =SUM(M98:M101) -> 303873.92 | N102: 187990.46 | O102: =SUM(O98:O101) -> 115883.47 | Q102: =SUM(Q98:Q101) -> 662964.57
B104: LIBRARY & DOCUMENTATION
A105: 1 | B105: DR MAIMUNA IZAH | C105: INSITUTE LIBRARIAN | D105: 17(9) | E105: 1435720 | G105: =200000 -> 200000 | I105: 0 | J105: =E105+F105+G105+H105+I105 -> 1635720 | K105: 1050209.1 | L105: =J105-K105 -> 585510.94 | M105: 270672.25 | N105: 180306.81 | O105: =M105-N105 -> 90365.441 | Q105: =L105-O105 -> 495145.5
A106: 2 | B106: CATHERINE E. IKOKOH | C106: SNR RESEARCH FELLOW DOCU | D106: 16(9) | E106: 762373.17 | G106: =160000+20000 -> 180000 | I106: 0 | J106: =E106+F106+G106+H106+I106 -> 942373.17 | K106: 631465.02 | L106: =J106-K106 -> 310908.14 | M106: 147687.53 | N106: 99703.216 | O106: =M106-N106 -> 47984.311 | Q106: =L106-O106 -> 262923.83
A107: 3 | B107: ALIYU SANNI ABUBAKAR | C107: RESEARCH FELLOW 11 DATA & DOCU | D107: 13(11) | E107: 441804.92 | G107: =120000 -> 120000 | I107: 41432.939 | J107: =E107+F107+G107+H107+I107 -> 603237.86 | K107: 418096.02 | L107: =J107-K107 -> 185141.84 | M107: 87575.783 | N107: 58814.673 | O107: =M107-N107 -> 28761.11 | Q107: =L107-O107 -> 156380.73
A108: 4 | B108: CHINAKO N. ASOGWA | C108: RESEARCH FELLOW 11 DATA & DOCU | D108: 13(11) | E108: 441804.92 | G108: =120000 -> 120000 | I108: 39820.117 | J108: =E108+F108+G108+H108+I108 -> 601625.03 | K108: 416483.19 | L108: =J108-K108 -> 185141.84 | M108: 87392.55 | N108: 58631.44 | O108: =M108-N108 -> 28761.11 | Q108: =L108-O108 -> 156380.73
...

Sheet Tax Reg Sch. 
A1: NATIONAL INSTITUTE FOR LEGISLATIVE AND DEMOCRATIC STUDIES
A2: NATIONAL ASSEMBLY ABUJA
A3: TAX COMPUTATION FOR 2022
A4: S/NO | B4: NAME | C4: MONTHLY TOTAL SALARY | D4: NO OF MONTHS | E4: ANNUAL SALARY GROSSED UP | F4: NATIONAL HOUSING SCHEME = 2.5% OF BASIC SALARY | G4: PENSION CONTRIBUTION = 8% OF CONSOLIDATED | H4: NHIS | I4: NET SALARY (EXC OF CRA) | M4: CRA=#200,000+(20% 0F NET SALARY (EXC OF CRA) | N4: TOTAL RELIEF | O4: CHARGEABLE INCOME | P4: FIRST N300,000 @ 7% | Q4: NEXT N300,000 @ 11% | R4: NEXT N500,000 @ 15% | S4: NEXT N500,000@ 19% | T4: NEXT N1,600,000 @ 21% | U4: ABOVE N3,200,000 @ 24% | V4: ANNUAL TAX PAYABLE | X4: MONTHLY TAX PAYABLE | Y4: MINIMUM TAX PAYABLE | Z4: NEW ACTUAL TAX PAYABLE | AB4: Difference
A5: 1 | B5: DG'S OFFICE
A6: 3 | B6: PROF. ABUBAKAR O. SULAIMAN | C6: 1158849.8 | D6: 12 | E6: =C6*D6 -> 13906198 | I6: =E6-F6-G6-H6 -> 13906198 | J6: 200000 | K6: 0.2 | L6: =I6*K6 -> 2781239.6 | M6: =J6+L6 -> 2981239.6 | N6: =F6+G6+H6+M6 -> 2981239.6 | O6: =E6-N6 -> 10924958 | P6: =IF(O6<300000,0.07*O6,21000) -> 21000 | Q6: =IF((O6-300000)<0,0,IF((O6-300000)<300000,0.11*(O6-300000),33000)) -> 33000 | R6: =IF((O6-600000)<0,0,IF((O6-600000)<500000,0.15*(O6-600000),75000)) -> 75000 | S6: =IF((O6-1100000)<0,0,IF((O6-1100000)<500000,0.19*(O6-1100000),95000)) -> 95000 | T6: =IF((O6-1600000)<0,0,IF((O6-1600000)<1600000,0.21*(O6-1600000),336000)) -> 336000 | U6: =24%*(O6-3200000) -> 1853990 | V6: =P6+Q6+R6+S6+T6+U6 -> 2413990 | W6: 12 | X6: =V6/W6 -> 201165.84 | Z6: =X6 -> 201165.84 | AA6: 201165.84 | AB6: =Z6-AA6 -> 0
A7: 4 | B7: RAHEEM USMAN AYIGORO | C7: 541465.02 | D7: 12 | E7: =C7*D7 -> 6497580.3 | I7: =E7-F7-G7-H7 -> 6497580.3 | J7: 200000 | K7: 0.2 | L7: =I7*K7 -> 1299516.1 | M7: =J7+L7 -> 1499516.1 | N7: =F7+G7+H7+M7 -> 1499516.1 | O7: =E7-N7 -> 4998064.2 | P7: =IF(O7<300000,0.07*O7,21000) -> 21000 | Q7: =IF((O7-300000)<0,0,IF((O7-300000)<300000,0.11*(O7-300000),33000)) -> 33000 | R7: =IF((O7-600000)<0,0,IF((O7-600000)<500000,0.15*(O7-600000),75000)) -> 75000 | S7: =IF((O7-1100000)<0,0,IF((O7-1100000)<500000,0.19*(O7-1100000),95000)) -> 95000 | T7: =IF((O7-1600000)<0,0,IF((O7-1600000)<1600000,0.21*(O7-1600000),336000)) -> 336000 | U7: =24%*(O7-3200000) -> 431535.42 | V7: =P7+Q7+R7+S7+T7+U7 -> 991535.42 | W7: 12 | X7: =V7/W7 -> 82627.951 | Z7: =X7 -> 82627.951 | AA7: 82627.951 | AB7: =Z7-AA7 -> 0
A8: 5 | B8: MARIAM MOHAMMED BELLO | C8: 741465.02 | D8: 12 | E8: =C8*D8 -> 8897580.3 | I8: =E8-F8-G8-H8 -> 8897580.3 | J8: 200000 | K8: 0.2 | L8: =I8*K8 -> 1779516.1 | M8: =J8+L8 -> 1979516.1 | N8: =F8+G8+H8+M8 -> 1979516.1 | O8: =E8-N8 -> 6918064.2 | P8: =IF(O8<300000,0.07*O8,21000) -> 21000 | Q8: =IF((O8-300000)<0,0,IF((O8-300000)<300000,0.11*(O8-300000),33000)) -> 33000 | R8: =IF((O8-600000)<0,0,IF((O8-600000)<500000,0.15*(O8-600000),75000)) -> 75000 | S8: =IF((O8-1100000)<0,0,IF((O8-1100000)<500000,0.19*(O8-1100000),95000)) -> 95000 | T8: =IF((O8-1600000)<0,0,IF((O8-1600000)<1600000,0.21*(O8-1600000),336000)) -> 336000 | U8: =24%*(O8-3200000) -> 892335.42 | V8: =P8+Q8+R8+S8+T8+U8 -> 1452335.4 | W8: 12 | X8: =V8/W8 -> 121027.95 | Z8: =X8 -> 121027.95 | AA8: 121027.95 | AB8: =Z8-AA8 -> 0
A9: 6 | B9: DR IKEME ARTHUR J.O | C9: 631465.02 | D9: 12 | E9: =C9*D9 -> 7577580.3 | F9: ='[4]JANUARY 2024'!$V$10*12 -> 12795.951 | I9: =E9-F9-G9-H9 -> 7564784.3 | J9: 200000 | K9: 0.2 | L9: =I9*K9 -> 1512956.9 | M9: =J9+L9 -> 1712956.9 | N9: =F9+G9+H9+M9 -> 1725752.8 | O9: =E9-N9 -> 5851827.5 | P9: =IF(O9<300000,0.07*O9,21000) -> 21000 | Q9: =IF((O9-300000)<0,0,IF((O9-300000)<300000,0.11*(O9-300000),33000)) -> 33000 | R9: =IF((O9-600000)<0,0,IF((O9-600000)<500000,0.15*(O9-600000),75000)) -> 75000 | S9: =IF((O9-1100000)<0,0,IF((O9-1100000)<500000,0.19*(O9-1100000),95000)) -> 95000 | T9: =IF((O9-1600000)<0,0,IF((O9-1600000)<1600000,0.21*(O9-1600000),336000)) -> 336000 | U9: =24%*(O9-3200000) -> 636438.59 | V9: =P9+Q9+R9+S9+T9+U9 -> 1196438.6 | W9: 12 | X9: =V9/W9 -> 99703.216 | Z9: =X9 -> 99703.216 | AA9: 99703.216 | AB9: =Z9-AA9 -> 0
A10: 7 | B10: MOSHOOD M. OLALERE | C10: 691465.02 | D10: 12 | E10: =C10*D10 -> 8297580.3 | F10: ='[4]JANUARY 2024'!$V$10*12 -> 12795.951 | I10: =E10-F10-G10-H10 -> 8284784.3 | J10: 200000 | K10: 0.2 | L10: =I10*K10 -> 1656956.9 | M10: =J10+L10 -> 1856956.9 | N10: =F10+G10+H10+M10 -> 1869752.8 | O10: =E10-N10 -> 6427827.5 | P10: =IF(O10<300000,0.07*O10,21000) -> 21000 | Q10: =IF((O10-300000)<0,0,IF((O10-300000)<300000,0.11*(O10-300000),33000)) -> 33000 | R10: =IF((O10-600000)<0,0,IF((O10-600000)<500000,0.15*(O10-600000),75000)) -> 75000 | S10: =IF((O10-1100000)<0,0,IF((O10-1100000)<500000,0.19*(O10-1100000),95000)) -> 95000 | T10: =IF((O10-1600000)<0,0,IF((O10-1600000)<1600000,0.21*(O10-1600000),336000)) -> 336000 | U10: =24%*(O10-3200000) -> 774678.59 | V10: =P10+Q10+R10+S10+T10+U10 -> 1334678.6 | W10: 12 | X10: =V10/W10 -> 111223.22 | Z10: =X10 -> 111223.22 | AA10: 111223.22 | AB10: =Z10-AA10 -> 0
A11: 8 | B11: REKIYA IBRAHIM ATTAH | C11: 641465.02 | D11: 12 | E11: =C11*D11 -> 7697580.3 | I11: =E11-F11-G11-H11 -> 7697580.3 | J11: 200000 | K11: 0.2 | L11: =I11*K11 -> 1539516.1 | M11: =J11+L11 -> 1739516.1 | N11: =F11+G11+H11+M11 -> 1739516.1 | O11: =E11-N11 -> 5958064.2 | P11: =IF(O11<300000,0.07*O11,21000) -> 21000 | Q11: =IF((O11-300000)<0,0,IF((O11-300000)<300000,0.11*(O11-300000),33000)) -> 33000 | R11: =IF((O11-600000)<0,0,IF((O11-600000)<500000,0.15*(O11-600000),75000)) -> 75000 | S11: =IF((O11-1100000)<0,0,IF((O11-1100000)<500000,0.19*(O11-1100000),95000)) -> 95000 | T11: =IF((O11-1600000)<0,0,IF((O11-1600000)<1600000,0.21*(O11-1600000),336000)) -> 336000 | U11: =24%*(O11-3200000) -> 661935.42 | V11: =P11+Q11+R11+S11+T11+U11 -> 1221935.4 | W11: 12 | X11: =V11/W11 -> 101827.95 | Z11: =X11 -> 101827.95 | AA11: 101827.95 | AB11: =Z11-AA11 -> 0
A12: 9 | B12: ANDRAWUS MUSA | C12: 497553.5 | D12: 12 | E12: =C12*D12 -> 5970642 | F12: ='[4]JANUARY 2024'!$V$13*12 -> 10052.25 | I12: =E12-F12-G12-H12 -> 5960589.8 | J12: 200000 | K12: 0.2 | L12: =I12*K12 -> 1192118 | M12: =J12+L12 -> 1392118 | N12: =F12+G12+H12+M12 -> 1402170.2 | O12: =E12-N12 -> 4568471.8 | P12: =IF(O12<300000,0.07*O12,21000) -> 21000 | Q12: =IF((O12-300000)<0,0,IF((O12-300000)<300000,0.11*(O12-300000),33000)) -> 33000 | R12: =IF((O12-600000)<0,0,IF((O12-600000)<500000,0.15*(O12-600000),75000)) -> 75000 | S12: =IF((O12-1100000)<0,0,IF((O12-1100000)<500000,0.19*(O12-1100000),95000)) -> 95000 | T12: =IF((O12-1600000)<0,0,IF((O12-1600000)<1600000,0.21*(O12-1600000),336000)) -> 336000 | U12: =24%*(O12-3200000) -> 328433.24 | V12: =P12+Q12+R12+S12+T12+U12 -> 888433.24 | W12: 12 | X12: =V12/W12 -> 74036.103 | Z12: =X12 -> 74036.103 | AA12: 74036.103 | AB12: =Z12-AA12 -> 0
A13: 10 | B13: DR FRANCIS NDUM OJIE | C13: 604729.22 | D13: 12 | E13: =C13*D13 -> 7256750.7 | F13: ='[4]JANUARY 2024'!$V$14*12 -> 9305.952 | I13: =E13-F13-G13-H13 -> 7247444.7 | J13: 200000 | K13: 0.2 | L13: =I13*K13 -> 1449488.9 | M13: =J13+L13 -> 1649488.9 | N13: =F13+G13+H13+M13 -> 1658794.9 | O13: =E13-N13 -> 5597955.8 | P13: =IF(O13<300000,0.07*O13,21000) -> 21000 | Q13: =IF((O13-300000)<0,0,IF((O13-300000)<300000,0.11*(O13-300000),33000)) -> 33000 | R13: =IF((O13-600000)<0,0,IF((O13-600000)<500000,0.15*(O13-600000),75000)) -> 75000 | S13: =IF((O13-1100000)<0,0,IF((O13-1100000)<500000,0.19*(O13-1100000),95000)) -> 95000 | T13: =IF((O13-1600000)<0,0,IF((O13-1600000)<1600000,0.21*(O13-1600000),336000)) -> 336000 | U13: =24%*(O13-3200000) -> 575509.38 | V13: =P13+Q13+R13+S13+T13+U13 -> 1135509.4 | W13: 12 | X13: =V13/W13 -> 94625.782 | Z13: =X13 -> 94625.782 | AA13: 94625.782 | AB13: =Z13-AA13 -> 0
A14: 11 | B14: ALI ABDULLAHI | C14: 343333.04 | D14: 12 | E14: =C14*D14 -> 4119996.4 | I14: =E14-F14-G14-H14 -> 4119996.4 | J14: 200000 | K14: 0.2 | L14: =I14*K14 -> 823999.28 | M14: =J14+L14 -> 1023999.3 | N14: =F14+G14+H14+M14 -> 1023999.3 | O14: =E14-N14 -> 3095997.1 | P14: =IF(O14<300000,0.07*O14,21000) -> 21000 | Q14: =IF((O14-300000)<0,0,IF((O14-300000)<300000,0.11*(O14-300000),33000)) -> 33000 | R14: =IF((O14-600000)<0,0,IF((O14-600000)<500000,0.15*(O14-600000),75000)) -> 75000 | S14: =IF((O14-1100000)<0,0,IF((O14-1100000)<500000,0.19*(O14-1100000),95000)) -> 95000 | T14: =IF((O14-1600000)<0,0,IF((O14-1600000)<1600000,0.21*(O14-1600000),336000)) -> 314159.4 | V14: =P14+Q14+R14+S14+T14+U14 -> 538159.4 | W14: 12 | X14: =V14/W14 -> 44846.617 | Z14: =X14 -> 44846.617 | AA14: 44846.617 | AB14: =Z14-AA14 -> 0
A15: 12 | B15: EMILY EKHIDE | C15: 463333.04 | D15: 12 | E15: =C15*D15 -> 5559996.4 | I15: =E15-F15-G15-H15 -> 5559996.4 | J15: 200000 | K15: 0.2 | L15: =I15*K15 -> 1111999.3 | M15: =J15+L15 -> 1311999.3 | N15: =F15+G15+H15+M15 -> 1311999.3 | O15: =E15-N15 -> 4247997.1 | P15: =IF(O15<300000,0.07*O15,21000) -> 21000 | Q15: =IF((O15-300000)<0,0,IF((O15-300000)<300000,0.11*(O15-300000),33000)) -> 33000 | R15: =IF((O15-600000)<0,0,IF((O15-600000)<500000,0.15*(O15-600000),75000)) -> 75000 | S15: =IF((O15-1100000)<0,0,IF((O15-1100000)<500000,0.19*(O15-1100000),95000)) -> 95000 | T15: =IF((O15-1600000)<0,0,IF((O15-1600000)<1600000,0.21*(O15-1600000),336000)) -> 336000 | U15: =24%*(O15-3200000) -> 251519.31 | V15: =P15+Q15+R15+S15+T15+U15 -> 811519.31 | W15: 12 | X15: =V15/W15 -> 67626.609 | Z15: =X15 -> 67626.609 | AA15: 46666.667 | AB15: =Z15-AA15 -> 20959.943
A16: 13 | B16: DORIS DAKDA AARON | C16: 547211.37 | D16: 12 | E16: =C16*D16 -> 6566536.4 | I16: =E16-F16-G16-H16 -> 6566536.4 | J16: 200000 | K16: 0.2 | L16: =I16*K16 -> 1313307.3 | M16: =J16+L16 -> 1513307.3 | N16: =F16+G16+H16+M16 -> 1513307.3 | O16: =E16-N16 -> 5053229.1 | P16: =IF(O16<300000,0.07*O16,21000) -> 21000 | Q16: =IF((O16-300000)<0,0,IF((O16-300000)<300000,0.11*(O16-300000),33000)) -> 33000 | R16: =IF((O16-600000)<0,0,IF((O16-600000)<500000,0.15*(O16-600000),75000)) -> 75000 | S16: =IF((O16-1100000)<0,0,IF((O16-1100000)<500000,0.19*(O16-1100000),95000)) -> 95000 | T16: =IF((O16-1600000)<0,0,IF((O16-1600000)<1600000,0.21*(O16-1600000),336000)) -> 336000 | U16: =24%*(O16-3200000) -> 444774.99 | V16: =P16+Q16+R16+S16+T16+U16 -> 1004775 | W16: 12 | X16: =V16/W16 -> 83731.249 | Z16: =X16 -> 83731.249 | AA16: 46666.667 | AB16: =Z16-AA16 -> 37064.583
A17: 14 | B17: ABDULSALAM S. MUSTAPHA | C17: 326663.08 | D17: 12 | E17: =C17*D17 -> 3919956.9 | I17: =E17-F17-G17-H17 -> 3919956.9 | J17: 200000 | K17: 0.2 | L17: =I17*K17 -> 783991.39 | M17: =J17+L17 -> 983991.39 | N17: =F17+G17+H17+M17 -> 983991.39 | O17: =E17-N17 -> 2935965.5 | P17: =IF(O17<300000,0.07*O17,21000) -> 21000 | Q17: =IF((O17-300000)<0,0,IF((O17-300000)<300000,0.11*(O17-300000),33000)) -> 33000 | R17: =IF((O17-600000)<0,0,IF((O17-600000)<500000,0.15*(O17-600000),75000)) -> 75000 | S17: =IF((O17-1100000)<0,0,IF((O17-1100000)<500000,0.19*(O17-1100000),95000)) -> 95000 | T17: =IF((O17-1600000)<0,0,IF((O17-1600000)<1600000,0.21*(O17-1600000),336000)) -> 280552.76 | V17: =P17+Q17+R17+S17+T17+U17 -> 504552.76 | W17: 12 | X17: =V17/W17 -> 42046.064 | Z17: =X17 -> 42046.064 | AA17: 42046.064 | AB17: =Z17-AA17 -> 0
A18: 15 | B18: PERCY TERFA GBAHABO | C18: 369177.65 | D18: 12 | E18: =C18*D18 -> 4430131.8 | I18: =E18-F18-G18-H18 -> 4430131.8 | J18: 200000 | K18: 0.2 | L18: =I18*K18 -> 886026.37 | M18: =J18+L18 -> 1086026.4 | N18: =F18+G18+H18+M18 -> 1086026.4 | O18: =E18-N18 -> 3344105.5 | P18: =IF(O18<300000,0.07*O18,21000) -> 21000 | Q18: =IF((O18-300000)<0,0,IF((O18-300000)<300000,0.11*(O18-300000),33000)) -> 33000 | R18: =IF((O18-600000)<0,0,IF((O18-600000)<500000,0.15*(O18-600000),75000)) -> 75000 | S18: =IF((O18-1100000)<0,0,IF((O18-1100000)<500000,0.19*(O18-1100000),95000)) -> 95000 | T18: =IF((O18-1600000)<0,0,IF((O18-1600000)<1600000,0.21*(O18-1600000),336000)) -> 336000 | U18: =24%*(O18-3200000) -> 34585.314 | V18: =P18+Q18+R18+S18+T18+U18 -> 594585.31 | W18: 12 | X18: =V18/W18 -> 49548.776 | Z18: =X18 -> 49548.776 | AA18: 46666.667 | AB18: =Z18-AA18 -> 2882.1095
A19: 16 | B19: HASSANA AHMED IBRAHIM | C19: 462001.06 | D19: 12 | E19: =C19*D19 -> 5544012.7 | I19: =E19-F19-G19-H19 -> 5544012.7 | J19: 200000 | K19: 0.2 | L19: =I19*K19 -> 1108802.5 | M19: =J19+L19 -> 1308802.5 | N19: =F19+G19+H19+M19 -> 1308802.5 | O19: =E19-N19 -> 4235210.2 | P19: =IF(O19<300000,0.07*O19,21000) -> 21000 | Q19: =IF((O19-300000)<0,0,IF((O19-300000)<300000,0.11*(O19-300000),33000)) -> 33000 | R19: =IF((O19-600000)<0,0,IF((O19-600000)<500000,0.15*(O19-600000),75000)) -> 75000 | S19: =IF((O19-1100000)<0,0,IF((O19-1100000)<500000,0.19*(O19-1100000),95000)) -> 95000 | T19: =IF((O19-1600000)<0,0,IF((O19-1600000)<1600000,0.21*(O19-1600000),336000)) -> 336000 | U19: =24%*(O19-3200000) -> 248450.44 | V19: =P19+Q19+R19+S19+T19+U19 -> 808450.44 | W19: 12 | X19: =V19/W19 -> 67370.87 | Z19: =X19 -> 67370.87 | AA19: 46666.667 | AB19: =Z19-AA19 -> 20704.204
A20: 17 | B20: ADUGBA RICHARD TERSEER | C20: 384537 | D20: 12 | E20: =C20*D20 -> 4614444 | I20: =E20-F20-G20-H20 -> 4614444 | J20: 200000 | K20: 0.2 | L20: =I20*K20 -> 922888.8 | M20: =J20+L20 -> 1122888.8 | N20: =F20+G20+H20+M20 -> 1122888.8 | O20: =E20-N20 -> 3491555.2 | P20: =IF(O20<300000,0.07*O20,21000) -> 21000 | Q20: =IF((O20-300000)<0,0,IF((O20-300000)<300000,0.11*(O20-300000),33000)) -> 33000 | R20: =IF((O20-600000)<0,0,IF((O20-600000)<500000,0.15*(O20-600000),75000)) -> 75000 | S20: =IF((O20-1100000)<0,0,IF((O20-1100000)<500000,0.19*(O20-1100000),95000)) -> 95000 | T20: =IF((O20-1600000)<0,0,IF((O20-1600000)<1600000,0.21*(O20-1600000),336000)) -> 336000 | U20: =24%*(O20-3200000) -> 69973.245 | V20: =P20+Q20+R20+S20+T20+U20 -> 629973.24 | W20: 12 | X20: =V20/W20 -> 52497.77 | Z20: =X20 -> 52497.77 | AA20: 52497.77 | AB20: =Z20-AA20 -> 0
A21: 18 | B21: LUCKY AGWOM | C21: 400372.08 | D21: 12 | E21: =C21*D21 -> 4804464.9 | I21: =E21-F21-G21-H21 -> 4804464.9 | J21: 200000 | K21: 0.2 | L21: =I21*K21 -> 960892.98 | M21: =J21+L21 -> 1160893 | N21: =F21+G21+H21+M21 -> 1160893 | O21: =E21-N21 -> 3643571.9 | P21: =IF(O21<300000,0.07*O21,21000) -> 21000 | Q21: =IF((O21-300000)<0,0,IF((O21-300000)<300000,0.11*(O21-300000),33000)) -> 33000 | R21: =IF((O21-600000)<0,0,IF((O21-600000)<500000,0.15*(O21-600000),75000)) -> 75000 | S21: =IF((O21-1100000)<0,0,IF((O21-1100000)<500000,0.19*(O21-1100000),95000)) -> 95000 | T21: =IF((O21-1600000)<0,0,IF((O21-1600000)<1600000,0.21*(O21-1600000),336000)) -> 336000 | U21: =24%*(O21-3200000) -> 106457.26 | V21: =P21+Q21+R21+S21+T21+U21 -> 666457.26 | W21: 12 | X21: =V21/W21 -> 55538.105 | Z21: =X21 -> 55538.105 | AA21: 46666.667 | AB21: =Z21-AA21 -> 8871.4384
A22: 19 | B22: IDRIS IBRAHIM | C22: =1015372.075-700000 -> 315372.07 | D22: 12 | E22: =C22*D22 -> 3784464.9 | I22: =E22-F22-G22-H22 -> 3784464.9 | J22: 200000 | K22: 0.2 | L22: =I22*K22 -> 756892.98 | M22: =J22+L22 -> 956892.98 | N22: =F22+G22+H22+M22 -> 956892.98 | O22: =E22-N22 -> 2827571.9 | P22: =IF(O22<300000,0.07*O22,21000) -> 21000 | Q22: =IF((O22-300000)<0,0,IF((O22-300000)<300000,0.11*(O22-300000),33000)) -> 33000 | R22: =IF((O22-600000)<0,0,IF((O22-600000)<500000,0.15*(O22-600000),75000)) -> 75000 | S22: =IF((O22-1100000)<0,0,IF((O22-1100000)<500000,0.19*(O22-1100000),95000)) -> 95000 | T22: =IF((O22-1600000)<0,0,IF((O22-1600000)<1600000,0.21*(O22-1600000),336000)) -> 257790.1 | V22: =P22+Q22+R22+S22+T22+U22 -> 481790.1 | W22: 12 | X22: =V22/W22 -> 40149.175 | Z22: =X22 -> 40149.175 | AA22: 46666.667 | AB22: =Z22-AA22 -> -6517.4914 | AC22: to be paid in February
A23: 20 | B23: FARUQ ATOFARATI | C23: 328602.08 | D23: 12 | E23: =C23*D23 -> 3943224.9 | I23: =E23-F23-G23-H23 -> 3943224.9 | J23: 200000 | K23: 0.2 | L23: =I23*K23 -> 788644.99 | M23: =J23+L23 -> 988644.99 | N23: =F23+G23+H23+M23 -> 988644.99 | O23: =E23-N23 -> 2954579.9 | P23: =IF(O23<300000,0.07*O23,21000) -> 21000 | Q23: =IF((O23-300000)<0,0,IF((O23-300000)<300000,0.11*(O23-300000),33000)) -> 33000 | R23: =IF((O23-600000)<0,0,IF((O23-600000)<500000,0.15*(O23-600000),75000)) -> 75000 | S23: =IF((O23-1100000)<0,0,IF((O23-1100000)<500000,0.19*(O23-1100000),95000)) -> 95000 | T23: =IF((O23-1600000)<0,0,IF((O23-1600000)<1600000,0.21*(O23-1600000),336000)) -> 284461.79 | V23: =P23+Q23+R23+S23+T23+U23 -> 508461.79 | W23: 12 | X23: =V23/W23 -> 42371.816 | Z23: =X23 -> 42371.816 | AA23: 42371.816 | AB23: =Z23-AA23 -> 0
A24: 21 | B24: ELIZABETH OGECHUKWU ONYEAKU | C24: 213508.01 | D24: 12 | E24: =C24*D24 -> 2562096.1 | I24: =E24-F24-G24-H24 -> 2562096.1 | J24: 200000 | K24: 0.2 | L24: =I24*K24 -> 512419.22 | M24: =J24+L24 -> 712419.22 | N24: =F24+G24+H24+M24 -> 712419.22 | O24: =E24-N24 -> 1849676.9 | P24: =IF(O24<300000,0.07*O24,21000) -> 21000 | Q24: =IF((O24-300000)<0,0,IF((O24-300000)<300000,0.11*(O24-300000),33000)) -> 33000 | R24: =IF((O24-600000)<0,0,IF((O24-600000)<500000,0.15*(O24-600000),75000)) -> 75000 | S24: =IF((O24-1100000)<0,0,IF((O24-1100000)<500000,0.19*(O24-1100000),95000)) -> 95000 | T24: =IF((O24-1600000)<0,0,IF((O24-1600000)<1600000,0.21*(O24-1600000),336000)) -> 52432.148 | V24: =P24+Q24+R24+S24+T24+U24 -> 276432.15 | W24: 12 | X24: =V24/W24 -> 23036.012 | Z24: =X24 -> 23036.012 | AA24: 23036.012 | AB24: =Z24-AA24 -> 0
A25: 22 | B25: VICTOR ASUKWO | C25: 213508.01 | D25: 12 | E25: =C25*D25 -> 2562096.1 | I25: =E25-F25-G25-H25 -> 2562096.1 | J25: 200000 | K25: 0.2 | L25: =I25*K25 -> 512419.22 | M25: =J25+L25 -> 712419.22 | N25: =F25+G25+H25+M25 -> 712419.22 | O25: =E25-N25 -> 1849676.9 | P25: =IF(O25<300000,0.07*O25,21000) -> 21000 | Q25: =IF((O25-300000)<0,0,IF((O25-300000)<300000,0.11*(O25-300000),33000)) -> 33000 | R25: =IF((O25-600000)<0,0,IF((O25-600000)<500000,0.15*(O25-600000),75000)) -> 75000 | S25: =IF((O25-1100000)<0,0,IF((O25-1100000)<500000,0.19*(O25-1100000),95000)) -> 95000 | T25: =IF((O25-1600000)<0,0,IF((O25-1600000)<1600000,0.21*(O25-1600000),336000)) -> 52432.148 | V25: =P25+Q25+R25+S25+T25+U25 -> 276432.15 | W25: 12 | X25: =V25/W25 -> 23036.012 | Z25: =X25 -> 23036.012 | AA25: 23036.012 | AB25: =Z25-AA25 -> 0
A26: 23 | B26: NNANDI LIVINUS ATURE | C26: 253508.01 | D26: 12 | E26: =C26*D26 -> 3042096.1 | I26: =E26-F26-G26-H26 -> 3042096.1 | J26: 200000 | K26: 0.2 | L26: =I26*K26 -> 608419.22 | M26: =J26+L26 -> 808419.22 | N26: =F26+G26+H26+M26 -> 808419.22 | O26: =E26-N26 -> 2233676.9 | P26: =IF(O26<300000,0.07*O26,21000) -> 21000 | Q26: =IF((O26-300000)<0,0,IF((O26-300000)<300000,0.11*(O26-300000),33000)) -> 33000 | R26: =IF((O26-600000)<0,0,IF((O26-600000)<500000,0.15*(O26-600000),75000)) -> 75000 | S26: =IF((O26-1100000)<0,0,IF((O26-1100000)<500000,0.19*(O26-1100000),95000)) -> 95000 | T26: =IF((O26-1600000)<0,0,IF((O26-1600000)<1600000,0.21*(O26-1600000),336000)) -> 133072.15 | V26: =P26+Q26+R26+S26+T26+U26 -> 357072.15 | W26: 12 | X26: =V26/W26 -> 29756.012 | Z26: =X26 -> 29756.012 | AA26: 29756.012 | AB26: =Z26-AA26 -> 0
A27: 24 | B27: ABDULRAHMAN A SULAIMAN | C27: 209356.05 | D27: 12 | E27: =C27*D27 -> 2512272.6 | I27: =E27-F27-G27-H27 -> 2512272.6 | J27: 200000 | K27: 0.2 | L27: =I27*K27 -> 502454.51 | M27: =J27+L27 -> 702454.51 | N27: =F27+G27+H27+M27 -> 702454.51 | O27: =E27-N27 -> 1809818.1 | P27: =IF(O27<300000,0.07*O27,21000) -> 21000 | Q27: =IF((O27-300000)<0,0,IF((O27-300000)<300000,0.11*(O27-300000),33000)) -> 33000 | R27: =IF((O27-600000)<0,0,IF((O27-600000)<500000,0.15*(O27-600000),75000)) -> 75000 | S27: =IF((O27-1100000)<0,0,IF((O27-1100000)<500000,0.19*(O27-1100000),95000)) -> 95000 | T27: =IF((O27-1600000)<0,0,IF((O27-1600000)<1600000,0.21*(O27-1600000),336000)) -> 44061.791 | V27: =P27+Q27+R27+S27+T27+U27 -> 268061.79 | W27: 12 | X27: =V27/W27 -> 22338.483 | Z27: =X27 -> 22338.483 | AA27: 22338.483 | AB27: =Z27-AA27 -> 0
A28: 25 | B28: DARE SHEU MAGBON | C28: 205204.08 | D28: 12 | E28: =C28*D28 -> 2462449 | I28: =E28-F28-G28-H28 -> 2462449 | J28: 200000 | K28: 0.2 | L28: =I28*K28 -> 492489.8 | M28: =J28+L28 -> 692489.8 | N28: =F28+G28+H28+M28 -> 692489.8 | O28: =E28-N28 -> 1769959.2 | P28: =IF(O28<300000,0.07*O28,21000) -> 21000 | Q28: =IF((O28-300000)<0,0,IF((O28-300000)<300000,0.11*(O28-300000),33000)) -> 33000 | R28: =IF((O28-600000)<0,0,IF((O28-600000)<500000,0.15*(O28-600000),75000)) -> 75000 | S28: =IF((O28-1100000)<0,0,IF((O28-1100000)<500000,0.19*(O28-1100000),95000)) -> 95000 | T28: =IF((O28-1600000)<0,0,IF((O28-1600000)<1600000,0.21*(O28-1600000),336000)) -> 35691.434 | V28: =P28+Q28+R28+S28+T28+U28 -> 259691.43 | W28: 12 | X28: =V28/W28 -> 21640.953 | Z28: =X28 -> 21640.953 | AA28: 21640.953 | AB28: =Z28-AA28 -> 0
A29: 26 | B29: ABUBAKAR SULAIMAN SODEEQ | C29: 205204.08 | D29: 12 | E29: =C29*D29 -> 2462449 | I29: =E29-F29-G29-H29 -> 2462449 | J29: 200000 | K29: 0.2 | L29: =I29*K29 -> 492489.8 | M29: =J29+L29 -> 692489.8 | N29: =F29+G29+H29+M29 -> 692489.8 | O29: =E29-N29 -> 1769959.2 | P29: =IF(O29<300000,0.07*O29,21000) -> 21000 | Q29: =IF((O29-300000)<0,0,IF((O29-300000)<300000,0.11*(O29-300000),33000)) -> 33000 | R29: =IF((O29-600000)<0,0,IF((O29-600000)<500000,0.15*(O29-600000),75000)) -> 75000 | S29: =IF((O29-1100000)<0,0,IF((O29-1100000)<500000,0.19*(O29-1100000),95000)) -> 95000 | T29: =IF((O29-1600000)<0,0,IF((O29-1600000)<1600000,0.21*(O29-1600000),336000)) -> 35691.434 | V29: =P29+Q29+R29+S29+T29+U29 -> 259691.43 | W29: 12 | X29: =V29/W29 -> 21640.953 | Z29: =X29 -> 21640.953 | AA29: 21640.953 | AB29: =Z29-AA29 -> 0
A30: 27 | B30: JIMOH ADEBAYO ZAKA | C30: 209356.05 | D30: 12 | E30: =C30*D30 -> 2512272.6 | I30: =E30-F30-G30-H30 -> 2512272.6 | J30: 200000 | K30: 0.2 | L30: =I30*K30 -> 502454.51 | M30: =J30+L30 -> 702454.51 | N30: =F30+G30+H30+M30 -> 702454.51 | O30: =E30-N30 -> 1809818.1 | P30: =IF(O30<300000,0.07*O30,21000) -> 21000 | Q30: =IF((O30-300000)<0,0,IF((O30-300000)<300000,0.11*(O30-300000),33000)) -> 33000 | R30: =IF((O30-600000)<0,0,IF((O30-600000)<500000,0.15*(O30-600000),75000)) -> 75000 | S30: =IF((O30-1100000)<0,0,IF((O30-1100000)<500000,0.19*(O30-1100000),95000)) -> 95000 | T30: =IF((O30-1600000)<0,0,IF((O30-1600000)<1600000,0.21*(O30-1600000),336000)) -> 44061.791 | V30: =P30+Q30+R30+S30+T30+U30 -> 268061.79 | W30: 12 | X30: =V30/W30 -> 22338.483 | Z30: =X30 -> 22338.483 | AA30: 22338.483 | AB30: =Z30-AA30 -> 0
A31: 28 | B31: MOHAMMED BELLO | C31: 180304.07 | D31: 12 | E31: =C31*D31 -> 2163648.8 | I31: =E31-F31-G31-H31 -> 2163648.8 | J31: 200000 | K31: 0.2 | L31: =I31*K31 -> 432729.76 | M31: =J31+L31 -> 632729.76 | N31: =F31+G31+H31+M31 -> 632729.76 | O31: =E31-N31 -> 1530919.1 | P31: =IF(O31<300000,0.07*O31,21000) -> 21000 | Q31: =IF((O31-300000)<0,0,IF((O31-300000)<300000,0.11*(O31-300000),33000)) -> 33000 | R31: =IF((O31-600000)<0,0,IF((O31-600000)<500000,0.15*(O31-600000),75000)) -> 75000 | S31: =IF((O31-1100000)<0,0,IF((O31-1100000)<500000,0.19*(O31-1100000),95000)) -> 81874.62 | T31: =IF((O31-1600000)<0,0,IF((O31-1600000)<1600000,0.21*(O31-1600000),336000)) -> 0 | V31: =P31+Q31+R31+S31+T31+U31 -> 210874.62 | W31: 12 | X31: =V31/W31 -> 17572.885 | Z31: =X31 -> 17572.885 | AA31: 17572.885 | AB31: =Z31-AA31 -> 0
A32: 29 | B32: HARUNA JIBRIL AMEH | C32: 173329.05 | D32: 12 | E32: =C32*D32 -> 2079948.6 | I32: =E32-F32-G32-H32 -> 2079948.6 | J32: 200000 | K32: 0.2 | L32: =I32*K32 -> 415989.72 | M32: =J32+L32 -> 615989.72 | N32: =F32+G32+H32+M32 -> 615989.72 | O32: =E32-N32 -> 1463958.9 | P32: =IF(O32<300000,0.07*O32,21000) -> 21000 | Q32: =IF((O32-300000)<0,0,IF((O32-300000)<300000,0.11*(O32-300000),33000)) -> 33000 | R32: =IF((O32-600000)<0,0,IF((O32-600000)<500000,0.15*(O32-600000),75000)) -> 75000 | S32: =IF((O32-1100000)<0,0,IF((O32-1100000)<500000,0.19*(O32-1100000),95000)) -> 69152.186 | T32: =IF((O32-1600000)<0,0,IF((O32-1600000)<1600000,0.21*(O32-1600000),336000)) -> 0 | V32: =P32+Q32+R32+S32+T32+U32 -> 198152.19 | W32: 12 | X32: =V32/W32 -> 16512.682 | Z32: =X32 -> 16512.682 | AA32: 16512.682 | AB32: =Z32-AA32 -> 0
A33: 31 | AB33: =SUM(AB6:AB32) -> 83964.785
A34: 32 | B34: INTERNAL AUDIT
B35: OSANAIYE DAVID AKINYEMI | C35: 950209.06 | D35: 12 | E35: =C35*D35 -> 11402509 | G35: =SUM(G5:G34) -> 0 | I35: =E35-F35-G35-H35 -> 11402509 | J35: 200000 | K35: 0.2 | L35: =I35*K35 -> 2280501.8 | M35: =J35+L35 -> 2480501.8 | N35: =F35+G35+H35+M35 -> 2480501.8 | O35: =E35-N35 -> 8922007 | P35: =IF(O35<300000,0.07*O35,21000) -> 21000 | Q35: =IF((O35-300000)<0,0,IF((O35-300000)<300000,0.11*(O35-300000),33000)) -> 33000 | R35: =IF((O35-600000)<0,0,IF((O35-600000)<500000,0.15*(O35-600000),75000)) -> 75000 | S35: =IF((O35-1100000)<0,0,IF((O35-1100000)<500000,0.19*(O35-1100000),95000)) -> 95000 | T35: =IF((O35-1600000)<0,0,IF((O35-1600000)<1600000,0.21*(O35-1600000),336000)) -> 336000 | U35: =24%*(O35-3200000) -> 1373281.7 | V35: =P35+Q35+R35+S35+T35+U35 -> 1933281.7 | W35: 12 | X35: =V35/W35 -> 161106.81 | Z35: =X35 -> 161106.81 | AA35: 161106.81 | AB35: =Z35-AA35 -> 0
B36: JAMILA ABDUL | C36: 176816.1 | D36: 12 | E36: =C36*D36 -> 2121793.2 | G36: =SUM(G6:G35) -> 0 | I36: =E36-F36-G36-H36 -> 2121793.2 | J36: 200000 | K36: 0.2 | L36: =I36*K36 -> 424358.64 | M36: =J36+L36 -> 624358.64 | N36: =F36+G36+H36+M36 -> 624358.64 | O36: =E36-N36 -> 1497434.6 | P36: =IF(O36<300000,0.07*O36,21000) -> 21000 | Q36: =IF((O36-300000)<0,0,IF((O36-300000)<300000,0.11*(O36-300000),33000)) -> 33000 | R36: =IF((O36-600000)<0,0,IF((O36-600000)<500000,0.15*(O36-600000),75000)) -> 75000 | S36: =IF((O36-1100000)<0,0,IF((O36-1100000)<500000,0.19*(O36-1100000),95000)) -> 75512.566 | T36: =IF((O36-1600000)<0,0,IF((O36-1600000)<1600000,0.21*(O36-1600000),336000)) -> 0 | V36: =P36+Q36+R36+S36+T36+U36 -> 204512.57 | W36: 12 | X36: =V36/W36 -> 17042.714 | Z36: =X36 -> 17042.714 | AA36: 17042.714 | AB36: =Z36-AA36 -> 0
A37: 33 | B37: IJEOMA EWELUKWA | C37: 233169.12 | D37: 12 | E37: =C37*D37 -> 2798029.4 | G37: =SUM(G7:G36) -> 0 | I37: =E37-F37-G37-H37 -> 2798029.4 | J37: 200000 | K37: 0.2 | L37: =I37*K37 -> 559605.88 | M37: =J37+L37 -> 759605.88 | N37: =F37+G37+H37+M37 -> 759605.88 | O37: =E37-N37 -> 2038423.5 | P37: =IF(O37<300000,0.07*O37,21000) -> 21000 | Q37: =IF((O37-300000)<0,0,IF((O37-300000)<300000,0.11*(O37-300000),33000)) -> 33000 | R37: =IF((O37-600000)<0,0,IF((O37-600000)<500000,0.15*(O37-600000),75000)) -> 75000 | S37: =IF((O37-1100000)<0,0,IF((O37-1100000)<500000,0.19*(O37-1100000),95000)) -> 95000 | T37: =IF((O37-1600000)<0,0,IF((O37-1600000)<1600000,0.21*(O37-1600000),336000)) -> 92068.941 | V37: =P37+Q37+R37+S37+T37+U37 -> 316068.94 | W37: 12 | X37: =V37/W37 -> 26339.078 | Z37: =X37 -> 26339.078 | AA37: 26339.078 | AB37: =Z37-AA37 -> 0
B39: LEG. SUPPORT SEVICES
A40: 35 | B40: PROF. EDOBA BRIGHT OMOREGBE | C40: 1050209.1 | D40: 12 | E40: =C40*D40 -> 12602509 | I40: =E40-F40-G40-H40 -> 12602509 | J40: 200000 | K40: 0.2 | L40: =I40*K40 -> 2520501.8 | M40: =J40+L40 -> 2720501.8 | N40: =F40+G40+H40+M40 -> 2720501.8 | O40: =E40-N40 -> 9882007 | P40: =IF(O40<300000,0.07*O40,21000) -> 21000 | Q40: =IF((O40-300000)<0,0,IF((O40-300000)<300000,0.11*(O40-300000),33000)) -> 33000 | R40: =IF((O40-600000)<0,0,IF((O40-600000)<500000,0.15*(O40-600000),75000)) -> 75000 | S40: =IF((O40-1100000)<0,0,IF((O40-1100000)<500000,0.19*(O40-1100000),95000)) -> 95000 | T40: =IF((O40-1600000)<0,0,IF((O40-1600000)<1600000,0.21*(O40-1600000),336000)) -> 336000 | U40: =0.24*(O40-3200000) -> 1603681.7 | V40: =P40+Q40+R40+S40+T40+U40 -> 2163681.7 | W40: 12 | X40: =V40/W40 -> 180306.81 | Z40: =X40 -> 180306.81 | AA40: 180306.81 | AB40: =Z40-AA40 -> 0
A41: 36 | B41: DR CLINTON JAJA | C41: 527553.5 | D41: 12 | E41: =C41*D41 -> 6330642 | I41: =E41-F41-G41-H41 -> 6330642 | J41: 200000 | K41: 0.2 | L41: =I41*K41 -> 1266128.4 | M41: =J41+L41 -> 1466128.4 | N41: =F41+G41+H41+M41 -> 1466128.4 | O41: =E41-N41 -> 4864513.6 | P41: =IF(O41<300000,0.07*O41,21000) -> 21000 | Q41: =IF((O41-300000)<0,0,IF((O41-300000)<300000,0.11*(O41-300000),33000)) -> 33000 | R41: =IF((O41-600000)<0,0,IF((O41-600000)<500000,0.15*(O41-600000),75000)) -> 75000 | S41: =IF((O41-1100000)<0,0,IF((O41-1100000)<500000,0.19*(O41-1100000),95000)) -> 95000 | T41: =IF((O41-1600000)<0,0,IF((O41-1600000)<1600000,0.21*(O41-1600000),336000)) -> 336000 | U41: =24%*(O41-3200000) -> 399483.27 | V41: =P41+Q41+R41+S41+T41+U41 -> 959483.27 | W41: 12 | X41: =V41/W41 -> 79956.939 | Z41: =X41 -> 79956.939 | AA41: 79956.939 | AB41: =Z41-AA41 -> 0
A42: 37 | B42: BETHEL UZOMA IHUGBA | C42: 617744 | D42: 12 | E42: =C42*D42 -> 7412927.9 | I42: =E42-F42-G42-H42 -> 7412927.9 | J42: 200000 | K42: 0.2 | L42: =I42*K42 -> 1482585.6 | M42: =J42+L42 -> 1682585.6 | N42: =F42+G42+H42+M42 -> 1682585.6 | O42: =E42-N42 -> 5730342.4 | P42: =IF(O42<300000,0.07*O42,21000) -> 21000 | Q42: =IF((O42-300000)<0,0,IF((O42-300000)<300000,0.11*(O42-300000),33000)) -> 33000 | R42: =IF((O42-600000)<0,0,IF((O42-600000)<500000,0.15*(O42-600000),75000)) -> 75000 | S42: =IF((O42-1100000)<0,0,IF((O42-1100000)<500000,0.19*(O42-1100000),95000)) -> 95000 | T42: =IF((O42-1600000)<0,0,IF((O42-1600000)<1600000,0.21*(O42-1600000),336000)) -> 336000 | U42: =24%*(O42-3200000) -> 607282.17 | V42: =P42+Q42+R42+S42+T42+U42 -> 1167282.2 | W42: 12 | X42: =V42/W42 -> 97273.514 | Z42: =X42 -> 97273.514 | AA42: 97273.514 | AB42: =Z42-AA42 -> 0
A43: 38 | B43: OGUCHE SAMUEL | C43: 527553.5 | D43: 12 | E43: =C43*D43 -> 6330642 | I43: =E43-F43-G43-H43 -> 6330642 | J43: 200000 | K43: 0.2 | L43: =I43*K43 -> 1266128.4 | M43: =J43+L43 -> 1466128.4 | N43: =F43+G43+H43+M43 -> 1466128.4 | O43: =E43-N43 -> 4864513.6 | P43: =IF(O43<300000,0.07*O43,21000) -> 21000 | Q43: =IF((O43-300000)<0,0,IF((O43-300000)<300000,0.11*(O43-300000),33000)) -> 33000 | R43: =IF((O43-600000)<0,0,IF((O43-600000)<500000,0.15*(O43-600000),75000)) -> 75000 | S43: =IF((O43-1100000)<0,0,IF((O43-1100000)<500000,0.19*(O43-1100000),95000)) -> 95000 | T43: =IF((O43-1600000)<0,0,IF((O43-1600000)<1600000,0.21*(O43-1600000),336000)) -> 336000 | U43: =24%*(O43-3200000) -> 399483.27 | V43: =P43+Q43+R43+S43+T43+U43 -> 959483.27 | W43: 12 | X43: =V43/W43 -> 79956.939 | Z43: =X43 -> 79956.939 | AA43: 79956.939 | AB43: =Z43-AA43 -> 0
A44: 39 | B44: IBRAHIM USMAN | C44: 527553.5 | D44: 12 | E44: =C44*D44 -> 6330642 | F44: ='[4]JANUARY 2024'!$V$47*12 -> 10052.25 | I44: =E44-F44-G44-H44 -> 6320589.8 | J44: 200000 | K44: 0.2 | L44: =I44*K44 -> 1264118 | M44: =J44+L44 -> 1464118 | N44: =F44+G44+H44+M44 -> 1474170.2 | O44: =E44-N44 -> 4856471.8 | P44: =IF(O44<300000,0.07*O44,21000) -> 21000 | Q44: =IF((O44-300000)<0,0,IF((O44-300000)<300000,0.11*(O44-300000),33000)) -> 33000 | R44: =IF((O44-600000)<0,0,IF((O44-600000)<500000,0.15*(O44-600000),75000)) -> 75000 | S44: =IF((O44-1100000)<0,0,IF((O44-1100000)<500000,0.19*(O44-1100000),95000)) -> 95000 | T44: =IF((O44-1600000)<0,0,IF((O44-1600000)<1600000,0.21*(O44-1600000),336000)) -> 336000 | U44: =24%*(O44-3200000) -> 397553.24 | V44: =P44+Q44+R44+S44+T44+U44 -> 957553.24 | W44: 12 | X44: =V44/W44 -> 79796.103 | Z44: =X44 -> 79796.103 | AA44: 79796.103 | AB44: =Z44-AA44 -> 0
A45: 40 | B45: DR MOHAMMED O. AMALI | C45: 504720.05 | D45: 12 | E45: =C45*D45 -> 6056640.6 | I45: =E45-F45-G45-H45 -> 6056640.6 | J45: 200000 | K45: 0.2 | L45: =I45*K45 -> 1211328.1 | M45: =J45+L45 -> 1411328.1 | N45: =F45+G45+H45+M45 -> 1411328.1 | O45: =E45-N45 -> 4645312.5 | P45: =IF(O45<300000,0.07*O45,21000) -> 21000 | Q45: =IF((O45-300000)<0,0,IF((O45-300000)<300000,0.11*(O45-300000),33000)) -> 33000 | R45: =IF((O45-600000)<0,0,IF((O45-600000)<500000,0.15*(O45-600000),75000)) -> 75000 | S45: =IF((O45-1100000)<0,0,IF((O45-1100000)<500000,0.19*(O45-1100000),95000)) -> 95000 | T45: =IF((O45-1600000)<0,0,IF((O45-1600000)<1600000,0.21*(O45-1600000),336000)) -> 336000 | U45: =24%*(O45-3200000) -> 346874.99 | V45: =P45+Q45+R45+S45+T45+U45 -> 906874.99 | W45: 12 | X45: =V45/W45 -> 75572.916 | Z45: =X45 -> 75572.916 | AA45: 75572.916 | AB45: =Z45-AA45 -> 0
A46: 41 | B46: YAHAYA SHAMSU | C46: 413333.04 | D46: 12 | E46: =C46*D46 -> 4959996.4 | I46: =E46-F46-G46-H46 -> 4959996.4 | J46: 200000 | K46: 0.2 | L46: =I46*K46 -> 991999.28 | M46: =J46+L46 -> 1191999.3 | N46: =F46+G46+H46+M46 -> 1191999.3 | O46: =E46-N46 -> 3767997.1 | P46: =IF(O46<300000,0.07*O46,21000) -> 21000 | Q46: =IF((O46-300000)<0,0,IF((O46-300000)<300000,0.11*(O46-300000),33000)) -> 33000 | R46: =IF((O46-600000)<0,0,IF((O46-600000)<500000,0.15*(O46-600000),75000)) -> 75000 | S46: =IF((O46-1100000)<0,0,IF((O46-1100000)<500000,0.19*(O46-1100000),95000)) -> 95000 | T46: =IF((O46-1600000)<0,0,IF((O46-1600000)<1600000,0.21*(O46-1600000),336000)) -> 336000 | U46: =24%*(O46-3200000) -> 136319.31 | V46: =P46+Q46+R46+S46+T46+U46 -> 696319.31 | W46: 12 | X46: =V46/W46 -> 58026.609 | Z46: =X46 -> 58026.609 | AA46: 58026.609 | AB46: =Z46-AA46 -> 0
A47: 42 | B47: BILKIS S. LAWAL-GAMBARI | C47: 273169.12 | D47: 12 | E47: =C47*D47 -> 3278029.4 | I47: =E47-F47-G47-H47 -> 3278029.4 | J47: 200000 | K47: 0.2 | L47: =I47*K47 -> 655605.88 | M47: =J47+L47 -> 855605.88 | N47: =F47+G47+H47+M47 -> 855605.88 | O47: =E47-N47 -> 2422423.5 | P47: =IF(O47<300000,0.07*O47,21000) -> 21000 | Q47: =IF((O47-300000)<0,0,IF((O47-300000)<300000,0.11*(O47-300000),33000)) -> 33000 | R47: =IF((O47-600000)<0,0,IF((O47-600000)<500000,0.15*(O47-600000),75000)) -> 75000 | S47: =IF((O47-1100000)<0,0,IF((O47-1100000)<500000,0.19*(O47-1100000),95000)) -> 95000 | T47: =IF((O47-1600000)<0,0,IF((O47-1600000)<1600000,0.21*(O47-1600000),336000)) -> 172708.94 | V47: =P47+Q47+R47+S47+T47+U47 -> 396708.94 | W47: 12 | X47: =V47/W47 -> 33059.078 | Z47: =X47 -> 33059.078 | AA47: 33059.078 | AB47: =Z47-AA47 -> 0
A48: 43 | B48: ZAINAB AKINDE | C48: 249356.05 | D48: 12 | E48: =C48*D48 -> 2992272.6 | I48: =E48-F48-G48-H48 -> 2992272.6 | J48: 200000 | K48: 0.2 | L48: =I48*K48 -> 598454.51 | M48: =J48+L48 -> 798454.51 | N48: =F48+G48+H48+M48 -> 798454.51 | O48: =E48-N48 -> 2193818.1 | P48: =IF(O48<300000,0.07*O48,21000) -> 21000 | Q48: =IF((O48-300000)<0,0,IF((O48-300000)<300000,0.11*(O48-300000),33000)) -> 33000 | R48: =IF((O48-600000)<0,0,IF((O48-600000)<500000,0.15*(O48-600000),75000)) -> 75000 | S48: =IF((O48-1100000)<0,0,IF((O48-1100000)<500000,0.19*(O48-1100000),95000)) -> 95000 | T48: =IF((O48-1600000)<0,0,IF((O48-1600000)<1600000,0.21*(O48-1600000),336000)) -> 124701.79 | V48: =P48+Q48+R48+S48+T48+U48 -> 348701.79 | W48: 12 | X48: =V48/W48 -> 29058.483 | Z48: =X48 -> 29058.483 | AA48: 29058.483 | AB48: =Z48-AA48 -> 0
A49: 44 | B49: ABDULLAHI AHMAD USMAN | C49: 249356.05 | D49: 12 | E49: =C49*D49 -> 2992272.6 | I49: =E49-F49-G49-H49 -> 2992272.6 | J49: 200000 | K49: 0.2 | L49: =I49*K49 -> 598454.51 | M49: =J49+L49 -> 798454.51 | N49: =F49+G49+H49+M49 -> 798454.51 | O49: =E49-N49 -> 2193818.1 | P49: =IF(O49<300000,0.07*O49,21000) -> 21000 | Q49: =IF((O49-300000)<0,0,IF((O49-300000)<300000,0.11*(O49-300000),33000)) -> 33000 | R49: =IF((O49-600000)<0,0,IF((O49-600000)<500000,0.15*(O49-600000),75000)) -> 75000 | S49: =IF((O49-1100000)<0,0,IF((O49-1100000)<500000,0.19*(O49-1100000),95000)) -> 95000 | T49: =IF((O49-1600000)<0,0,IF((O49-1600000)<1600000,0.21*(O49-1600000),336000)) -> 124701.79 | V49: =P49+Q49+R49+S49+T49+U49 -> 348701.79 | W49: 12 | X49: 28360.953 | Z49: =X49 -> 28360.953 | AA49: 28360.953 | AB49: =Z49-AA49 -> 0
A50: 45 | B50: GUNAT NANSAK MARK | C50: 249356.05 | D50: 12 | E50: =C50*D50 -> 2992272.6 | I50: =E50-F50-G50-H50 -> 2992272.6 | J50: 200000 | K50: 0.2 | L50: =I50*K50 -> 598454.51 | M50: =J50+L50 -> 798454.51 | N50: =F50+G50+H50+M50 -> 798454.51 | O50: =E50-N50 -> 2193818.1 | P50: =IF(O50<300000,0.07*O50,21000) -> 21000 | Q50: =IF((O50-300000)<0,0,IF((O50-300000)<300000,0.11*(O50-300000),33000)) -> 33000 | R50: =IF((O50-600000)<0,0,IF((O50-600000)<500000,0.15*(O50-600000),75000)) -> 75000 | S50: =IF((O50-1100000)<0,0,IF((O50-1100000)<500000,0.19*(O50-1100000),95000)) -> 95000 | T50: =IF((O50-1600000)<0,0,IF((O50-1600000)<1600000,0.21*(O50-1600000),336000)) -> 124701.79 | V50: =P50+Q50+R50+S50+T50+U50 -> 348701.79 | W50: 12 | X50: =V50/W50 -> 29058.483 | Z50: =X50 -> 29058.483 | AA50: 29058.483 | AB50: =Z50-AA50 -> 0
B52: LEGAL SERVICES
A53: 47 | B53: DR SHUIBU DANWANKA | C53: 1050209.1 | D53: 12 | E53: =C53*D53 -> 12602509 | I53: =E53-F53-G53-H53 -> 12602509 | J53: 200000 | K53: 0.2 | L53: =I53*K53 -> 2520501.8 | M53: =J53+L53 -> 2720501.8 | N53: =F53+G53+H53+M53 -> 2720501.8 | O53: =E53-N53 -> 9882007 | P53: =IF(O53<300000,0.07*O53,21000) -> 21000 | Q53: =IF((O53-300000)<0,0,IF((O53-300000)<300000,0.11*(O53-300000),33000)) -> 33000 | R53: =IF((O53-600000)<0,0,IF((O53-600000)<500000,0.15*(O53-600000),75000)) -> 75000 | S53: =IF((O53-1100000)<0,0,IF((O53-1100000)<500000,0.19*(O53-1100000),95000)) -> 95000 | T53: =IF((O53-1600000)<0,0,IF((O53-1600000)<1600000,0.21*(O53-1600000),336000)) -> 336000 | U53: =24%*(O53-3200000) -> 1603681.7 | V53: =P53+Q53+R53+S53+T53+U53 -> 2163681.7 | W53: 12 | X53: =V53/W53 -> 180306.81 | Z53: =X53 -> 180306.81 | AA53: 180306.81 | AB53: =Z53-AA53 -> 0
A54: 48 | B54: ABDULSALAM BAKO | C54: 447553.5 | D54: 12 | E54: =C54*D54 -> 5370642 | I54: =E54-F54-G54-H54 -> 5370642 | J54: 200000 | K54: 0.2 | L54: =I54*K54 -> 1074128.4 | M54: =J54+L54 -> 1274128.4 | N54: =F54+G54+H54+M54 -> 1274128.4 | O54: =E54-N54 -> 4096513.6 | P54: =IF(O54<300000,0.07*O54,21000) -> 21000 | Q54: =IF((O54-300000)<0,0,IF((O54-300000)<300000,0.11*(O54-300000),33000)) -> 33000 | R54: =IF((O54-600000)<0,0,IF((O54-600000)<500000,0.15*(O54-600000),75000)) -> 75000 | S54: =IF((O54-1100000)<0,0,IF((O54-1100000)<500000,0.19*(O54-1100000),95000)) -> 95000 | T54: =IF((O54-1600000)<0,0,IF((O54-1600000)<1600000,0.21*(O54-1600000),336000)) -> 336000 | U54: =24%*(O54-3200000) -> 215163.27 | V54: =P54+Q54+R54+S54+T54+U54 -> 775163.27 | W54: 12 | X54: =V54/W54 -> 64596.939 | Z54: =X54 -> 64596.939 | AA54: 64596.939 | AB54: =Z54-AA54 -> 0
A56: 49 | B56: DEMOCRACY & GOVERNANCE
A57: 50 | B57: DR. ADEWALE ADEREMI | C57: 1050209.1 | D57: 12 | E57: =C57*D57 -> 12602509 | I57: =E57-F57-G57-H57 -> 12602509 | J57: 200000 | K57: 0.2 | L57: =I57*K57 -> 2520501.8 | M57: =J57+L57 -> 2720501.8 | N57: =F57+G57+H57+M57 -> 2720501.8 | O57: =E57-N57 -> 9882007 | P57: =IF(O57<300000,0.07*O57,21000) -> 21000 | Q57: =IF((O57-300000)<0,0,IF((O57-300000)<300000,0.11*(O57-300000),33000)) -> 33000 | R57: =IF((O57-600000)<0,0,IF((O57-600000)<500000,0.15*(O57-600000),75000)) -> 75000 | S57: =IF((O57-1100000)<0,0,IF((O57-1100000)<500000,0.19*(O57-1100000),95000)) -> 95000 | T57: =IF((O57-1600000)<0,0,IF((O57-1600000)<1600000,0.21*(O57-1600000),336000)) -> 336000 | U57: =24%*(O57-3200000) -> 1603681.7 | V57: =P57+Q57+R57+S57+T57+U57 -> 2163681.7 | W57: 12 | X57: =V57/W57 -> 180306.81 | Z57: =X57 -> 180306.81 | AA57: 180306.81 | AB57: =Z57-AA57 -> 0
A58: 51 | B58: NDANUSA MOHAMMED MANZUMA | C58: 516137.05 | D58: 12 | E58: =C58*D58 -> 6193644.6 | I58: =E58-F58-G58-H58 -> 6193644.6 | J58: 200000 | K58: 0.2 | L58: =I58*K58 -> 1238728.9 | M58: =J58+L58 -> 1438728.9 | N58: =F58+G58+H58+M58 -> 1438728.9 | O58: =E58-N58 -> 4754915.7 | P58: =IF(O58<300000,0.07*O58,21000) -> 21000 | Q58: =IF((O58-300000)<0,0,IF((O58-300000)<300000,0.11*(O58-300000),33000)) -> 33000 | R58: =IF((O58-600000)<0,0,IF((O58-600000)<500000,0.15*(O58-600000),75000)) -> 75000 | S58: =IF((O58-1100000)<0,0,IF((O58-1100000)<500000,0.19*(O58-1100000),95000)) -> 95000 | T58: =IF((O58-1600000)<0,0,IF((O58-1600000)<1600000,0.21*(O58-1600000),336000)) -> 336000 | U58: =24%*(O58-3200000) -> 373179.76 | V58: =P58+Q58+R58+S58+T58+U58 -> 933179.76 | W58: 12 | X58: =V58/W58 -> 77764.98 | Z58: =X58 -> 77764.98 | AA58: 77764.98 | AB58: =Z58-AA58 -> 0
A59: 52 | B59: EJALONIBU GANIYU LAYI | C59: 397211.37 | D59: 12 | E59: =C59*D59 -> 4766536.4 | I59: =E59-F59-G59-H59 -> 4766536.4 | J59: 200000 | K59: 0.2 | L59: =I59*K59 -> 953307.28 | M59: =J59+L59 -> 1153307.3 | N59: =F59+G59+H59+M59 -> 1153307.3 | O59: =E59-N59 -> 3613229.1 | P59: =IF(O59<300000,0.07*O59,21000) -> 21000 | Q59: =IF((O59-300000)<0,0,IF((O59-300000)<300000,0.11*(O59-300000),33000)) -> 33000 | R59: =IF((O59-600000)<0,0,IF((O59-600000)<500000,0.15*(O59-600000),75000)) -> 75000 | S59: =IF((O59-1100000)<0,0,IF((O59-1100000)<500000,0.19*(O59-1100000),95000)) -> 95000 | T59: =IF((O59-1600000)<0,0,IF((O59-1600000)<1600000,0.21*(O59-1600000),336000)) -> 336000 | U59: =24%*(O59-3200000) -> 99174.991 | V59: =P59+Q59+R59+S59+T59+U59 -> 659174.99 | W59: 12 | X59: =V59/W59 -> 54931.249 | Z59: =X59 -> 54931.249 | AA59: 54931.249 | AB59: =Z59-AA59 -> 0
A60: 53 | B60: LOHNA BONKAT JONATHAN | C60: 369177.65 | D60: 12 | E60: =C60*D60 -> 4430131.8 | I60: =E60-F60-G60-H60 -> 4430131.8 | J60: 200000 | K60: 0.2 | L60: =I60*K60 -> 886026.37 | M60: =J60+L60 -> 1086026.4 | N60: =F60+G60+H60+M60 -> 1086026.4 | O60: =E60-N60 -> 3344105.5 | P60: =IF(O60<300000,0.07*O60,21000) -> 21000 | Q60: =IF((O60-300000)<0,0,IF((O60-300000)<300000,0.11*(O60-300000),33000)) -> 33000 | R60: =IF((O60-600000)<0,0,IF((O60-600000)<500000,0.15*(O60-600000),75000)) -> 75000 | S60: =IF((O60-1100000)<0,0,IF((O60-1100000)<500000,0.19*(O60-1100000),95000)) -> 95000 | T60: =IF((O60-1600000)<0,0,IF((O60-1600000)<1600000,0.21*(O60-1600000),336000)) -> 336000 | U60: =24%*(O60-3200000) -> 34585.314 | V60: =P60+Q60+R60+S60+T60+U60 -> 594585.31 | W60: 12 | X60: =V60/W60 -> 49548.776 | Z60: =X60 -> 49548.776 | AA60: 49548.776 | AB60: =Z60-AA60 -> 0
A61: 54 | B61: YUNUSA ABDULLAHI | C61: 421394.01 | D61: 12 | E61: =C61*D61 -> 5056728.1 | I61: =E61-F61-G61-H61 -> 5056728.1 | J61: 200000 | K61: 0.2 | L61: =I61*K61 -> 1011345.6 | M61: =J61+L61 -> 1211345.6 | N61: =F61+G61+H61+M61 -> 1211345.6 | O61: =E61-N61 -> 3845382.5 | P61: =IF(O61<300000,0.07*O61,21000) -> 21000 | Q61: =IF((O61-300000)<0,0,IF((O61-300000)<300000,0.11*(O61-300000),33000)) -> 33000 | R61: =IF((O61-600000)<0,0,IF((O61-600000)<500000,0.15*(O61-600000),75000)) -> 75000 | S61: =IF((O61-1100000)<0,0,IF((O61-1100000)<500000,0.19*(O61-1100000),95000)) -> 95000 | T61: =IF((O61-1600000)<0,0,IF((O61-1600000)<1600000,0.21*(O61-1600000),336000)) -> 336000 | U61: =24%*(O61-3200000) -> 154891.79 | V61: =P61+Q61+R61+S61+T61+U61 -> 714891.79 | W61: 12 | X61: =V61/W61 -> 59574.316 | Z61: =X61 -> 59574.316 | AA61: 46666.667 | AB61: =Z61-AA61 -> 12907.649
A62: 55 | B62: UDEFUNA NNADOZIE PATRICK | C62: 322454.07 | D62: 12 | E62: =C62*D62 -> 3869448.9 | I62: =E62-F62-G62-H62 -> 3869448.9 | J62: 200000 | K62: 0.2 | L62: =I62*K62 -> 773889.78 | M62: =J62+L62 -> 973889.78 | N62: =F62+G62+H62+M62 -> 973889.78 | O62: =E62-N62 -> 2895559.1 | P62: =IF(O62<300000,0.07*O62,21000) -> 21000 | Q62: =IF((O62-300000)<0,0,IF((O62-300000)<300000,0.11*(O62-300000),33000)) -> 33000 | R62: =IF((O62-600000)<0,0,IF((O62-600000)<500000,0.15*(O62-600000),75000)) -> 75000 | S62: =IF((O62-1100000)<0,0,IF((O62-1100000)<500000,0.19*(O62-1100000),95000)) -> 95000 | T62: =IF((O62-1600000)<0,0,IF((O62-1600000)<1600000,0.21*(O62-1600000),336000)) -> 272067.41 | V62: =P62+Q62+R62+S62+T62+U62 -> 496067.41 | W62: 12 | X62: =V62/W62 -> 41338.951 | Z62: =X62 -> 41338.951 | AA62: 41338.951 | AB62: =Z62-AA62 -> 0
A63: 56 | B63: SHAFIU YAHYA MIKAIL | C63: 322454.07 | D63: 12 | E63: =C63*D63 -> 3869448.9 | I63: =E63-F63-G63-H63 -> 3869448.9 | J63: 200000 | K63: 0.2 | L63: =I63*K63 -> 773889.78 | M63: =J63+L63 -> 973889.78 | N63: =F63+G63+H63+M63 -> 973889.78 | O63: =E63-N63 -> 2895559.1 | P63: =IF(O63<300000,0.07*O63,21000) -> 21000 | Q63: =IF((O63-300000)<0,0,IF((O63-300000)<300000,0.11*(O63-300000),33000)) -> 33000 | R63: =IF((O63-600000)<0,0,IF((O63-600000)<500000,0.15*(O63-600000),75000)) -> 75000 | S63: =IF((O63-1100000)<0,0,IF((O63-1100000)<500000,0.19*(O63-1100000),95000)) -> 95000 | T63: =IF((O63-1600000)<0,0,IF((O63-1600000)<1600000,0.21*(O63-1600000),336000)) -> 272067.41 | V63: =P63+Q63+R63+S63+T63+U63 -> 496067.41 | W63: 12 | X63: =V63/W63 -> 41338.951 | Z63: =X63 -> 41338.951 | AA63: 41338.951 | AB63: =Z63-AA63 -> 0
A64: 57 | B64: HASSAN YERIMA | C64: 322454.07 | D64: 12 | E64: =C64*D64 -> 3869448.9 | I64: =E64-F64-G64-H64 -> 3869448.9 | J64: 200000 | K64: 0.2 | L64: =I64*K64 -> 773889.78 | M64: =J64+L64 -> 973889.78 | N64: =F64+G64+H64+M64 -> 973889.78 | O64: =E64-N64 -> 2895559.1 | P64: =IF(O64<300000,0.07*O64,21000) -> 21000 | Q64: =IF((O64-300000)<0,0,IF((O64-300000)<300000,0.11*(O64-300000),33000)) -> 33000 | R64: =IF((O64-600000)<0,0,IF((O64-600000)<500000,0.15*(O64-600000),75000)) -> 75000 | S64: =IF((O64-1100000)<0,0,IF((O64-1100000)<500000,0.19*(O64-1100000),95000)) -> 95000 | T64: =IF((O64-1600000)<0,0,IF((O64-1600000)<1600000,0.21*(O64-1600000),336000)) -> 272067.41 | V64: =P64+Q64+R64+S64+T64+U64 -> 496067.41 | W64: 12 | X64: =V64/W64 -> 41338.951 | Z64: =X64 -> 41338.951 | AA64: 41338.951 | AB64: =Z64-AA64 -> 0
A65: 58 | B65: HAUWA PATE SADIQ | C65: 334537 | D65: 12 | E65: =C65*D65 -> 4014444 | I65: =E65-F65-G65-H65 -> 4014444 | J65: 200000 | K65: 0.2 | L65: =I65*K65 -> 802888.8 | M65: =J65+L65 -> 1002888.8 | N65: =F65+G65+H65+M65 -> 1002888.8 | O65: =E65-N65 -> 3011555.2 | P65: =IF(O65<300000,0.07*O65,21000) -> 21000 | Q65: =IF((O65-300000)<0,0,IF((O65-300000)<300000,0.11*(O65-300000),33000)) -> 33000 | R65: =IF((O65-600000)<0,0,IF((O65-600000)<500000,0.15*(O65-600000),75000)) -> 75000 | S65: =IF((O65-1100000)<0,0,IF((O65-1100000)<500000,0.19*(O65-1100000),95000)) -> 95000 | T65: =IF((O65-1600000)<0,0,IF((O65-1600000)<1600000,0.21*(O65-1600000),336000)) -> 296426.59 | V65: =P65+Q65+R65+S65+T65+U65 -> 520426.59 | W65: 12 | X65: =V65/W65 -> 43368.882 | Z65: =X65 -> 43368.882 | AA65: 43368.882 | AB65: =Z65-AA65 -> 0
A66: 59 | B66: KOLAPO Q. ABAYOMI | C66: 277734.05 | D66: 12 | E66: =C66*D66 -> 3332808.6 | I66: =E66-F66-G66-H66 -> 3332808.6 | J66: 200000 | K66: 0.2 | L66: =I66*K66 -> 666561.71 | M66: =J66+L66 -> 866561.71 | N66: =F66+G66+H66+M66 -> 866561.71 | O66: =E66-N66 -> 2466246.9 | P66: =IF(O66<300000,0.07*O66,21000) -> 21000 | Q66: =IF((O66-300000)<0,0,IF((O66-300000)<300000,0.11*(O66-300000),33000)) -> 33000 | R66: =IF((O66-600000)<0,0,IF((O66-600000)<500000,0.15*(O66-600000),75000)) -> 75000 | S66: =IF((O66-1100000)<0,0,IF((O66-1100000)<500000,0.19*(O66-1100000),95000)) -> 95000 | T66: =IF((O66-1600000)<0,0,IF((O66-1600000)<1600000,0.21*(O66-1600000),336000)) -> 181911.84 | V66: =P66+Q66+R66+S66+T66+U66 -> 405911.84 | W66: 12 | X66: =V66/W66 -> 33825.987 | Z66: =X66 -> 33825.987 | AA66: 33825.987 | AB66: =Z66-AA66 -> 0
A67: 60
A68: 61
B69: DEPARTMENT OF STUDIES
B70: DR ASIMIYU G. ABIOLA | C70: 1050209.1 | D70: 12 | E70: =C70*D70 -> 12602509 | I70: =E70-F70-G70-H70 -> 12602509 | J70: 200000 | K70: 0.2 | L70: =I70*K70 -> 2520501.8 | M70: =J70+L70 -> 2720501.8 | N70: =F70+G70+H70+M70 -> 2720501.8 | O70: =E70-N70 -> 9882007 | P70: =IF(O70<300000,0.07*O70,21000) -> 21000 | Q70: =IF((O70-300000)<0,0,IF((O70-300000)<300000,0.11*(O70-300000),33000)) -> 33000 | R70: =IF((O70-600000)<0,0,IF((O70-600000)<500000,0.15*(O70-600000),75000)) -> 75000 | S70: =IF((O70-1100000)<0,0,IF((O70-1100000)<500000,0.19*(O70-1100000),95000)) -> 95000 | T70: =IF((O70-1600000)<0,0,IF((O70-1600000)<1600000,0.21*(O70-1600000),336000)) -> 336000 | U70: =24%*(O70-3200000) -> 1603681.7 | V70: =P70+Q70+R70+S70+T70+U70 -> 2163681.7 | W70: 12 | X70: =V70/W70 -> 180306.81 | Z70: =X70 -> 180306.81 | AA70: 180306.81 | AB70: =Z70-AA70 -> 0
A71: 62 | B71: USMAN WALI | C71: 516137.05 | D71: 12 | E71: =C71*D71 -> 6193644.6 | I71: =E71-F71-G71-H71 -> 6193644.6 | J71: 200000 | K71: 0.2 | L71: =I71*K71 -> 1238728.9 | M71: =J71+L71 -> 1438728.9 | N71: =F71+G71+H71+M71 -> 1438728.9 | O71: =E71-N71 -> 4754915.7 | P71: =IF(O71<300000,0.07*O71,21000) -> 21000 | Q71: =IF((O71-300000)<0,0,IF((O71-300000)<300000,0.11*(O71-300000),33000)) -> 33000 | R71: =IF((O71-600000)<0,0,IF((O71-600000)<500000,0.15*(O71-600000),75000)) -> 75000 | S71: =IF((O71-1100000)<0,0,IF((O71-1100000)<500000,0.19*(O71-1100000),95000)) -> 95000 | T71: =IF((O71-1600000)<0,0,IF((O71-1600000)<1600000,0.21*(O71-1600000),336000)) -> 336000 | U71: =24%*(O71-3200000) -> 373179.76 | V71: =P71+Q71+R71+S71+T71+U71 -> 933179.76 | W71: 12 | X71: =V71/W71 -> 77764.98 | Z71: =X71 -> 77764.98 | AA71: 77764.98 | AB71: =Z71-AA71 -> 0
A72: 63 | B72: AYOBOLU OLAJIDE OLUFUNSHO | C72: 447553.5 | D72: 12 | E72: =C72*D72 -> 5370642 | I72: =E72-F72-G72-H72 -> 5370642 | J72: 200000 | K72: 0.2 | L72: =I72*K72 -> 1074128.4 | M72: =J72+L72 -> 1274128.4 | N72: =F72+G72+H72+M72 -> 1274128.4 | O72: =E72-N72 -> 4096513.6 | P72: =IF(O72<300000,0.07*O72,21000) -> 21000 | Q72: =IF((O72-300000)<0,0,IF((O72-300000)<300000,0.11*(O72-300000),33000)) -> 33000 | R72: =IF((O72-600000)<0,0,IF((O72-600000)<500000,0.15*(O72-600000),75000)) -> 75000 | S72: =IF((O72-1100000)<0,0,IF((O72-1100000)<500000,0.19*(O72-1100000),95000)) -> 95000 | T72: =IF((O72-1600000)<0,0,IF((O72-1600000)<1600000,0.21*(O72-1600000),336000)) -> 336000 | U72: =24%*(O72-3200000) -> 215163.27 | V72: =P72+Q72+R72+S72+T72+U72 -> 775163.27 | W72: 12 | X72: =V72/W72 -> 64596.939 | Z72: =X72 -> 64596.939 | AA72: 64596.939 | AB72: =Z72-AA72 -> 0
A73: 64 | B73: ANTHONY EDET | C73: 405272.06 | D73: 12 | E73: =C73*D73 -> 4863264.8 | F73: ='[4]JANUARY 2024'!$V$78*12 -> 8019.795 | I73: =E73-F73-G73-H73 -> 4855245 | J73: 200000 | K73: 0.2 | L73: =I73*K73 -> 971048.99 | M73: =J73+L73 -> 1171049 | N73: =F73+G73+H73+M73 -> 1179068.8 | O73: =E73-N73 -> 3684196 | P73: =IF(O73<300000,0.07*O73,21000) -> 21000 | Q73: =IF((O73-300000)<0,0,IF((O73-300000)<300000,0.11*(O73-300000),33000)) -> 33000 | R73: =IF((O73-600000)<0,0,IF((O73-600000)<500000,0.15*(O73-600000),75000)) -> 75000 | S73: =IF((O73-1100000)<0,0,IF((O73-1100000)<500000,0.19*(O73-1100000),95000)) -> 95000 | T73: =IF((O73-1600000)<0,0,IF((O73-1600000)<1600000,0.21*(O73-1600000),336000)) -> 336000 | U73: =24%*(O73-3200000) -> 116207.03 | V73: =P73+Q73+R73+S73+T73+U73 -> 676207.03 | W73: 12 | X73: =V73/W73 -> 56350.586 | Z73: =X73 -> 56350.586 | AA73: 56350.586 | AB73: =Z73-AA73 -> 0
A74: 65 | B74: IGWE STACY | C74: 273169.12 | D74: 12 | E74: =C74*D74 -> 3278029.4 | I74: =E74-F74-G74-H74 -> 3278029.4 | J74: 200000 | K74: 0.2 | L74: =I74*K74 -> 655605.88 | M74: =J74+L74 -> 855605.88 | N74: =F74+G74+H74+M74 -> 855605.88 | O74: =E74-N74 -> 2422423.5 | P74: =IF(O74<300000,0.07*O74,21000) -> 21000 | Q74: =IF((O74-300000)<0,0,IF((O74-300000)<300000,0.11*(O74-300000),33000)) -> 33000 | R74: =IF((O74-600000)<0,0,IF((O74-600000)<500000,0.15*(O74-600000),75000)) -> 75000 | S74: =IF((O74-1100000)<0,0,IF((O74-1100000)<500000,0.19*(O74-1100000),95000)) -> 95000 | T74: =IF((O74-1600000)<0,0,IF((O74-1600000)<1600000,0.21*(O74-1600000),336000)) -> 172708.94 | V74: =P74+Q74+R74+S74+T74+U74 -> 396708.94 | W74: 12 | X74: =V74/W74 -> 33059.078 | Z74: =X74 -> 33059.078 | AA74: 17507.549 | AB74: =Z74-AA74 -> 15551.529
B75: OLANIYAN TAIWO ABINBOLA | C75: 249356.05 | D75: 12 | E75: =C75*D75 -> 2992272.6 | I75: =E75-F75-G75-H75 -> 2992272.6 | J75: 200000 | K75: 0.2 | L75: =I75*K75 -> 598454.51 | M75: =J75+L75 -> 798454.51 | N75: =F75+G75+H75+M75 -> 798454.51 | O75: =E75-N75 -> 2193818.1 | P75: =IF(O75<300000,0.07*O75,21000) -> 21000 | Q75: =IF((O75-300000)<0,0,IF((O75-300000)<300000,0.11*(O75-300000),33000)) -> 33000 | R75: =IF((O75-600000)<0,0,IF((O75-600000)<500000,0.15*(O75-600000),75000)) -> 75000 | S75: =IF((O75-1100000)<0,0,IF((O75-1100000)<500000,0.19*(O75-1100000),95000)) -> 95000 | T75: =IF((O75-1600000)<0,0,IF((O75-1600000)<1600000,0.21*(O75-1600000),336000)) -> 124701.79 | V75: =P75+Q75+R75+S75+T75+U75 -> 348701.79 | W75: 12 | X75: =V75/W75 -> 29058.483 | Z75: =X75 -> 29058.483 | AA75: 29058.483 | AB75: =Z75-AA75 -> 0
B76: AMINAT JUMOKE SULAIMON | C76: 223717.28 | D76: 12 | E76: =C76*D76 -> 2684607.4 | I76: =E76-F76-G76-H76 -> 2684607.4 | J76: 200000 | K76: 0.2 | L76: =I76*K76 -> 536921.48 | M76: =J76+L76 -> 736921.48 | N76: =F76+G76+H76+M76 -> 736921.48 | O76: =E76-N76 -> 1947685.9 | P76: =IF(O76<300000,0.07*O76,21000) -> 21000 | Q76: =IF((O76-300000)<0,0,IF((O76-300000)<300000,0.11*(O76-300000),33000)) -> 33000 | R76: =IF((O76-600000)<0,0,IF((O76-600000)<500000,0.15*(O76-600000),75000)) -> 75000 | S76: =IF((O76-1100000)<0,0,IF((O76-1100000)<500000,0.19*(O76-1100000),95000)) -> 95000 | T76: =IF((O76-1600000)<0,0,IF((O76-1600000)<1600000,0.21*(O76-1600000),336000)) -> 73014.046 | U76: 0 | V76: =P76+Q76+R76+S76+T76+U76 -> 297014.05 | W76: 12 | X76: =V76/W76 -> 24751.17 | Z76: =X76 -> 24751.17 | AA76: 24751.17 | AB76: =Z76-AA76 -> 0
B77: TOTAL | AB77: =SUM(AB70:AB76) -> 15551.529
A78: 66
A79: 67 | B79: ECON. DEV. & SOC. RESEARCH | AB79: difference
A80: 68 | B80: TERFA WILLIAMS ABRAHAM | C80: 627553.5 | D80: 12 | E80: =C80*D80 -> 7530642 | I80: =E80-F80-G80-H80 -> 7530642 | J80: 200000 | K80: 0.2 | L80: =I80*K80 -> 1506128.4 | M80: =J80+L80 -> 1706128.4 | N80: =F80+G80+H80+M80 -> 1706128.4 | O80: =E80-N80 -> 5824513.6 | P80: =IF(O80<300000,0.07*O80,21000) -> 21000 | Q80: =IF((O80-300000)<0,0,IF((O80-300000)<300000,0.11*(O80-300000),33000)) -> 33000 | R80: =IF((O80-600000)<0,0,IF((O80-600000)<500000,0.15*(O80-600000),75000)) -> 75000 | S80: =IF((O80-1100000)<0,0,IF((O80-1100000)<500000,0.19*(O80-1100000),95000)) -> 95000 | T80: =IF((O80-1600000)<0,0,IF((O80-1600000)<1600000,0.21*(O80-1600000),336000)) -> 336000 | U80: =24%*(O80-3200000) -> 629883.27 | V80: =P80+Q80+R80+S80+T80+U80 -> 1189883.3 | W80: 12 | X80: =V80/W80 -> 99156.939 | Z80: =X80 -> 99156.939 | AA80: 99156.939 | AB80: =Z80-AA80 -> 0 | AC80: TERFA WILLIAMS ABRAHAM
A81: 69 | B81: DR AUGUSTINE C. OSIGWE | C81: 527553.5 | D81: 12 | E81: =C81*D81 -> 6330642 | F81: ='[4]JANUARY 2024'!$V$86*12 -> 10052.25 | I81: =E81-F81-G81-H81 -> 6320589.8 | J81: 200000 | K81: 0.2 | L81: =I81*K81 -> 1264118 | M81: =J81+L81 -> 1464118 | N81: =F81+G81+H81+M81 -> 1474170.2 | O81: =E81-N81 -> 4856471.8 | P81: =IF(O81<300000,0.07*O81,21000) -> 21000 | Q81: =IF((O81-300000)<0,0,IF((O81-300000)<300000,0.11*(O81-300000),33000)) -> 33000 | R81: =IF((O81-600000)<0,0,IF((O81-600000)<500000,0.15*(O81-600000),75000)) -> 75000 | S81: =IF((O81-1100000)<0,0,IF((O81-1100000)<500000,0.19*(O81-1100000),95000)) -> 95000 | T81: =IF((O81-1600000)<0,0,IF((O81-1600000)<1600000,0.21*(O81-1600000),336000)) -> 336000 | U81: =24%*(O81-3200000) -> 397553.24 | V81: =P81+Q81+R81+S81+T81+U81 -> 957553.24 | W81: 12 | X81: =V81/W81 -> 79796.103 | Z81: =X81 -> 79796.103 | AA81: 98996.103 | AB81: =Z81-AA81 -> -19200 | AC81: DR AUGUSTINE C. OSIGWE
A82: 70 | B82: OMOJU OLUWASOLA EMMANUEL | C82: 504729.22 | D82: 12 | E82: =C82*D82 -> 6056750.7 | I82: =E82-F82-G82-H82 -> 6056750.7 | J82: 200000 | K82: 0.2 | L82: =I82*K82 -> 1211350.1 | M82: =J82+L82 -> 1411350.1 | N82: =F82+G82+H82+M82 -> 1411350.1 | O82: =E82-N82 -> 4645400.5 | P82: =IF(O82<300000,0.07*O82,21000) -> 21000 | Q82: =IF((O82-300000)<0,0,IF((O82-300000)<300000,0.11*(O82-300000),33000)) -> 33000 | R82: =IF((O82-600000)<0,0,IF((O82-600000)<500000,0.15*(O82-600000),75000)) -> 75000 | S82: =IF((O82-1100000)<0,0,IF((O82-1100000)<500000,0.19*(O82-1100000),95000)) -> 95000 | T82: =IF((O82-1600000)<0,0,IF((O82-1600000)<1600000,0.21*(O82-1600000),336000)) -> 336000 | U82: =24%*(O82-3200000) -> 346896.13 | V82: =P82+Q82+R82+S82+T82+U82 -> 906896.13 | W82: 12 | X82: =V82/W82 -> 75574.677 | Z82: =X82 -> 75574.677 | AA82: 79956.939 | AB82: =Z82-AA82 -> -4382.2619 | AC82: OMOJU OLUWASOLA EMMANUEL
A83: 71 | B83: IBE EZECHI CYRIACUS | C83: 376663.08 | D83: 12 | E83: =C83*D83 -> 4519956.9 | I83: =E83-F83-G83-H83 -> 4519956.9 | J83: 200000 | K83: 0.2 | L83: =I83*K83 -> 903991.39 | M83: =J83+L83 -> 1103991.4 | N83: =F83+G83+H83+M83 -> 1103991.4 | O83: =E83-N83 -> 3415965.5 | P83: =IF(O83<300000,0.07*O83,21000) -> 21000 | Q83: =IF((O83-300000)<0,0,IF((O83-300000)<300000,0.11*(O83-300000),33000)) -> 33000 | R83: =IF((O83-600000)<0,0,IF((O83-600000)<500000,0.15*(O83-600000),75000)) -> 75000 | S83: =IF((O83-1100000)<0,0,IF((O83-1100000)<500000,0.19*(O83-1100000),95000)) -> 95000 | T83: =IF((O83-1600000)<0,0,IF((O83-1600000)<1600000,0.21*(O83-1600000),336000)) -> 336000 | U83: =24%*(O83-3200000) -> 51831.731 | V83: =P83+Q83+R83+S83+T83+U83 -> 611831.73 | W83: 12 | X83: =V83/W83 -> 50985.978 | Z83: =X83 -> 50985.978 | AA83: 75574.677 | AB83: =Z83-AA83 -> -24588.7 | AC83: IBE EZECHI CYRIACUS
A84: 72 | B84: OSIKHEN LEO IGBANOI | C84: 369177.65 | D84: 12 | E84: =C84*D84 -> 4430131.8 | I84: =E84-F84-G84-H84 -> 4430131.8 | J84: 200000 | K84: 0.2 | L84: =I84*K84 -> 886026.37 | M84: =J84+L84 -> 1086026.4 | N84: =F84+G84+H84+M84 -> 1086026.4 | O84: =E84-N84 -> 3344105.5 | P84: =IF(O84<300000,0.07*O84,21000) -> 21000 | Q84: =IF((O84-300000)<0,0,IF((O84-300000)<300000,0.11*(O84-300000),33000)) -> 33000 | R84: =IF((O84-600000)<0,0,IF((O84-600000)<500000,0.15*(O84-600000),75000)) -> 75000 | S84: =IF((O84-1100000)<0,0,IF((O84-1100000)<500000,0.19*(O84-1100000),95000)) -> 95000 | T84: =IF((O84-1600000)<0,0,IF((O84-1600000)<1600000,0.21*(O84-1600000),336000)) -> 336000 | U84: =24%*(O84-3200000) -> 34585.314 | V84: =P84+Q84+R84+S84+T84+U84 -> 594585.31 | W84: 12 | X84: =V84/W84 -> 49548.776 | Z84: =X84 -> 49548.776 | AA84: 50985.978 | AB84: =Z84-AA84 -> -1437.2014 | AC84: OSIKHEN LEO IGBANOI
A85: 73 | B85: OKUNGBOWA OSARETIN GODSPOWER | C85: 389153.06 | D85: 12 | E85: =C85*D85 -> 4669836.7 | I85: =E85-F85-G85-H85 -> 4669836.7 | J85: 200000 | K85: 0.2 | L85: =I85*K85 -> 933967.34 | M85: =J85+L85 -> 1133967.3 | N85: =F85+G85+H85+M85 -> 1133967.3 | O85: =E85-N85 -> 3535869.3 | P85: =IF(O85<300000,0.07*O85,21000) -> 21000 | Q85: =IF((O85-300000)<0,0,IF((O85-300000)<300000,0.11*(O85-300000),33000)) -> 33000 | R85: =IF((O85-600000)<0,0,IF((O85-600000)<500000,0.15*(O85-600000),75000)) -> 75000 | S85: =IF((O85-1100000)<0,0,IF((O85-1100000)<500000,0.19*(O85-1100000),95000)) -> 95000 | T85: =IF((O85-1600000)<0,0,IF((O85-1600000)<1600000,0.21*(O85-1600000),336000)) -> 336000 | U85: =24%*(O85-3200000) -> 80608.643 | V85: =P85+Q85+R85+S85+T85+U85 -> 640608.64 | W85: 12 | X85: =V85/W85 -> 53384.054 | Z85: =X85 -> 53384.054 | AA85: 49548.776 | AB85: =Z85-AA85 -> 3835.2774 | AC85: OKUNGBOWA OSARETIN GODSPOWER
A86: 74 | B86: YUSUF IBRAHIM | C86: 322454.07 | D86: 12 | E86: =C86*D86 -> 3869448.9 | I86: =E86-F86-G86-H86 -> 3869448.9 | J86: 200000 | K86: 0.2 | L86: =I86*K86 -> 773889.78 | M86: =J86+L86 -> 973889.78 | N86: =F86+G86+H86+M86 -> 973889.78 | O86: =E86-N86 -> 2895559.1 | P86: =IF(O86<300000,0.07*O86,21000) -> 21000 | Q86: =IF((O86-300000)<0,0,IF((O86-300000)<300000,0.11*(O86-300000),33000)) -> 33000 | R86: =IF((O86-600000)<0,0,IF((O86-600000)<500000,0.15*(O86-600000),75000)) -> 75000 | S86: =IF((O86-1100000)<0,0,IF((O86-1100000)<500000,0.19*(O86-1100000),95000)) -> 95000 | T86: =IF((O86-1600000)<0,0,IF((O86-1600000)<1600000,0.21*(O86-1600000),336000)) -> 272067.41 | V86: =P86+Q86+R86+S86+T86+U86 -> 496067.41 | W86: 12 | X86: =V86/W86 -> 41338.951 | Z86: =X86 -> 41338.951 | AA86: 53384.054 | AB86: =Z86-AA86 -> -12045.102 | AC86: YUSUF IBRAHIM
A87: 75 | B87: MUSTAPHA RAFIU AYOBANJI | C87: 346713.03 | D87: 12 | E87: =C87*D87 -> 4160556.4 | F87: ='[4]JANUARY 2024'!$V$92*12 -> 6922.497 | I87: =E87-F87-G87-H87 -> 4153633.9 | J87: 200000 | K87: 0.2 | L87: =I87*K87 -> 830726.78 | M87: =J87+L87 -> 1030726.8 | N87: =F87+G87+H87+M87 -> 1037649.3 | O87: =E87-N87 -> 3122907.1 | P87: =IF(O87<300000,0.07*O87,21000) -> 21000 | Q87: =IF((O87-300000)<0,0,IF((O87-300000)<300000,0.11*(O87-300000),33000)) -> 33000 | R87: =IF((O87-600000)<0,0,IF((O87-600000)<500000,0.15*(O87-600000),75000)) -> 75000 | S87: =IF((O87-1100000)<0,0,IF((O87-1100000)<500000,0.19*(O87-1100000),95000)) -> 95000 | T87: =IF((O87-1600000)<0,0,IF((O87-1600000)<1600000,0.21*(O87-1600000),336000)) -> 319810.5 | V87: =P87+Q87+R87+S87+T87+U87 -> 543810.5 | W87: 12 | X87: =V87/W87 -> 45317.541 | Z87: =X87 -> 45317.541 | AA87: 41242.036 | AB87: =Z87-AA87 -> 4075.5052 | AC87: MUSTAPHA RAFIU AYOBANJI
A88: 76 | B88: MARYAM MUSA SADA | C88: 277734.05 | D88: 12 | E88: =C88*D88 -> 3332808.6 | I88: =E88-F88-G88-H88 -> 3332808.6 | J88: 200000 | K88: 0.2 | L88: =I88*K88 -> 666561.71 | M88: =J88+L88 -> 866561.71 | N88: =F88+G88+H88+M88 -> 866561.71 | O88: =E88-N88 -> 2466246.9 | P88: =IF(O88<300000,0.07*O88,21000) -> 21000 | Q88: =IF((O88-300000)<0,0,IF((O88-300000)<300000,0.11*(O88-300000),33000)) -> 33000 | R88: =IF((O88-600000)<0,0,IF((O88-600000)<500000,0.15*(O88-600000),75000)) -> 75000 | S88: =IF((O88-1100000)<0,0,IF((O88-1100000)<500000,0.19*(O88-1100000),95000)) -> 95000 | T88: =IF((O88-1600000)<0,0,IF((O88-1600000)<1600000,0.21*(O88-1600000),336000)) -> 181911.84 | V88: =P88+Q88+R88+S88+T88+U88 -> 405911.84 | W88: 12 | X88: =V88/W88 -> 33825.987 | Z88: =X88 -> 33825.987 | AA88: 45414.456 | AB88: =Z88-AA88 -> -11588.47 | AC88: MARYAM MUSA SADA
B89: CHARITY EZENWAJIOBI | C89: 254870.26 | D89: 12 | E89: =C89*D89 -> 3058443.2 | I89: =E89-F89-G89-H89 -> 3058443.2 | J89: 200000 | K89: 0.2 | L89: =I89*K89 -> 611688.63 | M89: =J89+L89 -> 811688.63 | N89: =F89+G89+H89+M89 -> 811688.63 | O89: =E89-N89 -> 2246754.5 | P89: =IF(O89<300000,0.07*O89,21000) -> 21000 | Q89: =IF((O89-300000)<0,0,IF((O89-300000)<300000,0.11*(O89-300000),33000)) -> 33000 | R89: =IF((O89-600000)<0,0,IF((O89-600000)<500000,0.15*(O89-600000),75000)) -> 75000 | S89: =IF((O89-1100000)<0,0,IF((O89-1100000)<500000,0.19*(O89-1100000),95000)) -> 95000 | T89: =IF((O89-1600000)<0,0,IF((O89-1600000)<1600000,0.21*(O89-1600000),336000)) -> 135818.45 | V89: =P89+Q89+R89+S89+T89+U89 -> 359818.45 | W89: 12 | X89: =V89/W89 -> 29984.871 | Z89: =X89 -> 29984.871 | AA89: 33825.987 | AB89: =Z89-AA89 -> -3841.1156 | AC89: CHARITY EZENWAJIOBI
AB90: =SUM(AB80:AB89) -> -69172.068
A92: 78 | B92: TRAINING & INT''L COOP
A93: 79 | B93: AKINSANMI ADEJOKE OLUKEMI | C93: 541465.02 | D93: 12 | E93: =C93*D93 -> 6497580.3 | F93: ='[4]JANUARY 2024'!$V$98*12 -> 12795.951 | I93: =E93-F93-G93-H93 -> 6484784.3 | J93: 200000 | K93: 0.2 | L93: =I93*K93 -> 1296956.9 | M93: =J93+L93 -> 1496956.9 | N93: =F93+G93+H93+M93 -> 1509752.8 | O93: =E93-N93 -> 4987827.5 | P93: =IF(O93<300000,0.07*O93,21000) -> 21000 | Q93: =IF((O93-300000)<0,0,IF((O93-300000)<300000,0.11*(O93-300000),33000)) -> 33000 | R93: =IF((O93-600000)<0,0,IF((O93-600000)<500000,0.15*(O93-600000),75000)) -> 75000 | S93: =IF((O93-1100000)<0,0,IF((O93-1100000)<500000,0.19*(O93-1100000),95000)) -> 95000 | T93: =IF((O93-1600000)<0,0,IF((O93-1600000)<1600000,0.21*(O93-1600000),336000)) -> 336000 | U93: =24%*(O93-3200000) -> 429078.59 | V93: =P93+Q93+R93+S93+T93+U93 -> 989078.59 | W93: 12 | X93: =V93/W93 -> 82423.216 | Z93: =X93 -> 82423.216 | AA93: 82423.216 | AB93: =Z93-AA93 -> 0 | AC93: AKINSANMI ADEJOKE OLUKEMI
A94: 80 | B94: MOHAMMED R. ADAMU | C94: 335272.06 | D94: 12 | E94: =C94*D94 -> 4023264.8 | I94: =E94-F94-G94-H94 -> 4023264.8 | J94: 200000 | K94: 0.2 | L94: =I94*K94 -> 804652.95 | M94: =J94+L94 -> 1004653 | N94: =F94+G94+H94+M94 -> 1004653 | O94: =E94-N94 -> 3018611.8 | P94: =IF(O94<300000,0.07*O94,21000) -> 21000 | Q94: =IF((O94-300000)<0,0,IF((O94-300000)<300000,0.11*(O94-300000),33000)) -> 33000 | R94: =IF((O94-600000)<0,0,IF((O94-600000)<500000,0.15*(O94-600000),75000)) -> 75000 | S94: =IF((O94-1100000)<0,0,IF((O94-1100000)<500000,0.19*(O94-1100000),95000)) -> 95000 | T94: =IF((O94-1600000)<0,0,IF((O94-1600000)<1600000,0.21*(O94-1600000),336000)) -> 297908.48 | V94: =P94+Q94+R94+S94+T94+U94 -> 521908.48 | W94: 12 | X94: =V94/W94 -> 43492.373 | Z94: =X94 -> 43492.373 | AA94: 82627.951 | AB94: =Z94-AA94 -> -39135.578 | AC94: MOHAMMED R. ADAMU
A95: 81 | B95: OKECHUKWU UCHENNA HULDA | C95: 284537 | D95: 12 | E95: =C95*D95 -> 3414444 | I95: =E95-F95-G95-H95 -> 3414444 | J95: 200000 | K95: 0.2 | L95: =I95*K95 -> 682888.8 | M95: =J95+L95 -> 882888.8 | N95: =F95+G95+H95+M95 -> 882888.8 | O95: =E95-N95 -> 2531555.2 | P95: =IF(O95<300000,0.07*O95,21000) -> 21000 | Q95: =IF((O95-300000)<0,0,IF((O95-300000)<300000,0.11*(O95-300000),33000)) -> 33000 | R95: =IF((O95-600000)<0,0,IF((O95-600000)<500000,0.15*(O95-600000),75000)) -> 75000 | S95: =IF((O95-1100000)<0,0,IF((O95-1100000)<500000,0.19*(O95-1100000),95000)) -> 95000 | T95: =IF((O95-1600000)<0,0,IF((O95-1600000)<1600000,0.21*(O95-1600000),336000)) -> 195626.59 | V95: =P95+Q95+R95+S95+T95+U95 -> 419626.59 | W95: 12 | X95: =V95/W95 -> 34968.882 | Z95: =X95 -> 34968.882 | AA95: 43492.373 | AB95: =Z95-AA95 -> -8523.491 | AC95: OKECHUKWU UCHENNA HULDA
B96: TASSNEEM IBRAHIM | C96: 237734.05 | D96: 12 | E96: =C96*D96 -> 2852808.6 | I96: =E96-F96-G96-H96 -> 2852808.6 | J96: 200000 | K96: 0.2 | L96: =I96*K96 -> 570561.71 | M96: =J96+L96 -> 770561.71 | N96: =F96+G96+H96+M96 -> 770561.71 | O96: =E96-N96 -> 2082246.9 | P96: =IF(O96<300000,0.07*O96,21000) -> 21000 | Q96: =IF((O96-300000)<0,0,IF((O96-300000)<300000,0.11*(O96-300000),33000)) -> 33000 | R96: =IF((O96-600000)<0,0,IF((O96-600000)<500000,0.15*(O96-600000),75000)) -> 75000 | S96: =IF((O96-1100000)<0,0,IF((O96-1100000)<500000,0.19*(O96-1100000),95000)) -> 95000 | T96: =IF((O96-1600000)<0,0,IF((O96-1600000)<1600000,0.21*(O96-1600000),336000)) -> 101271.84 | V96: =P96+Q96+R96+S96+T96+U96 -> 325271.84 | W96: 12 | X96: =V96/W96 -> 27105.987 | Z96: =X96 -> 27105.987 | AA96: 34968.882 | AB96: =Z96-AA96 -> -7862.8959 | AC96: TASSNEEM IBRAHIM
B97: TOTAL | AB97: =SUM(AB93:AB96) -> -55521.965
A98: 83
A99: 84 | B99: LIBRARY & DOCUMENTATION | AB99: Difference
A100: 85 | B100: DR MAIMUNA IZAH | C100: 1050209.1 | D100: 12 | E100: =C100*D100 -> 12602509 | I100: =E100-F100-G100-H100 -> 12602509 | J100: 200000 | K100: 0.2 | L100: =I100*K100 -> 2520501.8 | M100: =J100+L100 -> 2720501.8 | N100: =F100+G100+H100+M100 -> 2720501.8 | O100: =E100-N100 -> 9882007 | P100: =IF(O100<300000,0.07*O100,21000) -> 21000 | Q100: =IF((O100-300000)<0,0,IF((O100-300000)<300000,0.11*(O100-300000),33000)) -> 33000 | R100: =IF((O100-600000)<0,0,IF((O100-600000)<500000,0.15*(O100-600000),75000)) -> 75000 | S100: =IF((O100-1100000)<0,0,IF((O100-1100000)<500000,0.19*(O100-1100000),95000)) -> 95000 | T100: =IF((O100-1600000)<0,0,IF((O100-1600000)<1600000,0.21*(O100-1600000),336000)) -> 336000 | U100: =24%*(O100-3200000) -> 1603681.7 | V100: =P100+Q100+R100+S100+T100+U100 -> 2163681.7 | W100: 12 | X100: =V100/W100 -> 180306.81 | Z100: =X100 -> 180306.81 | AA100: 180306.81 | AB100: =Z100-AA100 -> 0 | AC100: DR MAIMUNA IZAH
A101: 86 | B101: CATHERINE E. IKOKOH | C101: 631465.02 | D101: 12 | E101: =C101*D101 -> 7577580.3 | F101: ='[4]JANUARY 2024'!$V$106*12 -> 12795.951 | I101: =E101-F101-G101-H101 -> 7564784.3 | J101: 200000 | K101: 0.2 | L101: =I101*K101 -> 1512956.9 | M101: =J101+L101 -> 1712956.9 | N101: =F101+G101+H101+M101 -> 1725752.8 | O101: =E101-N101 -> 5851827.5 | P101: =IF(O101<300000,0.07*O101,21000) -> 21000 | Q101: =IF((O101-300000)<0,0,IF((O101-300000)<300000,0.11*(O101-300000),33000)) -> 33000 | R101: =IF((O101-600000)<0,0,IF((O101-600000)<500000,0.15*(O101-600000),75000)) -> 75000 | S101: =IF((O101-1100000)<0,0,IF((O101-1100000)<500000,0.19*(O101-1100000),95000)) -> 95000 | T101: =IF((O101-1600000)<0,0,IF((O101-1600000)<1600000,0.21*(O101-1600000),336000)) -> 336000 | U101: =24%*(O101-3200000) -> 636438.59 | V101: =P101+Q101+R101+S101+T101+U101 -> 1196438.6 | W101: 12 | X101: =V101/W101 -> 99703.216 | Z101: =X101 -> 99703.216 | AA101: 99703.216 | AB101: =Z101-AA101 -> 0 | AC101: CATHERINE E. IKOKOH
A102: 87 | B102: ALIYU SANNI ABUBAKAR | C102: 418096.02 | D102: 12 | E102: =C102*D102 -> 5017152.2 | F102: ='[4]JANUARY 2024'!$V$107*12 -> 7901.79 | I102: =E102-F102-G102-H102 -> 5009250.4 | J102: 200000 | K102: 0.2 | L102: =I102*K102 -> 1001850.1 | M102: =J102+L102 -> 1201850.1 | N102: =F102+G102+H102+M102 -> 1209751.9 | O102: =E102-N102 -> 3807400.3 | P102: =IF(O102<300000,0.07*O102,21000) -> 21000 | Q102: =IF((O102-300000)<0,0,IF((O102-300000)<300000,0.11*(O102-300000),33000)) -> 33000 | R102: =IF((O102-600000)<0,0,IF((O102-600000)<500000,0.15*(O102-600000),75000)) -> 75000 | S102: =IF((O102-1100000)<0,0,IF((O102-1100000)<500000,0.19*(O102-1100000),95000)) -> 95000 | T102: =IF((O102-1600000)<0,0,IF((O102-1600000)<1600000,0.21*(O102-1600000),336000)) -> 336000 | U102: =24%*(O102-3200000) -> 145776.08 | V102: =P102+Q102+R102+S102+T102+U102 -> 705776.08 | W102: 12 | X102: =V102/W102 -> 58814.673 | Z102: =X102 -> 58814.673 | AA102: 180180.38 | AB102: =Z102-AA102 -> -121365.71 | AC102: ALIYU SANNI ABUBAKAR
A103: 88 | B103: CHINAKO N. ASOGWA | C103: 416483.19 | D103: 12 | E103: =C103*D103 -> 4997798.3 | I103: =E103-F103-G103-H103 -> 4997798.3 | J103: 200000 | K103: 0.2 | L103: =I103*K103 -> 999559.67 | M103: =J103+L103 -> 1199559.7 | N103: =F103+G103+H103+M103 -> 1199559.7 | O103: =E103-N103 -> 3798238.7 | P103: =IF(O103<300000,0.07*O103,21000) -> 21000 | Q103: =IF((O103-300000)<0,0,IF((O103-300000)<300000,0.11*(O103-300000),33000)) -> 33000 | R103: =IF((O103-600000)<0,0,IF((O103-600000)<500000,0.15*(O103-600000),75000)) -> 75000 | S103: =IF((O103-1100000)<0,0,IF((O103-1100000)<500000,0.19*(O103-1100000),95000)) -> 95000 | T103: =IF((O103-1600000)<0,0,IF((O103-1600000)<1600000,0.21*(O103-1600000),336000)) -> 336000 | U103: =0.24*(O103-3200000) -> 143577.28 | V103: =P103+Q103+R103+S103+T103+U103 -> 703577.28 | W103: 12 | X103: =V103/W103 -> 58631.44 | Z103: =X103 -> 58631.44 | AA103: 99907.951 | AB103: =Z103-AA103 -> -41276.511 | AC103: CHINAKO N. ASOGWA
A104: 89 | B104: AMOS ABA | C104: 266099.22 | D104: 12 | E104: =C104*D104 -> 3193190.6 | I104: =E104-F104-G104-H104 -> 3193190.6 | J104: 200000 | K104: 0.2 | L104: =I104*K104 -> 638638.12 | M104: =J104+L104 -> 838638.12 | N104: =F104+G104+H104+M104 -> 838638.12 | O104: =E104-N104 -> 2354552.5 | P104: =IF(O104<300000,0.07*O104,21000) -> 21000 | Q104: =IF((O104-300000)<0,0,IF((O104-300000)<300000,0.11*(O104-300000),33000)) -> 33000 | R104: =IF((O104-600000)<0,0,IF((O104-600000)<500000,0.15*(O104-600000),75000)) -> 75000 | S104: =IF((O104-1100000)<0,0,IF((O104-1100000)<500000,0.19*(O104-1100000),95000)) -> 95000 | T104: =IF((O104-1600000)<0,0,IF((O104-1600000)<1600000,0.21*(O104-1600000),336000)) -> 158456.02 | V104: =P104+Q104+R104+S104+T104+U104 -> 382456.02 | W104: 12 | X104: =V104/W104 -> 31871.335 | Z104: =X104 -> 31871.335 | AA104: 58941.102 | AB104: =Z104-AA104 -> -27069.767 | AC104: AMOS ABA
...

Sheet  Excess Ded Paid
A2: S/N | B2: NAME | C2: INACCURATE TAX CHARGED | D2: ACCURATE TAX FIGURE | E2: EXCESS DEDUCTION
C3: N | D3: N | E3: N
A4: 1 | B4: DR AUGUSTINE C. OSIGWE | C4: 98996.103 | D4: 79796.103 | E4: =C4-D4 -> 19200
A5: 2 | B5: OMOJU OLUWASOLA EMMANUEL | C5: 79956.939 | D5: 75574.677 | E5: =C5-D5 -> 4382.2619
A6: 3 | B6: IBE EZECHI CYRIACUS | C6: 75574.677 | D6: 50985.978 | E6: =C6-D6 -> 24588.7
A7: 4 | B7: OSIKHEN LEO IGBANOI | C7: 50985.978 | D7: 49548.776 | E7: =C7-D7 -> 1437.2014
A8: 5 | B8: YUSUF IBRAHIM | C8: 53384.054 | D8: 41338.951 | E8: =C8-D8 -> 12045.102
A9: 6 | B9: MARYAM MUSA SADA | C9: 45414.456 | D9: 33825.987 | E9: =C9-D9 -> 11588.47
A10: 7 | B10: CHARITY EZENWAJIOBI | C10: 33825.987 | D10: 29984.871 | E10: =C10-D10 -> 3841.1156
A11: 8 | B11: MOHAMMED R. ADAMU | C11: 82627.951 | D11: 43492.373 | E11: =C11-D11 -> 39135.578
A12: 9 | B12: OKECHUKWU UCHENNA HULDA | C12: 43492.373 | D12: 34968.882 | E12: =C12-D12 -> 8523.491
A13: 10 | B13: TASSNEEM IBRAHIM | C13: 34968.882 | D13: 27105.987 | E13: =C13-D13 -> 7862.8959
A14: 11 | B14: ALIYU SANNI ABUBAKAR | C14: 180180.38 | D14: 58814.673 | E14: =C14-D14 -> 121365.71
A15: 12 | B15: CHINAKO N. ASOGWA | C15: 99907.951 | D15: 58631.44 | E15: =C15-D15 -> 41276.511
... A18: 15 | B18: ENENCHE JEREMIAH AGADA | C18: 31871.335 | D18: 29984.871 | E18: =C18-D18 -> 1886.4643
B19: TOTAL | C19: =SUM(C4:C18) -> 1028759.6 | D19: =SUM(D4:D18) -> 677146.05 | E19: =SUM(E4:E18) -> 351613.56

Sheet Changes in Gross & PAYE 
A1: NATIONAL INSTITUTE FOR LEGISLATIVE AND DEMOCRATIC STUDIES
A2: CHANGES IN GROSS SALARY AND PAYE TAX
E3: ='[1]FEB 08'!E11/'[1]FEB 08'!M11 -> #REF!
B4: STAFF NAME | C4: DESIGNATION | D4: GRADE LEVEL | E4: SALARY | F4: AREARS | G4: RESEARCH ALLOW. | H4: HARDSHIP ALLOW. | I4: DUTY ALLCE | J4: NEW GROSS SALARY | K4: OLD GROSS SALARY | L4: VARIATION IN GROSS SALARY | M4: NEW PAYE TAX | N4: OLD PAYE TAX | O4: VARIATION IN PAYE TAX
E5: N | F5: N | G5: N | H5: N | I5: N | M5: N
A6: S/N | B6: DG'S OFFICE
A7: 1 | B7: PROF. ABUBAKAR O. SULAIMAN | C7: DIRECTOR GENERAL | D7: CONSOL | E7: 1659751.2 | G7: =250000 -> 250000 | I7: 25235 | J7: =E7+F7+G7+H7+I7 -> 1934986.2 | K7: 1158849.8 | L7: =J7-K7 -> 776136.33 | M7: 350184.01 | N7: 201165.84 | O7: =M7-N7 -> 149018.17
A8: 2 | B8: RAHEEM USMAN AYIGORO | C8: SA-INFRASTRUCTURE | D8: 16 (9) | E8: 762373.17 | H8: =90000 -> 90000 | I8: 0 | J8: =E8+F8+G8+H8+I8 -> 852373.17 | K8: 541465.02 | L8: =J8-K8 -> 310908.14 | M8: 130612.26 | N8: 82627.951 | O8: =M8-N8 -> 47984.311
A9: 3 | B9: MARIAM MOHAMMED BELLO | C9: SA- SPECIAL DUTIES | D9: 16 (9) | E9: 762373.17 | H9: =90000 -> 90000 | I9: =100000+100000 -> 200000 | J9: =E9+F9+G9+H9+I9 -> 1052373.2 | K9: 741465.02 | L9: =J9-K9 -> 310908.14 | M9: 180722.31 | N9: 121027.95 | O9: =M9-N9 -> 59694.363
A10: 4 | B10: DR IKEME ARTHUR J.O | C10: DEPUTY DIRECTOR, M&E | D10: 16 (9) | E10: 762373.17 | G10: 180000 | I10: 0 | J10: =E10+F10+G10+H10+I10 -> 942373.17 | K10: 631465.02 | L10: =J10-K10 -> 310908.14 | M10: 147687.53 | N10: 99703.216 | O10: =M10-N10 -> 47984.311
A11: 5 | B11: MOSHOOD M. OLALERE | C11: PPS TO DG | D11: 16 (9) | E11: 762373.17 | H11: =80000+10000 -> 90000 | I11: 150000 | J11: =E11+F11+G11+H11+I11 -> 1002373.2 | K11: 691465.02 | L11: =J11-K11 -> 310908.14 | M11: 159207.53 | N11: 111223.22 | O11: =M11-N11 -> 47984.311
A12: 6 | B12: REKIYA IBRAHIM ATTAH | C12: DEPUTY DIRECTOR TRAINING | D12: 16 (9) | E12: 762373.17 | H12: =90000 -> 90000 | I12: 100000 | J12: =E12+F12+G12+H12+I12 -> 952373.17 | K12: 641465.02 | L12: =J12-K12 -> 310908.14 | M12: 161522.31 | N12: 101827.95 | O12: =M12-N12 -> 59694.363
A13: 7 | B13: ANDRAWUS MUSA | C13: ASST. DIRECTOR, STORES | D13: 15(9) | E13: 620675.58 | H13: =80000 -> 80000 | I13: 50000 | J13: =E13+F13+G13+H13+I13 -> 750675.58 | K13: 497553.5 | L13: =J13-K13 -> 253122.08 | M13: 113101.97 | N13: 74036.103 | O13: =M13-N13 -> 39065.863
A14: 8 | B14: DR FRANCIS NDUM OJIE | C14: AD, TRAINING & IC./SA TO DG | D14: 15(7) | E14: 582118.08 | G14: 160000 | I14: =100000 -> 100000 | J14: =E14+F14+G14+H14+I14 -> 842118.08 | K14: 604729.22 | L14: =J14-K14 -> 237388.86 | M14: 131263.11 | N14: 94625.782 | O14: =M14-N14 -> 36637.328
A15: 9 | B15: ALI ABDULLAHI | C15: CHIEF ICT OFFICER | D15: 14(11) | E15: 484373.75 | H15: =70000 -> 70000 | I15: =0 -> 0 | J15: =E15+F15+G15+H15+I15 -> 554373.75 | K15: 343333.04 | L15: =J15-K15 -> 211040.71 | M15: 77666.446 | N15: 44846.617 | O15: =M15-N15 -> 32819.829
A16: 10 | B16: EMILY EKHIDE | C16: RESEARCH FELLOW 1 | D16: 14(10) | E16: 470498 | G16: 140000 | I16: 50000 | J16: =E16+F16+G16+H16+I16 -> 660498 | K16: 463333.04 | L16: =J16-K16 -> 197164.96 | M16: 98255.433 | N16: 67626.609 | O16: =M16-N16 -> 30628.824
A17: 11 | B17: DORIS DAKDA AARON | C17: RESEARCH FELLOW I | D17: 14(8) | E17: 442746.5 | G17: =140000 -> 140000 | I17: 150000 | J17: =E17+F17+G17+H17+I17 -> 732746.5 | K17: 547211.37 | L17: =J17-K17 -> 185535.13 | M17: 112553.41 | N17: 83731.249 | O17: =M17-N17 -> 28822.159
A18: 12 | B18: ABDULSALAM S. MUSTAPHA | C18: ASST. MANAGER ICT | D18: 13(11) | E18: 441804.92 | H18: 70000 | J18: =E18+F18+G18+H18+I18 -> 511804.92 | K18: 326663.08 | L18: =J18-K18 -> 185141.84 | M18: 70147.087 | N18: 42046.064 | O18: =M18-N18 -> 28101.023
A19: 13 | B19: PERCY TERFA GBAHABO | C19: HEAD, NILDS LIAISON OFFICE | D19: 13(10) | E19: 428915.92 | G19: =120000 -> 120000 | I19: 0 | J19: =E19+F19+G19+H19+I19 -> 548915.92 | K19: 369177.65 | L19: =J19-K19 -> 179738.26 | M19: 77470.374 | N19: 49548.776 | O19: =M19-N19 -> 27921.598
A20: 14 | B20: HASSANA AHMED IBRAHIM | C20: PA- TRAINING | D20: 13 (9) | E20: 416026.92 | G20: =120000 -> 120000 | I20: =100000 -> 100000 | J20: =E20+F20+G20+H20+I20 -> 636026.92 | K20: 462001.06 | L20: =J20-K20 -> 174025.86 | M20: 94274.903 | N20: 67370.87 | O20: =M20-N20 -> 26904.033
A21: 15 | B21: ADUGBA RICHARD TERSEER | C21: PRINCIPAL INFO. OFFICER | D21: 12(9) | E21: 377895.17 | H21: =60000 -> 60000 | I21: 100000 | J21: =E21+F21+G21+H21+I21 -> 537895.17 | K21: 384537 | L21: =J21-K21 -> 153358.17 | M21: 76138.069 | N21: 52497.77 | O21: =M21-N21 -> 23640.299
A22: 16 | B22: LUCKY AGWOM | C22: PA-TECHNICAL | D22: 12(7) | E22: 353512.5 | G22: =100000 -> 100000 | I22: 100000 | J22: =E22+F22+G22+H22+I22 -> 553512.5 | K22: 400372.08 | L22: =J22-K22 -> 153140.42 | M22: 79511.115 | N22: 55538.105 | O22: =M22-N22 -> 23973.01
A23: 17 | B23: IDRIS IBRAHIM | C23: PRINCIPAL RESEARCH OFFICER | D23: 12(7) | E23: 353512.5 | G23: 110000 | I23: 0 | J23: =E23+F23+G23+H23+I23 -> 463512.5 | K23: 1015372.1 | L23: =J23-K23 -> -551859.58 | M23: 62231.115 | N23: 40149.175 | O23: =M23-N23 -> 22081.939
A24: 18 | B24: FARUQ ATOFARATI | C24: PA (SPECIAL DUTIES) TO DG | D24: 10(7) | E24: 293029.67 | H24: =50000+10000 -> 60000 | I24: 100000 | J24: =E24+F24+G24+H24+I24 -> 453029.67 | K24: 328602.08 | L24: =J24-K24 -> 124427.59 | M24: 61147.427 | N24: 42371.816 | O24: =M24-N24 -> 18775.611
A25: 19 | B25: ELIZABETH OGECHUKWU ONYEAKU | C25: ICT OFFICER | D25: 9(9) | E25: 270481.67 | H25: =50000+10000 -> 60000 | J25: =E25+F25+G25+H25+I25 -> 330481.67 | K25: 213508.01 | L25: =J25-K25 -> 116973.66 | M25: 39052.313 | N25: 23036.012 | O25: =M25-N25 -> 16016.301
A26: 20 | B26: VICTOR ASUKWO | C26: ICT OFFICER | D26: 9(9) | E26: 270481.67 | H26: =50000+10000 -> 60000 | J26: =E26+F26+G26+H26+I26 -> 330481.67 | K26: 213508.01 | L26: =J26-K26 -> 116973.66 | M26: 39052.313 | N26: 23036.012 | O26: =M26-N26 -> 16016.301
A27: 21 | B27: NNANDI LIVINUS ATURE | C27: RESEARCH ASSISTANT | D27: 9(9) | E27: 270481.67 | G27: =100000 -> 100000 | J27: =E27+F27+G27+H27+I27 -> 370481.67 | K27: 253508.01 | L27: =J27-K27 -> 116973.66 | M27: 45772.313 | N27: 29756.012 | O27: =M27-N27 -> 16016.301
A28: 22 | B28: ABDULRAHMAN A SULAIMAN | C28: STORE OFFICER | D28: 9(8) | E28: 263165.33 | H28: =60000 -> 60000 | J28: =E28+F28+G28+H28+I28 -> 323165.33 | K28: 209356.05 | L28: =J28-K28 -> 113809.29 | M28: 37921.501 | N28: 22338.483 | O28: =M28-N28 -> 15583.018
A29: 23 | B29: DARE SHEU MAGBON | C29: ADMINISTRATION OFFICER | D29: 9(7) | E29: 255849 | H29: =60000 -> 60000 | J29: =E29+F29+G29+H29+I29 -> 315849 | K29: 205204.08 | L29: =J29-K29 -> 110644.92 | M29: 36790.688 | N29: 21640.953 | O29: =M29-N29 -> 15149.735
A30: 24 | B30: ABUBAKAR SULAIMAN SODEEQ | C30: ADMINISTRATION OFFICER | D30: 9(7) | E30: 255849 | H30: =60000 -> 60000 | J30: =E30+F30+G30+H30+I30 -> 315849 | K30: 205204.08 | L30: =J30-K30 -> 110644.92 | M30: 36790.688 | N30: 21640.953 | O30: =M30-N30 -> 15149.735
A31: 25 | B31: JIMOH ADEBAYO ZAKA | C31: ASST. OFFICER/COMM | D31: 9(9) | E31: 270481.67 | H31: =60000 -> 60000 | J31: =E31+F31+G31+H31+I31 -> 330481.67 | K31: 209356.05 | L31: =J31-K31 -> 121125.62 | M31: 39052.313 | N31: 22338.483 | O31: =M31-N31 -> 16713.83
A32: 26 | B32: MOHAMMED BELLO | C32: PROTOCOL ASSISTANT | D32: 8(9) | E32: 230631.92 | H32: =50000 -> 50000 | J32: =E32+F32+G32+H32+I32 -> 280631.92 | K32: 180304.07 | L32: =J32-K32 -> 100327.85 | M32: 31213.136 | N32: 17572.885 | O32: =M32-N32 -> 13640.251
A33: 27 | B33: HARUNA JIBRIL AMEH | C33: ASST. ADMIN. OFFICER | D33: 8(8) | E33: 224459.75 | H33: 50000 | J33: =E33+F33+G33+H33+I33 -> 274459.75 | K33: 173329.05 | L33: =J33-K33 -> 101130.7 | M33: 30259.166 | N33: 16512.682 | O33: =M33-N33 -> 13746.483
B34: TOTAL | C34: 27 | E34: =SUM(E7:E33) -> 13048608 | F34: =SUM(F7:F33) -> 0 | G34: =SUM(G7:G33) -> 1420000 | H34: =SUM(H7:H33) -> 1160000 | I34: =SUM(I7:I33) -> 1225235 | J34: =SUM(J7:J33) -> 16853843 | K34: 12012338 | L34: =SUM(L7:L33) -> 4841505.6 | M34: =SUM(M7:M33) -> 2519600.8 | N34: 1629837.5 | O34: =SUM(O7:O33) -> 889763.31
B36: INTERNAL AUDIT
A37: 1 | B37: OSANAIYE DAVID AKINYEMI | C37: DIRECTOR INTERNAL AUDIT | D37: 17(9) | E37: 1435720 | H37: =100000 -> 100000 | J37: =E37+F37+G37+H37+I37 -> 1535720 | K37: 950209.06 | L37: =J37-K37 -> 585510.94 | M37: 251472.25 | N37: 161106.81 | O37: =M37-N37 -> 90365.441
A38: 2 | B38: JAMILA ABDUL | C38: SENIOR INTERNAL AUDITOR | D38: 10(7) | E38: 293029.67 | H38: =60000 -> 60000 | J38: =E38+F38+G38+H38+I38 -> 353029.67 | K38: 176816.1 | L38: =J38-K38 -> 176213.57 | M38: 42537.332 | N38: 17042.714 | O38: =M38-N38 -> 25494.618
A39: 3 | B39: IJEOMA EWELUKWA | C39: AUDIT OFFICER | D39: 10(8) | E39: 300965.58 | H39: =50000+10000 -> 60000 | J39: =E39+F39+G39+H39+I39 -> 360965.58 | K39: 233169.12 | L39: =J39-K39 -> 127796.47 | M39: 43763.907 | N39: 26339.078 | O39: =M39-N39 -> 17424.829
C40: 3 | E40: =SUM(E37:E39) -> 2029715.2 | F40: =SUM(F37:F39) -> 0 | G40: =SUM(G37:G39) -> 0 | H40: =SUM(H37:H39) -> 220000 | I40: =SUM(I37:I39) -> 0 | J40: =SUM(J37:J39) -> 2249715.2 | K40: 1360194.3 | L40: =SUM(L37:L39) -> 889520.97 | M40: =SUM(M37:M39) -> 337773.49 | N40: 204488.6 | O40: =SUM(O37:O39) -> 133284.89
B42: LEG. SUPPORT SEVICES
A43: 1 | B43: PROF. EDOBA BRIGHT OMOREGBE | C43: AG. DLSS | D43: 17(9) | E43: 1435720 | G43: =200000 -> 200000 | J43: =E43+F43+G43+H43+I43 -> 1635720 | K43: 1050209.1 | L43: =J43-K43 -> 585510.94 | M43: 270672.25 | N43: 180306.81 | O43: =M43-N43 -> 90365.441
A44: 2 | B44: DR CLINTON JAJA | C44: SENIOR RESEARCH FELLOW | D44: 15(9) | E44: 620675.58 | G44: =160000 -> 160000 | I44: 0 | J44: =E44+F44+G44+H44+I44 -> 780675.58 | K44: 527553.5 | L44: =J44-K44 -> 253122.08 | M44: 119022.8 | N44: 79956.939 | O44: =M44-N44 -> 39065.863
A45: 3 | B45: BETHEL UZOMA IHUGBA | C45: DEPUTY DIRECTOR, LEGAL RESEARCH | D45: 16(8) | E45: 739203.58 | G45: =180000 -> 180000 | J45: =E45+F45+G45+H45+I45 -> 919203.58 | K45: 617744 | L45: =J45-K45 -> 301459.59 | M45: 143799.59 | N45: 97273.514 | O45: =M45-N45 -> 46526.074
A46: 4 | B46: OGUCHE SAMUEL | C46: SNR RESEARCH FELLOW | D46: 15(9) | E46: 620675.58 | G46: =160000 -> 160000 | J46: =E46+F46+G46+H46+I46 -> 780675.58 | K46: 527553.5 | L46: =J46-K46 -> 253122.08 | M46: 119022.8 | N46: 79956.939 | O46: =M46-N46 -> 39065.863
A47: 5 | B47: IBRAHIM USMAN | C47: SNR RESEARCH FELLOW | D47: 15(9) | E47: 620675.58 | G47: =140000+20000 -> 160000 | I47: 0 | J47: =E47+F47+G47+H47+I47 -> 780675.58 | K47: 527553.5 | L47: =J47-K47 -> 253122.08 | M47: 118861.97 | N47: 79796.103 | O47: =M47-N47 -> 39065.863
A48: 6 | B48: DR MOHAMMED O. AMALI | C48: SNR RESEARCH FELLOW | D48: 15(7) | E48: 582118.08 | G48: =140000+20000 -> 160000 | J48: =E48+F48+G48+H48+I48 -> 742118.08 | K48: 504720.05 | L48: =J48-K48 -> 237398.04 | M48: 112212 | N48: 75572.916 | O48: =M48-N48 -> 36639.089
A49: 7 | B49: YAHAYA SHAMSU | C49: RESEARCH FELLOW 1 | D49: 14(10) | E49: 470498 | G49: =140000 -> 140000 | J49: =E49+F49+G49+H49+I49 -> 610498 | K49: 413333.04 | L49: =J49-K49 -> 197164.96 | M49: 88655.433 | N49: 58026.609 | O49: =M49-N49 -> 30628.824
A50: 8 | B50: BILKIS S. LAWAL-GAMBARI | C50: RESEARCH OFFICER | D50: 10(8) | E50: 300965.58 | G50: 100000 | J50: =E50+F50+G50+H50+I50 -> 400965.58 | K50: 273169.12 | L50: =J50-K50 -> 127796.47 | M50: 51029.227 | N50: 33059.078 | O50: =M50-N50 -> 17970.149
A51: 9 | B51: ZAINAB AKINDE | C51: RESEARCH OFFICER | D51: 9(8) | E51: 263165.33 | G51: =100000 -> 100000 | J51: =E51+F51+G51+H51+I51 -> 363165.33 | K51: 249356.05 | L51: =J51-K51 -> 113809.29 | M51: 44641.501 | N51: 29058.483 | O51: =M51-N51 -> 15583.018
A52: 10 | B52: ABDULLAHI AHMAD USMAN | C52: RESEARCH OFFICER | D52: 9(8) | E52: 263165.33 | G52: =100000 -> 100000 | J52: =E52+F52+G52+H52+I52 -> 363165.33 | K52: 249356.05 | L52: =J52-K52 -> 113809.29 | M52: 44641.501 | N52: 28360.953 | O52: =M52-N52 -> 16280.548
A53: 11 | B53: GUNAT NANSAK MARK | C53: RESEARCH OFFICER | D53: 9(8) | E53: 263165.33 | G53: =100000 -> 100000 | J53: =E53+F53+G53+H53+I53 -> 363165.33 | K53: 249356.05 | L53: =J53-K53 -> 113809.29 | M53: 44641.501 | N53: 29058.483 | O53: =M53-N53 -> 15583.018
B54: TOTAL | C54: 11 | E54: =SUM(E43:E53) -> 6180028 | F54: =SUM(F43:F53) -> 0 | G54: =SUM(G43:G53) -> 1560000 | H54: =SUM(H43:H53) -> 0 | I54: =SUM(I43:I53) -> 0 | J54: =SUM(J43:J53) -> 7740028 | K54: 5189903.9 | L54: =SUM(L43:L53) -> 2550124.1 | M54: =SUM(M43:M53) -> 1157200.6 | N54: 770426.82 | O54: =SUM(O43:O53) -> 386773.75
B56: LEGAL SERVICES
A57: 1 | B57: DR SHUIBU DANWANKA | C57: DIRECTOR LEGAL SERVICES | D57: 17(9) | E57: 1435720 | G57: =200000 -> 200000 | I57: 0 | J57: =E57+F57+G57+H57+I57 -> 1635720 | K57: 1050209.1 | L57: =J57-K57 -> 585510.94 | M57: 270672.25 | N57: 180306.81 | O57: =M57-N57 -> 90365.441
A58: 2 | B58: ABDULSALAM BAKO | C58: MANAGER, LEGAL SERVICES | D58: 15 (9) | E58: 620675.58 | H58: 80000 | J58: =E58+F58+G58+H58+I58 -> 700675.58 | K58: 447553.5 | L58: =J58-K58 -> 253122.08 | M58: 103662.8 | N58: 64596.939 | O58: =M58-N58 -> 39065.863
B59: TOTAL | C59: 2 | E59: =SUM(E57:E58) -> 2056395.6 | F59: =SUM(F57:F58) -> 0 | G59: =SUM(G57:G58) -> 200000 | H59: =SUM(H57:H58) -> 80000 | I59: =SUM(I57:I58) -> 0 | J59: =SUM(J57:J58) -> 2336395.6 | K59: 1497762.6 | L59: =SUM(L57:L58) -> 838633.02 | M59: =SUM(M57:M58) -> 374335.05 | N59: 244903.75 | O59: =SUM(O57:O58) -> 129431.3
B61: DEMOCRACY & GOVERNANCE
A62: 1 | B62: DR. ADEWALE ADEREMI | C62: DIRECTOR, DEMOCRATIC STUDIES | D62: 17(9) | E62: 1435720 | G62: =200000 -> 200000 | I62: 0 | J62: =E62+F62+G62+H62+I62 -> 1635720 | K62: 1050209.1 | L62: =J62-K62 -> 585510.94 | M62: 292724.91 | N62: 180306.81 | O62: =M62-N62 -> 112418.1
A63: 2 | B63: NDANUSA MOHAMMED MANZUMA | C63: SNR RESEARCH FELLOW | D63: 15(8) | E63: 601396.83 | G63: =160000 -> 160000 | I63: 0 | J63: =E63+F63+G63+H63+I63 -> 761396.83 | K63: 516137.05 | L63: =J63-K63 -> 245259.78 | M63: 115617.4 | N63: 77764.98 | O63: =M63-N63 -> 37852.423
A64: 3 | B64: EJALONIBU GANIYU LAYI | C64: RESEARCH FELLOW 1 | D64: 14(8) | E64: 442746.5 | G64: 140000 | J64: =E64+F64+G64+H64+I64 -> 582746.5 | K64: 397211.37 | L64: =J64-K64 -> 185535.13 | M64: 83753.408 | N64: 54931.249 | O64: =M64-N64 -> 28822.159
A65: 4 | B65: LOHNA BONKAT JONATHAN | C65: RESEARCH FELLOW 11 | D65: 13(10) | E65: 428915.92 | G65: =120000 -> 120000 | I65: 0 | J65: =E65+F65+G65+H65+I65 -> 548915.92 | K65: 369177.65 | L65: =J65-K65 -> 179738.26 | M65: 77470.374 | N65: 49548.776 | O65: =M65-N65 -> 27921.598
A66: 5 | B66: YUNUSA ABDULLAHI | C66: RESEARCH FELLOW 1 | D66: 14(11) | E66: 484373.75 | G66: =140000 -> 140000 | J66: =E66+F66+G66+H66+I66 -> 624373.75 | K66: 421394.01 | L66: =J66-K66 -> 202979.74 | M66: 91106.446 | N66: 59574.316 | O66: =M66-N66 -> 31532.13
A67: 7 | B67: UDEFUNA NNADOZIE PATRICK | C67: RESEARCH OFFICER | D67: 12(8) | E67: 365703.83 | G67: =110000 -> 110000 | I67: 0 | J67: =E67+F67+G67+H67+I67 -> 475703.83 | K67: 322454.07 | L67: =J67-K67 -> 153249.76 | M67: 64384.592 | N67: 41338.951 | O67: =M67-N67 -> 23045.641
A68: 8 | B68: SHAFIU YAHYA MIKAIL | C68: PRINCIPAL RESEARCH OFFICER | D68: 12(8) | E68: 365703.83 | G68: =110000 -> 110000 | I68: 0 | J68: =E68+F68+G68+H68+I68 -> 475703.83 | K68: 322454.07 | L68: =J68-K68 -> 153249.76 | M68: 64384.592 | N68: 41338.951 | O68: =M68-N68 -> 23045.641
A69: 9 | B69: HASSAN YERIMA | C69: PRINCIPAL RESEARCH OFFICER | D69: 12(8) | E69: 365703.83 | G69: =110000 -> 110000 | I69: 0 | J69: =E69+F69+G69+H69+I69 -> 475703.83 | K69: 322454.07 | L69: =J69-K69 -> 153249.76 | M69: 64384.592 | N69: 41338.951 | O69: =M69-N69 -> 23045.641
A70: 10 | B70: HAUWA PATE SADIQ | C70: PRINCIPAL PROGRAMME OFFICER | D70: 12(9) | E70: 377895.17 | G70: =110000 -> 110000 | J70: =E70+F70+G70+H70+I70 -> 487895.17 | K70: 334537 | L70: =J70-K70 -> 153358.17 | M70: 66538.069 | N70: 43368.882 | O70: =M70-N70 -> 23169.186
A71: 11 | B71: KOLAPO Q. ABAYOMI | C71: RESEARCH OFFICER | D71: 10(8) | E71: 300965.58 | G71: 100000 | J71: =E71+F71+G71+H71+I71 -> 400965.58 | K71: 277734.05 | L71: =J71-K71 -> 123231.54 | M71: 51029.227 | N71: 33825.987 | O71: =M71-N71 -> 17203.241
B72: TOTAL | C72: 12 | E72: =SUM(E62:E71) -> 5169125.2 | F72: =SUM(F62:F71) -> 0 | G72: =SUM(G62:G71) -> 1300000 | H72: =SUM(H62:H71) -> 0 | I72: =SUM(I62:I71) -> 0 | J72: =SUM(J62:J71) -> 6469125.2 | K72: 4333762.4 | L72: =SUM(L62:L71) -> 2135362.8 | M72: =SUM(M62:M71) -> 971393.61 | N72: 623337.85 | O72: =SUM(O62:O71) -> 348055.76
B74: DEPARTMENT OF STUDIES
A75: 1 | B75: DR ASIMIYU G. ABIOLA | C75: DIRECTOR POST GRADUATE | D75: 17(9) | E75: 1435720 | G75: =200000 -> 200000 | I75: 0 | J75: =E75+F75+G75+H75+I75 -> 1635720 | K75: 1050209.1 | L75: =J75-K75 -> 585510.94 | M75: 270672.25 | N75: 180306.81 | O75: =M75-N75 -> 90365.441
A76: 2 | B76: USMAN WALI | C76: SENIOR RESEARCH FELLOW | D76: 15 (8) | E76: 601396.83 | G76: =160000 -> 160000 | I76: 0 | J76: =E76+F76+G76+H76+I76 -> 761396.83 | K76: 516137.05 | L76: =J76-K76 -> 245259.78 | M76: 124854.86 | N76: 77764.98 | O76: =M76-N76 -> 47089.878
A77: 3 | B77: AYOBOLU OLAJIDE OLUFUNSHO | C77: ASST.DIR., INFORMATION | D77: 15 (9) | E77: 620675.58 | G77: 0 | H77: 80000 | I77: 0 | J77: =E77+F77+G77+H77+I77 -> 700675.58 | K77: 447553.5 | L77: =J77-K77 -> 253122.08 | M77: 113196.38 | N77: 64596.939 | O77: =M77-N77 -> 48599.44
A78: 4 | B78: ANTHONY EDET | C78: CHIEF PROGRAMMES OFFICER | D78: 14(9) | E78: 456622.25 | G78: =140000 -> 140000 | I78: 0 | J78: =E78+F78+G78+H78+I78 -> 596622.25 | K78: 405272.06 | L78: =J78-K78 -> 191350.19 | M78: 86076.104 | N78: 56350.586 | O78: =M78-N78 -> 29725.518
A79: 5 | B79: IGWE STACY | C79: PROGRAMME OFFICER | D79: 10(9) | E79: 308901.5 | G79: =100000 -> 100000 | J79: =E79+F79+G79+H79+I79 -> 408901.5 | K79: 273169.12 | L79: =J79-K79 -> 135732.38 | M79: 52431.028 | N79: 33059.078 | O79: =M79-N79 -> 19371.949
A80: 6 | B80: OLANIYAN TAIWO ABINBOLA | C80: PROGRAMME OFFICER | D80: 9(8) | E80: 263165.33 | G80: 100000 | J80: =E80+F80+G80+H80+I80 -> 363165.33 | K80: 249356.05 | L80: =J80-K80 -> 113809.29 | M80: 44641.501 | N80: 29058.483 | O80: =M80-N80 -> 15583.018
A81: 7 | B81: AMINAT JUMOKE SULAIMON | C81: AST. PROGRAMME OFFICER | D81: 8(8) | E81: 224459.75 | G81: 100000 | H81: 0 | J81: =E81+F81+G81+H81+I81 -> 324459.75 | K81: 223717.28 | L81: =J81-K81 -> 100742.47 | M81: 38659.166 | N81: 24751.17 | O81: =M81-N81 -> 13907.995
B82: TOTAL | C82: 7 | E82: =SUM(E75:E81) -> 3910941.3 | F82: =SUM(F75:F81) -> 0 | G82: =SUM(G75:G81) -> 800000 | H82: =SUM(H75:H81) -> 80000 | I82: =SUM(I75:I81) -> 0 | J82: =SUM(J75:J81) -> 4790941.2 | K82: 3165414.1 | L82: =SUM(L75:L81) -> 1625527.1 | M82: =SUM(M75:M81) -> 730531.28 | N82: 465888.04 | O82: =SUM(O75:O81) -> 264643.24
B84: ECON. DEV. & SOC. RESEARCH
A85: 1 | B85: TERFA WILLIAMS ABRAHAM | C85: SNR RESEARCH FELLOW | D85: 15(9) | E85: 620675.58 | G85: =160000 -> 160000 | I85: 100000 | J85: =E85+F85+G85+H85+I85 -> 880675.58 | K85: 627553.5 | L85: =J85-K85 -> 253122.08 | M85: 138222.8 | N85: 99156.939 | O85: =M85-N85 -> 39065.863
A86: 2 | B86: DR AUGUSTINE C. OSIGWE | C86: SNR RESEARCH FELLOW | D86: 15(9) | E86: 620675.58 | G86: =160000 -> 160000 | J86: =E86+F86+G86+H86+I86 -> 780675.58 | K86: 527553.5 | L86: =J86-K86 -> 253122.08 | M86: 118861.97 | N86: 79796.103 | O86: =M86-N86 -> 39065.863
A87: 3 | B87: OMOJU OLUWASOLA EMMANUEL | C87: SNR RESEARCH FELLOW | D87: 15(7) | E87: 582118.08 | G87: 160000 | J87: =E87+F87+G87+H87+I87 -> 742118.08 | K87: 504729.22 | L87: =J87-K87 -> 237388.86 | M87: 112212 | N87: 75574.677 | O87: =M87-N87 -> 36637.328
A88: 4 | B88: IBE EZECHI CYRIACUS | C88: RESEARCH FELLOW II | D88: 13(11) | E88: 441804.92 | G88: =120000 -> 120000 | I88: 0 | J88: =E88+F88+G88+H88+I88 -> 561804.92 | K88: 376663.08 | L88: =J88-K88 -> 185141.84 | M88: 79747.087 | N88: 50985.978 | O88: =M88-N88 -> 28761.11
A89: 5 | B89: OSIKHEN LEO IGBANOI | C89: RESEARCH FELLOW 11 | D89: 13(10) | E89: 428915.92 | G89: =120000 -> 120000 | I89: 0 | J89: =E89+F89+G89+H89+I89 -> 548915.92 | K89: 369177.65 | L89: =J89-K89 -> 179738.26 | M89: 77470.374 | N89: 49548.776 | O89: =M89-N89 -> 27921.598
A90: 6 | B90: OKUNGBOWA OSARETIN GODSPOWER | C90: RESEARCH FELLOW 1 | D90: 14(7) | E90: 428870.75 | G90: =140000 -> 140000 | I90: 0 | J90: =E90+F90+G90+H90+I90 -> 568870.75 | K90: 389153.06 | L90: =J90-K90 -> 179717.69 | M90: 81302.396 | N90: 53384.054 | O90: =M90-N90 -> 27918.342
A91: 7 | B91: YUSUF IBRAHIM | C91: PRINCIPAL RESEARCH OFFICER | D91: 12(8) | E91: 365703.83 | G91: =110000 -> 110000 | I91: 0 | J91: =E91+F91+G91+H91+I91 -> 475703.83 | K91: 322454.07 | L91: =J91-K91 -> 153249.76 | M91: 64384.592 | N91: 41338.951 | O91: =M91-N91 -> 23045.641
A92: 8 | B92: MUSTAPHA RAFIU AYOBANJI | C92: RESEARCH FELLOW 11 | D92: 13(7) | E92: 390248.92 | G92: 120000 | I92: 0 | J92: =E92+F92+G92+H92+I92 -> 510248.92 | K92: 346713.03 | L92: =J92-K92 -> 163535.88 | M92: 70529.475 | N92: 45317.541 | O92: =M92-N92 -> 25211.934
A93: 9 | B93: MARYAM MUSA SADA | C93: ASSIT. RESEARCH OFFICER | D93: 10(8) | E93: 300965.58 | G93: 100000 | J93: =E93+F93+G93+H93+I93 -> 400965.58 | K93: 277734.05 | L93: =J93-K93 -> 123231.54 | M93: 51029.227 | N93: 33825.987 | O93: =M93-N93 -> 17203.241
A94: 10 | B94: CHARITY EZENWAJIOBI | C94: REASEARCH. ASST. | D94: 8(9) | E94: 230631.92 | G94: =100000 -> 100000 | J94: =E94+F94+G94+H94+I94 -> 330631.92 | K94: 254870.26 | L94: =J94-K94 -> 75761.653 | M94: 39613.136 | N94: 29984.871 | O94: =M94-N94 -> 9628.2648
B95: TOTAL | C95: 11 | E95: =SUM(E85:E94) -> 4410611.1 | F95: =SUM(F85:F94) -> 0 | G95: =SUM(G85:G94) -> 1290000 | H95: =SUM(H85:H94) -> 0 | I95: =SUM(I85:I94) -> 100000 | J95: =SUM(J85:J94) -> 5800611.1 | K95: 3996601.4 | L95: =SUM(L85:L94) -> 1804009.7 | M95: =SUM(M85:M94) -> 833373.06 | N95: 558913.88 | O95: =SUM(O85:O94) -> 274459.18
B97: TRAINING & INT''L COOP
A98: 1 | B98: AKINSANMI ADEJOKE OLUKEMI | C98: Ag. DIR. TRAINING & IC | D98: 16(9) | E98: 762373.17 | H98: =80000+10000 -> 90000 | J98: =E98+F98+G98+H98+I98 -> 852373.17 | K98: 541465.02 | L98: =J98-K98 -> 310908.14 | M98: 130407.53 | N98: 82423.216 | O98: =M98-N98 -> 47984.311
A99: 2 | B99: MOHAMMED R. ADAMU | C99: CHIEF TRAINING OFFICER | D99: 14(9) | E99: 456622.25 | H99: 70000 | I99: 0 | J99: =E99+F99+G99+H99+I99 -> 526622.25 | K99: 335272.06 | L99: =J99-K99 -> 191350.19 | M99: 72764.421 | N99: 43492.373 | O99: =M99-N99 -> 29272.048
A100: 3 | B100: OKECHUKWU UCHENNA HULDA | C100: PRINCIPALTRAINING OFFICER | D100: 12(9) | E100: 377895.17 | H100: =60000 -> 60000 | J100: =E100+F100+G100+H100+I100 -> 437895.17 | K100: 284537 | L100: =J100-K100 -> 153358.17 | M100: 56938.069 | N100: 34968.882 | O100: =M100-N100 -> 21969.186
A101: 4 | B101: TASSNEEM IBRAHIM | C101: SENIOR PROGRAMME OFFICER | D101: 10(8) | E101: 300965.58 | H101: =60000 -> 60000 | J101: =E101+F101+G101+H101+I101 -> 360965.58 | K101: 237734.05 | L101: =J101-K101 -> 123231.54 | M101: 43763.907 | N101: 27105.987 | O101: =M101-N101 -> 16657.921
B102: TOTAL | C102: 4 | E102: =SUM(E98:E101) -> 1897856.2 | F102: =SUM(F98:F101) -> 0 | G102: =SUM(G98:G101) -> 0 | H102: =SUM(H98:H101) -> 280000 | I102: =SUM(I98:I101) -> 0 | J102: =SUM(J98:J101) -> 2177856.2 | K102: 1399008.1 | L102: =SUM(L98:L101) -> 778848.03 | M102: =SUM(M98:M101) -> 303873.92 | N102: 187990.46 | O102: =SUM(O98:O101) -> 115883.47
B104: LIBRARY & DOCUMENTATION
A105: 1 | B105: DR MAIMUNA IZAH | C105: INSITUTE LIBRARIAN | D105: 17(9) | E105: 1435720 | G105: =200000 -> 200000 | I105: 0 | J105: =E105+F105+G105+H105+I105 -> 1635720 | K105: 1050209.1 | L105: =J105-K105 -> 585510.94 | M105: 270672.25 | N105: 180306.81 | O105: =M105-N105 -> 90365.441
A106: 2 | B106: CATHERINE E. IKOKOH | C106: SNR RESEARCH FELLOW DOCU | D106: 16(9) | E106: 762373.17 | G106: =160000+20000 -> 180000 | I106: 0 | J106: =E106+F106+G106+H106+I106 -> 942373.17 | K106: 631465.02 | L106: =J106-K106 -> 310908.14 | M106: 147687.53 | N106: 99703.216 | O106: =M106-N106 -> 47984.311
A107: 3 | B107: ALIYU SANNI ABUBAKAR | C107: RESEARCH FELLOW 11 DATA & DOCU | D107: 13(11) | E107: 441804.92 | G107: =120000 -> 120000 | I107: 41432.939 | J107: =E107+F107+G107+H107+I107 -> 603237.86 | K107: 418096.02 | L107: =J107-K107 -> 185141.84 | M107: 87575.783 | N107: 58814.673 | O107: =M107-N107 -> 28761.11
A108: 4 | B108: CHINAKO N. ASOGWA | C108: RESEARCH FELLOW 11 DATA & DOCU | D108: 13(11) | E108: 441804.92 | G108: =120000 -> 120000 | I108: 39820.117 | J108: =E108+F108+G108+H108+I108 -> 601625.03 | K108: 416483.19 | L108: =J108-K108 -> 185141.84 | M108: 87392.55 | N108: 58631.44 | O108: =M108-N108 -> 28761.11
...

Sheet Feb New PAYE 
A1: NATIONAL INSTITUTE FOR LEGISLATIVE AND DEMOCRATIC STUDIES
A2: NATIONAL ASSEMBLY ABUJA
A3: TAX COMPUTATION FOR 2022
A4: S/NO | B4: NAME | C4: MONTHLY TOTAL SALARY | D4: NO OF MONTHS | E4: ANNUAL SALARY GROSSED UP | F4: NATIONAL HOUSING SCHEME = 2.5% OF BASIC SALARY | G4: PENSION CONTRIBUTION = 8% OF CONSOLIDATED | H4: NHIS | I4: NET SALARY (EXC OF CRA) | M4: CRA=#200,000+(20% 0F NET SALARY (EXC OF CRA) | N4: TOTAL RELIEF | O4: CHARGEABLE INCOME | P4: FIRST N300,000 @ 7% | Q4: NEXT N300,000 @ 11% | R4: NEXT N500,000 @ 15% | S4: NEXT N500,000@ 19% | T4: NEXT N1,600,000 @ 21% | U4: ABOVE N3,200,000 @ 24% | V4: ANNUAL TAX PAYABLE | X4: MONTHLY TAX PAYABLE | Y4: MINIMUM TAX PAYABLE | Z4: NEW ACTUAL TAX PAYABLE | AB4: Difference
A5: 1 | B5: DG'S OFFICE
A6: 3 | B6: PROF. ABUBAKAR O. SULAIMAN | C6: 1934986.2 | D6: 12 | E6: =C6*D6 -> 23219834 | I6: =E6-F6-G6-H6 -> 23219834 | J6: 200000 | K6: 0.2 | L6: =I6*K6 -> 4643966.8 | M6: =J6+L6 -> 4843966.8 | N6: =F6+G6+H6+M6 -> 4843966.8 | O6: =E6-N6 -> 18375867 | P6: =IF(O6<300000,0.07*O6,21000) -> 21000 | Q6: =IF((O6-300000)<0,0,IF((O6-300000)<300000,0.11*(O6-300000),33000)) -> 33000 | R6: =IF((O6-600000)<0,0,IF((O6-600000)<500000,0.15*(O6-600000),75000)) -> 75000 | S6: =IF((O6-1100000)<0,0,IF((O6-1100000)<500000,0.19*(O6-1100000),95000)) -> 95000 | T6: =IF((O6-1600000)<0,0,IF((O6-1600000)<1600000,0.21*(O6-1600000),336000)) -> 336000 | U6: =24%*(O6-3200000) -> 3642208.1 | V6: =P6+Q6+R6+S6+T6+U6 -> 4202208.1 | W6: 12 | X6: =V6/W6 -> 350184.01 | Z6: =X6 -> 350184.01 | AA6: 201165.84 | AB6: =Z6-AA6 -> 149018.17
A7: 4 | B7: RAHEEM USMAN AYIGORO | C7: 852373.17 | D7: 12 | E7: =C7*D7 -> 10228478 | G7: 731878.24 | I7: =E7-F7-G7-H7 -> 9496599.8 | J7: 200000 | K7: 0.2 | L7: =I7*K7 -> 1899320 | M7: =J7+L7 -> 2099320 | N7: =F7+G7+H7+M7 -> 2831198.2 | O7: =E7-N7 -> 7397279.8 | P7: =IF(O7<300000,0.07*O7,21000) -> 21000 | Q7: =IF((O7-300000)<0,0,IF((O7-300000)<300000,0.11*(O7-300000),33000)) -> 33000 | R7: =IF((O7-600000)<0,0,IF((O7-600000)<500000,0.15*(O7-600000),75000)) -> 75000 | S7: =IF((O7-1100000)<0,0,IF((O7-1100000)<500000,0.19*(O7-1100000),95000)) -> 95000 | T7: =IF((O7-1600000)<0,0,IF((O7-1600000)<1600000,0.21*(O7-1600000),336000)) -> 336000 | U7: =24%*(O7-3200000) -> 1007347.2 | V7: =P7+Q7+R7+S7+T7+U7 -> 1567347.2 | W7: 12 | X7: =V7/W7 -> 130612.26 | Z7: =X7 -> 130612.26 | AA7: 82627.951 | AB7: =Z7-AA7 -> 47984.311
A8: 5 | B8: MARIAM MOHAMMED BELLO | C8: 1052373.2 | D8: 12 | E8: =C8*D8 -> 12628478 | G8: 0 | I8: =E8-F8-G8-H8 -> 12628478 | J8: 200000 | K8: 0.2 | L8: =I8*K8 -> 2525695.6 | M8: =J8+L8 -> 2725695.6 | N8: =F8+G8+H8+M8 -> 2725695.6 | O8: =E8-N8 -> 9902782.4 | P8: =IF(O8<300000,0.07*O8,21000) -> 21000 | Q8: =IF((O8-300000)<0,0,IF((O8-300000)<300000,0.11*(O8-300000),33000)) -> 33000 | R8: =IF((O8-600000)<0,0,IF((O8-600000)<500000,0.15*(O8-600000),75000)) -> 75000 | S8: =IF((O8-1100000)<0,0,IF((O8-1100000)<500000,0.19*(O8-1100000),95000)) -> 95000 | T8: =IF((O8-1600000)<0,0,IF((O8-1600000)<1600000,0.21*(O8-1600000),336000)) -> 336000 | U8: =24%*(O8-3200000) -> 1608667.8 | V8: =P8+Q8+R8+S8+T8+U8 -> 2168667.8 | W8: 12 | X8: =V8/W8 -> 180722.31 | Z8: =X8 -> 180722.31 | AA8: 121027.95 | AB8: =Z8-AA8 -> 59694.363
A9: 6 | B9: DR IKEME ARTHUR J.O | C9: 942373.17 | D9: 12 | E9: =C9*D9 -> 11308478 | F9: ='[4]JANUARY 2024'!$V$10*12 -> 12795.951 | G9: 731878.24 | I9: =E9-F9-G9-H9 -> 10563804 | J9: 200000 | K9: 0.2 | L9: =I9*K9 -> 2112760.8 | M9: =J9+L9 -> 2312760.8 | N9: =F9+G9+H9+M9 -> 3057435 | O9: =E9-N9 -> 8251043 | P9: =IF(O9<300000,0.07*O9,21000) -> 21000 | Q9: =IF((O9-300000)<0,0,IF((O9-300000)<300000,0.11*(O9-300000),33000)) -> 33000 | R9: =IF((O9-600000)<0,0,IF((O9-600000)<500000,0.15*(O9-600000),75000)) -> 75000 | S9: =IF((O9-1100000)<0,0,IF((O9-1100000)<500000,0.19*(O9-1100000),95000)) -> 95000 | T9: =IF((O9-1600000)<0,0,IF((O9-1600000)<1600000,0.21*(O9-1600000),336000)) -> 336000 | U9: =24%*(O9-3200000) -> 1212250.3 | V9: =P9+Q9+R9+S9+T9+U9 -> 1772250.3 | W9: 12 | X9: =V9/W9 -> 147687.53 | Z9: =X9 -> 147687.53 | AA9: 99703.216 | AB9: =Z9-AA9 -> 47984.311
A10: 7 | B10: MOSHOOD M. OLALERE | C10: 1002373.2 | D10: 12 | E10: =C10*D10 -> 12028478 | F10: ='[4]JANUARY 2024'!$V$10*12 -> 12795.951 | G10: 731878.24 | I10: =E10-F10-G10-H10 -> 11283804 | J10: 200000 | K10: 0.2 | L10: =I10*K10 -> 2256760.8 | M10: =J10+L10 -> 2456760.8 | N10: =F10+G10+H10+M10 -> 3201435 | O10: =E10-N10 -> 8827043 | P10: =IF(O10<300000,0.07*O10,21000) -> 21000 | Q10: =IF((O10-300000)<0,0,IF((O10-300000)<300000,0.11*(O10-300000),33000)) -> 33000 | R10: =IF((O10-600000)<0,0,IF((O10-600000)<500000,0.15*(O10-600000),75000)) -> 75000 | S10: =IF((O10-1100000)<0,0,IF((O10-1100000)<500000,0.19*(O10-1100000),95000)) -> 95000 | T10: =IF((O10-1600000)<0,0,IF((O10-1600000)<1600000,0.21*(O10-1600000),336000)) -> 336000 | U10: =24%*(O10-3200000) -> 1350490.3 | V10: =P10+Q10+R10+S10+T10+U10 -> 1910490.3 | W10: 12 | X10: =V10/W10 -> 159207.53 | Z10: =X10 -> 159207.53 | AA10: 111223.22 | AB10: =Z10-AA10 -> 47984.311
A11: 8 | B11: REKIYA IBRAHIM ATTAH | C11: 952373.17 | D11: 12 | E11: =C11*D11 -> 11428478 | G11: 0 | I11: =E11-F11-G11-H11 -> 11428478 | J11: 200000 | K11: 0.2 | L11: =I11*K11 -> 2285695.6 | M11: =J11+L11 -> 2485695.6 | N11: =F11+G11+H11+M11 -> 2485695.6 | O11: =E11-N11 -> 8942782.4 | P11: =IF(O11<300000,0.07*O11,21000) -> 21000 | Q11: =IF((O11-300000)<0,0,IF((O11-300000)<300000,0.11*(O11-300000),33000)) -> 33000 | R11: =IF((O11-600000)<0,0,IF((O11-600000)<500000,0.15*(O11-600000),75000)) -> 75000 | S11: =IF((O11-1100000)<0,0,IF((O11-1100000)<500000,0.19*(O11-1100000),95000)) -> 95000 | T11: =IF((O11-1600000)<0,0,IF((O11-1600000)<1600000,0.21*(O11-1600000),336000)) -> 336000 | U11: =24%*(O11-3200000) -> 1378267.8 | V11: =P11+Q11+R11+S11+T11+U11 -> 1938267.8 | W11: 12 | X11: =V11/W11 -> 161522.31 | Z11: =X11 -> 161522.31 | AA11: 101827.95 | AB11: =Z11-AA11 -> 59694.363
A12: 9 | B12: ANDRAWUS MUSA | C12: 750675.58 | D12: 12 | E12: =C12*D12 -> 9008107 | F12: ='[4]JANUARY 2024'!$V$13*12 -> 10052.25 | G12: 595848.56 | I12: =E12-F12-G12-H12 -> 8402206.2 | J12: 200000 | K12: 0.2 | L12: =I12*K12 -> 1680441.2 | M12: =J12+L12 -> 1880441.2 | N12: =F12+G12+H12+M12 -> 2486342 | O12: =E12-N12 -> 6521765 | P12: =IF(O12<300000,0.07*O12,21000) -> 21000 | Q12: =IF((O12-300000)<0,0,IF((O12-300000)<300000,0.11*(O12-300000),33000)) -> 33000 | R12: =IF((O12-600000)<0,0,IF((O12-600000)<500000,0.15*(O12-600000),75000)) -> 75000 | S12: =IF((O12-1100000)<0,0,IF((O12-1100000)<500000,0.19*(O12-1100000),95000)) -> 95000 | T12: =IF((O12-1600000)<0,0,IF((O12-1600000)<1600000,0.21*(O12-1600000),336000)) -> 336000 | U12: =24%*(O12-3200000) -> 797223.59 | V12: =P12+Q12+R12+S12+T12+U12 -> 1357223.6 | W12: 12 | X12: =V12/W12 -> 113101.97 | Z12: =X12 -> 113101.97 | AA12: 74036.103 | AB12: =Z12-AA12 -> 39065.863
A13: 10 | B13: DR FRANCIS NDUM OJIE | C13: 842118.08 | D13: 12 | E13: =C13*D13 -> 10105417 | F13: ='[4]JANUARY 2024'!$V$14*12 -> 9305.952 | G13: 558833.36 | I13: =E13-F13-G13-H13 -> 9537277.7 | J13: 200000 | K13: 0.2 | L13: =I13*K13 -> 1907455.5 | M13: =J13+L13 -> 2107455.5 | N13: =F13+G13+H13+M13 -> 2675594.8 | O13: =E13-N13 -> 7429822.2 | P13: =IF(O13<300000,0.07*O13,21000) -> 21000 | Q13: =IF((O13-300000)<0,0,IF((O13-300000)<300000,0.11*(O13-300000),33000)) -> 33000 | R13: =IF((O13-600000)<0,0,IF((O13-600000)<500000,0.15*(O13-600000),75000)) -> 75000 | S13: =IF((O13-1100000)<0,0,IF((O13-1100000)<500000,0.19*(O13-1100000),95000)) -> 95000 | T13: =IF((O13-1600000)<0,0,IF((O13-1600000)<1600000,0.21*(O13-1600000),336000)) -> 336000 | U13: =24%*(O13-3200000) -> 1015157.3 | V13: =P13+Q13+R13+S13+T13+U13 -> 1575157.3 | W13: 12 | X13: =V13/W13 -> 131263.11 | Z13: =X13 -> 131263.11 | AA13: 94625.782 | AB13: =Z13-AA13 -> 36637.328
A14: 11 | B14: ALI ABDULLAHI | C14: 554373.75 | D14: 12 | E14: =C14*D14 -> 6652485 | G14: 464998.8 | I14: =E14-F14-G14-H14 -> 6187486.2 | J14: 200000 | K14: 0.2 | L14: =I14*K14 -> 1237497.2 | M14: =J14+L14 -> 1437497.2 | N14: =F14+G14+H14+M14 -> 1902496 | O14: =E14-N14 -> 4749989 | P14: =IF(O14<300000,0.07*O14,21000) -> 21000 | Q14: =IF((O14-300000)<0,0,IF((O14-300000)<300000,0.11*(O14-300000),33000)) -> 33000 | R14: =IF((O14-600000)<0,0,IF((O14-600000)<500000,0.15*(O14-600000),75000)) -> 75000 | S14: =IF((O14-1100000)<0,0,IF((O14-1100000)<500000,0.19*(O14-1100000),95000)) -> 95000 | T14: =IF((O14-1600000)<0,0,IF((O14-1600000)<1600000,0.21*(O14-1600000),336000)) -> 336000 | U14: =24%*(O14-3200000) -> 371997.35 | V14: =P14+Q14+R14+S14+T14+U14 -> 931997.35 | W14: 12 | X14: =V14/W14 -> 77666.446 | Z14: =X14 -> 77666.446 | AA14: 44846.617 | AB14: =Z14-AA14 -> 32819.829
A15: 12 | B15: EMILY EKHIDE | C15: 660498 | D15: 12 | E15: =C15*D15 -> 7925976 | G15: 451678.08 | I15: =E15-F15-G15-H15 -> 7474297.9 | J15: 200000 | K15: 0.2 | L15: =I15*K15 -> 1494859.6 | M15: =J15+L15 -> 1694859.6 | N15: =F15+G15+H15+M15 -> 2146537.7 | O15: =E15-N15 -> 5779438.3 | P15: =IF(O15<300000,0.07*O15,21000) -> 21000 | Q15: =IF((O15-300000)<0,0,IF((O15-300000)<300000,0.11*(O15-300000),33000)) -> 33000 | R15: =IF((O15-600000)<0,0,IF((O15-600000)<500000,0.15*(O15-600000),75000)) -> 75000 | S15: =IF((O15-1100000)<0,0,IF((O15-1100000)<500000,0.19*(O15-1100000),95000)) -> 95000 | T15: =IF((O15-1600000)<0,0,IF((O15-1600000)<1600000,0.21*(O15-1600000),336000)) -> 336000 | U15: =24%*(O15-3200000) -> 619065.2 | V15: =P15+Q15+R15+S15+T15+U15 -> 1179065.2 | W15: 12 | X15: =V15/W15 -> 98255.433 | Z15: =X15 -> 98255.433 | AA15: 46666.667 | AB15: =Z15-AA15 -> 51588.767
A16: 13 | B16: DORIS DAKDA AARON | C16: 732746.5 | D16: 12 | E16: =C16*D16 -> 8792958 | G16: 425036.64 | I16: =E16-F16-G16-H16 -> 8367921.4 | J16: 200000 | K16: 0.2 | L16: =I16*K16 -> 1673584.3 | M16: =J16+L16 -> 1873584.3 | N16: =F16+G16+H16+M16 -> 2298620.9 | O16: =E16-N16 -> 6494337.1 | P16: =IF(O16<300000,0.07*O16,21000) -> 21000 | Q16: =IF((O16-300000)<0,0,IF((O16-300000)<300000,0.11*(O16-300000),33000)) -> 33000 | R16: =IF((O16-600000)<0,0,IF((O16-600000)<500000,0.15*(O16-600000),75000)) -> 75000 | S16: =IF((O16-1100000)<0,0,IF((O16-1100000)<500000,0.19*(O16-1100000),95000)) -> 95000 | T16: =IF((O16-1600000)<0,0,IF((O16-1600000)<1600000,0.21*(O16-1600000),336000)) -> 336000 | U16: =24%*(O16-3200000) -> 790640.9 | V16: =P16+Q16+R16+S16+T16+U16 -> 1350640.9 | W16: 12 | X16: =V16/W16 -> 112553.41 | Z16: =X16 -> 112553.41 | AA16: 46666.667 | AB16: =Z16-AA16 -> 65886.742
A17: 14 | B17: ABDULSALAM S. MUSTAPHA | C17: 511804.92 | D17: 12 | E17: =C17*D17 -> 6141659 | G17: 424132.72 | I17: =E17-F17-G17-H17 -> 5717526.3 | J17: 200000 | K17: 0.2 | L17: =I17*K17 -> 1143505.3 | M17: =J17+L17 -> 1343505.3 | N17: =F17+G17+H17+M17 -> 1767638 | O17: =E17-N17 -> 4374021 | P17: =IF(O17<300000,0.07*O17,21000) -> 21000 | Q17: =IF((O17-300000)<0,0,IF((O17-300000)<300000,0.11*(O17-300000),33000)) -> 33000 | R17: =IF((O17-600000)<0,0,IF((O17-600000)<500000,0.15*(O17-600000),75000)) -> 75000 | S17: =IF((O17-1100000)<0,0,IF((O17-1100000)<500000,0.19*(O17-1100000),95000)) -> 95000 | T17: =IF((O17-1600000)<0,0,IF((O17-1600000)<1600000,0.21*(O17-1600000),336000)) -> 336000 | U17: =24%*(O17-3200000) -> 281765.05 | V17: =P17+Q17+R17+S17+T17+U17 -> 841765.05 | W17: 12 | X17: =V17/W17 -> 70147.087 | Z17: =X17 -> 70147.087 | AA17: 42046.064 | AB17: =Z17-AA17 -> 28101.023
A18: 15 | B18: PERCY TERFA GBAHABO | C18: 548915.92 | D18: 12 | E18: =C18*D18 -> 6586991 | G18: 411759.28 | I18: =E18-F18-G18-H18 -> 6175231.7 | J18: 200000 | K18: 0.2 | L18: =I18*K18 -> 1235046.3 | M18: =J18+L18 -> 1435046.3 | N18: =F18+G18+H18+M18 -> 1846805.6 | O18: =E18-N18 -> 4740185.4 | P18: =IF(O18<300000,0.07*O18,21000) -> 21000 | Q18: =IF((O18-300000)<0,0,IF((O18-300000)<300000,0.11*(O18-300000),33000)) -> 33000 | R18: =IF((O18-600000)<0,0,IF((O18-600000)<500000,0.15*(O18-600000),75000)) -> 75000 | S18: =IF((O18-1100000)<0,0,IF((O18-1100000)<500000,0.19*(O18-1100000),95000)) -> 95000 | T18: =IF((O18-1600000)<0,0,IF((O18-1600000)<1600000,0.21*(O18-1600000),336000)) -> 336000 | U18: =24%*(O18-3200000) -> 369644.49 | V18: =P18+Q18+R18+S18+T18+U18 -> 929644.49 | W18: 12 | X18: =V18/W18 -> 77470.374 | Z18: =X18 -> 77470.374 | AA18: 46666.667 | AB18: =Z18-AA18 -> 30803.708
A19: 16 | B19: HASSANA AHMED IBRAHIM | C19: 636026.92 | D19: 12 | E19: =C19*D19 -> 7632323 | F19: =618.53*12 -> 7422.36 | G19: 399385.84 | I19: =E19-F19-G19-H19 -> 7225514.8 | J19: 200000 | K19: 0.2 | L19: =I19*K19 -> 1445103 | M19: =J19+L19 -> 1645103 | N19: =F19+G19+H19+M19 -> 2051911.2 | O19: =E19-N19 -> 5580411.8 | P19: =IF(O19<300000,0.07*O19,21000) -> 21000 | Q19: =IF((O19-300000)<0,0,IF((O19-300000)<300000,0.11*(O19-300000),33000)) -> 33000 | R19: =IF((O19-600000)<0,0,IF((O19-600000)<500000,0.15*(O19-600000),75000)) -> 75000 | S19: =IF((O19-1100000)<0,0,IF((O19-1100000)<500000,0.19*(O19-1100000),95000)) -> 95000 | T19: =IF((O19-1600000)<0,0,IF((O19-1600000)<1600000,0.21*(O19-1600000),336000)) -> 336000 | U19: =24%*(O19-3200000) -> 571298.84 | V19: =P19+Q19+R19+S19+T19+U19 -> 1131298.8 | W19: 12 | X19: =V19/W19 -> 94274.903 | Z19: =X19 -> 94274.903 | AA19: 46666.667 | AB19: =Z19-AA19 -> 47608.237
A20: 17 | B20: ADUGBA RICHARD TERSEER | C20: 537895.17 | D20: 12 | E20: =C20*D20 -> 6454742 | G20: 362779.36 | I20: =E20-F20-G20-H20 -> 6091962.6 | J20: 200000 | K20: 0.2 | L20: =I20*K20 -> 1218392.5 | M20: =J20+L20 -> 1418392.5 | N20: =F20+G20+H20+M20 -> 1781171.9 | O20: =E20-N20 -> 4673570.1 | P20: =IF(O20<300000,0.07*O20,21000) -> 21000 | Q20: =IF((O20-300000)<0,0,IF((O20-300000)<300000,0.11*(O20-300000),33000)) -> 33000 | R20: =IF((O20-600000)<0,0,IF((O20-600000)<500000,0.15*(O20-600000),75000)) -> 75000 | S20: =IF((O20-1100000)<0,0,IF((O20-1100000)<500000,0.19*(O20-1100000),95000)) -> 95000 | T20: =IF((O20-1600000)<0,0,IF((O20-1600000)<1600000,0.21*(O20-1600000),336000)) -> 336000 | U20: =24%*(O20-3200000) -> 353656.83 | V20: =P20+Q20+R20+S20+T20+U20 -> 913656.83 | W20: 12 | X20: =V20/W20 -> 76138.069 | Z20: =X20 -> 76138.069 | AA20: 52497.77 | AB20: =Z20-AA20 -> 23640.299
A21: 18 | B21: LUCKY AGWOM | C21: 553512.5 | D21: 12 | E21: =C21*D21 -> 6642150 | G21: 339372 | I21: =E21-F21-G21-H21 -> 6302778 | J21: 200000 | K21: 0.2 | L21: =I21*K21 -> 1260555.6 | M21: =J21+L21 -> 1460555.6 | N21: =F21+G21+H21+M21 -> 1799927.6 | O21: =E21-N21 -> 4842222.4 | P21: =IF(O21<300000,0.07*O21,21000) -> 21000 | Q21: =IF((O21-300000)<0,0,IF((O21-300000)<300000,0.11*(O21-300000),33000)) -> 33000 | R21: =IF((O21-600000)<0,0,IF((O21-600000)<500000,0.15*(O21-600000),75000)) -> 75000 | S21: =IF((O21-1100000)<0,0,IF((O21-1100000)<500000,0.19*(O21-1100000),95000)) -> 95000 | T21: =IF((O21-1600000)<0,0,IF((O21-1600000)<1600000,0.21*(O21-1600000),336000)) -> 336000 | U21: =24%*(O21-3200000) -> 394133.38 | V21: =P21+Q21+R21+S21+T21+U21 -> 954133.38 | W21: 12 | X21: =V21/W21 -> 79511.115 | Z21: =X21 -> 79511.115 | AA21: 46666.667 | AB21: =Z21-AA21 -> 32844.448
A22: 19 | B22: IDRIS IBRAHIM | C22: 463512.5 | D22: 12 | E22: =C22*D22 -> 5562150 | G22: 339372 | I22: =E22-F22-G22-H22 -> 5222778 | J22: 200000 | K22: 0.2 | L22: =I22*K22 -> 1044555.6 | M22: =J22+L22 -> 1244555.6 | N22: =F22+G22+H22+M22 -> 1583927.6 | O22: =E22-N22 -> 3978222.4 | P22: =IF(O22<300000,0.07*O22,21000) -> 21000 | Q22: =IF((O22-300000)<0,0,IF((O22-300000)<300000,0.11*(O22-300000),33000)) -> 33000 | R22: =IF((O22-600000)<0,0,IF((O22-600000)<500000,0.15*(O22-600000),75000)) -> 75000 | S22: =IF((O22-1100000)<0,0,IF((O22-1100000)<500000,0.19*(O22-1100000),95000)) -> 95000 | T22: =IF((O22-1600000)<0,0,IF((O22-1600000)<1600000,0.21*(O22-1600000),336000)) -> 336000 | U22: =24%*(O22-3200000) -> 186773.38 | V22: =P22+Q22+R22+S22+T22+U22 -> 746773.38 | W22: 12 | X22: =V22/W22 -> 62231.115 | Z22: =X22 -> 62231.115 | AA22: 46666.667 | AB22: =Z22-AA22 -> 15564.448
A23: 20 | B23: FARUQ ATOFARATI | C23: 453029.67 | D23: 12 | E23: =C23*D23 -> 5436356 | G23: 281308.48 | I23: =E23-F23-G23-H23 -> 5155047.5 | J23: 200000 | K23: 0.2 | L23: =I23*K23 -> 1031009.5 | M23: =J23+L23 -> 1231009.5 | N23: =F23+G23+H23+M23 -> 1512318 | O23: =E23-N23 -> 3924038 | P23: =IF(O23<300000,0.07*O23,21000) -> 21000 | Q23: =IF((O23-300000)<0,0,IF((O23-300000)<300000,0.11*(O23-300000),33000)) -> 33000 | R23: =IF((O23-600000)<0,0,IF((O23-600000)<500000,0.15*(O23-600000),75000)) -> 75000 | S23: =IF((O23-1100000)<0,0,IF((O23-1100000)<500000,0.19*(O23-1100000),95000)) -> 95000 | T23: =IF((O23-1600000)<0,0,IF((O23-1600000)<1600000,0.21*(O23-1600000),336000)) -> 336000 | U23: =24%*(O23-3200000) -> 173769.12 | V23: =P23+Q23+R23+S23+T23+U23 -> 733769.12 | W23: 12 | X23: =V23/W23 -> 61147.427 | Z23: =X23 -> 61147.427 | AA23: 42371.816 | AB23: =Z23-AA23 -> 18775.611
A24: 21 | B24: ELIZABETH OGECHUKWU ONYEAKU | C24: 330481.67 | D24: 12 | E24: =C24*D24 -> 3965780 | G24: 259662.4 | I24: =E24-F24-G24-H24 -> 3706117.6 | J24: 200000 | K24: 0.2 | L24: =I24*K24 -> 741223.52 | M24: =J24+L24 -> 941223.52 | N24: =F24+G24+H24+M24 -> 1200885.9 | O24: =E24-N24 -> 2764894.1 | P24: =IF(O24<300000,0.07*O24,21000) -> 21000 | Q24: =IF((O24-300000)<0,0,IF((O24-300000)<300000,0.11*(O24-300000),33000)) -> 33000 | R24: =IF((O24-600000)<0,0,IF((O24-600000)<500000,0.15*(O24-600000),75000)) -> 75000 | S24: =IF((O24-1100000)<0,0,IF((O24-1100000)<500000,0.19*(O24-1100000),95000)) -> 95000 | T24: =IF((O24-1600000)<0,0,IF((O24-1600000)<1600000,0.21*(O24-1600000),336000)) -> 244627.76 | V24: =P24+Q24+R24+S24+T24+U24 -> 468627.76 | W24: 12 | X24: =V24/W24 -> 39052.313 | Z24: =X24 -> 39052.313 | AA24: 23036.012 | AB24: =Z24-AA24 -> 16016.301
A25: 22 | B25: VICTOR ASUKWO | C25: 330481.67 | D25: 12 | E25: =C25*D25 -> 3965780 | G25: 259662.4 | I25: =E25-F25-G25-H25 -> 3706117.6 | J25: 200000 | K25: 0.2 | L25: =I25*K25 -> 741223.52 | M25: =J25+L25 -> 941223.52 | N25: =F25+G25+H25+M25 -> 1200885.9 | O25: =E25-N25 -> 2764894.1 | P25: =IF(O25<300000,0.07*O25,21000) -> 21000 | Q25: =IF((O25-300000)<0,0,IF((O25-300000)<300000,0.11*(O25-300000),33000)) -> 33000 | R25: =IF((O25-600000)<0,0,IF((O25-600000)<500000,0.15*(O25-600000),75000)) -> 75000 | S25: =IF((O25-1100000)<0,0,IF((O25-1100000)<500000,0.19*(O25-1100000),95000)) -> 95000 | T25: =IF((O25-1600000)<0,0,IF((O25-1600000)<1600000,0.21*(O25-1600000),336000)) -> 244627.76 | V25: =P25+Q25+R25+S25+T25+U25 -> 468627.76 | W25: 12 | X25: =V25/W25 -> 39052.313 | Z25: =X25 -> 39052.313 | AA25: 23036.012 | AB25: =Z25-AA25 -> 16016.301
A26: 23 | B26: NNANDI LIVINUS ATURE | C26: 370481.67 | D26: 12 | E26: =C26*D26 -> 4445780 | G26: 259662.4 | I26: =E26-F26-G26-H26 -> 4186117.6 | J26: 200000 | K26: 0.2 | L26: =I26*K26 -> 837223.52 | M26: =J26+L26 -> 1037223.5 | N26: =F26+G26+H26+M26 -> 1296885.9 | O26: =E26-N26 -> 3148894.1 | P26: =IF(O26<300000,0.07*O26,21000) -> 21000 | Q26: =IF((O26-300000)<0,0,IF((O26-300000)<300000,0.11*(O26-300000),33000)) -> 33000 | R26: =IF((O26-600000)<0,0,IF((O26-600000)<500000,0.15*(O26-600000),75000)) -> 75000 | S26: =IF((O26-1100000)<0,0,IF((O26-1100000)<500000,0.19*(O26-1100000),95000)) -> 95000 | T26: =IF((O26-1600000)<0,0,IF((O26-1600000)<1600000,0.21*(O26-1600000),336000)) -> 325267.76 | V26: =P26+Q26+R26+S26+T26+U26 -> 549267.76 | W26: 12 | X26: =V26/W26 -> 45772.313 | Z26: =X26 -> 45772.313 | AA26: 29756.012 | AB26: =Z26-AA26 -> 16016.301
A27: 24 | B27: ABDULRAHMAN A SULAIMAN | C27: 323165.33 | D27: 12 | E27: =C27*D27 -> 3877984 | G27: 252638.72 | I27: =E27-F27-G27-H27 -> 3625345.3 | J27: 200000 | K27: 0.2 | L27: =I27*K27 -> 725069.06 | M27: =J27+L27 -> 925069.06 | N27: =F27+G27+H27+M27 -> 1177707.8 | O27: =E27-N27 -> 2700276.2 | P27: =IF(O27<300000,0.07*O27,21000) -> 21000 | Q27: =IF((O27-300000)<0,0,IF((O27-300000)<300000,0.11*(O27-300000),33000)) -> 33000 | R27: =IF((O27-600000)<0,0,IF((O27-600000)<500000,0.15*(O27-600000),75000)) -> 75000 | S27: =IF((O27-1100000)<0,0,IF((O27-1100000)<500000,0.19*(O27-1100000),95000)) -> 95000 | T27: =IF((O27-1600000)<0,0,IF((O27-1600000)<1600000,0.21*(O27-1600000),336000)) -> 231058.01 | V27: =P27+Q27+R27+S27+T27+U27 -> 455058.01 | W27: 12 | X27: =V27/W27 -> 37921.501 | Z27: =X27 -> 37921.501 | AA27: 22338.483 | AB27: =Z27-AA27 -> 15583.018
A28: 25 | B28: DARE SHEU MAGBON | C28: 315849 | D28: 12 | E28: =C28*D28 -> 3790188 | G28: 245615.04 | I28: =E28-F28-G28-H28 -> 3544573 | J28: 200000 | K28: 0.2 | L28: =I28*K28 -> 708914.59 | M28: =J28+L28 -> 908914.59 | N28: =F28+G28+H28+M28 -> 1154529.6 | O28: =E28-N28 -> 2635658.4 | P28: =IF(O28<300000,0.07*O28,21000) -> 21000 | Q28: =IF((O28-300000)<0,0,IF((O28-300000)<300000,0.11*(O28-300000),33000)) -> 33000 | R28: =IF((O28-600000)<0,0,IF((O28-600000)<500000,0.15*(O28-600000),75000)) -> 75000 | S28: =IF((O28-1100000)<0,0,IF((O28-1100000)<500000,0.19*(O28-1100000),95000)) -> 95000 | T28: =IF((O28-1600000)<0,0,IF((O28-1600000)<1600000,0.21*(O28-1600000),336000)) -> 217488.26 | V28: =P28+Q28+R28+S28+T28+U28 -> 441488.26 | W28: 12 | X28: =V28/W28 -> 36790.688 | Z28: =X28 -> 36790.688 | AA28: 21640.953 | AB28: =Z28-AA28 -> 15149.735
A29: 26 | B29: ABUBAKAR SULAIMAN SODEEQ | C29: 315849 | D29: 12 | E29: =C29*D29 -> 3790188 | G29: 245615.04 | I29: =E29-F29-G29-H29 -> 3544573 | J29: 200000 | K29: 0.2 | L29: =I29*K29 -> 708914.59 | M29: =J29+L29 -> 908914.59 | N29: =F29+G29+H29+M29 -> 1154529.6 | O29: =E29-N29 -> 2635658.4 | P29: =IF(O29<300000,0.07*O29,21000) -> 21000 | Q29: =IF((O29-300000)<0,0,IF((O29-300000)<300000,0.11*(O29-300000),33000)) -> 33000 | R29: =IF((O29-600000)<0,0,IF((O29-600000)<500000,0.15*(O29-600000),75000)) -> 75000 | S29: =IF((O29-1100000)<0,0,IF((O29-1100000)<500000,0.19*(O29-1100000),95000)) -> 95000 | T29: =IF((O29-1600000)<0,0,IF((O29-1600000)<1600000,0.21*(O29-1600000),336000)) -> 217488.26 | V29: =P29+Q29+R29+S29+T29+U29 -> 441488.26 | W29: 12 | X29: =V29/W29 -> 36790.688 | Z29: =X29 -> 36790.688 | AA29: 21640.953 | AB29: =Z29-AA29 -> 15149.735
A30: 27 | B30: JIMOH ADEBAYO ZAKA | C30: 330481.67 | D30: 12 | E30: =C30*D30 -> 3965780 | G30: 259662.4 | I30: =E30-F30-G30-H30 -> 3706117.6 | J30: 200000 | K30: 0.2 | L30: =I30*K30 -> 741223.52 | M30: =J30+L30 -> 941223.52 | N30: =F30+G30+H30+M30 -> 1200885.9 | O30: =E30-N30 -> 2764894.1 | P30: =IF(O30<300000,0.07*O30,21000) -> 21000 | Q30: =IF((O30-300000)<0,0,IF((O30-300000)<300000,0.11*(O30-300000),33000)) -> 33000 | R30: =IF((O30-600000)<0,0,IF((O30-600000)<500000,0.15*(O30-600000),75000)) -> 75000 | S30: =IF((O30-1100000)<0,0,IF((O30-1100000)<500000,0.19*(O30-1100000),95000)) -> 95000 | T30: =IF((O30-1600000)<0,0,IF((O30-1600000)<1600000,0.21*(O30-1600000),336000)) -> 244627.76 | V30: =P30+Q30+R30+S30+T30+U30 -> 468627.76 | W30: 12 | X30: =V30/W30 -> 39052.313 | Z30: =X30 -> 39052.313 | AA30: 22338.483 | AB30: =Z30-AA30 -> 16713.83
A31: 28 | B31: MOHAMMED BELLO | C31: 280631.92 | D31: 12 | E31: =C31*D31 -> 3367583 | G31: 221406.64 | I31: =E31-F31-G31-H31 -> 3146176.4 | J31: 200000 | K31: 0.2 | L31: =I31*K31 -> 629235.27 | M31: =J31+L31 -> 829235.27 | N31: =F31+G31+H31+M31 -> 1050641.9 | O31: =E31-N31 -> 2316941.1 | P31: =IF(O31<300000,0.07*O31,21000) -> 21000 | Q31: =IF((O31-300000)<0,0,IF((O31-300000)<300000,0.11*(O31-300000),33000)) -> 33000 | R31: =IF((O31-600000)<0,0,IF((O31-600000)<500000,0.15*(O31-600000),75000)) -> 75000 | S31: =IF((O31-1100000)<0,0,IF((O31-1100000)<500000,0.19*(O31-1100000),95000)) -> 95000 | T31: =IF((O31-1600000)<0,0,IF((O31-1600000)<1600000,0.21*(O31-1600000),336000)) -> 150557.63 | V31: =P31+Q31+R31+S31+T31+U31 -> 374557.63 | W31: 12 | X31: =V31/W31 -> 31213.136 | Z31: =X31 -> 31213.136 | AA31: 17572.885 | AB31: =Z31-AA31 -> 13640.251
A32: 29 | B32: HARUNA JIBRIL AMEH | C32: 274459.75 | D32: 12 | E32: =C32*D32 -> 3293517 | G32: =17956.78*12 -> 215481.36 | I32: =E32-F32-G32-H32 -> 3078035.6 | J32: 200000 | K32: 0.2 | L32: =I32*K32 -> 615607.13 | M32: =J32+L32 -> 815607.13 | N32: =F32+G32+H32+M32 -> 1031088.5 | O32: =E32-N32 -> 2262428.5 | P32: =IF(O32<300000,0.07*O32,21000) -> 21000 | Q32: =IF((O32-300000)<0,0,IF((O32-300000)<300000,0.11*(O32-300000),33000)) -> 33000 | R32: =IF((O32-600000)<0,0,IF((O32-600000)<500000,0.15*(O32-600000),75000)) -> 75000 | S32: =IF((O32-1100000)<0,0,IF((O32-1100000)<500000,0.19*(O32-1100000),95000)) -> 95000 | T32: =IF((O32-1600000)<0,0,IF((O32-1600000)<1600000,0.21*(O32-1600000),336000)) -> 139109.99 | V32: =P32+Q32+R32+S32+T32+U32 -> 363109.99 | W32: 12 | X32: =V32/W32 -> 30259.166 | Z32: =X32 -> 30259.166 | AA32: 16512.682 | AB32: =Z32-AA32 -> 13746.483
A33: 31
A34: 32 | B34: INTERNAL AUDIT
B35: OSANAIYE DAVID AKINYEMI | C35: 1535720 | D35: 12 | E35: =C35*D35 -> 18428640 | G35: 1378291.2 | I35: =E35-F35-G35-H35 -> 17050349 | J35: 200000 | K35: 0.2 | L35: =I35*K35 -> 3410069.8 | M35: =J35+L35 -> 3610069.8 | N35: =F35+G35+H35+M35 -> 4988361 | O35: =E35-N35 -> 13440279 | P35: =IF(O35<300000,0.07*O35,21000) -> 21000 | Q35: =IF((O35-300000)<0,0,IF((O35-300000)<300000,0.11*(O35-300000),33000)) -> 33000 | R35: =IF((O35-600000)<0,0,IF((O35-600000)<500000,0.15*(O35-600000),75000)) -> 75000 | S35: =IF((O35-1100000)<0,0,IF((O35-1100000)<500000,0.19*(O35-1100000),95000)) -> 95000 | T35: =IF((O35-1600000)<0,0,IF((O35-1600000)<1600000,0.21*(O35-1600000),336000)) -> 336000 | U35: =24%*(O35-3200000) -> 2457667 | V35: =P35+Q35+R35+S35+T35+U35 -> 3017667 | W35: 12 | X35: =V35/W35 -> 251472.25 | Z35: =X35 -> 251472.25 | AA35: 161106.81 | AB35: =Z35-AA35 -> 90365.441
B36: JAMILA ABDUL | C36: 353029.67 | D36: 12 | E36: =C36*D36 -> 4236356 | G36: 281308.48 | I36: =E36-F36-G36-H36 -> 3955047.5 | J36: 200000 | K36: 0.2 | L36: =I36*K36 -> 791009.5 | M36: =J36+L36 -> 991009.5 | N36: =F36+G36+H36+M36 -> 1272318 | O36: =E36-N36 -> 2964038 | P36: =IF(O36<300000,0.07*O36,21000) -> 21000 | Q36: =IF((O36-300000)<0,0,IF((O36-300000)<300000,0.11*(O36-300000),33000)) -> 33000 | R36: =IF((O36-600000)<0,0,IF((O36-600000)<500000,0.15*(O36-600000),75000)) -> 75000 | S36: =IF((O36-1100000)<0,0,IF((O36-1100000)<500000,0.19*(O36-1100000),95000)) -> 95000 | T36: =IF((O36-1600000)<0,0,IF((O36-1600000)<1600000,0.21*(O36-1600000),336000)) -> 286447.98 | V36: =P36+Q36+R36+S36+T36+U36 -> 510447.98 | W36: 12 | X36: =V36/W36 -> 42537.332 | Z36: =X36 -> 42537.332 | AA36: 17042.714 | AB36: =Z36-AA36 -> 25494.618
A37: 33 | B37: IJEOMA EWELUKWA | C37: 360965.58 | D37: 12 | E37: =C37*D37 -> 4331587 | G37: 288926.96 | I37: =E37-F37-G37-H37 -> 4042660 | J37: 200000 | K37: 0.2 | L37: =I37*K37 -> 808532.01 | M37: =J37+L37 -> 1008532 | N37: =F37+G37+H37+M37 -> 1297459 | O37: =E37-N37 -> 3034128 | P37: =IF(O37<300000,0.07*O37,21000) -> 21000 | Q37: =IF((O37-300000)<0,0,IF((O37-300000)<300000,0.11*(O37-300000),33000)) -> 33000 | R37: =IF((O37-600000)<0,0,IF((O37-600000)<500000,0.15*(O37-600000),75000)) -> 75000 | S37: =IF((O37-1100000)<0,0,IF((O37-1100000)<500000,0.19*(O37-1100000),95000)) -> 95000 | T37: =IF((O37-1600000)<0,0,IF((O37-1600000)<1600000,0.21*(O37-1600000),336000)) -> 301166.89 | V37: =P37+Q37+R37+S37+T37+U37 -> 525166.89 | W37: 12 | X37: =V37/W37 -> 43763.907 | Z37: =X37 -> 43763.907 | AA37: 26339.078 | AB37: =Z37-AA37 -> 17424.829
G38: 0
B39: LEG. SUPPORT SEVICES | G39: 0
A40: 35 | B40: PROF. EDOBA BRIGHT OMOREGBE | C40: 1635720 | D40: 12 | E40: =C40*D40 -> 19628640 | G40: 1378291.2 | I40: =E40-F40-G40-H40 -> 18250349 | J40: 200000 | K40: 0.2 | L40: =I40*K40 -> 3650069.8 | M40: =J40+L40 -> 3850069.8 | N40: =F40+G40+H40+M40 -> 5228361 | O40: =E40-N40 -> 14400279 | P40: =IF(O40<300000,0.07*O40,21000) -> 21000 | Q40: =IF((O40-300000)<0,0,IF((O40-300000)<300000,0.11*(O40-300000),33000)) -> 33000 | R40: =IF((O40-600000)<0,0,IF((O40-600000)<500000,0.15*(O40-600000),75000)) -> 75000 | S40: =IF((O40-1100000)<0,0,IF((O40-1100000)<500000,0.19*(O40-1100000),95000)) -> 95000 | T40: =IF((O40-1600000)<0,0,IF((O40-1600000)<1600000,0.21*(O40-1600000),336000)) -> 336000 | U40: =0.24*(O40-3200000) -> 2688067 | V40: =P40+Q40+R40+S40+T40+U40 -> 3248067 | W40: 12 | X40: =V40/W40 -> 270672.25 | Z40: =X40 -> 270672.25 | AA40: 180306.81 | AB40: =Z40-AA40 -> 90365.441
A41: 36 | B41: DR CLINTON JAJA | C41: 780675.58 | D41: 12 | E41: =C41*D41 -> 9368107 | G41: 595848.56 | I41: =E41-F41-G41-H41 -> 8772258.4 | J41: 200000 | K41: 0.2 | L41: =I41*K41 -> 1754451.7 | M41: =J41+L41 -> 1954451.7 | N41: =F41+G41+H41+M41 -> 2550300.2 | O41: =E41-N41 -> 6817806.8 | P41: =IF(O41<300000,0.07*O41,21000) -> 21000 | Q41: =IF((O41-300000)<0,0,IF((O41-300000)<300000,0.11*(O41-300000),33000)) -> 33000 | R41: =IF((O41-600000)<0,0,IF((O41-600000)<500000,0.15*(O41-600000),75000)) -> 75000 | S41: =IF((O41-1100000)<0,0,IF((O41-1100000)<500000,0.19*(O41-1100000),95000)) -> 95000 | T41: =IF((O41-1600000)<0,0,IF((O41-1600000)<1600000,0.21*(O41-1600000),336000)) -> 336000 | U41: =24%*(O41-3200000) -> 868273.62 | V41: =P41+Q41+R41+S41+T41+U41 -> 1428273.6 | W41: 12 | X41: =V41/W41 -> 119022.8 | Z41: =X41 -> 119022.8 | AA41: 79956.939 | AB41: =Z41-AA41 -> 39065.863
A42: 37 | B42: BETHEL UZOMA IHUGBA | C42: 919203.58 | D42: 12 | E42: =C42*D42 -> 11030443 | G42: 709635.44 | I42: =E42-F42-G42-H42 -> 10320808 | J42: 200000 | K42: 0.2 | L42: =I42*K42 -> 2064161.5 | M42: =J42+L42 -> 2264161.5 | N42: =F42+G42+H42+M42 -> 2973797 | O42: =E42-N42 -> 8056646 | P42: =IF(O42<300000,0.07*O42,21000) -> 21000 | Q42: =IF((O42-300000)<0,0,IF((O42-300000)<300000,0.11*(O42-300000),33000)) -> 33000 | R42: =IF((O42-600000)<0,0,IF((O42-600000)<500000,0.15*(O42-600000),75000)) -> 75000 | S42: =IF((O42-1100000)<0,0,IF((O42-1100000)<500000,0.19*(O42-1100000),95000)) -> 95000 | T42: =IF((O42-1600000)<0,0,IF((O42-1600000)<1600000,0.21*(O42-1600000),336000)) -> 336000 | U42: =24%*(O42-3200000) -> 1165595.1 | V42: =P42+Q42+R42+S42+T42+U42 -> 1725595.1 | W42: 12 | X42: =V42/W42 -> 143799.59 | Z42: =X42 -> 143799.59 | AA42: 97273.514 | AB42: =Z42-AA42 -> 46526.074
A43: 38 | B43: OGUCHE SAMUEL | C43: 780675.58 | D43: 12 | E43: =C43*D43 -> 9368107 | G43: 595848.56 | I43: =E43-F43-G43-H43 -> 8772258.4 | J43: 200000 | K43: 0.2 | L43: =I43*K43 -> 1754451.7 | M43: =J43+L43 -> 1954451.7 | N43: =F43+G43+H43+M43 -> 2550300.2 | O43: =E43-N43 -> 6817806.8 | P43: =IF(O43<300000,0.07*O43,21000) -> 21000 | Q43: =IF((O43-300000)<0,0,IF((O43-300000)<300000,0.11*(O43-300000),33000)) -> 33000 | R43: =IF((O43-600000)<0,0,IF((O43-600000)<500000,0.15*(O43-600000),75000)) -> 75000 | S43: =IF((O43-1100000)<0,0,IF((O43-1100000)<500000,0.19*(O43-1100000),95000)) -> 95000 | T43: =IF((O43-1600000)<0,0,IF((O43-1600000)<1600000,0.21*(O43-1600000),336000)) -> 336000 | U43: =24%*(O43-3200000) -> 868273.62 | V43: =P43+Q43+R43+S43+T43+U43 -> 1428273.6 | W43: 12 | X43: =V43/W43 -> 119022.8 | Z43: =X43 -> 119022.8 | AA43: 79956.939 | AB43: =Z43-AA43 -> 39065.863
A44: 39 | B44: IBRAHIM USMAN | C44: 780675.58 | D44: 12 | E44: =C44*D44 -> 9368107 | F44: ='[4]JANUARY 2024'!$V$47*12 -> 10052.25 | G44: 595848.56 | I44: =E44-F44-G44-H44 -> 8762206.2 | J44: 200000 | K44: 0.2 | L44: =I44*K44 -> 1752441.2 | M44: =J44+L44 -> 1952441.2 | N44: =F44+G44+H44+M44 -> 2558342 | O44: =E44-N44 -> 6809765 | P44: =IF(O44<300000,0.07*O44,21000) -> 21000 | Q44: =IF((O44-300000)<0,0,IF((O44-300000)<300000,0.11*(O44-300000),33000)) -> 33000 | R44: =IF((O44-600000)<0,0,IF((O44-600000)<500000,0.15*(O44-600000),75000)) -> 75000 | S44: =IF((O44-1100000)<0,0,IF((O44-1100000)<500000,0.19*(O44-1100000),95000)) -> 95000 | T44: =IF((O44-1600000)<0,0,IF((O44-1600000)<1600000,0.21*(O44-1600000),336000)) -> 336000 | U44: =24%*(O44-3200000) -> 866343.59 | V44: =P44+Q44+R44+S44+T44+U44 -> 1426343.6 | W44: 12 | X44: =V44/W44 -> 118861.97 | Z44: =X44 -> 118861.97 | AA44: 79796.103 | AB44: =Z44-AA44 -> 39065.863
A45: 40 | B45: DR MOHAMMED O. AMALI | C45: 742118.08 | D45: 12 | E45: =C45*D45 -> 8905417 | G45: 558833.36 | I45: =E45-F45-G45-H45 -> 8346583.6 | J45: 200000 | K45: 0.2 | L45: =I45*K45 -> 1669316.7 | M45: =J45+L45 -> 1869316.7 | N45: =F45+G45+H45+M45 -> 2428150.1 | O45: =E45-N45 -> 6477266.9 | P45: =IF(O45<300000,0.07*O45,21000) -> 21000 | Q45: =IF((O45-300000)<0,0,IF((O45-300000)<300000,0.11*(O45-300000),33000)) -> 33000 | R45: =IF((O45-600000)<0,0,IF((O45-600000)<500000,0.15*(O45-600000),75000)) -> 75000 | S45: =IF((O45-1100000)<0,0,IF((O45-1100000)<500000,0.19*(O45-1100000),95000)) -> 95000 | T45: =IF((O45-1600000)<0,0,IF((O45-1600000)<1600000,0.21*(O45-1600000),336000)) -> 336000 | U45: =24%*(O45-3200000) -> 786544.06 | V45: =P45+Q45+R45+S45+T45+U45 -> 1346544.1 | W45: 12 | X45: =V45/W45 -> 112212 | Z45: =X45 -> 112212 | AA45: 75572.916 | AB45: =Z45-AA45 -> 36639.089
A46: 41 | B46: YAHAYA SHAMSU | C46: 610498 | D46: 12 | E46: =C46*D46 -> 7325976 | G46: 451678.08 | I46: =E46-F46-G46-H46 -> 6874297.9 | J46: 200000 | K46: 0.2 | L46: =I46*K46 -> 1374859.6 | M46: =J46+L46 -> 1574859.6 | N46: =F46+G46+H46+M46 -> 2026537.7 | O46: =E46-N46 -> 5299438.3 | P46: =IF(O46<300000,0.07*O46,21000) -> 21000 | Q46: =IF((O46-300000)<0,0,IF((O46-300000)<300000,0.11*(O46-300000),33000)) -> 33000 | R46: =IF((O46-600000)<0,0,IF((O46-600000)<500000,0.15*(O46-600000),75000)) -> 75000 | S46: =IF((O46-1100000)<0,0,IF((O46-1100000)<500000,0.19*(O46-1100000),95000)) -> 95000 | T46: =IF((O46-1600000)<0,0,IF((O46-1600000)<1600000,0.21*(O46-1600000),336000)) -> 336000 | U46: =24%*(O46-3200000) -> 503865.2 | V46: =P46+Q46+R46+S46+T46+U46 -> 1063865.2 | W46: 12 | X46: =V46/W46 -> 88655.433 | Z46: =X46 -> 88655.433 | AA46: 58026.609 | AB46: =Z46-AA46 -> 30628.824
A47: 42 | B47: BILKIS S. LAWAL-GAMBARI | C47: 400965.58 | D47: 12 | E47: =C47*D47 -> 4811587 | G47: 288926.96 | I47: =E47-F47-G47-H47 -> 4522660 | J47: 200000 | K47: 0.2 | L47: =I47*K47 -> 904532.01 | M47: =J47+L47 -> 1104532 | N47: =F47+G47+H47+M47 -> 1393459 | O47: =E47-N47 -> 3418128 | P47: =IF(O47<300000,0.07*O47,21000) -> 21000 | Q47: =IF((O47-300000)<0,0,IF((O47-300000)<300000,0.11*(O47-300000),33000)) -> 33000 | R47: =IF((O47-600000)<0,0,IF((O47-600000)<500000,0.15*(O47-600000),75000)) -> 75000 | S47: =IF((O47-1100000)<0,0,IF((O47-1100000)<500000,0.19*(O47-1100000),95000)) -> 95000 | T47: =IF((O47-1600000)<0,0,IF((O47-1600000)<1600000,0.21*(O47-1600000),336000)) -> 336000 | U47: =24%*(O47-3200000) -> 52350.728 | V47: =P47+Q47+R47+S47+T47+U47 -> 612350.73 | W47: 12 | X47: =V47/W47 -> 51029.227 | Z47: =X47 -> 51029.227 | AA47: 33059.078 | AB47: =Z47-AA47 -> 17970.149
A48: 43 | B48: ZAINAB AKINDE | C48: 363165.33 | D48: 12 | E48: =C48*D48 -> 4357984 | G48: 252638.72 | I48: =E48-F48-G48-H48 -> 4105345.3 | J48: 200000 | K48: 0.2 | L48: =I48*K48 -> 821069.06 | M48: =J48+L48 -> 1021069.1 | N48: =F48+G48+H48+M48 -> 1273707.8 | O48: =E48-N48 -> 3084276.2 | P48: =IF(O48<300000,0.07*O48,21000) -> 21000 | Q48: =IF((O48-300000)<0,0,IF((O48-300000)<300000,0.11*(O48-300000),33000)) -> 33000 | R48: =IF((O48-600000)<0,0,IF((O48-600000)<500000,0.15*(O48-600000),75000)) -> 75000 | S48: =IF((O48-1100000)<0,0,IF((O48-1100000)<500000,0.19*(O48-1100000),95000)) -> 95000 | T48: =IF((O48-1600000)<0,0,IF((O48-1600000)<1600000,0.21*(O48-1600000),336000)) -> 311698.01 | V48: =P48+Q48+R48+S48+T48+U48 -> 535698.01 | W48: 12 | X48: =V48/W48 -> 44641.501 | Z48: =X48 -> 44641.501 | AA48: 29058.483 | AB48: =Z48-AA48 -> 15583.018
A49: 44 | B49: ABDULLAHI AHMAD USMAN | C49: 363165.33 | D49: 12 | E49: =C49*D49 -> 4357984 | G49: 252638.72 | I49: =E49-F49-G49-H49 -> 4105345.3 | J49: 200000 | K49: 0.2 | L49: =I49*K49 -> 821069.06 | M49: =J49+L49 -> 1021069.1 | N49: =F49+G49+H49+M49 -> 1273707.8 | O49: =E49-N49 -> 3084276.2 | P49: =IF(O49<300000,0.07*O49,21000) -> 21000 | Q49: =IF((O49-300000)<0,0,IF((O49-300000)<300000,0.11*(O49-300000),33000)) -> 33000 | R49: =IF((O49-600000)<0,0,IF((O49-600000)<500000,0.15*(O49-600000),75000)) -> 75000 | S49: =IF((O49-1100000)<0,0,IF((O49-1100000)<500000,0.19*(O49-1100000),95000)) -> 95000 | T49: =IF((O49-1600000)<0,0,IF((O49-1600000)<1600000,0.21*(O49-1600000),336000)) -> 311698.01 | V49: =P49+Q49+R49+S49+T49+U49 -> 535698.01 | W49: 12 | X49: =V49/W49 -> 44641.501 | Z49: =X49 -> 44641.501 | AA49: 28360.953 | AB49: =Z49-AA49 -> 16280.548
A50: 45 | B50: GUNAT NANSAK MARK | C50: 363165.33 | D50: 12 | E50: =C50*D50 -> 4357984 | G50: 252638.72 | I50: =E50-F50-G50-H50 -> 4105345.3 | J50: 200000 | K50: 0.2 | L50: =I50*K50 -> 821069.06 | M50: =J50+L50 -> 1021069.1 | N50: =F50+G50+H50+M50 -> 1273707.8 | O50: =E50-N50 -> 3084276.2 | P50: =IF(O50<300000,0.07*O50,21000) -> 21000 | Q50: =IF((O50-300000)<0,0,IF((O50-300000)<300000,0.11*(O50-300000),33000)) -> 33000 | R50: =IF((O50-600000)<0,0,IF((O50-600000)<500000,0.15*(O50-600000),75000)) -> 75000 | S50: =IF((O50-1100000)<0,0,IF((O50-1100000)<500000,0.19*(O50-1100000),95000)) -> 95000 | T50: =IF((O50-1600000)<0,0,IF((O50-1600000)<1600000,0.21*(O50-1600000),336000)) -> 311698.01 | V50: =P50+Q50+R50+S50+T50+U50 -> 535698.01 | W50: 12 | X50: =V50/W50 -> 44641.501 | Z50: =X50 -> 44641.501 | AA50: 29058.483 | AB50: =Z50-AA50 -> 15583.018
B52: LEGAL SERVICES
A53: 47 | B53: DR SHUAIBU DANWANKA | C53: 1635720 | D53: 12 | E53: =C53*D53 -> 19628640 | G53: 1378291.2 | I53: =E53-F53-G53-H53 -> 18250349 | J53: 200000 | K53: 0.2 | L53: =I53*K53 -> 3650069.8 | M53: =J53+L53 -> 3850069.8 | N53: =F53+G53+H53+M53 -> 5228361 | O53: =E53-N53 -> 14400279 | P53: =IF(O53<300000,0.07*O53,21000) -> 21000 | Q53: =IF((O53-300000)<0,0,IF((O53-300000)<300000,0.11*(O53-300000),33000)) -> 33000 | R53: =IF((O53-600000)<0,0,IF((O53-600000)<500000,0.15*(O53-600000),75000)) -> 75000 | S53: =IF((O53-1100000)<0,0,IF((O53-1100000)<500000,0.19*(O53-1100000),95000)) -> 95000 | T53: =IF((O53-1600000)<0,0,IF((O53-1600000)<1600000,0.21*(O53-1600000),336000)) -> 336000 | U53: =24%*(O53-3200000) -> 2688067 | V53: =P53+Q53+R53+S53+T53+U53 -> 3248067 | W53: 12 | X53: =V53/W53 -> 270672.25 | Z53: =X53 -> 270672.25 | AA53: 180306.81 | AB53: =Z53-AA53 -> 90365.441
A54: 48 | B54: ABDULSALAM BAKO | C54: 700675.58 | D54: 12 | E54: =C54*D54 -> 8408107 | G54: 595848.56 | I54: =E54-F54-G54-H54 -> 7812258.4 | J54: 200000 | K54: 0.2 | L54: =I54*K54 -> 1562451.7 | M54: =J54+L54 -> 1762451.7 | N54: =F54+G54+H54+M54 -> 2358300.2 | O54: =E54-N54 -> 6049806.8 | P54: =IF(O54<300000,0.07*O54,21000) -> 21000 | Q54: =IF((O54-300000)<0,0,IF((O54-300000)<300000,0.11*(O54-300000),33000)) -> 33000 | R54: =IF((O54-600000)<0,0,IF((O54-600000)<500000,0.15*(O54-600000),75000)) -> 75000 | S54: =IF((O54-1100000)<0,0,IF((O54-1100000)<500000,0.19*(O54-1100000),95000)) -> 95000 | T54: =IF((O54-1600000)<0,0,IF((O54-1600000)<1600000,0.21*(O54-1600000),336000)) -> 336000 | U54: =24%*(O54-3200000) -> 683953.62 | V54: =P54+Q54+R54+S54+T54+U54 -> 1243953.6 | W54: 12 | X54: =V54/W54 -> 103662.8 | Z54: =X54 -> 103662.8 | AA54: 64596.939 | AB54: =Z54-AA54 -> 39065.863
G55: 0
A56: 49 | B56: DEMOCRACY & GOVERNANCE | G56: 0
A57: 50 | B57: DR. ADEWALE ADEREMI | C57: 1635720 | D57: 12 | E57: =C57*D57 -> 19628640 | G57: 0 | I57: =E57-F57-G57-H57 -> 19628640 | J57: 200000 | K57: 0.2 | L57: =I57*K57 -> 3925728 | M57: =J57+L57 -> 4125728 | N57: =F57+G57+H57+M57 -> 4125728 | O57: =E57-N57 -> 15502912 | P57: =IF(O57<300000,0.07*O57,21000) -> 21000 | Q57: =IF((O57-300000)<0,0,IF((O57-300000)<300000,0.11*(O57-300000),33000)) -> 33000 | R57: =IF((O57-600000)<0,0,IF((O57-600000)<500000,0.15*(O57-600000),75000)) -> 75000 | S57: =IF((O57-1100000)<0,0,IF((O57-1100000)<500000,0.19*(O57-1100000),95000)) -> 95000 | T57: =IF((O57-1600000)<0,0,IF((O57-1600000)<1600000,0.21*(O57-1600000),336000)) -> 336000 | U57: =24%*(O57-3200000) -> 2952698.9 | V57: =P57+Q57+R57+S57+T57+U57 -> 3512698.9 | W57: 12 | X57: =V57/W57 -> 292724.91 | Z57: =X57 -> 292724.91 | AA57: 180306.81 | AB57: =Z57-AA57 -> 112418.1
A58: 51 | B58: NDANUSA MOHAMMED MANZUMA | C58: 761396.83 | D58: 12 | E58: =C58*D58 -> 9136762 | G58: =48111.7466666667*12 -> 577340.96 | I58: =E58-F58-G58-H58 -> 8559421 | J58: 200000 | K58: 0.2 | L58: =I58*K58 -> 1711884.2 | M58: =J58+L58 -> 1911884.2 | N58: =F58+G58+H58+M58 -> 2489225.2 | O58: =E58-N58 -> 6647536.8 | P58: =IF(O58<300000,0.07*O58,21000) -> 21000 | Q58: =IF((O58-300000)<0,0,IF((O58-300000)<300000,0.11*(O58-300000),33000)) -> 33000 | R58: =IF((O58-600000)<0,0,IF((O58-600000)<500000,0.15*(O58-600000),75000)) -> 75000 | S58: =IF((O58-1100000)<0,0,IF((O58-1100000)<500000,0.19*(O58-1100000),95000)) -> 95000 | T58: =IF((O58-1600000)<0,0,IF((O58-1600000)<1600000,0.21*(O58-1600000),336000)) -> 336000 | U58: =24%*(O58-3200000) -> 827408.84 | V58: =P58+Q58+R58+S58+T58+U58 -> 1387408.8 | W58: 12 | X58: =V58/W58 -> 115617.4 | Z58: =X58 -> 115617.4 | AA58: 77764.98 | AB58: =Z58-AA58 -> 37852.423
A59: 52 | B59: EJALONIBU GANIYU LAYI | C59: 582746.5 | D59: 12 | E59: =C59*D59 -> 6992958 | G59: 425036.64 | I59: =E59-F59-G59-H59 -> 6567921.4 | J59: 200000 | K59: 0.2 | L59: =I59*K59 -> 1313584.3 | M59: =J59+L59 -> 1513584.3 | N59: =F59+G59+H59+M59 -> 1938620.9 | O59: =E59-N59 -> 5054337.1 | P59: =IF(O59<300000,0.07*O59,21000) -> 21000 | Q59: =IF((O59-300000)<0,0,IF((O59-300000)<300000,0.11*(O59-300000),33000)) -> 33000 | R59: =IF((O59-600000)<0,0,IF((O59-600000)<500000,0.15*(O59-600000),75000)) -> 75000 | S59: =IF((O59-1100000)<0,0,IF((O59-1100000)<500000,0.19*(O59-1100000),95000)) -> 95000 | T59: =IF((O59-1600000)<0,0,IF((O59-1600000)<1600000,0.21*(O59-1600000),336000)) -> 336000 | U59: =24%*(O59-3200000) -> 445040.9 | V59: =P59+Q59+R59+S59+T59+U59 -> 1005040.9 | W59: 12 | X59: =V59/W59 -> 83753.408 | Z59: =X59 -> 83753.408 | AA59: 54931.249 | AB59: =Z59-AA59 -> 28822.159
A60: 53 | B60: LOHNA BONKAT JONATHAN | C60: 548915.92 | D60: 12 | E60: =C60*D60 -> 6586991 | G60: 411759.28 | I60: =E60-F60-G60-H60 -> 6175231.7 | J60: 200000 | K60: 0.2 | L60: =I60*K60 -> 1235046.3 | M60: =J60+L60 -> 1435046.3 | N60: =F60+G60+H60+M60 -> 1846805.6 | O60: =E60-N60 -> 4740185.4 | P60: =IF(O60<300000,0.07*O60,21000) -> 21000 | Q60: =IF((O60-300000)<0,0,IF((O60-300000)<300000,0.11*(O60-300000),33000)) -> 33000 | R60: =IF((O60-600000)<0,0,IF((O60-600000)<500000,0.15*(O60-600000),75000)) -> 75000 | S60: =IF((O60-1100000)<0,0,IF((O60-1100000)<500000,0.19*(O60-1100000),95000)) -> 95000 | T60: =IF((O60-1600000)<0,0,IF((O60-1600000)<1600000,0.21*(O60-1600000),336000)) -> 336000 | U60: =24%*(O60-3200000) -> 369644.49 | V60: =P60+Q60+R60+S60+T60+U60 -> 929644.49 | W60: 12 | X60: =V60/W60 -> 77470.374 | Z60: =X60 -> 77470.374 | AA60: 49548.776 | AB60: =Z60-AA60 -> 27921.598
