Workbook

Sheet JANUARY 2024
A1: NATIONAL INSTITUTE FOR LEGISLATIVE AND DEMOCRATIC STUDIES | H1: ='[1]FEB 08'!F8/'[1]FEB 08'!Q8 -> 0.3
A2: STAFF PAYROLL FOR THE MONTH OF JANUARY, 2024
E3: ='[1]FEB 08'!E11/'[1]FEB 08'!M11 -> #REF! | H3: ='[1]FEB 08'!F11/'[1]FEB 08'!Q11 -> #REF!
B4: STAFF NAME | C4: DESIGNATION | D4: GRADE LEVEL | E4: BASIC SALARY | F4: ALLCE/ AREARS | G4: RENT | H4: UTILITY | I4: DOMESTIC | J4: ENTERT. | K4: FURNIT. | L4: FUEL | M4: ALLOWANCE | N4: ALLOWANCE | O4: ALLCE | P4: ALLCE | Q4: DUTY ALLCE | R4: GROSS SALARY | S4: AUCTION | T4: COOP CONTR/SPEC SAVINGS | U4: COOP. LOAN RECOVERY | V4: NHF DED. | W4: PAYE | X4: TOTAL DEDUCTION | Y4: DECEMBER, 2023 | Z4: JANUARY, 2024
E5: N | G5: N | H5: N | I5: N | J5: N | K5: N | L5: N | M5: N | N5: N | O5: N | P5: N | Q5: N | R5: N | S5: N | T5: N | U5: N | V5: N | W5: N | X5: N | Y5: N | Z5: N
A6: S/N | B6: DG'S OFFICE
A7: 1 | B7: PROF. ABUBAKAR O. SULAIMAN | C7: DIRECTOR GENERAL | D7: CONSOL | E7: 160488.75 | G7: 320977.5 | H7: 48146.63 | I7: 120366.57 | J7: 72219.94 | K7: 0 | L7: 120366.57 | M7: =250000 -> 250000 | O7: 16048.88 | P7: 25000 | Q7: 25235 | R7: =Q7+P7+O7+N7+M7+L7+K7+J7+I7+H7+G7+F7+E7 -> 1158849.8 | W7: 201165.84 | X7: =W7+V7+U7+T7+S7 -> 201165.84 | Y7: 957684 | Z7: =R7-X7 -> 957684
A8: 2 | B8: RAHEEM USMAN AYIGORO | C8: SA-INFRASTRUCTURE | D8: 16 (9) | E8: =42653.17 -> 42653.17 | G8: =E8*300% -> 127959.51 | H8: =E8*7.5% -> 3198.9877 | I8: 40122.19 | J8: =E8*50% -> 21326.585 | K8: =E8*350% -> 149286.1 | L8: =E8*100% -> 42653.17 | N8: =90000 -> 90000 | O8: =E8*10% -> 4265.317 | P8: 20000 | Q8: 0 | R8: =Q8+P8+O8+N8+M8+L8+K8+J8+I8+H8+G8+F8+E8 -> 541465.02 | T8: =100000 -> 100000 | W8: 82627.951 | X8: =W8+V8+U8+T8+S8 -> 182627.95 | Y8: 358837.07 | Z8: =R8-X8 -> 358837.07
A9: 3 | B9: MARIAM MOHAMMED BELLO | C9: SA- SPECIAL DUTIES | D9: 16 (9) | E9: =42653.17 -> 42653.17 | G9: =E9*300% -> 127959.51 | H9: =E9*7.5% -> 3198.9877 | I9: 40122.19 | J9: =E9*50% -> 21326.585 | K9: =E9*350% -> 149286.1 | L9: =E9*100% -> 42653.17 | N9: =90000 -> 90000 | O9: =E9*10% -> 4265.317 | P9: 20000 | Q9: =100000+100000 -> 200000 | R9: =Q9+P9+O9+N9+M9+L9+K9+J9+I9+H9+G9+F9+E9 -> 741465.02 | W9: 121027.95 | X9: =W9+V9+U9+T9+S9 -> 121027.95 | Y9: 609350.49 | Z9: =R9-X9 -> 620437.07
A10: 4 | B10: DR IKEME ARTHUR J.O | C10: DEPUTY DIRECTOR, M&E | D10: 16 (9) | E10: =42653.17 -> 42653.17 | G10: =E10*300% -> 127959.51 | H10: =E10*7.5% -> 3198.9877 | I10: 40122.19 | J10: =E10*50% -> 21326.585 | K10: =E10*350% -> 149286.1 | L10: =E10*100% -> 42653.17 | M10: 180000 | O10: =E10*10% -> 4265.317 | P10: 20000 | Q10: 0 | R10: =Q10+P10+O10+N10+M10+L10+K10+J10+I10+H10+G10+F10+E10 -> 631465.02 | T10: =50000 -> 50000 | U10: 103000 | V10: =0.025*E10 -> 1066.3293 | W10: 99703.216 | X10: =W10+V10+U10+T10+S10 -> 253769.55 | Y10: 469602.37 | Z10: =R10-X10 -> 377695.48
A11: 5 | B11: MOSHOOD M. OLALERE | C11: DEPUTY DIR. GENERAL SERVICE | D11: 16 (9) | E11: =42653.17 -> 42653.17 | G11: =E11*300% -> 127959.51 | H11: =E11*7.5% -> 3198.9877 | I11: 40122.19 | J11: =E11*50% -> 21326.585 | K11: =E11*350% -> 149286.1 | L11: =E11*100% -> 42653.17 | N11: =80000+10000 -> 90000 | O11: =E11*10% -> 4265.317 | P11: 20000 | Q11: 150000 | R11: =Q11+P11+O11+N11+M11+L11+K11+J11+I11+H11+G11+F11+E11 -> 691465.02 | T11: =20000+60000 -> 80000 | U11: ='[2]OCTOBER 2023 '!$D$193 -> 230499.8 | V11: =0.025*E11 -> 1066.3293 | W11: 111223.22 | X11: =W11+V11+U11+T11+S11 -> 422789.35 | Y11: 257582.57 | Z11: =R11-X11 -> 268675.68
A12: 6 | B12: REKIYA IBRAHIM ATTAH | C12: DEPUTY DIRECTOR TRAINING | D12: 16 (9) | E12: =42653.17 -> 42653.17 | G12: =E12*300% -> 127959.51 | H12: =E12*7.5% -> 3198.9877 | I12: 40122.19 | J12: =E12*50% -> 21326.585 | K12: =E12*350% -> 149286.1 | L12: =E12*100% -> 42653.17 | N12: =90000 -> 90000 | O12: =E12*10% -> 4265.317 | P12: 20000 | Q12: 100000 | R12: =SUM(E12:Q12) -> 641465.02 | T12: =50000 -> 50000 | U12: =91666.67 -> 91666.67 | W12: 101827.95 | X12: =W12+V12+U12+T12+S12 -> 243494.62 | Y12: 386883.82 | Z12: =R12-X12 -> 397970.4
A13: 7 | B13: ANDRAWUS MUSA | C13: ASST. DIRECTOR, STORES | D13: 15(9) | E13: 33507.5 | G13: =E13*300% -> 100522.5 | H13: =E13*7.5% -> 2513.0625 | I13: =40122.19 -> 40122.19 | J13: =E13*50% -> 16753.75 | K13: =E13*350% -> 117276.25 | L13: =E13*100% -> 33507.5 | N13: =80000 -> 80000 | O13: =E13*10% -> 3350.75 | P13: 20000 | Q13: 50000 | R13: =Q13+P13+O13+N13+M13+L13+K13+J13+I13+H13+G13+F13+E13 -> 497553.5 | T13: =50000-40000 -> 10000 | U13: =90000+110000 -> 200000 | V13: =0.025*E13 -> 837.6875 | W13: 74036.103 | X13: =W13+V13+U13+T13+S13 -> 284873.79 | Y13: 212679.72 | Z13: =R13-X13 -> 212679.71
A14: 8 | B14: DR FRANCIS NDUM OJIE | C14: AD, TRAINING & IC./SA TO DG | D14: 15(7) | E14: 31019.84 | G14: =E14*300% -> 93059.52 | H14: =E14*7.5% -> 2326.488 | I14: =40122.19 -> 40122.19 | J14: =E14*50% -> 15509.92 | K14: =E14*350% -> 108569.44 | L14: =E14*100% -> 31019.84 | M14: 160000 | O14: =E14*10% -> 3101.984 | P14: 20000 | Q14: =100000 -> 100000 | R14: =SUM(E14:Q14) -> 604729.22 | V14: =0.025*E14 -> 775.496 | W14: 94625.782 | X14: =W14+V14+U14+T14+S14 -> 95401.278 | Y14: 509246.91 | Z14: =R14-X14 -> 509327.94
A15: 9 | B15: ALI ABDULLAHI | C15: CHIEF ICT OFFICER | D15: 14(11) | E15: 27611.23 | G15: =E15*300% -> 82833.69 | H15: =E15*7.5% -> 2070.8422 | I15: 0 | J15: =E15*50% -> 13805.615 | K15: =E15*350% -> 96639.305 | L15: =E15*100% -> 27611.23 | N15: =70000 -> 70000 | O15: =E15*10% -> 2761.123 | P15: 20000 | Q15: =0 -> 0 | R15: =Q15+P15+O15+N15+M15+L15+K15+J15+I15+H15+G15+F15+E15 -> 343333.04 | W15: 44846.617 | X15: =W15+V15+U15+T15+S15 -> 44846.617 | Y15: 298486.42 | Z15: =R15-X15 -> 298486.42
A16: 10 | B16: EMILY EKHIDE | C16: RESEARCH FELLOW 1 | D16: 14(10) | E16: 27611.23 | G16: =E16*300% -> 82833.69 | H16: =E16*7.5% -> 2070.8422 | I16: 0 | J16: =E16*50% -> 13805.615 | K16: =E16*350% -> 96639.305 | L16: =E16*100% -> 27611.23 | M16: 140000 | O16: =E16*10% -> 2761.123 | P16: 20000 | Q16: 50000 | R16: =SUM(E16:Q16) -> 463333.04 | T16: =50000 -> 50000 | W16: 46666.667 | X16: =W16+V16+U16+T16+S16 -> 96666.667 | Y16: 339193.16 | Z16: =R16-X16 -> 366666.37
A17: 11 | B17: DORIS DAKDA AARON | C17: RESEARCH FELLOW I | D17: 14(8) | E17: ='[3]December 2022'!$E$126 -> 25854.1 | G17: =E17*300% -> 77562.3 | H17: =E17*7.5% -> 1939.0575 | J17: =E17*50% -> 12927.05 | K17: =E17*350% -> 90489.35 | L17: =E17*100% -> 25854.1 | M17: =140000 -> 140000 | O17: =E17*10% -> 2585.41 | P17: 20000 | Q17: 150000 | R17: =SUM(E17:Q17) -> 547211.37 | T17: 70000 | W17: 46666.667 | X17: =W17+V17+U17+T17+S17 -> 116666.67 | Y17: 321708.62 | Z17: =R17-X17 -> 430544.7
A18: 12 | B18: ABDULSALAM S. MUSTAPHA | C18: ASST. MANAGER ICT | D18: 13(11) | E18: 26339.3 | G18: =E18*300% -> 79017.9 | H18: =E18*7.5% -> 1975.4475 | I18: 0 | J18: =E18*50% -> 13169.65 | K18: =E18*350% -> 92187.55 | L18: =E18*100% -> 26339.3 | N18: 70000 | O18: =E18*10% -> 2633.93 | P18: 15000 | R18: =SUM(E18:Q18) -> 326663.08 | W18: 42046.064 | X18: =42046.06 -> 42046.06 | Y18: 284617.02 | Z18: =R18-X18 -> 284617.02
A19: 13 | B19: PERCY TERFA GBAHABO | C19: HEAD, NILDS LIAISON OFFICE | D19: 13(10) | E19: =25523.45 -> 25523.45 | G19: =E19*300% -> 76570.35 | H19: =E19*7.5% -> 1914.2587 | I19: 0 | J19: =E19*50% -> 12761.725 | K19: =E19*350% -> 89332.075 | L19: =E19*100% -> 25523.45 | M19: =120000 -> 120000 | O19: =E19*10% -> 2552.345 | P19: 15000 | Q19: 0 | R19: =Q19+P19+O19+N19+M19+L19+K19+J19+I19+H19+G19+F19+E19 -> 369177.65 | T19: =50000 -> 50000 | U19: 0 | W19: 46666.667 | X19: =W19+V19+U19+T19+S19 -> 96666.667 | Y19: 265334.39 | Z19: =R19-X19 -> 272510.99
A20: 14 | B20: HASSANA AHMED IBRAHIM | C20: PA- TO DG | D20: 13 (9) | E20: 24741.26 | G20: =E20*300% -> 74223.78 | H20: =E20*7.5% -> 1855.5945 | J20: =E20*50% -> 12370.63 | K20: =E20*350% -> 86594.41 | L20: =E20*100% -> 24741.26 | M20: =120000 -> 120000 | O20: =E20*10% -> 2474.126 | P20: 15000 | Q20: =100000 -> 100000 | R20: =Q20+P20+O20+N20+M20+L20+K20+J20+I20+H20+G20+F20+E20 -> 462001.06 | T20: =30000-20000 -> 10000 | U20: =95833.33 -> 95833.33 | V20: =0.025*E20 -> 618.5315 | W20: 46666.667 | X20: =W20+V20+U20+T20+S20 -> 153118.53 | Y20: 281897.16 | Z20: =R20-X20 -> 308882.53
A21: 15 | B21: ADUGBA RICHARD TERSEER | C21: PRINCIPAL INFO. OFFICER | D21: 12(9) | E21: =22837.82 -> 22837.82 | G21: =E21*300% -> 68513.46 | H21: =E21*7.5% -> 1712.8365 | J21: =E21*50% -> 11418.91 | K21: =E21*350% -> 79932.37 | L21: =E21*100% -> 22837.82 | N21: =60000 -> 60000 | O21: =E21*10% -> 2283.782 | P21: 15000 | Q21: 100000 | R21: =Q21+P21+O21+N21+M21+L21+K21+J21+I21+H21+G21+F21+E21 -> 384537 | T21: =20000 -> 20000 | U21: =111833.33 -> 111833.33 | W21: 52497.77 | X21: =W21+V21+U21+T21+S21 -> 184331.1 | Y21: 193954.07 | Z21: =R21-X21 -> 200205.9
A22: 16 | B22: LUCKY AGWOM | C22: RESEARCH ASSISTANT | D22: 12(7) | E22: =20749 -> 20749 | G22: =E22*300% -> 62247 | H22: =E22*7.5% -> 1556.175 | J22: =E22*50% -> 10374.5 | K22: =E22*350% -> 72621.5 | L22: =E22*100% -> 20749 | M22: =100000 -> 100000 | O22: =E22*10% -> 2074.9 | P22: 10000 | Q22: 100000 | R22: =SUM(E22:Q22) -> 400372.08 | T22: 52000 | W22: 46666.667 | X22: =W22+V22+U22+T22+S22 -> 98666.667 | Y22: 344833.97 | Z22: =R22-X22 -> 301705.41
A23: 17 | B23: IDRIS IBRAHIM | C23: PRINCIPAL RESEARCH OFFICER | D23: 12(7) | E23: 20749 | F23: =700000 -> 700000 | G23: 62247 | H23: 1556.175 | I23: 0 | J23: 10374.5 | K23: 72621.5 | L23: 20749 | M23: 110000 | O23: 2074.9 | P23: 15000 | Q23: 0 | R23: =SUM(E23:Q23) -> 1015372.1 | T23: 0 | W23: 46666.667 | X23: =W23+V23+U23+T23+S23 -> 46666.667 | Z23: =R23-X23 -> 968705.41
A24: 18 | B24: FARUQ ATOFARATI | C24: PA (SPECIAL DUTIES) TO DG | D24: 10(7) | E24: =17286.33 -> 17286.33 | G24: =E24*300% -> 51858.99 | H24: =E24*7.5% -> 1296.4748 | J24: =E24*50% -> 8643.165 | K24: =E24*350% -> 60502.155 | L24: =E24*100% -> 17286.33 | N24: =50000+10000 -> 60000 | O24: =E24*10% -> 1728.633 | P24: 10000 | Q24: 100000 | R24: =SUM(E24:Q24) -> 328602.08 | W24: 42371.816 | X24: =W24+V24+U24+T24+S24 -> 42371.816 | Y24: 286230.26 | Z24: =R24-X24 -> 286230.26
A25: 19 | B25: ELIZABETH OGECHUKWU ONYEAKU | C25: ICT OFFICER | D25: 9(9) | E25: 15641.2 | G25: =E25*300% -> 46923.6 | H25: =E25*7.5% -> 1173.09 | J25: =E25*50% -> 7820.6 | K25: =E25*350% -> 54744.2 | L25: =E25*100% -> 15641.2 | N25: =50000+10000 -> 60000 | O25: =E25*10% -> 1564.12 | P25: 10000 | R25: =Q25+P25+O25+N25+M25+L25+K25+J25+I25+H25+G25+F25+E25 -> 213508.01 | T25: 10000 | U25: =20000 -> 20000 | W25: 23036.012 | X25: =W25+V25+U25+T25+S25 -> 53036.012 | Y25: 153563.13 | Z25: =R25-X25 -> 160472
A26: 20 | B26: VICTOR ASUKWO | C26: ICT OFFICER | D26: 9(9) | E26: 15641.2 | G26: =E26*300% -> 46923.6 | H26: =E26*7.5% -> 1173.09 | J26: =E26*50% -> 7820.6 | K26: =E26*350% -> 54744.2 | L26: =E26*100% -> 15641.2 | N26: =50000+10000 -> 60000 | O26: =E26*10% -> 1564.12 | P26: 10000 | R26: =Q26+P26+O26+N26+M26+L26+K26+J26+I26+H26+G26+F26+E26 -> 213508.01 | W26: 23036.012 | X26: =W26+V26+U26+T26+S26 -> 23036.012 | Y26: 187017.56 | Z26: =R26-X26 -> 190472
A27: 21 | B27: NNANDI LIVINUS ATURE | C27: RESEARCH ASSISTANT | D27: 9(9) | E27: 15641.2 | G27: =E27*300% -> 46923.6 | H27: =E27*7.5% -> 1173.09 | J27: =E27*50% -> 7820.6 | K27: =E27*350% -> 54744.2 | L27: =E27*100% -> 15641.2 | M27: =100000 -> 100000 | O27: =E27*10% -> 1564.12 | P27: 10000 | R27: =SUM(E27:Q27) -> 253508.01 | T27: =10000 -> 10000 | U27: =95833.33 -> 95833.33 | W27: 29756.012 | X27: =W27+V27+U27+T27+S27 -> 135589.34 | Y27: 114464.23 | Z27: =R27-X27 -> 117918.67
A28: 22 | B28: ABDULRAHMAN A SULAIMAN | C28: STORE OFFICER | D28: 9(8) | E28: =15188.67 -> 15188.67 | G28: =E28*300% -> 45566.01 | H28: =E28*7.5% -> 1139.1502 | J28: =E28*50% -> 7594.335 | K28: =E28*350% -> 53160.345 | L28: =E28*100% -> 15188.67 | N28: =60000 -> 60000 | O28: =E28*10% -> 1518.867 | P28: 10000 | R28: =SUM(E28:Q28) -> 209356.05 | T28: =20000 -> 20000 | U28: =17500 -> 17500 | W28: 22338.483 | X28: =W28+V28+U28+T28+S28 -> 59838.483 | Y28: 146063.2 | Z28: =R28-X28 -> 149517.56
A29: 23 | B29: DARE SHEU MAGBON | C29: ADMINISTRATION OFFICER | D29: 9(7) | E29: =14736.14 -> 14736.14 | G29: =E29*300% -> 44208.42 | H29: =E29*7.5% -> 1105.2105 | J29: =E29*50% -> 7368.07 | K29: =E29*350% -> 51576.49 | L29: =E29*100% -> 14736.14 | N29: =60000 -> 60000 | O29: =E29*10% -> 1473.614 | P29: 10000 | R29: =SUM(E29:Q29) -> 205204.08 | T29: =30000+20000 -> 50000 | U29: 0 | W29: 21640.953 | X29: =W29+V29+U29+T29+S29 -> 71640.953 | Y29: 138329.89 | Z29: =R29-X29 -> 133563.13
A30: 24 | B30: ABUBAKAR SULAIMAN SODEEQ | C30: ADMINISTRATION OFFICER | D30: 9(7) | E30: =14736.14 -> 14736.14 | G30: =E30*300% -> 44208.42 | H30: =E30*7.5% -> 1105.2105 | J30: =E30*50% -> 7368.07 | K30: =E30*350% -> 51576.49 | L30: =E30*100% -> 14736.14 | N30: =60000 -> 60000 | O30: =E30*10% -> 1473.614 | P30: 10000 | R30: =SUM(E30:Q30) -> 205204.08 | U30: 0 | W30: 21640.953 | X30: =W30+V30+U30+T30+S30 -> 21640.953 | Y30: 159773.23 | Z30: =R30-X30 -> 183563.13
A31: 25 | B31: JIMOH ADEBAYO ZAKA | C31: ASST. OFFICER/COMM | D31: 9(8) | E31: 15188.67 | G31: =E31*300% -> 45566.01 | H31: =E31*7.5% -> 1139.1502 | J31: =E31*50% -> 7594.335 | K31: =E31*350% -> 53160.345 | L31: =E31*100% -> 15188.67 | N31: =60000 -> 60000 | O31: =E31*10% -> 1518.867 | P31: 10000 | R31: =Q31+P31+O31+N31+M31+L31+K31+J31+I31+H31+G31+F31+E31 -> 209356.05 | T31: =50000 -> 50000 | U31: 50000 | W31: 22338.483 | X31: =W31+V31+U31+T31+S31 -> 122338.48 | Y31: 87017.565 | Z31: =R31-X31 -> 87017.565
A32: 26 | B32: MOHAMMED BELLO | C32: PROTOCOL ASSISTANT | D32: 8(9) | E32: 13112.16 | G32: =E32*300% -> 39336.48 | H32: =E32*7.5% -> 983.412 | J32: =E32*50% -> 6556.08 | K32: =E32*350% -> 45892.56 | L32: =E32*100% -> 13112.16 | N32: =50000 -> 50000 | O32: =E32*10% -> 1311.216 | P32: 10000 | R32: =SUM(E32:Q32) -> 180304.07 | T32: =0 -> 0 | U32: =26666.67 -> 26666.67 | W32: 17572.885 | X32: =W32+V32+U32+T32+S32 -> 44239.555 | Y32: 133106.72 | Z32: =R32-X32 -> 136064.51
A33: 27 | B33: HARUNA JIBRIL AMEH | C33: ASST. ADMIN. OFFICER | D33: 8(8) | E33: =12732 -> 12732 | G33: 37055.82 | H33: 926.3955 | J33: 6175.97 | K33: 43231.79 | L33: 12351.94 | N33: 50000 | O33: 1235.194 | P33: 10000 | R33: 173329.05 | T33: 20000 | U33: 0 | W33: 16512.682 | X33: =W33+V33+U33+T33+S33 -> 36512.682 | Y33: 136816.37 | Z33: =R33-X33 -> 136816.37
B34: TOTAL | C34: 27 | E34: =SUM(E7:E33) -> 810202.04 | F34: =SUM(F7:F33) -> 700000 | G34: =SUM(G7:G33) -> 2268977.2 | H34: =SUM(H7:H33) -> 96846.622 | I34: =SUM(I7:I33) -> 401221.9 | J34: =SUM(J7:J33) -> 396886.55 | K34: =SUM(K7:K33) -> 2272666.3 | L34: =SUM(L7:L33) -> 769699.8 | ... X34: =SUM(X7:X33) -> 3295070.2 | Y34: 7198101.1 | Z34: =SUM(Z7:Z33) -> 8717267.3
B36: INTERNAL AUDIT
A37: 1 | B37: OSANAIYE DAVID AKINYEMI | C37: DIRECTOR INTERNAL AUDIT | D37: 17(9) | E37: 81740.02 | G37: =E37*300% -> 245220.06 | H37: =E37*7.5% -> 6130.5015 | I37: 80244.38 | J37: =E37*50% -> 40870.01 | K37: =E37*350% -> 286090.07 | L37: =E37*100% -> 81740.02 | N37: =100000 -> 100000 | O37: =E37*10% -> 8174.002 | P37: 20000 | R37: =SUM(E37:Q37) -> 950209.06 | S37: ='JANUARY 2024'!F196 -> 0 | T37: 200000 | U37: 0 | W37: 161106.81 | X37: =W37+V37+U37+T37+S37 -> 361106.81 | Y37: 689102.26 | Z37: =R37-X37 -> 589102.26
A38: 2 | B38: JAMILA ABDUL | C38: AUDITOR II | D38: 8(8) | E38: =12732 -> 12732 | G38: =E38*300% -> 38196 | H38: =E38*7.5% -> 954.9 | J38: =E38*50% -> 6366 | K38: =E38*350% -> 44562 | L38: =E38*100% -> 12732 | N38: =50000 -> 50000 | O38: =E38*10% -> 1273.2 | P38: 10000 | R38: =(Q38+P38+O38+N38+M38+L38+K38+J38+I38+H38+G38+F38+E38) -> 176816.1 | T38: =20000 -> 20000 | V38: 0 | W38: 17042.714 | X38: =W38+V38+U38+T38+S38 -> 37042.714 | Y38: 136816.37 | Z38: =R38-X38 -> 139773.39
A39: 3 | B39: IJEOMA EWELUKWA | C39: AUDIT OFFICER | D39: 10(8) | E39: 17784.1 | G39: =E39*300% -> 53352.3 | H39: =E39*7.5% -> 1333.8075 | J39: =E39*50% -> 8892.05 | K39: =E39*350% -> 62244.35 | L39: =E39*100% -> 17784.1 | N39: =50000+10000 -> 60000 | O39: =E39*10% -> 1778.41 | P39: 10000 | R39: =SUM(E39:Q39) -> 233169.12 | T39: =10000 -> 10000 | W39: 26339.078 | X39: =W39+V39+U39+T39+S39 -> 36339.078 | Y39: 193030.35 | Z39: =R39-X39 -> 196830.04
C40: 3 | E40: =SUM(E37:E39) -> 112256.12 | F40: =SUM(F37:F39) -> 0 | G40: =SUM(G37:G39) -> 336768.36 | H40: =SUM(H37:H39) -> 8419.209 | I40: =SUM(I37:I39) -> 80244.38 | J40: =SUM(J37:J39) -> 56128.06 | K40: =SUM(K37:K39) -> 392896.42 | L40: =SUM(L37:L39) -> 112256.12 | ... X40: =SUM(X37:X39) -> 434488.6 | Y40: 1018949 | Z40: =SUM(Z37:Z39) -> 925705.68
B42: LEG. SUPPORT SEVICES
A43: 1 | B43: PROF. EDOBA BRIGHT OMOREGBE | C43: AG. DLSS | D43: 17(9) | E43: 81740.02 | G43: =E43*300% -> 245220.06 | H43: =E43*7.5% -> 6130.5015 | I43: 80244.38 | J43: =E43*50% -> 40870.01 | K43: =E43*350% -> 286090.07 | L43: =E43*100% -> 81740.02 | M43: =200000 -> 200000 | O43: =E43*10% -> 8174.002 | P43: 20000 | R43: =SUM(E43:Q43) -> 1050209.1 | T43: =200000 -> 200000 | U43: =380000 -> 380000 | W43: 180306.81 | X43: =W43+V43+U43+T43+S43 -> 760306.81 | Y43: 289902.26 | Z43: =R43-X43 -> 289902.26
A44: 2 | B44: DR CLINTON JAJA | C44: SENIOR RESEARCH FELLOW | D44: 15(9) | E44: 33507.5 | G44: =E44*300% -> 100522.5 | H44: =E44*7.5% -> 2513.0625 | I44: 40122.19 | J44: =E44*50% -> 16753.75 | K44: =E44*350% -> 117276.25 | L44: =E44*100% -> 33507.5 | M44: =160000 -> 160000 | O44: =E44*10% -> 3350.75 | P44: 20000 | Q44: 0 | R44: =SUM(E44:Q44) -> 527553.5 | T44: =50000 -> 50000 | U44: =385000 -> 385000 | W44: 79956.939 | X44: =W44+V44+U44+T44+S44 -> 514956.94 | Y44: -67360.376 | Z44: =R44-X44 -> 12596.563
A45: 3 | B45: BETHEL UZOMA IHUGBA | C45: DEPUTY DIRECTOR, LEGAL RESEARCH | D45: 16(8) | E45: 41157.69 | G45: =E45*300% -> 123473.07 | H45: =E45*7.5% -> 3086.8268 | I45: 40122.19 | J45: =E45*50% -> 20578.845 | K45: =E45*350% -> 144051.92 | L45: =E45*100% -> 41157.69 | M45: =180000 -> 180000 | O45: =E45*10% -> 4115.769 | P45: 20000 | R45: =SUM(E45:Q45) -> 617744 | T45: =80000+23000 -> 103000 | U45: =246905.96 -> 246905.96 | W45: 97273.514 | X45: =W45+V45+U45+T45+S45 -> 447179.47 | Y45: 715566.8 | Z45: =R45-X45 -> 170564.52
A46: 4 | B46: OGUCHE SAMUEL | C46: SNR RESEARCH FELLOW | D46: 15(9) | E46: 33507.5 | G46: =E46*300% -> 100522.5 | H46: =E46*7.5% -> 2513.0625 | I46: 40122.19 | J46: =E46*50% -> 16753.75 | K46: =E46*350% -> 117276.25 | L46: =E46*100% -> 33507.5 | M46: =160000 -> 160000 | O46: =E46*10% -> 3350.75 | P46: 20000 | R46: =SUM(E46:Q46) -> 527553.5 | T46: =30000 -> 30000 | U46: =176288.88 -> 176288.88 | W46: 79956.939 | X46: =W46+V46+U46+T46+S46 -> 286245.82 | Y46: 241307.68 | Z46: =R46-X46 -> 241307.68
A47: 5 | B47: IBRAHIM USMAN | C47: SNR RESEARCH FELLOW | D47: 15(9) | E47: 33507.5 | G47: =E47*300% -> 100522.5 | H47: =E47*7.5% -> 2513.0625 | I47: =40122.19 -> 40122.19 | J47: =E47*50% -> 16753.75 | K47: =E47*350% -> 117276.25 | L47: =E47*100% -> 33507.5 | M47: =140000+20000 -> 160000 | O47: =E47*10% -> 3350.75 | P47: 20000 | Q47: 0 | R47: =SUM(E47:Q47) -> 527553.5 | V47: =0.025*E47 -> 837.6875 | W47: 79796.103 | X47: =W47+V47+U47+T47+S47 -> 80633.791 | Y47: 437565.49 | Z47: =R47-X47 -> 446919.71
A48: 6 | B48: DR MOHAMMED O. AMALI | C48: SNR RESEARCH FELLOW | D48: 15(7) | E48: =31018.84 -> 31018.84 | G48: =E48*300% -> 93056.52 | H48: =E48*7.5% -> 2326.413 | I48: =40122.19 -> 40122.19 | J48: =E48*50% -> 15509.42 | K48: =E48*350% -> 108565.94 | L48: =E48*100% -> 31018.84 | M48: =140000+20000 -> 160000 | O48: =E48*10% -> 3101.884 | P48: 20000 | R48: =SUM(E48:Q48) -> 504720.05 | T48: =15000 -> 15000 | U48: =216666.67 -> 216666.67 | W48: 75572.916 | X48: =W48+V48+U48+T48+S48 -> 307239.59 | Y48: 197617.21 | Z48: =R48-X48 -> 197480.46
A49: 7 | B49: YAHAYA SHAMSU | C49: RESEARCH FELLOW 1 | D49: 14(10) | E49: 27611.23 | G49: =E49*300% -> 82833.69 | H49: =E49*7.5% -> 2070.8422 | J49: =E49*50% -> 13805.615 | K49: =E49*350% -> 96639.305 | L49: =E49*100% -> 27611.23 | M49: =140000 -> 140000 | O49: =E49*10% -> 2761.123 | P49: 20000 | R49: =SUM(E49:Q49) -> 413333.04 | V49: 0 | W49: 58026.609 | X49: =W49+V49+U49+T49+S49 -> 58026.609 | Y49: 355306.43 | Z49: =R49-X49 -> 355306.43
A50: 8 | B50: BILKIS S. LAWAL-GAMBARI | C50: RESEARCH OFFICER | D50: 10(8) | E50: 17784.1 | G50: =E50*300% -> 53352.3 | H50: =E50*7.5% -> 1333.8075 | J50: =E50*50% -> 8892.05 | K50: =E50*350% -> 62244.35 | L50: =E50*100% -> 17784.1 | M50: 100000 | O50: =E50*10% -> 1778.41 | P50: 10000 | R50: =SUM(E50:Q50) -> 273169.12 | W50: 33059.078 | X50: =W50+V50+U50+T50+S50 -> 33059.078 | Y50: 236310.26 | Z50: =R50-X50 -> 240110.04
A51: 9 | B51: ZAINAB AKINDE | C51: RESEARCH OFFICER | D51: 9(8) | E51: 15188.67 | G51: =E51*300% -> 45566.01 | H51: =E51*7.5% -> 1139.1502 | J51: =E51*50% -> 7594.335 | K51: =E51*350% -> 53160.345 | L51: =E51*100% -> 15188.67 | M51: =100000 -> 100000 | O51: =E51*10% -> 1518.867 | P51: 10000 | R51: =SUM(E51:Q51) -> 249356.05 | W51: 29058.483 | X51: =W51+V51+U51+T51+S51 -> 29058.483 | Y51: 216843.13 | Z51: =R51-X51 -> 220297.56
A52: 10 | B52: ABDULLAHI AHMAD USMAN | C52: RESEARCH OFFICER | D52: 9(8) | E52: 15188.67 | G52: =E52*300% -> 45566.01 | H52: =E52*7.5% -> 1139.1502 | J52: =E52*50% -> 7594.335 | K52: =E52*350% -> 53160.345 | L52: =E52*100% -> 15188.67 | M52: =100000 -> 100000 | O52: =E52*10% -> 1518.867 | P52: 10000 | R52: =SUM(E52:Q52) -> 249356.05 | W52: 28360.953 | X52: =W52+V52+U52+T52+S52 -> 28360.953 | Y52: 216843.13 | Z52: =R52-X52 -> 220995.09
A53: 11 | B53: GUNAT NANSAK MARK | C53: RESEARCH OFFICER | D53: 9(8) | E53: 15188.67 | G53: =E53*300% -> 45566.01 | H53: =E53*7.5% -> 1139.1502 | J53: =E53*50% -> 7594.335 | K53: =E53*350% -> 53160.345 | L53: =E53*100% -> 15188.67 | M53: =100000 -> 100000 | O53: =E53*10% -> 1518.867 | P53: 10000 | R53: =SUM(E53:Q53) -> 249356.05 | W53: 29058.483 | X53: =W53+V53+U53+T53+S53 -> 29058.483 | Y53: 216843.13 | Z53: =R53-X53 -> 220297.56
B54: TOTAL | C54: 11 | E54: =SUM(E43:E53) -> 345400.39 | F54: =SUM(F43:F53) -> 0 | G54: =SUM(G43:G53) -> 1036201.2 | H54: =SUM(H43:H53) -> 25905.029 | I54: =SUM(I43:I53) -> 280855.33 | J54: =SUM(J43:J53) -> 172700.19 | K54: =SUM(K43:K53) -> 1208901.4 | L54: =SUM(L43:L53) -> 345400.39 | ... X54: =SUM(X43:X53) -> 2574126 | Y54: 3378453.8 | Z54: =SUM(Z43:Z53) -> 2615777.9
B56: LEGAL SERVICES
A57: 1 | B57: DR SHUIBU DANWANKA | C57: DIRECTOR LEGAL SERVICES | D57: 17(9) | E57: 81740.02 | G57: =E57*300% -> 245220.06 | H57: =E57*7.5% -> 6130.5015 | I57: 80244.38 | J57: =E57*50% -> 40870.01 | K57: =E57*350% -> 286090.07 | L57: =E57*100% -> 81740.02 | M57: =200000 -> 200000 | O57: =E57*10% -> 8174.002 | P57: 20000 | Q57: 0 | R57: =SUM(E57:Q57) -> 1050209.1 | T57: 120000 | U57: 120000 | V57: 0 | W57: 180306.81 | X57: =W57+V57+U57+T57+S57 -> 420306.81 | Y57: 629902.26 | Z57: =R57-X57 -> 629902.26
A58: 2 | B58: ABDULSALAM BAKO | C58: MANAGER, LEGAL SERVICES | D58: 15 (9) | E58: 33507.5 | G58: =E58*300% -> 100522.5 | H58: =E58*7.5% -> 2513.0625 | I58: 40122.19 | J58: =E58*50% -> 16753.75 | K58: =E58*350% -> 117276.25 | L58: =E58*100% -> 33507.5 | N58: 80000 | O58: =E58*10% -> 3350.75 | P58: 20000 | R58: =SUM(E58:Q58) -> 447553.5 | T58: 50000 | U58: 145000 | V58: 0 | W58: 64596.939 | X58: 257404.98 | Y58: 178732.07 | Z58: 178732.07
B59: TOTAL | C59: 2 | E59: =SUM(E57:E58) -> 115247.52 | G59: =SUM(G57:G58) -> 345742.56 | H59: =SUM(H57:H58) -> 8643.564 | I59: =SUM(I57:I58) -> 120366.57 | J59: =SUM(J57:J58) -> 57623.76 | K59: =SUM(K57:K58) -> 403366.32 | L59: =SUM(L57:L58) -> 115247.52 | M59: =SUM(M57:M58) -> 200000 | N59: =SUM(N57:N58) -> 80000 | ... X59: =SUM(X57:X58) -> 677711.79 | Y59: 808634.33 | Z59: =SUM(Z57:Z58) -> 808634.33
B61: DEMOCRACY & GOVERNANCE
A62: 1 | B62: DR. ADEWALE ADEREMI | C62: DIRECTOR, DEMOCRATIC STUDIES | D62: 17(9) | E62: 81740.02 | G62: =E62*300% -> 245220.06 | H62: =E62*7.5% -> 6130.5015 | I62: =80244.38 -> 80244.38 | J62: =E62*50% -> 40870.01 | K62: =E62*350% -> 286090.07 | L62: =E62*100% -> 81740.02 | M62: =200000 -> 200000 | O62: =E62*10% -> 8174.002 | P62: 20000 | Q62: 0 | R62: =SUM(E62:Q62) -> 1050209.1 | T62: =100000+100000 -> 200000 | U62: =223611.11 -> 223611.11 | W62: 180306.81 | X62: =W62+V62+U62+T62+S62 -> 603917.92 | Y62: 446291.15 | Z62: =R62-X62 -> 446291.15
A63: 2 | B63: NDANUSA MOHAMMED MANZUMA | C63: SNR RESEARCH FELLOW | D63: 15(8) | E63: 32263.2 | G63: =E63*300% -> 96789.6 | H63: =E63*7.5% -> 2419.74 | I63: 40122.19 | J63: =E63*50% -> 16131.6 | K63: =E63*350% -> 112921.2 | L63: =E63*100% -> 32263.2 | M63: =160000 -> 160000 | O63: =E63*10% -> 3226.32 | P63: 20000 | Q63: 0 | R63: =SUM(E63:Q63) -> 516137.05 | T63: =100000 -> 100000 | U63: =131250 -> 131250 | W63: 77764.98 | X63: =W63+V63+U63+T63+S63 -> 309014.98 | Y63: 197897.13 | Z63: =R63-X63 -> 207122.07
A64: 3 | B64: EJALONIBU GANIYU LAYI | C64: RESEARCH FELLOW 1 | D64: 14(8) | E64: 25854.1 | G64: =E64*300% -> 77562.3 | H64: =E64*7.5% -> 1939.0575 | J64: =E64*50% -> 12927.05 | K64: =E64*350% -> 90489.35 | L64: =E64*100% -> 25854.1 | M64: 140000 | O64: =E64*10% -> 2585.41 | P64: 20000 | R64: =SUM(E64:Q64) -> 397211.37 | T64: =110000 -> 110000 | W64: 54931.249 | X64: =W64+V64+U64+T64+S64 -> 164931.25 | Y64: 232280.14 | Z64: =R64-X64 -> 232280.12
A65: 4 | B65: LOHNA BONKAT JONATHAN | C65: RESEARCH FELLOW 11 | D65: 13(10) | E65: =25523.45 -> 25523.45 | G65: =E65*300% -> 76570.35 | H65: =E65*7.5% -> 1914.2587 | I65: 0 | J65: =E65*50% -> 12761.725 | K65: =E65*350% -> 89332.075 | L65: =E65*100% -> 25523.45 | M65: =120000 -> 120000 | O65: =E65*10% -> 2552.345 | P65: 15000 | Q65: 0 | R65: =SUM(E65:Q65) -> 369177.65 | T65: =20000+65000 -> 85000 | U65: 0 | V65: 0 | W65: 49548.776 | X65: =W65+V65+U65+T65+S65 -> 134548.78 | Y65: 228830.19 | Z65: =R65-X65 -> 234628.88
A66: 5 | B66: YUNUSA ABDULLAHI | C66: RESEARCH FELLOW 1 | D66: 14(11) | E66: 28489.81 | G66: =E66*300% -> 85469.43 | H66: =E66*7.5% -> 2136.7357 | J66: =E66*50% -> 14244.905 | K66: =E66*350% -> 99714.335 | L66: =E66*100% -> 28489.81 | M66: =140000 -> 140000 | O66: =E66*10% -> 2848.981 | P66: 20000 | R66: =SUM(E66:Q66) -> 421394.01 | T66: =10000 -> 10000 | U66: =54585.66 -> 54585.66 | W66: 46666.667 | X66: =W66+V66+U66+T66+S66 -> 111252.33 | Y66: 290720.77 | Z66: =R66-X66 -> 310141.68
A67: 7 | B67: UDEFUNA NNADOZIE PATRICK | C67: RESEARCH OFFICER | D67: 12(8) | E67: 21520.88 | G67: =E67*300% -> 64562.64 | H67: =E67*7.5% -> 1614.066 | I67: 0 | J67: =E67*50% -> 10760.44 | K67: =E67*350% -> 75323.08 | L67: =E67*100% -> 21520.88 | M67: =110000 -> 110000 | O67: =E67*10% -> 2152.088 | P67: 15000 | Q67: 0 | R67: =SUM(E67:Q67) -> 322454.07 | T67: =10000 -> 10000 | U67: =65885.83 -> 65885.83 | W67: 41338.951 | X67: =W67+V67+U67+T67+S67 -> 117224.78 | Y67: 199337.07 | Z67: =R67-X67 -> 205229.29
A68: 8 | B68: SHAFIU YAHYA MIKAIL | C68: PRINCIPAL RESEARCH OFFICER | D68: 12(8) | E68: 21520.88 | G68: =E68*300% -> 64562.64 | H68: =E68*7.5% -> 1614.066 | I68: 0 | J68: =E68*50% -> 10760.44 | K68: =E68*350% -> 75323.08 | L68: =E68*100% -> 21520.88 | M68: =110000 -> 110000 | O68: =E68*10% -> 2152.088 | P68: 15000 | Q68: 0 | R68: =SUM(E68:Q68) -> 322454.07 | T68: =52000-2000 -> 50000 | W68: 41338.951 | X68: =W68+V68+U68+T68+S68 -> 91338.951 | Y68: 225222.9 | Z68: =R68-X68 -> 231115.12
A69: 9 | B69: HASSAN YERIMA | C69: PRINCIPAL RESEARCH OFFICER | D69: 12(8) | E69: 21520.88 | G69: =E69*300% -> 64562.64 | H69: =E69*7.5% -> 1614.066 | I69: 0 | J69: =E69*50% -> 10760.44 | K69: =E69*350% -> 75323.08 | L69: =E69*100% -> 21520.88 | M69: =110000 -> 110000 | O69: =E69*10% -> 2152.088 | P69: 15000 | Q69: 0 | R69: =SUM(E69:Q69) -> 322454.07 | T69: =67000-2000 -> 65000 | W69: 41338.951 | X69: =W69+V69+U69+T69+S69 -> 106338.95 | Y69: 210222.9 | Z69: =R69-X69 -> 216115.12
A70: 10 | B70: HAUWA PATE SADIQ | C70: PRINCIPAL PROGRAMME OFFICER | D70: 12(9) | E70: 22837.82 | G70: =E70*300% -> 68513.46 | H70: =E70*7.5% -> 1712.8365 | J70: =E70*50% -> 11418.91 | K70: =E70*350% -> 79932.37 | L70: =E70*100% -> 22837.82 | M70: =110000 -> 110000 | O70: =E70*10% -> 2283.782 | P70: 15000 | R70: =SUM(E70:Q70) -> 334537 | T70: =80000+20000 -> 100000 | W70: 43368.882 | X70: =W70+V70+U70+T70+S70 -> 143368.88 | Y70: 181115.12 | Z70: =R70-X70 -> 191168.12
A71: 11 | B71: KOLAPO Q. ABAYOMI | C71: RESEARCH OFFICER | D71: 10(8) | E71: 18281.64 | G71: =E71*300% -> 54844.92 | H71: =E71*7.5% -> 1371.123 | J71: =E71*50% -> 9140.82 | K71: =E71*350% -> 63985.74 | L71: =E71*100% -> 18281.64 | M71: 100000 | O71: =E71*10% -> 1828.164 | P71: 10000 | R71: =SUM(E71:Q71) -> 277734.05 | W71: 33825.987 | X71: =32291.82 -> 32291.82 | Y71: 236310.26 | Z71: =R71-X71 -> 245442.23
B72: TOTAL | C72: 12 | E72: =SUM(E62:E71) -> 299552.68 | F72: =SUM(F62:F71) -> 0 | G72: =SUM(G62:G71) -> 898658.04 | H72: =SUM(H62:H71) -> 22466.451 | I72: =SUM(I62:I71) -> 120366.57 | J72: =SUM(J62:J71) -> 149776.34 | K72: =SUM(K62:K71) -> 1048434.4 | L72: =SUM(L62:L71) -> 299552.68 | ... X72: =SUM(X62:X71) -> 1814228.6 | Y72: 2562691.9 | Z72: =SUM(Z62:Z71) -> 2519533.8
B74: DEPARTMENT OF STUDIES
A75: 1 | B75: DR ASIMIYU G. ABIOLA | C75: DIRECTOR POST GRADUATE | D75: 17(9) | E75: 81740.02 | G75: =E75*300% -> 245220.06 | H75: =E75*7.5% -> 6130.5015 | I75: 80244.38 | J75: =E75*50% -> 40870.01 | K75: =E75*350% -> 286090.07 | L75: =E75*100% -> 81740.02 | M75: =200000 -> 200000 | O75: =E75*10% -> 8174.002 | P75: 20000 | Q75: 0 | R75: =SUM(E75:Q75) -> 1050209.1 | T75: 250000 | U75: =0 -> 0 | V75: 0 | W75: 180306.81 | X75: =W75+V75+U75+T75+S75 -> 430306.81 | Y75: 619902.26 | Z75: =R75-X75 -> 619902.26
A76: 2 | B76: USMAN WALI | C76: SENIOR RESEARCH FELLOW | D76: 15 (8) | E76: 32263.2 | G76: =E76*300% -> 96789.6 | H76: =E76*7.5% -> 2419.74 | I76: 40122.19 | J76: =E76*50% -> 16131.6 | K76: =E76*350% -> 112921.2 | L76: =E76*100% -> 32263.2 | M76: =160000 -> 160000 | O76: =E76*10% -> 3226.32 | P76: 20000 | Q76: 0 | R76: =SUM(E76:Q76) -> 516137.05 | V76: 0 | W76: 77764.98 | X76: =W76+V76+U76+T76+S76 -> 77764.98 | Y76: 429147.13 | Z76: =R76-X76 -> 438372.07
A77: 3 | B77: AYOBOLU OLAJIDE OLUFUNSHO | C77: ASST.DIR., INFORMATION | D77: 15 (9) | E77: 33507.5 | G77: =E77*300% -> 100522.5 | H77: =E77*7.5% -> 2513.0625 | I77: 40122.19 | J77: =E77*50% -> 16753.75 | K77: =E77*350% -> 117276.25 | L77: =E77*100% -> 33507.5 | N77: =80000 -> 80000 | O77: =E77*10% -> 3350.75 | P77: 20000 | Q77: 0 | R77: =SUM(E77:Q77) -> 447553.5 | T77: =50000 -> 50000 | U77: =59583.33 -> 59583.33 | W77: 64596.939 | X77: =W77+V77+U77+T77+S77 -> 174180.27 | Y77: 264148.74 | Z77: =R77-X77 -> 273373.23
A78: 4 | B78: ANTHONY EDET | C78: CHIEF PROGRAMMES OFFICER | D78: 14(9) | E78: 26732.65 | G78: =E78*300% -> 80197.95 | H78: =E78*7.5% -> 2004.9488 | I78: 0 | J78: =E78*50% -> 13366.325 | K78: =E78*350% -> 93564.275 | L78: =E78*100% -> 26732.65 | M78: =140000 -> 140000 | O78: =E78*10% -> 2673.265 | P78: 20000 | Q78: 0 | R78: =SUM(E78:Q78) -> 405272.06 | T78: 20000 | U78: =96664.65 -> 96664.65 | V78: =0.025*E78 -> 668.31625 | W78: 56350.586 | X78: =W78+V78+U78+T78+S78 -> 173683.55 | Y78: 224977.4 | Z78: =R78-X78 -> 231588.51
A79: 5 | B79: IGWE STACY | C79: PROGRAMME OFFICER | D79: 10(9) | E79: 17784.1 | G79: =E79*300% -> 53352.3 | H79: =E79*7.5% -> 1333.8075 | J79: =E79*50% -> 8892.05 | K79: =E79*350% -> 62244.35 | L79: =E79*100% -> 17784.1 | M79: =100000 -> 100000 | O79: =E79*10% -> 1778.41 | P79: 10000 | R79: =SUM(E79:Q79) -> 273169.12 | T79: =50000 -> 50000 | U79: =50000 -> 50000 | W79: 17507.549 | X79: =W79+V79+U79+T79+S79 -> 117507.55 | Y79: 140110.04 | Z79: =R79-X79 -> 155661.57
A80: 6 | B80: OLANIYAN TAIWO ABINBOLA | C80: PROGRAMME OFFICER | D80: 9(8) | E80: 15188.67 | G80: =E80*300% -> 45566.01 | H80: =E80*7.5% -> 1139.1502 | J80: =E80*50% -> 7594.335 | K80: =E80*350% -> 53160.345 | L80: =E80*100% -> 15188.67 | M80: 100000 | O80: =E80*10% -> 1518.867 | P80: 10000 | R80: =SUM(E80:Q80) -> 249356.05 | W80: 29058.483 | X80: =W80+V80+U80+T80+S80 -> 29058.483 | Y80: 216843.13 | Z80: =R80-X80 -> 220297.56
A81: 7 | B81: AMINAT JUMOKE SULAIMON | C81: AST. PROGRAMME OFFICER | D81: 8(8) | E81: =12732 -> 12732 | G81: 37058.82 | H81: 926.4705 | J81: 6176.47 | K81: 43235.29 | L81: 12352.94 | M81: 100000 | N81: 0 | O81: 1235.294 | P81: 10000 | R81: =SUM(E81:Q81) -> 223717.28 | T81: 20000 | U81: 0 | V81: 0 | W81: 24751.17 | X81: =W81+V81+U81+T81+S81 -> 44751.17 | Y81: 178650.73 | Z81: =R81-X81 -> 178966.11
B82: TOTAL | C82: 7 | E82: =SUM(E75:E81) -> 219948.14 | F82: =SUM(F75:F81) -> 0 | G82: =SUM(G75:G81) -> 658707.24 | H82: =SUM(H75:H81) -> 16467.681 | I82: =SUM(I75:I81) -> 160488.76 | J82: =SUM(J75:J81) -> 109784.54 | K82: =SUM(K75:K81) -> 768491.78 | L82: =SUM(L75:L81) -> 219569.08 | ... X82: =SUM(X75:X81) -> 1047252.8 | Y82: 2073779.4 | Z82: =SUM(Z75:Z81) -> 2118161.3
B84: ECON. DEV. & SOC. RESEARCH
A85: 1 | B85: TERFA WILLIAMS ABRAHAM | C85: SNR RESEARCH FELLOW | D85: 15(9) | E85: 33507.5 | G85: =E85*300% -> 100522.5 | H85: =E85*7.5% -> 2513.0625 | I85: =40122.19 -> 40122.19 | J85: =E85*50% -> 16753.75 | K85: =E85*350% -> 117276.25 | L85: =E85*100% -> 33507.5 | M85: =160000 -> 160000 | O85: =E85*10% -> 3350.75 | P85: 20000 | Q85: 100000 | R85: =SUM(E85:Q85) -> 627553.5 | W85: 99156.939 | X85: =W85+V85+U85+T85+S85 -> 99156.939 | Y85: 528396.56 | Z85: =R85-X85 -> 528396.56
A86: 2 | B86: DR AUGUSTINE C. OSIGWE | C86: SNR RESEARCH FELLOW | D86: 15(9) | E86: 33507.5 | G86: =E86*300% -> 100522.5 | H86: =E86*7.5% -> 2513.0625 | I86: =40122.19 -> 40122.19 | J86: =E86*50% -> 16753.75 | K86: =E86*350% -> 117276.25 | L86: =E86*100% -> 33507.5 | M86: =160000 -> 160000 | O86: =E86*10% -> 3350.75 | P86: 20000 | R86: =SUM(E86:Q86) -> 527553.5 | T86: =30000 -> 30000 | U86: 98750 | V86: =0.025*E86 -> 837.6875 | W86: 98996.103 | X86: =W86+V86+U86+T86+S86 -> 228583.79 | Y86: 318169.71 | Z86: =R86-X86 -> 298969.71 | AA86: =Y86-Z86 -> 19200
A87: 3 | B87: OMOJU OLUWASOLA EMMANUEL | C87: SNR RESEARCH FELLOW | D87: 15(7) | E87: 31019.84 | G87: =E87*300% -> 93059.52 | H87: =E87*7.5% -> 2326.488 | I87: =40122.19 -> 40122.19 | J87: =E87*50% -> 15509.92 | K87: =E87*350% -> 108569.44 | L87: =E87*100% -> 31019.84 | M87: 160000 | O87: =E87*10% -> 3101.984 | P87: 20000 | R87: =SUM(E87:Q87) -> 504729.22 | T87: =50000 -> 50000 | U87: =79861.11 -> 79861.11 | W87: 79956.939 | X87: =W87+V87+U87+T87+S87 -> 209818.05 | Y87: 299295.17 | Z87: =R87-X87 -> 294911.17
A88: 4 | B88: IBE EZECHI CYRIACUS | C88: RESEARCH FELLOW II | D88: 13(11) | E88: 26339.3 | G88: =E88*300% -> 79017.9 | H88: =E88*7.5% -> 1975.4475 | I88: 0 | J88: =E88*50% -> 13169.65 | K88: =E88*350% -> 92187.55 | L88: =E88*100% -> 26339.3 | M88: =120000 -> 120000 | O88: =E88*10% -> 2633.93 | P88: 15000 | Q88: 0 | R88: =SUM(E88:Q88) -> 376663.08 | T88: =50000 -> 50000 | U88: 0 | W88: 75574.677 | X88: =W88+V88+U88+T88+S88 -> 125574.68 | Y88: 269628.88 | Z88: =R88-X88 -> 251088.4
A89: 5 | B89: OSIKHEN LEO IGBANOI | C89: RESEARCH FELLOW 11 | D89: 13(10) | E89: =25523.45 -> 25523.45 | G89: =E89*300% -> 76570.35 | H89: =E89*7.5% -> 1914.2587 | I89: 0 | J89: =E89*50% -> 12761.725 | K89: =E89*350% -> 89332.075 | L89: =E89*100% -> 25523.45 | M89: =120000 -> 120000 | O89: =E89*10% -> 2552.345 | P89: 15000 | Q89: 0 | R89: =SUM(E89:Q89) -> 369177.65 | T89: 50000 | U89: 20000 | W89: 50985.978 | X89: =W89+V89+U89+T89+S89 -> 120985.98 | Y89: 313830.19 | Z89: =R89-X89 -> 248191.68
A90: 6 | B90: OKUNGBOWA OSARETIN GODSPOWER | C90: RESEARCH FELLOW 1 | D90: 14(7) | E90: =[4]Sheet1!$D$17 -> 24975.81 | G90: =E90*300% -> 74927.43 | H90: =E90*7.5% -> 1873.1858 | I90: 0 | J90: =E90*50% -> 12487.905 | K90: =E90*350% -> 87415.335 | L90: =E90*100% -> 24975.81 | M90: =140000 -> 140000 | O90: =E90*10% -> 2497.581 | P90: 20000 | Q90: 0 | R90: =SUM(E90:Q90) -> 389153.06 | T90: =100000-100000 -> 0 | W90: 49548.776 | X90: =W90+V90+U90+T90+S90 -> 49548.776 | Y90: 335768.93 | Z90: =R90-X90 -> 339604.28
A91: 7 | B91: YUSUF IBRAHIM | C91: PRINCIPAL RESEARCH OFFICER | D91: 12(8) | E91: 21520.88 | G91: =E91*300% -> 64562.64 | H91: =E91*7.5% -> 1614.066 | I91: 0 | J91: =E91*50% -> 10760.44 | K91: =E91*350% -> 75323.08 | L91: =E91*100% -> 21520.88 | M91: =110000 -> 110000 | O91: =E91*10% -> 2152.088 | P91: 15000 | Q91: 0 | R91: =SUM(E91:Q91) -> 322454.07 | T91: =20000 -> 20000 | U91: 43750 | W91: 53384.054 | X91: =W91+V91+U91+T91+S91 -> 117134.05 | Y91: 211472.9 | Z91: =R91-X91 -> 205320.02
A92: 8 | B92: MUSTAPHA RAFIU AYOBANJI | C92: RESEARCH FELLOW 11 | D92: 13(7) | E92: 23074.99 | G92: =E92*300% -> 69224.97 | H92: =E92*7.5% -> 1730.6243 | I92: 0 | J92: =E92*50% -> 11537.495 | K92: =E92*350% -> 80762.465 | L92: =E92*100% -> 23074.99 | M92: 120000 | O92: =E92*10% -> 2307.499 | P92: 15000 | Q92: 0 | R92: =SUM(E92:Q92) -> 346713.03 | T92: 0 | V92: =0.025*E92 -> 576.87475 | W92: 41242.036 | X92: =W92+V92+U92+T92+S92 -> 41818.911 | Y92: 274704.17 | Z92: =R92-X92-9271.87 -> 295622.25
A93: 9 | B93: MARYAM MUSA SADA | C93: ASSIT. RESEARCH OFFICER | D93: 10(8) | E93: 18281.64 | G93: =E93*300% -> 54844.92 | H93: =E93*7.5% -> 1371.123 | J93: =E93*50% -> 9140.82 | K93: =E93*350% -> 63985.74 | L93: =E93*100% -> 18281.64 | M93: 100000 | O93: =E93*10% -> 1828.164 | P93: 10000 | R93: =SUM(E93:Q93) -> 277734.05 | W93: 45414.456 | X93: =W93+V93+U93+T93+S93 -> 45414.456 | Y93: 236310.26 | Z93: =R93-X93 -> 232319.59
A94: 10 | B94: CHARITY EZENWAJIOBI | C94: REASEARCH. ASST. | D94: 8(9) | E94: =13112.16 -> 13112.16 | G94: =E94*300% -> 39336.48 | H94: =E94*7.5% -> 983.412 | J94: =E94*50% -> 6556.08 | K94: =E94*350% -> 45892.56 | L94: =E94*100% -> 13112.16 | M94: =100000 -> 100000 | O94: =E94*10% -> 1311.216 | P94: 10000 | Q94: 24566.195 | R94: =SUM(E94:Q94) -> 254870.26 | T94: 50000 | V94: 0 | W94: 33825.987 | X94: =W94+V94+U94+T94+S94 -> 83825.987 | Y94: 148959.31 | Z94: =R94-X94 -> 171044.28
B95: TOTAL | C95: 11 | E95: =SUM(E85:E94) -> 250863.07 | F95: =SUM(F85:F94) -> 0 | G95: =SUM(G85:G94) -> 752589.21 | H95: =SUM(H85:H94) -> 18814.73 | I95: =SUM(I85:I94) -> 120366.57 | J95: =SUM(J85:J94) -> 125431.53 | K95: =SUM(K85:K94) -> 878020.74 | L95: =SUM(L85:L94) -> 250863.07 | ... X95: =SUM(X85:X94) -> 1121861.6 | Y95: 3181874.5 | Z95: =SUM(Z85:Z94) -> 2865467.9
B97: TRAINING & INT''L COOP
A98: 1 | B98: AKINSANMI ADEJOKE OLUKEMI | C98: Ag. DIR. TRAINING & IC | D98: 16(9) | E98: =42653.17 -> 42653.17 | G98: =E98*300% -> 127959.51 | H98: =E98*7.5% -> 3198.9877 | I98: 40122.19 | J98: =E98*50% -> 21326.585 | K98: =E98*350% -> 149286.1 | L98: =E98*100% -> 42653.17 | N98: =80000+10000 -> 90000 | O98: =E98*10% -> 4265.317 | P98: 20000 | R98: =Q98+P98+O98+N98+M98+L98+K98+J98+I98+H98+G98+F98+E98 -> 541465.02 | T98: =0 -> 0 | U98: 0 | V98: =0.025*E98 -> 1066.3293 | W98: 82423.216 | X98: =W98+V98+U98+T98+S98 -> 83489.545 | Y98: 822510.71 | Z98: =R98-X98 -> 457975.48
A99: 2 | B99: MOHAMMED R. ADAMU | C99: CHIEF TRAINING OFFICER | D99: 14(9) | E99: 26732.65 | G99: =E99*300% -> 80197.95 | H99: =E99*7.5% -> 2004.9488 | I99: 0 | J99: =E99*50% -> 13366.325 | K99: =E99*350% -> 93564.275 | L99: =E99*100% -> 26732.65 | N99: 70000 | O99: =E99*10% -> 2673.265 | P99: 20000 | Q99: 0 | R99: =SUM(E99:Q99) -> 335272.06 | T99: =10000 -> 10000 | U99: 175000 | W99: 82627.951 | X99: =W99+V99+U99+T99+S99 -> 267627.95 | Y99: 161513.24 | Z99: =R99-X99 -> 67644.112
A100: 3 | B100: OKECHUKWU UCHENNA HULDA | C100: PRINCIPALTRAINING OFFICER | D100: 12(9) | E100: =22837.82 -> 22837.82 | G100: =E100*300% -> 68513.46 | H100: =E100*7.5% -> 1712.8365 | J100: =E100*50% -> 11418.91 | K100: =E100*350% -> 79932.37 | L100: =E100*100% -> 22837.82 | N100: =60000 -> 60000 | O100: =E100*10% -> 2283.782 | P100: 15000 | R100: =SUM(E100:Q100) -> 284537 | T100: =5000 -> 5000 | U100: =64806.29 -> 64806.29 | W100: 43492.373 | X100: =W100+V100+U100+T100+S100 -> 113298.66 | Y100: 169708.83 | Z100: =R100-X100 -> 171238.34
A101: 4 | B101: TASSNEEM IBRAHIM | C101: SENIOR PROGRAMME OFFICER | D101: 10(8) | E101: 18281.64 | G101: =E101*300% -> 54844.92 | H101: =E101*7.5% -> 1371.123 | J101: =E101*50% -> 9140.82 | K101: =E101*350% -> 63985.74 | L101: =E101*100% -> 18281.64 | N101: =60000 -> 60000 | O101: =E101*10% -> 1828.164 | P101: 10000 | R101: =SUM(E101:Q101) -> 237734.05 | T101: =10000 -> 10000 | U101: =19583.33 -> 19583.33 | W101: 34968.882 | X101: =W101+V101+U101+T101+S101 -> 64552.212 | Y101: 173447.02 | Z101: =R101-X101 -> 173181.83
B102: TOTAL | C102: 4 | E102: =SUM(E98:E101) -> 110505.28 | F102: =SUM(F98:F101) -> 0 | G102: =SUM(G98:G101) -> 331515.84 | H102: =SUM(H98:H101) -> 8287.896 | I102: =SUM(I98:I101) -> 40122.19 | J102: =SUM(J98:J101) -> 55252.64 | K102: =SUM(K98:K101) -> 386768.48 | L102: =SUM(L98:L101) -> 110505.28 | ... X102: =SUM(X98:X101) -> 528968.37 | Y102: 1327179.8 | Z102: =SUM(Z98:Z101) -> 870039.76
B104: LIBRARY & DOCUMENTATION
A105: 1 | B105: DR MAIMUNA IZAH | C105: INSITUTE LIBRARIAN | D105: 17(9) | E105: 81740.02 | G105: =E105*300% -> 245220.06 | H105: =E105*7.5% -> 6130.5015 | I105: 80244.38 | J105: =E105*50% -> 40870.01 | K105: =E105*350% -> 286090.07 | L105: =E105*100% -> 81740.02 | M105: =200000 -> 200000 | O105: =E105*10% -> 8174.002 | P105: 20000 | Q105: 0 | R105: =SUM(E105:Q105) -> 1050209.1 | T105: =100000 -> 100000 | U105: 0 | V105: 0 | W105: 180306.81 | X105: =W105+V105+U105+T105+S105 -> 280306.81 | Y105: 770063.09 | Z105: =R105-X105 -> 769902.26
A106: 2 | B106: CATHERINE E. IKOKOH | C106: SNR RESEARCH FELLOW DOCU | D106: 16(9) | E106: =42653.17 -> 42653.17 | G106: =E106*300% -> 127959.51 | H106: =E106*7.5% -> 3198.9877 | I106: 40122.19 | J106: =E106*50% -> 21326.585 | K106: =E106*350% -> 149286.1 | L106: =E106*100% -> 42653.17 | M106: =160000+20000 -> 180000 | O106: =E106*10% -> 4265.317 | P106: 20000 | Q106: 0 | R106: =SUM(E106:Q106) -> 631465.02 | T106: 40000 | U106: =238888.89 -> 238888.89 | V106: =0.025*E106 -> 1066.3293 | W106: 99703.216 | X106: =SUM(S106:W106) -> 379658.44 | Y106: 240679.08 | Z106: =R106-X106 -> 251806.59
A107: 3 | B107: ALIYU SANNI ABUBAKAR | C107: RESEARCH FELLOW 11 DATA & DOCU | D107: 13(11) | E107: 26339.3 | G107: =E107*300% -> 79017.9 | H107: =E107*7.5% -> 1975.4475 | I107: 0 | J107: =E107*50% -> 13169.65 | K107: =E107*350% -> 92187.55 | L107: =E107*100% -> 26339.3 | M107: =120000 -> 120000 | O107: =E107*10% -> 2633.93 | P107: 15000 | Q107: 41432.939 | R107: =SUM(E107:Q107) -> 418096.02 | T107: 30000 | U107: =61111.11 -> 61111.11 | V107: =0.025*E107 -> 658.4825 | W107: 180180.38 | X107: =W107+V107+U107+T107+S107 -> 271949.97 | Y107: 267385.32 | Z107: =R107-X107 -> 146146.05
A108: 4 | B108: CHINAKO N. ASOGWA | C108: RESEARCH FELLOW 11 DATA & DOCU | D108: 13(11) | E108: 26339.3 | G108: =E108*300% -> 79017.9 | H108: =E108*7.5% -> 1975.4475 | I108: 0 | J108: =E108*50% -> 13169.65 | K108: =E108*350% -> 92187.55 | L108: =E108*100% -> 26339.3 | M108: =120000 -> 120000 | O108: =E108*10% -> 2633.93 | P108: 15000 | Q108: 39820.117 | R108: =SUM(E108:Q108) -> 416483.19 | T108: =50000 -> 50000 | U108: =0 -> 0 | W108: 99907.951 | X108: =W108+V108+U108+T108+S108 -> 149907.95 | Y108: 307542.09 | Z108: =R108-X108 -> 266575.24
...

Sheet Sheet4
A1: S/N | B1: DG'S OFFICE
A2: 1 | B2: PROF. ABUBAKAR O. SULAIMAN | C2: DIRECTOR GENERAL | D2: CONSOL
A3: 2 | B3: RAHEEM USMAN AYIGORO | C3: SA-INFRASTRUCTURE | D3: 16 (9)
A4: 3 | B4: MARIAM MOHAMMED BELLO | C4: SA- SPECIAL DUTIES | D4: 16(8)
A5: 4 | B5: DR IKEME ARTHUR J.O | C5: DEPUTY DIRECTOR, M&E | D5: 16(8)
A6: 5 | B6: MOSHOOD M. OLALERE | C6: DEPUTY DIR. GENERAL SERVICE | D6: 16(8)
A7: 6 | B7: REKIYA IBRAHIM ATTAH | C7: DEPUTY DIRECTOR TRAINING | D7: 16(8)
A8: 7 | B8: ANDRAWUS MUSA | C8: ASST. DIRECTOR, STORES | D8: 15(9)
A9: 8 | B9: DR FRANCIS NDUM OJIE | C9: AD, TRAINING & IC./SA TO DG | D9: 15(7)
A10: 9 | B10: ALI ABDULLAHI | C10: CHIEF ICT OFFICER | D10: 14(10)
A11: 10 | B11: EMILY EKHIDE | C11: RESEARCH FELLOW 1 | D11: 14(9)
A12: 11 | B12: ABDULSALAM S. MUSTAPHA | C12: ASST. MANAGER ICT | D12: 13(11)
A13: 12 | B13: PERCY TERFA GBAHABO | C13: HEAD, NILDS LIAISON OFFICE | D13: 13(9)
... A25: 24 | B25: HARUNA JIBRIL AMEH | C25: ASST. ADMIN. OFFICER | D25: 8(7)
B26: TOTAL | C26: 24
B28: INTERNAL AUDIT
A29: 1 | B29: OSANAIYE DAVID AKINYEMI | C29: DIRECTOR INTERNAL AUDIT | D29: 17(9)
A30: 2 | B30: JAMILA ABDUL | C30: AUDITOR II | D30: 8(7)
A31: 3 | B31: IJEOMA EWELUKWA | C31: AUDIT OFFICER | D31: 10(7)
C32: 3
B34: LEG. SUPPORT SEVICES
A35: 1 | B35: PROF. EDOBA BRIGHT OMOREGBE | C35: AG. DLSS | D35: 17(9)
A36: 2 | B36: DR CLINTON JAJA | C36: SENIOR RESEARCH FELLOW | D36: 15(9)
A37: 3 | B37: BETHEL UZOMA IHUGBA | C37: DEPUTY DIRECTOR, LEGAL RESEARCH | D37: 16(7)
A38: 4 | B38: OGUCHE SAMUEL | C38: SNR RESEARCH FELLOW | D38: 15(9)
A39: 5 | B39: IBRAHIM USMAN | C39: SNR RESEARCH FELLOW | D39: 15(8)
A40: 6 | B40: DR MOHAMMED O. AMALI | C40: SNR RESEARCH FELLOW | D40: 15(7)
A41: 7 | B41: YAHAYA SHAMSU | C41: RESEARCH FELLOW 1 | D41: 14(10)
A42: 8 | B42: DORIS DAKDA AARON | C42: RESEARCH FELLOW I | D42: 14(8)
A43: 9 | B43: BILKIS S. LAWAL-GAMBARI | C43: RESEARCH OFFICER | D43: 10(7)
A44: 10 | B44: ZAINAB AKINDE | C44: RESEARCH OFFICER | D44: 9(7)
A45: 11 | B45: ABDULLAHI AHMAD USMAN | C45: RESEARCH OFFICER | D45: 9(7)
A46: 12 | B46: GUNAT NANSAK MARK | C46: RESEARCH OFFICER | D46: 9(7)
B47: TOTAL | C47: 12
B49: LEGAL SERVICES
A50: 1 | B50: DR SHUIBU DANWANKA | C50: DIRECTOR LEGAL SERVICES | D50: 17(9)
A51: 2 | B51: ABDULSALAM BAKO | C51: MANAGER, LEGAL SERVICES | D51: 15 (8)
B52: TOTAL | C52: 2
B54: DEMOCRACY & GOVERNANCE
A55: 1 | B55: DR. ADEWALE ADEREMI | C55: DIRECTOR, DEMOCRATIC STUDIES | D55: 17(9)
A56: 2 | B56: NDANUSA MOHAMMED MANZUMA | C56: SNR RESEARCH FELLOW | D56: 15 (7)
A57: 3 | B57: EJALONIBU GANIYU LAYI | C57: RESEARCH FELLOW 1 | D57: 14(8)
A58: 4 | B58: LOHNA BONKAT JONATHAN | C58: RESEARCH FELLOW 11 | D58: 13(9)
A59: 5 | B59: YUNUSA ABDULLAHI | C59: RESEARCH FELLOW 1 | D59: 14(10)
A60: 7 | B60: UDEFUNA NNADOZIE PATRICK | C60: RESEARCH OFFICER | D60: 12(7)
A61: 8 | B61: SHAFIU YAHYA MIKAIL | C61: PRINCIPAL RESEARCH OFFICER | D61: 12(7)
A62: 9 | B62: HASSAN YERIMA | C62: PRINCIPAL RESEARCH OFFICER | D62: 12(7)
A63: 10 | B63: HAUWA PATE SADIQ | C63: PRINCIPAL PROGRAMME OFFICER | D63: 12(8)
A64: 11 | B64: KOLAPO Q. ABAYOMI | C64: RESEARCH OFFICER | D64: 10(7)
A65: 12 | B65: NNANDI LIVINUS ATURE | C65: RESEARCH ASSISTANT | D65: 9(8)
B66: TOTAL | C66: 12
B68: DEPARTMENT OF STUDIES
A69: 1 | B69: DR ASIMIYU G. ABIOLA | C69: DIRECTOR POST GRADUATE | D69: 17(9)
A70: 2 | B70: USMAN WALI | C70: SENIOR RESEARCH FELLOW | D70: 15 (7)
A71: 3 | B71: AYOBOLU OLAJIDE OLUFUNSHO | C71: ASST.DIR., INFORMATION | D71: 15 (8)
A72: 4 | B72: ANTHONY EDET | C72: CHIEF PROGRAMMES OFFICER | D72: 14(8)
A73: 5 | B73: IGWE STACY | C73: PROGRAMME OFFICER | D73: 10(8)
A74: 6 | B74: OLANIYAN TAIWO ABINBOLA | C74: PROGRAMME OFFICER | D74: 9(7)
A75: 7 | B75: AMINAT JUMOKE SULAIMON | C75: AST. PROGRAMME OFFICER | D75: 8(7)
B76: TOTAL | C76: 7
B78: ECON. DEV. & SOC. RESEARCH
A79: 1 | B79: TERFA WILLIAMS ABRAHAM | C79: SNR RESEARCH FELLOW | D79: 15(9)
A80: 2 | B80: DR AUGUSTINE C. OSIGWE | C80: SNR RESEARCH FELLOW | D80: 15(9)
A81: 3 | B81: NGARA CHRISTOPHER OCHANJA | C81: SNR RESEARCH FELLOW | D81: 15(7)
A82: 4 | B82: OMOJU OLUWASOLA EMMANUEL | C82: SNR RESEARCH FELLOW | D82: 15(7)
A83: 5 | B83: IBE EZECHI CYRIACUS | C83: RESEARCH FELLOW II | D83: 13(10)
A84: 6 | B84: OSIKHEN LEO IGBANOI | C84: RESEARCH FELLOW 11 | D84: 13(9)
A85: 7 | B85: OKUNGBOWA OSARETIN GODSPOWER | C85: RESEARCH FELLOW 1 | D85: 14(7)
A86: 8 | B86: YUSUF IBRAHIM | C86: PRINCIPAL RESEARCH OFFICER | D86: 12(7)
A87: 9 | B87: MUSTAPHA RAFIU AYOBANJI | C87: PRINCIPAL RESEARCH OFFICER | D87: 12(7)
A88: 10 | B88: MARYAM MUSA SADA | C88: ASSIT. RESEARCH OFFICER | D88: 10(7)
A89: 11 | B89: CHARITY EZENWAJIOBI | C89: REASEARCH. ASST. | D89: 8(8)
B90: TOTAL | C90: 11
B92: TRAINING & INT''L COOP
A93: 1 | B93: AKINSANMI ADEJOKE OLUKEMI | C93: Ag. DIR. TRAINING & IC | D93: 16(8)
A94: 2 | B94: MOHAMMED R. ADAMU | C94: CHIEF TRAINING OFFICER | D94: 14(8)
A95: 3 | B95: OKECHUKWU UCHENNA HULDA | C95: PRINCIPALTRAINING OFFICER | D95: 12(8)
A96: 4 | B96: TASSNEEM IBRAHIM | C96: SENIOR PROGRAMME OFFICER | D96: 10(7)
B97: TOTAL | C97: 4
B99: LIBRARY & DOCUMENTATION
A100: 1 | B100: DR MAIMUNA IZAH | C100: INSITUTE LIBRARIAN | D100: 17(9)
A101: 2 | B101: CATHERINE E. IKOKOH | C101: SNR RESEARCH FELLOW DOCU | D101: 16(8)
A102: 3 | B102: ALIYU SANNI ABUBAKAR | C102: RESEARCH FELLOW 11 DATA & DOCU | D102: 13(11)
A103: 4 | B103: CHINAKO N. ASOGWA | C103: RESEARCH FELLOW 11 DATA & DOCU | D103: 13(11)
A104: 5 | B104: AMOS ABA | C104: LIBRARY ASSISTANT | D104: 8(11)
A105: 6 | B105: TITILAYO DANIEL MARVELLOUS | C105: LIBRARY ASSISTANT | D105: 8(10)
A106: 7 | B106: ENENCHE JEREMIAH AGADA | C106: LIBRARY ASSISTANT | D106: 8(8)
B107: TOTAL | C107: 7
B109: LEG, CTRE FOR SEC. ANALYSIS
A110: 1 | B110: OSOLAFIA MUHAMMAD EGYE | C110: PRINCIPAL RESEARCH OFFICER | D110: 12(9)
A111: 2 | B111: EGUATU U. ONYEJELEM | C111: PRINCIPAL M&E OFFICER | D111: 12(8)
A112: 3 | B112: CHRISTIAN MADUABUCHI ODO | C112: PRINCIPAL ICT OFFICER | D112: 12(9)
B113: TOTAL | C113: 3
B115: FINANCE & ACCOUNTS
A116: 1 | B116: IBRAHIM M. MSHELIA | C116: DIR. FINANCE & ACCOUNTS | D116: 17(9)
A117: 2 | B117: RAHILA NURUDEEN HABU | C117: DEP. DIRECTOR, ACCOUNTS | D117: 16(7)
A118: 3 | B118: TONDO IORWUESE EDWARD | C118: ASST. DIRECTOR, ACCOUNTS | D118: 15(9)
A119: 4 | B119: ARAOYE GANIYAT TITILOLA | C119: ASST. DIRECTOR, ACCOUNTS | D119: 15(7)
A120: 5 | B120: SHEHU ABDULLAHI | C120: CHIEF ACCOUNT OFFICER | D120: 14(9)
A121: 6 | B121: OJOGIWA ABISOLA GANIAT | C121: ASST. CHIEF BUDGET OFFICER | D121: 14(8)
...

Sheet MEMO 1
A2: NATIONAL INSTITUTE FOR LEGISLATIVE AND DEMOCRATIC STUDIES
A3: INTERNAL MEMO
A4: FROM : DEPUTY DIRECTOR, FINANCE AND ACCOUNTS
A5: THRU: DIRECTOR, FINANCE AND ACCOUNTS
A6: TO: DG
A7: 29TH JANUARY , 2021
A9: SUBJECT: PAYROLL FOR THE MONTH OF JANUARY, 2021
A10: Find below the details of NILDS Staff Payroll for the month of January, 2021
A13: TO: | C13: DIRECTOR, GENERAL
A14: THRU: | C14: DIRECTOR, FINANCE AND ACCOUNT
A15: FROM: | C15: DEPUTY DIRECTOR, FINANCE AND ACCOUNTS
A16: DATE: | C16: 30TH JANUARY 2024
A18: SUBJECT: PAYROLL FOR THE MONTH OF JANUARY 2024
A19: Find below the details of NILDS Staff Payroll for the Month of January 2024: | G19: NGN | H19: NGN
A20: GROSS SALARY FOR JANUARY, 2024 | H20: ='JANUARY 2024'!R194 -> 53058224
A22: DEDUCTIONS
A23: COOP SOCIETY DEDUCTIONS ( CONTR.& SPEC. SAVINGS) | G23: ='JANUARY 2024'!T194 -> 5135500
A24: COOP LOAN RECOVERY | G24: ='JANUARY 2024'!U194 -> 7215945.7
A25: PAYE DEDUCTIONS | G25: ='JANUARY 2024'!W194 -> 7445494.6
A26: NHF DEDUCTIONS | G26: ='JANUARY 2024'!V194 -> 23031.314
A27: TOTAL DEDUCTIONS FOR JANUARY 2024 | H27: =G23+G24+G25+G26 -> 19819972
A28: NET PAY AS PER JANUARY, 2024 PAYROLL | H28: =H20-H27 -> 33238252
A29: NET PAY AS PER DECEMBER, 2023 PAYROLL | H29: ='JANUARY 2024'!Y194 -> 33766937
A30: NET INCREASE/ (DECREASE) IN PAY FOR JANUARY, 2024 | H30: =H28-H29 -> -528685.11
A31: ANALYSED AS FOLLOWS:
A32: Effect of Cooperative Adjustment for January, 2024 | H32: 570000
A33: Net Effect of Yearly Increment in Steps | H33: -620870.14
A34: Effect of Conversion of Dr Idris Ibrahim to Permanent Staff | H34: =-275222.9-586933.33 -> -862156.23
A35: Effect of Placement of Abubakar Suleiman & Rafiu Mustapha | H35: =-20302-26129.81 -> -46431.81
A36: Net effect of Leg. Duty Allowance to Dr. Doris Aaron | H36: -121199.98
A37: Effect of Removal of Promotion Arrears of Dr. Bethel Ighuba & 3 others | H37: =1609343.27 -> 1609343.3
H38: =SUM(H32:H37) -> 528685.11
E40: DECEMBER, 2023 | G40: JANUARY, 2024
E41: No. of Staff | F41: N | G41: No. of Staff | H41: N
A42: 1 | B42: Director General's Office | E42: 33 | F42: ='JANUARY 2024'!Y34 -> 7198101.1 | G42: ='JANUARY 2024'!C34 -> 27 | H42: ='JANUARY 2024'!Z34 -> 8717267.3
A43: 2 | B43: Internal Audit | E43: 2 | F43: ='JANUARY 2024'!Y40 -> 1018949 | G43: ='JANUARY 2024'!C40 -> 3 | H43: ='JANUARY 2024'!Z40 -> 925705.68
A44: 3 | B44: Legis. Support Services | E44: 11 | F44: ='JANUARY 2024'!Y54 -> 3378453.8 | G44: ='JANUARY 2024'!C54 -> 11 | H44: ='JANUARY 2024'!Z54 -> 2615777.9
A45: 4 | B45: Legal Services | E45: 2 | F45: ='JANUARY 2024'!Y59 -> 808634.33 | G45: ='JANUARY 2024'!C59 -> 2 | H45: ='JANUARY 2024'!Z59 -> 808634.33
A46: 5 | B46: Democracy and Governance | E46: 13 | F46: ='JANUARY 2024'!Y72 -> 2562691.9 | G46: ='JANUARY 2024'!C72 -> 12 | H46: ='JANUARY 2024'!Z72 -> 2519533.8
A47: 6 | B47: Studies | E47: 4 | F47: ='JANUARY 2024'!Y82 -> 2073779.4 | G47: ='JANUARY 2024'!C82 -> 7 | H47: ='JANUARY 2024'!Z82 -> 2118161.3
A48: 7 | B48: Economic Dev. & Social Research | E48: 12 | F48: ='JANUARY 2024'!Y95 -> 3181874.5 | G48: ='JANUARY 2024'!C95 -> 11 | H48: ='JANUARY 2024'!Z95 -> 2865467.9
A49: 8 | B49: Training & Int'l Cooperation | E49: 4 | F49: ='JANUARY 2024'!Y102 -> 1327179.8 | G49: ='JANUARY 2024'!C102 -> 4 | H49: ='JANUARY 2024'!Z102 -> 870039.76
A50: 9 | B50: Library & Documentation | E50: 8 | F50: ='JANUARY 2024'!Y112 -> 2142429.1 | G50: ='JANUARY 2024'!C112 -> 7 | H50: ='JANUARY 2024'!Z112 -> 1943184.8
A51: 10 | B51: Leg. Center for Security Analysis | E51: 2 | F51: ='JANUARY 2024'!Y118 -> 711797.57 | G51: ='JANUARY 2024'!C118 -> 2 | H51: ='JANUARY 2024'!Z118 -> 732856.3
A52: 11 | B52: Finance and Accounts | E52: 9 | F52: ='JANUARY 2024'!Y131 -> 2778218.1 | G52: ='JANUARY 2024'!C131 -> 10 | H52: ='JANUARY 2024'!Z131 -> 2223207.6
A53: 12 | B53: Admin & Human Resource | E53: 58 | F53: ='JANUARY 2024'!Y193 -> 6830167.4 | G53: ='JANUARY 2024'!C193 -> 59 | H53: ='JANUARY 2024'!Z193 -> 6881453.5
E54: =SUM(E42:E53) -> 158 | F54: =SUM(F42:F53) -> 34012276 | G54: 154 | H54: =SUM(H42:H53) -> 33221290
A56: The Director General is requested to consider and approve payment of N33, 221,290.19 to Guaranty Trust Bank being January, 2024 Salary, N12,351,445.68 being NILDS Coop Society deductions for January 2024, N7,445,494.58 being PAYE Tax Deductions from Staff Salary for the month of January 2024 and N23,031.31 being NHF deductions from staff for January 2024
A60: RAHILA NURUDEEN HABU
C164: =10000 -> 10000

Sheet ENHANCED WELFARE 2024
A1: NATIONAL INSTITUTE FOR LEGISLATIVE AND DEMOCRATIC STUDIES
A2: STAFF ENHANCED WELFARE SCHEDULE 2024
B4: STAFF NAME | C4: DESIGNATION | D4: GRADE LEVEL | E4: AMOUNT | F4: Grade Level 01 - 13 | G4: Grade Level 14 - 17
E5: N | F5: N | G5: N
A6: S/N | B6: DG'S OFFICE
A7: 1 | B7: PROF. ABUBAKAR O. SULAIMAN | C7: DIRECTOR GENERAL | D7: CONSOL | E7: 2000000 | G7: =E7 -> 2000000
A8: 2 | B8: RAHEEM USMAN AYIGORO | C8: SA-INFRASTRUCTURE | D8: 16 (9) | E8: 350000 | G8: =E8 -> 350000
A9: 3 | B9: MARIAM MOHAMMED BELLO | C9: SA- SPECIAL DUTIES | D9: 16 (9) | E9: 700000 | G9: =E9 -> 700000
A10: 4 | B10: DR IKEME ARTHUR J.O | C10: DEPUTY DIRECTOR, M&E | D10: 16 (9) | E10: 700000 | G10: =E10 -> 700000
A11: 5 | B11: MOSHOOD M. OLALERE | C11: DEPUTY DIR. GENERAL SERVICE | D11: 16 (9) | E11: 700000 | G11: =E11 -> 700000
A12: 6 | B12: REKIYA IBRAHIM ATTAH | C12: DEPUTY DIRECTOR TRAINING | D12: 16 (9) | E12: 700000 | G12: =E12 -> 700000
A13: 7 | B13: ANDRAWUS MUSA | C13: ASST. DIRECTOR, STORES | D13: 15(9) | E13: 700000 | G13: =E13 -> 700000
A14: 8 | B14: DR FRANCIS NDUM OJIE | C14: AD, TRAINING & IC./SA TO DG | D14: 15(7) | E14: 700000 | G14: =E14 -> 700000
A15: 9 | B15: ALI ABDULLAHI | C15: CHIEF ICT OFFICER | D15: 14(11) | E15: 500000 | G15: =E15 -> 500000
A16: 10 | B16: EMILY EKHIDE | C16: RESEARCH FELLOW 1 | D16: 14(10) | E16: 500000 | G16: =E16 -> 500000
A17: 11 | B17: ABDULSALAM S. MUSTAPHA | C17: ASST. MANAGER ICT | D17: 13(11) | E17: 500000 | F17: =E17 -> 500000
A18: 12 | B18: PERCY TERFA GBAHABO | C18: HEAD, NILDS LIAISON OFFICE | D18: 13(10) | E18: 500000 | F18: =E18 -> 500000
A19: 13 | B19: HASSANA AHMED IBRAHIM | C19: PA- TO DG | D19: 13 (9) | E19: 500000 | F19: =E19 -> 500000
A20: 14 | B20: ADUGBA RICHARD TERSEER | C20: PRINCIPAL INFO. OFFICER | D20: 12(9) | E20: 400000 | F20: =E20 -> 400000
A21: 15 | B21: LUCKY AGWOM | C21: RESEARCH ASSISTANT | D21: 12(7) | E21: 400000 | F21: =E21 -> 400000
A22: 16 | B22: FARUQ ATOFARATI | C22: PA (SPECIAL DUTIES) TO DG | D22: 10(7) | E22: 300000 | F22: =E22 -> 300000
A23: 17 | B23: ELIZABETH OGECHUKWU ONYEAKU | C23: ICT OFFICER | D23: 9(9) | E23: 300000 | F23: =E23 -> 300000
A24: 18 | B24: VICTOR ASUKWO | C24: ICT OFFICER | D24: 9(9) | E24: 300000 | F24: =E24 -> 300000
A25: 19 | B25: ABDULRAHMAN A SULAIMAN | C25: STORE OFFICER | D25: 9(8) | E25: 300000 | F25: =E25 -> 300000
A26: 20 | B26: DARE SHEU MAGBON | C26: ADMINISTRATION OFFICER | D26: 9(7) | E26: 300000 | F26: =E26 -> 300000
A27: 21 | B27: JIMOH ADEBAYO ZAKA | C27: ASST. OFFICER/COMM | D27: 9(8) | E27: 300000 | F27: =E27 -> 300000
A28: 22 | B28: MOHAMMED BELLO | C28: PROTOCOL ASSISTANT | D28: 8(9) | E28: 300000 | F28: =E28 -> 300000
... A30: 24 | B30: HARUNA JIBRIL AMEH | C30: ASST. ADMIN. OFFICER | D30: 8(8) | E30: 300000 | F30: =E30 -> 300000
B31: TOTAL | C31: 24 | E31: =SUM(E7:E30) -> 12550000 | F31: =SUM(F7:F30) -> 5000000 | G31: =SUM(G7:G30) -> 7550000
B33: INTERNAL AUDIT
A34: 1 | B34: OSANAIYE DAVID AKINYEMI | C34: DIRECTOR INTERNAL AUDIT | D34: 17(9) | E34: 1000000 | G34: =E34 -> 1000000
A35: 2 | B35: JAMILA ABDUL | C35: AUDITOR II | D35: 8(8) | E35: 300000 | F35: =E35 -> 300000
A36: 3 | B36: IJEOMA EWELUKWA | C36: AUDIT OFFICER | D36: 10(8) | E36: 300000 | F36: =E36 -> 300000
C37: 3 | E37: =SUM(E34:E36) -> 1600000 | F37: =SUM(F34:F36) -> 600000 | G37: =SUM(G34:G36) -> 1000000
B39: LEG. SUPPORT SEVICES
A40: 1 | B40: PROF. EDOBA BRIGHT OMOREGBE | C40: AG. DLSS | D40: 17(9) | E40: 1000000 | G40: =E40 -> 1000000
A41: 2 | B41: DR CLINTON JAJA | C41: SENIOR RESEARCH FELLOW | D41: 15(9) | E41: 700000 | G41: =E41 -> 700000
A42: 3 | B42: BETHEL UZOMA IHUGBA | C42: DEPUTY DIRECTOR, LEGAL RESEARCH | D42: 16(8) | E42: 700000 | G42: =E42 -> 700000
A43: 4 | B43: OGUCHE SAMUEL | C43: SNR RESEARCH FELLOW | D43: 15(9) | E43: 700000 | G43: =E43 -> 700000
A44: 5 | B44: IBRAHIM USMAN | C44: SNR RESEARCH FELLOW | D44: 15(9) | E44: 700000 | G44: =E44 -> 700000
A45: 6 | B45: DR MOHAMMED O. AMALI | C45: SNR RESEARCH FELLOW | D45: 15(7) | E45: 700000 | G45: =E45 -> 700000
A46: 7 | B46: YAHAYA SHAMSU | C46: RESEARCH FELLOW 1 | D46: 14(10) | E46: 500000 | G46: =E46 -> 500000
A47: 8 | B47: DORIS DAKDA AARON | C47: RESEARCH FELLOW I | D47: 14(8) | E47: 500000 | G47: =E47 -> 500000
A48: 9 | B48: BILKIS S. LAWAL-GAMBARI | C48: RESEARCH OFFICER | D48: 10(8) | E48: 300000 | F48: =E48 -> 300000
A49: 10 | B49: ZAINAB AKINDE | C49: RESEARCH OFFICER | D49: 9(8) | E49: 300000 | F49: =E49 -> 300000
A50: 11 | B50: ABDULLAHI AHMAD USMAN | C50: RESEARCH OFFICER | D50: 9(8) | E50: 300000 | F50: =E50 -> 300000
A51: 12 | B51: GUNAT NANSAK MARK | C51: RESEARCH OFFICER | D51: 9(8) | E51: 300000 | F51: =E51 -> 300000
B52: TOTAL | C52: 12 | E52: =SUM(E40:E51) -> 6700000 | F52: =SUM(F40:F51) -> 1200000 | G52: =SUM(G40:G51) -> 5500000
B54: LEGAL SERVICES
A55: 1 | B55: DR SHUIBU DANWANKA | C55: DIRECTOR LEGAL SERVICES | D55: 17(9) | E55: 500000 | G55: =E55 -> 500000
A56: 2 | B56: ABDULSALAM BAKO | C56: MANAGER, LEGAL SERVICES | D56: 15 (9) | E56: 700000 | G56: =E56 -> 700000
B57: TOTAL | C57: 2 | E57: =SUM(E55:E56) -> 1200000 | G57: =SUM(G55:G56) -> 1200000
B59: DEMOCRACY & GOVERNANCE
A60: 1 | B60: DR. ADEWALE ADEREMI | C60: DIRECTOR, DEMOCRATIC STUDIES | D60: 17(9) | E60: 500000 | G60: =E60 -> 500000
A61: 2 | B61: NDANUSA MOHAMMED MANZUMA | C61: SNR RESEARCH FELLOW | D61: 15(8) | E61: 350000 | G61: =E61 -> 350000
A62: 3 | B62: EJALONIBU GANIYU LAYI | C62: RESEARCH FELLOW 1 | D62: 14(8) | E62: 500000 | G62: =E62 -> 500000
A63: 4 | B63: LOHNA BONKAT JONATHAN | C63: RESEARCH FELLOW 11 | D63: 13(10) | E63: 500000 | F63: =E63 -> 500000
A64: 5 | B64: YUNUSA ABDULLAHI | C64: RESEARCH FELLOW 1 | D64: 14(11) | E64: 500000 | G64: =E64 -> 500000
A65: 7 | B65: UDEFUNA NNADOZIE PATRICK | C65: RESEARCH OFFICER | D65: 12(8) | E65: 400000 | F65: =E65 -> 400000
A66: 8 | B66: SHAFIU YAHYA MIKAIL | C66: PRINCIPAL RESEARCH OFFICER | D66: 12(8) | E66: 400000 | F66: =E66 -> 400000
A67: 9 | B67: HASSAN YERIMA | C67: PRINCIPAL RESEARCH OFFICER | D67: 12(8) | E67: 400000 | F67: =E67 -> 400000
A68: 10 | B68: HAUWA PATE SADIQ | C68: PRINCIPAL PROGRAMME OFFICER | D68: 12(9) | E68: 400000 | F68: =E68 -> 400000
A69: 11 | B69: KOLAPO Q. ABAYOMI | C69: RESEARCH OFFICER | D69: 10(8) | E69: 300000 | F69: =E69 -> 300000
A70: 12 | B70: NNANDI LIVINUS ATURE | C70: RESEARCH ASSISTANT | D70: 9(9) | E70: 300000 | F70: =E70 -> 300000
B71: TOTAL | C71: 12 | E71: =SUM(E60:E70) -> 4550000 | F71: =SUM(F60:F70) -> 2700000 | G71: =SUM(G60:G70) -> 1850000
B73: DEPARTMENT OF STUDIES
A74: 1 | B74: DR ASIMIYU G. ABIOLA | C74: DIRECTOR POST GRADUATE | D74: 17(9) | E74: 1000000 | G74: =E74 -> 1000000
A75: 2 | B75: USMAN WALI | C75: SENIOR RESEARCH FELLOW | D75: 15 (8) | E75: 700000 | G75: =E75 -> 700000
A76: 3 | B76: AYOBOLU OLAJIDE OLUFUNSHO | C76: ASST.DIR., INFORMATION | D76: 15 (9) | E76: 700000 | G76: =E76 -> 700000
A77: 4 | B77: ANTHONY EDET | C77: CHIEF PROGRAMMES OFFICER | D77: 14(9) | E77: 500000 | G77: =E77 -> 500000
A78: 5 | B78: IGWE STACY | C78: PROGRAMME OFFICER | D78: 10(9) | E78: 300000 | F78: =E78 -> 300000
A79: 6 | B79: OLANIYAN TAIWO ABINBOLA | C79: PROGRAMME OFFICER | D79: 9(8) | E79: 300000 | F79: =E79 -> 300000
A80: 7 | B80: AMINAT JUMOKE SULAIMON | C80: AST. PROGRAMME OFFICER | D80: 8(8) | E80: 300000 | F80: =E80 -> 300000
B81: TOTAL | C81: 7 | E81: =SUM(E74:E80) -> 3800000 | F81: =SUM(F74:F80) -> 900000 | G81: =SUM(G74:G80) -> 2900000
B83: ECON. DEV. & SOC. RESEARCH
A84: 1 | B84: TERFA WILLIAMS ABRAHAM | C84: SNR RESEARCH FELLOW | D84: 15(9) | E84: =700000 -> 700000 | G84: =E84 -> 700000
A85: 2 | B85: DR AUGUSTINE C. OSIGWE | C85: SNR RESEARCH FELLOW | D85: 15(9) | E85: =700000 -> 700000 | G85: =E85 -> 700000
A86: 3 | B86: NGARA CHRISTOPHER OCHANJA | C86: SNR RESEARCH FELLOW | D86: 15(8) | E86: =700000 -> 700000 | G86: =E86 -> 700000
A87: 4 | B87: OMOJU OLUWASOLA EMMANUEL | C87: SNR RESEARCH FELLOW | D87: 15(7) | E87: =700000 -> 700000 | G87: =E87 -> 700000
A88: 5 | B88: IBE EZECHI CYRIACUS | C88: RESEARCH FELLOW II | D88: 13(11) | E88: 500000 | F88: =E88 -> 500000
A89: 6 | B89: OSIKHEN LEO IGBANOI | C89: RESEARCH FELLOW 11 | D89: 13(10) | E89: 500000 | F89: =E89 -> 500000
A90: 7 | B90: OKUNGBOWA OSARETIN GODSPOWER | C90: RESEARCH FELLOW 1 | D90: 14(7) | E90: 250000 | G90: =E90 -> 250000
A91: 8 | B91: YUSUF IBRAHIM | C91: PRINCIPAL RESEARCH OFFICER | D91: 12(8) | E91: 400000 | F91: =E91 -> 400000
A92: 9 | B92: MUSTAPHA RAFIU AYOBANJI | C92: PRINCIPAL RESEARCH OFFICER | D92: 12(7) | E92: 400000 | F92: =E92 -> 400000
A93: 10 | B93: MARYAM MUSA SADA | C93: ASSIT. RESEARCH OFFICER | D93: 10(8) | E93: 300000 | F93: =E93 -> 300000
A94: 11 | B94: CHARITY EZENWAJIOBI | C94: REASEARCH. ASST. | D94: 8(9) | E94: 300000 | F94: =E94 -> 300000
B95: TOTAL | C95: 11 | E95: =SUM(E84:E94) -> 5450000 | F95: =SUM(F84:F94) -> 2400000 | G95: =SUM(G84:G94) -> 3050000
B97: TRAINING & INT''L COOP
A98: 1 | B98: AKINSANMI ADEJOKE OLUKEMI | C98: Ag. DIR. TRAINING & IC | D98: 16(9) | E98: 700000 | G98: 700000
A99: 2 | B99: MOHAMMED R. ADAMU | C99: CHIEF TRAINING OFFICER | D99: 14(9) | E99: 500000 | G99: 500000
A100: 3 | B100: OKECHUKWU UCHENNA HULDA | C100: PRINCIPALTRAINING OFFICER | D100: 12(9) | E100: 400000 | F100: 400000
A101: 4 | B101: TASSNEEM IBRAHIM | C101: SENIOR PROGRAMME OFFICER | D101: 10(8) | E101: 300000 | F101: 300000
B102: TOTAL | C102: 4 | E102: =SUM(E98:E101) -> 1900000 | F102: =SUM(F98:F101) -> 700000 | G102: =SUM(G98:G101) -> 1200000
B104: LIBRARY & DOCUMENTATION
A105: 1 | B105: DR MAIMUNA IZAH | C105: INSITUTE LIBRARIAN | D105: 17(9) | E105: 1000000 | G105: =E105 -> 1000000
A106: 2 | B106: CATHERINE E. IKOKOH | C106: SNR RESEARCH FELLOW DOCU | D106: 16(9) | E106: 700000 | G106: =E106 -> 700000
A107: 3 | B107: ALIYU SANNI ABUBAKAR | C107: RESEARCH FELLOW 11 DATA & DOCU | D107: 13(11) | E107: 500000 | F107: =E107 -> 500000
A108: 4 | B108: CHINAKO N. ASOGWA | C108: RESEARCH FELLOW 11 DATA & DOCU | D108: 13(11) | E108: 500000 | F108: =E108 -> 500000
A109: 5 | B109: AMOS ABA | C109: LIBRARY ASSISTANT | D109: 8(12) | E109: 300000 | F109: =E109 -> 300000
A110: 6 | B110: TITILAYO DANIEL MARVELLOUS | C110: LIBRARY ASSISTANT | D110: 8(11) | E110: 300000 | F110: =E110 -> 300000
...

Sheet PROMOTIONS 
A1: NATIONAL INSTITUTE FOR LEGISLATIVE AND DEMOCRATIC STUDIES | G1: ='[1]FEB 08'!F8/'[1]FEB 08'!Q8 -> 0.3
A2: STAFF PAYROLL FOR THE MONTH OF NOVEMBER 2023
E3: ='[1]FEB 08'!E11/'[1]FEB 08'!M11 -> #REF! | G3: ='[1]FEB 08'!F11/'[1]FEB 08'!Q11 -> #REF!
B4: STAFF NAME | C4: DESIGNATION | D4: CURRENT GRADE LEVEL | E4: BASIC SALARY | F4: RENT | G4: UTILITY | H4: DOMESTIC | I4: ENTERT. | J4: FURNIT. | K4: FUEL | L4: ALLOWANCE | M4: ALLOWANCE | N4: ALLCE | O4: ALLCE | P4: DUTY ALLCE | Q4: CURRENT GROSS SALARY | R4: NEW GRADE LEVEL | S4: NEW GROSS SALARY | T4: INCREMENT IN GROSS SALARY | U4: CURRENT NHF | V4: NEW NHF | W4: CURRENT PAYE | X4: NEW PAYE | Y4: INCREMENT IN PAYE | Z4: NET SALARY INCREMENT | AA4: NO OF MONTHS | AB4: ARREARS
E5: N | F5: N | G5: N | H5: N | I5: N | J5: N | K5: N | L5: N | M5: N | N5: N | O5: N | P5: N | Q5: N | S5: N | U5: N | W5: N
A6: S/N | B6: DG'S OFFICE
A7: 1 | B7: SHEU MAGABON DARE | C7: ADMIN ASSISTANT | D7: 8(10) | E7: 13492.21 | G7: =E7*300% -> 40476.63 | H7: =E7*7.5% -> 1011.9157 | J7: =E7*50% -> 6746.105 | K7: =E7*350% -> 47222.735 | L7: =E7*100% -> 13492.21 | N7: =50000 -> 50000 | O7: =E7*10% -> 1349.221 | P7: 10000 | Q7: =SUM(E7:Q7) -> 183791.03 | R7: 9(7) | S7: =205204.08 -> 205204.08 | T7: =205204.08-183791.03 -> 21413.05 | W7: 18102.9 | X7: =21640.88 -> 21640.88 | Y7: =X7-W7 -> 3537.98 | Z7: =T7-Y7 -> 17875.07 | AA7: =8/30 -> 0.26666667 | AB7: =Z7*AA7 -> 4766.6853
B8: TOTAL | E8: =SUM(E7:E7) -> 13492.21 | F8: =SUM(F7:F7) -> 0 | G8: =SUM(G7:G7) -> 40476.63 | H8: =SUM(H7:H7) -> 1011.9157 | I8: =SUM(I7:I7) -> 0 | J8: =SUM(J7:J7) -> 6746.105 | K8: =SUM(K7:K7) -> 47222.735 | L8: =SUM(L7:L7) -> 13492.21 | ... P8: =SUM(P7:P7) -> 10000 | Q8: =E8+F8+G8+H8+I8+J8+K8+L8+M8+N8+O8+P8 -> 183791.03 | S8: =SUM(S7:S7) -> 205204.08 | T8: =SUM(T7:T7) -> 21413.05 | U8: =SUM(U7:U7) -> 0 | V8: =SUM(V7:V7) -> 0 | W8: =SUM(W7:W7) -> 18102.9 | X8: =SUM(X7:X7) -> 21640.88 | Y8: =SUM(Y7:Y7) -> 3537.98 | Z8: =SUM(Z7:Z7) -> 17875.07 | AB8: =SUM(AB7:AB7) -> 4766.6853
B10: LEG. SUPPORT SEVICES
A11: 2 | B11: BETHEL UZOMA IHUGBA | C11: SNR RESEARCH FELLOW | D11: 15(9) | E11: 33507.5 | G11: =E11*300% -> 100522.5 | H11: =E11*7.5% -> 2513.0625 | I11: 40122.19 | J11: =E11*50% -> 16753.75 | K11: =E11*350% -> 117276.25 | L11: =E11*100% -> 33507.5 | M11: =160000 -> 160000 | O11: =E11*10% -> 3350.75 | P11: 20000 | Q11: =SUM(E11:Q11) -> 527553.5 | R11: 16(7) | S11: ='SALARY STRUCTURE'!H19+180000 -> 604023.33 | T11: =604023.33-527553.5 -> 76469.83 | U11: =837.69 -> 837.69 | V11: =1028.94 -> 1028.94 | W11: =79956.94 -> 79956.94 | X11: =94639.15 -> 94639.15 | Y11: =X11-W11 -> 14682.21 | Z11: =T11-Y11 -> 61787.62 | AA11: 9 | AB11: =Z11*AA11 -> 556088.58
A12: 3 | B12: DR MOHAMMED O. AMALI | C12: RESEARCH FELLOW I | D12: 14(10) | E12: 27611.23 | G12: =E12*300% -> 82833.69 | H12: =E12*7.5% -> 2070.8422 | J12: =E12*50% -> 13805.615 | K12: =E12*350% -> 96639.305 | L12: =E12*100% -> 27611.23 | M12: =140000 -> 140000 | O12: =E12*10% -> 2761.123 | P12: 20000 | Q12: =SUM(E12:Q12) -> 413333.04 | R12: 15(7) | S12: ='SALARY STRUCTURE'!H18+160000 -> 504720.17 | T12: =504720.05-413333.04 -> 91387.01 | U12: 0 | W12: 57889.865 | X12: =75436.17 -> 75436.17 | Y12: =X12-W12 -> 17546.305 | Z12: =T12-Y12 -> 73840.705 | AA12: 0 | AB12: =Z12*AA12 -> 0
B13: TOTAL | E13: =SUM(E11:E12) -> 61118.73 | F13: =SUM(F11:F12) -> 0 | G13: =SUM(G11:G12) -> 183356.19 | H13: =SUM(H11:H12) -> 4583.9047 | I13: =SUM(I11:I12) -> 40122.19 | J13: =SUM(J11:J12) -> 30559.365 | K13: =SUM(K11:K12) -> 213915.55 | L13: =SUM(L11:L12) -> 61118.73 | ... AB13: =SUM(AB11:AB12) -> 556088.58
T14: =S14-Q14 -> 0
Y15: =X15-W15 -> 0 | Z15: =T15-Y15 -> 0 | AB15: =Z15*AA15 -> 0
B16: FINANCE & ACCOUNTS | Y16: =X16-W16 -> 0 | Z16: =T16-Y16 -> 0 | AB16: =Z16*AA16 -> 0
A17: 3 | B17: RAHILA NURUDEEN HABU | C17: ASST. DIRECTOR, ACCOUNTS | D17: 15(9) | E17: 33507.5 | G17: =E17*300% -> 100522.5 | H17: =E17*7.5% -> 2513.0625 | I17: 40122.19 | J17: =E17*50% -> 16753.75 | K17: =E17*350% -> 117276.25 | L17: =E17*100% -> 33507.5 | M17: =80000 -> 80000 | N17: =E17*10% -> 3350.75 | O17: 20000 | P17: 100000 | Q17: =SUM(E17:P17) -> 547553.5 | R17: 16(7) | S17: ='SALARY STRUCTURE'!H19+190000 -> 614023.33 | T17: =S17-Q17 -> 66469.831 | U17: =837.69 -> 837.69 | V17: =1028.94 -> 1028.94 | W17: =83626.1 -> 83626.1 | X17: =96398.31 -> 96398.31 | Y17: =X17-W17 -> 12772.21 | Z17: =T17-Y17 -> 53697.621 | AA17: 11 | AB17: =Z17*AA17 -> 590673.83
B18: OJOGIWA ABISOLA GANIAT | C18: ASST. CHIEF BUDGET OFFICER | D18: 13(10) | E18: 25523.45 | G18: =E18*300% -> 76570.35 | H18: =E18*7.5% -> 1914.2587 | J18: =E18*50% -> 12761.725 | K18: =E18*350% -> 89332.075 | L18: =E18*100% -> 25523.45 | N18: =70000 -> 70000 | O18: =E18*10% -> 2552.345 | P18: 15000 | Q18: =SUM(E18:Q18) -> 319177.65 | R18: 14 (7) | S18: ='JANUARY 2024'!R127 -> 335272.06 | T18: =327211.37-319177.65 -> 8033.72 | U18: 638.09 | V18: 690.28 | W18: 40684.6 | X18: 42034.24 | Y18: =X18-W18 -> 1349.64 | Z18: =T18-Y18 -> 6684.08 | AA18: 0 | AB18: =Z18*AA18 -> 0
B19: TOTAL | E19: =SUM(E17:E17) -> 33507.5 | F19: =SUM(F17:F17) -> 0 | G19: =SUM(G17:G17) -> 100522.5 | H19: =SUM(H17:H17) -> 2513.0625 | I19: =SUM(I17:I17) -> 40122.19 | J19: =SUM(J17:J17) -> 16753.75 | K19: =SUM(K17:K17) -> 117276.25 | L19: =SUM(L17:L17) -> 33507.5 | M19: =SUM(#REF!) -> #REF! | N19: =SUM(M17:M17) -> 80000 | O19: =SUM(N17:N17) -> 3350.75 | P19: =SUM(O17:O17) -> 20000 | Q19: =SUM(P17:P17) -> 100000 | S19: =SUM(S17:S17) -> 614023.33 | T19: =SUM(T17:T17) -> 66469.831 | U19: =SUM(U17:U17) -> 837.69 | V19: =SUM(V17:V17) -> 1028.94 | W19: =SUM(W17:W17) -> 83626.1 | X19: =SUM(X17:X17) -> 96398.31 | Y19: =SUM(Y17:Y17) -> 12772.21 | Z19: =SUM(Z17:Z17) -> 53697.621 | AB19: =SUM(AB17:AB17) -> 590673.83
B21: FINANCE & ACCOUNTS
A22: 15 | B22: YUNUSA ABDULMUMINI ELEOJO | C22: SENIOR DRIVER | D22: 5(11) | E22: 5428.12 | F22: =E22*300% -> 16284.36 | G22: =E22*7.5% -> 407.109 | I22: =E22*50% -> 2714.06 | J22: =E22*350% -> 18998.42 | K22: =E22*100% -> 5428.12 | M22: =20000 -> 20000 | N22: =E22*10% -> 542.812 | O22: 5000 | P22: =7000 -> 7000 | Q22: =SUM(E22:P22) -> 81803.001 | R22: 7(3) | S22: ='SALARY STRUCTURE'!#REF!+30000 -> #REF! | T22: =S22-Q22 -> #REF! | W22: 4365.3308 | X22: ='[6]October 2023'!$Z$164 -> 8312.59 | Y22: =X22-W22 -> 3947.2592 | Z22: =T22-Y22 -> #REF! | AA22: =(10/31)+2 -> 2.3225806 | AB22: =Z22*AA22 -> #REF!
A23: 16 | B23: JOHN GIMAH | C23: SENIOR DRIVER | D23: 5(11) | E23: 5428.12 | F23: =E23*300% -> 16284.36 | G23: =E23*7.5% -> 407.109 | I23: =E23*50% -> 2714.06 | J23: =E23*350% -> 18998.42 | K23: =E23*100% -> 5428.12 | M23: =20000 -> 20000 | N23: =E23*10% -> 542.812 | O23: 5000 | P23: =7000 -> 7000 | Q23: =SUM(E23:P23) -> 81803.001 | R23: 7(3) | S23: ='SALARY STRUCTURE'!#REF!+30000 -> #REF! | T23: =S23-Q23 -> #REF! | W23: =4365.33075466667 -> 4365.3308 | X23: ='[6]October 2023'!$Z$164 -> 8312.59 | Y23: =X23-W23 -> 3947.2592 | Z23: =T23-Y23 -> #REF! | AA23: =(17/31)+1 -> 1.5483871 | AB23: =Z23*AA23 -> #REF!
A24: 17 | B24: ABUBAKAR MUSA DANLAMI | C24: SENIOR DRIVER | D24: 5(12) | E24: =5598.92 -> 5598.92 | F24: =E24*300% -> 16796.76 | G24: =E24*7.5% -> 419.919 | I24: =E24*50% -> 2799.46 | J24: =E24*350% -> 19596.22 | K24: =E24*100% -> 5598.92 | M24: =20000 -> 20000 | N24: =E24*10% -> 559.892 | O24: 5000 | P24: =7000 -> 7000 | Q24: =SUM(E24:P24) -> 83370.091 | R24: 7(3) | S24: 115104.92 | T24: =S24-Q24 -> 31734.826 | W24: 4504.4109 | X24: ='[6]October 2023'!$Z$164 -> 8312.59 | Y24: =X24-W24 -> 3808.1791 | Z24: =T24-Y24 -> 27926.647 | AA24: 8 | AB24: =Z24*AA24 -> 223413.17
L25: =226713.38+70000 -> 296713.38
B27: GRAND TOTAL | E27: =E19+E13+E8 -> 108118.44 | F27: =F19+F13+F8 -> 0 | G27: =G19+G13+G8 -> 324355.32 | H27: =H19+H13+H8 -> 8108.883 | I27: =I19+I13+I8 -> 80244.38 | J27: =J19+J13+J8 -> 54059.22 | K27: =K19+K13+K8 -> 378414.54 | L27: =L19+L13+L8 -> 108118.44 | ... AB27: =AB19+AB13+AB8 -> 1151529.1

Sheet CHRISTMAS WELFARE
A1: NATIONAL INSTITUTE FOR LEGISLATIVE AND DEMOCRATIC STUDIES
A2: STAFF CHRISTMAS WELFARE DECEMBER 2023
E3: ='[1]FEB 08'!E11/'[1]FEB 08'!M11 -> #REF!
B4: STAFF NAME | C4: DESIGNATION | D4: GRADE LEVEL | E4: AMOUNT
E5: N
A6: S/N | B6: DG'S OFFICE
A7: 1 | B7: PROF. ABUBAKAR O. SULAIMAN | C7: DIRECTOR GENERAL | D7: CONSOL | E7: 540000
A8: 2 | B8: RAHEEM USMAN AYIGORO | C8: SA-INFRASTRUCTURE | D8: 16 (9) | E8: 180000
A9: 3 | B9: MARIAM MOHAMMED BELLO | C9: SA- SPECIAL DUTIES | D9: 16(8) | E9: 180000
A10: 4 | B10: DR IKEME ARTHUR J.O | C10: DEPUTY DIRECTOR, M&E | D10: 16(8) | E10: 180000
A11: 5 | B11: MOSHOOD M. OLALERE | C11: DEPUTY DIR. GENERAL SERVICE | D11: 16(8) | E11: 180000
A12: 6 | B12: REKIYA IBRAHIM ATTAH | C12: DEPUTY DIRECTOR TRAINING | D12: 16(8) | E12: 180000
A13: 7 | B13: ANDRAWUS MUSA | C13: ASST. DIRECTOR, STORES | D13: 15(9) | E13: 126000
A14: 8 | B14: DR FRANCIS NDUM OJIE | C14: AD, TRAINING & IC./SA TO DG | D14: 15(7) | E14: 126000
A15: 9 | B15: ALI ABDULLAHI | C15: CHIEF ICT OFFICER | D15: 14(10) | E15: =90000 -> 90000
A16: 10 | B16: EMILY EKHIDE | C16: RESEARCH FELLOW 1 | D16: 14(9) | E16: =90000 -> 90000
A17: 11 | B17: ABDULSALAM S. MUSTAPHA | C17: ASST. MANAGER ICT | D17: 13(11) | E17: =90000 -> 90000
A18: 12 | B18: PERCY TERFA GBAHABO | C18: HEAD, NILDS LIAISON OFFICE | D18: 13(9) | E18: =90000 -> 90000
A19: 13 | B19: HASSANA AHMED IBRAHIM | C19: PA- TO DG | D19: 13 (8) | E19: =90000 -> 90000
A20: 14 | B20: ADUGBA RICHARD TERSEER | C20: PRINCIPAL INFO. OFFICER | D20: 12(8) | E20: 54000
A21: 15 | B21: LUCKY AGWOM | C21: RESEARCH ASSISTANT | D21: 12(7) | E21: 54000
A22: 16 | B22: FARUQ ATOFARATI | C22: PA (SPECIAL DUTIES) TO DG | D22: 10(7) | E22: 54000
A23: 17 | B23: ELIZABETH OGECHUKWU ONYEAKU | C23: ICT OFFICER | D23: 9(8) | E23: 54000
A24: 18 | B24: VICTOR ASUKWO | C24: ICT OFFICER | D24: 9(8) | E24: 54000
A25: 19 | B25: ABDULRAHMAN A SULAIMAN | C25: STORE OFFICER | D25: 9(7) | E25: 54000
A26: 20 | B26: DARE SHEU MAGBON | C26: ADMINISTRATION OFFICER | D26: 9(7) | E26: 54000
A27: 21 | B27: JIMOH ADEBAYO ZAKA | C27: ASST. OFFICER/COMM | D27: 9(8) | E27: 54000
A28: 22 | B28: MOHAMMED BELLO | C28: PROTOCOL ASSISTANT | D28: 8(8) | E28: 54000
A29: 23 | B29: SULEIMAN ABUBAKAR SODEEQ | C29: ASST. ADMIN. OFFICER | D29: 8(8) | E29: 54000
A30: 24 | B30: HARUNA JIBRIL AMEH | C30: ASST. ADMIN. OFFICER | D30: 8(7) | E30: 54000
B31: TOTAL | C31: 24 | E31: =SUM(E7:E30) -> 2736000
B33: INTERNAL AUDIT
A34: 1 | B34: OSANAIYE DAVID AKINYEMI | C34: DIRECTOR INTERNAL AUDIT | D34: 17(9) | E34: 270000
A35: 2 | B35: JAMILA ABDUL | C35: AUDITOR II | D35: 8(7) | E35: 54000
A36: 3 | B36: IJEOMA EWELUKWA | C36: AUDIT OFFICER | D36: 10(7) | E36: 54000
C37: 3 | E37: =SUM(E34:E36) -> 378000
B39: LEG. SUPPORT SEVICES
A40: 1 | B40: PROF. EDOBA BRIGHT OMOREGBE | C40: AG. DLSS | D40: 17(9) | E40: 270000
A41: 2 | B41: BETHEL UZOMA IHUGBA | C41: DEPUTY DIRECTOR, LEGAL RESEARCH | D41: 16(7) | E41: =180000 -> 180000
A42: 3 | B42: DR CLINTON JAJA | C42: SENIOR RESEARCH FELLOW | D42: 15(9) | E42: 126000
A43: 4 | B43: OGUCHE SAMUEL | C43: SNR RESEARCH FELLOW | D43: 15(9) | E43: 126000
A44: 5 | B44: IBRAHIM USMAN | C44: SNR RESEARCH FELLOW | D44: 15(8) | E44: 126000
A45: 6 | B45: DR MOHAMMED O. AMALI | C45: SNR RESEARCH FELLOW | D45: 15(7) | E45: 126000
A46: 7 | B46: YAHAYA SHAMSU | C46: RESEARCH FELLOW 1 | D46: 14(10) | E46: 90000
A47: 8 | B47: DORIS DAKDA AARON | C47: RESEARCH FELLOW I | D47: 14(8) | E47: 90000
A48: 9 | B48: BILKIS S. LAWAL-GAMBARI | C48: RESEARCH OFFICER | D48: 10(7) | E48: 54000
A49: 10 | B49: ZAINAB AKINDE | C49: RESEARCH OFFICER | D49: 9(7) | E49: 54000
A50: 11 | B50: ABDULLAHI AHMAD USMAN | C50: RESEARCH OFFICER | D50: 9(7) | E50: 54000
A51: 12 | B51: GUNAT NANSAK MARK | C51: RESEARCH OFFICER | D51: 9(7) | E51: 54000
B52: TOTAL | C52: 12 | E52: =SUM(E40:E51) -> 1350000
B54: LEGAL SERVICES
A55: 1 | B55: DR SHUIBU DANWANKA | C55: DIRECTOR LEGAL SERVICES | D55: 17(9) | E55: 270000
A56: 2 | B56: ABDULSALAM BAKO | C56: MANAGER, LEGAL SERVICES | D56: 15 (8) | E56: 126000
B57: TOTAL | C57: 2 | E57: =SUM(E55:E56) -> 396000
B59: DEMOCRACY & GOVERNANCE
A60: 1 | B60: DR. ADEWALE ADEREMI | C60: DIRECTOR, DEMOCRATIC STUDIES | D60: 17(9) | E60: 270000
A61: 2 | B61: NDANUSA MOHAMMED MANZUMA | C61: SNR RESEARCH FELLOW | D61: 15 (7) | E61: 126000
A62: 3 | B62: EJALONIBU GANIYU LAYI | C62: RESEARCH FELLOW 1 | D62: 14(8) | E62: 90000
A63: 4 | B63: LOHNA BONKAT JONATHAN | C63: RESEARCH FELLOW 11 | D63: 13(9) | E63: 90000
A64: 5 | B64: YUNUSA ABDULLAHI | C64: RESEARCH FELLOW 1 | D64: 14(10) | E64: 90000
A65: 7 | B65: UDEFUNA NNADOZIE PATRICK | C65: RESEARCH OFFICER | D65: 12(7) | E65: 54000
A66: 8 | B66: SHAFIU YAHYA MIKAIL | C66: PRINCIPAL RESEARCH OFFICER | D66: 12(7) | E66: 54000
A67: 9 | B67: HASSAN YERIMA | C67: PRINCIPAL RESEARCH OFFICER | D67: 12(7) | E67: 54000
A68: 10 | B68: HAUWA PATE SADIQ | C68: PRINCIPAL PROGRAMME OFFICER | D68: 12(8) | E68: 54000
A69: 11 | B69: KOLAPO Q. ABAYOMI | C69: RESEARCH OFFICER | D69: 10(7) | E69: 54000
A70: 12 | B70: NNANDI LIVINUS ATURE | C70: RESEARCH ASSISTANT | D70: 9(8) | E70: 54000
B71: TOTAL | C71: 12 | E71: =SUM(E60:E70) -> 990000
B73: DEPARTMENT OF STUDIES
A74: 1 | B74: DR ASIMIYU G. ABIOLA | C74: DIRECTOR POST GRADUATE | D74: 17(9) | E74: 270000
A75: 2 | B75: USMAN WALI | C75: SENIOR RESEARCH FELLOW | D75: 15 (7) | E75: 126000
A76: 3 | B76: AYOBOLU OLAJIDE OLUFUNSHO | C76: ASST.DIR., INFORMATION | D76: 15 (8) | E76: 126000
A77: 4 | B77: ANTHONY EDET | C77: CHIEF PROGRAMMES OFFICER | D77: 14(8) | E77: 90000
A78: 5 | B78: IGWE STACY | C78: PROGRAMME OFFICER | D78: 10(8) | E78: 54000
A79: 6 | B79: OLANIYAN TAIWO ABINBOLA | C79: PROGRAMME OFFICER | D79: 9(7) | E79: 54000
A80: 7 | B80: AMINAT JUMOKE SULAIMON | C80: AST. PROGRAMME OFFICER | D80: 8(7) | E80: 54000
B81: TOTAL | C81: 7 | E81: =SUM(E74:E80) -> 774000
B83: ECON. DEV. & SOC. RESEARCH
A84: 1 | B84: TERFA WILLIAMS ABRAHAM | C84: SNR RESEARCH FELLOW | D84: 15(9) | E84: 126000
A85: 2 | B85: DR AUGUSTINE C. OSIGWE | C85: SNR RESEARCH FELLOW | D85: 15(9) | E85: 126000
A86: 3 | B86: NGARA CHRISTOPHER OCHANJA | C86: SNR RESEARCH FELLOW | D86: 15(7) | E86: 126000
A87: 4 | B87: OMOJU OLUWASOLA EMMANUEL | C87: SNR RESEARCH FELLOW | D87: 15(7) | E87: 126000
A88: 5 | B88: IBE EZECHI CYRIACUS | C88: RESEARCH FELLOW II | D88: 13(10) | E88: 90000
A89: 6 | B89: OSIKHEN LEO IGBANOI | C89: RESEARCH FELLOW 11 | D89: 13(9) | E89: 90000
A90: 7 | B90: OKUNGBOWA OSARETIN GODSPOWER | C90: RESEARCH FELLOW 1 | D90: 14(7) | E90: 90000
A91: 8 | B91: YUSUF IBRAHIM | C91: PRINCIPAL RESEARCH OFFICER | D91: 12(7) | E91: 54000
A92: 9 | B92: MUSTAPHA RAFIU AYOBANJI | C92: PRINCIPAL RESEARCH OFFICER | D92: 12(7) | E92: 54000
A93: 10 | B93: MARYAM MUSA SADA | C93: ASSIT. RESEARCH OFFICER | D93: 10(7) | E93: 54000
A94: 11 | B94: CHARITY EZENWAJIOBI | C94: REASEARCH. ASST. | D94: 8(8) | E94: 54000
B95: TOTAL | C95: 11 | E95: =SUM(E84:E94) -> 990000
B97: TRAINING & INT''L COOP
A98: 1 | B98: AKINSANMI ADEJOKE OLUKEMI | C98: Ag. DIR. TRAINING & IC | D98: 16(8) | E98: =180000 -> 180000
A99: 2 | B99: MOHAMMED R. ADAMU | C99: CHIEF TRAINING OFFICER | D99: 14(8) | E99: 90000
A100: 3 | B100: OKECHUKWU UCHENNA HULDA | C100: PRINCIPALTRAINING OFFICER | D100: 12(8) | E100: 54000
A101: 4 | B101: TASSNEEM IBRAHIM | C101: SENIOR PROGRAMME OFFICER | D101: 10(7) | E101: 54000
B102: TOTAL | C102: 4 | E102: =SUM(E98:E101) -> 378000
B104: LIBRARY & DOCUMENTATION
A105: 1 | B105: DR MAIMUNA IZAH | C105: INSITUTE LIBRARIAN | D105: 17(9) | E105: 270000
A106: 2 | B106: CATHERINE E. IKOKOH | C106: SNR RESEARCH FELLOW DOCU | D106: 16(8) | E106: 180000
A107: 3 | B107: ALIYU SANNI ABUBAKAR | C107: RESEARCH FELLOW 11 DATA & DOCU | D107: 13(11) | E107: 90000
A108: 4 | B108: CHINAKO N. ASOGWA | C108: RESEARCH FELLOW 11 DATA & DOCU | D108: 13(11) | E108: 90000
...

Sheet CHRISTMAS WELFARE 1

Sheet HALF 2023 (2)
A1: NATIONAL INSTITUTE FOR LEGISLATIVE AND DEMOCRATIC STUDIES
A2: STAFF PAYROLL FOR THE MONTH OF DECEMBER 2023
B4: STAFF NAME | C4: DESIGNATION | D4: GRADE LEVEL | E4: CONS. SALARY | F4: HALF SALARY
E5: N | F5: N
A6: S/N | B6: DG'S OFFICE
A7: 1 | B7: PROF. ABUBAKAR O. SULAIMAN | C7: DIRECTOR GENERAL | D7: CONSOL | E7: 1158849.8 | F7: =E7/2 -> 579424.92
A8: 2 | B8: RAHEEM USMAN AYIGORO | C8: SA-INFRASTRUCTURE | D8: 16 (9) | E8: 541465.02 | F8: =E8/2 -> 270732.51
A9: 3 | B9: MARIAM MOHAMMED BELLO | C9: SA- SPECIAL DUTIES | D9: 16(8) | E9: 727744 | F9: =E9/2 -> 363872
A10: 4 | B10: DR IKEME ARTHUR J.O | C10: DEPUTY DIRECTOR, M&E | D10: 16(8) | E10: 617744 | F10: =E10/2 -> 308872
A11: 5 | B11: MOSHOOD M. OLALERE | C11: DEPUTY DIR. GENERAL SERVICE | D11: 16(8) | E11: 677744 | F11: =E11/2 -> 338872
A12: 6 | B12: REKIYA IBRAHIM ATTAH | C12: DEPUTY DIRECTOR TRAINING | D12: 16(8) | E12: 627744 | F12: =E12/2 -> 313872
A13: 7 | B13: ANDRAWUS MUSA | C13: ASST. DIRECTOR, STORES | D13: 15(9) | E13: 497553.5 | F13: =E13/2 -> 248776.75
A14: 8 | B14: DR FRANCIS NDUM OJIE | C14: AD, TRAINING & IC./SA TO DG | D14: 15(7) | E14: 604729.22 | F14: =E14/2 -> 302364.61
A15: 9 | B15: ALI ABDULLAHI | C15: CHIEF ICT OFFICER | D15: 14(10) | E15: 343333.04 | F15: =E15/2 -> 171666.52
A16: 10 | B16: EMILY EKHIDE | C16: RESEARCH FELLOW 1 | D16: 14(9) | E16: 455272.06 | F16: =E16/2 -> 227636.03
A17: 11 | B17: ABDULSALAM S. MUSTAPHA | C17: ASST. MANAGER ICT | D17: 13(11) | E17: 326663.08 | F17: =E17/2 -> 163331.54
A18: 12 | B18: PERCY TERFA GBAHABO | C18: HEAD, NILDS LIAISON OFFICE | D18: 13(9) | E18: 362001.06 | F18: =E18/2 -> 181000.53
... A30: 24 | B30: HARUNA JIBRIL AMEH | C30: ASST. ADMIN. OFFICER | D30: 8(7) | E30: 173329.05 | F30: =E30/2 -> 86664.525
B31: TOTAL | C31: 24 | E31: 10062524 | F31: =SUM(F7:F30) -> 5028878.8
B33: INTERNAL AUDIT
A34: 1 | B34: OSANAIYE DAVID AKINYEMI | C34: DIRECTOR INTERNAL AUDIT | D34: 17(9) | E34: 950209.06 | F34: =E34/2 -> 475104.53
A35: 2 | B35: JAMILA ABDUL | C35: AUDITOR II | D35: 8(7) | E35: 173329.05 | F35: =E35/2 -> 86664.525
A36: 3 | B36: IJEOMA EWELUKWA | C36: AUDIT OFFICER | D36: 10(7) | E36: 228602.08 | F36: =E36/2 -> 114301.04
C37: 3 | E37: 1352140.2 | F37: =SUM(F34:F36) -> 676070.1
B39: LEG. SUPPORT SEVICES
A40: 1 | B40: PROF. EDOBA BRIGHT OMOREGBE | C40: AG. DLSS | D40: 17(9) | E40: 1050209.1 | F40: =E40/2 -> 525104.53
A41: 2 | B41: DR CLINTON JAJA | C41: SENIOR RESEARCH FELLOW | D41: 15(9) | E41: 527553.5 | F41: =E41/2 -> 263776.75
A42: 3 | B42: BETHEL UZOMA IHUGBA | C42: DEPUTY DIRECTOR, LEGAL RESEARCH | D42: 16(7) | E42: 604023.33 | F42: =E42/2 -> 302011.66
A43: 4 | B43: OGUCHE SAMUEL | C43: SNR RESEARCH FELLOW | D43: 15(9) | E43: 527553.5 | F43: =E43/2 -> 263776.75
A44: 5 | B44: IBRAHIM USMAN | C44: SNR RESEARCH FELLOW | D44: 15(8) | E44: 516137.05 | F44: =E44/2 -> 258068.53
A45: 6 | B45: DR MOHAMMED O. AMALI | C45: SNR RESEARCH FELLOW | D45: 15(7) | E45: 504720.05 | F45: =E45/2 -> 252360.02
A46: 7 | B46: YAHAYA SHAMSU | C46: RESEARCH FELLOW 1 | D46: 14(10) | E46: 413333.04 | F46: =E46/2 -> 206666.52
A47: 8 | B47: DORIS DAKDA AARON | C47: RESEARCH FELLOW I | D47: 14(8) | E47: 397211.37 | F47: =E47/2 -> 198605.68
A48: 9 | B48: BILKIS S. LAWAL-GAMBARI | C48: RESEARCH OFFICER | D48: 10(7) | E48: 268602.08 | F48: =E48/2 -> 134301.04
A49: 10 | B49: ZAINAB AKINDE | C49: RESEARCH OFFICER | D49: 9(7) | E49: 245204.08 | F49: =E49/2 -> 122602.04
A50: 11 | B50: ABDULLAHI AHMAD USMAN | C50: RESEARCH OFFICER | D50: 9(7) | E50: 245204.08 | F50: =E50/2 -> 122602.04
A51: 12 | B51: GUNAT NANSAK MARK | C51: RESEARCH OFFICER | D51: 9(7) | E51: 245204.08 | F51: =E51/2 -> 122602.04
B52: TOTAL | C52: 12 | E52: 6101043.8 | F52: =SUM(F40:F51) -> 2772477.6
B54: LEGAL SERVICES
A55: 1 | B55: DR SHUIBU DANWANKA | C55: DIRECTOR LEGAL SERVICES | D55: 17(9) | E55: 1050209.1 | F55: =E55/2 -> 525104.53
A56: 2 | B56: ABDULSALAM BAKO | C56: MANAGER, LEGAL SERVICES | D56: 15 (8) | E56: 436137.05 | F56: =E56/2 -> 218068.53
B57: TOTAL | C57: 2 | E57: 1486346.1 | F57: =SUM(F55:F56) -> 743173.06
B59: DEMOCRACY & GOVERNANCE
A60: 1 | B60: DR. ADEWALE ADEREMI | C60: DIRECTOR, DEMOCRATIC STUDIES | D60: 17(9) | E60: 1050209.1 | F60: =E60/2 -> 525104.53
A61: 2 | B61: NDANUSA MOHAMMED MANZUMA | C61: SNR RESEARCH FELLOW | D61: 15 (7) | E61: 504720.05 | F61: =E61/2 -> 252360.02
A62: 3 | B62: EJALONIBU GANIYU LAYI | C62: RESEARCH FELLOW 1 | D62: 14(8) | E62: 397211.37 | F62: =E62/2 -> 198605.68
A63: 4 | B63: LOHNA BONKAT JONATHAN | C63: RESEARCH FELLOW 11 | D63: 13(9) | E63: 362001.06 | F63: =E63/2 -> 181000.53
A64: 5 | B64: YUNUSA ABDULLAHI | C64: RESEARCH FELLOW 1 | D64: 14(10) | E64: 413333.04 | F64: =E64/2 -> 206666.52
A65: 7 | B65: UDEFUNA NNADOZIE PATRICK | C65: RESEARCH OFFICER | D65: 12(7) | E65: 315372.08 | F65: =E65/2 -> 157686.04
A66: 8 | B66: SHAFIU YAHYA MIKAIL | C66: PRINCIPAL RESEARCH OFFICER | D66: 12(7) | E66: 315372.08 | F66: =E66/2 -> 157686.04
A67: 9 | B67: HASSAN YERIMA | C67: PRINCIPAL RESEARCH OFFICER | D67: 12(7) | E67: 315372.08 | F67: =E67/2 -> 157686.04
A68: 10 | B68: HAUWA PATE SADIQ | C68: PRINCIPAL PROGRAMME OFFICER | D68: 12(8) | E68: 322454.07 | F68: =E68/2 -> 161227.04
A69: 11 | B69: KOLAPO Q. ABAYOMI | C69: RESEARCH OFFICER | D69: 10(7) | E69: 268602.08 | F69: =E69/2 -> 134301.04
A70: 12 | B70: NNANDI LIVINUS ATURE | C70: RESEARCH ASSISTANT | D70: 9(8) | E70: 249356.05 | F70: =E70/2 -> 124678.02
B71: TOTAL | C71: 12 | E71: 4514003 | F71: =SUM(F60:F70) -> 2257001.5
B73: DEPARTMENT OF STUDIES
A74: 1 | B74: DR ASIMIYU G. ABIOLA | C74: DIRECTOR POST GRADUATE | D74: 17(9) | E74: 1050209.1 | F74: =E74/2 -> 525104.53
A75: 2 | B75: USMAN WALI | C75: SENIOR RESEARCH FELLOW | D75: 15 (7) | E75: 504720.05 | F75: =E75/2 -> 252360.02
A76: 3 | B76: AYOBOLU OLAJIDE OLUFUNSHO | C76: ASST.DIR., INFORMATION | D76: 15 (8) | E76: 436137.05 | F76: =E76/2 -> 218068.53
A77: 4 | B77: ANTHONY EDET | C77: CHIEF PROGRAMMES OFFICER | D77: 14(8) | E77: 397211.37 | F77: =E77/2 -> 198605.68
A78: 5 | B78: IGWE STACY | C78: PROGRAMME OFFICER | D78: 10(8) | E78: 273169.12 | F78: =E78/2 -> 136584.56
A79: 6 | B79: OLANIYAN TAIWO ABINBOLA | C79: PROGRAMME OFFICER | D79: 9(7) | E79: 245204.08 | F79: =E79/2 -> 122602.04
A80: 7 | B80: AMINAT JUMOKE SULAIMON | C80: AST. PROGRAMME OFFICER | D80: 8(7) | E80: 223338.22 | F80: =E80/2 -> 111669.11
B81: TOTAL | C81: 7 | E81: 3129989 | F81: =SUM(F74:F80) -> 1564994.5
B83: ECON. DEV. & SOC. RESEARCH
A84: 1 | B84: TERFA WILLIAMS ABRAHAM | C84: SNR RESEARCH FELLOW | D84: 15(9) | E84: 627553.5 | F84: =E84/2 -> 313776.75
A85: 2 | B85: DR AUGUSTINE C. OSIGWE | C85: SNR RESEARCH FELLOW | D85: 15(9) | E85: 527553.5 | F85: =E85/2 -> 263776.75
A86: 3 | B86: NGARA CHRISTOPHER OCHANJA | C86: SNR RESEARCH FELLOW | D86: 15(7) | E86: 504720.05 | F86: =E86/2 -> 252360.02
A87: 4 | B87: OMOJU OLUWASOLA EMMANUEL | C87: SNR RESEARCH FELLOW | D87: 15(7) | E87: 504729.22 | F87: =E87/2 -> 252364.61
A88: 5 | B88: IBE EZECHI CYRIACUS | C88: RESEARCH FELLOW II | D88: 13(10) | E88: 369177.65 | F88: =E88/2 -> 184588.83
A89: 6 | B89: OSIKHEN LEO IGBANOI | C89: RESEARCH FELLOW 11 | D89: 13(9) | E89: 362001.06 | F89: =E89/2 -> 181000.53
A90: 7 | B90: OKUNGBOWA OSARETIN GODSPOWER | C90: RESEARCH FELLOW 1 | D90: 14(7) | E90: 389153.06 | F90: =E90/2 -> 194576.53
A91: 8 | B91: YUSUF IBRAHIM | C91: PRINCIPAL RESEARCH OFFICER | D91: 12(7) | E91: 315372.08 | F91: =E91/2 -> 157686.04
A92: 9 | B92: MUSTAPHA RAFIU AYOBANJI | C92: PRINCIPAL RESEARCH OFFICER | D92: 12(7) | E92: 315372.08 | F92: =E92/2 -> 157686.04
A93: 10 | B93: MARYAM MUSA SADA | C93: ASSIT. RESEARCH OFFICER | D93: 10(7) | E93: 268602.08 | F93: =E93/2 -> 134301.04
A94: 11 | B94: CHARITY EZENWAJIOBI | C94: REASEARCH. ASST. | D94: 8(8) | E94: 223709.11 | F94: =E94/2 -> 111854.55
B95: TOTAL | C95: 11 | E95: 4407943.4 | F95: =SUM(F84:F94) -> 2203971.7
B97: TRAINING & INT''L COOP
A98: 1 | B98: AKINSANMI ADEJOKE OLUKEMI | C98: Ag. DIR. TRAINING & IC | D98: 16(8) | E98: 527744 | F98: =E98/2 -> 263872
A99: 2 | B99: MOHAMMED R. ADAMU | C99: CHIEF TRAINING OFFICER | D99: 14(8) | E99: 327211.37 | F99: =E99/2 -> 163605.68
A100: 3 | B100: OKECHUKWU UCHENNA HULDA | C100: PRINCIPALTRAINING OFFICER | D100: 12(8) | E100: 272454.07 | F100: =E100/2 -> 136227.04
A101: 4 | B101: TASSNEEM IBRAHIM | C101: SENIOR PROGRAMME OFFICER | D101: 10(7) | E101: 228602.08 | F101: =E101/2 -> 114301.04
B102: TOTAL | C102: 4 | E102: 1813825.7 | F102: =SUM(F98:F101) -> 678005.76
B104: LIBRARY & DOCUMENTATION
A105: 1 | B105: DR MAIMUNA IZAH | C105: INSITUTE LIBRARIAN | D105: 17(9) | E105: 1050209.1 | F105: =E105/2 -> 525104.53
A106: 2 | B106: CATHERINE E. IKOKOH | C106: SNR RESEARCH FELLOW DOCU | D106: 16(8) | E106: 617744 | F106: =E106/2 -> 308872
A107: 3 | B107: ALIYU SANNI ABUBAKAR | C107: RESEARCH FELLOW 11 DATA & DOCU | D107: 13(11) | E107: 418096.02 | F107: =E107/2 -> 209048.01
A108: 4 | B108: CHINAKO N. ASOGWA | C108: RESEARCH FELLOW 11 DATA & DOCU | D108: 13(11) | E108: 416483.19 | F108: =E108/2 -> 208241.6
A109: 5 | B109: AMOS ABA | C109: LIBRARY ASSISTANT | D109: 8(11) | E109: 262612.72 | F109: =E109/2 -> 131306.36
A110: 6 | B110: TITILAYO DANIEL MARVELLOUS | C110: LIBRARY ASSISTANT | D110: 8(10) | E110: 258740.8 | F110: =E110/2 -> 129370.4
A111: 7 | B111: ENENCHE JEREMIAH AGADA | C111: LIBRARY ASSISTANT | D111: 8(8) | E111: 251382.3 | F111: =E111/2 -> 125691.15
B112: TOTAL | C112: 7 | E112: 3275268.1 | F112: =SUM(F105:F111) -> 1637634
B114: LEG, CTRE FOR SEC. ANALYSIS
A115: 1 | B115: EGUATU U. ONYEJELEM | C115: PRINCIPAL M&E OFFICER | D115: 12(8) | E115: 322454.07 | F115: =E115/2 -> 161227.04
A116: 2 | B116: CHRISTIAN MADUABUCHI ODO | C116: PRINCIPAL ICT OFFICER | D116: 12(9) | E116: 284537 | F116: =E116/2 -> 142268.5
B117: TOTAL | C117: 2 | E117: 790446.85 | F117: =SUM(F115:F116) -> 303495.54
B119: FINANCE & ACCOUNTS
A120: 1 | B120: IBRAHIM M. MSHELIA | C120: DIR. FINANCE & ACCOUNTS | D120: 17(9) | E120: 1050209.1 | F120: =E120/2 -> 525104.53
A121: 2 | B121: RAHILA NURUDEEN HABU | C121: DEP. DIRECTOR, ACCOUNTS | D121: 16(7) | E121: 614023.33 | F121: =E121/2 -> 307011.66
A122: 3 | B122: TONDO IORWUESE EDWARD | C122: ASST. DIRECTOR, ACCOUNTS | D122: 15(9) | E122: 577553.5 | F122: =E122/2 -> 288776.75
...

Sheet Sheet3

Sheet NEW ENROLMENT IN NOVEMBER (2)
A1: NATIONAL INSTITUTE FOR LEGISLATIVE AND DEMOCRATIC STUDIES | G1: ='[1]FEB 08'!F8/'[1]FEB 08'!Q8 -> 0.3
A2: STAFF PAYROLL FOR THE MONTH OF NOVEMBER 2023
E3: ='[1]FEB 08'!E11/'[1]FEB 08'!M11 -> #REF! | G3: ='[1]FEB 08'!F11/'[1]FEB 08'!Q11 -> #REF!
B4: STAFF NAME | C4: DESIGNATION | D4: GRADE LEVEL | E4: BASIC SALARY | F4: ALLCE/ AREARS | G4: RENT | H4: UTILITY | I4: DOMESTIC | J4: ENTERT. | K4: FURNIT. | L4: FUEL | M4: ALLOWANCE | N4: ALLOWANCE | O4: ALLCE | P4: ALLCE | Q4: DUTY ALLCE | R4: GROSS SALARY | S4: PAYE | T4: TOTAL DEDUCTION | U4: OCTOBER, 2023 | V4: NOVEMBER, 2023 | W4: NO OF MONTHS | X4: ARREARS
E5: N | F5: N | G5: N | H5: N | I5: N | J5: N | K5: N | L5: N | M5: N | N5: N | O5: N | P5: N | Q5: N | S5: N
A6: S/N | B6: DG'S OFFICE
A7: 3 | B7: ABDULSALAM S. MUSTAPHA | C7: ASST. MANAGER ICT | D7: 13(11) | E7: 26339.3 | G7: =E7*300% -> 79017.9 | H7: =E7*7.5% -> 1975.4475 | I7: 0 | J7: =E7*50% -> 13169.65 | K7: =E7*350% -> 92187.55 | L7: =E7*100% -> 26339.3 | M7: 70000 | O7: =E7*10% -> 2633.93 | P7: 15000 | R7: =SUM(E7:Q7) -> 326663.08 | S7: =42046.06 -> 42046.06 | T7: =42046.06 -> 42046.06 | V7: =R7-T7 -> 284617.02 | W7: 1 | X7: =V7*W7 -> 284617.02
B8: TOTAL | E8: =SUM(E7:E7) -> 26339.3 | F8: =SUM(F7:F7) -> 0 | G8: =SUM(G7:G7) -> 79017.9 | H8: =SUM(H7:H7) -> 1975.4475 | I8: =SUM(I7:I7) -> 0 | J8: =SUM(J7:J7) -> 13169.65 | K8: =SUM(K7:K7) -> 92187.55 | L8: =SUM(L7:L7) -> 26339.3 | ... P8: =SUM(P7:P7) -> 15000 | R8: =SUM(R7) -> 326663.08 | S8: =SUM(S7:S7) -> 42046.06 | T8: =SUM(T7:T7) -> 42046.06 | U8: =SUM(U7:U7) -> 0 | V8: =SUM(V7:V7) -> 284617.02 | X8: =SUM(X7:X7) -> 284617.02
B10: DEM. & GOVERNANCE
A11: 10 | B11: KOLAPO Q. ABAYOMI | C11: RESEARCH OFFICER | D11: 10(7) | E11: 17286.33 | G11: =E11*300% -> 51858.99 | H11: =E11*7.5% -> 1296.4748 | J11: =E11*50% -> 8643.165 | K11: =E11*350% -> 60502.155 | L11: =E11*100% -> 17286.33 | M11: 100000 | O11: =E11*10% -> 1728.633 | P11: 10000 | R11: =SUM(E11:Q11) -> 268602.08 | S11: =32291.82 -> 32291.82 | T11: =32291.82 -> 32291.82 | V11: =R11-T11 -> 236310.26 | W11: =(25/31)+2 -> 2.8064516 | X11: =V11*W11 -> 663193.3
B12: TOTAL | E12: =SUM(E11:E11) -> 17286.33 | F12: =SUM(F11:F11) -> 0 | G12: =SUM(G11:G11) -> 51858.99 | H12: =SUM(H11:H11) -> 1296.4748 | I12: =SUM(I11:I11) -> 0 | J12: =SUM(J11:J11) -> 8643.165 | K12: =SUM(K11:K11) -> 60502.155 | L12: =SUM(L11:L11) -> 17286.33 | ... X12: =SUM(X11:X11) -> 663193.3
B14: GRAND TOTAL | E14: =E8+E12 -> 43625.63 | F14: =F8+F12 -> 0 | G14: =G8+G12 -> 130876.89 | H14: =H8+H12 -> 3271.9222 | I14: =I8+I12 -> 0 | J14: =J8+J12 -> 21812.815 | K14: =K8+K12 -> 152689.71 | L14: =L8+L12 -> 43625.63 | ... V14: =V8+V12 -> 520927.28 | X14: =X8+X12 -> 947810.32

Sheet Regularisation IN NOVEMBER (3)
A1: NATIONAL INSTITUTE FOR LEGISLATIVE AND DEMOCRATIC STUDIES | G1: ='[1]FEB 08'!F8/'[1]FEB 08'!Q8 -> 0.3
A2: STAFF PAYROLL FOR THE MONTH OF NOVEMBER 2023
E3: ='[1]FEB 08'!E11/'[1]FEB 08'!M11 -> #REF! | G3: ='[1]FEB 08'!F11/'[1]FEB 08'!Q11 -> #REF!
B4: STAFF NAME | C4: DESIGNATION | D4: GRADE LEVEL | E4: BASIC SALARY | F4: ALLCE/ AREARS | G4: RENT | H4: UTILITY | I4: DOMESTIC | J4: ENTERT. | K4: FURNIT. | L4: FUEL | M4: ALLOWANCE | N4: ALLOWANCE | O4: ALLCE | P4: ALLCE | Q4: DUTY ALLCE | R4: GROSS SALARY | S4: NEW GRADE LEVEL | T4: NEW GROSS SALARY | U4: INCREMENT IN GROSS SALARY | V4: CURRENT NHF | W4: NEW NHF | X4: CURRENT PAYE | Y4: NEW PAYE | Z4: INCREMENT IN PAYE | AA4: NET SALARY INCREMENT | AB4: NO OF MONTHS | AC4: ARREARS | AD4: ARREARS PAID IN OCTOBER | AE4: SHORTFALL IN ARREARS
E5: N | F5: N | G5: N | H5: N | I5: N | J5: N | K5: N | L5: N | M5: N | N5: N | O5: N | P5: N | Q5: N | S5: N
A6: S/N | B6: ADMIN & HR
A8: 40 | B8: YUNUSA ABDULMUMINI ELEOJO | C8: CHIEF MOTOR DRIVER MECH. | D8: 7(3) | E8: 5428.12 | G8: =E8*300% -> 16284.36 | H8: =E8*7.5% -> 407.109 | J8: =E8*50% -> 2714.06 | K8: =E8*350% -> 18998.42 | L8: =E8*100% -> 5428.12 | N8: =20000 -> 20000 | O8: =E8*10% -> 542.812 | P8: 5000 | Q8: =7000 -> 7000 | R8: =SUM(E8:Q8) -> 81803.001 | S8: 7(3) | T8: =122105 -> 122105 | U8: =T8-R8 -> 40301.999 | X8: 4365.3308 | Y8: =9152.6 -> 9152.6 | Z8: =Y8-X8 -> 4787.2692 | AA8: =U8-Z8 -> 35514.73 | AB8: =(11/31)+3 -> 3.3548387 | AC8: =AA8*AB8 -> 119146.19 | AD8: =66227.57 -> 66227.57 | AE8: =AC8-AD8 -> 52918.62
A9: 41 | B9: JOHN GIMAH | C9: CHIEF MOTOR DRIVER MECH. | D9: 7(3) | E9: 5428.12 | G9: =E9*300% -> 16284.36 | H9: =E9*7.5% -> 407.109 | J9: =E9*50% -> 2714.06 | K9: =E9*350% -> 18998.42 | L9: =E9*100% -> 5428.12 | N9: =20000 -> 20000 | O9: =E9*10% -> 542.812 | P9: 5000 | Q9: =7000 -> 7000 | R9: =SUM(E9:Q9) -> 81803.001 | S9: 7(3) | T9: =122105 -> 122105 | U9: =T9-R9 -> 40301.999 | X9: =4365.33075466667 -> 4365.3308 | Y9: =9152.6 -> 9152.6 | Z9: =Y9-X9 -> 4787.2692 | AA9: =U9-Z9 -> 35514.73 | AB9: =(17/31)+2 -> 2.5483871 | AC9: =AA9*AB9 -> 90505.279 | AD9: 44151.71 | AE9: =AC9-AD9 -> 46353.569
A10: 42 | B10: ABUBAKAR MUSA DANLAMI | C10: CHIEF MOTOR DRIVER MECH. | D10: 7(3) | E10: 5598.92 | G10: =E10*300% -> 16796.76 | H10: =E10*7.5% -> 419.919 | J10: =E10*50% -> 2799.46 | K10: =E10*350% -> 19596.22 | L10: =E10*100% -> 5598.92 | N10: =20000 -> 20000 | O10: =E10*10% -> 559.892 | P10: 5000 | Q10: =7000 -> 7000 | R10: =SUM(E10:Q10) -> 83370.091 | S10: 7(3) | T10: =122105 -> 122105 | U10: =T10-R10 -> 38734.909 | X10: 4504.4109 | Y10: =9152.6 -> 9152.6 | Z10: =Y10-X10 -> 4648.1891 | AA10: =U10-Z10 -> 34086.72 | AB10: 9 | AC10: =AA10*AB10 -> 306780.48 | AD10: 216693.09 | AE10: =AC10-AD10 -> 90087.389
AE11: =SUM(AE8:AE10) -> 189359.58
A13: 40 | B13: YUNUSA ABDULMUMINI ELEOJO | C13: CHIEF MOTOR DRIVER MECH. | D13: 7(3) | E13: =8730.79 -> 8730.79 | G13: =E13*300% -> 26192.37 | H13: =E13*7.5% -> 654.80925 | J13: =E13*50% -> 4365.395 | K13: =E13*350% -> 30557.765 | L13: =E13*100% -> 8730.79 | N13: 30000 | O13: =E13*10% -> 873.079 | P13: 5000 | Q13: =7000 -> 7000 | R13: =SUM(E13:Q13) -> 122105 | T13: =10000+5000+5000 -> 20000 | U13: =15625 -> 15625 | W13: =[7]PROMOTIONS!$X$42 -> 8312.59 | X13: =W13+V13+U13+T13+S13 -> 43937.59 | Y13: 106043.97 | Z13: =R13-X13 -> 78167.408
A14: 41 | B14: JOHN GIMAH | C14: CHIEF MOTOR DRIVER MECH. | D14: 7(3) | E14: =8730.79 -> 8730.79 | G14: =E14*300% -> 26192.37 | H14: =E14*7.5% -> 654.80925 | J14: =E14*50% -> 4365.395 | K14: =E14*350% -> 30557.765 | L14: =E14*100% -> 8730.79 | N14: 30000 | O14: =E14*10% -> 873.079 | P14: 5000 | Q14: =7000 -> 7000 | R14: =SUM(E14:Q14) -> 122105 | T14: 20000 | U14: 18333.33 | W14: =[7]PROMOTIONS!$X$42 -> 8312.59 | X14: =W14+V14+U14+T14+S14 -> 46645.92 | Y14: 80609.452 | Z14: =R14-X14 -> 75459.078
A15: 42 | B15: ABUBAKAR MUSA DANLAMI | C15: CHIEF MOTOR DRIVER MECH. | D15: 7(3) | E15: =8730.79 -> 8730.79 | G15: =E15*300% -> 26192.37 | H15: =E15*7.5% -> 654.80925 | J15: =E15*50% -> 4365.395 | K15: =E15*350% -> 30557.765 | L15: =E15*100% -> 8730.79 | N15: 30000 | O15: =E15*10% -> 873.079 | P15: 5000 | Q15: =7000 -> 7000 | R15: =SUM(E15:Q15) -> 122105 | T15: =3000+5000+5000 -> 13000 | U15: =44000 -> 44000 | W15: =[7]PROMOTIONS!$X$42 -> 8312.59 | X15: =W15+V15+U15+T15+S15 -> 65312.59 | Y15: 239903.58 | Z15: =R15-X15 -> 56792.408
B16: GRAND TOTAL | E16: =E8+E14 -> 14158.91 | F16: =F8+F14 -> 0 | G16: =G8+G14 -> 42476.73 | H16: =H8+H14 -> 1061.9182 | I16: =I8+I14 -> 0 | J16: =J8+J14 -> 7079.455 | K16: =K8+K14 -> 49556.185 | L16: =L8+L14 -> 14158.91 | ... V16: =V8+V14 -> 0 | X16: =X8+X14 -> 51011.251

Sheet Sheet2

Sheet PROMOTIONS
A1: NATIONAL INSTITUTE FOR LEGISLATIVE AND DEMOCRATIC STUDIES | G1: ='[1]FEB 08'!F8/'[1]FEB 08'!Q8 -> 0.3
A2: STAFF PAYROLL FOR THE MONTH OF OCTOBER 2023
E3: ='[1]FEB 08'!E11/'[1]FEB 08'!M11 -> #REF! | G3: ='[1]FEB 08'!F11/'[1]FEB 08'!Q11 -> #REF!
B4: STAFF NAME | C4: DESIGNATION | D4: CURRENT GRADE LEVEL | E4: BASIC SALARY | F4: RENT | G4: UTILITY | H4: DOMESTIC | I4: ENTERT. | J4: FURNIT. | K4: FUEL | L4: ALLOWANCE | M4: ALLOWANCE | N4: ALLCE | O4: ALLCE | P4: DUTY ALLCE | Q4: CURRENT GROSS SALARY | R4: NEW GRADE LEVEL | S4: NEW GROSS SALARY | T4: INCREMENT IN GROSS SALARY | U4: CURRENT NHF | V4: NEW NHF | W4: CURRENT PAYE | X4: NEW PAYE | Y4: INCREMENT IN PAYE | Z4: NET SALARY INCREMENT | AA4: NO OF MONTHS | AB4: ARREARS
E5: N | F5: N | G5: N | H5: N | I5: N | J5: N | K5: N | L5: N | M5: N | N5: N | O5: N | P5: N | Q5: N | S5: N | U5: N | W5: N
A6: S/N | B6: DG'S OFFICE
A7: 1 | B7: ABDULRAHMAN A SULAIMAN | C7: ASSISTANT STORES OFFICER | D7: 8(10) | E7: 13492.21 | F7: =E7*300% -> 40476.63 | G7: =E7*7.5% -> 1011.9157 | I7: =E7*50% -> 6746.105 | J7: =E7*350% -> 47222.735 | K7: =E7*100% -> 13492.21 | M7: =50000 -> 50000 | N7: =E7*10% -> 1349.221 | O7: 10000 | Q7: =SUM(E7:P7) -> 183791.03 | R7: 9(7) | S7: ='SALARY STRUCTURE'!H13+60000 -> 205203.67 | T7: =S7-Q7 -> 21412.64 | W7: 18102.903 | X7: ='[6]October 2023'!$Z$29 -> 21640.883 | Y7: =X7-W7 -> 3537.9799 | Z7: =T7-Y7 -> 17874.66 | AA7: =(19/31)+4 -> 4.6129032 | AB7: =Z7*AA7 -> 82454.077
B8: TOTAL | C8: 1 | E8: =SUM(E7:E7) -> 13492.21 | F8: =SUM(F7:F7) -> 40476.63 | G8: =SUM(G7:G7) -> 1011.9157 | H8: =SUM(H7:H7) -> 0 | I8: =SUM(I7:I7) -> 6746.105 | J8: =SUM(J7:J7) -> 47222.735 | K8: =SUM(K7:K7) -> 13492.21 | L8: =SUM(L7:L7) -> 0 | ... Q8: =SUM(Q7:Q7) -> 183791.03 | S8: =SUM(S7:S7) -> 205203.67 | T8: =SUM(T7:T7) -> 21412.64 | U8: =SUM(U7:U7) -> 0 | V8: =SUM(V7:V7) -> 0 | W8: =SUM(W7:W7) -> 18102.903 | X8: =SUM(X7:X7) -> 21640.883 | Y8: =SUM(Y7:Y7) -> 3537.9799 | Z8: =SUM(Z7:Z7) -> 17874.66 | AB8: =SUM(AB7:AB7) -> 82454.077
B10: LEG. SUPPORT SEVICES
A11: 2 | B11: DORIS DAKDA AARON | C11: RESEARCH FELLOW II | D11: 13(10) | E11: 25523.45 | F11: =E11*300% -> 76570.35 | G11: =E11*7.5% -> 1914.2587 | I11: =E11*50% -> 12761.725 | J11: =E11*350% -> 89332.075 | K11: =E11*100% -> 25523.45 | L11: =120000 -> 120000 | N11: =E11*10% -> 2552.345 | O11: 15000 | Q11: =SUM(E11:P11) -> 369177.65 | R11: 14(8) | S11: ='SALARY STRUCTURE'!I17+140000 -> 397211.25 | T11: =S11-Q11 -> 28033.596 | U11: 638.08625 | V11: =690.28 -> 690.28 | W11: 49548.776 | X11: ='[6]October 2023'!$Z$50 -> 54812.469 | Y11: =X11-W11 -> 5263.6924 | Z11: =T11-Y11 -> 22769.904 | AA11: =(18/31)+1 -> 1.5806452 | AB11: =Z11*AA11 -> 35991.138
B12: TOTAL | C12: 1 | E12: =SUM(E11:E11) -> 25523.45 | F12: =SUM(F11:F11) -> 76570.35 | G12: =SUM(G11:G11) -> 1914.2587 | H12: =SUM(H11:H11) -> 0 | I12: =SUM(I11:I11) -> 12761.725 | J12: =SUM(J11:J11) -> 89332.075 | K12: =SUM(K11:K11) -> 25523.45 | L12: =SUM(L11:L11) -> 120000 | ... Q12: =SUM(Q11:Q11) -> 369177.65 | S12: =SUM(S11:S11) -> 397211.25 | T12: =SUM(T11:T11) -> 28033.596 | U12: =SUM(U11:U11) -> 638.08625 | V12: =SUM(V11:V11) -> 690.28 | W12: =SUM(W11:W11) -> 49548.776 | X12: =SUM(X11:X11) -> 54812.469 | Y12: =SUM(Y11:Y11) -> 5263.6924 | Z12: =SUM(Z11:Z11) -> 22769.904 | AB12: =SUM(AB11:AB11) -> 35991.138
T13: =S13-Q13 -> 0
B14: DEMOCRACY & GOVERNANCE | T14: =S14-Q14 -> 0
A15: 3 | B15: NGARA CHRISTOPHER OCHANJA | C15: RESEARCH FELLOW 1 | D15: 14(11) | E15: =28489.81 -> 28489.81 | F15: =E15*300% -> 85469.43 | G15: =E15*7.5% -> 2136.7357 | I15: =E15*50% -> 14244.905 | J15: =E15*350% -> 99714.335 | K15: =E15*100% -> 28489.81 | L15: 140000 | N15: =E15*10% -> 2848.981 | O15: 20000 | P15: 0 | Q15: =SUM(E15:P15) -> 421394.01 | R15: 15(7) | S15: ='SALARY STRUCTURE'!H18+160000 -> 504720.17 | T15: =S15-Q15 -> 83326.16 | U15: 712.24525 | V15: =837.69 -> 837.69 | W15: 59441.782 | X15: ='[6]October 2023'!$Z$85 -> 75440.405 | Y15: =X15-W15 -> 15998.623 | Z15: =T15-Y15 -> 67327.537 | AA15: =9 -> 9 | AB15: =Z15*AA15 -> 605947.83
A16: 4 | B16: EJALONIBU GANIYU LAYI | C16: RESEARCH FELLOW 11 | D16: 13(10) | E16: 25523.45 | F16: =E16*300% -> 76570.35 | G16: =E16*7.5% -> 1914.2587 | I16: =E16*50% -> 12761.725 | J16: =E16*350% -> 89332.075 | K16: =E16*100% -> 25523.45 | L16: =120000 -> 120000 | N16: =E16*10% -> 2552.345 | O16: 15000 | Q16: =SUM(E16:P16) -> 369177.65 | R16: 14(8) | S16: ='SALARY STRUCTURE'!I17+140000 -> 397211.25 | T16: =S16-Q16 -> 28033.596 | W16: 49548.776 | X16: ='[6]October 2023'!$Z$62 -> 54931.227 | Y16: =X16-W16 -> 5382.4505 | Z16: =T16-Y16 -> 22651.146 | AA16: =(7/31)+2 -> 2.2258065 | AB16: =Z16*AA16 -> 50417.066
B17: TOTAL | C17: 2 | E17: =SUM(E15:E16) -> 54013.26 | F17: =SUM(F15:F16) -> 162039.78 | G17: =SUM(G15:G16) -> 4050.9945 | H17: =SUM(H15:H16) -> 0 | I17: =SUM(I15:I16) -> 27006.63 | J17: =SUM(J15:J16) -> 189046.41 | K17: =SUM(K15:K16) -> 54013.26 | L17: =SUM(L15:L16) -> 260000 | ... Q17: =SUM(Q15:Q16) -> 790571.66 | S17: =SUM(S15:S16) -> 901931.42 | T17: =SUM(T15:T16) -> 111359.76 | U17: =SUM(U15:U16) -> 712.24525 | V17: =SUM(V15:V16) -> 837.69 | W17: =SUM(W15:W16) -> 108990.56 | X17: =SUM(X15:X16) -> 130371.63 | Y17: =SUM(Y15:Y16) -> 21381.073 | Z17: =SUM(Z15:Z16) -> 89978.683 | AB17: =SUM(AB15:AB16) -> 656364.9
Y18: =X18-W18 -> 0 | Z18: =T18-Y18 -> 0 | AB18: =Z18*AA18 -> 0
B19: DEPARTMENT OF STUDIES | Y19: =X19-W19 -> 0 | Z19: =T19-Y19 -> 0 | AB19: =Z19*AA19 -> 0
A20: 5 | B20: ANTHONY EDET | C20: ASST. MGR M&E | D20: 13(10) | E20: 25523.45 | F20: =E20*300% -> 76570.35 | G20: =E20*7.5% -> 1914.2587 | H20: 0 | I20: =E20*50% -> 12761.725 | J20: =E20*350% -> 89332.075 | K20: =E20*100% -> 25523.45 | L20: =120000 -> 120000 | N20: =E20*10% -> 2552.345 | O20: 15000 | P20: 0 | Q20: =SUM(E20:P20) -> 369177.65 | R20: 14(8) | S20: ='SALARY STRUCTURE'!I17+140000 -> 397211.25 | T20: =S20-Q20 -> 28033.596 | U20: 638.08625 | W20: 49548.776 | X20: ='[6]October 2023'!$Z$78 -> 54931.227 | Y20: =X20-W20 -> 5382.4505 | Z20: =T20-Y20 -> 22651.146 | AA20: =9 -> 9 | AB20: =Z20*AA20 -> 203860.31
B21: TOTAL | C21: 1 | E21: =SUM(E20:E20) -> 25523.45 | F21: =SUM(F20:F20) -> 76570.35 | G21: =SUM(G20:G20) -> 1914.2587 | H21: =SUM(H20:H20) -> 0 | I21: =SUM(I20:I20) -> 12761.725 | J21: =SUM(J20:J20) -> 89332.075 | K21: =SUM(K20:K20) -> 25523.45 | L21: =SUM(L20:L20) -> 120000 | ... Q21: =SUM(Q20:Q20) -> 369177.65 | S21: =SUM(S20:S20) -> 397211.25 | U21: =SUM(U20:U20) -> 638.08625 | W21: =SUM(W20:W20) -> 49548.776 | X21: =SUM(X20:X20) -> 54931.227 | Y21: =SUM(Y20:Y20) -> 5382.4505 | Z21: =SUM(Z20:Z20) -> 22651.146 | AB21: =SUM(AB20:AB20) -> 203860.31
Y22: =X22-W22 -> 0 | Z22: =T22-Y22 -> 0 | AB22: =Z22*AA22 -> 0
B23: ECON. DEV. & SOC. RESEARCH | Y23: =X23-W23 -> 0 | Z23: =T23-Y23 -> 0 | AB23: =Z23*AA23 -> 0
A24: 6 | B24: OMOJU OLUWASOLA EMMANUEL | C24: RESEARCH FELLOW I | D24: 14(10) | E24: 27611.23 | F24: =E24*300% -> 82833.69 | G24: =E24*7.5% -> 2070.8422 | I24: =E24*50% -> 13805.615 | J24: =E24*350% -> 96639.305 | K24: =E24*100% -> 27611.23 | L24: 140000 | N24: =E24*10% -> 2761.123 | O24: 20000 | Q24: =SUM(E24:P24) -> 413333.04 | R24: 15(7) | S24: ='SALARY STRUCTURE'!H18+160000 -> 504720.17 | T24: =S24-Q24 -> 91387.131 | W24: 58026.609 | X24: ='[6]October 2023'!$Z$86 -> 75572.939 | Y24: =X24-W24 -> 17546.329 | Z24: =T24-Y24 -> 73840.802 | AA24: 1 | AB24: =Z24*AA24 -> 73840.802
A25: 7 | B25: OKUNGBOWA OSARETIN GODSPOWER | C25: RESEARCH FELLOW 11 | D25: 13(9) | E25: 24741.26 | F25: =E25*300% -> 74223.78 | G25: =E25*7.5% -> 1855.5945 | H25: 0 | I25: =E25*50% -> 12370.63 | J25: =E25*350% -> 86594.41 | K25: =E25*100% -> 24741.26 | L25: =120000 -> 120000 | N25: =E25*10% -> 2474.126 | O25: 15000 | P25: 0 | Q25: =SUM(E25:P25) -> 362001.06 | R25: 14(7) | S25: ='SALARY STRUCTURE'!H17+140000 -> 389153.42 | T25: =S25-Q25 -> 27152.356 | W25: 48170.87 | X25: ='[6]October 2023'!$Z$89 -> 53384.123 | Y25: =X25-W25 -> 5213.2524 | Z25: =T25-Y25 -> 21939.104 | AA25: =(19/31)+2 -> 2.6129032 | AB25: =Z25*AA25 -> 57324.755
B26: TOTAL | C26: 2 | E26: =SUM(E24:E25) -> 52352.49 | F26: =SUM(F24:F25) -> 157057.47 | G26: =SUM(G24:G25) -> 3926.4367 | H26: =SUM(H24:H25) -> 0 | I26: =SUM(I24:I25) -> 26176.245 | J26: =SUM(J24:J25) -> 183233.71 | K26: =SUM(K24:K25) -> 52352.49 | L26: =SUM(L24:L25) -> 260000 | ... Q26: =SUM(Q24:Q25) -> 775334.1 | S26: =SUM(S24:S25) -> 893873.58 | T26: =SUM(T24:T25) -> 118539.49 | U26: =SUM(U24:U25) -> 0 | V26: =SUM(V24:V25) -> 0 | W26: =SUM(W24:W25) -> 106197.48 | X26: =SUM(X24:X25) -> 128957.06 | Y26: =SUM(Y24:Y25) -> 22759.582 | Z26: =SUM(Z24:Z25) -> 95779.906 | AB26: =SUM(AB24:AB25) -> 131165.56
T27: =S27-Q27 -> 0 | Y27: =X27-W27 -> 0 | Z27: =T27-Y27 -> 0 | AB27: =Z27*AA27 -> 0
B28: TRAINING & INT''L COOP | T28: =S28-Q28 -> 0 | Y28: =X28-W28 -> 0 | Z28: =T28-Y28 -> 0 | AB28: =Z28*AA28 -> 0
A29: 8 | B29: DR FRANCIS NDUM OJIE | C29: CHIEF TRAINING OFFICER | D29: 14(10) | E29: 27611.23 | F29: =E29*300% -> 82833.69 | G29: =E29*7.5% -> 2070.8422 | I29: =E29*50% -> 13805.615 | J29: =E29*350% -> 96639.305 | K29: =E29*100% -> 27611.23 | L29: 140000 | N29: =E29*10% -> 2761.123 | O29: 20000 | P29: =100000 -> 100000 | Q29: =SUM(E29:P29) -> 513333.04 | R29: 15(7) | S29: ='SALARY STRUCTURE'!H18+160000+100000 -> 604720.17 | T29: =S29-Q29 -> 91387.131 | U29: 690.28075 | V29: =837.69 -> 837.69 | W29: =77098.29 -> 77098.29 | X29: ='[6]October 2023'!$Z$97 -> 94644.622 | Y29: =X29-W29 -> 17546.332 | Z29: =T29-Y29 -> 73840.8 | AA29: =3 -> 3 | AB29: =Z29*AA29 -> 221522.4
A30: 9 | B30: MOHAMMED R. ADAMU | C30: PRINCIPAL CONF. SECRETARY | D30: 13(10) | E30: 25523.45 | F30: =E30*300% -> 76570.35 | G30: =E30*7.5% -> 1914.2587 | H30: 0 | I30: =E30*50% -> 12761.725 | J30: =E30*350% -> 89332.075 | K30: =E30*100% -> 25523.45 | M30: 70000 | N30: =E30*10% -> 2552.345 | O30: 15000 | P30: 0 | Q30: =SUM(E30:P30) -> 319177.65 | R30: 14(8) | S30: ='SALARY STRUCTURE'!I17+70000 -> 327211.25 | T30: =S30-Q30 -> 8033.5963 | W30: 40698.125 | X30: ='[6]October 2023'!$Z$129 -> 42047.769 | Y30: =X30-W30 -> 1349.6442 | Z30: =T30-Y30 -> 6683.9521 | AA30: 7 | AB30: =Z30*AA30 -> 46787.665
A31: 10 | B31: TASSNEEM IBRAHIM | C31: ASSIST. INFO.OFFICER | D31: 8(10) | E31: 13492.21 | F31: 40476.63 | G31: 1011.9157 | I31: 6746.105 | J31: 47222.735 | K31: 13492.21 | M31: 50000 | N31: 1349.221 | O31: 10000 | Q31: 183791.03 | R31: 10(7) | S31: ='SALARY STRUCTURE'!H14+60000 -> 228601.58 | T31: =S31-Q31 -> 44810.557 | W31: 18102.903 | X31: ='[6]October 2023'!$Z$30 -> 25571.733 | Y31: =X31-W31 -> 7468.8299 | Z31: =T31-Y31 -> 37341.727 | AA31: 1 | AB31: =Z31*AA31 -> 37341.727
B32: TOTAL | C32: 3 | E32: =SUM(E29:E31) -> 66626.89 | F32: =SUM(F29:F31) -> 199880.67 | G32: =SUM(G29:G31) -> 4997.0167 | H32: =SUM(H29:H31) -> 0 | I32: =SUM(I29:I31) -> 33313.445 | J32: =SUM(J29:J31) -> 233194.11 | K32: =SUM(K29:K31) -> 66626.89 | L32: =SUM(L29:L31) -> 140000 | ... Q32: =SUM(Q29:Q31) -> 1016301.7 | S32: =SUM(S29:S31) -> 1160533 | T32: =S32-Q32 -> 144231.28 | U32: =SUM(U29:U31) -> 690.28075 | W32: =SUM(W29:W31) -> 135899.32 | X32: =SUM(X29:X31) -> 162264.12 | Y32: =SUM(Y29:Y31) -> 26364.806 | Z32: =SUM(Z29:Z31) -> 117866.48 | AB32: =SUM(AB29:AB31) -> 305651.79
Y33: =X33-W33 -> 0 | Z33: =T33-Y33 -> 0 | AB33: =Z33*AA33 -> 0
B34: FINANCE & ACCOUNTS | Y34: =X34-W34 -> 0 | Z34: =T34-Y34 -> 0 | AB34: =Z34*AA34 -> 0
A35: 11 | B35: RAHILA SALIHU | C35: ASST. CHIEF ACCOUNTOFFICER | D35: 13(10) | E35: 25523.45 | F35: =E35*300% -> 76570.35 | G35: =E35*7.5% -> 1914.2587 | I35: =E35*50% -> 12761.725 | J35: =E35*350% -> 89332.075 | K35: =E35*100% -> 25523.45 | M35: =70000 -> 70000 | N35: =E35*10% -> 2552.345 | O35: 15000 | Q35: =SUM(E35:P35) -> 319177.65 | R35: 14(8) | S35: ='SALARY STRUCTURE'!I17+70000 -> 327211.25 | T35: =S35-Q35 -> 8033.5963 | U35: 638.08625 | V35: =690.28 -> 690.28 | W35: 40684.599 | X35: ='[6]October 2023'!$Z$118 -> 42034.243 | Y35: =X35-W35 -> 1349.6442 | Z35: =T35-Y35 -> 6683.9521 | AA35: =9 -> 9 | AB35: =Z35*AA35 -> 60155.569
B36: TOTAL | C36: 1 | E36: =SUM(E35:E35) -> 25523.45 | F36: =SUM(F35:F35) -> 76570.35 | G36: =SUM(G35:G35) -> 1914.2587 | H36: =SUM(H35:H35) -> 0 | I36: =SUM(I35:I35) -> 12761.725 | J36: =SUM(J35:J35) -> 89332.075 | K36: =SUM(K35:K35) -> 25523.45 | L36: =SUM(L35:L35) -> 0 | ... Q36: =SUM(Q35:Q35) -> 319177.65 | S36: =SUM(S35:S35) -> 327211.25 | T36: =SUM(T35:T35) -> 8033.5963 | U36: =SUM(U35:U35) -> 638.08625 | V36: =SUM(V35:V35) -> 690.28 | W36: =SUM(W35:W35) -> 40684.599 | X36: =SUM(X35:X35) -> 42034.243 | Y36: =SUM(Y35:Y35) -> 1349.6442 | Z36: =SUM(Z35:Z35) -> 6683.9521 | AB36: =SUM(AB35:AB35) -> 60155.569
L37: =226713.38+70000 -> 296713.38
B38: ADMIN & HUMAN RESOURCE
A39: 12 | B39: ABDULWAHAB DAHIRU | C39: ADMIN OFFICER | D39: 10(10) | E39: 18779.3 | F39: =E39*300% -> 56337.9 | G39: =E39*7.5% -> 1408.4475 | I39: =E39*50% -> 9389.65 | J39: =E39*350% -> 65727.55 | K39: =E39*100% -> 18779.3 | M39: =60000 -> 60000 | N39: =E39*10% -> 1877.93 | O39: 10000 | Q39: =SUM(E39:P39) -> 242300.08 | R39: 12(7) | S39: ='SALARY STRUCTURE'!H15+60000 -> 265371.75 | T39: =S39-Q39 -> 23071.673 | U39: 469.4825 | V39: =570.95 -> 570.95 | W39: 27794.207 | X39: ='[6]October 2023'!$Z$134 -> 31653.201 | Y39: =X39-W39 -> 3858.9944 | Z39: =T39-Y39 -> 19212.678 | AA39: 9 | AB39: =Z39*AA39 -> 172914.1
A40: 13 | B40: ODEH SUZIE | C40: ADMIN. OFFICER | D40: 10(10) | E40: =18779.3 -> 18779.3 | F40: =E40*300% -> 56337.9 | G40: =E40*7.5% -> 1408.4475 | I40: =E40*50% -> 9389.65 | J40: =E40*350% -> 65727.55 | K40: =E40*100% -> 18779.3 | M40: 60000 | N40: =E40*10% -> 1877.93 | O40: 10000 | Q40: =SUM(E40:P40) -> 242300.08 | R40: 12(7) | S40: ='SALARY STRUCTURE'!H15+60000 -> 265371.75 | T40: =S40-Q40 -> 23071.673 | U40: 0 | W40: 27873.08 | X40: ='[6]October 2023'!$Z$24 -> 31749.121 | Y40: =X40-W40 -> 3876.041 | Z40: =T40-Y40 -> 19195.632 | AA40: 1 | AB40: =Z40*AA40 -> 19195.632
A41: 14 | B41: BUKOLA HAUWA SHIRU | C41: ADMIN. ASST. | D41: 8(10) | E41: 13492.21 | F41: =E41*300% -> 40476.63 | G41: =E41*7.5% -> 1011.9157 | I41: =E41*50% -> 6746.105 | J41: =E41*350% -> 47222.735 | K41: =E41*100% -> 13492.21 | M41: =50000 -> 50000 | N41: =E41*10% -> 1349.221 | O41: 10000 | Q41: =SUM(E41:P41) -> 183791.03 | R41: 9(7) | S41: ='SALARY STRUCTURE'!H13+60000 -> 205203.67 | T41: =S41-Q41 -> 21412.64 | W41: 18102.903 | X41: ='[6]October 2023'!$Z$145 -> 21640.883 | Y41: =X41-W41 -> 3537.9799 | Z41: =T41-Y41 -> 17874.66 | AA41: 2 | AB41: =Z41*AA41 -> 35749.32
A42: 15 | B42: YUNUSA ABDULMUMINI ELEOJO | C42: SENIOR DRIVER | D42: 5(11) | E42: 5428.12 | F42: =E42*300% -> 16284.36 | G42: =E42*7.5% -> 407.109 | I42: =E42*50% -> 2714.06 | J42: =E42*350% -> 18998.42 | K42: =E42*100% -> 5428.12 | M42: =20000 -> 20000 | N42: =E42*10% -> 542.812 | O42: 5000 | P42: =7000 -> 7000 | Q42: =SUM(E42:P42) -> 81803.001 | R42: 7(3) | S42: ='SALARY STRUCTURE'!D11+30000 -> 115104.92 | T42: =S42-Q42 -> 33301.916 | W42: 4365.3308 | X42: ='[6]October 2023'!$Z$164 -> 8312.59 | Y42: =X42-W42 -> 3947.2592 | Z42: =T42-Y42 -> 29354.656 | AA42: =(10/31)+2 -> 2.3225806 | AB42: =Z42*AA42 -> 68178.557
A43: 16 | B43: JOHN GIMAH | C43: SENIOR DRIVER | D43: 5(11) | E43: 5428.12 | F43: =E43*300% -> 16284.36 | G43: =E43*7.5% -> 407.109 | I43: =E43*50% -> 2714.06 | J43: =E43*350% -> 18998.42 | K43: =E43*100% -> 5428.12 | M43: =20000 -> 20000 | N43: =E43*10% -> 542.812 | O43: 5000 | P43: =7000 -> 7000 | Q43: =SUM(E43:P43) -> 81803.001 | R43: 7(3) | S43: ='SALARY STRUCTURE'!D11+30000 -> 115104.92 | T43: =S43-Q43 -> 33301.916 | W43: =4365.33075466667 -> 4365.3308 | X43: ='[6]October 2023'!$Z$164 -> 8312.59 | Y43: =X43-W43 -> 3947.2592 | Z43: =T43-Y43 -> 29354.656 | AA43: =(17/31)+1 -> 1.5483871 | AB43: =Z43*AA43 -> 45452.371
A44: 17 | B44: ABUBAKAR MUSA DANLAMI | C44: SENIOR DRIVER | D44: 5(12) | E44: =5598.92 -> 5598.92 | F44: =E44*300% -> 16796.76 | G44: =E44*7.5% -> 419.919 | I44: =E44*50% -> 2799.46 | J44: =E44*350% -> 19596.22 | K44: =E44*100% -> 5598.92 | M44: =20000 -> 20000 | N44: =E44*10% -> 559.892 | O44: 5000 | P44: =7000 -> 7000 | Q44: =SUM(E44:P44) -> 83370.091 | R44: 7(3) | S44: 115104.92 | T44: =S44-Q44 -> 31734.826 | W44: 4504.4109 | X44: ='[6]October 2023'!$Z$164 -> 8312.59 | Y44: =X44-W44 -> 3808.1791 | Z44: =T44-Y44 -> 27926.647 | AA44: 8 | AB44: =Z44*AA44 -> 223413.17
A45: 18 | B45: JOHN ETIMBUK UDO | C45: DRIVER | D45: 4(11) | E45: =4689.38 -> 4689.38 | F45: =E45*300% -> 14068.14 | G45: =E45*7.5% -> 351.7035 | I45: =E45*50% -> 2344.69 | J45: =E45*350% -> 16412.83 | K45: =E45*100% -> 4689.38 | M45: =15000 -> 15000 | N45: =E45*10% -> 468.938 | O45: 5000 | P45: =4000 -> 4000 | Q45: =SUM(E45:P45) -> 67025.061 | R45: 5(8) | S45: ='SALARY STRUCTURE'!I9+20000+7000 -> 77104.417 | T45: =S45-Q45 -> 10079.355 | W45: 3064.8721 | X45: ='[6]October 2023'!$Z$177 -> 3951.8553 | Y45: =X45-W45 -> 886.98325 | Z45: =T45-Y45 -> 9192.3719 | AA45: =(23/31)+6 -> 6.7419355 | AB45: =Z45*AA45 -> 61974.378
B46: TOTAL | C46: 7 | E46: =SUM(E39:E45) -> 72195.35 | F46: =SUM(F39:F45) -> 216586.05 | G46: =SUM(G39:G45) -> 5414.6512 | H46: =SUM(H39:H45) -> 0 | I46: =SUM(I39:I45) -> 36097.675 | J46: =SUM(J39:J45) -> 252683.72 | K46: =SUM(K39:K45) -> 72195.35 | L46: =SUM(L39:L45) -> 0 | ... Q46: =SUM(Q39:Q45) -> 982392.34 | S46: =SUM(S39:S45) -> 1158366.3 | T46: =SUM(T39:T45) -> 175974 | U46: =SUM(U39:U45) -> 469.4825 | V46: =SUM(V39:V45) -> 570.95 | W46: =SUM(W39:W45) -> 90070.134 | X46: =SUM(X39:X45) -> 113932.83 | Y46: =SUM(Y39:Y45) -> 23862.696 | Z46: =SUM(Z39:Z45) -> 152111.3 | AB46: =SUM(AB39:AB45) -> 626877.53
B47: GRAND TOTAL | C47: =C46+C36+C32+C26+C21+C17+C12+C8 -> 18 | E47: =E46+E36+E32+E26+E21+E17+E12+E8 -> 335250.55 | F47: =F46+F36+F32+F26+F21+F17+F12+F8 -> 1005751.7 | G47: =G46+G36+G32+G26+G21+G17+G12+G8 -> 25143.791 | H47: =H46+H36+H32+H26+H21+H17+H12+H8 -> 0 | I47: =I46+I36+I32+I26+I21+I17+I12+I8 -> 167625.28 | J47: =J46+J36+J32+J26+J21+J17+J12+J8 -> 1173376.9 | K47: =K46+K36+K32+K26+K21+K17+K12+K8 -> 335250.55 | L47: =L46+L36+L32+L26+L21+L17+L12+L8 -> 900000 | ... AB47: =AB46+AB36+AB32+AB26+AB21+AB17+AB12+AB8 -> 2102520.9

Sheet SALARY STRUCTURE
A1: NATIONAL INSTITUTE FOR LEGISLATIVE STUDIES
A2: TABLE OF MONTHLY CONSOLIDATED SALARY AND ALLOWANCES SCALES
B3: STEP 1 | C3: STEP 2 | D3: STEP 3 | E3: STEP 4 | F3: STEP 5 | G3: STEP 6 | H3: STEP 7 | I3: STEP 8 | J3: STEP 9 | K3: STEP 10 | L3: STEP 11 | M3: STEP 12 | N3: STEP 13 | O3: STEP 14 | P3: STEP 15
A4: CONLESS LEVEL | B4: N | C4: N | D4: N | E4: N | F4: N | G4: N | H4: N | I4: N | J4: N | K4: N | L4: N | M4: N | N4: N | O4: N | P4: N
A5: ,01 | B5: 32012.167 | C5: 32710.5 | D5: 33408.75 | E5: 34107.083 | F5: 34805.5 | G5: 35503.75 | H5: 36202.083 | I5: 36900.333 | J5: 37598.667 | K5: 38297.083 | L5: 38995.333 | M5: 39693.667 | N5: 40391.917 | O5: 41090.167 | P5: 41788.667
A6: ,02 | B6: 32532.167 | C6: 33445.167 | D6: 34358.333 | E6: 35271.25 | F6: 36184.25 | G6: 37097.417 | H6: 38010.333 | I6: 38923.417 | J6: 39836.417 | K6: 40749.417 | L6: 41662.5 | M6: 42575.5 | N6: 43488.667 | O6: 44401.583 | P6: 45314.583
A7: ,03 | B7: 32976.25 | C7: 34098.417 | D7: 35220.667 | E7: 36343 | F7: 37465.167 | G7: 38587.417 | H7: 39709.667 | I7: 40823.583 | J7: 41954.083 | K7: 43076.417 | L7: 44198.667 | M7: 45445.833 | N7: 46443.167 | O7: 47565.333 | P7: 48687.5
A8: ,04 | B8: 34542.5 | C8: 35890.833 | D8: 37238.917 | E8: 38587.167 | F8: 39935.5 | G8: 41283.75 | H8: 42631.917 | I8: 43980 | J8: 45328.333 | K8: 46676.417 | L8: 48024.667 | M8: 49373 | N8: 50721.167 | O8: 52069.417 | P8: 53417.5
A9: ,05 | B9: 39140.333 | C9: 40706.583 | D9: 42272.833 | E9: 43839.083 | F9: 45405.5 | G9: 46971.75 | H9: 48538 | I9: 50104.417 | J9: 51670.667 | K9: 53236.917 | L9: 54803.167 | M9: 56369.583 | N9: 57936 | O9: 59502.083 | P9: 61068.333
A10: ,06 | B10: 47723.333 | C10: 49632.5 | D10: 51541.75 | E10: 53450.917 | F10: 55360.167 | G10: 57269.417 | H10: 59178.667 | I10: 61087.833 | J10: 62997.083 | K10: 64906.25 | L10: 66815.5 | M10: 68724.667 | N10: 70633.917 | O10: 72543.167 | P10: 74452.417
A11: ,07 | B11: 79244.583 | C11: 82174.667 | D11: 85104.917 | E11: 88034.917 | F11: 106590 | G11: 93895 | H11: 96825.167 | I11: 99755.167 | J11: 102685.33 | K11: 105615.33 | L11: 108545.5 | M11: 111468 | N11: 114405.67 | O11: 117335.83 | P11: 120265.83
A12: ,08 | B12: 102403.75 | C12: 105891.25 | D12: 109378.75 | E12: 112866.25 | F12: 116353.67 | G12: 119841.17 | H12: 123328.67 | I12: 126816.17 | J12: 130303.67 | K12: 133791.17 | L12: 137278.67 | M12: 140766.17 | N12: 144253.67 | O12: 147741.17 | P12: 151228.67
A13: ,09 | B13: 120290 | C13: 124442.17 | D13: 128594.58 | E13: 132746.75 | F13: 136899.08 | G13: 141051.25 | H13: 145203.67 | I13: 149355.83 | J13: 153508 | K13: 157660.33 | L13: 161812.5 | M13: 165964.92 | N13: 170117.08 | O13: 174269.42 | P13: 178421.58
A14: ,10 | B14: 141204.92 | C14: 145770.92 | D14: 150337.08 | E14: 154903.33 | F14: 159469.42 | G14: 164035.5 | H14: 168601.58 | I14: 173167.67 | J14: 177733.75 | K14: 182299.92 | L14: 186865.92 | M14: 191432.17 | N14: 195998.33 | O14: 200564.42 | P14: 205130.5
A15: ,12 | B15: 162876.25 | C15: 169958.92 | D15: 177039.92 | E15: 184124.08 | F15: 191206.58 | G15: 198289.25 | H15: 205371.75 | I15: 212454.42 | J15: 219536.92 | K15: 226619.58 | L15: 233702.08
A16: ,13 | B16: 181786.42 | C16: 189274.25 | D16: 198324.58 | E16: 204249.92 | F16: 211737.67 | G16: 219225.5 | H16: 226713.33 | I16: 234201.17 | J16: 242001.42 | K16: 249176.75 | L16: 256664.58
A17: ,14 | B17: 200784.08 | C17: 208845.17 | D17: 216904.67 | E17: 224967.17 | F17: 233028.33 | G17: 241089.25 | H17: 249153.42 | I17: 257211.25 | J17: 265272.42 | K17: 273333.42 | L17: 281394.42
A18: ,15 | B18: 276221.25 | C18: 287637.83 | D18: 299054.25 | E18: 312760.25 | F18: 321887.17 | G18: 333303.75 | H18: 344720.17 | I18: 356136.75 | J18: 367553.17
A19: ,16 | B19: 341699.58 | C19: 355420.17 | D19: 369154.92 | E19: 382861.42 | F19: 396582.08 | G19: 410302.67 | H19: 424023.33 | I19: 437743.92 | J19: 451464.58
A20: ,17 | B20: 652000 | C20: 676776.17 | D20: 701552.17 | E20: 726328.33 | F20: 751104.42 | G20: 775880.5 | H20: 800656.58 | I20: 825432.67 | J20: 850208.75

Sheet Wage Grant
A1: NATIONAL INSTITUTE FOR LEGISLATIVE AND DEMOCRATIC STUDIES
A2: GRANT OF WAGE AWARD TO FEDERAL GOVERNMENT WORKERS
A3: SCHEDULE FOR FOUR (4) MONTHS SEPTEMBER TO DECEMBER 2023
A5: S/N | B5: STAFF NAME | C5: DESIGNATION | D5: GRADE LEVEL | E5: SEPTEMBER | F5: OCTOBER | G5: NOVEMBER | H5: DECEMBER | I5: SEPT. TO DEC. 2023
B6: DG'S OFFICE
A7: 1 | B7: PROF. ABUBAKAR O. SULAIMAN | C7: DIRECTOR GENERAL | D7: N/A | E7: 35000 | F7: 35000 | G7: 35000 | H7: 35000 | I7: =E7+F7+G7+H7 -> 140000
A8: 2 | B8: DR JAKE DABANG DAN AZUMI | C8: DEPUTY DIR. TECHNICAL | D8: 16(9) | E8: 35000 | F8: 35000 | G8: 35000 | H8: 35000 | I8: =E8+F8+G8+H8 -> 140000
A9: 3 | B9: RAHEEM USMAN AYIGORO | C9: SA-INFRASTRUCTURE | D9: 16 (9) | E9: 35000 | F9: 35000 | G9: 35000 | H9: 35000 | I9: =E9+F9+G9+H9 -> 140000
A10: 4 | B10: MARIAM MOHAMMED BELLO | C10: SA- SPECIAL DUTIES | D10: 16(8) | E10: 35000 | F10: 35000 | G10: 35000 | H10: 35000 | I10: =E10+F10+G10+H10 -> 140000
A11: 5 | B11: AKINSANMI ADEJOKE OLUKEMI | C11: DEPUTY DIR. INFO/PROTOCOL | D11: 16(8) | E11: 35000 | F11: 35000 | G11: 35000 | H11: 35000 | I11: =E11+F11+G11+H11 -> 140000
A12: 6 | B12: DR IKEME ARTHUR J.O | C12: DEPUTY DIRECTOR, M&E | D12: 16(8) | E12: 35000 | F12: 35000 | G12: 35000 | H12: 35000 | I12: =E12+F12+G12+H12 -> 140000
A13: 7 | B13: MOSHOOD M. OLALERE | C13: DEPUTY DIR. GENERAL SERVICE | D13: 16(8) | E13: 35000 | F13: 35000 | G13: 35000 | H13: 35000 | I13: =E13+F13+G13+H13 -> 140000
A14: 8 | B14: ANDRAWUS MUSA | C14: ASST. DIRECTOR, STORES | D14: 15(9) | E14: 35000 | F14: 35000 | G14: 35000 | H14: 35000 | I14: =E14+F14+G14+H14 -> 140000
A15: 9 | B15: DONALD E. MKPANAM | C15: CHIEF ICT OFFICER | D15: 14(10) | E15: 35000 | F15: 35000 | G15: 35000 | H15: 35000 | I15: =E15+F15+G15+H15 -> 140000
A16: 11 | B16: ALI ABDULLAHI | C16: CHIEF ICT OFFICER | D16: 14(10) | E16: 35000 | F16: 35000 | G16: 35000 | H16: 35000 | I16: =E16+F16+G16+H16 -> 140000
A17: 12 | B17: PERCY TERFA GBAHABO | C17: HEAD, NILDS LIAISON OFFICE | D17: 13(9) | E17: 35000 | F17: 35000 | G17: 35000 | H17: 35000 | I17: =E17+F17+G17+H17 -> 140000
A18: 13 | B18: HASSANA AHMED IBRAHIM | C18: PA- TO DG | D18: 13 (8) | E18: 35000 | F18: 35000 | G18: 35000 | H18: 35000 | I18: =E18+F18+G18+H18 -> 140000
... A27: 23 | B27: HARUNA JIBRIL AMEH | C27: ASST. ADMIN. OFFICER | D27: 8(7) | E27: 35000 | F27: 35000 | G27: 35000 | H27: 35000 | I27: =E27+F27+G27+H27 -> 140000
B28: TOTAL FOR DG'S OFFICE | E28: =SUM(E7:E27) -> 735000 | F28: =SUM(F7:F27) -> 735000 | G28: =SUM(G7:G27) -> 735000 | H28: =SUM(H7:H27) -> 735000 | I28: =SUM(I7:I27) -> 2940000
B30: INTERNAL AUDIT
A31: 1 | B31: OSANAIYE DAVID AKINYEMI | C31: DIRECTOR INTERNAL AUDIT | D31: 17(9) | E31: 35000 | F31: 35000 | G31: 35000 | H31: 35000 | I31: =E31+F31+G31+H31 -> 140000
A32: 2 | B32: JAMILA ABDUL | C32: AUDITOR II | D32: 8(7) | E32: 35000 | F32: 35000 | G32: 35000 | H32: 35000 | I32: =E32+F32+G32+H32 -> 140000
B33: TOTAL FOR AUDIT | E33: =SUM(E31:E32) -> 70000 | F33: =SUM(F31:F32) -> 70000 | G33: =SUM(G31:G32) -> 70000 | H33: =SUM(H31:H32) -> 70000 | I33: =SUM(I31:I32) -> 280000
B35: LEG. SUPPORT SEVICES
A36: 1 | B36: PROF. EDOBA BRIGHT OMOREGBE | C36: AG. DLSS | D36: 17(9) | E36: 35000 | F36: 35000 | G36: 35000 | H36: 35000 | I36: =E36+F36+G36+H36 -> 140000
A37: 2 | B37: DR CLINTON JAJA | C37: SENIOR RESEARCH FELLOW | D37: 15(9) | E37: 35000 | F37: 35000 | G37: 35000 | H37: 35000 | I37: =E37+F37+G37+H37 -> 140000
A38: 3 | B38: BETHEL UZOMA IHUGBA | C38: SNR RESEARCH FELLOW | D38: 15(9) | E38: 35000 | F38: 35000 | G38: 35000 | H38: 35000 | I38: =E38+F38+G38+H38 -> 140000
A39: 4 | B39: OGUCHE SAMUEL | C39: SNR RESEARCH FELLOW | D39: 15(9) | E39: 35000 | F39: 35000 | G39: 35000 | H39: 35000 | I39: =E39+F39+G39+H39 -> 140000
A40: 5 | B40: IBRAHIM USMAN | C40: SNR RESEARCH FELLOW | D40: 15(8) | E40: 35000 | F40: 35000 | G40: 35000 | H40: 35000 | I40: =E40+F40+G40+H40 -> 140000
A41: 6 | B41: DR MOHAMMED O. AMALI | C41: RESEARCH FELLOW I | D41: 14(10) | E41: 35000 | F41: 35000 | G41: 35000 | H41: 35000 | I41: =E41+F41+G41+H41 -> 140000
A42: 7 | B42: YAHAYA SHAMSU | C42: RESEARCH FELLOW 1 | D42: 14(10) | E42: 35000 | F42: 35000 | G42: 35000 | H42: 35000 | I42: =E42+F42+G42+H42 -> 140000
A43: 8 | B43: OFORDEME ADAOBI JULIA | C43: RESEARCH FELLOW 1 | D43: 14(9) | E43: 35000 | F43: 35000 | G43: 35000 | H43: 35000 | I43: =E43+F43+G43+H43 -> 140000
A44: 9 | B44: DORIS DAKDA AARON | C44: RESEARCH FELLOW II | D44: 13(10) | E44: 35000 | F44: 35000 | G44: 35000 | H44: 35000 | I44: =E44+F44+G44+H44 -> 140000
A45: 10 | B45: BILKIS S. LAWAL-GAMBARI | C45: RESEARCH OFFICER | D45: 10(7) | E45: 35000 | F45: 35000 | G45: 35000 | H45: 35000 | I45: =E45+F45+G45+H45 -> 140000
A46: 11 | B46: ZAINAB AKINDE | C46: RESEARCH OFFICER | D46: 9(7) | E46: 35000 | F46: 35000 | G46: 35000 | H46: 35000 | I46: =E46+F46+G46+H46 -> 140000
A47: 12 | B47: ABDULLAHI AHMAD USMAN | C47: RESEARCH OFFICER | D47: 9(7) | E47: 35000 | F47: 35000 | G47: 35000 | H47: 35000 | I47: =E47+F47+G47+H47 -> 140000
A48: 13 | B48: GUNAT NANSAK MARK | C48: RESEARCH OFFICER | D48: 9(7) | E48: 35000 | F48: 35000 | G48: 35000 | H48: 35000 | I48: =E48+F48+G48+H48 -> 140000
B49: TOTAL FOR LEGIS. SUPPORT SERVICES | E49: =SUM(E36:E48) -> 455000 | F49: =SUM(F36:F48) -> 455000 | G49: =SUM(G36:G48) -> 455000 | H49: =SUM(H36:H48) -> 455000 | I49: =SUM(I36:I48) -> 1820000
B51: LEGAL SERVICES
A52: 1 | B52: DR SHUIBU DANWANKA | C52: DIRECTOR LEGAL SERVICES | D52: 17(9) | E52: 35000 | F52: 35000 | G52: 35000 | H52: 35000 | I52: =E52+F52+G52+H52 -> 140000
A53: 2 | B53: ABDULSALAM BAKO | C53: MANAGER, LEGAL SERVICES | D53: 15 (8) | E53: 35000 | F53: 35000 | G53: 35000 | H53: 35000 | I53: =E53+F53+G53+H53 -> 140000
B54: TOTAL FOR LEGAL SERVICES | E54: =SUM(E52:E53) -> 70000 | F54: =SUM(F52:F53) -> 70000 | G54: =SUM(G52:G53) -> 70000 | H54: =SUM(H52:H53) -> 70000 | I54: =SUM(I52:I53) -> 280000
B56: DEMOCRACY & GOVERNANCE
A57: 1 | B57: DR. ADEWALE ADEREMI | C57: DIRECTOR, DEMOCRATIC STUDIES | D57: 17(9) | E57: 35000 | F57: 35000 | G57: 35000 | H57: 35000 | I57: =E57+F57+G57+H57 -> 140000
A58: 2 | B58: NDANUSA MOHAMMED MANZUMA | C58: SNR RESEARCH FELLOW | D58: 15 (7) | E58: 35000 | F58: 35000 | G58: 35000 | H58: 35000 | I58: =E58+F58+G58+H58 -> 140000
A59: 3 | B59: EJALONIBU GANIYU LAYI | C59: RESEARCH FELLOW 11 | D59: 13(10) | E59: 35000 | F59: 35000 | G59: 35000 | H59: 35000 | I59: =E59+F59+G59+H59 -> 140000
A60: 4 | B60: LOHNA BONKAT JONATHAN | C60: RESEARCH FELLOW 11 | D60: 13(9) | E60: 35000 | F60: 35000 | G60: 35000 | H60: 35000 | I60: =E60+F60+G60+H60 -> 140000
A61: 5 | B61: YUNUSA ABDULLAHI | C61: RESEARCH FELLOW 1 | D61: 14(10) | E61: 35000 | F61: 35000 | G61: 35000 | H61: 35000 | I61: =E61+F61+G61+H61 -> 140000
A62: 6 | B62: EMILY EKHIDE | C62: RESEARCH FELLOW 1 | D62: 14(9) | E62: 35000 | F62: 35000 | G62: 35000 | H62: 35000 | I62: =E62+F62+G62+H62 -> 140000
A63: 7 | B63: UDEFUNA NNADOZIE PATRICK | C63: RESEARCH OFFICER | D63: 12(7) | E63: 35000 | F63: 35000 | G63: 35000 | H63: 35000 | I63: =E63+F63+G63+H63 -> 140000
A64: 8 | B64: SHAFIU YAHYA MIKAIL | C64: PRINCIPAL RESEARCH OFFICER | D64: 12(7) | E64: 35000 | F64: 35000 | G64: 35000 | H64: 35000 | I64: =E64+F64+G64+H64 -> 140000
A65: 9 | B65: HASSAN YERIMA | C65: PRINCIPAL RESEARCH OFFICER | D65: 12(7) | E65: 35000 | F65: 35000 | G65: 35000 | H65: 35000 | I65: =E65+F65+G65+H65 -> 140000
A66: 10 | B66: HAUWA PATE SADIQ | C66: PRINCIPAL PROGRAMME OFFICER | D66: 12(8) | E66: 35000 | F66: 35000 | G66: 35000 | H66: 35000 | I66: =E66+F66+G66+H66 -> 140000
A67: 11 | B67: NNANDI LIVINUS ATURE | C67: RESEARCH ASSISTANT | D67: 9(8) | E67: 35000 | F67: 35000 | G67: 35000 | H67: 35000 | I67: =E67+F67+G67+H67 -> 140000
A68: 12 | B68: LUCKY AGWOM | C68: RESEARCH ASSISTANT | D68: 8(8) | E68: 35000 | F68: 35000 | G68: 35000 | H68: 35000 | I68: =E68+F68+G68+H68 -> 140000
B69: TOTAL DEMOCRACY & GOVERNANCE | E69: =SUM(E57:E68) -> 420000 | F69: =SUM(F57:F68) -> 420000 | G69: =SUM(G57:G68) -> 420000 | H69: =SUM(H57:H68) -> 420000 | I69: =SUM(I57:I68) -> 1680000
B71: DEPARTMENT OF STUDIES
A72: 1 | B72: DR ASIMIYU G. ABIOLA | C72: DIRECTOR POST GRADUATE | D72: 17(9) | E72: 35000 | F72: 35000 | G72: 35000 | H72: 35000 | I72: =E72+F72+G72+H72 -> 140000
A73: 2 | B73: USMAN WALI | C73: SENIOR RESEARCH FELLOW | D73: 15 (7) | E73: 35000 | F73: 35000 | G73: 35000 | H73: 35000 | I73: =E73+F73+G73+H73 -> 140000
A74: 3 | B74: AYOBOLU OLAJIDE OLUFUNSHO | C74: ASST.DIR., INFORMATION | D74: 15 (8) | E74: 35000 | F74: 35000 | G74: 35000 | H74: 35000 | I74: =E74+F74+G74+H74 -> 140000
A75: 4 | B75: ANTHONY EDET | C75: ASST. MGR M&E | D75: 13(10) | E75: 35000 | F75: 35000 | G75: 35000 | H75: 35000 | I75: =E75+F75+G75+H75 -> 140000
A76: 5 | B76: IGWE STACY | C76: PROGRAMME OFFICER | D76: 10(8) | E76: 35000 | F76: 35000 | G76: 35000 | H76: 35000 | I76: =E76+F76+G76+H76 -> 140000
A77: 6 | B77: OLANIYAN TAIWO ABINBOLA | C77: PROGRAMME OFFICER | D77: 9(7) | E77: 35000 | F77: 35000 | G77: 35000 | H77: 35000 | I77: =E77+F77+G77+H77 -> 140000
A78: 7 | B78: AMINAT JUMOKE SULAIMON | C78: AST. PROGRAMME OFFICER | D78: 8(7) | E78: 35000 | F78: 35000 | G78: 35000 | H78: 35000 | I78: =E78+F78+G78+H78 -> 140000
B79: TOTAL DEPARTMENT OF STUDIES | E79: =SUM(E72:E78) -> 245000 | F79: =SUM(F72:F78) -> 245000 | G79: =SUM(G72:G78) -> 245000 | H79: =SUM(H72:H78) -> 245000 | I79: =SUM(I72:I78) -> 980000
B81: ECON. DEV. & SOC. RESEARCH
A82: 1 | B82: TERFA WILLIAMS ABRAHAM | C82: SNR RESEARCH FELLOW | D82: 15(9) | E82: 35000 | F82: 35000 | G82: 35000 | H82: 35000 | I82: =35000*4 -> 140000
A83: 2 | B83: DR AUGUSTINE C. OSIGWE | C83: SNR RESEARCH FELLOW | D83: 15(9) | E83: 35000 | F83: 35000 | G83: 35000 | H83: 35000 | I83: =35000*4 -> 140000
A84: 3 | B84: NGARA CHRISTOPHER OCHANJA | C84: RESEARCH FELLOW 1 | D84: 14(11) | E84: 35000 | F84: 35000 | G84: 35000 | H84: 35000 | I84: =35000*4 -> 140000
A85: 4 | B85: OMOJU OLUWASOLA EMMANUEL | C85: RESEARCH FELLOW I | D85: 14(10) | E85: 35000 | F85: 35000 | G85: 35000 | H85: 35000 | I85: =35000*4 -> 140000
A86: 5 | B86: IBE EZECHI CYRIACUS | C86: RESEARCH FELLOW II | D86: 13(10) | E86: 35000 | F86: 35000 | G86: 35000 | H86: 35000 | I86: =35000*4 -> 140000
A87: 6 | B87: OSIKHEN LEO IGBANOI | C87: RESEARCH FELLOW 11 | D87: 13(9) | E87: 35000 | F87: 35000 | G87: 35000 | H87: 35000 | I87: =35000*4 -> 140000
A88: 7 | B88: OKUNGBOWA OSARETIN GODSPOWER | C88: RESEARCH FELLOW 11 | D88: 13(9) | E88: 35000 | F88: 35000 | G88: 35000 | H88: 35000 | I88: =35000*4 -> 140000
A89: 8 | B89: YUSUF IBRAHIM | C89: PRINCIPAL RESEARCH OFFICER | D89: 12(7) | E89: 35000 | F89: 35000 | G89: 35000 | H89: 35000 | I89: =35000*4 -> 140000
A90: 9 | B90: MUSTAPHA RAFIU AYOBANJI | C90: PRINCIPAL RESEARCH OFFICER | D90: 12(7) | E90: 35000 | F90: 35000 | G90: 35000 | H90: 35000 | I90: =35000*4 -> 140000
A91: 10 | B91: MARYAM MUSA SADA | C91: ASSIT. RESEARCH OFFICER | D91: 10(7) | E91: 35000 | F91: 35000 | G91: 35000 | H91: 35000 | I91: =35000*4 -> 140000
A92: 11 | B92: CHARITY EZENWAJIOBI | C92: REASEARCH. ASST. | D92: 8(8) | E92: 35000 | F92: 35000 | G92: 35000 | H92: 35000 | I92: =35000*4 -> 140000
B93: TOTAL ECON DEV & SOCIAL RESEARCH | E93: =SUM(E82:E92) -> 385000 | F93: =SUM(F82:F92) -> 385000 | G93: =SUM(G82:G92) -> 385000 | H93: =SUM(H82:H92) -> 385000 | I93: =SUM(I82:I92) -> 1540000
B95: TRAINING & INT''L COOP
A96: 1 | B96: REKIYA IBRAHIM ATTAH | C96: DEPUTY DIRECTOR TRAINING | D96: 16(8) | E96: 35000 | F96: 35000 | G96: 35000 | H96: 35000 | I96: =E96+F96+G96+H96 -> 140000
A97: 2 | B97: DR FRANCIS NDUM OJIE | C97: CHIEF TRAINING OFFICER | D97: 14(10) | E97: 35000 | F97: 35000 | G97: 35000 | H97: 35000 | I97: =E97+F97+G97+H97 -> 140000
A98: 3 | B98: OKECHUKWU UCHENNA HULDA | C98: PRINCIPALTRAINING OFFICER | D98: 12(8) | E98: 35000 | F98: 35000 | G98: 35000 | H98: 35000 | I98: =E98+F98+G98+H98 -> 140000
A99: 4 | B99: TASSNEEM IBRAHIM | C99: ASSIST. INFO.OFFICER | D99: 8(10) | E99: 35000 | F99: 35000 | G99: 35000 | H99: 35000 | I99: =E99+F99+G99+H99 -> 140000
B100: TOTAL FOR TRAINING & INT'L RELATIONS | E100: =SUM(E96:E99) -> 140000 | F100: =SUM(F96:F99) -> 140000 | G100: =SUM(G96:G99) -> 140000 | H100: =SUM(H96:H99) -> 140000 | I100: =SUM(I96:I99) -> 560000
B102: LIBRARY & DOCUMENTATION
A103: 1 | B103: DR MAIMUNA IZAH | C103: INSITUTE LIBRARIAN | D103: 17(9) | E103: =35000 -> 35000 | F103: =35000 -> 35000 | G103: =35000 -> 35000 | H103: =35000 -> 35000 | I103: =E103+F103+G103+H103 -> 140000
A104: 2 | B104: CATHERINE E. IKOKOH | C104: SNR RESEARCH FELLOW DOCU | D104: 16(8) | E104: =35000 -> 35000 | F104: =35000 -> 35000 | G104: =35000 -> 35000 | H104: =35000 -> 35000 | I104: =E104+F104+G104+H104 -> 140000
A105: 3 | B105: ALIYU SANNI ABUBAKAR | C105: RESEARCH FELLOW 11 DATA & DOCU | D105: 13(11) | E105: =35000 -> 35000 | F105: =35000 -> 35000 | G105: =35000 -> 35000 | H105: =35000 -> 35000 | I105: =E105+F105+G105+H105 -> 140000
A106: 4 | B106: CHINAKO N. ASOGWA | C106: RESEARCH FELLOW 11 DATA & DOCU | D106: 13(11) | E106: =35000 -> 35000 | F106: =35000 -> 35000 | G106: =35000 -> 35000 | H106: =35000 -> 35000 | I106: =E106+F106+G106+H106 -> 140000
A107: 5 | B107: AMOS ABA | C107: LIBRARY ASSISTANT | D107: 8(11) | E107: =35000 -> 35000 | F107: =35000 -> 35000 | G107: =35000 -> 35000 | H107: =35000 -> 35000 | I107: =E107+F107+G107+H107 -> 140000
A108: 6 | B108: TITILAYO DANIEL MARVELLOUS | C108: LIBRARY ASSISTANT | D108: 8(10) | E108: =35000 -> 35000 | F108: =35000 -> 35000 | G108: =35000 -> 35000 | H108: =35000 -> 35000 | I108: =E108+F108+G108+H108 -> 140000
A109: 7 | B109: ENENCHE JEREMIAH AGADA | C109: LIBRARY ASSISTANT | D109: 8(8) | E109: =35000 -> 35000 | F109: =35000 -> 35000 | G109: =35000 -> 35000 | H109: =35000 -> 35000 | I109: =E109+F109+G109+H109 -> 140000
B110: TOTAL FOR LIBRARY & DOCUMENTATION | E110: =SUM(E103:E109) -> 245000 | F110: =SUM(F103:F109) -> 245000 | G110: =SUM(G103:G109) -> 245000 | H110: =SUM(H103:H109) -> 245000 | I110: =SUM(I103:I109) -> 980000
B112: LEG, CTRE FOR SEC. ANALYSIS
A113: 1 | B113: OSOLAFIA MUHAMMAD EGYE | C113: PRINCIPAL RESEARCH OFFICER | D113: 12(9) | E113: 35000 | F113: 35000 | G113: 35000 | H113: 35000 | I113: =E113+F113+G113+H113 -> 140000
A114: 2 | B114: EGUATU U. ONYEJELEM | C114: PRINCIPAL M&E OFFICER | D114: 12(8) | E114: 35000 | F114: 35000 | G114: 35000 | H114: 35000 | I114: =E114+F114+G114+H114 -> 140000
A115: 3 | B115: CHRISTIAN MADUABUCHI ODO | C115: PRINCIPAL ICT OFFICER | D115: 12(9) | E115: 35000 | F115: 35000 | G115: 35000 | H115: 35000 | I115: =E115+F115+G115+H115 -> 140000
B116: TOTAL FOR LEG. CENTER FOR SECURITY ANALYSIS | E116: =SUM(E113:E115) -> 105000 | F116: =SUM(F113:F115) -> 105000 | G116: =SUM(G113:G115) -> 105000 | H116: =SUM(H113:H115) -> 105000 | I116: =SUM(I113:I115) -> 420000
B118: FINANCE & ACCOUNTS
A119: 1 | B119: IBRAHIM M. MSHELIA | C119: DIR. FINANCE & ACCOUNTS | D119: 17(9) | E119: 35000 | F119: 35000 | G119: 35000 | H119: 35000 | I119: =E119+F119+G119+H119 -> 140000
...

Sheet Wage Grant (2)
A1: NATIONAL INSTITUTE FOR LEGISLATIVE AND DEMOCRATIC STUDIES
A2: GRANT OF WAGE AWARD TO FEDERAL GOVERNMENT WORKERS
A3: SCHEDULE FOR FOUR (4) MONTHS SEPTEMBER TO DECEMBER 2023
A5: S/N | B5: STAFF NAME | C5: DESIGNATION | D5: SEPTEMBER, 2023 | E5: OCTOBER, 2023 | F5: NOVEMBER, 2023 | G5: DECEMBER, 2023 | H5: SEPT. TO DEC. 2023
A6: 1 | B6: Mohammed Etudaiye | C6: Office Assistant | D6: 35000 | E6: 35000 | F6: 35000 | G6: 35000 | H6: =D6+E6+F6+G6 -> 140000
A7: 2 | B7: Saratu Adamu Attajiri | C7: Office Assistant | D7: 35000 | E7: 35000 | F7: 35000 | G7: 35000 | H7: =D7+E7+F7+G7 -> 140000
A8: 3 | B8: Elizabeth Ogechukwu Onyeaku | C8: Consultant | D8: 35000 | E8: 35000 | F8: 35000 | G8: 35000 | H8: =D8+E8+F8+G8 -> 140000
A9: 4 | B9: Saratu Adamu Attajiri | C9: Office Assistant | D9: 35000 | E9: 35000 | F9: 35000 | G9: 35000 | H9: =D9+E9+F9+G9 -> 140000
A10: 5 | B10: Aboaman Innocent | C10: Casual | D10: 35000 | E10: 35000 | F10: 35000 | G10: 35000 | H10: =D10+E10+F10+G10 -> 140000
A11: 6 | B11: Kusai E. Richard | C11: Plumber | D11: 35000 | E11: 35000 | F11: 35000 | G11: 35000 | H11: =D11+E11+F11+G11 -> 140000
A12: 7 | B12: Bulus Ishaya | C12: Gardener | D12: 35000 | E12: 35000 | F12: 35000 | G12: 35000 | H12: =D12+E12+F12+G12 -> 140000
A13: 8 | B13: Alhamdu Iliya | C13: Casual-Gardner | D13: 35000 | E13: 35000 | F13: 35000 | G13: 35000 | H13: =D13+E13+F13+G13 -> 140000
A14: 9 | B14: Salihu Hassan | C14: Casual-Gardner | D14: 35000 | E14: 35000 | F14: 35000 | G14: 35000 | H14: =D14+E14+F14+G14 -> 140000
A15: 10 | B15: Ishaya Moro James | C15: Gardener | D15: 35000 | E15: 35000 | F15: 35000 | G15: 35000 | H15: =D15+E15+F15+G15 -> 140000
A16: 11 | B16: Dr. John Niyi Olanrewaju | C16: Consultancy | D16: 35000 | E16: 35000 | F16: 35000 | G16: 35000 | H16: =D16+E16+F16+G16 -> 140000
A17: 12 | B17: Dr. Shehu Wahab L | C17: Consultant | D17: 35000 | E17: 35000 | F17: 35000 | G17: 35000 | H17: =D17+E17+F17+G17 -> 140000
... A58: 53 | B58: Olufemi Emmanuel Oyegoke | C58: Casual | D58: 35000 | E58: 35000 | F58: 35000 | G58: 35000 | H58: =D58+E58+F58+G58 -> 140000
D59: =SUM(D8:D58) -> 1785000 | E59: =SUM(E8:E58) -> 1785000 | F59: =SUM(F8:F58) -> 1785000 | G59: =SUM(G8:G58) -> 1785000 | H59: =SUM(H8:H58) -> 7140000

Sheet 1st 28 days in Nov
A1: SCHEDULE OF 1ST 28 DAY TO THE NEWLY CONVERTED STAFF
A2: S/N | B2: NAME | C2: DESIGNATION | D2: AMOUNT (N20,000 X 28 DAYS) | E2: PAYE | F2: NET AMOUNT
A3: 1 | B3: KOLAPO Q. ABAYOMI | C3: RESEARCH OFFICER | D3: =20000*28 -> 560000 | E3: =86186.67 -> 86186.67 | F3: =D3-E3 -> 473813.33
A4: 2 | B4: ELIZABETHOGECHUKWU ONYEAKU | C4: ASST. ICT OFFICER | D4: =20000*28 -> 560000 | E4: =86186.67 -> 86186.67 | F4: =D4-E4 -> 473813.33
B5: TOTAL | D5: =SUM(D3:D4) -> 1120000 | E5: =SUM(E3:E4) -> 172373.34 | F5: =SUM(F3:F4) -> 947626.66

Sheet Sallah Welfare April 2023
A1: NATIONAL INSTITUTE FOR LEGISLATIVE AND DEMOCRATIC STUDIES
A2: STAFF WELFARE APRIL, 2023
B4: STAFF NAME | C4: DESIGNATION | D4: GRADE LEVEL | E4: AMOUNT
E5: N
A6: S/N | B6: DG'S OFFICE
A7: 1 | B7: PROF. ABUBAKAR O. SULAIMAN | C7: DIRECTOR GENERAL | D7: CONSOL | E7: 450000
A8: 2 | B8: DR JAKE DABANG DAN AZUMI | C8: DEPUTY DIR. TTECHNICAL | D8: 16(9) | E8: 150000
A9: 3 | B9: DR ABDULSALAM NASIRU NAEEM | C9: SA ACADEMICS | D9: 16(9) | E9: 150000
A10: 4 | B10: RAHEEM USMAN AYIGORO | C10: SA-INFRASTRUCTURE | D10: 16 (9) | E10: 150000
A11: 5 | B11: MARIAM MOHAMMED BELLO | C11: SA- SPECIAL DUTIES | D11: 16(8) | E11: 150000
A12: 6 | B12: AKINSANMI ADEJOKE OLUKEMI | C12: DEPUTY DIR. INFO/PROTOCOL | D12: 16(8) | E12: 150000
A13: 7 | B13: DR IKEME ARTHUR J.O | C13: DEPUTY DIRECTOR, M&E | D13: 16(8) | E13: 150000
A14: 8 | B14: MOSHOOD M. OLALERE | C14: DEPUTY DIR. GENERAL SERVICE | D14: 16(8) | E14: 150000
A15: 9 | B15: ANDRAWUS MUSA | C15: ASST. DIRECTOR, STORES | D15: 15(9) | E15: 105000
A16: 10 | B16: AYOBOLU OLAJIDE OLUFUNSHO | C16: ASST.DIR., INFORMATION | D16: 15 (8) | E16: 105000
A17: 11 | B17: HUSSEIN EGYE MUSA | C17: CHIEF PROTOCOL OFFICER | D17: 14(10) | E17: 75000
A18: 12 | B18: DONALD E. MKPANAM | C18: CHIEF ICT OFFICER | D18: 14(10) | E18: 75000
... A36: 30 | B36: SHOLAGBERU T. SOFIAT | C36: ASST. ACCOUNT. OFFICER | D36: 8(7) | E36: 45000
B37: TOTAL | C37: 30 | E37: =SUM(E7:E36) -> 2790000
B39: INTERNAL AUDIT
A40: 1 | B40: OSANAIYE DAVID AKINYEMI | C40: DIRECTOR INTERNAL AUDIT | D40: 17(9) | E40: 225000
A41: 2 | B41: JAMILA ABDUL | C41: AUDITOR II | D41: 8(7) | E41: 45000
C42: 2 | E42: =SUM(E40:E41) -> 270000
B44: LEG. SUPPORT SEVICES
A45: 1 | B45: PROF. EDOBA BRIGHT OMOREGBE | C45: AG. DLSS | D45: 17(9) | E45: 225000
A46: 2 | B46: DR CLINTON JAJA | C46: SENIOR RESEARCH FELLOW | D46: 15(9) | E46: 105000
A47: 3 | B47: BETHEL UZOMA IHUGBA | C47: SNR RESEARCH FELLOW | D47: 15(9) | E47: 105000
A48: 4 | B48: OGUCHE SAMUEL | C48: SNR RESEARCH FELLOW | D48: 15(9) | E48: 105000
A49: 5 | B49: IBRAHIM USMAN | C49: SNR RESEARCH FELLOW | D49: 15(8) | E49: 105000
A50: 6 | B50: DR MOHAMMED O. AMALI | C50: RESEARCH FELLOW I | D50: 14(10) | E50: 75000
A51: 7 | B51: YAHAYA SHAMSU | C51: RESEARCH FELLOW 1 | D51: 14(10) | E51: 75000
A52: 8 | B52: OFORDEME ADAOBI JULIA | C52: RESEARCH FELLOW 1 | D52: 14(9) | E52: 75000
A53: 9 | B53: DORIS DAKDA AARON | C53: RESEARCH FELLOW II | D53: 13(10) | E53: 75000
A54: 10 | B54: ZAINAB AKINDE | C54: RESEARCH OFFICER | D54: 9(7) | E54: 45000
A55: 11 | B55: ABDULLAHI AHMAD USMAN | C55: RESEARCH OFFICER | D55: 9(7) | E55: 45000
A56: 12 | B56: GUNAT NANSAK MARK | C56: RESEARCH OFFICER | D56: 9(7) | E56: 45000
B57: TOTAL | C57: 12 | E57: =SUM(E45:E56) -> 1080000
B59: LEGAL SERVICES
A60: 1 | B60: DR SHUIBU DANWANKA | C60: DIRECTOR LEGAL SERVICES | D60: 17(9) | E60: 225000
A61: 2 | B61: ABDULSALAM BAKO | C61: MANAGER, LEGAL SERVICES | D61: 15 (8) | E61: 105000
B62: TOTAL | C62: 2 | E62: =SUM(E60:E61) -> 330000
B64: DEMOCRACY & GOVERNANCE
A65: 1 | B65: DR. ADEWALE ADEREMI | C65: DIRECTOR, DEMOCRATIC STUDIES | D65: 17(9) | E65: 225000
A66: 2 | B66: NDANUSA MOHAMMED MANZUMA | C66: SNR RESEARCH FELLOW | D66: 15 (7) | E66: 105000
A67: 3 | B67: EJALONIBU GANIYU LAYI | C67: RESEARCH FELLOW 11 | D67: 13(10) | E67: 75000
A68: 4 | B68: LOHNA BONKAT JONATHAN | C68: RESEARCH FELLOW 11 | D68: 13(9) | E68: 75000
A69: 5 | B69: YUNUSA ABDULLAHI | C69: RESEARCH FELLOW 1 | D69: 14(10) | E69: 75000
A70: 6 | B70: EMILY EKHIDE | C70: RESEARCH FELLOW 1 | D70: 14(9) | E70: 75000
A71: 7 | B71: UDEFUNA NNADOZIE PATRICK | C71: RESEARCH OFFICER | D71: 12(7) | E71: 45000
A72: 8 | B72: OSOLAFIA MUHAMMAD EGYE | C72: PRINCIPAL RESEARCH OFFICER | D72: 12(9) | E72: 45000
A73: 9 | B73: SHAFIU YAHYA MIKAIL | C73: PRINCIPAL RESEARCH OFFICER | D73: 12(7) | E73: 45000
A74: 10 | B74: HASSAN YERIMA | C74: PRINCIPAL RESEARCH OFFICER | D74: 12(7) | E74: 45000
A75: 11 | B75: HAUWA PATE SADIQ | C75: PRINCIPAL PROGRAMME OFFICER | D75: 12(8) | E75: 45000
A76: 12 | B76: ABAYOMI KAYODE QUADRI | C76: RESEARCH OFFICER | D76: 10(8) | E76: 45000
... A78: 14 | B78: LUCKY AGWOM | C78: RESEARCH ASSISTANT | D78: 8(8) | E78: 45000
B79: TOTAL | C79: 14 | E79: =SUM(E65:E78) -> 990000
B81: DEPARTMENT OF STUDIES
A82: 1 | B82: DR ASIMIYU G. ABIOLA | C82: DIRECTOR POST GRADUATE | D82: 17(9) | E82: 225000
A83: 2 | B83: USMAN WALI | C83: SENIOR RESEARCH FELLOW | D83: 15 (7) | E83: 105000
A84: 3 | B84: MOSHOOD TOSHO AMUDA | C84: MANAGER, EXAMS & RECORDS | D84: 15 (7) | E84: 105000
A85: 4 | B85: ANTHONY EDET | C85: ASST. MGR M&E | D85: 13(10) | E85: 75000
A86: 5 | B86: IGWE STACY | C86: PROGRAMME OFFICER | D86: 10(8) | E86: 45000
B87: TOTAL | C87: 5 | E87: =SUM(E82:E86) -> 555000
B89: ECON. DEV. & SOC. RESEARCH
A90: 1 | B90: TERFA WILLIAMS ABRAHAM | C90: SNR RESEARCH FELLOW | D90: 15(9) | E90: 105000
A91: 2 | B91: DR AUGUSTINE C. OSIGWE | C91: SNR RESEARCH FELLOW | D91: 15(9) | E91: 105000
A92: 3 | B92: NGARA CHRISTOPHER OCHANJA | C92: RESEARCH FELLOW 1 | D92: 14(11) | E92: 75000
A93: 4 | B93: OMOJU OLUWASOLA EMMANUEL | C93: RESEARCH FELLOW I | D93: 14(10) | E93: 75000
A94: 5 | B94: IBE EZECHI CYRIACUS | C94: RESEARCH FELLOW II | D94: 13(10) | E94: 75000
A95: 6 | B95: OSIKHEN LEO IGBANOI | C95: RESEARCH FELLOW 11 | D95: 13(9) | E95: 75000
A96: 7 | B96: OKUNGBOWA OSARETIN GODSPOWER | C96: RESEARCH FELLOW 11 | D96: 13(9) | E96: 75000
A97: 8 | B97: YUSUF IBRAHIM | C97: PRINCIPAL RESEARCH OFFICER | D97: 12(7) | E97: 45000
A98: 9 | B98: MARYAM MUSA SADA | C98: ASSIT. RESEARCH OFFICER | D98: 10(7) | E98: 45000
A99: 10 | B99: CHARITY EZENWAJIOBI | C99: REASEARCH. ASST. | D99: 8(8) | E99: 45000
B100: TOTAL | C100: 10 | E100: =SUM(E90:E99) -> 720000
B102: TRAINING & INT''L COOP
A103: 1 | B103: REKIYA IBRAHIM ATTAH | C103: DEPUTY DIRECTOR TRAINING | D103: 16(8) | E103: 150000
A104: 2 | B104: DR FRANCIS NDUM OJIE | C104: CHIEF TRAINING OFFICER | D104: 14(10) | E104: 75000
A105: 3 | B105: OKECHUKWU UCHENNA HULDA | C105: PRINCIPALTRAINING OFFICER | D105: 12(8) | E105: 45000
A106: 4 | B106: TASNEEM IBRAHIM | C106: ASST. INFORMATION OFFICER | D106: 8(10) | E106: 45000
B107: TOTAL | C107: 3 | E107: =SUM(E103:E106) -> 315000
B109: LIBRARY & DOCUMENTATION
A110: 1 | B110: DR MAIMUNA IZAH | C110: INSITUTE LIBRARIAN | D110: 17(9) | E110: 225000
A111: 2 | B111: CATHERINE E. IKOKOH | C111: SNR RESEARCH FELLOW DOCU | D111: 16(8) | E111: 150000
A112: 3 | B112: ALIYU SANNI ABUBAKAR | C112: RESEARCH FELLOW 11 DATA & DOCU | D112: 13(11) | E112: 75000
A113: 4 | B113: CHINAKO N. ASOGWA | C113: RESEARCH FELLOW 11 DATA & DOCU | D113: 13(11) | E113: 75000
A114: 5 | B114: AMOS ABA | C114: LIBRARY ASSISTANT | D114: 8(11) | E114: 45000
A115: 6 | B115: TITILAYO DANIEL MARVELLOUS | C115: LIBRARY ASSISTANT | D115: 8(10) | E115: 45000
A116: 7 | B116: ENENCHE JEREMIAH AGADA | C116: LIBRARY ASSISTANT | D116: 8(8) | E116: 45000
B117: TOTAL | C117: 7 | E117: =SUM(E110:E116) -> 660000
B119: FINANCE & ACCOUNTS
A120: 1 | B120: IBRAHIM M. MSHELIA | C120: DIR. FINANCE & ACCOUNTS | D120: 17(9) | E120: 225000
A121: 2 | B121: RAHILA NURUDEEN HABU | C121: ASST. DIRECTOR, ACCOUNTS | D121: 15(9) | E121: 105000
A122: 3 | B122: TONDO IORWUESE EDWARD | C122: ASST. DIRECTOR, ACCOUNTS | D122: 15(9) | E122: 105000
A123: 4 | B123: ARAOYE GANIYAT TITILOLA | C123: ASST. DIRECTOR, ACCOUNTS | D123: 15(7) | E123: 105000
A124: 5 | B124: SHEHU ABDULLAHI | C124: CHIEF ACCOUNT OFFICER | D124: 14(9) | E124: 75000
A125: 6 | B125: OJOGIWA ABISOLA GANIAT | C125: ASST. CHIEF BUDGET OFFICER | D125: 13(10) | E125: 75000
A126: 7 | B126: RAHILA SALIHU | C126: ASST. CHIEF ACCOUNTOFFICER | D126: 13(10) | E126: 75000
A127: 8 | B127: HUSSAIN HAZEEM | C127: ACCOUNT. OFFICER | D127: 9(8) | E127: 45000
A128: 9 | B128: MUNIRAT JIMOH | C128: ACCOUNT ASSISTANT | D128: 8(8) | E128: 45000
...

Sheet Sallah Welfare June 2023
A1: NATIONAL INSTITUTE FOR LEGISLATIVE AND DEMOCRATIC STUDIES
A2: STAFF WELFARE APRIL, 2023
B4: STAFF NAME | C4: DESIGNATION | D4: GRADE LEVEL | E4: AMOUNT
E5: N
A6: S/N | B6: DG'S OFFICE
A7: 1 | B7: PROF. ABUBAKAR O. SULAIMAN | C7: DIRECTOR GENERAL | D7: CONSOL | E7: 450000
A8: 2 | B8: DR JAKE DABANG DAN AZUMI | C8: DEPUTY DIR. TTECHNICAL | D8: 16(9) | E8: 150000
A9: 3 | B9: DR ABDULSALAM NASIRU NAEEM | C9: SA ACADEMICS | D9: 16(9) | E9: 150000
A10: 4 | B10: RAHEEM USMAN AYIGORO | C10: SA-INFRASTRUCTURE | D10: 16 (9) | E10: 150000
A11: 5 | B11: MARIAM MOHAMMED BELLO | C11: SA- SPECIAL DUTIES | D11: 16(8) | E11: 150000
A12: 6 | B12: AKINSANMI ADEJOKE OLUKEMI | C12: DEPUTY DIR. INFO/PROTOCOL | D12: 16(8) | E12: 150000
A13: 7 | B13: DR IKEME ARTHUR J.O | C13: DEPUTY DIRECTOR, M&E | D13: 16(8) | E13: 150000
A14: 8 | B14: MOSHOOD M. OLALERE | C14: DEPUTY DIR. GENERAL SERVICE | D14: 16(8) | E14: 150000
A15: 9 | B15: ANDRAWUS MUSA | C15: ASST. DIRECTOR, STORES | D15: 15(9) | E15: 105000
A16: 10 | B16: AYOBOLU OLAJIDE OLUFUNSHO | C16: ASST.DIR., INFORMATION | D16: 15 (8) | E16: 105000
A17: 11 | B17: HUSSEIN EGYE MUSA | C17: CHIEF PROTOCOL OFFICER | D17: 14(10) | E17: 75000
A18: 12 | B18: DONALD E. MKPANAM | C18: CHIEF ICT OFFICER | D18: 14(10) | E18: 75000
... A35: 29 | B35: SHOLAGBERU T. SOFIAT | C35: ASST. ACCOUNT. OFFICER | D35: 8(7) | E35: 45000
B36: TOTAL | C36: 29 | E36: =SUM(E7:E35) -> 2745000
B38: INTERNAL AUDIT
A39: 1 | B39: OSANAIYE DAVID AKINYEMI | C39: DIRECTOR INTERNAL AUDIT | D39: 17(9) | E39: 225000
A40: 2 | B40: JAMILA ABDUL | C40: AUDITOR II | D40: 8(7) | E40: 45000
C41: 2 | E41: =SUM(E39:E40) -> 270000
B43: LEG. SUPPORT SEVICES
A44: 1 | B44: PROF. EDOBA BRIGHT OMOREGBE | C44: AG. DLSS | D44: 17(9) | E44: 225000
A45: 2 | B45: DR CLINTON JAJA | C45: SENIOR RESEARCH FELLOW | D45: 15(9) | E45: 105000
A46: 3 | B46: BETHEL UZOMA IHUGBA | C46: SNR RESEARCH FELLOW | D46: 15(9) | E46: 105000
A47: 4 | B47: OGUCHE SAMUEL | C47: SNR RESEARCH FELLOW | D47: 15(9) | E47: 105000
A48: 5 | B48: IBRAHIM USMAN | C48: SNR RESEARCH FELLOW | D48: 15(8) | E48: 105000
A49: 6 | B49: DR MOHAMMED O. AMALI | C49: RESEARCH FELLOW I | D49: 14(10) | E49: 75000
A50: 7 | B50: YAHAYA SHAMSU | C50: RESEARCH FELLOW 1 | D50: 14(10) | E50: 75000
A51: 8 | B51: OFORDEME ADAOBI JULIA | C51: RESEARCH FELLOW 1 | D51: 14(9) | E51: 75000
A52: 9 | B52: DORIS DAKDA AARON | C52: RESEARCH FELLOW II | D52: 13(10) | E52: 75000
A53: 10 | B53: ZAINAB AKINDE | C53: RESEARCH OFFICER | D53: 9(7) | E53: 45000
A54: 11 | B54: ABDULLAHI AHMAD USMAN | C54: RESEARCH OFFICER | D54: 9(7) | E54: 45000
A55: 12 | B55: GUNAT NANSAK MARK | C55: RESEARCH OFFICER | D55: 9(7) | E55: 45000
B56: TOTAL | C56: 12 | E56: =SUM(E44:E55) -> 1080000
B58: LEGAL SERVICES
A59: 1 | B59: DR SHUIBU DANWANKA | C59: DIRECTOR LEGAL SERVICES | D59: 17(9) | E59: 225000
A60: 2 | B60: ABDULSALAM BAKO | C60: MANAGER, LEGAL SERVICES | D60: 15 (8) | E60: 105000
B61: TOTAL | C61: 2 | E61: =SUM(E59:E60) -> 330000
B63: DEMOCRACY & GOVERNANCE
A64: 1 | B64: DR. ADEWALE ADEREMI | C64: DIRECTOR, DEMOCRATIC STUDIES | D64: 17(9) | E64: 225000
A65: 2 | B65: NDANUSA MOHAMMED MANZUMA | C65: SNR RESEARCH FELLOW | D65: 15 (7) | E65: 105000
A66: 3 | B66: EJALONIBU GANIYU LAYI | C66: RESEARCH FELLOW 11 | D66: 13(10) | E66: 75000
A67: 4 | B67: LOHNA BONKAT JONATHAN | C67: RESEARCH FELLOW 11 | D67: 13(9) | E67: 75000
A68: 5 | B68: YUNUSA ABDULLAHI | C68: RESEARCH FELLOW 1 | D68: 14(10) | E68: 75000
A69: 6 | B69: EMILY EKHIDE | C69: RESEARCH FELLOW 1 | D69: 14(9) | E69: 75000
A70: 7 | B70: UDEFUNA NNADOZIE PATRICK | C70: RESEARCH OFFICER | D70: 12(7) | E70: 45000
A71: 8 | B71: SHAFIU YAHYA MIKAIL | C71: PRINCIPAL RESEARCH OFFICER | D71: 12(7) | E71: 45000
A72: 9 | B72: HASSAN YERIMA | C72: PRINCIPAL RESEARCH OFFICER | D72: 12(7) | E72: 45000
A73: 10 | B73: HAUWA PATE SADIQ | C73: PRINCIPAL PROGRAMME OFFICER | D73: 12(8) | E73: 45000
A74: 11 | B74: ABAYOMI KAYODE QUADRI | C74: RESEARCH OFFICER | D74: 10(8) | E74: 45000
A75: 12 | B75: NNANDI LIVINUS ATURE | C75: RESEARCH ASSISTANT | D75: 9(8) | E75: 45000
A76: 13 | B76: LUCKY AGWOM | C76: RESEARCH ASSISTANT | D76: 8(8) | E76: 45000
B77: TOTAL | C77: 13 | E77: =SUM(E64:E76) -> 945000
B79: DEPARTMENT OF STUDIES
A80: 1 | B80: DR ASIMIYU G. ABIOLA | C80: DIRECTOR POST GRADUATE | D80: 17(9) | E80: 225000
A81: 2 | B81: USMAN WALI | C81: SENIOR RESEARCH FELLOW | D81: 15 (7) | E81: 105000
A82: 3 | B82: MOSHOOD TOSHO AMUDA | C82: MANAGER, EXAMS & RECORDS | D82: 15 (7) | E82: 105000
A83: 4 | B83: ANTHONY EDET | C83: ASST. MGR M&E | D83: 13(10) | E83: 75000
A84: 5 | B84: IGWE STACY | C84: PROGRAMME OFFICER | D84: 10(8) | E84: 45000
B85: TOTAL | C85: 5 | E85: =SUM(E80:E84) -> 555000
B87: ECON. DEV. & SOC. RESEARCH
A88: 1 | B88: TERFA WILLIAMS ABRAHAM | C88: SNR RESEARCH FELLOW | D88: 15(9) | E88: 105000
A89: 2 | B89: DR AUGUSTINE C. OSIGWE | C89: SNR RESEARCH FELLOW | D89: 15(9) | E89: 105000
A90: 3 | B90: NGARA CHRISTOPHER OCHANJA | C90: RESEARCH FELLOW 1 | D90: 14(11) | E90: 75000
A91: 4 | B91: OMOJU OLUWASOLA EMMANUEL | C91: RESEARCH FELLOW I | D91: 14(10) | E91: 75000
A92: 5 | B92: IBE EZECHI CYRIACUS | C92: RESEARCH FELLOW II | D92: 13(10) | E92: 75000
A93: 6 | B93: OSIKHEN LEO IGBANOI | C93: RESEARCH FELLOW 11 | D93: 13(9) | E93: 75000
A94: 7 | B94: OKUNGBOWA OSARETIN GODSPOWER | C94: RESEARCH FELLOW 11 | D94: 13(9) | E94: 75000
A95: 8 | B95: YUSUF IBRAHIM | C95: PRINCIPAL RESEARCH OFFICER | D95: 12(7) | E95: 45000
A96: 9 | B96: MARYAM MUSA SADA | C96: ASSIT. RESEARCH OFFICER | D96: 10(7) | E96: 45000
A97: 10 | B97: CHARITY EZENWAJIOBI | C97: REASEARCH. ASST. | D97: 8(8) | E97: 45000
B98: TOTAL | C98: 10 | E98: =SUM(E88:E97) -> 720000
B100: TRAINING & INT''L COOP
A101: 1 | B101: REKIYA IBRAHIM ATTAH | C101: DEPUTY DIRECTOR TRAINING | D101: 16(8) | E101: 150000
A102: 2 | B102: DR FRANCIS NDUM OJIE | C102: CHIEF TRAINING OFFICER | D102: 14(10) | E102: 75000
A103: 3 | B103: OKECHUKWU UCHENNA HULDA | C103: PRINCIPALTRAINING OFFICER | D103: 12(8) | E103: 45000
A104: 4 | B104: TASNEEM IBRAHIM | C104: ASST. INFORMATION OFFICER | D104: 8(10) | E104: 45000
B105: TOTAL | C105: 3 | E105: =SUM(E101:E104) -> 315000
B107: LIBRARY & DOCUMENTATION
A108: 1 | B108: DR MAIMUNA IZAH | C108: INSITUTE LIBRARIAN | D108: 17(9) | E108: 225000
A109: 2 | B109: CATHERINE E. IKOKOH | C109: SNR RESEARCH FELLOW DOCU | D109: 16(8) | E109: 150000
A110: 3 | B110: ALIYU SANNI ABUBAKAR | C110: RESEARCH FELLOW 11 DATA & DOCU | D110: 13(11) | E110: 75000
A111: 4 | B111: CHINAKO N. ASOGWA | C111: RESEARCH FELLOW 11 DATA & DOCU | D111: 13(11) | E111: 75000
A112: 5 | B112: AMOS ABA | C112: LIBRARY ASSISTANT | D112: 8(11) | E112: 45000
A113: 6 | B113: TITILAYO DANIEL MARVELLOUS | C113: LIBRARY ASSISTANT | D113: 8(10) | E113: 45000
A114: 7 | B114: ENENCHE JEREMIAH AGADA | C114: LIBRARY ASSISTANT | D114: 8(8) | E114: 45000
B115: TOTAL | C115: 7 | E115: =SUM(E108:E114) -> 660000
B117: LEG, CTRE FOR SECURITY ANALYSIS
A118: 1 | B118: OSOLAFIA MUHAMMAD EGYE | C118: PRINCIPAL RESEARCH OFFICER | D118: 12(9) | E118: 45000
A119: 2 | B119: EGUATU U. ONYEJELEM | C119: PRINCIPAL M&E OFFICER | D119: 12(8) | E119: 45000
B120: TOTAL | C120: 2 | E120: =SUM(E118:E119) -> 90000
B122: FINANCE & ACCOUNTS
A123: 1 | B123: IBRAHIM M. MSHELIA | C123: DIR. FINANCE & ACCOUNTS | D123: 17(9) | E123: 225000
A124: 2 | B124: RAHILA NURUDEEN HABU | C124: ASST. DIRECTOR, ACCOUNTS | D124: 15(9) | E124: 105000
A125: 3 | B125: TONDO IORWUESE EDWARD | C125: ASST. DIRECTOR, ACCOUNTS | D125: 15(9) | E125: 105000
A126: 4 | B126: ARAOYE GANIYAT TITILOLA | C126: ASST. DIRECTOR, ACCOUNTS | D126: 15(7) | E126: 105000
A127: 5 | B127: SHEHU ABDULLAHI | C127: CHIEF ACCOUNT OFFICER | D127: 14(9) | E127: 75000
...

Sheet Sallah Welfare June 2023 Latest
A1: NATIONAL INSTITUTE FOR LEGISLATIVE AND DEMOCRATIC STUDIES
A2: STAFF WELFARE APRIL, 2023
B4: STAFF NAME | C4: DESIGNATION | D4: GRADE LEVEL | E4: AMOUNT
E5: N
A6: S/N | B6: DG'S OFFICE
A7: 1 | B7: PROF. ABUBAKAR O. SULAIMAN | C7: DIRECTOR GENERAL | D7: CONSOL | E7: 540000
A8: 2 | B8: DR JAKE DABANG DAN AZUMI | C8: DEPUTY DIR. TTECHNICAL | D8: 16(9) | E8: 180000
A9: 3 | B9: RAHEEM USMAN AYIGORO | C9: SA-INFRASTRUCTURE | D9: 16 (9) | E9: 180000
A10: 4 | B10: MARIAM MOHAMMED BELLO | C10: SA- SPECIAL DUTIES | D10: 16(8) | E10: 180000
A11: 5 | B11: AKINSANMI ADEJOKE OLUKEMI | C11: DEPUTY DIR. INFO/PROTOCOL | D11: 16(8) | E11: 180000
A12: 6 | B12: DR IKEME ARTHUR J.O | C12: DEPUTY DIRECTOR, M&E | D12: 16(8) | E12: 180000
A13: 7 | B13: MOSHOOD M. OLALERE | C13: DEPUTY DIR. GENERAL SERVICE | D13: 16(8) | E13: 180000
A14: 8 | B14: ANDRAWUS MUSA | C14: ASST. DIRECTOR, STORES | D14: 15(9) | E14: 126000
A15: 9 | B15: AYOBOLU OLAJIDE OLUFUNSHO | C15: ASST.DIR., INFORMATION | D15: 15 (8) | E15: 126000
A16: 10 | B16: HUSSEIN EGYE MUSA | C16: CHIEF PROTOCOL OFFICER | D16: 14(10) | E16: 90000
A17: 11 | B17: DONALD E. MKPANAM | C17: CHIEF ICT OFFICER | D17: 14(10) | E17: 90000
A18: 12 | B18: JOY HARUNA MAKERI | C18: RESEARCH FELLOW 1 TRAINING | D18: 14(10) | E18: 90000
... A34: 28 | B34: SHOLAGBERU T. SOFIAT | C34: ASST. ACCOUNT. OFFICER | D34: 8(7) | E34: 54000
B35: TOTAL | C35: 28 | E35: =SUM(E7:E34) -> 3114000
B37: INTERNAL AUDIT
A38: 1 | B38: OSANAIYE DAVID AKINYEMI | C38: DIRECTOR INTERNAL AUDIT | D38: 17(9) | E38: 270000
A39: 2 | B39: JAMILA ABDUL | C39: AUDITOR II | D39: 8(7) | E39: 54000
C40: 2 | E40: 324000
B42: LEG. SUPPORT SEVICES
A43: 1 | B43: PROF. EDOBA BRIGHT OMOREGBE | C43: AG. DLSS | D43: 17(9) | E43: 270000
A44: 2 | B44: DR CLINTON JAJA | C44: SENIOR RESEARCH FELLOW | D44: 15(9) | E44: 126000
A45: 3 | B45: BETHEL UZOMA IHUGBA | C45: SNR RESEARCH FELLOW | D45: 15(9) | E45: 126000
A46: 4 | B46: OGUCHE SAMUEL | C46: SNR RESEARCH FELLOW | D46: 15(9) | E46: 126000
A47: 5 | B47: IBRAHIM USMAN | C47: SNR RESEARCH FELLOW | D47: 15(8) | E47: 126000
A48: 6 | B48: DR MOHAMMED O. AMALI | C48: RESEARCH FELLOW I | D48: 14(10) | E48: 90000
A49: 7 | B49: YAHAYA SHAMSU | C49: RESEARCH FELLOW 1 | D49: 14(10) | E49: 90000
A50: 8 | B50: OFORDEME ADAOBI JULIA | C50: RESEARCH FELLOW 1 | D50: 14(9) | E50: 90000
A51: 9 | B51: DORIS DAKDA AARON | C51: RESEARCH FELLOW II | D51: 13(10) | E51: 90000
A52: 10 | B52: ZAINAB AKINDE | C52: RESEARCH OFFICER | D52: 9(7) | E52: 54000
A53: 11 | B53: ABDULLAHI AHMAD USMAN | C53: RESEARCH OFFICER | D53: 9(7) | E53: 54000
A54: 12 | B54: GUNAT NANSAK MARK | C54: RESEARCH OFFICER | D54: 9(7) | E54: 54000
B55: TOTAL | C55: 12 | E55: 1296000
B57: LEGAL SERVICES
A58: 1 | B58: DR SHUIBU DANWANKA | C58: DIRECTOR LEGAL SERVICES | D58: 17(9) | E58: 270000
A59: 2 | B59: ABDULSALAM BAKO | C59: MANAGER, LEGAL SERVICES | D59: 15 (8) | E59: 126000
B60: TOTAL | C60: 2 | E60: 396000
B62: DEMOCRACY & GOVERNANCE
A63: 1 | B63: DR. ADEWALE ADEREMI | C63: DIRECTOR, DEMOCRATIC STUDIES | D63: 17(9) | E63: 270000
A64: 2 | B64: NDANUSA MOHAMMED MANZUMA | C64: SNR RESEARCH FELLOW | D64: 15 (7) | E64: 126000
A65: 3 | B65: EJALONIBU GANIYU LAYI | C65: RESEARCH FELLOW 11 | D65: 13(10) | E65: 90000
A66: 4 | B66: LOHNA BONKAT JONATHAN | C66: RESEARCH FELLOW 11 | D66: 13(9) | E66: 90000
A67: 5 | B67: YUNUSA ABDULLAHI | C67: RESEARCH FELLOW 1 | D67: 14(10) | E67: 90000
A68: 6 | B68: EMILY EKHIDE | C68: RESEARCH FELLOW 1 | D68: 14(9) | E68: 90000
A69: 7 | B69: UDEFUNA NNADOZIE PATRICK | C69: RESEARCH OFFICER | D69: 12(7) | E69: 54000
A70: 8 | B70: SHAFIU YAHYA MIKAIL | C70: PRINCIPAL RESEARCH OFFICER | D70: 12(7) | E70: 54000
A71: 9 | B71: HASSAN YERIMA | C71: PRINCIPAL RESEARCH OFFICER | D71: 12(7) | E71: 54000
A72: 10 | B72: HAUWA PATE SADIQ | C72: PRINCIPAL PROGRAMME OFFICER | D72: 12(8) | E72: 54000
A73: 11 | B73: ABAYOMI KAYODE QUADRI | C73: RESEARCH OFFICER | D73: 10(8) | E73: 54000
A74: 12 | B74: NNANDI LIVINUS ATURE | C74: RESEARCH ASSISTANT | D74: 9(8) | E74: 54000
A75: 13 | B75: LUCKY AGWOM | C75: RESEARCH ASSISTANT | D75: 8(8) | E75: 54000
B76: TOTAL | C76: 13 | E76: 1134000
B78: DEPARTMENT OF STUDIES
A79: 1 | B79: DR ASIMIYU G. ABIOLA | C79: DIRECTOR POST GRADUATE | D79: 17(9) | E79: 270000
A80: 2 | B80: USMAN WALI | C80: SENIOR RESEARCH FELLOW | D80: 15 (7) | E80: 126000
A81: 3 | B81: MOSHOOD TOSHO AMUDA | C81: MANAGER, EXAMS & RECORDS | D81: 15 (7) | E81: 126000
A82: 4 | B82: ANTHONY EDET | C82: ASST. MGR M&E | D82: 13(10) | E82: 90000
A83: 5 | B83: IGWE STACY | C83: PROGRAMME OFFICER | D83: 10(8) | E83: 54000
B84: TOTAL | C84: 5 | E84: 666000
B86: ECON. DEV. & SOC. RESEARCH
A87: 1 | B87: TERFA WILLIAMS ABRAHAM | C87: SNR RESEARCH FELLOW | D87: 15(9) | E87: 126000
A88: 2 | B88: DR AUGUSTINE C. OSIGWE | C88: SNR RESEARCH FELLOW | D88: 15(9) | E88: 126000
A89: 3 | B89: NGARA CHRISTOPHER OCHANJA | C89: RESEARCH FELLOW 1 | D89: 14(11) | E89: 90000
A90: 4 | B90: OMOJU OLUWASOLA EMMANUEL | C90: RESEARCH FELLOW I | D90: 14(10) | E90: 90000
A91: 5 | B91: IBE EZECHI CYRIACUS | C91: RESEARCH FELLOW II | D91: 13(10) | E91: 90000
A92: 6 | B92: OSIKHEN LEO IGBANOI | C92: RESEARCH FELLOW 11 | D92: 13(9) | E92: 90000
A93: 7 | B93: OKUNGBOWA OSARETIN GODSPOWER | C93: RESEARCH FELLOW 11 | D93: 13(9) | E93: 90000
A94: 8 | B94: YUSUF IBRAHIM | C94: PRINCIPAL RESEARCH OFFICER | D94: 12(7) | E94: 54000
A95: 9 | B95: MARYAM MUSA SADA | C95: ASSIT. RESEARCH OFFICER | D95: 10(7) | E95: 54000
A96: 10 | B96: CHARITY EZENWAJIOBI | C96: REASEARCH. ASST. | D96: 8(8) | E96: 54000
B97: TOTAL | C97: 10 | E97: 864000
B99: TRAINING & INT''L COOP
A100: 1 | B100: REKIYA IBRAHIM ATTAH | C100: DEPUTY DIRECTOR TRAINING | D100: 16(8) | E100: 180000
A101: 2 | B101: DR FRANCIS NDUM OJIE | C101: CHIEF TRAINING OFFICER | D101: 14(10) | E101: 90000
A102: 3 | B102: OKECHUKWU UCHENNA HULDA | C102: PRINCIPALTRAINING OFFICER | D102: 12(8) | E102: 54000
A103: 4 | B103: TASNEEM IBRAHIM | C103: ASST. INFORMATION OFFICER | D103: 8(10) | E103: 54000
B104: TOTAL | C104: 3 | E104: 378000
B106: LIBRARY & DOCUMENTATION
A107: 1 | B107: DR MAIMUNA IZAH | C107: INSITUTE LIBRARIAN | D107: 17(9) | E107: 270000
A108: 2 | B108: CATHERINE E. IKOKOH | C108: SNR RESEARCH FELLOW DOCU | D108: 16(8) | E108: 180000
A109: 3 | B109: ALIYU SANNI ABUBAKAR | C109: RESEARCH FELLOW 11 DATA & DOCU | D109: 13(11) | E109: 90000
A110: 4 | B110: CHINAKO N. ASOGWA | C110: RESEARCH FELLOW 11 DATA & DOCU | D110: 13(11) | E110: 90000
A111: 5 | B111: AMOS ABA | C111: LIBRARY ASSISTANT | D111: 8(11) | E111: 54000
A112: 6 | B112: TITILAYO DANIEL MARVELLOUS | C112: LIBRARY ASSISTANT | D112: 8(10) | E112: 54000
A113: 7 | B113: ENENCHE JEREMIAH AGADA | C113: LIBRARY ASSISTANT | D113: 8(8) | E113: 54000
B114: TOTAL | C114: 7 | E114: 792000
B116: LEG, CENTRE FOR SECURITY ANALYSIS
A117: 1 | B117: OSOLAFIA MUHAMMAD EGYE | C117: PRINCIPAL RESEARCH OFFICER | D117: 12(9) | E117: 54000
A118: 2 | B118: EGUATU U. ONYEJELEM | C118: PRINCIPAL M&E OFFICER | D118: 12(8) | E118: 54000
B119: TOTAL | C119: 2 | E119: 108000
B121: FINANCE & ACCOUNTS
A122: 1 | B122: IBRAHIM M. MSHELIA | C122: DIR. FINANCE & ACCOUNTS | D122: 17(9) | E122: 270000
A123: 2 | B123: RAHILA NURUDEEN HABU | C123: ASST. DIRECTOR, ACCOUNTS | D123: 15(9) | E123: 126000
A124: 3 | B124: TONDO IORWUESE EDWARD | C124: ASST. DIRECTOR, ACCOUNTS | D124: 15(9) | E124: 126000
A125: 4 | B125: ARAOYE GANIYAT TITILOLA | C125: ASST. DIRECTOR, ACCOUNTS | D125: 15(7) | E125: 126000
A126: 5 | B126: SHEHU ABDULLAHI | C126: CHIEF ACCOUNT OFFICER | D126: 14(9) | E126: 90000
...

Sheet Sheet1

Sheet January 2023 PAYE
A1: NATIONAL INSTITUTE FOR LEGISLATIVE AND DEMOCRATIC STUDIES
A2: STAFF PAYROLL FOR THE MONTH OF JANUARY 2023
B4: STAFF NAME | C4: DESIGNATION | D4: GRADE LEVEL | E4: OLD PAYE | F4: NEW PAYE | G4: DIFFRENCE
A5: S/N | B5: DG'S OFFICE | E5: N | F5: N | G5: N
A6: 1 | B6: PROF. ABUBAKAR O. SULAIMAN | C6: DIRECTOR GENERAL | D6: CONSOL | E6: =201165.84 -> 201165.84 | F6: 201165.84 | G6: 0
A7: 2 | B7: DR JAKE DABANG DAN AZUMI | C7: DEPUTY DIR. TTECHNICAL | D7: 16(9) | E7: =#REF! -> #REF! | F7: 128510.39 | G7: =F7-E7 -> #REF!
A8: 3 | B8: DR ABDULSALAM NASIRU NAEEM | C8: SA ACADEMICS | D8: 16(9) | E8: =116473.51 -> 116473.51 | F8: 119107.95 | G8: =F8-E8 -> 2634.4414
A9: 4 | B9: RAHEEM USMAN AYIGORO | C9: SA-INFRASTRUCTURE | D9: 16 (9) | E9: =79993.51 -> 79993.51 | F9: 82627.951 | G9: =F9-E9 -> 2634.4414
A10: 5 | B10: MARIAM MOHAMMED BELLO | C10: SA- SPECIAL DUTIES | D10: 16(8) | E10: =107095.69 -> 107095.69 | F10: 109730.05 | G10: =F10-E10 -> 2634.3634
A11: 6 | B11: AKINSANMI ADEJOKE OLUKEMI | C11: DEPUTY DIR. INFO/PROTOCOL | D11: 16(8) | E11: =#REF! -> #REF! | F11: 99032.678 | G11: =F11-E11 -> #REF!
A12: 7 | B12: DR IKEME ARTHUR J.O | C12: DEPUTY DIRECTOR, M&E | D12: 16(8) | E12: =#REF! -> #REF! | F12: 79832.678 | G12: =F12-E12 -> #REF!
A13: 8 | B13: MOSHOOD M. OLALERE | C13: DEPUTY DIR. GENERAL SERVICE | D13: 16(8) | E13: =#REF! -> #REF! | F13: 79832.678 | G13: =F13-E13 -> #REF!
A14: 9 | B14: ANDRAWUS MUSA | C14: ASST. DIRECTOR, STORES | D14: 15(9) | E14: =64436.1 -> 64436.1 | F14: 64436.103 | G14: =F14-E14 -> 0.0031466667
A15: 10 | B15: AYOBOLU OLAJIDE OLUFUNSHO | C15: ASST.DIR., INFORMATION | D15: 15 (8) | E15: =60212.92 -> 60212.92 | F15: 62404.98 | G15: =F15-E15 -> 2192.0603
A16: 11 | B16: HUSSEIN EGYE MUSA | C16: CHIEF PROTOCOL OFFICER | D16: 14(10) | E16: =52638.9 -> 52638.9 | F16: 54186.609 | G16: =F16-E16 -> 1547.7094
A17: 12 | B17: DONALD E. MKPANAM | C17: CHIEF ICT OFFICER | D17: 14(10) | E17: =43380 -> 43380 | F17: 44734.339 | G17: =F17-E17 -> 1354.3394
A18: 13 | B18: JOY HARUNA MAKERI | C18: RESEARCH FELLOW 1 TRAINING | D18: 14(10) | E18: =85278.9 -> 85278.9 | F18: 86826.609 | G18: =F18-E18 -> 1547.7094
A19: 14 | B19: ALI ABDULLAHI | C19: CHIEF ICT OFFICER | D19: 14(10) | E19: =#REF! -> #REF! | F19: 44006.617 | G19: =F19-E19 -> #REF!
A20: 15 | B20: PERCY TERFA GBAHABO | C20: HEAD, NILDS LIAISON OFFICE | D20: 13(9) | E20: =46673.26 -> 46673.26 | F20: 46666.667 | G20: =F20-E20 -> -6.5933333
A21: 16 | B21: HASSANA AHMED IBRAHIM | C21: PA- TO DG | D21: 13 (8) | E21: =63364.81 -> 63364.81 | F21: 64913.264 | G21: =F21-E21 -> 1548.4537
A22: 17 | B22: CHRISTIAN MADUABUCHI ODO | C22: PRINCIPAL ICT OFFICER | D22: 12(9) | E22: =31848.56 -> 31848.56 | F22: 34871.967 | G22: =F22-E22 -> 3023.4074
A23: 18 | B23: ADUGBA RICHARD TERSEER | C23: PRINCIPAL INFO. OFFICER | D23: 12(8) | E23: =#REF! -> #REF! | F23: 32008.563 | G23: =F23-E23 -> #REF!
A24: 19 | B24: EGUATU U. ONYEJELEM | C24: PRINCIPAL M&E OFFICER | D24: 12(8) | E24: =#REF! -> #REF! | F24: 32098.951 | G24: =F24-E24 -> #REF!
A25: 20 | B25: ODEH SUZIE | C25: ADMIN. OFFICER, LIASION OFFICE | D25: 10(10) | E25: =27105.99 -> 27105.99 | F25: 27873.08 | G25: =F25-E25 -> 767.08969
A26: 21 | B26: YAKUB OLUWATOYIN USMAN | C26: ASST. ADMIN. OFFICER | D26: 10(9) | E26: =26339.08 -> 26339.08 | F26: 27105.987 | G26: =F26-E26 -> 766.90656
A27: 22 | B27: ELIZABETH OGECHUKWU ONYEAKU | C27: ICT OFFICER | D27: 9(8) | E27: 21640.95 | F27: 21640.953 | G27: =F27-E27 -> 0.0028626667
A28: 23 | B28: VICTOR ASUKWO | C28: ICT OFFICER | D28: 9(8) | E28: =21640.95 -> 21640.95 | F28: 22338.483 | G28: =F28-E28 -> 697.5326
A29: 24 | B29: IJEOMA NKOLIKWA | C29: STORES OFFICER | D29: 9(8) | E29: 21640.95 | F29: 22338.483 | G29: =F29-E29 -> 697.5326
A30: 25 | B30: ABDULRAHMAN A SULAIMAN | C30: ASSISTANT STORES OFFICER | D30: 8 (10) | E30: =17572.89 -> 17572.89 | F30: 18102.903 | G30: =F30-E30 -> 530.01273
A31: 26 | B31: TASSNEEM IBRAHIM | C31: ASSIST. INFORMATION | D31: 8(10) | E31: =17572.89 -> 17572.89 | F31: 18102.903 | G31: =F31-E31 -> 530.01273
A32: 27 | B32: DARE SHEU MAGBON | C32: ASSIST. PG | D32: 8(10) | E32: =17572.89 -> 17572.89 | F32: 18102.903 | G32: =F32-E32 -> 530.01273
A33: 28 | B33: JIMOH ADEBAYO ZAKA | C33: ASST. OFFICER/COMM | D33: 9(8) | E33: 21640.95 | F33: 22338.483 | G33: =F33-E33 -> 697.5326
A34: 29 | B34: MOHAMMED BELLO | C34: RESEARCH ASSITANT PG | D34: 8(8) | E34: =16512.68 -> 16512.68 | F34: 17042.714 | G34: =F34-E34 -> 530.03387
A35: 30 | B35: SULEIMAN ABUBAKAR SODEEQ | C35: ASST. ADMIN. OFFICER | D35: 8(8) | E35: =16512.68 -> 16512.68 | F35: 17042.866 | G35: =F35-E35 -> 530.18587
A36: 31 | B36: HARUNA JIBRIL A. | C36: ASST. ADMIN. OFFICER | D36: 8(8) | E36: =16512.68 -> 16512.68 | F36: 17043.018 | G36: =F36-E36 -> 530.33787
B37: TOTAL | C37: 31 | E37: =SUM(E6:E36) -> #REF! | F37: =SUM(F6:F36) -> 1716067.7 | G37: =SUM(G6:G36) -> #REF!
B39: INTERNAL AUDIT
A40: 1 | B40: OSANAIYE DAVID AKINYEMI | C40: DIRECTOR INTERNAL AUDIT | D40: 17(9) | E40: =156349.82 -> 156349.82 | F40: 161106.81 | G40: =F40-E40 -> 4756.9869
A41: 2 | B41: JAMILA ABDUL | C41: AUDITOR II | D41: 8(7) | E41: =16512.68 -> 16512.68 | F41: 16512.682 | G41: =F41-E41 -> 0.0021906667
C42: 2 | E42: =SUM(E40:E41) -> 172862.5 | F42: =SUM(F40:F41) -> 177619.49 | G42: =SUM(G40:G41) -> 4756.989
B44: LEG. SUPPORT SEVICES
A45: 1 | B45: PROF. EDOBA BRIGHT OMOREGBE | C45: AG. DLSS | D45: 17(9) | E45: =180306.81 -> 180306.81 | F45: 180306.81 | G45: =F45-E45 -> -0.0031413333
A46: 2 | B46: DR CLINTON JAJA | C46: SENIOR RESEARCH FELLOW | D46: 15(9) | E46: =79956.94 -> 79956.94 | F46: 79956.939 | G46: =F46-E46 -> -0.00085333335
A47: 3 | B47: BETHEL UZOMA IHUGBA | C47: SNR RESEARCH FELLOW | D47: 15(9) | E47: =79956.94 -> 79956.94 | F47: 79956.939 | G47: =F47-E47 -> -0.00085333335
A48: 4 | B48: OGUCHE SAMUEL | C48: SNR RESEARCH FELLOW | D48: 15(9) | E48: =77764.98 -> 77764.98 | F48: 79956.939 | G48: =F48-E48 -> 2191.9591
A49: 5 | B49: IBRAHIM USMAN | C49: SNR RESEARCH FELLOW | D49: 15(8) | E49: =#REF! -> #REF! | F49: 70061.52 | G49: =F49-E49 -> #REF!
A50: 6 | B50: DR MOHAMMED O. AMALI | C50: RESEARCH FELLOW I | D50: 14(10) | E50: =56478.9 -> 56478.9 | F50: 57889.865 | G50: =F50-E50 -> 1410.9648
A51: 7 | B51: YAHAYA SHAMSU | C51: RESEARCH FELLOW 1 | D51: 14(10) | E51: =56478.9 -> 56478.9 | F51: 58026.609 | G51: =F51-E51 -> 1547.7094
A52: 8 | B52: OFORDEME ADAOBI JULIA | C52: RESEARCH FELLOW 1 | D52: 14(9) | E52: =#REF! -> #REF! | F52: 55518.903 | G52: =F52-E52 -> #REF!
A53: 9 | B53: DORIS DAKDA AARON | C53: RESEARCH FELLOW II | D53: 13(10) | E53: =48052.11 -> 48052.11 | F53: 49548.776 | G53: =F53-E53 -> 1496.6662
A54: 10 | B54: ZAINAB AKINDE | C54: RESEARCH OFFICER | D54: 9(7) | E54: =28360.95 -> 28360.95 | F54: 28360.953 | G54: =F54-E54 -> 0.0028626667
A55: 11 | B55: ABDULLAHI AHMAD USMAN | C55: RESEARCH OFFICER | D55: 9(7) | E55: =28360.95 -> 28360.95 | F55: 28360.953 | G55: =F55-E55 -> 0.0028626667
A56: 12 | B56: GUNAT NANSAK MARK | C56: RESEARCH OFFICER | D56: 9(7) | E56: =28360.95 -> 28360.95 | F56: 28360.953 | G56: =F56-E56 -> 0.0028626667
B57: TOTAL | C57: 12 | E57: =SUM(E45:E56) -> #REF! | F57: =SUM(F45:F56) -> 796306.16 | G57: =SUM(G45:G56) -> #REF!
B59: LEGAL SERVICES
A60: 1 | B60: DR SHUIBU DANWANKA | C60: DIRECTOR LEGAL SERVICES | D60: 17(9) | E60: =180306.81 -> 180306.81 | F60: ='[9]August 2022 (2)'!$AA$56 -> 180306.81 | G60: =F60-E60 -> -0.0031413333
B61: TOTAL | C61: 1 | E61: =SUM(E60:E60) -> 180306.81 | F61: =SUM(F60:F60) -> 180306.81 | G61: =F61-E61 -> -0.0031413333
B63: DEMOCRACY & GOVERNANCE
A64: 1 | B64: DR. ADEWALE ADEREMI | C64: DIRECTOR, DEMOCRATIC STUDIES | D64: 17(9) | E64: =180306.81 -> 180306.81 | F64: 180306.81 | G64: =F64-E64 -> -0.0031413333
A65: 2 | B65: NDANUSA MOHAMMED MANZUMA | C65: SNR RESEARCH FELLOW | D65: 15 (7) | E65: 75572.92 | F65: 75572.916 | G65: =F65-E65 -> -0.0043093333
A66: 3 | B66: EJALONIBU GANIYU LAYI | C66: RESEARCH FELLOW 11 | D66: 13(10) | E66: =48170.87 -> 48170.87 | F66: 49548.776 | G66: =F66-E66 -> 1377.9062
A67: 4 | B67: LOHNA BONKAT JONATHAN | C67: RESEARCH FELLOW 11 | D67: 13(9) | E67: =46673.26 -> 46673.26 | F67: 48170.87 | G67: =F67-E67 -> 1497.6103
A68: 5 | B68: YUNUSA ABDULLAHI | C68: RESEARCH FELLOW 1 | D68: 14(10) | E68: 56478.9 | F68: 58026.609 | G68: =F68-E68 -> 1547.7094
A69: 6 | B69: UDEFUNA NNADOZIE PATRICK | C69: RESEARCH OFFICER | D69: 10(14) | E69: 36127.27 | F69: 37661.421 | G69: =F69-E69 -> 1534.1514
A70: 7 | B70: OSOLAFIA MUHAMMAD EGYE | C70: PRINCIPAL RESEARCH OFFICER | D70: 12(9) | E70: 41248.56 | F70: 43278.495 | G70: =F70-E70 -> 2029.9348
A71: 8 | B71: SHAFIU YAHYA MIKAIL | C71: PRINCIPAL RESEARCH OFFICER | D71: 12(7) | E71: =40149.18 -> 40149.18 | F71: 40149.175 | G71: =F71-E71 -> -0.0047333333
A72: 9 | B72: HASSAN YERIMA | C72: PRINCIPAL RESEARCH OFFICER | D72: 12(7) | E72: =40149.18 -> 40149.18 | F72: 40149.175 | G72: =F72-E72 -> -0.0047333333
A73: 10 | B73: HAUWA PATE SADIQ | C73: PRINCIPAL PROGRAMME OFFICER | D73: 12(8) | E73: =#REF! -> #REF! | F73: ='[9]August 2022 (2)'!$Z$69 -> 41338.951 | G73: =F73-E73 -> #REF!
A74: 11 | B74: ABAYOMI KAYODE QUADRI | C74: RESEARCH OFFICER | D74: 10(8) | E74: =32291.82 -> 32291.82 | F74: 33059.078 | G74: =F74-E74 -> 767.25841
A75: 12 | B75: NNANDI LIVINUS ATURE | C75: RESEARCH ASSISTANT | D75: 9(8) | E75: =24685.95 -> 24685.95 | F75: 29058.483 | G75: =F75-E75 -> 4372.5326
A76: 13 | B76: LUCKY AGWOM | C76: RESEARCH ASSISTANT | D76: 8(8) | E76: =24685.95 -> 24685.95 | F76: 25271.771 | G76: =F76-E76 -> 585.82147
B77: TOTAL | C77: 13 | E77: =SUM(E64:E76) -> #REF! | F77: =SUM(F64:F76) -> 701592.53 | G77: =SUM(G64:G76) -> #REF!
B79: DEPARTMENT OF STUDIES
A80: 1 | B80: DR ASIMIYU G. ABIOLA | C80: DIRECTOR POST GRADUATE | D80: 17(9) | E80: =180306.81 -> 180306.81 | F80: 180306.81 | G80: =F80-E80 -> -0.0031413333
A81: 2 | B81: USMAN WALI | C81: SENIOR RESEARCH FELLOW | D81: 15 (7) | E81: =75572.92 -> 75572.92 | F81: 75572.916 | G81: =F81-E81 -> -0.0043093333
A82: 3 | B82: MOSHOOD TOSHO AMUDA | C82: MANAGER, EXAMS & RECORDS | D82: 15 (7) | E82: =75572.92 -> 75572.92 | F82: 75572.916 | G82: =F82-E82 -> -0.0043093333
A83: 4 | B83: ANTHONY EDET | C83: ASST. MGR M&E | D83: 13(10) | E83: 48170.87 | F83: 49548.776 | G83: =F83-E83 -> 1377.9062
A84: 5 | B84: IGWE STACY | C84: PROGRAMME OFFICER | D84: 10(8) | E84: =32291.82 -> 32291.82 | F84: 33059.078 | G84: =F84-E84 -> 767.25841
B85: TOTAL | C85: 5 | E85: =SUM(E80:E84) -> 411915.34 | F85: =SUM(F80:F84) -> 414060.49 | G85: =SUM(G80:G84) -> 2145.1528
B87: ECON. DEV. & SOC. RESEARCH
A88: 1 | B88: ASEMOTA OMOROGBE JOSEPH | C88: Ag. DEPUTY DIRECTOR, ECO & SOC DEV DEPT | D88: 16(9) | E88: =97273.51 -> 97273.51 | F88: 99907.951 | G88: =F88-E88 -> 2634.4414
A89: 2 | B89: TERFA WILLIAMS ABRAHAM | C89: SNR RESEARCH FELLOW | D89: 15(9) | E89: =79956.94 -> 79956.94 | F89: 79956.939 | G89: =F89-E89 -> -0.00085333335
A90: 3 | B90: DR AUGUSTINE C. OSIGWE | C90: SNR RESEARCH FELLOW | D90: 15(9) | E90: =79796.1 -> 79796.1 | F90: 79796.103 | G90: =F90-E90 -> 0.0031466666
A91: 4 | B91: NGARA CHRISTOPHER OCHANJA | C91: RESEARCH FELLOW 1 | D91: 14(11) | E91: =57894.08 -> 57894.08 | F91: 59441.782 | G91: =F91-E91 -> 1547.702
A92: 5 | B92: OMOJU OLUWASOLA EMMANUEL | C92: RESEARCH FELLOW I | D92: 14(10) | E92: =56478.9 -> 56478.9 | F92: 58026.609 | G92: =F92-E92 -> 1547.7094
A93: 6 | B93: IBE EZECHI CYRIACUS | C93: RESEARCH FELLOW II | D93: 13(10) | E93: =48170.87 -> 48170.87 | F93: 49548.776 | G93: =F93-E93 -> 1377.9062
A94: 7 | B94: OSIKHEN LEO IGBANOI | C94: RESEARCH FELLOW 11 | D94: 13(9) | E94: =46673.26 -> 46673.26 | F94: 48170.87 | G94: =F94-E94 -> 1497.6103
A95: 8 | B95: OKUNGBOWA OSARETIN GODSPOWER | C95: RESEARCH FELLOW 11 | D95: 13(9) | E95: =46673.26 -> 46673.26 | F95: 48170.87 | G95: =F95-E95 -> 1497.6103
A96: 9 | B96: YUSUF IBRAHIM | C96: PRINCIPAL RESEARCH OFFICER | D96: 12(7) | E96: =40149.18 -> 40149.18 | F96: 40149.175 | G96: =F96-E96 -> -0.0047333333
A97: 10 | B97: MARYAM MUSA SADA | C97: ASSIT. RESEARCH OFFICER | D97: 10(7) | E97: 0 | F97: 0 | G97: =F97-E97 -> 0
A98: 11 | B98: CHARITY EZENWAJIOBI | C98: REASEARCH. ASST. | D98: 8(8) | E98: =24685.95 -> 24685.95 | F98: 24749.797 | G98: =F98-E98 -> 63.847063
B99: TOTAL | C99: 11 | E99: =SUM(E88:E98) -> 577752.05 | F99: =SUM(F88:F98) -> 587918.87 | G99: =SUM(G88:G98) -> 10166.824
B101: TRAINING & INT''L COOP
A102: 1 | B102: REKIYA IBRAHIM ATTAH | C102: DEPUTY DIRECTOR TRAINING | D102: 16(8) | E102: =79993.51 -> 79993.51 | F102: 79993.514 | G102: =F102-E102 -> 0.0038506667
A103: 2 | B103: DR FRANCIS NDUM OJIE | C103: CHIEF TRAINING OFFICER | D103: 14(10) | E103: =43380.1 -> 43380.1 | F103: 44734.339 | G103: =F103-E103 -> 1354.2394
A104: 3 | B104: ABUBAKAR MOHAMMED BASHIR | C104: ASST. CHIEF TRAINING OFFICER | D104: 13(9) | E104: =38272.44 -> 38272.44 | F104: 39582.845 | G104: =F104-E104 -> 1310.4048
A105: 4 | B105: OKECHUKWU UCHENNA HULDA | C105: PRINCIPALTRAINING OFFICER | D105: 12(8) | E105: =#REF! -> #REF! | F105: 32098.951 | G105: =F105-E105 -> #REF!
B106: TOTAL | C106: 4 | E106: =SUM(E102:E105) -> #REF! | F106: =SUM(F102:F105) -> 196409.65 | G106: =SUM(G102:G105) -> #REF!
B108: LIBRARY & DOCUMENTATION
A109: 1 | B109: DR MAIMUNA IZAH | C109: INSITUTE LIBRARIAN | D109: 17(9) | E109: =180306.81 -> 180306.81 | F109: 180145.97 | G109: =F109-E109 -> -160.83914
...

Sheet January 2023 NHF)
A1: NATIONAL INSTITUTE FOR LEGISLATIVE AND DEMOCRATIC STUDIES
A2: STAFF PAYROLL FOR THE MONTH OF JANUARY 2023
E3: ='[1]FEB 08'!E11/'[1]FEB 08'!M11 -> #REF!
B4: STAFF NAME | C4: DESIGNATION | D4: GRADE LEVEL | E4: BASIC SALARY | F4: NEW NHF DED. | G4: OLD NHF DED. | H4: DIFFERENCE
A5: S/N | B5: DG'S OFFICE | E5: N | F5: N | G5: N | H5: N
A6: 1 | B6: PROF. ABUBAKAR O. SULAIMAN | C6: DIRECTOR GENERAL | D6: CONSOL | E6: 160488.75
A7: 2 | B7: DR JAKE DABANG DAN AZUMI | C7: DEPUTY DIR. TTECHNICAL | D7: 16(9) | E7: =42653.17 -> 42653.17 | F7: =0.025*E7 -> 1066.3293 | G7: ='[10]April 2022'!$H$26 -> 1028.9423 | H7: =F7-G7 -> 37.387
A8: 3 | B8: DR ABDULSALAM NASIRU NAEEM | C8: SA ACADEMICS | D8: 16(9) | E8: =42653.17 -> 42653.17 | H8: =F8-G8 -> 0
A9: 4 | B9: RAHEEM USMAN AYIGORO | C9: SA-INFRASTRUCTURE | D9: 16 (9) | E9: =42653.17 -> 42653.17 | H9: =F9-G9 -> 0
A10: 5 | B10: MARIAM MOHAMMED BELLO | C10: SA- SPECIAL DUTIES | D10: 16(8) | E10: 41157.69 | H10: =F10-G10 -> 0
A11: 6 | B11: AKINSANMI ADEJOKE OLUKEMI | C11: DEPUTY DIR. INFO/PROTOCOL | D11: 16(8) | E11: =41157.69 -> 41157.69 | F11: =0.025*E11 -> 1028.9423 | G11: =G7 -> 1028.9423 | H11: =F11-G11 -> 0
A12: 7 | B12: DR IKEME ARTHUR J.O | C12: DEPUTY DIRECTOR, M&E | D12: 16(8) | E12: =41157.69 -> 41157.69 | F12: =0.025*E12 -> 1028.9423 | G12: =1028.94 -> 1028.94 | H12: =F12-G12 -> 0.00225
A13: 8 | B13: MOSHOOD M. OLALERE | C13: DEPUTY DIR. GENERAL SERVICE | D13: 16(8) | E13: =41157.69 -> 41157.69 | F13: =0.025*E13 -> 1028.9423 | G13: =1028.94 -> 1028.94 | H13: =F13-G13 -> 0.00225
A14: 9 | B14: ANDRAWUS MUSA | C14: ASST. DIRECTOR, STORES | D14: 15(9) | E14: 33507.5 | F14: =0.025*E14 -> 837.6875 | G14: ='[10]April 2022'!$H$28 -> 837.6875 | H14: =F14-G14 -> 0
A15: 10 | B15: AYOBOLU OLAJIDE OLUFUNSHO | C15: ASST.DIR., INFORMATION | D15: 15 (8) | E15: 32263.2 | H15: =F15-G15 -> 0
A16: 11 | B16: HUSSEIN EGYE MUSA | C16: CHIEF PROTOCOL OFFICER | D16: 14(10) | E16: 27611.23 | F16: 0 | G16: 0 | H16: =F16-G16 -> 0
A17: 12 | B17: DONALD E. MKPANAM | C17: CHIEF ICT OFFICER | D17: 14(10) | E17: 27611.23 | F17: =0.025*E17 -> 690.28075 | G17: ='[10]April 2022'!$H$27 -> 668.31625 | H17: =F17-G17 -> 21.9645
A18: 13 | B18: JOY HARUNA MAKERI | C18: RESEARCH FELLOW 1 TRAINING | D18: 14(10) | E18: 27611.23 | H18: =F18-G18 -> 0
A19: 14 | B19: ALI ABDULLAHI | C19: CHIEF ICT OFFICER | D19: 14(10) | E19: 27611.23 | H19: =F19-G19 -> 0
A20: 15 | B20: PERCY TERFA GBAHABO | C20: HEAD, NILDS LIAISON OFFICE | D20: 13(9) | E20: 24741.26 | H20: =F20-G20 -> 0
A21: 16 | B21: HASSANA AHMED IBRAHIM | C21: PA- TO DG | D21: 13 (8) | E21: =23891.12 -> 23891.12 | F21: =0.025*E21 -> 597.278 | G21: ='[10]April 2022'!$H$52 -> 576.87475 | H21: =F21-G21 -> 20.40325
A22: 17 | B22: CHRISTIAN MADUABUCHI ODO | C22: PRINCIPAL ICT OFFICER | D22: 12(9) | E22: =22837.82 -> 22837.82 | F22: =0.025*E22 -> 570.9455 | G22: ='[10]April 2022'!$H$45 -> 538.022 | H22: =F22-G22 -> 32.9235
A23: 18 | B23: ADUGBA RICHARD TERSEER | C23: PRINCIPAL INFO. OFFICER | D23: 12(8) | E23: 21520.88 | H23: =F23-G23 -> 0
A24: 19 | B24: EGUATU U. ONYEJELEM | C24: PRINCIPAL M&E OFFICER | D24: 12(8) | E24: 21520.88 | H24: =F24-G24 -> 0
A25: 20 | B25: ODEH SUZIE | C25: ADMIN. OFFICER, LIASION OFFICE | D25: 10(10) | E25: =18779.3 -> 18779.3 | F25: =0 -> 0 | G25: =0 -> 0 | H25: =F25-G25 -> 0
A26: 21 | B26: YAKUB OLUWATOYIN USMAN | C26: ASST. ADMIN. OFFICER | D26: 10(9) | E26: 18281.64 | H26: =F26-G26 -> 0
A27: 22 | B27: ELIZABETH OGECHUKWU ONYEAKU | C27: ICT OFFICER | D27: 9(8) | E27: 14736.14 | H27: =F27-G27 -> 0
A28: 23 | B28: VICTOR ASUKWO | C28: ICT OFFICER | D28: 9(8) | E28: =15188.67 -> 15188.67 | H28: =F28-G28 -> 0
A29: 24 | B29: IJEOMA NKOLIKWA | C29: STORES OFFICER | D29: 9(8) | E29: =15188.67 -> 15188.67 | H29: =F29-G29 -> 0
A30: 25 | B30: ABDULRAHMAN A SULAIMAN | C30: ASSISTANT STORES OFFICER | D30: 8 (10) | E30: 13492.21 | H30: =F30-G30 -> 0
A31: 26 | B31: TASSNEEM IBRAHIM | C31: ASSIST. INFORMATION | D31: 8(10) | E31: 13492.21 | H31: =F31-G31 -> 0
A32: 27 | B32: DARE SHEU MAGBON | C32: ASSIST. PG | D32: 8(10) | E32: 13492.21 | H32: =F32-G32 -> 0
A33: 28 | B33: JIMOH ADEBAYO ZAKA | C33: ASST. OFFICER/COMM | D33: 9(8) | E33: 15188.67 | F33: =0 -> 0 | G33: =0 -> 0 | H33: =F33-G33 -> 0
A34: 29 | B34: MOHAMMED BELLO | C34: RESEARCH ASSITANT PG | D34: 8(8) | E34: =12732 -> 12732 | H34: =F34-G34 -> 0
A35: 30 | B35: SULEIMAN ABUBAKAR SODEEQ | C35: ASST. ADMIN. OFFICER | D35: 8(8) | E35: =12732 -> 12732 | H35: =F35-G35 -> 0
A36: 31 | B36: HARUNA JIBRIL A. | C36: ASST. ADMIN. OFFICER | D36: 8(8) | E36: =12732 -> 12732 | H36: =F36-G36 -> 0
B37: TOTAL | C37: 31 | E37: =SUM(E6:E36) -> 919842.32 | F37: =SUM(F6:F36) -> 6849.3477 | G37: =SUM(G6:G36) -> 6736.665 | H37: =F37-G37 -> 112.68275
H38: =F38-G38 -> 0
B39: INTERNAL AUDIT | H39: =F39-G39 -> 0
A40: 1 | B40: OSANAIYE DAVID AKINYEMI | C40: DIRECTOR INTERNAL AUDIT | D40: 17(9) | E40: 81740.02 | H40: =F40-G40 -> 0
A41: 2 | B41: JAMILA ABDUL | C41: AUDITOR II | D41: 8(7) | E41: 12351.94 | F41: =0 -> 0 | G41: =0 -> 0 | H41: =F41-G41 -> 0
C42: 2 | E42: =SUM(E40:E41) -> 94091.96 | F42: =SUM(F40:F41) -> 0 | G42: =SUM(G40:G41) -> 0 | H42: =F42-G42 -> 0
H43: =F43-G43 -> 0
B44: LEG. SUPPORT SEVICES | H44: =F44-G44 -> 0
A45: 1 | B45: PROF. EDOBA BRIGHT OMOREGBE | C45: AG. DLSS | D45: 17(9) | E45: 81740.02 | H45: =F45-G45 -> 0
A46: 2 | B46: DR CLINTON JAJA | C46: SENIOR RESEARCH FELLOW | D46: 15(9) | E46: 33507.5 | H46: =F46-G46 -> 0
A47: 3 | B47: BETHEL UZOMA IHUGBA | C47: SNR RESEARCH FELLOW | D47: 15(9) | E47: 33507.5 | H47: =F47-G47 -> 0
A48: 4 | B48: OGUCHE SAMUEL | C48: SNR RESEARCH FELLOW | D48: 15(9) | E48: 33507.5 | H48: =F48-G48 -> 0
A49: 5 | B49: IBRAHIM USMAN | C49: SNR RESEARCH FELLOW | D49: 15(8) | E49: 32263.2 | F49: =0.025*E49 -> 806.58 | G49: =837.69 -> 837.69 | H49: =F49-G49 -> -31.11
A50: 6 | B50: DR MOHAMMED O. AMALI | C50: RESEARCH FELLOW I | D50: 14(10) | E50: 27611.23 | H50: =F50-G50 -> 0
A51: 7 | B51: YAHAYA SHAMSU | C51: RESEARCH FELLOW 1 | D51: 14(10) | E51: 27611.23 | F51: 0 | G51: 0 | H51: =F51-G51 -> 0
A52: 8 | B52: OFORDEME ADAOBI JULIA | C52: RESEARCH FELLOW 1 | D52: 14(9) | E52: 26732.65 | H52: =F52-G52 -> 0
A53: 9 | B53: DORIS DAKDA AARON | C53: RESEARCH FELLOW II | D53: 13(10) | E53: 25523.45 | F53: =0.025*E53 -> 638.08625 | G53: ='[10]April 2022'!$H$46 -> 618.5315 | H53: =F53-G53 -> 19.55475
A54: 10 | B54: ZAINAB AKINDE | C54: RESEARCH OFFICER | D54: 9(7) | E54: =14736.14 -> 14736.14 | H54: =F54-G54 -> 0
A55: 11 | B55: ABDULLAHI AHMAD USMAN | C55: RESEARCH OFFICER | D55: 9(7) | E55: =14736.14 -> 14736.14 | H55: =F55-G55 -> 0
A56: 12 | B56: GUNAT NANSAK MARK | C56: RESEARCH OFFICER | D56: 9(7) | E56: =14736.14 -> 14736.14 | H56: =F56-G56 -> 0
B57: TOTAL | C57: 12 | E57: =SUM(E45:E56) -> 366212.7 | F57: =SUM(F45:F56) -> 1444.6663 | G57: =SUM(G45:G56) -> 1456.2215 | H57: =F57-G57 -> -11.55525
H58: =F58-G58 -> 0
B59: LEGAL SERVICES | H59: =F59-G59 -> 0
A60: 1 | B60: DR SHUIBU DANWANKA | C60: DIRECTOR LEGAL SERVICES | D60: 17(9) | E60: 81740.02 | F60: 0 | G60: 0 | H60: =F60-G60 -> 0
B61: TOTAL | C61: 1 | E61: =SUM(E60:E60) -> 81740.02 | F61: =SUM(F60:F60) -> 0 | G61: =SUM(G60:G60) -> 0 | H61: =F61-G61 -> 0
H62: =F62-G62 -> 0
B63: DEMOCRACY & GOVERNANCE | H63: =F63-G63 -> 0
A64: 1 | B64: DR. ADEWALE ADEREMI | C64: DIRECTOR, DEMOCRATIC STUDIES | D64: 17(9) | E64: 81740.02 | H64: =F64-G64 -> 0
A65: 2 | B65: NDANUSA MOHAMMED MANZUMA | C65: SNR RESEARCH FELLOW | D65: 15 (7) | E65: 31018.84 | H65: =F65-G65 -> 0
A66: 3 | B66: EJALONIBU GANIYU LAYI | C66: RESEARCH FELLOW 11 | D66: 13(10) | E66: 25523.45 | H66: =F66-G66 -> 0
A67: 4 | B67: LOHNA BONKAT JONATHAN | C67: RESEARCH FELLOW 11 | D67: 13(9) | E67: 24741.26 | F67: =0 -> 0 | G67: =0 -> 0 | H67: =F67-G67 -> 0
A68: 5 | B68: YUNUSA ABDULLAHI | C68: RESEARCH FELLOW 1 | D68: 14(10) | E68: 27611.23 | H68: =F68-G68 -> 0
A69: 6 | B69: UDEFUNA NNADOZIE PATRICK | C69: RESEARCH OFFICER | D69: 10(14) | E69: =20769.92 -> 20769.92 | H69: =F69-G69 -> 0
A70: 7 | B70: OSOLAFIA MUHAMMAD EGYE | C70: PRINCIPAL RESEARCH OFFICER | D70: 12(9) | E70: =22837.82 -> 22837.82 | F70: =0.025*E70 -> 570.9455 | G70: ='[10]April 2022'!$H$41 -> 538.022 | H70: =F70-G70 -> 32.9235
A71: 8 | B71: SHAFIU YAHYA MIKAIL | C71: PRINCIPAL RESEARCH OFFICER | D71: 12(7) | E71: 20749 | H71: =F71-G71 -> 0
A72: 9 | B72: HASSAN YERIMA | C72: PRINCIPAL RESEARCH OFFICER | D72: 12(7) | E72: 20749 | H72: =F72-G72 -> 0
A73: 10 | B73: HAUWA PATE SADIQ | C73: PRINCIPAL PROGRAMME OFFICER | D73: 12(8) | E73: 21520.88 | H73: =F73-G73 -> 0
A74: 11 | B74: ABAYOMI KAYODE QUADRI | C74: RESEARCH OFFICER | D74: 10(8) | E74: 17784.1 | H74: =F74-G74 -> 0
A75: 12 | B75: NNANDI LIVINUS ATURE | C75: RESEARCH ASSISTANT | D75: 9(8) | E75: =15188.67 -> 15188.67 | H75: =F75-G75 -> 0
A76: 13 | B76: LUCKY AGWOM | C76: RESEARCH ASSISTANT | D76: 8(8) | E76: =12732 -> 12732 | H76: =F76-G76 -> 0
B77: TOTAL | C77: 13 | E77: =SUM(E64:E76) -> 342966.19 | F77: =SUM(F64:F76) -> 570.9455 | G77: =SUM(G64:G76) -> 538.022 | H77: =F77-G77 -> 32.9235
H78: =F78-G78 -> 0
B79: DEPARTMENT OF STUDIES | H79: =F79-G79 -> 0
A80: 1 | B80: DR ASIMIYU G. ABIOLA | C80: DIRECTOR POST GRADUATE | D80: 17(9) | E80: 81740.02 | F80: 0 | G80: 0 | H80: =F80-G80 -> 0
A81: 2 | B81: USMAN WALI | C81: SENIOR RESEARCH FELLOW | D81: 15 (7) | E81: 31018.84 | F81: 0 | G81: 0 | H81: =F81-G81 -> 0
A82: 3 | B82: MOSHOOD TOSHO AMUDA | C82: MANAGER, EXAMS & RECORDS | D82: 15 (7) | E82: 31018.84 | F82: 0 | G82: 0 | H82: =F82-G82 -> 0
A83: 4 | B83: ANTHONY EDET | C83: ASST. MGR M&E | D83: 13(10) | E83: 25523.45 | F83: =0.025*E83 -> 638.08625 | G83: ='[10]April 2022'!$H$38 -> 618.5315 | H83: =F83-G83 -> 19.55475
A84: 5 | B84: IGWE STACY | C84: PROGRAMME OFFICER | D84: 10(8) | E84: 17784.1 | H84: =F84-G84 -> 0
B85: TOTAL | C85: 5 | E85: =SUM(E80:E84) -> 187085.25 | F85: =SUM(F80:F84) -> 638.08625 | G85: =SUM(G80:G84) -> 618.5315 | H85: =F85-G85 -> 19.55475
H86: =F86-G86 -> 0
B87: ECON. DEV. & SOC. RESEARCH | H87: =F87-G87 -> 0
A88: 1 | B88: ASEMOTA OMOROGBE JOSEPH | C88: Ag. DEPUTY DIRECTOR, ECO & SOC DEV DEPT | D88: 16(9) | E88: 42653.17 | H88: =F88-G88 -> 0
A89: 2 | B89: TERFA WILLIAMS ABRAHAM | C89: SNR RESEARCH FELLOW | D89: 15(9) | E89: 33507.5 | H89: =F89-G89 -> 0
A90: 3 | B90: DR AUGUSTINE C. OSIGWE | C90: SNR RESEARCH FELLOW | D90: 15(9) | E90: 33507.5 | F90: =0.025*E90 -> 837.6875 | G90: ='[10]April 2022'!$H$37 -> 837.6875 | H90: =F90-G90 -> 0
A91: 4 | B91: NGARA CHRISTOPHER OCHANJA | C91: RESEARCH FELLOW 1 | D91: 14(11) | E91: =28489.81 -> 28489.81 | F91: =0.025*E91 -> 712.24525 | G91: ='[10]April 2022'!$H$44 -> 690.28075 | H91: =F91-G91 -> 21.9645
A92: 5 | B92: OMOJU OLUWASOLA EMMANUEL | C92: RESEARCH FELLOW I | D92: 14(10) | E92: 27611.23 | H92: =F92-G92 -> 0
A93: 6 | B93: IBE EZECHI CYRIACUS | C93: RESEARCH FELLOW II | D93: 13(10) | E93: 25523.45 | H93: =F93-G93 -> 0
A94: 7 | B94: OSIKHEN LEO IGBANOI | C94: RESEARCH FELLOW 11 | D94: 13(9) | E94: 24741.26 | H94: =F94-G94 -> 0
A95: 8 | B95: OKUNGBOWA OSARETIN GODSPOWER | C95: RESEARCH FELLOW 11 | D95: 13(9) | E95: 24741.26 | H95: =F95-G95 -> 0
A96: 9 | B96: YUSUF IBRAHIM | C96: PRINCIPAL RESEARCH OFFICER | D96: 12(7) | E96: =20749 -> 20749 | H96: =F96-G96 -> 0
A97: 10 | B97: MARYAM MUSA SADA | C97: ASSIT. RESEARCH OFFICER | D97: 10(7) | E97: 0 | H97: =F97-G97 -> 0
A98: 11 | B98: CHARITY EZENWAJIOBI | C98: REASEARCH. ASST. | D98: 8(8) | E98: =12732 -> 12732 | F98: 0 | G98: 0 | H98: =F98-G98 -> 0
B99: TOTAL | C99: 11 | E99: =SUM(E88:E98) -> 274256.18 | F99: =SUM(F88:F98) -> 1549.9327 | G99: =SUM(G88:G98) -> 1527.9682 | H99: =F99-G99 -> 21.9645
H100: =F100-G100 -> 0
...

Sheet PAYE Computation
A1: NATIONAL INSTITUTE FOR LEGISLATIVE AND DEMOCRATIC STUDIES
A2: NATIONAL ASSEMBLY ABUJA
A3: TAX COMPUTATION FOR 2023
A4: S/NO | B4: NAME | C4: MONTHLY TOTAL SALARY | D4: NO OF MONTHS | E4: ANNUAL SALARY GROSSED UP | F4: NATIONAL HOUSING SCHEME = 2.5% OF BASIC SALARY | G4: PENSION CONTRIBUTION = 8% OF CONSOLIDATED | H4: NHIS | I4: NET SALARY (EXC OF CRA) | M4: CRA=#200,000+(20% 0F NET SALARY (EXC OF CRA) | N4: TOTAL RELIEF | O4: CHARGEABLE INCOME | P4: FIRST N300,000 @ 7% | Q4: NEXT N300,000 @ 11% | R4: NEXT N500,000 @ 15% | S4: NEXT N500,000@ 19% | T4: NEXT N1,600,000 @ 21% | U4: ABOVE N3,200,000 @ 24% | V4: ANNUAL TAX PAYABLE | X4: MONTHLY TAX PAYABLE | Y4: MINIMUM TAX PAYABLE | Z4: NEW ACTUAL TAX PAYABLE | AA4: OLD Tax | AB4: Difference
A5: 1 | B5: PROF. ABUBAKAR O. SULAIMAN | C5: 1158849.8 | D5: 12 | E5: 13906198 | I5: 13906198 | J5: 200000 | K5: 0.2 | L5: 2781239.6 | M5: 2981239.6 | N5: 2981239.6 | O5: 10924958 | P5: 21000 | Q5: 33000 | R5: 75000 | S5: 95000 | T5: 336000 | U5: 1853990 | V5: 2413990 | W5: 12 | X5: 201165.84 | Z5: 201165.84 | AA5: 201165.84 | AB5: -0.0040533334
A6: 3 | B6: DR JAKE DABANG DAN AZUMI | C6: 781465.02 | D6: 12 | E6: 9377580.3 | F6: 12347.31 | I6: 9365233 | J6: 200000 | K6: 0.2 | L6: 1873046.6 | M6: 2073046.6 | N6: 2085393.9 | O6: 7292186.4 | P6: 21000 | Q6: 33000 | R6: 75000 | S6: 95000 | T6: 336000 | U6: 982124.73 | V6: 1542124.7 | W6: 12 | X6: 128510.39 | Z6: 128510.39 | AA6: 128508.39 | AB6: 2.006208
A7: 4 | B7: DR ABDULSALAM NASIRU NAEEM | C7: 731465.02 | D7: 12 | E7: 8777580.3 | I7: 8777580.3 | J7: 200000 | K7: 0.2 | L7: 1755516.1 | M7: 1955516.1 | N7: 1955516.1 | O7: 6822064.2 | P7: 21000 | Q7: 33000 | R7: 75000 | S7: 95000 | T7: 336000 | U7: 869295.42 | V7: 1429295.4 | W7: 12 | X7: 119107.95 | Z7: 119107.95 | AA7: 116473.51 | AB7: 2634.4414
A8: 5 | B8: RAHEEM USMAN AYIGORO | C8: 541465.02 | D8: 12 | E8: 6497580.3 | I8: 6497580.3 | J8: 200000 | K8: 0.2 | L8: 1299516.1 | M8: 1499516.1 | N8: 1499516.1 | O8: 4998064.2 | P8: 21000 | Q8: 33000 | R8: 75000 | S8: 95000 | T8: 336000 | U8: 431535.42 | V8: 991535.42 | W8: 12 | X8: 82627.951 | Z8: 82627.951 | AA8: 79993.51 | AB8: 2634.4414
A9: 6 | B9: MARIAM MOHAMMED BELLO | C9: 682621.81 | D9: 12 | E9: 8191461.7 | I9: 8191461.7 | J9: 200000 | K9: 0.2 | L9: 1638292.3 | M9: 1838292.3 | N9: 1838292.3 | O9: 6353169.3 | P9: 21000 | Q9: 33000 | R9: 75000 | S9: 95000 | T9: 336000 | U9: 756760.64 | V9: 1316760.6 | W9: 12 | X9: 109730.05 | Z9: 109730.05 | AA9: 107095.69 | AB9: 2634.3634
A10: 7 | B10: AKINSANMI ADEJOKE OLUKEMI | C10: 627744 | D10: 12 | E10: 7532927.9 | F10: 10052.25 | I10: 7522875.7 | J10: 200000 | K10: 0.2 | L10: 1504575.1 | M10: 1704575.1 | N10: 1714627.4 | O10: 5818300.6 | P10: 21000 | Q10: 33000 | R10: 75000 | S10: 95000 | T10: 336000 | U10: 628392.13 | V10: 1188392.1 | W10: 12 | X10: 99032.678 | Z10: 99032.678 | AA10: 96398.374 | AB10: 2634.304
A11: 8 | B11: DR IKEME ARTHUR J.O | C11: 527744 | D11: 12 | E11: 6332927.9 | F11: 10052.25 | I11: 6322875.7 | J11: 200000 | K11: 0.2 | L11: 1264575.1 | M11: 1464575.1 | N11: 1474627.4 | O11: 4858300.6 | P11: 21000 | Q11: 33000 | R11: 75000 | S11: 95000 | T11: 336000 | U11: 397992.13 | V11: 957992.13 | W11: 12 | X11: 79832.678 | Z11: 79832.678 | AA11: 77198.374 | AB11: 2634.304
A12: 9 | B12: MOSHOOD M. OLALERE | C12: 527744 | D12: 12 | E12: 6332927.9 | F12: 10052.25 | I12: 6322875.7 | J12: 200000 | K12: 0.2 | L12: 1264575.1 | M12: 1464575.1 | N12: 1474627.4 | O12: 4858300.6 | P12: 21000 | Q12: 33000 | R12: 75000 | S12: 95000 | T12: 336000 | U12: 397992.13 | V12: 957992.13 | W12: 12 | X12: 79832.678 | Z12: 79832.678 | AA12: 77198.374 | AB12: 2634.304
A13: 10 | B13: ANDRAWUS MUSA | C13: 447553.5 | D13: 12 | E13: 5370642 | F13: 10052.25 | I13: 5360589.8 | J13: 200000 | K13: 0.2 | L13: 1072118 | M13: 1272118 | N13: 1282170.2 | O13: 4088471.8 | P13: 21000 | Q13: 33000 | R13: 75000 | S13: 95000 | T13: 336000 | U13: 213233.24 | V13: 773233.24 | W13: 12 | X13: 64436.103 | Z13: 64436.103 | AA13: 64436.1 | AB13: 0.0031466667
A14: 11 | B14: AYOBOLU OLAJIDE OLUFUNSHO | C14: 436137.05 | D14: 12 | E14: 5233644.6 | I14: 5233644.6 | J14: 200000 | K14: 0.2 | L14: 1046728.9 | M14: 1246728.9 | N14: 1246728.9 | O14: 3986915.7 | P14: 21000 | Q14: 33000 | R14: 75000 | S14: 95000 | T14: 336000 | U14: 188859.76 | V14: 748859.76 | W14: 12 | X14: 62404.98 | Z14: 62404.98 | AA14: 60212.92 | AB14: 2192.0603
A15: 12 | B15: HUSSEIN EGYE MUSA | C15: 393333.04 | D15: 12 | E15: 4719996.4 | I15: 4719996.4 | J15: 200000 | K15: 0.2 | L15: 943999.28 | M15: 1143999.3 | N15: 1143999.3 | O15: 3575997.1 | P15: 21000 | Q15: 33000 | R15: 75000 | S15: 95000 | T15: 336000 | U15: 90239.313 | V15: 650239.31 | W15: 12 | X15: 54186.609 | Z15: 54186.609 | AA15: 52638.9 | AB15: 1547.7094
A16: 13 | B16: DONALD E. MKPANAM | C16: 343333.04 | D16: 12 | E16: 4119996.4 | F16: 8019.8 | I16: 4111976.6 | J16: 200000 | K16: 0.2 | L16: 822395.32 | M16: 1022395.3 | N16: 1030415.1 | O16: 3089581.3 | P16: 21000 | Q16: 33000 | R16: 75000 | S16: 95000 | T16: 312812.07 | V16: 536812.07 | W16: 12 | X16: 44734.339 | Z16: 44734.339 | AA16: 43380 | AB16: 1354.3394
A17: 14 | B17: JOY HARUNA MAKERI | C17: 563333.04 | D17: 12 | E17: 6759996.4 | I17: 6759996.4 | J17: 200000 | K17: 0.2 | L17: 1351999.3 | M17: 1551999.3 | N17: 1551999.3 | O17: 5207997.1 | P17: 21000 | Q17: 33000 | R17: 75000 | S17: 95000 | T17: 336000 | U17: 481919.31 | V17: 1041919.3 | W17: 12 | X17: 86826.609 | Z17: 86826.609 | AA17: 85278.9 | AB17: 1547.7094
A18: 15 | B18: ALI ABDULLAHI | C18: 338333.04 | D18: 12 | E18: 4059996.4 | I18: 4059996.4 | J18: 200000 | K18: 0.2 | L18: 811999.28 | M18: 1011999.3 | N18: 1011999.3 | O18: 3047997.1 | P18: 21000 | Q18: 33000 | R18: 75000 | S18: 95000 | T18: 304079.4 | V18: 528079.4 | W18: 12 | X18: 44006.617 | Z18: 44006.617 | AA18: 43492.04 | AB18: 514.5769
A19: 16 | B19: PERCY TERFA GBAHABO | C19: 362001.06 | D19: 12 | E19: 4344012.7 | F19: 7422.38 | I19: 4336590.3 | J19: 200000 | K19: 0.2 | L19: 867318.07 | M19: 1067318.1 | N19: 1074740.4 | O19: 3269272.3 | P19: 21000 | Q19: 33000 | R19: 75000 | S19: 95000 | T19: 336000 | V19: 560000 | W19: 12 | X19: 46666.667 | Z19: 46666.667 | AA19: 46673.26 | AB19: -6.5933333
A20: 17 | B20: HASSANA AHMED IBRAHIM | C20: 449201.03 | D20: 12 | E20: 5390412.3 | I20: 5390412.3 | J20: 200000 | K20: 0.2 | L20: 1078082.5 | M20: 1278082.5 | N20: 1278082.5 | O20: 4112329.8 | P20: 21000 | Q20: 33000 | R20: 75000 | S20: 95000 | T20: 336000 | U20: 218959.16 | V20: 778959.16 | W20: 12 | X20: 64913.264 | Z20: 64913.264 | AA20: 63364.81 | AB20: 1548.4537
A21: 18 | B21: CHRISTIAN MADUABUCHI ODO | C21: 284537 | D21: 12 | E21: 3414444 | F21: 6922.5 | I21: 3407521.5 | J21: 200000 | K21: 0.2 | L21: 681504.3 | M21: 881504.3 | N21: 888426.8 | O21: 2526017.2 | P21: 21000 | Q21: 33000 | R21: 75000 | S21: 95000 | T21: 194463.61 | U21: 0 | V21: 418463.61 | W21: 12 | X21: 34871.967 | Z21: 34871.967 | AA21: 31848.56 | AB21: 3023.4074
A22: 19 | B22: ADUGBA RICHARD TERSEER | C22: 267454.07 | D22: 12 | E22: 3209448.9 | F22: 6456.26 | I22: 3202992.6 | J22: 200000 | K22: 0.2 | L22: 640598.53 | M22: 840598.53 | N22: 847054.79 | O22: 2362394.1 | P22: 21000 | Q22: 33000 | R22: 75000 | S22: 95000 | T22: 160102.76 | V22: 384102.76 | W22: 12 | X22: 32008.563 | Z22: 32008.563 | AA22: 31749.189 | AB22: 259.37433
A23: 20 | B23: EGUATU U. ONYEJELEM | C23: 267454.07 | D23: 12 | E23: 3209448.9 | I23: 3209448.9 | J23: 200000 | K23: 0.2 | L23: 641889.78 | M23: 841889.78 | N23: 841889.78 | O23: 2367559.1 | P23: 21000 | Q23: 33000 | R23: 75000 | S23: 95000 | T23: 161187.41 | V23: 385187.41 | W23: 12 | X23: 32098.951 | Z23: 32098.951 | AA23: 31749.189 | AB23: 349.76197
A24: 21 | B24: ODEH SUZIE | C24: 242300.08 | D24: 12 | E24: 2907600.9 | I24: 2907600.9 | J24: 200000 | K24: 0.2 | L24: 581520.19 | M24: 781520.19 | N24: 781520.19 | O24: 2126080.7 | P24: 21000 | Q24: 33000 | R24: 75000 | S24: 95000 | T24: 110476.96 | V24: 334476.96 | W24: 12 | X24: 27873.08 | Z24: 27873.08 | AA24: 27105.99 | AB24: 767.08969
A25: 22 | B25: YAKUB OLUWATOYIN USMAN | C25: 237734.05 | D25: 12 | E25: 2852808.6 | I25: 2852808.6 | J25: 200000 | K25: 0.2 | L25: 570561.71 | M25: 770561.71 | N25: 770561.71 | O25: 2082246.9 | P25: 21000 | Q25: 33000 | R25: 75000 | S25: 95000 | T25: 101271.84 | V25: 325271.84 | W25: 12 | X25: 27105.987 | Z25: 27105.987 | AA25: 26339.08 | AB25: 766.90656
A26: 23 | B26: ELIZABETH OGECHUKWU ONYEAKU | C26: 205204.08 | D26: 12 | E26: 2462449 | I26: 2462449 | J26: 200000 | K26: 0.2 | L26: 492489.8 | M26: 692489.8 | N26: 692489.8 | O26: 1769959.2 | P26: 21000 | Q26: 33000 | R26: 75000 | S26: 95000 | T26: 35691.434 | V26: 259691.43 | W26: 12 | X26: 21640.953 | Z26: 21640.953 | AA26: 21640.95 | AB26: 0.0028626667
A27: 24 | B27: VICTOR ASUKWO | C27: 209356.05 | D27: 12 | E27: 2512272.6 | I27: 2512272.6 | J27: 200000 | K27: 0.2 | L27: 502454.51 | M27: 702454.51 | N27: 702454.51 | O27: 1809818.1 | P27: 21000 | Q27: 33000 | R27: 75000 | S27: 95000 | T27: 44061.791 | V27: 268061.79 | W27: 12 | X27: 22338.483 | Z27: 22338.483 | AA27: 21640.95 | AB27: 697.5326
A28: 25 | B28: IJEOMA NKOLIKWA | C28: 209356.05 | D28: 12 | E28: 2512272.6 | I28: 2512272.6 | J28: 200000 | K28: 0.2 | L28: 502454.51 | M28: 702454.51 | N28: 702454.51 | O28: 1809818.1 | P28: 21000 | Q28: 33000 | R28: 75000 | S28: 95000 | T28: 44061.791 | V28: 268061.79 | W28: 12 | X28: 22338.483 | Z28: 22338.483 | AA28: 21640.95 | AB28: 697.5326
A29: 26 | B29: ABDULRAHMAN A SULAIMAN | C29: 183791.03 | D29: 12 | E29: 2205492.3 | I29: 2205492.3 | J29: 200000 | K29: 0.2 | L29: 441098.46 | M29: 641098.46 | N29: 641098.46 | O29: 1564393.9 | P29: 21000 | Q29: 33000 | R29: 75000 | S29: 88234.833 | T29: 0 | V29: 217234.83 | W29: 12 | X29: 18102.903 | Z29: 18102.903 | AA29: 17572.89 | AB29: 530.01273
A30: 27 | B30: TASSNEEM IBRAHIM | C30: 183791.03 | D30: 12 | E30: 2205492.3 | I30: 2205492.3 | J30: 200000 | K30: 0.2 | L30: 441098.46 | M30: 641098.46 | N30: 641098.46 | O30: 1564393.9 | P30: 21000 | Q30: 33000 | R30: 75000 | S30: 88234.833 | T30: 0 | V30: 217234.83 | W30: 12 | X30: 18102.903 | Z30: 18102.903 | AA30: 17572.89 | AB30: 530.01273
A31: 28 | B31: DARE SHEU MAGBON | C31: 183791.03 | D31: 12 | E31: 2205492.3 | I31: 2205492.3 | J31: 200000 | K31: 0.2 | L31: 441098.46 | M31: 641098.46 | N31: 641098.46 | O31: 1564393.9 | P31: 21000 | Q31: 33000 | R31: 75000 | S31: 88234.833 | T31: 0 | V31: 217234.83 | W31: 12 | X31: 18102.903 | Z31: 18102.903 | AA31: 17572.89 | AB31: 530.01273
A32: 29 | B32: JIMOH ADEBAYO ZAKA | C32: 209356.05 | D32: 12 | E32: 2512272.6 | I32: 2512272.6 | J32: 200000 | K32: 0.2 | L32: 502454.51 | M32: 702454.51 | N32: 702454.51 | O32: 1809818.1 | P32: 21000 | Q32: 33000 | R32: 75000 | S32: 95000 | T32: 44061.791 | V32: 268061.79 | W32: 12 | X32: 22338.483 | Z32: 22338.483 | AA32: 21640.95 | AB32: 697.5326
A33: 30 | B33: MOHAMMED BELLO | C33: 176816.1 | D33: 12 | E33: 2121793.2 | I33: 2121793.2 | J33: 200000 | K33: 0.2 | L33: 424358.64 | M33: 624358.64 | N33: 624358.64 | O33: 1497434.6 | P33: 21000 | Q33: 33000 | R33: 75000 | S33: 75512.566 | T33: 0 | V33: 204512.57 | W33: 12 | X33: 17042.714 | Z33: 17042.714 | AA33: 16512.68 | AB33: 530.03387
A34: 31 | B34: SULEIMAN ABUBAKAR SODEEQ | C34: 176817.1 | D34: 12 | E34: 2121805.2 | I34: 2121805.2 | J34: 200000 | K34: 0.2 | L34: 424361.04 | M34: 624361.04 | N34: 624361.04 | O34: 1497444.2 | P34: 21000 | Q34: 33000 | R34: 75000 | S34: 75514.39 | T34: 0 | V34: 204514.39 | W34: 12 | X34: 17042.866 | Z34: 17042.866 | AA34: 16512.68 | AB34: 530.18587
A35: 32 | B35: HARUNA JIBRIL A. | C35: 176818.1 | D35: 12 | E35: 2121817.2 | I35: 2121817.2 | J35: 200000 | K35: 0.2 | L35: 424363.44 | M35: 624363.44 | N35: 624363.44 | O35: 1497453.8 | P35: 21000 | Q35: 33000 | R35: 75000 | S35: 75516.214 | T35: 0 | V35: 204516.21 | W35: 12 | X35: 17043.018 | Z35: 17043.018 | AA35: 16512.68 | AB35: 530.33787
C36: 12126899 | G36: 0 | Z36: 1716067.7 | AA36: 1681121.5 | AB36: 34946.156
A38: 33 | B38: OSANAIYE DAVID AKINYEMI | C38: 950209.06 | D38: 12 | E38: 11402509 | I38: 11402509 | J38: 200000 | K38: 0.2 | L38: 2280501.8 | M38: 2480501.8 | N38: 2480501.8 | O38: 8922007 | P38: 21000 | Q38: 33000 | R38: 75000 | S38: 95000 | T38: 336000 | U38: 1373281.7 | V38: 1933281.7 | W38: 12 | X38: 161106.81 | Z38: 161106.81 | AA38: 156349.82 | AB38: 4756.9869
A39: 34 | B39: JAMILA ABDUL | C39: 173329.05 | D39: 12 | E39: 2079948.6 | I39: 2079948.6 | J39: 200000 | K39: 0.2 | L39: 415989.72 | M39: 615989.72 | N39: 615989.72 | O39: 1463958.9 | P39: 21000 | Q39: 33000 | R39: 75000 | S39: 69152.186 | T39: 0 | V39: 198152.19 | W39: 12 | X39: 16512.682 | Z39: 16512.682 | AA39: 16512.68 | AB39: 0.0021906667
A42: 35 | B42: PROF. EDOBA BRIGHT OMOREGBE | C42: 1050209.1 | D42: 12 | E42: 12602509 | I42: 12602509 | J42: 200000 | K42: 0.2 | L42: 2520501.8 | M42: 2720501.8 | N42: 2720501.8 | O42: 9882007 | P42: 21000 | Q42: 33000 | R42: 75000 | S42: 95000 | T42: 336000 | U42: 1603681.7 | V42: 2163681.7 | W42: 12 | X42: 180306.81 | Z42: 180306.81 | AA42: 180306.81 | AB42: -0.0031413333
A43: 36 | B43: DR CLINTON JAJA | C43: 527553.5 | D43: 12 | E43: 6330642 | I43: 6330642 | J43: 200000 | K43: 0.2 | L43: 1266128.4 | M43: 1466128.4 | N43: 1466128.4 | O43: 4864513.6 | P43: 21000 | Q43: 33000 | R43: 75000 | S43: 95000 | T43: 336000 | U43: 399483.27 | V43: 959483.27 | W43: 12 | X43: 79956.939 | Z43: 79956.939 | AA43: 79956.94 | AB43: -0.00085333335
A44: 37 | B44: BETHEL UZOMA IHUGBA | C44: 527553.5 | D44: 12 | E44: 6330642 | I44: 6330642 | J44: 200000 | K44: 0.2 | L44: 1266128.4 | M44: 1466128.4 | N44: 1466128.4 | O44: 4864513.6 | P44: 21000 | Q44: 33000 | R44: 75000 | S44: 95000 | T44: 336000 | U44: 399483.27 | V44: 959483.27 | W44: 12 | X44: 79956.939 | Z44: 79956.939 | AA44: 79956.94 | AB44: -0.00085333335
A45: 38 | B45: OGUCHE SAMUEL | C45: 527553.5 | D45: 12 | E45: 6330642 | I45: 6330642 | J45: 200000 | K45: 0.2 | L45: 1266128.4 | M45: 1466128.4 | N45: 1466128.4 | O45: 4864513.6 | P45: 21000 | Q45: 33000 | R45: 75000 | S45: 95000 | T45: 336000 | U45: 399483.27 | V45: 959483.27 | W45: 12 | X45: 79956.939 | Z45: 79956.939 | AA45: 77764.98 | AB45: 2191.9591
A46: 39 | B46: IBRAHIM USMAN | C46: 476014.86 | D46: 12 | E46: 5712178.3 | I46: 5712178.3 | J46: 200000 | K46: 0.2 | L46: 1142435.7 | M46: 1342435.7 | N46: 1342435.7 | O46: 4369742.7 | P46: 21000 | Q46: 33000 | R46: 75000 | S46: 95000 | T46: 336000 | U46: 280738.24 | V46: 840738.24 | W46: 12 | X46: 70061.52 | Z46: 70061.52 | AA46: 75436.115 | AB46: -5374.5955
