Workbook

Sheet JANUARY 2026
A1: NATIONAL INSTITUTE FOR LEGISLATIVE AND DEMOCRATIC STUDIES
A2: STAFF PAYROLL FOR THE MONTH OF JANUARY 2026
E3: ='[1]FEB 08'!E11/'[1]FEB 08'!M11 -> #REF!
B4: STAFF NAME | C4: DESIGNATION | D4: GRADE LEVEL | E4: BASIC SALARY | F4: ALLCE/ AREARS | G4: ALLOWANCE | H4: ALLOWANCE | I4: DUTY ALLCE | J4: GROSS SALARY | K4: AUCTION | L4: COOP 1 CONTR/SPEC SAVINGS | M4: COOP 1 LOAN RECOVERY | N4: COOP 2 CONTR/SPEC SAVINGS | O4: NHF DED. | P4: PAYE | Q4: EMPLOYEE PENSIONS | R4: TOTAL DEDUCTION | S4: DECEMBER, 2025 | T4: JANUARY, 2026
E5: N | F5: N | G5: N | H5: N | I5: N | J5: N | K5: N | L5: N | M5: N | O5: N | P5: N | Q5: N | R5: N | S5: N | T5: N
A6: S/N | B6: DG'S OFFICE
A7: 1 | B7: PROF. ABUBAKAR O. SULAIMAN | C7: DIRECTOR GENERAL | D7: CONSOL | E7: 1971137.1 | G7: =250000 -> 250000 | I7: 25235 | J7: =E7+F7+G7+H7+I7 -> 2246372.1 | O7: 0 | P7: 427498.91 | R7: =P7+O7+M7+N7+L7+K7+Q7 -> 427498.91 | S7: 1836402 | T7: =J7-R7 -> 1818873.2
A8: 2 | B8: RAHEEM USMAN AYIGORO | C8: SA-INFRASTRUCTURE | D8: 16 (9) | E8: 905306.75 | H8: =90000 -> 90000 | I8: =100000 -> 100000 | J8: =E8+F8+G8+H8+I8 -> 1095306.8 | L8: =250000 -> 250000 | N8: 100000 | P8: 167305.26 | Q8: 72424.54 | R8: =P8+O8+M8+N8+L8+K8+Q8 -> 589729.8 | S8: 497822.16 | T8: =J8-R8 -> 505576.95
A9: 3 | B9: MARIAM MOHAMMED BELLO | C9: SA- SPECIAL DUTIES | D9: 16 (9) | E9: 905306.75 | H9: =90000 -> 90000 | I9: =200000+100000 -> 300000 | J9: =E9+F9+G9+H9+I9 -> 1295306.8 | O9: 0 | P9: 224514.42 | R9: =P9+O9+M9+N9+L9+K9+Q9 -> 224514.42 | S9: 1067941.2 | T9: =J9-R9 -> 1070792.3
A10: 4 | B10: DR IKEME ARTHUR J.O | C10: DEPUTY DIRECTOR, M&E | D10: 16 (9) | E10: 905306.75 | G10: 180000 | I10: 0 | J10: =E10+F10+G10+H10+I10 -> 1085306.8 | L10: =50000 -> 50000 | O10: 13866.737 | P10: 162322.79 | Q10: 72424.54 | R10: =P10+O10+M10+N10+L10+K10+Q10 -> 298614.06 | S10: 778537.84 | T10: =J10-R10 -> 786692.69
A11: 5 | B11: ANDRAWUS MUSA | C11: DEP. DIRECTOR, STORES & PROCUREMENT | D11: 16(9) | E11: 905306.75 | H11: =90000 -> 90000 | I11: 50000 | J11: =E11+F11+G11+H11+I11 -> 1045306.8 | L11: =50000-40000 -> 10000 | M11: =90000+110000 -> 200000 | O11: 13866.737 | P11: 155122.79 | Q11: 72424.54 | R11: =P11+O11+M11+N11+L11+K11+Q11 -> 451414.06 | S11: 569000.89 | T11: =J11-R11 -> 593892.69
A12: 6 | B12: DR FRANCIS NDUM OJIE | C12: AD, TRAINING & IC./SA TO DG | D12: 15(9) | E12: 744477 | G12: 160000 | I12: =100000+100000 -> 200000 | J12: =E12+F12+G12+H12+I12 -> 1104477 | O12: 11475.263 | P12: 169523.15 | Q12: 59558.16 | R12: =P12+O12+M12+N12+L12+K12+Q12 -> 240556.57 | S12: 840352.81 | T12: =J12-R12 -> 863920.43
A13: 7 | B13: ALI ABDULLAHI | C13: ASST DIRECTOR ICT | D13: 15(7) | E13: 700713.92 | H13: =80000 -> 80000 | I13: =0 -> 0 | J13: =E13+F13+G13+H13+I13 -> 780713.92 | P13: 112938.22 | Q13: 56057.113 | R13: =P13+O13+M13+N13+L13+K13+Q13 -> 168995.34 | S13: 605150.2 | T13: =J13-R13 -> 611718.58
A14: 8 | B14: EMILY EKHIDE | C14: SENIOR RESEARCH FELLOW | D14: 15(9) | E14: 744477 | G14: 160000 | I14: =50000 -> 50000 | J14: =E14+F14+G14+H14+I14 -> 954477 | L14: =50000 -> 50000 | P14: 143585.39 | Q14: 59558.16 | R14: =P14+O14+M14+N14+L14+K14+Q14 -> 253143.55 | S14: 678161.92 | T14: =J14-R14 -> 701333.45
A15: 9 | B15: DORIS DAKDA AARON | C15: RESEARCH FELLOW I | D15: 14(10) | E15: 573911.08 | G15: =140000 -> 140000 | I15: =150000+100000 -> 250000 | J15: =E15+F15+G15+H15+I15 -> 963911.08 | L15: 150000 | M15: 0 | O15: 8926.6667 | P15: 146132.88 | Q15: 45912.887 | R15: =P15+O15+M15+N15+L15+K15+Q15 -> 350972.43 | S15: 592678.16 | T15: =J15-R15 -> 612938.65
A16: 10 | B16: ABDULSALAM S. MUSTAPHA | C16: ASST. DIRECTOR ICT | D16: 15(8) | E16: 722595.5 | H16: 80000 | I16: 50000 | J16: =E16+F16+G16+H16+I16 -> 852595.5 | N16: 10000 | P16: 125561.81 | Q16: 57807.64 | R16: =P16+O16+M16+N16+L16+K16+Q16 -> 193369.45 | S16: 637256.03 | T16: =J16-R16 -> 659226.05
A17: 11 | B17: PERCY TERFA GBAHABO | C17: RESEARCH FELLOW 1 | D17: 14(8) | E17: 542419.5 | G17: =140000 -> 140000 | I17: 0 | J17: =E17+F17+G17+H17+I17 -> 682419.5 | P17: 97524.669 | Q17: 43393.56 | R17: =P17+O17+M17+N17+L17+K17+Q17 -> 140918.23 | S17: 538909.56 | T17: =J17-R17 -> 541501.27
A18: 12 | B18: HASSANA AHMED IBRAHIM | C18: PA- TO DG | D18: 13(11) | E18: 541351.33 | G18: =120000 -> 120000 | I18: =100000+100000 -> 200000 | J18: =E18+F18+G18+H18+I18 -> 861351.33 | L18: =30000-20000 -> 10000 | M18: =127777.78 -> 127777.78 | O18: 8443.2708 | P18: 128227.99 | Q18: 43308.107 | R18: =P18+O18+M18+N18+L18+K18+Q18 -> 317757.15 | S18: 527015.2 | T18: =J18-R18 -> 543594.18
A19: 13 | B19: IKIP LEBO | C19: ASST CHIEF PROC. OFFICER | D19: 13 (9) | E19: 512098.92 | H19: 70000 | J19: =E19+F19+G19+H19+I19 -> 582098.92 | L19: 50000 | M19: 250000 | O19: 8008.9771 | P19: 78461.965 | Q19: 40967.913 | R19: =P19+O19+M19+N19+L19+K19+Q19 -> 427438.86 | S19: 141398.88 | T19: =J19-R19 -> 154660.06
A20: 14 | B20: ALABI ADESINA MUHYDEEN | C20: HEAD, NILDS LIAISON OFFICE | D20: 13 (9) | E20: 512098.92 | G20: 120000 | J20: =E20+F20+G20+H20+I20 -> 632098.92 | P20: 88903.581 | Q20: 40967.913 | R20: =P20+O20+M20+N20+L20+K20+Q20 -> 129871.49 | S20: 488094.68 | T20: =J20-R20 -> 502227.42
A21: 15 | B21: BASSEY NSONGURUA UDOFIA | C21: PRINC.CONF SEC 1/PPS | D21: 13(8) | E21: 497472.75 | H21: =70000 -> 70000 | I21: =250000 -> 250000 | J21: =E21+F21+G21+H21+I21 -> 817472.75 | L21: 20000 | M21: =68750 -> 68750 | O21: 7791.8313 | P21: 121078.96 | Q21: 39797.82 | R21: =P21+O21+M21+N21+L21+K21+Q21 -> 257418.61 | S21: 540487.46 | T21: =J21-R21 -> 560054.14
A22: 16 | B22: ADUGBA RICHARD TERSEER | C22: ASSIST. CHIEF INFO OFFICER | D22: 13(7) | E22: 482846.58 | H22: =70000 -> 70000 | I22: =100000+50000 -> 150000 | J22: =E22+F22+G22+H22+I22 -> 702846.58 | L22: =10000 -> 10000 | M22: 292813.77 | O22: 7574.6854 | P22: 100695.95 | Q22: 38627.727 | R22: =P22+O22+M22+N22+L22+K22+Q22 -> 449712.13 | S22: 244123.33 | T22: =J22-R22 -> 253134.45
A23: 17 | B23: LUCKY AGWOM | C23: RESEARCH ASSISTANT | D23: 12(9) | E23: 468828.17 | G23: =100000 -> 100000 | I23: =100000+100000 -> 200000 | J23: =E23+F23+G23+H23+I23 -> 768828.17 | L23: =50000+100000 -> 150000 | P23: 114137.94 | Q23: 37506.253 | R23: =P23+O23+M23+N23+L23+K23+Q23 -> 301644.2 | S23: 451957.36 | T23: =J23-R23 -> 467183.97
A24: 18 | B24: IDRIS IBRAHIM | C24: PRINCIPAL RESEARCH OFFICER | D24: 12(9) | E24: 468828.17 | G24: 110000 | I24: 0 | J24: =E24+F24+G24+H24+I24 -> 578828.17 | L24: 0 | N24: 30000 | O24: 7366.5729 | P24: 78611.961 | Q24: 37506.253 | R24: =P24+O24+M24+N24+L24+K24+Q24 -> 153484.79 | S24: 411276.19 | T24: =J24-R24 -> 425343.38
A25: 19 | B25: FARUQ ATOFARATI | C25: PA (SPECIAL DUTIES) TO DG | D25: 10(8) | E25: 381140.67 | H25: =50000+10000 -> 60000 | I25: =100000+100000 -> 200000 | J25: =E25+F25+G25+H25+I25 -> 641140.67 | L25: 150000 | P25: 92416.894 | Q25: 30491.253 | R25: =P25+O25+M25+N25+L25+K25+Q25 -> 272908.15 | S25: 364738.06 | T25: =J25-R25 -> 368232.52
A26: 20 | B26: RASHEEDAT DAIBU | C26: SENIOR INFO. OFFICER | D26: 10(9) | E26: 390135.83 | H26: 60000 | J26: =E26+F26+G26+H26+I26 -> 450135.83 | L26: 50000 | N26: 10000 | O26: 6154.2792 | P26: 56798.724 | Q26: 31210.867 | R26: =P26+O26+M26+N26+L26+K26+Q26 -> 154163.87 | S26: 287116.19 | T26: =J26-R26 -> 295971.96
A27: 21 | B27: VICTOR ASUKWO | C27: SENIOR ICT OFFICER | D27: 10(7) | E27: 372145.33 | F27: 67298.667 | H27: =50000+10000 -> 60000 | J27: =E27+F27+G27+H27+I27 -> 499444 | O27: 5889.4458 | P27: 65980.927 | Q27: 29771.627 | R27: =P27+O27+M27+N27+L27+K27+Q27 -> 101642 | S27: 394160.16 | T27: =J27-R27 -> 397802
A28: 22 | B28: NNANDI LIVINUS ATURE | C28: SENIOR RESEARCH OFFICER | D28: 10(8) | E28: 381140.67 | G28: =110000 -> 110000 | J28: =E28+F28+G28+H28+I28 -> 491140.67 | L28: =10000 -> 10000 | M28: 127777.78 | O28: 6021.8646 | P28: 64332.959 | Q28: 30491.253 | R28: =P28+O28+M28+N28+L28+K28+Q28 -> 238623.86 | S28: 251434.71 | T28: =J28-R28 -> 252516.81
A29: 23 | B29: ABDULRAHMAN A SULAIMAN | C29: STORE OFFICER | D29: 9(10) | E29: 355320.67 | H29: =60000 -> 60000 | J29: =E29+F29+G29+H29+I29 -> 415320.67 | L29: =20000 -> 20000 | M29: =17500 -> 17500 | N29: 50000 | P29: 52141.102 | Q29: 28425.653 | R29: =P29+O29+M29+N29+L29+K29+Q29 -> 168066.76 | S29: 240271.27 | T29: =J29-R29 -> 247253.91
A30: 24 | B30: DARE SHEU MAGBON | C30: ADMINISTRATION OFFICER | D30: 9(9) | E30: 347016.17 | H30: =60000 -> 60000 | J30: =E30+F30+G30+H30+I30 -> 407016.17 | L30: =30000+20000 -> 50000 | M30: 0 | P30: 50765.877 | Q30: 27761.293 | R30: =P30+O30+M30+N30+L30+K30+Q30 -> 128527.17 | S30: 271598.04 | T30: =J30-R30 -> 278489
A31: 25 | B31: ABUBAKAR SULAIMAN SODEEQ | C31: SENIOR M&E OFFICER | D31: 10(7) | E31: 372145.33 | H31: 60000 | J31: =E31+F31+G31+H31+I31 -> 432145.33 | M31: 0 | O31: 5889.4458 | P31: 53867.167 | Q31: 29771.627 | R31: =P31+O31+M31+N31+L31+K31+Q31 -> 89528.239 | S31: 339932.12 | T31: =J31-R31 -> 342617.09
A32: 26 | B32: JIMOH ADEBAYO ZAKA | C32: SENIOR INFO OFFICER | D32: 10(7) | E32: 372145.33 | H32: 60000 | J32: =E32+F32+G32+H32+I32 -> 432145.33 | L32: =20000 -> 20000 | M32: =161429.76+39000+50000 -> 250429.76 | O32: 5889.4458 | P32: 53867.167 | Q32: 29771.627 | R32: =P32+O32+M32+N32+L32+K32+Q32 -> 359958 | S32: 69502.357 | T32: =J32-R32 -> 72187.334
A33: 27 | B33: ABDULMUSHIN TAWFIQ LADAN | C33: ICT OFFICER | D33: 9(9) | E33: 347016.17 | H33: =60000 -> 60000 | J33: =E33+F33+G33+H33+I33 -> 407016.17 | M33: 0 | P33: 50765.877 | Q33: 27761.293 | R33: =P33+O33+M33+N33+L33+K33+Q33 -> 78527.171 | S33: 321853.15 | T33: =J33-R33 -> 328489
A34: 28 | B34: MOHAMMED BELLO | C34: SENIOR PROTOCOL OFFICER | D34: 10(7) | E34: 372145.33 | H34: 60000 | J34: =E34+F34+G34+H34+I34 -> 432145.33 | L34: =0 -> 0 | P34: 54927.267 | Q34: 29771.627 | R34: =P34+O34+M34+N34+L34+K34+Q34 -> 84698.894 | S34: 346192.86 | T34: =J34-R34 -> 347446.44
A35: 29 | B35: HOLINESS PAUL UDO | C35: ADMINISTRATION OFFICER, M&E | D35: 9(8) | E35: 338711.67 | H35: =60000 -> 60000 | J35: =E35+F35+G35+H35+I35 -> 398711.67 | L35: 50000 | O35: 5443.3354 | P35: 48410.852 | Q35: 27096.933 | R35: =P35+O35+M35+N35+L35+K35+Q35 -> 130951.12 | S35: 256765.88 | T35: =J35-R35 -> 267760.55
A36: 30 | B36: CHARITY UDO AKAN | C36: ADMINISTRATION OFFICER, M&E | D36: 9(8) | E36: 338711.67 | H36: =60000 -> 60000 | J36: =E36+F36+G36+H36+I36 -> 398711.67 | L36: 50000 | M36: 60625 | O36: 5443.3354 | P36: 48410.852 | Q36: 27096.933 | R36: =P36+O36+M36+N36+L36+K36+Q36 -> 191576.12 | S36: 199480.69 | T36: =J36-R36 -> 207135.55
A37: 31 | B37: SANI UMAR IBRAHIM | C37: STORE OFFICER | D37: 9(8) | E37: 338711.67 | H37: =60000 -> 60000 | J37: =E37+F37+G37+H37+I37 -> 398711.67 | P37: 49390.652 | Q37: 27096.933 | R37: =P37+O37+M37+N37+L37+K37+Q37 -> 76487.585 | S37: 315426.23 | T37: =J37-R37 -> 322224.08
A38: 32 | B38: FAHAD ABUBUKAR LONGMAN | C38: ICT OFFICER | D38: 9(8) | E38: 338711.67 | H38: =60000 -> 60000 | J38: =E38+F38+G38+H38+I38 -> 398711.67 | O38: 5443.3354 | P38: 48410.852 | Q38: 27096.933 | R38: =P38+O38+M38+N38+L38+K38+Q38 -> 80951.12 | S38: 310106.43 | T38: =J38-R38 -> 317760.55
A39: 33 | B39: HARUNA JIBRIL AMEH | C39: ASST. ADMIN. OFFICER | D39: 8(10) | E39: 308920.67 | H39: 50000 | J39: =E39+F39+G39+H39+I39 -> 358920.67 | L39: 20000 | M39: 0 | O39: 5013.7354 | P39: 41754.79 | Q39: 24713.653 | R39: =P39+O39+M39+N39+L39+K39+Q39 -> 91482.179 | S39: 260618.79 | T39: =J39-R39 -> 267438.49
A40: 34 | B40: RAMATU IBRAHIM ABDULRAHEEM | C40: INFORMATION OFFICER | D40: 8(9) | E40: 301910.75 | H40: 50000 | J40: =E40+F40+G40+H40+I40 -> 351910.75 | L40: 50000 | M40: 45833.33 | N40: 50000 | O40: 4909.1104 | P40: 40612.78 | Q40: 24152.86 | R40: =P40+O40+M40+N40+L40+K40+Q40 -> 215508.08 | S40: 129524.41 | T40: =J40-R40 -> 136402.67
A41: 35 | B41: EDIDIONG EZEKIEL ATAT | C41: ASSIST PROCUREMENT OFFICER | D41: 8(8) | E41: 294900.83 | H41: =50000 -> 50000 | J41: =E41+F41+G41+H41+I41 -> 344900.83 | L41: 10000 | M41: 66666.67 | O41: 4804.4854 | P41: 39470.771 | Q41: 23592.067 | R41: =P41+O41+M41+N41+L41+K41+Q41 -> 144533.99 | S41: 260886.27 | T41: =J41-R41 -> 200366.84
A42: 36 | B42: MAHMUD ADEWOLE HASSAN | C42: ASSIST ICT OFFICER | D42: 8(8) | E42: 294900.83 | H42: =50000 -> 50000 | J42: =E42+F42+G42+H42+I42 -> 344900.83 | N42: 70000 | P42: 40335.578 | Q42: 23592.067 | R42: =P42+O42+M42+N42+L42+K42+Q42 -> 133927.64 | S42: 204796.56 | T42: =J42-R42 -> 210973.19
A43: 37 | B43: YUSUF KABIRU TURAKI | C43: ASSIST ICT OFFICER | D43: 8(8) | E43: 294900.83 | H43: =50000 -> 50000 | J43: =E43+F43+G43+H43+I43 -> 344900.83 | P43: 40335.578 | Q43: 23592.067 | R43: =P43+O43+M43+N43+L43+K43+Q43 -> 63927.645 | S43: 274796.56 | T43: =J43-R43 -> 280973.19
A44: 38 | B44: FATIMA OMAR IBRAHIM | C44: ASSIST PROTOCOL OFFICER | D44: 8(8) | E44: 294900.83 | H44: =50000 -> 50000 | J44: =E44+F44+G44+H44+I44 -> 344900.83 | L44: 20000 | P44: 40335.578 | Q44: 23592.067 | R44: =P44+O44+M44+N44+L44+K44+Q44 -> 83927.645 | S44: 254796.56 | T44: =J44-R44 -> 260973.19
A45: 39 | B45: EBERE ANASTHESIA IGWE | C45: ASSIST ICT OFFICER | D45: 8(8) | E45: 294900.83 | H45: =50000 -> 50000 | J45: =E45+F45+G45+H45+I45 -> 344900.83 | L45: 20000 | M45: 150000 | P45: 40335.578 | Q45: 23592.067 | R45: =P45+O45+M45+N45+L45+K45+Q45 -> 233927.64 | S45: 104796.56 | T45: =J45-R45 -> 110973.19
A46: 40 | B46: ALIYU GARBA LERE | C46: ASSIST INFORMATION OFFICER | D46: 8(8) | E46: 294900.83 | H46: =50000 -> 50000 | J46: =E46+F46+G46+H46+I46 -> 344900.83 | P46: 40335.578 | Q46: 23592.067 | R46: =P46+O46+M46+N46+L46+K46+Q46 -> 63927.645 | S46: 274797.32 | T46: =J46-R46 -> 280973.19
B47: TOTAL | C47: 40 | E47: =SUM(E7:E46) -> 20529918 | F47: =SUM(F7:F46) -> 67298.667 | G47: =SUM(G7:G46) -> 1590000 | H47: =SUM(H7:H46) -> 1820000 | I47: =SUM(I7:I46) -> 2025235 | J47: =E47+F47+G47+H47+I47 -> 26032451 | K47: =SUM(K7:K46) -> 0 | L47: =SUM(L7:L46) -> 1270000 | M47: =SUM(M7:M46) -> 1658174.1 | N47: =SUM(N7:N46) -> 320000 | O47: =SUM(O7:O46) -> 148222.56 | P47: =SUM(P7:P46) -> 3756152 | Q47: =SUM(Q7:Q46) -> 1412277.9 | R47: =SUM(R7:R46) -> 8564826.6 | S47: 17180157 | T47: =SUM(T7:T46) -> 17467625
J48: =E48+F48+G48+H48+I48 -> 0
B49: INTERNAL AUDIT | J49: =E49+F49+G49+H49+I49 -> 0
A50: 1 | B50: OSANAIYE DAVID AKINYEMI | C50: DIRECTOR INTERNAL AUDIT | D50: 17(9) | E50: 1747106.4 | H50: =100000 -> 100000 | J50: =E50+F50+G50+H50+I50 -> 1847106.4 | K50: ='JANUARY 2026'!F251 -> 0 | L50: =300000 -> 300000 | M50: =458333.33 -> 458333.33 | P50: 311040.96 | Q50: 139768.51 | R50: =P50+O50+M50+N50+L50+K50+Q50 -> 1209142.8 | S50: 642529.03 | T50: =J50-R50 -> 637963.61
A51: 2 | B51: EVELYN ETONKE AGAN | C51: ASST DIR AUDIT | D51: 15(8) | E51: 722595.5 | H51: =80000 -> 80000 | I51: 0 | J51: =E51+F51+G51+H51+I51 -> 802595.5 | L51: 50000 | P51: 116561.81 | Q51: 57807.64 | R51: =P51+O51+M51+N51+L51+K51+Q51 -> 224369.45 | S51: 556856.03 | T51: =J51-R51 -> 578226.05
A52: 3 | B52: JAMILA ABDUL | C52: SENIOR INTERNAL AUDITOR | D52: 10(9) | E52: 390135.83 | H52: =60000 -> 60000 | J52: =E52+F52+G52+H52+I52 -> 450135.83 | L52: =20000 -> 20000 | M52: 73333.33 | N52: 20000 | O52: 6154.2792 | P52: 56798.724 | Q52: 31210.867 | R52: =P52+O52+M52+N52+L52+K52+Q52 -> 207497.2 | S52: 233782.86 | T52: =J52-R52 -> 242638.63
A53: 4 | B53: IJEOMA EWELUKWA | C53: PRINCIPAL AUDIT OFFICER | D53: 12(8) | E53: 454993.58 | H53: =60000 -> 60000 | J53: =E53+F53+G53+H53+I53 -> 514993.58 | L53: =10000 -> 10000 | P53: 68646.937 | Q53: 36399.487 | R53: =P53+O53+M53+N53+L53+K53+Q53 -> 115046.42 | S53: 389088.8 | T53: =J53-R53 -> 399947.16
A54: 5 | B54: HASSAN ABDULHADI | C54: SENIOR INTERNAL AUDITOR | D54: 9(8) | E54: 338711.67 | H54: 60000 | J54: =E54+F54+G54+H54+I54 -> 398711.67 | L54: =100000 -> 100000 | O54: 5443.3354 | P54: 48410.852 | Q54: 27096.933 | R54: =P54+O54+M54+N54+L54+K54+Q54 -> 180951.12 | S54: 210104.94 | T54: =J54-R54 -> 217760.55
A55: 6 | B55: YUSUF YUSUF DAYYABU | C55: INERNAL AUDIT OFFICER | D55: 9(9) | E55: 347016.17 | H55: 60000 | J55: =E55+F55+G55+H55+I55 -> 407016.17 | L55: 20000 | M55: 98878.69 | O55: 5566.8646 | P55: 49763.842 | Q55: 27761.293 | R55: =P55+O55+M55+N55+L55+K55+Q55 -> 201970.69 | S55: 197276.01 | T55: =J55-R55 -> 205045.48
A56: 7 | B56: UDONSI QUEENETH CHIWENDU | C56: ASSIST PROGRAMME OFFICER | D56: 8(8) | E56: 294900.83 | H56: 50000 | J56: =E56+F56+G56+H56+I56 -> 344900.83 | L56: 102000 | P56: 40335.578 | Q56: 23592.067 | R56: =P56+O56+M56+N56+L56+K56+Q56 -> 165927.64 | S56: 274796.56 | T56: =J56-R56 -> 178973.19
C57: 7 | E57: =SUM(E50:E56) -> 4295460 | F57: =SUM(F50:F56) -> 0 | G57: =SUM(G50:G56) -> 0 | H57: =SUM(H50:H56) -> 470000 | I57: =SUM(I50:I56) -> 0 | J57: =E57+F57+G57+H57+I57 -> 4765460 | K57: =SUM(K50:K56) -> 0 | L57: =SUM(L50:L56) -> 602000 | M57: =SUM(M50:M56) -> 630545.35 | N57: =SUM(N50:N56) -> 20000 | O57: =SUM(O50:O56) -> 17164.479 | P57: =SUM(P50:P56) -> 691558.71 | Q57: =SUM(Q50:Q56) -> 343636.8 | R57: =SUM(R50:R56) -> 2304905.3 | S57: 2504434.2 | T57: =SUM(T50:T56) -> 2460554.7
J58: =E58+F58+G58+H58+I58 -> 0
B59: LEG. SUPPORT SEVICES | J59: =E59+F59+G59+H59+I59 -> 0
A60: 1 | B60: BETHEL UZOMA IHUGBA | C60: AG. DIRECTOR, AEEP | D60: 17(8) | E60: 1697359.3 | G60: =200000 -> 200000 | J60: =E60+F60+G60+H60+I60 -> 1897359.3 | L60: =80000+23000+300000 -> 403000 | M60: =246905.96 -> 246905.96 | N60: 150000 | P60: 322429.82 | Q60: 135788.75 | R60: =P60+O60+M60+N60+L60+K60+Q60 -> 1258124.5 | S60: 596394.42 | T60: =J60-R60 -> 639234.8
A61: 2 | B61: OGUCHE SAMUEL | C61: SNR RESEARCH FELLOW | D61: 15(9) | E61: 744477 | G61: =160000 -> 160000 | J61: =E61+F61+G61+H61+I61 -> 904477 | L61: =30000 -> 30000 | M61: 223059.88 | P61: 134585.39 | Q61: 59558.16 | R61: =P61+O61+M61+N61+L61+K61+Q61 -> 447203.43 | S61: 450967.88 | T61: =J61-R61 -> 457273.57
A62: 3 | B62: IBRAHIM USMAN | C62: SNR RESEARCH FELLOW | D62: 15(9) | E62: 744477 | G62: =140000+20000 -> 160000 | I62: 0 | J62: =E62+F62+G62+H62+I62 -> 904477 | N62: 50000 | O62: 11475.263 | P62: 132519.84 | Q62: 59558.16 | R62: =P62+O62+M62+N62+L62+K62+Q62 -> 253553.27 | S62: 644755.74 | T62: =J62-R62 -> 650923.73
A63: 4 | B63: DR MOHAMMED O. AMALI | C63: SNR RESEARCH FELLOW | D63: 15(9) | E63: 744477 | G63: =140000+20000 -> 160000 | J63: =E63+F63+G63+H63+I63 -> 904477 | L63: =15000 -> 15000 | M63: 198731.33 | P63: 134585.39 | Q63: 59558.16 | R63: =P63+O63+M63+N63+L63+K63+Q63 -> 407874.88 | S63: 474030.59 | T63: =J63-R63 -> 496602.12
A64: 5 | B64: YAHAYA SHAMSU | C64: SNR RESEARCH FELLOW | D64: 15(8) | E64: 722595.5 | G64: =160000 -> 160000 | J64: =E64+F64+G64+H64+I64 -> 882595.5 | N64: 20000 | O64: 0 | P64: 130961.81 | Q64: 57807.64 | R64: =P64+O64+M64+N64+L64+K64+Q64 -> 208769.45 | S64: 651496.03 | T64: =J64-R64 -> 673826.05
A65: 6 | B65: CHIDEBE MATHEW NWANKWO | C65: SNR RESEARCH FELLOW | D65: 15(8) | E65: 722595.5 | G65: =160000 -> 160000 | J65: =E65+F65+G65+H65+I65 -> 882595.5 | L65: 102000 | O65: 0 | P65: 130961.81 | Q65: 57807.64 | R65: =P65+O65+M65+N65+L65+K65+Q65 -> 290769.45 | S65: 671496.03 | T65: =J65-R65 -> 591826.05
A66: 7 | B66: UMAR MUSA PADAH | C66: PRINC. RESEARCH OFFICER | D66: 12(8) | E66: 454993.58 | G66: =110000 -> 110000 | J66: =E66+F66+G66+H66+I66 -> 564993.58 | N66: 20000 | P66: 77646.937 | Q66: 36399.487 | R66: =P66+O66+M66+N66+L66+K66+Q66 -> 134046.42 | S66: 418153.29 | T66: =J66-R66 -> 430947.16
A67: 8 | B67: BILKIS S. LAWAL-GAMBARI | C67: RESEARCH OFFICER | D67: 10(10) | E67: 399131.17 | G67: 100000 | J67: =E67+F67+G67+H67+I67 -> 499131.17 | P67: 66596.121 | Q67: 31930.493 | R67: =P67+O67+M67+N67+L67+K67+Q67 -> 98526.615 | S67: 392144.71 | T67: =J67-R67 -> 400604.55
A68: 9 | B68: UMOH USENOBONG EMMANUEL | C68: SENIOR RESEARCH OFFICER | D68: 10(8) | E68: 381140.67 | G68: =100000 -> 100000 | J68: =E68+F68+G68+H68+I68 -> 481140.67 | P68: 63616.894 | Q68: 30491.253 | R68: =P68+O68+M68+N68+L68+K68+Q68 -> 94108.148 | S68: 378771.29 | T68: =J68-R68 -> 387032.52
A69: 10 | B69: ZAINAB AKINDE | C69: RESEARCH OFFICER | D69: 9(10) | E69: 355320.67 | G69: =100000 -> 100000 | J69: =E69+F69+G69+H69+I69 -> 455320.67 | P69: 59341.102 | Q69: 28425.653 | R69: =P69+O69+M69+N69+L69+K69+Q69 -> 87766.756 | S69: 360091.27 | T69: =J69-R69 -> 367553.91
A70: 11 | B70: GUNAT NANSAK MARK | C70: RESEARCH OFFICER | D70: 9(10) | E70: 355320.67 | G70: =100000 -> 100000 | J70: =E70+F70+G70+H70+I70 -> 455320.67 | P70: 59341.102 | Q70: 28425.653 | R70: =P70+O70+M70+N70+L70+K70+Q70 -> 87766.756 | S70: 360091.27 | T70: =J70-R70 -> 367553.91
A71: 12 | B71: MANDU ESSIEN NDEM | C71: RESEARCH OFFICER | D71: 9(8) | E71: 338711.67 | G71: =100000 -> 100000 | J71: =E71+F71+G71+H71+I71 -> 438711.67 | P71: 56590.652 | Q71: 27096.933 | R71: =P71+O71+M71+N71+L71+K71+Q71 -> 83687.585 | S71: 333825.44 | T71: =J71-R71 -> 355024.08
B72: TOTAL | C72: 12 | E72: =SUM(E60:E71) -> 7660599.8 | F72: =SUM(F60:F71) -> 0 | G72: =SUM(G60:G71) -> 1610000 | H72: =SUM(H60:H71) -> 0 | I72: =SUM(I60:I71) -> 0 | J72: =E72+F72+G72+H72+I72 -> 9270599.8 | K72: =SUM(K60:K71) -> 0 | L72: =SUM(L60:L71) -> 550000 | M72: =SUM(M60:M71) -> 668697.17 | N72: =SUM(N60:N71) -> 240000 | O72: =SUM(O60:O71) -> 11475.263 | P72: =SUM(P60:P71) -> 1369176.9 | Q72: =SUM(Q60:Q71) -> 612847.98 | R72: =SUM(R60:R71) -> 3452197.3 | S72: 5732218 | T72: =SUM(T60:T71) -> 5818402.4
J73: =E73+F73+G73+H73+I73 -> 0
B74: LEGAL SERVICES | J74: =E74+F74+G74+H74+I74 -> 0
A75: 1 | B75: DR SHUAIBU DANWANKA | C75: DIRECTOR LEGAL SERVICES | D75: 17(9) | E75: 1747106.4 | G75: =200000 -> 200000 | I75: 0 | J75: =E75+F75+G75+H75+I75 -> 1947106.4 | L75: 250000 | N75: 500000 | O75: 0 | P75: 332040.96 | Q75: 139768.51 | R75: =P75+O75+M75+N75+L75+K75+Q75 -> 1221809.5 | S75: 731662.36 | T75: =J75-R75 -> 725296.94
A76: 2 | B76: ABDULSALAM BAKO | C76: MANAGER, LEGAL SERVICES | D76: 15 (9) | E76: 744477 | H76: 80000 | J76: =E76+F76+G76+H76+I76 -> 824477 | L76: 50000 | M76: 345000 | O76: 0 | P76: 120185.39 | Q76: 59558.16 | R76: =P76+O76+M76+N76+L76+K76+Q76 -> 574743.55 | S76: 244387.76 | T76: =J76-R76 -> 249733.45
B77: TOTAL | C77: 2 | E77: =SUM(E75:E76) -> 2491583.4 | F77: =SUM(F75:F76) -> 0 | G77: =SUM(G75:G76) -> 200000 | H77: =SUM(H75:H76) -> 80000 | I77: =SUM(I75:I76) -> 0 | J77: =E77+F77+G77+H77+I77 -> 2771583.4 | K77: =SUM(K75:K76) -> 0 | L77: =SUM(L75:L76) -> 300000 | M77: =SUM(M75:M76) -> 345000 | N77: =SUM(N75:N76) -> 500000 | O77: =SUM(O75:O76) -> 0 | P77: =SUM(P75:P76) -> 452226.35 | Q77: =SUM(Q75:Q76) -> 199326.67 | R77: =SUM(R75:R76) -> 1796553 | S77: 976050.12 | T77: =SUM(T75:T76) -> 975030.39
J78: =E78+F78+G78+H78+I78 -> 0
B79: DEMOCRACY & GOVERNANCE | J79: =E79+F79+G79+H79+I79 -> 0
A80: 1 | B80: NGARA CHRISTOPHER OCHANJA | C80: DEP DIR DEM & GOVERNANCE | D80: 16(9) | E80: 905306.75 | G80: 180000 | I80: 0 | J80: =E80+F80+G80+H80+I80 -> 1085306.8 | L80: =100000 -> 100000 | M80: =163103.59 -> 163103.59 | O80: 13866.737 | P80: 162322.79 | Q80: 72424.54 | R80: =P80+O80+M80+N80+L80+K80+Q80 -> 511717.65 | S80: 565434.25 | T80: =J80-R80 -> 573589.1
A81: 2 | B81: EJALONIBU GANIYU LAYI | C81: RESEARCH FELLOW 1 | D81: 14(10) | E81: 573911.08 | G81: 140000 | J81: =E81+F81+G81+H81+I81 -> 713911.08 | L81: =110000+90000 -> 200000 | N81: 80000 | P81: 102739.68 | Q81: 45912.887 | R81: =P81+O81+M81+N81+L81+K81+Q81 -> 428652.56 | S81: 269371.05 | T81: =J81-R81 -> 285258.52
A82: 3 | B82: MARTINS SOLOMON UDOM | C82: RESEARCH FELLOW 11 | D82: 13(8) | E82: 497472.75 | G82: =120000 -> 120000 | I82: 0 | J82: =E82+F82+G82+H82+I82 -> 617472.75 | L82: 30000 | M82: 15000 | O82: 7791.8313 | P82: 85078.958 | Q82: 39797.82 | R82: =P82+O82+M82+N82+L82+K82+Q82 -> 177668.61 | S82: 424647.48 | T82: =J82-R82 -> 439804.14
A83: 4 | B83: ISHAKA DELE | C83: RESEARCH FELLOW 11 | D83: 13(8) | E83: 497472.75 | G83: =120000 -> 120000 | I83: 0 | J83: =E83+F83+G83+H83+I83 -> 617472.75 | L83: 100000 | N83: 52000 | O83: 7791.8313 | P83: 85078.958 | Q83: 39797.82 | R83: =P83+O83+M83+N83+L83+K83+Q83 -> 284668.61 | S83: 369647.48 | T83: =J83-R83 -> 332804.14
A84: 5 | B84: UDEFUNA NNADOZIE PATRICK | C84: RESEARCH OFFICER | D84: 12(10) | E84: 482662.67 | G84: =110000 -> 110000 | I84: 0 | J84: =E84+F84+G84+H84+I84 -> 592662.67 | L84: 10000 | M84: =163196.67 -> 163196.67 | O84: 7571.9667 | P84: 80865.984 | Q84: 38613.013 | R84: =P84+O84+M84+N84+L84+K84+Q84 -> 300247.63 | S84: 278158.2 | T84: =J84-R84 -> 292415.03
A85: 6 | B85: SHAFIU YAHYA MIKAIL | C85: PRINCIPAL RESEARCH OFFICER | D85: 12(10) | E85: 482662.67 | G85: =110000 -> 110000 | I85: 0 | J85: =E85+F85+G85+H85+I85 -> 592662.67 | N85: 50000 | P85: 82228.938 | Q85: 38613.013 | R85: =P85+O85+M85+N85+L85+K85+Q85 -> 170841.95 | S85: 408721.44 | T85: =J85-R85 -> 421820.72
A86: 7 | B86: HASSAN YERIMA | C86: PRINCIPAL RESEARCH OFFICER | D86: 12(10) | E86: 482662.67 | G86: =110000 -> 110000 | I86: 0 | J86: =E86+F86+G86+H86+I86 -> 592662.67 | L86: =67000-2000 -> 65000 | N86: 40000 | P86: 82228.938 | Q86: 38613.013 | R86: =P86+O86+M86+N86+L86+K86+Q86 -> 225841.95 | S86: 353721.44 | T86: =J86-R86 -> 366820.72
A87: 8 | B87: HAUWA PATE SADIQ | C87: ASST CHIEF PROGRAMME OFFICER | D87: 13(7) | E87: 482846.58 | G87: =120000 -> 120000 | J87: =E87+F87+G87+H87+I87 -> 602846.58 | L87: =80000+20000 -> 100000 | N87: =40000 -> 40000 | P87: 84059.394 | Q87: 38627.727 | R87: =P87+O87+M87+N87+L87+K87+Q87 -> 262687.12 | S87: 337222.17 | T87: =J87-R87 -> 340159.46
A88: 9 | B88: OBOT ETIMBUK EMMANUEL | C88: PRINCIPAL INFO. OFFICER | D88: 12(8) | E88: 454993.58 | G88: 110000 | J88: =E88+F88+G88+H88+I88 -> 564993.58 | L88: 20000 | M88: 50000 | O88: 7161.1771 | P88: 76357.926 | Q88: 36399.487 | R88: =P88+O88+M88+N88+L88+K88+Q88 -> 189918.59 | S88: 361197.51 | T88: =J88-R88 -> 375074.99
A89: 10 | B89: KOLAPO Q. ABAYOMI | C89: RESEARCH OFFICER | D89: 10(10) | E89: 399131.17 | G89: 100000 | J89: =E89+F89+G89+H89+I89 -> 499131.17 | N89: 30000 | O89: 6286.6979 | P89: 65464.516 | Q89: 31930.493 | R89: =P89+O89+M89+N89+L89+K89+Q89 -> 133681.71 | S89: 357172.05 | T89: =J89-R89 -> 365449.46
A90: 11 | B90: SALIHU SHAMSUDEEN OPEYEMI | C90: PROGRAMME OFFICER | D90: 9(8) | E90: 338711.67 | G90: =100000 -> 100000 | J90: =E90+F90+G90+H90+I90 -> 438711.67 | N90: 52000 | P90: 56590.652 | Q90: 27096.933 | R90: =P90+O90+M90+N90+L90+K90+Q90 -> 135687.59 | S90: 347744.74 | T90: =J90-R90 -> 303024.08
B91: TOTAL | C91: 11 | E91: =SUM(E80:E90) -> 5597834.3 | F91: =SUM(F80:F90) -> 0 | G91: =SUM(G80:G90) -> 1320000 | H91: =SUM(H80:H90) -> 0 | I91: =SUM(I80:I90) -> 0 | J91: =E91+F91+G91+H91+I91 -> 6917834.3 | K91: =SUM(K80:K90) -> 0 | L91: =SUM(L80:L90) -> 625000 | M91: =SUM(M80:M90) -> 391300.26 | N91: =SUM(N80:N90) -> 344000 | O91: =SUM(O80:O90) -> 50470.242 | P91: =SUM(P80:P90) -> 963016.72 | Q91: =SUM(Q80:Q90) -> 447826.75 | R91: =SUM(R80:R90) -> 2821614 | S91: 4073037.8 | T91: =SUM(T80:T90) -> 4096220.4
J92: =E92+F92+G92+H92+I92 -> 0
B93: DEPARTMENT OF STUDIES | J93: =E93+F93+G93+H93+I93 -> 0
A94: 1 | B94: DR ASIMIYU G. ABIOLA | C94: DIRECTOR POST GRADUATE | D94: 17(9) | E94: 1747106.4 | G94: =200000 -> 200000 | I94: 0 | J94: =E94+F94+G94+H94+I94 -> 1947106.4 | L94: 350000 | M94: =0 -> 0 | N94: 100000 | P94: 332040.96 | Q94: 139768.51 | R94: =P94+O94+M94+N94+L94+K94+Q94 -> 921809.47 | S94: 1031662.4 | T94: =J94-R94 -> 1025296.9
A95: 2 | B95: AYOBOLU OLAJIDE OLUFUNSHO | C95: ASSISTANT DIR. EXXAMS & RECORD | D95: 15(8) | E95: 722595.5 | G95: 160000 | J95: =E95+F95+G95+H95+I95 -> 882595.5 | L95: =50000 -> 50000 | M95: =144081 -> 144081 | P95: 130961.81 | Q95: 57807.64 | R95: =P95+O95+M95+N95+L95+K95+Q95 -> 382850.45 | S95: 493680.92 | T95: =J95-R95 -> 499745.05
A96: 3 | B96: DR. HADIZA SAIDU | C96: ASSISTANT DIRECTOR | D96: 15(8) | E96: 722595.5 | G96: 160000 | J96: =E96+F96+G96+H96+I96 -> 882595.5 | P96: 130961.81 | Q96: 57807.64 | R96: =P96+O96+M96+N96+L96+K96+Q96 -> 188769.45 | S96: 687761.92 | T96: =J96-R96 -> 693826.05
A97: 4 | B97: ANTHONY EDET | C97: CHIEF PROGRAMMES OFFICER | D97: 14(11) | E97: 589657 | G97: =140000 -> 140000 | I97: 0 | J97: =E97+F97+G97+H97+I97 -> 729657 | L97: 20000 | M97: 210785.51 | O97: 9160.4375 | P97: 103698.32 | Q97: 47172.56 | R97: =P97+O97+M97+N97+L97+K97+Q97 -> 390816.83 | S97: 323077.62 | T97: =J97-R97 -> 338840.17
A98: 5 | B98: CHRISTIAN MADUABUCHI ODO | C98: ASSIST. CHIEF ICT OFFICER | D98: 13(8) | E98: 497472.75 | G98: 120000 | J98: =E98+F98+G98+H98+I98 -> 617472.75 | O98: 7791.8313 | P98: 85078.958 | Q98: 39797.82 | R98: =P98+O98+M98+N98+L98+K98+Q98 -> 132668.61 | S98: 469647.48 | T98: =J98-R98 -> 484804.14
A99: 6 | B99: DR. IBANGA ISSAC JONAH | C99: ASSIST. CHIEF PROGRM OFFICER | D99: 13(8) | E99: 497472.75 | G99: =120000 -> 120000 | I99: 0 | J99: =E99+F99+G99+H99+I99 -> 617472.75 | L99: 100000 | M99: 50000 | N99: 100000 | P99: 86481.487 | Q99: 39797.82 | R99: =P99+O99+M99+N99+L99+K99+Q99 -> 376279.31 | S99: 227222.17 | T99: =J99-R99 -> 241193.44
A100: 7 | B100: IGWE STACY | C100: PRINC. PROGRAMME OFFICER | D100: 12(9) | E100: 468828.17 | G100: =110000 -> 110000 | J100: =E100+F100+G100+H100+I100 -> 578828.17 | L100: =50000 -> 50000 | M100: =50000 -> 50000 | O100: 7366.5729 | P100: 78611.961 | Q100: 37506.253 | R100: =P100+O100+M100+N100+L100+K100+Q100 -> 223484.79 | S100: 341276.19 | T100: =J100-R100 -> 355343.38
...

Sheet MEMO
A2: NATIONAL INSTITUTE FOR LEGISLATIVE AND DEMOCRATIC STUDIES
A3: INTERNAL MEMO
A4: FROM : DEPUTY DIRECTOR, FINANCE AND ACCOUNTS
A5: THRU: DIRECTOR, FINANCE AND ACCOUNTS
A6: TO: DG
A7: 29TH JANUARY , 2021
A9: SUBJECT: PAYROLL FOR THE MONTH OF JANUARY, 2021
A10: Find below the details of NILDS Staff Payroll for the month of January, 2021
A13: TO: | C13: DIRECTOR, GENERAL
A14: THRU: | C14: DIRECTOR, FINANCE AND ACCOUNT
A15: FROM: | C15: DEPUTY DIRECTOR, FINANCE AND ACCOUNTS
A16: DATE: | C16: 26TH JANUARY 2026
A18: SUBJECT: PAYROLL FOR THE MONTH OF JANUARY 2026
A19: Find below the details of NILDS Staff Payroll for the Month of January 2026: | G19: NGN | H19: NGN
A20: GROSS SALARY FOR JANUARY 2026 | H20: ='JANUARY 2026'!J249 -> 1.2122022e+08
A22: DEDUCTIONS
A23: COOP SOCIETY 1 DEDUCTIONS ( CONTR.& SPEC. SAVINGS) | G23: ='JANUARY 2026'!L249 -> 8086500
A24: COOP 1 LOAN RECOVERY | G24: ='JANUARY 2026'!M249 -> 10235600
A25: COOP SOCIETY 2 DEDUCTIONS ( CONTR.& SPEC. SAVINGS) | G25: ='JANUARY 2026'!N249 -> 2975000
A26: NHF DEDUCTIONS | G26: ='JANUARY 2026'!O249 -> 677813.77
A27: PAYE DEDUCTIONS | G27: ='JANUARY 2026'!P249 -> 17007534
A28: PENSION DEDUCTIONS | G28: ='JANUARY 2026'!Q249 -> 7849660.5
A29: TOTAL DEDUCTIONS FOR JANUARY 2026 | H29: =G23+G24+G25+G27+G26+G28 -> 46832109
A30: NET PAY AS PER JANUARY 2026 PAYROLL | H30: =H20-H29 -> 74388110
A31: NET PAY AS PER DECEMBER 2025 PAYROLL | H31: ='JANUARY 2026'!S249 -> 73541205
A32: NET INCREASE/ (DECREASE) IN PAY FOR JANUARY 2026 | H32: =H30-H31 -> 846905.16
A33: ANALYSED AS FOLLOWS:
A34: Effect of Cooperative 1 Adjustments for January 2026 | H34: 485541.67
A35: Effect of Cooperative 2 Adjustments for January 2026 | H35: =190000-50000 -> 140000
A36: Effect of Annual Steps increase within Grade Levels | H36: -2102396.8
A37: Effect of Changes in Pensions due to changes in steps | H37: 126177.23
A38: Effect of Changes in NHF due to changes in steps | H38: =13714.8 -> 13714.8
A39: Effect of Changes in PAYE Tax due to the Implementation of New Tax Laws | H39: -205647.52
A40: Effect of the Stoppage of payment to Muhammed Osolafia due to voluntary retirement | H40: =578828.16 -> 578828.16
A41: Effect of regularisation of deductions of Bakari Husseini & 1 other | H41: =52361.12 -> 52361.12
A42: Effect of removal of arrears of change of cadre from Ene Vincent-Orugbo | H42: =64516.13 -> 64516.13
H43: =SUM(H34:H42) -> -846905.16
E46: DECEMBER, 2025 | G46: JANUARY, 2026
E47: No. of Staff | F47: N | G47: No. of Staff | H47: N
A48: 1 | B48: Director General's Office | E48: 32 | F48: ='JANUARY 2026'!S47 -> 17180157 | G48: ='JANUARY 2026'!C47 -> 40 | H48: ='JANUARY 2026'!T47 -> 17467625
A49: 2 | B49: Internal Audit | E49: 3 | F49: ='JANUARY 2026'!S57 -> 2504434.2 | G49: ='JANUARY 2026'!C57 -> 7 | H49: ='JANUARY 2026'!T57 -> 2460554.7
A50: 3 | B50: Legis. Support Services | E50: 11 | F50: ='JANUARY 2026'!S72 -> 5732218 | G50: ='JANUARY 2026'!C72 -> 12 | H50: ='JANUARY 2026'!T72 -> 5818402.4
A51: 4 | B51: Legal Services | E51: 2 | F51: ='JANUARY 2026'!S77 -> 976050.12 | G51: ='JANUARY 2026'!C77 -> 2 | H51: ='JANUARY 2026'!T77 -> 975030.39
A52: 5 | B52: Democracy and Governance | E52: 12 | F52: ='JANUARY 2026'!S91 -> 4073037.8 | G52: ='JANUARY 2026'!C91 -> 11 | H52: ='JANUARY 2026'!T91 -> 4096220.4
A53: 6 | B53: Studies | E53: 6 | F53: ='JANUARY 2026'!S105 -> 4731930.8 | G53: ='JANUARY 2026'!C105 -> 11 | H53: ='JANUARY 2026'!T105 -> 4820379.7
A54: 7 | B54: Economic Dev. & Social Research | E54: 11 | F54: ='JANUARY 2026'!S121 -> 6781166.1 | G54: ='JANUARY 2026'!C121 -> 13 | H54: ='JANUARY 2026'!T121 -> 6975906.1
A55: 8 | B55: Training & Int'l Cooperation | E55: 4 | F55: ='JANUARY 2026'!S131 -> 2735722.7 | G55: ='JANUARY 2026'!C131 -> 7 | H55: ='JANUARY 2026'!T131 -> 2840181.7
A56: 9 | B56: Library & Documentation | E56: 7 | F56: ='JANUARY 2026'!S145 -> 5419159.5 | G56: ='JANUARY 2026'!C145 -> 11 | H56: ='JANUARY 2026'!T145 -> 5383305.1
A57: 10 | B57: Leg. Center for Security Analysis | E57: 2 | F57: ='JANUARY 2026'!S156 -> 2938155.4 | G57: ='JANUARY 2026'!C156 -> 8 | H57: ='JANUARY 2026'!T156 -> 2555346.3
A58: 11 | B58: Democracy Radio 104.9 | E58: 3 | F58: ='JANUARY 2026'!S164 -> 1436265.7 | G58: 5 | H58: ='JANUARY 2026'!T164 -> 1514087.9
A59: 12 | B59: Finance and Accounts | E59: 10 | F59: ='JANUARY 2026'!S179 -> 4349210.7 | G59: ='JANUARY 2026'!C179 -> 12 | H59: ='JANUARY 2026'!T179 -> 4463908.9
A60: 13 | B60: Admin & Human Resource | E60: 61 | F60: ='JANUARY 2026'!S248 -> 14683697 | G60: ='JANUARY 2026'!C248 -> 66 | H60: ='JANUARY 2026'!T248 -> 15017162
E61: =SUM(E48:E60) -> 164 | F61: =SUM(F48:F60) -> 73541205 | G61: 199 | H61: =SUM(H48:H60) -> 74388110
A63: The Director General is requested to consider and approve the payment of N74,388,110.10, to Guaranty Trust Bank, being the January 2026 Net Salary, N18,322,100.38, and N2,975,000 being NILDS Coop Society 1 and Coop Society 2 deductions for January 2026. N17,007,533.92 PAYE Tax Deductions from Staff Salary for the month of January 2026 and N677,813.77 being NHF deductions from staff for January 2026
A67: RAHILA NURUDEEN HABU
C171: =10000 -> 10000

Sheet Changes in PAYE (4)
A1: NATIONAL INSTITUTE FOR LEGISLATIVE AND DEMOCRATIC STUDIES
A2: NATIONAL ASSEMBLY ABUJA
A3: TAX COMPUTATION FOR 2022
A4: S/NO | B4: NAME | C4: N | D4: NO OF MONTHS | E4: ANNUAL SALARY GROSSED UP | F4: ANNUAL RENT RELIEF (20% MAX OF N500,000) | G4: NATIONAL HOUSING SCHEME = 2.5% OF BASIC SALARY | H4: PENSION CONTRIBUTION = 8% OF CONSOLIDATED | I4: NHIS | J4: TOTAL RELIEF | K4: CHARGEABLE INCOME | L4: ANNUAL TAX PAYABLE | N4: MONTHLY TAX PAYABLE | O4: OLD ACTUAL TAX PAYABLE | P4: INCREASE/DECREASE IN PAYE
A5: S/N | B5: DG'S OFFICE
A6: 1 | B6: PROF. ABUBAKAR O. SULAIMAN | C6: 2246372.1 | D6: 12 | E6: =C6*D6 -> 26956465 | H6: 0 | J6: =F6+G6+H6 -> 0 | K6: =E6-J6 -> 26956465 | L6: =IF(K6<=800000,0,IF(K6<=3000000,(K6-800000)*15%,IF(K6<=12000000,330000+(K6-3000000)*18%,IF(K6<=25000000,1950000+(K6-12000000)*21%,IF(K6<=50000000,4680000+(K6-25000000)*23%,10430000+(K6-50000000)*25%))))) -> 5129986.9 | M6: 12 | N6: =L6/M6 -> 427498.91 | O6: 409970.11 | P6: =N6-O6 -> 17528.806
A7: 2 | B7: RAHEEM USMAN AYIGORO | C7: 1095306.8 | D7: 12 | E7: =C7*D7 -> 13143681 | G7: 0 | H7: 869094.48 | J7: =F7+G7+H7 -> 869094.48 | K7: =E7-J7 -> 12274587 | L7: =IF(K7<=800000,0,IF(K7<=3000000,(K7-800000)*15%,IF(K7<=12000000,330000+(K7-3000000)*18%,IF(K7<=25000000,1950000+(K7-12000000)*21%,IF(K7<=50000000,4680000+(K7-25000000)*23%,10430000+(K7-50000000)*25%))))) -> 2007663.2 | M7: 12 | N7: =L7/M7 -> 167305.26 | O7: 175060.05 | P7: =N7-O7 -> -7754.7869
A8: 3 | B8: MARIAM MOHAMMED BELLO | C8: 1295306.8 | D8: 12 | E8: =C8*D8 -> 15543681 | G8: 0 | H8: 0 | J8: =F8+G8+H8 -> 0 | K8: =E8-J8 -> 15543681 | L8: =IF(K8<=800000,0,IF(K8<=3000000,(K8-800000)*15%,IF(K8<=12000000,330000+(K8-3000000)*18%,IF(K8<=25000000,1950000+(K8-12000000)*21%,IF(K8<=50000000,4680000+(K8-25000000)*23%,10430000+(K8-50000000)*25%))))) -> 2694173 | M8: 12 | N8: =L8/M8 -> 224514.42 | O8: 227365.56 | P8: =N8-O8 -> -2851.1452
A9: 4 | B9: DR IKEME ARTHUR J.O | C9: 1085306.8 | D9: 12 | E9: =C9*D9 -> 13023681 | G9: 166400.85 | H9: 869094.48 | J9: =F9+G9+H9 -> 1035495.3 | K9: =E9-J9 -> 11988186 | L9: =IF(K9<=800000,0,IF(K9<=3000000,(K9-800000)*15%,IF(K9<=12000000,330000+(K9-3000000)*18%,IF(K9<=25000000,1950000+(K9-12000000)*21%,IF(K9<=50000000,4680000+(K9-25000000)*23%,10430000+(K9-50000000)*25%))))) -> 1947873.4 | M9: 12 | N9: =L9/M9 -> 162322.79 | O9: 170477.64 | P9: =N9-O9 -> -8154.8523
A10: 5 | B10: ANDRAWUS MUSA | C10: 1045306.8 | D10: 12 | E10: =C10*D10 -> 12543681 | G10: 166400.85 | H10: 869094.48 | J10: =F10+G10+H10 -> 1035495.3 | K10: =E10-J10 -> 11508186 | L10: =IF(K10<=800000,0,IF(K10<=3000000,(K10-800000)*15%,IF(K10<=12000000,330000+(K10-3000000)*18%,IF(K10<=25000000,1950000+(K10-12000000)*21%,IF(K10<=50000000,4680000+(K10-25000000)*23%,10430000+(K10-50000000)*25%))))) -> 1861473.4 | M10: 12 | N10: =L10/M10 -> 155122.79 | O10: 158706.48 | P10: =N10-O10 -> -3583.6962
A11: 6 | B11: DR FRANCIS NDUM OJIE | C11: 1104477 | D11: 12 | E11: =C11*D11 -> 13253724 | G11: 137703.15 | H11: 714697.92 | J11: =F11+G11+H11 -> 852401.07 | K11: =E11-J11 -> 12401323 | L11: =IF(K11<=800000,0,IF(K11<=3000000,(K11-800000)*15%,IF(K11<=12000000,330000+(K11-3000000)*18%,IF(K11<=25000000,1950000+(K11-12000000)*21%,IF(K11<=50000000,4680000+(K11-25000000)*23%,10430000+(K11-50000000)*25%))))) -> 2034277.8 | M11: 12 | N11: =L11/M11 -> 169523.15 | O11: 173285.16 | P11: =N11-O11 -> -3762.0045
A12: 7 | B12: ALI ABDULLAHI | C12: 780713.92 | D12: 12 | E12: =C12*D12 -> 9368567 | G12: 0 | H12: 672685.36 | J12: =F12+G12+H12 -> 672685.36 | K12: =E12-J12 -> 8695881.6 | L12: =IF(K12<=800000,0,IF(K12<=3000000,(K12-800000)*15%,IF(K12<=12000000,330000+(K12-3000000)*18%,IF(K12<=25000000,1950000+(K12-12000000)*21%,IF(K12<=50000000,4680000+(K12-25000000)*23%,10430000+(K12-50000000)*25%))))) -> 1355258.7 | M12: 12 | N12: =L12/M12 -> 112938.22 | O12: 119506.61 | P12: =N12-O12 -> -6568.3825
A13: 8 | B13: EMILY EKHIDE | C13: 954477 | D13: 12 | E13: =C13*D13 -> 11453724 | G13: 0 | H13: 714697.92 | J13: =F13+G13+H13 -> 714697.92 | K13: =E13-J13 -> 10739026 | L13: =IF(K13<=800000,0,IF(K13<=3000000,(K13-800000)*15%,IF(K13<=12000000,330000+(K13-3000000)*18%,IF(K13<=25000000,1950000+(K13-12000000)*21%,IF(K13<=50000000,4680000+(K13-25000000)*23%,10430000+(K13-50000000)*25%))))) -> 1723024.7 | M13: 12 | N13: =L13/M13 -> 143585.39 | O13: 146625.94 | P13: =N13-O13 -> -3040.5446
A14: 9 | B14: DORIS DAKDA AARON | C14: 963911.08 | D14: 12 | E14: =C14*D14 -> 11566933 | G14: 107120 | H14: 550954.64 | J14: =F14+G14+H14 -> 658074.64 | K14: =E14-J14 -> 10908858 | L14: =IF(K14<=800000,0,IF(K14<=3000000,(K14-800000)*15%,IF(K14<=12000000,330000+(K14-3000000)*18%,IF(K14<=25000000,1950000+(K14-12000000)*21%,IF(K14<=50000000,4680000+(K14-25000000)*23%,10430000+(K14-50000000)*25%))))) -> 1753594.5 | M14: 12 | N14: =L14/M14 -> 146132.88 | O14: 152140.98 | P14: =N14-O14 -> -6008.101
A15: 10 | B15: ABDULSALAM S. MUSTAPHA | C15: 852595.5 | D15: 12 | E15: =C15*D15 -> 10231146 | G15: 0 | H15: 693691.68 | J15: =F15+G15+H15 -> 693691.68 | K15: =E15-J15 -> 9537454.3 | L15: =IF(K15<=800000,0,IF(K15<=3000000,(K15-800000)*15%,IF(K15<=12000000,330000+(K15-3000000)*18%,IF(K15<=25000000,1950000+(K15-12000000)*21%,IF(K15<=50000000,4680000+(K15-25000000)*23%,10430000+(K15-50000000)*25%))))) -> 1506741.8 | M15: 12 | N15: =L15/M15 -> 125561.81 | O15: 127400.77 | P15: =N15-O15 -> -1838.9581
A16: 11 | B16: PERCY TERFA GBAHABO | C16: 682419.5 | D16: 12 | E16: =C16*D16 -> 8189034 | G16: 0 | H16: 520722.72 | J16: =F16+G16+H16 -> 520722.72 | K16: =E16-J16 -> 7668311.3 | L16: =IF(K16<=800000,0,IF(K16<=3000000,(K16-800000)*15%,IF(K16<=12000000,330000+(K16-3000000)*18%,IF(K16<=25000000,1950000+(K16-12000000)*21%,IF(K16<=50000000,4680000+(K16-25000000)*23%,10430000+(K16-50000000)*25%))))) -> 1170296 | M16: 12 | N16: =L16/M16 -> 97524.669 | O16: 101376.05 | P16: =N16-O16 -> -3851.385
A17: 12 | B17: HASSANA AHMED IBRAHIM | C17: 861351.33 | D17: 12 | E17: =C17*D17 -> 10336216 | G17: 101319.25 | H17: 519697.28 | J17: =F17+G17+H17 -> 621016.53 | K17: =E17-J17 -> 9715199.5 | L17: =IF(K17<=800000,0,IF(K17<=3000000,(K17-800000)*15%,IF(K17<=12000000,330000+(K17-3000000)*18%,IF(K17<=25000000,1950000+(K17-12000000)*21%,IF(K17<=50000000,4680000+(K17-25000000)*23%,10430000+(K17-50000000)*25%))))) -> 1538735.9 | M17: 12 | N17: =L17/M17 -> 128227.99 | O17: 131567.97 | P17: =N17-O17 -> -3339.9777
A18: 13 | B18: IKIP LEBO | C18: 582098.92 | D18: 12 | E18: =C18*D18 -> 6985187 | G18: 96107.725 | H18: 491614.96 | J18: =F18+G18+H18 -> 587722.69 | K18: =E18-J18 -> 6397464.3 | L18: =IF(K18<=800000,0,IF(K18<=3000000,(K18-800000)*15%,IF(K18<=12000000,330000+(K18-3000000)*18%,IF(K18<=25000000,1950000+(K18-12000000)*21%,IF(K18<=50000000,4680000+(K18-25000000)*23%,10430000+(K18-50000000)*25%))))) -> 941543.58 | M18: 12 | N18: =L18/M18 -> 78461.965 | O18: 78484.222 | P18: =N18-O18 -> -22.256902
... A25: 20 | B25: RASHEEDAT DAIBU | C25: 450135.83 | D25: 12 | E25: =C25*D25 -> 5401630 | G25: 73851.35 | H25: 374530.4 | J25: =F25+G25+H25 -> 448381.75 | K25: =E25-J25 -> 4953248.3 | L25: =IF(K25<=800000,0,IF(K25<=3000000,(K25-800000)*15%,IF(K25<=12000000,330000+(K25-3000000)*18%,IF(K25<=25000000,1950000+(K25-12000000)*21%,IF(K25<=50000000,4680000+(K25-25000000)*23%,10430000+(K25-50000000)*25%))))) -> 681584.69 | M25: 12 | N25: =L25/M25 -> 56798.724 | O25: 57511.354 | P25: =N25-O25 -> -712.63028
A26: 21 | B26: ELIZABETH OGECHUKWU ONYEAKU | C26: 0 | D26: 12 | E26: =C26*D26 -> 0 | G26: 0 | H26: 0 | J26: =F26+G26+H26 -> 0 | K26: =E26-J26 -> 0 | L26: =IF(K26<=800000,0,IF(K26<=3000000,(K26-800000)*15%,IF(K26<=12000000,330000+(K26-3000000)*18%,IF(K26<=25000000,1950000+(K26-12000000)*21%,IF(K26<=50000000,4680000+(K26-25000000)*23%,10430000+(K26-50000000)*25%))))) -> 0 | M26: 12 | N26: =L26/M26 -> 0 | P26: =N26-O26 -> 0
A27: 22 | B27: VICTOR ASUKWO | C27: 499444 | D27: 12 | E27: =C27*D27 -> 5993328 | G27: 70673.35 | H27: 357259.52 | J27: =F27+G27+H27 -> 427932.87 | K27: =E27-J27 -> 5565395.1 | L27: =IF(K27<=800000,0,IF(K27<=3000000,(K27-800000)*15%,IF(K27<=12000000,330000+(K27-3000000)*18%,IF(K27<=25000000,1950000+(K27-12000000)*21%,IF(K27<=50000000,4680000+(K27-25000000)*23%,10430000+(K27-50000000)*25%))))) -> 791771.12 | M27: 12 | N27: =L27/M27 -> 65980.927 | O27: 69102.189 | P27: =N27-O27 -> -3121.2623
A28: 23 | B28: NNANDI LIVINUS ATURE | C28: 491140.67 | D28: 12 | E28: =C28*D28 -> 5893688 | G28: 72262.375 | H28: 365895.04 | J28: =F28+G28+H28 -> 438157.41 | K28: =E28-J28 -> 5455530.6 | L28: =IF(K28<=800000,0,IF(K28<=3000000,(K28-800000)*15%,IF(K28<=12000000,330000+(K28-3000000)*18%,IF(K28<=25000000,1950000+(K28-12000000)*21%,IF(K28<=50000000,4680000+(K28-25000000)*23%,10430000+(K28-50000000)*25%))))) -> 771995.51 | M28: 12 | N28: =L28/M28 -> 64332.959 | O28: 56180.845 | P28: =N28-O28 -> 8152.1135
A29: 24 | B29: ABDULRAHMAN A SULAIMAN | C29: 415320.67 | D29: 12 | E29: =C29*D29 -> 4983848 | G29: 0 | H29: 341107.84 | J29: =F29+G29+H29 -> 341107.84 | K29: =E29-J29 -> 4642740.2 | L29: =IF(K29<=800000,0,IF(K29<=3000000,(K29-800000)*15%,IF(K29<=12000000,330000+(K29-3000000)*18%,IF(K29<=25000000,1950000+(K29-12000000)*21%,IF(K29<=50000000,4680000+(K29-25000000)*23%,10430000+(K29-50000000)*25%))))) -> 625693.23 | M29: 12 | N29: =L29/M29 -> 52141.102 | O29: 51483.602 | P29: =N29-O29 -> 657.50005
A30: 25 | B30: DARE SHEU MAGBON | C30: 407016.17 | D30: 12 | E30: =C30*D30 -> 4884194 | G30: 0 | H30: 333135.52 | J30: =F30+G30+H30 -> 333135.52 | K30: =E30-J30 -> 4551058.5 | L30: =IF(K30<=800000,0,IF(K30<=3000000,(K30-800000)*15%,IF(K30<=12000000,330000+(K30-3000000)*18%,IF(K30<=25000000,1950000+(K30-12000000)*21%,IF(K30<=50000000,4680000+(K30-25000000)*23%,10430000+(K30-50000000)*25%))))) -> 609190.53 | M30: 12 | N30: =L30/M30 -> 50765.877 | O30: 50016.695 | P30: =N30-O30 -> 749.18173
A31: 26 | B31: ABUBAKAR SULAIMAN SODEEQ | C31: 432145.33 | D31: 12 | E31: =C31*D31 -> 5185744 | G31: 70673.35 | H31: 357259.52 | J31: =F31+G31+H31 -> 427932.87 | K31: =E31-J31 -> 4757811.1 | L31: =IF(K31<=800000,0,IF(K31<=3000000,(K31-800000)*15%,IF(K31<=12000000,330000+(K31-3000000)*18%,IF(K31<=25000000,1950000+(K31-12000000)*21%,IF(K31<=50000000,4680000+(K31-25000000)*23%,10430000+(K31-50000000)*25%))))) -> 646406 | M31: 12 | N31: =L31/M31 -> 53867.167 | O31: 56180.845 | P31: =N31-O31 -> -2313.6783
A32: 27 | B32: JIMOH ADEBAYO ZAKA | C32: 432145.33 | D32: 12 | E32: =C32*D32 -> 5185744 | G32: 70673.35 | H32: 357259.52 | J32: =F32+G32+H32 -> 427932.87 | K32: =E32-J32 -> 4757811.1 | L32: =IF(K32<=800000,0,IF(K32<=3000000,(K32-800000)*15%,IF(K32<=12000000,330000+(K32-3000000)*18%,IF(K32<=25000000,1950000+(K32-12000000)*21%,IF(K32<=50000000,4680000+(K32-25000000)*23%,10430000+(K32-50000000)*25%))))) -> 646406 | M32: 12 | N32: =L32/M32 -> 53867.167 | O32: 56180.845 | P32: =N32-O32 -> -2313.6783
A33: 28 | B33: ABDULMUSHIN TAWFIQ LADAN | C33: 407016.17 | D33: 12 | E33: =C33*D33 -> 4884194 | G33: 0 | H33: 333135.52 | J33: =F33+G33+H33 -> 333135.52 | K33: =E33-J33 -> 4551058.5 | L33: =IF(K33<=800000,0,IF(K33<=3000000,(K33-800000)*15%,IF(K33<=12000000,330000+(K33-3000000)*18%,IF(K33<=25000000,1950000+(K33-12000000)*21%,IF(K33<=50000000,4680000+(K33-25000000)*23%,10430000+(K33-50000000)*25%))))) -> 609190.53 | M33: 12 | N33: =L33/M33 -> 50765.877 | O33: 49761.581 | P33: =N33-O33 -> 1004.296
A34: 29 | B34: MOHAMMED BELLO | C34: 432145.33 | D34: 12 | E34: =C34*D34 -> 5185744 | G34: 0 | H34: 357259.52 | J34: =F34+G34+H34 -> 357259.52 | K34: =E34-J34 -> 4828484.5 | L34: =IF(K34<=800000,0,IF(K34<=3000000,(K34-800000)*15%,IF(K34<=12000000,330000+(K34-3000000)*18%,IF(K34<=25000000,1950000+(K34-12000000)*21%,IF(K34<=50000000,4680000+(K34-25000000)*23%,10430000+(K34-50000000)*25%))))) -> 659127.21 | M34: 12 | N34: =L34/M34 -> 54927.267 | O34: 56180.845 | P34: =N34-O34 -> -1253.578
A35: 30 | B35: HOLINESS PAUL UDO | C35: 398711.67 | D35: 12 | E35: =C35*D35 -> 4784540 | G35: 65320.025 | H35: 325163.2 | J35: =F35+G35+H35 -> 390483.22 | K35: =E35-J35 -> 4394056.8 | L35: =IF(K35<=800000,0,IF(K35<=3000000,(K35-800000)*15%,IF(K35<=12000000,330000+(K35-3000000)*18%,IF(K35<=25000000,1950000+(K35-12000000)*21%,IF(K35<=50000000,4680000+(K35-25000000)*23%,10430000+(K35-50000000)*25%))))) -> 580930.22 | M35: 12 | N35: =L35/M35 -> 48410.852 | O35: 48549.774 | P35: =N35-O35 -> -138.92224
A36: 31 | B36: CHARITY UDO AKAN | C36: 398711.67 | D36: 12 | E36: =C36*D36 -> 4784540 | G36: 65320.025 | H36: 325163.2 | J36: =F36+G36+H36 -> 390483.22 | K36: =E36-J36 -> 4394056.8 | L36: =IF(K36<=800000,0,IF(K36<=3000000,(K36-800000)*15%,IF(K36<=12000000,330000+(K36-3000000)*18%,IF(K36<=25000000,1950000+(K36-12000000)*21%,IF(K36<=50000000,4680000+(K36-25000000)*23%,10430000+(K36-50000000)*25%))))) -> 580930.22 | M36: 12 | N36: =L36/M36 -> 48410.852 | O36: 48549.951 | P36: =N36-O36 -> -139.09888
A37: 32 | B37: SANI UMAR IBRAHIM | C37: 398711.67 | D37: 12 | E37: =C37*D37 -> 4784540 | G37: 0 | H37: 325163.2 | J37: =F37+G37+H37 -> 325163.2 | K37: =E37-J37 -> 4459376.8 | L37: =IF(K37<=800000,0,IF(K37<=3000000,(K37-800000)*15%,IF(K37<=12000000,330000+(K37-3000000)*18%,IF(K37<=25000000,1950000+(K37-12000000)*21%,IF(K37<=50000000,4680000+(K37-25000000)*23%,10430000+(K37-50000000)*25%))))) -> 592687.82 | M37: 12 | N37: =L37/M37 -> 49390.652 | O37: 48550.127 | P37: =N37-O37 -> 840.52485
A38: 33 | B38: FAHAD ABUBUKAR LONGMAN | C38: 398711.67 | D38: 12 | E38: =C38*D38 -> 4784540 | G38: 65320.025 | H38: 325163.2 | J38: =F38+G38+H38 -> 390483.22 | K38: =E38-J38 -> 4394056.8 | L38: =IF(K38<=800000,0,IF(K38<=3000000,(K38-800000)*15%,IF(K38<=12000000,330000+(K38-3000000)*18%,IF(K38<=25000000,1950000+(K38-12000000)*21%,IF(K38<=50000000,4680000+(K38-25000000)*23%,10430000+(K38-50000000)*25%))))) -> 580930.22 | M38: 12 | N38: =L38/M38 -> 48410.852 | O38: 48550.127 | P38: =N38-O38 -> -139.27552
... A46: 41 | B46: ALIYU GARBA LERE | C46: 344900.83 | D46: 12 | E46: =C46*D46 -> 4138810 | G46: 0 | H46: 283104.8 | J46: =F46+G46+H46 -> 283104.8 | K46: =E46-J46 -> 3855705.2 | L46: =IF(K46<=800000,0,IF(K46<=3000000,(K46-800000)*15%,IF(K46<=12000000,330000+(K46-3000000)*18%,IF(K46<=25000000,1950000+(K46-12000000)*21%,IF(K46<=50000000,4680000+(K46-25000000)*23%,10430000+(K46-50000000)*25%))))) -> 484026.94 | M46: 12 | N46: =L46/M46 -> 40335.578 | O46: 40063.241 | P46: =N46-O46 -> 272.33669
B47: TOTAL | C47: =SUM(C6:C46) -> 26032451 | E47: =SUM(E6:E46) -> 312389414 | F47: =SUM(F6:F46) -> 0 | G47: =SUM(G6:G46) -> 1778670.7 | H47: =SUM(H6:H46) -> 16947335 | I47: =SUM(I6:I46) -> 0 | J47: =SUM(J6:J46) -> 18726005 | K47: =SUM(K6:K46) -> 2.9366341e+08 | L47: =SUM(L6:L46) -> 45073825 | ... P47: =SUM(P6:P46) -> -47758.25
B49: INTERNAL AUDIT
A50: 1 | B50: OSANAIYE DAVID AKINYEMI | C50: 1847106.4 | D50: 12 | E50: =C50*D50 -> 22165277 | G50: 0 | H50: 1677222.2 | J50: =F50+G50+H50 -> 1677222.2 | K50: =E50-J50 -> 20488055 | L50: =IF(K50<=800000,0,IF(K50<=3000000,(K50-800000)*15%,IF(K50<=12000000,330000+(K50-3000000)*18%,IF(K50<=25000000,1950000+(K50-12000000)*21%,IF(K50<=50000000,4680000+(K50-25000000)*23%,10430000+(K50-50000000)*25%))))) -> 3732491.5 | M50: 12 | N50: =L50/M50 -> 311040.96 | O50: 306475.54 | P50: =N50-O50 -> 4565.4156
A51: 2 | B51: EVELYN ETONKE AGAN | C51: 802595.5 | D51: 12 | E51: =C51*D51 -> 9631146 | G51: 0 | H51: 693691.68 | J51: =F51+G51+H51 -> 693691.68 | K51: =E51-J51 -> 8937454.3 | L51: =IF(K51<=800000,0,IF(K51<=3000000,(K51-800000)*15%,IF(K51<=12000000,330000+(K51-3000000)*18%,IF(K51<=25000000,1950000+(K51-12000000)*21%,IF(K51<=50000000,4680000+(K51-25000000)*23%,10430000+(K51-50000000)*25%))))) -> 1398741.8 | M51: 12 | N51: =L51/M51 -> 116561.81 | O51: 117800.77 | P51: =N51-O51 -> -1238.9581
A52: 3 | B52: JAMILA ABDUL | C52: 450135.83 | D52: 12 | E52: =C52*D52 -> 5401630 | G52: 73851.35 | H52: 374530.4 | J52: =F52+G52+H52 -> 448381.75 | K52: =E52-J52 -> 4953248.3 | L52: =IF(K52<=800000,0,IF(K52<=3000000,(K52-800000)*15%,IF(K52<=12000000,330000+(K52-3000000)*18%,IF(K52<=25000000,1950000+(K52-12000000)*21%,IF(K52<=50000000,4680000+(K52-25000000)*23%,10430000+(K52-50000000)*25%))))) -> 681584.69 | M52: 12 | N52: =L52/M52 -> 56798.724 | O52: 57511.354 | P52: =N52-O52 -> -712.63028
A53: 4 | B53: IJEOMA EWELUKWA | C53: 514993.58 | D53: 12 | E53: =C53*D53 -> 6179923 | G53: 0 | H53: 436793.84 | J53: =F53+G53+H53 -> 436793.84 | K53: =E53-J53 -> 5743129.2 | L53: =IF(K53<=800000,0,IF(K53<=3000000,(K53-800000)*15%,IF(K53<=12000000,330000+(K53-3000000)*18%,IF(K53<=25000000,1950000+(K53-12000000)*21%,IF(K53<=50000000,4680000+(K53-25000000)*23%,10430000+(K53-50000000)*25%))))) -> 823763.25 | M53: 12 | N53: =L53/M53 -> 68646.937 | O53: 66777.482 | P53: =N53-O53 -> 1869.455
A54: 5 | B54: HASSAN ABDULHADI | C54: 398711.67 | D54: 12 | E54: =C54*D54 -> 4784540 | G54: 65320.025 | H54: 325163.2 | J54: =F54+G54+H54 -> 390483.22 | K54: =E54-J54 -> 4394056.8 | L54: =IF(K54<=800000,0,IF(K54<=3000000,(K54-800000)*15%,IF(K54<=12000000,330000+(K54-3000000)*18%,IF(K54<=25000000,1950000+(K54-12000000)*21%,IF(K54<=50000000,4680000+(K54-25000000)*23%,10430000+(K54-50000000)*25%))))) -> 580930.22 | M54: 12 | N54: =L54/M54 -> 48410.852 | O54: 48549.774 | P54: =N54-O54 -> -138.92224
A55: 6 | B55: YUSUF YUSUF DAYYABU | C55: 407016.17 | D55: 12 | E55: =C55*D55 -> 4884194 | G55: 66802.375 | H55: 333135.52 | J55: =F55+G55+H55 -> 399937.89 | K55: =E55-J55 -> 4484256.1 | L55: =IF(K55<=800000,0,IF(K55<=3000000,(K55-800000)*15%,IF(K55<=12000000,330000+(K55-3000000)*18%,IF(K55<=25000000,1950000+(K55-12000000)*21%,IF(K55<=50000000,4680000+(K55-25000000)*23%,10430000+(K55-50000000)*25%))))) -> 597166.1 | M55: 12 | N55: =L55/M55 -> 49763.842 | O55: 50016.695 | P55: =N55-O55 -> -252.85389
A56: 7 | B56: UDONSI QUEENETH CHIWENDU | C56: 344900.83 | D56: 12 | E56: =C56*D56 -> 4138810 | G56: 0 | H56: 283104.8 | J56: =F56+G56+H56 -> 283104.8 | K56: =E56-J56 -> 3855705.2 | L56: =IF(K56<=800000,0,IF(K56<=3000000,(K56-800000)*15%,IF(K56<=12000000,330000+(K56-3000000)*18%,IF(K56<=25000000,1950000+(K56-12000000)*21%,IF(K56<=50000000,4680000+(K56-25000000)*23%,10430000+(K56-50000000)*25%))))) -> 484026.94 | M56: 12 | N56: =L56/M56 -> 40335.578 | O56: 40063.087 | P56: =N56-O56 -> 272.49125
C57: =SUM(C50:C56) -> 4765460 | E57: =SUM(E50:E56) -> 57185520 | G57: =SUM(G50:G56) -> 205973.75 | H57: =SUM(H50:H56) -> 4123641.6 | J57: =SUM(J50:J56) -> 4329615.3 | K57: =SUM(K50:K56) -> 52855905 | L57: =SUM(L50:L56) -> 8298704.5 | N57: =SUM(N50:N56) -> 691558.71 | O57: =SUM(O50:O56) -> 687194.71 | P57: =SUM(P50:P56) -> 4363.9973
B59: LEG. SUPPORT SEVICES
A60: 1 | B60: BETHEL UZOMA IHUGBA | C60: 1897359.3 | D60: 12 | E60: =C60*D60 -> 22768312 | G60: 0 | H60: 1629465 | J60: =F60+G60+H60 -> 1629465 | K60: =E60-J60 -> 21138847 | L60: =IF(K60<=800000,0,IF(K60<=3000000,(K60-800000)*15%,IF(K60<=12000000,330000+(K60-3000000)*18%,IF(K60<=25000000,1950000+(K60-12000000)*21%,IF(K60<=50000000,4680000+(K60-25000000)*23%,10430000+(K60-50000000)*25%))))) -> 3869157.9 | M60: 12 | N60: =L60/M60 -> 322429.82 | O60: 319502.66 | P60: =N60-O60 -> 2927.1642
A61: 2 | B61: OGUCHE SAMUEL | C61: 904477 | D61: 12 | E61: =C61*D61 -> 10853724 | G61: 0 | H61: 714697.92 | J61: =F61+G61+H61 -> 714697.92 | K61: =E61-J61 -> 10139026 | L61: =IF(K61<=800000,0,IF(K61<=3000000,(K61-800000)*15%,IF(K61<=12000000,330000+(K61-3000000)*18%,IF(K61<=25000000,1950000+(K61-12000000)*21%,IF(K61<=50000000,4680000+(K61-25000000)*23%,10430000+(K61-50000000)*25%))))) -> 1615024.7 | M61: 12 | N61: =L61/M61 -> 134585.39 | O61: 140891.08 | P61: =N61-O61 -> -6305.6927
A62: 3 | B62: IBRAHIM USMAN | C62: 904477 | D62: 12 | E62: =C62*D62 -> 10853724 | G62: 137703.15 | H62: 714697.92 | J62: =F62+G62+H62 -> 852401.07 | K62: =E62-J62 -> 10001323 | L62: =IF(K62<=800000,0,IF(K62<=3000000,(K62-800000)*15%,IF(K62<=12000000,330000+(K62-3000000)*18%,IF(K62<=25000000,1950000+(K62-12000000)*21%,IF(K62<=50000000,4680000+(K62-25000000)*23%,10430000+(K62-50000000)*25%))))) -> 1590238.1 | M62: 12 | N62: =L62/M62 -> 132519.84 | O62: 138687.83 | P62: =N62-O62 -> -6167.9896
A63: 4 | B63: DR MOHAMMED O. AMALI | C63: 904477 | D63: 12 | E63: =C63*D63 -> 10853724 | G63: 0 | H63: 714697.92 | J63: =F63+G63+H63 -> 714697.92 | K63: =E63-J63 -> 10139026 | L63: =IF(K63<=800000,0,IF(K63<=3000000,(K63-800000)*15%,IF(K63<=12000000,330000+(K63-3000000)*18%,IF(K63<=25000000,1950000+(K63-12000000)*21%,IF(K63<=50000000,4680000+(K63-25000000)*23%,10430000+(K63-50000000)*25%))))) -> 1615024.7 | M63: 12 | N63: =L63/M63 -> 134585.39 | O63: 137025.94 | P63: =N63-O63 -> -2440.5446
A64: 5 | B64: YAHAYA SHAMSU | C64: 882595.5 | D64: 12 | E64: =C64*D64 -> 10591146 | G64: 0 | H64: 693691.68 | J64: =F64+G64+H64 -> 693691.68 | K64: =E64-J64 -> 9897454.3 | L64: =IF(K64<=800000,0,IF(K64<=3000000,(K64-800000)*15%,IF(K64<=12000000,330000+(K64-3000000)*18%,IF(K64<=25000000,1950000+(K64-12000000)*21%,IF(K64<=50000000,4680000+(K64-25000000)*23%,10430000+(K64-50000000)*25%))))) -> 1571541.8 | M64: 12 | N64: =L64/M64 -> 130961.81 | O64: 133160.77 | P64: =N64-O64 -> -2198.9581
A65: 6 | B65: CHIDEBE MATHEW NWANKWO | C65: 882595.5 | D65: 12 | E65: =C65*D65 -> 10591146 | G65: 0 | H65: 693691.68 | J65: =F65+G65+H65 -> 693691.68 | K65: =E65-J65 -> 9897454.3 | L65: =IF(K65<=800000,0,IF(K65<=3000000,(K65-800000)*15%,IF(K65<=12000000,330000+(K65-3000000)*18%,IF(K65<=25000000,1950000+(K65-12000000)*21%,IF(K65<=50000000,4680000+(K65-25000000)*23%,10430000+(K65-50000000)*25%))))) -> 1571541.8 | M65: 12 | N65: =L65/M65 -> 130961.81 | O65: 133160.77 | P65: =N65-O65 -> -2198.9581
A66: 7 | B66: UMAR MUSA PADAH | C66: 564993.58 | D66: 12 | E66: =C66*D66 -> 6779923 | G66: 0 | H66: 436793.84 | J66: =F66+G66+H66 -> 436793.84 | K66: =E66-J66 -> 6343129.2 | L66: =IF(K66<=800000,0,IF(K66<=3000000,(K66-800000)*15%,IF(K66<=12000000,330000+(K66-3000000)*18%,IF(K66<=25000000,1950000+(K66-12000000)*21%,IF(K66<=50000000,4680000+(K66-25000000)*23%,10430000+(K66-50000000)*25%))))) -> 931763.25 | M66: 12 | N66: =L66/M66 -> 77646.937 | O66: 77712.992 | P66: =N66-O66 -> -66.055027
A67: 8 | B67: BILKIS S. LAWAL-GAMBARI | C67: 499131.17 | D67: 12 | E67: =C67*D67 -> 5989574 | G67: 0 | H67: 383165.92 | J67: =F67+G67+H67 -> 383165.92 | K67: =E67-J67 -> 5606408.1 | L67: =IF(K67<=800000,0,IF(K67<=3000000,(K67-800000)*15%,IF(K67<=12000000,330000+(K67-3000000)*18%,IF(K67<=25000000,1950000+(K67-12000000)*21%,IF(K67<=50000000,4680000+(K67-25000000)*23%,10430000+(K67-50000000)*25%))))) -> 799153.45 | M67: 12 | N67: =L67/M67 -> 66596.121 | O67: 66780.26 | P67: =N67-O67 -> -184.13907
A68: 9 | B68: UMOH USENOBONG EMMANUEL | C68: 481140.67 | D68: 12 | E68: =C68*D68 -> 5773688 | G68: 0 | H68: 365895.04 | J68: =F68+G68+H68 -> 365895.04 | K68: =E68-J68 -> 5407793 | L68: =IF(K68<=800000,0,IF(K68<=3000000,(K68-800000)*15%,IF(K68<=12000000,330000+(K68-3000000)*18%,IF(K68<=25000000,1950000+(K68-12000000)*21%,IF(K68<=50000000,4680000+(K68-25000000)*23%,10430000+(K68-50000000)*25%))))) -> 763402.73 | M68: 12 | N68: =L68/M68 -> 63616.894 | O68: 63602.418 | P68: =N68-O68 -> 14.476053
A69: 10 | B69: ZAINAB AKINDE | C69: 455320.67 | D69: 12 | E69: =C69*D69 -> 5463848 | G69: 0 | H69: 341107.84 | J69: =F69+G69+H69 -> 341107.84 | K69: =E69-J69 -> 5122740.2 | L69: =IF(K69<=800000,0,IF(K69<=3000000,(K69-800000)*15%,IF(K69<=12000000,330000+(K69-3000000)*18%,IF(K69<=25000000,1950000+(K69-12000000)*21%,IF(K69<=50000000,4680000+(K69-25000000)*23%,10430000+(K69-50000000)*25%))))) -> 712093.23 | M69: 12 | N69: =L69/M69 -> 59341.102 | O69: 59163.602 | P69: =N69-O69 -> 177.50005
A70: 11 | B70: GUNAT NANSAK MARK | C70: 455320.67 | D70: 12 | E70: =C70*D70 -> 5463848 | G70: 0 | H70: 341107.84 | J70: =F70+G70+H70 -> 341107.84 | K70: =E70-J70 -> 5122740.2 | L70: =IF(K70<=800000,0,IF(K70<=3000000,(K70-800000)*15%,IF(K70<=12000000,330000+(K70-3000000)*18%,IF(K70<=25000000,1950000+(K70-12000000)*21%,IF(K70<=50000000,4680000+(K70-25000000)*23%,10430000+(K70-50000000)*25%))))) -> 712093.23 | M70: 12 | N70: =L70/M70 -> 59341.102 | O70: 59163.602 | P70: =N70-O70 -> 177.50005
A71: 12 | B71: MANDU ESSIEN NDEM | C71: 438711.67 | D71: 12 | E71: =C71*D71 -> 5264540 | G71: 0 | H71: 325163.2 | J71: =F71+G71+H71 -> 325163.2 | K71: =E71-J71 -> 4939376.8 | L71: =IF(K71<=800000,0,IF(K71<=3000000,(K71-800000)*15%,IF(K71<=12000000,330000+(K71-3000000)*18%,IF(K71<=25000000,1950000+(K71-12000000)*21%,IF(K71<=50000000,4680000+(K71-25000000)*23%,10430000+(K71-50000000)*25%))))) -> 679087.82 | M71: 12 | N71: =L71/M71 -> 56590.652 | O71: 70149.074 | P71: =N71-O71 -> -13558.422
B72: TOTAL | C72: =SUM(C60:C71) -> 9270599.8 | E72: =SUM(E60:E71) -> 111247197 | G72: =SUM(G60:G71) -> 137703.15 | H72: =SUM(H60:H71) -> 7354175.8 | J72: =SUM(J60:J71) -> 7491878.9 | K72: =SUM(K60:K71) -> 1.0375532e+08 | L72: =SUM(L60:L71) -> 16430123 | N72: =SUM(N60:N71) -> 1369176.9 | O72: =SUM(O60:O71) -> 1399001 | P72: =SUM(P60:P71) -> -29824.119
B74: LEGAL SERVICES
A75: 1 | B75: DR SHUAIBU DANWANKA | C75: 1947106.4 | D75: 12 | E75: =C75*D75 -> 23365277 | G75: 0 | H75: 1677222.2 | J75: =F75+G75+H75 -> 1677222.2 | K75: =E75-J75 -> 21688055 | L75: =IF(K75<=800000,0,IF(K75<=3000000,(K75-800000)*15%,IF(K75<=12000000,330000+(K75-3000000)*18%,IF(K75<=25000000,1950000+(K75-12000000)*21%,IF(K75<=50000000,4680000+(K75-25000000)*23%,10430000+(K75-50000000)*25%))))) -> 3984491.5 | M75: 12 | N75: =L75/M75 -> 332040.96 | O75: 325675.54 | P75: =N75-O75 -> 6365.4156
A76: 2 | B76: ABDULSALAM BAKO | C76: 824477 | D76: 12 | E76: =C76*D76 -> 9893724 | G76: 0 | H76: 714697.92 | J76: =F76+G76+H76 -> 714697.92 | K76: =E76-J76 -> 9179026.1 | L76: =IF(K76<=800000,0,IF(K76<=3000000,(K76-800000)*15%,IF(K76<=12000000,330000+(K76-3000000)*18%,IF(K76<=25000000,1950000+(K76-12000000)*21%,IF(K76<=50000000,4680000+(K76-25000000)*23%,10430000+(K76-50000000)*25%))))) -> 1442224.7 | M76: 12 | N76: =L76/M76 -> 120185.39 | O76: 125531.08 | P76: =N76-O76 -> -5345.6927
C77: =SUM(C75:C76) -> 2771583.4 | E77: =SUM(E75:E76) -> 33259001 | G77: =SUM(G75:G76) -> 0 | H77: =SUM(H75:H76) -> 2391920.1 | J77: =SUM(J75:J76) -> 2391920.1 | K77: =SUM(K75:K76) -> 30867081 | L77: =SUM(L75:L76) -> 5426716.2 | N77: =SUM(N75:N76) -> 452226.35 | O77: =SUM(O75:O76) -> 451206.63 | P77: =SUM(P75:P76) -> 1019.7228
B79: DEMOCRACY & GOVERNANCE
A80: 1 | B80: NGARA CHRISTOPHER OCHANJA | C80: 1085306.8 | D80: 12 | E80: =C80*D80 -> 13023681 | G80: 166400.85 | H80: 869094.48 | J80: =F80+G80+H80 -> 1035495.3 | K80: =E80-J80 -> 11988186 | L80: =IF(K80<=800000,0,IF(K80<=3000000,(K80-800000)*15%,IF(K80<=12000000,330000+(K80-3000000)*18%,IF(K80<=25000000,1950000+(K80-12000000)*21%,IF(K80<=50000000,4680000+(K80-25000000)*23%,10430000+(K80-50000000)*25%))))) -> 1947873.4 | M80: 12 | N80: =L80/M80 -> 162322.79 | O80: 170477.64 | P80: =N80-O80 -> -8154.8523
A81: 2 | B81: EJALONIBU GANIYU LAYI | C81: 713911.08 | D81: 12 | E81: =C81*D81 -> 8566933 | G81: 0 | H81: 550954.64 | J81: =F81+G81+H81 -> 550954.64 | K81: =E81-J81 -> 8015978.4 | L81: =IF(K81<=800000,0,IF(K81<=3000000,(K81-800000)*15%,IF(K81<=12000000,330000+(K81-3000000)*18%,IF(K81<=25000000,1950000+(K81-12000000)*21%,IF(K81<=50000000,4680000+(K81-25000000)*23%,10430000+(K81-50000000)*25%))))) -> 1232876.1 | M81: 12 | N81: =L81/M81 -> 102739.68 | O81: 104140.98 | P81: =N81-O81 -> -1401.301
A82: 3 | B82: MARTINS SOLOMON UDOM | C82: 617472.75 | D82: 12 | E82: =C82*D82 -> 7409673 | G82: 93501.975 | H82: 477573.84 | J82: =F82+G82+H82 -> 571075.81 | K82: =E82-J82 -> 6838597.2 | L82: =IF(K82<=800000,0,IF(K82<=3000000,(K82-800000)*15%,IF(K82<=12000000,330000+(K82-3000000)*18%,IF(K82<=25000000,1950000+(K82-12000000)*21%,IF(K82<=50000000,4680000+(K82-25000000)*23%,10430000+(K82-50000000)*25%))))) -> 1020947.5 | M82: 12 | N82: =L82/M82 -> 85078.958 | O82: 86996.687 | P82: =N82-O82 -> -1917.7294
A83: 4 | B83: ISHAKA DELE | C83: 617472.75 | D83: 12 | E83: =C83*D83 -> 7409673 | G83: 93501.975 | H83: 477573.84 | J83: =F83+G83+H83 -> 571075.81 | K83: =E83-J83 -> 6838597.2 | L83: =IF(K83<=800000,0,IF(K83<=3000000,(K83-800000)*15%,IF(K83<=12000000,330000+(K83-3000000)*18%,IF(K83<=25000000,1950000+(K83-12000000)*21%,IF(K83<=50000000,4680000+(K83-25000000)*23%,10430000+(K83-50000000)*25%))))) -> 1020947.5 | M83: 12 | N83: =L83/M83 -> 85078.958 | O83: 86996.687 | P83: =N83-O83 -> -1917.7294
A84: 5 | B84: UDEFUNA NNADOZIE PATRICK | C84: 592662.67 | D84: 12 | E84: =C84*D84 -> 7111952 | G84: 90863.6 | H84: 463356.16 | J84: =F84+G84+H84 -> 554219.76 | K84: =E84-J84 -> 6557732.2 | L84: =IF(K84<=800000,0,IF(K84<=3000000,(K84-800000)*15%,IF(K84<=12000000,330000+(K84-3000000)*18%,IF(K84<=25000000,1950000+(K84-12000000)*21%,IF(K84<=50000000,4680000+(K84-25000000)*23%,10430000+(K84-50000000)*25%))))) -> 970391.8 | M84: 12 | N84: =L84/M84 -> 80865.984 | O84: 82600.474 | P84: =N84-O84 -> -1734.4904
A85: 6 | B85: SHAFIU YAHYA MIKAIL | C85: 592662.67 | D85: 12 | E85: =C85*D85 -> 7111952 | G85: 0 | H85: 463356.16 | J85: =F85+G85+H85 -> 463356.16 | K85: =E85-J85 -> 6648595.8 | L85: =IF(K85<=800000,0,IF(K85<=3000000,(K85-800000)*15%,IF(K85<=12000000,330000+(K85-3000000)*18%,IF(K85<=25000000,1950000+(K85-12000000)*21%,IF(K85<=50000000,4680000+(K85-25000000)*23%,10430000+(K85-50000000)*25%))))) -> 986747.25 | M85: 12 | N85: =L85/M85 -> 82228.938 | O85: 82600.474 | P85: =N85-O85 -> -371.53643
A86: 7 | B86: HASSAN YERIMA | C86: 592662.67 | D86: 12 | E86: =C86*D86 -> 7111952 | G86: 0 | H86: 463356.16 | J86: =F86+G86+H86 -> 463356.16 | K86: =E86-J86 -> 6648595.8 | L86: =IF(K86<=800000,0,IF(K86<=3000000,(K86-800000)*15%,IF(K86<=12000000,330000+(K86-3000000)*18%,IF(K86<=25000000,1950000+(K86-12000000)*21%,IF(K86<=50000000,4680000+(K86-25000000)*23%,10430000+(K86-50000000)*25%))))) -> 986747.25 | M86: 12 | N86: =L86/M86 -> 82228.938 | O86: 82600.474 | P86: =N86-O86 -> -371.53643
A87: 8 | B87: HAUWA PATE SADIQ | C87: 602846.58 | D87: 12 | E87: =C87*D87 -> 7234159 | G87: 0 | H87: 463532.72 | J87: =F87+G87+H87 -> 463532.72 | K87: =E87-J87 -> 6770626.3 | L87: =IF(K87<=800000,0,IF(K87<=3000000,(K87-800000)*15%,IF(K87<=12000000,330000+(K87-3000000)*18%,IF(K87<=25000000,1950000+(K87-12000000)*21%,IF(K87<=50000000,4680000+(K87-25000000)*23%,10430000+(K87-50000000)*25%))))) -> 1008712.7 | M87: 12 | N87: =L87/M87 -> 84059.394 | O87: 86996.687 | P87: =N87-O87 -> -2937.2929
A88: 9 | B88: OBOT ETIMBUK EMMANUEL | C88: 564993.58 | D88: 12 | E88: =C88*D88 -> 6779923 | G88: 85934.125 | H88: 436793.84 | J88: =F88+G88+H88 -> 522727.97 | K88: =E88-J88 -> 6257195 | L88: =IF(K88<=800000,0,IF(K88<=3000000,(K88-800000)*15%,IF(K88<=12000000,330000+(K88-3000000)*18%,IF(K88<=25000000,1950000+(K88-12000000)*21%,IF(K88<=50000000,4680000+(K88-25000000)*23%,10430000+(K88-50000000)*25%))))) -> 916295.11 | M88: 12 | N88: =L88/M88 -> 76357.926 | O88: 77712.992 | P88: =N88-O88 -> -1355.0669
A89: 10 | B89: KOLAPO Q. ABAYOMI | C89: 499131.17 | D89: 12 | E89: =C89*D89 -> 5989574 | G89: 75440.375 | H89: 383165.92 | J89: =F89+G89+H89 -> 458606.29 | K89: =E89-J89 -> 5530967.7 | L89: =IF(K89<=800000,0,IF(K89<=3000000,(K89-800000)*15%,IF(K89<=12000000,330000+(K89-3000000)*18%,IF(K89<=25000000,1950000+(K89-12000000)*21%,IF(K89<=50000000,4680000+(K89-25000000)*23%,10430000+(K89-50000000)*25%))))) -> 785574.19 | M89: 12 | N89: =L89/M89 -> 65464.516 | O89: 65598.639 | P89: =N89-O89 -> -134.12309
A90: 11 | B90: SALIHU SHAMSUDEEN OPEYEMI | C90: 438711.67 | D90: 12 | E90: =C90*D90 -> 5264540 | G90: 0 | H90: 325163.2 | J90: =F90+G90+H90 -> 325163.2 | K90: =E90-J90 -> 4939376.8 | L90: =IF(K90<=800000,0,IF(K90<=3000000,(K90-800000)*15%,IF(K90<=12000000,330000+(K90-3000000)*18%,IF(K90<=25000000,1950000+(K90-12000000)*21%,IF(K90<=50000000,4680000+(K90-25000000)*23%,10430000+(K90-50000000)*25%))))) -> 679087.82 | M90: 12 | N90: =L90/M90 -> 56590.652 | O90: 56229.774 | P90: =N90-O90 -> 360.87813
C91: =SUM(C80:C90) -> 6917834.3 | E91: =SUM(E80:E90) -> 83014012 | G91: =SUM(G80:G90) -> 605642.9 | H91: =SUM(H80:H90) -> 5373921 | J91: =SUM(J80:J90) -> 5979563.9 | K91: =SUM(K80:K90) -> 77034448 | L91: =SUM(L80:L90) -> 11556201 | N91: =SUM(N80:N90) -> 963016.72 | O91: =SUM(O80:O90) -> 982951.5 | P91: =SUM(P80:P90) -> -19934.78
B93: DEPARTMENT OF STUDIES
A94: 1 | B94: DR ASIMIYU G. ABIOLA | C94: 1947106.4 | D94: 12 | E94: =C94*D94 -> 23365277 | G94: 0 | H94: 1677222.2 | J94: =F94+G94+H94 -> 1677222.2 | K94: =E94-J94 -> 21688055 | L94: =IF(K94<=800000,0,IF(K94<=3000000,(K94-800000)*15%,IF(K94<=12000000,330000+(K94-3000000)*18%,IF(K94<=25000000,1950000+(K94-12000000)*21%,IF(K94<=50000000,4680000+(K94-25000000)*23%,10430000+(K94-50000000)*25%))))) -> 3984491.5 | M94: 12 | N94: =L94/M94 -> 332040.96 | O94: 325675.54 | P94: =N94-O94 -> 6365.4156
A95: 2 | B95: AYOBOLU OLAJIDE OLUFUNSHO | C95: 882595.5 | D95: 12 | E95: =C95*D95 -> 10591146 | G95: 0 | H95: 693691.68 | J95: =F95+G95+H95 -> 693691.68 | K95: =E95-J95 -> 9897454.3 | L95: =IF(K95<=800000,0,IF(K95<=3000000,(K95-800000)*15%,IF(K95<=12000000,330000+(K95-3000000)*18%,IF(K95<=25000000,1950000+(K95-12000000)*21%,IF(K95<=50000000,4680000+(K95-25000000)*23%,10430000+(K95-50000000)*25%))))) -> 1571541.8 | M95: 12 | N95: =L95/M95 -> 130961.81 | O95: 137025.94 | P95: =N95-O95 -> -6064.121
A96: 3 | B96: DR. HADIZA SAIDU | C96: 882595.5 | D96: 12 | E96: =C96*D96 -> 10591146 | G96: 0 | H96: 693691.68 | J96: =F96+G96+H96 -> 693691.68 | K96: =E96-J96 -> 9897454.3 | L96: =IF(K96<=800000,0,IF(K96<=3000000,(K96-800000)*15%,IF(K96<=12000000,330000+(K96-3000000)*18%,IF(K96<=25000000,1950000+(K96-12000000)*21%,IF(K96<=50000000,4680000+(K96-25000000)*23%,10430000+(K96-50000000)*25%))))) -> 1571541.8 | M96: 12 | N96: =L96/M96 -> 130961.81 | O96: 137025.94 | P96: =N96-O96 -> -6064.121
A97: 4 | B97: ANTHONY EDET | C97: 729657 | D97: 12 | E97: =C97*D97 -> 8755884 | G97: 109925.25 | H97: 566070.72 | J97: =F97+G97+H97 -> 675995.97 | K97: =E97-J97 -> 8079888 | L97: =IF(K97<=800000,0,IF(K97<=3000000,(K97-800000)*15%,IF(K97<=12000000,330000+(K97-3000000)*18%,IF(K97<=25000000,1950000+(K97-12000000)*21%,IF(K97<=50000000,4680000+(K97-25000000)*23%,10430000+(K97-50000000)*25%))))) -> 1244379.8 | M97: 12 | N97: =L97/M97 -> 103698.32 | O97: 105208.4 | P97: =N97-O97 -> -1510.08
A98: 5 | B98: CHRISTIAN MADUABUCHI ODO | C98: 617472.75 | D98: 12 | E98: =C98*D98 -> 7409673 | G98: 93501.975 | H98: 477573.84 | J98: =F98+G98+H98 -> 571075.81 | K98: =E98-J98 -> 6838597.2 | L98: =IF(K98<=800000,0,IF(K98<=3000000,(K98-800000)*15%,IF(K98<=12000000,330000+(K98-3000000)*18%,IF(K98<=25000000,1950000+(K98-12000000)*21%,IF(K98<=50000000,4680000+(K98-25000000)*23%,10430000+(K98-50000000)*25%))))) -> 1020947.5 | M98: 12 | N98: =L98/M98 -> 85078.958 | O98: 86996.687 | P98: =N98-O98 -> -1917.7294
A99: 6 | B99: DR. IBANGA ISSAC JONAH | C99: 617472.75 | D99: 12 | E99: =C99*D99 -> 7409673 | G99: 0 | H99: 477573.84 | J99: =F99+G99+H99 -> 477573.84 | K99: =E99-J99 -> 6932099.2 | L99: =IF(K99<=800000,0,IF(K99<=3000000,(K99-800000)*15%,IF(K99<=12000000,330000+(K99-3000000)*18%,IF(K99<=25000000,1950000+(K99-12000000)*21%,IF(K99<=50000000,4680000+(K99-25000000)*23%,10430000+(K99-50000000)*25%))))) -> 1037777.8 | M99: 12 | N99: =L99/M99 -> 86481.487 | O99: 86996.687 | P99: =N99-O99 -> -515.19975
A100: 7 | B100: IGWE STACY | C100: 578828.17 | D100: 12 | E100: =C100*D100 -> 6945938 | G100: 88398.875 | H100: 450075.04 | J100: =F100+G100+H100 -> 538473.92 | K100: =E100-J100 -> 6407464.1 | L100: =IF(K100<=800000,0,IF(K100<=3000000,(K100-800000)*15%,IF(K100<=12000000,330000+(K100-3000000)*18%,IF(K100<=25000000,1950000+(K100-12000000)*21%,IF(K100<=50000000,4680000+(K100-25000000)*23%,10430000+(K100-50000000)*25%))))) -> 943343.54 | M100: 12 | N100: =L100/M100 -> 78611.961 | O100: 80156.733 | P100: =N100-O100 -> -1544.772
A101: 8 | B101: MUNIRU JIBRIN | C101: 481140.67 | D101: 12 | E101: =C101*D101 -> 5773688 | G101: 0 | H101: 365895.04 | J101: =F101+G101+H101 -> 365895.04 | K101: =E101-J101 -> 5407793 | L101: =IF(K101<=800000,0,IF(K101<=3000000,(K101-800000)*15%,IF(K101<=12000000,330000+(K101-3000000)*18%,IF(K101<=25000000,1950000+(K101-12000000)*21%,IF(K101<=50000000,4680000+(K101-25000000)*23%,10430000+(K101-50000000)*25%))))) -> 763402.73 | M101: 12 | N101: =L101/M101 -> 63616.894 | O101: 63602.418 | P101: =N101-O101 -> 14.476053
A102: 9 | B102: OLANIYAN TAIWO ABINBOLA | C102: 447016.17 | D102: 12 | E102: =C102*D102 -> 5364194 | G102: 66802.375 | H102: 333135.52 | J102: =F102+G102+H102 -> 399937.89 | K102: =E102-J102 -> 4964256.1 | L102: =IF(K102<=800000,0,IF(K102<=3000000,(K102-800000)*15%,IF(K102<=12000000,330000+(K102-3000000)*18%,IF(K102<=25000000,1950000+(K102-12000000)*21%,IF(K102<=50000000,4680000+(K102-25000000)*23%,10430000+(K102-50000000)*25%))))) -> 683566.1 | M102: 12 | N102: =L102/M102 -> 56963.842 | O102: 59163.602 | P102: =N102-O102 -> -2199.7608
A103: 10 | B103: MUSA ALKASIM ADAMU | C103: 438711.67 | D103: 12 | E103: =C103*D103 -> 5264540 | G103: 0 | H103: 325163.2 | J103: =F103+G103+H103 -> 325163.2 | K103: =E103-J103 -> 4939376.8 | L103: =IF(K103<=800000,0,IF(K103<=3000000,(K103-800000)*15%,IF(K103<=12000000,330000+(K103-3000000)*18%,IF(K103<=25000000,1950000+(K103-12000000)*21%,IF(K103<=50000000,4680000+(K103-25000000)*23%,10430000+(K103-50000000)*25%))))) -> 679087.82 | M103: 12 | N103: =L103/M103 -> 56590.652 | O103: 56229.774 | P103: =N103-O103 -> 360.87813
A104: 11 | B104: AMINAT JUMOKE SULAIMON | C104: 408920.67 | D104: 12 | E104: =C104*D104 -> 4907048 | G104: 0 | H104: 296563.84 | J104: =F104+G104+H104 -> 296563.84 | K104: =E104-J104 -> 4610484.2 | L104: =IF(K104<=800000,0,IF(K104<=3000000,(K104-800000)*15%,IF(K104<=12000000,330000+(K104-3000000)*18%,IF(K104<=25000000,1950000+(K104-12000000)*21%,IF(K104<=50000000,4680000+(K104-25000000)*23%,10430000+(K104-50000000)*25%))))) -> 619887.15 | M104: 12 | N104: =L104/M104 -> 51657.262 | O104: 51196.182 | P104: =N104-O104 -> 461.08085
B105: TOTAL | C105: =SUM(C94:C104) -> 8031517.2 | E105: =SUM(E94:E104) -> 96378207 | G105: =SUM(G94:G104) -> 358628.47 | H105: =SUM(H94:H104) -> 6356656.6 | J105: =SUM(J94:J104) -> 6715285 | K105: =SUM(K94:K104) -> 89662922 | L105: =SUM(L94:L104) -> 14119968 | N105: =SUM(N94:N104) -> 1176664 | O105: =SUM(O94:O104) -> 1189277.9 | P105: =SUM(P94:P104) -> -12613.933
B107: ECON. DEV. & SOC. RESEARCH
A108: 1 | B108: DR AUGUSTINE C. OSIGWE | C108: 1897359.3 | D108: 12 | E108: =C108*D108 -> 22768312 | G108: 316881.85 | H108: 1629465 | J108: =F108+G108+H108 -> 1946346.8 | K108: =E108-J108 -> 20821965 | L108: =IF(K108<=800000,0,IF(K108<=3000000,(K108-800000)*15%,IF(K108<=12000000,330000+(K108-3000000)*18%,IF(K108<=25000000,1950000+(K108-12000000)*21%,IF(K108<=50000000,4680000+(K108-25000000)*23%,10430000+(K108-50000000)*25%))))) -> 3802612.7 | M108: 12 | N108: =L108/M108 -> 316884.39 | O108: 303177.16 | P108: =N108-O108 -> 13707.228
A109: 2 | B109: TERFA WILLIAMS ABRAHAM | C109: 1259008.9 | D109: 12 | E109: =C109*D109 -> 15108107 | G109: 0 | H109: 843848.56 | J109: =F109+G109+H109 -> 843848.56 | K109: =E109-J109 -> 14264258 | L109: =IF(K109<=800000,0,IF(K109<=3000000,(K109-800000)*15%,IF(K109<=12000000,330000+(K109-3000000)*18%,IF(K109<=25000000,1950000+(K109-12000000)*21%,IF(K109<=50000000,4680000+(K109-25000000)*23%,10430000+(K109-50000000)*25%))))) -> 2425494.3 | M109: 12 | N109: =L109/M109 -> 202124.52 | O109: 202249.55 | P109: =N109-O109 -> -125.02973
A110: 3 | B110: OMOJU OLUWASOLA EMMANUEL | C110: 904477 | D110: 12 | E110: =C110*D110 -> 10853724 | G110: 0 | H110: 714697.92 | J110: =F110+G110+H110 -> 714697.92 | K110: =E110-J110 -> 10139026 | L110: =IF(K110<=800000,0,IF(K110<=3000000,(K110-800000)*15%,IF(K110<=12000000,330000+(K110-3000000)*18%,IF(K110<=25000000,1950000+(K110-12000000)*21%,IF(K110<=50000000,4680000+(K110-25000000)*23%,10430000+(K110-50000000)*25%))))) -> 1615024.7 | M110: 12 | N110: =L110/M110 -> 134585.39 | O110: 137025.94 | P110: =N110-O110 -> -2440.5446
A111: 4 | B111: IBE EZECHI CYRIACUS | C111: 713911.08 | D111: 12 | E111: =C111*D111 -> 8566933 | G111: 107120 | H111: 550954.64 | J111: =F111+G111+H111 -> 658074.64 | K111: =E111-J111 -> 7908858.4 | L111: =IF(K111<=800000,0,IF(K111<=3000000,(K111-800000)*15%,IF(K111<=12000000,330000+(K111-3000000)*18%,IF(K111<=25000000,1950000+(K111-12000000)*21%,IF(K111<=50000000,4680000+(K111-25000000)*23%,10430000+(K111-50000000)*25%))))) -> 1213594.5 | M111: 12 | N111: =L111/M111 -> 101132.88 | O111: 102472.11 | P111: =N111-O111 -> -1339.2365
A112: 5 | B112: OSIKHEN LEO IGBANOI | C112: 713911.08 | D112: 12 | E112: =C112*D112 -> 8566933 | G112: 107120 | H112: 550954.64 | J112: =F112+G112+H112 -> 658074.64 | K112: =E112-J112 -> 7908858.4 | L112: =IF(K112<=800000,0,IF(K112<=3000000,(K112-800000)*15%,IF(K112<=12000000,330000+(K112-3000000)*18%,IF(K112<=25000000,1950000+(K112-12000000)*21%,IF(K112<=50000000,4680000+(K112-25000000)*23%,10430000+(K112-50000000)*25%))))) -> 1213594.5 | M112: 12 | N112: =L112/M112 -> 101132.88 | O112: 102472.11 | P112: =N112-O112 -> -1339.2365
A113: 6 | B113: OKUNGBOWA OSARETIN GODSPOWER | C113: 698166.25 | D113: 12 | E113: =C113*D113 -> 8377995 | G113: 0 | H113: 535839.6 | J113: =F113+G113+H113 -> 535839.6 | K113: =E113-J113 -> 7842155.4 | L113: =IF(K113<=800000,0,IF(K113<=3000000,(K113-800000)*15%,IF(K113<=12000000,330000+(K113-3000000)*18%,IF(K113<=25000000,1950000+(K113-12000000)*21%,IF(K113<=50000000,4680000+(K113-25000000)*23%,10430000+(K113-50000000)*25%))))) -> 1201588 | M113: 12 | N113: =L113/M113 -> 100132.33 | O113: 101359.65 | P113: =N113-O113 -> -1227.3161
A114: 7 | B114: YUSUF IBRAHIM | C114: 592662.67 | D114: 12 | E114: =C114*D114 -> 7111952 | G114: 0 | H114: 463356.16 | J114: =F114+G114+H114 -> 463356.16 | K114: =E114-J114 -> 6648595.8 | L114: =IF(K114<=800000,0,IF(K114<=3000000,(K114-800000)*15%,IF(K114<=12000000,330000+(K114-3000000)*18%,IF(K114<=25000000,1950000+(K114-12000000)*21%,IF(K114<=50000000,4680000+(K114-25000000)*23%,10430000+(K114-50000000)*25%))))) -> 986747.25 | M114: 12 | N114: =L114/M114 -> 82228.938 | O114: 82600.474 | P114: =N114-O114 -> -371.53643
A115: 8 | B115: MUSTAPHA RAFIU AYOBANJI | C115: 632098.92 | D115: 12 | E115: =C115*D115 -> 7585187 | G115: 96107.725 | H115: 491614.96 | J115: =F115+G115+H115 -> 587722.69 | K115: =E115-J115 -> 6997464.3 | L115: =IF(K115<=800000,0,IF(K115<=3000000,(K115-800000)*15%,IF(K115<=12000000,330000+(K115-3000000)*18%,IF(K115<=25000000,1950000+(K115-12000000)*21%,IF(K115<=50000000,4680000+(K115-25000000)*23%,10430000+(K115-50000000)*25%))))) -> 1049543.6 | M115: 12 | N115: =L115/M115 -> 87461.965 | O115: 88084.222 | P115: =N115-O115 -> -622.2569
A116: 9 | B116: UDOKANG NSISONG BONIFACE | C116: 564993.58 | D116: 12 | E116: =C116*D116 -> 6779923 | G116: 0 | H116: 436793.84 | J116: =F116+G116+H116 -> 436793.84 | K116: =E116-J116 -> 6343129.2 | L116: =IF(K116<=800000,0,IF(K116<=3000000,(K116-800000)*15%,IF(K116<=12000000,330000+(K116-3000000)*18%,IF(K116<=25000000,1950000+(K116-12000000)*21%,IF(K116<=50000000,4680000+(K116-25000000)*23%,10430000+(K116-50000000)*25%))))) -> 931763.25 | M116: 12 | N116: =L116/M116 -> 77646.937 | O116: 77712.992 | P116: =N116-O116 -> -66.055027
A117: 10 | B117: MARYAM MUSA SADA | C117: 499131.17 | D117: 12 | E117: =C117*D117 -> 5989574 | G117: 0 | H117: 383165.92 | J117: =F117+G117+H117 -> 383165.92 | K117: =E117-J117 -> 5606408.1 | L117: =IF(K117<=800000,0,IF(K117<=3000000,(K117-800000)*15%,IF(K117<=12000000,330000+(K117-3000000)*18%,IF(K117<=25000000,1950000+(K117-12000000)*21%,IF(K117<=50000000,4680000+(K117-25000000)*23%,10430000+(K117-50000000)*25%))))) -> 799153.45 | M117: 12 | N117: =L117/M117 -> 66596.121 | O117: 66780.26 | P117: =N117-O117 -> -184.13907
A118: 11 | B118: TAWAKALTU FOLASHADE SADIQ | C118: 438711.67 | D118: 12 | E118: =C118*D118 -> 5264540 | G118: 0 | H118: 325163.2 | J118: =F118+G118+H118 -> 325163.2 | K118: =E118-J118 -> 4939376.8 | L118: =IF(K118<=800000,0,IF(K118<=3000000,(K118-800000)*15%,IF(K118<=12000000,330000+(K118-3000000)*18%,IF(K118<=25000000,1950000+(K118-12000000)*21%,IF(K118<=50000000,4680000+(K118-25000000)*23%,10430000+(K118-50000000)*25%))))) -> 679087.82 | M118: 12 | N118: =L118/M118 -> 56590.652 | O118: 56229.774 | P118: =N118-O118 -> 360.87813
A119: 12 | B119: MURTALA ADAM MUHAMMAD | C119: 438711.67 | D119: 12 | E119: =C119*D119 -> 5264540 | G119: 0 | H119: 325163.2 | J119: =F119+G119+H119 -> 325163.2 | K119: =E119-J119 -> 4939376.8 | L119: =IF(K119<=800000,0,IF(K119<=3000000,(K119-800000)*15%,IF(K119<=12000000,330000+(K119-3000000)*18%,IF(K119<=25000000,1950000+(K119-12000000)*21%,IF(K119<=50000000,4680000+(K119-25000000)*23%,10430000+(K119-50000000)*25%))))) -> 679087.82 | M119: 12 | N119: =L119/M119 -> 56590.652 | O119: 56229.774 | P119: =N119-O119 -> 360.87813
...

Sheet New Steps, Pensions & NHF
A1: NATIONAL INSTITUTE FOR LEGISLATIVE AND DEMOCRATIC STUDIES
A2: STAFF PAYROLL FOR THE MONTH OF JANUARY 2026
E3: ='[1]FEB 08'!E11/'[1]FEB 08'!M11 -> #REF!
B4: STAFF NAME | C4: DESIGNATION | D4: OLD GRADE LEVEL | E4: OLD BASIC SALARY | F4: NEW GRADE LEVEL | G4: NEW BASIC SALARY | H4: CHANGE IN STEPS (GROSS) | I4: OLD EMPLOYEE PENSIONS | J4: NEW EMPLOYEE PENSIONS | K4: CHANGES IN PENSIONS | L4: NEW ANNUAL PENSIONS | M4: NEW GRADE LEVEL | N4: NEW BASIC | O4: NHF 2.5% | P4: OLD NHF DED. | Q4: INCREASE IN NHF | R4: NHF ANNUAL
E5: N | G5: N | H5: N | I5: N | J5: N | K5: N | L5: N | P5: N
A6: S/N | B6: DG'S OFFICE
A7: 1 | B7: PROF. ABUBAKAR O. SULAIMAN | C7: DIRECTOR GENERAL | D7: CONSOL | E7: 1971137.1 | F7: CONSOL | G7: 1971137.1 | H7: =G7-E7 -> 0 | I7: 0 | K7: =J7-I7 -> 0 | L7: =J7*12 -> 0 | M7: CONSOL | O7: =N7*0.025 -> 0
A8: 2 | B8: RAHEEM USMAN AYIGORO | C8: SA-INFRASTRUCTURE | D8: 16 (9) | E8: 905306.75 | F8: 16 (9) | G8: 905306.75 | H8: =G8-E8 -> 0 | I8: 72424.54 | J8: =G8*0.08 -> 72424.54 | K8: =J8-I8 -> 0 | L8: =J8*12 -> 869094.48 | M8: 16 (9) | N8: 554669.5 | Q8: =O8-P8 -> 0 | R8: =O8*12 -> 0
A9: 3 | B9: MARIAM MOHAMMED BELLO | C9: SA- SPECIAL DUTIES | D9: 16 (9) | E9: 905306.75 | F9: 16 (9) | G9: 905306.75 | H9: =G9-E9 -> 0 | K9: =J9-I9 -> 0 | L9: =J9*12 -> 0 | M9: 16 (9) | O9: =N9*0.025 -> 0 | Q9: =O9-P9 -> 0 | R9: =O9*12 -> 0
A10: 4 | B10: DR IKEME ARTHUR J.O | C10: DEPUTY DIRECTOR, M&E | D10: 16 (9) | E10: 905306.75 | F10: 16 (9) | G10: 905306.75 | H10: =G10-E10 -> 0 | I10: 72424.54 | J10: =G10*0.08 -> 72424.54 | K10: =J10-I10 -> 0 | L10: =J10*12 -> 869094.48 | M10: 16 (9) | N10: 554669.5 | O10: =N10*0.025 -> 13866.737 | P10: 13866.737 | Q10: =O10-P10 -> 0 | R10: =O10*12 -> 166400.85
A11: 5 | B11: ANDRAWUS MUSA | C11: DEP. DIRECTOR, STORES & PROCUREMENT | D11: 16(8) | E11: 879008.92 | F11: 16(9) | G11: 905306.75 | H11: =G11-E11 -> 26297.833 | I11: 68216.887 | J11: =G11*0.08 -> 72424.54 | K11: =J11-I11 -> 4207.6533 | L11: =J11*12 -> 869094.48 | M11: 16(9) | N11: 554669.5 | O11: =N11*0.025 -> 13866.737 | P11: 13084.663 | Q11: =O11-P11 -> 782.075 | R11: =O11*12 -> 166400.85
A12: 6 | B12: DR FRANCIS NDUM OJIE | C12: AD, TRAINING & IC./SA TO DG | D12: 15(8) | E12: 722595.5 | F12: 15(9) | G12: 744477 | H12: =G12-E12 -> 21881.5 | I12: 57807.64 | J12: =G12*0.08 -> 59558.16 | K12: =J12-I12 -> 1750.52 | L12: =J12*12 -> 714697.92 | M12: 15(9) | N12: 459010.5 | O12: =N12*0.025 -> 11475.263 | P12: 11149.896 | Q12: =O12-P12 -> 325.36667 | R12: =O12*12 -> 137703.15
A13: 7 | B13: ALI ABDULLAHI | C13: ASST DIRECTOR ICT | D13: 15(7) | E13: 700713.92 | F13: 15(7) | G13: 700713.92 | H13: =G13-E13 -> 0 | I13: 56057.113 | J13: =G13*0.08 -> 56057.113 | K13: =J13-I13 -> 0 | L13: =J13*12 -> 672685.36 | M13: 15(7) | N13: 432981.08 | Q13: =O13-P13 -> 0 | R13: =O13*12 -> 0
A14: 8 | B14: EMILY EKHIDE | C14: SENIOR RESEARCH FELLOW | D14: 15(8) | E14: 722595.5 | F14: 15(9) | G14: 744477 | H14: =G14-E14 -> 21881.5 | I14: 57807.64 | J14: =G14*0.08 -> 59558.16 | K14: =J14-I14 -> 1750.52 | L14: =J14*12 -> 714697.92 | M14: 15(9) | N14: 459010.5 | Q14: =O14-P14 -> 0 | R14: =O14*12 -> 0
A15: 9 | B15: DORIS DAKDA AARON | C15: RESEARCH FELLOW I | D15: 14(9) | E15: 558165.25 | F15: 14(10) | G15: 573911.08 | H15: =G15-E15 -> 15745.833 | I15: 44653.22 | J15: =G15*0.08 -> 45912.887 | K15: =J15-I15 -> 1259.6667 | L15: =J15*12 -> 550954.64 | M15: 14(10) | N15: 357066.67 | O15: =N15*0.025 -> 8926.6667 | P15: 8692.8979 | Q15: =O15-P15 -> 233.76875 | R15: =O15*12 -> 107120
A16: 10 | B16: ABDULSALAM S. MUSTAPHA | C16: ASST. DIRECTOR ICT | D16: 15(7) | E16: 700713.92 | F16: 15(8) | G16: 722595.5 | H16: =G16-E16 -> 21881.583 | I16: 56057.113 | J16: =G16*0.08 -> 57807.64 | K16: =J16-I16 -> 1750.5267 | L16: =J16*12 -> 693691.68 | M16: 15(8) | N16: 445995.83 | Q16: =O16-P16 -> 0 | R16: =O16*12 -> 0
A17: 11 | B17: PERCY TERFA GBAHABO | C17: RESEARCH FELLOW 1 | D17: 14(7) | E17: 542419.5 | F17: 14(8) | G17: ='[21] FGN 2024 MGT Monthly'!$I$42+'[21]Peculiar Allowance'!$I$42 -> 542419.5 | H17: =G17-E17 -> 0 | I17: 42133.887 | J17: =G17*0.08 -> 43393.56 | K17: =J17-I17 -> 1259.6733 | L17: =J17*12 -> 520722.72 | M17: 14(8) | N17: 338365.25 | Q17: =O17-P17 -> 0 | R17: =O17*12 -> 0
A18: 12 | B18: HASSANA AHMED IBRAHIM | C18: PA- TO DG | D18: 13(10) | E18: 526725.08 | F18: 13(11) | G18: ='[21]Peculiar Allowance'!$L$41+'[21] FGN 2024 MGT Monthly'!$L$41 -> 541351.33 | H18: =G18-E18 -> 14626.25 | I18: 42138.007 | J18: =G18*0.08 -> 43308.107 | K18: =J18-I18 -> 1170.1 | L18: =J18*12 -> 519697.28 | M18: 13(11) | N18: 337730.83 | O18: =N18*0.025 -> 8443.2708 | P18: 8226.1229 | Q18: =O18-P18 -> 217.14792 | R18: =O18*12 -> 101319.25
A19: 13 | B19: IKIP LEBO | C19: ASST CHIEF PROC. OFFICER | D19: 13 (8) | E19: 497472.75 | F19: 13 (9) | G19: ='[21] FGN 2024 MGT Monthly'!$J$41+'[21]Peculiar Allowance'!$J$41 -> 512098.92 | H19: =G19-E19 -> 14626.167 | I19: 39797.82 | J19: =G19*0.08 -> 40967.913 | K19: =J19-I19 -> 1170.0933 | L19: =J19*12 -> 491614.96 | M19: 13 (9) | N19: ='[21] FGN 2024 MGT Monthly'!$J$41 -> 320359.08 | O19: =N19*0.025 -> 8008.9771 | P19: 7791.8313 | Q19: =O19-P19 -> 217.14583 | R19: =O19*12 -> 96107.725
A20: 14 | B20: ALABI ADESINA MUHYDEEN | C20: HEAD, NILDS LIAISON OFFICE | D20: 13 (8) | E20: 497472.75 | F20: 13 (9) | G20: ='[21] FGN 2024 MGT Monthly'!$J$41+'[21]Peculiar Allowance'!$J$41 -> 512098.92 | H20: =G20-E20 -> 14626.167 | I20: 39797.82 | J20: =G20*0.08 -> 40967.913 | K20: =J20-I20 -> 1170.0933 | L20: =J20*12 -> 491614.96 | M20: 13 (9) | N20: ='[21] FGN 2024 MGT Monthly'!$J$41 -> 320359.08 | Q20: =O20-P20 -> 0 | R20: =O20*12 -> 0
A21: 15 | B21: BASSEY NSONGURUA UDOFIA | C21: PRINC.CONF SEC 1/PPS | D21: 13(7) | E21: 482846.58 | F21: 13(8) | G21: 497472.75 | H21: =G21-E21 -> 14626.167 | I21: 42138.007 | J21: =G21*0.08 -> 39797.82 | K21: =J21-I21 -> -2340.1867 | L21: =J21*12 -> 477573.84 | M21: 13(8) | N21: 311673.25 | O21: =N21*0.025 -> 7791.8313 | P21: 7777.3604 | Q21: =O21-P21 -> 14.470833 | R21: =O21*12 -> 93501.975
A22: 16 | B22: ADUGBA RICHARD TERSEER | C22: ASSIST. CHIEF INFO OFFICER | D22: 13(7) | E22: 482846.58 | F22: 13(7) | G22: 482846.58 | H22: =G22-E22 -> 0 | I22: 42138.007 | J22: =G22*0.08 -> 38627.727 | K22: =J22-I22 -> -3510.28 | L22: =J22*12 -> 463532.72 | M22: 13(7) | N22: 302987.42 | O22: =N22*0.025 -> 7574.6854 | P22: 7571.9667 | Q22: =O22-P22 -> 2.71875 | R22: =O22*12 -> 90896.225
A23: 17 | B23: LUCKY AGWOM | C23: RESEARCH ASSISTANT | D23: 12(8) | E23: 454993.58 | F23: 12(9) | G23: 468828.17 | H23: =G23-E23 -> 13834.583 | I23: 36399.487 | J23: =G23*0.08 -> 37506.253 | K23: =J23-I23 -> 1106.7667 | L23: =J23*12 -> 450075.04 | M23: 12(9) | N23: 294662.92 | Q23: =O23-P23 -> 0 | R23: =O23*12 -> 0
A24: 18 | B24: IDRIS IBRAHIM | C24: PRINCIPAL RESEARCH OFFICER | D24: 12(8) | E24: 454993.58 | F24: 12(9) | G24: 468828.17 | H24: =G24-E24 -> 13834.583 | I24: 36399.487 | J24: =G24*0.08 -> 37506.253 | K24: =J24-I24 -> 1106.7667 | L24: =J24*12 -> 450075.04 | M24: 12(9) | N24: 294662.92 | O24: =N24*0.025 -> 7366.5729 | P24: 7161.1771 | Q24: =O24-P24 -> 205.39583 | R24: =O24*12 -> 88398.875
A25: 19 | B25: FARUQ ATOFARATI | C25: PA (SPECIAL DUTIES) TO DG | D25: 10(7) | E25: 381140.67 | F25: 10(8) | G25: 381140.67 | H25: =G25-E25 -> 0 | I25: 30491.253 | J25: =G25*0.08 -> 30491.253 | K25: =J25-I25 -> 0 | L25: =J25*12 -> 365895.04 | M25: 10(8) | N25: 240874.58 | Q25: =O25-P25 -> 0 | R25: =O25*12 -> 0
A26: 20 | B26: RASHEEDAT DAIBU | C26: SENIOR INFO. OFFICER | D26: 10(8) | E26: 381140.67 | F26: 10(9) | G26: 390135.83 | H26: =G26-E26 -> 8995.1667 | I26: 30491.253 | J26: =G26*0.08 -> 31210.867 | K26: =J26-I26 -> 719.61333 | L26: =J26*12 -> 374530.4 | M26: 10(9) | N26: 246171.17 | O26: =N26*0.025 -> 6154.2792 | P26: 6021.8646 | Q26: =O26-P26 -> 132.41458 | R26: =O26*12 -> 73851.35
A27: 21 | B27: ELIZABETH OGECHUKWU ONYEAKU | C27: ICT OFFICER | D27: 9(10) | H27: =G27-E27 -> 0 | J27: =G27*0.08 -> 0 | K27: =J27-I27 -> 0 | L27: =J27*12 -> 0 | Q27: =O27-P27 -> 0 | R27: =O27*12 -> 0
A28: 22 | B28: VICTOR ASUKWO | C28: SENIOR ICT OFFICER | D28: 10(7) | E28: 372145.33 | F28: 10(7) | G28: 372145.33 | H28: =G28-E28 -> 0 | I28: 30491.253 | J28: =G28*0.08 -> 29771.627 | K28: =J28-I28 -> -719.62667 | L28: =J28*12 -> 357259.52 | M28: 10(7) | N28: ='[21] FGN 2024 MGT Monthly'!$H$39 -> 235577.83 | O28: =N28*0.025 -> 5889.4458 | P28: 5690.3938 | Q28: =O28-P28 -> 199.05208 | R28: =O28*12 -> 70673.35
A29: 23 | B29: NNANDI LIVINUS ATURE | C29: SENIOR RESEARCH OFFICER | D29: 10(7) | E29: 372145.33 | F29: 10(8) | G29: 381140.67 | H29: =G29-E29 -> 8995.3333 | I29: 30491.253 | J29: =G29*0.08 -> 30491.253 | K29: =J29-I29 -> 0 | L29: =J29*12 -> 365895.04 | M29: 10(8) | N29: 240874.58 | O29: =N29*0.025 -> 6021.8646 | P29: 6260.74 | Q29: =O29-P29 -> -238.87542 | R29: =O29*12 -> 72262.375
A30: 24 | B30: ABDULRAHMAN A SULAIMAN | C30: STORE OFFICER | D30: 9(9) | E30: 347016.17 | F30: 9(10) | G30: ='[21]Peculiar Allowance'!$K$38+'[21] FGN 2024 MGT Monthly'!$K$38 -> 355320.67 | H30: =G30-E30 -> 8304.5 | I30: 27761.293 | J30: =G30*0.08 -> 28425.653 | K30: =J30-I30 -> 664.36 | L30: =J30*12 -> 341107.84 | M30: 9(10) | N30: 227615.75 | Q30: =O30-P30 -> 0 | R30: =O30*12 -> 0
A31: 25 | B31: DARE SHEU MAGBON | C31: ADMINISTRATION OFFICER | D31: 9(8) | E31: 338711.67 | F31: 9(9) | G31: 347016.17 | H31: =G31-E31 -> 8304.5 | I31: 27096.933 | J31: =G31*0.08 -> 27761.293 | K31: =J31-I31 -> 664.36 | L31: =J31*12 -> 333135.52 | M31: 9(9) | N31: 222674.58 | Q31: =O31-P31 -> 0 | R31: =O31*12 -> 0
A32: 26 | B32: ABUBAKAR SULAIMAN SODEEQ | C32: SENIOR M&E OFFICER | D32: 10(7) | E32: 372145.33 | F32: 10(7) | G32: 372145.33 | H32: =G32-E32 -> 0 | I32: 29771.627 | J32: =G32*0.08 -> 29771.627 | K32: =J32-I32 -> -5.8207661e-11 | L32: =J32*12 -> 357259.52 | M32: 10(7) | N32: ='[21] FGN 2024 MGT Monthly'!$H$39 -> 235577.83 | O32: =N32*0.025 -> 5889.4458 | P32: 6260.744 | Q32: =O32-P32 -> -371.29817 | R32: =O32*12 -> 70673.35
A33: 27 | B33: JIMOH ADEBAYO ZAKA | C33: SENIOR INFO OFFICER | D33: 10(7) | E33: 372145.33 | F33: 10(7) | G33: 372145.33 | H33: =G33-E33 -> 0 | I33: 29771.627 | J33: =G33*0.08 -> 29771.627 | K33: =J33-I33 -> -5.8207661e-11 | L33: =J33*12 -> 357259.52 | M33: 10(7) | N33: ='[21] FGN 2024 MGT Monthly'!$H$39 -> 235577.83 | O33: =N33*0.025 -> 5889.4458 | P33: 6260.744 | Q33: =O33-P33 -> -371.29817 | R33: =O33*12 -> 70673.35
A34: 28 | B34: ABDULMUSHIN TAWFIQ LADAN | C34: ICT OFFICER | D34: 9(8) | E34: 338711.67 | F34: 9(9) | G34: 347016.17 | H34: =G34-E34 -> 8304.5 | I34: 27096.933 | J34: =G34*0.08 -> 27761.293 | K34: =J34-I34 -> 664.36 | L34: =J34*12 -> 333135.52 | M34: 9(9) | N34: 222674.58 | Q34: =O34-P34 -> 0 | R34: =O34*12 -> 0
A35: 29 | B35: MOHAMMED BELLO | C35: SENIOR PROTOCOL OFFICER | D35: 10(7) | E35: 372145.33 | F35: 10(7) | G35: 372145.33 | H35: =G35-E35 -> 0 | I35: 29771.627 | J35: =G35*0.08 -> 29771.627 | K35: =J35-I35 -> -5.8207661e-11 | L35: =J35*12 -> 357259.52 | M35: 10(7) | N35: ='[21] FGN 2024 MGT Monthly'!$H$39 -> 235577.83 | Q35: =O35-P35 -> 0 | R35: =O35*12 -> 0
A36: 30 | B36: HOLINESS PAUL UDO | C36: ADMINISTRATION OFFICER, M&E | D36: 9(7) | E36: 330407.08 | F36: 9(8) | G36: 338711.67 | H36: =G36-E36 -> 8304.5833 | I36: 29771.627 | J36: =G36*0.08 -> 27096.933 | K36: =J36-I36 -> -2674.6933 | L36: =J36*12 -> 325163.2 | M36: 9(8) | N36: 217733.42 | O36: =N36*0.025 -> 5443.3354 | P36: 5319.8 | Q36: =O36-P36 -> 123.53542 | R36: =O36*12 -> 65320.025
A37: 31 | B37: CHARITY UDO AKAN | C37: ADMINISTRATION OFFICER, M&E | D37: 9(7) | E37: 330408.08 | F37: 9(8) | G37: 338711.67 | H37: =G37-E37 -> 8303.5833 | I37: 26432.647 | J37: =G37*0.08 -> 27096.933 | K37: =J37-I37 -> 664.28667 | L37: =J37*12 -> 325163.2 | M37: 9(8) | N37: 217733.42 | O37: =N37*0.025 -> 5443.3354 | P37: 5319.8 | Q37: =O37-P37 -> 123.53542 | R37: =O37*12 -> 65320.025
A38: 32 | B38: SANI UMAR IBRAHIM | C38: STORE OFFICER | D38: 9(7) | E38: 330409.08 | F38: 9(8) | G38: 338711.67 | H38: =G38-E38 -> 8302.5833 | I38: 26432.727 | J38: =G38*0.08 -> 27096.933 | K38: =J38-I38 -> 664.20667 | L38: =J38*12 -> 325163.2 | M38: 9(8) | N38: 217733.42 | Q38: =O38-P38 -> 0 | R38: =O38*12 -> 0
A39: 33 | B39: FAHAD ABUBUKAR LONGMAN | C39: ICT OFFICER | D39: 9(7) | E39: 330409.08 | F39: 9(8) | G39: 338711.67 | H39: =G39-E39 -> 8302.5833 | I39: 26432.727 | J39: =G39*0.08 -> 27096.933 | K39: =J39-I39 -> 664.20667 | L39: =J39*12 -> 325163.2 | M39: 9(8) | N39: 217733.42 | O39: =N39*0.025 -> 5443.3354 | P39: 5319.8 | Q39: =O39-P39 -> 123.53542 | R39: =O39*12 -> 65320.025
A40: 34 | B40: HARUNA JIBRIL AMEH | C40: ASST. ADMIN. OFFICER | D40: 8(9) | E40: 301910.75 | F40: 8(10) | G40: 308920.67 | H40: =G40-E40 -> 7009.9167 | I40: 24152.86 | J40: =G40*0.08 -> 24713.653 | K40: =J40-I40 -> 560.79333 | L40: =J40*12 -> 296563.84 | M40: 8(10) | N40: 200549.42 | O40: =N40*0.025 -> 5013.7354 | P40: 4909.1104 | Q40: =O40-P40 -> 104.625 | R40: =O40*12 -> 60164.825
A41: 35 | B41: RAMATU IBRAHIM ABDULRAHEEM | C41: INFORMATION OFFICER | D41: 8(8) | E41: 294900.83 | F41: 8(9) | G41: 301910.75 | H41: =G41-E41 -> 7009.9167 | I41: 23592.067 | J41: =G41*0.08 -> 24152.86 | K41: =J41-I41 -> 560.79333 | L41: =J41*12 -> 289834.32 | M41: 8(9) | N41: 196364.42 | O41: =N41*0.025 -> 4909.1104 | P41: 4804.4854 | Q41: =O41-P41 -> 104.625 | R41: =O41*12 -> 58909.325
A42: 36 | B42: EDIDIONG EZEKIEL ATAT | C42: ASSIST PROCUREMENT OFFICER | D42: 8(7) | E42: 287890.92 | F42: 8(8) | G42: 294900.83 | H42: =G42-E42 -> 7009.9167 | I42: 23031.273 | J42: =G42*0.08 -> 23592.067 | K42: =J42-I42 -> 560.79333 | L42: =J42*12 -> 283104.8 | M42: 8(8) | N42: 192179.42 | O42: =N42*0.025 -> 4804.4854 | P42: =4699.86 -> 4699.86 | Q42: =O42-P42 -> 104.62542 | R42: =O42*12 -> 57653.825
A43: 37 | B43: MAHMUD ADEWOLE HASSAN | C43: ASSIST ICT OFFICER | D43: 8(7) | E43: 287890.92 | F43: 8(8) | G43: 294900.83 | H43: =G43-E43 -> 7009.9167 | I43: 23031.273 | J43: =G43*0.08 -> 23592.067 | K43: =J43-I43 -> 560.79333 | L43: =J43*12 -> 283104.8 | M43: 8(8) | N43: 192179.42 | Q43: =O43-P43 -> 0 | R43: =O43*12 -> 0
A44: 38 | B44: YUSUF KABIRU TURAKI | C44: ASSIST ICT OFFICER | D44: 8(7) | E44: 287890.92 | F44: 8(8) | G44: 294900.83 | H44: =G44-E44 -> 7009.9167 | I44: 23031.273 | J44: =G44*0.08 -> 23592.067 | K44: =J44-I44 -> 560.79333 | L44: =J44*12 -> 283104.8 | M44: 8(8) | N44: 192179.42 | Q44: =O44-P44 -> 0 | R44: =O44*12 -> 0
A45: 39 | B45: FATIMA OMAR IBRAHIM | C45: ASSIST PROTOCOL OFFICER | D45: 8(7) | E45: 287890.92 | F45: 8(8) | G45: 294900.83 | H45: =G45-E45 -> 7009.9167 | I45: 23031.273 | J45: =G45*0.08 -> 23592.067 | K45: =J45-I45 -> 560.79333 | L45: =J45*12 -> 283104.8 | M45: 8(8) | N45: 192179.42 | Q45: =O45-P45 -> 0 | R45: =O45*12 -> 0
A46: 40 | B46: EBERE ANASTHESIA IGWE | C46: ASSIST ICT OFFICER | D46: 8(7) | E46: 287890.92 | F46: 8(8) | G46: 294900.83 | H46: =G46-E46 -> 7009.9167 | I46: 23031.273 | J46: =G46*0.08 -> 23592.067 | K46: =J46-I46 -> 560.79333 | L46: =J46*12 -> 283104.8 | M46: 8(8) | N46: 192179.42 | Q46: =O46-P46 -> 0 | R46: =O46*12 -> 0
A47: 41 | B47: ALIYU GARBA LERE | C47: ASSIST INFORMATION OFFICER | D47: 8(7) | E47: 287891.92 | F47: 8(8) | G47: 294900.83 | H47: =G47-E47 -> 7008.9167 | I47: 23031.353 | J47: =G47*0.08 -> 23592.067 | K47: =J47-I47 -> 560.71333 | L47: =J47*12 -> 283104.8 | M47: 8(8) | N47: 192179.42 | Q47: =O47-P47 -> 0 | R47: =O47*12 -> 0
B48: TOTAL | C48: 41 | E48: =SUM(E7:E47) -> 20203860 | G48: =SUM(G7:G47) -> 20529918 | H48: =SUM(H7:H47) -> 326057.83 | I48: =SUM(I7:I47) -> 1394628.6 | J48: =SUM(J7:J47) -> 1412277.9 | K48: =SUM(K7:K47) -> 17649.253 | L48: =SUM(L7:L47) -> 16947335 | M48: =SUM(M7:M47) -> 0 | N48: =SUM(N7:N47) -> 11102994 | ... R48: =SUM(R7:R47) -> 1778670.7
B50: INTERNAL AUDIT
A51: 1 | B51: OSANAIYE DAVID AKINYEMI | C51: DIRECTOR INTERNAL AUDIT | D51: 17(9) | E51: 1747106.4 | F51: 17(9) | G51: 1747106.4 | H51: =G51-E51 -> 0 | I51: 139768.51 | J51: =G51*0.08 -> 139768.51 | K51: =J51-I51 -> 0 | L51: =J51*12 -> 1677222.2 | M51: 17(9) | N51: 1086777.1 | Q51: =O51-P51 -> 0 | R51: =O51*12 -> 0
A52: 2 | B52: EVELYN ETONKE AGAN | C52: ASST DIR AUDIT | D52: 15(7) | E52: 700713.92 | F52: 15(8) | G52: 722595.5 | H52: =G52-E52 -> 21881.583 | I52: 56057.113 | J52: =G52*0.08 -> 57807.64 | K52: =J52-I52 -> 1750.5267 | L52: =J52*12 -> 693691.68 | M52: 15(8) | N52: 445995.83 | Q52: =O52-P52 -> 0 | R52: =O52*12 -> 0
A53: 3 | B53: JAMILA ABDUL | C53: SENIOR INTERNAL AUDITOR | D53: 10(8) | E53: 381140.67 | F53: 10(9) | G53: 390135.83 | H53: =G53-E53 -> 8995.1667 | I53: 30491.253 | J53: =G53*0.08 -> 31210.867 | K53: =J53-I53 -> 719.61333 | L53: =J53*12 -> 374530.4 | M53: 10(9) | N53: 246171.17 | O53: =N53*0.025 -> 6154.2792 | P53: 6021.8646 | Q53: =O53-P53 -> 132.41458 | R53: =O53*12 -> 73851.35
A54: 4 | B54: IJEOMA EWELUKWA | C54: PRINCIPAL AUDIT OFFICER | D54: 12(7) | E54: 441159 | F54: 12(8) | G54: 454993.58 | H54: =G54-E54 -> 13834.583 | I54: 35292.72 | J54: =G54*0.08 -> 36399.487 | K54: =J54-I54 -> 1106.7667 | L54: =J54*12 -> 436793.84 | M54: 12(8) | N54: 286447.08 | Q54: =O54-P54 -> 0 | R54: =O54*12 -> 0
A55: 5 | B55: HASSAN ABDULHADI | C55: SENIOR INTERNAL AUDITOR | D55: 9(7) | E55: 330407.08 | F55: 9(8) | G55: 338711.67 | H55: =G55-E55 -> 8304.5833 | I55: 26432.567 | J55: =G55*0.08 -> 27096.933 | K55: =J55-I55 -> 664.36667 | L55: =J55*12 -> 325163.2 | M55: 9(8) | N55: 217733.42 | O55: =N55*0.025 -> 5443.3354 | P55: 5319.8 | Q55: =O55-P55 -> 123.53542 | R55: =O55*12 -> 65320.025
A56: 6 | B56: YUSUF YUSUF DAYYABU | C56: INERNAL AUDIT OFFICER | D56: 9(8) | E56: 338711.67 | F56: 9(9) | G56: 347016.17 | H56: =G56-E56 -> 8304.5 | I56: 27096.933 | J56: =G56*0.08 -> 27761.293 | K56: =J56-I56 -> 664.36 | L56: =J56*12 -> 333135.52 | M56: 9(9) | N56: 222674.58 | O56: =N56*0.025 -> 5566.8646 | P56: 5443.3354 | Q56: =O56-P56 -> 123.52917 | R56: =O56*12 -> 66802.375
A57: 7 | B57: UDONSI QUEENETH CHIWENDU | C57: ASSIST PROGRAMME OFFICER | D57: 8(7) | E57: 287890.92 | F57: 8(8) | G57: 294900.83 | H57: =G57-E57 -> 7009.9167 | I57: 23031.273 | J57: =G57*0.08 -> 23592.067 | K57: =J57-I57 -> 560.79333 | L57: =J57*12 -> 283104.8 | M57: 8(8) | N57: 192179.42 | Q57: =O57-P57 -> 0 | R57: =O57*12 -> 0
C58: 7 | E58: =SUM(E51:E57) -> 4227129.7 | G58: =SUM(G51:G57) -> 4295460 | H58: =SUM(H51:H57) -> 68330.333 | I58: =SUM(I51:I57) -> 338170.37 | J58: =SUM(J51:J57) -> 343636.8 | K58: =SUM(K51:K57) -> 5466.4267 | L58: =SUM(L51:L57) -> 4123641.6 | M58: =SUM(M51:M57) -> 0 | N58: =SUM(N51:N57) -> 2697978.6 | ... R58: =SUM(R51:R57) -> 205973.75
B60: LEG. SUPPORT SEVICES
A61: 1 | B61: BETHEL UZOMA IHUGBA | C61: AG. DIRECTOR, AEEP | D61: 17(7) | E61: 1647612 | F61: 17(8) | G61: 1697359.3 | H61: =G61-E61 -> 49747.333 | I61: 131808.96 | J61: =G61*0.08 -> 135788.75 | K61: =J61-I61 -> 3979.7867 | L61: =J61*12 -> 1629465 | M61: 17(8) | N61: 1056272.8 | Q61: =O61-P61 -> 0 | R61: =O61*12 -> 0
A62: 2 | B62: OGUCHE SAMUEL | C62: SNR RESEARCH FELLOW | D62: 15(9) | E62: 744477 | F62: 15(9) | G62: 744477 | H62: =G62-E62 -> 0 | I62: 59558.16 | J62: =G62*0.08 -> 59558.16 | K62: =J62-I62 -> 0 | L62: =J62*12 -> 714697.92 | M62: 15(9) | N62: 459010.5 | Q62: =O62-P62 -> 0 | R62: =O62*12 -> 0
A63: 3 | B63: IBRAHIM USMAN | C63: SNR RESEARCH FELLOW | D63: 15(9) | E63: 744477 | F63: 15(9) | G63: 744477 | H63: =G63-E63 -> 0 | I63: 59558.16 | J63: =G63*0.08 -> 59558.16 | K63: =J63-I63 -> 0 | L63: =J63*12 -> 714697.92 | M63: 15(9) | N63: 459010.5 | O63: =N63*0.025 -> 11475.263 | P63: 11475.263 | Q63: =O63-P63 -> 0 | R63: =O63*12 -> 137703.15
A64: 4 | B64: DR MOHAMMED O. AMALI | C64: SNR RESEARCH FELLOW | D64: 15(8) | E64: 722595.5 | F64: 15(9) | G64: 744477 | H64: =G64-E64 -> 21881.5 | I64: 57807.64 | J64: =G64*0.08 -> 59558.16 | K64: =J64-I64 -> 1750.52 | L64: =J64*12 -> 714697.92 | M64: 15(9) | N64: 459010.5 | Q64: =O64-P64 -> 0 | R64: =O64*12 -> 0
A65: 5 | B65: YAHAYA SHAMSU | C65: SNR RESEARCH FELLOW | D65: 15(7) | E65: 700713.92 | F65: 15(8) | G65: 722595.5 | H65: =G65-E65 -> 21881.583 | I65: 56057.113 | J65: =G65*0.08 -> 57807.64 | K65: =J65-I65 -> 1750.5267 | L65: =J65*12 -> 693691.68 | M65: 15(8) | N65: 445995.83 | P65: 0 | Q65: =O65-P65 -> 0 | R65: =O65*12 -> 0
A66: 6 | B66: CHIDEBE MATHEW NWANKWO | C66: SNR RESEARCH FELLOW | D66: 15(7) | E66: 700713.92 | F66: 15(8) | G66: 722595.5 | H66: =G66-E66 -> 21881.583 | I66: 56057.113 | J66: =G66*0.08 -> 57807.64 | K66: =J66-I66 -> 1750.5267 | L66: =J66*12 -> 693691.68 | M66: 15(8) | N66: 445995.83 | P66: 0 | Q66: =O66-P66 -> 0 | R66: =O66*12 -> 0
A67: 7 | B67: UMAR MUSA PADAH | C67: PRINC. RESEARCH OFFICER | D67: 12(7) | E67: 441159 | F67: 12(8) | G67: 454993.58 | H67: =G67-E67 -> 13834.583 | I67: 35292.72 | J67: =G67*0.08 -> 36399.487 | K67: =J67-I67 -> 1106.7667 | L67: =J67*12 -> 436793.84 | M67: 12(8) | N67: 286447.08 | Q67: =O67-P67 -> 0 | R67: =O67*12 -> 0
A68: 8 | B68: BILKIS S. LAWAL-GAMBARI | C68: RESEARCH OFFICER | D68: 10(9) | E68: 390135.83 | F68: 10(10) | G68: ='[21] FGN 2024 MGT Monthly'!$K$39+'[21]Peculiar Allowance'!$K$39 -> 399131.17 | H68: =G68-E68 -> 8995.3333 | I68: 31210.867 | J68: =G68*0.08 -> 31930.493 | K68: =J68-I68 -> 719.62667 | L68: =J68*12 -> 383165.92 | M68: 10(10) | N68: 251467.92 | Q68: =O68-P68 -> 0 | R68: =O68*12 -> 0
A69: 9 | B69: UMOH USENOBONG EMMANUEL | C69: SENIOR RESEARCH OFFICER | D69: 10(7) | E69: 372145.33 | F69: 10(8) | G69: 381140.67 | H69: =G69-E69 -> 8995.3333 | I69: 29771.627 | J69: =G69*0.08 -> 30491.253 | K69: =J69-I69 -> 719.62667 | L69: =J69*12 -> 365895.04 | M69: 10(8) | N69: 240874.58 | Q69: =O69-P69 -> 0 | R69: =O69*12 -> 0
A70: 10 | B70: ZAINAB AKINDE | C70: RESEARCH OFFICER | D70: 9(9) | E70: 347016.17 | F70: 9(10) | G70: 355320.67 | H70: =G70-E70 -> 8304.5 | I70: 27761.293 | J70: =G70*0.08 -> 28425.653 | K70: =J70-I70 -> 664.36 | L70: =J70*12 -> 341107.84 | M70: 9(10) | N70: 227615.75 | Q70: =O70-P70 -> 0 | R70: =O70*12 -> 0
A71: 11 | B71: GUNAT NANSAK MARK | C71: RESEARCH OFFICER | D71: 9(9) | E71: 347016.17 | F71: 9(10) | G71: 355320.67 | H71: =G71-E71 -> 8304.5 | I71: 27761.293 | J71: =G71*0.08 -> 28425.653 | K71: =J71-I71 -> 664.36 | L71: =J71*12 -> 341107.84 | M71: 9(10) | N71: 227615.75 | Q71: =O71-P71 -> 0 | R71: =O71*12 -> 0
A72: 12 | B72: MANDU ESSIEN NDEM | C72: RESEARCH OFFICER | D72: 9(7) | E72: 330407.08 | F72: 9(8) | G72: 338711.67 | H72: =G72-E72 -> 8304.5833 | I72: 26432.567 | J72: =G72*0.08 -> 27096.933 | K72: =J72-I72 -> 664.36667 | L72: =J72*12 -> 325163.2 | M72: 9(8) | N72: 217733.42 | Q72: =O72-P72 -> 0 | R72: =O72*12 -> 0
B73: TOTAL | C73: 12 | E73: =SUM(E61:E72) -> 7488468.9 | G73: =SUM(G61:G72) -> 7660599.8 | H73: =SUM(H61:H72) -> 172130.83 | I73: =SUM(I61:I72) -> 599077.51 | J73: =SUM(J61:J72) -> 612847.98 | K73: =SUM(K61:K72) -> 13770.467 | L73: =SUM(L61:L72) -> 7354175.8 | M73: =SUM(M61:M72) -> 0 | N73: =SUM(N61:N72) -> 4777050.5 | ... R73: =SUM(R61:R72) -> 137703.15
B75: LEGAL SERVICES
A76: 1 | B76: DR SHUAIBU DANWANKA | C76: DIRECTOR LEGAL SERVICES | D76: 17(9) | E76: 1747106.4 | F76: 17(9) | G76: 1747106.4 | H76: =G76-E76 -> 0 | I76: 139768.51 | J76: 139768.51 | K76: =J76-I76 -> 0 | L76: =J76*12 -> 1677222.2 | M76: 17(9) | N76: 1086777.1 | P76: 0 | Q76: =O76-P76 -> 0 | R76: =O76*12 -> 0
A77: 2 | B77: ABDULSALAM BAKO | C77: MANAGER, LEGAL SERVICES | D77: 15 (9) | E77: 744477 | F77: 15 (9) | G77: 744477 | H77: =G77-E77 -> 0 | I77: 59558.16 | J77: 59558.16 | K77: =J77-I77 -> 0 | L77: =J77*12 -> 714697.92 | M77: 15 (9) | N77: 459010.5 | P77: 0 | Q77: =O77-P77 -> 0 | R77: =O77*12 -> 0
B78: TOTAL | C78: 2 | E78: =SUM(E76:E77) -> 2491583.4 | G78: =SUM(G76:G77) -> 2491583.4 | H78: =SUM(H76:H77) -> 0 | I78: =SUM(I76:I77) -> 199326.67 | J78: =SUM(J76:J77) -> 199326.67 | K78: =SUM(K76:K77) -> 0 | L78: =J78*12 -> 2391920.1 | P78: =SUM(P76:P77) -> 0
B80: DEMOCRACY & GOVERNANCE
A81: 1 | B81: NGARA CHRISTOPHER OCHANJA | C81: DEP DIR DEM & GOVERNANCE | D81: 16(9) | E81: 905306.75 | F81: 16(9) | G81: 905306.75 | H81: =G81-E81 -> 0 | I81: 72424.54 | J81: =G81*0.08 -> 72424.54 | K81: =J81-I81 -> 0 | L81: =J81*12 -> 869094.48 | M81: 16(9) | N81: 554669.5 | O81: =N81*0.025 -> 13866.737 | P81: 13866.737 | Q81: =O81-P81 -> 0 | R81: =O81*12 -> 166400.85
A82: 2 | B82: EJALONIBU GANIYU LAYI | C82: RESEARCH FELLOW 1 | D82: 14(9) | E82: 558165.25 | F82: 14(10) | G82: 573911.08 | H82: =G82-E82 -> 15745.833 | I82: 44653.22 | J82: =G82*0.08 -> 45912.887 | K82: =J82-I82 -> 1259.6667 | L82: =J82*12 -> 550954.64 | M82: 14(10) | N82: 357066.67 | Q82: =O82-P82 -> 0 | R82: =O82*12 -> 0
A83: 3 | B83: MARTINS SOLOMON UDOM | C83: RESEARCH FELLOW 11 | D83: 13(7) | E83: 482846.58 | F83: 13(8) | G83: 497472.75 | H83: =G83-E83 -> 14626.167 | I83: 38627.727 | J83: =G83*0.08 -> 39797.82 | K83: =J83-I83 -> 1170.0933 | L83: =J83*12 -> 477573.84 | M83: 13(8) | N83: 311673.25 | O83: =N83*0.025 -> 7791.8313 | P83: 7574.69 | Q83: =O83-P83 -> 217.14125 | R83: =O83*12 -> 93501.975
A84: 4 | B84: ISHAKA DELE | C84: RESEARCH FELLOW 11 | D84: 13(7) | E84: 482846.58 | F84: 13(8) | G84: 497472.75 | H84: =G84-E84 -> 14626.167 | I84: 38627.727 | J84: =G84*0.08 -> 39797.82 | K84: =J84-I84 -> 1170.0933 | L84: =J84*12 -> 477573.84 | M84: 13(8) | N84: 311673.25 | O84: =N84*0.025 -> 7791.8313 | P84: 7574.69 | Q84: =O84-P84 -> 217.14125 | R84: =O84*12 -> 93501.975
A85: 5 | B85: UDEFUNA NNADOZIE PATRICK | C85: RESEARCH OFFICER | D85: 12(9) | E85: 468828.17 | F85: 12(10) | G85: 482662.67 | H85: =G85-E85 -> 13834.5 | I85: 37506.253 | J85: =G85*0.08 -> 38613.013 | K85: =J85-I85 -> 1106.76 | L85: =J85*12 -> 463356.16 | M85: 12(10) | N85: 302878.67 | O85: =N85*0.025 -> 7571.9667 | P85: =7366.57 -> 7366.57 | Q85: =O85-P85 -> 205.39667 | R85: =O85*12 -> 90863.6
A86: 6 | B86: SHAFIU YAHYA MIKAIL | C86: PRINCIPAL RESEARCH OFFICER | D86: 12(9) | E86: 468828.17 | F86: 12(10) | G86: 482662.67 | H86: =G86-E86 -> 13834.5 | I86: 37506.253 | J86: =G86*0.08 -> 38613.013 | K86: =J86-I86 -> 1106.76 | L86: =J86*12 -> 463356.16 | M86: 12(10) | N86: 302878.67 | Q86: =O86-P86 -> 0 | R86: =O86*12 -> 0
A87: 7 | B87: HASSAN YERIMA | C87: PRINCIPAL RESEARCH OFFICER | D87: 12(9) | E87: 468828.17 | F87: 12(10) | G87: 482662.67 | H87: =G87-E87 -> 13834.5 | I87: 37506.253 | J87: =G87*0.08 -> 38613.013 | K87: =J87-I87 -> 1106.76 | L87: =J87*12 -> 463356.16 | M87: 12(10) | N87: 302878.67 | Q87: =O87-P87 -> 0 | R87: =O87*12 -> 0
A88: 8 | B88: HAUWA PATE SADIQ | C88: ASST CHIEF PROGRAMME OFFICER | D88: 13(7) | E88: 482846.58 | F88: 13(7) | G88: 482846.58 | H88: =G88-E88 -> 0 | I88: 38627.727 | J88: =G88*0.08 -> 38627.727 | K88: =J88-I88 -> -5.8207661e-11 | L88: =J88*12 -> 463532.72 | M88: 13(7) | N88: 302987.42 | Q88: =O88-P88 -> 0 | R88: =O88*12 -> 0
A89: 9 | B89: OBOT ETIMBUK EMMANUEL | C89: PRINCIPAL INFO. OFFICER | D89: 12(7) | E89: 441159 | F89: 12(8) | G89: 454993.58 | H89: =G89-E89 -> 13834.583 | I89: 35292.72 | J89: =G89*0.08 -> 36399.487 | K89: =J89-I89 -> 1106.7667 | L89: =J89*12 -> 436793.84 | M89: 12(8) | N89: 286447.08 | O89: =N89*0.025 -> 7161.1771 | P89: 6955.7812 | Q89: =O89-P89 -> 205.39583 | R89: =O89*12 -> 85934.125
A90: 10 | B90: KOLAPO Q. ABAYOMI | C90: RESEARCH OFFICER | D90: 10(9) | E90: 390135.83 | F90: 10(10) | G90: 399131.17 | H90: =G90-E90 -> 8995.3333 | I90: 31210.867 | J90: =G90*0.08 -> 31930.493 | K90: =J90-I90 -> 719.62667 | L90: =J90*12 -> 383165.92 | M90: 10(10) | N90: 251467.92 | O90: =N90*0.025 -> 6286.6979 | P90: 6154.2792 | Q90: =O90-P90 -> 132.41875 | R90: =O90*12 -> 75440.375
A91: 11 | B91: SALIHU SHAMSUDEEN OPEYEMI | C91: PROGRAMME OFFICER | D91: 9(7) | E91: 330407.08 | F91: 9(8) | G91: 338711.67 | H91: =G91-E91 -> 8304.5833 | I91: 26432.567 | J91: =G91*0.08 -> 27096.933 | K91: =J91-I91 -> 664.36667 | L91: =J91*12 -> 325163.2 | M91: 9(8) | N91: 217733.42 | Q91: =O91-P91 -> 0 | R91: =O91*12 -> 0
B92: TOTAL | C92: 11 | E92: =SUM(E81:E91) -> 5480198.2 | G92: =SUM(G81:G91) -> 5597834.3 | H92: =SUM(H81:H91) -> 117636.17 | I92: =SUM(I81:I91) -> 438415.85 | J92: =SUM(J81:J91) -> 447826.75 | K92: =SUM(K81:K91) -> 9410.8933 | L92: =SUM(L81:L91) -> 5373921 | M92: =SUM(M81:M91) -> 0 | N92: =SUM(N81:N91) -> 3502354.5 | ... R92: =SUM(R81:R91) -> 605642.9
B94: DEPARTMENT OF STUDIES
A95: 1 | B95: DR ASIMIYU G. ABIOLA | C95: DIRECTOR POST GRADUATE | D95: 17(9) | E95: 1747106.4 | F95: 17(9) | G95: 1747106.4 | H95: =G95-E95 -> 0 | I95: 139768.51 | J95: =G95*0.08 -> 139768.51 | K95: =J95-I95 -> 0 | L95: =J95*12 -> 1677222.2 | M95: 17(9) | N95: 1086777.1 | P95: 0 | Q95: =O95-P95 -> 0 | R95: =O95*12 -> 0
A96: 2 | B96: AYOBOLU OLAJIDE OLUFUNSHO | C96: ASSISTANT DIR. EXXAMS & RECORD | D96: 15(7) | E96: 722595.5 | F96: 15(8) | G96: 722595.5 | H96: =G96-E96 -> 0 | I96: 57807.64 | J96: =G96*0.08 -> 57807.64 | K96: =J96-I96 -> 0 | L96: =J96*12 -> 693691.68 | M96: 15(8) | N96: 445995.83 | Q96: =O96-P96 -> 0 | R96: =O96*12 -> 0
A97: 3 | B97: DR. HADIZA SAIDU | C97: ASSISTANT DIRECTOR | D97: 15(7) | E97: 722595.5 | F97: 15(8) | G97: 722595.5 | H97: =G97-E97 -> 0 | I97: 57807.64 | J97: =G97*0.08 -> 57807.64 | K97: =J97-I97 -> 0 | L97: =J97*12 -> 693691.68 | M97: 15(8) | N97: 445995.83 | Q97: =O97-P97 -> 0 | R97: =O97*12 -> 0
A98: 4 | B98: ANTHONY EDET | C98: CHIEF PROGRAMMES OFFICER | D98: 14(10) | E98: 573911.08 | F98: 14(11) | G98: ='[21]Peculiar Allowance'!$L$42+'[21] FGN 2024 MGT Monthly'!$L$42 -> 589657 | H98: =G98-E98 -> 15745.917 | I98: 45912.887 | J98: =G98*0.08 -> 47172.56 | K98: =J98-I98 -> 1259.6733 | L98: =J98*12 -> 566070.72 | M98: 14(11) | N98: 366417.5 | O98: =N98*0.025 -> 9160.4375 | P98: 8926.6667 | Q98: =O98-P98 -> 233.77083 | R98: =O98*12 -> 109925.25
A99: 5 | B99: CHRISTIAN MADUABUCHI ODO | C99: ASSIST. CHIEF ICT OFFICER | D99: 13(7) | E99: 482846.58 | F99: 13(8) | G99: 497472.75 | H99: =G99-E99 -> 14626.167 | I99: 38627.727 | J99: =G99*0.08 -> 39797.82 | K99: =J99-I99 -> 1170.0933 | L99: =J99*12 -> 477573.84 | M99: 13(8) | N99: 311673.25 | O99: =N99*0.025 -> 7791.8313 | P99: 7574.6854 | Q99: =O99-P99 -> 217.14583 | R99: =O99*12 -> 93501.975
A100: 6 | B100: DR. IBANGA ISSAC JONAH | C100: ASSIST. CHIEF PROGRM OFFICER | D100: 13(7) | E100: 482846.58 | F100: 13(8) | G100: 497472.75 | H100: =G100-E100 -> 14626.167 | I100: 38627.727 | J100: =G100*0.08 -> 39797.82 | K100: =J100-I100 -> 1170.0933 | L100: =J100*12 -> 477573.84 | M100: 13(8) | N100: 311673.25 | Q100: =O100-P100 -> 0 | R100: =O100*12 -> 0
A101: 7 | B101: IGWE STACY | C101: PRINC. PROGRAMME OFFICER | D101: 12(8) | E101: 454993.58 | F101: 12(9) | G101: 468828.17 | H101: =G101-E101 -> 13834.583 | I101: 36399.487 | J101: =G101*0.08 -> 37506.253 | K101: =J101-I101 -> 1106.7667 | L101: =J101*12 -> 450075.04 | M101: 12(9) | N101: 294662.92 | O101: =N101*0.025 -> 7366.5729 | P101: 7161.1771 | Q101: =O101-P101 -> 205.39583 | R101: =O101*12 -> 88398.875
A102: 8 | B102: MUNIRU JIBRIN | C102: SENIOR PROGRAMME OFFICER | D102: 10(7) | E102: 372145.33 | F102: 10(8) | G102: 381140.67 | H102: =G102-E102 -> 8995.3333 | I102: 29771.627 | J102: =G102*0.08 -> 30491.253 | K102: =J102-I102 -> 719.62667 | L102: =J102*12 -> 365895.04 | M102: 10(8) | N102: 240874.58 | Q102: =O102-P102 -> 0 | R102: =O102*12 -> 0
A103: 9 | B103: OLANIYAN TAIWO ABINBOLA | C103: PROGRAMME OFFICER | D103: 9(8) | E103: 347016.17 | F103: 9(9) | G103: 347016.17 | H103: =G103-E103 -> 0 | I103: 27761.293 | J103: =G103*0.08 -> 27761.293 | K103: =J103-I103 -> 0 | L103: =J103*12 -> 333135.52 | M103: 9(9) | N103: 222674.58 | O103: =N103*0.025 -> 5566.8646 | P103: 5566.8646 | Q103: =O103-P103 -> 0 | R103: =O103*12 -> 66802.375
A104: 10 | B104: MUSA ALKASIM ADAMU | C104: PROGRAMME OFFICER | D104: 9(7) | E104: 330407.08 | F104: 9(8) | G104: 338711.67 | H104: =G104-E104 -> 8304.5833 | I104: 26432.567 | J104: =G104*0.08 -> 27096.933 | K104: =J104-I104 -> 664.36667 | L104: =J104*12 -> 325163.2 | M104: 9(8) | N104: 217733.42 | Q104: =O104-P104 -> 0 | R104: =O104*12 -> 0
A105: 11 | B105: AMINAT JUMOKE SULAIMON | C105: AST. PROGRAMME OFFICER | D105: 8(9) | E105: 301910.75 | F105: 8(10) | G105: 308920.67 | H105: =G105-E105 -> 7009.9167 | I105: 24152.86 | J105: =G105*0.08 -> 24713.653 | K105: =J105-I105 -> 560.79333 | L105: =J105*12 -> 296563.84 | M105: 8(10) | N105: 200549.42 | P105: 0 | Q105: =O105-P105 -> 0 | R105: =O105*12 -> 0
...

Sheet Basic & Pensions (2)
A1: NATIONAL INSTITUTE FOR LEGISLATIVE AND DEMOCRATIC STUDIES
A2: STAFF PAYROLL FOR THE MONTH OF JANUARY, 2026
E3: ='[1]FEB 08'!E11/'[1]FEB 08'!M11 -> #REF!
B4: STAFF NAME | C4: DESIGNATION | D4: GRADE LEVEL | E4: OLD CUM BASIC SALARY | F4: NEW BASIC SALARY | G4: PECULIAR ALLOW | H4: NEW CUM BASIC SALARY | I4: INCREASE IN CUM BASIC SALARY | J4: OLD EMPLOYEE PENSION 8% | K4: NEW EMPLOYEE PENSION 8% | L4: INCREASE IN DEDUCTION | M4: OLD NHF | N4: NEW NHF | O4: INCREASE IN NHF | P4: ANNUAL NEW EMPLOYEE PENSIONS | Q4: ANNUAL NEW NHF
E5: N | F5: N | G5: N | H5: N | I5: N | J5: N | K5: N | L5: N | M5: N | N5: N | O5: N | P5: N | Q5: N
E6: A | F6: B | G6: C | H6: D | I6: E | J6: F | K6: G | L6: H | M6: I | N6: J | O6: K | P6: L | Q6: M
A7: S/N | B7: DG'S OFFICE | H7: (B+C) | I7: (D-A) | J7: (8% of A) | K7: (8% of D) | L7: (G-F) | N7: (2.5% of B) | O7: (J-I) | P7: (J-I) | Q7: (J-I)
A8: 1 | B8: PROF. ABUBAKAR O. SULAIMAN | C8: DIRECTOR GENERAL | D8: CONSOL | E8: 1659751.2 | F8: 1086777.1 | G8: 884360 | H8: =F8+G8 -> 1971137.1 | I8: =H8-E8 -> 311385.92 | L8: =K8-J8 -> 0 | O8: =N8-M8 -> 0 | P8: =K8*12 -> 0 | Q8: =N8*12 -> 0
A9: 2 | B9: RAHEEM USMAN AYIGORO | C9: SA-INFRASTRUCTURE | D9: 16 (9) | E9: 762373.17 | F9: 554669.5 | G9: 350637.25 | H9: =F9+G9 -> 905306.75 | I9: =H9-E9 -> 142933.58 | J9: 60989.853 | K9: =H9*0.08 -> 72424.54 | L9: =K9-J9 -> 11434.687 | O9: =N9-M9 -> 0 | P9: =K9*12 -> 869094.48 | Q9: =N9*12 -> 0
A10: 3 | B10: MARIAM MOHAMMED BELLO | C10: SA- SPECIAL DUTIES | D10: 16 (9) | E10: 762373.17 | F10: 554669.5 | G10: 350637.25 | H10: =F10+G10 -> 905306.75 | I10: =H10-E10 -> 142933.58 | L10: =K10-J10 -> 0 | O10: =N10-M10 -> 0 | P10: =K10*12 -> 0 | Q10: =N10*12 -> 0
A11: 4 | B11: DR IKEME ARTHUR J.O | C11: DEPUTY DIRECTOR, M&E | D11: 16 (9) | E11: 762373.17 | F11: 554669.5 | G11: 350637.25 | H11: =F11+G11 -> 905306.75 | I11: =H11-E11 -> 142933.58 | J11: 60989.853 | K11: =H11*0.08 -> 72424.54 | L11: =K11-J11 -> 11434.687 | M11: 10293.398 | N11: =0.025*F11 -> 13866.737 | O11: =N11-M11 -> 3573.3396 | P11: =K11*12 -> 869094.48 | Q11: =N11*12 -> 166400.85
A12: 5 | B12: ANDRAWUS MUSA | C12: DEP. DIRECTOR, STORES & PROCUREMENT | D12: 16(8) | E12: 716034 | F12: ='[19] FGN 2024 MGT Monthly'!$I$44 -> 539028 | G12: ='[19]Peculiar Allowance'!$I$44 -> 339980.92 | H12: =F12+G12 -> 879008.92 | I12: =H12-E12 -> 162974.92 | J12: 59136.287 | K12: =H12*0.08 -> 70320.713 | L12: =K12-J12 -> 11184.427 | M12: 10293.398 | N12: =0.025*F12 -> 13475.7 | O12: =N12-M12 -> 3182.3021 | P12: =K12*12 -> 843848.56 | Q12: =N12*12 -> 161708.4
A13: 6 | B13: DR FRANCIS NDUM OJIE | C13: AD, TRAINING & IC./SA TO DG | D13: 15(8) | E13: 601396.83 | F13: 445995.83 | G13: 276599.67 | H13: =F13+G13 -> 722595.5 | I13: =H13-E13 -> 121198.67 | J13: 46569.447 | K13: =H13*0.08 -> 57807.64 | L13: =K13-J13 -> 11238.193 | M13: 7859.6313 | N13: =0.025*F13 -> 11149.896 | O13: =N13-M13 -> 3290.2646 | P13: =K13*12 -> 693691.68 | Q13: =N13*12 -> 133798.75
A14: 7 | B14: ALI ABDULLAHI | C14: CHIEF ICT OFFICER | D14: 14(11) | E14: 484373.75 | F14: 366417.5 | G14: 223239.5 | H14: =F14+G14 -> 589657 | I14: =H14-E14 -> 105283.25 | J14: 38749.9 | K14: =H14*0.08 -> 47172.56 | L14: =K14-J14 -> 8422.66 | O14: =N14-M14 -> 0 | P14: =K14*12 -> 566070.72 | Q14: =N14*12 -> 0
A15: 8 | B15: EMILY EKHIDE | C15: SENIOR RESEARCH FELLOW | D15: 15(8) | E15: 601396.83 | F15: ='[18] FGN 2024 MGT Monthly'!$I$43 -> 445995.83 | G15: 276599.67 | H15: =F15+G15 -> 722595.5 | I15: =H15-E15 -> 121198.67 | J15: 46569.45 | K15: =H15*0.08 -> 57807.64 | L15: =K15-J15 -> 11238.19 | O15: =N15-M15 -> 0 | P15: =K15*12 -> 693691.68 | Q15: =N15*12 -> 0
A16: 9 | B16: DORIS DAKDA AARON | C16: RESEARCH FELLOW I | D16: 14(9) | E16: 456622.25 | F16: 347715.92 | G16: 210449.33 | H16: =F16+G16 -> 558165.25 | I16: =H16-E16 -> 101543 | J16: 35419.72 | K16: =H16*0.08 -> 44653.22 | L16: =K16-J16 -> 9233.5 | O16: =N16-M16 -> 0 | P16: =K16*12 -> 535838.64 | Q16: =N16*12 -> 0
A17: 10 | B17: ABDULSALAM S. MUSTAPHA | C17: ASST. DIRECTOR ICT | D17: 15(7) | E17: 582118.08 | F17: 432981.08 | G17: 267732.83 | H17: =F17+G17 -> 700713.92 | I17: =H17-E17 -> 118595.83 | J17: 46569.45 | K17: =H17*0.08 -> 56057.113 | L17: =K17-J17 -> 9487.6633 | O17: =N17-M17 -> 0 | P17: =K17*12 -> 672685.36 | Q17: =N17*12 -> 0
A18: 11 | B18: PERCY TERFA GBAHABO | C18: HEAD, NILDS LIAISON OFFICE | D18: 13(11) | E18: 441804.92 | F18: 337730.83 | G18: 203620.5 | H18: =F18+G18 -> 541351.33 | I18: =H18-E18 -> 99546.417 | J18: 34313.273 | K18: =H18*0.08 -> 43308.107 | L18: =K18-J18 -> 8994.8333 | O18: =N18-M18 -> 0 | P18: =K18*12 -> 519697.28 | Q18: =N18*12 -> 0
A19: 12 | B19: HASSANA AHMED IBRAHIM | C19: PA- TO DG | D19: 13 (10) | E19: 428915.92 | F19: 329044.92 | G19: 197680.17 | H19: =F19+G19 -> 526725.08 | I19: =H19-E19 -> 97809.167 | J19: 33282.153 | K19: =H19*0.08 -> 42138.007 | L19: =K19-J19 -> 8855.8533 | M19: 5607.1771 | N19: =0.025*F19 -> 8226.1229 | O19: =N19-M19 -> 2618.9458 | P19: =K19*12 -> 505656.08 | Q19: =N19*12 -> 98713.475
A20: 13 | B20: IKIP LEBO | C20: ASST CHIEF PROC. OFFICER | D20: 13 (8) | E20: 403138 | F20: 311673.25 | G20: 185799.5 | H20: =F20+G20 -> 497472.75 | I20: =H20-E20 -> 94334.75 | J20: 31219.913 | K20: =H20*0.08 -> 39797.82 | L20: =K20-J20 -> 8577.9067 | M20: 5967.3062 | N20: =0.025*F20 -> 7791.8313 | O20: =N20-M20 -> 1824.525 | P20: =K20*12 -> 477573.84 | Q20: =N20*12 -> 93501.975
A21: 14 | B21: ALABI ADESINA MUHYDEEN | C21: HEAD, NILDS LIAISON OFFICE | D21: 13 (8) | E21: 403138 | F21: 311673.25 | G21: 185799.5 | H21: =F21+G21 -> 497472.75 | I21: =H21-E21 -> 94334.75 | J21: 31219.913 | K21: =H21*0.08 -> 39797.82 | L21: =K21-J21 -> 8577.9067 | O21: =N21-M21 -> 0 | P21: =K21*12 -> 477573.84 | Q21: =N21*12 -> 0
A22: 15 | B22: BASSEY NSONGURUA UDOFIA | C22: PRINC.CONF SEC/PPS | D22: 12(11) | E22: 402278 | F22: ='[18] FGN 2024 MGT Monthly'!$L$40 -> 311094.42 | G22: 185402.75 | H22: =F22+G22 -> 496497.17 | I22: =H22-E22 -> 94219.167 | J22: 31206.92 | K22: =H22*0.08 -> 39719.773 | L22: =K22-J22 -> 8512.8533 | M22: 5257.5625 | N22: =0.025*F22 -> 7777.3604 | O22: =N22-M22 -> 2519.7979 | P22: =K22*12 -> 476637.28 | Q22: =N22*12 -> 93328.325
A23: 16 | B23: ADUGBA RICHARD TERSEER | C23: PRINCIPAL INFO. OFFICER | D23: 12(10) | E23: 390086.5 | F23: 302878.67 | G23: 179784 | H23: =F23+G23 -> 482662.67 | I23: =H23-E23 -> 92576.167 | J23: 30231.613 | K23: =H23*0.08 -> 38613.013 | L23: =K23-J23 -> 8381.4 | N23: =0.025*F23 -> 7571.9667 | O23: =N23-M23 -> 7571.9667 | P23: =K23*12 -> 463356.16 | Q23: =N23*12 -> 90863.6
A24: 17 | B24: LUCKY AGWOM | C24: RESEARCH ASSISTANT | D24: 12(8) | E24: 365704 | F24: 286447.08 | G24: 168546.5 | H24: =F24+G24 -> 454993.58 | I24: =H24-E24 -> 89289.583 | J24: 28281 | K24: =H24*0.08 -> 36399.487 | L24: =K24-J24 -> 8118.4867 | O24: =N24-M24 -> 0 | P24: =K24*12 -> 436793.84 | Q24: =N24*12 -> 0
A25: 18 | B25: IDRIS IBRAHIM | C25: PRINCIPAL RESEARCH OFFICER | D25: 12(8) | E25: 365704 | F25: 286447.08 | G25: 168546.5 | H25: =F25+G25 -> 454993.58 | I25: =H25-E25 -> 89289.583 | J25: 28281 | K25: =H25*0.08 -> 36399.487 | L25: =K25-J25 -> 8118.4867 | O25: =N25-M25 -> 0 | P25: =K25*12 -> 436793.84 | Q25: =N25*12 -> 0
A26: 19 | B26: FARUQ ATOFARATI | C26: PA (SPECIAL DUTIES) TO DG | D26: 10(7) | E26: 293029.67 | F26: 240874.58 | G26: 140266.08 | H26: =F26+G26 -> 381140.67 | I26: =H26-E26 -> 88111 | J26: 23442.373 | K26: =H26*0.08 -> 30491.253 | L26: =K26-J26 -> 7048.88 | O26: =N26-M26 -> 0 | P26: =K26*12 -> 365895.04 | Q26: =N26*12 -> 0
A27: 20 | B27: RASHEEDAT DAIBU | C27: SENIOR INFO. OFFICER | D27: 10(8) | E27: 300965.58 | F27: 240874.58 | G27: 140266.08 | H27: =F27+G27 -> 381140.67 | I27: =H27-E27 -> 80175.083 | J27: 23442.373 | K27: =H27*0.08 -> 30491.253 | L27: =K27-J27 -> 7048.88 | N27: =0.025*F27 -> 6021.8646 | O27: =N27-M27 -> 6021.8646 | P27: =K27*12 -> 365895.04 | Q27: =N27*12 -> 72262.375
A28: 21 | B28: ELIZABETH OGECHUKWU ONYEAKU | C28: ICT OFFICER | D28: 9(10) | E28: 277798 | F28: 227615.75 | G28: 127704.92 | H28: =F28+G28 -> 355320.67 | I28: =H28-E28 -> 77522.667 | J28: 21638.533 | K28: =H28*0.08 -> 28425.653 | L28: =K28-J28 -> 6787.12 | N28: =0.025*F28 -> 5690.3938 | O28: =N28-M28 -> 5690.3938 | P28: =K28*12 -> 341107.84 | Q28: =N28*12 -> 68284.725
A29: 22 | B29: VICTOR ASUKWO | C29: ICT OFFICER | D29: 9(10) | E29: 277798 | F29: 227615.75 | G29: 127704.92 | H29: =F29+G29 -> 355320.67 | I29: =H29-E29 -> 77522.667 | J29: 21638.533 | K29: =H29*0.08 -> 28425.653 | L29: =K29-J29 -> 6787.12 | N29: =0.025*F29 -> 5690.3938 | O29: =N29-M29 -> 5690.3938 | P29: =K29*12 -> 341107.84 | Q29: =N29*12 -> 68284.725
A30: 23 | B30: NNANDI LIVINUS ATURE | C30: RESEARCH ASSISTANT | D30: 9(10) | E30: 277798 | F30: 227615.75 | G30: 127704.92 | H30: =F30+G30 -> 355320.67 | I30: =H30-E30 -> 77522.667 | J30: 21638.533 | K30: =H30*0.08 -> 28425.653 | L30: =K30-J30 -> 6787.12 | O30: =N30-M30 -> 0 | P30: =K30*12 -> 341107.84 | Q30: =N30*12 -> 0
A31: 24 | B31: ABDULRAHMAN A SULAIMAN | C31: STORE OFFICER | D31: 9(9) | E31: 270481.67 | F31: 222674.58 | G31: 124341.58 | H31: =F31+G31 -> 347016.17 | I31: =H31-E31 -> 76534.5 | J31: 21053.227 | K31: =H31*0.08 -> 27761.293 | L31: =K31-J31 -> 6708.0667 | O31: =N31-M31 -> 0 | P31: =K31*12 -> 333135.52 | Q31: =N31*12 -> 0
A32: 25 | B32: DARE SHEU MAGBON | C32: ADMINISTRATION OFFICER | D32: 9(8) | E32: 263165.33 | F32: 217733.42 | G32: 120978.25 | H32: =F32+G32 -> 338711.67 | I32: =H32-E32 -> 75546.333 | J32: 20467.92 | K32: =H32*0.08 -> 27096.933 | L32: =K32-J32 -> 6629.0133 | O32: =N32-M32 -> 0 | P32: =K32*12 -> 325163.2 | Q32: =N32*12 -> 0
A33: 26 | B33: ABUBAKAR SULAIMAN SODEEQ | C33: ADMINISTRATION OFFICER | D33: 9(8) | E33: 263165.33 | F33: 217733.42 | G33: 120978.25 | H33: =F33+G33 -> 338711.67 | I33: =H33-E33 -> 75546.333 | J33: 20467.92 | K33: =H33*0.08 -> 27096.933 | L33: =K33-J33 -> 6629.0133 | O33: =N33-M33 -> 0 | P33: =K33*12 -> 325163.2 | Q33: =N33*12 -> 0
A34: 27 | B34: JIMOH ADEBAYO ZAKA | C34: ASST. OFFICER/COMM | D34: 9(10) | E34: 277798 | F34: 227615.75 | G34: 127704.92 | H34: =F34+G34 -> 355320.67 | I34: =H34-E34 -> 77522.667 | J34: 21638.533 | K34: =H34*0.08 -> 28425.653 | L34: =K34-J34 -> 6787.12 | M34: 3653.5 | N34: =0.025*F34 -> 5690.3938 | O34: =N34-M34 -> 2036.8937 | P34: =K34*12 -> 341107.84 | Q34: =N34*12 -> 68284.725
A35: 28 | B35: ABDULMUSHIN TAWFIQ LADAN | C35: ICT OFFICER | D35: 9(8) | E35: 263165.33 | F35: 217733.42 | G35: 120978.25 | H35: =F35+G35 -> 338711.67 | I35: =H35-E35 -> 75546.333 | J35: 20467.92 | K35: =H35*0.08 -> 27096.933 | L35: =K35-J35 -> 6629.0133 | O35: =N35-M35 -> 0 | P35: =K35*12 -> 325163.2 | Q35: =N35*12 -> 0
A36: 29 | B36: MOHAMMED BELLO | C36: PROTOCOL ASSISTANT | D36: 9(8) | E36: 263165.33 | F36: 217733.42 | G36: 120978.25 | H36: =F36+G36 -> 338711.67 | I36: =H36-E36 -> 75546.333 | J36: 20467.92 | K36: =H36*0.08 -> 27096.933 | L36: =K36-J36 -> 6629.0133 | O36: =N36-M36 -> 0 | P36: =K36*12 -> 325163.2 | Q36: =N36*12 -> 0
A37: 30 | B37: HARUNA JIBRIL AMEH | C37: ASST. ADMIN. OFFICER | D37: 8(9) | E37: 230631.92 | F37: 196364.42 | G37: 105546.33 | H37: =F37+G37 -> 301910.75 | I37: =H37-E37 -> 71278.833 | J37: 17956.78 | K37: =H37*0.08 -> 24152.86 | L37: =K37-J37 -> 6196.08 | N37: =0.025*F37 -> 4909.1104 | O37: =N37-M37 -> 4909.1104 | P37: =K37*12 -> 289834.32 | Q37: =N37*12 -> 58909.325
A38: 31 | B38: RAMATU IBRAHIM ABDULRAHEEM | C38: INFORMATION OFFICER | D38: 8(8) | E38: 224459.75 | F38: 192179.42 | G38: 102721.42 | H38: =F38+G38 -> 294900.83 | I38: =H38-E38 -> 70441.083 | J38: 17463.007 | K38: =H38*0.08 -> 23592.067 | L38: =K38-J38 -> 6129.06 | N38: =0.025*F38 -> 4804.4854 | O38: =N38-M38 -> 4804.4854 | P38: =K38*12 -> 283104.8 | Q38: =N38*12 -> 57653.825
B39: TOTAL | C39: 31 | E39: =SUM(E8:E38) -> 14073004 | F39: =SUM(F8:F38) -> 10680274 | G39: =SUM(G8:G38) -> 6613927.2 | H39: =SUM(H8:H38) -> 17294201 | I39: =SUM(I8:I38) -> 3221197.1 | J39: =SUM(J8:J38) -> 914813.32 | K39: =SUM(K8:K38) -> 1153420.6 | L39: =SUM(L8:L38) -> 238607.23 | ... Q39: =SUM(Q8:Q38) -> 1231995.1
B41: INTERNAL AUDIT
A42: 1 | B42: OSANAIYE DAVID AKINYEMI | C42: DIRECTOR INTERNAL AUDIT | D42: 17(9) | E42: 1435720 | F42: 1086777.1 | G42: 660329.33 | H42: =F42+G42 -> 1747106.4 | I42: =H42-E42 -> 311386.42 | J42: 114857.6 | K42: =H42*0.08 -> 139768.51 | L42: =K42-J42 -> 24910.913 | O42: =N42-M42 -> 0 | P42: =K42*12 -> 1677222.2
A43: 2 | B43: JAMILA ABDUL | C43: SENIOR INTERNAL AUDITOR | D43: 10(8) | E43: 300965.58 | F43: 240874.58 | G43: 140266.08 | H43: =F43+G43 -> 381140.67 | I43: =H43-E43 -> 80175.083 | J43: 23442.373 | K43: =H43*0.08 -> 30491.253 | L43: =K43-J43 -> 7048.88 | N43: =0.025*F43 -> 6021.8646 | O43: =N43-M43 -> 6021.8646 | P43: =K43*12 -> 365895.04
A44: 3 | B44: IJEOMA EWELUKWA | C44: SENIOR INTERNAL AUDITOR | D44: 10(9) | E44: 308901.5 | F44: 246171.17 | G44: 143964.67 | H44: =F44+G44 -> 390135.83 | I44: =H44-E44 -> 81234.333 | J44: 24077.247 | K44: =H44*0.08 -> 31210.867 | L44: =K44-J44 -> 7133.62 | O44: =N44-M44 -> 0 | P44: =K44*12 -> 374530.4
A45: 4 | B45: YUSUF YUSUF DAYYABU | C45: INERNAL AUDIT OFFICER | D45: 9(8) | E45: 263165.33 | F45: 217733.42 | G45: 120978.25 | H45: =F45+G45 -> 338711.67 | I45: =H45-E45 -> 75546.333 | J45: 20467.92 | K45: =H45*0.08 -> 27096.933 | L45: =K45-J45 -> 6629.0133 | N45: =0.025*F45 -> 5443.3354 | O45: =N45-M45 -> 5443.3354 | P45: =K45*12 -> 325163.2
C46: 4 | E46: =SUM(E42:E45) -> 2308752.4 | F46: =SUM(F42:F45) -> 1791556.2 | G46: =SUM(G42:G45) -> 1065538.3 | H46: =SUM(H42:H45) -> 2857094.6 | I46: =SUM(I42:I45) -> 548342.17 | J46: =SUM(J42:J45) -> 182845.14 | K46: =SUM(K42:K45) -> 228567.57 | L46: =SUM(L42:L45) -> 45722.427 | ... Q46: =SUM(Q42:Q45) -> 0
B48: LEG. SUPPORT SEVICES
A49: 1 | B49: BETHEL UZOMA IHUGBA | C49: DEPUTY DIRECTOR, LEGAL RESEARCH | D49: 16(9) | E49: 762373.17 | F49: 554669.5 | G49: 350637.25 | H49: =F49+G49 -> 905306.75 | I49: =H49-E49 -> 142933.58 | J49: 59136.287 | K49: =H49*0.08 -> 72424.54 | L49: =K49-J49 -> 13288.253 | O49: =N49-M49 -> 0 | P49: =K49*12 -> 869094.48
A50: 2 | B50: OGUCHE SAMUEL | C50: SNR RESEARCH FELLOW | D50: 15(9) | E50: 620675.58 | F50: 459010.5 | G50: 285466.5 | H50: =F50+G50 -> 744477 | I50: =H50-E50 -> 123801.42 | J50: 49654.047 | K50: =H50*0.08 -> 59558.16 | L50: =K50-J50 -> 9904.1133 | O50: =N50-M50 -> 0 | P50: =K50*12 -> 714697.92
A51: 3 | B51: IBRAHIM USMAN | C51: SNR RESEARCH FELLOW | D51: 15(9) | E51: 620675.58 | F51: 459010.5 | G51: 285466.5 | H51: =F51+G51 -> 744477 | I51: =H51-E51 -> 123801.42 | J51: 49654.047 | K51: =H51*0.08 -> 59558.16 | L51: =K51-J51 -> 9904.1133 | M51: 8380.2271 | N51: =0.025*F51 -> 11475.263 | O51: =N51-M51 -> 3095.0354 | P51: =K51*12 -> 714697.92 | Q51: =N51*12 -> 137703.15
A52: 4 | B52: DR MOHAMMED O. AMALI | C52: SNR RESEARCH FELLOW | D52: 15(8) | E52: 601396.83 | F52: 445995.83 | G52: 276599.67 | H52: =F52+G52 -> 722595.5 | I52: =H52-E52 -> 121198.67 | J52: 46569.447 | K52: =H52*0.08 -> 57807.64 | L52: =K52-J52 -> 11238.193 | O52: =N52-M52 -> 0 | P52: =K52*12 -> 693691.68
A53: 5 | B53: YAHAYA SHAMSU | C53: SNR RESEARCH FELLOW | D53: 15(7) | E53: 582118.08 | F53: 432981.08 | G53: 267732.83 | H53: =F53+G53 -> 700713.92 | I53: =H53-E53 -> 118595.83 | J53: 46569.45 | K53: =H53*0.08 -> 56057.113 | L53: =K53-J53 -> 9487.6633 | O53: =N53-M53 -> 0 | P53: =K53*12 -> 672685.36
A54: 6 | B54: BILKIS S. LAWAL-GAMBARI | C54: RESEARCH OFFICER | D54: 10(9) | E54: 308901.5 | F54: 246171.17 | G54: 143964.67 | H54: =F54+G54 -> 390135.83 | I54: =H54-E54 -> 81234.333 | J54: 24077.247 | K54: =H54*0.08 -> 31210.867 | L54: =K54-J54 -> 7133.62 | O54: =N54-M54 -> 0 | P54: =K54*12 -> 374530.4
A55: 7 | B55: ZAINAB AKINDE | C55: RESEARCH OFFICER | D55: 9(9) | E55: 270481.67 | F55: 222674.58 | G55: 124341.58 | H55: =F55+G55 -> 347016.17 | I55: =H55-E55 -> 76534.5 | J55: 21053.227 | K55: =H55*0.08 -> 27761.293 | L55: =K55-J55 -> 6708.0667 | O55: =N55-M55 -> 0 | P55: =K55*12 -> 333135.52
A56: 8 | B56: GUNAT NANSAK MARK | C56: RESEARCH OFFICER | D56: 9(9) | E56: 270481.67 | F56: 222674.58 | G56: 124341.58 | H56: =F56+G56 -> 347016.17 | I56: =H56-E56 -> 76534.5 | J56: 21053.227 | K56: =H56*0.08 -> 27761.293 | L56: =K56-J56 -> 6708.0667 | O56: =N56-M56 -> 0 | P56: =K56*12 -> 333135.52
B57: TOTAL | C57: 8 | E57: =SUM(E49:E56) -> 4037104.1 | F57: =SUM(F49:F56) -> 3043187.8 | G57: =SUM(G49:G56) -> 1858550.6 | H57: =SUM(H49:H56) -> 4901738.3 | I57: =SUM(I49:I56) -> 864634.25 | J57: =SUM(J49:J56) -> 317766.98 | K57: =SUM(K49:K56) -> 392139.07 | L57: =SUM(L49:L56) -> 74372.09 | ... Q57: =SUM(Q49:Q56) -> 137703.15
B59: LEGAL SERVICES
A60: 1 | B60: DR SHUAIBU DANWANKA | C60: DIRECTOR LEGAL SERVICES | D60: 17(9) | E60: 1435720 | F60: 1086777.1 | G60: 660329.33 | H60: =F60+G60 -> 1747106.4 | I60: =H60-E60 -> 311386.42 | J60: 114857.6 | K60: =H60*0.08 -> 139768.51 | L60: =K60-J60 -> 24910.913 | O60: =N60-M60 -> 0 | P60: =K60*12 -> 1677222.2
A61: 2 | B61: ABDULSALAM BAKO | C61: MANAGER, LEGAL SERVICES | D61: 15 (9) | E61: 620675.58 | F61: 459010.5 | G61: 285466.5 | H61: =F61+G61 -> 744477 | I61: =H61-E61 -> 123801.42 | J61: 49654.047 | K61: =H61*0.08 -> 59558.16 | L61: =K61-J61 -> 9904.1133 | O61: =N61-M61 -> 0 | P61: =K61*12 -> 714697.92
B62: TOTAL | C62: 2 | E62: =SUM(E60:E61) -> 2056395.6 | F62: =SUM(F60:F61) -> 1545787.6 | G62: =SUM(G60:G61) -> 945795.83 | H62: =SUM(H60:H61) -> 2491583.4 | I62: =SUM(I60:I61) -> 435187.83 | J62: =SUM(J60:J61) -> 164511.65 | K62: =SUM(K60:K61) -> 199326.67 | L62: =SUM(L60:L61) -> 34815.027 | ... Q62: =SUM(Q60:Q61) -> 0
B64: DEMOCRACY & GOVERNANCE
A65: 1 | B65: NGARA CHRISTOPHER OCHANJA | C65: DEP DIR DEM & GOVERNANCE | D65: 16(9) | E65: 762373.17 | F65: 554669.5 | G65: 350637.25 | H65: =F65+G65 -> 905306.75 | I65: =H65-E65 -> 142933.58 | J65: 60989.853 | K65: =H65*0.08 -> 72424.54 | L65: =K65-J65 -> 11434.687 | M65: 10293.398 | N65: =0.025*F65 -> 13866.737 | O65: =N65-M65 -> 3573.3396 | P65: =K65*12 -> 869094.48 | Q65: =N65*12 -> 166400.85
A66: 2 | B66: EJALONIBU GANIYU LAYI | C66: RESEARCH FELLOW 1 | D66: 14(9) | E66: 456622.25 | F66: 347715.92 | G66: 210449.33 | H66: =F66+G66 -> 558165.25 | I66: =H66-E66 -> 101543 | J66: 35419.72 | K66: =H66*0.08 -> 44653.22 | L66: =K66-J66 -> 9233.5 | O66: =N66-M66 -> 0 | P66: =K66*12 -> 535838.64
A67: 3 | B67: UDEFUNA NNADOZIE PATRICK | C67: RESEARCH OFFICER | D67: 12(9) | E67: 377895.17 | F67: 294662.92 | G67: 174165.25 | H67: =F67+G67 -> 468828.17 | I67: =H67-E67 -> 90933 | J67: 29256.307 | K67: =H67*0.08 -> 37506.253 | L67: =K67-J67 -> 8249.9467 | O67: =N67-M67 -> 0 | P67: =K67*12 -> 450075.04
A68: 4 | B68: SHAFIU YAHYA MIKAIL | C68: PRINCIPAL RESEARCH OFFICER | D68: 12(9) | E68: 377895.17 | F68: 294662.92 | G68: 174165.25 | H68: =F68+G68 -> 468828.17 | I68: =H68-E68 -> 90933 | J68: 29256.307 | K68: =H68*0.08 -> 37506.253 | L68: =K68-J68 -> 8249.9467 | O68: =N68-M68 -> 0 | P68: =K68*12 -> 450075.04
A69: 5 | B69: HASSAN YERIMA | C69: PRINCIPAL RESEARCH OFFICER | D69: 12(9) | E69: 377895.17 | F69: 294662.92 | G69: 174165.25 | H69: =F69+G69 -> 468828.17 | I69: =H69-E69 -> 90933 | J69: 29256.307 | K69: =H69*0.08 -> 37506.253 | L69: =K69-J69 -> 8249.9467 | O69: =N69-M69 -> 0 | P69: =K69*12 -> 450075.04
A70: 6 | B70: HAUWA PATE SADIQ | C70: PRINCIPAL PROGRAMME OFFICER | D70: 12(10) | E70: 390086.5 | F70: 302878.67 | G70: 179784 | H70: =F70+G70 -> 482662.67 | I70: =H70-E70 -> 92576.167 | J70: 30231.613 | K70: =H70*0.08 -> 38613.013 | L70: =K70-J70 -> 8381.4 | O70: =N70-M70 -> 0 | P70: =K70*12 -> 463356.16
A71: 7 | B71: KOLAPO Q. ABAYOMI | C71: RESEARCH OFFICER | D71: 10(9) | E71: 308901.5 | F71: 246171.17 | G71: 143964.67 | H71: =F71+G71 -> 390135.83 | I71: =H71-E71 -> 81234.333 | J71: 24077.247 | K71: =H71*0.08 -> 31210.867 | L71: =K71-J71 -> 7133.62 | N71: =0.025*F71 -> 6154.2792 | O71: =N71-M71 -> 6154.2792 | P71: =K71*12 -> 374530.4
B72: TOTAL | C72: 7 | E72: =SUM(E65:E71) -> 3051668.9 | F72: =SUM(F65:F71) -> 2335424 | G72: =SUM(G65:G71) -> 1407331 | H72: =SUM(H65:H71) -> 3742755 | I72: =SUM(I65:I71) -> 691086.08 | J72: =SUM(J65:J71) -> 238487.35 | K72: =SUM(K65:K71) -> 299420.4 | L72: =SUM(L65:L71) -> 60933.047 | ... Q72: =SUM(Q65:Q71) -> 166400.85
B74: DEPARTMENT OF STUDIES
A75: 1 | B75: DR ASIMIYU G. ABIOLA | C75: DIRECTOR POST GRADUATE | D75: 17(9) | E75: 1435720 | F75: 1086777.1 | G75: 660329.33 | H75: =F75+G75 -> 1747106.4 | I75: =H75-E75 -> 311386.42 | J75: 114857.6 | K75: =H75*0.08 -> 139768.51 | L75: =K75-J75 -> 24910.913 | O75: =N75-M75 -> 0 | P75: =K75*12 -> 1677222.2
A76: 2 | B76: DR. HADIZA SAIDU | C76: ASSISTANT DIRECTOR | D76: 15(7) | E76: 582118.08 | F76: 445995.83 | G76: 276599.67 | H76: =F76+G76 -> 722595.5 | I76: =H76-E76 -> 140477.42 | J76: 46569.447 | K76: =H76*0.08 -> 57807.64 | L76: =K76-J76 -> 11238.193 | O76: =N76-M76 -> 0 | P76: =K76*12 -> 693691.68
A77: 3 | B77: ANTHONY EDET | C77: CHIEF PROGRAMMES OFFICER | D77: 14(10) | E77: 470498 | F77: 357066.67 | G77: 216844.42 | H77: =F77+G77 -> 573911.08 | I77: =H77-E77 -> 103413.08 | J77: 36529.78 | K77: =H77*0.08 -> 45912.887 | L77: =K77-J77 -> 9383.1067 | M77: 6154.3229 | N77: =0.025*F77 -> 8926.6667 | O77: =N77-M77 -> 2772.3438 | P77: =K77*12 -> 550954.64 | Q77: =N77*12 -> 107120
A78: 4 | B78: IGWE STACY | C78: PRINC. PROGRAMME OFFICER | D78: 12(8) | E78: 365703.83 | F78: 286447.08 | G78: 168546.5 | H78: =F78+G78 -> 454993.58 | I78: =H78-E78 -> 89289.75 | J78: 28281 | K78: =H78*0.08 -> 36399.487 | L78: =K78-J78 -> 8118.4867 | O78: =N78-M78 -> 0 | P78: =K78*12 -> 436793.84
A79: 5 | B79: OLANIYAN TAIWO ABINBOLA | C79: PROGRAMME OFFICER | D79: 9(8) | E79: 263165.33 | F79: 222674.58 | G79: 124341.58 | H79: =F79+G79 -> 347016.17 | I79: =H79-E79 -> 83850.833 | J79: 21053.227 | K79: =H79*0.08 -> 27761.293 | L79: =K79-J79 -> 6708.0667 | N79: =0.025*F79 -> 5566.8646 | O79: =N79-M79 -> 5566.8646 | P79: =K79*12 -> 333135.52
A80: 6 | B80: AMINAT JUMOKE SULAIMON | C80: AST. PROGRAMME OFFICER | D80: 8(9) | E80: 230631.92 | F80: 196364.42 | G80: 105546.33 | H80: =F80+G80 -> 301910.75 | I80: =H80-E80 -> 71278.833 | J80: 17956.78 | K80: =H80*0.08 -> 24152.86 | L80: =K80-J80 -> 6196.08 | O80: =N80-M80 -> 0 | P80: =K80*12 -> 289834.32
B81: TOTAL | C81: 6 | E81: =SUM(E75:E80) -> 3347837.2 | F81: =SUM(F75:F80) -> 2595325.7 | G81: =SUM(G75:G80) -> 1552207.8 | H81: =SUM(H75:H80) -> 4147533.5 | I81: =SUM(I75:I80) -> 799696.33 | J81: =SUM(J75:J80) -> 265247.83 | K81: =SUM(K75:K80) -> 331802.68 | L81: =SUM(L75:L80) -> 66554.847 | ... Q81: =SUM(Q75:Q80) -> 107120
B83: ECON. DEV. & SOC. RESEARCH
A84: 1 | B84: DR AUGUSTINE C. OSIGWE | C84: SNR RESEARCH FELLOW | D84: 17(7) | E84: ='[3]Annual & Monthly'!$H$44 -> 1352042.7 | F84: 1025768.3 | G84: 621843.67 | H84: =F84+G84 -> 1647612 | I84: =H84-E84 -> 295569.33 | J84: 114857.6 | K84: =H84*0.08 -> 131808.96 | L84: =K84-J84 -> 16951.36 | M84: 18254.975 | N84: =0.025*F84 -> 25644.208 | O84: =N84-M84 -> 7389.2333 | P84: =12*K84 -> 1581707.5 | Q84: =N84*12 -> 307730.5
A85: 2 | B85: TERFA WILLIAMS ABRAHAM | C85: DEP. DIRECTOR ECON & SOCIAL RES | D85: 16(7) | E85: 716034 | F85: 523386.5 | G85: 329324.58 | H85: =F85+G85 -> 852711.08 | I85: =H85-E85 -> 136677.08 | J85: 59136.287 | K85: =H85*0.08 -> 68216.887 | L85: =K85-J85 -> 9080.6 | O85: =N85-M85 -> 0 | P85: =12*K85 -> 818602.64
A86: 3 | B86: OMOJU OLUWASOLA EMMANUEL | C86: SNR RESEARCH FELLOW | D86: 15(8) | E86: 601396.83 | F86: 445995.83 | G86: 276599.67 | H86: =F86+G86 -> 722595.5 | I86: =H86-E86 -> 121198.67 | J86: 46569.447 | K86: =H86*0.08 -> 57807.64 | L86: =K86-J86 -> 11238.193 | O86: =N86-M86 -> 0 | P86: =12*K86 -> 693691.68
A87: 4 | B87: IBE EZECHI CYRIACUS | C87: RESEARCH FELLOW 1 | D87: 14(9) | E87: 456622.25 | F87: 347715.92 | G87: 210449.33 | H87: =F87+G87 -> 558165.25 | I87: =H87-E87 -> 101543 | J87: 35344.393 | K87: =H87*0.08 -> 44653.22 | L87: =K87-J87 -> 9308.8267 | O87: =N87-M87 -> 0 | P87: =12*K87 -> 535838.64
A88: 5 | B88: OSIKHEN LEO IGBANOI | C88: RESEARCH FELLOW 1 | D88: 14(9) | E88: 456622.25 | F88: 347716.92 | G88: 210449.33 | H88: =F88+G88 -> 558166.25 | I88: =H88-E88 -> 101544 | J88: 35419.72 | K88: =H88*0.08 -> 44653.3 | L88: =K88-J88 -> 9233.58 | N88: =0.025*F88 -> 8692.9229 | O88: =N88-M88 -> 8692.9229 | P88: =12*K88 -> 535839.6 | Q88: =N88*12 -> 104315.07
A89: 6 | B89: OKUNGBOWA OSARETIN GODSPOWER | C89: RESEARCH FELLOW 1 | D89: 14(8) | E89: 442746.5 | F89: 338365.25 | G89: 204054.25 | H89: =F89+G89 -> 542419.5 | I89: =H89-E89 -> 99673 | J89: 34309.66 | K89: =H89*0.08 -> 43393.56 | L89: =K89-J89 -> 9083.9 | O89: =N89-M89 -> 0 | P89: =12*K89 -> 520722.72
A90: 7 | B90: YUSUF IBRAHIM | C90: PRINCIPAL RESEARCH OFFICER | D90: 12(9) | E90: 377895.17 | F90: 294662.92 | G90: 174165.25 | H90: =F90+G90 -> 468828.17 | I90: =H90-E90 -> 90933 | J90: 29256.307 | K90: =H90*0.08 -> 37506.253 | L90: =K90-J90 -> 8249.9467 | O90: =N90-M90 -> 0 | P90: =12*K90 -> 450075.04
A91: 8 | B91: MUSTAPHA RAFIU AYOBANJI | C91: RESEARCH FELLOW 11 | D91: 13(8) | E91: 403137.92 | F91: 311673.25 | G91: 185799.5 | H91: =F91+G91 -> 497472.75 | I91: =H91-E91 -> 94334.833 | J91: 31219.913 | K91: =H91*0.08 -> 39797.82 | L91: =K91-J91 -> 8577.9067 | M91: 5259.7437 | N91: =0.025*F91 -> 7791.8313 | O91: =N91-M91 -> 2532.0875 | P91: =12*K91 -> 477573.84 | Q91: =N91*12 -> 93501.975
A92: 9 | B92: MARYAM MUSA SADA | C92: ASSIT. RESEARCH OFFICER | D92: 10(9) | E92: 308901.5 | F92: 246171.17 | G92: 143964.67 | H92: =F92+G92 -> 390135.83 | I92: =H92-E92 -> 81234.333 | J92: 24077.247 | K92: =H92*0.08 -> 31210.867 | L92: =K92-J92 -> 7133.62 | O92: =N92-M92 -> 0 | P92: =12*K92 -> 374530.4
A93: 10 | B93: CHARITY EZENWAJIOBI | C93: REASEARCH. ASST. | D93: 8(10) | E93: 236804.08 | F93: 200549.42 | G93: 108371.25 | H93: =F93+G93 -> 308920.67 | I93: =H93-E93 -> 72116.583 | J93: 18450.553 | K93: =H93*0.08 -> 24713.653 | L93: =K93-J93 -> 6263.1 | N93: =0.025*F93 -> 5013.7354 | O93: =N93-M93 -> 5013.7354 | P93: =12*K93 -> 296563.84
B94: TOTAL | C94: 10 | E94: =SUM(E84:E93) -> 5352203.2 | F94: =SUM(F84:F93) -> 4082005.5 | G94: =SUM(G84:G93) -> 2465021.5 | H94: =SUM(H84:H93) -> 6547027 | I94: =SUM(I84:I93) -> 1194823.8 | J94: =SUM(J84:J93) -> 428641.13 | K94: =SUM(K84:K93) -> 523762.16 | L94: =SUM(L84:L93) -> 95121.033 | ... Q94: =SUM(Q84:Q93) -> 505547.55
B96: TRAINING & INT''L COOP
A97: 1 | B97: AKINSANMI ADEJOKE OLUKEMI | C97: Ag. DIR. TRAINING & IC | D97: 17(8) | E97: 1393881.3 | F97: 1056272.8 | G97: 641086.5 | H97: =F97+G97 -> 1697359.3 | I97: =H97-E97 -> 303478 | J97: 114857.6 | K97: =H97*0.08 -> 135788.75 | L97: =K97-J97 -> 20931.147 | M97: 18254.975 | N97: =0.025*F97 -> 26406.821 | O97: =N97-M97 -> 8151.8458 | P97: =12*K97 -> 1629465 | Q97: =N97*12 -> 316881.85
A98: 2 | B98: MOHAMMED R. ADAMU | C98: CHIEF TRAINING OFFICER | D98: 14(10) | E98: 470498 | F98: 357066.67 | G98: 216844.42 | H98: =F98+G98 -> 573911.08 | I98: =H98-E98 -> 103413.08 | J98: 36529.78 | K98: =H98*0.08 -> 45912.887 | L98: =K98-J98 -> 9383.1067 | O98: =N98-M98 -> 0 | P98: =12*K98 -> 550954.64 | Q98: =N98*12 -> 0
A99: 3 | B99: EROMOSELE OMONIGBO | C99: ASSIST. CHIEF PERSONNEL OFFICER | D99: 13(8) | E99: 403137.92 | F99: 311673.25 | G99: 185799.5 | H99: =F99+G99 -> 497472.75 | I99: =H99-E99 -> 94334.833 | J99: 31219.91 | K99: =H99*0.08 -> 39797.82 | L99: =K99-J99 -> 8577.91 | M99: 5967.3062 | N99: =0.025*F99 -> 7791.8313 | O99: =N99-M99 -> 1824.525 | P99: =12*K99 -> 477573.84 | Q99: =N99*12 -> 93501.975
A100: 4 | B100: OKECHUKWU UCHENNA HULDA | C100: PRINCIPALTRAINING OFFICER | D100: 12(10) | E100: 390086.5 | F100: 302878.67 | G100: 179784 | H100: =F100+G100 -> 482662.67 | I100: =H100-E100 -> 92576.167 | J100: 30231.613 | K100: =H100*0.08 -> 38613.013 | L100: =K100-J100 -> 8381.4 | O100: =N100-M100 -> 0 | P100: =12*K100 -> 463356.16 | Q100: =N100*12 -> 0
A101: 5 | B101: TASSNEEM IBRAHIM | C101: SENIOR PROGRAMME OFFICER | D101: 10(9) | E101: 308901.5 | F101: 246171.17 | G101: 143964.67 | H101: =F101+G101 -> 390135.83 | I101: =H101-E101 -> 81234.333 | J101: 24077.247 | K101: =H101*0.08 -> 31210.867 | L101: =K101-J101 -> 7133.62 | O101: =N101-M101 -> 0 | P101: =12*K101 -> 374530.4 | Q101: =N101*12 -> 0
B102: TOTAL | C102: 5 | E102: =SUM(E97:E101) -> 2966505.2 | F102: =SUM(F97:F101) -> 2274062.6 | G102: =SUM(G97:G101) -> 1367479.1 | H102: =SUM(H97:H101) -> 3641541.7 | I102: =SUM(I97:I101) -> 675036.42 | J102: =SUM(J97:J101) -> 236916.15 | K102: =SUM(K97:K101) -> 291323.33 | L102: =SUM(L97:L101) -> 54407.183 | ... Q102: =SUM(Q97:Q101) -> 410383.82
B104: LIBRARY & DOCUMENTATION
A105: 1 | B105: DR MAIMUNA IZAH | C105: INSITUTE LIBRARIAN | D105: 17(9) | E105: 1435720 | F105: 1086777.1 | G105: 660329.33 | H105: =F105+G105 -> 1747106.4 | I105: =H105-E105 -> 311386.42 | J105: 114857.6 | K105: =H105*0.08 -> 139768.51 | L105: =K105-J105 -> 24910.913 | M105: 0 | O105: =N105-M105 -> 0 | P105: =K105*12 -> 1677222.2
A106: 2 | B106: CATHERINE E. IKOKOH | C106: SNR RESEARCH FELLOW DOCU | D106: 16(9) | E106: 762373.17 | F106: 554669.5 | G106: 350637.25 | H106: =F106+G106 -> 905306.75 | I106: =H106-E106 -> 142933.58 | J106: 60989.853 | K106: =H106*0.08 -> 72424.54 | L106: =K106-J106 -> 11434.687 | M106: 10293.398 | N106: =0.025*F106 -> 13866.737 | O106: =N106-M106 -> 3573.3396 | P106: =K106*12 -> 869094.48 | Q106: =N106*12 -> 166400.85
A107: 3 | B107: ALIYU SANNI ABUBAKAR | C107: RESEARCH FELLOW 11 DATA & DOCU | D107: 13(11) | E107: 441804.92 | F107: 337730.83 | G107: 203620.5 | H107: =F107+G107 -> 541351.33 | I107: =H107-E107 -> 99546.417 | J107: 35344.393 | K107: =H107*0.08 -> 43308.107 | L107: =K107-J107 -> 7963.7133 | M107: 5954.6104 | N107: =0.025*F107 -> 8443.2708 | O107: =N107-M107 -> 2488.6604 | P107: =K107*12 -> 519697.28 | Q107: =N107*12 -> 101319.25
A108: 4 | B108: CHINAKO N. ASOGWA | C108: RESEARCH FELLOW 11 DATA & DOCU | D108: 14(7) | E108: 441804.92 | F108: 338365.25 | G108: 204054.25 | H108: =F108+G108 -> 542419.5 | I108: =H108-E108 -> 100614.58 | J108: 35344.393 | K108: =H108*0.08 -> 43393.56 | L108: =K108-J108 -> 8049.1667 | O108: =N108-M108 -> 0 | P108: =K108*12 -> 520722.72
...

Sheet Sheet18

Sheet 2025 Promotions (2)
A1: NATIONAL INSTITUTE FOR LEGISLATIVE & DEMOCRATIC STUDIES
A2: 2025 ANALYSIS OF STAFF PROMOTION ARREARS
A4: SN | B4: Name of Employee | C4: Department | D4: Present Grade Level | E4: New Grade Level | F4: Consolidated Salary of Present Position | G4: Consolidated Salary of New Position | H4: Diference/Arrears | I4: Effective Date | J4: No of Months | K4: Total Amount of Arrears (Gross)
F5: N | G5: N | H5: N | K5: N
A6: 13 | B6: Victor Etim Asukwo | C6: DG's Office | D6: 9/10 | E6: 10/7 | F6: 415320.67 | G6: 432145.33 | H6: =G6-F6 -> 16824.667 | I6: 6th August 2025 | J6: 4 | K6: =J6*H6 -> 67298.667
B7: TOTAL | H7: =SUM(H6:H6) -> 16824.667 | K7: =SUM(K6:K6) -> 67298.667

Sheet Christmas Welfare 2025 (2)
A1: NATIONAL INSTITUTE FOR LEGISLATIVE AND DEMOCRATIC STUDIES
A2: STAFF CHRISTMAS WELFARE DECEMBER 2025
B4: STAFF NAME | C4: DESIGNATION | D4: GRADE LEVEL | E4: AMOUNT
A6: S/N | B6: DG'S OFFICE | E6: N
A7: 1 | B7: PROF. ABUBAKAR O. SULAIMAN | C7: DIRECTOR GENERAL | D7: CONSOL | E7: 648000
A8: 2 | B8: RAHEEM USMAN AYIGORO | C8: SA-INFRASTRUCTURE | D8: 16 (9) | E8: 216000
A9: 3 | B9: MARIAM MOHAMMED BELLO | C9: SA- SPECIAL DUTIES | D9: 16 (9) | E9: 216000
A10: 4 | B10: DR IKEME ARTHUR J.O | C10: DEPUTY DIRECTOR, M&E | D10: 16 (9) | E10: 216000
A11: 5 | B11: ANDRAWUS MUSA | C11: DEP. DIRECTOR, STORES & PROCUREMENT | D11: 16(8) | E11: 216000
A12: 6 | B12: DR FRANCIS NDUM OJIE | C12: AD, TRAINING & IC./SA TO DG | D12: 15(8) | E12: 151200
A13: 7 | B13: ALI ABDULLAHI | C13: ASST DIRECTOR ICT | D13: 15(7) | E13: 151200
A14: 8 | B14: EMILY EKHIDE | C14: SENIOR RESEARCH FELLOW | D14: 15(8) | E14: 151200
A15: 9 | B15: DORIS DAKDA AARON | C15: RESEARCH FELLOW I | D15: 14(9) | E15: 108000
A16: 10 | B16: ABDULSALAM S. MUSTAPHA | C16: ASST. DIRECTOR ICT | D16: 15(7) | E16: 151200
A17: 11 | B17: PERCY TERFA GBAHABO | C17: RESEARCH FELLOW 1 | D17: 14(7) | E17: 108000
A18: 12 | B18: HASSANA AHMED IBRAHIM | C18: PA- TO DG | D18: 13(10) | E18: 108000
... A46: 40 | B46: ALIYU GARBA LERE | C46: ASSIST INFORMATION OFFICER | D46: 8(7) | E46: 64800
B47: TOTAL | C47: 40 | E47: =SUM(E7:E46) -> 4579200
B49: INTERNAL AUDIT
A50: 1 | B50: OSANAIYE DAVID AKINYEMI | C50: DIRECTOR INTERNAL AUDIT | D50: 17(9) | E50: 324000
A51: 2 | B51: EVELYN ETONKE AGAN | C51: ASST DIR AUDIT | D51: 15(7) | E51: 151200
A52: 3 | B52: JAMILA ABDUL | C52: SENIOR INTERNAL AUDITOR | D52: 10(8) | E52: 81600
A53: 4 | B53: IJEOMA EWELUKWA | C53: PRINCIPAL AUDIT OFFICER | D53: 12(7) | E53: 81600
A54: 5 | B54: HASSAN ABDULHADI | C54: SENIOR INTERNAL AUDITOR | D54: 9(7) | E54: 64800
A55: 6 | B55: YUSUF YUSUF DAYYABU | C55: INERNAL AUDIT OFFICER | D55: 9(8) | E55: 64800
A56: 7 | B56: UDONSI QUEENETH CHIWENDU | C56: ASSIST PROGRAMME OFFICER | D56: 8(7) | E56: 64800
C57: 7 | E57: =SUM(E50:E56) -> 832800
B59: LEG. SUPPORT SEVICES
A60: 1 | B60: BETHEL UZOMA IHUGBA | C60: AG. DIRECTOR, AEEP | D60: 17(7) | E60: 324000
A61: 2 | B61: OGUCHE SAMUEL | C61: SNR RESEARCH FELLOW | D61: 15(9) | E61: 151200
A62: 3 | B62: IBRAHIM USMAN | C62: SNR RESEARCH FELLOW | D62: 15(9) | E62: 151200
A63: 4 | B63: DR MOHAMMED O. AMALI | C63: SNR RESEARCH FELLOW | D63: 15(8) | E63: 151200
A64: 5 | B64: YAHAYA SHAMSU | C64: SNR RESEARCH FELLOW | D64: 15(7) | E64: 151200
A65: 6 | B65: CHIDEBE MATHEW NWANKWO | C65: SNR RESEARCH FELLOW | D65: 15(7) | E65: 151200
A66: 7 | B66: UMAR MUSA PADAH | C66: PRINC. RESEARCH OFFICER | D66: 12(7) | E66: 81600
A67: 8 | B67: BILKIS S. LAWAL-GAMBARI | C67: RESEARCH OFFICER | D67: 10(9) | E67: 81600
A68: 9 | B68: UMOH USENOBONG EMMANUEL | C68: SENIOR RESEARCH OFFICER | D68: 10(7) | E68: 81600
A69: 10 | B69: ZAINAB AKINDE | C69: RESEARCH OFFICER | D69: 9(9) | E69: 64800
A70: 11 | B70: GUNAT NANSAK MARK | C70: RESEARCH OFFICER | D70: 9(9) | E70: 64800
A71: 12 | B71: MANDU ESSIEN NDEM | C71: RESEARCH OFFICER | D71: 9(7) | E71: 64800
B72: TOTAL | C72: 12 | E72: =SUM(E60:E71) -> 1519200
B74: LEGAL SERVICES
A75: 1 | B75: DR SHUAIBU DANWANKA | C75: DIRECTOR LEGAL SERVICES | D75: 17(9) | E75: 324000
A76: 2 | B76: ABDULSALAM BAKO | C76: MANAGER, LEGAL SERVICES | D76: 15 (9) | E76: 151200
B77: TOTAL | C77: 2 | E77: =SUM(E75:E76) -> 475200
B79: DEMOCRACY & GOVERNANCE
A80: 1 | B80: NGARA CHRISTOPHER OCHANJA | C80: DEP DIR DEM & GOVERNANCE | D80: 16(9) | E80: 216000
A81: 2 | B81: EJALONIBU GANIYU LAYI | C81: RESEARCH FELLOW 1 | D81: 14(9) | E81: 108000
A82: 3 | B82: MARTINS SOLOMON UDOM | C82: RESEARCH FELLOW 11 | D82: 13(7) | E82: 108000
A83: 4 | B83: ISHAKA DELE | C83: RESEARCH FELLOW 11 | D83: 13(7) | E83: 108000
A84: 5 | B84: UDEFUNA NNADOZIE PATRICK | C84: RESEARCH OFFICER | D84: 12(9) | E84: 81600
A85: 6 | B85: SHAFIU YAHYA MIKAIL | C85: PRINCIPAL RESEARCH OFFICER | D85: 12(9) | E85: 81600
A86: 7 | B86: HASSAN YERIMA | C86: PRINCIPAL RESEARCH OFFICER | D86: 12(9) | E86: 81600
A87: 8 | B87: HAUWA PATE SADIQ | C87: ASST CHIEF PROGRAMME OFFICER | D87: 13(7) | E87: 108000
A88: 9 | B88: OBOT ETIMBUK EMMANUEL | C88: PRINCIPAL INFO. OFFICER | D88: 12(7) | E88: 81600
A89: 10 | B89: KOLAPO Q. ABAYOMI | C89: RESEARCH OFFICER | D89: 10(9) | E89: 81600
A90: 11 | B90: SALIHU SHAMSUDEEN OPEYEMI | C90: PROGRAMME OFFICER | D90: 9(7) | E90: 64800
B91: TOTAL | C91: 11 | E91: =SUM(E80:E90) -> 1120800
B93: DEPARTMENT OF STUDIES
A94: 1 | B94: DR ASIMIYU G. ABIOLA | C94: DIRECTOR POST GRADUATE | D94: 17(9) | E94: 324000
A95: 2 | B95: AYOBOLU OLAJIDE OLUFUNSHO | C95: ASSISTANT DIR. EXXAMS & RECORD | D95: 15(7) | E95: 151200
A96: 3 | B96: DR. HADIZA SAIDU | C96: ASSISTANT DIRECTOR | D96: 15(7) | E96: 151200
A97: 4 | B97: ANTHONY EDET | C97: CHIEF PROGRAMMES OFFICER | D97: 14(10) | E97: 108000
A98: 5 | B98: CHRISTIAN MADUABUCHI ODO | C98: ASSIST. CHIEF ICT OFFICER | D98: 13(7) | E98: 108000
A99: 6 | B99: DR. IBANGA ISSAC JONAH | C99: ASSIST. CHIEF PROGRM OFFICER | D99: 13(7) | E99: 108000
A100: 7 | B100: IGWE STACY | C100: PRINC. PROGRAMME OFFICER | D100: 12(8) | E100: 81600
A101: 8 | B101: MUNIRU JIBRIN | C101: SENIOR PROGRAMME OFFICER | D101: 10(7) | E101: 81600
A102: 9 | B102: OLANIYAN TAIWO ABINBOLA | C102: PROGRAMME OFFICER | D102: 9(8) | E102: 64800
A103: 10 | B103: MUSA ALKASIM ADAMU | C103: PROGRAMME OFFICER | D103: 9(7) | E103: 64800
A104: 11 | B104: AMINAT JUMOKE SULAIMON | C104: AST. PROGRAMME OFFICER | D104: 8(9) | E104: 64800
B105: TOTAL | C105: 11 | E105: =SUM(E94:E104) -> 1308000
B107: ECON. DEV. & SOC. RESEARCH
A108: 1 | B108: DR AUGUSTINE C. OSIGWE | C108: AG. DIRECTOR, ESR | D108: 17(7) | E108: 324000
A109: 2 | B109: TERFA WILLIAMS ABRAHAM | C109: DEP. DIRECTOR ECON & SOCIAL RES | D109: 16(7) | E109: 216000
A110: 3 | B110: OMOJU OLUWASOLA EMMANUEL | C110: SNR RESEARCH FELLOW | D110: 15(8) | E110: 151200
A111: 4 | B111: IBE EZECHI CYRIACUS | C111: RESEARCH FELLOW 1 | D111: 14(9) | E111: 108000
A112: 5 | B112: OSIKHEN LEO IGBANOI | C112: RESEARCH FELLOW 1 | D112: 14(9) | E112: 108000
A113: 6 | B113: OKUNGBOWA OSARETIN GODSPOWER | C113: RESEARCH FELLOW 1 | D113: 14(8) | E113: 108000
A114: 7 | B114: YUSUF IBRAHIM | C114: PRINCIPAL RESEARCH OFFICER | D114: 12(9) | E114: 81600
A115: 8 | B115: MUSTAPHA RAFIU AYOBANJI | C115: RESEARCH FELLOW 11 | D115: 13(8) | E115: 108000
A116: 9 | B116: UDOKANG NSISONG BONIFACE | C116: PRINC. RESEARCH OFFICER | D116: 12(7) | E116: 81600
A117: 10 | B117: MARYAM MUSA SADA | C117: ASSIT. RESEARCH OFFICER | D117: 10(9) | E117: 81600
A118: 11 | B118: TAWAKALTU FOLASHADE SADIQ | C118: RESEARCH OFFICER | D118: 9(7) | E118: 64800
A119: 12 | B119: MURTALA ADAM MUHAMMAD | C119: RESEARCH OFFICER | D119: 9(7) | E119: 64800
A120: 13 | B120: CHARITY EZENWAJIOBI | C120: REASEARCH. ASST. | D120: 8(10) | E120: 64800
B121: TOTAL | C121: 13 | E121: =SUM(E108:E120) -> 1562400
B123: TRAINING & INT''L COOP
A124: 1 | B124: AKINSANMI ADEJOKE OLUKEMI | C124: AG. DIR. TRAINING & IC | D124: 17(8) | E124: 324000
A125: 2 | B125: MOHAMMED R. ADAMU | C125: CHIEF TRAINING OFFICER | D125: 14(10) | E125: 108000
A126: 3 | B126: EROMOSELE OMONIGBO | C126: ASSIST. CHIEF PERSONNEL OFFICER | D126: 13(8) | E126: 108000
A127: 4 | B127: DR. SAMUEL AKPAN MBADAH | C127: ASSIST. CHIEF TRAINING OFFICER | D127: 13(7) | E127: 108000
A128: 5 | B128: OKECHUKWU UCHENNA HULDA | C128: ASSIST. CHIEF TRAINING OFFICER | D128: 13(7) | E128: 108000
A129: 6 | B129: TASSNEEM IBRAHIM | C129: SENIOR PROGRAMME OFFICER | D129: 10(9) | E129: 81600
A130: 7 | B130: MAHMUD ABDULKADIR | C130: ASST. TRAINING OFFICER | D130: 10(7) | E130: 81600
B131: TOTAL | C131: 7 | E131: =SUM(E124:E130) -> 919200
B133: LIBRARY & DOCUMENTATION
A134: 1 | B134: MAIMUNA IZAH | C134: INSITUTE LIBRARIAN | D134: 17(9) | E134: 324000
A135: 2 | B135: CATHERINE E. IKOKOH | C135: SNR RESEARCH FELLOW DOCU | D135: 16(9) | E135: 216000
A136: 3 | B136: ALIYU SANNI ABUBAKAR | C136: CHIEF LIBRARIAN | D136: 14(7) | E136: 108000
A137: 4 | B137: CHINAKO N. ASOGWA | C137: CHIEF LIBRARIAN | D137: 14(7) | E137: 108000
...

Sheet Sum of Welfare (3)
A1: SUMMARY OF 2025 CHRISTMAS WELFARE
A2: 1 | B2: Permanent Staff | C2: ='Christmas Welfare 2025 (2)'!E250 -> 21102403
A3: 2 | B3: Contract Staff | C3: ='[20]Chr. Welfare Contract'!$E$32 -> 2611200
A4: 3 | B4: Casual, Sabbatical & NYSC | C4: ='[20]CASUAL, SABB & NYSC Chr Welfare'!$D$93 -> 4250400
A5: 4 | B5: Consultants/Freelance | C5: ='[20]CONSULTANTS Chr. Welfare'!$D$20 -> 1296000
A6: 5 | B6: Cleaners & Security Personnel
B7: Total | C7: =SUM(C2:C6) -> 29260003

Sheet New NHF Enrolment (3)
A1: NATIONAL INSTITUTE FOR LEGISLATIVE AND DEMOCRATIC STUDIES
A2: STAFF PAYROLL FOR THE MONTH OF JUNE, 2025
E3: ='[1]FEB 08'!E11/'[1]FEB 08'!M11 -> #REF!
B4: STAFF NAME | C4: DESIGNATION | D4: GRADE LEVEL | E4: OLD CUM BASIC SALARY | F4: NEW BASIC SALARY | G4: OLD NHF | H4: NEW NHF | I4: INCREASE IN NHF | J4: ANNUAL NEW NHF
E5: N | F5: N | G5: N | H5: N | I5: N | J5: N
E6: A | F6: B | G6: I | H6: J | I6: K | J6: M
A7: S/N | B7: DG'S OFFICE | H7: (2.5% of B) | I7: (J-I) | J7: (J-I)
A8: 1 | B8: PROF. ABUBAKAR O. SULAIMAN | C8: DIRECTOR GENERAL | D8: CONSOL | E8: 1659751.2 | F8: 1086777.1 | I8: =H8-G8 -> 0 | J8: =H8*12 -> 0
A9: 2 | B9: RAHEEM USMAN AYIGORO | C9: SA-INFRASTRUCTURE | D9: 16 (9) | E9: 762373.17 | F9: 554669.5 | I9: =H9-G9 -> 0 | J9: =H9*12 -> 0
A10: 3 | B10: MARIAM MOHAMMED BELLO | C10: SA- SPECIAL DUTIES | D10: 16 (9) | E10: 762373.17 | F10: 554669.5 | I10: =H10-G10 -> 0 | J10: =H10*12 -> 0
A11: 4 | B11: DR IKEME ARTHUR J.O | C11: DEPUTY DIRECTOR, M&E | D11: 16 (9) | E11: 762373.17 | F11: 554669.5 | G11: 10293.398 | H11: =0.025*F11 -> 13866.737 | I11: =H11-G11 -> 3573.3396 | J11: =H11*12 -> 166400.85
A12: 5 | B12: ANDRAWUS MUSA | C12: DEP. DIRECTOR, STORES & PROCUREMENT | D12: 16(7) | E12: 716034 | F12: ='[18] FGN 2024 MGT Monthly'!$H$44 -> 523386.5 | G12: 10293.398 | H12: =0.025*F12 -> 13084.663 | I12: =H12-G12 -> 2791.2646 | J12: =H12*12 -> 157015.95
A13: 6 | B13: DR FRANCIS NDUM OJIE | C13: AD, TRAINING & IC./SA TO DG | D13: 15(8) | E13: 601396.83 | F13: 445995.83 | G13: 7859.6313 | H13: =0.025*F13 -> 11149.896 | I13: =H13-G13 -> 3290.2646 | J13: =H13*12 -> 133798.75
A14: 7 | B14: ALI ABDULLAHI | C14: CHIEF ICT OFFICER | D14: 14(11) | E14: 484373.75 | F14: 366417.5 | H14: =0.025*F14 -> 9160.4375 | I14: =H14-G14 -> 9160.4375 | J14: =H14*12 -> 109925.25
A15: 8 | B15: EMILY EKHIDE | C15: SENIOR RESEARCH FELLOW | D15: 15(8) | E15: 601396.83 | F15: ='[18] FGN 2024 MGT Monthly'!$I$43 -> 445995.83 | H15: =0.025*F15 -> 11149.896 | I15: =H15-G15 -> 11149.896 | J15: =H15*12 -> 133798.75
A16: 9 | B16: DORIS DAKDA AARON | C16: RESEARCH FELLOW I | D16: 14(9) | E16: 456622.25 | F16: 347715.92 | H16: =0.025*F16 -> 8692.8979 | I16: =H16-G16 -> 8692.8979 | J16: =H16*12 -> 104314.77
A17: 10 | B17: ABDULSALAM S. MUSTAPHA | C17: ASST. DIRECTOR ICT | D17: 15(7) | E17: 582118.08 | F17: 432981.08 | H17: =0.025*F17 -> 10824.527 | I17: =H17-G17 -> 10824.527 | J17: =H17*12 -> 129894.32
A18: 11 | B18: PERCY TERFA GBAHABO | C18: HEAD, NILDS LIAISON OFFICE | D18: 13(11) | E18: 441804.92 | F18: 337730.83 | H18: =0.025*F18 -> 8443.2708 | I18: =H18-G18 -> 8443.2708 | J18: =H18*12 -> 101319.25
A19: 12 | B19: HASSANA AHMED IBRAHIM | C19: PA- TO DG | D19: 13 (10) | E19: 428915.92 | F19: 329044.92 | G19: 5607.1771 | H19: =0.025*F19 -> 8226.1229 | I19: =H19-G19 -> 2618.9458 | J19: =H19*12 -> 98713.475
A20: 13 | B20: IKIP LEBO | C20: ASST CHIEF PROC. OFFICER | D20: 13 (8) | E20: 403138 | F20: 311673.25 | G20: 5967.3062 | H20: =0.025*F20 -> 7791.8313 | I20: =H20-G20 -> 1824.525 | J20: =H20*12 -> 93501.975
A21: 14 | B21: ALABI ADESINA MUHYDEEN | C21: HEAD, NILDS LIAISON OFFICE | D21: 13 (8) | E21: 403138 | F21: 311673.25 | H21: =0.025*F21 -> 7791.8313 | I21: =H21-G21 -> 7791.8313 | J21: =H21*12 -> 93501.975
A22: 15 | B22: BASSEY NSONGURUA UDOFIA | C22: PRINC.CONF SEC/PPS | D22: 12(11) | E22: 402278 | F22: ='[18] FGN 2024 MGT Monthly'!$L$40 -> 311094.42 | G22: 5257.5625 | H22: =0.025*F22 -> 7777.3604 | I22: =H22-G22 -> 2519.7979 | J22: =H22*12 -> 93328.325
A23: 16 | B23: ADUGBA RICHARD TERSEER | C23: PRINCIPAL INFO. OFFICER | D23: 12(10) | E23: 390086.5 | F23: 302878.67 | H23: =0.025*F23 -> 7571.9667 | I23: =H23-G23 -> 7571.9667 | J23: =H23*12 -> 90863.6
A24: 17 | B24: LUCKY AGWOM | C24: RESEARCH ASSISTANT | D24: 12(8) | E24: 365704 | F24: 286447.08 | H24: =0.025*F24 -> 7161.1771 | I24: =H24-G24 -> 7161.1771 | J24: =H24*12 -> 85934.125
A25: 18 | B25: IDRIS IBRAHIM | C25: PRINCIPAL RESEARCH OFFICER | D25: 12(8) | E25: 365704 | F25: 286447.08 | H25: =0.025*F25 -> 7161.1771 | I25: =H25-G25 -> 7161.1771 | J25: =H25*12 -> 85934.125
A26: 19 | B26: FARUQ ATOFARATI | C26: PA (SPECIAL DUTIES) TO DG | D26: 10(7) | E26: 293029.67 | F26: 240874.58 | H26: =0.025*F26 -> 6021.8646 | I26: =H26-G26 -> 6021.8646 | J26: =H26*12 -> 72262.375
A27: 20 | B27: RASHEEDAT DAIBU | C27: SENIOR INFO. OFFICER | D27: 10(8) | E27: 300965.58 | F27: 240874.58 | H27: =0.025*F27 -> 6021.8646 | I27: =H27-G27 -> 6021.8646 | J27: =H27*12 -> 72262.375
A28: 21 | B28: ELIZABETH OGECHUKWU ONYEAKU | C28: ICT OFFICER | D28: 9(10) | E28: 277798 | F28: 227615.75 | H28: =0.025*F28 -> 5690.3938 | I28: =H28-G28 -> 5690.3938 | J28: =H28*12 -> 68284.725
A29: 22 | B29: VICTOR ASUKWO | C29: ICT OFFICER | D29: 9(10) | E29: 277798 | F29: 227615.75 | H29: =0.025*F29 -> 5690.3938 | I29: =H29-G29 -> 5690.3938 | J29: =H29*12 -> 68284.725
A30: 23 | B30: NNANDI LIVINUS ATURE | C30: RESEARCH ASSISTANT | D30: 9(10) | E30: 277798 | F30: 227615.75 | H30: =0.025*F30 -> 5690.3938 | I30: =H30-G30 -> 5690.3938 | J30: =H30*12 -> 68284.725
A31: 24 | B31: ABDULRAHMAN A SULAIMAN | C31: STORE OFFICER | D31: 9(9) | E31: 270481.67 | F31: 222674.58 | H31: =0.025*F31 -> 5566.8646 | I31: =H31-G31 -> 5566.8646 | J31: =H31*12 -> 66802.375
A32: 25 | B32: DARE SHEU MAGBON | C32: ADMINISTRATION OFFICER | D32: 9(8) | E32: 263165.33 | F32: 217733.42 | H32: =0.025*F32 -> 5443.3354 | I32: =H32-G32 -> 5443.3354 | J32: =H32*12 -> 65320.025
A33: 26 | B33: ABUBAKAR SULAIMAN SODEEQ | C33: ADMINISTRATION OFFICER | D33: 9(8) | E33: 263165.33 | F33: 217733.42 | H33: =0.025*F33 -> 5443.3354 | I33: =H33-G33 -> 5443.3354 | J33: =H33*12 -> 65320.025
A34: 27 | B34: JIMOH ADEBAYO ZAKA | C34: ASST. OFFICER/COMM | D34: 9(10) | E34: 277798 | F34: 227615.75 | G34: 3653.5 | H34: =0.025*F34 -> 5690.3938 | I34: =H34-G34 -> 2036.8937 | J34: =H34*12 -> 68284.725
A35: 28 | B35: ABDULMUSHIN TAWFIQ LADAN | C35: ICT OFFICER | D35: 9(8) | E35: 263165.33 | F35: 217733.42 | H35: =0.025*F35 -> 5443.3354 | I35: =H35-G35 -> 5443.3354 | J35: =H35*12 -> 65320.025
A36: 29 | B36: MOHAMMED BELLO | C36: PROTOCOL ASSISTANT | D36: 9(8) | E36: 263165.33 | F36: 217733.42 | H36: =0.025*F36 -> 5443.3354 | I36: =H36-G36 -> 5443.3354 | J36: =H36*12 -> 65320.025
A37: 30 | B37: HARUNA JIBRIL AMEH | C37: ASST. ADMIN. OFFICER | D37: 8(9) | E37: 230631.92 | F37: 196364.42 | H37: =0.025*F37 -> 4909.1104 | I37: =H37-G37 -> 4909.1104 | J37: =H37*12 -> 58909.325
A38: 31 | B38: RAMATU IBRAHIM ABDULRAHEEM | C38: INFORMATION OFFICER | D38: 8(8) | E38: 224459.75 | F38: 192179.42 | H38: =0.025*F38 -> 4804.4854 | I38: =H38-G38 -> 4804.4854 | J38: =H38*12 -> 57653.825
B39: TOTAL | C39: 31 | E39: =SUM(E8:E38) -> 14073004 | F39: =SUM(F8:F38) -> 10664632 | G39: =SUM(G8:G38) -> 48931.973 | H39: =SUM(H8:H38) -> 211712.9 | I39: =SUM(I8:I38) -> 162780.92 | J39: =SUM(J8:J38) -> 2540554.8
B41: INTERNAL AUDIT
A42: 1 | B42: OSANAIYE DAVID AKINYEMI | C42: DIRECTOR INTERNAL AUDIT | D42: 17(9) | E42: 1435720 | F42: 1086777.1 | H42: =0.025*F42 -> 27169.427 | I42: =H42-G42 -> 27169.427
A43: 2 | B43: JAMILA ABDUL | C43: SENIOR INTERNAL AUDITOR | D43: 10(8) | E43: 300965.58 | F43: 240874.58 | H43: =0.025*F43 -> 6021.8646 | I43: =H43-G43 -> 6021.8646
A44: 3 | B44: IJEOMA EWELUKWA | C44: SENIOR INTERNAL AUDITOR | D44: 10(9) | E44: 308901.5 | F44: 246171.17 | H44: =0.025*F44 -> 6154.2792 | I44: =H44-G44 -> 6154.2792
A45: 4 | B45: YUSUF YUSUF DAYYABU | C45: INERNAL AUDIT OFFICER | D45: 9(8) | E45: 263165.33 | F45: 217733.42 | H45: =0.025*F45 -> 5443.3354 | I45: =H45-G45 -> 5443.3354
C46: 4 | E46: =SUM(E42:E45) -> 2308752.4 | F46: =SUM(F42:F45) -> 1791556.2 | G46: =SUM(G42:G45) -> 0 | H46: =SUM(H42:H45) -> 44788.906 | I46: =SUM(I42:I45) -> 44788.906 | J46: =SUM(J42:J45) -> 0
B48: LEG. SUPPORT SEVICES
A49: 1 | B49: BETHEL UZOMA IHUGBA | C49: DEPUTY DIRECTOR, LEGAL RESEARCH | D49: 16(9) | E49: 762373.17 | F49: 554669.5 | H49: =0.025*F49 -> 13866.737 | I49: =H49-G49 -> 13866.737
A50: 2 | B50: OGUCHE SAMUEL | C50: SNR RESEARCH FELLOW | D50: 15(9) | E50: 620675.58 | F50: 459010.5 | H50: =0.025*F50 -> 11475.263 | I50: =H50-G50 -> 11475.263
A51: 3 | B51: IBRAHIM USMAN | C51: SNR RESEARCH FELLOW | D51: 15(9) | E51: 620675.58 | F51: 459010.5 | G51: 8380.2271 | H51: =0.025*F51 -> 11475.263 | I51: =H51-G51 -> 3095.0354 | J51: =H51*12 -> 137703.15
A52: 4 | B52: DR MOHAMMED O. AMALI | C52: SNR RESEARCH FELLOW | D52: 15(8) | E52: 601396.83 | F52: 445995.83 | H52: =0.025*F52 -> 11149.896 | I52: =H52-G52 -> 11149.896
A53: 5 | B53: YAHAYA SHAMSU | C53: SNR RESEARCH FELLOW | D53: 15(7) | E53: 582118.08 | F53: 432981.08 | H53: =0.025*F53 -> 10824.527 | I53: =H53-G53 -> 10824.527
A54: 6 | B54: BILKIS S. LAWAL-GAMBARI | C54: RESEARCH OFFICER | D54: 10(9) | E54: 308901.5 | F54: 246171.17 | H54: =0.025*F54 -> 6154.2792 | I54: =H54-G54 -> 6154.2792
A55: 7 | B55: ZAINAB AKINDE | C55: RESEARCH OFFICER | D55: 9(9) | E55: 270481.67 | F55: 222674.58 | H55: =0.025*F55 -> 5566.8646 | I55: =H55-G55 -> 5566.8646
A56: 8 | B56: GUNAT NANSAK MARK | C56: RESEARCH OFFICER | D56: 9(9) | E56: 270481.67 | F56: 222674.58 | H56: =0.025*F56 -> 5566.8646 | I56: =H56-G56 -> 5566.8646
B57: TOTAL | C57: 8 | E57: =SUM(E49:E56) -> 4037104.1 | F57: =SUM(F49:F56) -> 3043187.8 | G57: =SUM(G49:G56) -> 8380.2271 | H57: =SUM(H49:H56) -> 76079.694 | I57: =SUM(I49:I56) -> 67699.467 | J57: =SUM(J49:J56) -> 137703.15
B59: LEGAL SERVICES
A60: 1 | B60: DR SHUAIBU DANWANKA | C60: DIRECTOR LEGAL SERVICES | D60: 17(9) | E60: 1435720 | F60: 1086777.1 | H60: =0.025*F60 -> 27169.427 | I60: =H60-G60 -> 27169.427
A61: 2 | B61: ABDULSALAM BAKO | C61: MANAGER, LEGAL SERVICES | D61: 15 (9) | E61: 620675.58 | F61: 459010.5 | H61: =0.025*F61 -> 11475.263 | I61: =H61-G61 -> 11475.263
B62: TOTAL | C62: 2 | E62: =SUM(E60:E61) -> 2056395.6 | F62: =SUM(F60:F61) -> 1545787.6 | G62: =SUM(G60:G61) -> 0 | H62: =SUM(H60:H61) -> 38644.69 | I62: =SUM(I60:I61) -> 38644.69 | J62: =SUM(J60:J61) -> 0
B64: DEMOCRACY & GOVERNANCE
A65: 1 | B65: NGARA CHRISTOPHER OCHANJA | C65: DEP DIR DEM & GOVERNANCE | D65: 16(9) | E65: 762373.17 | F65: 554669.5 | G65: 10293.398 | H65: =0.025*F65 -> 13866.737 | I65: =H65-G65 -> 3573.3396 | J65: =H65*12 -> 166400.85
A66: 2 | B66: EJALONIBU GANIYU LAYI | C66: RESEARCH FELLOW 1 | D66: 14(9) | E66: 456622.25 | F66: 347715.92 | H66: =0.025*F66 -> 8692.8979 | I66: =H66-G66 -> 8692.8979
A67: 3 | B67: UDEFUNA NNADOZIE PATRICK | C67: RESEARCH OFFICER | D67: 12(9) | E67: 377895.17 | F67: 294662.92 | H67: =0.025*F67 -> 7366.5729 | I67: =H67-G67 -> 7366.5729
A68: 4 | B68: SHAFIU YAHYA MIKAIL | C68: PRINCIPAL RESEARCH OFFICER | D68: 12(9) | E68: 377895.17 | F68: 294662.92 | H68: =0.025*F68 -> 7366.5729 | I68: =H68-G68 -> 7366.5729
A69: 5 | B69: HASSAN YERIMA | C69: PRINCIPAL RESEARCH OFFICER | D69: 12(9) | E69: 377895.17 | F69: 294662.92 | H69: =0.025*F69 -> 7366.5729 | I69: =H69-G69 -> 7366.5729
A70: 6 | B70: HAUWA PATE SADIQ | C70: PRINCIPAL PROGRAMME OFFICER | D70: 12(10) | E70: 390086.5 | F70: 302878.67 | H70: =0.025*F70 -> 7571.9667 | I70: =H70-G70 -> 7571.9667
A71: 7 | B71: KOLAPO Q. ABAYOMI | C71: RESEARCH OFFICER | D71: 10(9) | E71: 308901.5 | F71: 246171.17 | H71: =0.025*F71 -> 6154.2792 | I71: =H71-G71 -> 6154.2792
B72: TOTAL | C72: 7 | E72: =SUM(E65:E71) -> 3051668.9 | F72: =SUM(F65:F71) -> 2335424 | G72: =SUM(G65:G71) -> 10293.398 | H72: =SUM(H65:H71) -> 58385.6 | I72: =SUM(I65:I71) -> 48092.202 | J72: =SUM(J65:J71) -> 166400.85
B74: DEPARTMENT OF STUDIES
A75: 1 | B75: DR ASIMIYU G. ABIOLA | C75: DIRECTOR POST GRADUATE | D75: 17(9) | E75: 1435720 | F75: 1086777.1 | H75: =0.025*F75 -> 27169.427 | I75: =H75-G75 -> 27169.427
A76: 2 | B76: DR. HADIZA SAIDU | C76: ASSISTANT DIRECTOR | D76: 15(7) | E76: 582118.08 | F76: 445995.83 | H76: =0.025*F76 -> 11149.896 | I76: =H76-G76 -> 11149.896
A77: 3 | B77: ANTHONY EDET | C77: CHIEF PROGRAMMES OFFICER | D77: 14(10) | E77: 470498 | F77: 357066.67 | G77: 6154.3229 | H77: =0.025*F77 -> 8926.6667 | I77: =H77-G77 -> 2772.3438 | J77: =H77*12 -> 107120
A78: 4 | B78: IGWE STACY | C78: PRINC. PROGRAMME OFFICER | D78: 12(8) | E78: 365703.83 | F78: 286447.08 | H78: =0.025*F78 -> 7161.1771 | I78: =H78-G78 -> 7161.1771
A79: 5 | B79: OLANIYAN TAIWO ABINBOLA | C79: PROGRAMME OFFICER | D79: 9(8) | E79: 263165.33 | F79: 222674.58 | H79: =0.025*F79 -> 5566.8646 | I79: =H79-G79 -> 5566.8646
A80: 6 | B80: AMINAT JUMOKE SULAIMON | C80: AST. PROGRAMME OFFICER | D80: 8(9) | E80: 230631.92 | F80: 196364.42 | H80: =0.025*F80 -> 4909.1104 | I80: =H80-G80 -> 4909.1104
B81: TOTAL | C81: 6 | E81: =SUM(E75:E80) -> 3347837.2 | F81: =SUM(F75:F80) -> 2595325.7 | G81: =SUM(G75:G80) -> 6154.3229 | H81: =SUM(H75:H80) -> 64883.142 | I81: =SUM(I75:I80) -> 58728.819 | J81: =SUM(J75:J80) -> 107120
B83: ECON. DEV. & SOC. RESEARCH
A84: 1 | B84: DR AUGUSTINE C. OSIGWE | C84: SNR RESEARCH FELLOW | D84: 17(7) | E84: ='[3]Annual & Monthly'!$H$44 -> 1352042.7 | F84: 1025768.3 | G84: 18254.975 | H84: =0.025*F84 -> 25644.208 | I84: =H84-G84 -> 7389.2333 | J84: =H84*12 -> 307730.5
A85: 2 | B85: TERFA WILLIAMS ABRAHAM | C85: DEP. DIRECTOR ECON & SOCIAL RES | D85: 16(7) | E85: 716034 | F85: 523386.5 | H85: =0.025*F85 -> 13084.663 | I85: =H85-G85 -> 13084.663
A86: 3 | B86: OMOJU OLUWASOLA EMMANUEL | C86: SNR RESEARCH FELLOW | D86: 15(8) | E86: 601396.83 | F86: 445995.83 | H86: =0.025*F86 -> 11149.896 | I86: =H86-G86 -> 11149.896
A87: 4 | B87: IBE EZECHI CYRIACUS | C87: RESEARCH FELLOW 1 | D87: 14(9) | E87: 456622.25 | F87: 442746.5 | H87: =0.025*F87 -> 11068.663 | I87: =H87-G87 -> 11068.663
A88: 5 | B88: OSIKHEN LEO IGBANOI | C88: RESEARCH FELLOW 1 | D88: 14(9) | E88: 456622.25 | F88: 442746.5 | H88: =0.025*F88 -> 11068.663 | I88: =H88-G88 -> 11068.663
A89: 6 | B89: OKUNGBOWA OSARETIN GODSPOWER | C89: RESEARCH FELLOW 1 | D89: 14(8) | E89: 442746.5 | F89: 428870.75 | H89: =0.025*F89 -> 10721.769 | I89: =H89-G89 -> 10721.769
A90: 7 | B90: YUSUF IBRAHIM | C90: PRINCIPAL RESEARCH OFFICER | D90: 12(9) | E90: 377895.17 | F90: 294662.92 | H90: =0.025*F90 -> 7366.5729 | I90: =H90-G90 -> 7366.5729
A91: 8 | B91: MUSTAPHA RAFIU AYOBANJI | C91: RESEARCH FELLOW 11 | D91: 13(8) | E91: 403137.92 | F91: 311673.25 | G91: 5259.7437 | H91: =0.025*F91 -> 7791.8313 | I91: =H91-G91 -> 2532.0875 | J91: =H91*12 -> 93501.975
A92: 9 | B92: MARYAM MUSA SADA | C92: ASSIT. RESEARCH OFFICER | D92: 10(9) | E92: 308901.5 | F92: 246171.17 | H92: =0.025*F92 -> 6154.2792 | I92: =H92-G92 -> 6154.2792
A93: 10 | B93: CHARITY EZENWAJIOBI | C93: REASEARCH. ASST. | D93: 8(10) | E93: 236804.08 | F93: 200549.42 | H93: =0.025*F93 -> 5013.7354 | I93: =H93-G93 -> 5013.7354
B94: TOTAL | C94: 10 | E94: =SUM(E84:E93) -> 5352203.2 | F94: =SUM(F84:F93) -> 4362571.2 | G94: =SUM(G84:G93) -> 23514.719 | H94: =SUM(H84:H93) -> 109064.28 | I94: =SUM(I84:I93) -> 85549.56 | J94: =SUM(J84:J93) -> 401232.47
B96: TRAINING & INT''L COOP
A97: 1 | B97: AKINSANMI ADEJOKE OLUKEMI | C97: Ag. DIR. TRAINING & IC | D97: 17(8) | E97: 1393881.3 | F97: 1056272.8 | G97: 18254.975 | H97: =0.025*F97 -> 26406.821 | I97: =H97-G97 -> 8151.8458 | J97: =H97*12 -> 316881.85
A98: 2 | B98: MOHAMMED R. ADAMU | C98: CHIEF TRAINING OFFICER | D98: 14(10) | E98: 470498 | F98: 357066.67 | H98: =0.025*F98 -> 8926.6667 | I98: =H98-G98 -> 8926.6667 | J98: =H98*12 -> 107120
A99: 3 | B99: EROMOSELE OMONIGBO | C99: ASSIST. CHIEF PERSONNEL OFFICER | D99: 13(8) | E99: 403137.92 | F99: 311673.25 | G99: 5967.3062 | H99: =0.025*F99 -> 7791.8313 | I99: =H99-G99 -> 1824.525 | J99: =H99*12 -> 93501.975
A100: 4 | B100: OKECHUKWU UCHENNA HULDA | C100: PRINCIPALTRAINING OFFICER | D100: 12(10) | E100: 390086.5 | F100: 302878.67 | H100: =0.025*F100 -> 7571.9667 | I100: =H100-G100 -> 7571.9667 | J100: =H100*12 -> 90863.6
A101: 5 | B101: TASSNEEM IBRAHIM | C101: SENIOR PROGRAMME OFFICER | D101: 10(9) | E101: 308901.5 | F101: 246171.17 | H101: =0.025*F101 -> 6154.2792 | I101: =H101-G101 -> 6154.2792 | J101: =H101*12 -> 73851.35
B102: TOTAL | C102: 5 | E102: =SUM(E97:E101) -> 2966505.2 | F102: =SUM(F97:F101) -> 2274062.6 | G102: =SUM(G97:G101) -> 24222.281 | H102: =SUM(H97:H101) -> 56851.565 | I102: =SUM(I97:I101) -> 32629.283 | J102: =SUM(J97:J101) -> 682218.77
B104: LIBRARY & DOCUMENTATION
A105: 1 | B105: DR MAIMUNA IZAH | C105: INSITUTE LIBRARIAN | D105: 17(9) | E105: 1435720 | F105: 1086777.1 | G105: 0 | H105: =0.025*F105 -> 27169.427 | I105: =H105-G105 -> 27169.427
A106: 2 | B106: CATHERINE E. IKOKOH | C106: SNR RESEARCH FELLOW DOCU | D106: 16(9) | E106: 762373.17 | F106: 554669.5 | G106: 10293.398 | H106: =0.025*F106 -> 13866.737 | I106: =H106-G106 -> 3573.3396 | J106: =H106*12 -> 166400.85
A107: 3 | B107: ALIYU SANNI ABUBAKAR | C107: RESEARCH FELLOW 11 DATA & DOCU | D107: 13(11) | E107: 441804.92 | F107: 337730.83 | G107: 5954.6104 | H107: =0.025*F107 -> 8443.2708 | I107: =H107-G107 -> 2488.6604 | J107: =H107*12 -> 101319.25
A108: 4 | B108: CHINAKO N. ASOGWA | C108: RESEARCH FELLOW 11 DATA & DOCU | D108: 13(11) | E108: 441804.92 | F108: 337730.83 | H108: =0.025*F108 -> 8443.2708 | I108: =H108-G108 -> 8443.2708
...

Sheet Sheet17

Sheet Changes in PAYE (3)
A1: NATIONAL INSTITUTE FOR LEGISLATIVE AND DEMOCRATIC STUDIES
A2: NATIONAL ASSEMBLY ABUJA
A3: TAX COMPUTATION FOR 2022
A4: S/NO | B4: NAME | C4: MONTHLY TOTAL SALARY | D4: NO OF MONTHS | E4: ANNUAL SALARY GROSSED UP | F4: NATIONAL HOUSING SCHEME = 2.5% OF BASIC SALARY | G4: PENSION CONTRIBUTION = 8% OF CONSOLIDATED | H4: NHIS | I4: NET SALARY (EXC OF CRA) | M4: CRA=#200,000+(20% 0F NET SALARY (EXC OF CRA) | N4: TOTAL RELIEF | O4: CHARGEABLE INCOME | P4: FIRST N300,000 @ 7% | Q4: NEXT N300,000 @ 11% | R4: NEXT N500,000 @ 15% | S4: NEXT N500,000@ 19% | T4: NEXT N1,600,000 @ 21% | U4: ABOVE N3,200,000 @ 24% | V4: ANNUAL TAX PAYABLE | X4: MONTHLY TAX PAYABLE | Y4: MINIMUM TAX PAYABLE | Z4: NEW ACTUAL TAX PAYABLE | AA4: OLD ACTUAL TAX PAYABLE | AB4: INCREASE IN PAYE
A5: 1 | B5: DG'S OFFICE
A6: 3 | B6: PROF. ABUBAKAR O. SULAIMAN | C6: 2246372.1 | D6: 12 | E6: =C6*D6 -> 26956465 | G6: 0 | I6: =E6-F6-G6-H6 -> 26956465 | J6: 200000 | K6: 0.2 | L6: =I6*K6 -> 5391293 | M6: =J6+L6 -> 5591293 | N6: =F6+G6+H6+M6 -> 5591293 | O6: =E6-N6 -> 21365172 | P6: =IF(O6<300000,0.07*O6,21000) -> 21000 | Q6: =IF((O6-300000)<0,0,IF((O6-300000)<300000,0.11*(O6-300000),33000)) -> 33000 | R6: =IF((O6-600000)<0,0,IF((O6-600000)<500000,0.15*(O6-600000),75000)) -> 75000 | S6: =IF((O6-1100000)<0,0,IF((O6-1100000)<500000,0.19*(O6-1100000),95000)) -> 95000 | T6: =IF((O6-1600000)<0,0,IF((O6-1600000)<1600000,0.21*(O6-1600000),336000)) -> 336000 | U6: =24%*(O6-3200000) -> 4359641.3 | V6: =P6+Q6+R6+S6+T6+U6 -> 4919641.3 | W6: 12 | X6: =V6/W6 -> 409970.11 | Z6: =X6 -> 409970.11 | AA6: 350184.01 | AB6: =Z6-AA6 -> 59786.096
A7: 4 | B7: RAHEEM USMAN AYIGORO | C7: 1095306.8 | D7: 12 | E7: =C7*D7 -> 13143681 | G7: 869094.48 | I7: =E7-F7-G7-H7 -> 12274587 | J7: 200000 | K7: 0.2 | L7: =I7*K7 -> 2454917.3 | M7: =J7+L7 -> 2654917.3 | N7: =F7+G7+H7+M7 -> 3524011.8 | O7: =E7-N7 -> 9619669.2 | P7: =IF(O7<300000,0.07*O7,21000) -> 21000 | Q7: =IF((O7-300000)<0,0,IF((O7-300000)<300000,0.11*(O7-300000),33000)) -> 33000 | R7: =IF((O7-600000)<0,0,IF((O7-600000)<500000,0.15*(O7-600000),75000)) -> 75000 | S7: =IF((O7-1100000)<0,0,IF((O7-1100000)<500000,0.19*(O7-1100000),95000)) -> 95000 | T7: =IF((O7-1600000)<0,0,IF((O7-1600000)<1600000,0.21*(O7-1600000),336000)) -> 336000 | U7: =24%*(O7-3200000) -> 1540720.6 | V7: =P7+Q7+R7+S7+T7+U7 -> 2100720.6 | W7: 12 | X7: =V7/W7 -> 175060.05 | Z7: =X7 -> 175060.05 | AA7: 149812.26 | AB7: =Z7-AA7 -> 25247.788
A8: 5 | B8: MARIAM MOHAMMED BELLO | C8: 1463969.9 | D8: 12 | E8: =C8*D8 -> 17567639 | G8: 0 | I8: =E8-F8-G8-H8 -> 17567639 | J8: 200000 | K8: 0.2 | L8: =I8*K8 -> 3513527.8 | M8: =J8+L8 -> 3713527.8 | N8: =F8+G8+H8+M8 -> 3713527.8 | O8: =E8-N8 -> 13854111 | P8: =IF(O8<300000,0.07*O8,21000) -> 21000 | Q8: =IF((O8-300000)<0,0,IF((O8-300000)<300000,0.11*(O8-300000),33000)) -> 33000 | R8: =IF((O8-600000)<0,0,IF((O8-600000)<500000,0.15*(O8-600000),75000)) -> 75000 | S8: =IF((O8-1100000)<0,0,IF((O8-1100000)<500000,0.19*(O8-1100000),95000)) -> 95000 | T8: =IF((O8-1600000)<0,0,IF((O8-1600000)<1600000,0.21*(O8-1600000),336000)) -> 336000 | U8: =24%*(O8-3200000) -> 2556986.6 | V8: =P8+Q8+R8+S8+T8+U8 -> 3116986.6 | W8: 12 | X8: =V8/W8 -> 259748.89 | Z8: =X8 -> 259748.89 | AA8: 199922.31 | AB8: =Z8-AA8 -> 59826.572
A9: 6 | B9: DR IKEME ARTHUR J.O | C9: 1085306.8 | D9: 12 | E9: =C9*D9 -> 13023681 | F9: 166400.85 | G9: 869094.48 | I9: =E9-F9-G9-H9 -> 11988186 | J9: 200000 | K9: 0.2 | L9: =I9*K9 -> 2397637.1 | M9: =J9+L9 -> 2597637.1 | N9: =F9+G9+H9+M9 -> 3633132.5 | O9: =E9-N9 -> 9390548.5 | P9: =IF(O9<300000,0.07*O9,21000) -> 21000 | Q9: =IF((O9-300000)<0,0,IF((O9-300000)<300000,0.11*(O9-300000),33000)) -> 33000 | R9: =IF((O9-600000)<0,0,IF((O9-600000)<500000,0.15*(O9-600000),75000)) -> 75000 | S9: =IF((O9-1100000)<0,0,IF((O9-1100000)<500000,0.19*(O9-1100000),95000)) -> 95000 | T9: =IF((O9-1600000)<0,0,IF((O9-1600000)<1600000,0.21*(O9-1600000),336000)) -> 336000 | U9: =24%*(O9-3200000) -> 1485731.6 | V9: =P9+Q9+R9+S9+T9+U9 -> 2045731.6 | W9: 12 | X9: =V9/W9 -> 170477.64 | Z9: =X9 -> 170477.64 | AA9: 147687.53 | AB9: =Z9-AA9 -> 22790.11
A10: 7 | B10: ANDRAWUS MUSA | C10: 1019008.9 | D10: 12 | E10: =C10*D10 -> 12228107 | F10: 157015.95 | G10: 818602.64 | I10: =E10-F10-G10-H10 -> 11252488 | J10: 200000 | K10: 0.2 | L10: =I10*K10 -> 2250497.7 | M10: =J10+L10 -> 2450497.7 | N10: =F10+G10+H10+M10 -> 3426116.3 | O10: =E10-N10 -> 8801990.7 | P10: =IF(O10<300000,0.07*O10,21000) -> 21000 | Q10: =IF((O10-300000)<0,0,IF((O10-300000)<300000,0.11*(O10-300000),33000)) -> 33000 | R10: =IF((O10-600000)<0,0,IF((O10-600000)<500000,0.15*(O10-600000),75000)) -> 75000 | S10: =IF((O10-1100000)<0,0,IF((O10-1100000)<500000,0.19*(O10-1100000),95000)) -> 95000 | T10: =IF((O10-1600000)<0,0,IF((O10-1600000)<1600000,0.21*(O10-1600000),336000)) -> 336000 | U10: =24%*(O10-3200000) -> 1344477.8 | V10: =P10+Q10+R10+S10+T10+U10 -> 1904477.8 | W10: 12 | X10: =V10/W10 -> 158706.48 | Z10: =X10 -> 158706.48 | AA10: 129694.7 | AB10: =Z10-AA10 -> 29011.786
A11: 8 | B11: DR FRANCIS NDUM OJIE | C11: 1082595.5 | D11: 12 | E11: =C11*D11 -> 12991146 | F11: 133798.75 | G11: 693691.68 | I11: =E11-F11-G11-H11 -> 12163656 | J11: 200000 | K11: 0.2 | L11: =I11*K11 -> 2432731.1 | M11: =J11+L11 -> 2632731.1 | N11: =F11+G11+H11+M11 -> 3460221.5 | O11: =E11-N11 -> 9530924.5 | P11: =IF(O11<300000,0.07*O11,21000) -> 21000 | Q11: =IF((O11-300000)<0,0,IF((O11-300000)<300000,0.11*(O11-300000),33000)) -> 33000 | R11: =IF((O11-600000)<0,0,IF((O11-600000)<500000,0.15*(O11-600000),75000)) -> 75000 | S11: =IF((O11-1100000)<0,0,IF((O11-1100000)<500000,0.19*(O11-1100000),95000)) -> 95000 | T11: =IF((O11-1600000)<0,0,IF((O11-1600000)<1600000,0.21*(O11-1600000),336000)) -> 336000 | U11: =24%*(O11-3200000) -> 1519421.9 | V11: =P11+Q11+R11+S11+T11+U11 -> 2079421.9 | W11: 12 | X11: =V11/W11 -> 173285.16 | Z11: =X11 -> 173285.16 | AA11: 150463.11 | AB11: =Z11-AA11 -> 22822.046
A12: 9 | B12: ALI ABDULLAHI | C12: 780713.92 | D12: 12 | E12: =C12*D12 -> 9368567 | G12: 566070.72 | I12: =E12-F12-G12-H12 -> 8802496.3 | J12: 200000 | K12: 0.2 | L12: =I12*K12 -> 1760499.3 | M12: =J12+L12 -> 1960499.3 | N12: =F12+G12+H12+M12 -> 2526570 | O12: =E12-N12 -> 6841997 | P12: =IF(O12<300000,0.07*O12,21000) -> 21000 | Q12: =IF((O12-300000)<0,0,IF((O12-300000)<300000,0.11*(O12-300000),33000)) -> 33000 | R12: =IF((O12-600000)<0,0,IF((O12-600000)<500000,0.15*(O12-600000),75000)) -> 75000 | S12: =IF((O12-1100000)<0,0,IF((O12-1100000)<500000,0.19*(O12-1100000),95000)) -> 95000 | T12: =IF((O12-1600000)<0,0,IF((O12-1600000)<1600000,0.21*(O12-1600000),336000)) -> 336000 | U12: =24%*(O12-3200000) -> 874079.29 | V12: =P12+Q12+R12+S12+T12+U12 -> 1434079.3 | W12: 12 | X12: =V12/W12 -> 119506.61 | Z12: =X12 -> 119506.61 | AA12: 77666.446 | AB12: =Z12-AA12 -> 41840.161
A13: 10 | B13: EMILY EKHIDE | C13: 932595.5 | D13: 12 | E13: =C13*D13 -> 11191146 | G13: 693691.68 | I13: =E13-F13-G13-H13 -> 10497454 | J13: 200000 | K13: 0.2 | L13: =I13*K13 -> 2099490.9 | M13: =J13+L13 -> 2299490.9 | N13: =F13+G13+H13+M13 -> 2993182.5 | O13: =E13-N13 -> 8197963.5 | P13: =IF(O13<300000,0.07*O13,21000) -> 21000 | Q13: =IF((O13-300000)<0,0,IF((O13-300000)<300000,0.11*(O13-300000),33000)) -> 33000 | R13: =IF((O13-600000)<0,0,IF((O13-600000)<500000,0.15*(O13-600000),75000)) -> 75000 | S13: =IF((O13-1100000)<0,0,IF((O13-1100000)<500000,0.19*(O13-1100000),95000)) -> 95000 | T13: =IF((O13-1600000)<0,0,IF((O13-1600000)<1600000,0.21*(O13-1600000),336000)) -> 336000 | U13: =24%*(O13-3200000) -> 1199511.2 | V13: =P13+Q13+R13+S13+T13+U13 -> 1759511.2 | W13: 12 | X13: =V13/W13 -> 146625.94 | Z13: =X13 -> 146625.94 | AA13: 141011.99 | AB13: =Z13-AA13 -> 5613.9468
A14: 11 | B14: DORIS DAKDA AARON | C14: 948165.25 | D14: 12 | E14: =C14*D14 -> 11377983 | G14: 535838.64 | I14: =E14-F14-G14-H14 -> 10842144 | J14: 200000 | K14: 0.2 | L14: =I14*K14 -> 2168428.9 | M14: =J14+L14 -> 2368428.9 | N14: =F14+G14+H14+M14 -> 2904267.5 | O14: =E14-N14 -> 8473715.5 | P14: =IF(O14<300000,0.07*O14,21000) -> 21000 | Q14: =IF((O14-300000)<0,0,IF((O14-300000)<300000,0.11*(O14-300000),33000)) -> 33000 | R14: =IF((O14-600000)<0,0,IF((O14-600000)<500000,0.15*(O14-600000),75000)) -> 75000 | S14: =IF((O14-1100000)<0,0,IF((O14-1100000)<500000,0.19*(O14-1100000),95000)) -> 95000 | T14: =IF((O14-1600000)<0,0,IF((O14-1600000)<1600000,0.21*(O14-1600000),336000)) -> 336000 | U14: =24%*(O14-3200000) -> 1265691.7 | V14: =P14+Q14+R14+S14+T14+U14 -> 1825691.7 | W14: 12 | X14: =V14/W14 -> 152140.98 | Z14: =X14 -> 152140.98 | AA14: 131753.41 | AB14: =Z14-AA14 -> 20387.568
A15: 12 | B15: ABDULSALAM S. MUSTAPHA | C15: 830713.92 | D15: 12 | E15: =C15*D15 -> 9968567 | G15: 672685.36 | I15: =E15-F15-G15-H15 -> 9295881.6 | J15: 200000 | K15: 0.2 | L15: =I15*K15 -> 1859176.3 | M15: =J15+L15 -> 2059176.3 | N15: =F15+G15+H15+M15 -> 2731861.7 | O15: =E15-N15 -> 7236705.3 | P15: =IF(O15<300000,0.07*O15,21000) -> 21000 | Q15: =IF((O15-300000)<0,0,IF((O15-300000)<300000,0.11*(O15-300000),33000)) -> 33000 | R15: =IF((O15-600000)<0,0,IF((O15-600000)<500000,0.15*(O15-600000),75000)) -> 75000 | S15: =IF((O15-1100000)<0,0,IF((O15-1100000)<500000,0.19*(O15-1100000),95000)) -> 95000 | T15: =IF((O15-1600000)<0,0,IF((O15-1600000)<1600000,0.21*(O15-1600000),336000)) -> 336000 | U15: =24%*(O15-3200000) -> 968809.27 | V15: =P15+Q15+R15+S15+T15+U15 -> 1528809.3 | W15: 12 | X15: =V15/W15 -> 127400.77 | Z15: =X15 -> 127400.77 | AA15: 106452 | AB15: =Z15-AA15 -> 20948.773
A16: 13 | B16: PERCY TERFA GBAHABO | C16: 682419.5 | D16: 12 | E16: =C16*D16 -> 8189034 | G16: 519697.28 | I16: =E16-F16-G16-H16 -> 7669336.7 | J16: 200000 | K16: 0.2 | L16: =I16*K16 -> 1533867.3 | M16: =J16+L16 -> 1733867.3 | N16: =F16+G16+H16+M16 -> 2253564.6 | O16: =E16-N16 -> 5935469.4 | P16: =IF(O16<300000,0.07*O16,21000) -> 21000 | Q16: =IF((O16-300000)<0,0,IF((O16-300000)<300000,0.11*(O16-300000),33000)) -> 33000 | R16: =IF((O16-600000)<0,0,IF((O16-600000)<500000,0.15*(O16-600000),75000)) -> 75000 | S16: =IF((O16-1100000)<0,0,IF((O16-1100000)<500000,0.19*(O16-1100000),95000)) -> 95000 | T16: =IF((O16-1600000)<0,0,IF((O16-1600000)<1600000,0.21*(O16-1600000),336000)) -> 336000 | U16: =24%*(O16-3200000) -> 656512.65 | V16: =P16+Q16+R16+S16+T16+U16 -> 1216512.7 | W16: 12 | X16: =V16/W16 -> 101376.05 | Z16: =X16 -> 101376.05 | AA16: 77470.374 | AB16: =Z16-AA16 -> 23905.68
A17: 14 | B17: HASSANA AHMED IBRAHIM | C17: 846725.08 | D17: 12 | E17: =C17*D17 -> 10160701 | F17: 98713.475 | G17: 505656.08 | I17: =E17-F17-G17-H17 -> 9556331.4 | J17: 200000 | K17: 0.2 | L17: =I17*K17 -> 1911266.3 | M17: =J17+L17 -> 2111266.3 | N17: =F17+G17+H17+M17 -> 2715635.8 | O17: =E17-N17 -> 7445065.2 | P17: =IF(O17<300000,0.07*O17,21000) -> 21000 | Q17: =IF((O17-300000)<0,0,IF((O17-300000)<300000,0.11*(O17-300000),33000)) -> 33000 | R17: =IF((O17-600000)<0,0,IF((O17-600000)<500000,0.15*(O17-600000),75000)) -> 75000 | S17: =IF((O17-1100000)<0,0,IF((O17-1100000)<500000,0.19*(O17-1100000),95000)) -> 95000 | T17: =IF((O17-1600000)<0,0,IF((O17-1600000)<1600000,0.21*(O17-1600000),336000)) -> 336000 | U17: =24%*(O17-3200000) -> 1018815.6 | V17: =P17+Q17+R17+S17+T17+U17 -> 1578815.6 | W17: 12 | X17: =V17/W17 -> 131567.97 | Z17: =X17 -> 131567.97 | AA17: 113474.9 | AB17: =Z17-AA17 -> 18093.066
A18: 15 | B18: IKIP LEBO | C18: 567472.75 | D18: 12 | E18: =C18*D18 -> 6809673 | F18: 93501.975 | G18: 477573.84 | I18: =E18-F18-G18-H18 -> 6238597.2 | J18: 200000 | K18: 0.2 | L18: =I18*K18 -> 1247719.4 | M18: =J18+L18 -> 1447719.4 | N18: =F18+G18+H18+M18 -> 2018795.3 | O18: =E18-N18 -> 4790877.7 | P18: =IF(O18<300000,0.07*O18,21000) -> 21000 | Q18: =IF((O18-300000)<0,0,IF((O18-300000)<300000,0.11*(O18-300000),33000)) -> 33000 | R18: =IF((O18-600000)<0,0,IF((O18-600000)<500000,0.15*(O18-600000),75000)) -> 75000 | S18: =IF((O18-1100000)<0,0,IF((O18-1100000)<500000,0.19*(O18-1100000),95000)) -> 95000 | T18: =IF((O18-1600000)<0,0,IF((O18-1600000)<1600000,0.21*(O18-1600000),336000)) -> 336000 | U18: =24%*(O18-3200000) -> 381810.66 | V18: =P18+Q18+R18+S18+T18+U18 -> 941810.66 | W18: 12 | X18: =V18/W18 -> 78484.222 | Z18: =X18 -> 78484.222 | AA18: 61040.235 | AB18: =Z18-AA18 -> 17443.986
A19: 16 | B19: ALABI ADESINA MUHYDEEN | C19: 617472.75 | D19: 12 | E19: =C19*D19 -> 7409673 | F19: 0 | G19: 477573.84 | I19: =E19-F19-G19-H19 -> 6932099.2 | J19: 200000 | K19: 0.2 | L19: =I19*K19 -> 1386419.8 | M19: =J19+L19 -> 1586419.8 | N19: =F19+G19+H19+M19 -> 2063993.7 | O19: =E19-N19 -> 5345679.3 | P19: =IF(O19<300000,0.07*O19,21000) -> 21000 | Q19: =IF((O19-300000)<0,0,IF((O19-300000)<300000,0.11*(O19-300000),33000)) -> 33000 | R19: =IF((O19-600000)<0,0,IF((O19-600000)<500000,0.15*(O19-600000),75000)) -> 75000 | S19: =IF((O19-1100000)<0,0,IF((O19-1100000)<500000,0.19*(O19-1100000),95000)) -> 95000 | T19: =IF((O19-1600000)<0,0,IF((O19-1600000)<1600000,0.21*(O19-1600000),336000)) -> 336000 | U19: =24%*(O19-3200000) -> 514963.04 | V19: =P19+Q19+R19+S19+T19+U19 -> 1074963 | W19: 12 | X19: =V19/W19 -> 89580.253 | Z19: =X19 -> 89580.253 | AA19: 70640.235 | AB19: =Z19-AA19 -> 18940.018
A20: 17 | B20: BASSEY NSONGURUA UDOFIA | C20: 802846.58 | D20: 12 | E20: =C20*D20 -> 9634159 | F20: 93328.325 | G20: 476637.28 | I20: =E20-F20-G20-H20 -> 9064193.4 | J20: 200000 | K20: 0.2 | L20: =I20*K20 -> 1812838.7 | M20: =J20+L20 -> 2012838.7 | N20: =F20+G20+H20+M20 -> 2582804.3 | O20: =E20-N20 -> 7051354.7 | P20: =IF(O20<300000,0.07*O20,21000) -> 21000 | Q20: =IF((O20-300000)<0,0,IF((O20-300000)<300000,0.11*(O20-300000),33000)) -> 33000 | R20: =IF((O20-600000)<0,0,IF((O20-600000)<500000,0.15*(O20-600000),75000)) -> 75000 | S20: =IF((O20-1100000)<0,0,IF((O20-1100000)<500000,0.19*(O20-1100000),95000)) -> 95000 | T20: =IF((O20-1600000)<0,0,IF((O20-1600000)<1600000,0.21*(O20-1600000),336000)) -> 336000 | U20: =24%*(O20-3200000) -> 924325.13 | V20: =P20+Q20+R20+S20+T20+U20 -> 1484325.1 | W20: 12 | X20: =V20/W20 -> 123693.76 | Z20: =X20 -> 123693.76 | AA20: 106297.15 | AB20: =Z20-AA20 -> 17396.611
A21: 18 | B21: ADUGBA RICHARD TERSEER | C21: 702846.58 | D21: 12 | E21: =C21*D21 -> 8434159 | G21: 463356.16 | I21: =E21-F21-G21-H21 -> 7970802.8 | J21: 200000 | K21: 0.2 | L21: =I21*K21 -> 1594160.6 | M21: =J21+L21 -> 1794160.6 | N21: =F21+G21+H21+M21 -> 2257516.7 | O21: =E21-N21 -> 6176642.3 | P21: =IF(O21<300000,0.07*O21,21000) -> 21000 | Q21: =IF((O21-300000)<0,0,IF((O21-300000)<300000,0.11*(O21-300000),33000)) -> 33000 | R21: =IF((O21-600000)<0,0,IF((O21-600000)<500000,0.15*(O21-600000),75000)) -> 75000 | S21: =IF((O21-1100000)<0,0,IF((O21-1100000)<500000,0.19*(O21-1100000),95000)) -> 95000 | T21: =IF((O21-1600000)<0,0,IF((O21-1600000)<1600000,0.21*(O21-1600000),336000)) -> 336000 | U21: =24%*(O21-3200000) -> 714394.15 | V21: =P21+Q21+R21+S21+T21+U21 -> 1274394.1 | W21: 12 | X21: =V21/W21 -> 106199.51 | Z21: =X21 -> 106199.51 | AA21: 82601.205 | AB21: =Z21-AA21 -> 23598.307
A22: 19 | B22: LUCKY AGWOM | C22: 754993.58 | D22: 12 | E22: =C22*D22 -> 9059923 | G22: 436793.84 | I22: =E22-F22-G22-H22 -> 8623129.2 | J22: 200000 | K22: 0.2 | L22: =I22*K22 -> 1724625.8 | M22: =J22+L22 -> 1924625.8 | N22: =F22+G22+H22+M22 -> 2361419.7 | O22: =E22-N22 -> 6698503.3 | P22: =IF(O22<300000,0.07*O22,21000) -> 21000 | Q22: =IF((O22-300000)<0,0,IF((O22-300000)<300000,0.11*(O22-300000),33000)) -> 33000 | R22: =IF((O22-600000)<0,0,IF((O22-600000)<500000,0.15*(O22-600000),75000)) -> 75000 | S22: =IF((O22-1100000)<0,0,IF((O22-1100000)<500000,0.19*(O22-1100000),95000)) -> 95000 | T22: =IF((O22-1600000)<0,0,IF((O22-1600000)<1600000,0.21*(O22-1600000),336000)) -> 336000 | U22: =24%*(O22-3200000) -> 839640.8 | V22: =P22+Q22+R22+S22+T22+U22 -> 1399640.8 | W22: 12 | X22: =V22/W22 -> 116636.73 | Z22: =X22 -> 116636.73 | AA22: 98711.115 | AB22: =Z22-AA22 -> 17925.619
A23: 20 | B23: IDRIS IBRAHIM | C23: 564993.58 | D23: 12 | E23: =C23*D23 -> 6779923 | G23: 436793.84 | I23: =E23-F23-G23-H23 -> 6343129.2 | J23: 200000 | K23: 0.2 | L23: =I23*K23 -> 1268625.8 | M23: =J23+L23 -> 1468625.8 | N23: =F23+G23+H23+M23 -> 1905419.7 | O23: =E23-N23 -> 4874503.3 | P23: =IF(O23<300000,0.07*O23,21000) -> 21000 | Q23: =IF((O23-300000)<0,0,IF((O23-300000)<300000,0.11*(O23-300000),33000)) -> 33000 | R23: =IF((O23-600000)<0,0,IF((O23-600000)<500000,0.15*(O23-600000),75000)) -> 75000 | S23: =IF((O23-1100000)<0,0,IF((O23-1100000)<500000,0.19*(O23-1100000),95000)) -> 95000 | T23: =IF((O23-1600000)<0,0,IF((O23-1600000)<1600000,0.21*(O23-1600000),336000)) -> 336000 | U23: =24%*(O23-3200000) -> 401880.8 | V23: =P23+Q23+R23+S23+T23+U23 -> 961880.8 | W23: 12 | X23: =V23/W23 -> 80156.733 | Z23: =X23 -> 80156.733 | AA23: 62231.115 | AB23: =Z23-AA23 -> 17925.619
A24: 21 | B24: FARUQ ATOFARATI | C24: 641140.67 | D24: 12 | E24: =C24*D24 -> 7693688 | G24: 365895.04 | I24: =E24-F24-G24-H24 -> 7327793 | J24: 200000 | K24: 0.2 | L24: =I24*K24 -> 1465558.6 | M24: =J24+L24 -> 1665558.6 | N24: =F24+G24+H24+M24 -> 2031453.6 | O24: =E24-N24 -> 5662234.4 | P24: =IF(O24<300000,0.07*O24,21000) -> 21000 | Q24: =IF((O24-300000)<0,0,IF((O24-300000)<300000,0.11*(O24-300000),33000)) -> 33000 | R24: =IF((O24-600000)<0,0,IF((O24-600000)<500000,0.15*(O24-600000),75000)) -> 75000 | S24: =IF((O24-1100000)<0,0,IF((O24-1100000)<500000,0.19*(O24-1100000),95000)) -> 95000 | T24: =IF((O24-1600000)<0,0,IF((O24-1600000)<1600000,0.21*(O24-1600000),336000)) -> 336000 | U24: =24%*(O24-3200000) -> 590936.25 | V24: =P24+Q24+R24+S24+T24+U24 -> 1150936.2 | W24: 12 | X24: =V24/W24 -> 95911.354 | Z24: =X24 -> 95911.354 | AA24: 80347.427 | AB24: =Z24-AA24 -> 15563.927
A25: 22 | B25: RASHEEDAT DAIBU | C25: 441140.67 | D25: 12 | E25: =C25*D25 -> 5293688 | G25: 365895.04 | I25: =E25-F25-G25-H25 -> 4927793 | J25: 200000 | K25: 0.2 | L25: =I25*K25 -> 985558.59 | M25: =J25+L25 -> 1185558.6 | N25: =F25+G25+H25+M25 -> 1551453.6 | O25: =E25-N25 -> 3742234.4 | P25: =IF(O25<300000,0.07*O25,21000) -> 21000 | Q25: =IF((O25-300000)<0,0,IF((O25-300000)<300000,0.11*(O25-300000),33000)) -> 33000 | R25: =IF((O25-600000)<0,0,IF((O25-600000)<500000,0.15*(O25-600000),75000)) -> 75000 | S25: =IF((O25-1100000)<0,0,IF((O25-1100000)<500000,0.19*(O25-1100000),95000)) -> 95000 | T25: =IF((O25-1600000)<0,0,IF((O25-1600000)<1600000,0.21*(O25-1600000),336000)) -> 336000 | U25: =24%*(O25-3200000) -> 130136.25 | V25: =P25+Q25+R25+S25+T25+U25 -> 690136.25 | W25: 12 | X25: =V25/W25 -> 57511.354 | Z25: =X25 -> 57511.354 | AA25: 42537.332 | AB25: =Z25-AA25 -> 14974.022
A26: 23 | B26: ELIZABETH OGECHUKWU ONYEAKU | C26: 415320.67 | D26: 12 | E26: =C26*D26 -> 4983848 | G26: 341107.84 | I26: =E26-F26-G26-H26 -> 4642740.2 | J26: 200000 | K26: 0.2 | L26: =I26*K26 -> 928548.03 | M26: =J26+L26 -> 1128548 | N26: =F26+G26+H26+M26 -> 1469655.9 | O26: =E26-N26 -> 3514192.1 | P26: =IF(O26<300000,0.07*O26,21000) -> 21000 | Q26: =IF((O26-300000)<0,0,IF((O26-300000)<300000,0.11*(O26-300000),33000)) -> 33000 | R26: =IF((O26-600000)<0,0,IF((O26-600000)<500000,0.15*(O26-600000),75000)) -> 75000 | S26: =IF((O26-1100000)<0,0,IF((O26-1100000)<500000,0.19*(O26-1100000),95000)) -> 95000 | T26: =IF((O26-1600000)<0,0,IF((O26-1600000)<1600000,0.21*(O26-1600000),336000)) -> 336000 | U26: =24%*(O26-3200000) -> 75406.111 | V26: =P26+Q26+R26+S26+T26+U26 -> 635406.11 | W26: 12 | X26: =V26/W26 -> 52950.509 | Z26: =X26 -> 52950.509 | AA26: 39052.313 | AB26: =Z26-AA26 -> 13898.196
A27: 24 | B27: VICTOR ASUKWO | C27: 499444 | D27: 12 | E27: =C27*D27 -> 5993328 | G27: 341107.84 | I27: =E27-F27-G27-H27 -> 5652220.2 | J27: 200000 | K27: 0.2 | L27: =I27*K27 -> 1130444 | M27: =J27+L27 -> 1330444 | N27: =F27+G27+H27+M27 -> 1671551.9 | O27: =E27-N27 -> 4321776.1 | P27: =IF(O27<300000,0.07*O27,21000) -> 21000 | Q27: =IF((O27-300000)<0,0,IF((O27-300000)<300000,0.11*(O27-300000),33000)) -> 33000 | R27: =IF((O27-600000)<0,0,IF((O27-600000)<500000,0.15*(O27-600000),75000)) -> 75000 | S27: =IF((O27-1100000)<0,0,IF((O27-1100000)<500000,0.19*(O27-1100000),95000)) -> 95000 | T27: =IF((O27-1600000)<0,0,IF((O27-1600000)<1600000,0.21*(O27-1600000),336000)) -> 336000 | U27: =24%*(O27-3200000) -> 269226.27 | V27: =P27+Q27+R27+S27+T27+U27 -> 829226.27 | W27: 12 | X27: =V27/W27 -> 69102.189 | Z27: =X27 -> 69102.189 | AA27: 39052.313 | AB27: =Z27-AA27 -> 30049.876
A28: 25 | B28: NNANDI LIVINUS ATURE | C28: 684288.36 | D28: 12 | E28: =C28*D28 -> 8211460.3 | G28: 341107.84 | I28: =E28-F28-G28-H28 -> 7870352.4 | J28: 200000 | K28: 0.2 | L28: =I28*K28 -> 1574070.5 | M28: =J28+L28 -> 1774070.5 | N28: =F28+G28+H28+M28 -> 2115178.3 | O28: =E28-N28 -> 6096282 | P28: =IF(O28<300000,0.07*O28,21000) -> 21000 | Q28: =IF((O28-300000)<0,0,IF((O28-300000)<300000,0.11*(O28-300000),33000)) -> 33000 | R28: =IF((O28-600000)<0,0,IF((O28-600000)<500000,0.15*(O28-600000),75000)) -> 75000 | S28: =IF((O28-1100000)<0,0,IF((O28-1100000)<500000,0.19*(O28-1100000),95000)) -> 95000 | T28: =IF((O28-1600000)<0,0,IF((O28-1600000)<1600000,0.21*(O28-1600000),336000)) -> 336000 | U28: =24%*(O28-3200000) -> 695107.67 | V28: =P28+Q28+R28+S28+T28+U28 -> 1255107.7 | W28: 12 | X28: =V28/W28 -> 104592.31 | Z28: =X28 -> 104592.31 | AA28: 45772.313 | AB28: =Z28-AA28 -> 58819.993
A29: 26 | B29: ABDULRAHMAN A SULAIMAN | C29: 407016.17 | D29: 12 | E29: =C29*D29 -> 4884194 | G29: 333135.52 | I29: =E29-F29-G29-H29 -> 4551058.5 | J29: 200000 | K29: 0.2 | L29: =I29*K29 -> 910211.7 | M29: =J29+L29 -> 1110211.7 | N29: =F29+G29+H29+M29 -> 1443347.2 | O29: =E29-N29 -> 3440846.8 | P29: =IF(O29<300000,0.07*O29,21000) -> 21000 | Q29: =IF((O29-300000)<0,0,IF((O29-300000)<300000,0.11*(O29-300000),33000)) -> 33000 | R29: =IF((O29-600000)<0,0,IF((O29-600000)<500000,0.15*(O29-600000),75000)) -> 75000 | S29: =IF((O29-1100000)<0,0,IF((O29-1100000)<500000,0.19*(O29-1100000),95000)) -> 95000 | T29: =IF((O29-1600000)<0,0,IF((O29-1600000)<1600000,0.21*(O29-1600000),336000)) -> 336000 | U29: =24%*(O29-3200000) -> 57803.228 | V29: =P29+Q29+R29+S29+T29+U29 -> 617803.23 | W29: 12 | X29: =V29/W29 -> 51483.602 | Z29: =X29 -> 51483.602 | AA29: 37921.501 | AB29: =Z29-AA29 -> 13562.102
A30: 27 | B30: DARE SHEU MAGBON | C30: 398711.67 | D30: 12 | E30: =C30*D30 -> 4784540 | G30: 325163.2 | I30: =E30-F30-G30-H30 -> 4459376.8 | J30: 200000 | K30: 0.2 | L30: =I30*K30 -> 891875.36 | M30: =J30+L30 -> 1091875.4 | N30: =F30+G30+H30+M30 -> 1417038.6 | O30: =E30-N30 -> 3367501.4 | P30: =IF(O30<300000,0.07*O30,21000) -> 21000 | Q30: =IF((O30-300000)<0,0,IF((O30-300000)<300000,0.11*(O30-300000),33000)) -> 33000 | R30: =IF((O30-600000)<0,0,IF((O30-600000)<500000,0.15*(O30-600000),75000)) -> 75000 | S30: =IF((O30-1100000)<0,0,IF((O30-1100000)<500000,0.19*(O30-1100000),95000)) -> 95000 | T30: =IF((O30-1600000)<0,0,IF((O30-1600000)<1600000,0.21*(O30-1600000),336000)) -> 336000 | U30: =24%*(O30-3200000) -> 40200.346 | V30: =P30+Q30+R30+S30+T30+U30 -> 600200.35 | W30: 12 | X30: =V30/W30 -> 50016.695 | Z30: =X30 -> 50016.695 | AA30: 36790.688 | AB30: =Z30-AA30 -> 13226.007
A31: 28 | B31: ABUBAKAR SULAIMAN SODEEQ | C31: 502248.18 | D31: 12 | E31: =C31*D31 -> 6026978.2 | G31: 325163.2 | I31: =E31-F31-G31-H31 -> 5701815 | J31: 200000 | K31: 0.2 | L31: =I31*K31 -> 1140363 | M31: =J31+L31 -> 1340363 | N31: =F31+G31+H31+M31 -> 1665526.2 | O31: =E31-N31 -> 4361452 | P31: =IF(O31<300000,0.07*O31,21000) -> 21000 | Q31: =IF((O31-300000)<0,0,IF((O31-300000)<300000,0.11*(O31-300000),33000)) -> 33000 | R31: =IF((O31-600000)<0,0,IF((O31-600000)<500000,0.15*(O31-600000),75000)) -> 75000 | S31: =IF((O31-1100000)<0,0,IF((O31-1100000)<500000,0.19*(O31-1100000),95000)) -> 95000 | T31: =IF((O31-1600000)<0,0,IF((O31-1600000)<1600000,0.21*(O31-1600000),336000)) -> 336000 | U31: =24%*(O31-3200000) -> 278748.48 | V31: =P31+Q31+R31+S31+T31+U31 -> 838748.48 | W31: 12 | X31: =V31/W31 -> 69895.707 | Z31: =X31 -> 69895.707 | AA31: 36790.688 | AB31: =Z31-AA31 -> 33105.018
A32: 29 | B32: JIMOH ADEBAYO ZAKA | C32: 467422.86 | D32: 12 | E32: =C32*D32 -> 5609074.3 | G32: 341107.84 | I32: =E32-F32-G32-H32 -> 5267966.5 | J32: 200000 | K32: 0.2 | L32: =I32*K32 -> 1053593.3 | M32: =J32+L32 -> 1253593.3 | N32: =F32+G32+H32+M32 -> 1594701.1 | O32: =E32-N32 -> 4014373.2 | P32: =IF(O32<300000,0.07*O32,21000) -> 21000 | Q32: =IF((O32-300000)<0,0,IF((O32-300000)<300000,0.11*(O32-300000),33000)) -> 33000 | R32: =IF((O32-600000)<0,0,IF((O32-600000)<500000,0.15*(O32-600000),75000)) -> 75000 | S32: =IF((O32-1100000)<0,0,IF((O32-1100000)<500000,0.19*(O32-1100000),95000)) -> 95000 | T32: =IF((O32-1600000)<0,0,IF((O32-1600000)<1600000,0.21*(O32-1600000),336000)) -> 336000 | U32: =24%*(O32-3200000) -> 195449.56 | V32: =P32+Q32+R32+S32+T32+U32 -> 755449.56 | W32: 12 | X32: =V32/W32 -> 62954.13 | Z32: =X32 -> 62954.13 | AA32: 39052.313 | AB32: =Z32-AA32 -> 23901.817
... A34: 32 | B34: MOHAMMED BELLO | C34: 432145.33 | D34: 12 | E34: =C34*D34 -> 5185744 | G34: 341107.84 | I34: =E34-F34-G34-H34 -> 4844636.2 | J34: 200000 | K34: 0.2 | L34: =I34*K34 -> 968927.23 | M34: =J34+L34 -> 1168927.2 | N34: =F34+G34+H34+M34 -> 1510035.1 | O34: =E34-N34 -> 3675708.9 | P34: =IF(O34<300000,0.07*O34,21000) -> 21000 | Q34: =IF((O34-300000)<0,0,IF((O34-300000)<300000,0.11*(O34-300000),33000)) -> 33000 | R34: =IF((O34-600000)<0,0,IF((O34-600000)<500000,0.15*(O34-600000),75000)) -> 75000 | S34: =IF((O34-1100000)<0,0,IF((O34-1100000)<500000,0.19*(O34-1100000),95000)) -> 95000 | T34: =IF((O34-1600000)<0,0,IF((O34-1600000)<1600000,0.21*(O34-1600000),336000)) -> 336000 | U34: =24%*(O34-3200000) -> 114170.14 | V34: =P34+Q34+R34+S34+T34+U34 -> 674170.14 | W34: 12 | X34: =V34/W34 -> 56180.845 | Z34: =X34 -> 56180.845 | AA34: 36790.688 | AB34: =Z34-AA34 -> 19390.157
A35: 33 | B35: HARUNA JIBRIL AMEH | C35: 351910.75 | D35: 12 | E35: =C35*D35 -> 4222929 | G35: 289834.32 | I35: =E35-F35-G35-H35 -> 3933094.7 | J35: 200000 | K35: 0.2 | L35: =I35*K35 -> 786618.94 | M35: =J35+L35 -> 986618.94 | N35: =F35+G35+H35+M35 -> 1276453.3 | O35: =E35-N35 -> 2946475.7 | P35: =IF(O35<300000,0.07*O35,21000) -> 21000 | Q35: =IF((O35-300000)<0,0,IF((O35-300000)<300000,0.11*(O35-300000),33000)) -> 33000 | R35: =IF((O35-600000)<0,0,IF((O35-600000)<500000,0.15*(O35-600000),75000)) -> 75000 | S35: =IF((O35-1100000)<0,0,IF((O35-1100000)<500000,0.19*(O35-1100000),95000)) -> 95000 | T35: =IF((O35-1600000)<0,0,IF((O35-1600000)<1600000,0.21*(O35-1600000),336000)) -> 282759.91 | V35: =P35+Q35+R35+S35+T35+U35 -> 506759.91 | W35: 12 | X35: =V35/W35 -> 42229.992 | Z35: =X35 -> 42229.992 | AA35: 30259.166 | AB35: =Z35-AA35 -> 11970.827
A36: 34 | B36: RAMATU IBRAHIM ABDULRAHEEM | C36: 344900.83 | D36: 12 | E36: =C36*D36 -> 4138810 | G36: 283104.8 | I36: =E36-F36-G36-H36 -> 3855705.2 | J36: 200000 | K36: 0.2 | L36: =I36*K36 -> 771141.04 | M36: =J36+L36 -> 971141.04 | N36: =F36+G36+H36+M36 -> 1254245.8 | O36: =E36-N36 -> 2884564.2 | P36: =IF(O36<300000,0.07*O36,21000) -> 21000 | Q36: =IF((O36-300000)<0,0,IF((O36-300000)<300000,0.11*(O36-300000),33000)) -> 33000 | R36: =IF((O36-600000)<0,0,IF((O36-600000)<500000,0.15*(O36-600000),75000)) -> 75000 | S36: =IF((O36-1100000)<0,0,IF((O36-1100000)<500000,0.19*(O36-1100000),95000)) -> 95000 | T36: =IF((O36-1600000)<0,0,IF((O36-1600000)<1600000,0.21*(O36-1600000),336000)) -> 269758.47 | V36: =P36+Q36+R36+S36+T36+U36 -> 493758.47 | W36: 12 | X36: =V36/W36 -> 41146.539 | Z36: =X36 -> 41146.539 | AA36: 29305.196 | AB36: =Z36-AA36 -> 11841.344
B38: INTERNAL AUDIT
B39: OSANAIYE DAVID AKINYEMI | C39: 1847106.4 | D39: 12 | E39: =C39*D39 -> 22165277 | G39: 1677222.2 | I39: =E39-F39-G39-H39 -> 20488055 | J39: 200000 | K39: 0.2 | L39: =I39*K39 -> 4097611 | M39: =J39+L39 -> 4297611 | N39: =F39+G39+H39+M39 -> 5974833.1 | O39: =E39-N39 -> 16190444 | P39: =IF(O39<300000,0.07*O39,21000) -> 21000 | Q39: =IF((O39-300000)<0,0,IF((O39-300000)<300000,0.11*(O39-300000),33000)) -> 33000 | R39: =IF((O39-600000)<0,0,IF((O39-600000)<500000,0.15*(O39-600000),75000)) -> 75000 | S39: =IF((O39-1100000)<0,0,IF((O39-1100000)<500000,0.19*(O39-1100000),95000)) -> 95000 | T39: =IF((O39-1600000)<0,0,IF((O39-1600000)<1600000,0.21*(O39-1600000),336000)) -> 336000 | U39: =24%*(O39-3200000) -> 3117706.5 | V39: =P39+Q39+R39+S39+T39+U39 -> 3677706.5 | W39: 12 | X39: =V39/W39 -> 306475.54 | Z39: =X39 -> 306475.54 | AA39: 251472.25 | AB39: =Z39-AA39 -> 55003.297
B40: JAMILA ABDUL | C40: 441140.67 | D40: 12 | E40: =C40*D40 -> 5293688 | G40: 365895.04 | I40: =E40-F40-G40-H40 -> 4927793 | J40: 200000 | K40: 0.2 | L40: =I40*K40 -> 985558.59 | M40: =J40+L40 -> 1185558.6 | N40: =F40+G40+H40+M40 -> 1551453.6 | O40: =E40-N40 -> 3742234.4 | P40: =IF(O40<300000,0.07*O40,21000) -> 21000 | Q40: =IF((O40-300000)<0,0,IF((O40-300000)<300000,0.11*(O40-300000),33000)) -> 33000 | R40: =IF((O40-600000)<0,0,IF((O40-600000)<500000,0.15*(O40-600000),75000)) -> 75000 | S40: =IF((O40-1100000)<0,0,IF((O40-1100000)<500000,0.19*(O40-1100000),95000)) -> 95000 | T40: =IF((O40-1600000)<0,0,IF((O40-1600000)<1600000,0.21*(O40-1600000),336000)) -> 336000 | U40: =24%*(O40-3200000) -> 130136.25 | V40: =P40+Q40+R40+S40+T40+U40 -> 690136.25 | W40: 12 | X40: =V40/W40 -> 57511.354 | Z40: =X40 -> 57511.354 | AA40: 42537.332 | AB40: =Z40-AA40 -> 14974.022
B41: IJEOMA EWELUKWA | C41: 655929.27 | D41: 12 | E41: =C41*D41 -> 7871151.3 | G41: 374530.4 | I41: =E41-F41-G41-H41 -> 7496620.9 | J41: 200000 | K41: 0.2 | L41: =I41*K41 -> 1499324.2 | M41: =J41+L41 -> 1699324.2 | N41: =F41+G41+H41+M41 -> 2073854.6 | O41: =E41-N41 -> 5797296.7 | P41: =IF(O41<300000,0.07*O41,21000) -> 21000 | Q41: =IF((O41-300000)<0,0,IF((O41-300000)<300000,0.11*(O41-300000),33000)) -> 33000 | R41: =IF((O41-600000)<0,0,IF((O41-600000)<500000,0.15*(O41-600000),75000)) -> 75000 | S41: =IF((O41-1100000)<0,0,IF((O41-1100000)<500000,0.19*(O41-1100000),95000)) -> 95000 | T41: =IF((O41-1600000)<0,0,IF((O41-1600000)<1600000,0.21*(O41-1600000),336000)) -> 336000 | U41: =24%*(O41-3200000) -> 623351.21 | V41: =P41+Q41+R41+S41+T41+U41 -> 1183351.2 | W41: 12 | X41: =V41/W41 -> 98612.601 | Z41: =X41 -> 98612.601 | AA41: 43763.907 | AB41: =Z41-AA41 -> 54848.693
B42: YUSUF YUSUF DAYYABU | C42: 398711.67 | D42: 12 | E42: =C42*D42 -> 4784540 | G42: 325163.2 | I42: =E42-F42-G42-H42 -> 4459376.8 | J42: 200000 | K42: 0.2 | L42: =I42*K42 -> 891875.36 | M42: =J42+L42 -> 1091875.4 | N42: =F42+G42+H42+M42 -> 1417038.6 | O42: =E42-N42 -> 3367501.4 | P42: =IF(O42<300000,0.07*O42,21000) -> 21000 | Q42: =IF((O42-300000)<0,0,IF((O42-300000)<300000,0.11*(O42-300000),33000)) -> 33000 | R42: =IF((O42-600000)<0,0,IF((O42-600000)<500000,0.15*(O42-600000),75000)) -> 75000 | S42: =IF((O42-1100000)<0,0,IF((O42-1100000)<500000,0.19*(O42-1100000),95000)) -> 95000 | T42: =IF((O42-1600000)<0,0,IF((O42-1600000)<1600000,0.21*(O42-1600000),336000)) -> 336000 | U42: =24%*(O42-3200000) -> 40200.346 | V42: =P42+Q42+R42+S42+T42+U42 -> 600200.35 | W42: 12 | X42: =V42/W42 -> 50016.695 | Z42: =X42 -> 50016.695 | AA42: 36790.688 | AB42: =Z42-AA42 -> 13226.007
B44: LEG. SUPPORT SEVICES
A45: 35 | B45: BETHEL UZOMA IHUGBA | C45: 1847612 | D45: 12 | E45: =C45*D45 -> 22171344 | G45: 869094.48 | I45: =E45-F45-G45-H45 -> 21302250 | J45: 200000 | K45: 0.2 | L45: =I45*K45 -> 4260449.9 | M45: =J45+L45 -> 4460449.9 | N45: =F45+G45+H45+M45 -> 5329544.4 | O45: =E45-N45 -> 16841800 | P45: =IF(O45<300000,0.07*O45,21000) -> 21000 | Q45: =IF((O45-300000)<0,0,IF((O45-300000)<300000,0.11*(O45-300000),33000)) -> 33000 | R45: =IF((O45-600000)<0,0,IF((O45-600000)<500000,0.15*(O45-600000),75000)) -> 75000 | S45: =IF((O45-1100000)<0,0,IF((O45-1100000)<500000,0.19*(O45-1100000),95000)) -> 95000 | T45: =IF((O45-1600000)<0,0,IF((O45-1600000)<1600000,0.21*(O45-1600000),336000)) -> 336000 | U45: =0.24*(O45-3200000) -> 3274031.9 | V45: =P45+Q45+R45+S45+T45+U45 -> 3834031.9 | W45: 12 | X45: =V45/W45 -> 319502.66 | Z45: =X45 -> 319502.66 | AA45: 162999.59 | AB45: =Z45-AA45 -> 156503.07
A46: 36 | B46: OGUCHE SAMUEL | C46: 904477 | D46: 12 | E46: =C46*D46 -> 10853724 | G46: 714697.92 | I46: =E46-F46-G46-H46 -> 10139026 | J46: 200000 | K46: 0.2 | L46: =I46*K46 -> 2027805.2 | M46: =J46+L46 -> 2227805.2 | N46: =F46+G46+H46+M46 -> 2942503.1 | O46: =E46-N46 -> 7911220.9 | P46: =IF(O46<300000,0.07*O46,21000) -> 21000 | Q46: =IF((O46-300000)<0,0,IF((O46-300000)<300000,0.11*(O46-300000),33000)) -> 33000 | R46: =IF((O46-600000)<0,0,IF((O46-600000)<500000,0.15*(O46-600000),75000)) -> 75000 | S46: =IF((O46-1100000)<0,0,IF((O46-1100000)<500000,0.19*(O46-1100000),95000)) -> 95000 | T46: =IF((O46-1600000)<0,0,IF((O46-1600000)<1600000,0.21*(O46-1600000),336000)) -> 336000 | U46: =24%*(O46-3200000) -> 1130693 | V46: =P46+Q46+R46+S46+T46+U46 -> 1690693 | W46: 12 | X46: =V46/W46 -> 140891.08 | Z46: =X46 -> 140891.08 | AA46: 119022.8 | AB46: =Z46-AA46 -> 21868.282
