Workbook

Sheet MARCH 2025
A1: NATIONAL INSTITUTE FOR LEGISLATIVE AND DEMOCRATIC STUDIES
A2: STAFF PAYROLL FOR THE MONTH OF MARCH, 2025
E3: ='[1]FEB 08'!E11/'[1]FEB 08'!M11 -> #REF!
B4: STAFF NAME | C4: DESIGNATION | D4: GRADE LEVEL | E4: BASIC SALARY | F4: ALLCE/ AREARS | G4: ALLOWANCE | H4: ALLOWANCE | I4: DUTY ALLCE | J4: GROSS SALARY | K4: AUCTION | L4: COOP CONTR/SPEC SAVINGS | M4: COOP. LOAN RECOVERY | N4: NHF DED. | O4: PAYE | P4: EMPLOYEE PENSIONS | Q4: TOTAL DEDUCTION | R4: FEBRUARY, 2025 | S4: MARCH, 2025
E5: N | F5: N | G5: N | H5: N | I5: N | J5: N | K5: N | L5: N | M5: N | N5: N | O5: N | P5: N | Q5: N | R5: N | S5: N
A6: S/N | B6: DG'S OFFICE
A7: 1 | B7: PROF. ABUBAKAR O. SULAIMAN | C7: DIRECTOR GENERAL | D7: CONSOL | E7: 1659751.2 | G7: =250000 -> 250000 | I7: 25235 | J7: =E7+F7+G7+H7+I7 -> 1934986.2 | O7: 350184.01 | Q7: =O7+N7+M7+L7+K7+P7 -> 350184.01 | R7: 1584802.2 | S7: =J7-Q7 -> 1584802.2
A8: 2 | B8: RAHEEM USMAN AYIGORO | C8: SA-INFRASTRUCTURE | D8: 16 (9) | E8: 762373.17 | H8: =90000 -> 90000 | I8: =100000 -> 100000 | J8: =E8+F8+G8+H8+I8 -> 952373.17 | L8: =250000 -> 250000 | O8: ='Additional Leg Duty Allowance'!P7 -> 149812.26 | P8: 60989.853 | Q8: =O8+N8+M8+L8+K8+P8 -> 460802.12 | R8: 491571.05 | S8: =J8-Q8 -> 491571.05
A9: 3 | B9: MARIAM MOHAMMED BELLO | C9: SA- SPECIAL DUTIES | D9: 16 (9) | E9: 762373.17 | H9: =90000 -> 90000 | I9: =200000+100000 -> 300000 | J9: =E9+F9+G9+H9+I9 -> 1152373.2 | O9: ='Additional Leg Duty Allowance'!P8 -> 199922.31 | Q9: =O9+N9+M9+L9+K9+P9 -> 199922.31 | R9: 952450.85 | S9: =J9-Q9 -> 952450.85
A10: 4 | B10: DR IKEME ARTHUR J.O | C10: DEPUTY DIRECTOR, M&E | D10: 16 (9) | E10: 762373.17 | G10: 180000 | I10: 0 | J10: =E10+F10+G10+H10+I10 -> 942373.17 | L10: =50000 -> 50000 | M10: 0 | N10: 10293.398 | O10: 147687.53 | P10: 60989.853 | Q10: =O10+N10+M10+L10+K10+P10 -> 268970.78 | R10: 673402.39 | S10: =J10-Q10 -> 673402.39
A11: 5 | B11: MOSHOOD M. OLALERE | C11: DEPUTY DIR. GENERAL SERVICE | D11: 16 (9) | E11: 762373.17 | H11: =80000+10000 -> 90000 | I11: =150000+100000 -> 250000 | J11: =E11+F11+G11+H11+I11 -> 1102373.2 | L11: =20000+60000 -> 80000 | M11: ='[2]OCTOBER 2023 '!$D$193 -> 230499.8 | N11: 10293.398 | O11: ='Additional Leg Duty Allowance'!P9 -> 178407.53 | P11: 60989.853 | Q11: =O11+N11+M11+L11+K11+P11 -> 560190.58 | R11: 542182.59 | S11: =J11-Q11 -> 542182.59
A12: 6 | B12: ANDRAWUS MUSA | C12: ASST. DIRECTOR, STORES | D12: 15(9) | E12: 620675.58 | H12: =80000 -> 80000 | I12: 50000 | J12: =E12+F12+G12+H12+I12 -> 750675.58 | L12: =50000-40000 -> 10000 | M12: =90000+110000 -> 200000 | N12: 8380.2271 | O12: 113101.97 | P12: 49654.047 | Q12: =O12+N12+M12+L12+K12+P12 -> 381136.24 | R12: 369539.34 | S12: =J12-Q12 -> 369539.34
A13: 7 | B13: DR FRANCIS NDUM OJIE | C13: AD, TRAINING & IC./SA TO DG | D13: 15(7) | E13: 582118.08 | G13: 160000 | I13: =100000+100000 -> 200000 | J13: =E13+F13+G13+H13+I13 -> 942118.08 | N13: 7859.6313 | O13: ='Additional Leg Duty Allowance'!P12 -> 150463.11 | P13: 46569.447 | Q13: =O13+N13+M13+L13+K13+P13 -> 204892.19 | R13: 737225.9 | S13: =J13-Q13 -> 737225.9
A14: 8 | B14: ALI ABDULLAHI | C14: CHIEF ICT OFFICER | D14: 14(11) | E14: 484373.75 | H14: =70000 -> 70000 | I14: =0 -> 0 | J14: =E14+F14+G14+H14+I14 -> 554373.75 | O14: 77666.446 | P14: 38749.9 | Q14: =O14+N14+M14+L14+K14+P14 -> 116416.35 | R14: 437957.4 | S14: =J14-Q14 -> 437957.4
A15: 9 | B15: EMILY EKHIDE | C15: SENIOR RESEARCH FELLOW | D15: 15(7) | E15: 582118.08 | G15: 160000 | I15: =50000+100000 -> 150000 | J15: =E15+F15+G15+H15+I15 -> 892118.08 | L15: =50000 -> 50000 | O15: 141011.99 | P15: =46569.45 -> 46569.45 | Q15: =O15+N15+M15+L15+K15+P15 -> 237581.44 | R15: 654536.64 | S15: =J15-Q15 -> 654536.64
A16: 10 | B16: DORIS DAKDA AARON | C16: RESEARCH FELLOW I | D16: 14(8) | E16: 442746.5 | G16: =140000 -> 140000 | I16: =150000+100000 -> 250000 | J16: =E16+F16+G16+H16+I16 -> 832746.5 | L16: 70000 | M16: 175000 | O16: ='Additional Leg Duty Allowance'!P13 -> 131753.41 | P16: 35419.72 | Q16: =O16+N16+M16+L16+K16+P16 -> 412173.13 | R16: 420573.37 | S16: =J16-Q16 -> 420573.37
A17: 11 | B17: ABDULSALAM S. MUSTAPHA | C17: ASST. DIRECTOR ICT | D17: 15(7) | E17: 582118.08 | H17: 80000 | I17: 50000 | J17: =E17+F17+G17+H17+I17 -> 712118.08 | O17: 106452 | P17: =46569.45 -> 46569.45 | Q17: =O17+N17+M17+L17+K17+P17 -> 153021.45 | R17: 559096.63 | S17: =J17-Q17 -> 559096.63
A18: 12 | B18: PERCY TERFA GBAHABO | C18: HEAD, NILDS LIAISON OFFICE | D18: 13(10) | E18: 428915.92 | G18: =120000 -> 120000 | I18: 0 | J18: =E18+F18+G18+H18+I18 -> 548915.92 | O18: 77470.374 | P18: 34313.273 | Q18: =O18+N18+M18+L18+K18+P18 -> 111783.65 | R18: 437132.27 | S18: =J18-Q18 -> 437132.27
A19: 13 | B19: HASSANA AHMED IBRAHIM | C19: PA- TO DG | D19: 13 (9) | E19: 416026.92 | G19: =120000 -> 120000 | I19: =100000+100000 -> 200000 | J19: =E19+F19+G19+H19+I19 -> 736026.92 | L19: =30000-20000 -> 10000 | M19: =95833.33 -> 95833.33 | N19: 5607.1771 | O19: ='Additional Leg Duty Allowance'!P14 -> 113474.9 | P19: 33282.153 | Q19: =O19+N19+M19+L19+K19+P19 -> 258197.56 | R19: 477829.35 | S19: =J19-Q19 -> 477829.35
A20: 14 | B20: IKIP LEBO | C20: ASST CHIEF PROC. OFFICER | D20: 13 (7) | E20: ='[3]Annual & Monthly'!$H$40 -> 390248.92 | H20: 70000 | J20: =E20+F20+G20+H20+I20 -> 460248.92 | L20: 50000 | O20: =61040.2353066666 -> 61040.235 | P20: =390248.916666667*0.08 -> 31219.913 | Q20: =O20+N20+M20+L20+K20+P20 -> 142260.15 | R20: 317988.77 | S20: =J20-Q20 -> 317988.77
A21: 15 | B21: ALABI ADESINA MUHYDEEN | C21: HEAD, NILDS LIAISON OFFICE | D21: 13 (7) | E21: 390248.92 | G21: 120000 | J21: =E21+F21+G21+H21+I21 -> 510248.92 | O21: =70640.2353066667 -> 70640.235 | P21: 31219.913 | Q21: =O21+N21+M21+L21+K21+P21 -> 101860.15 | R21: 408388.77 | S21: =J21-Q21 -> 408388.77
A22: 16 | B22: ADUGBA RICHARD TERSEER | C22: PRINCIPAL INFO. OFFICER | D22: 12(9) | E22: 377895.17 | H22: =60000 -> 60000 | I22: =100000+50000 -> 150000 | J22: =E22+F22+G22+H22+I22 -> 587895.17 | L22: =10000 -> 10000 | M22: 292813.77 | O22: 82601.205 | P22: 30231.613 | Q22: =O22+N22+M22+L22+K22+P22 -> 415646.59 | R22: 313229.02 | S22: =J22-Q22 -> 172248.58
A23: 17 | B23: LUCKY AGWOM | C23: RESEARCH ASSISTANT | D23: 12(7) | E23: 353512.5 | G23: =100000 -> 100000 | I23: =100000+100000 -> 200000 | J23: =E23+F23+G23+H23+I23 -> 653512.5 | L23: =50000+100000 -> 150000 | O23: ='Additional Leg Duty Allowance'!P15 -> 98711.115 | P23: 28281 | Q23: =O23+N23+M23+L23+K23+P23 -> 276992.11 | R23: 376520.39 | S23: =J23-Q23 -> 376520.39
A24: 18 | B24: IDRIS IBRAHIM | C24: PRINCIPAL RESEARCH OFFICER | D24: 12(7) | E24: 353512.5 | G24: 110000 | I24: 0 | J24: =E24+F24+G24+H24+I24 -> 463512.5 | L24: 0 | O24: 62231.115 | P24: 28281 | Q24: =O24+N24+M24+L24+K24+P24 -> 90512.115 | R24: 373000.39 | S24: =J24-Q24 -> 373000.39
A25: 19 | B25: FARUQ ATOFARATI | C25: PA (SPECIAL DUTIES) TO DG | D25: 10(7) | E25: 293029.67 | H25: =50000+10000 -> 60000 | I25: =100000+100000 -> 200000 | J25: =E25+F25+G25+H25+I25 -> 553029.67 | L25: 150000 | O25: ='Additional Leg Duty Allowance'!P16 -> 80347.427 | P25: 23442.373 | Q25: =O25+N25+M25+L25+K25+P25 -> 253789.8 | R25: 319239.87 | S25: =J25-Q25 -> 299239.87
A26: 20 | B26: RASHEEDAT DAIBU | C26: SENIOR INFO. OFFICER | D26: 10(7) | E26: 293029.67 | H26: 60000 | J26: =E26+F26+G26+H26+I26 -> 353029.67 | L26: 50000 | O26: =42537.3319466667 -> 42537.332 | P26: 23442.373 | Q26: =O26+N26+M26+L26+K26+P26 -> 115979.71 | R26: 237049.96 | S26: =J26-Q26 -> 237049.96
A27: 21 | B27: ELIZABETH OGECHUKWU ONYEAKU | C27: ICT OFFICER | D27: 9(9) | E27: 270481.67 | H27: =50000+10000 -> 60000 | J27: =E27+F27+G27+H27+I27 -> 330481.67 | L27: 10000 | O27: 39052.313 | P27: 21638.533 | Q27: =O27+N27+M27+L27+K27+P27 -> 70690.846 | R27: 259790.82 | S27: =J27-Q27 -> 259790.82
A28: 22 | B28: VICTOR ASUKWO | C28: ICT OFFICER | D28: 9(9) | E28: 270481.67 | H28: =50000+10000 -> 60000 | J28: =E28+F28+G28+H28+I28 -> 330481.67 | O28: 39052.313 | P28: 21638.533 | Q28: =O28+N28+M28+L28+K28+P28 -> 60690.846 | R28: 269790.82 | S28: =J28-Q28 -> 269790.82
A29: 23 | B29: NNANDI LIVINUS ATURE | C29: RESEARCH ASSISTANT | D29: 9(9) | E29: 270481.67 | G29: =100000 -> 100000 | J29: =E29+F29+G29+H29+I29 -> 370481.67 | L29: =10000 -> 10000 | M29: =95833.33 -> 95833.33 | O29: 45772.313 | P29: 21638.533 | Q29: =O29+N29+M29+L29+K29+P29 -> 173244.18 | R29: 197237.49 | S29: =J29-Q29 -> 197237.49
A30: 24 | B30: ABDULRAHMAN A SULAIMAN | C30: STORE OFFICER | D30: 9(8) | E30: 263165.33 | H30: =60000 -> 60000 | J30: =E30+F30+G30+H30+I30 -> 323165.33 | L30: =20000 -> 20000 | M30: =17500 -> 17500 | O30: 37921.501 | P30: 21053.227 | Q30: =O30+N30+M30+L30+K30+P30 -> 96474.727 | R30: 226690.61 | S30: =J30-Q30 -> 226690.61
A31: 25 | B31: DARE SHEU MAGBON | C31: ADMINISTRATION OFFICER | D31: 9(7) | E31: 255849 | H31: =60000 -> 60000 | J31: =E31+F31+G31+H31+I31 -> 315849 | L31: =30000+20000 -> 50000 | M31: 0 | O31: 36790.688 | P31: 20467.92 | Q31: =O31+N31+M31+L31+K31+P31 -> 107258.61 | R31: 208590.39 | S31: =J31-Q31 -> 208590.39
A32: 26 | B32: ABUBAKAR SULAIMAN SODEEQ | C32: ADMINISTRATION OFFICER | D32: 9(7) | E32: 255849 | H32: =60000 -> 60000 | J32: =E32+F32+G32+H32+I32 -> 315849 | M32: 0 | O32: 36790.688 | P32: 20467.92 | Q32: =O32+N32+M32+L32+K32+P32 -> 57258.608 | R32: 258590.39 | S32: =J32-Q32 -> 258590.39
A33: 27 | B33: JIMOH ADEBAYO ZAKA | C33: ASST. OFFICER/COMM | D33: 9(9) | E33: 270481.67 | H33: =60000 -> 60000 | J33: =E33+F33+G33+H33+I33 -> 330481.67 | L33: =10000 -> 10000 | M33: 161429.76 | N33: =3653.5 -> 3653.5 | O33: 39052.313 | P33: 21638.533 | Q33: =O33+N33+M33+L33+K33+P33 -> 235774.11 | R33: 94707.56 | S33: =J33-Q33 -> 94707.56
A34: 28 | B34: ABDULMUSHIN TAWFIQ LADAN | C34: ICT OFFICER | D34: 9(7) | E34: 255849 | H34: =60000 -> 60000 | J34: =E34+F34+G34+H34+I34 -> 315849 | M34: 0 | O34: =36790.6881066667 -> 36790.688 | P34: 20467.92 | Q34: =O34+N34+M34+L34+K34+P34 -> 57258.608 | R34: 258590.39 | S34: =J34-Q34 -> 258590.39
A35: 29 | B35: MOHAMMED BELLO | C35: PROTOCOL ASSISTANT | D35: 9(7) | E35: 255849 | H35: =60000 -> 60000 | J35: =E35+F35+G35+H35+I35 -> 315849 | L35: =0 -> 0 | O35: 36790.688 | P35: 20467.92 | Q35: =O35+N35+M35+L35+K35+P35 -> 57258.608 | R35: 258590.39 | S35: =J35-Q35 -> 258590.39
A36: 30 | B36: HARUNA JIBRIL AMEH | C36: ASST. ADMIN. OFFICER | D36: 8(8) | E36: 224459.75 | H36: 50000 | J36: =E36+F36+G36+H36+I36 -> 274459.75 | L36: 20000 | M36: 0 | O36: 30259.166 | P36: 17956.78 | Q36: =O36+N36+M36+L36+K36+P36 -> 68215.946 | R36: 206243.8 | S36: =J36-Q36 -> 206243.8
A37: 31 | B37: RAMATU IBRAHIM ABDULRAHEEM | C37: INFORMATION OFFICER | D37: 8(7) | E37: 218287.58 | H37: 50000 | J37: =E37+F37+G37+H37+I37 -> 268287.58 | L37: 50000 | M37: 45833.33 | O37: =29305.1955466667 -> 29305.196 | P37: =218287.583333333*0.08 -> 17463.007 | Q37: =O37+N37+M37+L37+K37+P37 -> 142601.53 | R37: 125686.05 | S37: =J37-Q37 -> 125686.05
B38: TOTAL | C38: 31 | E38: =SUM(E7:E37) -> 14111049 | F38: =SUM(F7:F37) -> 0 | G38: =SUM(G7:G37) -> 1560000 | H38: =SUM(H7:H37) -> 1330000 | I38: =SUM(I7:I37) -> 2125235 | J38: =SUM(J7:J37) -> 19126284 | K38: =SUM(K7:K37) -> 0 | L38: =SUM(L7:L37) -> 1100000 | ... Q38: =SUM(Q7:Q37) -> 6239039 | R38: 13048226 | S38: =SUM(S7:S37) -> 12887245
B40: INTERNAL AUDIT
A41: 1 | B41: OSANAIYE DAVID AKINYEMI | C41: DIRECTOR INTERNAL AUDIT | D41: 17(9) | E41: 1435720 | H41: =100000 -> 100000 | J41: =SUM(E41:I41) -> 1535720 | K41: ='MARCH 2025'!F204 -> 0 | L41: =300000 -> 300000 | M41: =458333.33 -> 458333.33 | O41: 251472.25 | P41: 114857.6 | Q41: =O41+N41+M41+L41+K41+P41 -> 1124663.2 | R41: 411056.82 | S41: =J41-Q41 -> 411056.82
A42: 2 | B42: JAMILA ABDUL | C42: SENIOR INTERNAL AUDITOR | D42: 10(7) | E42: 293029.67 | H42: =60000 -> 60000 | J42: =SUM(E42:I42) -> 353029.67 | L42: =20000 -> 20000 | M42: 45833.33 | O42: 42537.332 | P42: 23442.373 | Q42: =O42+N42+M42+L42+K42+P42 -> 131813.04 | R42: 221216.63 | S42: =J42-Q42 -> 221216.63
A43: 3 | B43: IJEOMA EWELUKWA | C43: SENIOR INTERNAL AUDITOR | D43: 10(8) | E43: 300965.58 | H43: =50000+10000 -> 60000 | J43: =SUM(E43:I43) -> 360965.58 | L43: =10000 -> 10000 | O43: 43763.907 | P43: 24077.247 | Q43: =O43+N43+M43+L43+K43+P43 -> 77841.154 | R43: 283124.43 | S43: =J43-Q43 -> 283124.43
A44: 4 | B44: YUSUF YUSUF DAYYABU | C44: INERNAL AUDIT OFFICER | D44: 9(7) | E44: ='[3]Annual & Monthly'!$H$37 -> 255849 | H44: 60000 | J44: =SUM(E44:I44) -> 315849 | L44: 50000 | O44: =36790.6881066667 -> 36790.688 | P44: =255849*0.08 -> 20467.92 | Q44: =O44+N44+M44+L44+K44+P44 -> 107258.61 | R44: 208590.39 | S44: =J44-Q44 -> 208590.39
C45: 4 | E45: =SUM(E41:E44) -> 2285564.2 | F45: =SUM(F41:F44) -> 0 | G45: =SUM(G41:G44) -> 0 | H45: =SUM(H41:H44) -> 280000 | I45: =SUM(I41:I44) -> 0 | J45: =SUM(J41:J44) -> 2565564.2 | K45: =SUM(K41:K44) -> 0 | L45: =SUM(L41:L44) -> 380000 | ... Q45: =SUM(Q41:Q44) -> 1441576 | R45: 1123988.3 | S45: =SUM(S41:S44) -> 1123988.3
B47: LEG. SUPPORT SEVICES
A48: 2 | B48: BETHEL UZOMA IHUGBA | C48: DEPUTY DIRECTOR, LEGAL RESEARCH | D48: 16(8) | E48: 739203.58 | G48: =180000 -> 180000 | J48: =SUM(E48:I48) -> 919203.58 | L48: =80000+23000 -> 103000 | M48: =246905.96 -> 246905.96 | O48: 143799.59 | P48: 59136.287 | Q48: =O48+N48+M48+L48+K48+P48 -> 552841.83 | R48: 366361.75 | S48: =J48-Q48 -> 366361.75
A49: 3 | B49: OGUCHE SAMUEL | C49: SNR RESEARCH FELLOW | D49: 15(9) | E49: 620675.58 | G49: =160000 -> 160000 | J49: =SUM(E49:I49) -> 780675.58 | L49: =30000 -> 30000 | M49: 223059.88 | O49: 119022.8 | P49: 49654.047 | Q49: =O49+N49+M49+L49+K49+P49 -> 421736.73 | R49: 358938.85 | S49: =J49-Q49 -> 358938.85
A50: 4 | B50: IBRAHIM USMAN | C50: SNR RESEARCH FELLOW | D50: 15(9) | E50: 620675.58 | G50: =140000+20000 -> 160000 | I50: 0 | J50: =SUM(E50:I50) -> 780675.58 | N50: ='New NHF Deduction'!G48 -> 8380.2271 | O50: 118861.97 | P50: 49654.047 | Q50: =O50+N50+M50+L50+K50+P50 -> 176896.24 | R50: 603779.34 | S50: =J50-Q50 -> 603779.34
A51: 5 | B51: DR MOHAMMED O. AMALI | C51: SNR RESEARCH FELLOW | D51: 15(7) | E51: 582118.08 | G51: =140000+20000 -> 160000 | J51: =SUM(E51:I51) -> 742118.08 | L51: =15000 -> 15000 | M51: 99000 | O51: 112212 | P51: 46569.447 | Q51: =O51+N51+M51+L51+K51+P51 -> 272781.45 | R51: 469336.63 | S51: =J51-Q51 -> 469336.63
A52: 6 | B52: YAHAYA SHAMSU | C52: SNR RESEARCH FELLOW | D52: 15(7) | E52: 582118.08 | G52: =160000 -> 160000 | J52: =SUM(E52:I52) -> 742118.08 | N52: 0 | O52: 112211.99 | P52: =46569.45 -> 46569.45 | Q52: =O52+N52+M52+L52+K52+P52 -> 158781.44 | R52: 583336.64 | S52: =J52-Q52 -> 583336.64
A53: 7 | B53: BILKIS S. LAWAL-GAMBARI | C53: RESEARCH OFFICER | D53: 10(8) | E53: 300965.58 | G53: 100000 | J53: =SUM(E53:I53) -> 400965.58 | O53: 51029.227 | P53: 24077.247 | Q53: =O53+N53+M53+L53+K53+P53 -> 75106.474 | R53: 325859.11 | S53: =J53-Q53 -> 325859.11
A54: 8 | B54: ZAINAB AKINDE | C54: RESEARCH OFFICER | D54: 9(8) | E54: 263165.33 | G54: =100000 -> 100000 | J54: =SUM(E54:I54) -> 363165.33 | O54: 44641.501 | P54: 21053.227 | Q54: =O54+N54+M54+L54+K54+P54 -> 65694.727 | R54: 297470.61 | S54: =J54-Q54 -> 297470.61
A55: 9 | B55: GUNAT NANSAK MARK | C55: RESEARCH OFFICER | D55: 9(8) | E55: 263165.33 | G55: =100000 -> 100000 | J55: =SUM(E55:I55) -> 363165.33 | O55: 44641.501 | P55: 21053.227 | Q55: =O55+N55+M55+L55+K55+P55 -> 65694.727 | R55: 297470.61 | S55: =J55-Q55 -> 297470.61
B56: TOTAL | C56: 9 | E56: =SUM(E48:E55) -> 3972087.2 | F56: =SUM(F48:F55) -> 0 | G56: =SUM(G48:G55) -> 1120000 | H56: =SUM(H48:H55) -> 0 | I56: =SUM(I48:I55) -> 0 | J56: =SUM(J48:J55) -> 5092087.2 | K56: =SUM(K48:K55) -> 0 | L56: =SUM(L48:L55) -> 148000 | ... Q56: =SUM(Q48:Q55) -> 1789533.6 | R56: 3302553.5 | S56: =SUM(S48:S55) -> 3302553.5
B58: LEGAL SERVICES
A59: 1 | B59: DR SHUAIBU DANWANKA | C59: DIRECTOR LEGAL SERVICES | D59: 17(9) | E59: 1435720 | G59: =200000 -> 200000 | I59: 0 | J59: =SUM(E59:I59) -> 1635720 | L59: 250000 | N59: 0 | O59: 270672.25 | P59: 114857.6 | Q59: =O59+N59+M59+L59+K59+P59 -> 635529.85 | R59: 1000190.2 | S59: =J59-Q59 -> 1000190.2
A60: 2 | B60: ABDULSALAM BAKO | C60: MANAGER, LEGAL SERVICES | D60: 15 (9) | E60: 620675.58 | H60: 80000 | J60: =SUM(E60:I60) -> 700675.58 | L60: 50000 | M60: 145000 | N60: 0 | O60: 103662.8 | P60: 49654.047 | Q60: =O60+N60+M60+L60+K60+P60 -> 348316.85 | R60: 352358.73 | S60: =J60-Q60 -> 352358.73
B61: TOTAL | C61: 2 | E61: =SUM(E59:E60) -> 2056395.6 | F61: =SUM(F59:F60) -> 0 | G61: =SUM(G59:G60) -> 200000 | H61: =SUM(H59:H60) -> 80000 | I61: =SUM(I59:I60) -> 0 | J61: =SUM(J59:J60) -> 2336395.6 | K61: =SUM(K59:K60) -> 0 | L61: =SUM(L59:L60) -> 300000 | ... Q61: =SUM(Q59:Q60) -> 983846.7 | R61: 1352548.9 | S61: =SUM(S59:S60) -> 1352548.9
B63: DEMOCRACY & GOVERNANCE
A64: 1 | B64: DR. ADEWALE ADEREMI | C64: DIRECTOR, DEMOCRATIC STUDIES | D64: 17(9) | E64: =1435720*(10/31) -> 463135.48 | G64: =200000*(10/31) -> 64516.129 | I64: 0 | J64: =SUM(E64:I64) -> 527651.61 | M64: 447675.83 | O64: 79975.78 | Q64: =O64+N64+M64+L64+K64+P64 -> 527651.61 | R64: 442995.09 | S64: =J64-Q64 -> 0.0029032258
A65: 2 | B65: NDANUSA MOHAMMED MANZUMA | C65: SNR RESEARCH FELLOW | D65: 15(8) | E65: 601396.83 | G65: =160000 -> 160000 | I65: 0 | J65: 0 | Q65: =O65+N65+M65+L65+K65+P65 -> 0 | R65: 267139.94 | S65: =J65-Q65 -> 0
A66: 3 | B66: EJALONIBU GANIYU LAYI | C66: RESEARCH FELLOW 1 | D66: 14(8) | E66: 442746.5 | G66: 140000 | J66: =SUM(E66:I66) -> 582746.5 | L66: =110000+90000 -> 200000 | O66: 83753.408 | P66: 35419.72 | Q66: =O66+N66+M66+L66+K66+P66 -> 319173.13 | R66: 263573.37 | S66: =J66-Q66 -> 263573.37
A67: 4 | B67: UDEFUNA NNADOZIE PATRICK | C67: RESEARCH OFFICER | D67: 12(8) | E67: 365703.83 | G67: =110000 -> 110000 | I67: 0 | J67: =SUM(E67:I67) -> 475703.83 | L67: 10000 | M67: =163196.67 -> 163196.67 | O67: 64384.592 | P67: 29256.307 | Q67: =O67+N67+M67+L67+K67+P67 -> 266837.57 | R67: 208866.26 | S67: =J67-Q67 -> 208866.26
A68: 5 | B68: SHAFIU YAHYA MIKAIL | C68: PRINCIPAL RESEARCH OFFICER | D68: 12(8) | E68: 365703.83 | G68: =110000 -> 110000 | I68: 0 | J68: =SUM(E68:I68) -> 475703.83 | L68: =52000-2000 -> 50000 | O68: 64384.592 | P68: 29256.307 | Q68: =O68+N68+M68+L68+K68+P68 -> 143640.9 | R68: 332062.93 | S68: =J68-Q68 -> 332062.93
A69: 6 | B69: HASSAN YERIMA | C69: PRINCIPAL RESEARCH OFFICER | D69: 12(8) | E69: 365703.83 | G69: =110000 -> 110000 | I69: 0 | J69: =SUM(E69:I69) -> 475703.83 | L69: =67000-2000 -> 65000 | O69: 64384.592 | P69: 29256.307 | Q69: =O69+N69+M69+L69+K69+P69 -> 158640.9 | R69: 317062.93 | S69: =J69-Q69 -> 317062.93
A70: 7 | B70: HAUWA PATE SADIQ | C70: PRINCIPAL PROGRAMME OFFICER | D70: 12(9) | E70: 377895.17 | G70: =110000 -> 110000 | J70: =SUM(E70:I70) -> 487895.17 | L70: =80000+20000 -> 100000 | O70: 66538.069 | P70: 30231.613 | Q70: =O70+N70+M70+L70+K70+P70 -> 196769.68 | R70: 291125.48 | S70: =J70-Q70 -> 291125.48
A71: 8 | B71: KOLAPO Q. ABAYOMI | C71: RESEARCH OFFICER | D71: 10(8) | E71: 300965.58 | G71: 100000 | J71: =SUM(E71:I71) -> 400965.58 | O71: 51029.227 | P71: 24077.247 | Q71: =O71+N71+M71+L71+K71+P71 -> 75106.474 | R71: 325859.11 | S71: =J71-Q71 -> 325859.11
B72: TOTAL | C72: 8 | E72: =SUM(E64:E71) -> 3283251.1 | F72: =SUM(F64:F71) -> 0 | G72: =SUM(G64:G71) -> 904516.13 | H72: =SUM(H64:H71) -> 0 | I72: =SUM(I64:I71) -> 0 | J72: =SUM(J64:J71) -> 3426370.4 | K72: =SUM(K64:K71) -> 0 | L72: =SUM(L64:L71) -> 425000 | ... Q72: =SUM(Q64:Q71) -> 1687820.3 | R72: 2448685.1 | S72: =SUM(S64:S71) -> 1738550.1
B74: DEPARTMENT OF STUDIES
A75: 1 | B75: DR ASIMIYU G. ABIOLA | C75: DIRECTOR POST GRADUATE | D75: 17(9) | E75: 1435720 | G75: =200000 -> 200000 | I75: 0 | J75: =SUM(E75:I75) -> 1635720 | L75: 350000 | M75: =0 -> 0 | N75: 0 | O75: 270672.25 | P75: 114857.6 | Q75: =O75+N75+M75+L75+K75+P75 -> 735529.85 | R75: 900190.15 | S75: =J75-Q75 -> 900190.15
A76: 2 | B76: DR. HADIZA SAIDU | C76: ASSISTANT DIRECTOR | D76: 15(7) | E76: 582118.08 | G76: 160000 | J76: =SUM(E76:I76) -> 742118.08 | O76: 112212 | P76: 46569.447 | Q76: =O76+N76+M76+L76+K76+P76 -> 158781.45 | R76: 583336.63 | S76: =J76-Q76 -> 583336.63
A77: 3 | B77: ANTHONY EDET | C77: CHIEF PROGRAMMES OFFICER | D77: 14(9) | E77: 456622.25 | G77: =140000 -> 140000 | I77: 0 | J77: =SUM(E77:I77) -> 596622.25 | L77: 20000 | M77: 210785.51 | N77: ='New NHF Deduction'!G79 -> 6154.3229 | O77: 86076.104 | P77: 36529.78 | Q77: =O77+N77+M77+L77+K77+P77 -> 359545.72 | R77: 237076.53 | S77: =J77-Q77 -> 237076.53
A78: 4 | B78: IGWE STACY | C78: PRINC. PROGRAMME OFFICER | D78: 12(7) | E78: 353512.5 | G78: =110000 -> 110000 | J78: =SUM(E78:I78) -> 463512.5 | L78: =50000 -> 50000 | M78: =50000 -> 50000 | O78: =62231.1146666667 -> 62231.115 | P78: =28281 -> 28281 | Q78: =O78+N78+M78+L78+K78+P78 -> 190512.11 | R78: 273000.39 | S78: =J78-Q78 -> 273000.39
A79: 5 | B79: OLANIYAN TAIWO ABINBOLA | C79: PROGRAMME OFFICER | D79: 9(8) | E79: 263165.33 | G79: 100000 | J79: =SUM(E79:I79) -> 363165.33 | O79: 44641.501 | P79: 21053.227 | Q79: =O79+N79+M79+L79+K79+P79 -> 65694.727 | R79: 297470.61 | S79: =J79-Q79 -> 297470.61
A80: 6 | B80: AMINAT JUMOKE SULAIMON | C80: AST. PROGRAMME OFFICER | D80: 8(8) | E80: 224459.75 | G80: 100000 | H80: 0 | J80: =SUM(E80:I80) -> 324459.75 | L80: 80000 | M80: 0 | N80: 0 | O80: 38659.166 | P80: 17956.78 | Q80: =O80+N80+M80+L80+K80+P80 -> 136615.95 | R80: 187843.8 | S80: =J80-Q80 -> 187843.8
B81: TOTAL | C81: 6 | E81: =SUM(E75:E80) -> 3315597.9 | F81: =SUM(F75:F80) -> 0 | G81: =SUM(G75:G80) -> 810000 | H81: =SUM(H75:H80) -> 0 | I81: =SUM(I75:I80) -> 0 | J81: =SUM(J75:J80) -> 4125597.9 | K81: =SUM(K75:K80) -> 0 | L81: =SUM(L75:L80) -> 500000 | ... Q81: =SUM(Q75:Q80) -> 1646679.8 | R81: 2478918.1 | S81: =SUM(S75:S80) -> 2478918.1
B83: ECON. DEV. & SOC. RESEARCH
A84: 1 | B84: TERFA WILLIAMS ABRAHAM | C84: SNR RESEARCH FELLOW | D84: 15(9) | E84: 620675.58 | G84: =160000 -> 160000 | I84: =100000+100000 -> 200000 | J84: =SUM(E84:I84) -> 980675.58 | O84: ='Additional Leg Duty Allowance'!P11 -> 157422.8 | P84: 49654.047 | Q84: =O84+N84+M84+L84+K84+P84 -> 207076.85 | R84: 773598.73 | S84: =J84-Q84 -> 773598.73
A85: 2 | B85: DR AUGUSTINE C. OSIGWE | C85: SNR RESEARCH FELLOW | D85: 15(9) | E85: 620675.58 | G85: =160000 -> 160000 | J85: =SUM(E85:I85) -> 780675.58 | L85: =30000 -> 30000 | M85: 98750 | N85: ='New NHF Deduction'!G87 -> 8380.2271 | O85: 118861.97 | P85: 49654.047 | Q85: =O85+N85+M85+L85+K85+P85 -> 305646.24 | R85: 475029.34 | S85: =J85-Q85 -> 475029.34
A86: 3 | B86: OMOJU OLUWASOLA EMMANUEL | C86: SNR RESEARCH FELLOW | D86: 15(7) | E86: 582118.08 | G86: 160000 | J86: =SUM(E86:I86) -> 742118.08 | L86: =50000 -> 50000 | O86: 112212 | P86: 46569.447 | Q86: =O86+N86+M86+L86+K86+P86 -> 208781.45 | R86: 533336.63 | S86: =J86-Q86 -> 533336.63
A87: 4 | B87: IBE EZECHI CYRIACUS | C87: RESEARCH FELLOW 1 | D87: 14(8) | E87: 442746.5 | G87: =140000 -> 140000 | I87: 0 | J87: =SUM(E87:I87) -> 582746.5 | L87: =50000 -> 50000 | M87: =77638.89 -> 77638.89 | O87: 83767.87 | P87: 35344.393 | Q87: =O87+N87+M87+L87+K87+P87 -> 246751.15 | R87: 335995.35 | S87: =J87-Q87 -> 335995.35
A88: 5 | B88: OSIKHEN LEO IGBANOI | C88: RESEARCH FELLOW 1 | D88: 14(8) | E88: 442746.5 | G88: =140000 -> 140000 | I88: 0 | J88: =SUM(E88:I88) -> 582746.5 | L88: 50000 | M88: 0 | O88: 83753.408 | P88: =35419.72 -> 35419.72 | Q88: =O88+N88+M88+L88+K88+P88 -> 169173.13 | R88: 413573.37 | S88: =J88-Q88 -> 413573.37
A89: 6 | B89: OKUNGBOWA OSARETIN GODSPOWER | C89: RESEARCH FELLOW 1 | D89: 14(7) | E89: 428870.75 | G89: =140000 -> 140000 | I89: 0 | J89: =SUM(E89:I89) -> 568870.75 | L89: =100000-100000 -> 0 | O89: 81302.396 | P89: 34309.66 | Q89: =O89+N89+M89+L89+K89+P89 -> 115612.06 | R89: 453258.69 | S89: =J89-Q89 -> 453258.69
A90: 7 | B90: YUSUF IBRAHIM | C90: PRINCIPAL RESEARCH OFFICER | D90: 12(8) | E90: 365703.83 | G90: =110000 -> 110000 | I90: 0 | J90: =SUM(E90:I90) -> 475703.83 | L90: =20000 -> 20000 | M90: 43750 | O90: 64384.592 | P90: 29256.307 | Q90: =O90+N90+M90+L90+K90+P90 -> 157390.9 | R90: 318312.93 | S90: =J90-Q90 -> 318312.93
A91: 8 | B91: MUSTAPHA RAFIU AYOBANJI | C91: RESEARCH FELLOW 11 | D91: 13(7) | E91: 390248.92 | G91: 120000 | I91: 0 | J91: =SUM(E91:I91) -> 510248.92 | L91: 0 | N91: ='New NHF Deduction'!G93 -> 5259.7437 | O91: 70529.475 | P91: 31219.913 | Q91: =O91+N91+M91+L91+K91+P91 -> 107009.13 | R91: 403239.78 | S91: =J91-Q91 -> 403239.78
A92: 9 | B92: MARYAM MUSA SADA | C92: ASSIT. RESEARCH OFFICER | D92: 10(8) | E92: 300965.58 | G92: 100000 | J92: =SUM(E92:I92) -> 400965.58 | O92: 51029.227 | P92: 24077.247 | Q92: =O92+N92+M92+L92+K92+P92 -> 75106.474 | R92: 325859.11 | S92: =J92-Q92 -> 325859.11
A93: 10 | B93: CHARITY EZENWAJIOBI | C93: REASEARCH. ASST. | D93: 8(9) | E93: 230631.92 | G93: =100000 -> 100000 | J93: =SUM(E93:I93) -> 330631.92 | L93: 50000 | N93: 0 | O93: 39613.136 | P93: 18450.553 | Q93: =O93+N93+M93+L93+K93+P93 -> 108063.69 | R93: 222568.23 | S93: =J93-Q93 -> 222568.23
B94: TOTAL | C94: 10 | E94: =SUM(E84:E93) -> 4425383.2 | F94: =SUM(F84:F93) -> 0 | G94: =SUM(G84:G93) -> 1330000 | H94: =SUM(H84:H93) -> 0 | I94: =SUM(I84:I93) -> 200000 | J94: =SUM(J84:J93) -> 5955383.2 | K94: =SUM(K84:K93) -> 0 | L94: =SUM(L84:L93) -> 250000 | ... Q94: =SUM(Q84:Q93) -> 1700611.1 | R94: 4254772.2 | S94: =SUM(S84:S93) -> 4254772.2
B96: TRAINING & INT''L COOP
A97: 1 | B97: AKINSANMI ADEJOKE OLUKEMI | C97: Ag. DIR. TRAINING & IC | D97: 17(7) | E97: ='[3]Annual & Monthly'!$H$44 -> 1352042.7 | H97: =100000 -> 100000 | J97: =E97+F97+G97+H97+I97 -> 1452042.7 | L97: 500000 | M97: 0 | N97: ='New NHF Deduction'!G99 -> 18254.975 | O97: ='March New PAYE '!Z93 -> 236486.75 | P97: ='Upgrade in March'!P8 -> 114857.6 | Q97: =O97+N97+M97+L97+K97+P97 -> 869599.32 | R97: 582443.34 | S97: =J97-Q97 -> 582443.34
A98: 2 | B98: MOHAMMED R. ADAMU | C98: CHIEF TRAINING OFFICER | D98: 14(9) | E98: 456622.25 | H98: 70000 | I98: 0 | J98: =E98+F98+G98+H98+I98 -> 526622.25 | L98: =10000 -> 10000 | M98: 175000 | O98: 72764.421 | P98: 36529.78 | Q98: =O98+N98+M98+L98+K98+P98 -> 294294.2 | R98: 232328.05 | S98: =J98-Q98 -> 232328.05
A99: 6 | B99: EROMOSELE OMONIGBO | C99: ASSIST. CHIEF PERSONNEL OFFICER | D99: 13(7) | E99: 390248.92 | H99: =70000 -> 70000 | I99: 0 | J99: =SUM(E99:I99) -> 460248.92 | L99: 40000 | M99: 87500 | N99: 5967.3062 | O99: 59711.115 | P99: =31219.91 -> 31219.91 | Q99: =O99+N99+M99+L99+K99+P99 -> 224398.33 | R99: 245450.59 | S99: =J99-Q99 -> 235850.59
A100: 3 | B100: OKECHUKWU UCHENNA HULDA | C100: PRINCIPALTRAINING OFFICER | D100: 12(9) | E100: 377895.17 | H100: =60000 -> 60000 | J100: =E100+F100+G100+H100+I100 -> 437895.17 | L100: =5000 -> 5000 | M100: 52500 | O100: 56938.069 | P100: 30231.613 | Q100: =O100+N100+M100+L100+K100+P100 -> 144669.68 | R100: 293225.48 | S100: =J100-Q100 -> 293225.48
A101: 4 | B101: TASSNEEM IBRAHIM | C101: SENIOR PROGRAMME OFFICER | D101: 10(8) | E101: 300965.58 | H101: =60000 -> 60000 | J101: =E101+F101+G101+H101+I101 -> 360965.58 | L101: =10000+80000 -> 90000 | M101: =19583.33 -> 19583.33 | O101: 43763.907 | P101: 24077.247 | Q101: =O101+N101+M101+L101+K101+P101 -> 177424.48 | R101: 183541.1 | S101: =J101-Q101 -> 183541.1
B102: TOTAL | C102: 4 | E102: =SUM(E97:E101) -> 2877774.6 | F102: =SUM(F97:F101) -> 0 | G102: =SUM(G97:G101) -> 0 | H102: =SUM(H97:H101) -> 360000 | I102: =SUM(I97:I101) -> 0 | J102: =SUM(J97:J101) -> 3237774.6 | K102: =SUM(K97:K101) -> 0 | L102: =SUM(L97:L101) -> 645000 | ... Q102: =SUM(Q97:Q101) -> 1710386 | R102: 1536988.6 | S102: =SUM(S97:S101) -> 1527388.6
B104: LIBRARY & DOCUMENTATION
A105: 1 | B105: DR MAIMUNA IZAH | C105: INSITUTE LIBRARIAN | D105: 17(9) | E105: 1435720 | G105: =200000 -> 200000 | I105: 0 | J105: =SUM(E105:I105) -> 1635720 | L105: =100000 -> 100000 | M105: 0 | N105: 0 | O105: 270672.25 | P105: 114857.6 | Q105: =O105+N105+M105+L105+K105+P105 -> 485529.85 | R105: 1150190.2 | S105: =J105-Q105 -> 1150190.2
A106: 2 | B106: CATHERINE E. IKOKOH | C106: SNR RESEARCH FELLOW DOCU | D106: 16(9) | E106: 762373.17 | G106: =160000+20000 -> 180000 | I106: 0 | J106: =SUM(E106:I106) -> 942373.17 | L106: 110000 | N106: 10293.398 | O106: 147687.53 | P106: 60989.853 | Q106: =O106+N106+M106+L106+K106+P106 -> 328970.78 | R106: 613402.39 | S106: =J106-Q106 -> 613402.39
A107: 3 | B107: ALIYU SANNI ABUBAKAR | C107: RESEARCH FELLOW 11 DATA & DOCU | D107: 13(11) | E107: 441804.92 | G107: =120000 -> 120000 | I107: 41432.939 | J107: =SUM(E107:I107) -> 603237.86 | L107: 30000 | M107: =61111.11 -> 61111.11 | N107: 5954.6104 | O107: 87575.783 | P107: 35344.393 | Q107: =O107+N107+M107+L107+K107+P107 -> 219985.9 | R107: 383251.96 | S107: =J107-Q107 -> 383251.96
A108: 4 | B108: CHINAKO N. ASOGWA | C108: RESEARCH FELLOW 11 DATA & DOCU | D108: 13(11) | E108: 441804.92 | G108: =120000 -> 120000 | I108: 39820.117 | J108: =SUM(E108:I108) -> 601625.03 | L108: =50000 -> 50000 | M108: 45833.33 | O108: 87392.55 | P108: 35344.393 | Q108: =O108+N108+M108+L108+K108+P108 -> 218570.27 | R108: 383054.76 | S108: =J108-Q108 -> 383054.76
...

Sheet MEMO
A2: NATIONAL INSTITUTE FOR LEGISLATIVE AND DEMOCRATIC STUDIES
A3: INTERNAL MEMO
A4: FROM : DEPUTY DIRECTOR, FINANCE AND ACCOUNTS
A5: THRU: DIRECTOR, FINANCE AND ACCOUNTS
A6: TO: DG
A7: 29TH JANUARY , 2021
A9: SUBJECT: PAYROLL FOR THE MONTH OF JANUARY, 2021
A10: Find below the details of NILDS Staff Payroll for the month of January, 2021
A13: TO: | C13: DIRECTOR, GENERAL
A14: THRU: | C14: DIRECTOR, FINANCE AND ACCOUNT
A15: FROM: | C15: DEPUTY DIRECTOR, FINANCE AND ACCOUNTS
A16: DATE: | C16: 27TH MARCH 2025
A18: SUBJECT: PAYROLL FOR THE MONTH OF MARCH 2025
A19: Find below the details of NILDS Staff Payroll for the Month of March, 2025: | G19: NGN | H19: NGN
A20: GROSS SALARY FOR MARCH, 2025 | H20: ='MARCH 2025'!J202 -> 77088525
A22: DEDUCTIONS
A23: COOP SOCIETY DEDUCTIONS ( CONTR.& SPEC. SAVINGS) | G23: ='MARCH 2025'!L202 -> 6251500
A24: COOP LOAN RECOVERY | G24: ='MARCH 2025'!M202 -> 8553215.4
A25: NHF DEDUCTIONS | G25: ='MARCH 2025'!N202 -> 237989.65
A26: PAYE DEDUCTIONS | G26: ='MARCH 2025'!O202 -> 10821560
A27: PENSION DEDUCTIONS | G27: ='MARCH 2025'!P202 -> 4699546.2
A28: TOTAL DEDUCTIONS FOR MARCH 2025 | H28: =G23+G24+G26+G25+G27 -> 30563811
A29: NET PAY AS PER MARCH 2025 PAYROLL | H29: =H20-H28 -> 46524714
A30: NET PAY AS PER FEBRUARY, 2025 PAYROLL | H30: ='MARCH 2025'!R202 -> 48377702
A31: NET INCREASE/ (DECREASE) IN PAY FOR MARCH, 2025 | H31: =H29-H30 -> -1852988.4
A32: ANALYSED AS FOLLOWS:
A33: Effect of Cooperative Adjustment for March, 2025 | H33: =919105.44 -> 919105.44
A34: Effect of removal of Arrears for Omo & Chris Odoh | H34: =19200 -> 19200
A35: Effect of Stoppage of payment to Ndanusa M. Manzuma | H35: =267139.95 -> 267139.95
A36: Effect of Prorated Payment to Adewale Aderemi | H36: =442995.09 -> 442995.09
A37: Net Effect of Regularization of Salary to Joseph Gwatana | H37: =204547.91 -> 204547.91
H38: =SUM(H33:H37) -> 1852988.4
E41: JANUARY, 2025 | G41: FEBRUARY, 2025
E42: No. of Staff | F42: N | G42: No. of Staff | H42: N
A43: 1 | B43: Director General's Office | E43: 32 | F43: ='MARCH 2025'!R38 -> 13048226 | G43: ='MARCH 2025'!C38 -> 31 | H43: ='MARCH 2025'!S38 -> 12887245
A44: 2 | B44: Internal Audit | E44: 3 | F44: ='MARCH 2025'!R45 -> 1123988.3 | G44: ='MARCH 2025'!C45 -> 4 | H44: ='MARCH 2025'!S45 -> 1123988.3
A45: 3 | B45: Legis. Support Services | E45: 11 | F45: ='MARCH 2025'!R56 -> 3302553.5 | G45: ='MARCH 2025'!C56 -> 9 | H45: ='MARCH 2025'!S56 -> 3302553.5
A46: 4 | B46: Legal Services | E46: 2 | F46: ='MARCH 2025'!R61 -> 1352548.9 | G46: ='MARCH 2025'!C61 -> 2 | H46: ='MARCH 2025'!S61 -> 1352548.9
A47: 5 | B47: Democracy and Governance | E47: 12 | F47: ='MARCH 2025'!R72 -> 2448685.1 | G47: ='MARCH 2025'!C72 -> 8 | H47: ='MARCH 2025'!S72 -> 1738550.1
A48: 6 | B48: Studies | E48: 6 | F48: ='MARCH 2025'!R81 -> 2478918.1 | G48: ='MARCH 2025'!C81 -> 6 | H48: ='MARCH 2025'!S81 -> 2478918.1
A49: 7 | B49: Economic Dev. & Social Research | E49: 11 | F49: ='MARCH 2025'!R94 -> 4254772.2 | G49: ='MARCH 2025'!C94 -> 10 | H49: ='MARCH 2025'!S94 -> 4254772.2
A50: 8 | B50: Training & Int'l Cooperation | E50: 4 | F50: ='MARCH 2025'!R102 -> 1536988.6 | G50: ='MARCH 2025'!C102 -> 4 | H50: ='MARCH 2025'!S102 -> 1527388.6
A51: 9 | B51: Library & Documentation | E51: 7 | F51: ='MARCH 2025'!R112 -> 3308491.6 | G51: ='MARCH 2025'!C112 -> 7 | H51: ='MARCH 2025'!S112 -> 3308491.6
A52: 10 | B52: Leg. Center for Security Analysis | E52: 2 | F52: ='MARCH 2025'!R118 -> 1008539.7 | G52: ='MARCH 2025'!C118 -> 2 | H52: ='MARCH 2025'!S118 -> 998939.68
A53: 11 | B53: Democracy Radio 104.9 | E53: 3 | F53: ='MARCH 2025'!R124 -> 664558.14 | G53: 3 | H53: ='MARCH 2025'!S124 -> 664558.14
A54: 12 | B54: Finance and Accounts | E54: 10 | F54: ='MARCH 2025'!R137 -> 3206493.4 | G54: ='MARCH 2025'!C137 -> 10 | H54: ='MARCH 2025'!S137 -> 3206493.4
A55: 13 | B55: Admin & Human Resource | E55: 61 | F55: ='MARCH 2025'!R201 -> 10642939 | G55: ='MARCH 2025'!C201 -> 61 | H55: ='MARCH 2025'!S201 -> 9680266.1
E56: =SUM(E43:E55) -> 164 | F56: =SUM(F43:F55) -> 48377702 | G56: 155 | H56: =SUM(H43:H55) -> 46524714
A58: The Director General is requested to consider and approve payment of N46,524,713.92 to Guaranty Trust Bank being March, 2025 Salary, N14,804,715.39 being NILDS Coop Society deductions for March 2025, N10,821,559.70 being PAYE Tax Deductions from Staff Salary for the month of March 2025 and N237,989.65 being NHF deductions from staff for March 2025
A62: RAHILA NURUDEEN HABU
C166: =10000 -> 10000

Sheet 2024 Promotion Arrears
A1: NATIONAL INSTITUTE FOR LEGISLATIVE & DEMOCRATIC STUDIES
A2: 2024 ANALYSIS OF STAFF PROMOTION ARREARS
A4: SN | B4: Name of Employee | C4: Department | D4: Present Grade Level | E4: New Grade Level | F4: Consolidated Salary of Present Position | G4: Consolidated Salary of New Position | H4: Diference/Arrears | I4: No of Months | J4: Total Amount of Arrears (Gross)
F5: N | G5: N | H5: N | J5: N
A6: 1 | B6: ABDULSALAM MUSTAPHA | C6: DG's Office | D6: 13/11 | E6: 15/7 | F6: =511804.92 -> 511804.92 | G6: =582118+80000 -> 662118 | H6: =G6-F6 -> 150313.08 | I6: 1 | J6: =H6*I6 -> 150313.08
A7: 2 | B7: EMILY EDIOSA IKHIDE | C7: DG's Office | D7: 014/10 | E7: 015/7 | F7: 610498 | G7: =582118+160000 -> 742118 | H7: =G7-F7 -> 131620 | I7: 4 | J7: =H7*I7 -> 526480
A8: 3 | B8: SIMON WAKAWA | C8: DG's Office | D8: 014/11 | E8: 015/7 | F8: 554373.75 | G8: =582118+80000 -> 662118 | H8: =G8-F8 -> 107744.25 | I8: =2.71 -> 2.71 | J8: =H8*I8 -> 291986.92
A9: 4 | B9: WAZIRI USMAN | C9: Admin. & HR | D9: 014/11 | E9: 015/7 | F9: 554374.75 | G9: =582118+80000 -> 662118 | H9: =G9-F9 -> 107743.25 | I9: =2.71 -> 2.71 | J9: =H9*I9 -> 291984.21
A10: 5 | B10: TAIWO I. OYINLOLA | C10: Admin. & HR | D10: 05/9 | E10: 07/3 | F10: 121145.75 | G10: 189814.17 | H10: =G10-F10 -> 68668.417 | I10: 0 | J10: =H10*I10 -> 0 | K10: Effective in Dec
A11: 6 | B11: SARATU ATAJIRI | C11: Admin. & HR | D11: N/A | E11: 09/7 | F11: 120000 | G11: =255849+60000 -> 315849 | H11: =G11-F11 -> 195849 | I11: 8 | J11: =H11*I11 -> 1566792
A12: 7 | B12: YUSIF SANI SADIQ | C12: Admin. & HR | D12: 10/9 | E12: 12/7 | F12: 368901.5 | G12: 413512.5 | H12: =G12-F12 -> 44611 | I12: 2.71 | J12: =H12*I12 -> 120895.81
A13: 8 | B13: STELLA NGOZI PAUL | C13: Admin. & HR | D13: 10/10 | E13: 12/7 | F13: 376837.42 | G13: 413512.5 | H13: =G13-F13 -> 36675.083 | I13: 2.71 | J13: =H13*I13 -> 99389.476
A14: 9 | B14: OMONIGHO EROMOSELE-WESEY | C14: Admin. & HR | D14: 12/10 | E14: 13/7 | F14: 450086.5 | G14: 510248.92 | H14: =G14-F14 -> 60162.417 | I14: 8 | J14: =H14*I14 -> 481299.33
A15: 10 | B15: QUEEN ONYEKESON | C15: Admin. & HR | D15: 12/10 | E15: 13/7 | F15: 450086.5 | G15: 510248.92 | H15: =G15-F15 -> 60162.417 | I15: 2.71 | J15: =H15*I15 -> 163040.15
A16: 11 | B16: SHAMSUDEEN YAHAYA | C16: LSS | D16: 014/10 | E16: 015/7 | F16: 610498 | G16: 742118 | H16: =G16-F16 -> 131620 | I16: 3 | J16: =H16*I16 -> 394860
A17: 12 | B17: SALAMATU YAKUBU | C17: LSS | D17: 014/11 | E17: 015/7 | F17: 554373.75 | G17: 662118 | H17: =G17-F17 -> 107744.25 | I17: 3 | J17: =H17*I17 -> 323232.75
A18: 13 | B18: ROTIMI OGUNYOMI | C18: LSS | D18: 12/10 | E18: 13/7 | F18: 450086.5 | G18: 510248.92 | H18: =G18-F18 -> 60162.417 | I18: 3 | J18: =H18*I18 -> 180487.25
A19: 14 | B19: LEO IGBANOI | C19: Dem. & Gov. | D19: 13/10 | E19: 14/8 | F19: 548915.92 | G19: 582746.5 | H19: =G19-F19 -> 33830.583 | I19: 20 | J19: =H19*I19 -> 676611.67
A20: 15 | B20: TOSIN OWOEYE | C20: Dem. & Gov. | D20: 10/9 | E20: 12/7 | F20: 368901.5 | G20: 413512.5 | H20: =G20-F20 -> 44611 | I20: 9 | J20: =H20*I20 -> 401499
A21: 16 | B21: STACY CHINYERE IGWE | C21: DOS | D21: 10/9 | E21: 12/7 | F21: 408901.5 | G21: =353512.5+110000 -> 463512.5 | H21: =G21-F21 -> 54611 | I21: 12 | J21: =H21*I21 -> 655332
A22: 17 | B22: TANIMU M. LAWAL | C22: Econ/ & Social Res. | D22: 04/10 | E22: 07/3 | F22: 102926.92 | G22: 189814.17 | H22: =G22-F22 -> 86887.25 | I22: 1 | J22: =H22*I22 -> 86887.25
A23: 18 | B23: CHRISTIAN MADUABUCHI ODO | C23: Finance & Accts | D23: 12/10 | E23: 13/7 | F23: 450086.5 | G23: 510248.92 | H23: =G23-F23 -> 60162.417 | I23: 3 | J23: =H23*I23 -> 180487.25
B24: TOTAL | J24: =SUM(J6:J23) -> 6591578.1

Sheet  PAYE regul
A1: NATIONAL INSTITUTE FOR LEGISLATIVE AND DEMOCRATIC STUDIES
A2: NATIONAL ASSEMBLY ABUJA
A3: TAX COMPUTATION FOR 2022
A4: S/NO | B4: NAME | C4: MONTHLY TOTAL SALARY | D4: NO OF MONTHS | E4: ANNUAL SALARY GROSSED UP | F4: NATIONAL HOUSING SCHEME = 2.5% OF BASIC SALARY | G4: PENSION CONTRIBUTION = 8% OF CONSOLIDATED | H4: NHIS | I4: NET SALARY (EXC OF CRA) | M4: CRA=#200,000+(20% 0F NET SALARY (EXC OF CRA) | N4: TOTAL RELIEF | O4: CHARGEABLE INCOME | P4: FIRST N300,000 @ 7% | Q4: NEXT N300,000 @ 11% | R4: NEXT N500,000 @ 15% | S4: NEXT N500,000@ 19% | T4: NEXT N1,600,000 @ 21% | U4: ABOVE N3,200,000 @ 24% | V4: ANNUAL TAX PAYABLE | X4: MONTHLY TAX PAYABLE | Y4: MINIMUM TAX PAYABLE | Z4: NEW ACTUAL TAX PAYABLE | AA4: TAX OF DEC 2024 | AB4: EXCESS PAID
A5: 1 | B5: OMONIGHO EROMOSELE-WESEY | C5: 460248.92 | D5: 12 | E5: =C5*D5 -> 5522987 | F5: =6922.5*12 -> 83070 | G5: 374638.96 | I5: =E5-F5-G5-H5 -> 5065278 | J5: 200000 | K5: 0.2 | L5: =I5*K5 -> 1013055.6 | M5: =J5+L5 -> 1213055.6 | N5: =F5+G5+H5+M5 -> 1670764.6 | O5: =E5-N5 -> 3852222.4 | P5: =IF(O5<300000,0.07*O5,21000) -> 21000 | Q5: =IF((O5-300000)<0,0,IF((O5-300000)<300000,0.11*(O5-300000),33000)) -> 33000 | R5: =IF((O5-600000)<0,0,IF((O5-600000)<500000,0.15*(O5-600000),75000)) -> 75000 | S5: =IF((O5-1100000)<0,0,IF((O5-1100000)<500000,0.19*(O5-1100000),95000)) -> 95000 | T5: =IF((O5-1600000)<0,0,IF((O5-1600000)<1600000,0.21*(O5-1600000),336000)) -> 336000 | U5: =24%*(O5-3200000) -> 156533.38 | V5: =P5+Q5+R5+S5+T5+U5 -> 716533.38 | W5: 12 | X5: =V5/W5 -> 59711.115 | Z5: =X5 -> 59711.115 | AA5: 69311.115 | AB5: =AA5-Z5 -> 9600 | AD5: OMONIGHO EROMOSELE-WESEY
A6: 2 | B6: QUEEN ONYEKESON | C6: 460248.92 | D6: 12 | E6: =C6*D6 -> 5522987 | G6: 374638.96 | I6: =E6-F6-G6-H6 -> 5148348 | J6: 200000 | K6: 0.2 | L6: =I6*K6 -> 1029669.6 | M6: =J6+L6 -> 1229669.6 | N6: =F6+G6+H6+M6 -> 1604308.6 | O6: =E6-N6 -> 3918678.4 | P6: =IF(O6<300000,0.07*O6,21000) -> 21000 | Q6: =IF((O6-300000)<0,0,IF((O6-300000)<300000,0.11*(O6-300000),33000)) -> 33000 | R6: =IF((O6-600000)<0,0,IF((O6-600000)<500000,0.15*(O6-600000),75000)) -> 75000 | S6: =IF((O6-1100000)<0,0,IF((O6-1100000)<500000,0.19*(O6-1100000),95000)) -> 95000 | T6: =IF((O6-1600000)<0,0,IF((O6-1600000)<1600000,0.21*(O6-1600000),336000)) -> 336000 | U6: =24%*(O6-3200000) -> 172482.82 | V6: =P6+Q6+R6+S6+T6+U6 -> 732482.82 | W6: 12 | X6: =V6/W6 -> 61040.235 | Z6: =X6 -> 61040.235 | AA6: 70640.235 | AB6: =AA6-Z6 -> 9600 | AD6: QUEEN ONYEKESON
A7: 3 | B7: ROTIMI OGUNYOMI | C7: 460248.92 | D7: 12 | E7: =C7*D7 -> 5522987 | G7: 374638.96 | I7: =E7-F7-G7-H7 -> 5148348 | J7: 200000 | K7: 0.2 | L7: =I7*K7 -> 1029669.6 | M7: =J7+L7 -> 1229669.6 | N7: =F7+G7+H7+M7 -> 1604308.6 | O7: =E7-N7 -> 3918678.4 | P7: =IF(O7<300000,0.07*O7,21000) -> 21000 | Q7: =IF((O7-300000)<0,0,IF((O7-300000)<300000,0.11*(O7-300000),33000)) -> 33000 | R7: =IF((O7-600000)<0,0,IF((O7-600000)<500000,0.15*(O7-600000),75000)) -> 75000 | S7: =IF((O7-1100000)<0,0,IF((O7-1100000)<500000,0.19*(O7-1100000),95000)) -> 95000 | T7: =IF((O7-1600000)<0,0,IF((O7-1600000)<1600000,0.21*(O7-1600000),336000)) -> 336000 | U7: =24%*(O7-3200000) -> 172482.82 | V7: =P7+Q7+R7+S7+T7+U7 -> 732482.82 | W7: 12 | X7: =V7/W7 -> 61040.235 | Z7: =X7 -> 61040.235 | AA7: 70640.235 | AB7: =AA7-Z7 -> 9600 | AD7: ROTIMI OGUNYOMI
A8: 4 | B8: CHRISTIAN MADUABUCHI ODO | C8: 110955 | D8: 12 | E8: =C8*D8 -> 1331460 | I8: =E8-F8-G8-H8 -> 1331460 | J8: 200000 | K8: 0.2 | L8: =I8*K8 -> 266292 | M8: =J8+L8 -> 466292 | N8: =F8+G8+H8+M8 -> 466292 | O8: =E8-N8 -> 865168 | P8: =IF(O8<300000,0.07*O8,21000) -> 21000 | Q8: =IF((O8-300000)<0,0,IF((O8-300000)<300000,0.11*(O8-300000),33000)) -> 33000 | R8: =IF((O8-600000)<0,0,IF((O8-600000)<500000,0.15*(O8-600000),75000)) -> 39775.2 | S8: =IF((O8-1100000)<0,0,IF((O8-1100000)<500000,0.19*(O8-1100000),95000)) -> 0 | T8: =IF((O8-1600000)<0,0,IF((O8-1600000)<1600000,0.21*(O8-1600000),336000)) -> 0 | V8: =P8+Q8+R8+S8+T8+U8 -> 93775.2 | W8: 12 | X8: =V8/W8 -> 7814.6 | Z8: =X8 -> 7814.6 | AA8: 69311.115 | AB8: =AA8-Z8 -> 61496.515 | AD8: CHRISTIAN MADUABUCHI ODO
B9: TOTAL - ANNUAL | C9: =SUM(C5:C8) -> 1491701.8 | F9: =SUM(F5:F8) -> 83070 | G9: =SUM(G5:G8) -> 1123916.9 | AB9: =SUM(AB5:AB8) -> 90296.515
B10: TOTAL - MONTHLY | F10: =F9/12 -> 6922.5 | G10: =G9/12 -> 93659.741

Sheet Promotion in Sept
A1: NATIONAL INSTITUTE FOR LEGISLATIVE AND DEMOCRATIC STUDIES | G1: ='[1]FEB 08'!F8/'[1]FEB 08'!Q8 -> 0.3
A2: STAFF PAYROLL FOR THE MONTH OF NOVEMBER 2024
E3: ='[1]FEB 08'!E11/'[1]FEB 08'!M11 -> #REF! | G3: ='[1]FEB 08'!F11/'[1]FEB 08'!Q11 -> #REF!
B4: STAFF NAME | C4: DESIGNATION | D4: GRADE LEVEL | E4: BASIC SALARY | F4: ALLCE/ AREARS | G4: ALLOWANCE | H4: ALLOWANCE | I4: DUTY ALLCE | J4: CURRENT GROSS SALARY | K4: NEW GRADE LEVEL | L4: NEW GROSS SALARY | M4: INCREMENT IN GROSS SALARY | N4: CURRENT NHF | O4: NEW NHF | P4: CURRENT PAYE | Q4: NEW PAYE | S4: INCREMENT IN PAYE | T4: NET SALARY INCREMENT | U4: NO OF MONTHS | V4: ARREARS
E5: N | F5: N | G5: N | H5: N | I5: N | J5: N | L5: N | N5: N | P5: N
A7: 1 | B7: IBE EZECHI CYRIACUS | C7: RESEARCH FELLOW II | D7: 13(11) | E7: 441804.92 | G7: =120000 -> 120000 | I7: 0 | J7: =SUM(E7:I7) -> 561804.92 | K7: 14(7) | L7: =442746.5+140000 -> 582746.5 | M7: =L7-J7 -> 20941.583 | P7: 79747.087 | Q7: =83767.87 -> 83767.87 | S7: =Q7-P7 -> 4020.7829 | T7: =M7-S7 -> 16920.8 | U7: 4.55 | V7: =T7*U7 -> 76989.642
B8: TOTAL | E8: =SUM(E7:E7) -> 441804.92 | F8: =SUM(F7:F7) -> 0 | G8: =SUM(G7:G7) -> 120000 | H8: =SUM(H7:H7) -> 0 | I8: =SUM(I7:I7) -> 0 | J8: =SUM(J7:J7) -> 561804.92 | L8: =SUM(L7:L7) -> 582746.5 | M8: =SUM(M7:M7) -> 20941.583 | N8: =SUM(N7:N7) -> 0 | O8: =SUM(O7:O7) -> 0 | P8: =SUM(P7:P7) -> 79747.087 | Q8: =SUM(Q7:Q7) -> 83767.87 | S8: =SUM(S7:S7) -> 4020.7829 | T8: =SUM(T7:T7) -> 16920.8 | V8: =SUM(V7:V7) -> 76989.642

Sheet Tax on Arrears
A1: NATIONAL INSTITUTE FOR LEGISLATIVE AND DEMOCRATIC STUDIES
A2: NATIONAL ASSEMBLY ABUJA
A3: TAX COMPUTATION FOR 2022
A4: S/NO | B4: NAME | C4: ARREARS OF PROMOTION | D4: NO OF MONTHS | E4: ANNUAL SALARY GROSSED UP | F4: NATIONAL HOUSING SCHEME = 2.5% OF BASIC SALARY | G4: PENSION CONTRIBUTION = 8% OF CONSOLIDATED | H4: NHIS | I4: NET SALARY (EXC OF CRA) | M4: CRA=#200,000+(20% 0F NET SALARY (EXC OF CRA) | N4: TOTAL RELIEF | O4: CHARGEABLE INCOME | P4: FIRST N300,000 @ 7% | Q4: NEXT N300,000 @ 11% | R4: NEXT N500,000 @ 15% | S4: NEXT N500,000@ 19% | T4: NEXT N1,600,000 @ 21% | U4: ABOVE N3,200,000 @ 24% | V4: ANNUAL TAX PAYABLE | X4: MONTHLY TAX PAYABLE | Y4: MINIMUM TAX PAYABLE | Z4: TAX PAYABLE ON ARREARS
A5: 1 | B5: ABDULSALAM MUSTAPHA | C5: 150313.08 | D5: 12 | E5: =C5*D5 -> 1803757 | G5: 558833.36 | I5: =E5-F5-G5-H5 -> 1244923.6 | J5: 200000 | K5: 0.2 | L5: =I5*K5 -> 248984.72 | M5: =J5+L5 -> 448984.72 | N5: =F5+G5+H5+M5 -> 1007818.1 | O5: =E5-N5 -> 795938.88 | P5: =IF(O5<300000,0.07*O5,21000) -> 21000 | Q5: =IF((O5-300000)<0,0,IF((O5-300000)<300000,0.11*(O5-300000),33000)) -> 33000 | R5: =IF((O5-600000)<0,0,IF((O5-600000)<500000,0.15*(O5-600000),75000)) -> 29390.832 | S5: =IF((O5-1100000)<0,0,IF((O5-1100000)<500000,0.19*(O5-1100000),95000)) -> 0 | T5: =IF((O5-1600000)<0,0,IF((O5-1600000)<1600000,0.21*(O5-1600000),336000)) -> 0 | U5: 0 | V5: =P5+Q5+R5+S5+T5+U5 -> 83390.832 | W5: 12 | X5: =V5/W5 -> 6949.236 | Z5: =X5 -> 6949.236
A6: 2 | B6: EMILY EDIOSA IKHIDE | C6: 526480 | D6: 12 | E6: =C6*D6 -> 6317760 | G6: 558833.36 | I6: =E6-F6-G6-H6 -> 5758926.6 | J6: 200000 | K6: 0.2 | L6: =I6*K6 -> 1151785.3 | M6: =J6+L6 -> 1351785.3 | N6: =F6+G6+H6+M6 -> 1910618.7 | O6: =E6-N6 -> 4407141.3 | P6: =IF(O6<300000,0.07*O6,21000) -> 21000 | Q6: =IF((O6-300000)<0,0,IF((O6-300000)<300000,0.11*(O6-300000),33000)) -> 33000 | R6: =IF((O6-600000)<0,0,IF((O6-600000)<500000,0.15*(O6-600000),75000)) -> 75000 | S6: =IF((O6-1100000)<0,0,IF((O6-1100000)<500000,0.19*(O6-1100000),95000)) -> 95000 | T6: =IF((O6-1600000)<0,0,IF((O6-1600000)<1600000,0.21*(O6-1600000),336000)) -> 336000 | U6: =24%*(O6-3200000) -> 289713.92 | V6: =P6+Q6+R6+S6+T6+U6 -> 849713.92 | W6: 12 | X6: =V6/W6 -> 70809.493 | Z6: =X6 -> 70809.493
A7: 3 | B7: SIMON WAKAWA | C7: 291986.92 | D7: 12 | E7: =C7*D7 -> 3503843 | F7: =8019.8*12 -> 96237.6 | G7: 558833.36 | I7: =E7-F7-G7-H7 -> 2848772.1 | J7: 200000 | K7: 0.2 | L7: =I7*K7 -> 569754.41 | M7: =J7+L7 -> 769754.41 | N7: =F7+G7+H7+M7 -> 1424825.4 | O7: =E7-N7 -> 2079017.6 | P7: =IF(O7<300000,0.07*O7,21000) -> 21000 | Q7: =IF((O7-300000)<0,0,IF((O7-300000)<300000,0.11*(O7-300000),33000)) -> 33000 | R7: =IF((O7-600000)<0,0,IF((O7-600000)<500000,0.15*(O7-600000),75000)) -> 75000 | S7: =IF((O7-1100000)<0,0,IF((O7-1100000)<500000,0.19*(O7-1100000),95000)) -> 95000 | T7: =IF((O7-1600000)<0,0,IF((O7-1600000)<1600000,0.21*(O7-1600000),336000)) -> 100593.7 | V7: =P7+Q7+R7+S7+T7+U7 -> 324593.7 | W7: 12 | X7: =V7/W7 -> 27049.475 | Z7: =X7 -> 27049.475
A8: 4 | B8: WAZIRI USMAN | C8: 291984.21 | D8: 12 | E8: =C8*D8 -> 3503810.5 | F8: =8019.8*12 -> 96237.6 | G8: 558833.36 | I8: =E8-F8-G8-H8 -> 2848739.5 | J8: 200000 | K8: 0.2 | L8: =I8*K8 -> 569747.91 | M8: =J8+L8 -> 769747.91 | N8: =F8+G8+H8+M8 -> 1424818.9 | O8: =E8-N8 -> 2078991.6 | P8: =IF(O8<300000,0.07*O8,21000) -> 21000 | Q8: =IF((O8-300000)<0,0,IF((O8-300000)<300000,0.11*(O8-300000),33000)) -> 33000 | R8: =IF((O8-600000)<0,0,IF((O8-600000)<500000,0.15*(O8-600000),75000)) -> 75000 | S8: =IF((O8-1100000)<0,0,IF((O8-1100000)<500000,0.19*(O8-1100000),95000)) -> 95000 | T8: =IF((O8-1600000)<0,0,IF((O8-1600000)<1600000,0.21*(O8-1600000),336000)) -> 100588.24 | V8: =P8+Q8+R8+S8+T8+U8 -> 324588.24 | W8: 12 | X8: =V8/W8 -> 27049.02 | Z8: =X8 -> 27049.02
A9: 5 | B9: TAIWO I. OYINLOLA | C9: 0 | D9: 0 | E9: =C9*D9 -> 0 | G9: 0 | I9: =E9-F9-G9-H9 -> 0 | J9: 0 | K9: 0.2 | L9: =I9*K9 -> 0 | M9: =J9+L9 -> 0 | N9: =F9+G9+H9+M9 -> 0 | O9: =E9-N9 -> 0 | P9: =IF(O9<300000,0.07*O9,21000) -> 0 | Q9: =IF((O9-300000)<0,0,IF((O9-300000)<300000,0.11*(O9-300000),33000)) -> 0 | R9: =IF((O9-600000)<0,0,IF((O9-600000)<500000,0.15*(O9-600000),75000)) -> 0 | S9: =IF((O9-1100000)<0,0,IF((O9-1100000)<500000,0.19*(O9-1100000),95000)) -> 0 | T9: =IF((O9-1600000)<0,0,IF((O9-1600000)<1600000,0.21*(O9-1600000),336000)) -> 0 | V9: =P9+Q9+R9+S9+T9+U9 -> 0 | W9: 12 | X9: =V9/W9 -> 0 | Z9: =X9 -> 0
A10: 6 | B10: SARATU ATAJIRI | C10: 1486792 | D10: 12 | E10: =C10*D10 -> 17841504 | G10: 245615.04 | I10: =E10-F10-G10-H10 -> 17595889 | J10: 200000 | K10: 0.2 | L10: =I10*K10 -> 3519177.8 | M10: =J10+L10 -> 3719177.8 | N10: =F10+G10+H10+M10 -> 3964792.8 | O10: =E10-N10 -> 13876711 | P10: =IF(O10<300000,0.07*O10,21000) -> 21000 | Q10: =IF((O10-300000)<0,0,IF((O10-300000)<300000,0.11*(O10-300000),33000)) -> 33000 | R10: =IF((O10-600000)<0,0,IF((O10-600000)<500000,0.15*(O10-600000),75000)) -> 75000 | S10: =IF((O10-1100000)<0,0,IF((O10-1100000)<500000,0.19*(O10-1100000),95000)) -> 95000 | T10: =IF((O10-1600000)<0,0,IF((O10-1600000)<1600000,0.21*(O10-1600000),336000)) -> 336000 | U10: =24%*(O10-3200000) -> 2562410.7 | V10: =P10+Q10+R10+S10+T10+U10 -> 3122410.7 | W10: 12 | X10: =V10/W10 -> 260200.89 | Z10: =X10 -> 260200.89
A11: 7 | B11: YUSIF SANI SADIQ | C11: 120895.81 | D11: 12 | E11: =C11*D11 -> 1450749.7 | G11: 339372 | I11: =E11-F11-G11-H11 -> 1111377.7 | J11: 200000 | K11: 0.2 | L11: =I11*K11 -> 222275.54 | M11: =J11+L11 -> 422275.54 | N11: =F11+G11+H11+M11 -> 761647.54 | O11: =E11-N11 -> 689102.18 | P11: =IF(O11<300000,0.07*O11,21000) -> 21000 | Q11: =IF((O11-300000)<0,0,IF((O11-300000)<300000,0.11*(O11-300000),33000)) -> 33000 | R11: =IF((O11-600000)<0,0,IF((O11-600000)<500000,0.15*(O11-600000),75000)) -> 13365.326 | S11: =IF((O11-1100000)<0,0,IF((O11-1100000)<500000,0.19*(O11-1100000),95000)) -> 0 | T11: =IF((O11-1600000)<0,0,IF((O11-1600000)<1600000,0.21*(O11-1600000),336000)) -> 0 | V11: =P11+Q11+R11+S11+T11+U11 -> 67365.326 | W11: 12 | X11: =V11/W11 -> 5613.7772 | Z11: =X11 -> 5613.7772
A12: 8 | B12: STELLA NGOZI PAUL | C12: 99389.476 | D12: 12 | E12: =C12*D12 -> 1192673.7 | G12: 339372 | I12: =E12-F12-G12-H12 -> 853301.71 | J12: 200000 | K12: 0.2 | L12: =I12*K12 -> 170660.34 | M12: =J12+L12 -> 370660.34 | N12: =F12+G12+H12+M12 -> 710032.34 | O12: =E12-N12 -> 482641.37 | P12: =IF(O12<300000,0.07*O12,21000) -> 21000 | Q12: =IF((O12-300000)<0,0,IF((O12-300000)<300000,0.11*(O12-300000),33000)) -> 20090.55 | R12: =IF((O12-600000)<0,0,IF((O12-600000)<500000,0.15*(O12-600000),75000)) -> 0 | S12: =IF((O12-1100000)<0,0,IF((O12-1100000)<500000,0.19*(O12-1100000),95000)) -> 0 | T12: =IF((O12-1600000)<0,0,IF((O12-1600000)<1600000,0.21*(O12-1600000),336000)) -> 0 | V12: =P12+Q12+R12+S12+T12+U12 -> 41090.55 | W12: 12 | X12: =V12/W12 -> 3424.2125 | Z12: =X12 -> 3424.2125
A13: 9 | B13: OMONIGHO EROMOSELE-WESEY | C13: 481299.33 | D13: 12 | E13: =C13*D13 -> 5775592 | F13: =6922.5*12 -> 83070 | G13: 374638.96 | I13: =E13-F13-G13-H13 -> 5317883 | J13: 200000 | K13: 0.2 | L13: =I13*K13 -> 1063576.6 | M13: =J13+L13 -> 1263576.6 | N13: =F13+G13+H13+M13 -> 1721285.6 | O13: =E13-N13 -> 4054306.4 | P13: =IF(O13<300000,0.07*O13,21000) -> 21000 | Q13: =IF((O13-300000)<0,0,IF((O13-300000)<300000,0.11*(O13-300000),33000)) -> 33000 | R13: =IF((O13-600000)<0,0,IF((O13-600000)<500000,0.15*(O13-600000),75000)) -> 75000 | S13: =IF((O13-1100000)<0,0,IF((O13-1100000)<500000,0.19*(O13-1100000),95000)) -> 95000 | T13: =IF((O13-1600000)<0,0,IF((O13-1600000)<1600000,0.21*(O13-1600000),336000)) -> 336000 | U13: =24%*(O13-3200000) -> 205033.54 | V13: =P13+Q13+R13+S13+T13+U13 -> 765033.54 | W13: 12 | X13: =V13/W13 -> 63752.795 | Z13: =X13 -> 63752.795
A14: 10 | B14: QUEEN ONYEKESON | C14: 163040.15 | D14: 12 | E14: =C14*D14 -> 1956481.8 | G14: 374638.96 | I14: =E14-F14-G14-H14 -> 1581842.8 | J14: 200000 | K14: 0.2 | L14: =I14*K14 -> 316368.57 | M14: =J14+L14 -> 516368.57 | N14: =F14+G14+H14+M14 -> 891007.53 | O14: =E14-N14 -> 1065474.3 | P14: =IF(O14<300000,0.07*O14,21000) -> 21000 | Q14: =IF((O14-300000)<0,0,IF((O14-300000)<300000,0.11*(O14-300000),33000)) -> 33000 | R14: =IF((O14-600000)<0,0,IF((O14-600000)<500000,0.15*(O14-600000),75000)) -> 69821.139 | S14: =IF((O14-1100000)<0,0,IF((O14-1100000)<500000,0.19*(O14-1100000),95000)) -> 0 | T14: =IF((O14-1600000)<0,0,IF((O14-1600000)<1600000,0.21*(O14-1600000),336000)) -> 0 | V14: =P14+Q14+R14+S14+T14+U14 -> 123821.14 | W14: 12 | X14: =V14/W14 -> 10318.428 | Z14: =X14 -> 10318.428
A15: 11 | B15: SHAMSUDEEN YAHAYA | C15: 394860 | D15: 12 | E15: =C15*D15 -> 4738320 | G15: 558833.36 | I15: =E15-F15-G15-H15 -> 4179486.6 | J15: 200000 | K15: 0.2 | L15: =I15*K15 -> 835897.33 | M15: =J15+L15 -> 1035897.3 | N15: =F15+G15+H15+M15 -> 1594730.7 | O15: =E15-N15 -> 3143589.3 | P15: =IF(O15<300000,0.07*O15,21000) -> 21000 | Q15: =IF((O15-300000)<0,0,IF((O15-300000)<300000,0.11*(O15-300000),33000)) -> 33000 | R15: =IF((O15-600000)<0,0,IF((O15-600000)<500000,0.15*(O15-600000),75000)) -> 75000 | S15: =IF((O15-1100000)<0,0,IF((O15-1100000)<500000,0.19*(O15-1100000),95000)) -> 95000 | T15: =IF((O15-1600000)<0,0,IF((O15-1600000)<1600000,0.21*(O15-1600000),336000)) -> 324153.76 | V15: =P15+Q15+R15+S15+T15+U15 -> 548153.76 | W15: 12 | X15: =V15/W15 -> 45679.48 | Z15: =X15 -> 45679.48
A16: 12 | B16: SALAMATU YAKUBU | C16: 323232.75 | D16: 12 | E16: =C16*D16 -> 3878793 | F16: =8019.8*12 -> 96237.6 | G16: 558833.36 | I16: =E16-F16-G16-H16 -> 3223722 | J16: 200000 | K16: 0.2 | L16: =I16*K16 -> 644744.41 | M16: =J16+L16 -> 844744.41 | N16: =F16+G16+H16+M16 -> 1499815.4 | O16: =E16-N16 -> 2378977.6 | P16: =IF(O16<300000,0.07*O16,21000) -> 21000 | Q16: =IF((O16-300000)<0,0,IF((O16-300000)<300000,0.11*(O16-300000),33000)) -> 33000 | R16: =IF((O16-600000)<0,0,IF((O16-600000)<500000,0.15*(O16-600000),75000)) -> 75000 | S16: =IF((O16-1100000)<0,0,IF((O16-1100000)<500000,0.19*(O16-1100000),95000)) -> 95000 | T16: =IF((O16-1600000)<0,0,IF((O16-1600000)<1600000,0.21*(O16-1600000),336000)) -> 163585.3 | V16: =P16+Q16+R16+S16+T16+U16 -> 387585.3 | W16: 12 | X16: =V16/W16 -> 32298.775 | Z16: =X16 -> 32298.775
A17: 13 | B17: ROTIMI OGUNYOMI | C17: 180487.25 | D17: 12 | E17: =C17*D17 -> 2165847 | G17: 374638.96 | I17: =E17-F17-G17-H17 -> 1791208 | J17: 200000 | K17: 0.2 | L17: =I17*K17 -> 358241.61 | M17: =J17+L17 -> 558241.61 | N17: =F17+G17+H17+M17 -> 932880.57 | O17: =E17-N17 -> 1232966.4 | P17: =IF(O17<300000,0.07*O17,21000) -> 21000 | Q17: =IF((O17-300000)<0,0,IF((O17-300000)<300000,0.11*(O17-300000),33000)) -> 33000 | R17: =IF((O17-600000)<0,0,IF((O17-600000)<500000,0.15*(O17-600000),75000)) -> 75000 | S17: =IF((O17-1100000)<0,0,IF((O17-1100000)<500000,0.19*(O17-1100000),95000)) -> 25263.622 | T17: =IF((O17-1600000)<0,0,IF((O17-1600000)<1600000,0.21*(O17-1600000),336000)) -> 0 | V17: =P17+Q17+R17+S17+T17+U17 -> 154263.62 | W17: 12 | X17: =V17/W17 -> 12855.302 | Z17: =X17 -> 12855.302
A18: 14 | B18: LEO IGBANOI | C18: 676611.67 | D18: 12 | E18: =C18*D18 -> 8119340 | G18: 425036.64 | I18: =E18-F18-G18-H18 -> 7694303.4 | J18: 200000 | K18: 0.2 | L18: =I18*K18 -> 1538860.7 | M18: =J18+L18 -> 1738860.7 | N18: =F18+G18+H18+M18 -> 2163897.3 | O18: =E18-N18 -> 5955442.7 | P18: =IF(O18<300000,0.07*O18,21000) -> 21000 | Q18: =IF((O18-300000)<0,0,IF((O18-300000)<300000,0.11*(O18-300000),33000)) -> 33000 | R18: =IF((O18-600000)<0,0,IF((O18-600000)<500000,0.15*(O18-600000),75000)) -> 75000 | S18: =IF((O18-1100000)<0,0,IF((O18-1100000)<500000,0.19*(O18-1100000),95000)) -> 95000 | T18: =IF((O18-1600000)<0,0,IF((O18-1600000)<1600000,0.21*(O18-1600000),336000)) -> 336000 | U18: =24%*(O18-3200000) -> 661306.25 | V18: =P18+Q18+R18+S18+T18+U18 -> 1221306.2 | W18: 12 | X18: =V18/W18 -> 101775.52 | Z18: =X18 -> 101775.52
A19: 15 | B19: LOHNA BONKAT JONATHAN | C19: 575119.92 | D19: 12 | E19: =C19*D19 -> 6901439 | G19: 425036.64 | I19: =E19-F19-G19-H19 -> 6476402.4 | J19: 200000 | K19: 0.2 | L19: =I19*K19 -> 1295280.5 | M19: =J19+L19 -> 1495280.5 | N19: =F19+G19+H19+M19 -> 1920317.1 | O19: =E19-N19 -> 4981121.9 | P19: =IF(O19<300000,0.07*O19,21000) -> 21000 | Q19: =IF((O19-300000)<0,0,IF((O19-300000)<300000,0.11*(O19-300000),33000)) -> 33000 | R19: =IF((O19-600000)<0,0,IF((O19-600000)<500000,0.15*(O19-600000),75000)) -> 75000 | S19: =IF((O19-1100000)<0,0,IF((O19-1100000)<500000,0.19*(O19-1100000),95000)) -> 95000 | T19: =IF((O19-1600000)<0,0,IF((O19-1600000)<1600000,0.21*(O19-1600000),336000)) -> 336000 | U19: =24%*(O19-3200000) -> 427469.25 | V19: =P19+Q19+R19+S19+T19+U19 -> 987469.25 | W19: 12 | X19: =V19/W19 -> 82289.104 | Z19: =X19 -> 82289.104
A20: 16 | B20: TOSIN OWOEYE | C20: 401499 | D20: 12 | E20: =C20*D20 -> 4817988 | G20: 339372 | I20: =E20-F20-G20-H20 -> 4478616 | J20: 200000 | K20: 0.2 | L20: =I20*K20 -> 895723.2 | M20: =J20+L20 -> 1095723.2 | N20: =F20+G20+H20+M20 -> 1435095.2 | O20: =E20-N20 -> 3382892.8 | P20: =IF(O20<300000,0.07*O20,21000) -> 21000 | Q20: =IF((O20-300000)<0,0,IF((O20-300000)<300000,0.11*(O20-300000),33000)) -> 33000 | R20: =IF((O20-600000)<0,0,IF((O20-600000)<500000,0.15*(O20-600000),75000)) -> 75000 | S20: =IF((O20-1100000)<0,0,IF((O20-1100000)<500000,0.19*(O20-1100000),95000)) -> 95000 | T20: =IF((O20-1600000)<0,0,IF((O20-1600000)<1600000,0.21*(O20-1600000),336000)) -> 336000 | U20: =24%*(O20-3200000) -> 43894.272 | V20: =P20+Q20+R20+S20+T20+U20 -> 603894.27 | W20: 12 | X20: =V20/W20 -> 50324.523 | Z20: =X20 -> 50324.523
A21: 17 | B21: STACY CHINYERE IGWE | C21: 655332 | D21: 12 | E21: =C21*D21 -> 7863984 | G21: 339372 | I21: =E21-F21-G21-H21 -> 7524612 | J21: 200000 | K21: 0.2 | L21: =I21*K21 -> 1504922.4 | M21: =J21+L21 -> 1704922.4 | N21: =F21+G21+H21+M21 -> 2044294.4 | O21: =E21-N21 -> 5819689.6 | P21: =IF(O21<300000,0.07*O21,21000) -> 21000 | Q21: =IF((O21-300000)<0,0,IF((O21-300000)<300000,0.11*(O21-300000),33000)) -> 33000 | R21: =IF((O21-600000)<0,0,IF((O21-600000)<500000,0.15*(O21-600000),75000)) -> 75000 | S21: =IF((O21-1100000)<0,0,IF((O21-1100000)<500000,0.19*(O21-1100000),95000)) -> 95000 | T21: =IF((O21-1600000)<0,0,IF((O21-1600000)<1600000,0.21*(O21-1600000),336000)) -> 336000 | U21: =24%*(O21-3200000) -> 628725.5 | V21: =P21+Q21+R21+S21+T21+U21 -> 1188725.5 | W21: 12 | X21: =V21/W21 -> 99060.459 | Z21: =X21 -> 99060.459
A22: 18 | B22: TITILAYO MARVELOUS DANIEL | C22: 176519 | D22: 12 | E22: =C22*D22 -> 2118228 | G22: 245615.04 | I22: =E22-F22-G22-H22 -> 1872613 | J22: 200000 | K22: 0.2 | L22: =I22*K22 -> 374522.59 | M22: =J22+L22 -> 574522.59 | N22: =F22+G22+H22+M22 -> 820137.63 | O22: =E22-N22 -> 1298090.4 | P22: =IF(O22<300000,0.07*O22,21000) -> 21000 | Q22: =IF((O22-300000)<0,0,IF((O22-300000)<300000,0.11*(O22-300000),33000)) -> 33000 | R22: =IF((O22-600000)<0,0,IF((O22-600000)<500000,0.15*(O22-600000),75000)) -> 75000 | S22: =IF((O22-1100000)<0,0,IF((O22-1100000)<500000,0.19*(O22-1100000),95000)) -> 37637.17 | T22: =IF((O22-1600000)<0,0,IF((O22-1600000)<1600000,0.21*(O22-1600000),336000)) -> 0 | V22: =P22+Q22+R22+S22+T22+U22 -> 166637.17 | W22: 12 | X22: =V22/W22 -> 13886.431 | Z22: =X22 -> 13886.431
A23: 19 | B23: TANIMU M. LAWAL | C23: 86887.25 | D23: 12 | E23: =C23*D23 -> 1042647 | G23: 146701.6 | I23: =E23-F23-G23-H23 -> 895945.4 | J23: 200000 | K23: 0.2 | L23: =I23*K23 -> 179189.08 | M23: =J23+L23 -> 379189.08 | N23: =F23+G23+H23+M23 -> 525890.68 | O23: =E23-N23 -> 516756.32 | P23: =IF(O23<300000,0.07*O23,21000) -> 21000 | Q23: =IF((O23-300000)<0,0,IF((O23-300000)<300000,0.11*(O23-300000),33000)) -> 23843.195 | R23: =IF((O23-600000)<0,0,IF((O23-600000)<500000,0.15*(O23-600000),75000)) -> 0 | S23: =IF((O23-1100000)<0,0,IF((O23-1100000)<500000,0.19*(O23-1100000),95000)) -> 0 | T23: =IF((O23-1600000)<0,0,IF((O23-1600000)<1600000,0.21*(O23-1600000),336000)) -> 0 | V23: =P23+Q23+R23+S23+T23+U23 -> 44843.195 | W23: 12 | X23: =V23/W23 -> 3736.9329 | Z23: =X23 -> 3736.9329
A24: 20 | B24: CHRISTIAN MADUABUCHI ODO | C24: 180487.25 | D24: 12 | E24: =C24*D24 -> 2165847 | F24: =6922.5*12 -> 83070 | G24: 374638.96 | I24: =E24-F24-G24-H24 -> 1708138 | J24: 200000 | K24: 0.2 | L24: =I24*K24 -> 341627.61 | M24: =J24+L24 -> 541627.61 | N24: =F24+G24+H24+M24 -> 999336.57 | O24: =E24-N24 -> 1166510.4 | P24: =IF(O24<300000,0.07*O24,21000) -> 21000 | Q24: =IF((O24-300000)<0,0,IF((O24-300000)<300000,0.11*(O24-300000),33000)) -> 33000 | R24: =IF((O24-600000)<0,0,IF((O24-600000)<500000,0.15*(O24-600000),75000)) -> 75000 | S24: =IF((O24-1100000)<0,0,IF((O24-1100000)<500000,0.19*(O24-1100000),95000)) -> 12636.982 | T24: =IF((O24-1600000)<0,0,IF((O24-1600000)<1600000,0.21*(O24-1600000),336000)) -> 0 | V24: =P24+Q24+R24+S24+T24+U24 -> 141636.98 | W24: 12 | X24: =V24/W24 -> 11803.082 | Z24: =X24 -> 11803.082
Z25: 11287301

Sheet Stoppage of Salary
A1: NATIONAL INSTITUTE FOR LEGISLATIVE AND DEMOCRATIC STUDIES
A2: STAFF PAYROLL FOR THE MONTH OF NOVEMBER, 2024
E3: ='[1]FEB 08'!E11/'[1]FEB 08'!M11 -> #REF!
B4: STAFF NAME | C4: DESIGNATION | D4: GRADE LEVEL | E4: BASIC SALARY | F4: ALLCE/ AREARS | G4: ALLOWANCE | H4: ALLOWANCE | I4: DUTY ALLCE | J4: GROSS SALARY | K4: AUCTION | L4: COOP CONTR/SPEC SAVINGS | M4: COOP. LOAN RECOVERY | N4: NHF DED. | O4: PAYE | P4: EMPLOYEE PENSIONS | Q4: TOTAL DEDUCTION | R4: OCTOBER, 2024 | S4: NOVEMBER, 2024
E5: N | F5: N | G5: N | H5: N | I5: N | J5: N | K5: N | L5: N | M5: N | N5: N | O5: N | P5: N | Q5: N | R5: N | S5: N
A6: S/N | B6: DG'S OFFICE
A7: 2 | B7: DR CLINTON JAJA | C7: SENIOR RESEARCH FELLOW | D7: 15(9) | E7: 620675.58 | G7: =160000 -> 160000 | I7: 0 | J7: =SUM(E7:I7) -> 780675.58 | L7: =50000 -> 50000 | M7: =385000 -> 385000 | O7: 119022.8 | P7: 49654.047 | Q7: =O7+N7+M7+L7+K7+P7 -> 603676.85 | R7: 176998.73 | S7: =J7-Q7 -> 176998.73
A8: 3 | B8: LOHNA BONKAT JONATHAN | C8: RESEARCH FELLOW 11 | D8: 13(10) | E8: 428915.92 | F8: 0 | G8: =120000 -> 120000 | I8: 0 | J8: =SUM(E8:I8) -> 548915.92 | L8: =20000+65000+65000 -> 150000 | M8: 0 | N8: 0 | O8: 77470.374 | P8: 34313.273 | Q8: =O8+N8+M8+L8+K8+P8 -> 261783.65 | R8: 287132.27 | S8: =J8-Q8 -> 287132.27
B9: TOTAL | C9: 31 | E9: =SUM(E7:E8) -> 1049591.5 | F9: =SUM(F7:F8) -> 0 | G9: =SUM(G7:G8) -> 280000 | H9: =SUM(H7:H8) -> 0 | I9: =SUM(I7:I8) -> 0 | J9: =SUM(J7:J8) -> 1329591.5 | K9: =SUM(K7:K8) -> 0 | L9: =SUM(L7:L8) -> 200000 | ... Q9: =SUM(Q7:Q8) -> 865460.5 | R9: 13026183 | S9: =SUM(S7:S8) -> 464131

Sheet New PAYE

Sheet New Pensions Promotion
A1: NATIONAL INSTITUTE FOR LEGISLATIVE & DEMOCRATIC STUDIES
A2: 2024 ANALYSIS OF STAFF PROMOTION ARREARS
A4: SN | B4: Name of Employee | C4: Department | D4: New Grade Level | E4: Annual Consolidated Salary of New Position(Less Res/Harsh Allow | F4: Monthly Consolidated Salary of New Position(Less Res/Harsh Allow | G4: 8% Employee Contr | H4: Annual 8% Employee Contr
F5: N | G5: N | H5: N
A6: 1 | B6: ABDULSALAM MUSTAPHA | C6: DG's Office | D6: 15/7 | E6: =F6*12 -> 6985417 | F6: =582118.08 -> 582118.08 | G6: =F6*0.08 -> 46569.446 | H6: =G6*12 -> 558833.36
A7: 2 | B7: EMILY EDIOSA IKHIDE | C7: DG's Office | D7: 015/7 | E7: =F7*12 -> 6985417 | F7: =582118.08 -> 582118.08 | G7: =F7*0.08 -> 46569.446 | H7: =G7*12 -> 558833.36
A8: 3 | B8: SIMON WAKAWA | C8: DG's Office | D8: 015/7 | E8: =F8*12 -> 6985417 | F8: =582118.08 -> 582118.08 | G8: =F8*0.08 -> 46569.446 | H8: =G8*12 -> 558833.36
A9: 4 | B9: WAZIRI USMAN | C9: DG's Office | D9: 015/7 | E9: =F9*12 -> 6985417 | F9: =582118.08 -> 582118.08 | G9: =F9*0.08 -> 46569.446 | H9: =G9*12 -> 558833.36
A10: 5 | B10: TAIWO I. OYINLOLA | C10: Admin. & HR | D10: 07/3 | E10: =F10*12 -> 1833770 | F10: =152814.17 -> 152814.17 | G10: =F10*0.08 -> 12225.134 | H10: =G10*12 -> 146701.6
A11: 6 | B11: SARATU ATAJIRI | C11: Admin. & HR | D11: 09/7 | E11: =F11*12 -> 3070188 | F11: =255849 -> 255849 | G11: =F11*0.08 -> 20467.92 | H11: =G11*12 -> 245615.04
A12: 7 | B12: YUSIF SANI SADIQ | C12: Admin. & HR | D12: 12/7 | E12: =F12*12 -> 4242150 | F12: =353512.5 -> 353512.5 | G12: =F12*0.08 -> 28281 | H12: =G12*12 -> 339372
A13: 8 | B13: STELLA NGOZI PAUL | C13: Admin. & HR | D13: 12/7 | E13: =F13*12 -> 4242150 | F13: =353512.5 -> 353512.5 | G13: =F13*0.08 -> 28281 | H13: =G13*12 -> 339372
A14: 9 | B14: OMONIGHO EROMOSELE-WESEY | C14: Admin. & HR | D14: 13/7 | E14: =F14*12 -> 4682987 | F14: =390248.92 -> 390248.92 | G14: =F14*0.08 -> 31219.914 | H14: =G14*12 -> 374638.96
A15: 10 | B15: QUEEN ONYEKESON | C15: Admin. & HR | D15: 13/7 | E15: =F15*12 -> 4682987 | F15: =390248.92 -> 390248.92 | G15: =F15*0.08 -> 31219.914 | H15: =G15*12 -> 374638.96
A16: 11 | B16: SHAMSUDEEN YAHAYA | C16: LSS | D16: 015/7 | E16: =F16*12 -> 6985417 | F16: 582118.08 | G16: =F16*0.08 -> 46569.446 | H16: =G16*12 -> 558833.36
A17: 12 | B17: SALAMATU YAKUBU | C17: LSS | D17: 015/7 | E17: =F17*12 -> 6985417 | F17: 582118.08 | G17: =F17*0.08 -> 46569.446 | H17: =G17*12 -> 558833.36
A18: 13 | B18: ROTIMI OGUNYOMI | C18: LSS | D18: 13/7 | E18: =F18*12 -> 4682987 | F18: 390248.92 | G18: =F18*0.08 -> 31219.914 | H18: =G18*12 -> 374638.96
A19: 14 | B19: LEO IGBANOI | C19: Dem. & Gov. | D19: 14/8 | E19: =F19*12 -> 5312958 | F19: =442746.5 -> 442746.5 | G19: =F19*0.08 -> 35419.72 | H19: =G19*12 -> 425036.64
A20: 15 | B20: LOHNA BONKAT JONATHAN | C20: Dem. & Gov. | D20: 14/8 | E20: =F20*12 -> 5312958 | F20: =442746.5 -> 442746.5 | G20: =F20*0.08 -> 35419.72 | H20: =G20*12 -> 425036.64
A21: 16 | B21: TOSIN OWOEYE | C21: Dem. & Gov. | D21: 12/7 | E21: =F21*12 -> 4242150 | F21: 353512.5 | G21: =F21*0.08 -> 28281 | H21: =G21*12 -> 339372
A22: 17 | B22: STACY CHINYERE IGWE | C22: DOS | D22: 12/7 | E22: =F22*12 -> 4242150 | F22: 353512.5 | G22: =F22*0.08 -> 28281 | H22: =G22*12 -> 339372
A23: 18 | B23: TITILAYO MARVELOUS DANIEL | C23: Library | D23: 09/7 | E23: =F23*12 -> 3070188 | F23: 255849 | G23: =F23*0.08 -> 20467.92 | H23: =G23*12 -> 245615.04
A24: 19 | B24: TANIMU M. LAWAL | C24: Econ/ & Social Res. | D24: 07/3 | E24: =F24*12 -> 1833770 | F24: 152814.17 | G24: =F24*0.08 -> 12225.134 | H24: =G24*12 -> 146701.6
A25: 20 | B25: CHRISTIAN MADUABUCHI ODO | C25: Finance & Accts | D25: 13/7 | E25: =F25*12 -> 4682987 | F25: 390248.92 | G25: =F25*0.08 -> 31219.914 | H25: =G25*12 -> 374638.96
B26: TOTAL

Sheet Conversion in Nov
A1: NATIONAL INSTITUTE FOR LEGISLATIVE AND DEMOCRATIC STUDIES
A2: STAFF PAYROLL FOR THE MONTH OF NOVEMBER, 2024
E3: ='[1]FEB 08'!E11/'[1]FEB 08'!M11 -> #REF!
B4: STAFF NAME | C4: DESIGNATION | D4: GRADE LEVEL | E4: BASIC SALARY | F4: ALLCE/ AREARS | G4: ALLOWANCE | H4: ALLOWANCE | I4: DUTY ALLCE | J4: GROSS SALARY | K4: AUCTION | L4: COOP CONTR/SPEC SAVINGS | M4: COOP. LOAN RECOVERY | N4: NHF DED. | O4: PAYE | P4: EMPLOYEE PENSIONS | Q4: TOTAL DEDUCTION | R4: OCTOBER, 2024 | S4: NOVEMBER, 2024
E5: N | F5: N | G5: N | H5: N | I5: N | J5: N | K5: N | L5: N | M5: N | N5: N | O5: N | P5: N | Q5: N | R5: N | S5: N
A6: S/N | B6: DG'S OFFICE
A7: 25 | B7: SARATU ATAJIRI | C7: ADMINI OFFICER | D7: 9(7) | E7: 255849 | H7: =60000 -> 60000 | J7: =E7+F7+G7+H7+I7 -> 315849 | O7: 36790.688 | P7: 20467.92 | Q7: =O7+N7+M7+L7+K7+P7 -> 57258.608 | S7: =J7-Q7 -> 258590.39

Sheet Christmas Welfare 2024
A1: NATIONAL INSTITUTE FOR LEGISLATIVE AND DEMOCRATIC STUDIES
A2: STAFF CHRISTMAS WELFARE DECEMBER, 2024
B4: STAFF NAME | C4: DESIGNATION | D4: GRADE LEVEL | E4: AMOUNT
E5: N
A6: S/N | B6: DG'S OFFICE
A7: 1 | B7: PROF. ABUBAKAR O. SULAIMAN | C7: DIRECTOR GENERAL | D7: CONSOL | E7: 540000
A8: 2 | B8: RAHEEM USMAN AYIGORO | C8: SA-INFRASTRUCTURE | D8: 16 (9) | E8: 180000
A9: 3 | B9: MARIAM MOHAMMED BELLO | C9: SA- SPECIAL DUTIES | D9: 16 (9) | E9: 180000
A10: 4 | B10: DR IKEME ARTHUR J.O | C10: DEPUTY DIRECTOR, M&E | D10: 16 (9) | E10: 180000
A11: 5 | B11: MOSHOOD M. OLALERE | C11: DEPUTY DIR. GENERAL SERVICE | D11: 16 (9) | E11: 180000
A12: 6 | B12: ANDRAWUS MUSA | C12: ASST. DIRECTOR, STORES | D12: 15(9) | E12: 126000
A13: 7 | B13: DR FRANCIS NDUM OJIE | C13: AD, TRAINING & IC./SA TO DG | D13: 15(7) | E13: 126000
A14: 8 | B14: ALI ABDULLAHI | C14: CHIEF ICT OFFICER | D14: 14(11) | E14: 90000
A15: 9 | B15: EMILY EKHIDE | C15: SENIOR RESEARCH FELLOW | D15: 15(7) | E15: 126000
A16: 10 | B16: DORIS DAKDA AARON | C16: RESEARCH FELLOW I | D16: 14(8) | E16: 90000
A17: 11 | B17: ABDULSALAM S. MUSTAPHA | C17: ASST. DIRECTOR ICT | D17: 15(7) | E17: 126000
A18: 12 | B18: PERCY TERFA GBAHABO | C18: HEAD, NILDS LIAISON OFFICE | D18: 13(10) | E18: 90000
... A37: 31 | B37: RAMATU IBRAHIM ABDULRAHEEM | C37: INFORMATION OFFICER | D37: 8(7) | E37: 54000
B38: TOTAL | C38: 31 | E38: =SUM(E7:E37) -> 3238000
B40: INTERNAL AUDIT
A41: 1 | B41: OSANAIYE DAVID AKINYEMI | C41: DIRECTOR INTERNAL AUDIT | D41: 17(9) | E41: 270000
A42: 2 | B42: JAMILA ABDUL | C42: SENIOR INTERNAL AUDITOR | D42: 10(7) | E42: 68000
A43: 3 | B43: IJEOMA EWELUKWA | C43: SENIOR INTERNAL AUDITOR | D43: 10(8) | E43: 68000
A44: 4 | B44: YUSUF YUSUF DAYYABU | C44: INERNAL AUDIT OFFICER | D44: 9(7) | E44: 54000
C45: 4 | E45: =SUM(E41:E44) -> 460000
B47: LEG. SUPPORT SEVICES
A48: 1 | B48: PROF. EDOBA BRIGHT OMOREGBE | C48: AG. DLSS | D48: 17(9) | E48: 0
A49: 2 | B49: DR CLINTON JAJA | C49: SENIOR RESEARCH FELLOW | D49: 15(9) | E49: 0
A50: 3 | B50: BETHEL UZOMA IHUGBA | C50: DEPUTY DIRECTOR, LEGAL RESEARCH | D50: 16(8) | E50: 180000
A51: 4 | B51: OGUCHE SAMUEL | C51: SNR RESEARCH FELLOW | D51: 15(9) | E51: 126000
A52: 5 | B52: IBRAHIM USMAN | C52: SNR RESEARCH FELLOW | D52: 15(9) | E52: 126000
A53: 6 | B53: DR MOHAMMED O. AMALI | C53: SNR RESEARCH FELLOW | D53: 15(7) | E53: 126000
A54: 7 | B54: YAHAYA SHAMSU | C54: SNR RESEARCH FELLOW | D54: 15(7) | E54: 126000
A55: 8 | B55: BILKIS S. LAWAL-GAMBARI | C55: RESEARCH OFFICER | D55: 10(8) | E55: 68000
A56: 9 | B56: ZAINAB AKINDE | C56: RESEARCH OFFICER | D56: 9(8) | E56: 54000
A57: 10 | B57: GUNAT NANSAK MARK | C57: RESEARCH OFFICER | D57: 9(8) | E57: 54000
B58: TOTAL | C58: 10 | E58: =SUM(E48:E57) -> 860000
B60: LEGAL SERVICES
A61: 1 | B61: DR SHUIBU DANWANKA | C61: DIRECTOR LEGAL SERVICES | D61: 17(9) | E61: 270000
A62: 2 | B62: ABDULSALAM BAKO | C62: MANAGER, LEGAL SERVICES | D62: 15 (9) | E62: 126000
B63: TOTAL | C63: 2 | E63: =SUM(E61:E62) -> 396000
B65: DEMOCRACY & GOVERNANCE
A66: 1 | B66: DR. ADEWALE ADEREMI | C66: DIRECTOR, DEMOCRATIC STUDIES | D66: 17(9) | E66: 270000
A67: 2 | B67: NDANUSA MOHAMMED MANZUMA | C67: SNR RESEARCH FELLOW | D67: 15(8) | E67: 126000
A68: 3 | B68: EJALONIBU GANIYU LAYI | C68: RESEARCH FELLOW 1 | D68: 14(8) | E68: 90000
A69: 4 | B69: LOHNA BONKAT JONATHAN | C69: RESEARCH FELLOW 11 | D69: 13(10) | E69: 0
A70: 7 | B70: UDEFUNA NNADOZIE PATRICK | C70: RESEARCH OFFICER | D70: 12(8) | E70: 68000
A71: 8 | B71: SHAFIU YAHYA MIKAIL | C71: PRINCIPAL RESEARCH OFFICER | D71: 12(8) | E71: 68000
A72: 9 | B72: HASSAN YERIMA | C72: PRINCIPAL RESEARCH OFFICER | D72: 12(8) | E72: 68000
A73: 10 | B73: HAUWA PATE SADIQ | C73: PRINCIPAL PROGRAMME OFFICER | D73: 12(9) | E73: 68000
A74: 11 | B74: KOLAPO Q. ABAYOMI | C74: RESEARCH OFFICER | D74: 10(8) | E74: 68000
B75: TOTAL | C75: 11 | E75: =SUM(E66:E74) -> 826000
B77: DEPARTMENT OF STUDIES
A78: 1 | B78: DR ASIMIYU G. ABIOLA | C78: DIRECTOR POST GRADUATE | D78: 17(9) | E78: 270000
A79: 2 | B79: DR. HADIZA SAIDU | C79: ASSISTANT DIRECTOR | D79: 15(7) | E79: 126000
A80: 3 | B80: ANTHONY EDET | C80: CHIEF PROGRAMMES OFFICER | D80: 14(9) | E80: 90000
A81: 4 | B81: IGWE STACY | C81: PRINC. PROGRAMME OFFICER | D81: 12(7) | E81: 68000
A82: 5 | B82: OLANIYAN TAIWO ABINBOLA | C82: PROGRAMME OFFICER | D82: 9(8) | E82: 54000
A83: 6 | B83: AMINAT JUMOKE SULAIMON | C83: AST. PROGRAMME OFFICER | D83: 8(8) | E83: 54000
B84: TOTAL | C84: 6 | E84: =SUM(E78:E83) -> 662000
B86: ECON. DEV. & SOC. RESEARCH
A87: 1 | B87: TERFA WILLIAMS ABRAHAM | C87: SNR RESEARCH FELLOW | D87: 15(9) | E87: 126000
A88: 2 | B88: DR AUGUSTINE C. OSIGWE | C88: SNR RESEARCH FELLOW | D88: 15(9) | E88: 126000
A89: 3 | B89: OMOJU OLUWASOLA EMMANUEL | C89: SNR RESEARCH FELLOW | D89: 15(7) | E89: 126000
A90: 4 | B90: IBE EZECHI CYRIACUS | C90: RESEARCH FELLOW 1 | D90: 14(8) | E90: 90000
A91: 5 | B91: OSIKHEN LEO IGBANOI | C91: RESEARCH FELLOW 1 | D91: 14(8) | E91: 90000
A92: 6 | B92: OKUNGBOWA OSARETIN GODSPOWER | C92: RESEARCH FELLOW 1 | D92: 14(7) | E92: 90000
A93: 7 | B93: YUSUF IBRAHIM | C93: PRINCIPAL RESEARCH OFFICER | D93: 12(8) | E93: 68000
A94: 8 | B94: MUSTAPHA RAFIU AYOBANJI | C94: RESEARCH FELLOW 11 | D94: 13(7) | E94: 90000
A95: 9 | B95: MARYAM MUSA SADA | C95: ASSIT. RESEARCH OFFICER | D95: 10(8) | E95: 68000
A96: 10 | B96: CHARITY EZENWAJIOBI | C96: REASEARCH. ASST. | D96: 8(9) | E96: 54000
B97: TOTAL | C97: 10 | E97: =SUM(E87:E96) -> 928000
B99: TRAINING & INT''L COOP
A100: 1 | B100: AKINSANMI ADEJOKE OLUKEMI | C100: Ag. DIR. TRAINING & IC | D100: 17(7) | E100: 270000
A101: 2 | B101: MOHAMMED R. ADAMU | C101: CHIEF TRAINING OFFICER | D101: 14(9) | E101: 90000
A102: 3 | B102: OKECHUKWU UCHENNA HULDA | C102: PRINCIPALTRAINING OFFICER | D102: 12(9) | E102: 68000
A103: 4 | B103: TASSNEEM IBRAHIM | C103: SENIOR PROGRAMME OFFICER | D103: 10(8) | E103: 68000
B104: TOTAL | C104: 4 | E104: =SUM(E100:E103) -> 496000
B106: LIBRARY & DOCUMENTATION
A107: 1 | B107: DR MAIMUNA IZAH | C107: INSITUTE LIBRARIAN | D107: 17(9) | E107: 270000
A108: 2 | B108: CATHERINE E. IKOKOH | C108: SNR RESEARCH FELLOW DOCU | D108: 16(9) | E108: 180000
A109: 3 | B109: ALIYU SANNI ABUBAKAR | C109: RESEARCH FELLOW 11 DATA & DOCU | D109: 13(11) | E109: 90000
A110: 4 | B110: CHINAKO N. ASOGWA | C110: RESEARCH FELLOW 11 DATA & DOCU | D110: 13(11) | E110: 90000
A111: 5 | B111: AMOS ABA | C111: LIBRARY ASSISTANT | D111: 8(12) | E111: 54000
A112: 6 | B112: TITILAYO DANIEL MARVELLOUS | C112: LIBRARY ASSISTANT | D112: 8(11) | E112: 54000
A113: 7 | B113: ENENCHE JEREMIAH AGADA | C113: LIBRARY ASSISTANT | D113: 8(9) | E113: 54000
B114: TOTAL | C114: 7 | E114: =SUM(E107:E113) -> 792000
B116: LEG, CTRE FOR SEC. ANALYSIS
A117: 1 | B117: NGARA CHRISTOPHER OCHANJA | C117: SNR RESEARCH FELLOW | D117: 15(8) | E117: 126000
A118: 2 | B118: EGUATU U. ONYEJELEM | C118: PRINCIPAL M&E OFFICER | D118: 12(9) | E118: 68000
A119: 3 | B119: CHRISTIAN MADUABUCHI ODO | C119: ASSIST. CHIEF ICT OFFICER | D119: 13(7) | E119: 90000
B120: TOTAL | C120: 2 | E120: =SUM(E117:E119) -> 284000
B122: DEMOCRACY RADIO 104.9
A123: 1 | B123: MUGISAT ABDULGANIYU | C123: PRESENTER/ANNOUNCER | D123: 8(7) | E123: 54000
A124: 2 | B124: ZAINAB BAKARI | C124: NEWS CASTER | D124: 8(7) | E124: 54000
A125: 3 | B125: SHUGGE NGALABAK | C125: DIGITAL PRODUCER/MARKETER | D125: 8(7) | E125: 54000
B126: TOTAL | C126: 3 | E126: =SUM(E123:E125) -> 162000
B128: FINANCE & ACCOUNTS
A129: 1 | B129: IBRAHIM M. MSHELIA | C129: DIR. FINANCE & ACCOUNTS | D129: 17(9) | E129: 270000
A130: 2 | B130: RAHILA NURUDEEN HABU | C130: DEP. DIRECTOR, ACCOUNTS | D130: 16(8) | E130: 180000
...

Sheet Sum of Welfare
A1: SUMMARY OF CHRISTMAS WELFARE
A2: 1 | B2: Permanent Staff | C2: ='Christmas Welfare 2024'!E205 -> 13744000
A3: 2 | B3: New Permanent Staff | C3: ='[4]Christmas 2024'!$E$58 -> 1470000
A4: 3 | B4: Contract Staff | C4: ='[5]WELFARE CONTRACT '!$E$21 -> 1692000
A5: 4 | B5: New Contract Staff | C5: ='[5]NEW CONTR WELFARE'!$E$31 -> 1676000
A6: 5 | B6: Casual, Sabbatical & NYSC | C6: ='[5]WELFARE CAS. SABB. NYSC'!$D$68 -> 2259000
A7: 6 | B7: Consultants/Freelance | C7: ='[5]WELFARE CONSULTANCY'!$D$30 -> 1656000
A8: 7 | B8: Cleaners & Security Personnel | C8: ='[5]WELFARE - OTHERS'!$C$95 -> 1555000
B9: Total | C9: =SUM(C2:C8) -> 24052000

Sheet Staff Bonus
A1: NATIONAL INSTITUTE FOR LEGISLATIVE AND DEMOCRATIC STUDIES
A2: STAFF END OF YEAR BONUS DECEMBER 2024
B4: STAFF NAME | C4: DESIGNATION | D4: GRADE LEVEL | E4: GROSS SALARY | F4: HALF SALARY
E5: N | F5: N
A6: S/N | B6: DG'S OFFICE
A7: 1 | B7: PROF. ABUBAKAR O. SULAIMAN | C7: DIRECTOR GENERAL | D7: CONSOL | E7: 1934986.2 | F7: =E7/2 -> 967493.08
A8: 2 | B8: RAHEEM USMAN AYIGORO | C8: SA-INFRASTRUCTURE | D8: 16 (9) | E8: 952373.17 | F8: =E8/2 -> 476186.58
A9: 3 | B9: MARIAM MOHAMMED BELLO | C9: SA- SPECIAL DUTIES | D9: 16 (9) | E9: 1152373.2 | F9: =E9/2 -> 576186.58
A10: 4 | B10: DR IKEME ARTHUR J.O | C10: DEPUTY DIRECTOR, M&E | D10: 16 (9) | E10: 942373.17 | F10: =E10/2 -> 471186.58
A11: 5 | B11: MOSHOOD M. OLALERE | C11: DEPUTY DIR. GENERAL SERVICE | D11: 16 (9) | E11: 1102373.2 | F11: =E11/2 -> 551186.58
A12: 6 | B12: ANDRAWUS MUSA | C12: ASST. DIRECTOR, STORES | D12: 15(9) | E12: 750675.58 | F12: =E12/2 -> 375337.79
A13: 7 | B13: DR FRANCIS NDUM OJIE | C13: AD, TRAINING & IC./SA TO DG | D13: 15(7) | E13: 942118.08 | F13: =E13/2 -> 471059.04
A14: 8 | B14: ALI ABDULLAHI | C14: CHIEF ICT OFFICER | D14: 14(11) | E14: 554373.75 | F14: =E14/2 -> 277186.88
A15: 9 | B15: EMILY EKHIDE | C15: SENIOR RESEARCH FELLOW | D15: 15(7) | E15: 892118.08 | F15: =E15/2 -> 446059.04
A16: 10 | B16: DORIS DAKDA AARON | C16: RESEARCH FELLOW I | D16: 14(8) | E16: 832746.5 | F16: =E16/2 -> 416373.25
A17: 11 | B17: ABDULSALAM S. MUSTAPHA | C17: ASST. DIRECTOR ICT | D17: 15(7) | E17: 662118.08 | F17: =E17/2 -> 331059.04
A18: 12 | B18: PERCY TERFA GBAHABO | C18: HEAD, NILDS LIAISON OFFICE | D18: 13(10) | E18: 548915.92 | F18: =E18/2 -> 274457.96
... A37: 31 | B37: RAMATU IBRAHIM ABDULRAHEEM | C37: INFORMATION OFFICER | D37: 8(7) | E37: 268287.58 | F37: =E37/2 -> 134143.79
B38: TOTAL | C38: 31 | E38: 19076284 | F38: =SUM(F7:F37) -> 9538142.2
B40: INTERNAL AUDIT
A41: 1 | B41: OSANAIYE DAVID AKINYEMI | C41: DIRECTOR INTERNAL AUDIT | D41: 17(9) | E41: 1535720 | F41: =E41/2 -> 767860
A42: 2 | B42: JAMILA ABDUL | C42: SENIOR INTERNAL AUDITOR | D42: 10(7) | E42: 353029.67 | F42: =E42/2 -> 176514.83
A43: 3 | B43: IJEOMA EWELUKWA | C43: SENIOR INTERNAL AUDITOR | D43: 10(8) | E43: 360965.58 | F43: =E43/2 -> 180482.79
A44: 4 | B44: YUSUF YUSUF DAYYABU | C44: INERNAL AUDIT OFFICER | D44: 9(7) | E44: 315849 | F44: =E44/2 -> 157924.5
C45: 4 | E45: 2565564.2 | F45: =SUM(F41:F44) -> 1282782.1
B47: LEG. SUPPORT SEVICES
A48: 1 | B48: PROF. EDOBA BRIGHT OMOREGBE | C48: AG. DLSS | D48: 17(9) | E48: ='MARCH 2025'!J59 -> 1635720 | F48: =E48/2 -> 817860
A49: 2 | B49: DR CLINTON JAJA | C49: SENIOR RESEARCH FELLOW | D49: 15(9) | E49: 0 | F49: =E49/2 -> 0
A50: 3 | B50: BETHEL UZOMA IHUGBA | C50: DEPUTY DIRECTOR, LEGAL RESEARCH | D50: 16(8) | E50: 919203.58 | F50: =E50/2 -> 459601.79
A51: 4 | B51: OGUCHE SAMUEL | C51: SNR RESEARCH FELLOW | D51: 15(9) | E51: 780675.58 | F51: =E51/2 -> 390337.79
A52: 5 | B52: IBRAHIM USMAN | C52: SNR RESEARCH FELLOW | D52: 15(9) | E52: 780675.58 | F52: =E52/2 -> 390337.79
A53: 6 | B53: DR MOHAMMED O. AMALI | C53: SNR RESEARCH FELLOW | D53: 15(7) | E53: 742118.08 | F53: =E53/2 -> 371059.04
A54: 7 | B54: YAHAYA SHAMSU | C54: SNR RESEARCH FELLOW | D54: 15(7) | E54: 742118.08 | F54: =E54/2 -> 371059.04
A55: 8 | B55: BILKIS S. LAWAL-GAMBARI | C55: RESEARCH OFFICER | D55: 10(8) | E55: 400965.58 | F55: =E55/2 -> 200482.79
A56: 9 | B56: ZAINAB AKINDE | C56: RESEARCH OFFICER | D56: 9(8) | E56: 363165.33 | F56: =E56/2 -> 181582.67
A57: 10 | B57: GUNAT NANSAK MARK | C57: RESEARCH OFFICER | D57: 9(8) | E57: 363165.33 | F57: =E57/2 -> 181582.67
B58: TOTAL | C58: 10 | E58: =SUM(E48:E57) -> 6727807.2 | F58: =SUM(F48:F57) -> 3363903.6
B60: LEGAL SERVICES
A61: 1 | B61: DR SHUIBU DANWANKA | C61: DIRECTOR LEGAL SERVICES | D61: 17(9) | E61: 1635720 | F61: =E61/2 -> 817860
A62: 2 | B62: ABDULSALAM BAKO | C62: MANAGER, LEGAL SERVICES | D62: 15 (9) | E62: 700675.58 | F62: =E62/2 -> 350337.79
B63: TOTAL | C63: 2 | E63: 700675.58 | F63: =SUM(F61:F62) -> 1168197.8
B65: DEMOCRACY & GOVERNANCE
A66: 1 | B66: DR. ADEWALE ADEREMI | C66: DIRECTOR, DEMOCRATIC STUDIES | D66: 17(9) | E66: 1635720 | F66: =E66/2 -> 817860
A67: 2 | B67: NDANUSA MOHAMMED MANZUMA | C67: SNR RESEARCH FELLOW | D67: 15(8) | E67: 761396.83 | F67: =E67/2 -> 380698.42
A68: 3 | B68: EJALONIBU GANIYU LAYI | C68: RESEARCH FELLOW 1 | D68: 14(8) | E68: 582746.5 | F68: =E68/2 -> 291373.25
A69: 4 | B69: LOHNA BONKAT JONATHAN | C69: RESEARCH FELLOW 11 | D69: 13(10) | E69: 0 | F69: =E69/2 -> 0
A70: 7 | B70: UDEFUNA NNADOZIE PATRICK | C70: RESEARCH OFFICER | D70: 12(8) | E70: 475703.83 | F70: =E70/2 -> 237851.92
A71: 8 | B71: SHAFIU YAHYA MIKAIL | C71: PRINCIPAL RESEARCH OFFICER | D71: 12(8) | E71: 475703.83 | F71: =E71/2 -> 237851.92
A72: 9 | B72: HASSAN YERIMA | C72: PRINCIPAL RESEARCH OFFICER | D72: 12(8) | E72: 475703.83 | F72: =E72/2 -> 237851.92
A73: 10 | B73: HAUWA PATE SADIQ | C73: PRINCIPAL PROGRAMME OFFICER | D73: 12(9) | E73: 487895.17 | F73: =E73/2 -> 243947.58
A74: 11 | B74: KOLAPO Q. ABAYOMI | C74: RESEARCH OFFICER | D74: 10(8) | E74: 400965.58 | F74: =E74/2 -> 200482.79
B75: TOTAL | C75: 11 | E75: 5295835.6 | F75: =SUM(F66:F74) -> 2647917.8
B77: DEPARTMENT OF STUDIES
A78: 1 | B78: DR ASIMIYU G. ABIOLA | C78: DIRECTOR POST GRADUATE | D78: 17(9) | E78: 1635720 | F78: =E78/2 -> 817860
A79: 2 | B79: DR. HADIZA SAIDU | C79: ASSISTANT DIRECTOR | D79: 15(7) | E79: 742118.08 | F79: =E79/2 -> 371059.04
A80: 3 | B80: ANTHONY EDET | C80: CHIEF PROGRAMMES OFFICER | D80: 14(9) | E80: 596622.25 | F80: =E80/2 -> 298311.12
A81: 4 | B81: IGWE STACY | C81: PRINC. PROGRAMME OFFICER | D81: 12(7) | E81: 463512.5 | F81: =E81/2 -> 231756.25
A82: 5 | B82: OLANIYAN TAIWO ABINBOLA | C82: PROGRAMME OFFICER | D82: 9(8) | E82: 363165.33 | F82: =E82/2 -> 181582.67
A83: 6 | B83: AMINAT JUMOKE SULAIMON | C83: AST. PROGRAMME OFFICER | D83: 8(8) | E83: 324459.75 | F83: =E83/2 -> 162229.88
B84: TOTAL | C84: 6 | E84: 4125597.9 | F84: =SUM(F78:F83) -> 2062799
B86: ECON. DEV. & SOC. RESEARCH
A87: 1 | B87: TERFA WILLIAMS ABRAHAM | C87: SNR RESEARCH FELLOW | D87: 15(9) | E87: 980675.58 | F87: =E87/2 -> 490337.79
A88: 2 | B88: DR AUGUSTINE C. OSIGWE | C88: SNR RESEARCH FELLOW | D88: 15(9) | E88: 780675.58 | F88: =E88/2 -> 390337.79
A89: 3 | B89: OMOJU OLUWASOLA EMMANUEL | C89: SNR RESEARCH FELLOW | D89: 15(7) | E89: 742118.08 | F89: =E89/2 -> 371059.04
A90: 4 | B90: IBE EZECHI CYRIACUS | C90: RESEARCH FELLOW 1 | D90: 14(8) | E90: 582746.5 | F90: =E90/2 -> 291373.25
A91: 5 | B91: OSIKHEN LEO IGBANOI | C91: RESEARCH FELLOW 1 | D91: 14(8) | E91: 562746.5 | F91: =E91/2 -> 281373.25
A92: 6 | B92: OKUNGBOWA OSARETIN GODSPOWER | C92: RESEARCH FELLOW 1 | D92: 14(7) | E92: 568870.75 | F92: =E92/2 -> 284435.38
A93: 7 | B93: YUSUF IBRAHIM | C93: PRINCIPAL RESEARCH OFFICER | D93: 12(8) | E93: 475703.83 | F93: =E93/2 -> 237851.92
A94: 8 | B94: MUSTAPHA RAFIU AYOBANJI | C94: RESEARCH FELLOW 11 | D94: 13(7) | E94: 510248.92 | F94: =E94/2 -> 255124.46
A95: 9 | B95: MARYAM MUSA SADA | C95: ASSIT. RESEARCH OFFICER | D95: 10(8) | E95: 400965.58 | F95: =E95/2 -> 200482.79
A96: 10 | B96: CHARITY EZENWAJIOBI | C96: REASEARCH. ASST. | D96: 8(9) | E96: 330631.92 | F96: =E96/2 -> 165315.96
B97: TOTAL | C97: 10 | E97: 5935383.2 | F97: =SUM(F87:F96) -> 2967691.6
B99: TRAINING & INT''L COOP
A100: 1 | B100: AKINSANMI ADEJOKE OLUKEMI | C100: Ag. DIR. TRAINING & IC | D100: 17(7) | E100: 1452042.7 | F100: =E100/2 -> 726021.33
A101: 2 | B101: MOHAMMED R. ADAMU | C101: CHIEF TRAINING OFFICER | D101: 14(9) | E101: 526622.25 | F101: =E101/2 -> 263311.12
A102: 3 | B102: OKECHUKWU UCHENNA HULDA | C102: PRINCIPALTRAINING OFFICER | D102: 12(9) | E102: 437895.17 | F102: =E102/2 -> 218947.58
A103: 4 | B103: TASSNEEM IBRAHIM | C103: SENIOR PROGRAMME OFFICER | D103: 10(8) | E103: 360965.58 | F103: =E103/2 -> 180482.79
B104: TOTAL | C104: 4 | E104: 2777525.7 | F104: =SUM(F100:F103) -> 1388762.8
B106: LIBRARY & DOCUMENTATION
A107: 1 | B107: DR MAIMUNA IZAH | C107: INSITUTE LIBRARIAN | D107: 17(9) | E107: 1635720 | F107: =E107/2 -> 817860
A108: 2 | B108: CATHERINE E. IKOKOH | C108: SNR RESEARCH FELLOW DOCU | D108: 16(9) | E108: 942373.17 | F108: =E108/2 -> 471186.58
A109: 3 | B109: ALIYU SANNI ABUBAKAR | C109: RESEARCH FELLOW 11 DATA & DOCU | D109: 13(11) | E109: 603237.86 | F109: =E109/2 -> 301618.93
A110: 4 | B110: CHINAKO N. ASOGWA | C110: RESEARCH FELLOW 11 DATA & DOCU | D110: 13(11) | E110: 601625.03 | F110: =E110/2 -> 300812.52
A111: 5 | B111: AMOS ABA | C111: LIBRARY ASSISTANT | D111: 8(12) | E111: 374481.86 | F111: =E111/2 -> 187240.93
A112: 6 | B112: TITILAYO DANIEL MARVELLOUS | C112: LIBRARY ASSISTANT | D112: 8(11) | E112: 367926.02 | F112: =E112/2 -> 183963.01
A113: 7 | B113: ENENCHE JEREMIAH AGADA | C113: LIBRARY ASSISTANT | D113: 8(9) | E113: 355198.11 | F113: =E113/2 -> 177599.06
B114: TOTAL | C114: 7 | E114: 4880562.1 | F114: =SUM(F107:F113) -> 2440281
B116: LEG, CTRE FOR SEC. ANALYSIS
A117: 1 | B117: NGARA CHRISTOPHER OCHANJA | C117: SNR RESEARCH FELLOW | D117: 15(8) | E117: 761396.83 | F117: =E117/2 -> 380698.42
A118: 2 | B118: EGUATU U. ONYEJELEM | C118: PRINCIPAL M&E OFFICER | D118: 12(9) | E118: 487895.17 | F118: =E118/2 -> 243947.58
A119: 3 | B119: CHRISTIAN MADUABUCHI ODO | C119: ASSIST. CHIEF ICT OFFICER | D119: 13(7) | E119: 460248.92 | F119: =E119/2 -> 230124.46
B120: TOTAL | C120: 2 | E120: 1709540.9 | F120: =SUM(F117:F119) -> 854770.46
B122: DEMOCRACY RADIO 104.9
A123: 1 | B123: MUGISAT ABDULGANIYU | C123: PRESENTER/ANNOUNCER | D123: 8(7) | E123: 268287.58 | F123: =E123/2 -> 134143.79
A124: 2 | B124: ZAINAB BAKARI | C124: NEWS CASTER | D124: 8(7) | E124: 268287.58 | F124: =E124/2 -> 134143.79
A125: 3 | B125: SHUGGE NGALABAK | C125: DIGITAL PRODUCER/MARKETER | D125: 8(7) | E125: 268287.58 | F125: =E125/2 -> 134143.79
B126: TOTAL | C126: 3 | E126: 804862.75 | F126: =SUM(F123:F125) -> 402431.38
B128: FINANCE & ACCOUNTS
A129: 1 | B129: IBRAHIM M. MSHELIA | C129: DIR. FINANCE & ACCOUNTS | D129: 17(9) | E129: 1635720 | F129: =E129/2 -> 817860
A130: 2 | B130: RAHILA NURUDEEN HABU | C130: DEP. DIRECTOR, ACCOUNTS | D130: 16(8) | E130: 929203.58 | F130: =E130/2 -> 464601.79
...

Sheet Sum of Bonus
A1: SUMMARY OF END OF YEAR BONUS
A2: 1 | B2: Permanent Staff | C2: ='Staff Bonus'!F205 -> 40455221
A3: 2 | B3: New Permanent Staff | C3: ='[4]NEW STAFF BONUS'!$F$57 -> 3962895.7
A4: 3 | B4: Contract Staff | C4: ='[5]BONUS CONTRACT'!$F$21 -> 4618070.7
A5: 4 | B5: New Contract Staff | C5: ='[5]NEW CONTR BONUS'!$F$30 -> 4681559.8
A6: 5 | B6: Casual, Sabbatical & NYSC | C6: ='[5]CAS. SABB. NYSC BONUS'!$E$67 -> 4877192.4
A7: 6 | B7: Consultants | C7: ='[5]CONSULTANCY BONUS'!$E$28 -> 2750000
B8: Total | C8: =SUM(C2:C7) -> 61344940

Sheet Bonus PAYE
A1: NATIONAL INSTITUTE FOR LEGISLATIVE AND DEMOCRATIC STUDIES
A2: NATIONAL ASSEMBLY ABUJA
A3: TAX COMPUTATION FOR 2022
A4: S/NO | B4: NAME | C4: MONTHLY TOTAL SALARY | D4: NO OF MONTHS | E4: ANNUAL SALARY GROSSED UP | F4: NATIONAL HOUSING SCHEME = 2.5% OF BASIC SALARY | G4: PENSION CONTRIBUTION = 8% OF CONSOLIDATED | H4: NHIS | I4: NET SALARY (EXC OF CRA) | M4: CRA=#200,000+(20% 0F NET SALARY (EXC OF CRA) | N4: TOTAL RELIEF | O4: CHARGEABLE INCOME | P4: FIRST N300,000 @ 7% | Q4: NEXT N300,000 @ 11% | R4: NEXT N500,000 @ 15% | S4: NEXT N500,000@ 19% | T4: NEXT N1,600,000 @ 21% | U4: ABOVE N3,200,000 @ 24% | V4: ANNUAL TAX PAYABLE | X4: MONTHLY TAX PAYABLE | Y4: MINIMUM TAX PAYABLE | Z4: NEW ACTUAL TAX PAYABLE | AB4: Difference
A5: 1 | B5: DG'S OFFICE
A6: 3 | B6: PROF. ABUBAKAR O. SULAIMAN | C6: 967493.08 | D6: 12 | E6: =C6*D6 -> 11609917 | I6: =E6-F6-G6-H6 -> 11609917 | J6: 200000 | K6: 0.2 | L6: =I6*K6 -> 2321983.4 | M6: =J6+L6 -> 2521983.4 | N6: =F6+G6+H6+M6 -> 2521983.4 | O6: =E6-N6 -> 9087933.6 | P6: =IF(O6<300000,0.07*O6,21000) -> 21000 | Q6: =IF((O6-300000)<0,0,IF((O6-300000)<300000,0.11*(O6-300000),33000)) -> 33000 | R6: =IF((O6-600000)<0,0,IF((O6-600000)<500000,0.15*(O6-600000),75000)) -> 75000 | S6: =IF((O6-1100000)<0,0,IF((O6-1100000)<500000,0.19*(O6-1100000),95000)) -> 95000 | T6: =IF((O6-1600000)<0,0,IF((O6-1600000)<1600000,0.21*(O6-1600000),336000)) -> 336000 | U6: =24%*(O6-3200000) -> 1413104.1 | V6: =P6+Q6+R6+S6+T6+U6 -> 1973104.1 | W6: 12 | X6: =V6/W6 -> 164425.34 | Z6: =X6 -> 164425.34 | AA6: 201165.84 | AB6: =Z6-AA6 -> -36740.497
A7: 4 | B7: RAHEEM USMAN AYIGORO | C7: 476186.58 | D7: 12 | E7: =C7*D7 -> 5714239 | G7: 731878.24 | I7: =E7-F7-G7-H7 -> 4982360.8 | J7: 200000 | K7: 0.2 | L7: =I7*K7 -> 996472.15 | M7: =J7+L7 -> 1196472.2 | N7: =F7+G7+H7+M7 -> 1928350.4 | O7: =E7-N7 -> 3785888.6 | P7: =IF(O7<300000,0.07*O7,21000) -> 21000 | Q7: =IF((O7-300000)<0,0,IF((O7-300000)<300000,0.11*(O7-300000),33000)) -> 33000 | R7: =IF((O7-600000)<0,0,IF((O7-600000)<500000,0.15*(O7-600000),75000)) -> 75000 | S7: =IF((O7-1100000)<0,0,IF((O7-1100000)<500000,0.19*(O7-1100000),95000)) -> 95000 | T7: =IF((O7-1600000)<0,0,IF((O7-1600000)<1600000,0.21*(O7-1600000),336000)) -> 336000 | U7: =24%*(O7-3200000) -> 140613.27 | V7: =P7+Q7+R7+S7+T7+U7 -> 700613.27 | W7: 12 | X7: =V7/W7 -> 58384.439 | Z7: =X7 -> 58384.439 | AA7: 82627.951 | AB7: =Z7-AA7 -> -24243.513
A8: 5 | B8: MARIAM MOHAMMED BELLO | C8: 576186.58 | D8: 12 | E8: =C8*D8 -> 6914239 | G8: 0 | I8: =E8-F8-G8-H8 -> 6914239 | J8: 200000 | K8: 0.2 | L8: =I8*K8 -> 1382847.8 | M8: =J8+L8 -> 1582847.8 | N8: =F8+G8+H8+M8 -> 1582847.8 | O8: =E8-N8 -> 5331391.2 | P8: =IF(O8<300000,0.07*O8,21000) -> 21000 | Q8: =IF((O8-300000)<0,0,IF((O8-300000)<300000,0.11*(O8-300000),33000)) -> 33000 | R8: =IF((O8-600000)<0,0,IF((O8-600000)<500000,0.15*(O8-600000),75000)) -> 75000 | S8: =IF((O8-1100000)<0,0,IF((O8-1100000)<500000,0.19*(O8-1100000),95000)) -> 95000 | T8: =IF((O8-1600000)<0,0,IF((O8-1600000)<1600000,0.21*(O8-1600000),336000)) -> 336000 | U8: =24%*(O8-3200000) -> 511533.89 | V8: =P8+Q8+R8+S8+T8+U8 -> 1071533.9 | W8: 12 | X8: =V8/W8 -> 89294.491 | Z8: =X8 -> 89294.491 | AA8: 121027.95 | AB8: =Z8-AA8 -> -31733.461
A9: 6 | B9: DR IKEME ARTHUR J.O | C9: 471186.58 | D9: 12 | E9: =C9*D9 -> 5654239 | F9: ='[6]JANUARY 2024'!$V$10*12 -> 12795.951 | G9: 731878.24 | I9: =E9-F9-G9-H9 -> 4909564.8 | J9: 200000 | K9: 0.2 | L9: =I9*K9 -> 981912.96 | M9: =J9+L9 -> 1181913 | N9: =F9+G9+H9+M9 -> 1926587.2 | O9: =E9-N9 -> 3727651.8 | P9: =IF(O9<300000,0.07*O9,21000) -> 21000 | Q9: =IF((O9-300000)<0,0,IF((O9-300000)<300000,0.11*(O9-300000),33000)) -> 33000 | R9: =IF((O9-600000)<0,0,IF((O9-600000)<500000,0.15*(O9-600000),75000)) -> 75000 | S9: =IF((O9-1100000)<0,0,IF((O9-1100000)<500000,0.19*(O9-1100000),95000)) -> 95000 | T9: =IF((O9-1600000)<0,0,IF((O9-1600000)<1600000,0.21*(O9-1600000),336000)) -> 336000 | U9: =24%*(O9-3200000) -> 126636.44 | V9: =P9+Q9+R9+S9+T9+U9 -> 686636.44 | W9: 12 | X9: =V9/W9 -> 57219.704 | Z9: =X9 -> 57219.704 | AA9: 99703.216 | AB9: =Z9-AA9 -> -42483.513
A10: 7 | B10: MOSHOOD M. OLALERE | C10: 551186.58 | D10: 12 | E10: =C10*D10 -> 6614239 | F10: ='[6]JANUARY 2024'!$V$10*12 -> 12795.951 | G10: 731878.24 | I10: =E10-F10-G10-H10 -> 5869564.8 | J10: 200000 | K10: 0.2 | L10: =I10*K10 -> 1173913 | M10: =J10+L10 -> 1373913 | N10: =F10+G10+H10+M10 -> 2118587.2 | O10: =E10-N10 -> 4495651.8 | P10: =IF(O10<300000,0.07*O10,21000) -> 21000 | Q10: =IF((O10-300000)<0,0,IF((O10-300000)<300000,0.11*(O10-300000),33000)) -> 33000 | R10: =IF((O10-600000)<0,0,IF((O10-600000)<500000,0.15*(O10-600000),75000)) -> 75000 | S10: =IF((O10-1100000)<0,0,IF((O10-1100000)<500000,0.19*(O10-1100000),95000)) -> 95000 | T10: =IF((O10-1600000)<0,0,IF((O10-1600000)<1600000,0.21*(O10-1600000),336000)) -> 336000 | U10: =24%*(O10-3200000) -> 310956.44 | V10: =P10+Q10+R10+S10+T10+U10 -> 870956.44 | W10: 12 | X10: =V10/W10 -> 72579.704 | Z10: =X10 -> 72579.704 | AA10: 111223.22 | AB10: =Z10-AA10 -> -38643.513
A11: 8 | B11: ANDRAWUS MUSA | C11: 375337.79 | D11: 12 | E11: =C11*D11 -> 4504053.5 | G11: 0 | I11: =E11-F11-G11-H11 -> 4504053.5 | J11: 200000 | K11: 0.2 | L11: =I11*K11 -> 900810.7 | M11: =J11+L11 -> 1100810.7 | N11: =F11+G11+H11+M11 -> 1100810.7 | O11: =E11-N11 -> 3403242.8 | P11: =IF(O11<300000,0.07*O11,21000) -> 21000 | Q11: =IF((O11-300000)<0,0,IF((O11-300000)<300000,0.11*(O11-300000),33000)) -> 33000 | R11: =IF((O11-600000)<0,0,IF((O11-600000)<500000,0.15*(O11-600000),75000)) -> 75000 | S11: =IF((O11-1100000)<0,0,IF((O11-1100000)<500000,0.19*(O11-1100000),95000)) -> 95000 | T11: =IF((O11-1600000)<0,0,IF((O11-1600000)<1600000,0.21*(O11-1600000),336000)) -> 336000 | U11: =24%*(O11-3200000) -> 48778.272 | V11: =P11+Q11+R11+S11+T11+U11 -> 608778.27 | W11: 12 | X11: =V11/W11 -> 50731.523 | Z11: =X11 -> 50731.523 | AA11: 101827.95 | AB11: =Z11-AA11 -> -51096.429
A12: 9 | B12: DR FRANCIS NDUM OJIE | C12: 471059.04 | D12: 12 | E12: =C12*D12 -> 5652708.5 | F12: ='[6]JANUARY 2024'!$V$13*12 -> 10052.25 | G12: 595848.56 | I12: =E12-F12-G12-H12 -> 5046807.7 | J12: 200000 | K12: 0.2 | L12: =I12*K12 -> 1009361.5 | M12: =J12+L12 -> 1209361.5 | N12: =F12+G12+H12+M12 -> 1815262.3 | O12: =E12-N12 -> 3837446.2 | P12: =IF(O12<300000,0.07*O12,21000) -> 21000 | Q12: =IF((O12-300000)<0,0,IF((O12-300000)<300000,0.11*(O12-300000),33000)) -> 33000 | R12: =IF((O12-600000)<0,0,IF((O12-600000)<500000,0.15*(O12-600000),75000)) -> 75000 | S12: =IF((O12-1100000)<0,0,IF((O12-1100000)<500000,0.19*(O12-1100000),95000)) -> 95000 | T12: =IF((O12-1600000)<0,0,IF((O12-1600000)<1600000,0.21*(O12-1600000),336000)) -> 336000 | U12: =24%*(O12-3200000) -> 152987.08 | V12: =P12+Q12+R12+S12+T12+U12 -> 712987.08 | W12: 12 | X12: =V12/W12 -> 59415.59 | Z12: =X12 -> 59415.59 | AA12: 74036.103 | AB12: =Z12-AA12 -> -14620.513
A13: 10 | B13: ALI ABDULLAHI | C13: 277186.88 | D13: 12 | E13: =C13*D13 -> 3326242.5 | F13: ='[6]JANUARY 2024'!$V$14*12 -> 9305.952 | G13: 558833.36 | I13: =E13-F13-G13-H13 -> 2758103.2 | J13: 200000 | K13: 0.2 | L13: =I13*K13 -> 551620.64 | M13: =J13+L13 -> 751620.64 | N13: =F13+G13+H13+M13 -> 1319759.9 | O13: =E13-N13 -> 2006482.6 | P13: =IF(O13<300000,0.07*O13,21000) -> 21000 | Q13: =IF((O13-300000)<0,0,IF((O13-300000)<300000,0.11*(O13-300000),33000)) -> 33000 | R13: =IF((O13-600000)<0,0,IF((O13-600000)<500000,0.15*(O13-600000),75000)) -> 75000 | S13: =IF((O13-1100000)<0,0,IF((O13-1100000)<500000,0.19*(O13-1100000),95000)) -> 95000 | T13: =IF((O13-1600000)<0,0,IF((O13-1600000)<1600000,0.21*(O13-1600000),336000)) -> 85361.336 | V13: =P13+Q13+R13+S13+T13+U13 -> 309361.34 | W13: 12 | X13: =V13/W13 -> 25780.111 | Z13: =X13 -> 25780.111 | AA13: 94625.782 | AB13: =Z13-AA13 -> -68845.671
A14: 11 | B14: EMILY EKHIDE | C14: 446059.04 | D14: 12 | E14: =C14*D14 -> 5352708.5 | G14: 464998.8 | I14: =E14-F14-G14-H14 -> 4887709.7 | J14: 200000 | K14: 0.2 | L14: =I14*K14 -> 977541.94 | M14: =J14+L14 -> 1177541.9 | N14: =F14+G14+H14+M14 -> 1642540.7 | O14: =E14-N14 -> 3710167.8 | P14: =IF(O14<300000,0.07*O14,21000) -> 21000 | Q14: =IF((O14-300000)<0,0,IF((O14-300000)<300000,0.11*(O14-300000),33000)) -> 33000 | R14: =IF((O14-600000)<0,0,IF((O14-600000)<500000,0.15*(O14-600000),75000)) -> 75000 | S14: =IF((O14-1100000)<0,0,IF((O14-1100000)<500000,0.19*(O14-1100000),95000)) -> 95000 | T14: =IF((O14-1600000)<0,0,IF((O14-1600000)<1600000,0.21*(O14-1600000),336000)) -> 336000 | U14: =24%*(O14-3200000) -> 122440.26 | V14: =P14+Q14+R14+S14+T14+U14 -> 682440.26 | W14: 12 | X14: =V14/W14 -> 56870.022 | Z14: =X14 -> 56870.022 | AA14: 44846.617 | AB14: =Z14-AA14 -> 12023.405
A15: 12 | B15: DORIS DAKDA AARON | C15: 416373.25 | D15: 12 | E15: =C15*D15 -> 4996479 | G15: 451678.08 | I15: =E15-F15-G15-H15 -> 4544800.9 | J15: 200000 | K15: 0.2 | L15: =I15*K15 -> 908960.18 | M15: =J15+L15 -> 1108960.2 | N15: =F15+G15+H15+M15 -> 1560638.3 | O15: =E15-N15 -> 3435840.7 | P15: =IF(O15<300000,0.07*O15,21000) -> 21000 | Q15: =IF((O15-300000)<0,0,IF((O15-300000)<300000,0.11*(O15-300000),33000)) -> 33000 | R15: =IF((O15-600000)<0,0,IF((O15-600000)<500000,0.15*(O15-600000),75000)) -> 75000 | S15: =IF((O15-1100000)<0,0,IF((O15-1100000)<500000,0.19*(O15-1100000),95000)) -> 95000 | T15: =IF((O15-1600000)<0,0,IF((O15-1600000)<1600000,0.21*(O15-1600000),336000)) -> 336000 | U15: =24%*(O15-3200000) -> 56601.777 | V15: =P15+Q15+R15+S15+T15+U15 -> 616601.78 | W15: 12 | X15: =V15/W15 -> 51383.481 | Z15: =X15 -> 51383.481 | AA15: 46666.667 | AB15: =Z15-AA15 -> 4716.8147
A16: 13 | B16: ABDULSALAM S. MUSTAPHA | C16: 331059.04 | D16: 12 | E16: =C16*D16 -> 3972708.5 | G16: 425036.64 | I16: =E16-F16-G16-H16 -> 3547671.9 | J16: 200000 | K16: 0.2 | L16: =I16*K16 -> 709534.37 | M16: =J16+L16 -> 909534.37 | N16: =F16+G16+H16+M16 -> 1334571 | O16: =E16-N16 -> 2638137.5 | P16: =IF(O16<300000,0.07*O16,21000) -> 21000 | Q16: =IF((O16-300000)<0,0,IF((O16-300000)<300000,0.11*(O16-300000),33000)) -> 33000 | R16: =IF((O16-600000)<0,0,IF((O16-600000)<500000,0.15*(O16-600000),75000)) -> 75000 | S16: =IF((O16-1100000)<0,0,IF((O16-1100000)<500000,0.19*(O16-1100000),95000)) -> 95000 | T16: =IF((O16-1600000)<0,0,IF((O16-1600000)<1600000,0.21*(O16-1600000),336000)) -> 218008.87 | V16: =P16+Q16+R16+S16+T16+U16 -> 442008.87 | W16: 12 | X16: =V16/W16 -> 36834.073 | Z16: =X16 -> 36834.073 | AA16: 46666.667 | AB16: =Z16-AA16 -> -9832.594
A17: 14 | B17: PERCY TERFA GBAHABO | C17: 274457.96 | D17: 12 | E17: =C17*D17 -> 3293495.5 | G17: 424132.72 | I17: =E17-F17-G17-H17 -> 2869362.8 | J17: 200000 | K17: 0.2 | L17: =I17*K17 -> 573872.56 | M17: =J17+L17 -> 773872.56 | N17: =F17+G17+H17+M17 -> 1198005.3 | O17: =E17-N17 -> 2095490.2 | P17: =IF(O17<300000,0.07*O17,21000) -> 21000 | Q17: =IF((O17-300000)<0,0,IF((O17-300000)<300000,0.11*(O17-300000),33000)) -> 33000 | R17: =IF((O17-600000)<0,0,IF((O17-600000)<500000,0.15*(O17-600000),75000)) -> 75000 | S17: =IF((O17-1100000)<0,0,IF((O17-1100000)<500000,0.19*(O17-1100000),95000)) -> 95000 | T17: =IF((O17-1600000)<0,0,IF((O17-1600000)<1600000,0.21*(O17-1600000),336000)) -> 104052.95 | V17: =P17+Q17+R17+S17+T17+U17 -> 328052.95 | W17: 12 | X17: =V17/W17 -> 27337.746 | Z17: =X17 -> 27337.746 | AA17: 42046.064 | AB17: =Z17-AA17 -> -14708.318
A18: 15 | B18: HASSANA AHMED IBRAHIM | C18: 368013.46 | D18: 12 | E18: =C18*D18 -> 4416161.5 | G18: 411759.28 | I18: =E18-F18-G18-H18 -> 4004402.2 | J18: 200000 | K18: 0.2 | L18: =I18*K18 -> 800880.44 | M18: =J18+L18 -> 1000880.4 | N18: =F18+G18+H18+M18 -> 1412639.7 | O18: =E18-N18 -> 3003521.8 | P18: =IF(O18<300000,0.07*O18,21000) -> 21000 | Q18: =IF((O18-300000)<0,0,IF((O18-300000)<300000,0.11*(O18-300000),33000)) -> 33000 | R18: =IF((O18-600000)<0,0,IF((O18-600000)<500000,0.15*(O18-600000),75000)) -> 75000 | S18: =IF((O18-1100000)<0,0,IF((O18-1100000)<500000,0.19*(O18-1100000),95000)) -> 95000 | T18: =IF((O18-1600000)<0,0,IF((O18-1600000)<1600000,0.21*(O18-1600000),336000)) -> 294739.57 | V18: =P18+Q18+R18+S18+T18+U18 -> 518739.57 | W18: 12 | X18: =V18/W18 -> 43228.298 | Z18: =X18 -> 43228.298 | AA18: 46666.667 | AB18: =Z18-AA18 -> -3438.3689
A19: 16 | B19: IKIP LEBO | C19: 230124.46 | D19: 12 | E19: =C19*D19 -> 2761493.5 | F19: =618.53*12 -> 7422.36 | G19: 399385.84 | I19: =E19-F19-G19-H19 -> 2354685.3 | J19: 200000 | K19: 0.2 | L19: =I19*K19 -> 470937.06 | M19: =J19+L19 -> 670937.06 | N19: =F19+G19+H19+M19 -> 1077745.3 | O19: =E19-N19 -> 1683748.2 | P19: =IF(O19<300000,0.07*O19,21000) -> 21000 | Q19: =IF((O19-300000)<0,0,IF((O19-300000)<300000,0.11*(O19-300000),33000)) -> 33000 | R19: =IF((O19-600000)<0,0,IF((O19-600000)<500000,0.15*(O19-600000),75000)) -> 75000 | S19: =IF((O19-1100000)<0,0,IF((O19-1100000)<500000,0.19*(O19-1100000),95000)) -> 95000 | T19: =IF((O19-1600000)<0,0,IF((O19-1600000)<1600000,0.21*(O19-1600000),336000)) -> 17587.13 | V19: =P19+Q19+R19+S19+T19+U19 -> 241587.13 | W19: 12 | X19: =V19/W19 -> 20132.261 | Z19: =X19 -> 20132.261 | AA19: 46666.667 | AB19: =Z19-AA19 -> -26534.406
A20: 17 | B20: ALABI ADESINA MUHYDEEN | C20: 255124.46 | D20: 12 | E20: =C20*D20 -> 3061493.5 | G20: 362779.36 | I20: =E20-F20-G20-H20 -> 2698714.1 | J20: 200000 | K20: 0.2 | L20: =I20*K20 -> 539742.83 | M20: =J20+L20 -> 739742.83 | N20: =F20+G20+H20+M20 -> 1102522.2 | O20: =E20-N20 -> 1958971.3 | P20: =IF(O20<300000,0.07*O20,21000) -> 21000 | Q20: =IF((O20-300000)<0,0,IF((O20-300000)<300000,0.11*(O20-300000),33000)) -> 33000 | R20: =IF((O20-600000)<0,0,IF((O20-600000)<500000,0.15*(O20-600000),75000)) -> 75000 | S20: =IF((O20-1100000)<0,0,IF((O20-1100000)<500000,0.19*(O20-1100000),95000)) -> 95000 | T20: =IF((O20-1600000)<0,0,IF((O20-1600000)<1600000,0.21*(O20-1600000),336000)) -> 75383.976 | V20: =P20+Q20+R20+S20+T20+U20 -> 299383.98 | W20: 12 | X20: =V20/W20 -> 24948.665 | Z20: =X20 -> 24948.665 | AA20: 52497.77 | AB20: =Z20-AA20 -> -27549.106
A21: 18 | B21: ADUGBA RICHARD TERSEER | C21: 293947.58 | D21: 12 | E21: =C21*D21 -> 3527371 | G21: 339372 | I21: =E21-F21-G21-H21 -> 3187999 | J21: 200000 | K21: 0.2 | L21: =I21*K21 -> 637599.8 | M21: =J21+L21 -> 837599.8 | N21: =F21+G21+H21+M21 -> 1176971.8 | O21: =E21-N21 -> 2350399.2 | P21: =IF(O21<300000,0.07*O21,21000) -> 21000 | Q21: =IF((O21-300000)<0,0,IF((O21-300000)<300000,0.11*(O21-300000),33000)) -> 33000 | R21: =IF((O21-600000)<0,0,IF((O21-600000)<500000,0.15*(O21-600000),75000)) -> 75000 | S21: =IF((O21-1100000)<0,0,IF((O21-1100000)<500000,0.19*(O21-1100000),95000)) -> 95000 | T21: =IF((O21-1600000)<0,0,IF((O21-1600000)<1600000,0.21*(O21-1600000),336000)) -> 157583.83 | V21: =P21+Q21+R21+S21+T21+U21 -> 381583.83 | W21: 12 | X21: =V21/W21 -> 31798.653 | Z21: =X21 -> 31798.653 | AA21: 46666.667 | AB21: =Z21-AA21 -> -14868.014
A22: 19 | B22: LUCKY AGWOM | C22: 326756.25 | D22: 12 | E22: =C22*D22 -> 3921075 | G22: 339372 | I22: =E22-F22-G22-H22 -> 3581703 | J22: 200000 | K22: 0.2 | L22: =I22*K22 -> 716340.6 | M22: =J22+L22 -> 916340.6 | N22: =F22+G22+H22+M22 -> 1255712.6 | O22: =E22-N22 -> 2665362.4 | P22: =IF(O22<300000,0.07*O22,21000) -> 21000 | Q22: =IF((O22-300000)<0,0,IF((O22-300000)<300000,0.11*(O22-300000),33000)) -> 33000 | R22: =IF((O22-600000)<0,0,IF((O22-600000)<500000,0.15*(O22-600000),75000)) -> 75000 | S22: =IF((O22-1100000)<0,0,IF((O22-1100000)<500000,0.19*(O22-1100000),95000)) -> 95000 | T22: =IF((O22-1600000)<0,0,IF((O22-1600000)<1600000,0.21*(O22-1600000),336000)) -> 223726.1 | V22: =P22+Q22+R22+S22+T22+U22 -> 447726.1 | W22: 12 | X22: =V22/W22 -> 37310.509 | Z22: =X22 -> 37310.509 | AA22: 46666.667 | AB22: =Z22-AA22 -> -9356.158
A23: 20 | B23: IDRIS IBRAHIM | C23: 231756.25 | D23: 12 | E23: =C23*D23 -> 2781075 | G23: 281308.48 | I23: =E23-F23-G23-H23 -> 2499766.5 | J23: 200000 | K23: 0.2 | L23: =I23*K23 -> 499953.3 | M23: =J23+L23 -> 699953.3 | N23: =F23+G23+H23+M23 -> 981261.78 | O23: =E23-N23 -> 1799813.2 | P23: =IF(O23<300000,0.07*O23,21000) -> 21000 | Q23: =IF((O23-300000)<0,0,IF((O23-300000)<300000,0.11*(O23-300000),33000)) -> 33000 | R23: =IF((O23-600000)<0,0,IF((O23-600000)<500000,0.15*(O23-600000),75000)) -> 75000 | S23: =IF((O23-1100000)<0,0,IF((O23-1100000)<500000,0.19*(O23-1100000),95000)) -> 95000 | T23: =IF((O23-1600000)<0,0,IF((O23-1600000)<1600000,0.21*(O23-1600000),336000)) -> 41960.775 | V23: =P23+Q23+R23+S23+T23+U23 -> 265960.78 | W23: 12 | X23: =V23/W23 -> 22163.398 | Z23: =X23 -> 22163.398 | AA23: 42371.816 | AB23: =Z23-AA23 -> -20208.418
A24: 21 | B24: FARUQ ATOFARATI | C24: 276514.83 | D24: 12 | E24: =C24*D24 -> 3318178 | G24: 259662.4 | I24: =E24-F24-G24-H24 -> 3058515.6 | J24: 200000 | K24: 0.2 | L24: =I24*K24 -> 611703.12 | M24: =J24+L24 -> 811703.12 | N24: =F24+G24+H24+M24 -> 1071365.5 | O24: =E24-N24 -> 2246812.5 | P24: =IF(O24<300000,0.07*O24,21000) -> 21000 | Q24: =IF((O24-300000)<0,0,IF((O24-300000)<300000,0.11*(O24-300000),33000)) -> 33000 | R24: =IF((O24-600000)<0,0,IF((O24-600000)<500000,0.15*(O24-600000),75000)) -> 75000 | S24: =IF((O24-1100000)<0,0,IF((O24-1100000)<500000,0.19*(O24-1100000),95000)) -> 95000 | T24: =IF((O24-1600000)<0,0,IF((O24-1600000)<1600000,0.21*(O24-1600000),336000)) -> 135830.62 | V24: =P24+Q24+R24+S24+T24+U24 -> 359830.62 | W24: 12 | X24: =V24/W24 -> 29985.885 | Z24: =X24 -> 29985.885 | AA24: 23036.012 | AB24: =Z24-AA24 -> 6949.8727
A25: 22 | B25: RASHEEDAT DAIBU | C25: 176514.83 | D25: 12 | E25: =C25*D25 -> 2118178 | G25: 259662.4 | I25: =E25-F25-G25-H25 -> 1858515.6 | J25: 200000 | K25: 0.2 | L25: =I25*K25 -> 371703.12 | M25: =J25+L25 -> 571703.12 | N25: =F25+G25+H25+M25 -> 831365.52 | O25: =E25-N25 -> 1286812.5 | P25: =IF(O25<300000,0.07*O25,21000) -> 21000 | Q25: =IF((O25-300000)<0,0,IF((O25-300000)<300000,0.11*(O25-300000),33000)) -> 33000 | R25: =IF((O25-600000)<0,0,IF((O25-600000)<500000,0.15*(O25-600000),75000)) -> 75000 | S25: =IF((O25-1100000)<0,0,IF((O25-1100000)<500000,0.19*(O25-1100000),95000)) -> 35494.371 | T25: =IF((O25-1600000)<0,0,IF((O25-1600000)<1600000,0.21*(O25-1600000),336000)) -> 0 | V25: =P25+Q25+R25+S25+T25+U25 -> 164494.37 | W25: 12 | X25: =V25/W25 -> 13707.864 | Z25: =X25 -> 13707.864 | AA25: 23036.012 | AB25: =Z25-AA25 -> -9328.1481
A26: 23 | B26: ELIZABETH OGECHUKWU ONYEAKU | C26: 165240.83 | D26: 12 | E26: =C26*D26 -> 1982890 | G26: 259662.4 | I26: =E26-F26-G26-H26 -> 1723227.6 | J26: 200000 | K26: 0.2 | L26: =I26*K26 -> 344645.52 | M26: =J26+L26 -> 544645.52 | N26: =F26+G26+H26+M26 -> 804307.92 | O26: =E26-N26 -> 1178582.1 | P26: =IF(O26<300000,0.07*O26,21000) -> 21000 | Q26: =IF((O26-300000)<0,0,IF((O26-300000)<300000,0.11*(O26-300000),33000)) -> 33000 | R26: =IF((O26-600000)<0,0,IF((O26-600000)<500000,0.15*(O26-600000),75000)) -> 75000 | S26: =IF((O26-1100000)<0,0,IF((O26-1100000)<500000,0.19*(O26-1100000),95000)) -> 14930.595 | T26: =IF((O26-1600000)<0,0,IF((O26-1600000)<1600000,0.21*(O26-1600000),336000)) -> 0 | V26: =P26+Q26+R26+S26+T26+U26 -> 143930.6 | W26: 12 | X26: =V26/W26 -> 11994.216 | Z26: =X26 -> 11994.216 | AA26: 29756.012 | AB26: =Z26-AA26 -> -17761.796
A27: 24 | B27: VICTOR ASUKWO | C27: 165240.83 | D27: 12 | E27: =C27*D27 -> 1982890 | G27: 252638.72 | I27: =E27-F27-G27-H27 -> 1730251.3 | J27: 200000 | K27: 0.2 | L27: =I27*K27 -> 346050.26 | M27: =J27+L27 -> 546050.26 | N27: =F27+G27+H27+M27 -> 798688.98 | O27: =E27-N27 -> 1184201 | P27: =IF(O27<300000,0.07*O27,21000) -> 21000 | Q27: =IF((O27-300000)<0,0,IF((O27-300000)<300000,0.11*(O27-300000),33000)) -> 33000 | R27: =IF((O27-600000)<0,0,IF((O27-600000)<500000,0.15*(O27-600000),75000)) -> 75000 | S27: =IF((O27-1100000)<0,0,IF((O27-1100000)<500000,0.19*(O27-1100000),95000)) -> 15998.195 | T27: =IF((O27-1600000)<0,0,IF((O27-1600000)<1600000,0.21*(O27-1600000),336000)) -> 0 | V27: =P27+Q27+R27+S27+T27+U27 -> 144998.19 | W27: 12 | X27: =V27/W27 -> 12083.183 | Z27: =X27 -> 12083.183 | AA27: 22338.483 | AB27: =Z27-AA27 -> -10255.3
A28: 25 | B28: NNANDI LIVINUS ATURE | C28: 185240.83 | D28: 12 | E28: =C28*D28 -> 2222890 | G28: 245615.04 | I28: =E28-F28-G28-H28 -> 1977275 | J28: 200000 | K28: 0.2 | L28: =I28*K28 -> 395454.99 | M28: =J28+L28 -> 595454.99 | N28: =F28+G28+H28+M28 -> 841070.03 | O28: =E28-N28 -> 1381820 | P28: =IF(O28<300000,0.07*O28,21000) -> 21000 | Q28: =IF((O28-300000)<0,0,IF((O28-300000)<300000,0.11*(O28-300000),33000)) -> 33000 | R28: =IF((O28-600000)<0,0,IF((O28-600000)<500000,0.15*(O28-600000),75000)) -> 75000 | S28: =IF((O28-1100000)<0,0,IF((O28-1100000)<500000,0.19*(O28-1100000),95000)) -> 53545.794 | T28: =IF((O28-1600000)<0,0,IF((O28-1600000)<1600000,0.21*(O28-1600000),336000)) -> 0 | V28: =P28+Q28+R28+S28+T28+U28 -> 182545.79 | W28: 12 | X28: =V28/W28 -> 15212.149 | Z28: =X28 -> 15212.149 | AA28: 21640.953 | AB28: =Z28-AA28 -> -6428.8034
A29: 26 | B29: ABDULRAHMAN A SULAIMAN | C29: 161582.67 | D29: 12 | E29: =C29*D29 -> 1938992 | G29: 245615.04 | I29: =E29-F29-G29-H29 -> 1693377 | J29: 200000 | K29: 0.2 | L29: =I29*K29 -> 338675.39 | M29: =J29+L29 -> 538675.39 | N29: =F29+G29+H29+M29 -> 784290.43 | O29: =E29-N29 -> 1154701.6 | P29: =IF(O29<300000,0.07*O29,21000) -> 21000 | Q29: =IF((O29-300000)<0,0,IF((O29-300000)<300000,0.11*(O29-300000),33000)) -> 33000 | R29: =IF((O29-600000)<0,0,IF((O29-600000)<500000,0.15*(O29-600000),75000)) -> 75000 | S29: =IF((O29-1100000)<0,0,IF((O29-1100000)<500000,0.19*(O29-1100000),95000)) -> 10393.298 | T29: =IF((O29-1600000)<0,0,IF((O29-1600000)<1600000,0.21*(O29-1600000),336000)) -> 0 | V29: =P29+Q29+R29+S29+T29+U29 -> 139393.3 | W29: 12 | X29: =V29/W29 -> 11616.108 | Z29: =X29 -> 11616.108 | AA29: 21640.953 | AB29: =Z29-AA29 -> -10024.845
A30: 27 | B30: DARE SHEU MAGBON | C30: 157924.5 | D30: 12 | E30: =C30*D30 -> 1895094 | G30: 259662.4 | I30: =E30-F30-G30-H30 -> 1635431.6 | J30: 200000 | K30: 0.2 | L30: =I30*K30 -> 327086.32 | M30: =J30+L30 -> 527086.32 | N30: =F30+G30+H30+M30 -> 786748.72 | O30: =E30-N30 -> 1108345.3 | P30: =IF(O30<300000,0.07*O30,21000) -> 21000 | Q30: =IF((O30-300000)<0,0,IF((O30-300000)<300000,0.11*(O30-300000),33000)) -> 33000 | R30: =IF((O30-600000)<0,0,IF((O30-600000)<500000,0.15*(O30-600000),75000)) -> 75000 | S30: =IF((O30-1100000)<0,0,IF((O30-1100000)<500000,0.19*(O30-1100000),95000)) -> 1585.6032 | T30: =IF((O30-1600000)<0,0,IF((O30-1600000)<1600000,0.21*(O30-1600000),336000)) -> 0 | V30: =P30+Q30+R30+S30+T30+U30 -> 130585.6 | W30: 12 | X30: =V30/W30 -> 10882.134 | Z30: =X30 -> 10882.134 | AA30: 22338.483 | AB30: =Z30-AA30 -> -11456.349
A31: 28 | B31: ABUBAKAR SULAIMAN SODEEQ | C31: 157924.5 | D31: 12 | E31: =C31*D31 -> 1895094 | G31: 221406.64 | I31: =E31-F31-G31-H31 -> 1673687.4 | J31: 200000 | K31: 0.2 | L31: =I31*K31 -> 334737.47 | M31: =J31+L31 -> 534737.47 | N31: =F31+G31+H31+M31 -> 756144.11 | O31: =E31-N31 -> 1138949.9 | P31: =IF(O31<300000,0.07*O31,21000) -> 21000 | Q31: =IF((O31-300000)<0,0,IF((O31-300000)<300000,0.11*(O31-300000),33000)) -> 33000 | R31: =IF((O31-600000)<0,0,IF((O31-600000)<500000,0.15*(O31-600000),75000)) -> 75000 | S31: =IF((O31-1100000)<0,0,IF((O31-1100000)<500000,0.19*(O31-1100000),95000)) -> 7400.4787 | T31: =IF((O31-1600000)<0,0,IF((O31-1600000)<1600000,0.21*(O31-1600000),336000)) -> 0 | V31: =P31+Q31+R31+S31+T31+U31 -> 136400.48 | W31: 12 | X31: =V31/W31 -> 11366.707 | Z31: =X31 -> 11366.707 | AA31: 17572.885 | AB31: =Z31-AA31 -> -6206.1784
A32: 29 | B32: JIMOH ADEBAYO ZAKA | C32: 165240.83 | D32: 12 | E32: =C32*D32 -> 1982890 | G32: =17956.78*12 -> 215481.36 | I32: =E32-F32-G32-H32 -> 1767408.6 | J32: 200000 | K32: 0.2 | L32: =I32*K32 -> 353481.73 | M32: =J32+L32 -> 553481.73 | N32: =F32+G32+H32+M32 -> 768963.09 | O32: =E32-N32 -> 1213926.9 | P32: =IF(O32<300000,0.07*O32,21000) -> 21000 | Q32: =IF((O32-300000)<0,0,IF((O32-300000)<300000,0.11*(O32-300000),33000)) -> 33000 | R32: =IF((O32-600000)<0,0,IF((O32-600000)<500000,0.15*(O32-600000),75000)) -> 75000 | S32: =IF((O32-1100000)<0,0,IF((O32-1100000)<500000,0.19*(O32-1100000),95000)) -> 21646.113 | T32: =IF((O32-1600000)<0,0,IF((O32-1600000)<1600000,0.21*(O32-1600000),336000)) -> 0 | V32: =P32+Q32+R32+S32+T32+U32 -> 150646.11 | W32: 12 | X32: =V32/W32 -> 12553.843 | Z32: =X32 -> 12553.843 | AA32: 16512.682 | AB32: =Z32-AA32 -> -3958.8394
B33: ABDULMUSHIN TAWFIQ LADAN | C33: 157924.5 | D33: 12 | E33: =C33*D33 -> 1895094 | G33: =17956.78*12 -> 215481.36 | I33: =E33-F33-G33-H33 -> 1679612.6 | J33: 200000 | K33: 0.2 | L33: =I33*K33 -> 335922.53 | M33: =J33+L33 -> 535922.53 | N33: =F33+G33+H33+M33 -> 751403.89 | O33: =E33-N33 -> 1143690.1 | P33: =IF(O33<300000,0.07*O33,21000) -> 21000 | Q33: =IF((O33-300000)<0,0,IF((O33-300000)<300000,0.11*(O33-300000),33000)) -> 33000 | R33: =IF((O33-600000)<0,0,IF((O33-600000)<500000,0.15*(O33-600000),75000)) -> 75000 | S33: =IF((O33-1100000)<0,0,IF((O33-1100000)<500000,0.19*(O33-1100000),95000)) -> 8301.1213 | T33: =IF((O33-1600000)<0,0,IF((O33-1600000)<1600000,0.21*(O33-1600000),336000)) -> 0 | V33: =P33+Q33+R33+S33+T33+U33 -> 137301.12 | W33: 12 | X33: =V33/W33 -> 11441.76 | Z33: =X33 -> 11441.76
B34: MOHAMMED BELLO | C34: 157924.5 | D34: 12 | E34: =C34*D34 -> 1895094 | G34: =17956.78*12 -> 215481.36 | I34: =E34-F34-G34-H34 -> 1679612.6 | J34: 200000 | K34: 0.2 | L34: =I34*K34 -> 335922.53 | M34: =J34+L34 -> 535922.53 | N34: =F34+G34+H34+M34 -> 751403.89 | O34: =E34-N34 -> 1143690.1 | P34: =IF(O34<300000,0.07*O34,21000) -> 21000 | Q34: =IF((O34-300000)<0,0,IF((O34-300000)<300000,0.11*(O34-300000),33000)) -> 33000 | R34: =IF((O34-600000)<0,0,IF((O34-600000)<500000,0.15*(O34-600000),75000)) -> 75000 | S34: =IF((O34-1100000)<0,0,IF((O34-1100000)<500000,0.19*(O34-1100000),95000)) -> 8301.1213 | T34: =IF((O34-1600000)<0,0,IF((O34-1600000)<1600000,0.21*(O34-1600000),336000)) -> 0 | V34: =P34+Q34+R34+S34+T34+U34 -> 137301.12 | W34: 12 | X34: =V34/W34 -> 11441.76 | Z34: =X34 -> 11441.76
A35: 31 | B35: HARUNA JIBRIL AMEH | C35: 137229.88 | D35: 12 | E35: =C35*D35 -> 1646758.5 | G35: =17956.78*12 -> 215481.36 | I35: =E35-F35-G35-H35 -> 1431277.1 | J35: 200000 | K35: 0.2 | L35: =I35*K35 -> 286255.43 | M35: =J35+L35 -> 486255.43 | N35: =F35+G35+H35+M35 -> 701736.79 | O35: =E35-N35 -> 945021.71 | P35: =IF(O35<300000,0.07*O35,21000) -> 21000 | Q35: =IF((O35-300000)<0,0,IF((O35-300000)<300000,0.11*(O35-300000),33000)) -> 33000 | R35: =IF((O35-600000)<0,0,IF((O35-600000)<500000,0.15*(O35-600000),75000)) -> 51753.257 | S35: =IF((O35-1100000)<0,0,IF((O35-1100000)<500000,0.19*(O35-1100000),95000)) -> 0 | T35: =IF((O35-1600000)<0,0,IF((O35-1600000)<1600000,0.21*(O35-1600000),336000)) -> 0 | V35: =P35+Q35+R35+S35+T35+U35 -> 105753.26 | W35: 12 | X35: =V35/W35 -> 8812.7714 | Z35: =X35 -> 8812.7714
A36: 32 | B36: RAMATU IBRAHIM ABDULRAHEEM | C36: 134143.79 | D36: 12 | E36: =C36*D36 -> 1609725.5 | G36: =17956.78*12 -> 215481.36 | I36: =E36-F36-G36-H36 -> 1394244.1 | J36: 200000 | K36: 0.2 | L36: =I36*K36 -> 278848.83 | M36: =J36+L36 -> 478848.83 | N36: =F36+G36+H36+M36 -> 694330.19 | O36: =E36-N36 -> 915395.31 | P36: =IF(O36<300000,0.07*O36,21000) -> 21000 | Q36: =IF((O36-300000)<0,0,IF((O36-300000)<300000,0.11*(O36-300000),33000)) -> 33000 | R36: =IF((O36-600000)<0,0,IF((O36-600000)<500000,0.15*(O36-600000),75000)) -> 47309.297 | S36: =IF((O36-1100000)<0,0,IF((O36-1100000)<500000,0.19*(O36-1100000),95000)) -> 0 | T36: =IF((O36-1600000)<0,0,IF((O36-1600000)<1600000,0.21*(O36-1600000),336000)) -> 0 | V36: =P36+Q36+R36+S36+T36+U36 -> 101309.3 | W36: 12 | X36: =V36/W36 -> 8442.4414 | Z36: =X36 -> 8442.4414
B39: OSANAIYE DAVID AKINYEMI | C39: 767860 | D39: 12 | E39: =C39*D39 -> 9214320 | G39: 1378291.2 | I39: =E39-F39-G39-H39 -> 7836028.8 | J39: 200000 | K39: 0.2 | L39: =I39*K39 -> 1567205.8 | M39: =J39+L39 -> 1767205.8 | N39: =F39+G39+H39+M39 -> 3145497 | O39: =E39-N39 -> 6068823 | P39: =IF(O39<300000,0.07*O39,21000) -> 21000 | Q39: =IF((O39-300000)<0,0,IF((O39-300000)<300000,0.11*(O39-300000),33000)) -> 33000 | R39: =IF((O39-600000)<0,0,IF((O39-600000)<500000,0.15*(O39-600000),75000)) -> 75000 | S39: =IF((O39-1100000)<0,0,IF((O39-1100000)<500000,0.19*(O39-1100000),95000)) -> 95000 | T39: =IF((O39-1600000)<0,0,IF((O39-1600000)<1600000,0.21*(O39-1600000),336000)) -> 336000 | U39: =24%*(O39-3200000) -> 688517.53 | V39: =P39+Q39+R39+S39+T39+U39 -> 1248517.5 | W39: 12 | X39: =V39/W39 -> 104043.13 | Z39: =X39 -> 104043.13 | AA39: 161106.81 | AB39: =Z39-AA39 -> -57063.679
B40: JAMILA ABDUL | C40: 176514.83 | D40: 12 | E40: =C40*D40 -> 2118178 | G40: 281308.48 | I40: =E40-F40-G40-H40 -> 1836869.5 | J40: 200000 | K40: 0.2 | L40: =I40*K40 -> 367373.9 | M40: =J40+L40 -> 567373.9 | N40: =F40+G40+H40+M40 -> 848682.38 | O40: =E40-N40 -> 1269495.6 | P40: =IF(O40<300000,0.07*O40,21000) -> 21000 | Q40: =IF((O40-300000)<0,0,IF((O40-300000)<300000,0.11*(O40-300000),33000)) -> 33000 | R40: =IF((O40-600000)<0,0,IF((O40-600000)<500000,0.15*(O40-600000),75000)) -> 75000 | S40: =IF((O40-1100000)<0,0,IF((O40-1100000)<500000,0.19*(O40-1100000),95000)) -> 32204.167 | T40: =IF((O40-1600000)<0,0,IF((O40-1600000)<1600000,0.21*(O40-1600000),336000)) -> 0 | V40: =P40+Q40+R40+S40+T40+U40 -> 161204.17 | W40: 12 | X40: =V40/W40 -> 13433.681 | Z40: =X40 -> 13433.681 | AA40: 17042.714 | AB40: =Z40-AA40 -> -3609.0333
A41: 33 | B41: IJEOMA EWELUKWA | C41: 180482.79 | D41: 12 | E41: =C41*D41 -> 2165793.5 | G41: 288926.96 | I41: =E41-F41-G41-H41 -> 1876866.5 | J41: 200000 | K41: 0.2 | L41: =I41*K41 -> 375373.31 | M41: =J41+L41 -> 575373.31 | N41: =F41+G41+H41+M41 -> 864300.27 | O41: =E41-N41 -> 1301493.2 | P41: =IF(O41<300000,0.07*O41,21000) -> 21000 | Q41: =IF((O41-300000)<0,0,IF((O41-300000)<300000,0.11*(O41-300000),33000)) -> 33000 | R41: =IF((O41-600000)<0,0,IF((O41-600000)<500000,0.15*(O41-600000),75000)) -> 75000 | S41: =IF((O41-1100000)<0,0,IF((O41-1100000)<500000,0.19*(O41-1100000),95000)) -> 38283.714 | T41: =IF((O41-1600000)<0,0,IF((O41-1600000)<1600000,0.21*(O41-1600000),336000)) -> 0 | V41: =P41+Q41+R41+S41+T41+U41 -> 167283.71 | W41: 12 | X41: =V41/W41 -> 13940.31 | Z41: =X41 -> 13940.31 | AA41: 26339.078 | AB41: =Z41-AA41 -> -12398.769
A42: 33 | B42: YUSUF YUSUF DAYYABU | C42: 157924.5 | D42: 12 | E42: =C42*D42 -> 1895094 | G42: 288926.96 | I42: =E42-F42-G42-H42 -> 1606167 | J42: 200000 | K42: 0.2 | L42: =I42*K42 -> 321233.41 | M42: =J42+L42 -> 521233.41 | N42: =F42+G42+H42+M42 -> 810160.37 | O42: =E42-N42 -> 1084933.6 | P42: =IF(O42<300000,0.07*O42,21000) -> 21000 | Q42: =IF((O42-300000)<0,0,IF((O42-300000)<300000,0.11*(O42-300000),33000)) -> 33000 | R42: =IF((O42-600000)<0,0,IF((O42-600000)<500000,0.15*(O42-600000),75000)) -> 72740.045 | S42: =IF((O42-1100000)<0,0,IF((O42-1100000)<500000,0.19*(O42-1100000),95000)) -> 0 | T42: =IF((O42-1600000)<0,0,IF((O42-1600000)<1600000,0.21*(O42-1600000),336000)) -> 0 | V42: =P42+Q42+R42+S42+T42+U42 -> 126740.04 | W42: 12 | X42: =V42/W42 -> 10561.67 | Z42: =X42 -> 10561.67 | AA42: 26339.078 | AB42: =Z42-AA42 -> -15777.408
B44: LEG. SUPPORT SEVICES
A45: 35 | B45: PROF. EDOBA BRIGHT OMOREGBE | C45: 1635720 | D45: 12 | E45: =C45*D45 -> 19628640 | G45: 1378291.2 | I45: =E45-F45-G45-H45 -> 18250349 | J45: 200000 | K45: 0.2 | L45: =I45*K45 -> 3650069.8 | M45: =J45+L45 -> 3850069.8 | N45: =F45+G45+H45+M45 -> 5228361 | O45: =E45-N45 -> 14400279 | P45: =IF(O45<300000,0.07*O45,21000) -> 21000 | Q45: =IF((O45-300000)<0,0,IF((O45-300000)<300000,0.11*(O45-300000),33000)) -> 33000 | R45: =IF((O45-600000)<0,0,IF((O45-600000)<500000,0.15*(O45-600000),75000)) -> 75000 | S45: =IF((O45-1100000)<0,0,IF((O45-1100000)<500000,0.19*(O45-1100000),95000)) -> 95000 | T45: =IF((O45-1600000)<0,0,IF((O45-1600000)<1600000,0.21*(O45-1600000),336000)) -> 336000 | U45: =0.24*(O45-3200000) -> 2688067 | V45: =P45+Q45+R45+S45+T45+U45 -> 3248067 | W45: 12 | X45: =V45/W45 -> 270672.25 | Z45: =X45 -> 270672.25 | AA45: 180306.81 | AB45: =Z45-AA45 -> 90365.441
A46: 36 | B46: DR CLINTON JAJA | C46: 780675.58 | D46: 12 | E46: =C46*D46 -> 9368107 | G46: 595848.56 | I46: =E46-F46-G46-H46 -> 8772258.4 | J46: 200000 | K46: 0.2 | L46: =I46*K46 -> 1754451.7 | M46: =J46+L46 -> 1954451.7 | N46: =F46+G46+H46+M46 -> 2550300.2 | O46: =E46-N46 -> 6817806.8 | P46: =IF(O46<300000,0.07*O46,21000) -> 21000 | Q46: =IF((O46-300000)<0,0,IF((O46-300000)<300000,0.11*(O46-300000),33000)) -> 33000 | R46: =IF((O46-600000)<0,0,IF((O46-600000)<500000,0.15*(O46-600000),75000)) -> 75000 | S46: =IF((O46-1100000)<0,0,IF((O46-1100000)<500000,0.19*(O46-1100000),95000)) -> 95000 | T46: =IF((O46-1600000)<0,0,IF((O46-1600000)<1600000,0.21*(O46-1600000),336000)) -> 336000 | U46: =24%*(O46-3200000) -> 868273.62 | V46: =P46+Q46+R46+S46+T46+U46 -> 1428273.6 | W46: 12 | X46: =V46/W46 -> 119022.8 | Z46: =X46 -> 119022.8 | AA46: 79956.939 | AB46: =Z46-AA46 -> 39065.863
A47: 37 | B47: BETHEL UZOMA IHUGBA | C47: 919203.58 | D47: 12 | E47: =C47*D47 -> 11030443 | G47: 709635.44 | I47: =E47-F47-G47-H47 -> 10320808 | J47: 200000 | K47: 0.2 | L47: =I47*K47 -> 2064161.5 | M47: =J47+L47 -> 2264161.5 | N47: =F47+G47+H47+M47 -> 2973797 | O47: =E47-N47 -> 8056646 | P47: =IF(O47<300000,0.07*O47,21000) -> 21000 | Q47: =IF((O47-300000)<0,0,IF((O47-300000)<300000,0.11*(O47-300000),33000)) -> 33000 | R47: =IF((O47-600000)<0,0,IF((O47-600000)<500000,0.15*(O47-600000),75000)) -> 75000 | S47: =IF((O47-1100000)<0,0,IF((O47-1100000)<500000,0.19*(O47-1100000),95000)) -> 95000 | T47: =IF((O47-1600000)<0,0,IF((O47-1600000)<1600000,0.21*(O47-1600000),336000)) -> 336000 | U47: =24%*(O47-3200000) -> 1165595.1 | V47: =P47+Q47+R47+S47+T47+U47 -> 1725595.1 | W47: 12 | X47: =V47/W47 -> 143799.59 | Z47: =X47 -> 143799.59 | AA47: 97273.514 | AB47: =Z47-AA47 -> 46526.074
A48: 38 | B48: OGUCHE SAMUEL | C48: 780675.58 | D48: 12 | E48: =C48*D48 -> 9368107 | G48: 595848.56 | I48: =E48-F48-G48-H48 -> 8772258.4 | J48: 200000 | K48: 0.2 | L48: =I48*K48 -> 1754451.7 | M48: =J48+L48 -> 1954451.7 | N48: =F48+G48+H48+M48 -> 2550300.2 | O48: =E48-N48 -> 6817806.8 | P48: =IF(O48<300000,0.07*O48,21000) -> 21000 | Q48: =IF((O48-300000)<0,0,IF((O48-300000)<300000,0.11*(O48-300000),33000)) -> 33000 | R48: =IF((O48-600000)<0,0,IF((O48-600000)<500000,0.15*(O48-600000),75000)) -> 75000 | S48: =IF((O48-1100000)<0,0,IF((O48-1100000)<500000,0.19*(O48-1100000),95000)) -> 95000 | T48: =IF((O48-1600000)<0,0,IF((O48-1600000)<1600000,0.21*(O48-1600000),336000)) -> 336000 | U48: =24%*(O48-3200000) -> 868273.62 | V48: =P48+Q48+R48+S48+T48+U48 -> 1428273.6 | W48: 12 | X48: =V48/W48 -> 119022.8 | Z48: =X48 -> 119022.8 | AA48: 79956.939 | AB48: =Z48-AA48 -> 39065.863
A49: 39 | B49: IBRAHIM USMAN | C49: 780675.58 | D49: 12 | E49: =C49*D49 -> 9368107 | F49: ='[6]JANUARY 2024'!$V$47*12 -> 10052.25 | G49: 595848.56 | I49: =E49-F49-G49-H49 -> 8762206.2 | J49: 200000 | K49: 0.2 | L49: =I49*K49 -> 1752441.2 | M49: =J49+L49 -> 1952441.2 | N49: =F49+G49+H49+M49 -> 2558342 | O49: =E49-N49 -> 6809765 | P49: =IF(O49<300000,0.07*O49,21000) -> 21000 | Q49: =IF((O49-300000)<0,0,IF((O49-300000)<300000,0.11*(O49-300000),33000)) -> 33000 | R49: =IF((O49-600000)<0,0,IF((O49-600000)<500000,0.15*(O49-600000),75000)) -> 75000 | S49: =IF((O49-1100000)<0,0,IF((O49-1100000)<500000,0.19*(O49-1100000),95000)) -> 95000 | T49: =IF((O49-1600000)<0,0,IF((O49-1600000)<1600000,0.21*(O49-1600000),336000)) -> 336000 | U49: =24%*(O49-3200000) -> 866343.59 | V49: =P49+Q49+R49+S49+T49+U49 -> 1426343.6 | W49: 12 | X49: =V49/W49 -> 118861.97 | Z49: =X49 -> 118861.97 | AA49: 79796.103 | AB49: =Z49-AA49 -> 39065.863
A50: 40 | B50: DR MOHAMMED O. AMALI | C50: 742118.08 | D50: 12 | E50: =C50*D50 -> 8905417 | G50: 558833.36 | I50: =E50-F50-G50-H50 -> 8346583.6 | J50: 200000 | K50: 0.2 | L50: =I50*K50 -> 1669316.7 | M50: =J50+L50 -> 1869316.7 | N50: =F50+G50+H50+M50 -> 2428150.1 | O50: =E50-N50 -> 6477266.9 | P50: =IF(O50<300000,0.07*O50,21000) -> 21000 | Q50: =IF((O50-300000)<0,0,IF((O50-300000)<300000,0.11*(O50-300000),33000)) -> 33000 | R50: =IF((O50-600000)<0,0,IF((O50-600000)<500000,0.15*(O50-600000),75000)) -> 75000 | S50: =IF((O50-1100000)<0,0,IF((O50-1100000)<500000,0.19*(O50-1100000),95000)) -> 95000 | T50: =IF((O50-1600000)<0,0,IF((O50-1600000)<1600000,0.21*(O50-1600000),336000)) -> 336000 | U50: =24%*(O50-3200000) -> 786544.06 | V50: =P50+Q50+R50+S50+T50+U50 -> 1346544.1 | W50: 12 | X50: =V50/W50 -> 112212 | Z50: =X50 -> 112212 | AA50: 75572.916 | AB50: =Z50-AA50 -> 36639.089
A51: 41 | B51: YAHAYA SHAMSU | C51: 610498 | D51: 12 | E51: =C51*D51 -> 7325976 | G51: 451678.08 | I51: =E51-F51-G51-H51 -> 6874297.9 | J51: 200000 | K51: 0.2 | L51: =I51*K51 -> 1374859.6 | M51: =J51+L51 -> 1574859.6 | N51: =F51+G51+H51+M51 -> 2026537.7 | O51: =E51-N51 -> 5299438.3 | P51: =IF(O51<300000,0.07*O51,21000) -> 21000 | Q51: =IF((O51-300000)<0,0,IF((O51-300000)<300000,0.11*(O51-300000),33000)) -> 33000 | R51: =IF((O51-600000)<0,0,IF((O51-600000)<500000,0.15*(O51-600000),75000)) -> 75000 | S51: =IF((O51-1100000)<0,0,IF((O51-1100000)<500000,0.19*(O51-1100000),95000)) -> 95000 | T51: =IF((O51-1600000)<0,0,IF((O51-1600000)<1600000,0.21*(O51-1600000),336000)) -> 336000 | U51: =24%*(O51-3200000) -> 503865.2 | V51: =P51+Q51+R51+S51+T51+U51 -> 1063865.2 | W51: 12 | X51: =V51/W51 -> 88655.433 | Z51: =X51 -> 88655.433 | AA51: 58026.609 | AB51: =Z51-AA51 -> 30628.824
A52: 42 | B52: BILKIS S. LAWAL-GAMBARI | C52: 400965.58 | D52: 12 | E52: =C52*D52 -> 4811587 | G52: 288926.96 | I52: =E52-F52-G52-H52 -> 4522660 | J52: 200000 | K52: 0.2 | L52: =I52*K52 -> 904532.01 | M52: =J52+L52 -> 1104532 | N52: =F52+G52+H52+M52 -> 1393459 | O52: =E52-N52 -> 3418128 | P52: =IF(O52<300000,0.07*O52,21000) -> 21000 | Q52: =IF((O52-300000)<0,0,IF((O52-300000)<300000,0.11*(O52-300000),33000)) -> 33000 | R52: =IF((O52-600000)<0,0,IF((O52-600000)<500000,0.15*(O52-600000),75000)) -> 75000 | S52: =IF((O52-1100000)<0,0,IF((O52-1100000)<500000,0.19*(O52-1100000),95000)) -> 95000 | T52: =IF((O52-1600000)<0,0,IF((O52-1600000)<1600000,0.21*(O52-1600000),336000)) -> 336000 | U52: =24%*(O52-3200000) -> 52350.728 | V52: =P52+Q52+R52+S52+T52+U52 -> 612350.73 | W52: 12 | X52: =V52/W52 -> 51029.227 | Z52: =X52 -> 51029.227 | AA52: 33059.078 | AB52: =Z52-AA52 -> 17970.149
A53: 43 | B53: ZAINAB AKINDE | C53: 363165.33 | D53: 12 | E53: =C53*D53 -> 4357984 | G53: 252638.72 | I53: =E53-F53-G53-H53 -> 4105345.3 | J53: 200000 | K53: 0.2 | L53: =I53*K53 -> 821069.06 | M53: =J53+L53 -> 1021069.1 | N53: =F53+G53+H53+M53 -> 1273707.8 | O53: =E53-N53 -> 3084276.2 | P53: =IF(O53<300000,0.07*O53,21000) -> 21000 | Q53: =IF((O53-300000)<0,0,IF((O53-300000)<300000,0.11*(O53-300000),33000)) -> 33000 | R53: =IF((O53-600000)<0,0,IF((O53-600000)<500000,0.15*(O53-600000),75000)) -> 75000 | S53: =IF((O53-1100000)<0,0,IF((O53-1100000)<500000,0.19*(O53-1100000),95000)) -> 95000 | T53: =IF((O53-1600000)<0,0,IF((O53-1600000)<1600000,0.21*(O53-1600000),336000)) -> 311698.01 | V53: =P53+Q53+R53+S53+T53+U53 -> 535698.01 | W53: 12 | X53: =V53/W53 -> 44641.501 | Z53: =X53 -> 44641.501 | AA53: 29058.483 | AB53: =Z53-AA53 -> 15583.018
A54: 44 | B54: GUNAT NANSAK MARK | C54: 363165.33 | D54: 12 | E54: =C54*D54 -> 4357984 | G54: 252638.72 | I54: =E54-F54-G54-H54 -> 4105345.3 | J54: 200000 | K54: 0.2 | L54: =I54*K54 -> 821069.06 | M54: =J54+L54 -> 1021069.1 | N54: =F54+G54+H54+M54 -> 1273707.8 | O54: =E54-N54 -> 3084276.2 | P54: =IF(O54<300000,0.07*O54,21000) -> 21000 | Q54: =IF((O54-300000)<0,0,IF((O54-300000)<300000,0.11*(O54-300000),33000)) -> 33000 | R54: =IF((O54-600000)<0,0,IF((O54-600000)<500000,0.15*(O54-600000),75000)) -> 75000 | S54: =IF((O54-1100000)<0,0,IF((O54-1100000)<500000,0.19*(O54-1100000),95000)) -> 95000 | T54: =IF((O54-1600000)<0,0,IF((O54-1600000)<1600000,0.21*(O54-1600000),336000)) -> 311698.01 | V54: =P54+Q54+R54+S54+T54+U54 -> 535698.01 | W54: 12 | X54: =V54/W54 -> 44641.501 | Z54: =X54 -> 44641.501 | AA54: 28360.953 | AB54: =Z54-AA54 -> 16280.548
B57: LEGAL SERVICES
A58: 47 | B58: DR SHUAIBU DANWANKA | C58: 1635720 | D58: 12 | E58: =C58*D58 -> 19628640 | G58: 1378291.2 | I58: =E58-F58-G58-H58 -> 18250349 | J58: 200000 | K58: 0.2 | L58: =I58*K58 -> 3650069.8 | M58: =J58+L58 -> 3850069.8 | N58: =F58+G58+H58+M58 -> 5228361 | O58: =E58-N58 -> 14400279 | P58: =IF(O58<300000,0.07*O58,21000) -> 21000 | Q58: =IF((O58-300000)<0,0,IF((O58-300000)<300000,0.11*(O58-300000),33000)) -> 33000 | R58: =IF((O58-600000)<0,0,IF((O58-600000)<500000,0.15*(O58-600000),75000)) -> 75000 | S58: =IF((O58-1100000)<0,0,IF((O58-1100000)<500000,0.19*(O58-1100000),95000)) -> 95000 | T58: =IF((O58-1600000)<0,0,IF((O58-1600000)<1600000,0.21*(O58-1600000),336000)) -> 336000 | U58: =24%*(O58-3200000) -> 2688067 | V58: =P58+Q58+R58+S58+T58+U58 -> 3248067 | W58: 12 | X58: =V58/W58 -> 270672.25 | Z58: =X58 -> 270672.25 | AA58: 180306.81 | AB58: =Z58-AA58 -> 90365.441
A59: 48 | B59: ABDULSALAM BAKO | C59: 700675.58 | D59: 12 | E59: =C59*D59 -> 8408107 | G59: 595848.56 | I59: =E59-F59-G59-H59 -> 7812258.4 | J59: 200000 | K59: 0.2 | L59: =I59*K59 -> 1562451.7 | M59: =J59+L59 -> 1762451.7 | N59: =F59+G59+H59+M59 -> 2358300.2 | O59: =E59-N59 -> 6049806.8 | P59: =IF(O59<300000,0.07*O59,21000) -> 21000 | Q59: =IF((O59-300000)<0,0,IF((O59-300000)<300000,0.11*(O59-300000),33000)) -> 33000 | R59: =IF((O59-600000)<0,0,IF((O59-600000)<500000,0.15*(O59-600000),75000)) -> 75000 | S59: =IF((O59-1100000)<0,0,IF((O59-1100000)<500000,0.19*(O59-1100000),95000)) -> 95000 | T59: =IF((O59-1600000)<0,0,IF((O59-1600000)<1600000,0.21*(O59-1600000),336000)) -> 336000 | U59: =24%*(O59-3200000) -> 683953.62 | V59: =P59+Q59+R59+S59+T59+U59 -> 1243953.6 | W59: 12 | X59: =V59/W59 -> 103662.8 | Z59: =X59 -> 103662.8 | AA59: 64596.939 | AB59: =Z59-AA59 -> 39065.863
G60: 0
A61: 49 | B61: DEMOCRACY & GOVERNANCE | G61: 0
A62: 50 | B62: DR. ADEWALE ADEREMI | C62: 1635720 | D62: 12 | E62: =C62*D62 -> 19628640 | G62: 0 | I62: =E62-F62-G62-H62 -> 19628640 | J62: 200000 | K62: 0.2 | L62: =I62*K62 -> 3925728 | M62: =J62+L62 -> 4125728 | N62: =F62+G62+H62+M62 -> 4125728 | O62: =E62-N62 -> 15502912 | P62: =IF(O62<300000,0.07*O62,21000) -> 21000 | Q62: =IF((O62-300000)<0,0,IF((O62-300000)<300000,0.11*(O62-300000),33000)) -> 33000 | R62: =IF((O62-600000)<0,0,IF((O62-600000)<500000,0.15*(O62-600000),75000)) -> 75000 | S62: =IF((O62-1100000)<0,0,IF((O62-1100000)<500000,0.19*(O62-1100000),95000)) -> 95000 | T62: =IF((O62-1600000)<0,0,IF((O62-1600000)<1600000,0.21*(O62-1600000),336000)) -> 336000 | U62: =24%*(O62-3200000) -> 2952698.9 | V62: =P62+Q62+R62+S62+T62+U62 -> 3512698.9 | W62: 12 | X62: =V62/W62 -> 292724.91 | Z62: =X62 -> 292724.91 | AA62: 180306.81 | AB62: =Z62-AA62 -> 112418.1
A63: 51 | B63: NDANUSA MOHAMMED MANZUMA | C63: 761396.83 | D63: 12 | E63: =C63*D63 -> 9136762 | G63: =48111.7466666667*12 -> 577340.96 | I63: =E63-F63-G63-H63 -> 8559421 | J63: 200000 | K63: 0.2 | L63: =I63*K63 -> 1711884.2 | M63: =J63+L63 -> 1911884.2 | N63: =F63+G63+H63+M63 -> 2489225.2 | O63: =E63-N63 -> 6647536.8 | P63: =IF(O63<300000,0.07*O63,21000) -> 21000 | Q63: =IF((O63-300000)<0,0,IF((O63-300000)<300000,0.11*(O63-300000),33000)) -> 33000 | R63: =IF((O63-600000)<0,0,IF((O63-600000)<500000,0.15*(O63-600000),75000)) -> 75000 | S63: =IF((O63-1100000)<0,0,IF((O63-1100000)<500000,0.19*(O63-1100000),95000)) -> 95000 | T63: =IF((O63-1600000)<0,0,IF((O63-1600000)<1600000,0.21*(O63-1600000),336000)) -> 336000 | U63: =24%*(O63-3200000) -> 827408.84 | V63: =P63+Q63+R63+S63+T63+U63 -> 1387408.8 | W63: 12 | X63: =V63/W63 -> 115617.4 | Z63: =X63 -> 115617.4 | AA63: 77764.98 | AB63: =Z63-AA63 -> 37852.423
A64: 52 | B64: EJALONIBU GANIYU LAYI | C64: 582746.5 | D64: 12 | E64: =C64*D64 -> 6992958 | G64: 425036.64 | I64: =E64-F64-G64-H64 -> 6567921.4 | J64: 200000 | K64: 0.2 | L64: =I64*K64 -> 1313584.3 | M64: =J64+L64 -> 1513584.3 | N64: =F64+G64+H64+M64 -> 1938620.9 | O64: =E64-N64 -> 5054337.1 | P64: =IF(O64<300000,0.07*O64,21000) -> 21000 | Q64: =IF((O64-300000)<0,0,IF((O64-300000)<300000,0.11*(O64-300000),33000)) -> 33000 | R64: =IF((O64-600000)<0,0,IF((O64-600000)<500000,0.15*(O64-600000),75000)) -> 75000 | S64: =IF((O64-1100000)<0,0,IF((O64-1100000)<500000,0.19*(O64-1100000),95000)) -> 95000 | T64: =IF((O64-1600000)<0,0,IF((O64-1600000)<1600000,0.21*(O64-1600000),336000)) -> 336000 | U64: =24%*(O64-3200000) -> 445040.9 | V64: =P64+Q64+R64+S64+T64+U64 -> 1005040.9 | W64: 12 | X64: =V64/W64 -> 83753.408 | Z64: =X64 -> 83753.408 | AA64: 54931.249 | AB64: =Z64-AA64 -> 28822.159
A65: 53 | B65: LOHNA BONKAT JONATHAN | C65: 548915.92 | D65: 12 | E65: =C65*D65 -> 6586991 | G65: 411759.28 | I65: =E65-F65-G65-H65 -> 6175231.7 | J65: 200000 | K65: 0.2 | L65: =I65*K65 -> 1235046.3 | M65: =J65+L65 -> 1435046.3 | N65: =F65+G65+H65+M65 -> 1846805.6 | O65: =E65-N65 -> 4740185.4 | P65: =IF(O65<300000,0.07*O65,21000) -> 21000 | Q65: =IF((O65-300000)<0,0,IF((O65-300000)<300000,0.11*(O65-300000),33000)) -> 33000 | R65: =IF((O65-600000)<0,0,IF((O65-600000)<500000,0.15*(O65-600000),75000)) -> 75000 | S65: =IF((O65-1100000)<0,0,IF((O65-1100000)<500000,0.19*(O65-1100000),95000)) -> 95000 | T65: =IF((O65-1600000)<0,0,IF((O65-1600000)<1600000,0.21*(O65-1600000),336000)) -> 336000 | U65: =24%*(O65-3200000) -> 369644.49 | V65: =P65+Q65+R65+S65+T65+U65 -> 929644.49 | W65: 12 | X65: =V65/W65 -> 77470.374 | Z65: =X65 -> 77470.374 | AA65: 49548.776 | AB65: =Z65-AA65 -> 27921.598
A66: 54 | B66: YUNUSA ABDULLAHI | C66: 624373.75 | D66: 12 | E66: =C66*D66 -> 7492485 | G66: 464998.8 | I66: =E66-F66-G66-H66 -> 7027486.2 | J66: 200000 | K66: 0.2 | L66: =I66*K66 -> 1405497.2 | M66: =J66+L66 -> 1605497.2 | N66: =F66+G66+H66+M66 -> 2070496 | O66: =E66-N66 -> 5421989 | P66: =IF(O66<300000,0.07*O66,21000) -> 21000 | Q66: =IF((O66-300000)<0,0,IF((O66-300000)<300000,0.11*(O66-300000),33000)) -> 33000 | R66: =IF((O66-600000)<0,0,IF((O66-600000)<500000,0.15*(O66-600000),75000)) -> 75000 | S66: =IF((O66-1100000)<0,0,IF((O66-1100000)<500000,0.19*(O66-1100000),95000)) -> 95000 | T66: =IF((O66-1600000)<0,0,IF((O66-1600000)<1600000,0.21*(O66-1600000),336000)) -> 336000 | U66: =24%*(O66-3200000) -> 533277.35 | V66: =P66+Q66+R66+S66+T66+U66 -> 1093277.4 | W66: 12 | X66: =V66/W66 -> 91106.446 | Z66: =X66 -> 91106.446 | AA66: 46666.667 | AB66: =Z66-AA66 -> 44439.779
A67: 55 | B67: UDEFUNA NNADOZIE PATRICK | C67: 475703.83 | D67: 12 | E67: =C67*D67 -> 5708446 | G67: 351075.68 | I67: =E67-F67-G67-H67 -> 5357370.3 | J67: 200000 | K67: 0.2 | L67: =I67*K67 -> 1071474.1 | M67: =J67+L67 -> 1271474.1 | N67: =F67+G67+H67+M67 -> 1622549.7 | O67: =E67-N67 -> 4085896.3 | P67: =IF(O67<300000,0.07*O67,21000) -> 21000 | Q67: =IF((O67-300000)<0,0,IF((O67-300000)<300000,0.11*(O67-300000),33000)) -> 33000 | R67: =IF((O67-600000)<0,0,IF((O67-600000)<500000,0.15*(O67-600000),75000)) -> 75000 | S67: =IF((O67-1100000)<0,0,IF((O67-1100000)<500000,0.19*(O67-1100000),95000)) -> 95000 | T67: =IF((O67-1600000)<0,0,IF((O67-1600000)<1600000,0.21*(O67-1600000),336000)) -> 336000 | U67: =24%*(O67-3200000) -> 212615.1 | V67: =P67+Q67+R67+S67+T67+U67 -> 772615.1 | W67: 12 | X67: =V67/W67 -> 64384.592 | Z67: =X67 -> 64384.592 | AA67: 41338.951 | AB67: =Z67-AA67 -> 23045.641
A68: 56 | B68: SHAFIU YAHYA MIKAIL | C68: 475703.83 | D68: 12 | E68: =C68*D68 -> 5708446 | G68: 351075.68 | I68: =E68-F68-G68-H68 -> 5357370.3 | J68: 200000 | K68: 0.2 | L68: =I68*K68 -> 1071474.1 | M68: =J68+L68 -> 1271474.1 | N68: =F68+G68+H68+M68 -> 1622549.7 | O68: =E68-N68 -> 4085896.3 | P68: =IF(O68<300000,0.07*O68,21000) -> 21000 | Q68: =IF((O68-300000)<0,0,IF((O68-300000)<300000,0.11*(O68-300000),33000)) -> 33000 | R68: =IF((O68-600000)<0,0,IF((O68-600000)<500000,0.15*(O68-600000),75000)) -> 75000 | S68: =IF((O68-1100000)<0,0,IF((O68-1100000)<500000,0.19*(O68-1100000),95000)) -> 95000 | T68: =IF((O68-1600000)<0,0,IF((O68-1600000)<1600000,0.21*(O68-1600000),336000)) -> 336000 | U68: =24%*(O68-3200000) -> 212615.1 | V68: =P68+Q68+R68+S68+T68+U68 -> 772615.1 | W68: 12 | X68: =V68/W68 -> 64384.592 | Z68: =X68 -> 64384.592 | AA68: 41338.951 | AB68: =Z68-AA68 -> 23045.641
A69: 57 | B69: HASSAN YERIMA | C69: 475703.83 | D69: 12 | E69: =C69*D69 -> 5708446 | G69: 351075.68 | I69: =E69-F69-G69-H69 -> 5357370.3 | J69: 200000 | K69: 0.2 | L69: =I69*K69 -> 1071474.1 | M69: =J69+L69 -> 1271474.1 | N69: =F69+G69+H69+M69 -> 1622549.7 | O69: =E69-N69 -> 4085896.3 | P69: =IF(O69<300000,0.07*O69,21000) -> 21000 | Q69: =IF((O69-300000)<0,0,IF((O69-300000)<300000,0.11*(O69-300000),33000)) -> 33000 | R69: =IF((O69-600000)<0,0,IF((O69-600000)<500000,0.15*(O69-600000),75000)) -> 75000 | S69: =IF((O69-1100000)<0,0,IF((O69-1100000)<500000,0.19*(O69-1100000),95000)) -> 95000 | T69: =IF((O69-1600000)<0,0,IF((O69-1600000)<1600000,0.21*(O69-1600000),336000)) -> 336000 | U69: =24%*(O69-3200000) -> 212615.1 | V69: =P69+Q69+R69+S69+T69+U69 -> 772615.1 | W69: 12 | X69: =V69/W69 -> 64384.592 | Z69: =X69 -> 64384.592 | AA69: 41338.951 | AB69: =Z69-AA69 -> 23045.641
A70: 58 | B70: HAUWA PATE SADIQ | C70: 487895.17 | D70: 12 | E70: =C70*D70 -> 5854742 | G70: 362779.36 | I70: =E70-F70-G70-H70 -> 5491962.6 | J70: 200000 | K70: 0.2 | L70: =I70*K70 -> 1098392.5 | M70: =J70+L70 -> 1298392.5 | N70: =F70+G70+H70+M70 -> 1661171.9 | O70: =E70-N70 -> 4193570.1 | P70: =IF(O70<300000,0.07*O70,21000) -> 21000 | Q70: =IF((O70-300000)<0,0,IF((O70-300000)<300000,0.11*(O70-300000),33000)) -> 33000 | R70: =IF((O70-600000)<0,0,IF((O70-600000)<500000,0.15*(O70-600000),75000)) -> 75000 | S70: =IF((O70-1100000)<0,0,IF((O70-1100000)<500000,0.19*(O70-1100000),95000)) -> 95000 | T70: =IF((O70-1600000)<0,0,IF((O70-1600000)<1600000,0.21*(O70-1600000),336000)) -> 336000 | U70: =24%*(O70-3200000) -> 238456.83 | V70: =P70+Q70+R70+S70+T70+U70 -> 798456.83 | W70: 12 | X70: =V70/W70 -> 66538.069 | Z70: =X70 -> 66538.069 | AA70: 43368.882 | AB70: =Z70-AA70 -> 23169.186
A71: 59 | B71: KOLAPO Q. ABAYOMI | C71: 400965.58 | D71: 12 | E71: =C71*D71 -> 4811587 | G71: 288926.96 | I71: =E71-F71-G71-H71 -> 4522660 | J71: 200000 | K71: 0.2 | L71: =I71*K71 -> 904532.01 | M71: =J71+L71 -> 1104532 | N71: =F71+G71+H71+M71 -> 1393459 | O71: =E71-N71 -> 3418128 | P71: =IF(O71<300000,0.07*O71,21000) -> 21000 | Q71: =IF((O71-300000)<0,0,IF((O71-300000)<300000,0.11*(O71-300000),33000)) -> 33000 | R71: =IF((O71-600000)<0,0,IF((O71-600000)<500000,0.15*(O71-600000),75000)) -> 75000 | S71: =IF((O71-1100000)<0,0,IF((O71-1100000)<500000,0.19*(O71-1100000),95000)) -> 95000 | T71: =IF((O71-1600000)<0,0,IF((O71-1600000)<1600000,0.21*(O71-1600000),336000)) -> 336000 | U71: =24%*(O71-3200000) -> 52350.728 | V71: =P71+Q71+R71+S71+T71+U71 -> 612350.73 | W71: 12 | X71: =V71/W71 -> 51029.227 | Z71: =X71 -> 51029.227 | AA71: 33825.987 | AB71: =Z71-AA71 -> 17203.241
A72: 60
A73: 61
B74: DEPARTMENT OF STUDIES
B75: DR ASIMIYU G. ABIOLA | C75: 1635720 | D75: 12 | E75: =C75*D75 -> 19628640 | G75: 1378291.2 | I75: =E75-F75-G75-H75 -> 18250349 | J75: 200000 | K75: 0.2 | L75: =I75*K75 -> 3650069.8 | M75: =J75+L75 -> 3850069.8 | N75: =F75+G75+H75+M75 -> 5228361 | O75: =E75-N75 -> 14400279 | P75: =IF(O75<300000,0.07*O75,21000) -> 21000 | Q75: =IF((O75-300000)<0,0,IF((O75-300000)<300000,0.11*(O75-300000),33000)) -> 33000 | R75: =IF((O75-600000)<0,0,IF((O75-600000)<500000,0.15*(O75-600000),75000)) -> 75000 | S75: =IF((O75-1100000)<0,0,IF((O75-1100000)<500000,0.19*(O75-1100000),95000)) -> 95000 | T75: =IF((O75-1600000)<0,0,IF((O75-1600000)<1600000,0.21*(O75-1600000),336000)) -> 336000 | U75: =24%*(O75-3200000) -> 2688067 | V75: =P75+Q75+R75+S75+T75+U75 -> 3248067 | W75: 12 | X75: =V75/W75 -> 270672.25 | Z75: =X75 -> 270672.25 | AA75: 180306.81 | AB75: =Z75-AA75 -> 90365.441
A76: 62 | B76: USMAN WALI | C76: 761396.83 | D76: 12 | E76: =C76*D76 -> 9136762 | G76: 0 | I76: =E76-F76-G76-H76 -> 9136762 | J76: 200000 | K76: 0.2 | L76: =I76*K76 -> 1827352.4 | M76: =J76+L76 -> 2027352.4 | N76: =F76+G76+H76+M76 -> 2027352.4 | O76: =E76-N76 -> 7109409.6 | P76: =IF(O76<300000,0.07*O76,21000) -> 21000 | Q76: =IF((O76-300000)<0,0,IF((O76-300000)<300000,0.11*(O76-300000),33000)) -> 33000 | R76: =IF((O76-600000)<0,0,IF((O76-600000)<500000,0.15*(O76-600000),75000)) -> 75000 | S76: =IF((O76-1100000)<0,0,IF((O76-1100000)<500000,0.19*(O76-1100000),95000)) -> 95000 | T76: =IF((O76-1600000)<0,0,IF((O76-1600000)<1600000,0.21*(O76-1600000),336000)) -> 336000 | U76: =24%*(O76-3200000) -> 938258.3 | V76: =P76+Q76+R76+S76+T76+U76 -> 1498258.3 | W76: 12 | X76: =V76/W76 -> 124854.86 | Z76: =X76 -> 124854.86 | AA76: 77764.98 | AB76: =Z76-AA76 -> 47089.878
A77: 63 | B77: AYOBOLU OLAJIDE OLUFUNSHO | C77: =700675.583333333+80000 -> 780675.58 | D77: 12 | E77: =C77*D77 -> 9368107 | G77: 0 | I77: =E77-F77-G77-H77 -> 9368107 | J77: 200000 | K77: 0.2 | L77: =I77*K77 -> 1873621.4 | M77: =J77+L77 -> 2073621.4 | N77: =F77+G77+H77+M77 -> 2073621.4 | O77: =E77-N77 -> 7294485.6 | P77: =IF(O77<300000,0.07*O77,21000) -> 21000 | Q77: =IF((O77-300000)<0,0,IF((O77-300000)<300000,0.11*(O77-300000),33000)) -> 33000 | R77: =IF((O77-600000)<0,0,IF((O77-600000)<500000,0.15*(O77-600000),75000)) -> 75000 | S77: =IF((O77-1100000)<0,0,IF((O77-1100000)<500000,0.19*(O77-1100000),95000)) -> 95000 | T77: =IF((O77-1600000)<0,0,IF((O77-1600000)<1600000,0.21*(O77-1600000),336000)) -> 336000 | U77: =24%*(O77-3200000) -> 982676.54 | V77: =P77+Q77+R77+S77+T77+U77 -> 1542676.5 | W77: 12 | X77: =V77/W77 -> 128556.38 | Z77: =X77 -> 128556.38 | AA77: 64596.939 | AB77: =Z77-AA77 -> 63959.44
A78: 64 | B78: ANTHONY EDET | C78: 596622.25 | D78: 12 | E78: =C78*D78 -> 7159467 | F78: ='[6]JANUARY 2024'!$V$78*12 -> 8019.795 | G78: 438357.36 | I78: =E78-F78-G78-H78 -> 6713089.8 | J78: 200000 | K78: 0.2 | L78: =I78*K78 -> 1342618 | M78: =J78+L78 -> 1542618 | N78: =F78+G78+H78+M78 -> 1988995.1 | O78: =E78-N78 -> 5170471.9 | P78: =IF(O78<300000,0.07*O78,21000) -> 21000 | Q78: =IF((O78-300000)<0,0,IF((O78-300000)<300000,0.11*(O78-300000),33000)) -> 33000 | R78: =IF((O78-600000)<0,0,IF((O78-600000)<500000,0.15*(O78-600000),75000)) -> 75000 | S78: =IF((O78-1100000)<0,0,IF((O78-1100000)<500000,0.19*(O78-1100000),95000)) -> 95000 | T78: =IF((O78-1600000)<0,0,IF((O78-1600000)<1600000,0.21*(O78-1600000),336000)) -> 336000 | U78: =24%*(O78-3200000) -> 472913.25 | V78: =P78+Q78+R78+S78+T78+U78 -> 1032913.3 | W78: 12 | X78: =V78/W78 -> 86076.104 | Z78: =X78 -> 86076.104 | AA78: 56350.586 | AB78: =Z78-AA78 -> 29725.518
A79: 65 | B79: IGWE STACY | C79: 408901.5 | D79: 12 | E79: =C79*D79 -> 4906818 | G79: 296545.44 | I79: =E79-F79-G79-H79 -> 4610272.6 | J79: 200000 | K79: 0.2 | L79: =I79*K79 -> 922054.51 | M79: =J79+L79 -> 1122054.5 | N79: =F79+G79+H79+M79 -> 1418600 | O79: =E79-N79 -> 3488218 | P79: =IF(O79<300000,0.07*O79,21000) -> 21000 | Q79: =IF((O79-300000)<0,0,IF((O79-300000)<300000,0.11*(O79-300000),33000)) -> 33000 | R79: =IF((O79-600000)<0,0,IF((O79-600000)<500000,0.15*(O79-600000),75000)) -> 75000 | S79: =IF((O79-1100000)<0,0,IF((O79-1100000)<500000,0.19*(O79-1100000),95000)) -> 95000 | T79: =IF((O79-1600000)<0,0,IF((O79-1600000)<1600000,0.21*(O79-1600000),336000)) -> 336000 | U79: =0.24*(O79-3200000) -> 69172.332 | V79: =P79+Q79+R79+S79+T79+U79 -> 629172.33 | W79: 12 | X79: =V79/W79 -> 52431.028 | Z79: =X79 -> 52431.028 | AA79: 17507.549 | AB79: =Z79-AA79 -> 34923.479
B80: OLANIYAN TAIWO ABINBOLA | C80: 363165.33 | D80: 12 | E80: =C80*D80 -> 4357984 | G80: 252638.72 | I80: =E80-F80-G80-H80 -> 4105345.3 | J80: 200000 | K80: 0.2 | L80: =I80*K80 -> 821069.06 | M80: =J80+L80 -> 1021069.1 | N80: =F80+G80+H80+M80 -> 1273707.8 | O80: =E80-N80 -> 3084276.2 | P80: =IF(O80<300000,0.07*O80,21000) -> 21000 | Q80: =IF((O80-300000)<0,0,IF((O80-300000)<300000,0.11*(O80-300000),33000)) -> 33000 | R80: =IF((O80-600000)<0,0,IF((O80-600000)<500000,0.15*(O80-600000),75000)) -> 75000 | S80: =IF((O80-1100000)<0,0,IF((O80-1100000)<500000,0.19*(O80-1100000),95000)) -> 95000 | T80: =IF((O80-1600000)<0,0,IF((O80-1600000)<1600000,0.21*(O80-1600000),336000)) -> 311698.01 | V80: =P80+Q80+R80+S80+T80+U80 -> 535698.01 | W80: 12 | X80: =V80/W80 -> 44641.501 | Z80: =X80 -> 44641.501 | AA80: 29058.483 | AB80: =Z80-AA80 -> 15583.018
B81: AMINAT JUMOKE SULAIMON | C81: 324459.75 | D81: 12 | E81: =C81*D81 -> 3893517 | G81: 215481.36 | I81: =E81-F81-G81-H81 -> 3678035.6 | J81: 200000 | K81: 0.2 | L81: =I81*K81 -> 735607.13 | M81: =J81+L81 -> 935607.13 | N81: =F81+G81+H81+M81 -> 1151088.5 | O81: =E81-N81 -> 2742428.5 | P81: =IF(O81<300000,0.07*O81,21000) -> 21000 | Q81: =IF((O81-300000)<0,0,IF((O81-300000)<300000,0.11*(O81-300000),33000)) -> 33000 | R81: =IF((O81-600000)<0,0,IF((O81-600000)<500000,0.15*(O81-600000),75000)) -> 75000 | S81: =IF((O81-1100000)<0,0,IF((O81-1100000)<500000,0.19*(O81-1100000),95000)) -> 95000 | T81: =IF((O81-1600000)<0,0,IF((O81-1600000)<1600000,0.21*(O81-1600000),336000)) -> 239909.99 | V81: =P81+Q81+R81+S81+T81+U81 -> 463909.99 | W81: 12 | X81: =V81/W81 -> 38659.166 | Z81: =X81 -> 38659.166 | AA81: 24751.17 | AB81: =Z81-AA81 -> 13907.995
B82: TOTAL
A83: 66
A84: 67 | B84: ECON. DEV. & SOC. RESEARCH | AB84: difference
A85: 68 | B85: TERFA WILLIAMS ABRAHAM | C85: =880675.583333333+100000 -> 980675.58 | D85: 12 | E85: =C85*D85 -> 11768107 | G85: 595848.56 | I85: =E85-F85-G85-H85 -> 11172258 | J85: 200000 | K85: 0.2 | L85: =I85*K85 -> 2234451.7 | M85: =J85+L85 -> 2434451.7 | N85: =F85+G85+H85+M85 -> 3030300.2 | O85: =E85-N85 -> 8737806.8 | P85: =IF(O85<300000,0.07*O85,21000) -> 21000 | Q85: =IF((O85-300000)<0,0,IF((O85-300000)<300000,0.11*(O85-300000),33000)) -> 33000 | R85: =IF((O85-600000)<0,0,IF((O85-600000)<500000,0.15*(O85-600000),75000)) -> 75000 | S85: =IF((O85-1100000)<0,0,IF((O85-1100000)<500000,0.19*(O85-1100000),95000)) -> 95000 | T85: =IF((O85-1600000)<0,0,IF((O85-1600000)<1600000,0.21*(O85-1600000),336000)) -> 336000 | U85: =24%*(O85-3200000) -> 1329073.6 | V85: =P85+Q85+R85+S85+T85+U85 -> 1889073.6 | W85: 12 | X85: =V85/W85 -> 157422.8 | Z85: =X85 -> 157422.8 | AA85: 99156.939 | AB85: =Z85-AA85 -> 58265.863 | AC85: TERFA WILLIAMS ABRAHAM
A86: 69 | B86: DR AUGUSTINE C. OSIGWE | C86: 780675.58 | D86: 12 | E86: =C86*D86 -> 9368107 | F86: ='[6]JANUARY 2024'!$V$86*12 -> 10052.25 | G86: 595848.56 | I86: =E86-F86-G86-H86 -> 8762206.2 | J86: 200000 | K86: 0.2 | L86: =I86*K86 -> 1752441.2 | M86: =J86+L86 -> 1952441.2 | N86: =F86+G86+H86+M86 -> 2558342 | O86: =E86-N86 -> 6809765 | P86: =IF(O86<300000,0.07*O86,21000) -> 21000 | Q86: =IF((O86-300000)<0,0,IF((O86-300000)<300000,0.11*(O86-300000),33000)) -> 33000 | R86: =IF((O86-600000)<0,0,IF((O86-600000)<500000,0.15*(O86-600000),75000)) -> 75000 | S86: =IF((O86-1100000)<0,0,IF((O86-1100000)<500000,0.19*(O86-1100000),95000)) -> 95000 | T86: =IF((O86-1600000)<0,0,IF((O86-1600000)<1600000,0.21*(O86-1600000),336000)) -> 336000 | U86: =24%*(O86-3200000) -> 866343.59 | V86: =P86+Q86+R86+S86+T86+U86 -> 1426343.6 | W86: 12 | X86: =V86/W86 -> 118861.97 | Z86: =X86 -> 118861.97 | AA86: 98996.103 | AB86: =Z86-AA86 -> 19865.863 | AC86: DR AUGUSTINE C. OSIGWE
A87: 70 | B87: OMOJU OLUWASOLA EMMANUEL | C87: 587895.17 | D87: 12 | E87: =C87*D87 -> 7054742 | G87: 558833.36 | I87: =E87-F87-G87-H87 -> 6495908.6 | J87: 200000 | K87: 0.2 | L87: =I87*K87 -> 1299181.7 | M87: =J87+L87 -> 1499181.7 | N87: =F87+G87+H87+M87 -> 2058015.1 | O87: =E87-N87 -> 4996726.9 | P87: =IF(O87<300000,0.07*O87,21000) -> 21000 | Q87: =IF((O87-300000)<0,0,IF((O87-300000)<300000,0.11*(O87-300000),33000)) -> 33000 | R87: =IF((O87-600000)<0,0,IF((O87-600000)<500000,0.15*(O87-600000),75000)) -> 75000 | S87: =IF((O87-1100000)<0,0,IF((O87-1100000)<500000,0.19*(O87-1100000),95000)) -> 95000 | T87: =IF((O87-1600000)<0,0,IF((O87-1600000)<1600000,0.21*(O87-1600000),336000)) -> 336000 | U87: =24%*(O87-3200000) -> 431214.46 | V87: =P87+Q87+R87+S87+T87+U87 -> 991214.46 | W87: 12 | X87: =V87/W87 -> 82601.205 | Z87: =X87 -> 82601.205 | AA87: 79956.939 | AB87: =Z87-AA87 -> 2644.2658 | AC87: OMOJU OLUWASOLA EMMANUEL
A88: 71 | B88: IBE EZECHI CYRIACUS | C88: 582746.5 | D88: 12 | E88: =C88*D88 -> 6992958 | G88: 424132.72 | I88: =E88-F88-G88-H88 -> 6568825.3 | J88: 200000 | K88: 0.2 | L88: =I88*K88 -> 1313765.1 | M88: =J88+L88 -> 1513765.1 | N88: =F88+G88+H88+M88 -> 1937897.8 | O88: =E88-N88 -> 5055060.2 | P88: =IF(O88<300000,0.07*O88,21000) -> 21000 | Q88: =IF((O88-300000)<0,0,IF((O88-300000)<300000,0.11*(O88-300000),33000)) -> 33000 | R88: =IF((O88-600000)<0,0,IF((O88-600000)<500000,0.15*(O88-600000),75000)) -> 75000 | S88: =IF((O88-1100000)<0,0,IF((O88-1100000)<500000,0.19*(O88-1100000),95000)) -> 95000 | T88: =IF((O88-1600000)<0,0,IF((O88-1600000)<1600000,0.21*(O88-1600000),336000)) -> 336000 | U88: =24%*(O88-3200000) -> 445214.45 | V88: =P88+Q88+R88+S88+T88+U88 -> 1005214.5 | W88: 12 | X88: =V88/W88 -> 83767.871 | Z88: =X88 -> 83767.871 | AA88: 75574.677 | AB88: =Z88-AA88 -> 8193.1939 | AC88: IBE EZECHI CYRIACUS
A89: 72 | B89: OSIKHEN LEO IGBANOI | C89: 548915.92 | D89: 12 | E89: =C89*D89 -> 6586991 | G89: 411759.28 | I89: =E89-F89-G89-H89 -> 6175231.7 | J89: 200000 | K89: 0.2 | L89: =I89*K89 -> 1235046.3 | M89: =J89+L89 -> 1435046.3 | N89: =F89+G89+H89+M89 -> 1846805.6 | O89: =E89-N89 -> 4740185.4 | P89: =IF(O89<300000,0.07*O89,21000) -> 21000 | Q89: =IF((O89-300000)<0,0,IF((O89-300000)<300000,0.11*(O89-300000),33000)) -> 33000 | R89: =IF((O89-600000)<0,0,IF((O89-600000)<500000,0.15*(O89-600000),75000)) -> 75000 | S89: =IF((O89-1100000)<0,0,IF((O89-1100000)<500000,0.19*(O89-1100000),95000)) -> 95000 | T89: =IF((O89-1600000)<0,0,IF((O89-1600000)<1600000,0.21*(O89-1600000),336000)) -> 336000 | U89: =24%*(O89-3200000) -> 369644.49 | V89: =P89+Q89+R89+S89+T89+U89 -> 929644.49 | W89: 12 | X89: =V89/W89 -> 77470.374 | Z89: =X89 -> 77470.374 | AA89: 50985.978 | AB89: =Z89-AA89 -> 26484.397 | AC89: OSIKHEN LEO IGBANOI
A90: 73 | B90: OKUNGBOWA OSARETIN GODSPOWER | C90: 568870.75 | D90: 12 | E90: =C90*D90 -> 6826449 | G90: 411715.92 | I90: =E90-F90-G90-H90 -> 6414733.1 | J90: 200000 | K90: 0.2 | L90: =I90*K90 -> 1282946.6 | M90: =J90+L90 -> 1482946.6 | N90: =F90+G90+H90+M90 -> 1894662.5 | O90: =E90-N90 -> 4931786.5 | P90: =IF(O90<300000,0.07*O90,21000) -> 21000 | Q90: =IF((O90-300000)<0,0,IF((O90-300000)<300000,0.11*(O90-300000),33000)) -> 33000 | R90: =IF((O90-600000)<0,0,IF((O90-600000)<500000,0.15*(O90-600000),75000)) -> 75000 | S90: =IF((O90-1100000)<0,0,IF((O90-1100000)<500000,0.19*(O90-1100000),95000)) -> 95000 | T90: =IF((O90-1600000)<0,0,IF((O90-1600000)<1600000,0.21*(O90-1600000),336000)) -> 336000 | U90: =24%*(O90-3200000) -> 415628.75 | V90: =P90+Q90+R90+S90+T90+U90 -> 975628.75 | W90: 12 | X90: =V90/W90 -> 81302.396 | Z90: =X90 -> 81302.396 | AA90: 49548.776 | AB90: =Z90-AA90 -> 31753.62 | AC90: OKUNGBOWA OSARETIN GODSPOWER
A91: 74 | B91: YUSUF IBRAHIM | C91: 475703.83 | D91: 12 | E91: =C91*D91 -> 5708446 | G91: =29256.3066666667*12 -> 351075.68 | I91: =E91-F91-G91-H91 -> 5357370.3 | J91: 200000 | K91: 0.2 | L91: =I91*K91 -> 1071474.1 | M91: =J91+L91 -> 1271474.1 | N91: =F91+G91+H91+M91 -> 1622549.7 | O91: =E91-N91 -> 4085896.3 | P91: =IF(O91<300000,0.07*O91,21000) -> 21000 | Q91: =IF((O91-300000)<0,0,IF((O91-300000)<300000,0.11*(O91-300000),33000)) -> 33000 | R91: =IF((O91-600000)<0,0,IF((O91-600000)<500000,0.15*(O91-600000),75000)) -> 75000 | S91: =IF((O91-1100000)<0,0,IF((O91-1100000)<500000,0.19*(O91-1100000),95000)) -> 95000 | T91: =IF((O91-1600000)<0,0,IF((O91-1600000)<1600000,0.21*(O91-1600000),336000)) -> 336000 | U91: =24%*(O91-3200000) -> 212615.1 | V91: =P91+Q91+R91+S91+T91+U91 -> 772615.1 | W91: 12 | X91: =V91/W91 -> 64384.592 | Z91: =X91 -> 64384.592 | AA91: 53384.054 | AB91: =Z91-AA91 -> 11000.538 | AC91: YUSUF IBRAHIM
A92: 75 | B92: MUSTAPHA RAFIU AYOBANJI | C92: 510248.92 | D92: 12 | E92: =C92*D92 -> 6122987 | F92: ='[6]JANUARY 2024'!$V$92*12 -> 6922.497 | G92: 374638.96 | I92: =E92-F92-G92-H92 -> 5741425.5 | J92: 200000 | K92: 0.2 | L92: =I92*K92 -> 1148285.1 | M92: =J92+L92 -> 1348285.1 | N92: =F92+G92+H92+M92 -> 1729846.6 | O92: =E92-N92 -> 4393140.4 | P92: =IF(O92<300000,0.07*O92,21000) -> 21000 | Q92: =IF((O92-300000)<0,0,IF((O92-300000)<300000,0.11*(O92-300000),33000)) -> 33000 | R92: =IF((O92-600000)<0,0,IF((O92-600000)<500000,0.15*(O92-600000),75000)) -> 75000 | S92: =IF((O92-1100000)<0,0,IF((O92-1100000)<500000,0.19*(O92-1100000),95000)) -> 95000 | T92: =IF((O92-1600000)<0,0,IF((O92-1600000)<1600000,0.21*(O92-1600000),336000)) -> 336000 | U92: =24%*(O92-3200000) -> 286353.7 | V92: =P92+Q92+R92+S92+T92+U92 -> 846353.7 | W92: 12 | X92: =V92/W92 -> 70529.475 | Z92: =X92 -> 70529.475 | AA92: 41242.036 | AB92: =Z92-AA92 -> 29287.439 | AC92: MUSTAPHA RAFIU AYOBANJI
A93: 76 | B93: MARYAM MUSA SADA | C93: 400965.58 | D93: 12 | E93: =C93*D93 -> 4811587 | G93: 288926.96 | I93: =E93-F93-G93-H93 -> 4522660 | J93: 200000 | K93: 0.2 | L93: =I93*K93 -> 904532.01 | M93: =J93+L93 -> 1104532 | N93: =F93+G93+H93+M93 -> 1393459 | O93: =E93-N93 -> 3418128 | P93: =IF(O93<300000,0.07*O93,21000) -> 21000 | Q93: =IF((O93-300000)<0,0,IF((O93-300000)<300000,0.11*(O93-300000),33000)) -> 33000 | R93: =IF((O93-600000)<0,0,IF((O93-600000)<500000,0.15*(O93-600000),75000)) -> 75000 | S93: =IF((O93-1100000)<0,0,IF((O93-1100000)<500000,0.19*(O93-1100000),95000)) -> 95000 | T93: =IF((O93-1600000)<0,0,IF((O93-1600000)<1600000,0.21*(O93-1600000),336000)) -> 336000 | U93: =24%*(O93-3200000) -> 52350.728 | V93: =P93+Q93+R93+S93+T93+U93 -> 612350.73 | W93: 12 | X93: =V93/W93 -> 51029.227 | Z93: =X93 -> 51029.227 | AA93: 45414.456 | AB93: =Z93-AA93 -> 5614.7711 | AC93: MARYAM MUSA SADA
B94: CHARITY EZENWAJIOBI | C94: 330631.92 | D94: 12 | E94: =C94*D94 -> 3967583 | G94: 221406.64 | I94: =E94-F94-G94-H94 -> 3746176.4 | J94: 200000 | K94: 0.2 | L94: =I94*K94 -> 749235.27 | M94: =J94+L94 -> 949235.27 | N94: =F94+G94+H94+M94 -> 1170641.9 | O94: =E94-N94 -> 2796941.1 | P94: =IF(O94<300000,0.07*O94,21000) -> 21000 | Q94: =IF((O94-300000)<0,0,IF((O94-300000)<300000,0.11*(O94-300000),33000)) -> 33000 | R94: =IF((O94-600000)<0,0,IF((O94-600000)<500000,0.15*(O94-600000),75000)) -> 75000 | S94: =IF((O94-1100000)<0,0,IF((O94-1100000)<500000,0.19*(O94-1100000),95000)) -> 95000 | T94: =IF((O94-1600000)<0,0,IF((O94-1600000)<1600000,0.21*(O94-1600000),336000)) -> 251357.63 | V94: =P94+Q94+R94+S94+T94+U94 -> 475357.63 | W94: 12 | X94: =V94/W94 -> 39613.136 | Z94: =X94 -> 39613.136 | AA94: 33825.987 | AB94: =Z94-AA94 -> 5787.1491 | AC94: CHARITY EZENWAJIOBI
A97: 78 | B97: TRAINING & INT''L COOP
A98: 79 | B98: AKINSANMI ADEJOKE OLUKEMI | C98: 1452042.7 | D98: 12 | E98: =C98*D98 -> 17424512 | F98: ='[6]JANUARY 2024'!$V$98*12 -> 12795.951 | G98: =(0.08*1352042.67)*12 -> 1297961 | I98: =E98-F98-G98-H98 -> 16113755 | J98: 200000 | K98: 0.2 | L98: =I98*K98 -> 3222751 | M98: =J98+L98 -> 3422751 | N98: =F98+G98+H98+M98 -> 4733507.9 | O98: =E98-N98 -> 12691004 | P98: =IF(O98<300000,0.07*O98,21000) -> 21000 | Q98: =IF((O98-300000)<0,0,IF((O98-300000)<300000,0.11*(O98-300000),33000)) -> 33000 | R98: =IF((O98-600000)<0,0,IF((O98-600000)<500000,0.15*(O98-600000),75000)) -> 75000 | S98: =IF((O98-1100000)<0,0,IF((O98-1100000)<500000,0.19*(O98-1100000),95000)) -> 95000 | T98: =IF((O98-1600000)<0,0,IF((O98-1600000)<1600000,0.21*(O98-1600000),336000)) -> 336000 | U98: =24%*(O98-3200000) -> 2277841 | V98: =P98+Q98+R98+S98+T98+U98 -> 2837841 | W98: 12 | X98: =V98/W98 -> 236486.75 | Z98: =X98 -> 236486.75 | AA98: 82423.216 | AB98: =Z98-AA98 -> 154063.53 | AC98: AKINSANMI ADEJOKE OLUKEMI
A99: 80 | B99: MOHAMMED R. ADAMU | C99: 526622.25 | D99: 12 | E99: =C99*D99 -> 6319467 | G99: 438357.36 | I99: =E99-F99-G99-H99 -> 5881109.6 | J99: 200000 | K99: 0.2 | L99: =I99*K99 -> 1176221.9 | M99: =J99+L99 -> 1376221.9 | N99: =F99+G99+H99+M99 -> 1814579.3 | O99: =E99-N99 -> 4504887.7 | P99: =IF(O99<300000,0.07*O99,21000) -> 21000 | Q99: =IF((O99-300000)<0,0,IF((O99-300000)<300000,0.11*(O99-300000),33000)) -> 33000 | R99: =IF((O99-600000)<0,0,IF((O99-600000)<500000,0.15*(O99-600000),75000)) -> 75000 | S99: =IF((O99-1100000)<0,0,IF((O99-1100000)<500000,0.19*(O99-1100000),95000)) -> 95000 | T99: =IF((O99-1600000)<0,0,IF((O99-1600000)<1600000,0.21*(O99-1600000),336000)) -> 336000 | U99: =24%*(O99-3200000) -> 313173.05 | V99: =P99+Q99+R99+S99+T99+U99 -> 873173.05 | W99: 12 | X99: =V99/W99 -> 72764.421 | Z99: =X99 -> 72764.421 | AA99: 82627.951 | AB99: =Z99-AA99 -> -9863.5305 | AC99: MOHAMMED R. ADAMU
A100: 81 | B100: OKECHUKWU UCHENNA HULDA | C100: 437895.17 | D100: 12 | E100: =C100*D100 -> 5254742 | G100: 362779.36 | I100: =E100-F100-G100-H100 -> 4891962.6 | J100: 200000 | K100: 0.2 | L100: =I100*K100 -> 978392.53 | M100: =J100+L100 -> 1178392.5 | N100: =F100+G100+H100+M100 -> 1541171.9 | O100: =E100-N100 -> 3713570.1 | P100: =IF(O100<300000,0.07*O100,21000) -> 21000 | Q100: =IF((O100-300000)<0,0,IF((O100-300000)<300000,0.11*(O100-300000),33000)) -> 33000 | R100: =IF((O100-600000)<0,0,IF((O100-600000)<500000,0.15*(O100-600000),75000)) -> 75000 | S100: =IF((O100-1100000)<0,0,IF((O100-1100000)<500000,0.19*(O100-1100000),95000)) -> 95000 | T100: =IF((O100-1600000)<0,0,IF((O100-1600000)<1600000,0.21*(O100-1600000),336000)) -> 336000 | U100: =24%*(O100-3200000) -> 123256.83 | V100: =P100+Q100+R100+S100+T100+U100 -> 683256.83 | W100: 12 | X100: =V100/W100 -> 56938.069 | Z100: =X100 -> 56938.069 | AA100: 43492.373 | AB100: =Z100-AA100 -> 13445.696 | AC100: OKECHUKWU UCHENNA HULDA
B101: TASSNEEM IBRAHIM | C101: 360965.58 | D101: 12 | E101: =C101*D101 -> 4331587 | G101: 288926.96 | I101: =E101-F101-G101-H101 -> 4042660 | J101: 200000 | K101: 0.2 | L101: =I101*K101 -> 808532.01 | M101: =J101+L101 -> 1008532 | N101: =F101+G101+H101+M101 -> 1297459 | O101: =E101-N101 -> 3034128 | P101: =IF(O101<300000,0.07*O101,21000) -> 21000 | Q101: =IF((O101-300000)<0,0,IF((O101-300000)<300000,0.11*(O101-300000),33000)) -> 33000 | R101: =IF((O101-600000)<0,0,IF((O101-600000)<500000,0.15*(O101-600000),75000)) -> 75000 | S101: =IF((O101-1100000)<0,0,IF((O101-1100000)<500000,0.19*(O101-1100000),95000)) -> 95000 | T101: =IF((O101-1600000)<0,0,IF((O101-1600000)<1600000,0.21*(O101-1600000),336000)) -> 301166.89 | V101: =P101+Q101+R101+S101+T101+U101 -> 525166.89 | W101: 12 | X101: =V101/W101 -> 43763.907 | Z101: =X101 -> 43763.907 | AA101: 34968.882 | AB101: =Z101-AA101 -> 8795.0248 | AC101: TASSNEEM IBRAHIM
B102: TOTAL | G102: 0
A103: 83 | G103: 0
A104: 84 | B104: LIBRARY & DOCUMENTATION | G104: 0 | AB104: Difference
A105: 85 | B105: DR MAIMUNA IZAH | C105: 1635720 | D105: 12 | E105: =C105*D105 -> 19628640 | G105: 1378291.2 | I105: =E105-F105-G105-H105 -> 18250349 | J105: 200000 | K105: 0.2 | L105: =I105*K105 -> 3650069.8 | M105: =J105+L105 -> 3850069.8 | N105: =F105+G105+H105+M105 -> 5228361 | O105: =E105-N105 -> 14400279 | P105: =IF(O105<300000,0.07*O105,21000) -> 21000 | Q105: =IF((O105-300000)<0,0,IF((O105-300000)<300000,0.11*(O105-300000),33000)) -> 33000 | R105: =IF((O105-600000)<0,0,IF((O105-600000)<500000,0.15*(O105-600000),75000)) -> 75000 | S105: =IF((O105-1100000)<0,0,IF((O105-1100000)<500000,0.19*(O105-1100000),95000)) -> 95000 | T105: =IF((O105-1600000)<0,0,IF((O105-1600000)<1600000,0.21*(O105-1600000),336000)) -> 336000 | U105: =24%*(O105-3200000) -> 2688067 | V105: =P105+Q105+R105+S105+T105+U105 -> 3248067 | W105: 12 | X105: =V105/W105 -> 270672.25 | Z105: =X105 -> 270672.25 | AA105: 180306.81 | AB105: =Z105-AA105 -> 90365.441 | AC105: DR MAIMUNA IZAH
A106: 86 | B106: CATHERINE E. IKOKOH | C106: 942373.17 | D106: 12 | E106: =C106*D106 -> 11308478 | F106: ='[6]JANUARY 2024'!$V$106*12 -> 12795.951 | G106: 731878.24 | I106: =E106-F106-G106-H106 -> 10563804 | J106: 200000 | K106: 0.2 | L106: =I106*K106 -> 2112760.8 | M106: =J106+L106 -> 2312760.8 | N106: =F106+G106+H106+M106 -> 3057435 | O106: =E106-N106 -> 8251043 | P106: =IF(O106<300000,0.07*O106,21000) -> 21000 | Q106: =IF((O106-300000)<0,0,IF((O106-300000)<300000,0.11*(O106-300000),33000)) -> 33000 | R106: =IF((O106-600000)<0,0,IF((O106-600000)<500000,0.15*(O106-600000),75000)) -> 75000 | S106: =IF((O106-1100000)<0,0,IF((O106-1100000)<500000,0.19*(O106-1100000),95000)) -> 95000 | T106: =IF((O106-1600000)<0,0,IF((O106-1600000)<1600000,0.21*(O106-1600000),336000)) -> 336000 | U106: =24%*(O106-3200000) -> 1212250.3 | V106: =P106+Q106+R106+S106+T106+U106 -> 1772250.3 | W106: 12 | X106: =V106/W106 -> 147687.53 | Z106: =X106 -> 147687.53 | AA106: 99703.216 | AB106: =Z106-AA106 -> 47984.311 | AC106: CATHERINE E. IKOKOH
A107: 87 | B107: ALIYU SANNI ABUBAKAR | C107: 603237.86 | D107: 12 | E107: =C107*D107 -> 7238854.3 | F107: ='[6]JANUARY 2024'!$V$107*12 -> 7901.79 | G107: 424132.72 | I107: =E107-F107-G107-H107 -> 6806819.8 | J107: 200000 | K107: 0.2 | L107: =I107*K107 -> 1361364 | M107: =J107+L107 -> 1561364 | N107: =F107+G107+H107+M107 -> 1993398.5 | O107: =E107-N107 -> 5245455.8 | P107: =IF(O107<300000,0.07*O107,21000) -> 21000 | Q107: =IF((O107-300000)<0,0,IF((O107-300000)<300000,0.11*(O107-300000),33000)) -> 33000 | R107: =IF((O107-600000)<0,0,IF((O107-600000)<500000,0.15*(O107-600000),75000)) -> 75000 | S107: =IF((O107-1100000)<0,0,IF((O107-1100000)<500000,0.19*(O107-1100000),95000)) -> 95000 | T107: =IF((O107-1600000)<0,0,IF((O107-1600000)<1600000,0.21*(O107-1600000),336000)) -> 336000 | U107: =24%*(O107-3200000) -> 490909.39 | V107: =P107+Q107+R107+S107+T107+U107 -> 1050909.4 | W107: 12 | X107: =V107/W107 -> 87575.783 | Z107: =X107 -> 87575.783 | AA107: 180180.38 | AB107: =Z107-AA107 -> -92604.596 | AC107: ALIYU SANNI ABUBAKAR
...

Sheet Sheet5

Sheet New Enrolmt
B4: STAFF NAME | C4: DESIGNATION | D4: GRADE LEVEL | E4: BASIC SALARY | F4: ALLOWANCE | G4: DUTY ALLCE | H4: GROSS SALARY | I4: PAYE | J4: EMPLOYEE PENSIONS | K4: TOTAL DEDUCTION | L4: AUGUST, 2024
A5: 1 | B5: JOSEPH GWATANA | C5: SENIOR MOTOR DRIVER MECH. | D5: 5(7) | E5: 83955 | F5: =20000 -> 20000 | G5: =4000+3000 -> 7000 | H5: =SUM(E5:G5) -> 110955 | I5: 5719.04 | K5: 5719.04 | L5: =H5-K5 -> 105235.96
B6: PRORATED FOR 12 DAYS | E6: 83955 | F6: =20000 -> 20000 | G6: =4000+3000 -> 7000 | H6: =SUM(E6:G6)*(12/31) -> 42950.323 | I6: 3127.74 | J6: 0 | K6: 3127.74 | L6: =H6-K6 -> 39822.583
A7: 2 | B7: ABDULMUSHIN TAWFIQ LADAN | C7: ICT OFFICER | D7: 95(7) | E7: 255849 | F7: 60000 | H7: =SUM(E7:G7) -> 315849 | I7: =36790.6881 -> 36790.688 | J7: ='MARCH 2025'!P34 -> 20467.92 | K7: =I7+J7 -> 57258.608 | L7: =H7-K7 -> 258590.39
B8: TOTAL | L8: =SUM(L6:L7) -> 298412.97

Sheet 1ST 28 DAYS
A1: SCHEDULE OF 1ST 28 DAY TO THE NEWLY CONVERTED STAFF
A2: S/N | B2: NAME | C2: GRADE LEVEL | D2: AMOUNT (NGN) | E2: PAYE (NGN) | F2: NET AMOUNT (NGN)
A3: 1 | B3: Alabi Adesina Muhydeen | C3: 13 | D3: =25000*28 -> 700000 | E3: 104125.33 | F3: =D3-E3 -> 595874.67
A4: 2 | B4: Ikip Lebo | C4: 13 | D4: =25000*28 -> 700000 | E4: 104125.33 | F4: =D4-E4 -> 595874.67
A5: 3 | B5: Rasheedat Daibu | C5: 10 | D5: =20000*28 -> 560000 | E5: =86186.67 -> 86186.67 | F5: =D5-E5 -> 473813.33
A6: 4 | B6: Yussuf Yussuf Dayyabu | C6: 09 | D6: =20000*28 -> 560000 | E6: =86186.67 -> 86186.67 | F6: =D6-E6 -> 473813.33
A7: 5 | B7: Rahimat Onize Suberu | C7: 08 | D7: =20000*28 -> 560000 | E7: =86186.67 -> 86186.67 | F7: =D7-E7 -> 473813.33
A8: 6 | B8: Ramatu Ibrahim Abdulraheem | C8: 08 | D8: =20000*28 -> 560000 | E8: =86186.67 -> 86186.67 | F8: =D8-E8 -> 473813.33
A9: 7 | B9: Katman Emmanuel | C9: 08 | D9: =20000*28 -> 560000 | E9: =86186.67 -> 86186.67 | F9: =D9-E9 -> 473813.33
A10: 8 | B10: Usman Muhammed Gidado | C10: 08 | D10: =20000*28 -> 560000 | E10: =86186.67 -> 86186.67 | F10: =D10-E10 -> 473813.33
B11: TOTAL | D11: =SUM(D3:D10) -> 4760000 | E11: =SUM(E3:E10) -> 725370.68 | F11: =SUM(F3:F10) -> 4034629.3
A14: S/N | B14: NAME | C14: GRADE LEVEL | D14: AMOUNT (NGN) | E14: PAYE (NGN) | F14: NET AMOUNT (NGN)
B15: Abdulmushin Tawfiq Ladan | C15: 09 | D15: =20000*28 -> 560000 | E15: =86186.67 -> 86186.67 | F15: =D15-E15 -> 473813.33
B16: Joseph Gwatana | C16: 05 | D16: =10000*28 -> 280000 | E16: 31272.88 | F16: =D16-E16 -> 248727.12
B17: TOTAL | D17: =SUM(D15:D16) -> 840000 | E17: =SUM(E15:E16) -> 117459.55 | F17: =SUM(F15:F16) -> 722540.45

Sheet Conversion in Sept
A1: S/N | B1: STAFF NAME | C1: DESIGNATION | D1: GRADE LEVEL | E1: SALARY | F1: RESEARCH/HARDSHIP | G1: ARREARS | H1: GROSS SALARY | I1: DEDUCTIONS | N1: JULY 2024 NET SALARY
I2: COOP CONTR/SPEC. SAVINGS | J2: COOP LOAN REC. | K2: PAYE TAX | L2: PENSION DEDUCTION | M2: TOTAL DEDUCTION
E4: N | F4: N | G4: N | H4: N | I4: N | J4: N | K4: N | L4: N | M4: N | N4: N
A5: 1 | B5: Mugisat Abdulganiyu | C5: Presenter/Announcer | D5: 8(7) | E5: ='[3]Annual & Monthly'!$H$36 -> 218287.58 | F5: 50000 | H5: =E5+F5+G5 -> 268287.58 | K5: 29305.196 | L5: 17463.007 | M5: =I5+J5+K5+L5 -> 46768.202 | N5: =H5-M5 -> 221519.38
A6: 2 | B6: Zainab Bakari | C6: News Caster | D6: 8(7) | E6: ='[3]Annual & Monthly'!$H$36 -> 218287.58 | F6: 50000 | H6: =E6+F6+G6 -> 268287.58 | K6: 29305.196 | L6: =218287.583333333*0.08 -> 17463.007 | M6: =I6+J6+K6+L6 -> 46768.202 | N6: =H6-M6 -> 221519.38
A7: 3 | B7: Shugge Ngalabak | C7: Digital Producer/Marketer | D7: 8(7) | E7: ='[3]Annual & Monthly'!$H$36 -> 218287.58 | F7: 50000 | H7: =E7+F7+G7 -> 268287.58 | K7: 29305.196 | L7: =218287.583333333*0.08 -> 17463.007 | M7: =I7+J7+K7+L7 -> 46768.202 | N7: =H7-M7 -> 221519.38
A8: 5 | B8: Dr. Hadiza Saidu | C8: Assistant Director | D8: 15(7) | E8: 582118.08 | F8: 160000 | H8: =E8+F8+G8 -> 742118.08 | K8: 112212 | L8: 46569.447 | M8: =I8+J8+K8+L8 -> 158781.45 | N8: =H8-M8 -> 583336.63
B9: TOTAL | E9: =SUM(E5:E8) -> 1236980.8 | F9: =SUM(F5:F8) -> 310000 | G9: =SUM(G5:G8) -> 0 | H9: =SUM(H5:H8) -> 1546980.8 | I9: =SUM(I5:I8) -> 0 | J9: =SUM(J5:J8) -> 0 | K9: =SUM(K5:K8) -> 200127.59 | L9: =SUM(L5:L8) -> 98958.467 | ... N9: =SUM(N5:N8) -> 1247894.8

Sheet Conversion & Enrol Effect
A1: S/N | B1: STAFF NAME | C1: DESIGNATION | D1: GRADE LEVEL | E1: SALARY | F1: RESEARCH/HARDSHIP | G1: ARREARS | H1: GROSS SALARY | I1: DEDUCTIONS | N1: JULY 2024 NET SALARY
I2: COOP CONTR/SPEC. SAVINGS | J2: COOP LOAN REC. | K2: PAYE TAX | L2: PENSION DEDUCTION | M2: TOTAL DEDUCTION
E4: N | F4: N | G4: N | H4: N | I4: N | J4: N | K4: N | L4: N | M4: N | N4: N
A5: 1 | B5: Mugisat Abdulganiyu | C5: Presenter/Announcer | D5: 8(7) | E5: ='[3]Annual & Monthly'!$H$36 -> 218287.58 | F5: 50000 | H5: =E5+F5+G5 -> 268287.58 | K5: 29305.196 | L5: 17463.007 | M5: =I5+J5+K5+L5 -> 46768.202 | N5: =H5-M5 -> 221519.38
A6: 2 | B6: Zainab Bakari | C6: News Caster | D6: 8(7) | E6: ='[3]Annual & Monthly'!$H$36 -> 218287.58 | F6: 50000 | H6: =E6+F6+G6 -> 268287.58 | K6: 29305.196 | L6: =218287.583333333*0.08 -> 17463.007 | M6: =I6+J6+K6+L6 -> 46768.202 | N6: =H6-M6 -> 221519.38
A7: 3 | B7: Shugge Ngalabak | C7: Digital Producer/Marketer | D7: 8(7) | E7: ='[3]Annual & Monthly'!$H$36 -> 218287.58 | F7: 50000 | H7: =E7+F7+G7 -> 268287.58 | K7: 29305.196 | L7: =218287.583333333*0.08 -> 17463.007 | M7: =I7+J7+K7+L7 -> 46768.202 | N7: =H7-M7 -> 221519.38
A8: 4 | B8: Olufemi E. Oyegoke | C8: Marketer | D8: 8(7) | E8: ='[3]Annual & Monthly'!$H$36 -> 218287.58 | F8: 50000 | H8: =E8+F8+G8 -> 268287.58 | K8: 29305.196 | L8: =218287.583333333*0.08 -> 17463.007 | M8: =I8+J8+K8+L8 -> 46768.202 | N8: =H8-M8 -> 221519.38
A9: 5 | B9: Dr. Hadiza Saidu | C9: Assistant Director | D9: 15(7) | E9: 582118.08 | F9: 160000 | H9: =E9+F9+G9 -> 742118.08 | K9: 112212 | L9: 46569.447 | M9: =I9+J9+K9+L9 -> 158781.45 | N9: =H9-M9 -> 583336.63
B10: TOTAL | E10: =SUM(E5:E9) -> 1455268.4 | F10: =SUM(F5:F9) -> 360000 | G10: =SUM(G5:G9) -> 0 | H10: =SUM(H5:H9) -> 1815268.4 | I10: =SUM(I5:I9) -> 0 | J10: =SUM(J5:J9) -> 0 | K10: =SUM(K5:K9) -> 229432.79 | L10: =SUM(L5:L9) -> 116421.47 | ... N10: =SUM(N5:N9) -> 1469414.2

Sheet Converted Staff PAYE
A1: NATIONAL INSTITUTE FOR LEGISLATIVE AND DEMOCRATIC STUDIES
A2: NATIONAL ASSEMBLY ABUJA
A3: TAX COMPUTATION FOR 2022
A4: S/NO | B4: NAME | C4: MONTHLY TOTAL SALARY | D4: NO OF MONTHS | E4: ANNUAL SALARY GROSSED UP | F4: NATIONAL HOUSING SCHEME = 2.5% OF BASIC SALARY | G4: PENSION CONTRIBUTION = 8% OF CONSOLIDATED | H4: NHIS | I4: NET SALARY (EXC OF CRA) | M4: CRA=#200,000+(20% 0F NET SALARY (EXC OF CRA) | N4: TOTAL RELIEF | O4: CHARGEABLE INCOME | P4: FIRST N300,000 @ 7% | Q4: NEXT N300,000 @ 11% | R4: NEXT N500,000 @ 15% | S4: NEXT N500,000@ 19% | T4: NEXT N1,600,000 @ 21% | U4: ABOVE N3,200,000 @ 24% | V4: ANNUAL TAX PAYABLE | X4: MONTHLY TAX PAYABLE | Y4: MINIMUM TAX PAYABLE | Z4: NEW ACTUAL TAX PAYABLE
A5: 1
A6: 3 | B6: Rahimat Suberu Onize | C6: 268287.58 | D6: 12 | E6: =C6*D6 -> 3219451 | G6: 209556.08 | I6: =E6-F6-G6-H6 -> 3009894.9 | J6: 200000 | K6: 0.2 | L6: =I6*K6 -> 601978.98 | M6: =J6+L6 -> 801978.98 | N6: =F6+G6+H6+M6 -> 1011535.1 | O6: =E6-N6 -> 2207915.9 | P6: =IF(O6<300000,0.07*O6,21000) -> 21000 | Q6: =IF((O6-300000)<0,0,IF((O6-300000)<300000,0.11*(O6-300000),33000)) -> 33000 | R6: =IF((O6-600000)<0,0,IF((O6-600000)<500000,0.15*(O6-600000),75000)) -> 75000 | S6: =IF((O6-1100000)<0,0,IF((O6-1100000)<500000,0.19*(O6-1100000),95000)) -> 95000 | T6: =IF((O6-1600000)<0,0,IF((O6-1600000)<1600000,0.21*(O6-1600000),336000)) -> 127662.35 | V6: =P6+Q6+R6+S6+T6+U6 -> 351662.35 | W6: 12 | X6: =V6/W6 -> 29305.196 | Z6: =X6 -> 29305.196
A7: 4 | B7: Ikip Lebo | C7: 460248.92 | D7: 12 | E7: =C7*D7 -> 5522987 | G7: 374638.96 | I7: =E7-F7-G7-H7 -> 5148348 | J7: 200000 | K7: 0.2 | L7: =I7*K7 -> 1029669.6 | M7: =J7+L7 -> 1229669.6 | N7: =F7+G7+H7+M7 -> 1604308.6 | O7: =E7-N7 -> 3918678.4 | P7: =IF(O7<300000,0.07*O7,21000) -> 21000 | Q7: =IF((O7-300000)<0,0,IF((O7-300000)<300000,0.11*(O7-300000),33000)) -> 33000 | R7: =IF((O7-600000)<0,0,IF((O7-600000)<500000,0.15*(O7-600000),75000)) -> 75000 | S7: =IF((O7-1100000)<0,0,IF((O7-1100000)<500000,0.19*(O7-1100000),95000)) -> 95000 | T7: =IF((O7-1600000)<0,0,IF((O7-1600000)<1600000,0.21*(O7-1600000),336000)) -> 336000 | U7: =24%*(O7-3200000) -> 172482.82 | V7: =P7+Q7+R7+S7+T7+U7 -> 732482.82 | W7: 12 | X7: =V7/W7 -> 61040.235 | Z7: =X7 -> 61040.235
A8: 5 | B8: Yusuf Yusuf Dayyabu | C8: 315849 | D8: 12 | E8: =C8*D8 -> 3790188 | G8: 245615.04 | I8: =E8-F8-G8-H8 -> 3544573 | J8: 200000 | K8: 0.2 | L8: =I8*K8 -> 708914.59 | M8: =J8+L8 -> 908914.59 | N8: =F8+G8+H8+M8 -> 1154529.6 | O8: =E8-N8 -> 2635658.4 | P8: =IF(O8<300000,0.07*O8,21000) -> 21000 | Q8: =IF((O8-300000)<0,0,IF((O8-300000)<300000,0.11*(O8-300000),33000)) -> 33000 | R8: =IF((O8-600000)<0,0,IF((O8-600000)<500000,0.15*(O8-600000),75000)) -> 75000 | S8: =IF((O8-1100000)<0,0,IF((O8-1100000)<500000,0.19*(O8-1100000),95000)) -> 95000 | T8: =IF((O8-1600000)<0,0,IF((O8-1600000)<1600000,0.21*(O8-1600000),336000)) -> 217488.26 | V8: =P8+Q8+R8+S8+T8+U8 -> 441488.26 | W8: 12 | X8: =V8/W8 -> 36790.688 | Z8: =X8 -> 36790.688
A9: 6 | B9: Ramatu Ibrahim Abdulrahim | C9: 268287.58 | D9: 12 | E9: =C9*D9 -> 3219451 | G9: 209556.08 | I9: =E9-F9-G9-H9 -> 3009894.9 | J9: 200000 | K9: 0.2 | L9: =I9*K9 -> 601978.98 | M9: =J9+L9 -> 801978.98 | N9: =F9+G9+H9+M9 -> 1011535.1 | O9: =E9-N9 -> 2207915.9 | P9: =IF(O9<300000,0.07*O9,21000) -> 21000 | Q9: =IF((O9-300000)<0,0,IF((O9-300000)<300000,0.11*(O9-300000),33000)) -> 33000 | R9: =IF((O9-600000)<0,0,IF((O9-600000)<500000,0.15*(O9-600000),75000)) -> 75000 | S9: =IF((O9-1100000)<0,0,IF((O9-1100000)<500000,0.19*(O9-1100000),95000)) -> 95000 | T9: =IF((O9-1600000)<0,0,IF((O9-1600000)<1600000,0.21*(O9-1600000),336000)) -> 127662.35 | V9: =P9+Q9+R9+S9+T9+U9 -> 351662.35 | W9: 12 | X9: =V9/W9 -> 29305.196 | Z9: =X9 -> 29305.196
A10: 7 | B10: Rasheedat Daibu | C10: 353029.67 | D10: 12 | E10: =C10*D10 -> 4236356 | G10: 281308.48 | I10: =E10-F10-G10-H10 -> 3955047.5 | J10: 200000 | K10: 0.2 | L10: =I10*K10 -> 791009.5 | M10: =J10+L10 -> 991009.5 | N10: =F10+G10+H10+M10 -> 1272318 | O10: =E10-N10 -> 2964038 | P10: =IF(O10<300000,0.07*O10,21000) -> 21000 | Q10: =IF((O10-300000)<0,0,IF((O10-300000)<300000,0.11*(O10-300000),33000)) -> 33000 | R10: =IF((O10-600000)<0,0,IF((O10-600000)<500000,0.15*(O10-600000),75000)) -> 75000 | S10: =IF((O10-1100000)<0,0,IF((O10-1100000)<500000,0.19*(O10-1100000),95000)) -> 95000 | T10: =IF((O10-1600000)<0,0,IF((O10-1600000)<1600000,0.21*(O10-1600000),336000)) -> 286447.98 | V10: =P10+Q10+R10+S10+T10+U10 -> 510447.98 | W10: 12 | X10: =V10/W10 -> 42537.332 | Z10: =X10 -> 42537.332
A11: 8 | B11: Dr. Alabi Adesina Muhydeen | C11: 510248.92 | D11: 12 | E11: =C11*D11 -> 6122987 | G11: 374638.96 | I11: =E11-F11-G11-H11 -> 5748348 | J11: 200000 | K11: 0.2 | L11: =I11*K11 -> 1149669.6 | M11: =J11+L11 -> 1349669.6 | N11: =F11+G11+H11+M11 -> 1724308.6 | O11: =E11-N11 -> 4398678.4 | P11: =IF(O11<300000,0.07*O11,21000) -> 21000 | Q11: =IF((O11-300000)<0,0,IF((O11-300000)<300000,0.11*(O11-300000),33000)) -> 33000 | R11: =IF((O11-600000)<0,0,IF((O11-600000)<500000,0.15*(O11-600000),75000)) -> 75000 | S11: =IF((O11-1100000)<0,0,IF((O11-1100000)<500000,0.19*(O11-1100000),95000)) -> 95000 | T11: =IF((O11-1600000)<0,0,IF((O11-1600000)<1600000,0.21*(O11-1600000),336000)) -> 336000 | U11: =24%*(O11-3200000) -> 287682.82 | V11: =P11+Q11+R11+S11+T11+U11 -> 847682.82 | W11: 12 | X11: =V11/W11 -> 70640.235 | Z11: =X11 -> 70640.235
A12: 9 | B12: Katman Emmanuel | C12: 268287.58 | D12: 12 | E12: =C12*D12 -> 3219451 | G12: 209556.08 | I12: =E12-F12-G12-H12 -> 3009894.9 | J12: 200000 | K12: 0.2 | L12: =I12*K12 -> 601978.98 | M12: =J12+L12 -> 801978.98 | N12: =F12+G12+H12+M12 -> 1011535.1 | O12: =E12-N12 -> 2207915.9 | P12: =IF(O12<300000,0.07*O12,21000) -> 21000 | Q12: =IF((O12-300000)<0,0,IF((O12-300000)<300000,0.11*(O12-300000),33000)) -> 33000 | R12: =IF((O12-600000)<0,0,IF((O12-600000)<500000,0.15*(O12-600000),75000)) -> 75000 | S12: =IF((O12-1100000)<0,0,IF((O12-1100000)<500000,0.19*(O12-1100000),95000)) -> 95000 | T12: =IF((O12-1600000)<0,0,IF((O12-1600000)<1600000,0.21*(O12-1600000),336000)) -> 127662.35 | V12: =P12+Q12+R12+S12+T12+U12 -> 351662.35 | W12: 12 | X12: =V12/W12 -> 29305.196 | Z12: =X12 -> 29305.196
A13: 10 | B13: Usman Muhammed Gidado | C13: 268287.58 | D13: 12 | E13: =C13*D13 -> 3219451 | G13: 209556.08 | I13: =E13-F13-G13-H13 -> 3009894.9 | J13: 200000 | K13: 0.2 | L13: =I13*K13 -> 601978.98 | M13: =J13+L13 -> 801978.98 | N13: =F13+G13+H13+M13 -> 1011535.1 | O13: =E13-N13 -> 2207915.9 | P13: =IF(O13<300000,0.07*O13,21000) -> 21000 | Q13: =IF((O13-300000)<0,0,IF((O13-300000)<300000,0.11*(O13-300000),33000)) -> 33000 | R13: =IF((O13-600000)<0,0,IF((O13-600000)<500000,0.15*(O13-600000),75000)) -> 75000 | S13: =IF((O13-1100000)<0,0,IF((O13-1100000)<500000,0.19*(O13-1100000),95000)) -> 95000 | T13: =IF((O13-1600000)<0,0,IF((O13-1600000)<1600000,0.21*(O13-1600000),336000)) -> 127662.35 | V13: =P13+Q13+R13+S13+T13+U13 -> 351662.35 | W13: 12 | X13: =V13/W13 -> 29305.196 | Z13: =X13 -> 29305.196
B14: TOTAL - MONTHLY | Z14: =SUM(Z6:Z13) -> 328229.27
C16: MONTHLY PENSIONS | D16: 12 | E16: ANNUAL PENSIONS
B17: Rahimat Suberu Onize | C17: =218287.583333333*0.08 -> 17463.007 | D17: 12 | E17: =C17*D17 -> 209556.08
B18: Ikip Lebo | C18: =390248.916666667*0.08 -> 31219.913 | D18: 12 | E18: =C18*D18 -> 374638.96
B19: Yusuf Yusuf Dayyabu | C19: =255849*0.08 -> 20467.92 | D19: 12 | E19: =C19*D19 -> 245615.04
B20: Ramatu Ibrahim Abdulrahim | C20: =218287.583333333*0.08 -> 17463.007 | D20: 12 | E20: =C20*D20 -> 209556.08
B21: Rasheedat Daibu | C21: =293029.666666667*0.08 -> 23442.373 | D21: 12 | E21: =C21*D21 -> 281308.48
B22: Dr. Alabi Adesina Muhydeen | C22: =390248.916666667*0.08 -> 31219.913 | D22: 12 | E22: =C22*D22 -> 374638.96
B23: Katman Emmanuel | C23: =218287.583333333*0.08 -> 17463.007 | D23: 12 | E23: =C23*D23 -> 209556.08
B24: Usman Muhammed Gidado | C24: =218287.583333333*0.08 -> 17463.007 | D24: 12 | E24: =C24*D24 -> 209556.08

Sheet Movt to Contract
B3: STAFF NAME | C3: DESIGNATION | D3: GRADE LEVEL | E3: BASIC SALARY | F3: ALLCE/ AREARS | G3: ALLOWANCE | H3: ALLOWANCE | I3: DUTY ALLCE | J3: GROSS SALARY | K3: AUCTION | L3: COOP CONTR/SPEC SAVINGS | M3: COOP. LOAN RECOVERY | N3: NHF DED. | O3: PAYE | P3: EMPLOYEE PENSIONS | Q3: TOTAL DEDUCTION | R3: JUNE, 2024 | S3: JULY, 2024
E4: N | F4: N | G4: N | H4: N | I4: N | J4: N | K4: N | L4: N | M4: N | N4: N | O4: N | P4: N | Q4: N | R4: N | S4: N
A5: 1 | B5: USMAN WALI | C5: SENIOR RESEARCH FELLOW | D5: 15 (8) | E5: 601396.83 | G5: =160000 -> 160000 | I5: 0 | J5: =SUM(E5:I5) -> 761396.83 | N5: 0 | O5: 124854.86 | Q5: =O5+N5+M5+L5+K5+P5 -> 124854.86 | R5: 636541.97 | S5: =J5-Q5 -> 636541.97
A6: 2 | B6: AYOBOLU OLAJIDE OLUFUNSHO | C6: ASST.DIR., INFORMATION | D6: 15 (9) | E6: 620675.58 | G6: 160000 | I6: 0 | J6: =SUM(E6:I6) -> 780675.58 | L6: =50000 -> 50000 | M6: =59583.33 -> 59583.33 | O6: =128556.38 -> 128556.38 | Q6: =O6+N6+M6+L6+K6+P6 -> 238139.71 | R6: 542535.87 | S6: =J6-Q6 -> 542535.87
A7: 3 | B7: ARAOYE GANIYAT TITILOLA | C7: ASST. DIRECTOR, ACCOUNTS | D7: 15(7) | E7: 582118.08 | H7: =80000 -> 80000 | I7: 0 | J7: =SUM(E7:I7) -> 662118.08 | L7: =100000 -> 100000 | M7: =103000 -> 103000 | N7: 0 | O7: 105793.34 | Q7: =O7+N7+M7+L7+K7+P7 -> 308793.34 | R7: 353324.74 | S7: =J7-Q7 -> 353324.74
A8: 4 | B8: MAGAJI BALA | C8: DD ADMIN | D8: 16(9) | E8: 762373.17 | H8: 90000 | J8: =SUM(E8:I8) -> 852373.17 | L8: 50000 | M8: 200000 | O8: 142322.31 | Q8: =O8+N8+M8+L8+K8+P8 -> 392322.31 | R8: 460050.85 | S8: =J8-Q8 -> 460050.85
E9: =SUM(E5:E8) -> 2566563.7 | F9: =SUM(F5:F8) -> 0 | G9: =SUM(G5:G8) -> 320000 | H9: =SUM(H5:H8) -> 170000 | I9: =SUM(I5:I8) -> 0 | J9: =SUM(J5:J8) -> 3056563.7 | K9: =SUM(K5:K8) -> 0 | L9: =SUM(L5:L8) -> 200000 | ... S9: =SUM(S5:S8) -> 1992453.4

Sheet Sheet10

Sheet Sheet8
B3: STAFF NAME | C3: DESIGNATION | D3: GRADE LEVEL | E3: BASIC SALARY | F3: ALLCE/ AREARS | G3: ALLOWANCE | H3: ALLOWANCE | I3: DUTY ALLCE | J3: GROSS SALARY | K3: AUCTION | L3: COOP CONTR/SPEC SAVINGS | M3: COOP. LOAN RECOVERY | N3: NHF DED. | O3: PAYE | P3: EMPLOYEE PENSIONS | Q3: TOTAL DEDUCTION | R3: JUNE, 2024 | S3: JULY, 2024
E4: N | F4: N | G4: N | H4: N | I4: N | J4: N | K4: N | L4: N | M4: N | N4: N | O4: N | P4: N | Q4: N | R4: N | S4: N
A5: 6 | B5: REKIYA IBRAHIM ATTAH | C5: DEPUTY DIRECTOR TRAINING | D5: 16 (9) | E5: 762373.17 | H5: =90000 -> 90000 | I5: =100000+100000 -> 200000 | J5: =E5+F5+G5+H5+I5 -> 1052373.2 | L5: =50000 -> 50000 | M5: =91666.67 -> 91666.67 | O5: ='Additional Leg Duty Allowance'!P3 -> 0 | Q5: =O5+N5+M5+L5+K5+P5 -> 141666.67 | R5: 729984.18 | S5: =J5-Q5 -> 910706.5

Sheet Welfare June
A1: NATIONAL INSTITUTE FOR LEGISLATIVE AND DEMOCRATIC STUDIES
A2: STAFF SALLAH WELFARE JUNE, 2024
B4: STAFF NAME | C4: DESIGNATION | D4: GRADE LEVEL | E4: AMOUNT
E5: N
A6: S/N | B6: DG'S OFFICE
A7: 1 | B7: PROF. ABUBAKAR O. SULAIMAN | C7: DIRECTOR GENERAL | D7: CONSOL | E7: 540000
A8: 2 | B8: RAHEEM USMAN AYIGORO | C8: SA-INFRASTRUCTURE | D8: 16 (9) | E8: 180000
A9: 3 | B9: MARIAM MOHAMMED BELLO | C9: SA- SPECIAL DUTIES | D9: 16 (9) | E9: 180000
A10: 4 | B10: DR IKEME ARTHUR J.O | C10: DEPUTY DIRECTOR, M&E | D10: 16 (9) | E10: 180000
A11: 5 | B11: MOSHOOD M. OLALERE | C11: DEPUTY DIR. GENERAL SERVICE | D11: 16 (9) | E11: 180000
A12: 6 | B12: REKIYA IBRAHIM ATTAH | C12: DEPUTY DIRECTOR TRAINING | D12: 16 (9) | E12: 180000
A13: 7 | B13: ANDRAWUS MUSA | C13: ASST. DIRECTOR, STORES | D13: 15(9) | E13: 126000
A14: 8 | B14: DR FRANCIS NDUM OJIE | C14: AD, TRAINING & IC./SA TO DG | D14: 15(7) | E14: 126000
A15: 9 | B15: ALI ABDULLAHI | C15: CHIEF ICT OFFICER | D15: 14(11) | E15: 90000
A16: 10 | B16: EMILY EKHIDE | C16: RESEARCH FELLOW 1 | D16: 14(10) | E16: 90000
A17: 11 | B17: DORIS DAKDA AARON | C17: RESEARCH FELLOW I | D17: 14(8) | E17: 90000
A18: 12 | B18: ABDULSALAM S. MUSTAPHA | C18: ASST. MANAGER ICT | D18: 13(11) | E18: 90000
... A33: 27 | B33: HARUNA JIBRIL AMEH | C33: ASST. ADMIN. OFFICER | D33: 8(8) | E33: 54000
B34: TOTAL | C34: 27 | E34: =SUM(E7:E33) -> 2990000
B36: INTERNAL AUDIT
A37: 1 | B37: OSANAIYE DAVID AKINYEMI | C37: DIRECTOR INTERNAL AUDIT | D37: 17(9) | E37: 270000
A38: 2 | B38: JAMILA ABDUL | C38: SENIOR INTERNAL AUDITOR | D38: 10(7) | E38: 68000
A39: 3 | B39: IJEOMA EWELUKWA | C39: SENIOR INTERNAL AUDITOR | D39: 10(8) | E39: 68000
C40: 3 | E40: =SUM(E37:E39) -> 406000
B42: LEG. SUPPORT SEVICES
A43: 1 | B43: PROF. EDOBA BRIGHT OMOREGBE | C43: AG. DLSS | D43: 17(9) | E43: 270000
A44: 2 | B44: DR CLINTON JAJA | C44: SENIOR RESEARCH FELLOW | D44: 15(9) | E44: 126000
A45: 3 | B45: BETHEL UZOMA IHUGBA | C45: DEPUTY DIRECTOR, LEGAL RESEARCH | D45: 16(8) | E45: 180000
A46: 4 | B46: OGUCHE SAMUEL | C46: SNR RESEARCH FELLOW | D46: 15(9) | E46: 126000
A47: 5 | B47: IBRAHIM USMAN | C47: SNR RESEARCH FELLOW | D47: 15(9) | E47: 126000
A48: 6 | B48: DR MOHAMMED O. AMALI | C48: SNR RESEARCH FELLOW | D48: 15(7) | E48: 126000
A49: 7 | B49: YAHAYA SHAMSU | C49: RESEARCH FELLOW 1 | D49: 14(10) | E49: 90000
A50: 8 | B50: BILKIS S. LAWAL-GAMBARI | C50: RESEARCH OFFICER | D50: 10(8) | E50: 68000
A51: 9 | B51: ZAINAB AKINDE | C51: RESEARCH OFFICER | D51: 9(8) | E51: 54000
A52: 10 | B52: ABDULLAHI AHMAD USMAN | C52: RESEARCH OFFICER | D52: 9(8) | E52: 54000
A53: 11 | B53: GUNAT NANSAK MARK | C53: RESEARCH OFFICER | D53: 9(8) | E53: 54000
B54: TOTAL | C54: 11 | E54: =SUM(E43:E53) -> 1274000
B56: LEGAL SERVICES
A57: 1 | B57: DR SHUIBU DANWANKA | C57: DIRECTOR LEGAL SERVICES | D57: 17(9) | E57: 270000
A58: 2 | B58: ABDULSALAM BAKO | C58: MANAGER, LEGAL SERVICES | D58: 15 (9) | E58: 126000
B59: TOTAL | C59: 2 | E59: =SUM(E57:E58) -> 396000
B61: DEMOCRACY & GOVERNANCE
A62: 1 | B62: DR. ADEWALE ADEREMI | C62: DIRECTOR, DEMOCRATIC STUDIES | D62: 17(9) | E62: 270000
A63: 2 | B63: NDANUSA MOHAMMED MANZUMA | C63: SNR RESEARCH FELLOW | D63: 15(8) | E63: 126000
A64: 3 | B64: EJALONIBU GANIYU LAYI | C64: RESEARCH FELLOW 1 | D64: 14(8) | E64: 90000
A65: 4 | B65: LOHNA BONKAT JONATHAN | C65: RESEARCH FELLOW 11 | D65: 13(10) | E65: 90000
A66: 5 | B66: YUNUSA ABDULLAHI | C66: RESEARCH FELLOW 1 | D66: 14(11) | E66: 90000
A67: 7 | B67: UDEFUNA NNADOZIE PATRICK | C67: RESEARCH OFFICER | D67: 12(8) | E67: 68000
A68: 8 | B68: SHAFIU YAHYA MIKAIL | C68: PRINCIPAL RESEARCH OFFICER | D68: 12(8) | E68: 68000
A69: 9 | B69: HASSAN YERIMA | C69: PRINCIPAL RESEARCH OFFICER | D69: 12(8) | E69: 68000
A70: 10 | B70: HAUWA PATE SADIQ | C70: PRINCIPAL PROGRAMME OFFICER | D70: 12(9) | E70: 68000
A71: 11 | B71: KOLAPO Q. ABAYOMI | C71: RESEARCH OFFICER | D71: 10(8) | E71: 68000
B72: TOTAL | C72: 12 | E72: =SUM(E62:E71) -> 1006000
B74: DEPARTMENT OF STUDIES
A75: 1 | B75: DR ASIMIYU G. ABIOLA | C75: DIRECTOR POST GRADUATE | D75: 17(9) | E75: 270000
A76: 2 | B76: USMAN WALI | C76: SENIOR RESEARCH FELLOW | D76: 15 (8) | E76: 126000
A77: 3 | B77: AYOBOLU OLAJIDE OLUFUNSHO | C77: ASST.DIR., INFORMATION | D77: 15 (9) | E77: 126000
A78: 4 | B78: ANTHONY EDET | C78: CHIEF PROGRAMMES OFFICER | D78: 14(9) | E78: 90000
A79: 5 | B79: IGWE STACY | C79: PROGRAMME OFFICER | D79: 10(9) | E79: 68000
A80: 6 | B80: OLANIYAN TAIWO ABINBOLA | C80: PROGRAMME OFFICER | D80: 9(8) | E80: 54000
A81: 7 | B81: AMINAT JUMOKE SULAIMON | C81: AST. PROGRAMME OFFICER | D81: 8(8) | E81: 54000
B82: TOTAL | C82: 7 | E82: =SUM(E75:E81) -> 788000
B84: ECON. DEV. & SOC. RESEARCH
A85: 1 | B85: TERFA WILLIAMS ABRAHAM | C85: SNR RESEARCH FELLOW | D85: 15(9) | E85: 126000
A86: 2 | B86: DR AUGUSTINE C. OSIGWE | C86: SNR RESEARCH FELLOW | D86: 15(9) | E86: 126000
A87: 3 | B87: OMOJU OLUWASOLA EMMANUEL | C87: SNR RESEARCH FELLOW | D87: 15(7) | E87: 126000
A88: 4 | B88: IBE EZECHI CYRIACUS | C88: RESEARCH FELLOW II | D88: 13(11) | E88: 90000
A89: 5 | B89: OSIKHEN LEO IGBANOI | C89: RESEARCH FELLOW 11 | D89: 13(10) | E89: 90000
A90: 6 | B90: OKUNGBOWA OSARETIN GODSPOWER | C90: RESEARCH FELLOW 1 | D90: 14(7) | E90: 90000
A91: 7 | B91: YUSUF IBRAHIM | C91: PRINCIPAL RESEARCH OFFICER | D91: 12(8) | E91: 68000
A92: 8 | B92: MUSTAPHA RAFIU AYOBANJI | C92: RESEARCH FELLOW 11 | D92: 13(7) | E92: 90000
A93: 9 | B93: MARYAM MUSA SADA | C93: ASSIT. RESEARCH OFFICER | D93: 10(8) | E93: 68000
A94: 10 | B94: CHARITY EZENWAJIOBI | C94: REASEARCH. ASST. | D94: 8(9) | E94: 54000
B95: TOTAL | C95: 11 | E95: =SUM(E85:E94) -> 928000
B97: TRAINING & INT''L COOP
A98: 1 | B98: AKINSANMI ADEJOKE OLUKEMI | C98: Ag. DIR. TRAINING & IC | D98: 17(7) | E98: 270000
A99: 2 | B99: MOHAMMED R. ADAMU | C99: CHIEF TRAINING OFFICER | D99: 14(9) | E99: 90000
A100: 3 | B100: OKECHUKWU UCHENNA HULDA | C100: PRINCIPALTRAINING OFFICER | D100: 12(9) | E100: 68000
A101: 4 | B101: TASSNEEM IBRAHIM | C101: SENIOR PROGRAMME OFFICER | D101: 10(8) | E101: 68000
B102: TOTAL | C102: 4 | E102: =SUM(E98:E101) -> 496000
B104: LIBRARY & DOCUMENTATION
A105: 1 | B105: DR MAIMUNA IZAH | C105: INSITUTE LIBRARIAN | D105: 17(9) | E105: 270000
A106: 2 | B106: CATHERINE E. IKOKOH | C106: SNR RESEARCH FELLOW DOCU | D106: 16(9) | E106: 180000
A107: 3 | B107: ALIYU SANNI ABUBAKAR | C107: RESEARCH FELLOW 11 DATA & DOCU | D107: 13(11) | E107: 90000
A108: 4 | B108: CHINAKO N. ASOGWA | C108: RESEARCH FELLOW 11 DATA & DOCU | D108: 13(11) | E108: 90000
A109: 5 | B109: AMOS ABA | C109: LIBRARY ASSISTANT | D109: 8(12) | E109: 54000
A110: 6 | B110: TITILAYO DANIEL MARVELLOUS | C110: LIBRARY ASSISTANT | D110: 8(11) | E110: 54000
A111: 7 | B111: ENENCHE JEREMIAH AGADA | C111: LIBRARY ASSISTANT | D111: 8(9) | E111: 54000
B112: TOTAL | C112: 7 | E112: =SUM(E105:E111) -> 792000
B114: LEG, CTRE FOR SEC. ANALYSIS
A115: 1 | B115: NGARA CHRISTOPHER OCHANJA | C115: SNR RESEARCH FELLOW | D115: 15(8) | E115: 126000
A116: 2 | B116: EGUATU U. ONYEJELEM | C116: PRINCIPAL M&E OFFICER | D116: 12(9) | E116: 68000
A117: 3 | B117: CHRISTIAN MADUABUCHI ODO | C117: PRINCIPAL ICT OFFICER | D117: 12(10) | E117: 68000
B118: TOTAL | C118: 2 | E118: =SUM(E115:E117) -> 262000
B120: FINANCE & ACCOUNTS
A121: 1 | B121: IBRAHIM M. MSHELIA | C121: DIR. FINANCE & ACCOUNTS | D121: 17(9) | E121: 270000
A122: 2 | B122: RAHILA NURUDEEN HABU | C122: DEP. DIRECTOR, ACCOUNTS | D122: 16(8) | E122: 180000
A123: 3 | B123: TONDO IORWUESE EDWARD | C123: ASST. DIRECTOR, ACCOUNTS | D123: 15(9) | E123: 126000
A124: 4 | B124: ARAOYE GANIYAT TITILOLA | C124: ASST. DIRECTOR, ACCOUNTS | D124: 15(7) | E124: 126000
A125: 5 | B125: SHEHU ABDULLAHI | C125: CHIEF ACCOUNT OFFICER | D125: 14(10) | E125: 90000
...

Sheet Welfare Summary
A2: 1 | B2: Permanent Staff | C2: ='Welfare June'!E194 -> 13858000
A3: 2 | B3: Contract Staff | C3: ='[7]CONTRACT Welfare'!$E$26 -> 1688000
A4: 3 | B4: Casual, Sabbatical & NYSC | C4: ='[7]CAS. SABB. NYSC Welfare'!$D$58 -> 1791000
A5: 4 | B5: Consultants | C5: ='[7]CONSULTANCY Welfare'!$D$31 -> 1746000
A6: 5 | B6: Cleaners & Securities | C6: ='[7]Welfare Others'!$C$92 -> 1225000
C7: =SUM(C2:C6) -> 20308000

Sheet Arrears of Res. Allow
D1: OLD PAYE | E1: ADJUSTED PAYE | F1: DIFFERENCE | G1: FOR 7 MONTHS | H1: TOTAL DIFF IN RES ALLOW | I1: NET DIFFERENCE
A2: AYOBOLU OLAJIDE OLUFUNSHO | B2: ASST.DIR., INFORMATION | C2: 15 (9) | D2: =64596.94 -> 64596.94 | E2: =79956.94 -> 79956.94 | F2: =E2-D2 -> 15360 | G2: =F2*7 -> 107520 | H2: 560000 | I2: =H2-G2 -> 452480

Sheet Additional Leg Duty Allowance
A1: NATIONAL INSTITUTE FOR LEGISLATIVE AND DEMOCRATIC STUDIES
A2: STAFF PAYROLL FOR THE MONTH OF MARCH, 2024
E3: ='[1]FEB 08'!E11/'[1]FEB 08'!M11 -> #REF!
B4: STAFF NAME | C4: DESIGNATION | D4: GRADE LEVEL | E4: BASIC SALARY | F4: ALLCE/ AREARS | G4: ALLOWANCE | H4: ALLOWANCE | I4: DUTY ALLCE | J4: GROSS SALARY | K4: AUCTION | L4: COOP CONTR/SPEC SAVINGS | M4: COOP. LOAN RECOVERY | N4: NHF DED. | O4: PAYE | P4: NEW PAYE | Q4: DIFFERENCE | R4: EMPLOYEE PENSIONS | S4: TOTAL DEDUCTION | T4: FEBRUARY, 2024 | U4: MARCH, 2024
E5: N | G5: N | H5: N | I5: N | J5: N | K5: N | L5: N | M5: N | N5: N | O5: N | P5: N | Q5: N | R5: N | S5: N | T5: N | U5: N
A6: S/N | B6: DG'S OFFICE
A7: 1 | B7: RAHEEM USMAN AYIGORO | C7: SA-INFRASTRUCTURE | D7: 16 (9) | E7: 762373.17 | H7: =90000 -> 90000 | I7: 0 | J7: =E7+F7+G7+H7+I7 -> 852373.17 | L7: =100000 -> 100000 | O7: 130612.26 | P7: ='March New PAYE '!Z7 -> 149812.26 | Q7: =P7-O7 -> 19200 | R7: 60989.853 | S7: =O7+N7+M7+L7+K7+R7 -> 291602.12 | T7: 560771.05 | U7: =J7-S7 -> 560771.05
A8: 2 | B8: MARIAM MOHAMMED BELLO | C8: SA- SPECIAL DUTIES | D8: 16 (9) | E8: 762373.17 | H8: =90000 -> 90000 | I8: =100000+100000 -> 200000 | J8: =E8+F8+G8+H8+I8 -> 1052373.2 | O8: 180722.31 | P8: ='March New PAYE '!Z8 -> 199922.31 | Q8: =P8-O8 -> 19200 | S8: =O8+N8+M8+L8+K8+R8 -> 180722.31 | T8: 871650.85 | U8: =J8-S8 -> 871650.85
A9: 3 | B9: MOSHOOD M. OLALERE | C9: DEPUTY DIR. GENERAL SERVICE | D9: 16 (9) | E9: 762373.17 | H9: =80000+10000 -> 90000 | I9: 150000 | J9: =E9+F9+G9+H9+I9 -> 1002373.2 | L9: =20000+60000 -> 80000 | M9: ='[2]OCTOBER 2023 '!$D$193 -> 230499.8 | N9: 1066.3293 | O9: 159207.53 | P9: ='March New PAYE '!Z10 -> 178407.53 | Q9: =P9-O9 -> 19200 | R9: 60989.853 | S9: =O9+N9+M9+L9+K9+R9 -> 531763.51 | T9: 470609.66 | U9: =J9-S9 -> 470609.66
A10: 4 | B10: REKIYA IBRAHIM ATTAH | C10: DEPUTY DIRECTOR TRAINING | D10: 16 (9) | E10: 762373.17 | H10: =90000 -> 90000 | I10: 100000 | J10: =E10+F10+G10+H10+I10 -> 952373.17 | L10: =50000 -> 50000 | M10: =91666.67 -> 91666.67 | O10: 161522.31 | P10: ='March New PAYE '!Z11 -> 180722.31 | Q10: =P10-O10 -> 19200 | S10: =O10+N10+M10+L10+K10+R10 -> 303188.98 | T10: 649184.18 | U10: =J10-S10 -> 649184.18
A11: 5 | B11: TERFA WILLIAMS ABRAHAM | C11: SNR RESEARCH FELLOW | D11: 15(9) | E11: 620675.58 | G11: =160000 -> 160000 | I11: 100000 | J11: =SUM(E11:I11) -> 880675.58 | O11: 138222.8 | P11: ='March New PAYE '!Z80 -> 157422.8 | Q11: =P11-O11 -> 19200 | R11: 49654.047 | S11: =O11+N11+M11+L11+K11+R11 -> 187876.85 | T11: 692798.73 | U11: =J11-S11 -> 692798.73
A12: 6 | B12: DR FRANCIS NDUM OJIE | C12: AD, TRAINING & IC./SA TO DG | D12: 15(7) | E12: 582118.08 | G12: 160000 | I12: =100000 -> 100000 | J12: =E12+F12+G12+H12+I12 -> 842118.08 | N12: 775.496 | O12: 131263.11 | P12: ='March New PAYE '!Z13 -> 150463.11 | Q12: =P12-O12 -> 19200 | R12: 46569.447 | S12: =O12+N12+M12+L12+K12+R12 -> 178608.05 | T12: 663510.03 | U12: =J12-S12 -> 663510.03
A13: 7 | B13: DORIS DAKDA AARON | C13: RESEARCH FELLOW I | D13: 14(8) | E13: 442746.5 | G13: =140000 -> 140000 | I13: 150000 | J13: =E13+F13+G13+H13+I13 -> 732746.5 | L13: 70000 | O13: 112553.41 | P13: ='March New PAYE '!Z16 -> 131753.41 | Q13: =P13-O13 -> 19200 | R13: 35419.72 | S13: =O13+N13+M13+L13+K13+R13 -> 217973.13 | T13: 514773.37 | U13: =J13-S13 -> 514773.37
A14: 8 | B14: HASSANA AHMED IBRAHIM | C14: PA- TO DG | D14: 13 (9) | E14: 416026.92 | G14: =120000 -> 120000 | I14: =100000 -> 100000 | J14: =E14+F14+G14+H14+I14 -> 636026.92 | L14: =30000-20000 -> 10000 | M14: =95833.33 -> 95833.33 | N14: 618.5315 | O14: 94274.903 | P14: ='March New PAYE '!Z19 -> 113474.9 | Q14: =P14-O14 -> 19200 | R14: 33282.153 | S14: =O14+N14+M14+L14+K14+R14 -> 234008.92 | T14: 402018 | U14: =J14-S14 -> 402018
A15: 9 | B15: LUCKY AGWOM | C15: RESEARCH ASSISTANT | D15: 12(7) | E15: 353512.5 | G15: =100000 -> 100000 | I15: 100000 | J15: =E15+F15+G15+H15+I15 -> 553512.5 | L15: 50000 | O15: 79511.115 | P15: ='March New PAYE '!Z21 -> 98711.115 | Q15: =P15-O15 -> 19200 | R15: 28281 | S15: =O15+N15+M15+L15+K15+R15 -> 157792.11 | T15: 395720.39 | U15: =J15-S15 -> 395720.39
A16: 10 | B16: FARUQ ATOFARATI | C16: PA (SPECIAL DUTIES) TO DG | D16: 10(7) | E16: 293029.67 | H16: =50000+10000 -> 60000 | I16: 100000 | J16: =E16+F16+G16+H16+I16 -> 453029.67 | O16: 61147.427 | P16: ='March New PAYE '!Z23 -> 80347.427 | Q16: =P16-O16 -> 19200 | R16: 23442.373 | S16: =O16+N16+M16+L16+K16+R16 -> 84589.8 | T16: 368439.87 | U16: =J16-S16 -> 368439.87
B17: TOTAL | C17: 10 | E17: 14898686 | G17: =SUM(#REF!) -> #REF! | H17: =SUM(#REF!) -> #REF! | I17: =SUM(#REF!) -> #REF! | J17: =SUM(#REF!) -> #REF! | K17: =SUM(#REF!) -> #REF! | L17: =SUM(#REF!) -> #REF! | M17: =SUM(#REF!) -> #REF! | N17: 6347.233 | O17: =SUM(O7:O16) -> 1249037.2 | P17: =SUM(P7:P16) -> 1441037.2 | Q17: =SUM(Q7:Q16) -> 192000 | R17: 1130905.1 | S17: =SUM(#REF!) -> #REF! | T17: 11108681 | U17: =SUM(#REF!) -> #REF!
J19: PREPARED BY: Rahila N. Habu SIGNATURE……………….. DATE: 29TH JANUARY, 2024

Sheet March New PAYE 
A1: NATIONAL INSTITUTE FOR LEGISLATIVE AND DEMOCRATIC STUDIES
A2: NATIONAL ASSEMBLY ABUJA
A3: TAX COMPUTATION FOR 2022
A4: S/NO | B4: NAME | C4: MONTHLY TOTAL SALARY | D4: NO OF MONTHS | E4: ANNUAL SALARY GROSSED UP | F4: NATIONAL HOUSING SCHEME = 2.5% OF BASIC SALARY | G4: PENSION CONTRIBUTION = 8% OF CONSOLIDATED | H4: NHIS | I4: NET SALARY (EXC OF CRA) | M4: CRA=#200,000+(20% 0F NET SALARY (EXC OF CRA) | N4: TOTAL RELIEF | O4: CHARGEABLE INCOME | P4: FIRST N300,000 @ 7% | Q4: NEXT N300,000 @ 11% | R4: NEXT N500,000 @ 15% | S4: NEXT N500,000@ 19% | T4: NEXT N1,600,000 @ 21% | U4: ABOVE N3,200,000 @ 24% | V4: ANNUAL TAX PAYABLE | X4: MONTHLY TAX PAYABLE | Y4: MINIMUM TAX PAYABLE | Z4: NEW ACTUAL TAX PAYABLE | AB4: Difference
A5: 1 | B5: DG'S OFFICE
A6: 3 | B6: PROF. ABUBAKAR O. SULAIMAN | C6: 1934986.2 | D6: 12 | E6: =C6*D6 -> 23219834 | I6: =E6-F6-G6-H6 -> 23219834 | J6: 200000 | K6: 0.2 | L6: =I6*K6 -> 4643966.8 | M6: =J6+L6 -> 4843966.8 | N6: =F6+G6+H6+M6 -> 4843966.8 | O6: =E6-N6 -> 18375867 | P6: =IF(O6<300000,0.07*O6,21000) -> 21000 | Q6: =IF((O6-300000)<0,0,IF((O6-300000)<300000,0.11*(O6-300000),33000)) -> 33000 | R6: =IF((O6-600000)<0,0,IF((O6-600000)<500000,0.15*(O6-600000),75000)) -> 75000 | S6: =IF((O6-1100000)<0,0,IF((O6-1100000)<500000,0.19*(O6-1100000),95000)) -> 95000 | T6: =IF((O6-1600000)<0,0,IF((O6-1600000)<1600000,0.21*(O6-1600000),336000)) -> 336000 | U6: =24%*(O6-3200000) -> 3642208.1 | V6: =P6+Q6+R6+S6+T6+U6 -> 4202208.1 | W6: 12 | X6: =V6/W6 -> 350184.01 | Z6: =X6 -> 350184.01 | AA6: 201165.84 | AB6: =Z6-AA6 -> 149018.17
A7: 4 | B7: RAHEEM USMAN AYIGORO | C7: =852373.166666667+100000 -> 952373.17 | D7: 12 | E7: =C7*D7 -> 11428478 | G7: 731878.24 | I7: =E7-F7-G7-H7 -> 10696600 | J7: 200000 | K7: 0.2 | L7: =I7*K7 -> 2139320 | M7: =J7+L7 -> 2339320 | N7: =F7+G7+H7+M7 -> 3071198.2 | O7: =E7-N7 -> 8357279.8 | P7: =IF(O7<300000,0.07*O7,21000) -> 21000 | Q7: =IF((O7-300000)<0,0,IF((O7-300000)<300000,0.11*(O7-300000),33000)) -> 33000 | R7: =IF((O7-600000)<0,0,IF((O7-600000)<500000,0.15*(O7-600000),75000)) -> 75000 | S7: =IF((O7-1100000)<0,0,IF((O7-1100000)<500000,0.19*(O7-1100000),95000)) -> 95000 | T7: =IF((O7-1600000)<0,0,IF((O7-1600000)<1600000,0.21*(O7-1600000),336000)) -> 336000 | U7: =24%*(O7-3200000) -> 1237747.2 | V7: =P7+Q7+R7+S7+T7+U7 -> 1797747.2 | W7: 12 | X7: =V7/W7 -> 149812.26 | Z7: =X7 -> 149812.26 | AA7: 82627.951 | AB7: =Z7-AA7 -> 67184.311
A8: 5 | B8: MARIAM MOHAMMED BELLO | C8: =1052373.16666667+100000 -> 1152373.2 | D8: 12 | E8: =C8*D8 -> 13828478 | G8: 0 | I8: =E8-F8-G8-H8 -> 13828478 | J8: 200000 | K8: 0.2 | L8: =I8*K8 -> 2765695.6 | M8: =J8+L8 -> 2965695.6 | N8: =F8+G8+H8+M8 -> 2965695.6 | O8: =E8-N8 -> 10862782 | P8: =IF(O8<300000,0.07*O8,21000) -> 21000 | Q8: =IF((O8-300000)<0,0,IF((O8-300000)<300000,0.11*(O8-300000),33000)) -> 33000 | R8: =IF((O8-600000)<0,0,IF((O8-600000)<500000,0.15*(O8-600000),75000)) -> 75000 | S8: =IF((O8-1100000)<0,0,IF((O8-1100000)<500000,0.19*(O8-1100000),95000)) -> 95000 | T8: =IF((O8-1600000)<0,0,IF((O8-1600000)<1600000,0.21*(O8-1600000),336000)) -> 336000 | U8: =24%*(O8-3200000) -> 1839067.8 | V8: =P8+Q8+R8+S8+T8+U8 -> 2399067.8 | W8: 12 | X8: =V8/W8 -> 199922.31 | Z8: =X8 -> 199922.31 | AA8: 121027.95 | AB8: =Z8-AA8 -> 78894.363
A9: 6 | B9: DR IKEME ARTHUR J.O | C9: 942373.17 | D9: 12 | E9: =C9*D9 -> 11308478 | F9: ='[6]JANUARY 2024'!$V$10*12 -> 12795.951 | G9: 731878.24 | I9: =E9-F9-G9-H9 -> 10563804 | J9: 200000 | K9: 0.2 | L9: =I9*K9 -> 2112760.8 | M9: =J9+L9 -> 2312760.8 | N9: =F9+G9+H9+M9 -> 3057435 | O9: =E9-N9 -> 8251043 | P9: =IF(O9<300000,0.07*O9,21000) -> 21000 | Q9: =IF((O9-300000)<0,0,IF((O9-300000)<300000,0.11*(O9-300000),33000)) -> 33000 | R9: =IF((O9-600000)<0,0,IF((O9-600000)<500000,0.15*(O9-600000),75000)) -> 75000 | S9: =IF((O9-1100000)<0,0,IF((O9-1100000)<500000,0.19*(O9-1100000),95000)) -> 95000 | T9: =IF((O9-1600000)<0,0,IF((O9-1600000)<1600000,0.21*(O9-1600000),336000)) -> 336000 | U9: =24%*(O9-3200000) -> 1212250.3 | V9: =P9+Q9+R9+S9+T9+U9 -> 1772250.3 | W9: 12 | X9: =V9/W9 -> 147687.53 | Z9: =X9 -> 147687.53 | AA9: 99703.216 | AB9: =Z9-AA9 -> 47984.311
A10: 7 | B10: MOSHOOD M. OLALERE | C10: =1002373.16666667+100000 -> 1102373.2 | D10: 12 | E10: =C10*D10 -> 13228478 | F10: ='[6]JANUARY 2024'!$V$10*12 -> 12795.951 | G10: 731878.24 | I10: =E10-F10-G10-H10 -> 12483804 | J10: 200000 | K10: 0.2 | L10: =I10*K10 -> 2496760.8 | M10: =J10+L10 -> 2696760.8 | N10: =F10+G10+H10+M10 -> 3441435 | O10: =E10-N10 -> 9787043 | P10: =IF(O10<300000,0.07*O10,21000) -> 21000 | Q10: =IF((O10-300000)<0,0,IF((O10-300000)<300000,0.11*(O10-300000),33000)) -> 33000 | R10: =IF((O10-600000)<0,0,IF((O10-600000)<500000,0.15*(O10-600000),75000)) -> 75000 | S10: =IF((O10-1100000)<0,0,IF((O10-1100000)<500000,0.19*(O10-1100000),95000)) -> 95000 | T10: =IF((O10-1600000)<0,0,IF((O10-1600000)<1600000,0.21*(O10-1600000),336000)) -> 336000 | U10: =24%*(O10-3200000) -> 1580890.3 | V10: =P10+Q10+R10+S10+T10+U10 -> 2140890.3 | W10: 12 | X10: =V10/W10 -> 178407.53 | Z10: =X10 -> 178407.53 | AA10: 111223.22 | AB10: =Z10-AA10 -> 67184.311
A11: 8 | B11: REKIYA IBRAHIM ATTAH | C11: =952373.166666667+100000 -> 1052373.2 | D11: 12 | E11: =C11*D11 -> 12628478 | G11: 0 | I11: =E11-F11-G11-H11 -> 12628478 | J11: 200000 | K11: 0.2 | L11: =I11*K11 -> 2525695.6 | M11: =J11+L11 -> 2725695.6 | N11: =F11+G11+H11+M11 -> 2725695.6 | O11: =E11-N11 -> 9902782.4 | P11: =IF(O11<300000,0.07*O11,21000) -> 21000 | Q11: =IF((O11-300000)<0,0,IF((O11-300000)<300000,0.11*(O11-300000),33000)) -> 33000 | R11: =IF((O11-600000)<0,0,IF((O11-600000)<500000,0.15*(O11-600000),75000)) -> 75000 | S11: =IF((O11-1100000)<0,0,IF((O11-1100000)<500000,0.19*(O11-1100000),95000)) -> 95000 | T11: =IF((O11-1600000)<0,0,IF((O11-1600000)<1600000,0.21*(O11-1600000),336000)) -> 336000 | U11: =24%*(O11-3200000) -> 1608667.8 | V11: =P11+Q11+R11+S11+T11+U11 -> 2168667.8 | W11: 12 | X11: =V11/W11 -> 180722.31 | Z11: =X11 -> 180722.31 | AA11: 101827.95 | AB11: =Z11-AA11 -> 78894.363
A12: 9 | B12: ANDRAWUS MUSA | C12: 750675.58 | D12: 12 | E12: =C12*D12 -> 9008107 | F12: ='[6]JANUARY 2024'!$V$13*12 -> 10052.25 | G12: 595848.56 | I12: =E12-F12-G12-H12 -> 8402206.2 | J12: 200000 | K12: 0.2 | L12: =I12*K12 -> 1680441.2 | M12: =J12+L12 -> 1880441.2 | N12: =F12+G12+H12+M12 -> 2486342 | O12: =E12-N12 -> 6521765 | P12: =IF(O12<300000,0.07*O12,21000) -> 21000 | Q12: =IF((O12-300000)<0,0,IF((O12-300000)<300000,0.11*(O12-300000),33000)) -> 33000 | R12: =IF((O12-600000)<0,0,IF((O12-600000)<500000,0.15*(O12-600000),75000)) -> 75000 | S12: =IF((O12-1100000)<0,0,IF((O12-1100000)<500000,0.19*(O12-1100000),95000)) -> 95000 | T12: =IF((O12-1600000)<0,0,IF((O12-1600000)<1600000,0.21*(O12-1600000),336000)) -> 336000 | U12: =24%*(O12-3200000) -> 797223.59 | V12: =P12+Q12+R12+S12+T12+U12 -> 1357223.6 | W12: 12 | X12: =V12/W12 -> 113101.97 | Z12: =X12 -> 113101.97 | AA12: 74036.103 | AB12: =Z12-AA12 -> 39065.863
A13: 10 | B13: DR FRANCIS NDUM OJIE | C13: =842118.083333333+100000 -> 942118.08 | D13: 12 | E13: =C13*D13 -> 11305417 | F13: ='[6]JANUARY 2024'!$V$14*12 -> 9305.952 | G13: 558833.36 | I13: =E13-F13-G13-H13 -> 10737278 | J13: 200000 | K13: 0.2 | L13: =I13*K13 -> 2147455.5 | M13: =J13+L13 -> 2347455.5 | N13: =F13+G13+H13+M13 -> 2915594.8 | O13: =E13-N13 -> 8389822.2 | P13: =IF(O13<300000,0.07*O13,21000) -> 21000 | Q13: =IF((O13-300000)<0,0,IF((O13-300000)<300000,0.11*(O13-300000),33000)) -> 33000 | R13: =IF((O13-600000)<0,0,IF((O13-600000)<500000,0.15*(O13-600000),75000)) -> 75000 | S13: =IF((O13-1100000)<0,0,IF((O13-1100000)<500000,0.19*(O13-1100000),95000)) -> 95000 | T13: =IF((O13-1600000)<0,0,IF((O13-1600000)<1600000,0.21*(O13-1600000),336000)) -> 336000 | U13: =24%*(O13-3200000) -> 1245557.3 | V13: =P13+Q13+R13+S13+T13+U13 -> 1805557.3 | W13: 12 | X13: =V13/W13 -> 150463.11 | Z13: =X13 -> 150463.11 | AA13: 94625.782 | AB13: =Z13-AA13 -> 55837.328
A14: 11 | B14: ALI ABDULLAHI | C14: 554373.75 | D14: 12 | E14: =C14*D14 -> 6652485 | G14: 464998.8 | I14: =E14-F14-G14-H14 -> 6187486.2 | J14: 200000 | K14: 0.2 | L14: =I14*K14 -> 1237497.2 | M14: =J14+L14 -> 1437497.2 | N14: =F14+G14+H14+M14 -> 1902496 | O14: =E14-N14 -> 4749989 | P14: =IF(O14<300000,0.07*O14,21000) -> 21000 | Q14: =IF((O14-300000)<0,0,IF((O14-300000)<300000,0.11*(O14-300000),33000)) -> 33000 | R14: =IF((O14-600000)<0,0,IF((O14-600000)<500000,0.15*(O14-600000),75000)) -> 75000 | S14: =IF((O14-1100000)<0,0,IF((O14-1100000)<500000,0.19*(O14-1100000),95000)) -> 95000 | T14: =IF((O14-1600000)<0,0,IF((O14-1600000)<1600000,0.21*(O14-1600000),336000)) -> 336000 | U14: =24%*(O14-3200000) -> 371997.35 | V14: =P14+Q14+R14+S14+T14+U14 -> 931997.35 | W14: 12 | X14: =V14/W14 -> 77666.446 | Z14: =X14 -> 77666.446 | AA14: 44846.617 | AB14: =Z14-AA14 -> 32819.829
A15: 12 | B15: EMILY EKHIDE | C15: =660498 -> 660498 | D15: 12 | E15: =C15*D15 -> 7925976 | G15: 451678.08 | I15: =E15-F15-G15-H15 -> 7474297.9 | J15: 200000 | K15: 0.2 | L15: =I15*K15 -> 1494859.6 | M15: =J15+L15 -> 1694859.6 | N15: =F15+G15+H15+M15 -> 2146537.7 | O15: =E15-N15 -> 5779438.3 | P15: =IF(O15<300000,0.07*O15,21000) -> 21000 | Q15: =IF((O15-300000)<0,0,IF((O15-300000)<300000,0.11*(O15-300000),33000)) -> 33000 | R15: =IF((O15-600000)<0,0,IF((O15-600000)<500000,0.15*(O15-600000),75000)) -> 75000 | S15: =IF((O15-1100000)<0,0,IF((O15-1100000)<500000,0.19*(O15-1100000),95000)) -> 95000 | T15: =IF((O15-1600000)<0,0,IF((O15-1600000)<1600000,0.21*(O15-1600000),336000)) -> 336000 | U15: =24%*(O15-3200000) -> 619065.2 | V15: =P15+Q15+R15+S15+T15+U15 -> 1179065.2 | W15: 12 | X15: =V15/W15 -> 98255.433 | Z15: =X15 -> 98255.433 | AA15: 46666.667 | AB15: =Z15-AA15 -> 51588.767
A16: 13 | B16: DORIS DAKDA AARON | C16: =732746.5+100000 -> 832746.5 | D16: 12 | E16: =C16*D16 -> 9992958 | G16: 425036.64 | I16: =E16-F16-G16-H16 -> 9567921.4 | J16: 200000 | K16: 0.2 | L16: =I16*K16 -> 1913584.3 | M16: =J16+L16 -> 2113584.3 | N16: =F16+G16+H16+M16 -> 2538620.9 | O16: =E16-N16 -> 7454337.1 | P16: =IF(O16<300000,0.07*O16,21000) -> 21000 | Q16: =IF((O16-300000)<0,0,IF((O16-300000)<300000,0.11*(O16-300000),33000)) -> 33000 | R16: =IF((O16-600000)<0,0,IF((O16-600000)<500000,0.15*(O16-600000),75000)) -> 75000 | S16: =IF((O16-1100000)<0,0,IF((O16-1100000)<500000,0.19*(O16-1100000),95000)) -> 95000 | T16: =IF((O16-1600000)<0,0,IF((O16-1600000)<1600000,0.21*(O16-1600000),336000)) -> 336000 | U16: =24%*(O16-3200000) -> 1021040.9 | V16: =P16+Q16+R16+S16+T16+U16 -> 1581040.9 | W16: 12 | X16: =V16/W16 -> 131753.41 | Z16: =X16 -> 131753.41 | AA16: 46666.667 | AB16: =Z16-AA16 -> 85086.742
A17: 14 | B17: ABDULSALAM S. MUSTAPHA | C17: 511804.92 | D17: 12 | E17: =C17*D17 -> 6141659 | G17: 424132.72 | I17: =E17-F17-G17-H17 -> 5717526.3 | J17: 200000 | K17: 0.2 | L17: =I17*K17 -> 1143505.3 | M17: =J17+L17 -> 1343505.3 | N17: =F17+G17+H17+M17 -> 1767638 | O17: =E17-N17 -> 4374021 | P17: =IF(O17<300000,0.07*O17,21000) -> 21000 | Q17: =IF((O17-300000)<0,0,IF((O17-300000)<300000,0.11*(O17-300000),33000)) -> 33000 | R17: =IF((O17-600000)<0,0,IF((O17-600000)<500000,0.15*(O17-600000),75000)) -> 75000 | S17: =IF((O17-1100000)<0,0,IF((O17-1100000)<500000,0.19*(O17-1100000),95000)) -> 95000 | T17: =IF((O17-1600000)<0,0,IF((O17-1600000)<1600000,0.21*(O17-1600000),336000)) -> 336000 | U17: =24%*(O17-3200000) -> 281765.05 | V17: =P17+Q17+R17+S17+T17+U17 -> 841765.05 | W17: 12 | X17: =V17/W17 -> 70147.087 | Z17: =X17 -> 70147.087 | AA17: 42046.064 | AB17: =Z17-AA17 -> 28101.023
