Workbook

Sheet APRIL 2026
A1: NATIONAL INSTITUTE FOR LEGISLATIVE AND DEMOCRATIC STUDIES
A2: STAFF PAYROLL FOR THE MONTH OF APRIL 2026
E3: ='[1]FEB 08'!E11/'[1]FEB 08'!M11 -> #REF!
B4: STAFF NAME | C4: DESIGNATION | D4: GRADE LEVEL | E4: BASIC SALARY | F4: ALLCE/ AREARS | G4: ALLOWANCE | H4: ALLOWANCE | I4: DUTY ALLCE | J4: GROSS SALARY | K4: AUCTION | L4: COOP 1 CONTR/SPEC SAVINGS | M4: COOP 1 LOAN RECOVERY | N4: COOP 2 CONTR/SPEC SAVINGS | O4: COOP 2 LOAN RECOVERY | P4: NHF DED. | Q4: PAYE | R4: EMPLOYEE PENSIONS | S4: TOTAL DEDUCTION | T4: MARCH, 2026 | U4: APRIL, 2026
E5: N | F5: N | G5: N | H5: N | I5: N | J5: N | K5: N | L5: N | M5: N | N5: N | P5: N | Q5: N | R5: N | S5: N | T5: N | U5: N
A6: S/N | B6: DG'S OFFICE
A7: 1 | B7: PROF. ABUBAKAR O. SULAIMAN | C7: DIRECTOR GENERAL | D7: CONSOL | E7: 1971137.1 | G7: =250000 -> 250000 | I7: 25235 | J7: =E7+F7+G7+H7+I7 -> 2246372.1 | P7: 0 | Q7: 427498.91 | S7: =SUM(K7:R7) -> 427498.91 | T7: 1818873.2 | U7: =J7-S7 -> 1818873.2
A8: 2 | B8: RAHEEM USMAN AYIGORO | C8: SA-INFRASTRUCTURE | D8: 16 (9) | E8: 905306.75 | H8: =90000 -> 90000 | I8: =100000 -> 100000 | J8: =E8+F8+G8+H8+I8 -> 1095306.8 | L8: =250000 -> 250000 | N8: 100000 | Q8: 167305.26 | R8: 72424.54 | S8: =SUM(K8:R8) -> 589729.8 | T8: 505576.95 | U8: =J8-S8 -> 505576.95
A9: 3 | B9: MARIAM MOHAMMED BELLO | C9: SA- SPECIAL DUTIES | D9: 16 (9) | E9: 905306.75 | H9: =90000 -> 90000 | I9: =200000+100000 -> 300000 | J9: =E9+F9+G9+H9+I9 -> 1295306.8 | P9: 0 | Q9: 224514.42 | S9: =SUM(K9:R9) -> 224514.42 | T9: 1070792.3 | U9: =J9-S9 -> 1070792.3
A10: 4 | B10: DR IKEME ARTHUR J.O | C10: DEPUTY DIRECTOR, M&E | D10: 16 (9) | E10: 905306.75 | G10: 180000 | I10: 0 | J10: =E10+F10+G10+H10+I10 -> 1085306.8 | L10: =50000 -> 50000 | P10: 13866.737 | Q10: 162322.79 | R10: 72424.54 | S10: =SUM(K10:R10) -> 298614.06 | T10: 786692.69 | U10: =J10-S10 -> 786692.69
A11: 5 | B11: ANDRAWUS MUSA | C11: DEP. DIRECTOR, STORES & PROCUREMENT | D11: 16(9) | E11: 905306.75 | H11: =90000 -> 90000 | I11: 50000 | J11: =E11+F11+G11+H11+I11 -> 1045306.8 | L11: =50000-40000 -> 10000 | M11: =90000+110000 -> 200000 | P11: 13866.737 | Q11: 155122.79 | R11: 72424.54 | S11: =SUM(K11:R11) -> 451414.06 | T11: 593892.69 | U11: =J11-S11 -> 593892.69
A12: 6 | B12: DR FRANCIS NDUM OJIE | C12: AD, TRAINING & IC./SA TO DG | D12: 15(9) | E12: 744477 | G12: 160000 | I12: =100000+100000 -> 200000 | J12: =E12+F12+G12+H12+I12 -> 1104477 | P12: 11475.263 | Q12: 169523.15 | R12: 59558.16 | S12: =SUM(K12:R12) -> 240556.57 | T12: 863920.43 | U12: =J12-S12 -> 863920.43
A13: 7 | B13: ALI ABDULLAHI | C13: ASST DIRECTOR ICT | D13: 15(7) | E13: 700713.92 | H13: =80000 -> 80000 | I13: =0 -> 0 | J13: =E13+F13+G13+H13+I13 -> 780713.92 | Q13: 112938.22 | R13: 56057.113 | S13: =SUM(K13:R13) -> 168995.34 | T13: 611718.58 | U13: =J13-S13 -> 611718.58
A14: 8 | B14: EMILY EKHIDE | C14: SENIOR RESEARCH FELLOW | D14: 15(9) | E14: 744477 | G14: 160000 | I14: =50000 -> 50000 | J14: =E14+F14+G14+H14+I14 -> 954477 | L14: =50000 -> 50000 | Q14: 143585.39 | R14: 59558.16 | S14: =SUM(K14:R14) -> 253143.55 | T14: 701333.45 | U14: =J14-S14 -> 701333.45
A15: 9 | B15: DORIS DAKDA AARON | C15: RESEARCH FELLOW I | D15: 14(10) | E15: 573911.08 | G15: =140000 -> 140000 | I15: =150000+100000 -> 250000 | J15: =E15+F15+G15+H15+I15 -> 963911.08 | L15: 150000 | M15: 0 | P15: 8926.6667 | Q15: 146132.88 | R15: 45912.887 | S15: =SUM(K15:R15) -> 350972.43 | T15: 612938.65 | U15: =J15-S15 -> 612938.65
A16: 10 | B16: ABDULSALAM S. MUSTAPHA | C16: ASST. DIRECTOR ICT | D16: 15(8) | E16: 722595.5 | H16: 80000 | I16: 50000 | J16: =E16+F16+G16+H16+I16 -> 852595.5 | N16: 10000 | O16: 57818.75 | Q16: 125561.81 | R16: 57807.64 | S16: =SUM(K16:R16) -> 251188.2 | T16: 601407.3 | U16: =J16-S16 -> 601407.3
A17: 11 | B17: PERCY TERFA GBAHABO | C17: RESEARCH FELLOW 1 | D17: 14(8) | E17: 542419.5 | G17: =140000 -> 140000 | I17: 0 | J17: =E17+F17+G17+H17+I17 -> 682419.5 | Q17: 97524.669 | R17: 43393.56 | S17: =SUM(K17:R17) -> 140918.23 | T17: 541501.27 | U17: =J17-S17 -> 541501.27
A18: 12 | B18: HASSANA AHMED IBRAHIM | C18: PA- TO DG | D18: 13(11) | E18: 541351.33 | G18: =120000 -> 120000 | I18: =100000+100000 -> 200000 | J18: =E18+F18+G18+H18+I18 -> 861351.33 | L18: =30000-20000 -> 10000 | M18: =127777.78 -> 127777.78 | P18: 8443.2708 | Q18: 128227.99 | R18: 43308.107 | S18: =SUM(K18:R18) -> 317757.15 | T18: 543594.18 | U18: =J18-S18 -> 543594.18
A19: 13 | B19: IKIP LEBO | C19: ASST CHIEF PROC. OFFICER | D19: 13 (9) | E19: 512098.92 | H19: 70000 | J19: =E19+F19+G19+H19+I19 -> 582098.92 | L19: 50000 | M19: 250000 | P19: 8008.9771 | Q19: 78461.965 | R19: 40967.913 | S19: =SUM(K19:R19) -> 427438.86 | T19: 154660.06 | U19: =J19-S19 -> 154660.06
A20: 14 | B20: ALABI ADESINA MUHYDEEN | C20: HEAD, NILDS LIAISON OFFICE | D20: 13 (9) | E20: 512098.92 | G20: 120000 | J20: =E20+F20+G20+H20+I20 -> 632098.92 | Q20: 88903.581 | R20: 40967.913 | S20: =SUM(K20:R20) -> 129871.49 | T20: 502227.42 | U20: =J20-S20 -> 502227.42
A21: 15 | B21: BASSEY NSONGURUA UDOFIA | C21: PRINC.CONF SEC 1/PPS | D21: 13(8) | E21: 497472.75 | H21: =70000 -> 70000 | I21: =250000 -> 250000 | J21: =E21+F21+G21+H21+I21 -> 817472.75 | L21: 20000 | M21: =68750 -> 68750 | P21: 7791.8313 | Q21: 121078.96 | R21: 39797.82 | S21: =SUM(K21:R21) -> 257418.61 | T21: 560054.14 | U21: =J21-S21 -> 560054.14
A22: 16 | B22: ADUGBA RICHARD TERSEER | C22: ASSIST. CHIEF INFO OFFICER | D22: 13(7) | E22: 482846.58 | H22: =70000 -> 70000 | I22: =100000+50000 -> 150000 | J22: =E22+F22+G22+H22+I22 -> 702846.58 | L22: =10000 -> 10000 | M22: 292813.77 | P22: 7574.6854 | Q22: 100695.95 | R22: 38627.727 | S22: =SUM(K22:R22) -> 449712.13 | T22: 253134.45 | U22: =J22-S22 -> 253134.45
A23: 17 | B23: LUCKY AGWOM | C23: RESEARCH ASSISTANT | D23: 12(9) | E23: 468828.17 | G23: =100000 -> 100000 | I23: =100000+100000 -> 200000 | J23: =E23+F23+G23+H23+I23 -> 768828.17 | L23: =50000+100000 -> 150000 | Q23: 114137.94 | R23: 37506.253 | S23: =SUM(K23:R23) -> 301644.2 | T23: 467183.97 | U23: =J23-S23 -> 467183.97
A24: 18 | B24: IDRIS IBRAHIM | C24: PRINCIPAL RESEARCH OFFICER | D24: 12(9) | E24: 468828.17 | G24: 110000 | I24: 0 | J24: =E24+F24+G24+H24+I24 -> 578828.17 | L24: 0 | N24: 30000 | P24: 7366.5729 | Q24: 75611.961 | R24: 37506.253 | S24: =SUM(K24:R24) -> 150484.79 | T24: 428343.38 | U24: =J24-S24 -> 428343.38
A25: 19 | B25: FARUQ ATOFARATI | C25: PA (SPECIAL DUTIES) TO DG | D25: 10(8) | E25: 381140.67 | H25: =50000+10000 -> 60000 | I25: =100000+100000 -> 200000 | J25: =E25+F25+G25+H25+I25 -> 641140.67 | L25: 150000 | Q25: 92416.894 | R25: 30491.253 | S25: =SUM(K25:R25) -> 272908.15 | T25: 368232.52 | U25: =J25-S25 -> 368232.52
A26: 20 | B26: RASHEEDAT DAIBU | C26: SENIOR INFO. OFFICER | D26: 10(9) | E26: 390135.83 | H26: 60000 | J26: =E26+F26+G26+H26+I26 -> 450135.83 | L26: 50000 | N26: 10000 | P26: 6154.2792 | Q26: 56798.724 | R26: 31210.867 | S26: =SUM(K26:R26) -> 154163.87 | T26: 295971.96 | U26: =J26-S26 -> 295971.96
A27: 21 | B27: VICTOR ASUKWO | C27: SENIOR ICT OFFICER | D27: 10(7) | E27: 372145.33 | H27: =50000+10000 -> 60000 | J27: =E27+F27+G27+H27+I27 -> 432145.33 | P27: 5889.4458 | Q27: 53867.167 | R27: 29771.627 | S27: =SUM(K27:R27) -> 89528.239 | T27: 342617.09 | U27: =J27-S27 -> 342617.09
A28: 22 | B28: NNANDI LIVINUS ATURE | C28: SENIOR RESEARCH OFFICER | D28: 10(8) | E28: 381140.67 | G28: =110000 -> 110000 | J28: =E28+F28+G28+H28+I28 -> 491140.67 | L28: =10000 -> 10000 | M28: 127777.78 | P28: 6021.8646 | Q28: 59832.959 | R28: 30491.253 | S28: =SUM(K28:R28) -> 234123.86 | T28: 257016.81 | U28: =J28-S28 -> 257016.81
A29: 23 | B29: ABDULRAHMAN A SULAIMAN | C29: STORE OFFICER | D29: 9(9) | E29: 347016.17 | H29: =60000 -> 60000 | J29: =E29+F29+G29+H29+I29 -> 407016.17 | L29: =20000 -> 20000 | M29: =17500 -> 17500 | N29: 50000 | Q29: 50765.877 | R29: 27761.293 | S29: =SUM(K29:R29) -> 166027.17 | T29: 240989 | U29: =J29-S29 -> 240989
A30: 24 | B30: DARE SHEU MAGBON | C30: ADMINISTRATION OFFICER | D30: 9(9) | E30: 347016.17 | H30: =60000 -> 60000 | J30: =E30+F30+G30+H30+I30 -> 407016.17 | L30: =30000+20000 -> 50000 | M30: 0 | Q30: 50765.877 | R30: 27761.293 | S30: =SUM(K30:R30) -> 128527.17 | T30: 278489 | U30: =J30-S30 -> 278489
A31: 25 | B31: ABUBAKAR SULAIMAN SODEEQ | C31: SENIOR M&E OFFICER | D31: 10(8) | E31: 381140.67 | F31: 19969.64 | H31: 60000 | J31: =E31+F31+G31+H31+I31 -> 461110.31 | M31: 0 | P31: 5889.4458 | Q31: 55486.327 | R31: 30491.253 | S31: =SUM(K31:R31) -> 91867.026 | T31: 342617.09 | U31: =J31-S31 -> 369243.28
A32: 26 | B32: JIMOH ADEBAYO ZAKA | C32: SENIOR INFO OFFICER | D32: 10(7) | E32: 372145.33 | H32: 60000 | J32: =E32+F32+G32+H32+I32 -> 432145.33 | L32: =20000 -> 20000 | M32: =161429.76+39000+50000 -> 250429.76 | P32: 5889.4458 | Q32: 53867.167 | R32: 29771.627 | S32: =SUM(K32:R32) -> 359958 | T32: 72187.334 | U32: =J32-S32 -> 72187.334
A33: 27 | B33: ABDULMUSHIN TAWFIQ LADAN | C33: ICT OFFICER | D33: 9(9) | E33: 347016.17 | H33: =60000 -> 60000 | J33: =E33+F33+G33+H33+I33 -> 407016.17 | M33: 0 | Q33: 50765.877 | R33: 27761.293 | S33: =SUM(K33:R33) -> 78527.171 | T33: 328489 | U33: =J33-S33 -> 328489
A34: 28 | B34: MOHAMMED BELLO | C34: SENIOR PROTOCOL OFFICER | D34: 10(7) | E34: 372145.33 | H34: 60000 | J34: =E34+F34+G34+H34+I34 -> 432145.33 | L34: =0 -> 0 | Q34: 54927.267 | R34: 29771.627 | S34: =SUM(K34:R34) -> 84698.894 | T34: 347446.44 | U34: =J34-S34 -> 347446.44
A35: 29 | B35: HOLINESS PAUL UDO | C35: ADMINISTRATION OFFICER, M&E | D35: 9(8) | E35: 338711.67 | H35: =60000 -> 60000 | J35: =E35+F35+G35+H35+I35 -> 398711.67 | L35: 50000 | P35: 5443.3354 | Q35: 45410.852 | R35: 27096.933 | S35: =SUM(K35:R35) -> 127951.12 | T35: 270760.55 | U35: =J35-S35 -> 270760.55
A36: 30 | B36: CHARITY UDO AKAN | C36: ADMINISTRATION OFFICER, M&E | D36: 9(8) | E36: 338711.67 | H36: =60000 -> 60000 | J36: =E36+F36+G36+H36+I36 -> 398711.67 | L36: 50000 | M36: 60625 | P36: 5443.3354 | Q36: 43010.852 | R36: 27096.933 | S36: =SUM(K36:R36) -> 186176.12 | T36: 223335.55 | U36: =J36-S36 -> 212535.55
A37: 31 | B37: SANI UMAR IBRAHIM | C37: STORE OFFICER | D37: 9(8) | E37: 338711.67 | H37: =60000 -> 60000 | J37: =E37+F37+G37+H37+I37 -> 398711.67 | Q37: 49390.652 | R37: 27096.933 | S37: =SUM(K37:R37) -> 76487.585 | T37: 322224.08 | U37: =J37-S37 -> 322224.08
A38: 32 | B38: FAHAD ABUBUKAR LONGMAN | C38: ICT OFFICER | D38: 9(8) | E38: 338711.67 | H38: =60000 -> 60000 | J38: =E38+F38+G38+H38+I38 -> 398711.67 | P38: 5443.3354 | Q38: 48410.852 | R38: 27096.933 | S38: =SUM(K38:R38) -> 80951.12 | T38: 317760.55 | U38: =J38-S38 -> 317760.55
A39: 33 | B39: HARUNA JIBRIL AMEH | C39: ASST. ADMIN. OFFICER | D39: 8(10) | E39: 308920.67 | H39: 50000 | J39: =E39+F39+G39+H39+I39 -> 358920.67 | L39: 20000 | M39: 22916.66 | P39: 5013.7354 | Q39: 41754.79 | R39: 24713.653 | S39: =SUM(K39:R39) -> 114398.84 | T39: 267438.49 | U39: =J39-S39 -> 244521.83
A40: 34 | B40: RAMATU IBRAHIM ABDULRAHEEM | C40: INFORMATION OFFICER | D40: 8(9) | E40: 301910.75 | H40: 50000 | J40: =E40+F40+G40+H40+I40 -> 351910.75 | L40: 50000 | M40: 45833.33 | N40: 50000 | P40: 4909.1104 | Q40: 40612.78 | R40: 24152.86 | S40: =SUM(K40:R40) -> 215508.08 | T40: 136402.67 | U40: =J40-S40 -> 136402.67
A41: 35 | B41: EDIDIONG EZEKIEL ATAT | C41: ASSIST PROCUREMENT OFFICER | D41: 8(8) | E41: 294900.83 | H41: =50000 -> 50000 | J41: =E41+F41+G41+H41+I41 -> 344900.83 | L41: 10000 | M41: 66666.67 | P41: 4804.4854 | Q41: 39470.771 | R41: 23592.067 | S41: =SUM(K41:R41) -> 144533.99 | T41: 200366.84 | U41: =J41-S41 -> 200366.84
A42: 36 | B42: MAHMUD ADEWOLE HASSAN | C42: ASSIST ICT OFFICER | D42: 8(8) | E42: 294900.83 | H42: =50000 -> 50000 | J42: =E42+F42+G42+H42+I42 -> 344900.83 | N42: 70000 | Q42: 40335.578 | R42: 23592.067 | S42: =SUM(K42:R42) -> 133927.64 | T42: 210973.19 | U42: =J42-S42 -> 210973.19
A43: 37 | B43: YUSUF KABIRU TURAKI | C43: ASSIST ICT OFFICER | D43: 8(8) | E43: 294900.83 | H43: =50000 -> 50000 | J43: =E43+F43+G43+H43+I43 -> 344900.83 | Q43: 40335.578 | R43: 23592.067 | S43: =SUM(K43:R43) -> 63927.645 | T43: 280973.19 | U43: =J43-S43 -> 280973.19
A44: 38 | B44: FATIMA OMAR IBRAHIM | C44: ASSIST PROTOCOL OFFICER | D44: 8(8) | E44: 294900.83 | H44: =50000 -> 50000 | J44: =E44+F44+G44+H44+I44 -> 344900.83 | L44: 20000 | Q44: 40335.578 | R44: 23592.067 | S44: =SUM(K44:R44) -> 83927.645 | T44: 260973.19 | U44: =J44-S44 -> 260973.19
A45: 39 | B45: EBERE ANASTHESIA IGWE | C45: ASSIST ICT OFFICER | D45: 8(8) | E45: 294900.83 | H45: =50000 -> 50000 | J45: =E45+F45+G45+H45+I45 -> 344900.83 | L45: 20000 | M45: 150000 | Q45: 40335.578 | R45: 23592.067 | S45: =SUM(K45:R45) -> 233927.64 | T45: 110973.19 | U45: =J45-S45 -> 110973.19
A46: 40 | B46: ALIYU GARBA LERE | C46: ASSIST INFORMATION OFFICER | D46: 8(8) | E46: 294900.83 | H46: =50000 -> 50000 | J46: =E46+F46+G46+H46+I46 -> 344900.83 | Q46: 40335.578 | R46: 23592.067 | S46: =SUM(K46:R46) -> 63927.645 | T46: 280973.19 | U46: =J46-S46 -> 280973.19
B47: TOTAL | C47: 40 | E47: =SUM(E7:E46) -> 20530608 | F47: =SUM(F7:F46) -> 19969.64 | G47: =SUM(G7:G46) -> 1590000 | H47: =SUM(H7:H46) -> 1820000 | I47: =SUM(I7:I46) -> 2025235 | J47: =E47+F47+G47+H47+I47 -> 25985813 | K47: =SUM(K7:K46) -> 0 | L47: =SUM(L7:L46) -> 1270000 | M47: =SUM(M7:M46) -> 1681090.8 | N47: =SUM(N7:N46) -> 320000 | O47: =SUM(O7:O46) -> 57818.75 | P47: =SUM(P7:P46) -> 148222.56 | Q47: =SUM(Q7:Q46) -> 3728382.2 | R47: =SUM(R7:R46) -> 1412333.2 | S47: =SUM(S7:S46) -> 8617847.4 | T47: 17375056 | U47: =SUM(U7:U46) -> 17367966
B49: INTERNAL AUDIT
A50: 1 | B50: OSANAIYE DAVID AKINYEMI | C50: DIRECTOR INTERNAL AUDIT | D50: 17(9) | E50: 1747106.4 | H50: =100000 -> 100000 | J50: =E50+F50+G50+H50+I50 -> 1847106.4 | K50: ='APRIL 2026'!F248 -> 0 | L50: =300000 -> 300000 | M50: =458333.33 -> 458333.33 | Q50: 311040.96 | R50: 139768.51 | S50: =SUM(K50:R50) -> 1209142.8 | T50: 637963.61 | U50: =J50-S50 -> 637963.61
A51: 2 | B51: EVELYN ETONKE AGAN | C51: ASST DIR AUDIT | D51: 15(8) | E51: 722595.5 | H51: =80000 -> 80000 | I51: 0 | J51: =E51+F51+G51+H51+I51 -> 802595.5 | L51: 50000 | Q51: 116561.81 | R51: 57807.64 | S51: =SUM(K51:R51) -> 224369.45 | T51: 578226.05 | U51: =J51-S51 -> 578226.05
A52: 3 | B52: JAMILA ABDUL | C52: SENIOR INTERNAL AUDITOR | D52: 10(9) | E52: 390135.83 | H52: =60000 -> 60000 | J52: =E52+F52+G52+H52+I52 -> 450135.83 | L52: =20000 -> 20000 | M52: 73333.33 | N52: 20000 | P52: 6154.2792 | Q52: 56798.724 | R52: 31210.867 | S52: =SUM(K52:R52) -> 207497.2 | T52: 215509.88 | U52: =J52-S52 -> 242638.63
A53: 4 | B53: IJEOMA EWELUKWA | C53: PRINCIPAL AUDIT OFFICER | D53: 12(8) | E53: 454993.58 | H53: =60000 -> 60000 | J53: =E53+F53+G53+H53+I53 -> 514993.58 | L53: =10000 -> 10000 | Q53: 68646.937 | R53: 36399.487 | S53: =SUM(K53:R53) -> 115046.42 | T53: 399947.16 | U53: =J53-S53 -> 399947.16
A54: 5 | B54: HASSAN ABDULHADI | C54: SENIOR INTERNAL AUDITOR | D54: 9(8) | E54: 338711.67 | H54: 60000 | J54: =E54+F54+G54+H54+I54 -> 398711.67 | L54: =100000 -> 100000 | O54: 77277.75 | P54: 5443.3354 | Q54: 44810.852 | R54: 27096.933 | S54: =SUM(K54:R54) -> 254628.87 | T54: 151282.8 | U54: =J54-S54 -> 144082.8
A55: 6 | B55: YUSUF YUSUF DAYYABU | C55: INERNAL AUDIT OFFICER | D55: 9(9) | E55: 347016.17 | H55: 60000 | J55: =E55+F55+G55+H55+I55 -> 407016.17 | L55: 20000 | M55: 98878.69 | P55: 5566.8646 | Q55: 49763.842 | R55: 27761.293 | S55: =SUM(K55:R55) -> 201970.69 | T55: 205045.48 | U55: =J55-S55 -> 205045.48
A56: 7 | B56: UDONSI QUEENETH CHIWENDU | C56: ASSIST PROGRAMME OFFICER | D56: 8(8) | E56: 294900.83 | H56: 50000 | J56: =E56+F56+G56+H56+I56 -> 344900.83 | L56: 100000 | O56: 20453.13 | Q56: 38685.578 | R56: 23592.067 | S56: =SUM(K56:R56) -> 182730.77 | T56: 162170.06 | U56: =J56-S56 -> 162170.06
C57: 7 | E57: =SUM(E50:E56) -> 4295460 | F57: =SUM(F50:F56) -> 0 | G57: =SUM(G50:G56) -> 0 | H57: =SUM(H50:H56) -> 470000 | I57: =SUM(I50:I56) -> 0 | J57: =E57+F57+G57+H57+I57 -> 4765460 | K57: =SUM(K50:K56) -> 0 | L57: =SUM(L50:L56) -> 600000 | M57: =SUM(M50:M56) -> 630545.35 | N57: =SUM(N50:N56) -> 20000 | O57: =SUM(O50:O56) -> 97730.88 | P57: =SUM(P50:P56) -> 17164.479 | Q57: =SUM(Q50:Q56) -> 686308.71 | R57: =SUM(R50:R56) -> 343636.8 | S57: =SUM(S50:S56) -> 2395386.2 | T57: 2350145 | U57: =SUM(U50:U56) -> 2370073.8
B59: LEG. SUPPORT SEVICES
A60: 1 | B60: BETHEL UZOMA IHUGBA | C60: AG. DIRECTOR, AEEP | D60: 17(8) | E60: 1697359.3 | G60: =200000 -> 200000 | J60: =E60+F60+G60+H60+I60 -> 1897359.3 | L60: =80000+23000+300000 -> 403000 | M60: =246905.96 -> 246905.96 | N60: 150000 | Q60: 322429.82 | R60: 135788.75 | S60: =SUM(K60:R60) -> 1258124.5 | T60: 639234.8 | U60: =J60-S60 -> 639234.8
A61: 2 | B61: OGUCHE SAMUEL | C61: DEPUTY DIRECTOR | D61: 16(7) | E61: =852711.083333 -> 852711.08 | G61: =180000 -> 180000 | J61: =E61+F61+G61+H61+I61 -> 1032711.1 | L61: =30000 -> 30000 | M61: 223059.88 | Q61: 157667.53 | R61: =0.08*E61 -> 68216.887 | S61: =SUM(K61:R61) -> 478944.29 | T61: 457273.57 | U61: =J61-S61 -> 553766.79
A62: 3 | B62: IBRAHIM USMAN | C62: SNR RESEARCH FELLOW | D62: 15(9) | E62: 744477 | G62: =140000+20000 -> 160000 | I62: 0 | J62: =E62+F62+G62+H62+I62 -> 904477 | N62: 50000 | O62: 30855 | P62: 11475.263 | Q62: 132519.84 | R62: 59558.16 | S62: =SUM(K62:R62) -> 284408.27 | T62: 620068.73 | U62: =J62-S62 -> 620068.73
A63: 4 | B63: DR MOHAMMED O. AMALI | C63: SNR RESEARCH FELLOW | D63: 15(9) | E63: 744477 | G63: =140000+20000 -> 160000 | J63: =E63+F63+G63+H63+I63 -> 904477 | L63: =15000 -> 15000 | M63: 198731.33 | N63: 27000 | Q63: 134585.39 | R63: 59558.16 | S63: =SUM(K63:R63) -> 434874.88 | T63: 496602.12 | U63: =J63-S63 -> 469602.12
A64: 5 | B64: YAHAYA SHAMSU | C64: SNR RESEARCH FELLOW | D64: 15(8) | E64: 722595.5 | G64: =160000 -> 160000 | J64: =E64+F64+G64+H64+I64 -> 882595.5 | N64: 20000 | P64: 0 | Q64: 130961.81 | R64: 57807.64 | S64: =SUM(K64:R64) -> 208769.45 | T64: 673826.05 | U64: =J64-S64 -> 673826.05
A65: 6 | B65: CHIDEBE MATHEW NWANKWO | C65: SNR RESEARCH FELLOW | D65: 15(8) | E65: 722595.5 | G65: =160000 -> 160000 | J65: =E65+F65+G65+H65+I65 -> 882595.5 | L65: 100000 | P65: 0 | Q65: 130961.81 | R65: 57807.64 | S65: =SUM(K65:R65) -> 288769.45 | T65: 593826.05 | U65: =J65-S65 -> 593826.05
A66: 7 | B66: UMAR MUSA PADAH | C66: PRINC. RESEARCH OFFICER | D66: 12(8) | E66: 454993.58 | G66: =110000 -> 110000 | J66: =E66+F66+G66+H66+I66 -> 564993.58 | N66: 20000 | Q66: 77646.937 | R66: 36399.487 | S66: =SUM(K66:R66) -> 134046.42 | T66: 430947.16 | U66: =J66-S66 -> 430947.16
A67: 8 | B67: BILKIS S. LAWAL-GAMBARI | C67: RESEARCH OFFICER | D67: 10(10) | E67: 399131.17 | G67: 100000 | J67: =E67+F67+G67+H67+I67 -> 499131.17 | Q67: 66596.121 | R67: 31930.493 | S67: =SUM(K67:R67) -> 98526.615 | T67: 400604.55 | U67: =J67-S67 -> 400604.55
A68: 9 | B68: UMOH USENOBONG EMMANUEL | C68: SENIOR RESEARCH OFFICER | D68: 10(8) | E68: 381140.67 | G68: =100000 -> 100000 | J68: =E68+F68+G68+H68+I68 -> 481140.67 | Q68: 63616.894 | R68: 30491.253 | S68: =SUM(K68:R68) -> 94108.148 | T68: 387032.52 | U68: =J68-S68 -> 387032.52
A69: 10 | B69: ZAINAB AKINDE | C69: RESEARCH OFFICER | D69: 9(10) | E69: 355320.67 | G69: =100000 -> 100000 | J69: =E69+F69+G69+H69+I69 -> 455320.67 | Q69: 59341.102 | R69: 28425.653 | S69: =SUM(K69:R69) -> 87766.756 | T69: 367553.91 | U69: =J69-S69 -> 367553.91
A70: 11 | B70: GUNAT NANSAK MARK | C70: RESEARCH OFFICER | D70: 9(10) | E70: 355320.67 | G70: =100000 -> 100000 | J70: =E70+F70+G70+H70+I70 -> 455320.67 | Q70: 59341.102 | R70: 28425.653 | S70: =SUM(K70:R70) -> 87766.756 | T70: 367553.91 | U70: =J70-S70 -> 367553.91
A71: 12 | B71: MANDU ESSIEN NDEM | C71: RESEARCH OFFICER | D71: 9(8) | E71: 338711.67 | G71: =100000 -> 100000 | J71: =E71+F71+G71+H71+I71 -> 438711.67 | Q71: 56590.652 | R71: 27096.933 | S71: =SUM(K71:R71) -> 83687.585 | T71: 355024.08 | U71: =J71-S71 -> 355024.08
B72: TOTAL | C72: 12 | E72: =SUM(E60:E71) -> 7768833.8 | F72: =SUM(F60:F71) -> 0 | G72: =SUM(G60:G71) -> 1630000 | H72: =SUM(H60:H71) -> 0 | I72: =SUM(I60:I71) -> 0 | J72: =E72+F72+G72+H72+I72 -> 9398833.8 | K72: =SUM(K60:K71) -> 0 | L72: =SUM(L60:L71) -> 548000 | M72: =SUM(M60:M71) -> 668697.17 | N72: =SUM(N60:N71) -> 267000 | O72: =SUM(O60:O71) -> 30855 | P72: =SUM(P60:P71) -> 11475.263 | Q72: =SUM(Q60:Q71) -> 1392259 | R72: =SUM(R60:R71) -> 621506.71 | S72: =SUM(S60:S71) -> 3539793.2 | T72: 5789547.4 | U72: =SUM(U60:U71) -> 5859040.7
B74: LEGAL SERVICES
A75: 1 | B75: DR SHUAIBU DANWANKA | C75: DIRECTOR LEGAL SERVICES | D75: 17(9) | E75: 1747106.4 | G75: =200000 -> 200000 | I75: 0 | J75: =E75+F75+G75+H75+I75 -> 1947106.4 | L75: 250000 | N75: 500000 | P75: 0 | Q75: 332040.96 | R75: 139768.51 | S75: =SUM(K75:R75) -> 1221809.5 | T75: 725296.94 | U75: =J75-S75 -> 725296.94
A76: 2 | B76: ABDULSALAM BAKO | C76: DEP DIR., LEGAL SERVICES | D76: 16(7) | E76: 852711.08 | H76: 90000 | J76: =E76+F76+G76+H76+I76 -> 942711.08 | L76: 50000 | M76: 345000 | P76: 0 | Q76: 141467.53 | R76: 68216.887 | S76: =SUM(K76:R76) -> 604684.41 | T76: 249733.45 | U76: =J76-S76 -> 338026.67
B77: TOTAL | C77: 2 | E77: =SUM(E75:E76) -> 2599817.5 | F77: =SUM(F75:F76) -> 0 | G77: =SUM(G75:G76) -> 200000 | H77: =SUM(H75:H76) -> 90000 | I77: =SUM(I75:I76) -> 0 | J77: =E77+F77+G77+H77+I77 -> 2889817.5 | K77: =SUM(K75:K76) -> 0 | L77: =SUM(L75:L76) -> 300000 | M77: =SUM(M75:M76) -> 345000 | N77: =SUM(N75:N76) -> 500000 | O77: =SUM(O75:O76) -> 0 | P77: =SUM(P75:P76) -> 0 | Q77: =SUM(Q75:Q76) -> 473508.49 | R77: =SUM(R75:R76) -> 207985.4 | S77: =SUM(S75:S76) -> 1826493.9 | T77: 975030.39 | U77: =SUM(U75:U76) -> 1063323.6
B79: DEMOCRACY & GOVERNANCE
A80: 1 | B80: NGARA CHRISTOPHER OCHANJA | C80: DEP DIR DEM & GOVERNANCE | D80: 16(9) | E80: 905306.75 | G80: 180000 | I80: 0 | J80: =E80+F80+G80+H80+I80 -> 1085306.8 | L80: =100000 -> 100000 | M80: =163103.59 -> 163103.59 | P80: 13866.737 | Q80: 162322.79 | R80: 72424.54 | S80: =SUM(K80:R80) -> 511717.65 | T80: 573589.1 | U80: =J80-S80 -> 573589.1
A81: 2 | B81: EJALONIBU GANIYU LAYI | C81: RESEARCH FELLOW 1 | D81: 14(10) | E81: 573911.08 | G81: 140000 | J81: =E81+F81+G81+H81+I81 -> 713911.08 | L81: =110000+90000 -> 200000 | N81: 80000 | Q81: 102739.68 | R81: 45912.887 | S81: =SUM(K81:R81) -> 428652.56 | T81: 285258.52 | U81: =J81-S81 -> 285258.52
A82: 3 | B82: MARTINS SOLOMON UDOM | C82: RESEARCH FELLOW 2 | D82: 13(8) | E82: 497472.75 | G82: =120000 -> 120000 | I82: 0 | J82: =E82+F82+G82+H82+I82 -> 617472.75 | L82: 30000 | M82: 15000 | P82: 7791.8313 | Q82: 85078.958 | R82: 39797.82 | S82: =SUM(K82:R82) -> 177668.61 | T82: 439804.14 | U82: =J82-S82 -> 439804.14
A83: 4 | B83: ISHAKA DELE | C83: RESEARCH FELLOW 2 | D83: 13(8) | E83: 497472.75 | G83: =120000 -> 120000 | I83: 0 | J83: =E83+F83+G83+H83+I83 -> 617472.75 | L83: 100000 | N83: 50000 | P83: 7791.8313 | Q83: 85078.958 | R83: 39797.82 | S83: =SUM(K83:R83) -> 282668.61 | T83: 334804.14 | U83: =J83-S83 -> 334804.14
A84: 5 | B84: UDEFUNA NNADOZIE PATRICK | C84: RESEARCH FELLOW 2 | D84: 13(7) | E84: 482846.58 | G84: =120000 -> 120000 | I84: 0 | J84: =E84+F84+G84+H84+I84 -> 602846.58 | L84: 10000 | M84: =163196.67 -> 163196.67 | P84: 7571.9667 | Q84: 85241.783 | R84: 38627.727 | S84: =SUM(K84:R84) -> 304638.15 | T84: 298208.44 | U84: =J84-S84 -> 298208.44
A85: 6 | B85: SHAFIU YAHYA MIKAIL | C85: PRINCIPAL RESEARCH OFFICER | D85: 12(10) | E85: 482662.67 | G85: =110000 -> 110000 | I85: 0 | J85: =E85+F85+G85+H85+I85 -> 592662.67 | N85: 50000 | Q85: 82228.938 | R85: 38613.013 | S85: =SUM(K85:R85) -> 170841.95 | T85: 421820.72 | U85: =J85-S85 -> 421820.72
A86: 7 | B86: HASSAN YERIMA | C86: PRINCIPAL RESEARCH OFFICER | D86: 12(10) | E86: 482662.67 | G86: =110000 -> 110000 | I86: 0 | J86: =E86+F86+G86+H86+I86 -> 592662.67 | L86: =67000-2000 -> 65000 | N86: 40000 | Q86: 82228.938 | R86: 38613.013 | S86: =SUM(K86:R86) -> 225841.95 | T86: 366820.72 | U86: =J86-S86 -> 366820.72
A87: 8 | B87: HAUWA PATE SADIQ | C87: ASST CHIEF PROGRAMME OFFICER | D87: 13(7) | E87: 482846.58 | G87: =120000 -> 120000 | J87: =E87+F87+G87+H87+I87 -> 602846.58 | L87: =80000+20000 -> 100000 | N87: =40000 -> 40000 | Q87: 84059.394 | R87: 38627.727 | S87: =SUM(K87:R87) -> 262687.12 | T87: 340159.46 | U87: =J87-S87 -> 340159.46
A88: 9 | B88: OBOT ETIMBUK EMMANUEL | C88: PRINCIPAL INFO. OFFICER | D88: 12(8) | E88: 454993.58 | G88: 110000 | J88: =E88+F88+G88+H88+I88 -> 564993.58 | L88: 20000 | M88: 50000 | P88: 7161.1771 | Q88: 72757.926 | R88: 36399.487 | S88: =SUM(K88:R88) -> 186318.59 | T88: 385874.99 | U88: =J88-S88 -> 378674.99
A89: 10 | B89: KOLAPO Q. ABAYOMI | C89: PRINCIPAL RESEARCH OFFICER | D89: 12(7) | E89: 441159 | F89: 194278.67 | G89: 110000 | J89: =E89+F89+G89+H89+I89 -> 745437.67 | N89: 30000 | P89: 6286.6979 | Q89: =67329.53 -> 67329.53 | R89: 35292.72 | S89: =SUM(K89:R89) -> 138908.95 | T89: 217971.38 | U89: =J89-S89 -> 606528.72
A90: 11 | B90: SALIHU SHAMSUDEEN OPEYEMI | C90: PROGRAMME OFFICER | D90: 9(8) | E90: 338711.67 | G90: =100000 -> 100000 | J90: =E90+F90+G90+H90+I90 -> 438711.67 | N90: 50000 | Q90: 56590.652 | R90: 27096.933 | S90: =SUM(K90:R90) -> 133687.59 | T90: 305024.08 | U90: =J90-S90 -> 305024.08
B91: TOTAL | C91: 11 | E91: =SUM(E80:E90) -> 5640046.1 | F91: =SUM(F80:F90) -> 194278.67 | G91: =SUM(G80:G90) -> 1340000 | H91: =SUM(H80:H90) -> 0 | I91: =SUM(I80:I90) -> 0 | J91: =E91+F91+G91+H91+I91 -> 7174324.8 | K91: =SUM(K80:K90) -> 0 | L91: =SUM(L80:L90) -> 625000 | M91: =SUM(M80:M90) -> 391300.26 | N91: =SUM(N80:N90) -> 340000 | O91: =SUM(O80:O90) -> 0 | P91: =SUM(P80:P90) -> 50470.242 | Q91: =SUM(Q80:Q90) -> 965657.54 | R91: =SUM(R80:R90) -> 451203.69 | S91: =SUM(S80:S90) -> 2823631.7 | T91: 3969335.7 | U91: =SUM(U80:U90) -> 4350693
B93: DEPARTMENT OF STUDIES
A94: 1 | B94: DR ASIMIYU G. ABIOLA | C94: DIRECTOR POST GRADUATE | D94: 17(9) | E94: 1747106.4 | G94: =200000 -> 200000 | I94: 0 | J94: =E94+F94+G94+H94+I94 -> 1947106.4 | L94: 350000 | M94: =0 -> 0 | N94: 100000 | Q94: 332040.96 | R94: 139768.51 | S94: =SUM(K94:R94) -> 921809.47 | T94: 1025296.9 | U94: =J94-S94 -> 1025296.9
A95: 2 | B95: AYOBOLU OLAJIDE OLUFUNSHO | C95: ASSISTANT DIR. EXXAMS & RECORD | D95: 15(8) | E95: 722595.5 | G95: 160000 | J95: =E95+F95+G95+H95+I95 -> 882595.5 | L95: =50000 -> 50000 | M95: 240056.6 | Q95: 130961.81 | R95: 57807.64 | S95: =SUM(K95:R95) -> 478826.05 | T95: 403769.45 | U95: =J95-S95 -> 403769.45
A96: 3 | B96: DR. HADIZA SAIDU | C96: ASSISTANT DIRECTOR | D96: 15(8) | E96: 722595.5 | G96: 160000 | J96: =E96+F96+G96+H96+I96 -> 882595.5 | Q96: 130961.81 | R96: 57807.64 | S96: =SUM(K96:R96) -> 188769.45 | T96: 693826.05 | U96: =J96-S96 -> 693826.05
A97: 4 | B97: ANTHONY EDET | C97: CHIEF PROGRAMMES OFFICER | D97: 14(11) | E97: 589657 | G97: =140000 -> 140000 | I97: 0 | J97: =E97+F97+G97+H97+I97 -> 729657 | L97: 20000 | M97: 210785.51 | P97: 9160.4375 | Q97: 103698.32 | R97: 47172.56 | S97: =SUM(K97:R97) -> 390816.83 | T97: 338840.17 | U97: =J97-S97 -> 338840.17
A98: 5 | B98: CHRISTIAN MADUABUCHI ODO | C98: ASSIST. CHIEF ICT OFFICER | D98: 13(8) | E98: 497472.75 | G98: 120000 | J98: =E98+F98+G98+H98+I98 -> 617472.75 | P98: 7791.8313 | Q98: 85078.958 | R98: 39797.82 | S98: =SUM(K98:R98) -> 132668.61 | T98: 484804.14 | U98: =J98-S98 -> 484804.14
A99: 6 | B99: DR. IBANGA ISSAC JONAH | C99: ASSIST. CHIEF PROGRM OFFICER | D99: 13(8) | E99: 497472.75 | G99: =120000 -> 120000 | I99: 0 | J99: =E99+F99+G99+H99+I99 -> 617472.75 | L99: 100000 | M99: 50000 | N99: 100000 | Q99: 82581.487 | R99: 39797.82 | S99: =SUM(K99:R99) -> 372379.31 | T99: 252893.44 | U99: =J99-S99 -> 245093.44
A100: 7 | B100: IGWE STACY | C100: PRINC. PROGRAMME OFFICER | D100: 12(9) | E100: 468828.17 | G100: =110000 -> 110000 | J100: =E100+F100+G100+H100+I100 -> 578828.17 | L100: =50000 -> 50000 | M100: =50000 -> 50000 | P100: 7366.5729 | Q100: 78611.961 | R100: 37506.253 | S100: =SUM(K100:R100) -> 223484.79 | T100: 355343.38 | U100: =J100-S100 -> 355343.38
A101: 8 | B101: MUNIRU JIBRIN | C101: SENIOR PROGRAMME OFFICER | D101: 10(8) | E101: 381140.67 | G101: =100000 -> 100000 | J101: =E101+F101+G101+H101+I101 -> 481140.67 | L101: 50000 | Q101: 63616.894 | R101: 30491.253 | S101: =SUM(K101:R101) -> 144108.15 | T101: 337032.52 | U101: =J101-S101 -> 337032.52
A102: 9 | B102: OLANIYAN TAIWO ABINBOLA | C102: PROGRAMME OFFICER | D102: 9(9) | E102: 347016.17 | G102: 100000 | J102: =E102+F102+G102+H102+I102 -> 447016.17 | N102: 30000 | P102: 5566.8646 | Q102: 56963.842 | R102: 27761.293 | S102: =SUM(K102:R102) -> 120292 | T102: 326724.17 | U102: =J102-S102 -> 326724.17
A103: 10 | B103: MUSA ALKASIM ADAMU | C103: PROGRAMME OFFICER | D103: 9(8) | E103: 338711.67 | G103: =100000 -> 100000 | J103: =E103+F103+G103+H103+I103 -> 438711.67 | L103: 10000 | M103: 30000 | Q103: 56590.652 | R103: 27096.933 | S103: =SUM(K103:R103) -> 123687.59 | T103: 315024.08 | U103: =J103-S103 -> 315024.08
A104: 11 | B104: AMINAT JUMOKE SULAIMON | C104: AST. PROGRAMME OFFICER | D104: 8(10) | E104: 308920.67 | G104: 100000 | H104: 0 | J104: =E104+F104+G104+H104+I104 -> 408920.67 | L104: 80000 | M104: 50000 | Q104: 51657.262 | R104: 24713.653 | S104: =SUM(K104:R104) -> 206370.92 | T104: 202549.75 | U104: =J104-S104 -> 202549.75
B105: TOTAL | C105: 11 | E105: =SUM(E94:E104) -> 6621517.2 | F105: =SUM(F94:F104) -> 0 | G105: =SUM(G94:G104) -> 1410000 | H105: =SUM(H94:H104) -> 0 | I105: =SUM(I94:I104) -> 0 | J105: =E105+F105+G105+H105+I105 -> 8031517.2 | K105: =SUM(K94:K104) -> 0 | L105: =SUM(L94:L104) -> 710000 | M105: =SUM(M94:M104) -> 630842.11 | N105: =SUM(N94:N104) -> 230000 | O105: =SUM(O94:O104) -> 0 | P105: =SUM(P94:P104) -> 29885.706 | Q105: =SUM(Q94:Q104) -> 1172764 | R105: =SUM(R94:R104) -> 529721.38 | S105: =SUM(S94:S104) -> 3303213.2 | T105: 4736104.1 | U105: =SUM(U94:U104) -> 4728304.1
...

Sheet MEMO
A2: NATIONAL INSTITUTE FOR LEGISLATIVE AND DEMOCRATIC STUDIES
A3: INTERNAL MEMO
A4: FROM : DEPUTY DIRECTOR, FINANCE AND ACCOUNTS
A5: THRU: DIRECTOR, FINANCE AND ACCOUNTS
A6: TO: DG
A7: 29TH JANUARY , 2021
A9: SUBJECT: PAYROLL FOR THE MONTH OF JANUARY, 2021
A10: Find below the details of NILDS Staff Payroll for the month of January, 2021
A13: TO: | C13: DIRECTOR, GENERAL
A14: THRU: | C14: DIRECTOR, FINANCE AND ACCOUNT
A15: FROM: | C15: DEPUTY DIRECTOR, FINANCE AND ACCOUNTS
A16: DATE: | C16: 24TH APRIL 2026
A18: SUBJECT: PAYROLL FOR THE MONTH OF APRIL 2026
A19: Find below the details of NILDS Staff Payroll for the Month of April 2026: | G19: NGN | H19: NGN
A20: GROSS SALARY FOR APRIL 2026 | H20: ='APRIL 2026'!J246 -> 1.1970445e+08
A22: DEDUCTIONS
A23: COOP SOCIETY 1 DEDUCTIONS ( CONTR.& SPEC. SAVINGS) | G23: ='APRIL 2026'!L246 -> 8015500
A24: COOP 1 LOAN RECOVERY | G24: ='APRIL 2026'!M246 -> 10754395
A25: COOP SOCIETY 2 DEDUCTIONS ( CONTR.& SPEC. SAVINGS) | G25: ='APRIL 2026'!N246 -> 3199000
A26: COOP 1 LOAN RECOVERY | G26: ='APRIL 2026'!O246 -> 1093983.8
A27: NHF DEDUCTIONS | G27: ='APRIL 2026'!P246 -> 689591.03
A28: PAYE DEDUCTIONS | G28: ='APRIL 2026'!Q246 -> 16728102
A29: PENSION DEDUCTIONS | G29: ='APRIL 2026'!R246 -> 7706696.7
A30: TOTAL DEDUCTIONS FOR APRIL 2026 | H30: =SUM(G23:G29) -> 48187269
A31: NET PAY AS PER APRIL 2026 PAYROLL | H31: =H20-H30 -> 71517177
A32: NET PAY AS PER MARCH 2026 PAYROLL | H32: ='APRIL 2026'!T246 -> 71998730
A33: NET INCREASE/ (DECREASE) IN PAY FOR APRIL 2026 | H33: =H31-H32 -> -481553.44
A34: ANALYSED AS FOLLOWS:
A35: Effect of Cooperative 1 Adjustments for April 2026 | H35: 552777.77
A36: Effect of Cooperative 2 Adjustments for April 2026 | H36: =41910-27128.75 -> 14781.25
A37: Effect of prorated payment to Dr. Maimuna Izah due to retirement | H37: 960092.25
A38: Effect of arrears of Annual Tax Relief from Charity Udo Akan & 5 others | H38: 54540.92
A39: Effect promotion of Dr. Samuel Oguche & 2 others | H39: -685455.22
A40: Effect of regularization of PAYE IFO Kolapo Abayomi | H40: -388557.34
A41: Effect of regularisation of steps IFO Abubakar Sodeeq | H41: -26626.19
H42: =SUM(H35:H41) -> 481553.44
E45: MARCH, 2026 | G45: APRIL, 2026
E46: No. of Staff | F46: N | G46: No. of Staff | H46: N
A47: 1 | B47: Director General's Office | E47: 32 | F47: ='APRIL 2026'!T47 -> 17375056 | G47: ='APRIL 2026'!C47 -> 40 | H47: ='APRIL 2026'!U47 -> 17367966
A48: 2 | B48: Internal Audit | E48: 3 | F48: ='APRIL 2026'!T57 -> 2350145 | G48: ='APRIL 2026'!C57 -> 7 | H48: ='APRIL 2026'!U57 -> 2370073.8
A49: 3 | B49: Legis. Support Services | E49: 11 | F49: ='APRIL 2026'!T72 -> 5789547.4 | G49: ='APRIL 2026'!C72 -> 12 | H49: ='APRIL 2026'!U72 -> 5859040.7
A50: 4 | B50: Legal Services | E50: 2 | F50: ='APRIL 2026'!T77 -> 975030.39 | G50: ='APRIL 2026'!C77 -> 2 | H50: ='APRIL 2026'!U77 -> 1063323.6
A51: 5 | B51: Democracy and Governance | E51: 12 | F51: ='APRIL 2026'!T91 -> 3969335.7 | G51: ='APRIL 2026'!C91 -> 11 | H51: ='APRIL 2026'!U91 -> 4350693
A52: 6 | B52: Studies | E52: 6 | F52: ='APRIL 2026'!T105 -> 4736104.1 | G52: ='APRIL 2026'!C105 -> 11 | H52: ='APRIL 2026'!U105 -> 4728304.1
A53: 7 | B53: Economic Dev. & Social Research | E53: 11 | F53: ='APRIL 2026'!T120 -> 6209038.4 | G53: ='APRIL 2026'!C120 -> 12 | H53: ='APRIL 2026'!U120 -> 6156538.4
A54: 8 | B54: Training & Int'l Cooperation | E54: 4 | F54: ='APRIL 2026'!T130 -> 2961824.2 | G54: ='APRIL 2026'!C130 -> 7 | H54: ='APRIL 2026'!U130 -> 2961824.2
A55: 9 | B55: Library & Documentation | E55: 7 | F55: ='APRIL 2026'!T144 -> 5317116 | G55: ='APRIL 2026'!C144 -> 11 | H55: ='APRIL 2026'!U144 -> 4133412.7
A56: 10 | B56: Leg. Center for Security Analysis | E56: 2 | F56: ='APRIL 2026'!T154 -> 2555346.3 | G56: ='APRIL 2026'!C154 -> 8 | H56: ='APRIL 2026'!U154 -> 2555346.3
A57: 11 | B57: Democracy Radio 104.9 | E57: 3 | F57: ='APRIL 2026'!T161 -> 1159855.4 | G57: 5 | H57: ='APRIL 2026'!U161 -> 1107855.4
A58: 12 | B58: Finance and Accounts | E58: 10 | F58: ='APRIL 2026'!T176 -> 4319455 | G58: ='APRIL 2026'!C176 -> 12 | H58: ='APRIL 2026'!U176 -> 4306914.1
A59: 13 | B59: Admin & Human Resource | E59: 61 | F59: ='APRIL 2026'!T245 -> 14280876 | G59: ='APRIL 2026'!C245 -> 66 | H59: ='APRIL 2026'!U245 -> 14555885
E60: =SUM(E47:E59) -> 164 | F60: =SUM(F47:F59) -> 71998730 | G60: 199 | H60: =SUM(H47:H59) -> 71517177
A62: The Director General is requested to consider and approve the payment of N71,517,176.77 to Guaranty Trust Bank, being the April 2026 Net Salary, N18,769,895.42 and N4,292,983.82 being NILDS Coop Society 1 and Coop Society 2 deductions for April 2026. N16,728,101.74 PAYE Tax Deductions from Staff Salary for the month of April 2026 and N689,591.03 being NHF deductions from staff for April 2026
A66: RAHILA NURUDEEN HABU
C170: =10000 -> 10000

Sheet Changes in PAYE (4)
A1: NATIONAL INSTITUTE FOR LEGISLATIVE AND DEMOCRATIC STUDIES
A2: NATIONAL ASSEMBLY ABUJA
A3: TAX COMPUTATION FOR 2022
A4: S/NO | B4: NAME | C4: N | D4: NO OF MONTHS | E4: ANNUAL SALARY GROSSED UP | F4: ANNUAL RENT RELIEF (20% MAX OF N500,000) | G4: NATIONAL HOUSING SCHEME = 2.5% OF BASIC SALARY | H4: PENSION CONTRIBUTION = 8% OF CONSOLIDATED | I4: NHIS | J4: TOTAL RELIEF | K4: CHARGEABLE INCOME | L4: ANNUAL TAX PAYABLE | N4: MONTHLY TAX PAYABLE | O4: OLD ACTUAL TAX PAYABLE | P4: INCREASE/DECREASE IN PAYE
A5: S/N | B5: DG'S OFFICE
A6: 1 | B6: PROF. ABUBAKAR O. SULAIMAN | C6: 2246372.1 | D6: 12 | E6: =C6*D6 -> 26956465 | H6: 0 | J6: =F6+G6+H6 -> 0 | K6: =E6-J6 -> 26956465 | L6: =IF(K6<=800000,0,IF(K6<=3000000,(K6-800000)*15%,IF(K6<=12000000,330000+(K6-3000000)*18%,IF(K6<=25000000,1950000+(K6-12000000)*21%,IF(K6<=50000000,4680000+(K6-25000000)*23%,10430000+(K6-50000000)*25%))))) -> 5129986.9 | M6: 12 | N6: =L6/M6 -> 427498.91 | O6: 427498.91 | P6: =N6-O6 -> 0
A7: 2 | B7: RAHEEM USMAN AYIGORO | C7: 1095306.8 | D7: 12 | E7: =C7*D7 -> 13143681 | G7: 0 | H7: 869094.48 | J7: =F7+G7+H7 -> 869094.48 | K7: =E7-J7 -> 12274587 | L7: =IF(K7<=800000,0,IF(K7<=3000000,(K7-800000)*15%,IF(K7<=12000000,330000+(K7-3000000)*18%,IF(K7<=25000000,1950000+(K7-12000000)*21%,IF(K7<=50000000,4680000+(K7-25000000)*23%,10430000+(K7-50000000)*25%))))) -> 2007663.2 | M7: 12 | N7: =L7/M7 -> 167305.26 | O7: 167305.26 | P7: =N7-O7 -> 0
A8: 3 | B8: MARIAM MOHAMMED BELLO | C8: 1295306.8 | D8: 12 | E8: =C8*D8 -> 15543681 | G8: 0 | H8: 0 | J8: =F8+G8+H8 -> 0 | K8: =E8-J8 -> 15543681 | L8: =IF(K8<=800000,0,IF(K8<=3000000,(K8-800000)*15%,IF(K8<=12000000,330000+(K8-3000000)*18%,IF(K8<=25000000,1950000+(K8-12000000)*21%,IF(K8<=50000000,4680000+(K8-25000000)*23%,10430000+(K8-50000000)*25%))))) -> 2694173 | M8: 12 | N8: =L8/M8 -> 224514.42 | O8: 224514.42 | P8: =N8-O8 -> 0
A9: 4 | B9: DR IKEME ARTHUR J.O | C9: 1085306.8 | D9: 12 | E9: =C9*D9 -> 13023681 | G9: 166400.85 | H9: 869094.48 | J9: =F9+G9+H9 -> 1035495.3 | K9: =E9-J9 -> 11988186 | L9: =IF(K9<=800000,0,IF(K9<=3000000,(K9-800000)*15%,IF(K9<=12000000,330000+(K9-3000000)*18%,IF(K9<=25000000,1950000+(K9-12000000)*21%,IF(K9<=50000000,4680000+(K9-25000000)*23%,10430000+(K9-50000000)*25%))))) -> 1947873.4 | M9: 12 | N9: =L9/M9 -> 162322.79 | O9: 162322.79 | P9: =N9-O9 -> 0
A10: 5 | B10: ANDRAWUS MUSA | C10: 1045306.8 | D10: 12 | E10: =C10*D10 -> 12543681 | G10: 166400.85 | H10: 869094.48 | J10: =F10+G10+H10 -> 1035495.3 | K10: =E10-J10 -> 11508186 | L10: =IF(K10<=800000,0,IF(K10<=3000000,(K10-800000)*15%,IF(K10<=12000000,330000+(K10-3000000)*18%,IF(K10<=25000000,1950000+(K10-12000000)*21%,IF(K10<=50000000,4680000+(K10-25000000)*23%,10430000+(K10-50000000)*25%))))) -> 1861473.4 | M10: 12 | N10: =L10/M10 -> 155122.79 | O10: 155122.79 | P10: =N10-O10 -> 0
A11: 6 | B11: DR FRANCIS NDUM OJIE | C11: 1104477 | D11: 12 | E11: =C11*D11 -> 13253724 | G11: 137703.15 | H11: 714697.92 | J11: =F11+G11+H11 -> 852401.07 | K11: =E11-J11 -> 12401323 | L11: =IF(K11<=800000,0,IF(K11<=3000000,(K11-800000)*15%,IF(K11<=12000000,330000+(K11-3000000)*18%,IF(K11<=25000000,1950000+(K11-12000000)*21%,IF(K11<=50000000,4680000+(K11-25000000)*23%,10430000+(K11-50000000)*25%))))) -> 2034277.8 | M11: 12 | N11: =L11/M11 -> 169523.15 | O11: 169523.15 | P11: =N11-O11 -> 0
A12: 7 | B12: ALI ABDULLAHI | C12: 780713.92 | D12: 12 | E12: =C12*D12 -> 9368567 | G12: 0 | H12: 672685.36 | J12: =F12+G12+H12 -> 672685.36 | K12: =E12-J12 -> 8695881.6 | L12: =IF(K12<=800000,0,IF(K12<=3000000,(K12-800000)*15%,IF(K12<=12000000,330000+(K12-3000000)*18%,IF(K12<=25000000,1950000+(K12-12000000)*21%,IF(K12<=50000000,4680000+(K12-25000000)*23%,10430000+(K12-50000000)*25%))))) -> 1355258.7 | M12: 12 | N12: =L12/M12 -> 112938.22 | O12: 112938.22 | P12: =N12-O12 -> -1.1641532e-10
A13: 8 | B13: EMILY EKHIDE | C13: 954477 | D13: 12 | E13: =C13*D13 -> 11453724 | G13: 0 | H13: 714697.92 | J13: =F13+G13+H13 -> 714697.92 | K13: =E13-J13 -> 10739026 | L13: =IF(K13<=800000,0,IF(K13<=3000000,(K13-800000)*15%,IF(K13<=12000000,330000+(K13-3000000)*18%,IF(K13<=25000000,1950000+(K13-12000000)*21%,IF(K13<=50000000,4680000+(K13-25000000)*23%,10430000+(K13-50000000)*25%))))) -> 1723024.7 | M13: 12 | N13: =L13/M13 -> 143585.39 | O13: 143585.39 | P13: =N13-O13 -> 0
A14: 9 | B14: DORIS DAKDA AARON | C14: 963911.08 | D14: 12 | E14: =C14*D14 -> 11566933 | G14: 107120 | H14: 550954.64 | J14: =F14+G14+H14 -> 658074.64 | K14: =E14-J14 -> 10908858 | L14: =IF(K14<=800000,0,IF(K14<=3000000,(K14-800000)*15%,IF(K14<=12000000,330000+(K14-3000000)*18%,IF(K14<=25000000,1950000+(K14-12000000)*21%,IF(K14<=50000000,4680000+(K14-25000000)*23%,10430000+(K14-50000000)*25%))))) -> 1753594.5 | M14: 12 | N14: =L14/M14 -> 146132.88 | O14: 146132.88 | P14: =N14-O14 -> 0
A15: 10 | B15: ABDULSALAM S. MUSTAPHA | C15: 852595.5 | D15: 12 | E15: =C15*D15 -> 10231146 | G15: 0 | H15: 693691.68 | J15: =F15+G15+H15 -> 693691.68 | K15: =E15-J15 -> 9537454.3 | L15: =IF(K15<=800000,0,IF(K15<=3000000,(K15-800000)*15%,IF(K15<=12000000,330000+(K15-3000000)*18%,IF(K15<=25000000,1950000+(K15-12000000)*21%,IF(K15<=50000000,4680000+(K15-25000000)*23%,10430000+(K15-50000000)*25%))))) -> 1506741.8 | M15: 12 | N15: =L15/M15 -> 125561.81 | O15: 125561.81 | P15: =N15-O15 -> 0
A16: 11 | B16: PERCY TERFA GBAHABO | C16: 682419.5 | D16: 12 | E16: =C16*D16 -> 8189034 | G16: 0 | H16: 520722.72 | J16: =F16+G16+H16 -> 520722.72 | K16: =E16-J16 -> 7668311.3 | L16: =IF(K16<=800000,0,IF(K16<=3000000,(K16-800000)*15%,IF(K16<=12000000,330000+(K16-3000000)*18%,IF(K16<=25000000,1950000+(K16-12000000)*21%,IF(K16<=50000000,4680000+(K16-25000000)*23%,10430000+(K16-50000000)*25%))))) -> 1170296 | M16: 12 | N16: =L16/M16 -> 97524.669 | O16: 97524.669 | P16: =N16-O16 -> 0
A17: 12 | B17: HASSANA AHMED IBRAHIM | C17: 861351.33 | D17: 12 | E17: =C17*D17 -> 10336216 | G17: 101319.25 | H17: 519697.28 | J17: =F17+G17+H17 -> 621016.53 | K17: =E17-J17 -> 9715199.5 | L17: =IF(K17<=800000,0,IF(K17<=3000000,(K17-800000)*15%,IF(K17<=12000000,330000+(K17-3000000)*18%,IF(K17<=25000000,1950000+(K17-12000000)*21%,IF(K17<=50000000,4680000+(K17-25000000)*23%,10430000+(K17-50000000)*25%))))) -> 1538735.9 | M17: 12 | N17: =L17/M17 -> 128227.99 | O17: 128227.99 | P17: =N17-O17 -> 0
A18: 13 | B18: IKIP LEBO | C18: 582098.92 | D18: 12 | E18: =C18*D18 -> 6985187 | G18: 96107.725 | H18: 491614.96 | J18: =F18+G18+H18 -> 587722.69 | K18: =E18-J18 -> 6397464.3 | L18: =IF(K18<=800000,0,IF(K18<=3000000,(K18-800000)*15%,IF(K18<=12000000,330000+(K18-3000000)*18%,IF(K18<=25000000,1950000+(K18-12000000)*21%,IF(K18<=50000000,4680000+(K18-25000000)*23%,10430000+(K18-50000000)*25%))))) -> 941543.58 | M18: 12 | N18: =L18/M18 -> 78461.965 | O18: 78461.965 | P18: =N18-O18 -> 0
... A22: 17 | B22: LUCKY AGWOM | C22: 768828.17 | D22: 12 | E22: =C22*D22 -> 9225938 | G22: 0 | H22: 450075.04 | J22: =F22+G22+H22 -> 450075.04 | K22: =E22-J22 -> 8775863 | L22: =IF(K22<=800000,0,IF(K22<=3000000,(K22-800000)*15%,IF(K22<=12000000,330000+(K22-3000000)*18%,IF(K22<=25000000,1950000+(K22-12000000)*21%,IF(K22<=50000000,4680000+(K22-25000000)*23%,10430000+(K22-50000000)*25%))))) -> 1369655.3 | M22: 12 | N22: =L22/M22 -> 114137.94 | O22: 114137.94 | P22: =N22-O22 -> 0
A23: 18 | B23: IDRIS IBRAHIM | C23: 578828.17 | D23: 12 | E23: =C23*D23 -> 6945938 | F23: 200000 | G23: 88398.875 | H23: 450075.04 | J23: =F23+G23+H23 -> 738473.92 | K23: =E23-J23 -> 6207464.1 | L23: =IF(K23<=800000,0,IF(K23<=3000000,(K23-800000)*15%,IF(K23<=12000000,330000+(K23-3000000)*18%,IF(K23<=25000000,1950000+(K23-12000000)*21%,IF(K23<=50000000,4680000+(K23-25000000)*23%,10430000+(K23-50000000)*25%))))) -> 907343.54 | M23: 12 | N23: =L23/M23 -> 75611.961 | O23: 78611.961 | P23: =N23-O23 -> -3000
A24: 19 | B24: FARUQ ATOFARATI | C24: 641140.67 | D24: 12 | E24: =C24*D24 -> 7693688 | G24: 0 | H24: 365895.04 | J24: =F24+G24+H24 -> 365895.04 | K24: =E24-J24 -> 7327793 | L24: =IF(K24<=800000,0,IF(K24<=3000000,(K24-800000)*15%,IF(K24<=12000000,330000+(K24-3000000)*18%,IF(K24<=25000000,1950000+(K24-12000000)*21%,IF(K24<=50000000,4680000+(K24-25000000)*23%,10430000+(K24-50000000)*25%))))) -> 1109002.7 | M24: 12 | N24: =L24/M24 -> 92416.894 | O24: 92416.894 | P24: =N24-O24 -> 0
A25: 20 | B25: RASHEEDAT DAIBU | C25: 450135.83 | D25: 12 | E25: =C25*D25 -> 5401630 | G25: 73851.35 | H25: 374530.4 | J25: =F25+G25+H25 -> 448381.75 | K25: =E25-J25 -> 4953248.3 | L25: =IF(K25<=800000,0,IF(K25<=3000000,(K25-800000)*15%,IF(K25<=12000000,330000+(K25-3000000)*18%,IF(K25<=25000000,1950000+(K25-12000000)*21%,IF(K25<=50000000,4680000+(K25-25000000)*23%,10430000+(K25-50000000)*25%))))) -> 681584.69 | M25: 12 | N25: =L25/M25 -> 56798.724 | O25: 56798.724 | P25: =N25-O25 -> 0
A26: 21 | B26: ELIZABETH OGECHUKWU ONYEAKU | C26: 0 | D26: 12 | E26: =C26*D26 -> 0 | G26: 0 | H26: 0 | J26: =F26+G26+H26 -> 0 | K26: =E26-J26 -> 0 | L26: =IF(K26<=800000,0,IF(K26<=3000000,(K26-800000)*15%,IF(K26<=12000000,330000+(K26-3000000)*18%,IF(K26<=25000000,1950000+(K26-12000000)*21%,IF(K26<=50000000,4680000+(K26-25000000)*23%,10430000+(K26-50000000)*25%))))) -> 0 | M26: 12 | N26: =L26/M26 -> 0 | O26: 0 | P26: =N26-O26 -> 0
A27: 22 | B27: VICTOR ASUKWO | C27: 432145.33 | D27: 12 | E27: =C27*D27 -> 5185744 | G27: 70673.35 | H27: 357259.52 | J27: =F27+G27+H27 -> 427932.87 | K27: =E27-J27 -> 4757811.1 | L27: =IF(K27<=800000,0,IF(K27<=3000000,(K27-800000)*15%,IF(K27<=12000000,330000+(K27-3000000)*18%,IF(K27<=25000000,1950000+(K27-12000000)*21%,IF(K27<=50000000,4680000+(K27-25000000)*23%,10430000+(K27-50000000)*25%))))) -> 646406 | M27: 12 | N27: =L27/M27 -> 53867.167 | O27: 53867.167 | P27: =N27-O27 -> 0
A28: 23 | B28: NNANDI LIVINUS ATURE | C28: 491140.67 | D28: 12 | E28: =C28*D28 -> 5893688 | F28: 300000 | G28: 72262.375 | H28: 365895.04 | J28: =F28+G28+H28 -> 738157.41 | K28: =E28-J28 -> 5155530.6 | L28: =IF(K28<=800000,0,IF(K28<=3000000,(K28-800000)*15%,IF(K28<=12000000,330000+(K28-3000000)*18%,IF(K28<=25000000,1950000+(K28-12000000)*21%,IF(K28<=50000000,4680000+(K28-25000000)*23%,10430000+(K28-50000000)*25%))))) -> 717995.51 | M28: 12 | N28: =L28/M28 -> 59832.959 | O28: 64332.959 | P28: =N28-O28 -> -4500
A29: 24 | B29: ABDULRAHMAN A SULAIMAN | C29: 415320.67 | D29: 12 | E29: =C29*D29 -> 4983848 | G29: 0 | H29: 341107.84 | J29: =F29+G29+H29 -> 341107.84 | K29: =E29-J29 -> 4642740.2 | L29: =IF(K29<=800000,0,IF(K29<=3000000,(K29-800000)*15%,IF(K29<=12000000,330000+(K29-3000000)*18%,IF(K29<=25000000,1950000+(K29-12000000)*21%,IF(K29<=50000000,4680000+(K29-25000000)*23%,10430000+(K29-50000000)*25%))))) -> 625693.23 | M29: 12 | N29: =L29/M29 -> 52141.102 | O29: 52141.102 | P29: =N29-O29 -> 0
A30: 25 | B30: DARE SHEU MAGBON | C30: 407016.17 | D30: 12 | E30: =C30*D30 -> 4884194 | G30: 0 | H30: 333135.52 | J30: =F30+G30+H30 -> 333135.52 | K30: =E30-J30 -> 4551058.5 | L30: =IF(K30<=800000,0,IF(K30<=3000000,(K30-800000)*15%,IF(K30<=12000000,330000+(K30-3000000)*18%,IF(K30<=25000000,1950000+(K30-12000000)*21%,IF(K30<=50000000,4680000+(K30-25000000)*23%,10430000+(K30-50000000)*25%))))) -> 609190.53 | M30: 12 | N30: =L30/M30 -> 50765.877 | O30: 50765.877 | P30: =N30-O30 -> 0
A31: 26 | B31: ABUBAKAR SULAIMAN SODEEQ | C31: 441140.67 | D31: 12 | E31: =C31*D31 -> 5293688 | G31: 70673.35 | H31: 357259.52 | J31: =F31+G31+H31 -> 427932.87 | K31: =E31-J31 -> 4865755.1 | L31: =IF(K31<=800000,0,IF(K31<=3000000,(K31-800000)*15%,IF(K31<=12000000,330000+(K31-3000000)*18%,IF(K31<=25000000,1950000+(K31-12000000)*21%,IF(K31<=50000000,4680000+(K31-25000000)*23%,10430000+(K31-50000000)*25%))))) -> 665835.92 | M31: 12 | N31: =L31/M31 -> 55486.327 | O31: 53867.167 | P31: =N31-O31 -> 1619.16
A32: 27 | B32: JIMOH ADEBAYO ZAKA | C32: 432145.33 | D32: 12 | E32: =C32*D32 -> 5185744 | G32: 70673.35 | H32: 357259.52 | J32: =F32+G32+H32 -> 427932.87 | K32: =E32-J32 -> 4757811.1 | L32: =IF(K32<=800000,0,IF(K32<=3000000,(K32-800000)*15%,IF(K32<=12000000,330000+(K32-3000000)*18%,IF(K32<=25000000,1950000+(K32-12000000)*21%,IF(K32<=50000000,4680000+(K32-25000000)*23%,10430000+(K32-50000000)*25%))))) -> 646406 | M32: 12 | N32: =L32/M32 -> 53867.167 | O32: 53867.167 | P32: =N32-O32 -> 0
A33: 28 | B33: ABDULMUSHIN TAWFIQ LADAN | C33: 407016.17 | D33: 12 | E33: =C33*D33 -> 4884194 | G33: 0 | H33: 333135.52 | J33: =F33+G33+H33 -> 333135.52 | K33: =E33-J33 -> 4551058.5 | L33: =IF(K33<=800000,0,IF(K33<=3000000,(K33-800000)*15%,IF(K33<=12000000,330000+(K33-3000000)*18%,IF(K33<=25000000,1950000+(K33-12000000)*21%,IF(K33<=50000000,4680000+(K33-25000000)*23%,10430000+(K33-50000000)*25%))))) -> 609190.53 | M33: 12 | N33: =L33/M33 -> 50765.877 | O33: 50765.877 | P33: =N33-O33 -> 0
A34: 29 | B34: MOHAMMED BELLO | C34: 432145.33 | D34: 12 | E34: =C34*D34 -> 5185744 | G34: 0 | H34: 357259.52 | J34: =F34+G34+H34 -> 357259.52 | K34: =E34-J34 -> 4828484.5 | L34: =IF(K34<=800000,0,IF(K34<=3000000,(K34-800000)*15%,IF(K34<=12000000,330000+(K34-3000000)*18%,IF(K34<=25000000,1950000+(K34-12000000)*21%,IF(K34<=50000000,4680000+(K34-25000000)*23%,10430000+(K34-50000000)*25%))))) -> 659127.21 | M34: 12 | N34: =L34/M34 -> 54927.267 | O34: 54927.267 | P34: =N34-O34 -> -5.8207661e-11
A35: 30 | B35: HOLINESS PAUL UDO | C35: 398711.67 | D35: 12 | E35: =C35*D35 -> 4784540 | F35: 200000 | G35: 65320.025 | H35: 325163.2 | J35: =F35+G35+H35 -> 590483.22 | K35: =E35-J35 -> 4194056.8 | L35: =IF(K35<=800000,0,IF(K35<=3000000,(K35-800000)*15%,IF(K35<=12000000,330000+(K35-3000000)*18%,IF(K35<=25000000,1950000+(K35-12000000)*21%,IF(K35<=50000000,4680000+(K35-25000000)*23%,10430000+(K35-50000000)*25%))))) -> 544930.22 | M35: 12 | N35: =L35/M35 -> 45410.852 | O35: 48410.852 | P35: =N35-O35 -> -3000
A36: 31 | B36: CHARITY UDO AKAN | C36: 398711.67 | D36: 12 | E36: =C36*D36 -> 4784540 | F36: 360000 | G36: 65320.025 | H36: 325163.2 | J36: =F36+G36+H36 -> 750483.22 | K36: =E36-J36 -> 4034056.8 | L36: =IF(K36<=800000,0,IF(K36<=3000000,(K36-800000)*15%,IF(K36<=12000000,330000+(K36-3000000)*18%,IF(K36<=25000000,1950000+(K36-12000000)*21%,IF(K36<=50000000,4680000+(K36-25000000)*23%,10430000+(K36-50000000)*25%))))) -> 516130.22 | M36: 12 | N36: =L36/M36 -> 43010.852 | O36: 48410.852 | P36: =N36-O36 -> -5400
A37: 32 | B37: SANI UMAR IBRAHIM | C37: 398711.67 | D37: 12 | E37: =C37*D37 -> 4784540 | G37: 0 | H37: 325163.2 | J37: =F37+G37+H37 -> 325163.2 | K37: =E37-J37 -> 4459376.8 | L37: =IF(K37<=800000,0,IF(K37<=3000000,(K37-800000)*15%,IF(K37<=12000000,330000+(K37-3000000)*18%,IF(K37<=25000000,1950000+(K37-12000000)*21%,IF(K37<=50000000,4680000+(K37-25000000)*23%,10430000+(K37-50000000)*25%))))) -> 592687.82 | M37: 12 | N37: =L37/M37 -> 49390.652 | O37: 49390.652 | P37: =N37-O37 -> 0
A38: 33 | B38: FAHAD ABUBUKAR LONGMAN | C38: 398711.67 | D38: 12 | E38: =C38*D38 -> 4784540 | G38: 65320.025 | H38: 325163.2 | J38: =F38+G38+H38 -> 390483.22 | K38: =E38-J38 -> 4394056.8 | L38: =IF(K38<=800000,0,IF(K38<=3000000,(K38-800000)*15%,IF(K38<=12000000,330000+(K38-3000000)*18%,IF(K38<=25000000,1950000+(K38-12000000)*21%,IF(K38<=50000000,4680000+(K38-25000000)*23%,10430000+(K38-50000000)*25%))))) -> 580930.22 | M38: 12 | N38: =L38/M38 -> 48410.852 | O38: 48410.852 | P38: =N38-O38 -> 0
A39: 34 | B39: HARUNA JIBRIL AMEH | C39: 358920.67 | D39: 12 | E39: =C39*D39 -> 4307048 | G39: 60164.825 | H39: 296563.84 | J39: =F39+G39+H39 -> 356728.66 | K39: =E39-J39 -> 3950319.3 | L39: =IF(K39<=800000,0,IF(K39<=3000000,(K39-800000)*15%,IF(K39<=12000000,330000+(K39-3000000)*18%,IF(K39<=25000000,1950000+(K39-12000000)*21%,IF(K39<=50000000,4680000+(K39-25000000)*23%,10430000+(K39-50000000)*25%))))) -> 501057.48 | M39: 12 | N39: =L39/M39 -> 41754.79 | O39: 41754.79 | P39: =N39-O39 -> 0
A40: 35 | B40: RAMATU IBRAHIM ABDULRAHEEM | C40: 351910.75 | D40: 12 | E40: =C40*D40 -> 4222929 | G40: 58909.325 | H40: 289834.32 | J40: =F40+G40+H40 -> 348743.65 | K40: =E40-J40 -> 3874185.4 | L40: =IF(K40<=800000,0,IF(K40<=3000000,(K40-800000)*15%,IF(K40<=12000000,330000+(K40-3000000)*18%,IF(K40<=25000000,1950000+(K40-12000000)*21%,IF(K40<=50000000,4680000+(K40-25000000)*23%,10430000+(K40-50000000)*25%))))) -> 487353.36 | M40: 12 | N40: =L40/M40 -> 40612.78 | O40: 40612.78 | P40: =N40-O40 -> 0
A41: 36 | B41: EDIDIONG EZEKIEL ATAT | C41: 344900.83 | D41: 12 | E41: =C41*D41 -> 4138810 | G41: 57653.825 | H41: 283104.8 | J41: =F41+G41+H41 -> 340758.63 | K41: =E41-J41 -> 3798051.4 | L41: =IF(K41<=800000,0,IF(K41<=3000000,(K41-800000)*15%,IF(K41<=12000000,330000+(K41-3000000)*18%,IF(K41<=25000000,1950000+(K41-12000000)*21%,IF(K41<=50000000,4680000+(K41-25000000)*23%,10430000+(K41-50000000)*25%))))) -> 473649.25 | M41: 12 | N41: =L41/M41 -> 39470.771 | O41: 39470.771 | P41: =N41-O41 -> 0
A42: 37 | B42: MAHMUD ADEWOLE HASSAN | C42: 344900.83 | D42: 12 | E42: =C42*D42 -> 4138810 | G42: 0 | H42: 283104.8 | J42: =F42+G42+H42 -> 283104.8 | K42: =E42-J42 -> 3855705.2 | L42: =IF(K42<=800000,0,IF(K42<=3000000,(K42-800000)*15%,IF(K42<=12000000,330000+(K42-3000000)*18%,IF(K42<=25000000,1950000+(K42-12000000)*21%,IF(K42<=50000000,4680000+(K42-25000000)*23%,10430000+(K42-50000000)*25%))))) -> 484026.94 | M42: 12 | N42: =L42/M42 -> 40335.578 | O42: 40335.578 | P42: =N42-O42 -> 0
A43: 38 | B43: YUSUF KABIRU TURAKI | C43: 344900.83 | D43: 12 | E43: =C43*D43 -> 4138810 | G43: 0 | H43: 283104.8 | J43: =F43+G43+H43 -> 283104.8 | K43: =E43-J43 -> 3855705.2 | L43: =IF(K43<=800000,0,IF(K43<=3000000,(K43-800000)*15%,IF(K43<=12000000,330000+(K43-3000000)*18%,IF(K43<=25000000,1950000+(K43-12000000)*21%,IF(K43<=50000000,4680000+(K43-25000000)*23%,10430000+(K43-50000000)*25%))))) -> 484026.94 | M43: 12 | N43: =L43/M43 -> 40335.578 | O43: 40335.578 | P43: =N43-O43 -> 0
A44: 39 | B44: FATIMA OMAR IBRAHIM | C44: 344900.83 | D44: 12 | E44: =C44*D44 -> 4138810 | G44: 0 | H44: 283104.8 | J44: =F44+G44+H44 -> 283104.8 | K44: =E44-J44 -> 3855705.2 | L44: =IF(K44<=800000,0,IF(K44<=3000000,(K44-800000)*15%,IF(K44<=12000000,330000+(K44-3000000)*18%,IF(K44<=25000000,1950000+(K44-12000000)*21%,IF(K44<=50000000,4680000+(K44-25000000)*23%,10430000+(K44-50000000)*25%))))) -> 484026.94 | M44: 12 | N44: =L44/M44 -> 40335.578 | O44: 40335.578 | P44: =N44-O44 -> 0
A45: 40 | B45: EBERE ANASTHESIA IGWE | C45: 344900.83 | D45: 12 | E45: =C45*D45 -> 4138810 | G45: 0 | H45: 283104.8 | J45: =F45+G45+H45 -> 283104.8 | K45: =E45-J45 -> 3855705.2 | L45: =IF(K45<=800000,0,IF(K45<=3000000,(K45-800000)*15%,IF(K45<=12000000,330000+(K45-3000000)*18%,IF(K45<=25000000,1950000+(K45-12000000)*21%,IF(K45<=50000000,4680000+(K45-25000000)*23%,10430000+(K45-50000000)*25%))))) -> 484026.94 | M45: 12 | N45: =L45/M45 -> 40335.578 | O45: 40335.578 | P45: =N45-O45 -> 0
A46: 41 | B46: ALIYU GARBA LERE | C46: 344900.83 | D46: 12 | E46: =C46*D46 -> 4138810 | G46: 0 | H46: 283104.8 | J46: =F46+G46+H46 -> 283104.8 | K46: =E46-J46 -> 3855705.2 | L46: =IF(K46<=800000,0,IF(K46<=3000000,(K46-800000)*15%,IF(K46<=12000000,330000+(K46-3000000)*18%,IF(K46<=25000000,1950000+(K46-12000000)*21%,IF(K46<=50000000,4680000+(K46-25000000)*23%,10430000+(K46-50000000)*25%))))) -> 484026.94 | M46: 12 | N46: =L46/M46 -> 40335.578 | O46: 40335.578 | P46: =N46-O46 -> 0
B47: TOTAL | C47: =SUM(C6:C46) -> 25974148 | E47: =SUM(E6:E46) -> 311689774 | F47: =SUM(F6:F46) -> 1060000 | G47: =SUM(G6:G46) -> 1778670.7 | H47: =SUM(H6:H46) -> 16947335 | I47: =SUM(I6:I46) -> 0 | J47: =SUM(J6:J46) -> 19786005 | K47: =SUM(K6:K46) -> 2.9190377e+08 | L47: =SUM(L6:L46) -> 44757089 | ... N47: =SUM(N6:N46) -> 3729757.4 | O47: 3744038.3 | P47: =SUM(P6:P46) -> -14280.84
B49: INTERNAL AUDIT
A50: 1 | B50: OSANAIYE DAVID AKINYEMI | C50: 1847106.4 | D50: 12 | E50: =C50*D50 -> 22165277 | G50: 0 | H50: 1677222.2 | J50: =F50+G50+H50 -> 1677222.2 | K50: =E50-J50 -> 20488055 | L50: =IF(K50<=800000,0,IF(K50<=3000000,(K50-800000)*15%,IF(K50<=12000000,330000+(K50-3000000)*18%,IF(K50<=25000000,1950000+(K50-12000000)*21%,IF(K50<=50000000,4680000+(K50-25000000)*23%,10430000+(K50-50000000)*25%))))) -> 3732491.5 | M50: 12 | N50: =L50/M50 -> 311040.96 | O50: 311040.96 | P50: =N50-O50 -> 0
A51: 2 | B51: EVELYN ETONKE AGAN | C51: 802595.5 | D51: 12 | E51: =C51*D51 -> 9631146 | G51: 0 | H51: 693691.68 | J51: =F51+G51+H51 -> 693691.68 | K51: =E51-J51 -> 8937454.3 | L51: =IF(K51<=800000,0,IF(K51<=3000000,(K51-800000)*15%,IF(K51<=12000000,330000+(K51-3000000)*18%,IF(K51<=25000000,1950000+(K51-12000000)*21%,IF(K51<=50000000,4680000+(K51-25000000)*23%,10430000+(K51-50000000)*25%))))) -> 1398741.8 | M51: 12 | N51: =L51/M51 -> 116561.81 | O51: 116561.81 | P51: =N51-O51 -> 0
A52: 3 | B52: JAMILA ABDUL | C52: 450135.83 | D52: 12 | E52: =C52*D52 -> 5401630 | G52: 73851.35 | H52: 374530.4 | J52: =F52+G52+H52 -> 448381.75 | K52: =E52-J52 -> 4953248.3 | L52: =IF(K52<=800000,0,IF(K52<=3000000,(K52-800000)*15%,IF(K52<=12000000,330000+(K52-3000000)*18%,IF(K52<=25000000,1950000+(K52-12000000)*21%,IF(K52<=50000000,4680000+(K52-25000000)*23%,10430000+(K52-50000000)*25%))))) -> 681584.69 | M52: 12 | N52: =L52/M52 -> 56798.724 | O52: 56798.724 | P52: =N52-O52 -> 0
A53: 4 | B53: IJEOMA EWELUKWA | C53: 514993.58 | D53: 12 | E53: =C53*D53 -> 6179923 | G53: 0 | H53: 436793.84 | J53: =F53+G53+H53 -> 436793.84 | K53: =E53-J53 -> 5743129.2 | L53: =IF(K53<=800000,0,IF(K53<=3000000,(K53-800000)*15%,IF(K53<=12000000,330000+(K53-3000000)*18%,IF(K53<=25000000,1950000+(K53-12000000)*21%,IF(K53<=50000000,4680000+(K53-25000000)*23%,10430000+(K53-50000000)*25%))))) -> 823763.25 | M53: 12 | N53: =L53/M53 -> 68646.937 | O53: 68646.937 | P53: =N53-O53 -> 0
A54: 5 | B54: HASSAN ABDULHADI | C54: 398711.67 | D54: 12 | E54: =C54*D54 -> 4784540 | F54: 240000 | G54: 65320.025 | H54: 325163.2 | J54: =F54+G54+H54 -> 630483.22 | K54: =E54-J54 -> 4154056.8 | L54: =IF(K54<=800000,0,IF(K54<=3000000,(K54-800000)*15%,IF(K54<=12000000,330000+(K54-3000000)*18%,IF(K54<=25000000,1950000+(K54-12000000)*21%,IF(K54<=50000000,4680000+(K54-25000000)*23%,10430000+(K54-50000000)*25%))))) -> 537730.22 | M54: 12 | N54: =L54/M54 -> 44810.852 | O54: 48410.852 | P54: =N54-O54 -> -3600
A55: 6 | B55: YUSUF YUSUF DAYYABU | C55: 407016.17 | D55: 12 | E55: =C55*D55 -> 4884194 | G55: 66802.375 | H55: 333135.52 | J55: =F55+G55+H55 -> 399937.89 | K55: =E55-J55 -> 4484256.1 | L55: =IF(K55<=800000,0,IF(K55<=3000000,(K55-800000)*15%,IF(K55<=12000000,330000+(K55-3000000)*18%,IF(K55<=25000000,1950000+(K55-12000000)*21%,IF(K55<=50000000,4680000+(K55-25000000)*23%,10430000+(K55-50000000)*25%))))) -> 597166.1 | M55: 12 | N55: =L55/M55 -> 49763.842 | O55: 49763.842 | P55: =N55-O55 -> 0
A56: 7 | B56: UDONSI QUEENETH CHIWENDU | C56: 344900.83 | D56: 12 | E56: =C56*D56 -> 4138810 | F56: 110000 | G56: 0 | H56: 283104.8 | J56: =F56+G56+H56 -> 393104.8 | K56: =E56-J56 -> 3745705.2 | L56: =IF(K56<=800000,0,IF(K56<=3000000,(K56-800000)*15%,IF(K56<=12000000,330000+(K56-3000000)*18%,IF(K56<=25000000,1950000+(K56-12000000)*21%,IF(K56<=50000000,4680000+(K56-25000000)*23%,10430000+(K56-50000000)*25%))))) -> 464226.94 | M56: 12 | N56: =L56/M56 -> 38685.578 | O56: 40335.578 | P56: =N56-O56 -> -1650
C57: =SUM(C50:C56) -> 4765460 | E57: =SUM(E50:E56) -> 57185520 | G57: =SUM(G50:G56) -> 205973.75 | H57: =SUM(H50:H56) -> 4123641.6 | J57: =SUM(J50:J56) -> 4679615.3 | K57: =SUM(K50:K56) -> 52505905 | L57: =SUM(L50:L56) -> 8235704.5 | N57: =SUM(N50:N56) -> 686308.71 | O57: 691558.71 | P57: =SUM(P50:P56) -> -5250
B59: LEG. SUPPORT SEVICES
A60: 1 | B60: BETHEL UZOMA IHUGBA | C60: 1897359.3 | D60: 12 | E60: =C60*D60 -> 22768312 | G60: 0 | H60: 1629465 | J60: =F60+G60+H60 -> 1629465 | K60: =E60-J60 -> 21138847 | L60: =IF(K60<=800000,0,IF(K60<=3000000,(K60-800000)*15%,IF(K60<=12000000,330000+(K60-3000000)*18%,IF(K60<=25000000,1950000+(K60-12000000)*21%,IF(K60<=50000000,4680000+(K60-25000000)*23%,10430000+(K60-50000000)*25%))))) -> 3869157.9 | M60: 12 | N60: =L60/M60 -> 322429.82 | O60: 322429.82 | P60: =N60-O60 -> 0
A61: 2 | B61: OGUCHE SAMUEL | C61: 1032711.1 | D61: 12 | E61: =C61*D61 -> 12392533 | G61: 0 | H61: 714697.92 | J61: =F61+G61+H61 -> 714697.92 | K61: =E61-J61 -> 11677835 | L61: =IF(K61<=800000,0,IF(K61<=3000000,(K61-800000)*15%,IF(K61<=12000000,330000+(K61-3000000)*18%,IF(K61<=25000000,1950000+(K61-12000000)*21%,IF(K61<=50000000,4680000+(K61-25000000)*23%,10430000+(K61-50000000)*25%))))) -> 1892010.3 | M61: 12 | N61: =L61/M61 -> 157667.53 | O61: 134585.39 | P61: =N61-O61 -> 23082.135
A62: 3 | B62: IBRAHIM USMAN | C62: 904477 | D62: 12 | E62: =C62*D62 -> 10853724 | G62: 137703.15 | H62: 714697.92 | J62: =F62+G62+H62 -> 852401.07 | K62: =E62-J62 -> 10001323 | L62: =IF(K62<=800000,0,IF(K62<=3000000,(K62-800000)*15%,IF(K62<=12000000,330000+(K62-3000000)*18%,IF(K62<=25000000,1950000+(K62-12000000)*21%,IF(K62<=50000000,4680000+(K62-25000000)*23%,10430000+(K62-50000000)*25%))))) -> 1590238.1 | M62: 12 | N62: =L62/M62 -> 132519.84 | O62: 132519.84 | P62: =N62-O62 -> 0
A63: 4 | B63: DR MOHAMMED O. AMALI | C63: 904477 | D63: 12 | E63: =C63*D63 -> 10853724 | G63: 0 | H63: 714697.92 | J63: =F63+G63+H63 -> 714697.92 | K63: =E63-J63 -> 10139026 | L63: =IF(K63<=800000,0,IF(K63<=3000000,(K63-800000)*15%,IF(K63<=12000000,330000+(K63-3000000)*18%,IF(K63<=25000000,1950000+(K63-12000000)*21%,IF(K63<=50000000,4680000+(K63-25000000)*23%,10430000+(K63-50000000)*25%))))) -> 1615024.7 | M63: 12 | N63: =L63/M63 -> 134585.39 | O63: 134585.39 | P63: =N63-O63 -> 0
A64: 5 | B64: YAHAYA SHAMSU | C64: 882595.5 | D64: 12 | E64: =C64*D64 -> 10591146 | G64: 0 | H64: 693691.68 | J64: =F64+G64+H64 -> 693691.68 | K64: =E64-J64 -> 9897454.3 | L64: =IF(K64<=800000,0,IF(K64<=3000000,(K64-800000)*15%,IF(K64<=12000000,330000+(K64-3000000)*18%,IF(K64<=25000000,1950000+(K64-12000000)*21%,IF(K64<=50000000,4680000+(K64-25000000)*23%,10430000+(K64-50000000)*25%))))) -> 1571541.8 | M64: 12 | N64: =L64/M64 -> 130961.81 | O64: 130961.81 | P64: =N64-O64 -> 0
A65: 6 | B65: CHIDEBE MATHEW NWANKWO | C65: 882595.5 | D65: 12 | E65: =C65*D65 -> 10591146 | G65: 0 | H65: 693691.68 | J65: =F65+G65+H65 -> 693691.68 | K65: =E65-J65 -> 9897454.3 | L65: =IF(K65<=800000,0,IF(K65<=3000000,(K65-800000)*15%,IF(K65<=12000000,330000+(K65-3000000)*18%,IF(K65<=25000000,1950000+(K65-12000000)*21%,IF(K65<=50000000,4680000+(K65-25000000)*23%,10430000+(K65-50000000)*25%))))) -> 1571541.8 | M65: 12 | N65: =L65/M65 -> 130961.81 | O65: 130961.81 | P65: =N65-O65 -> 0
A66: 7 | B66: UMAR MUSA PADAH | C66: 564993.58 | D66: 12 | E66: =C66*D66 -> 6779923 | G66: 0 | H66: 436793.84 | J66: =F66+G66+H66 -> 436793.84 | K66: =E66-J66 -> 6343129.2 | L66: =IF(K66<=800000,0,IF(K66<=3000000,(K66-800000)*15%,IF(K66<=12000000,330000+(K66-3000000)*18%,IF(K66<=25000000,1950000+(K66-12000000)*21%,IF(K66<=50000000,4680000+(K66-25000000)*23%,10430000+(K66-50000000)*25%))))) -> 931763.25 | M66: 12 | N66: =L66/M66 -> 77646.937 | O66: 77646.937 | P66: =N66-O66 -> 0
A67: 8 | B67: BILKIS S. LAWAL-GAMBARI | C67: 499131.17 | D67: 12 | E67: =C67*D67 -> 5989574 | G67: 0 | H67: 383165.92 | J67: =F67+G67+H67 -> 383165.92 | K67: =E67-J67 -> 5606408.1 | L67: =IF(K67<=800000,0,IF(K67<=3000000,(K67-800000)*15%,IF(K67<=12000000,330000+(K67-3000000)*18%,IF(K67<=25000000,1950000+(K67-12000000)*21%,IF(K67<=50000000,4680000+(K67-25000000)*23%,10430000+(K67-50000000)*25%))))) -> 799153.45 | M67: 12 | N67: =L67/M67 -> 66596.121 | O67: 66596.121 | P67: =N67-O67 -> 0
A68: 9 | B68: UMOH USENOBONG EMMANUEL | C68: 481140.67 | D68: 12 | E68: =C68*D68 -> 5773688 | G68: 0 | H68: 365895.04 | J68: =F68+G68+H68 -> 365895.04 | K68: =E68-J68 -> 5407793 | L68: =IF(K68<=800000,0,IF(K68<=3000000,(K68-800000)*15%,IF(K68<=12000000,330000+(K68-3000000)*18%,IF(K68<=25000000,1950000+(K68-12000000)*21%,IF(K68<=50000000,4680000+(K68-25000000)*23%,10430000+(K68-50000000)*25%))))) -> 763402.73 | M68: 12 | N68: =L68/M68 -> 63616.894 | O68: 63616.894 | P68: =N68-O68 -> 0
A69: 10 | B69: ZAINAB AKINDE | C69: 455320.67 | D69: 12 | E69: =C69*D69 -> 5463848 | G69: 0 | H69: 341107.84 | J69: =F69+G69+H69 -> 341107.84 | K69: =E69-J69 -> 5122740.2 | L69: =IF(K69<=800000,0,IF(K69<=3000000,(K69-800000)*15%,IF(K69<=12000000,330000+(K69-3000000)*18%,IF(K69<=25000000,1950000+(K69-12000000)*21%,IF(K69<=50000000,4680000+(K69-25000000)*23%,10430000+(K69-50000000)*25%))))) -> 712093.23 | M69: 12 | N69: =L69/M69 -> 59341.102 | O69: 59341.102 | P69: =N69-O69 -> 0
A70: 11 | B70: GUNAT NANSAK MARK | C70: 455320.67 | D70: 12 | E70: =C70*D70 -> 5463848 | G70: 0 | H70: 341107.84 | J70: =F70+G70+H70 -> 341107.84 | K70: =E70-J70 -> 5122740.2 | L70: =IF(K70<=800000,0,IF(K70<=3000000,(K70-800000)*15%,IF(K70<=12000000,330000+(K70-3000000)*18%,IF(K70<=25000000,1950000+(K70-12000000)*21%,IF(K70<=50000000,4680000+(K70-25000000)*23%,10430000+(K70-50000000)*25%))))) -> 712093.23 | M70: 12 | N70: =L70/M70 -> 59341.102 | O70: 59341.102 | P70: =N70-O70 -> 0
A71: 12 | B71: MANDU ESSIEN NDEM | C71: 438711.67 | D71: 12 | E71: =C71*D71 -> 5264540 | G71: 0 | H71: 325163.2 | J71: =F71+G71+H71 -> 325163.2 | K71: =E71-J71 -> 4939376.8 | L71: =IF(K71<=800000,0,IF(K71<=3000000,(K71-800000)*15%,IF(K71<=12000000,330000+(K71-3000000)*18%,IF(K71<=25000000,1950000+(K71-12000000)*21%,IF(K71<=50000000,4680000+(K71-25000000)*23%,10430000+(K71-50000000)*25%))))) -> 679087.82 | M71: 12 | N71: =L71/M71 -> 56590.652 | O71: 56590.652 | P71: =N71-O71 -> 0
B72: TOTAL | C72: =SUM(C60:C71) -> 9398833.8 | E72: =SUM(E60:E71) -> 1.1278601e+08 | G72: =SUM(G60:G71) -> 137703.15 | H72: =SUM(H60:H71) -> 7354175.8 | J72: =SUM(J60:J71) -> 7491878.9 | K72: =SUM(K60:K71) -> 1.0529413e+08 | L72: =SUM(L60:L71) -> 16707108 | N72: =SUM(N60:N71) -> 1392259 | O72: 1369176.9 | P72: =SUM(P60:P71) -> 23082.135
B74: LEGAL SERVICES
A75: 1 | B75: DR SHUAIBU DANWANKA | C75: 1947106.4 | D75: 12 | E75: =C75*D75 -> 23365277 | G75: 0 | H75: 1677222.2 | J75: =F75+G75+H75 -> 1677222.2 | K75: =E75-J75 -> 21688055 | L75: =IF(K75<=800000,0,IF(K75<=3000000,(K75-800000)*15%,IF(K75<=12000000,330000+(K75-3000000)*18%,IF(K75<=25000000,1950000+(K75-12000000)*21%,IF(K75<=50000000,4680000+(K75-25000000)*23%,10430000+(K75-50000000)*25%))))) -> 3984491.5 | M75: 12 | N75: =L75/M75 -> 332040.96 | O75: 332040.96 | P75: =N75-O75 -> -4.6566129e-10
A76: 2 | B76: ABDULSALAM BAKO | C76: 942711.08 | D76: 12 | E76: =C76*D76 -> 11312533 | G76: 0 | H76: 714697.92 | J76: =F76+G76+H76 -> 714697.92 | K76: =E76-J76 -> 10597835 | L76: =IF(K76<=800000,0,IF(K76<=3000000,(K76-800000)*15%,IF(K76<=12000000,330000+(K76-3000000)*18%,IF(K76<=25000000,1950000+(K76-12000000)*21%,IF(K76<=50000000,4680000+(K76-25000000)*23%,10430000+(K76-50000000)*25%))))) -> 1697610.3 | M76: 12 | N76: =L76/M76 -> 141467.53 | O76: 120185.39 | P76: =N76-O76 -> 21282.135
C77: =SUM(C75:C76) -> 2889817.5 | E77: =SUM(E75:E76) -> 34677810 | G77: =SUM(G75:G76) -> 0 | H77: =SUM(H75:H76) -> 2391920.1 | J77: =SUM(J75:J76) -> 2391920.1 | K77: =SUM(K75:K76) -> 32285890 | L77: =SUM(L75:L76) -> 5682101.8 | N77: =SUM(N75:N76) -> 473508.49 | O77: 452226.35 | P77: =SUM(P75:P76) -> 21282.135
B79: DEMOCRACY & GOVERNANCE
A80: 1 | B80: NGARA CHRISTOPHER OCHANJA | C80: 1085306.8 | D80: 12 | E80: =C80*D80 -> 13023681 | G80: 166400.85 | H80: 869094.48 | J80: =F80+G80+H80 -> 1035495.3 | K80: =E80-J80 -> 11988186 | L80: =IF(K80<=800000,0,IF(K80<=3000000,(K80-800000)*15%,IF(K80<=12000000,330000+(K80-3000000)*18%,IF(K80<=25000000,1950000+(K80-12000000)*21%,IF(K80<=50000000,4680000+(K80-25000000)*23%,10430000+(K80-50000000)*25%))))) -> 1947873.4 | M80: 12 | N80: =L80/M80 -> 162322.79 | O80: 162322.79 | P80: =N80-O80 -> 0
A81: 2 | B81: EJALONIBU GANIYU LAYI | C81: 713911.08 | D81: 12 | E81: =C81*D81 -> 8566933 | G81: 0 | H81: 550954.64 | J81: =F81+G81+H81 -> 550954.64 | K81: =E81-J81 -> 8015978.4 | L81: =IF(K81<=800000,0,IF(K81<=3000000,(K81-800000)*15%,IF(K81<=12000000,330000+(K81-3000000)*18%,IF(K81<=25000000,1950000+(K81-12000000)*21%,IF(K81<=50000000,4680000+(K81-25000000)*23%,10430000+(K81-50000000)*25%))))) -> 1232876.1 | M81: 12 | N81: =L81/M81 -> 102739.68 | O81: 102739.68 | P81: =N81-O81 -> 1.1641532e-10
A82: 3 | B82: MARTINS SOLOMON UDOM | C82: 617472.75 | D82: 12 | E82: =C82*D82 -> 7409673 | G82: 93501.975 | H82: 477573.84 | J82: =F82+G82+H82 -> 571075.81 | K82: =E82-J82 -> 6838597.2 | L82: =IF(K82<=800000,0,IF(K82<=3000000,(K82-800000)*15%,IF(K82<=12000000,330000+(K82-3000000)*18%,IF(K82<=25000000,1950000+(K82-12000000)*21%,IF(K82<=50000000,4680000+(K82-25000000)*23%,10430000+(K82-50000000)*25%))))) -> 1020947.5 | M82: 12 | N82: =L82/M82 -> 85078.958 | O82: 85078.958 | P82: =N82-O82 -> 0
A83: 4 | B83: ISHAKA DELE | C83: 617472.75 | D83: 12 | E83: =C83*D83 -> 7409673 | G83: 93501.975 | H83: 477573.84 | J83: =F83+G83+H83 -> 571075.81 | K83: =E83-J83 -> 6838597.2 | L83: =IF(K83<=800000,0,IF(K83<=3000000,(K83-800000)*15%,IF(K83<=12000000,330000+(K83-3000000)*18%,IF(K83<=25000000,1950000+(K83-12000000)*21%,IF(K83<=50000000,4680000+(K83-25000000)*23%,10430000+(K83-50000000)*25%))))) -> 1020947.5 | M83: 12 | N83: =L83/M83 -> 85078.958 | O83: 85078.958 | P83: =N83-O83 -> 0
A84: 5 | B84: UDEFUNA NNADOZIE PATRICK | C84: 616972.66 | D84: 12 | E84: =C84*D84 -> 7403671.9 | G84: 90863.6 | H84: 463356.16 | J84: =F84+G84+H84 -> 554219.76 | K84: =E84-J84 -> 6849452.2 | L84: =IF(K84<=800000,0,IF(K84<=3000000,(K84-800000)*15%,IF(K84<=12000000,330000+(K84-3000000)*18%,IF(K84<=25000000,1950000+(K84-12000000)*21%,IF(K84<=50000000,4680000+(K84-25000000)*23%,10430000+(K84-50000000)*25%))))) -> 1022901.4 | M84: 12 | N84: =L84/M84 -> 85241.783 | O84: 85241.783 | P84: =N84-O84 -> 0
A85: 6 | B85: SHAFIU YAHYA MIKAIL | C85: 592662.67 | D85: 12 | E85: =C85*D85 -> 7111952 | G85: 0 | H85: 463356.16 | J85: =F85+G85+H85 -> 463356.16 | K85: =E85-J85 -> 6648595.8 | L85: =IF(K85<=800000,0,IF(K85<=3000000,(K85-800000)*15%,IF(K85<=12000000,330000+(K85-3000000)*18%,IF(K85<=25000000,1950000+(K85-12000000)*21%,IF(K85<=50000000,4680000+(K85-25000000)*23%,10430000+(K85-50000000)*25%))))) -> 986747.25 | M85: 12 | N85: =L85/M85 -> 82228.938 | O85: 82228.938 | P85: =N85-O85 -> 0
A86: 7 | B86: HASSAN YERIMA | C86: 592662.67 | D86: 12 | E86: =C86*D86 -> 7111952 | G86: 0 | H86: 463356.16 | J86: =F86+G86+H86 -> 463356.16 | K86: =E86-J86 -> 6648595.8 | L86: =IF(K86<=800000,0,IF(K86<=3000000,(K86-800000)*15%,IF(K86<=12000000,330000+(K86-3000000)*18%,IF(K86<=25000000,1950000+(K86-12000000)*21%,IF(K86<=50000000,4680000+(K86-25000000)*23%,10430000+(K86-50000000)*25%))))) -> 986747.25 | M86: 12 | N86: =L86/M86 -> 82228.938 | O86: 82228.938 | P86: =N86-O86 -> 0
A87: 8 | B87: HAUWA PATE SADIQ | C87: 602846.58 | D87: 12 | E87: =C87*D87 -> 7234159 | G87: 0 | H87: 463532.72 | J87: =F87+G87+H87 -> 463532.72 | K87: =E87-J87 -> 6770626.3 | L87: =IF(K87<=800000,0,IF(K87<=3000000,(K87-800000)*15%,IF(K87<=12000000,330000+(K87-3000000)*18%,IF(K87<=25000000,1950000+(K87-12000000)*21%,IF(K87<=50000000,4680000+(K87-25000000)*23%,10430000+(K87-50000000)*25%))))) -> 1008712.7 | M87: 12 | N87: =L87/M87 -> 84059.394 | O87: 84059.394 | P87: =N87-O87 -> 0
A88: 9 | B88: OBOT ETIMBUK EMMANUEL | C88: 564993.58 | D88: 12 | E88: =C88*D88 -> 6779923 | F88: 240000 | G88: 85934.125 | H88: 436793.84 | J88: =F88+G88+H88 -> 762727.96 | K88: =E88-J88 -> 6017195 | L88: =IF(K88<=800000,0,IF(K88<=3000000,(K88-800000)*15%,IF(K88<=12000000,330000+(K88-3000000)*18%,IF(K88<=25000000,1950000+(K88-12000000)*21%,IF(K88<=50000000,4680000+(K88-25000000)*23%,10430000+(K88-50000000)*25%))))) -> 873095.11 | M88: 12 | N88: =L88/M88 -> 72757.926 | O88: 76357.926 | P88: =N88-O88 -> -3600
A89: 10 | B89: KOLAPO Q. ABAYOMI | C89: 551159 | D89: 12 | E89: =C89*D89 -> 6613908 | F89: 500000 | G89: 75440.375 | H89: 383165.92 | J89: =F89+G89+H89 -> 958606.3 | K89: =E89-J89 -> 5655301.7 | L89: =IF(K89<=800000,0,IF(K89<=3000000,(K89-800000)*15%,IF(K89<=12000000,330000+(K89-3000000)*18%,IF(K89<=25000000,1950000+(K89-12000000)*21%,IF(K89<=50000000,4680000+(K89-25000000)*23%,10430000+(K89-50000000)*25%))))) -> 807954.31 | M89: 12 | N89: =L89/M89 -> 67329.526 | O89: 270358.2 | P89: =N89-O89 -> -203028.67
A90: 11 | B90: SALIHU SHAMSUDEEN OPEYEMI | C90: 438711.67 | D90: 12 | E90: =C90*D90 -> 5264540 | G90: 0 | H90: 325163.2 | J90: =F90+G90+H90 -> 325163.2 | K90: =E90-J90 -> 4939376.8 | L90: =IF(K90<=800000,0,IF(K90<=3000000,(K90-800000)*15%,IF(K90<=12000000,330000+(K90-3000000)*18%,IF(K90<=25000000,1950000+(K90-12000000)*21%,IF(K90<=50000000,4680000+(K90-25000000)*23%,10430000+(K90-50000000)*25%))))) -> 679087.82 | M90: 12 | N90: =L90/M90 -> 56590.652 | O90: 56590.652 | P90: =N90-O90 -> 0
C91: =SUM(C80:C90) -> 6994172.2 | E91: =SUM(E80:E90) -> 83930066 | G91: =SUM(G80:G90) -> 605642.9 | H91: =SUM(H80:H90) -> 5373921 | J91: =SUM(J80:J90) -> 6719563.9 | K91: =SUM(K80:K90) -> 77210502 | L91: =SUM(L80:L90) -> 11587890 | N91: =SUM(N80:N90) -> 965657.53 | O91: 1172286.2 | P91: =SUM(P80:P90) -> -206628.67
B93: DEPARTMENT OF STUDIES
A94: 1 | B94: DR ASIMIYU G. ABIOLA | C94: 1947106.4 | D94: 12 | E94: =C94*D94 -> 23365277 | G94: 0 | H94: 1677222.2 | J94: =F94+G94+H94 -> 1677222.2 | K94: =E94-J94 -> 21688055 | L94: =IF(K94<=800000,0,IF(K94<=3000000,(K94-800000)*15%,IF(K94<=12000000,330000+(K94-3000000)*18%,IF(K94<=25000000,1950000+(K94-12000000)*21%,IF(K94<=50000000,4680000+(K94-25000000)*23%,10430000+(K94-50000000)*25%))))) -> 3984491.5 | M94: 12 | N94: =L94/M94 -> 332040.96 | O94: 332040.96 | P94: =N94-O94 -> 0
A95: 2 | B95: AYOBOLU OLAJIDE OLUFUNSHO | C95: 882595.5 | D95: 12 | E95: =C95*D95 -> 10591146 | G95: 0 | H95: 693691.68 | J95: =F95+G95+H95 -> 693691.68 | K95: =E95-J95 -> 9897454.3 | L95: =IF(K95<=800000,0,IF(K95<=3000000,(K95-800000)*15%,IF(K95<=12000000,330000+(K95-3000000)*18%,IF(K95<=25000000,1950000+(K95-12000000)*21%,IF(K95<=50000000,4680000+(K95-25000000)*23%,10430000+(K95-50000000)*25%))))) -> 1571541.8 | M95: 12 | N95: =L95/M95 -> 130961.81 | O95: 130961.81 | P95: =N95-O95 -> 0
A96: 3 | B96: DR. HADIZA SAIDU | C96: 882595.5 | D96: 12 | E96: =C96*D96 -> 10591146 | G96: 0 | H96: 693691.68 | J96: =F96+G96+H96 -> 693691.68 | K96: =E96-J96 -> 9897454.3 | L96: =IF(K96<=800000,0,IF(K96<=3000000,(K96-800000)*15%,IF(K96<=12000000,330000+(K96-3000000)*18%,IF(K96<=25000000,1950000+(K96-12000000)*21%,IF(K96<=50000000,4680000+(K96-25000000)*23%,10430000+(K96-50000000)*25%))))) -> 1571541.8 | M96: 12 | N96: =L96/M96 -> 130961.81 | O96: 130961.81 | P96: =N96-O96 -> 0
A97: 4 | B97: ANTHONY EDET | C97: 729657 | D97: 12 | E97: =C97*D97 -> 8755884 | G97: 109925.25 | H97: 566070.72 | J97: =F97+G97+H97 -> 675995.97 | K97: =E97-J97 -> 8079888 | L97: =IF(K97<=800000,0,IF(K97<=3000000,(K97-800000)*15%,IF(K97<=12000000,330000+(K97-3000000)*18%,IF(K97<=25000000,1950000+(K97-12000000)*21%,IF(K97<=50000000,4680000+(K97-25000000)*23%,10430000+(K97-50000000)*25%))))) -> 1244379.8 | M97: 12 | N97: =L97/M97 -> 103698.32 | O97: 103698.32 | P97: =N97-O97 -> 0
A98: 5 | B98: CHRISTIAN MADUABUCHI ODO | C98: 617472.75 | D98: 12 | E98: =C98*D98 -> 7409673 | G98: 93501.975 | H98: 477573.84 | J98: =F98+G98+H98 -> 571075.81 | K98: =E98-J98 -> 6838597.2 | L98: =IF(K98<=800000,0,IF(K98<=3000000,(K98-800000)*15%,IF(K98<=12000000,330000+(K98-3000000)*18%,IF(K98<=25000000,1950000+(K98-12000000)*21%,IF(K98<=50000000,4680000+(K98-25000000)*23%,10430000+(K98-50000000)*25%))))) -> 1020947.5 | M98: 12 | N98: =L98/M98 -> 85078.958 | O98: 85078.958 | P98: =N98-O98 -> 0
A99: 6 | B99: DR. IBANGA ISSAC JONAH | C99: 617472.75 | D99: 12 | E99: =C99*D99 -> 7409673 | F99: 260000 | G99: 0 | H99: 477573.84 | J99: =F99+G99+H99 -> 737573.84 | K99: =E99-J99 -> 6672099.2 | L99: =IF(K99<=800000,0,IF(K99<=3000000,(K99-800000)*15%,IF(K99<=12000000,330000+(K99-3000000)*18%,IF(K99<=25000000,1950000+(K99-12000000)*21%,IF(K99<=50000000,4680000+(K99-25000000)*23%,10430000+(K99-50000000)*25%))))) -> 990977.85 | M99: 12 | N99: =L99/M99 -> 82581.487 | O99: 86481.487 | P99: =N99-O99 -> -3900
A100: 7 | B100: IGWE STACY | C100: 578828.17 | D100: 12 | E100: =C100*D100 -> 6945938 | G100: 88398.875 | H100: 450075.04 | J100: =F100+G100+H100 -> 538473.92 | K100: =E100-J100 -> 6407464.1 | L100: =IF(K100<=800000,0,IF(K100<=3000000,(K100-800000)*15%,IF(K100<=12000000,330000+(K100-3000000)*18%,IF(K100<=25000000,1950000+(K100-12000000)*21%,IF(K100<=50000000,4680000+(K100-25000000)*23%,10430000+(K100-50000000)*25%))))) -> 943343.54 | M100: 12 | N100: =L100/M100 -> 78611.961 | O100: 78611.961 | P100: =N100-O100 -> 0
A101: 8 | B101: MUNIRU JIBRIN | C101: 481140.67 | D101: 12 | E101: =C101*D101 -> 5773688 | G101: 0 | H101: 365895.04 | J101: =F101+G101+H101 -> 365895.04 | K101: =E101-J101 -> 5407793 | L101: =IF(K101<=800000,0,IF(K101<=3000000,(K101-800000)*15%,IF(K101<=12000000,330000+(K101-3000000)*18%,IF(K101<=25000000,1950000+(K101-12000000)*21%,IF(K101<=50000000,4680000+(K101-25000000)*23%,10430000+(K101-50000000)*25%))))) -> 763402.73 | M101: 12 | N101: =L101/M101 -> 63616.894 | O101: 63616.894 | P101: =N101-O101 -> 0
A102: 9 | B102: OLANIYAN TAIWO ABINBOLA | C102: 447016.17 | D102: 12 | E102: =C102*D102 -> 5364194 | G102: 66802.375 | H102: 333135.52 | J102: =F102+G102+H102 -> 399937.89 | K102: =E102-J102 -> 4964256.1 | L102: =IF(K102<=800000,0,IF(K102<=3000000,(K102-800000)*15%,IF(K102<=12000000,330000+(K102-3000000)*18%,IF(K102<=25000000,1950000+(K102-12000000)*21%,IF(K102<=50000000,4680000+(K102-25000000)*23%,10430000+(K102-50000000)*25%))))) -> 683566.1 | M102: 12 | N102: =L102/M102 -> 56963.842 | O102: 56963.842 | P102: =N102-O102 -> 0
A103: 10 | B103: MUSA ALKASIM ADAMU | C103: 438711.67 | D103: 12 | E103: =C103*D103 -> 5264540 | G103: 0 | H103: 325163.2 | J103: =F103+G103+H103 -> 325163.2 | K103: =E103-J103 -> 4939376.8 | L103: =IF(K103<=800000,0,IF(K103<=3000000,(K103-800000)*15%,IF(K103<=12000000,330000+(K103-3000000)*18%,IF(K103<=25000000,1950000+(K103-12000000)*21%,IF(K103<=50000000,4680000+(K103-25000000)*23%,10430000+(K103-50000000)*25%))))) -> 679087.82 | M103: 12 | N103: =L103/M103 -> 56590.652 | O103: 56590.652 | P103: =N103-O103 -> 0
A104: 11 | B104: AMINAT JUMOKE SULAIMON | C104: 408920.67 | D104: 12 | E104: =C104*D104 -> 4907048 | G104: 0 | H104: 296563.84 | J104: =F104+G104+H104 -> 296563.84 | K104: =E104-J104 -> 4610484.2 | L104: =IF(K104<=800000,0,IF(K104<=3000000,(K104-800000)*15%,IF(K104<=12000000,330000+(K104-3000000)*18%,IF(K104<=25000000,1950000+(K104-12000000)*21%,IF(K104<=50000000,4680000+(K104-25000000)*23%,10430000+(K104-50000000)*25%))))) -> 619887.15 | M104: 12 | N104: =L104/M104 -> 51657.262 | O104: 51657.262 | P104: =N104-O104 -> 0
B105: TOTAL | C105: =SUM(C94:C104) -> 8031517.2 | E105: =SUM(E94:E104) -> 96378207 | G105: =SUM(G94:G104) -> 358628.47 | H105: =SUM(H94:H104) -> 6356656.6 | J105: =SUM(J94:J104) -> 6975285 | K105: =SUM(K94:K104) -> 89402922 | L105: =SUM(L94:L104) -> 14073168 | N105: =SUM(N94:N104) -> 1172764 | O105: 1176664 | P105: =SUM(P94:P104) -> -3900
B107: ECON. DEV. & SOC. RESEARCH
A108: 1 | B108: DR AUGUSTINE C. OSIGWE | C108: 1897359.3 | D108: 12 | E108: =C108*D108 -> 22768312 | G108: 316881.85 | H108: 1629465 | J108: =F108+G108+H108 -> 1946346.8 | K108: =E108-J108 -> 20821965 | L108: =IF(K108<=800000,0,IF(K108<=3000000,(K108-800000)*15%,IF(K108<=12000000,330000+(K108-3000000)*18%,IF(K108<=25000000,1950000+(K108-12000000)*21%,IF(K108<=50000000,4680000+(K108-25000000)*23%,10430000+(K108-50000000)*25%))))) -> 3802612.7 | M108: 12 | N108: =L108/M108 -> 316884.39 | O108: 316884.39 | P108: =N108-O108 -> 0
A109: 2 | B109: TERFA WILLIAMS ABRAHAM | C109: 1259008.9 | D109: 12 | E109: =C109*D109 -> 15108107 | G109: 0 | H109: 843848.56 | J109: =F109+G109+H109 -> 843848.56 | K109: =E109-J109 -> 14264258 | L109: =IF(K109<=800000,0,IF(K109<=3000000,(K109-800000)*15%,IF(K109<=12000000,330000+(K109-3000000)*18%,IF(K109<=25000000,1950000+(K109-12000000)*21%,IF(K109<=50000000,4680000+(K109-25000000)*23%,10430000+(K109-50000000)*25%))))) -> 2425494.3 | M109: 12 | N109: =L109/M109 -> 202124.52 | O109: 202124.52 | P109: =N109-O109 -> -2.910383e-10
...

Sheet SALLAH WELF
A1: NATIONAL INSTITUTE FOR LEGISLATIVE AND DEMOCRATIC STUDIES
A2: STAFF SALLAH WELFARE MARCH 2026
B4: STAFF NAME | C4: DESIGNATION | D4: GRADE LEVEL | E4: AMOUNT
A6: S/N | B6: DG'S OFFICE | E6: N
A7: 1 | B7: PROF. ABUBAKAR O. SULAIMAN | C7: DIRECTOR GENERAL | D7: CONSOL | E7: 648000
A8: 2 | B8: RAHEEM USMAN AYIGORO | C8: SA-INFRASTRUCTURE | D8: 16 (9) | E8: 216000
A9: 3 | B9: MARIAM MOHAMMED BELLO | C9: SA- SPECIAL DUTIES | D9: 16 (9) | E9: 216000
A10: 4 | B10: DR IKEME ARTHUR J.O | C10: DEPUTY DIRECTOR, M&E | D10: 16 (9) | E10: 216000
A11: 5 | B11: ANDRAWUS MUSA | C11: DEP. DIRECTOR, STORES & PROCUREMENT | D11: 16(9) | E11: 216000
A12: 6 | B12: DR FRANCIS NDUM OJIE | C12: AD, TRAINING & IC./SA TO DG | D12: 15(9) | E12: 151200
A13: 7 | B13: ALI ABDULLAHI | C13: ASST DIRECTOR ICT | D13: 15(7) | E13: 151200
A14: 8 | B14: EMILY EKHIDE | C14: SENIOR RESEARCH FELLOW | D14: 15(9) | E14: 151200
A15: 9 | B15: DORIS DAKDA AARON | C15: RESEARCH FELLOW I | D15: 14(10) | E15: 108000
A16: 10 | B16: ABDULSALAM S. MUSTAPHA | C16: ASST. DIRECTOR ICT | D16: 15(8) | E16: 151200
A17: 11 | B17: PERCY TERFA GBAHABO | C17: RESEARCH FELLOW 1 | D17: 14(8) | E17: 108000
A18: 12 | B18: HASSANA AHMED IBRAHIM | C18: PA- TO DG | D18: 13(11) | E18: 108000
... A46: 40 | B46: ALIYU GARBA LERE | C46: ASSIST INFORMATION OFFICER | D46: 8(8) | E46: 64800
B47: TOTAL | C47: 40 | E47: =SUM(E7:E46) -> 4579200
B49: INTERNAL AUDIT
A50: 1 | B50: OSANAIYE DAVID AKINYEMI | C50: DIRECTOR INTERNAL AUDIT | D50: 17(9) | E50: 324000
A51: 2 | B51: EVELYN ETONKE AGAN | C51: ASST DIR AUDIT | D51: 15(8) | E51: 151200
A52: 3 | B52: JAMILA ABDUL | C52: SENIOR INTERNAL AUDITOR | D52: 10(9) | E52: 81600
A53: 4 | B53: IJEOMA EWELUKWA | C53: PRINCIPAL AUDIT OFFICER | D53: 12(8) | E53: 81600
A54: 5 | B54: HASSAN ABDULHADI | C54: SENIOR INTERNAL AUDITOR | D54: 9(8) | E54: 64800
A55: 6 | B55: YUSUF YUSUF DAYYABU | C55: INERNAL AUDIT OFFICER | D55: 9(9) | E55: 64800
A56: 7 | B56: UDONSI QUEENETH CHIWENDU | C56: ASSIST PROGRAMME OFFICER | D56: 8(8) | E56: 64800
C57: 7 | E57: =SUM(E50:E56) -> 832800
B59: LEG. SUPPORT SEVICES
A60: 1 | B60: BETHEL UZOMA IHUGBA | C60: AG. DIRECTOR, AEEP | D60: 17(8) | E60: 324000
A61: 2 | B61: OGUCHE SAMUEL | C61: SNR RESEARCH FELLOW | D61: 15(9) | E61: 151200
A62: 3 | B62: IBRAHIM USMAN | C62: SNR RESEARCH FELLOW | D62: 15(9) | E62: 151200
A63: 4 | B63: DR MOHAMMED O. AMALI | C63: SNR RESEARCH FELLOW | D63: 15(9) | E63: 151200
A64: 5 | B64: YAHAYA SHAMSU | C64: SNR RESEARCH FELLOW | D64: 15(8) | E64: 151200
A65: 6 | B65: CHIDEBE MATHEW NWANKWO | C65: SNR RESEARCH FELLOW | D65: 15(8) | E65: 151200
A66: 7 | B66: UMAR MUSA PADAH | C66: PRINC. RESEARCH OFFICER | D66: 12(8) | E66: 81600
A67: 8 | B67: BILKIS S. LAWAL-GAMBARI | C67: RESEARCH OFFICER | D67: 10(10) | E67: 81600
A68: 9 | B68: UMOH USENOBONG EMMANUEL | C68: SENIOR RESEARCH OFFICER | D68: 10(8) | E68: 81600
A69: 10 | B69: ZAINAB AKINDE | C69: RESEARCH OFFICER | D69: 9(10) | E69: 64800
A70: 11 | B70: GUNAT NANSAK MARK | C70: RESEARCH OFFICER | D70: 9(10) | E70: 64800
A71: 12 | B71: MANDU ESSIEN NDEM | C71: RESEARCH OFFICER | D71: 9(8) | E71: 64800
B72: TOTAL | C72: 12 | E72: =SUM(E60:E71) -> 1519200
B74: LEGAL SERVICES
A75: 1 | B75: DR SHUAIBU DANWANKA | C75: DIRECTOR LEGAL SERVICES | D75: 17(9) | E75: 324000
A76: 2 | B76: ABDULSALAM BAKO | C76: MANAGER, LEGAL SERVICES | D76: 15 (9) | E76: 151200
B77: TOTAL | C77: 2 | E77: =SUM(E75:E76) -> 475200
B79: DEMOCRACY & GOVERNANCE
A80: 1 | B80: NGARA CHRISTOPHER OCHANJA | C80: DEP DIR DEM & GOVERNANCE | D80: 16(9) | E80: 324000
A81: 2 | B81: EJALONIBU GANIYU LAYI | C81: RESEARCH FELLOW 1 | D81: 14(10) | E81: 108000
A82: 3 | B82: MARTINS SOLOMON UDOM | C82: RESEARCH FELLOW 2 | D82: 13(8) | E82: 108000
A83: 4 | B83: ISHAKA DELE | C83: RESEARCH FELLOW 2 | D83: 13(8) | E83: 108000
A84: 5 | B84: UDEFUNA NNADOZIE PATRICK | C84: RESEARCH FELLOW 2 | D84: 13(7) | E84: 108000
A85: 6 | B85: SHAFIU YAHYA MIKAIL | C85: PRINCIPAL RESEARCH OFFICER | D85: 12(10) | E85: 81600
A86: 7 | B86: HASSAN YERIMA | C86: PRINCIPAL RESEARCH OFFICER | D86: 12(10) | E86: 81600
A87: 8 | B87: HAUWA PATE SADIQ | C87: ASST CHIEF PROGRAMME OFFICER | D87: 13(7) | E87: 108000
A88: 9 | B88: OBOT ETIMBUK EMMANUEL | C88: PRINCIPAL INFO. OFFICER | D88: 12(8) | E88: 81600
A89: 10 | B89: KOLAPO Q. ABAYOMI | C89: PRINCIPAL RESEARCH OFFICER | D89: 12(7) | E89: 81600
A90: 11 | B90: SALIHU SHAMSUDEEN OPEYEMI | C90: PROGRAMME OFFICER | D90: 9(8) | E90: 64800
B91: TOTAL | C91: 11 | E91: =SUM(E80:E90) -> 1255200
B93: DEPARTMENT OF STUDIES
A94: 1 | B94: DR ASIMIYU G. ABIOLA | C94: DIRECTOR POST GRADUATE | D94: 17(9) | E94: 324000
A95: 2 | B95: AYOBOLU OLAJIDE OLUFUNSHO | C95: ASSISTANT DIR. EXXAMS & RECORD | D95: 15(8) | E95: 151200
A96: 3 | B96: DR. HADIZA SAIDU | C96: ASSISTANT DIRECTOR | D96: 15(8) | E96: 151200
A97: 4 | B97: ANTHONY EDET | C97: CHIEF PROGRAMMES OFFICER | D97: 14(11) | E97: 108000
A98: 5 | B98: CHRISTIAN MADUABUCHI ODO | C98: ASSIST. CHIEF ICT OFFICER | D98: 13(8) | E98: 108000
A99: 6 | B99: DR. IBANGA ISSAC JONAH | C99: ASSIST. CHIEF PROGRM OFFICER | D99: 13(8) | E99: 108000
A100: 7 | B100: IGWE STACY | C100: PRINC. PROGRAMME OFFICER | D100: 12(9) | E100: 81600
A101: 8 | B101: MUNIRU JIBRIN | C101: SENIOR PROGRAMME OFFICER | D101: 10(8) | E101: 81600
A102: 9 | B102: OLANIYAN TAIWO ABINBOLA | C102: PROGRAMME OFFICER | D102: 9(9) | E102: 64800
A103: 10 | B103: MUSA ALKASIM ADAMU | C103: PROGRAMME OFFICER | D103: 9(8) | E103: 64800
A104: 11 | B104: AMINAT JUMOKE SULAIMON | C104: AST. PROGRAMME OFFICER | D104: 8(10) | E104: 64800
B105: TOTAL | C105: 11 | E105: =SUM(E94:E104) -> 1308000
B107: ECON. DEV. & SOC. RESEARCH
A108: 1 | B108: DR AUGUSTINE C. OSIGWE | C108: AG. DIRECTOR, ESR | D108: 17(8) | E108: 324000
A109: 2 | B109: TERFA WILLIAMS ABRAHAM | C109: DEP. DIRECTOR ECON & SOCIAL RES | D109: 16(8) | E109: 216000
A110: 3 | B110: IBE EZECHI CYRIACUS | C110: RESEARCH FELLOW 1 | D110: 14(10) | E110: 108000
A111: 4 | B111: OSIKHEN LEO IGBANOI | C111: RESEARCH FELLOW 1 | D111: 14(10) | E111: 108000
A112: 5 | B112: OKUNGBOWA OSARETIN GODSPOWER | C112: RESEARCH FELLOW 1 | D112: 14(9) | E112: 108000
A113: 6 | B113: YUSUF IBRAHIM | C113: PRINCIPAL RESEARCH OFFICER | D113: 12(10) | E113: 81600
A114: 7 | B114: MUSTAPHA RAFIU AYOBANJI | C114: RESEARCH FELLOW 11 | D114: 13(9) | E114: 108000
A115: 8 | B115: UDOKANG NSISONG BONIFACE | C115: PRINC. RESEARCH OFFICER | D115: 12(8) | E115: 81600
A116: 9 | B116: MARYAM MUSA SADA | C116: ASSIT. RESEARCH OFFICER | D116: 10(10) | E116: 81600
A117: 10 | B117: TAWAKALTU FOLASHADE SADIQ | C117: RESEARCH OFFICER | D117: 9(8) | E117: 64800
A118: 11 | B118: MURTALA ADAM MUHAMMAD | C118: RESEARCH OFFICER | D118: 9(8) | E118: 64800
A119: 12 | B119: CHARITY EZENWAJIOBI | C119: RESEARCH OFFICER | D119: 9(7) | E119: 64800
B120: TOTAL | C120: 12 | E120: =SUM(E108:E119) -> 1411200
B122: TRAINING & INT''L COOP
A123: 1 | B123: AKINSANMI ADEJOKE OLUKEMI | C123: AG. DIR. TRAINING & IC | D123: 17(9) | E123: 324000
A124: 2 | B124: MOHAMMED R. ADAMU | C124: CHIEF TRAINING OFFICER | D124: 14(11) | E124: 108000
A125: 3 | B125: EROMOSELE OMONIGBO | C125: ASSIST. CHIEF PERSONNEL OFFICER | D125: 13(9) | E125: 108000
A126: 4 | B126: DR. SAMUEL AKPAN MBADAH | C126: ASSIST. CHIEF TRAINING OFFICER | D126: 13(8) | E126: 108000
A127: 5 | B127: OKECHUKWU UCHENNA HULDA | C127: ASSIST. CHIEF TRAINING OFFICER | D127: 13(8) | E127: 108000
A128: 6 | B128: TASSNEEM IBRAHIM | C128: SENIOR PROGRAMME OFFICER | D128: 10(10) | E128: 81600
A129: 7 | B129: MAHMUD ABDULKADIR | C129: ASST. TRAINING OFFICER | D129: 10(8) | E129: 81600
B130: TOTAL | C130: 7 | E130: =SUM(E123:E129) -> 919200
B132: LIBRARY & DOCUMENTATION
A133: 1 | B133: MAIMUNA IZAH | C133: INSITUTE LIBRARIAN | D133: 17(9) | E133: 324000
A134: 2 | B134: CATHERINE E. IKOKOH | C134: SNR RESEARCH FELLOW DOCU | D134: 16(9) | E134: 216000
A135: 3 | B135: ALIYU SANNI ABUBAKAR | C135: CHIEF LIBRARIAN | D135: 14(9) | E135: 108000
A136: 4 | B136: CHINAKO N. ASOGWA | C136: CHIEF LIBRARIAN | D136: 14(9) | E136: 108000
A137: 5 | B137: AMAKA IJEOMA OLUMONA | C137: PRINC. LIBRARIAN | D137: 12(8) | E137: 81600
...

Sheet Sum of Welfare (4)
A1: SUMMARY OF MARCH 2026 SALLAH WELFARE
C2: N
A3: 1 | B3: Permanent Staff | C3: ='SALLAH WELF'!E246 -> 20868000
A4: 2 | B4: New Permanent Staff | C4: ='[22]Sallah Welf'!$E$89 -> 4550400
A5: 3 | B5: Contract Staff | C5: ='[23]Sallah Welf Contr'!$E$26 -> 2313600
A6: 4 | B6: New Contract Staff | C6: ='[23]Sallah Welf New Contr'!$E$26 -> 1363200
A7: 5 | B7: Casual, Sabbatical & NYSC | C7: ='[23]Sal Welfr CASUAL, SABB & NYSC'!$D$101 -> 54000
A8: 6 | B8: Consultants/Freelance | C8: ='[23]Sallah Welfr CONSULTANTS'!$D$17 -> 928800
A9: 7 | B9: Cleaners & Security Personnel | C9: ='[24]Sallah Welfare'!$E$141 -> 2035000
B10: Total | C10: =SUM(C3:C9) -> 32113000

Sheet 2026 ENHANCED WELFARE (2)
A1: NATIONAL INSTITUTE FOR LEGISLATIVE AND DEMOCRATIC STUDIES
A2: STAFF ENHANCED WELFARE SCHEDULE 2026
B4: STAFF NAME | C4: DESIGNATION | D4: GRADE LEVEL | E4: AMOUNT | F4: Grade Level 01 - 10 | G4: Grade Level 12 - 14 | H4: Grade Level 15 - 17
E5: N | F5: N | G5: N | H5: N
A6: S/N | B6: DG'S OFFICE
A7: 1 | B7: PROF. ABUBAKAR O. SULAIMAN | C7: DIRECTOR GENERAL | D7: CONSOL | E7: 2000000 | H7: =E7 -> 2000000
A8: 2 | B8: RAHEEM USMAN AYIGORO | C8: SA-INFRASTRUCTURE | D8: 16 (9) | E8: 350000 | H8: =E8 -> 350000
A9: 3 | B9: MARIAM MOHAMMED BELLO | C9: SA- SPECIAL DUTIES | D9: 16 (9) | E9: 700000 | H9: =E9 -> 700000
A10: 4 | B10: DR IKEME ARTHUR J.O | C10: DEPUTY DIRECTOR, M&E | D10: 16 (9) | E10: 700000 | H10: =E10 -> 700000
A11: 5 | B11: ANDRAWUS MUSA | C11: DEP. DIRECTOR, STORES & PROCUREMENT | D11: 16(9) | E11: 700000 | H11: =E11 -> 700000
A12: 6 | B12: DR FRANCIS NDUM OJIE | C12: AD, TRAINING & IC./SA TO DG | D12: 15(9) | E12: 700000 | H12: =E12 -> 700000
A13: 7 | B13: ALI ABDULLAHI | C13: ASST DIRECTOR ICT | D13: 15(7) | E13: 700000 | H13: =E13 -> 700000
A14: 8 | B14: EMILY EKHIDE | C14: SENIOR RESEARCH FELLOW | D14: 15(9) | E14: 700000 | H14: =E14 -> 700000
A15: 9 | B15: DORIS DAKDA AARON | C15: RESEARCH FELLOW I | D15: 14(10) | E15: 500000 | G15: =E15 -> 500000
A16: 10 | B16: ABDULSALAM S. MUSTAPHA | C16: ASST. DIRECTOR ICT | D16: 15(8) | E16: 700000 | H16: =E16 -> 700000
A17: 11 | B17: PERCY TERFA GBAHABO | C17: RESEARCH FELLOW 1 | D17: 14(8) | E17: 500000 | G17: =E17 -> 500000
A18: 12 | B18: HASSANA AHMED IBRAHIM | C18: PA- TO DG | D18: 13(11) | E18: 500000 | G18: =E18 -> 500000
A19: 13 | B19: IKIP LEBO | C19: ASST CHIEF PROC. OFFICER | D19: 13 (9) | E19: 250000 | G19: =E19 -> 250000
A20: 14 | B20: ALABI ADESINA MUHYDEEN | C20: HEAD, NILDS LIAISON OFFICE | D20: 13 (9) | E20: 500000 | G20: =E20 -> 500000
A21: 15 | B21: BASSEY NSONGURUA UDOFIA | C21: PRINC.CONF SEC 1/PPS | D21: 13(8) | E21: 500000 | G21: =E21 -> 500000
A22: 16 | B22: ADUGBA RICHARD TERSEER | C22: ASSIST. CHIEF INFO OFFICER | D22: 13(7) | E22: 500000 | G22: =E22 -> 500000
A23: 17 | B23: LUCKY AGWOM | C23: RESEARCH ASSISTANT | D23: 12(9) | E23: 400000 | G23: =E23 -> 400000
A24: 18 | B24: IDRIS IBRAHIM | C24: PRINCIPAL RESEARCH OFFICER | D24: 12(9) | E24: 400000 | G24: =E24 -> 400000
A25: 19 | B25: FARUQ ATOFARATI | C25: PA (SPECIAL DUTIES) TO DG | D25: 10(8) | E25: 300000 | F25: =E25 -> 300000
A26: 20 | B26: RASHEEDAT DAIBU | C26: SENIOR INFO. OFFICER | D26: 10(9) | E26: 300000 | F26: =E26 -> 300000
A27: 21 | B27: VICTOR ASUKWO | C27: SENIOR ICT OFFICER | D27: 10(7) | E27: 300000 | F27: =E27 -> 300000
A28: 22 | B28: NNANDI LIVINUS ATURE | C28: SENIOR RESEARCH OFFICER | D28: 10(8) | E28: 300000 | F28: =E28 -> 300000
A29: 23 | B29: ABDULRAHMAN A SULAIMAN | C29: STORE OFFICER | D29: 9(10) | E29: 300000 | F29: =E29 -> 300000
A30: 24 | B30: DARE SHEU MAGBON | C30: ADMINISTRATION OFFICER | D30: 9(9) | E30: 300000 | F30: =E30 -> 300000
A31: 25 | B31: ABUBAKAR SULAIMAN SODEEQ | C31: SENIOR M&E OFFICER | D31: 10(7) | E31: 300000 | F31: =E31 -> 300000
A32: 26 | B32: JIMOH ADEBAYO ZAKA | C32: SENIOR INFO OFFICER | D32: 10(7) | E32: 300000 | F32: =E32 -> 300000
A33: 27 | B33: ABDULMUSHIN TAWFIQ LADAN | C33: ICT OFFICER | D33: 9(9) | E33: 300000 | F33: =E33 -> 300000
A34: 28 | B34: MOHAMMED BELLO | C34: SENIOR PROTOCOL OFFICER | D34: 10(7) | E34: 300000 | F34: =E34 -> 300000
A35: 29 | B35: HOLINESS PAUL UDO | C35: ADMINISTRATION OFFICER, M&E | D35: 9(8) | E35: 300000 | F35: =E35 -> 300000
A36: 30 | B36: CHARITY UDO AKAN | C36: ADMINISTRATION OFFICER, M&E | D36: 9(8) | E36: 300000 | F36: =E36 -> 300000
... A46: 40 | B46: ALIYU GARBA LERE | C46: ASSIST INFORMATION OFFICER | D46: 8(8) | E46: 300000 | F46: =E46 -> 300000
B47: TOTAL | C47: 40 | E47: =SUM(E7:E46) -> 17900000 | F47: =SUM(F7:F46) -> 6600000 | G47: =SUM(G7:G46) -> 4050000 | H47: =SUM(H7:H46) -> 7250000
B49: INTERNAL AUDIT
A50: 1 | B50: OSANAIYE DAVID AKINYEMI | C50: DIRECTOR INTERNAL AUDIT | D50: 17(9) | E50: 1000000 | H50: =E50 -> 1000000
A51: 2 | B51: EVELYN ETONKE AGAN | C51: ASST DIR AUDIT | D51: 15(8) | E51: 700000 | H51: =E51 -> 700000
A52: 3 | B52: JAMILA ABDUL | C52: SENIOR INTERNAL AUDITOR | D52: 10(9) | E52: 300000 | F52: =E52 -> 300000
A53: 4 | B53: IJEOMA EWELUKWA | C53: PRINCIPAL AUDIT OFFICER | D53: 12(8) | E53: 400000 | G53: =E53 -> 400000
A54: 5 | B54: HASSAN ABDULHADI | C54: SENIOR INTERNAL AUDITOR | D54: 9(8) | E54: 300000 | F54: =E54 -> 300000
A55: 6 | B55: YUSUF YUSUF DAYYABU | C55: INERNAL AUDIT OFFICER | D55: 9(9) | E55: 300000 | F55: =E55 -> 300000
A56: 7 | B56: UDONSI QUEENETH CHIWENDU | C56: ASSIST PROGRAMME OFFICER | D56: 8(8) | E56: 300000 | F56: =E56 -> 300000
C57: 7 | E57: =SUM(E50:E56) -> 3300000 | F57: =SUM(F50:F56) -> 1200000 | G57: =SUM(G50:G56) -> 400000 | H57: =SUM(H50:H56) -> 1700000
B59: LEG. SUPPORT SEVICES
A60: 1 | B60: BETHEL UZOMA IHUGBA | C60: AG. DIRECTOR, AEEP | D60: 17(8) | E60: 1000000 | H60: =E60 -> 1000000
A61: 2 | B61: OGUCHE SAMUEL | C61: DEPUTY DIRECTOR | D61: 16(7) | E61: 700000 | H61: =E61 -> 700000
A62: 3 | B62: IBRAHIM USMAN | C62: SNR RESEARCH FELLOW | D62: 15(9) | E62: 700000 | H62: =E62 -> 700000
A63: 4 | B63: DR MOHAMMED O. AMALI | C63: SNR RESEARCH FELLOW | D63: 15(9) | E63: 700000 | H63: =E63 -> 700000
A64: 5 | B64: YAHAYA SHAMSU | C64: SNR RESEARCH FELLOW | D64: 15(8) | E64: 700000 | H64: =E64 -> 700000
A65: 6 | B65: CHIDEBE MATHEW NWANKWO | C65: SNR RESEARCH FELLOW | D65: 15(8) | E65: 700000 | H65: =E65 -> 700000
A66: 7 | B66: UMAR MUSA PADAH | C66: PRINC. RESEARCH OFFICER | D66: 12(8) | E66: 400000 | G66: =E66 -> 400000
A67: 8 | B67: BILKIS S. LAWAL-GAMBARI | C67: RESEARCH OFFICER | D67: 10(10) | E67: 300000 | F67: =E67 -> 300000
A68: 9 | B68: UMOH USENOBONG EMMANUEL | C68: SENIOR RESEARCH OFFICER | D68: 10(8) | E68: 300000 | F68: =E68 -> 300000
A69: 10 | B69: ZAINAB AKINDE | C69: RESEARCH OFFICER | D69: 9(10) | E69: 300000 | F69: =E69 -> 300000
A70: 11 | B70: GUNAT NANSAK MARK | C70: RESEARCH OFFICER | D70: 9(10) | E70: 300000 | F70: =E70 -> 300000
A71: 12 | B71: MANDU ESSIEN NDEM | C71: RESEARCH OFFICER | D71: 9(8) | E71: 300000 | F71: =E71 -> 300000
B72: TOTAL | C72: 12 | E72: =SUM(E60:E71) -> 6400000 | F72: =SUM(F60:F71) -> 1500000 | G72: =SUM(G60:G71) -> 400000 | H72: =SUM(H60:H71) -> 4500000
B74: LEGAL SERVICES
A75: 1 | B75: DR SHUAIBU DANWANKA | C75: DIRECTOR LEGAL SERVICES | D75: 17(9) | E75: 500000 | H75: =E75 -> 500000
A76: 2 | B76: ABDULSALAM BAKO | C76: DD LEGAL SERVICES | D76: 16 (7) | E76: 700000 | H76: =E76 -> 700000
B77: TOTAL | C77: 2 | E77: =SUM(E75:E76) -> 1200000 | F77: =SUM(F75:F76) -> 0 | G77: =SUM(G75:G76) -> 0 | H77: =SUM(H75:H76) -> 1200000
B79: DEMOCRACY & GOVERNANCE
A80: 1 | B80: NGARA CHRISTOPHER OCHANJA | C80: DEP DIR DEM & GOVERNANCE | D80: 16(9) | E80: 1000000 | H80: =E80 -> 1000000
A81: 2 | B81: EJALONIBU GANIYU LAYI | C81: RESEARCH FELLOW 1 | D81: 14(10) | E81: 500000 | G81: =E81 -> 500000
A82: 3 | B82: MARTINS SOLOMON UDOM | C82: RESEARCH FELLOW 11 | D82: 13(8) | E82: 500000 | G82: =E82 -> 500000
A83: 4 | B83: ISHAKA DELE | C83: RESEARCH FELLOW 11 | D83: 13(8) | E83: 500000 | G83: =E83 -> 500000
A84: 5 | B84: UDEFUNA NNADOZIE PATRICK | C84: RESEARCH OFFICER | D84: 12(10) | E84: 400000 | G84: =E84 -> 400000
A85: 6 | B85: SHAFIU YAHYA MIKAIL | C85: PRINCIPAL RESEARCH OFFICER | D85: 12(10) | E85: 400000 | G85: =E85 -> 400000
A86: 7 | B86: HASSAN YERIMA | C86: PRINCIPAL RESEARCH OFFICER | D86: 12(10) | E86: 400000 | G86: =E86 -> 400000
A87: 8 | B87: HAUWA PATE SADIQ | C87: ASST CHIEF PROGRAMME OFFICER | D87: 13(7) | E87: 500000 | G87: =E87 -> 500000
A88: 9 | B88: OBOT ETIMBUK EMMANUEL | C88: PRINCIPAL INFO. OFFICER | D88: 12(8) | E88: 400000 | G88: =E88 -> 400000
A89: 10 | B89: KOLAPO Q. ABAYOMI | C89: RESEARCH OFFICER | D89: 12(8) | E89: 400000 | G89: =E89 -> 400000
A90: 11 | B90: SALIHU SHAMSUDEEN OPEYEMI | C90: PROGRAMME OFFICER | D90: 9(8) | E90: 300000 | F90: =E90 -> 300000
B91: TOTAL | C91: 11 | E91: =SUM(E80:E90) -> 5300000 | F91: =SUM(F80:F90) -> 300000 | G91: =SUM(G80:G90) -> 4000000 | H91: =SUM(H80:H90) -> 1000000
B93: DEPARTMENT OF STUDIES
A94: 1 | B94: DR ASIMIYU G. ABIOLA | C94: DIRECTOR POST GRADUATE | D94: 17(9) | E94: 1000000 | H94: =E94 -> 1000000
A95: 2 | B95: AYOBOLU OLAJIDE OLUFUNSHO | C95: ASSISTANT DIR. EXXAMS & RECORD | D95: 15(8) | E95: 700000 | H95: =E95 -> 700000
A96: 3 | B96: DR. HADIZA SAIDU | C96: ASSISTANT DIRECTOR | D96: 15(8) | E96: 700000 | H96: =E96 -> 700000
A97: 4 | B97: ANTHONY EDET | C97: CHIEF PROGRAMMES OFFICER | D97: 14(11) | E97: 500000 | G97: =E97 -> 500000
A98: 5 | B98: CHRISTIAN MADUABUCHI ODO | C98: ASSIST. CHIEF ICT OFFICER | D98: 13(8) | E98: 500000 | G98: =E98 -> 500000
A99: 6 | B99: DR. IBANGA ISSAC JONAH | C99: ASSIST. CHIEF PROGRM OFFICER | D99: 13(8) | E99: 500000 | G99: =E99 -> 500000
A100: 7 | B100: IGWE STACY | C100: PRINC. PROGRAMME OFFICER | D100: 12(9) | E100: 400000 | G100: =E100 -> 400000
A101: 8 | B101: MUNIRU JIBRIN | C101: SENIOR PROGRAMME OFFICER | D101: 10(8) | E101: 300000 | F101: =E101 -> 300000
A102: 9 | B102: OLANIYAN TAIWO ABINBOLA | C102: PROGRAMME OFFICER | D102: 9(9) | E102: 300000 | F102: =E102 -> 300000
A103: 10 | B103: MUSA ALKASIM ADAMU | C103: PROGRAMME OFFICER | D103: 9(8) | E103: 300000 | F103: =E103 -> 300000
A104: 11 | B104: AMINAT JUMOKE SULAIMON | C104: AST. PROGRAMME OFFICER | D104: 8(10) | E104: 300000 | F104: =E104 -> 300000
B105: TOTAL | C105: 11 | E105: =SUM(E94:E104) -> 5500000 | F105: =SUM(F94:F104) -> 1200000 | G105: =SUM(G94:G104) -> 1900000 | H105: =SUM(H94:H104) -> 2400000
B107: ECON. DEV. & SOC. RESEARCH
A108: 1 | B108: DR AUGUSTINE C. OSIGWE | C108: AG. DIRECTOR, ESR | D108: 17(8) | E108: 1000000 | H108: =E108 -> 1000000
A109: 2 | B109: TERFA WILLIAMS ABRAHAM | C109: DEP. DIRECTOR ECON & SOCIAL RES | D109: 16(8) | E109: 700000 | H109: =E109 -> 700000
A110: 3 | B110: IBE EZECHI CYRIACUS | C110: RESEARCH FELLOW 1 | D110: 14(10) | E110: 500000 | G110: =E110 -> 500000
A111: 4 | B111: OSIKHEN LEO IGBANOI | C111: RESEARCH FELLOW 1 | D111: 14(10) | E111: 500000 | G111: =E111 -> 500000
A112: 5 | B112: OKUNGBOWA OSARETIN GODSPOWER | C112: RESEARCH FELLOW 1 | D112: 14(9) | E112: 250000 | G112: =E112 -> 250000
A113: 6 | B113: YUSUF IBRAHIM | C113: PRINCIPAL RESEARCH OFFICER | D113: 12(10) | E113: 400000 | G113: =E113 -> 400000
A114: 7 | B114: MUSTAPHA RAFIU AYOBANJI | C114: RESEARCH FELLOW 11 | D114: 13(9) | E114: 250000 | G114: =E114 -> 250000
A115: 8 | B115: UDOKANG NSISONG BONIFACE | C115: PRINC. RESEARCH OFFICER | D115: 12(8) | E115: 400000 | G115: =E115 -> 400000
A116: 9 | B116: MARYAM MUSA SADA | C116: ASSIT. RESEARCH OFFICER | D116: 10(10) | E116: 300000 | F116: =E116 -> 300000
...

Sheet Sheet18

Sheet FCTIRS Template
A1: PAY AS YOU EARN COMPUTATION
A2: NAME ORGANISATION:
A3: ASSESSMENT YEAR: | D3: 2026 | E3: ELIGIBLE DEDUCTIONS
A4: S/N | B4: EMPLOYEE NAME | C4: TAX IDENTIFICATION | D4: ANNUAL GROSS EMOLUMENTS | E4: ANNUAL RENT | F4: RENT | G4: NHF | H4: NHIS | I4: PENSION CONTRIBUTION | J4: TOTAL ELIGIBLE DEDUCTIONS | K4: CHARGEABLE INCOME | L4: 1ST 800,000 @ 0% | M4: NEXT 2,200,000 @ 15% | N4: NEXT 9,000,000 @ 18% | O4: NEXT 13,000,000 @ 21% | P4: NEXT 25000000 @ 23% | Q4: EXCESS OF 50000000 @ 25% | R4: ANNUAL TAX DUE | S4: MONTHLY TAX DUE
C5: FCT TAXPAYER ID | F5: RELIEF | G5: 2.5% of Annual Income | H5: 1.75% of Annual Emoluments | I5: 8% of the Gross Salary
D6: Enter Total Annual Earnings Here | F6: Lower of the 20% actual rent paid or N500,000 | G6: Leave as computed if dedeuctions tally, otherwise, enter correct deductions. Note: You may be required to show evidence of deductions and remittance
B7: DG'S OFFICE
A8: 1 | B8: PROF. ABUBAKAR O. SULAIMAN | F8: =MIN(0.2*E8,500000) -> 0 | J8: =SUM(F8:I8) -> 0 | K8: =(D8-J8) -> 0 | L8: =(K8*0%) -> 0 | M8: =IF((K8-800000)<=0,0,IF((K8-800000)>=2200000,2200000*15%,(K8-800000)*15%)) -> 0 | N8: =IF((K8-(3000000))<=0,0,IF((K8-(3000000))>=9000000,9000000*18%,(K8-(3000000))*18%)) -> 0 | O8: =IF((K8-(12000000))<=0,0,IF((K8-(12000000))>=13000000,13000000*21%,(K8-(12000000))*21%)) -> 0 | P8: =IF((K8-(25000000))<=0,0,IF((K8-(25000000))>=25000000,25000000*23%,(K8-(25000000))*23%)) -> 0 | Q8: =IF((K8-(50000000))<=0,0,(K8-(50000000))*25%) -> 0 | R8: =SUM(L8:Q8) -> 0 | S8: =R8/12 -> 0
A9: 2 | B9: RAHEEM USMAN AYIGORO | F9: =MIN(0.2*E9,500000) -> 0 | J9: =SUM(F9:I9) -> 0 | K9: =(D9-J9) -> 0 | L9: =(K9*0%) -> 0 | M9: =IF((K9-800000)<=0,0,IF((K9-800000)>=2200000,2200000*15%,(K9-800000)*15%)) -> 0 | N9: =IF((K9-(3000000))<=0,0,IF((K9-(3000000))>=9000000,9000000*18%,(K9-(3000000))*18%)) -> 0 | O9: =IF((K9-(12000000))<=0,0,IF((K9-(12000000))>=13000000,13000000*21%,(K9-(12000000))*21%)) -> 0 | P9: =IF((K9-(25000000))<=0,0,IF((K9-(25000000))>=25000000,25000000*23%,(K9-(25000000))*23%)) -> 0 | Q9: =IF((K9-(50000000))<=0,0,(K9-(50000000))*25%) -> 0 | R9: =SUM(L9:Q9) -> 0 | S9: =R9/12 -> 0
A10: 3 | B10: MARIAM MOHAMMED BELLO | F10: =MIN(0.2*E10,500000) -> 0 | J10: =SUM(F10:I10) -> 0 | K10: =(D10-J10) -> 0 | L10: =(K10*0%) -> 0 | M10: =IF((K10-800000)<=0,0,IF((K10-800000)>=2200000,2200000*15%,(K10-800000)*15%)) -> 0 | N10: =IF((K10-(3000000))<=0,0,IF((K10-(3000000))>=9000000,9000000*18%,(K10-(3000000))*18%)) -> 0 | O10: =IF((K10-(12000000))<=0,0,IF((K10-(12000000))>=13000000,13000000*21%,(K10-(12000000))*21%)) -> 0 | P10: =IF((K10-(25000000))<=0,0,IF((K10-(25000000))>=25000000,25000000*23%,(K10-(25000000))*23%)) -> 0 | Q10: =IF((K10-(50000000))<=0,0,(K10-(50000000))*25%) -> 0 | R10: =SUM(L10:Q10) -> 0 | S10: =R10/12 -> 0
A11: 4 | B11: DR IKEME ARTHUR J.O | F11: =MIN(0.2*E11,500000) -> 0 | J11: =SUM(F11:I11) -> 0 | K11: =(D11-J11) -> 0 | L11: =(K11*0%) -> 0 | M11: =IF((K11-800000)<=0,0,IF((K11-800000)>=2200000,2200000*15%,(K11-800000)*15%)) -> 0 | N11: =IF((K11-(3000000))<=0,0,IF((K11-(3000000))>=9000000,9000000*18%,(K11-(3000000))*18%)) -> 0 | O11: =IF((K11-(12000000))<=0,0,IF((K11-(12000000))>=13000000,13000000*21%,(K11-(12000000))*21%)) -> 0 | P11: =IF((K11-(25000000))<=0,0,IF((K11-(25000000))>=25000000,25000000*23%,(K11-(25000000))*23%)) -> 0 | Q11: =IF((K11-(50000000))<=0,0,(K11-(50000000))*25%) -> 0 | R11: =SUM(L11:Q11) -> 0 | S11: =R11/12 -> 0
A12: 5 | B12: ANDRAWUS MUSA | F12: =MIN(0.2*E12,500000) -> 0 | J12: =SUM(F12:I12) -> 0 | K12: =(D12-J12) -> 0 | L12: =(K12*0%) -> 0 | M12: =IF((K12-800000)<=0,0,IF((K12-800000)>=2200000,2200000*15%,(K12-800000)*15%)) -> 0 | N12: =IF((K12-(3000000))<=0,0,IF((K12-(3000000))>=9000000,9000000*18%,(K12-(3000000))*18%)) -> 0 | O12: =IF((K12-(12000000))<=0,0,IF((K12-(12000000))>=13000000,13000000*21%,(K12-(12000000))*21%)) -> 0 | P12: =IF((K12-(25000000))<=0,0,IF((K12-(25000000))>=25000000,25000000*23%,(K12-(25000000))*23%)) -> 0 | Q12: =IF((K12-(50000000))<=0,0,(K12-(50000000))*25%) -> 0 | R12: =SUM(L12:Q12) -> 0 | S12: =R12/12 -> 0
A13: 6 | B13: DR FRANCIS NDUM OJIE | F13: =MIN(0.2*E13,500000) -> 0 | J13: =SUM(F13:I13) -> 0 | K13: =(D13-J13) -> 0 | L13: =(K13*0%) -> 0 | M13: =IF((K13-800000)<=0,0,IF((K13-800000)>=2200000,2200000*15%,(K13-800000)*15%)) -> 0 | N13: =IF((K13-(3000000))<=0,0,IF((K13-(3000000))>=9000000,9000000*18%,(K13-(3000000))*18%)) -> 0 | O13: =IF((K13-(12000000))<=0,0,IF((K13-(12000000))>=13000000,13000000*21%,(K13-(12000000))*21%)) -> 0 | P13: =IF((K13-(25000000))<=0,0,IF((K13-(25000000))>=25000000,25000000*23%,(K13-(25000000))*23%)) -> 0 | Q13: =IF((K13-(50000000))<=0,0,(K13-(50000000))*25%) -> 0 | R13: =SUM(L13:Q13) -> 0 | S13: =R13/12 -> 0
A14: 7 | B14: ALI ABDULLAHI | F14: =MIN(0.2*E14,500000) -> 0 | J14: =SUM(F14:I14) -> 0 | K14: =(D14-J14) -> 0 | L14: =(K14*0%) -> 0 | M14: =IF((K14-800000)<=0,0,IF((K14-800000)>=2200000,2200000*15%,(K14-800000)*15%)) -> 0 | N14: =IF((K14-(3000000))<=0,0,IF((K14-(3000000))>=9000000,9000000*18%,(K14-(3000000))*18%)) -> 0 | O14: =IF((K14-(12000000))<=0,0,IF((K14-(12000000))>=13000000,13000000*21%,(K14-(12000000))*21%)) -> 0 | P14: =IF((K14-(25000000))<=0,0,IF((K14-(25000000))>=25000000,25000000*23%,(K14-(25000000))*23%)) -> 0 | Q14: =IF((K14-(50000000))<=0,0,(K14-(50000000))*25%) -> 0 | R14: =SUM(L14:Q14) -> 0 | S14: =R14/12 -> 0
A15: 8 | B15: EMILY EKHIDE | F15: =MIN(0.2*E15,500000) -> 0 | G15: =D15*2.5% -> 0 | J15: =SUM(J8:J14) -> 0 | K15: =(D15-J15) -> 0 | L15: =(K15*0%) -> 0 | M15: =IF((K15-800000)<=0,0,IF((K15-800000)>=2200000,2200000*15%,(K15-800000)*15%)) -> 0 | N15: =IF((K15-(3000000))<=0,0,IF((K15-(3000000))>=9000000,9000000*18%,(K15-(3000000))*18%)) -> 0 | O15: =IF((K15-(12000000))<=0,0,IF((K15-(12000000))>=13000000,13000000*21%,(K15-(12000000))*21%)) -> 0 | P15: =IF((K15-(25000000))<=0,0,IF((K15-(25000000))>=25000000,25000000*23%,(K15-(25000000))*23%)) -> 0 | Q15: =IF((K15-(50000000))<=0,0,(K15-(50000000))*25%) -> 0 | R15: =SUM(R8:R14) -> 0 | S15: =SUM(S8:S14) -> 0
A16: 9 | B16: DORIS DAKDA AARON | F16: =MIN(0.2*E16,500000) -> 0 | G16: =D16*2.5% -> 0 | H16: =D16*1.75% -> 0 | I16: =D16*8% -> 0 | J16: =SUM(F16:I16) -> 0 | K16: =(D16-J16) -> 0 | L16: =(K16*0%) -> 0 | M16: =IF((K16-800000)<=0,0,IF((K16-800000)>=2200000,2200000*15%,(K16-800000)*15%)) -> 0 | N16: =IF((K16-(3000000))<=0,0,IF((K16-(3000000))>=9000000,9000000*18%,(K16-(3000000))*18%)) -> 0 | O16: =IF((K16-(12000000))<=0,0,IF((K16-(12000000))>=13000000,13000000*21%,(K16-(12000000))*21%)) -> 0 | P16: =IF((K16-(25000000))<=0,0,IF((K16-(25000000))>=25000000,25000000*23%,(K16-(25000000))*23%)) -> 0 | Q16: =IF((K16-(50000000))<=0,0,(K16-(50000000))*25%) -> 0 | R16: =SUM(L16:Q16) -> 0 | S16: =R16/12 -> 0
A17: 10 | B17: ABDULSALAM S. MUSTAPHA | F17: =MIN(0.2*E17,500000) -> 0 | G17: =D17*2.5% -> 0 | H17: =D17*1.75% -> 0 | I17: =D17*8% -> 0 | J17: =SUM(F17:I17) -> 0 | K17: =(D17-J17) -> 0 | L17: =(K17*0%) -> 0 | M17: =IF((K17-800000)<=0,0,IF((K17-800000)>=2200000,2200000*15%,(K17-800000)*15%)) -> 0 | N17: =IF((K17-(3000000))<=0,0,IF((K17-(3000000))>=9000000,9000000*18%,(K17-(3000000))*18%)) -> 0 | O17: =IF((K17-(12000000))<=0,0,IF((K17-(12000000))>=13000000,13000000*21%,(K17-(12000000))*21%)) -> 0 | P17: =IF((K17-(25000000))<=0,0,IF((K17-(25000000))>=25000000,25000000*23%,(K17-(25000000))*23%)) -> 0 | Q17: =IF((K17-(50000000))<=0,0,(K17-(50000000))*25%) -> 0 | R17: =SUM(L17:Q17) -> 0 | S17: =R17/12 -> 0
A18: 11 | B18: PERCY TERFA GBAHABO | F18: =MIN(0.2*E18,500000) -> 0 | G18: =D18*2.5% -> 0 | H18: =D18*1.75% -> 0 | I18: =D18*8% -> 0 | J18: =SUM(F18:I18) -> 0 | K18: =(D18-J18) -> 0 | L18: =(K18*0%) -> 0 | M18: =IF((K18-800000)<=0,0,IF((K18-800000)>=2200000,2200000*15%,(K18-800000)*15%)) -> 0 | N18: =IF((K18-(3000000))<=0,0,IF((K18-(3000000))>=9000000,9000000*18%,(K18-(3000000))*18%)) -> 0 | O18: =IF((K18-(12000000))<=0,0,IF((K18-(12000000))>=13000000,13000000*21%,(K18-(12000000))*21%)) -> 0 | P18: =IF((K18-(25000000))<=0,0,IF((K18-(25000000))>=25000000,25000000*23%,(K18-(25000000))*23%)) -> 0 | Q18: =IF((K18-(50000000))<=0,0,(K18-(50000000))*25%) -> 0 | R18: =SUM(L18:Q18) -> 0 | S18: =R18/12 -> 0
A19: 12 | B19: HASSANA AHMED IBRAHIM | F19: =MIN(0.2*E19,500000) -> 0 | G19: =D19*2.5% -> 0 | H19: =D19*1.75% -> 0 | I19: =D19*8% -> 0 | J19: =SUM(F19:I19) -> 0 | K19: =(D19-J19) -> 0 | L19: =(K19*0%) -> 0 | M19: =IF((K19-800000)<=0,0,IF((K19-800000)>=2200000,2200000*15%,(K19-800000)*15%)) -> 0 | N19: =IF((K19-(3000000))<=0,0,IF((K19-(3000000))>=9000000,9000000*18%,(K19-(3000000))*18%)) -> 0 | O19: =IF((K19-(12000000))<=0,0,IF((K19-(12000000))>=13000000,13000000*21%,(K19-(12000000))*21%)) -> 0 | P19: =IF((K19-(25000000))<=0,0,IF((K19-(25000000))>=25000000,25000000*23%,(K19-(25000000))*23%)) -> 0 | Q19: =IF((K19-(50000000))<=0,0,(K19-(50000000))*25%) -> 0 | R19: =SUM(L19:Q19) -> 0 | S19: =R19/12 -> 0
A20: 13 | B20: IKIP LEBO | F20: =MIN(0.2*E20,500000) -> 0 | G20: =D20*2.5% -> 0 | H20: =D20*1.75% -> 0 | I20: =D20*8% -> 0 | J20: =SUM(F20:I20) -> 0 | K20: =(D20-J20) -> 0 | L20: =(K20*0%) -> 0 | M20: =IF((K20-800000)<=0,0,IF((K20-800000)>=2200000,2200000*15%,(K20-800000)*15%)) -> 0 | N20: =IF((K20-(3000000))<=0,0,IF((K20-(3000000))>=9000000,9000000*18%,(K20-(3000000))*18%)) -> 0 | O20: =IF((K20-(12000000))<=0,0,IF((K20-(12000000))>=13000000,13000000*21%,(K20-(12000000))*21%)) -> 0 | P20: =IF((K20-(25000000))<=0,0,IF((K20-(25000000))>=25000000,25000000*23%,(K20-(25000000))*23%)) -> 0 | Q20: =IF((K20-(50000000))<=0,0,(K20-(50000000))*25%) -> 0 | R20: =SUM(L20:Q20) -> 0 | S20: =R20/12 -> 0
A21: 14 | B21: ALABI ADESINA MUHYDEEN | F21: =MIN(0.2*E21,500000) -> 0 | G21: =D21*2.5% -> 0 | H21: =D21*1.75% -> 0 | I21: =D21*8% -> 0 | J21: =SUM(F21:I21) -> 0 | K21: =(D21-J21) -> 0 | L21: =(K21*0%) -> 0 | M21: =IF((K21-800000)<=0,0,IF((K21-800000)>=2200000,2200000*15%,(K21-800000)*15%)) -> 0 | N21: =IF((K21-(3000000))<=0,0,IF((K21-(3000000))>=9000000,9000000*18%,(K21-(3000000))*18%)) -> 0 | O21: =IF((K21-(12000000))<=0,0,IF((K21-(12000000))>=13000000,13000000*21%,(K21-(12000000))*21%)) -> 0 | P21: =IF((K21-(25000000))<=0,0,IF((K21-(25000000))>=25000000,25000000*23%,(K21-(25000000))*23%)) -> 0 | Q21: =IF((K21-(50000000))<=0,0,(K21-(50000000))*25%) -> 0 | R21: =SUM(L21:Q21) -> 0 | S21: =R21/12 -> 0
A22: 15 | B22: BASSEY NSONGURUA UDOFIA | F22: =MIN(0.2*E22,500000) -> 0 | G22: =D22*2.5% -> 0 | H22: =D22*1.75% -> 0 | I22: =D22*8% -> 0 | J22: =SUM(F22:I22) -> 0 | K22: =(D22-J22) -> 0 | L22: =(K22*0%) -> 0 | M22: =IF((K22-800000)<=0,0,IF((K22-800000)>=2200000,2200000*15%,(K22-800000)*15%)) -> 0 | N22: =IF((K22-(3000000))<=0,0,IF((K22-(3000000))>=9000000,9000000*18%,(K22-(3000000))*18%)) -> 0 | O22: =IF((K22-(12000000))<=0,0,IF((K22-(12000000))>=13000000,13000000*21%,(K22-(12000000))*21%)) -> 0 | P22: =IF((K22-(25000000))<=0,0,IF((K22-(25000000))>=25000000,25000000*23%,(K22-(25000000))*23%)) -> 0 | Q22: =IF((K22-(50000000))<=0,0,(K22-(50000000))*25%) -> 0 | R22: =SUM(L22:Q22) -> 0 | S22: =R22/12 -> 0
A23: 16 | B23: ADUGBA RICHARD TERSEER | F23: =MIN(0.2*E23,500000) -> 0 | G23: =D23*2.5% -> 0 | H23: =D23*1.75% -> 0 | I23: =D23*8% -> 0 | J23: =SUM(F23:I23) -> 0 | K23: =(D23-J23) -> 0 | L23: =(K23*0%) -> 0 | M23: =IF((K23-800000)<=0,0,IF((K23-800000)>=2200000,2200000*15%,(K23-800000)*15%)) -> 0 | N23: =IF((K23-(3000000))<=0,0,IF((K23-(3000000))>=9000000,9000000*18%,(K23-(3000000))*18%)) -> 0 | O23: =IF((K23-(12000000))<=0,0,IF((K23-(12000000))>=13000000,13000000*21%,(K23-(12000000))*21%)) -> 0 | P23: =IF((K23-(25000000))<=0,0,IF((K23-(25000000))>=25000000,25000000*23%,(K23-(25000000))*23%)) -> 0 | Q23: =IF((K23-(50000000))<=0,0,(K23-(50000000))*25%) -> 0 | R23: =SUM(L23:Q23) -> 0 | S23: =R23/12 -> 0
A24: 17 | B24: LUCKY AGWOM | F24: =MIN(0.2*E24,500000) -> 0 | G24: =D24*2.5% -> 0 | H24: =D24*1.75% -> 0 | I24: =D24*8% -> 0 | J24: =SUM(F24:I24) -> 0 | K24: =(D24-J24) -> 0 | L24: =(K24*0%) -> 0 | M24: =IF((K24-800000)<=0,0,IF((K24-800000)>=2200000,2200000*15%,(K24-800000)*15%)) -> 0 | N24: =IF((K24-(3000000))<=0,0,IF((K24-(3000000))>=9000000,9000000*18%,(K24-(3000000))*18%)) -> 0 | O24: =IF((K24-(12000000))<=0,0,IF((K24-(12000000))>=13000000,13000000*21%,(K24-(12000000))*21%)) -> 0 | P24: =IF((K24-(25000000))<=0,0,IF((K24-(25000000))>=25000000,25000000*23%,(K24-(25000000))*23%)) -> 0 | Q24: =IF((K24-(50000000))<=0,0,(K24-(50000000))*25%) -> 0 | R24: =SUM(L24:Q24) -> 0 | S24: =R24/12 -> 0
A25: 18 | B25: IDRIS IBRAHIM | F25: =MIN(0.2*E25,500000) -> 0 | G25: =D25*2.5% -> 0 | H25: =D25*1.75% -> 0 | I25: =D25*8% -> 0 | J25: =SUM(F25:I25) -> 0 | K25: =(D25-J25) -> 0 | L25: =(K25*0%) -> 0 | M25: =IF((K25-800000)<=0,0,IF((K25-800000)>=2200000,2200000*15%,(K25-800000)*15%)) -> 0 | N25: =IF((K25-(3000000))<=0,0,IF((K25-(3000000))>=9000000,9000000*18%,(K25-(3000000))*18%)) -> 0 | O25: =IF((K25-(12000000))<=0,0,IF((K25-(12000000))>=13000000,13000000*21%,(K25-(12000000))*21%)) -> 0 | P25: =IF((K25-(25000000))<=0,0,IF((K25-(25000000))>=25000000,25000000*23%,(K25-(25000000))*23%)) -> 0 | Q25: =IF((K25-(50000000))<=0,0,(K25-(50000000))*25%) -> 0 | R25: =SUM(L25:Q25) -> 0 | S25: =R25/12 -> 0
A26: 19 | B26: FARUQ ATOFARATI | F26: =MIN(0.2*E26,500000) -> 0 | G26: =D26*2.5% -> 0 | H26: =D26*1.75% -> 0 | I26: =D26*8% -> 0 | J26: =SUM(F26:I26) -> 0 | K26: =(D26-J26) -> 0 | L26: =(K26*0%) -> 0 | M26: =IF((K26-800000)<=0,0,IF((K26-800000)>=2200000,2200000*15%,(K26-800000)*15%)) -> 0 | N26: =IF((K26-(3000000))<=0,0,IF((K26-(3000000))>=9000000,9000000*18%,(K26-(3000000))*18%)) -> 0 | O26: =IF((K26-(12000000))<=0,0,IF((K26-(12000000))>=13000000,13000000*21%,(K26-(12000000))*21%)) -> 0 | P26: =IF((K26-(25000000))<=0,0,IF((K26-(25000000))>=25000000,25000000*23%,(K26-(25000000))*23%)) -> 0 | Q26: =IF((K26-(50000000))<=0,0,(K26-(50000000))*25%) -> 0 | R26: =SUM(L26:Q26) -> 0 | S26: =R26/12 -> 0
A27: 20 | B27: RASHEEDAT DAIBU | F27: =MIN(0.2*E27,500000) -> 0 | G27: =D27*2.5% -> 0 | H27: =D27*1.75% -> 0 | I27: =D27*8% -> 0 | J27: =SUM(F27:I27) -> 0 | K27: =(D27-J27) -> 0 | L27: =(K27*0%) -> 0 | M27: =IF((K27-800000)<=0,0,IF((K27-800000)>=2200000,2200000*15%,(K27-800000)*15%)) -> 0 | N27: =IF((K27-(3000000))<=0,0,IF((K27-(3000000))>=9000000,9000000*18%,(K27-(3000000))*18%)) -> 0 | O27: =IF((K27-(12000000))<=0,0,IF((K27-(12000000))>=13000000,13000000*21%,(K27-(12000000))*21%)) -> 0 | P27: =IF((K27-(25000000))<=0,0,IF((K27-(25000000))>=25000000,25000000*23%,(K27-(25000000))*23%)) -> 0 | Q27: =IF((K27-(50000000))<=0,0,(K27-(50000000))*25%) -> 0 | R27: =SUM(L27:Q27) -> 0 | S27: =R27/12 -> 0
... A48: 41 | B48: ALIYU GARBA LERE | F48: =MIN(0.2*E48,500000) -> 0 | G48: =D48*2.5% -> 0 | H48: =D48*1.75% -> 0 | I48: =D48*8% -> 0 | J48: =SUM(F48:I48) -> 0 | K48: =(D48-J48) -> 0 | L48: =(K48*0%) -> 0 | M48: =IF((K48-800000)<=0,0,IF((K48-800000)>=2200000,2200000*15%,(K48-800000)*15%)) -> 0 | N48: =IF((K48-(3000000))<=0,0,IF((K48-(3000000))>=9000000,9000000*18%,(K48-(3000000))*18%)) -> 0 | O48: =IF((K48-(12000000))<=0,0,IF((K48-(12000000))>=13000000,13000000*21%,(K48-(12000000))*21%)) -> 0 | P48: =IF((K48-(25000000))<=0,0,IF((K48-(25000000))>=25000000,25000000*23%,(K48-(25000000))*23%)) -> 0 | Q48: =IF((K48-(50000000))<=0,0,(K48-(50000000))*25%) -> 0 | R48: =SUM(L48:Q48) -> 0 | S48: =R48/12 -> 0
B50: INTERNAL AUDIT
A51: 1 | B51: OSANAIYE DAVID AKINYEMI
A52: 2 | B52: EVELYN ETONKE AGAN
A53: 3 | B53: JAMILA ABDUL
A54: 4 | B54: IJEOMA EWELUKWA
A55: 5 | B55: HASSAN ABDULHADI
A56: 6 | B56: YUSUF YUSUF DAYYABU
A57: 7 | B57: UDONSI QUEENETH CHIWENDU
B59: LEG. SUPPORT SEVICES
A60: 1 | B60: BETHEL UZOMA IHUGBA
A61: 2 | B61: OGUCHE SAMUEL
A62: 3 | B62: IBRAHIM USMAN
A63: 4 | B63: DR MOHAMMED O. AMALI
A64: 5 | B64: YAHAYA SHAMSU
A65: 6 | B65: CHIDEBE MATHEW NWANKWO
A66: 7 | B66: UMAR MUSA PADAH
A67: 8 | B67: BILKIS S. LAWAL-GAMBARI
A68: 9 | B68: UMOH USENOBONG EMMANUEL
A69: 10 | B69: ZAINAB AKINDE
A70: 11 | B70: GUNAT NANSAK MARK
A71: 12 | B71: MANDU ESSIEN NDEM
B73: LEGAL SERVICES
A74: 1 | B74: DR SHUAIBU DANWANKA
A75: 2 | B75: ABDULSALAM BAKO
B77: DEMOCRACY & GOVERNANCE
A78: 1 | B78: NGARA CHRISTOPHER OCHANJA
A79: 2 | B79: EJALONIBU GANIYU LAYI
A80: 3 | B80: MARTINS SOLOMON UDOM
A81: 4 | B81: ISHAKA DELE
A82: 5 | B82: UDEFUNA NNADOZIE PATRICK
A83: 6 | B83: SHAFIU YAHYA MIKAIL
A84: 7 | B84: HASSAN YERIMA
A85: 8 | B85: HAUWA PATE SADIQ
A86: 9 | B86: OBOT ETIMBUK EMMANUEL
A87: 10 | B87: KOLAPO Q. ABAYOMI
A88: 11 | B88: SALIHU SHAMSUDEEN OPEYEMI
B90: DEPARTMENT OF STUDIES
A91: 1 | B91: DR ASIMIYU G. ABIOLA
A92: 2 | B92: AYOBOLU OLAJIDE OLUFUNSHO
A93: 3 | B93: DR. HADIZA SAIDU
A94: 4 | B94: ANTHONY EDET
A95: 5 | B95: CHRISTIAN MADUABUCHI ODO
A96: 6 | B96: DR. IBANGA ISSAC JONAH
A97: 7 | B97: IGWE STACY
A98: 8 | B98: MUNIRU JIBRIN
A99: 9 | B99: OLANIYAN TAIWO ABINBOLA
A100: 10 | B100: MUSA ALKASIM ADAMU
A101: 11 | B101: AMINAT JUMOKE SULAIMON

Sheet Rent Relief
A1: NATIONAL INSTITUTE FOR LEGISLATIVE AND DEMOCRATIC STUDIES
A2: STAFF ANNUAL RENT RELIEF
A4: S/N | B4: NAME | C4: GL | D4: ANNUAL RENT | E4: 20% OF ANNUAL RENT
B5: DG'S OFFICE | D5: N | E5: N
A6: 1 | B6: PROF. ABUBAKAR O. SULAIMAN | C6: CONSOL | E6: =D6*0.2 -> 0
A7: 2 | B7: RAHEEM USMAN AYIGORO | C7: 16 (9) | E7: =D7*0.2 -> 0
A8: 3 | B8: MARIAM MOHAMMED BELLO | C8: 16 (9) | E8: =D8*0.2 -> 0
A9: 4 | B9: DR IKEME ARTHUR J.O | C9: 16 (9) | E9: =D9*0.2 -> 0
A10: 5 | B10: ANDRAWUS MUSA | C10: 16(9) | E10: =D10*0.2 -> 0
A11: 6 | B11: DR FRANCIS NDUM OJIE | C11: 15(9) | E11: =D11*0.2 -> 0
A12: 7 | B12: ALI ABDULLAHI | C12: 15(7) | E12: =D12*0.2 -> 0
A13: 8 | B13: EMILY EKHIDE | C13: 15(9) | E13: =D13*0.2 -> 0
A14: 9 | B14: DORIS DAKDA AARON | C14: 14(10) | E14: =D14*0.2 -> 0
A15: 10 | B15: ABDULSALAM S. MUSTAPHA | C15: 15(8) | E15: =D15*0.2 -> 0
A16: 11 | B16: PERCY TERFA GBAHABO | C16: 14(8) | E16: =D16*0.2 -> 0
A17: 12 | B17: HASSANA AHMED IBRAHIM | C17: 13(11) | E17: =D17*0.2 -> 0
... A22: 17 | B22: LUCKY AGWOM | C22: 12(9) | E22: =D22*0.2 -> 0
A23: 18 | B23: IDRIS IBRAHIM | C23: 12(9) | D23: 1000000 | E23: =D23*0.2 -> 200000
A24: 19 | B24: FARUQ ATOFARATI | C24: 10(8) | E24: =D24*0.2 -> 0
A25: 20 | B25: RASHEEDAT DAIBU | C25: 10(9) | E25: =D25*0.2 -> 0
A26: 21 | B26: VICTOR ASUKWO | C26: 10(7) | E26: =D26*0.2 -> 0
A27: 22 | B27: NNANDI LIVINUS ATURE | C27: 10(8) | D27: 1500000 | E27: =D27*0.2 -> 300000
A28: 23 | B28: ABDULRAHMAN A SULAIMAN | C28: 9(10) | E28: =D28*0.2 -> 0
A29: 24 | B29: DARE SHEU MAGBON | C29: 9(9) | E29: =D29*0.2 -> 0
A30: 25 | B30: ABUBAKAR SULAIMAN SODEEQ | C30: 10(7) | E30: =D30*0.2 -> 0
A31: 26 | B31: JIMOH ADEBAYO ZAKA | C31: 10(7) | E31: =D31*0.2 -> 0
A32: 27 | B32: ABDULMUSHIN TAWFIQ LADAN | C32: 9(9) | E32: =D32*0.2 -> 0
A33: 28 | B33: MOHAMMED BELLO | C33: 10(7) | E33: =D33*0.2 -> 0
A34: 29 | B34: HOLINESS PAUL UDO | C34: 9(8) | D34: 1000000 | E34: =D34*0.2 -> 200000
A35: 30 | B35: CHARITY UDO AKAN | C35: 9(8) | E35: =D35*0.2 -> 0
A36: 31 | B36: SANI UMAR IBRAHIM | C36: 9(8) | E36: =D36*0.2 -> 0
A37: 32 | B37: FAHAD ABUBUKAR LONGMAN | C37: 9(8) | E37: =D37*0.2 -> 0
A38: 33 | B38: HARUNA JIBRIL AMEH | C38: 8(10) | E38: =D38*0.2 -> 0
A39: 34 | B39: RAMATU IBRAHIM ABDULRAHEEM | C39: 8(9) | E39: =D39*0.2 -> 0
A40: 35 | B40: EDIDIONG EZEKIEL ATAT | C40: 8(8) | E40: =D40*0.2 -> 0
A41: 36 | B41: MAHMUD ADEWOLE HASSAN | C41: 8(8) | E41: =D41*0.2 -> 0
A42: 37 | B42: YUSUF KABIRU TURAKI | C42: 8(8) | E42: =D42*0.2 -> 0
A43: 38 | B43: FATIMA OMAR IBRAHIM | C43: 8(8) | E43: =D43*0.2 -> 0
A44: 39 | B44: EBERE ANASTHESIA IGWE | C44: 8(8) | E44: =D44*0.2 -> 0
A45: 40 | B45: ALIYU GARBA LERE | C45: 8(8) | E45: =D45*0.2 -> 0
B46: TOTAL | D46: =SUM(D6:D45) -> 3500000 | E46: =SUM(E6:E45) -> 700000
B48: INTERNAL AUDIT
A49: 1 | B49: OSANAIYE DAVID AKINYEMI | C49: 17(9) | E49: =D49*0.2 -> 0
A50: 2 | B50: EVELYN ETONKE AGAN | C50: 15(8) | E50: =D50*0.2 -> 0
A51: 3 | B51: JAMILA ABDUL | C51: 10(9) | E51: =D51*0.2 -> 0
A52: 4 | B52: IJEOMA EWELUKWA | C52: 12(8) | E52: =D52*0.2 -> 0
A53: 5 | B53: HASSAN ABDULHADI | C53: 9(8) | E53: =D53*0.2 -> 0
A54: 6 | B54: YUSUF YUSUF DAYYABU | C54: 9(9) | E54: =D54*0.2 -> 0
A55: 7 | B55: UDONSI QUEENETH CHIWENDU | C55: 8(8) | D55: 550000 | E55: =D55*0.2 -> 110000
D56: =SUM(D49:D55) -> 550000 | E56: =SUM(E49:E55) -> 110000
B58: LEG. SUPPORT SEVICES
A59: 1 | B59: BETHEL UZOMA IHUGBA | C59: 17(8) | E59: =D59*0.2 -> 0
A60: 2 | B60: OGUCHE SAMUEL | C60: 15(9) | E60: =D60*0.2 -> 0
A61: 3 | B61: IBRAHIM USMAN | C61: 15(9) | E61: =D61*0.2 -> 0
A62: 4 | B62: DR MOHAMMED O. AMALI | C62: 15(9) | E62: =D62*0.2 -> 0
A63: 5 | B63: YAHAYA SHAMSU | C63: 15(8) | E63: =D63*0.2 -> 0
A64: 6 | B64: CHIDEBE MATHEW NWANKWO | C64: 15(8) | E64: =D64*0.2 -> 0
A65: 7 | B65: UMAR MUSA PADAH | C65: 12(8) | E65: =D65*0.2 -> 0
A66: 8 | B66: BILKIS S. LAWAL-GAMBARI | C66: 10(10) | E66: =D66*0.2 -> 0
A67: 9 | B67: UMOH USENOBONG EMMANUEL | C67: 10(8) | E67: =D67*0.2 -> 0
A68: 10 | B68: ZAINAB AKINDE | C68: 9(10) | E68: =D68*0.2 -> 0
A69: 11 | B69: GUNAT NANSAK MARK | C69: 9(10) | E69: =D69*0.2 -> 0
A70: 12 | B70: MANDU ESSIEN NDEM | C70: 9(8) | E70: =D70*0.2 -> 0
B71: TOTAL | D71: =SUM(D59:D70) -> 0 | E71: =SUM(E59:E70) -> 0
B73: LEGAL SERVICES
A74: 1 | B74: DR SHUAIBU DANWANKA | C74: 17(9) | E74: =D74*0.2 -> 0
A75: 2 | B75: ABDULSALAM BAKO | C75: 15 (9) | E75: =D75*0.2 -> 0
B76: TOTAL | D76: =SUM(D74:D75) -> 0 | E76: =SUM(E74:E75) -> 0
B78: DEMOCRACY & GOVERNANCE
A79: 1 | B79: NGARA CHRISTOPHER OCHANJA | C79: 16(9) | E79: =D79*0.2 -> 0
A80: 2 | B80: EJALONIBU GANIYU LAYI | C80: 14(10) | E80: =D80*0.2 -> 0
A81: 3 | B81: MARTINS SOLOMON UDOM | C81: 13(8) | E81: =D81*0.2 -> 0
A82: 4 | B82: ISHAKA DELE | C82: 13(8) | E82: =D82*0.2 -> 0
A83: 5 | B83: UDEFUNA NNADOZIE PATRICK | C83: 12(10) | E83: =D83*0.2 -> 0
A84: 6 | B84: SHAFIU YAHYA MIKAIL | C84: 12(10) | E84: =D84*0.2 -> 0
A85: 7 | B85: HASSAN YERIMA | C85: 12(10) | E85: =D85*0.2 -> 0
A86: 8 | B86: HAUWA PATE SADIQ | C86: 13(7) | E86: =D86*0.2 -> 0
A87: 9 | B87: OBOT ETIMBUK EMMANUEL | C87: 12(8) | E87: =D87*0.2 -> 0
A88: 10 | B88: KOLAPO Q. ABAYOMI | C88: 10(10) | D88: 2500000 | E88: =D88*0.2 -> 500000
A89: 11 | B89: SALIHU SHAMSUDEEN OPEYEMI | C89: 9(8) | E89: =D89*0.2 -> 0
B90: TOTAL | D90: =SUM(D79:D89) -> 2500000 | E90: =SUM(E79:E89) -> 500000
B92: DEPARTMENT OF STUDIES
A93: 1 | B93: DR ASIMIYU G. ABIOLA | C93: 17(9) | E93: =D93*0.2 -> 0
A94: 2 | B94: AYOBOLU OLAJIDE OLUFUNSHO | C94: 15(8) | E94: =D94*0.2 -> 0
A95: 3 | B95: DR. HADIZA SAIDU | C95: 15(8) | E95: =D95*0.2 -> 0
A96: 4 | B96: ANTHONY EDET | C96: 14(11) | E96: =D96*0.2 -> 0
A97: 5 | B97: CHRISTIAN MADUABUCHI ODO | C97: 13(8) | E97: =D97*0.2 -> 0
A98: 6 | B98: DR. IBANGA ISSAC JONAH | C98: 13(8) | E98: =D98*0.2 -> 0
A99: 7 | B99: IGWE STACY | C99: 12(9) | E99: =D99*0.2 -> 0
A100: 8 | B100: MUNIRU JIBRIN | C100: 10(8) | E100: =D100*0.2 -> 0
A101: 9 | B101: OLANIYAN TAIWO ABINBOLA | C101: 9(9) | E101: =D101*0.2 -> 0
A102: 10 | B102: MUSA ALKASIM ADAMU | C102: 9(8) | E102: =D102*0.2 -> 0
A103: 11 | B103: AMINAT JUMOKE SULAIMON | C103: 8(10) | E103: =D103*0.2 -> 0
B104: TOTAL | D104: =SUM(D93:D103) -> 0 | E104: =SUM(E93:E103) -> 0
B106: ECON. DEV. & SOC. RESEARCH
A107: 1 | B107: DR AUGUSTINE C. OSIGWE | C107: 17(8) | E107: =D107*0.2 -> 0
A108: 2 | B108: TERFA WILLIAMS ABRAHAM | C108: 16(8) | E108: =D108*0.2 -> 0
A109: 3 | B109: OMOJU OLUWASOLA EMMANUEL | C109: 15(9) | E109: =D109*0.2 -> 0
A110: 4 | B110: IBE EZECHI CYRIACUS | C110: 14(10) | E110: =D110*0.2 -> 0
A111: 5 | B111: OSIKHEN LEO IGBANOI | C111: 14(10) | E111: =D111*0.2 -> 0
...

Sheet  Promotions
A1: NATIONAL INSTITUTE FOR LEGISLATIVE & DEMOCRATIC STUDIES
A2: ANALYSIS OF STAFF PROMOTION ARREARS
A4: SN | B4: Name of Employee | C4: Department | D4: Present Grade Level | E4: New Grade Level | F4: Gross Salary of Present Position | G4: Gross Salary of New Position | H4: Diference/Arrears | I4: Effective Date | J4: No of Months | K4: Total Amount of Arrears (Gross)
F5: N | G5: N | H5: N | K5: N
A6: 1 | B6: Patrick Adefuna | C6: DD&G | D6: '12/10 | E6: 13/7 | F6: 592662.67 | G6: ='[21]Peculiar Allowance'!$H$41+'[21] FGN 2024 MGT Monthly'!$H$41+120000 -> 602846.58 | H6: =G6-F6 -> 10183.917 | I6: 20th Dec 2025 | J6: =1+(12/31) -> 1.3870968 | K6: =H6*J6 -> 14126.078
A7: 2 | B7: Kolapo Quadri Abayomi | C7: CAEEP | D7: '10/10 | E7: 12/7 | F7: 499131.17 | G7: ='[21] FGN 2024 MGT Monthly'!$H$40+'[21]Peculiar Allowance'!$H$40+110000 -> 551159 | H7: =G7-F7 -> 52027.833 | I7: 24th June 2024 | J7: =19+(7/30) -> 19.233333 | K7: =H7*J7 -> 1000668.7
A8: 3 | B8: Charity Ezenwajiobi | C8: DD&G | D8: '8/12 | E8: 9/7 | F8: 415930.58 | G8: =330408.083333333+100000 -> 430408.08 | H8: =G8-F8 -> 14477.5 | I8: 1st June 2025 | J8: 8 | K8: =H8*J8 -> 115820
A9: 4 | B9: Sunday Adeyi | C9: Admin & HR | D9: '5/12 | E9: 7/5 | F9: 176217.75 | G9: 252750.58 | H9: =G9-F9 -> 76532.833 | I9: 28th Oct 2025 | J9: =3+(4/31) -> 3.1290323 | K9: =H9*J9 -> 239473.7
B10: TOTAL | H10: =SUM(H6:H6) -> 10183.917 | K10: =SUM(K6:K9) -> 1370088.4

Sheet Sheet20

Sheet 2026 ENHANCED WELFARE
A1: NATIONAL INSTITUTE FOR LEGISLATIVE AND DEMOCRATIC STUDIES
A2: STAFF ENHANCED WELFARE SCHEDULE 2026
B4: STAFF NAME | C4: DESIGNATION | D4: GRADE LEVEL | E4: AMOUNT | F4: Grade Level 01 - 10 | G4: Grade Level 12 - 14 | H4: Grade Level 15 - 17
E5: N | F5: N | G5: N | H5: N
A6: S/N | B6: DG'S OFFICE
A7: 1 | B7: PROF. ABUBAKAR O. SULAIMAN | C7: DIRECTOR GENERAL | D7: CONSOL | E7: 2000000 | H7: =E7 -> 2000000
A8: 2 | B8: RAHEEM USMAN AYIGORO | C8: SA-INFRASTRUCTURE | D8: 16 (9) | E8: 350000 | H8: =E8 -> 350000
A9: 3 | B9: MARIAM MOHAMMED BELLO | C9: SA- SPECIAL DUTIES | D9: 16 (9) | E9: 700000 | H9: =E9 -> 700000
A10: 4 | B10: DR IKEME ARTHUR J.O | C10: DEPUTY DIRECTOR, M&E | D10: 16 (9) | E10: 700000 | H10: =E10 -> 700000
A11: 5 | B11: ANDRAWUS MUSA | C11: DEP. DIRECTOR, STORES & PROCUREMENT | D11: 16(9) | E11: 700000 | H11: =E11 -> 700000
A12: 6 | B12: DR FRANCIS NDUM OJIE | C12: AD, TRAINING & IC./SA TO DG | D12: 15(9) | E12: 700000 | H12: =E12 -> 700000
A13: 7 | B13: ALI ABDULLAHI | C13: ASST DIRECTOR ICT | D13: 15(7) | E13: 700000 | H13: =E13 -> 700000
A14: 8 | B14: EMILY EKHIDE | C14: SENIOR RESEARCH FELLOW | D14: 15(9) | E14: 700000 | H14: =E14 -> 700000
A15: 9 | B15: DORIS DAKDA AARON | C15: RESEARCH FELLOW I | D15: 14(10) | E15: 500000 | G15: =E15 -> 500000
A16: 10 | B16: ABDULSALAM S. MUSTAPHA | C16: ASST. DIRECTOR ICT | D16: 15(8) | E16: 700000 | H16: =E16 -> 700000
A17: 11 | B17: PERCY TERFA GBAHABO | C17: RESEARCH FELLOW 1 | D17: 14(8) | E17: 500000 | G17: =E17 -> 500000
A18: 12 | B18: HASSANA AHMED IBRAHIM | C18: PA- TO DG | D18: 13(11) | E18: 500000 | G18: =E18 -> 500000
A19: 13 | B19: IKIP LEBO | C19: ASST CHIEF PROC. OFFICER | D19: 13 (9) | E19: 250000 | G19: =E19 -> 250000
A20: 14 | B20: ALABI ADESINA MUHYDEEN | C20: HEAD, NILDS LIAISON OFFICE | D20: 13 (9) | E20: 500000 | G20: =E20 -> 500000
A21: 15 | B21: BASSEY NSONGURUA UDOFIA | C21: PRINC.CONF SEC 1/PPS | D21: 13(8) | E21: 500000 | G21: =E21 -> 500000
A22: 16 | B22: ADUGBA RICHARD TERSEER | C22: ASSIST. CHIEF INFO OFFICER | D22: 13(7) | E22: 500000 | G22: =E22 -> 500000
A23: 17 | B23: LUCKY AGWOM | C23: RESEARCH ASSISTANT | D23: 12(9) | E23: 400000 | G23: =E23 -> 400000
A24: 18 | B24: IDRIS IBRAHIM | C24: PRINCIPAL RESEARCH OFFICER | D24: 12(9) | E24: 400000 | G24: =E24 -> 400000
A25: 19 | B25: FARUQ ATOFARATI | C25: PA (SPECIAL DUTIES) TO DG | D25: 10(8) | E25: 300000 | F25: =E25 -> 300000
A26: 20 | B26: RASHEEDAT DAIBU | C26: SENIOR INFO. OFFICER | D26: 10(9) | E26: 300000 | F26: =E26 -> 300000
A27: 21 | B27: VICTOR ASUKWO | C27: SENIOR ICT OFFICER | D27: 10(7) | E27: 300000 | F27: =E27 -> 300000
A28: 22 | B28: NNANDI LIVINUS ATURE | C28: SENIOR RESEARCH OFFICER | D28: 10(8) | E28: 300000 | F28: =E28 -> 300000
A29: 23 | B29: ABDULRAHMAN A SULAIMAN | C29: STORE OFFICER | D29: 9(10) | E29: 300000 | F29: =E29 -> 300000
A30: 24 | B30: DARE SHEU MAGBON | C30: ADMINISTRATION OFFICER | D30: 9(9) | E30: 300000 | F30: =E30 -> 300000
A31: 25 | B31: ABUBAKAR SULAIMAN SODEEQ | C31: SENIOR M&E OFFICER | D31: 10(7) | E31: 300000 | F31: =E31 -> 300000
A32: 26 | B32: JIMOH ADEBAYO ZAKA | C32: SENIOR INFO OFFICER | D32: 10(7) | E32: 300000 | F32: =E32 -> 300000
A33: 27 | B33: ABDULMUSHIN TAWFIQ LADAN | C33: ICT OFFICER | D33: 9(9) | E33: 300000 | F33: =E33 -> 300000
A34: 28 | B34: MOHAMMED BELLO | C34: SENIOR PROTOCOL OFFICER | D34: 10(7) | E34: 300000 | F34: =E34 -> 300000
A35: 29 | B35: HOLINESS PAUL UDO | C35: ADMINISTRATION OFFICER, M&E | D35: 9(8) | E35: 300000 | F35: =E35 -> 300000
A36: 30 | B36: CHARITY UDO AKAN | C36: ADMINISTRATION OFFICER, M&E | D36: 9(8) | E36: 300000 | F36: =E36 -> 300000
... A46: 40 | B46: ALIYU GARBA LERE | C46: ASSIST INFORMATION OFFICER | D46: 8(8) | E46: 300000 | F46: =E46 -> 300000
B47: TOTAL | C47: 40 | E47: =SUM(E7:E46) -> 17900000 | F47: =SUM(F7:F46) -> 6600000 | G47: =SUM(G7:G46) -> 4050000 | H47: =SUM(H7:H46) -> 7250000
B49: INTERNAL AUDIT
A50: 1 | B50: OSANAIYE DAVID AKINYEMI | C50: DIRECTOR INTERNAL AUDIT | D50: 17(9) | E50: 1000000 | H50: =E50 -> 1000000
A51: 2 | B51: EVELYN ETONKE AGAN | C51: ASST DIR AUDIT | D51: 15(8) | E51: 700000 | H51: =E51 -> 700000
A52: 3 | B52: JAMILA ABDUL | C52: SENIOR INTERNAL AUDITOR | D52: 10(9) | E52: 300000 | F52: =E52 -> 300000
A53: 4 | B53: IJEOMA EWELUKWA | C53: PRINCIPAL AUDIT OFFICER | D53: 12(8) | E53: 400000 | G53: =E53 -> 400000
A54: 5 | B54: HASSAN ABDULHADI | C54: SENIOR INTERNAL AUDITOR | D54: 9(8) | E54: 300000 | F54: =E54 -> 300000
A55: 6 | B55: YUSUF YUSUF DAYYABU | C55: INERNAL AUDIT OFFICER | D55: 9(9) | E55: 300000 | F55: =E55 -> 300000
A56: 7 | B56: UDONSI QUEENETH CHIWENDU | C56: ASSIST PROGRAMME OFFICER | D56: 8(8) | E56: 300000 | F56: =E56 -> 300000
C57: 7 | E57: =SUM(E50:E56) -> 3300000 | F57: =SUM(F50:F56) -> 1200000 | G57: =SUM(G50:G56) -> 400000 | H57: =SUM(H50:H56) -> 1700000
B59: LEG. SUPPORT SEVICES
A60: 1 | B60: BETHEL UZOMA IHUGBA | C60: AG. DIRECTOR, AEEP | D60: 17(8) | E60: 1000000 | H60: =E60 -> 1000000
A61: 2 | B61: OGUCHE SAMUEL | C61: DEPUTY DIRECTOR | D61: 16(7) | E61: 700000 | H61: =E61 -> 700000
A62: 3 | B62: IBRAHIM USMAN | C62: SNR RESEARCH FELLOW | D62: 15(9) | E62: 700000 | H62: =E62 -> 700000
A63: 4 | B63: DR MOHAMMED O. AMALI | C63: SNR RESEARCH FELLOW | D63: 15(9) | E63: 700000 | H63: =E63 -> 700000
A64: 5 | B64: YAHAYA SHAMSU | C64: SNR RESEARCH FELLOW | D64: 15(8) | E64: 700000 | H64: =E64 -> 700000
A65: 6 | B65: CHIDEBE MATHEW NWANKWO | C65: SNR RESEARCH FELLOW | D65: 15(8) | E65: 700000 | H65: =E65 -> 700000
A66: 7 | B66: UMAR MUSA PADAH | C66: PRINC. RESEARCH OFFICER | D66: 12(8) | E66: 400000 | G66: =E66 -> 400000
A67: 8 | B67: BILKIS S. LAWAL-GAMBARI | C67: RESEARCH OFFICER | D67: 10(10) | E67: 300000 | F67: =E67 -> 300000
A68: 9 | B68: UMOH USENOBONG EMMANUEL | C68: SENIOR RESEARCH OFFICER | D68: 10(8) | E68: 300000 | F68: =E68 -> 300000
A69: 10 | B69: ZAINAB AKINDE | C69: RESEARCH OFFICER | D69: 9(10) | E69: 300000 | F69: =E69 -> 300000
A70: 11 | B70: GUNAT NANSAK MARK | C70: RESEARCH OFFICER | D70: 9(10) | E70: 300000 | F70: =E70 -> 300000
A71: 12 | B71: MANDU ESSIEN NDEM | C71: RESEARCH OFFICER | D71: 9(8) | E71: 300000 | F71: =E71 -> 300000
B72: TOTAL | C72: 12 | E72: =SUM(E60:E71) -> 6400000 | F72: =SUM(F60:F71) -> 1500000 | G72: =SUM(G60:G71) -> 400000 | H72: =SUM(H60:H71) -> 4500000
B74: LEGAL SERVICES
A75: 1 | B75: DR SHUAIBU DANWANKA | C75: DIRECTOR LEGAL SERVICES | D75: 17(9) | E75: 500000 | H75: =E75 -> 500000
A76: 2 | B76: ABDULSALAM BAKO | C76: DD LEGAL SERVICES | D76: 16 (7) | E76: 700000 | H76: =E76 -> 700000
B77: TOTAL | C77: 2 | E77: =SUM(E75:E76) -> 1200000 | F77: =SUM(F75:F76) -> 0 | H77: =SUM(H75:H76) -> 1200000
B79: DEMOCRACY & GOVERNANCE
A80: 1 | B80: NGARA CHRISTOPHER OCHANJA | C80: DEP DIR DEM & GOVERNANCE | D80: 16(9) | E80: 1000000 | H80: =E80 -> 1000000
A81: 2 | B81: EJALONIBU GANIYU LAYI | C81: RESEARCH FELLOW 1 | D81: 14(10) | E81: 500000 | G81: =E81 -> 500000
A82: 3 | B82: MARTINS SOLOMON UDOM | C82: RESEARCH FELLOW 11 | D82: 13(8) | E82: 500000 | G82: =E82 -> 500000
A83: 4 | B83: ISHAKA DELE | C83: RESEARCH FELLOW 11 | D83: 13(8) | E83: 500000 | G83: =E83 -> 500000
A84: 5 | B84: UDEFUNA NNADOZIE PATRICK | C84: RESEARCH OFFICER | D84: 12(10) | E84: 400000 | G84: =E84 -> 400000
A85: 6 | B85: SHAFIU YAHYA MIKAIL | C85: PRINCIPAL RESEARCH OFFICER | D85: 12(10) | E85: 400000 | G85: =E85 -> 400000
A86: 7 | B86: HASSAN YERIMA | C86: PRINCIPAL RESEARCH OFFICER | D86: 12(10) | E86: 400000 | G86: =E86 -> 400000
A87: 8 | B87: HAUWA PATE SADIQ | C87: ASST CHIEF PROGRAMME OFFICER | D87: 13(7) | E87: 500000 | G87: =E87 -> 500000
A88: 9 | B88: OBOT ETIMBUK EMMANUEL | C88: PRINCIPAL INFO. OFFICER | D88: 12(8) | E88: 400000 | G88: =E88 -> 400000
A89: 10 | B89: KOLAPO Q. ABAYOMI | C89: RESEARCH OFFICER | D89: 12(8) | E89: 400000 | G89: =E89 -> 400000
A90: 11 | B90: SALIHU SHAMSUDEEN OPEYEMI | C90: PROGRAMME OFFICER | D90: 9(8) | E90: 300000 | F90: =E90 -> 300000
B91: TOTAL | C91: 11 | E91: =SUM(E80:E90) -> 5300000 | F91: =SUM(F80:F90) -> 300000 | G91: =SUM(G80:G90) -> 4000000 | H91: =SUM(H80:H90) -> 1000000
B93: DEPARTMENT OF STUDIES
A94: 1 | B94: DR ASIMIYU G. ABIOLA | C94: DIRECTOR POST GRADUATE | D94: 17(9) | E94: 1000000 | H94: =E94 -> 1000000
A95: 2 | B95: AYOBOLU OLAJIDE OLUFUNSHO | C95: ASSISTANT DIR. EXXAMS & RECORD | D95: 15(8) | E95: 700000 | H95: =E95 -> 700000
A96: 3 | B96: DR. HADIZA SAIDU | C96: ASSISTANT DIRECTOR | D96: 15(8) | E96: 700000 | H96: =E96 -> 700000
A97: 4 | B97: ANTHONY EDET | C97: CHIEF PROGRAMMES OFFICER | D97: 14(11) | E97: 500000 | G97: =E97 -> 500000
A98: 5 | B98: CHRISTIAN MADUABUCHI ODO | C98: ASSIST. CHIEF ICT OFFICER | D98: 13(8) | E98: 500000 | G98: =E98 -> 500000
A99: 6 | B99: DR. IBANGA ISSAC JONAH | C99: ASSIST. CHIEF PROGRM OFFICER | D99: 13(8) | E99: 500000 | G99: =E99 -> 500000
A100: 7 | B100: IGWE STACY | C100: PRINC. PROGRAMME OFFICER | D100: 12(9) | E100: 400000 | G100: =E100 -> 400000
A101: 8 | B101: MUNIRU JIBRIN | C101: SENIOR PROGRAMME OFFICER | D101: 10(8) | E101: 300000 | F101: =E101 -> 300000
A102: 9 | B102: OLANIYAN TAIWO ABINBOLA | C102: PROGRAMME OFFICER | D102: 9(9) | E102: 300000 | F102: =E102 -> 300000
A103: 10 | B103: MUSA ALKASIM ADAMU | C103: PROGRAMME OFFICER | D103: 9(8) | E103: 300000 | F103: =E103 -> 300000
A104: 11 | B104: AMINAT JUMOKE SULAIMON | C104: AST. PROGRAMME OFFICER | D104: 8(10) | E104: 300000 | F104: =E104 -> 300000
B105: TOTAL | C105: 11 | E105: =SUM(E94:E104) -> 5500000 | F105: =SUM(F94:F104) -> 1200000 | G105: =SUM(G94:G104) -> 1900000 | H105: =SUM(H94:H104) -> 2400000
B107: ECON. DEV. & SOC. RESEARCH
A108: 1 | B108: DR AUGUSTINE C. OSIGWE | C108: AG. DIRECTOR, ESR | D108: 17(8) | E108: 1000000 | H108: =E108 -> 1000000
A109: 2 | B109: TERFA WILLIAMS ABRAHAM | C109: DEP. DIRECTOR ECON & SOCIAL RES | D109: 16(8) | E109: 700000 | H109: =E109 -> 700000
A110: 3 | B110: IBE EZECHI CYRIACUS | C110: RESEARCH FELLOW 1 | D110: 14(10) | E110: 500000 | G110: =E110 -> 500000
A111: 4 | B111: OSIKHEN LEO IGBANOI | C111: RESEARCH FELLOW 1 | D111: 14(10) | E111: 500000 | G111: =E111 -> 500000
A112: 5 | B112: OKUNGBOWA OSARETIN GODSPOWER | C112: RESEARCH FELLOW 1 | D112: 14(9) | E112: 250000 | G112: =E112 -> 250000
A113: 6 | B113: YUSUF IBRAHIM | C113: PRINCIPAL RESEARCH OFFICER | D113: 12(10) | E113: 400000 | G113: =E113 -> 400000
A114: 7 | B114: MUSTAPHA RAFIU AYOBANJI | C114: RESEARCH FELLOW 11 | D114: 13(9) | E114: 250000 | G114: =E114 -> 250000
A115: 8 | B115: UDOKANG NSISONG BONIFACE | C115: PRINC. RESEARCH OFFICER | D115: 12(8) | E115: 400000 | G115: =E115 -> 400000
A116: 9 | B116: MARYAM MUSA SADA | C116: ASSIT. RESEARCH OFFICER | D116: 10(10) | E116: 300000 | F116: =E116 -> 300000
...

Sheet Summary EW
A3: SUMMARY OF 2026 STAFF ENHANCED WELFARE
B4: Particulars | C4: Grade Level 1-10 | D4: Grade Level 12-14 | E4: Grade Level 15-17 | F4: TOTAL
C5: N | D5: N | E5: N | F5: N
A6: 1 | B6: Permanent Staff | C6: ='2026 ENHANCED WELFARE'!F245 -> 28450000 | D6: ='2026 ENHANCED WELFARE'!G245 -> 23050000 | E6: ='2026 ENHANCED WELFARE'!H245 -> 29550000 | F6: =SUM(C6:E6) -> 81050000
A7: 2 | B7: New Permanent Staff | C7: ='[25]Enh Wlf New Perm Staff'!$F$92 -> 13200000 | D7: ='[25]Enh Wlf New Perm Staff'!$G$92 -> 3900000 | E7: ='[25]Enh Wlf New Perm Staff'!$H$92 -> 3500000 | F7: =SUM(C7:E7) -> 20600000
A8: 3 | B8: Contract Staff | D8: ='[23]ENH WELF Contract'!$F$31 -> 6700000 | E8: ='[23]ENH WELF Contract'!$G$31 -> 2900000 | F8: =SUM(C8:E8) -> 9600000
A9: 4 | B9: New Contract Staff | D9: ='[23]Enh Wlf New Cntr'!$F$27 -> 6100000 | E9: ='[23]Enh Wlf New Cntr'!$G$27 -> 1000000 | F9: =SUM(C9:E9) -> 7100000
A10: 5 | B10: Casual & Others | D10: ='[23]Enh Wlfr Casual'!$E$36 -> 2850000 | E10: ='[23]Enh Wlfr Casual'!$F$36 -> 1000000 | F10: =SUM(C10:E10) -> 3850000
B11: Grand Total | C11: =SUM(C6:C10) -> 41650000 | D11: =SUM(D6:D10) -> 42600000 | E11: =SUM(E6:E10) -> 37950000 | F11: =SUM(F6:F10) -> 122200000
B13: Particulars | C13: Grade Level 1-10 | D13: Grade Level 12-14 | E13: Grade Level 15-17 | F13: TOTAL
C14: N | D14: N | E14: N | F14: N
B15: Permanent Staff | C15: ='2026 ENHANCED WELFARE (2)'!F245 -> 28450000 | D15: ='2026 ENHANCED WELFARE (2)'!G245 -> 23050000 | E15: ='2026 ENHANCED WELFARE (2)'!H245 -> 29550000 | F15: =SUM(C15:E15) -> 81050000

Sheet New Steps, Pensions & NHF
A1: NATIONAL INSTITUTE FOR LEGISLATIVE AND DEMOCRATIC STUDIES
A2: STAFF PAYROLL FOR THE MONTH OF JANUARY 2026
E3: ='[1]FEB 08'!E11/'[1]FEB 08'!M11 -> #REF!
B4: STAFF NAME | C4: DESIGNATION | D4: OLD GRADE LEVEL | E4: OLD BASIC SALARY | F4: NEW GRADE LEVEL | G4: NEW BASIC SALARY | H4: CHANGE IN STEPS (GROSS) | I4: OLD EMPLOYEE PENSIONS | J4: NEW EMPLOYEE PENSIONS | K4: CHANGES IN PENSIONS | L4: NEW ANNUAL PENSIONS | M4: NEW GRADE LEVEL | N4: NEW BASIC | O4: NHF 2.5% | P4: OLD NHF DED. | Q4: INCREASE IN NHF | R4: NHF ANNUAL
E5: N | G5: N | H5: N | I5: N | J5: N | K5: N | L5: N | P5: N
A6: S/N | B6: DG'S OFFICE
A7: 1 | B7: PROF. ABUBAKAR O. SULAIMAN | C7: DIRECTOR GENERAL | D7: CONSOL | E7: 1971137.1 | F7: CONSOL | G7: 1971137.1 | H7: =G7-E7 -> 0 | I7: 0 | K7: =J7-I7 -> 0 | L7: =J7*12 -> 0 | M7: CONSOL | O7: =N7*0.025 -> 0
A8: 2 | B8: RAHEEM USMAN AYIGORO | C8: SA-INFRASTRUCTURE | D8: 16 (9) | E8: 905306.75 | F8: 16 (9) | G8: 905306.75 | H8: =G8-E8 -> 0 | I8: 72424.54 | J8: =G8*0.08 -> 72424.54 | K8: =J8-I8 -> 0 | L8: =J8*12 -> 869094.48 | M8: 16 (9) | N8: 554669.5 | Q8: =O8-P8 -> 0 | R8: =O8*12 -> 0
A9: 3 | B9: MARIAM MOHAMMED BELLO | C9: SA- SPECIAL DUTIES | D9: 16 (9) | E9: 905306.75 | F9: 16 (9) | G9: 905306.75 | H9: =G9-E9 -> 0 | K9: =J9-I9 -> 0 | L9: =J9*12 -> 0 | M9: 16 (9) | O9: =N9*0.025 -> 0 | Q9: =O9-P9 -> 0 | R9: =O9*12 -> 0
A10: 4 | B10: DR IKEME ARTHUR J.O | C10: DEPUTY DIRECTOR, M&E | D10: 16 (9) | E10: 905306.75 | F10: 16 (9) | G10: 905306.75 | H10: =G10-E10 -> 0 | I10: 72424.54 | J10: =G10*0.08 -> 72424.54 | K10: =J10-I10 -> 0 | L10: =J10*12 -> 869094.48 | M10: 16 (9) | N10: 554669.5 | O10: =N10*0.025 -> 13866.737 | P10: 13866.737 | Q10: =O10-P10 -> 0 | R10: =O10*12 -> 166400.85
A11: 5 | B11: ANDRAWUS MUSA | C11: DEP. DIRECTOR, STORES & PROCUREMENT | D11: 16(8) | E11: 879008.92 | F11: 16(9) | G11: 905306.75 | H11: =G11-E11 -> 26297.833 | I11: 68216.887 | J11: =G11*0.08 -> 72424.54 | K11: =J11-I11 -> 4207.6533 | L11: =J11*12 -> 869094.48 | M11: 16(9) | N11: 554669.5 | O11: =N11*0.025 -> 13866.737 | P11: 13084.663 | Q11: =O11-P11 -> 782.075 | R11: =O11*12 -> 166400.85
A12: 6 | B12: DR FRANCIS NDUM OJIE | C12: AD, TRAINING & IC./SA TO DG | D12: 15(8) | E12: 722595.5 | F12: 15(9) | G12: 744477 | H12: =G12-E12 -> 21881.5 | I12: 57807.64 | J12: =G12*0.08 -> 59558.16 | K12: =J12-I12 -> 1750.52 | L12: =J12*12 -> 714697.92 | M12: 15(9) | N12: 459010.5 | O12: =N12*0.025 -> 11475.263 | P12: 11149.896 | Q12: =O12-P12 -> 325.36667 | R12: =O12*12 -> 137703.15
A13: 7 | B13: ALI ABDULLAHI | C13: ASST DIRECTOR ICT | D13: 15(7) | E13: 700713.92 | F13: 15(7) | G13: 700713.92 | H13: =G13-E13 -> 0 | I13: 56057.113 | J13: =G13*0.08 -> 56057.113 | K13: =J13-I13 -> 0 | L13: =J13*12 -> 672685.36 | M13: 15(7) | N13: 432981.08 | Q13: =O13-P13 -> 0 | R13: =O13*12 -> 0
A14: 8 | B14: EMILY EKHIDE | C14: SENIOR RESEARCH FELLOW | D14: 15(8) | E14: 722595.5 | F14: 15(9) | G14: 744477 | H14: =G14-E14 -> 21881.5 | I14: 57807.64 | J14: =G14*0.08 -> 59558.16 | K14: =J14-I14 -> 1750.52 | L14: =J14*12 -> 714697.92 | M14: 15(9) | N14: 459010.5 | Q14: =O14-P14 -> 0 | R14: =O14*12 -> 0
A15: 9 | B15: DORIS DAKDA AARON | C15: RESEARCH FELLOW I | D15: 14(9) | E15: 558165.25 | F15: 14(10) | G15: 573911.08 | H15: =G15-E15 -> 15745.833 | I15: 44653.22 | J15: =G15*0.08 -> 45912.887 | K15: =J15-I15 -> 1259.6667 | L15: =J15*12 -> 550954.64 | M15: 14(10) | N15: 357066.67 | O15: =N15*0.025 -> 8926.6667 | P15: 8692.8979 | Q15: =O15-P15 -> 233.76875 | R15: =O15*12 -> 107120
A16: 10 | B16: ABDULSALAM S. MUSTAPHA | C16: ASST. DIRECTOR ICT | D16: 15(7) | E16: 700713.92 | F16: 15(8) | G16: 722595.5 | H16: =G16-E16 -> 21881.583 | I16: 56057.113 | J16: =G16*0.08 -> 57807.64 | K16: =J16-I16 -> 1750.5267 | L16: =J16*12 -> 693691.68 | M16: 15(8) | N16: 445995.83 | Q16: =O16-P16 -> 0 | R16: =O16*12 -> 0
A17: 11 | B17: PERCY TERFA GBAHABO | C17: RESEARCH FELLOW 1 | D17: 14(7) | E17: 542419.5 | F17: 14(8) | G17: ='[21] FGN 2024 MGT Monthly'!$I$42+'[21]Peculiar Allowance'!$I$42 -> 542419.5 | H17: =G17-E17 -> 0 | I17: 42133.887 | J17: =G17*0.08 -> 43393.56 | K17: =J17-I17 -> 1259.6733 | L17: =J17*12 -> 520722.72 | M17: 14(8) | N17: 338365.25 | Q17: =O17-P17 -> 0 | R17: =O17*12 -> 0
A18: 12 | B18: HASSANA AHMED IBRAHIM | C18: PA- TO DG | D18: 13(10) | E18: 526725.08 | F18: 13(11) | G18: ='[21]Peculiar Allowance'!$L$41+'[21] FGN 2024 MGT Monthly'!$L$41 -> 541351.33 | H18: =G18-E18 -> 14626.25 | I18: 42138.007 | J18: =G18*0.08 -> 43308.107 | K18: =J18-I18 -> 1170.1 | L18: =J18*12 -> 519697.28 | M18: 13(11) | N18: 337730.83 | O18: =N18*0.025 -> 8443.2708 | P18: 8226.1229 | Q18: =O18-P18 -> 217.14792 | R18: =O18*12 -> 101319.25
A19: 13 | B19: IKIP LEBO | C19: ASST CHIEF PROC. OFFICER | D19: 13 (8) | E19: 497472.75 | F19: 13 (9) | G19: ='[21] FGN 2024 MGT Monthly'!$J$41+'[21]Peculiar Allowance'!$J$41 -> 512098.92 | H19: =G19-E19 -> 14626.167 | I19: 39797.82 | J19: =G19*0.08 -> 40967.913 | K19: =J19-I19 -> 1170.0933 | L19: =J19*12 -> 491614.96 | M19: 13 (9) | N19: ='[21] FGN 2024 MGT Monthly'!$J$41 -> 320359.08 | O19: =N19*0.025 -> 8008.9771 | P19: 7791.8313 | Q19: =O19-P19 -> 217.14583 | R19: =O19*12 -> 96107.725
A20: 14 | B20: ALABI ADESINA MUHYDEEN | C20: HEAD, NILDS LIAISON OFFICE | D20: 13 (8) | E20: 497472.75 | F20: 13 (9) | G20: ='[21] FGN 2024 MGT Monthly'!$J$41+'[21]Peculiar Allowance'!$J$41 -> 512098.92 | H20: =G20-E20 -> 14626.167 | I20: 39797.82 | J20: =G20*0.08 -> 40967.913 | K20: =J20-I20 -> 1170.0933 | L20: =J20*12 -> 491614.96 | M20: 13 (9) | N20: ='[21] FGN 2024 MGT Monthly'!$J$41 -> 320359.08 | Q20: =O20-P20 -> 0 | R20: =O20*12 -> 0
A21: 15 | B21: BASSEY NSONGURUA UDOFIA | C21: PRINC.CONF SEC 1/PPS | D21: 13(7) | E21: 482846.58 | F21: 13(8) | G21: 497472.75 | H21: =G21-E21 -> 14626.167 | I21: 42138.007 | J21: =G21*0.08 -> 39797.82 | K21: =J21-I21 -> -2340.1867 | L21: =J21*12 -> 477573.84 | M21: 13(8) | N21: 311673.25 | O21: =N21*0.025 -> 7791.8313 | P21: 7777.3604 | Q21: =O21-P21 -> 14.470833 | R21: =O21*12 -> 93501.975
A22: 16 | B22: ADUGBA RICHARD TERSEER | C22: ASSIST. CHIEF INFO OFFICER | D22: 13(7) | E22: 482846.58 | F22: 13(7) | G22: 482846.58 | H22: =G22-E22 -> 0 | I22: 42138.007 | J22: =G22*0.08 -> 38627.727 | K22: =J22-I22 -> -3510.28 | L22: =J22*12 -> 463532.72 | M22: 13(7) | N22: 302987.42 | O22: =N22*0.025 -> 7574.6854 | P22: 7571.9667 | Q22: =O22-P22 -> 2.71875 | R22: =O22*12 -> 90896.225
A23: 17 | B23: LUCKY AGWOM | C23: RESEARCH ASSISTANT | D23: 12(8) | E23: 454993.58 | F23: 12(9) | G23: 468828.17 | H23: =G23-E23 -> 13834.583 | I23: 36399.487 | J23: =G23*0.08 -> 37506.253 | K23: =J23-I23 -> 1106.7667 | L23: =J23*12 -> 450075.04 | M23: 12(9) | N23: 294662.92 | Q23: =O23-P23 -> 0 | R23: =O23*12 -> 0
A24: 18 | B24: IDRIS IBRAHIM | C24: PRINCIPAL RESEARCH OFFICER | D24: 12(8) | E24: 454993.58 | F24: 12(9) | G24: 468828.17 | H24: =G24-E24 -> 13834.583 | I24: 36399.487 | J24: =G24*0.08 -> 37506.253 | K24: =J24-I24 -> 1106.7667 | L24: =J24*12 -> 450075.04 | M24: 12(9) | N24: 294662.92 | O24: =N24*0.025 -> 7366.5729 | P24: 7161.1771 | Q24: =O24-P24 -> 205.39583 | R24: =O24*12 -> 88398.875
A25: 19 | B25: FARUQ ATOFARATI | C25: PA (SPECIAL DUTIES) TO DG | D25: 10(7) | E25: 381140.67 | F25: 10(8) | G25: 381140.67 | H25: =G25-E25 -> 0 | I25: 30491.253 | J25: =G25*0.08 -> 30491.253 | K25: =J25-I25 -> 0 | L25: =J25*12 -> 365895.04 | M25: 10(8) | N25: 240874.58 | Q25: =O25-P25 -> 0 | R25: =O25*12 -> 0
A26: 20 | B26: RASHEEDAT DAIBU | C26: SENIOR INFO. OFFICER | D26: 10(8) | E26: 381140.67 | F26: 10(9) | G26: 390135.83 | H26: =G26-E26 -> 8995.1667 | I26: 30491.253 | J26: =G26*0.08 -> 31210.867 | K26: =J26-I26 -> 719.61333 | L26: =J26*12 -> 374530.4 | M26: 10(9) | N26: 246171.17 | O26: =N26*0.025 -> 6154.2792 | P26: 6021.8646 | Q26: =O26-P26 -> 132.41458 | R26: =O26*12 -> 73851.35
A27: 21 | B27: ELIZABETH OGECHUKWU ONYEAKU | C27: ICT OFFICER | D27: 9(10) | H27: =G27-E27 -> 0 | J27: =G27*0.08 -> 0 | K27: =J27-I27 -> 0 | L27: =J27*12 -> 0 | Q27: =O27-P27 -> 0 | R27: =O27*12 -> 0
A28: 22 | B28: VICTOR ASUKWO | C28: SENIOR ICT OFFICER | D28: 10(7) | E28: 372145.33 | F28: 10(7) | G28: 372145.33 | H28: =G28-E28 -> 0 | I28: 30491.253 | J28: =G28*0.08 -> 29771.627 | K28: =J28-I28 -> -719.62667 | L28: =J28*12 -> 357259.52 | M28: 10(7) | N28: ='[21] FGN 2024 MGT Monthly'!$H$39 -> 235577.83 | O28: =N28*0.025 -> 5889.4458 | P28: 5690.3938 | Q28: =O28-P28 -> 199.05208 | R28: =O28*12 -> 70673.35
A29: 23 | B29: NNANDI LIVINUS ATURE | C29: SENIOR RESEARCH OFFICER | D29: 10(7) | E29: 372145.33 | F29: 10(8) | G29: 381140.67 | H29: =G29-E29 -> 8995.3333 | I29: 30491.253 | J29: =G29*0.08 -> 30491.253 | K29: =J29-I29 -> 0 | L29: =J29*12 -> 365895.04 | M29: 10(8) | N29: 240874.58 | O29: =N29*0.025 -> 6021.8646 | P29: 6260.74 | Q29: =O29-P29 -> -238.87542 | R29: =O29*12 -> 72262.375
A30: 24 | B30: ABDULRAHMAN A SULAIMAN | C30: STORE OFFICER | D30: 9(9) | E30: 347016.17 | F30: 9(10) | G30: ='[21]Peculiar Allowance'!$K$38+'[21] FGN 2024 MGT Monthly'!$K$38 -> 355320.67 | H30: =G30-E30 -> 8304.5 | I30: 27761.293 | J30: =G30*0.08 -> 28425.653 | K30: =J30-I30 -> 664.36 | L30: =J30*12 -> 341107.84 | M30: 9(10) | N30: 227615.75 | Q30: =O30-P30 -> 0 | R30: =O30*12 -> 0
A31: 25 | B31: DARE SHEU MAGBON | C31: ADMINISTRATION OFFICER | D31: 9(8) | E31: 338711.67 | F31: 9(9) | G31: 347016.17 | H31: =G31-E31 -> 8304.5 | I31: 27096.933 | J31: =G31*0.08 -> 27761.293 | K31: =J31-I31 -> 664.36 | L31: =J31*12 -> 333135.52 | M31: 9(9) | N31: 222674.58 | Q31: =O31-P31 -> 0 | R31: =O31*12 -> 0
A32: 26 | B32: ABUBAKAR SULAIMAN SODEEQ | C32: SENIOR M&E OFFICER | D32: 10(7) | E32: 372145.33 | F32: 10(7) | G32: 372145.33 | H32: =G32-E32 -> 0 | I32: 29771.627 | J32: =G32*0.08 -> 29771.627 | K32: =J32-I32 -> -5.8207661e-11 | L32: =J32*12 -> 357259.52 | M32: 10(7) | N32: ='[21] FGN 2024 MGT Monthly'!$H$39 -> 235577.83 | O32: =N32*0.025 -> 5889.4458 | P32: 6260.744 | Q32: =O32-P32 -> -371.29817 | R32: =O32*12 -> 70673.35
A33: 27 | B33: JIMOH ADEBAYO ZAKA | C33: SENIOR INFO OFFICER | D33: 10(7) | E33: 372145.33 | F33: 10(7) | G33: 372145.33 | H33: =G33-E33 -> 0 | I33: 29771.627 | J33: =G33*0.08 -> 29771.627 | K33: =J33-I33 -> -5.8207661e-11 | L33: =J33*12 -> 357259.52 | M33: 10(7) | N33: ='[21] FGN 2024 MGT Monthly'!$H$39 -> 235577.83 | O33: =N33*0.025 -> 5889.4458 | P33: 6260.744 | Q33: =O33-P33 -> -371.29817 | R33: =O33*12 -> 70673.35
A34: 28 | B34: ABDULMUSHIN TAWFIQ LADAN | C34: ICT OFFICER | D34: 9(8) | E34: 338711.67 | F34: 9(9) | G34: 347016.17 | H34: =G34-E34 -> 8304.5 | I34: 27096.933 | J34: =G34*0.08 -> 27761.293 | K34: =J34-I34 -> 664.36 | L34: =J34*12 -> 333135.52 | M34: 9(9) | N34: 222674.58 | Q34: =O34-P34 -> 0 | R34: =O34*12 -> 0
A35: 29 | B35: MOHAMMED BELLO | C35: SENIOR PROTOCOL OFFICER | D35: 10(7) | E35: 372145.33 | F35: 10(7) | G35: 372145.33 | H35: =G35-E35 -> 0 | I35: 29771.627 | J35: =G35*0.08 -> 29771.627 | K35: =J35-I35 -> -5.8207661e-11 | L35: =J35*12 -> 357259.52 | M35: 10(7) | N35: ='[21] FGN 2024 MGT Monthly'!$H$39 -> 235577.83 | Q35: =O35-P35 -> 0 | R35: =O35*12 -> 0
A36: 30 | B36: HOLINESS PAUL UDO | C36: ADMINISTRATION OFFICER, M&E | D36: 9(7) | E36: 330407.08 | F36: 9(8) | G36: 338711.67 | H36: =G36-E36 -> 8304.5833 | I36: 29771.627 | J36: =G36*0.08 -> 27096.933 | K36: =J36-I36 -> -2674.6933 | L36: =J36*12 -> 325163.2 | M36: 9(8) | N36: 217733.42 | O36: =N36*0.025 -> 5443.3354 | P36: 5319.8 | Q36: =O36-P36 -> 123.53542 | R36: =O36*12 -> 65320.025
A37: 31 | B37: CHARITY UDO AKAN | C37: ADMINISTRATION OFFICER, M&E | D37: 9(7) | E37: 330408.08 | F37: 9(8) | G37: 338711.67 | H37: =G37-E37 -> 8303.5833 | I37: 26432.647 | J37: =G37*0.08 -> 27096.933 | K37: =J37-I37 -> 664.28667 | L37: =J37*12 -> 325163.2 | M37: 9(8) | N37: 217733.42 | O37: =N37*0.025 -> 5443.3354 | P37: 5319.8 | Q37: =O37-P37 -> 123.53542 | R37: =O37*12 -> 65320.025
A38: 32 | B38: SANI UMAR IBRAHIM | C38: STORE OFFICER | D38: 9(7) | E38: 330409.08 | F38: 9(8) | G38: 338711.67 | H38: =G38-E38 -> 8302.5833 | I38: 26432.727 | J38: =G38*0.08 -> 27096.933 | K38: =J38-I38 -> 664.20667 | L38: =J38*12 -> 325163.2 | M38: 9(8) | N38: 217733.42 | Q38: =O38-P38 -> 0 | R38: =O38*12 -> 0
A39: 33 | B39: FAHAD ABUBUKAR LONGMAN | C39: ICT OFFICER | D39: 9(7) | E39: 330409.08 | F39: 9(8) | G39: 338711.67 | H39: =G39-E39 -> 8302.5833 | I39: 26432.727 | J39: =G39*0.08 -> 27096.933 | K39: =J39-I39 -> 664.20667 | L39: =J39*12 -> 325163.2 | M39: 9(8) | N39: 217733.42 | O39: =N39*0.025 -> 5443.3354 | P39: 5319.8 | Q39: =O39-P39 -> 123.53542 | R39: =O39*12 -> 65320.025
A40: 34 | B40: HARUNA JIBRIL AMEH | C40: ASST. ADMIN. OFFICER | D40: 8(9) | E40: 301910.75 | F40: 8(10) | G40: 308920.67 | H40: =G40-E40 -> 7009.9167 | I40: 24152.86 | J40: =G40*0.08 -> 24713.653 | K40: =J40-I40 -> 560.79333 | L40: =J40*12 -> 296563.84 | M40: 8(10) | N40: 200549.42 | O40: =N40*0.025 -> 5013.7354 | P40: 4909.1104 | Q40: =O40-P40 -> 104.625 | R40: =O40*12 -> 60164.825
A41: 35 | B41: RAMATU IBRAHIM ABDULRAHEEM | C41: INFORMATION OFFICER | D41: 8(8) | E41: 294900.83 | F41: 8(9) | G41: 301910.75 | H41: =G41-E41 -> 7009.9167 | I41: 23592.067 | J41: =G41*0.08 -> 24152.86 | K41: =J41-I41 -> 560.79333 | L41: =J41*12 -> 289834.32 | M41: 8(9) | N41: 196364.42 | O41: =N41*0.025 -> 4909.1104 | P41: 4804.4854 | Q41: =O41-P41 -> 104.625 | R41: =O41*12 -> 58909.325
A42: 36 | B42: EDIDIONG EZEKIEL ATAT | C42: ASSIST PROCUREMENT OFFICER | D42: 8(7) | E42: 287890.92 | F42: 8(8) | G42: 294900.83 | H42: =G42-E42 -> 7009.9167 | I42: 23031.273 | J42: =G42*0.08 -> 23592.067 | K42: =J42-I42 -> 560.79333 | L42: =J42*12 -> 283104.8 | M42: 8(8) | N42: 192179.42 | O42: =N42*0.025 -> 4804.4854 | P42: =4699.86 -> 4699.86 | Q42: =O42-P42 -> 104.62542 | R42: =O42*12 -> 57653.825
A43: 37 | B43: MAHMUD ADEWOLE HASSAN | C43: ASSIST ICT OFFICER | D43: 8(7) | E43: 287890.92 | F43: 8(8) | G43: 294900.83 | H43: =G43-E43 -> 7009.9167 | I43: 23031.273 | J43: =G43*0.08 -> 23592.067 | K43: =J43-I43 -> 560.79333 | L43: =J43*12 -> 283104.8 | M43: 8(8) | N43: 192179.42 | Q43: =O43-P43 -> 0 | R43: =O43*12 -> 0
A44: 38 | B44: YUSUF KABIRU TURAKI | C44: ASSIST ICT OFFICER | D44: 8(7) | E44: 287890.92 | F44: 8(8) | G44: 294900.83 | H44: =G44-E44 -> 7009.9167 | I44: 23031.273 | J44: =G44*0.08 -> 23592.067 | K44: =J44-I44 -> 560.79333 | L44: =J44*12 -> 283104.8 | M44: 8(8) | N44: 192179.42 | Q44: =O44-P44 -> 0 | R44: =O44*12 -> 0
A45: 39 | B45: FATIMA OMAR IBRAHIM | C45: ASSIST PROTOCOL OFFICER | D45: 8(7) | E45: 287890.92 | F45: 8(8) | G45: 294900.83 | H45: =G45-E45 -> 7009.9167 | I45: 23031.273 | J45: =G45*0.08 -> 23592.067 | K45: =J45-I45 -> 560.79333 | L45: =J45*12 -> 283104.8 | M45: 8(8) | N45: 192179.42 | Q45: =O45-P45 -> 0 | R45: =O45*12 -> 0
A46: 40 | B46: EBERE ANASTHESIA IGWE | C46: ASSIST ICT OFFICER | D46: 8(7) | E46: 287890.92 | F46: 8(8) | G46: 294900.83 | H46: =G46-E46 -> 7009.9167 | I46: 23031.273 | J46: =G46*0.08 -> 23592.067 | K46: =J46-I46 -> 560.79333 | L46: =J46*12 -> 283104.8 | M46: 8(8) | N46: 192179.42 | Q46: =O46-P46 -> 0 | R46: =O46*12 -> 0
A47: 41 | B47: ALIYU GARBA LERE | C47: ASSIST INFORMATION OFFICER | D47: 8(7) | E47: 287891.92 | F47: 8(8) | G47: 294900.83 | H47: =G47-E47 -> 7008.9167 | I47: 23031.353 | J47: =G47*0.08 -> 23592.067 | K47: =J47-I47 -> 560.71333 | L47: =J47*12 -> 283104.8 | M47: 8(8) | N47: 192179.42 | Q47: =O47-P47 -> 0 | R47: =O47*12 -> 0
B48: TOTAL | C48: 41 | E48: =SUM(E7:E47) -> 20203860 | G48: =SUM(G7:G47) -> 20529918 | H48: =SUM(H7:H47) -> 326057.83 | I48: =SUM(I7:I47) -> 1394628.6 | J48: =SUM(J7:J47) -> 1412277.9 | K48: =SUM(K7:K47) -> 17649.253 | L48: =SUM(L7:L47) -> 16947335 | M48: =SUM(M7:M47) -> 0 | N48: =SUM(N7:N47) -> 11102994 | ... R48: =SUM(R7:R47) -> 1778670.7
B50: INTERNAL AUDIT
A51: 1 | B51: OSANAIYE DAVID AKINYEMI | C51: DIRECTOR INTERNAL AUDIT | D51: 17(9) | E51: 1747106.4 | F51: 17(9) | G51: 1747106.4 | H51: =G51-E51 -> 0 | I51: 139768.51 | J51: =G51*0.08 -> 139768.51 | K51: =J51-I51 -> 0 | L51: =J51*12 -> 1677222.2 | M51: 17(9) | N51: 1086777.1 | Q51: =O51-P51 -> 0 | R51: =O51*12 -> 0
A52: 2 | B52: EVELYN ETONKE AGAN | C52: ASST DIR AUDIT | D52: 15(7) | E52: 700713.92 | F52: 15(8) | G52: 722595.5 | H52: =G52-E52 -> 21881.583 | I52: 56057.113 | J52: =G52*0.08 -> 57807.64 | K52: =J52-I52 -> 1750.5267 | L52: =J52*12 -> 693691.68 | M52: 15(8) | N52: 445995.83 | Q52: =O52-P52 -> 0 | R52: =O52*12 -> 0
A53: 3 | B53: JAMILA ABDUL | C53: SENIOR INTERNAL AUDITOR | D53: 10(8) | E53: 381140.67 | F53: 10(9) | G53: 390135.83 | H53: =G53-E53 -> 8995.1667 | I53: 30491.253 | J53: =G53*0.08 -> 31210.867 | K53: =J53-I53 -> 719.61333 | L53: =J53*12 -> 374530.4 | M53: 10(9) | N53: 246171.17 | O53: =N53*0.025 -> 6154.2792 | P53: 6021.8646 | Q53: =O53-P53 -> 132.41458 | R53: =O53*12 -> 73851.35
A54: 4 | B54: IJEOMA EWELUKWA | C54: PRINCIPAL AUDIT OFFICER | D54: 12(7) | E54: 441159 | F54: 12(8) | G54: 454993.58 | H54: =G54-E54 -> 13834.583 | I54: 35292.72 | J54: =G54*0.08 -> 36399.487 | K54: =J54-I54 -> 1106.7667 | L54: =J54*12 -> 436793.84 | M54: 12(8) | N54: 286447.08 | Q54: =O54-P54 -> 0 | R54: =O54*12 -> 0
A55: 5 | B55: HASSAN ABDULHADI | C55: SENIOR INTERNAL AUDITOR | D55: 9(7) | E55: 330407.08 | F55: 9(8) | G55: 338711.67 | H55: =G55-E55 -> 8304.5833 | I55: 26432.567 | J55: =G55*0.08 -> 27096.933 | K55: =J55-I55 -> 664.36667 | L55: =J55*12 -> 325163.2 | M55: 9(8) | N55: 217733.42 | O55: =N55*0.025 -> 5443.3354 | P55: 5319.8 | Q55: =O55-P55 -> 123.53542 | R55: =O55*12 -> 65320.025
A56: 6 | B56: YUSUF YUSUF DAYYABU | C56: INERNAL AUDIT OFFICER | D56: 9(8) | E56: 338711.67 | F56: 9(9) | G56: 347016.17 | H56: =G56-E56 -> 8304.5 | I56: 27096.933 | J56: =G56*0.08 -> 27761.293 | K56: =J56-I56 -> 664.36 | L56: =J56*12 -> 333135.52 | M56: 9(9) | N56: 222674.58 | O56: =N56*0.025 -> 5566.8646 | P56: 5443.3354 | Q56: =O56-P56 -> 123.52917 | R56: =O56*12 -> 66802.375
A57: 7 | B57: UDONSI QUEENETH CHIWENDU | C57: ASSIST PROGRAMME OFFICER | D57: 8(7) | E57: 287890.92 | F57: 8(8) | G57: 294900.83 | H57: =G57-E57 -> 7009.9167 | I57: 23031.273 | J57: =G57*0.08 -> 23592.067 | K57: =J57-I57 -> 560.79333 | L57: =J57*12 -> 283104.8 | M57: 8(8) | N57: 192179.42 | Q57: =O57-P57 -> 0 | R57: =O57*12 -> 0
C58: 7 | E58: =SUM(E51:E57) -> 4227129.7 | G58: =SUM(G51:G57) -> 4295460 | H58: =SUM(H51:H57) -> 68330.333 | I58: =SUM(I51:I57) -> 338170.37 | J58: =SUM(J51:J57) -> 343636.8 | K58: =SUM(K51:K57) -> 5466.4267 | L58: =SUM(L51:L57) -> 4123641.6 | M58: =SUM(M51:M57) -> 0 | N58: =SUM(N51:N57) -> 2697978.6 | ... R58: =SUM(R51:R57) -> 205973.75
B60: LEG. SUPPORT SEVICES
A61: 1 | B61: BETHEL UZOMA IHUGBA | C61: AG. DIRECTOR, AEEP | D61: 17(7) | E61: 1647612 | F61: 17(8) | G61: 1697359.3 | H61: =G61-E61 -> 49747.333 | I61: 131808.96 | J61: =G61*0.08 -> 135788.75 | K61: =J61-I61 -> 3979.7867 | L61: =J61*12 -> 1629465 | M61: 17(8) | N61: 1056272.8 | Q61: =O61-P61 -> 0 | R61: =O61*12 -> 0
A62: 2 | B62: OGUCHE SAMUEL | C62: SNR RESEARCH FELLOW | D62: 15(9) | E62: 744477 | F62: 15(9) | G62: 744477 | H62: =G62-E62 -> 0 | I62: 59558.16 | J62: =G62*0.08 -> 59558.16 | K62: =J62-I62 -> 0 | L62: =J62*12 -> 714697.92 | M62: 15(9) | N62: 459010.5 | Q62: =O62-P62 -> 0 | R62: =O62*12 -> 0
A63: 3 | B63: IBRAHIM USMAN | C63: SNR RESEARCH FELLOW | D63: 15(9) | E63: 744477 | F63: 15(9) | G63: 744477 | H63: =G63-E63 -> 0 | I63: 59558.16 | J63: =G63*0.08 -> 59558.16 | K63: =J63-I63 -> 0 | L63: =J63*12 -> 714697.92 | M63: 15(9) | N63: 459010.5 | O63: =N63*0.025 -> 11475.263 | P63: 11475.263 | Q63: =O63-P63 -> 0 | R63: =O63*12 -> 137703.15
A64: 4 | B64: DR MOHAMMED O. AMALI | C64: SNR RESEARCH FELLOW | D64: 15(8) | E64: 722595.5 | F64: 15(9) | G64: 744477 | H64: =G64-E64 -> 21881.5 | I64: 57807.64 | J64: =G64*0.08 -> 59558.16 | K64: =J64-I64 -> 1750.52 | L64: =J64*12 -> 714697.92 | M64: 15(9) | N64: 459010.5 | Q64: =O64-P64 -> 0 | R64: =O64*12 -> 0
A65: 5 | B65: YAHAYA SHAMSU | C65: SNR RESEARCH FELLOW | D65: 15(7) | E65: 700713.92 | F65: 15(8) | G65: 722595.5 | H65: =G65-E65 -> 21881.583 | I65: 56057.113 | J65: =G65*0.08 -> 57807.64 | K65: =J65-I65 -> 1750.5267 | L65: =J65*12 -> 693691.68 | M65: 15(8) | N65: 445995.83 | P65: 0 | Q65: =O65-P65 -> 0 | R65: =O65*12 -> 0
A66: 6 | B66: CHIDEBE MATHEW NWANKWO | C66: SNR RESEARCH FELLOW | D66: 15(7) | E66: 700713.92 | F66: 15(8) | G66: 722595.5 | H66: =G66-E66 -> 21881.583 | I66: 56057.113 | J66: =G66*0.08 -> 57807.64 | K66: =J66-I66 -> 1750.5267 | L66: =J66*12 -> 693691.68 | M66: 15(8) | N66: 445995.83 | P66: 0 | Q66: =O66-P66 -> 0 | R66: =O66*12 -> 0
A67: 7 | B67: UMAR MUSA PADAH | C67: PRINC. RESEARCH OFFICER | D67: 12(7) | E67: 441159 | F67: 12(8) | G67: 454993.58 | H67: =G67-E67 -> 13834.583 | I67: 35292.72 | J67: =G67*0.08 -> 36399.487 | K67: =J67-I67 -> 1106.7667 | L67: =J67*12 -> 436793.84 | M67: 12(8) | N67: 286447.08 | Q67: =O67-P67 -> 0 | R67: =O67*12 -> 0
A68: 8 | B68: BILKIS S. LAWAL-GAMBARI | C68: RESEARCH OFFICER | D68: 10(9) | E68: 390135.83 | F68: 10(10) | G68: ='[21] FGN 2024 MGT Monthly'!$K$39+'[21]Peculiar Allowance'!$K$39 -> 399131.17 | H68: =G68-E68 -> 8995.3333 | I68: 31210.867 | J68: =G68*0.08 -> 31930.493 | K68: =J68-I68 -> 719.62667 | L68: =J68*12 -> 383165.92 | M68: 10(10) | N68: 251467.92 | Q68: =O68-P68 -> 0 | R68: =O68*12 -> 0
A69: 9 | B69: UMOH USENOBONG EMMANUEL | C69: SENIOR RESEARCH OFFICER | D69: 10(7) | E69: 372145.33 | F69: 10(8) | G69: 381140.67 | H69: =G69-E69 -> 8995.3333 | I69: 29771.627 | J69: =G69*0.08 -> 30491.253 | K69: =J69-I69 -> 719.62667 | L69: =J69*12 -> 365895.04 | M69: 10(8) | N69: 240874.58 | Q69: =O69-P69 -> 0 | R69: =O69*12 -> 0
A70: 10 | B70: ZAINAB AKINDE | C70: RESEARCH OFFICER | D70: 9(9) | E70: 347016.17 | F70: 9(10) | G70: 355320.67 | H70: =G70-E70 -> 8304.5 | I70: 27761.293 | J70: =G70*0.08 -> 28425.653 | K70: =J70-I70 -> 664.36 | L70: =J70*12 -> 341107.84 | M70: 9(10) | N70: 227615.75 | Q70: =O70-P70 -> 0 | R70: =O70*12 -> 0
A71: 11 | B71: GUNAT NANSAK MARK | C71: RESEARCH OFFICER | D71: 9(9) | E71: 347016.17 | F71: 9(10) | G71: 355320.67 | H71: =G71-E71 -> 8304.5 | I71: 27761.293 | J71: =G71*0.08 -> 28425.653 | K71: =J71-I71 -> 664.36 | L71: =J71*12 -> 341107.84 | M71: 9(10) | N71: 227615.75 | Q71: =O71-P71 -> 0 | R71: =O71*12 -> 0
A72: 12 | B72: MANDU ESSIEN NDEM | C72: RESEARCH OFFICER | D72: 9(7) | E72: 330407.08 | F72: 9(8) | G72: 338711.67 | H72: =G72-E72 -> 8304.5833 | I72: 26432.567 | J72: =G72*0.08 -> 27096.933 | K72: =J72-I72 -> 664.36667 | L72: =J72*12 -> 325163.2 | M72: 9(8) | N72: 217733.42 | Q72: =O72-P72 -> 0 | R72: =O72*12 -> 0
B73: TOTAL | C73: 12 | E73: =SUM(E61:E72) -> 7488468.9 | G73: =SUM(G61:G72) -> 7660599.8 | H73: =SUM(H61:H72) -> 172130.83 | I73: =SUM(I61:I72) -> 599077.51 | J73: =SUM(J61:J72) -> 612847.98 | K73: =SUM(K61:K72) -> 13770.467 | L73: =SUM(L61:L72) -> 7354175.8 | M73: =SUM(M61:M72) -> 0 | N73: =SUM(N61:N72) -> 4777050.5 | ... R73: =SUM(R61:R72) -> 137703.15
B75: LEGAL SERVICES
A76: 1 | B76: DR SHUAIBU DANWANKA | C76: DIRECTOR LEGAL SERVICES | D76: 17(9) | E76: 1747106.4 | F76: 17(9) | G76: 1747106.4 | H76: =G76-E76 -> 0 | I76: 139768.51 | J76: 139768.51 | K76: =J76-I76 -> 0 | L76: =J76*12 -> 1677222.2 | M76: 17(9) | N76: 1086777.1 | P76: 0 | Q76: =O76-P76 -> 0 | R76: =O76*12 -> 0
A77: 2 | B77: ABDULSALAM BAKO | C77: MANAGER, LEGAL SERVICES | D77: 15 (9) | E77: 744477 | F77: 15 (9) | G77: 744477 | H77: =G77-E77 -> 0 | I77: 59558.16 | J77: 59558.16 | K77: =J77-I77 -> 0 | L77: =J77*12 -> 714697.92 | M77: 15 (9) | N77: 459010.5 | P77: 0 | Q77: =O77-P77 -> 0 | R77: =O77*12 -> 0
B78: TOTAL | C78: 2 | E78: =SUM(E76:E77) -> 2491583.4 | G78: =SUM(G76:G77) -> 2491583.4 | H78: =SUM(H76:H77) -> 0 | I78: =SUM(I76:I77) -> 199326.67 | J78: =SUM(J76:J77) -> 199326.67 | K78: =SUM(K76:K77) -> 0 | L78: =J78*12 -> 2391920.1 | P78: =SUM(P76:P77) -> 0
B80: DEMOCRACY & GOVERNANCE
A81: 1 | B81: NGARA CHRISTOPHER OCHANJA | C81: DEP DIR DEM & GOVERNANCE | D81: 16(9) | E81: 905306.75 | F81: 16(9) | G81: 905306.75 | H81: =G81-E81 -> 0 | I81: 72424.54 | J81: =G81*0.08 -> 72424.54 | K81: =J81-I81 -> 0 | L81: =J81*12 -> 869094.48 | M81: 16(9) | N81: 554669.5 | O81: =N81*0.025 -> 13866.737 | P81: 13866.737 | Q81: =O81-P81 -> 0 | R81: =O81*12 -> 166400.85
A82: 2 | B82: EJALONIBU GANIYU LAYI | C82: RESEARCH FELLOW 1 | D82: 14(9) | E82: 558165.25 | F82: 14(10) | G82: 573911.08 | H82: =G82-E82 -> 15745.833 | I82: 44653.22 | J82: =G82*0.08 -> 45912.887 | K82: =J82-I82 -> 1259.6667 | L82: =J82*12 -> 550954.64 | M82: 14(10) | N82: 357066.67 | Q82: =O82-P82 -> 0 | R82: =O82*12 -> 0
A83: 3 | B83: MARTINS SOLOMON UDOM | C83: RESEARCH FELLOW 11 | D83: 13(7) | E83: 482846.58 | F83: 13(8) | G83: 497472.75 | H83: =G83-E83 -> 14626.167 | I83: 38627.727 | J83: =G83*0.08 -> 39797.82 | K83: =J83-I83 -> 1170.0933 | L83: =J83*12 -> 477573.84 | M83: 13(8) | N83: 311673.25 | O83: =N83*0.025 -> 7791.8313 | P83: 7574.69 | Q83: =O83-P83 -> 217.14125 | R83: =O83*12 -> 93501.975
A84: 4 | B84: ISHAKA DELE | C84: RESEARCH FELLOW 11 | D84: 13(7) | E84: 482846.58 | F84: 13(8) | G84: 497472.75 | H84: =G84-E84 -> 14626.167 | I84: 38627.727 | J84: =G84*0.08 -> 39797.82 | K84: =J84-I84 -> 1170.0933 | L84: =J84*12 -> 477573.84 | M84: 13(8) | N84: 311673.25 | O84: =N84*0.025 -> 7791.8313 | P84: 7574.69 | Q84: =O84-P84 -> 217.14125 | R84: =O84*12 -> 93501.975
A85: 5 | B85: UDEFUNA NNADOZIE PATRICK | C85: RESEARCH OFFICER | D85: 12(9) | E85: 468828.17 | F85: 12(10) | G85: 482662.67 | H85: =G85-E85 -> 13834.5 | I85: 37506.253 | J85: =G85*0.08 -> 38613.013 | K85: =J85-I85 -> 1106.76 | L85: =J85*12 -> 463356.16 | M85: 12(10) | N85: 302878.67 | O85: =N85*0.025 -> 7571.9667 | P85: =7366.57 -> 7366.57 | Q85: =O85-P85 -> 205.39667 | R85: =O85*12 -> 90863.6
A86: 6 | B86: SHAFIU YAHYA MIKAIL | C86: PRINCIPAL RESEARCH OFFICER | D86: 12(9) | E86: 468828.17 | F86: 12(10) | G86: 482662.67 | H86: =G86-E86 -> 13834.5 | I86: 37506.253 | J86: =G86*0.08 -> 38613.013 | K86: =J86-I86 -> 1106.76 | L86: =J86*12 -> 463356.16 | M86: 12(10) | N86: 302878.67 | Q86: =O86-P86 -> 0 | R86: =O86*12 -> 0
A87: 7 | B87: HASSAN YERIMA | C87: PRINCIPAL RESEARCH OFFICER | D87: 12(9) | E87: 468828.17 | F87: 12(10) | G87: 482662.67 | H87: =G87-E87 -> 13834.5 | I87: 37506.253 | J87: =G87*0.08 -> 38613.013 | K87: =J87-I87 -> 1106.76 | L87: =J87*12 -> 463356.16 | M87: 12(10) | N87: 302878.67 | Q87: =O87-P87 -> 0 | R87: =O87*12 -> 0
A88: 8 | B88: HAUWA PATE SADIQ | C88: ASST CHIEF PROGRAMME OFFICER | D88: 13(7) | E88: 482846.58 | F88: 13(7) | G88: 482846.58 | H88: =G88-E88 -> 0 | I88: 38627.727 | J88: =G88*0.08 -> 38627.727 | K88: =J88-I88 -> -5.8207661e-11 | L88: =J88*12 -> 463532.72 | M88: 13(7) | N88: 302987.42 | Q88: =O88-P88 -> 0 | R88: =O88*12 -> 0
A89: 9 | B89: OBOT ETIMBUK EMMANUEL | C89: PRINCIPAL INFO. OFFICER | D89: 12(7) | E89: 441159 | F89: 12(8) | G89: 454993.58 | H89: =G89-E89 -> 13834.583 | I89: 35292.72 | J89: =G89*0.08 -> 36399.487 | K89: =J89-I89 -> 1106.7667 | L89: =J89*12 -> 436793.84 | M89: 12(8) | N89: 286447.08 | O89: =N89*0.025 -> 7161.1771 | P89: 6955.7812 | Q89: =O89-P89 -> 205.39583 | R89: =O89*12 -> 85934.125
A90: 10 | B90: KOLAPO Q. ABAYOMI | C90: RESEARCH OFFICER | D90: 10(9) | E90: 390135.83 | F90: 10(10) | G90: 399131.17 | H90: =G90-E90 -> 8995.3333 | I90: 31210.867 | J90: =G90*0.08 -> 31930.493 | K90: =J90-I90 -> 719.62667 | L90: =J90*12 -> 383165.92 | M90: 10(10) | N90: 251467.92 | O90: =N90*0.025 -> 6286.6979 | P90: 6154.2792 | Q90: =O90-P90 -> 132.41875 | R90: =O90*12 -> 75440.375
A91: 11 | B91: SALIHU SHAMSUDEEN OPEYEMI | C91: PROGRAMME OFFICER | D91: 9(7) | E91: 330407.08 | F91: 9(8) | G91: 338711.67 | H91: =G91-E91 -> 8304.5833 | I91: 26432.567 | J91: =G91*0.08 -> 27096.933 | K91: =J91-I91 -> 664.36667 | L91: =J91*12 -> 325163.2 | M91: 9(8) | N91: 217733.42 | Q91: =O91-P91 -> 0 | R91: =O91*12 -> 0
B92: TOTAL | C92: 11 | E92: =SUM(E81:E91) -> 5480198.2 | G92: =SUM(G81:G91) -> 5597834.3 | H92: =SUM(H81:H91) -> 117636.17 | I92: =SUM(I81:I91) -> 438415.85 | J92: =SUM(J81:J91) -> 447826.75 | K92: =SUM(K81:K91) -> 9410.8933 | L92: =SUM(L81:L91) -> 5373921 | M92: =SUM(M81:M91) -> 0 | N92: =SUM(N81:N91) -> 3502354.5 | ... R92: =SUM(R81:R91) -> 605642.9
B94: DEPARTMENT OF STUDIES
A95: 1 | B95: DR ASIMIYU G. ABIOLA | C95: DIRECTOR POST GRADUATE | D95: 17(9) | E95: 1747106.4 | F95: 17(9) | G95: 1747106.4 | H95: =G95-E95 -> 0 | I95: 139768.51 | J95: =G95*0.08 -> 139768.51 | K95: =J95-I95 -> 0 | L95: =J95*12 -> 1677222.2 | M95: 17(9) | N95: 1086777.1 | P95: 0 | Q95: =O95-P95 -> 0 | R95: =O95*12 -> 0
A96: 2 | B96: AYOBOLU OLAJIDE OLUFUNSHO | C96: ASSISTANT DIR. EXXAMS & RECORD | D96: 15(7) | E96: 722595.5 | F96: 15(8) | G96: 722595.5 | H96: =G96-E96 -> 0 | I96: 57807.64 | J96: =G96*0.08 -> 57807.64 | K96: =J96-I96 -> 0 | L96: =J96*12 -> 693691.68 | M96: 15(8) | N96: 445995.83 | Q96: =O96-P96 -> 0 | R96: =O96*12 -> 0
A97: 3 | B97: DR. HADIZA SAIDU | C97: ASSISTANT DIRECTOR | D97: 15(7) | E97: 722595.5 | F97: 15(8) | G97: 722595.5 | H97: =G97-E97 -> 0 | I97: 57807.64 | J97: =G97*0.08 -> 57807.64 | K97: =J97-I97 -> 0 | L97: =J97*12 -> 693691.68 | M97: 15(8) | N97: 445995.83 | Q97: =O97-P97 -> 0 | R97: =O97*12 -> 0
A98: 4 | B98: ANTHONY EDET | C98: CHIEF PROGRAMMES OFFICER | D98: 14(10) | E98: 573911.08 | F98: 14(11) | G98: ='[21]Peculiar Allowance'!$L$42+'[21] FGN 2024 MGT Monthly'!$L$42 -> 589657 | H98: =G98-E98 -> 15745.917 | I98: 45912.887 | J98: =G98*0.08 -> 47172.56 | K98: =J98-I98 -> 1259.6733 | L98: =J98*12 -> 566070.72 | M98: 14(11) | N98: 366417.5 | O98: =N98*0.025 -> 9160.4375 | P98: 8926.6667 | Q98: =O98-P98 -> 233.77083 | R98: =O98*12 -> 109925.25
A99: 5 | B99: CHRISTIAN MADUABUCHI ODO | C99: ASSIST. CHIEF ICT OFFICER | D99: 13(7) | E99: 482846.58 | F99: 13(8) | G99: 497472.75 | H99: =G99-E99 -> 14626.167 | I99: 38627.727 | J99: =G99*0.08 -> 39797.82 | K99: =J99-I99 -> 1170.0933 | L99: =J99*12 -> 477573.84 | M99: 13(8) | N99: 311673.25 | O99: =N99*0.025 -> 7791.8313 | P99: 7574.6854 | Q99: =O99-P99 -> 217.14583 | R99: =O99*12 -> 93501.975
A100: 6 | B100: DR. IBANGA ISSAC JONAH | C100: ASSIST. CHIEF PROGRM OFFICER | D100: 13(7) | E100: 482846.58 | F100: 13(8) | G100: 497472.75 | H100: =G100-E100 -> 14626.167 | I100: 38627.727 | J100: =G100*0.08 -> 39797.82 | K100: =J100-I100 -> 1170.0933 | L100: =J100*12 -> 477573.84 | M100: 13(8) | N100: 311673.25 | Q100: =O100-P100 -> 0 | R100: =O100*12 -> 0
A101: 7 | B101: IGWE STACY | C101: PRINC. PROGRAMME OFFICER | D101: 12(8) | E101: 454993.58 | F101: 12(9) | G101: 468828.17 | H101: =G101-E101 -> 13834.583 | I101: 36399.487 | J101: =G101*0.08 -> 37506.253 | K101: =J101-I101 -> 1106.7667 | L101: =J101*12 -> 450075.04 | M101: 12(9) | N101: 294662.92 | O101: =N101*0.025 -> 7366.5729 | P101: 7161.1771 | Q101: =O101-P101 -> 205.39583 | R101: =O101*12 -> 88398.875
A102: 8 | B102: MUNIRU JIBRIN | C102: SENIOR PROGRAMME OFFICER | D102: 10(7) | E102: 372145.33 | F102: 10(8) | G102: 381140.67 | H102: =G102-E102 -> 8995.3333 | I102: 29771.627 | J102: =G102*0.08 -> 30491.253 | K102: =J102-I102 -> 719.62667 | L102: =J102*12 -> 365895.04 | M102: 10(8) | N102: 240874.58 | Q102: =O102-P102 -> 0 | R102: =O102*12 -> 0
A103: 9 | B103: OLANIYAN TAIWO ABINBOLA | C103: PROGRAMME OFFICER | D103: 9(8) | E103: 347016.17 | F103: 9(9) | G103: 347016.17 | H103: =G103-E103 -> 0 | I103: 27761.293 | J103: =G103*0.08 -> 27761.293 | K103: =J103-I103 -> 0 | L103: =J103*12 -> 333135.52 | M103: 9(9) | N103: 222674.58 | O103: =N103*0.025 -> 5566.8646 | P103: 5566.8646 | Q103: =O103-P103 -> 0 | R103: =O103*12 -> 66802.375
A104: 10 | B104: MUSA ALKASIM ADAMU | C104: PROGRAMME OFFICER | D104: 9(7) | E104: 330407.08 | F104: 9(8) | G104: 338711.67 | H104: =G104-E104 -> 8304.5833 | I104: 26432.567 | J104: =G104*0.08 -> 27096.933 | K104: =J104-I104 -> 664.36667 | L104: =J104*12 -> 325163.2 | M104: 9(8) | N104: 217733.42 | Q104: =O104-P104 -> 0 | R104: =O104*12 -> 0
A105: 11 | B105: AMINAT JUMOKE SULAIMON | C105: AST. PROGRAMME OFFICER | D105: 8(9) | E105: 301910.75 | F105: 8(10) | G105: 308920.67 | H105: =G105-E105 -> 7009.9167 | I105: 24152.86 | J105: =G105*0.08 -> 24713.653 | K105: =J105-I105 -> 560.79333 | L105: =J105*12 -> 296563.84 | M105: 8(10) | N105: 200549.42 | P105: 0 | Q105: =O105-P105 -> 0 | R105: =O105*12 -> 0
...

Sheet Basic & Pensions (2)
A1: NATIONAL INSTITUTE FOR LEGISLATIVE AND DEMOCRATIC STUDIES
A2: STAFF PAYROLL FOR THE MONTH OF JANUARY, 2026
E3: ='[1]FEB 08'!E11/'[1]FEB 08'!M11 -> #REF!
B4: STAFF NAME | C4: DESIGNATION | D4: GRADE LEVEL | E4: OLD CUM BASIC SALARY | F4: NEW BASIC SALARY | G4: PECULIAR ALLOW | H4: NEW CUM BASIC SALARY | I4: INCREASE IN CUM BASIC SALARY | J4: OLD EMPLOYEE PENSION 8% | K4: NEW EMPLOYEE PENSION 8% | L4: INCREASE IN DEDUCTION | M4: OLD NHF | N4: NEW NHF | O4: INCREASE IN NHF | P4: ANNUAL NEW EMPLOYEE PENSIONS | Q4: ANNUAL NEW NHF
E5: N | F5: N | G5: N | H5: N | I5: N | J5: N | K5: N | L5: N | M5: N | N5: N | O5: N | P5: N | Q5: N
E6: A | F6: B | G6: C | H6: D | I6: E | J6: F | K6: G | L6: H | M6: I | N6: J | O6: K | P6: L | Q6: M
A7: S/N | B7: DG'S OFFICE | H7: (B+C) | I7: (D-A) | J7: (8% of A) | K7: (8% of D) | L7: (G-F) | N7: (2.5% of B) | O7: (J-I) | P7: (J-I) | Q7: (J-I)
A8: 1 | B8: PROF. ABUBAKAR O. SULAIMAN | C8: DIRECTOR GENERAL | D8: CONSOL | E8: 1659751.2 | F8: 1086777.1 | G8: 884360 | H8: =F8+G8 -> 1971137.1 | I8: =H8-E8 -> 311385.92 | L8: =K8-J8 -> 0 | O8: =N8-M8 -> 0 | P8: =K8*12 -> 0 | Q8: =N8*12 -> 0
A9: 2 | B9: RAHEEM USMAN AYIGORO | C9: SA-INFRASTRUCTURE | D9: 16 (9) | E9: 762373.17 | F9: 554669.5 | G9: 350637.25 | H9: =F9+G9 -> 905306.75 | I9: =H9-E9 -> 142933.58 | J9: 60989.853 | K9: =H9*0.08 -> 72424.54 | L9: =K9-J9 -> 11434.687 | O9: =N9-M9 -> 0 | P9: =K9*12 -> 869094.48 | Q9: =N9*12 -> 0
A10: 3 | B10: MARIAM MOHAMMED BELLO | C10: SA- SPECIAL DUTIES | D10: 16 (9) | E10: 762373.17 | F10: 554669.5 | G10: 350637.25 | H10: =F10+G10 -> 905306.75 | I10: =H10-E10 -> 142933.58 | L10: =K10-J10 -> 0 | O10: =N10-M10 -> 0 | P10: =K10*12 -> 0 | Q10: =N10*12 -> 0
A11: 4 | B11: DR IKEME ARTHUR J.O | C11: DEPUTY DIRECTOR, M&E | D11: 16 (9) | E11: 762373.17 | F11: 554669.5 | G11: 350637.25 | H11: =F11+G11 -> 905306.75 | I11: =H11-E11 -> 142933.58 | J11: 60989.853 | K11: =H11*0.08 -> 72424.54 | L11: =K11-J11 -> 11434.687 | M11: 10293.398 | N11: =0.025*F11 -> 13866.737 | O11: =N11-M11 -> 3573.3396 | P11: =K11*12 -> 869094.48 | Q11: =N11*12 -> 166400.85
A12: 5 | B12: ANDRAWUS MUSA | C12: DEP. DIRECTOR, STORES & PROCUREMENT | D12: 16(8) | E12: 716034 | F12: ='[19] FGN 2024 MGT Monthly'!$I$44 -> 539028 | G12: ='[19]Peculiar Allowance'!$I$44 -> 339980.92 | H12: =F12+G12 -> 879008.92 | I12: =H12-E12 -> 162974.92 | J12: 59136.287 | K12: =H12*0.08 -> 70320.713 | L12: =K12-J12 -> 11184.427 | M12: 10293.398 | N12: =0.025*F12 -> 13475.7 | O12: =N12-M12 -> 3182.3021 | P12: =K12*12 -> 843848.56 | Q12: =N12*12 -> 161708.4
A13: 6 | B13: DR FRANCIS NDUM OJIE | C13: AD, TRAINING & IC./SA TO DG | D13: 15(8) | E13: 601396.83 | F13: 445995.83 | G13: 276599.67 | H13: =F13+G13 -> 722595.5 | I13: =H13-E13 -> 121198.67 | J13: 46569.447 | K13: =H13*0.08 -> 57807.64 | L13: =K13-J13 -> 11238.193 | M13: 7859.6313 | N13: =0.025*F13 -> 11149.896 | O13: =N13-M13 -> 3290.2646 | P13: =K13*12 -> 693691.68 | Q13: =N13*12 -> 133798.75
A14: 7 | B14: ALI ABDULLAHI | C14: CHIEF ICT OFFICER | D14: 14(11) | E14: 484373.75 | F14: 366417.5 | G14: 223239.5 | H14: =F14+G14 -> 589657 | I14: =H14-E14 -> 105283.25 | J14: 38749.9 | K14: =H14*0.08 -> 47172.56 | L14: =K14-J14 -> 8422.66 | O14: =N14-M14 -> 0 | P14: =K14*12 -> 566070.72 | Q14: =N14*12 -> 0
A15: 8 | B15: EMILY EKHIDE | C15: SENIOR RESEARCH FELLOW | D15: 15(8) | E15: 601396.83 | F15: ='[18] FGN 2024 MGT Monthly'!$I$43 -> 445995.83 | G15: 276599.67 | H15: =F15+G15 -> 722595.5 | I15: =H15-E15 -> 121198.67 | J15: 46569.45 | K15: =H15*0.08 -> 57807.64 | L15: =K15-J15 -> 11238.19 | O15: =N15-M15 -> 0 | P15: =K15*12 -> 693691.68 | Q15: =N15*12 -> 0
A16: 9 | B16: DORIS DAKDA AARON | C16: RESEARCH FELLOW I | D16: 14(9) | E16: 456622.25 | F16: 347715.92 | G16: 210449.33 | H16: =F16+G16 -> 558165.25 | I16: =H16-E16 -> 101543 | J16: 35419.72 | K16: =H16*0.08 -> 44653.22 | L16: =K16-J16 -> 9233.5 | O16: =N16-M16 -> 0 | P16: =K16*12 -> 535838.64 | Q16: =N16*12 -> 0
A17: 10 | B17: ABDULSALAM S. MUSTAPHA | C17: ASST. DIRECTOR ICT | D17: 15(7) | E17: 582118.08 | F17: 432981.08 | G17: 267732.83 | H17: =F17+G17 -> 700713.92 | I17: =H17-E17 -> 118595.83 | J17: 46569.45 | K17: =H17*0.08 -> 56057.113 | L17: =K17-J17 -> 9487.6633 | O17: =N17-M17 -> 0 | P17: =K17*12 -> 672685.36 | Q17: =N17*12 -> 0
A18: 11 | B18: PERCY TERFA GBAHABO | C18: HEAD, NILDS LIAISON OFFICE | D18: 13(11) | E18: 441804.92 | F18: 337730.83 | G18: 203620.5 | H18: =F18+G18 -> 541351.33 | I18: =H18-E18 -> 99546.417 | J18: 34313.273 | K18: =H18*0.08 -> 43308.107 | L18: =K18-J18 -> 8994.8333 | O18: =N18-M18 -> 0 | P18: =K18*12 -> 519697.28 | Q18: =N18*12 -> 0
A19: 12 | B19: HASSANA AHMED IBRAHIM | C19: PA- TO DG | D19: 13 (10) | E19: 428915.92 | F19: 329044.92 | G19: 197680.17 | H19: =F19+G19 -> 526725.08 | I19: =H19-E19 -> 97809.167 | J19: 33282.153 | K19: =H19*0.08 -> 42138.007 | L19: =K19-J19 -> 8855.8533 | M19: 5607.1771 | N19: =0.025*F19 -> 8226.1229 | O19: =N19-M19 -> 2618.9458 | P19: =K19*12 -> 505656.08 | Q19: =N19*12 -> 98713.475
A20: 13 | B20: IKIP LEBO | C20: ASST CHIEF PROC. OFFICER | D20: 13 (8) | E20: 403138 | F20: 311673.25 | G20: 185799.5 | H20: =F20+G20 -> 497472.75 | I20: =H20-E20 -> 94334.75 | J20: 31219.913 | K20: =H20*0.08 -> 39797.82 | L20: =K20-J20 -> 8577.9067 | M20: 5967.3062 | N20: =0.025*F20 -> 7791.8313 | O20: =N20-M20 -> 1824.525 | P20: =K20*12 -> 477573.84 | Q20: =N20*12 -> 93501.975
A21: 14 | B21: ALABI ADESINA MUHYDEEN | C21: HEAD, NILDS LIAISON OFFICE | D21: 13 (8) | E21: 403138 | F21: 311673.25 | G21: 185799.5 | H21: =F21+G21 -> 497472.75 | I21: =H21-E21 -> 94334.75 | J21: 31219.913 | K21: =H21*0.08 -> 39797.82 | L21: =K21-J21 -> 8577.9067 | O21: =N21-M21 -> 0 | P21: =K21*12 -> 477573.84 | Q21: =N21*12 -> 0
A22: 15 | B22: BASSEY NSONGURUA UDOFIA | C22: PRINC.CONF SEC/PPS | D22: 12(11) | E22: 402278 | F22: ='[18] FGN 2024 MGT Monthly'!$L$40 -> 311094.42 | G22: 185402.75 | H22: =F22+G22 -> 496497.17 | I22: =H22-E22 -> 94219.167 | J22: 31206.92 | K22: =H22*0.08 -> 39719.773 | L22: =K22-J22 -> 8512.8533 | M22: 5257.5625 | N22: =0.025*F22 -> 7777.3604 | O22: =N22-M22 -> 2519.7979 | P22: =K22*12 -> 476637.28 | Q22: =N22*12 -> 93328.325
A23: 16 | B23: ADUGBA RICHARD TERSEER | C23: PRINCIPAL INFO. OFFICER | D23: 12(10) | E23: 390086.5 | F23: 302878.67 | G23: 179784 | H23: =F23+G23 -> 482662.67 | I23: =H23-E23 -> 92576.167 | J23: 30231.613 | K23: =H23*0.08 -> 38613.013 | L23: =K23-J23 -> 8381.4 | N23: =0.025*F23 -> 7571.9667 | O23: =N23-M23 -> 7571.9667 | P23: =K23*12 -> 463356.16 | Q23: =N23*12 -> 90863.6
A24: 17 | B24: LUCKY AGWOM | C24: RESEARCH ASSISTANT | D24: 12(8) | E24: 365704 | F24: 286447.08 | G24: 168546.5 | H24: =F24+G24 -> 454993.58 | I24: =H24-E24 -> 89289.583 | J24: 28281 | K24: =H24*0.08 -> 36399.487 | L24: =K24-J24 -> 8118.4867 | O24: =N24-M24 -> 0 | P24: =K24*12 -> 436793.84 | Q24: =N24*12 -> 0
A25: 18 | B25: IDRIS IBRAHIM | C25: PRINCIPAL RESEARCH OFFICER | D25: 12(8) | E25: 365704 | F25: 286447.08 | G25: 168546.5 | H25: =F25+G25 -> 454993.58 | I25: =H25-E25 -> 89289.583 | J25: 28281 | K25: =H25*0.08 -> 36399.487 | L25: =K25-J25 -> 8118.4867 | O25: =N25-M25 -> 0 | P25: =K25*12 -> 436793.84 | Q25: =N25*12 -> 0
A26: 19 | B26: FARUQ ATOFARATI | C26: PA (SPECIAL DUTIES) TO DG | D26: 10(7) | E26: 293029.67 | F26: 240874.58 | G26: 140266.08 | H26: =F26+G26 -> 381140.67 | I26: =H26-E26 -> 88111 | J26: 23442.373 | K26: =H26*0.08 -> 30491.253 | L26: =K26-J26 -> 7048.88 | O26: =N26-M26 -> 0 | P26: =K26*12 -> 365895.04 | Q26: =N26*12 -> 0
A27: 20 | B27: RASHEEDAT DAIBU | C27: SENIOR INFO. OFFICER | D27: 10(8) | E27: 300965.58 | F27: 240874.58 | G27: 140266.08 | H27: =F27+G27 -> 381140.67 | I27: =H27-E27 -> 80175.083 | J27: 23442.373 | K27: =H27*0.08 -> 30491.253 | L27: =K27-J27 -> 7048.88 | N27: =0.025*F27 -> 6021.8646 | O27: =N27-M27 -> 6021.8646 | P27: =K27*12 -> 365895.04 | Q27: =N27*12 -> 72262.375
A28: 21 | B28: ELIZABETH OGECHUKWU ONYEAKU | C28: ICT OFFICER | D28: 9(10) | E28: 277798 | F28: 227615.75 | G28: 127704.92 | H28: =F28+G28 -> 355320.67 | I28: =H28-E28 -> 77522.667 | J28: 21638.533 | K28: =H28*0.08 -> 28425.653 | L28: =K28-J28 -> 6787.12 | N28: =0.025*F28 -> 5690.3938 | O28: =N28-M28 -> 5690.3938 | P28: =K28*12 -> 341107.84 | Q28: =N28*12 -> 68284.725
A29: 22 | B29: VICTOR ASUKWO | C29: ICT OFFICER | D29: 9(10) | E29: 277798 | F29: 227615.75 | G29: 127704.92 | H29: =F29+G29 -> 355320.67 | I29: =H29-E29 -> 77522.667 | J29: 21638.533 | K29: =H29*0.08 -> 28425.653 | L29: =K29-J29 -> 6787.12 | N29: =0.025*F29 -> 5690.3938 | O29: =N29-M29 -> 5690.3938 | P29: =K29*12 -> 341107.84 | Q29: =N29*12 -> 68284.725
A30: 23 | B30: NNANDI LIVINUS ATURE | C30: RESEARCH ASSISTANT | D30: 9(10) | E30: 277798 | F30: 227615.75 | G30: 127704.92 | H30: =F30+G30 -> 355320.67 | I30: =H30-E30 -> 77522.667 | J30: 21638.533 | K30: =H30*0.08 -> 28425.653 | L30: =K30-J30 -> 6787.12 | O30: =N30-M30 -> 0 | P30: =K30*12 -> 341107.84 | Q30: =N30*12 -> 0
A31: 24 | B31: ABDULRAHMAN A SULAIMAN | C31: STORE OFFICER | D31: 9(9) | E31: 270481.67 | F31: 222674.58 | G31: 124341.58 | H31: =F31+G31 -> 347016.17 | I31: =H31-E31 -> 76534.5 | J31: 21053.227 | K31: =H31*0.08 -> 27761.293 | L31: =K31-J31 -> 6708.0667 | O31: =N31-M31 -> 0 | P31: =K31*12 -> 333135.52 | Q31: =N31*12 -> 0
A32: 25 | B32: DARE SHEU MAGBON | C32: ADMINISTRATION OFFICER | D32: 9(8) | E32: 263165.33 | F32: 217733.42 | G32: 120978.25 | H32: =F32+G32 -> 338711.67 | I32: =H32-E32 -> 75546.333 | J32: 20467.92 | K32: =H32*0.08 -> 27096.933 | L32: =K32-J32 -> 6629.0133 | O32: =N32-M32 -> 0 | P32: =K32*12 -> 325163.2 | Q32: =N32*12 -> 0
A33: 26 | B33: ABUBAKAR SULAIMAN SODEEQ | C33: ADMINISTRATION OFFICER | D33: 9(8) | E33: 263165.33 | F33: 217733.42 | G33: 120978.25 | H33: =F33+G33 -> 338711.67 | I33: =H33-E33 -> 75546.333 | J33: 20467.92 | K33: =H33*0.08 -> 27096.933 | L33: =K33-J33 -> 6629.0133 | O33: =N33-M33 -> 0 | P33: =K33*12 -> 325163.2 | Q33: =N33*12 -> 0
A34: 27 | B34: JIMOH ADEBAYO ZAKA | C34: ASST. OFFICER/COMM | D34: 9(10) | E34: 277798 | F34: 227615.75 | G34: 127704.92 | H34: =F34+G34 -> 355320.67 | I34: =H34-E34 -> 77522.667 | J34: 21638.533 | K34: =H34*0.08 -> 28425.653 | L34: =K34-J34 -> 6787.12 | M34: 3653.5 | N34: =0.025*F34 -> 5690.3938 | O34: =N34-M34 -> 2036.8937 | P34: =K34*12 -> 341107.84 | Q34: =N34*12 -> 68284.725
A35: 28 | B35: ABDULMUSHIN TAWFIQ LADAN | C35: ICT OFFICER | D35: 9(8) | E35: 263165.33 | F35: 217733.42 | G35: 120978.25 | H35: =F35+G35 -> 338711.67 | I35: =H35-E35 -> 75546.333 | J35: 20467.92 | K35: =H35*0.08 -> 27096.933 | L35: =K35-J35 -> 6629.0133 | O35: =N35-M35 -> 0 | P35: =K35*12 -> 325163.2 | Q35: =N35*12 -> 0
A36: 29 | B36: MOHAMMED BELLO | C36: PROTOCOL ASSISTANT | D36: 9(8) | E36: 263165.33 | F36: 217733.42 | G36: 120978.25 | H36: =F36+G36 -> 338711.67 | I36: =H36-E36 -> 75546.333 | J36: 20467.92 | K36: =H36*0.08 -> 27096.933 | L36: =K36-J36 -> 6629.0133 | O36: =N36-M36 -> 0 | P36: =K36*12 -> 325163.2 | Q36: =N36*12 -> 0
A37: 30 | B37: HARUNA JIBRIL AMEH | C37: ASST. ADMIN. OFFICER | D37: 8(9) | E37: 230631.92 | F37: 196364.42 | G37: 105546.33 | H37: =F37+G37 -> 301910.75 | I37: =H37-E37 -> 71278.833 | J37: 17956.78 | K37: =H37*0.08 -> 24152.86 | L37: =K37-J37 -> 6196.08 | N37: =0.025*F37 -> 4909.1104 | O37: =N37-M37 -> 4909.1104 | P37: =K37*12 -> 289834.32 | Q37: =N37*12 -> 58909.325
A38: 31 | B38: RAMATU IBRAHIM ABDULRAHEEM | C38: INFORMATION OFFICER | D38: 8(8) | E38: 224459.75 | F38: 192179.42 | G38: 102721.42 | H38: =F38+G38 -> 294900.83 | I38: =H38-E38 -> 70441.083 | J38: 17463.007 | K38: =H38*0.08 -> 23592.067 | L38: =K38-J38 -> 6129.06 | N38: =0.025*F38 -> 4804.4854 | O38: =N38-M38 -> 4804.4854 | P38: =K38*12 -> 283104.8 | Q38: =N38*12 -> 57653.825
B39: TOTAL | C39: 31 | E39: =SUM(E8:E38) -> 14073004 | F39: =SUM(F8:F38) -> 10680274 | G39: =SUM(G8:G38) -> 6613927.2 | H39: =SUM(H8:H38) -> 17294201 | I39: =SUM(I8:I38) -> 3221197.1 | J39: =SUM(J8:J38) -> 914813.32 | K39: =SUM(K8:K38) -> 1153420.6 | L39: =SUM(L8:L38) -> 238607.23 | ... Q39: =SUM(Q8:Q38) -> 1231995.1
B41: INTERNAL AUDIT
A42: 1 | B42: OSANAIYE DAVID AKINYEMI | C42: DIRECTOR INTERNAL AUDIT | D42: 17(9) | E42: 1435720 | F42: 1086777.1 | G42: 660329.33 | H42: =F42+G42 -> 1747106.4 | I42: =H42-E42 -> 311386.42 | J42: 114857.6 | K42: =H42*0.08 -> 139768.51 | L42: =K42-J42 -> 24910.913 | O42: =N42-M42 -> 0 | P42: =K42*12 -> 1677222.2
A43: 2 | B43: JAMILA ABDUL | C43: SENIOR INTERNAL AUDITOR | D43: 10(8) | E43: 300965.58 | F43: 240874.58 | G43: 140266.08 | H43: =F43+G43 -> 381140.67 | I43: =H43-E43 -> 80175.083 | J43: 23442.373 | K43: =H43*0.08 -> 30491.253 | L43: =K43-J43 -> 7048.88 | N43: =0.025*F43 -> 6021.8646 | O43: =N43-M43 -> 6021.8646 | P43: =K43*12 -> 365895.04
A44: 3 | B44: IJEOMA EWELUKWA | C44: SENIOR INTERNAL AUDITOR | D44: 10(9) | E44: 308901.5 | F44: 246171.17 | G44: 143964.67 | H44: =F44+G44 -> 390135.83 | I44: =H44-E44 -> 81234.333 | J44: 24077.247 | K44: =H44*0.08 -> 31210.867 | L44: =K44-J44 -> 7133.62 | O44: =N44-M44 -> 0 | P44: =K44*12 -> 374530.4
A45: 4 | B45: YUSUF YUSUF DAYYABU | C45: INERNAL AUDIT OFFICER | D45: 9(8) | E45: 263165.33 | F45: 217733.42 | G45: 120978.25 | H45: =F45+G45 -> 338711.67 | I45: =H45-E45 -> 75546.333 | J45: 20467.92 | K45: =H45*0.08 -> 27096.933 | L45: =K45-J45 -> 6629.0133 | N45: =0.025*F45 -> 5443.3354 | O45: =N45-M45 -> 5443.3354 | P45: =K45*12 -> 325163.2
C46: 4 | E46: =SUM(E42:E45) -> 2308752.4 | F46: =SUM(F42:F45) -> 1791556.2 | G46: =SUM(G42:G45) -> 1065538.3 | H46: =SUM(H42:H45) -> 2857094.6 | I46: =SUM(I42:I45) -> 548342.17 | J46: =SUM(J42:J45) -> 182845.14 | K46: =SUM(K42:K45) -> 228567.57 | L46: =SUM(L42:L45) -> 45722.427 | ... Q46: =SUM(Q42:Q45) -> 0
B48: LEG. SUPPORT SEVICES
A49: 1 | B49: BETHEL UZOMA IHUGBA | C49: DEPUTY DIRECTOR, LEGAL RESEARCH | D49: 16(9) | E49: 762373.17 | F49: 554669.5 | G49: 350637.25 | H49: =F49+G49 -> 905306.75 | I49: =H49-E49 -> 142933.58 | J49: 59136.287 | K49: =H49*0.08 -> 72424.54 | L49: =K49-J49 -> 13288.253 | O49: =N49-M49 -> 0 | P49: =K49*12 -> 869094.48
A50: 2 | B50: OGUCHE SAMUEL | C50: SNR RESEARCH FELLOW | D50: 15(9) | E50: 620675.58 | F50: 459010.5 | G50: 285466.5 | H50: =F50+G50 -> 744477 | I50: =H50-E50 -> 123801.42 | J50: 49654.047 | K50: =H50*0.08 -> 59558.16 | L50: =K50-J50 -> 9904.1133 | O50: =N50-M50 -> 0 | P50: =K50*12 -> 714697.92
A51: 3 | B51: IBRAHIM USMAN | C51: SNR RESEARCH FELLOW | D51: 15(9) | E51: 620675.58 | F51: 459010.5 | G51: 285466.5 | H51: =F51+G51 -> 744477 | I51: =H51-E51 -> 123801.42 | J51: 49654.047 | K51: =H51*0.08 -> 59558.16 | L51: =K51-J51 -> 9904.1133 | M51: 8380.2271 | N51: =0.025*F51 -> 11475.263 | O51: =N51-M51 -> 3095.0354 | P51: =K51*12 -> 714697.92 | Q51: =N51*12 -> 137703.15
A52: 4 | B52: DR MOHAMMED O. AMALI | C52: SNR RESEARCH FELLOW | D52: 15(8) | E52: 601396.83 | F52: 445995.83 | G52: 276599.67 | H52: =F52+G52 -> 722595.5 | I52: =H52-E52 -> 121198.67 | J52: 46569.447 | K52: =H52*0.08 -> 57807.64 | L52: =K52-J52 -> 11238.193 | O52: =N52-M52 -> 0 | P52: =K52*12 -> 693691.68
A53: 5 | B53: YAHAYA SHAMSU | C53: SNR RESEARCH FELLOW | D53: 15(7) | E53: 582118.08 | F53: 432981.08 | G53: 267732.83 | H53: =F53+G53 -> 700713.92 | I53: =H53-E53 -> 118595.83 | J53: 46569.45 | K53: =H53*0.08 -> 56057.113 | L53: =K53-J53 -> 9487.6633 | O53: =N53-M53 -> 0 | P53: =K53*12 -> 672685.36
A54: 6 | B54: BILKIS S. LAWAL-GAMBARI | C54: RESEARCH OFFICER | D54: 10(9) | E54: 308901.5 | F54: 246171.17 | G54: 143964.67 | H54: =F54+G54 -> 390135.83 | I54: =H54-E54 -> 81234.333 | J54: 24077.247 | K54: =H54*0.08 -> 31210.867 | L54: =K54-J54 -> 7133.62 | O54: =N54-M54 -> 0 | P54: =K54*12 -> 374530.4
A55: 7 | B55: ZAINAB AKINDE | C55: RESEARCH OFFICER | D55: 9(9) | E55: 270481.67 | F55: 222674.58 | G55: 124341.58 | H55: =F55+G55 -> 347016.17 | I55: =H55-E55 -> 76534.5 | J55: 21053.227 | K55: =H55*0.08 -> 27761.293 | L55: =K55-J55 -> 6708.0667 | O55: =N55-M55 -> 0 | P55: =K55*12 -> 333135.52
A56: 8 | B56: GUNAT NANSAK MARK | C56: RESEARCH OFFICER | D56: 9(9) | E56: 270481.67 | F56: 222674.58 | G56: 124341.58 | H56: =F56+G56 -> 347016.17 | I56: =H56-E56 -> 76534.5 | J56: 21053.227 | K56: =H56*0.08 -> 27761.293 | L56: =K56-J56 -> 6708.0667 | O56: =N56-M56 -> 0 | P56: =K56*12 -> 333135.52
B57: TOTAL | C57: 8 | E57: =SUM(E49:E56) -> 4037104.1 | F57: =SUM(F49:F56) -> 3043187.8 | G57: =SUM(G49:G56) -> 1858550.6 | H57: =SUM(H49:H56) -> 4901738.3 | I57: =SUM(I49:I56) -> 864634.25 | J57: =SUM(J49:J56) -> 317766.98 | K57: =SUM(K49:K56) -> 392139.07 | L57: =SUM(L49:L56) -> 74372.09 | ... Q57: =SUM(Q49:Q56) -> 137703.15
B59: LEGAL SERVICES
A60: 1 | B60: DR SHUAIBU DANWANKA | C60: DIRECTOR LEGAL SERVICES | D60: 17(9) | E60: 1435720 | F60: 1086777.1 | G60: 660329.33 | H60: =F60+G60 -> 1747106.4 | I60: =H60-E60 -> 311386.42 | J60: 114857.6 | K60: =H60*0.08 -> 139768.51 | L60: =K60-J60 -> 24910.913 | O60: =N60-M60 -> 0 | P60: =K60*12 -> 1677222.2
A61: 2 | B61: ABDULSALAM BAKO | C61: MANAGER, LEGAL SERVICES | D61: 15 (9) | E61: 620675.58 | F61: 459010.5 | G61: 285466.5 | H61: =F61+G61 -> 744477 | I61: =H61-E61 -> 123801.42 | J61: 49654.047 | K61: =H61*0.08 -> 59558.16 | L61: =K61-J61 -> 9904.1133 | O61: =N61-M61 -> 0 | P61: =K61*12 -> 714697.92
B62: TOTAL | C62: 2 | E62: =SUM(E60:E61) -> 2056395.6 | F62: =SUM(F60:F61) -> 1545787.6 | G62: =SUM(G60:G61) -> 945795.83 | H62: =SUM(H60:H61) -> 2491583.4 | I62: =SUM(I60:I61) -> 435187.83 | J62: =SUM(J60:J61) -> 164511.65 | K62: =SUM(K60:K61) -> 199326.67 | L62: =SUM(L60:L61) -> 34815.027 | ... Q62: =SUM(Q60:Q61) -> 0
B64: DEMOCRACY & GOVERNANCE
A65: 1 | B65: NGARA CHRISTOPHER OCHANJA | C65: DEP DIR DEM & GOVERNANCE | D65: 16(9) | E65: 762373.17 | F65: 554669.5 | G65: 350637.25 | H65: =F65+G65 -> 905306.75 | I65: =H65-E65 -> 142933.58 | J65: 60989.853 | K65: =H65*0.08 -> 72424.54 | L65: =K65-J65 -> 11434.687 | M65: 10293.398 | N65: =0.025*F65 -> 13866.737 | O65: =N65-M65 -> 3573.3396 | P65: =K65*12 -> 869094.48 | Q65: =N65*12 -> 166400.85
A66: 2 | B66: EJALONIBU GANIYU LAYI | C66: RESEARCH FELLOW 1 | D66: 14(9) | E66: 456622.25 | F66: 347715.92 | G66: 210449.33 | H66: =F66+G66 -> 558165.25 | I66: =H66-E66 -> 101543 | J66: 35419.72 | K66: =H66*0.08 -> 44653.22 | L66: =K66-J66 -> 9233.5 | O66: =N66-M66 -> 0 | P66: =K66*12 -> 535838.64
A67: 3 | B67: UDEFUNA NNADOZIE PATRICK | C67: RESEARCH OFFICER | D67: 12(9) | E67: 377895.17 | F67: 294662.92 | G67: 174165.25 | H67: =F67+G67 -> 468828.17 | I67: =H67-E67 -> 90933 | J67: 29256.307 | K67: =H67*0.08 -> 37506.253 | L67: =K67-J67 -> 8249.9467 | O67: =N67-M67 -> 0 | P67: =K67*12 -> 450075.04
A68: 4 | B68: SHAFIU YAHYA MIKAIL | C68: PRINCIPAL RESEARCH OFFICER | D68: 12(9) | E68: 377895.17 | F68: 294662.92 | G68: 174165.25 | H68: =F68+G68 -> 468828.17 | I68: =H68-E68 -> 90933 | J68: 29256.307 | K68: =H68*0.08 -> 37506.253 | L68: =K68-J68 -> 8249.9467 | O68: =N68-M68 -> 0 | P68: =K68*12 -> 450075.04
A69: 5 | B69: HASSAN YERIMA | C69: PRINCIPAL RESEARCH OFFICER | D69: 12(9) | E69: 377895.17 | F69: 294662.92 | G69: 174165.25 | H69: =F69+G69 -> 468828.17 | I69: =H69-E69 -> 90933 | J69: 29256.307 | K69: =H69*0.08 -> 37506.253 | L69: =K69-J69 -> 8249.9467 | O69: =N69-M69 -> 0 | P69: =K69*12 -> 450075.04
A70: 6 | B70: HAUWA PATE SADIQ | C70: PRINCIPAL PROGRAMME OFFICER | D70: 12(10) | E70: 390086.5 | F70: 302878.67 | G70: 179784 | H70: =F70+G70 -> 482662.67 | I70: =H70-E70 -> 92576.167 | J70: 30231.613 | K70: =H70*0.08 -> 38613.013 | L70: =K70-J70 -> 8381.4 | O70: =N70-M70 -> 0 | P70: =K70*12 -> 463356.16
A71: 7 | B71: KOLAPO Q. ABAYOMI | C71: RESEARCH OFFICER | D71: 10(9) | E71: 308901.5 | F71: 246171.17 | G71: 143964.67 | H71: =F71+G71 -> 390135.83 | I71: =H71-E71 -> 81234.333 | J71: 24077.247 | K71: =H71*0.08 -> 31210.867 | L71: =K71-J71 -> 7133.62 | N71: =0.025*F71 -> 6154.2792 | O71: =N71-M71 -> 6154.2792 | P71: =K71*12 -> 374530.4
B72: TOTAL | C72: 7 | E72: =SUM(E65:E71) -> 3051668.9 | F72: =SUM(F65:F71) -> 2335424 | G72: =SUM(G65:G71) -> 1407331 | H72: =SUM(H65:H71) -> 3742755 | I72: =SUM(I65:I71) -> 691086.08 | J72: =SUM(J65:J71) -> 238487.35 | K72: =SUM(K65:K71) -> 299420.4 | L72: =SUM(L65:L71) -> 60933.047 | ... Q72: =SUM(Q65:Q71) -> 166400.85
B74: DEPARTMENT OF STUDIES
A75: 1 | B75: DR ASIMIYU G. ABIOLA | C75: DIRECTOR POST GRADUATE | D75: 17(9) | E75: 1435720 | F75: 1086777.1 | G75: 660329.33 | H75: =F75+G75 -> 1747106.4 | I75: =H75-E75 -> 311386.42 | J75: 114857.6 | K75: =H75*0.08 -> 139768.51 | L75: =K75-J75 -> 24910.913 | O75: =N75-M75 -> 0 | P75: =K75*12 -> 1677222.2
A76: 2 | B76: DR. HADIZA SAIDU | C76: ASSISTANT DIRECTOR | D76: 15(7) | E76: 582118.08 | F76: 445995.83 | G76: 276599.67 | H76: =F76+G76 -> 722595.5 | I76: =H76-E76 -> 140477.42 | J76: 46569.447 | K76: =H76*0.08 -> 57807.64 | L76: =K76-J76 -> 11238.193 | O76: =N76-M76 -> 0 | P76: =K76*12 -> 693691.68
A77: 3 | B77: ANTHONY EDET | C77: CHIEF PROGRAMMES OFFICER | D77: 14(10) | E77: 470498 | F77: 357066.67 | G77: 216844.42 | H77: =F77+G77 -> 573911.08 | I77: =H77-E77 -> 103413.08 | J77: 36529.78 | K77: =H77*0.08 -> 45912.887 | L77: =K77-J77 -> 9383.1067 | M77: 6154.3229 | N77: =0.025*F77 -> 8926.6667 | O77: =N77-M77 -> 2772.3438 | P77: =K77*12 -> 550954.64 | Q77: =N77*12 -> 107120
A78: 4 | B78: IGWE STACY | C78: PRINC. PROGRAMME OFFICER | D78: 12(8) | E78: 365703.83 | F78: 286447.08 | G78: 168546.5 | H78: =F78+G78 -> 454993.58 | I78: =H78-E78 -> 89289.75 | J78: 28281 | K78: =H78*0.08 -> 36399.487 | L78: =K78-J78 -> 8118.4867 | O78: =N78-M78 -> 0 | P78: =K78*12 -> 436793.84
A79: 5 | B79: OLANIYAN TAIWO ABINBOLA | C79: PROGRAMME OFFICER | D79: 9(8) | E79: 263165.33 | F79: 222674.58 | G79: 124341.58 | H79: =F79+G79 -> 347016.17 | I79: =H79-E79 -> 83850.833 | J79: 21053.227 | K79: =H79*0.08 -> 27761.293 | L79: =K79-J79 -> 6708.0667 | N79: =0.025*F79 -> 5566.8646 | O79: =N79-M79 -> 5566.8646 | P79: =K79*12 -> 333135.52
A80: 6 | B80: AMINAT JUMOKE SULAIMON | C80: AST. PROGRAMME OFFICER | D80: 8(9) | E80: 230631.92 | F80: 196364.42 | G80: 105546.33 | H80: =F80+G80 -> 301910.75 | I80: =H80-E80 -> 71278.833 | J80: 17956.78 | K80: =H80*0.08 -> 24152.86 | L80: =K80-J80 -> 6196.08 | O80: =N80-M80 -> 0 | P80: =K80*12 -> 289834.32
B81: TOTAL | C81: 6 | E81: =SUM(E75:E80) -> 3347837.2 | F81: =SUM(F75:F80) -> 2595325.7 | G81: =SUM(G75:G80) -> 1552207.8 | H81: =SUM(H75:H80) -> 4147533.5 | I81: =SUM(I75:I80) -> 799696.33 | J81: =SUM(J75:J80) -> 265247.83 | K81: =SUM(K75:K80) -> 331802.68 | L81: =SUM(L75:L80) -> 66554.847 | ... Q81: =SUM(Q75:Q80) -> 107120
B83: ECON. DEV. & SOC. RESEARCH
A84: 1 | B84: DR AUGUSTINE C. OSIGWE | C84: SNR RESEARCH FELLOW | D84: 17(7) | E84: ='[3]Annual & Monthly'!$H$44 -> 1352042.7 | F84: 1025768.3 | G84: 621843.67 | H84: =F84+G84 -> 1647612 | I84: =H84-E84 -> 295569.33 | J84: 114857.6 | K84: =H84*0.08 -> 131808.96 | L84: =K84-J84 -> 16951.36 | M84: 18254.975 | N84: =0.025*F84 -> 25644.208 | O84: =N84-M84 -> 7389.2333 | P84: =12*K84 -> 1581707.5 | Q84: =N84*12 -> 307730.5
A85: 2 | B85: TERFA WILLIAMS ABRAHAM | C85: DEP. DIRECTOR ECON & SOCIAL RES | D85: 16(7) | E85: 716034 | F85: 523386.5 | G85: 329324.58 | H85: =F85+G85 -> 852711.08 | I85: =H85-E85 -> 136677.08 | J85: 59136.287 | K85: =H85*0.08 -> 68216.887 | L85: =K85-J85 -> 9080.6 | O85: =N85-M85 -> 0 | P85: =12*K85 -> 818602.64
A86: 3 | B86: OMOJU OLUWASOLA EMMANUEL | C86: SNR RESEARCH FELLOW | D86: 15(8) | E86: 601396.83 | F86: 445995.83 | G86: 276599.67 | H86: =F86+G86 -> 722595.5 | I86: =H86-E86 -> 121198.67 | J86: 46569.447 | K86: =H86*0.08 -> 57807.64 | L86: =K86-J86 -> 11238.193 | O86: =N86-M86 -> 0 | P86: =12*K86 -> 693691.68
A87: 4 | B87: IBE EZECHI CYRIACUS | C87: RESEARCH FELLOW 1 | D87: 14(9) | E87: 456622.25 | F87: 347715.92 | G87: 210449.33 | H87: =F87+G87 -> 558165.25 | I87: =H87-E87 -> 101543 | J87: 35344.393 | K87: =H87*0.08 -> 44653.22 | L87: =K87-J87 -> 9308.8267 | O87: =N87-M87 -> 0 | P87: =12*K87 -> 535838.64
A88: 5 | B88: OSIKHEN LEO IGBANOI | C88: RESEARCH FELLOW 1 | D88: 14(9) | E88: 456622.25 | F88: 347716.92 | G88: 210449.33 | H88: =F88+G88 -> 558166.25 | I88: =H88-E88 -> 101544 | J88: 35419.72 | K88: =H88*0.08 -> 44653.3 | L88: =K88-J88 -> 9233.58 | N88: =0.025*F88 -> 8692.9229 | O88: =N88-M88 -> 8692.9229 | P88: =12*K88 -> 535839.6 | Q88: =N88*12 -> 104315.07
A89: 6 | B89: OKUNGBOWA OSARETIN GODSPOWER | C89: RESEARCH FELLOW 1 | D89: 14(8) | E89: 442746.5 | F89: 338365.25 | G89: 204054.25 | H89: =F89+G89 -> 542419.5 | I89: =H89-E89 -> 99673 | J89: 34309.66 | K89: =H89*0.08 -> 43393.56 | L89: =K89-J89 -> 9083.9 | O89: =N89-M89 -> 0 | P89: =12*K89 -> 520722.72
A90: 7 | B90: YUSUF IBRAHIM | C90: PRINCIPAL RESEARCH OFFICER | D90: 12(9) | E90: 377895.17 | F90: 294662.92 | G90: 174165.25 | H90: =F90+G90 -> 468828.17 | I90: =H90-E90 -> 90933 | J90: 29256.307 | K90: =H90*0.08 -> 37506.253 | L90: =K90-J90 -> 8249.9467 | O90: =N90-M90 -> 0 | P90: =12*K90 -> 450075.04
A91: 8 | B91: MUSTAPHA RAFIU AYOBANJI | C91: RESEARCH FELLOW 11 | D91: 13(8) | E91: 403137.92 | F91: 311673.25 | G91: 185799.5 | H91: =F91+G91 -> 497472.75 | I91: =H91-E91 -> 94334.833 | J91: 31219.913 | K91: =H91*0.08 -> 39797.82 | L91: =K91-J91 -> 8577.9067 | M91: 5259.7437 | N91: =0.025*F91 -> 7791.8313 | O91: =N91-M91 -> 2532.0875 | P91: =12*K91 -> 477573.84 | Q91: =N91*12 -> 93501.975
A92: 9 | B92: MARYAM MUSA SADA | C92: ASSIT. RESEARCH OFFICER | D92: 10(9) | E92: 308901.5 | F92: 246171.17 | G92: 143964.67 | H92: =F92+G92 -> 390135.83 | I92: =H92-E92 -> 81234.333 | J92: 24077.247 | K92: =H92*0.08 -> 31210.867 | L92: =K92-J92 -> 7133.62 | O92: =N92-M92 -> 0 | P92: =12*K92 -> 374530.4
A93: 10 | B93: CHARITY EZENWAJIOBI | C93: REASEARCH. ASST. | D93: 8(10) | E93: 236804.08 | F93: 200549.42 | G93: 108371.25 | H93: =F93+G93 -> 308920.67 | I93: =H93-E93 -> 72116.583 | J93: 18450.553 | K93: =H93*0.08 -> 24713.653 | L93: =K93-J93 -> 6263.1 | N93: =0.025*F93 -> 5013.7354 | O93: =N93-M93 -> 5013.7354 | P93: =12*K93 -> 296563.84
B94: TOTAL | C94: 10 | E94: =SUM(E84:E93) -> 5352203.2 | F94: =SUM(F84:F93) -> 4082005.5 | G94: =SUM(G84:G93) -> 2465021.5 | H94: =SUM(H84:H93) -> 6547027 | I94: =SUM(I84:I93) -> 1194823.8 | J94: =SUM(J84:J93) -> 428641.13 | K94: =SUM(K84:K93) -> 523762.16 | L94: =SUM(L84:L93) -> 95121.033 | ... Q94: =SUM(Q84:Q93) -> 505547.55
B96: TRAINING & INT''L COOP
A97: 1 | B97: AKINSANMI ADEJOKE OLUKEMI | C97: Ag. DIR. TRAINING & IC | D97: 17(8) | E97: 1393881.3 | F97: 1056272.8 | G97: 641086.5 | H97: =F97+G97 -> 1697359.3 | I97: =H97-E97 -> 303478 | J97: 114857.6 | K97: =H97*0.08 -> 135788.75 | L97: =K97-J97 -> 20931.147 | M97: 18254.975 | N97: =0.025*F97 -> 26406.821 | O97: =N97-M97 -> 8151.8458 | P97: =12*K97 -> 1629465 | Q97: =N97*12 -> 316881.85
A98: 2 | B98: MOHAMMED R. ADAMU | C98: CHIEF TRAINING OFFICER | D98: 14(10) | E98: 470498 | F98: 357066.67 | G98: 216844.42 | H98: =F98+G98 -> 573911.08 | I98: =H98-E98 -> 103413.08 | J98: 36529.78 | K98: =H98*0.08 -> 45912.887 | L98: =K98-J98 -> 9383.1067 | O98: =N98-M98 -> 0 | P98: =12*K98 -> 550954.64 | Q98: =N98*12 -> 0
A99: 3 | B99: EROMOSELE OMONIGBO | C99: ASSIST. CHIEF PERSONNEL OFFICER | D99: 13(8) | E99: 403137.92 | F99: 311673.25 | G99: 185799.5 | H99: =F99+G99 -> 497472.75 | I99: =H99-E99 -> 94334.833 | J99: 31219.91 | K99: =H99*0.08 -> 39797.82 | L99: =K99-J99 -> 8577.91 | M99: 5967.3062 | N99: =0.025*F99 -> 7791.8313 | O99: =N99-M99 -> 1824.525 | P99: =12*K99 -> 477573.84 | Q99: =N99*12 -> 93501.975
A100: 4 | B100: OKECHUKWU UCHENNA HULDA | C100: PRINCIPALTRAINING OFFICER | D100: 12(10) | E100: 390086.5 | F100: 302878.67 | G100: 179784 | H100: =F100+G100 -> 482662.67 | I100: =H100-E100 -> 92576.167 | J100: 30231.613 | K100: =H100*0.08 -> 38613.013 | L100: =K100-J100 -> 8381.4 | O100: =N100-M100 -> 0 | P100: =12*K100 -> 463356.16 | Q100: =N100*12 -> 0
A101: 5 | B101: TASSNEEM IBRAHIM | C101: SENIOR PROGRAMME OFFICER | D101: 10(9) | E101: 308901.5 | F101: 246171.17 | G101: 143964.67 | H101: =F101+G101 -> 390135.83 | I101: =H101-E101 -> 81234.333 | J101: 24077.247 | K101: =H101*0.08 -> 31210.867 | L101: =K101-J101 -> 7133.62 | O101: =N101-M101 -> 0 | P101: =12*K101 -> 374530.4 | Q101: =N101*12 -> 0
B102: TOTAL | C102: 5 | E102: =SUM(E97:E101) -> 2966505.2 | F102: =SUM(F97:F101) -> 2274062.6 | G102: =SUM(G97:G101) -> 1367479.1 | H102: =SUM(H97:H101) -> 3641541.7 | I102: =SUM(I97:I101) -> 675036.42 | J102: =SUM(J97:J101) -> 236916.15 | K102: =SUM(K97:K101) -> 291323.33 | L102: =SUM(L97:L101) -> 54407.183 | ... Q102: =SUM(Q97:Q101) -> 410383.82
B104: LIBRARY & DOCUMENTATION
A105: 1 | B105: DR MAIMUNA IZAH | C105: INSITUTE LIBRARIAN | D105: 17(9) | E105: 1435720 | F105: 1086777.1 | G105: 660329.33 | H105: =F105+G105 -> 1747106.4 | I105: =H105-E105 -> 311386.42 | J105: 114857.6 | K105: =H105*0.08 -> 139768.51 | L105: =K105-J105 -> 24910.913 | M105: 0 | O105: =N105-M105 -> 0 | P105: =K105*12 -> 1677222.2
A106: 2 | B106: CATHERINE E. IKOKOH | C106: SNR RESEARCH FELLOW DOCU | D106: 16(9) | E106: 762373.17 | F106: 554669.5 | G106: 350637.25 | H106: =F106+G106 -> 905306.75 | I106: =H106-E106 -> 142933.58 | J106: 60989.853 | K106: =H106*0.08 -> 72424.54 | L106: =K106-J106 -> 11434.687 | M106: 10293.398 | N106: =0.025*F106 -> 13866.737 | O106: =N106-M106 -> 3573.3396 | P106: =K106*12 -> 869094.48 | Q106: =N106*12 -> 166400.85
A107: 3 | B107: ALIYU SANNI ABUBAKAR | C107: RESEARCH FELLOW 11 DATA & DOCU | D107: 13(11) | E107: 441804.92 | F107: 337730.83 | G107: 203620.5 | H107: =F107+G107 -> 541351.33 | I107: =H107-E107 -> 99546.417 | J107: 35344.393 | K107: =H107*0.08 -> 43308.107 | L107: =K107-J107 -> 7963.7133 | M107: 5954.6104 | N107: =0.025*F107 -> 8443.2708 | O107: =N107-M107 -> 2488.6604 | P107: =K107*12 -> 519697.28 | Q107: =N107*12 -> 101319.25
A108: 4 | B108: CHINAKO N. ASOGWA | C108: RESEARCH FELLOW 11 DATA & DOCU | D108: 14(7) | E108: 441804.92 | F108: 338365.25 | G108: 204054.25 | H108: =F108+G108 -> 542419.5 | I108: =H108-E108 -> 100614.58 | J108: 35344.393 | K108: =H108*0.08 -> 43393.56 | L108: =K108-J108 -> 8049.1667 | O108: =N108-M108 -> 0 | P108: =K108*12 -> 520722.72
...

Sheet Sum 
A2: S/N | B2: DG'S OFFICE
A3: 1 | B3: PROF. ABUBAKAR O. SULAIMAN | C3: CONSOL | D3: 1971137.1
A4: 2 | B4: RAHEEM USMAN AYIGORO | C4: 16 (9) | D4: 905306.75
A5: 3 | B5: MARIAM MOHAMMED BELLO | C5: 16 (9) | D5: 905306.75
A6: 4 | B6: DR IKEME ARTHUR J.O | C6: 16 (9) | D6: 905306.75
A7: 5 | B7: ANDRAWUS MUSA | C7: 16(9) | D7: 905306.75
A8: 6 | B8: DR FRANCIS NDUM OJIE | C8: 15(9) | D8: 744477
A9: 7 | B9: ALI ABDULLAHI | C9: 15(7) | D9: 700713.92
A10: 8 | B10: EMILY EKHIDE | C10: 15(9) | D10: 744477
A11: 9 | B11: DORIS DAKDA AARON | C11: 14(10) | D11: 573911.08
A12: 10 | B12: ABDULSALAM S. MUSTAPHA | C12: 15(8) | D12: 722595.5
A13: 11 | B13: PERCY TERFA GBAHABO | C13: 14(8) | D13: 542419.5
A14: 12 | B14: HASSANA AHMED IBRAHIM | C14: 13(11) | D14: 541351.33
... A42: 40 | B42: ALIYU GARBA LERE | C42: 8(8) | D42: 294900.83
B43: TOTAL | D43: =SUM(D3:D42) -> 20529918
B45: INTERNAL AUDIT
A46: 1 | B46: OSANAIYE DAVID AKINYEMI | C46: 17(9) | D46: 1747106.4
A47: 2 | B47: EVELYN ETONKE AGAN | C47: 15(8) | D47: 722595.5
A48: 3 | B48: JAMILA ABDUL | C48: 10(9) | D48: 390135.83
A49: 4 | B49: IJEOMA EWELUKWA | C49: 12(8) | D49: 454993.58
A50: 5 | B50: HASSAN ABDULHADI | C50: 9(8) | D50: 338711.67
A51: 6 | B51: YUSUF YUSUF DAYYABU | C51: 9(9) | D51: 347016.17
A52: 7 | B52: UDONSI QUEENETH CHIWENDU | C52: 8(8) | D52: 294900.83
D53: =SUM(D46:D52) -> 4295460
B55: LEG. SUPPORT SEVICES
A56: 1 | B56: BETHEL UZOMA IHUGBA | C56: 17(8) | D56: 1697359.3
A57: 2 | B57: OGUCHE SAMUEL | C57: 15(9) | D57: 744477
A58: 3 | B58: IBRAHIM USMAN | C58: 15(9) | D58: 744477
A59: 4 | B59: DR MOHAMMED O. AMALI | C59: 15(9) | D59: 744477
A60: 5 | B60: YAHAYA SHAMSU | C60: 15(8) | D60: 722595.5
A61: 6 | B61: CHIDEBE MATHEW NWANKWO | C61: 15(8) | D61: 722595.5
A62: 7 | B62: UMAR MUSA PADAH | C62: 12(8) | D62: 454993.58
A63: 8 | B63: BILKIS S. LAWAL-GAMBARI | C63: 10(10) | D63: 399131.17
A64: 9 | B64: UMOH USENOBONG EMMANUEL | C64: 10(8) | D64: 381140.67
A65: 10 | B65: ZAINAB AKINDE | C65: 9(10) | D65: 355320.67
A66: 11 | B66: GUNAT NANSAK MARK | C66: 9(10) | D66: 355320.67
A67: 12 | B67: MANDU ESSIEN NDEM | C67: 9(8) | D67: 338711.67
B68: TOTAL | D68: =SUM(D56:D67) -> 7660599.8
B70: LEGAL SERVICES
A71: 1 | B71: DR SHUAIBU DANWANKA | C71: 17(9) | D71: 1747106.4
A72: 2 | B72: ABDULSALAM BAKO | C72: 15 (9) | D72: 744477
B73: TOTAL | D73: =SUM(D71:D72) -> 2491583.4
B75: DEMOCRACY & GOVERNANCE
A76: 1 | B76: NGARA CHRISTOPHER OCHANJA | C76: 16(9) | D76: 905306.75
A77: 2 | B77: EJALONIBU GANIYU LAYI | C77: 14(10) | D77: 573911.08
A78: 3 | B78: MARTINS SOLOMON UDOM | C78: 13(8) | D78: 497472.75
A79: 4 | B79: ISHAKA DELE | C79: 13(8) | D79: 497472.75
A80: 5 | B80: UDEFUNA NNADOZIE PATRICK | C80: 12(10) | D80: 482662.67
A81: 6 | B81: SHAFIU YAHYA MIKAIL | C81: 12(10) | D81: 482662.67
A82: 7 | B82: HASSAN YERIMA | C82: 12(10) | D82: 482662.67
A83: 8 | B83: HAUWA PATE SADIQ | C83: 13(7) | D83: 482846.58
A84: 9 | B84: OBOT ETIMBUK EMMANUEL | C84: 12(8) | D84: 454993.58
A85: 10 | B85: KOLAPO Q. ABAYOMI | C85: 10(10) | D85: 399131.17
A86: 11 | B86: SALIHU SHAMSUDEEN OPEYEMI | C86: 9(8) | D86: 338711.67
B87: TOTAL | D87: =SUM(D76:D86) -> 5597834.3
B89: DEPARTMENT OF STUDIES
A90: 1 | B90: DR ASIMIYU G. ABIOLA | C90: 17(9) | D90: 1747106.4
A91: 2 | B91: AYOBOLU OLAJIDE OLUFUNSHO | C91: 15(8) | D91: 722595.5
A92: 3 | B92: DR. HADIZA SAIDU | C92: 15(8) | D92: 722595.5
A93: 4 | B93: ANTHONY EDET | C93: 14(11) | D93: 589657
