Workbook

Sheet JANURAY, 2021
B3: STAFF PAYROLL FOR THE MONTH OF JANUARY, 2021
E4: ='[1]FEB 08'!E8/'[1]FEB 08'!M8 -> 0.22 | H4: ='[1]FEB 08'!F8/'[1]FEB 08'!Q8 -> 0.3
B5: STAFF NAME | T5: DEDUCTIONS | Z5: NET SALARY
C6: DESIGNATION | D6: SALARY | E6: BASIC | L6: MOTOR/ | M6: RESEARCH | O6: LEAVE | P6: OUT FIT | Q6: LEGISLATIVE | R6: GROSS | Y6: DECEMBER,2020 | Z6: JANUARY,2021
D7: LEVEL | E7: SALARY | F7: SALARY/ALLOWCE AREARS | G7: RENT | H7: UTILITY | I7: DOMESTIC | J7: ENTERT. | K7: FURNIT. | L7: FUEL | M7: ALLOWANCE | O7: ALLCE | P7: ALLCE | Q7: DUTY ALLCE | R7: SALARY | T7: COOP SOCIETY | U7: COOP. LOAN RECOVERY | V7: NHF DEDUCTION | W7: PAYE | X7: TOTAL
A8: S/N | B8: DG OFFICE | E8: N | H8: N | R8: N | W8: N
A9: 1 | B9: PROF. ABUBAKAR O. SULAIMAN | C9: DIRECTOR GENERAL | D9: CONSOL | E9: 160488.75 | G9: 320977.5 | H9: 48146.63 | I9: 120366.57 | J9: 72219.94 | K9: 0 | L9: 120366.57 | M9: =200000 -> 200000 | O9: 16048.88 | P9: 25000 | Q9: 25235 | R9: =SUM(E9:Q9) -> 1108849.8 | W9: 113176.97 | X9: =T9+U9+V9+W9 -> 113176.97 | Y9: 995672.87 | Z9: =R9-X9 -> 995672.87
A10: 2 | B10: DR ADEYEMI AKEEB FAJINGBESI | C10: DIR. SPECIAL DUTIES, DG OFFICE | D10: 17(9) | E10: 81740.02 | G10: =E10*300% -> 245220.06 | H10: =E10*7.5% -> 6130.5015 | I10: 80244.38 | J10: =E10*50% -> 40870.01 | K10: =E10*350% -> 286090.07 | L10: =E10*100% -> 81740.02 | M10: =150000 -> 150000 | O10: =E10*10% -> 8174.002 | P10: 20000 | Q10: 0 | R10: =SUM(E10:Q10) -> 1000209.1 | T10: 200000 | U10: =59722.22 -> 59722.22 | V10: ='[2]Jan 2021'!$H$38 -> 806.58 | W10: 52776.63 | X10: =SUM(T10:W10) -> 313305.43 | Y10: 685666.71 | Z10: =R10-X10 -> 686903.63
A11: 3 | B11: AKINSANMI ADEJOKE OLUKEMI | C11: AM INFORMATION | D11: 15(9) | E11: 33507.5 | G11: =E11*300% -> 100522.5 | H11: =E11*7.5% -> 2513.0625 | I11: 40122.19 | J11: =E11*50% -> 16753.75 | K11: =E11*350% -> 117276.25 | L11: =E11*100% -> 33507.5 | M11: =100000 -> 100000 | O11: =E11*10% -> 3350.75 | P11: 20000 | Q11: =100000 -> 100000 | R11: =SUM(E11:Q11) -> 567553.5 | T11: =0 -> 0 | U11: 0 | V11: ='[2]Jan 2021'!$H$29 -> 806.58 | W11: 15548.33 | X11: =T11+U11+V11+W11 -> 16354.91 | Y11: 551167.48 | Z11: =R11-X11 -> 551198.59
A12: 4 | B12: DR IKEME ARTHUR J.O | C12: SNR RESEARCH FELLOW | D12: 15(9) | E12: =33507.5 -> 33507.5 | G12: =E12*300% -> 100522.5 | H12: =E12*7.5% -> 2513.0625 | I12: 40122.19 | J12: =E12*50% -> 16753.75 | K12: =E12*350% -> 117276.25 | L12: =E12*100% -> 33507.5 | M12: =100000 -> 100000 | O12: =E12*10% -> 3350.75 | P12: 20000 | Q12: 0 | R12: =SUM(E12:Q12) -> 467553.5 | T12: 50000 | U12: =212642 -> 212642 | V12: ='[3]DECEMBER 2019'!$H$38 -> 837.6875 | W12: 15548.33 | X12: =SUM(T12:W12) -> 279028.02 | Y12: 188525.48 | Z12: =R12-X12 -> 188525.48
A13: 5 | B13: MOSHOOD M. OLALERE | C13: MANAGER ADMIN DG's OFFICE | D13: 15(9) | E13: =33507.5 -> 33507.5 | G13: =E13*300% -> 100522.5 | H13: =E13*7.5% -> 2513.0625 | I13: 40122.19 | J13: =E13*50% -> 16753.75 | K13: =E13*350% -> 117276.25 | L13: =E13*100% -> 33507.5 | M13: =100000 -> 100000 | O13: =E13*10% -> 3350.75 | P13: 20000 | Q13: 0 | R13: =SUM(E13:Q13) -> 467553.5 | T13: =5000 -> 5000 | U13: =179017.51 -> 179017.51 | V13: ='[3]DECEMBER 2019'!$H$35 -> 837.6875 | W13: 15548.33 | X13: =T13+U13+V13+W13 -> 200403.53 | Y13: 267149.97 | Z13: =R13-X13 -> 267149.97
A14: 6 | B14: SARAFADEEN ALABELEWE | C14: SA ADMINISTRATION | D14: 16(9) | E14: =42653.17 -> 42653.17 | G14: =E14*300% -> 127959.51 | H14: =E14*7.5% -> 3198.9877 | I14: 40122.19 | J14: =E14*50% -> 21326.585 | K14: =E14*350% -> 149286.1 | L14: =E14*100% -> 42653.17 | M14: =100000 -> 100000 | O14: =E14*10% -> 4265.317 | P14: 20000 | R14: =SUM(E14:Q14) -> 551465.02 | T14: =100000 -> 100000 | U14: =137500 -> 137500 | W14: 21618.09 | X14: =T14+U14+V14+W14 -> 259118.09 | Y14: 278625.91 | Z14: =R14-X14 -> 292346.93
A15: 7 | B15: DR ABDULSALAM NASIRU NAEEM | C15: SA ACADEMICS | D15: 16(7) | E15: =39662.25 -> 39662.25 | G15: =E15*300% -> 118986.75 | H15: =E15*7.5% -> 2974.6687 | I15: 40122.19 | J15: =E15*50% -> 19831.125 | K15: =E15*350% -> 138817.88 | L15: =E15*100% -> 39662.25 | M15: =150000 -> 150000 | O15: =E15*10% -> 3966.225 | P15: 20000 | Q15: =100000 -> 100000 | R15: =SUM(E15:Q15) -> 674023.33 | W15: =21618.09 -> 21618.09 | X15: =T15+U15+V15+W15 -> 21618.09 | Y15: 590588.72 | Z15: =R15-X15 -> 652405.24
A16: 8 | B16: TOKUNBO ALFRED ADULOJU | C16: AM LIAISON OFFICE | D16: 13(10) | E16: =25523.45 -> 25523.45 | G16: =E16*300% -> 76570.35 | H16: =E16*7.5% -> 1914.2587 | J16: =E16*50% -> 12761.725 | K16: =E16*350% -> 89332.075 | L16: =E16*100% -> 25523.45 | M16: =100000 -> 100000 | O16: =E16*10% -> 2552.345 | P16: 15000 | Q16: =100000 -> 100000 | R16: =SUM(E16:Q16) -> 449177.65 | T16: =100000 -> 100000 | U16: =0 -> 0 | V16: ='[2]Jan 2021'!$H$22 -> 806.58 | W16: 7709.76 | X16: =T16+U16+V16+W16 -> 108516.34 | Y16: 333672.77 | Z16: =R16-X16 -> 340661.31
A17: 9 | B17: HUSSEIN EGYE MUSA | C17: AM PROTOCOL | D17: 13(10) | E17: =25523.45 -> 25523.45 | G17: =E17*300% -> 76570.35 | H17: =E17*7.5% -> 1914.2587 | J17: =E17*50% -> 12761.725 | K17: =E17*350% -> 89332.075 | L17: =E17*100% -> 25523.45 | M17: =100000 -> 100000 | O17: =E17*10% -> 2552.345 | P17: 15000 | Q17: 50000 | R17: =SUM(E17:Q17) -> 399177.65 | T17: 10000 | U17: =103000 -> 103000 | V17: 0 | W17: 7709.76 | X17: =T17+U17+V17+W17 -> 120709.76 | Y17: 271291.3 | Z17: =R17-X17 -> 278467.89
A18: 10 | B18: DONALD E. MKPANAM | C18: AM ICT | D18: 13(11) | E18: 26339.3 | G18: =E18*300% -> 79017.9 | H18: =E18*7.5% -> 1975.4475 | J18: =E18*50% -> 13169.65 | K18: =E18*350% -> 92187.55 | L18: =E18*100% -> 26339.3 | M18: =100000 -> 100000 | O18: =E18*10% -> 2633.93 | P18: 15000 | Q18: 0 | R18: =SUM(E18:Q18) -> 356663.08 | V18: ='[2]Jan 2021'!$H$31 -> 457.041 | W18: 7709.76 | X18: =T18+U18+V18+W18 -> 8166.801 | Y18: 348294.83 | Z18: =R18-X18 -> 348496.28
A19: 11 | B19: JOY HARUNA MAKERI | C19: AM TRAINING | D19: 13(10) | E19: =25523.45 -> 25523.45 | G19: =E19*300% -> 76570.35 | H19: =E19*7.5% -> 1914.2587 | J19: =E19*50% -> 12761.725 | K19: =E19*350% -> 89332.075 | L19: =E19*100% -> 25523.45 | M19: 150000 | O19: =E19*10% -> 2552.345 | P19: 15000 | Q19: =50000+100000 -> 150000 | R19: =SUM(E19:Q19) -> 549177.65 | W19: =7709.76 -> 7709.76 | X19: =SUM(T19:W19) -> 7709.76 | Y19: 534291.3 | Z19: =R19-X19 -> 541467.89
A20: 12 | B20: ALI ABDULLAHI | C20: AM ICT | D20: 13(11) | E20: =26339.3 -> 26339.3 | F20: 0 | G20: =E20*300% -> 79017.9 | H20: =E20*7.5% -> 1975.4475 | I20: 0 | J20: =E20*50% -> 13169.65 | K20: =E20*350% -> 92187.55 | L20: =E20*100% -> 26339.3 | M20: =100000 -> 100000 | O20: =E20*10% -> 2633.93 | P20: 15000 | Q20: =0 -> 0 | R20: =SUM(E20:Q20) -> 356663.08 | W20: =7709.76 -> 7709.76 | X20: =T20+U20+V20+W20 -> 7709.76 | Y20: 348953.32 | Z20: =R20-X20 -> 348953.32
A21: 13 | B21: ADUGBA RICHARD TERSEER | C21: INFORMATION OFFICER | D21: 10(9) | E21: =18281.64 -> 18281.64 | G21: =E21*300% -> 54844.92 | H21: =E21*7.5% -> 1371.123 | J21: =E21*50% -> 9140.82 | K21: =E21*350% -> 63985.74 | L21: =E21*100% -> 18281.64 | M21: =100000 -> 100000 | O21: =E21*10% -> 1828.164 | P21: 10000 | R21: =SUM(E21:Q21) -> 277734.05 | T21: =50000 -> 50000 | U21: =111833.33 -> 111833.33 | W21: 3369.51 | X21: =T21+U21+V21+W21 -> 165202.84 | Y21: 107965.36 | Z21: =R21-X21 -> 112531.21
A22: 14 | B22: CHRISTIAN MADUABUCHI ODO | C22: ICT OFFICER | D22: 10(11) | E22: =19276.95 -> 19276.95 | G22: =E22*300% -> 57830.85 | H22: =E22*7.5% -> 1445.7713 | J22: =E22*50% -> 9638.475 | K22: =E22*350% -> 67469.325 | L22: =E22*100% -> 19276.95 | M22: =100000 -> 100000 | O22: =E22*10% -> 1927.695 | P22: 10000 | R22: =SUM(E22:Q22) -> 286866.02 | T22: =20000 -> 20000 | U22: =82500 -> 82500 | V22: ='[2]Jan 2021'!$H$50 -> 646.3525 | W22: 3369.51 | X22: =T22+U22+V22+W22 -> 106515.86 | Y22: 175961.08 | Z22: =R22-X22 -> 180350.15
A23: 15 | B23: VICTOR ASUKWO | C23: ICT OFFICER | D23: 8 (9) | E23: =13112.16 -> 13112.16 | G23: =E23*300% -> 39336.48 | H23: =E23*7.5% -> 983.412 | J23: =E23*50% -> 6556.08 | K23: =E23*350% -> 45892.56 | L23: =E23*100% -> 13112.16 | M23: =100000 -> 100000 | O23: =E23*10% -> 1311.216 | P23: 10000 | R23: =SUM(E23:Q23) -> 230304.07 | T23: =10000 -> 10000 | W23: 1484.37 | X23: =T23+U23+V23+W23 -> 11484.37 | Y23: 215331.73 | Z23: =R23-X23 -> 218819.7
A24: 16 | B24: SULEIMAN ABUBAKAR SODEEQ | C24: ASST. ADMIN. OFFICER | D24: 8(7) | E24: =12351.94 -> 12351.94 | F24: =0 -> 0 | G24: =E24*300% -> 37055.82 | H24: =E24*7.5% -> 926.3955 | J24: =E24*50% -> 6175.97 | K24: =E24*350% -> 43231.79 | L24: =E24*100% -> 12351.94 | M24: =100000 -> 100000 | O24: =E24*10% -> 1235.194 | P24: 10000 | R24: =SUM(E24:Q24) -> 223329.05 | W24: =1235.19 -> 1235.19 | X24: =SUM(T24:W24) -> 1235.19 | Y24: 222093.86 | Z24: =R24-X24 -> 222093.86
A25: 17 | B25: YAKUB OLUWATOYIN USMAN | C25: ASST. ADMIN. OFFICER | D25: 8(7) | E25: =12351.94 -> 12351.94 | F25: =0 -> 0 | G25: =E25*300% -> 37055.82 | H25: =E25*7.5% -> 926.3955 | J25: =E25*50% -> 6175.97 | K25: =E25*350% -> 43231.79 | L25: =E25*100% -> 12351.94 | M25: =100000 -> 100000 | O25: =E25*10% -> 1235.194 | P25: 10000 | R25: =SUM(E25:Q25) -> 223329.05 | T25: =10000 -> 10000 | W25: =1235.19 -> 1235.19 | X25: =SUM(T25:W25) -> 11235.19 | Y25: 112093.86 | Z25: =R25-X25 -> 212093.86
A26: 18 | B26: ANTHONY EDET | C26: ASST. MGR M&E | D26: 13(8) | E26: =23891.12 -> 23891.12 | F26: =ARREARS!V9 -> 423372 | G26: =E26*300% -> 71673.36 | H26: =E26*7.5% -> 1791.834 | I26: 0 | J26: =E26*50% -> 11945.56 | K26: =E26*350% -> 83618.92 | L26: =E26*100% -> 23891.12 | M26: =100000 -> 100000 | O26: =E26*10% -> 2389.112 | P26: 15000 | Q26: 0 | R26: =SUM(E26:Q26) -> 757573.03 | T26: 10000 | V26: ='[2]Jan 2021'!$H$42 -> 638.08625 | W26: =7709.76+ARREARS!AJ9 -> 59792.76 | X26: =SUM(T26:W26) -> 70430.846 | Y26: 277568.26 | Z26: =R26-X26 -> 687142.18
A27: 19 | B27: EGUATU U. ONYEJELEM | C27: OFFICER M&E | D27: 10(9) | E27: =18281.64 -> 18281.64 | G27: =E27*300% -> 54844.92 | H27: =E27*7.5% -> 1371.123 | J27: =E27*50% -> 9140.82 | K27: =E27*350% -> 63985.74 | L27: =E27*100% -> 18281.64 | M27: =100000 -> 100000 | O27: =E27*10% -> 1828.164 | P27: 10000 | R27: =SUM(E27:Q27) -> 277734.05 | T27: =20000 -> 20000 | U27: =87500+43750 -> 131250 | W27: 3369.51 | X27: =SUM(T27:W27) -> 154619.51 | Y27: 118548.69 | Z27: =R27-X27 -> 123114.54
A28: 20 | B28: ODEH SUZIE | C28: ADMIN. OFFICER, LIASION OFFICE | D28: 10(8) | E28: =17784 -> 17784 | F28: =0 -> 0 | G28: =E28*300% -> 53352 | H28: =E28*7.5% -> 1333.8 | J28: =E28*50% -> 8892 | K28: =E28*350% -> 62244 | L28: =E28*100% -> 17784 | M28: 100000 | O28: =E28*10% -> 1778.4 | P28: 10000 | R28: =SUM(E28:Q28) -> 273168.2 | T28: =30000+20000 -> 50000 | V28: =0 -> 0 | W28: 3369.51 | X28: =T28+U28+V28+W28 -> 53369.51 | Y28: 255232.57 | Z28: =R28-X28 -> 219798.69
B29: TOTAL | C29: 20 | E29: =SUM(E9:E28) -> 689647.03 | F29: =SUM(F9:F28) -> 423372 | G29: =SUM(G9:G28) -> 1908452.3 | H29: =SUM(H9:H28) -> 87833.501 | I29: =SUM(I9:I28) -> 401221.9 | J29: =SUM(J9:J28) -> 336799.08 | K29: =SUM(K9:K28) -> 1852054 | L29: =SUM(L9:L28) -> 649524.85 | M29: =SUM(M9:M28) -> 2250000 | O29: =SUM(O9:O28) -> 68964.708 | P29: =SUM(P9:P28) -> 305000 | Q29: =SUM(Q9:Q28) -> 525235 | R29: =SUM(R9:R28) -> 9498104.4 | T29: =SUM(T9:T28) -> 635000 | U29: =SUM(U9:U28) -> 1017465.1 | V29: =SUM(V9:V28) -> 5836.5948 | W29: =SUM(W9:W28) -> 371609.12 | X29: =SUM(X9:X28) -> 2029910.8 | Y29: =SUM(Y9:Y28) -> 6878696.1 | Z29: =SUM(Z9:Z28) -> 7468193.6
B31: INTERNAL AUDIT
A32: 1 | B32: NWOSU MATHEW EZE | C32: Ag. DIRECTOR INT. AUDIT | D32: 17(8) | E32: =79039.64 -> 79039.64 | G32: =E32*300% -> 237118.92 | H32: =E32*7.5% -> 5927.973 | I32: =80244.38 -> 80244.38 | J32: =E32*50% -> 39519.82 | K32: =E32*350% -> 276638.74 | L32: =E32*100% -> 79039.64 | M32: =100000 -> 100000 | O32: =E32*10% -> 7903.964 | P32: 20000 | Q32: 0 | R32: =SUM(E32:Q32) -> 925433.08 | T32: =100000 -> 100000 | U32: =287500 -> 287500 | V32: ='[2]Jan 2021'!$H$26 -> 837.6875 | W32: =52776.63 -> 52776.63 | X32: =T32+U32+V32+W32 -> 441114.32 | Y32: 459351.89 | Z32: =R32-X32 -> 484318.76
A33: 2 | B33: BASHIRU ABBA WALI | C33: OFF. INT. AUDIT | D33: 10(10) | E33: =18779.3 -> 18779.3 | G33: =E33*300% -> 56337.9 | H33: =E33*7.5% -> 1408.4475 | I33: 0 | J33: =E33*50% -> 9389.65 | K33: =E33*350% -> 65727.55 | L33: =E33*100% -> 18779.3 | M33: =100000 -> 100000 | O33: =E33*10% -> 1877.93 | P33: 10000 | Q33: 0 | R33: =0 -> 0 | T33: =0 -> 0 | U33: =0 -> 0 | W33: =0 -> 0 | X33: =T33+U33+V33+W33 -> 0 | Y33: 278930.57 | Z33: =R33-X33 -> 0
C34: 2 | E34: =SUM(E32:E33) -> 97818.94 | G34: =SUM(G32:G33) -> 293456.82 | H34: =SUM(H32:H33) -> 7336.4205 | I34: =SUM(I32:I33) -> 80244.38 | J34: =SUM(J32:J33) -> 48909.47 | K34: =SUM(K32:K33) -> 342366.29 | L34: =SUM(L32:L33) -> 97818.94 | M34: =SUM(M32:M33) -> 200000 | O34: =SUM(O32:O33) -> 9781.894 | P34: =SUM(P32:P33) -> 30000 | Q34: =SUM(Q32:Q33) -> 0 | R34: =SUM(R32:R33) -> 925433.08 | T34: =SUM(T32:T33) -> 100000 | U34: =SUM(U32:U33) -> 287500 | V34: =SUM(V32:V33) -> 837.6875 | W34: =SUM(W32:W33) -> 52776.63 | X34: =SUM(X32:X33) -> 441114.32 | Y34: =SUM(Y32:Y33) -> 738282.45 | Z34: =SUM(Z32:Z33) -> 484318.76
B36: LEG. SUPPORT SEVICES
A37: 1 | B37: PROF. EDOBA BRIGHT OMOREGBE | C37: AG. DLSS | D37: 17(9) | E37: =81740.02 -> 81740.02 | G37: =E37*300% -> 245220.06 | H37: =E37*7.5% -> 6130.5015 | I37: 80244.38 | J37: =E37*50% -> 40870.01 | K37: =E37*350% -> 286090.07 | L37: =E37*100% -> 81740.02 | M37: =150000 -> 150000 | O37: =E37*10% -> 8174.002 | P37: 20000 | R37: =SUM(E37:Q37) -> 1000209.1 | T37: =100000+2000 -> 102000 | W37: =52776.63 -> 52776.63 | X37: =W37+T37+U37+V37 -> 154776.63 | Y37: 922656.45 | Z37: =R37-X37 -> 845432.43
A38: 2 | B38: DR CLINTON JAJA | C38: SENIOR RESEARCH FELLOW | D38: 15(9) | E38: =33507.5 -> 33507.5 | G38: =E38*300% -> 100522.5 | H38: =E38*7.5% -> 2513.0625 | I38: 40122.19 | J38: =E38*50% -> 16753.75 | K38: =E38*350% -> 117276.25 | L38: =E38*100% -> 33507.5 | M38: =150000 -> 150000 | O38: =E38*10% -> 3350.75 | P38: 20000 | Q38: 0 | R38: =SUM(E38:Q38) -> 517553.5 | T38: 50000 | U38: =240909.11 -> 240909.11 | W38: 15548.33 | X38: =SUM(T38:W38) -> 306457.44 | Y38: 211096.06 | Z38: =R38-X38 -> 211096.06
A39: 3 | B39: BETHEL UZOMA IHUGBA | C39: SNR RESEARCH FELLOW | D39: 15(9) | E39: =33507.5 -> 33507.5 | G39: =E39*300% -> 100522.5 | H39: =E39*7.5% -> 2513.0625 | I39: 40122.19 | J39: =E39*50% -> 16753.75 | K39: =E39*350% -> 117276.25 | L39: =E39*100% -> 33507.5 | M39: =150000 -> 150000 | O39: =E39*10% -> 3350.75 | P39: 20000 | R39: =SUM(E39:Q39) -> 517553.5 | T39: =30000+13000 -> 43000 | U39: =246905.96 -> 246905.96 | W39: 15548.33 | X39: =W39+T39+U39+V39 -> 305454.29 | Y39: 200682.76 | Z39: =R39-X39 -> 212099.21
A40: 4 | B40: OGUCHE SAMUEL | C40: RESEARCH FELLOW I | D40: 14(11) | E40: 28489.81 | G40: =E40*300% -> 85469.43 | H40: =E40*7.5% -> 2136.7357 | J40: =E40*50% -> 14244.905 | K40: =E40*350% -> 99714.335 | L40: =E40*100% -> 28489.81 | M40: =150000 -> 150000 | O40: =E40*10% -> 2848.981 | P40: 20000 | R40: =SUM(E40:Q40) -> 431394.01 | T40: =30000 -> 30000 | U40: =179165.6+26250 -> 205415.6 | W40: 7709.76 | X40: =SUM(T40:W40) -> 243125.36 | Y40: 188268.65 | Z40: =R40-X40 -> 188268.65
A41: 5 | B41: IBRAHIM USMAN | C41: RESEARCH FELLOW I | D41: 14(11) | E41: =28489.81 -> 28489.81 | G41: =E41*300% -> 85469.43 | H41: =E41*7.5% -> 2136.7357 | I41: 0 | J41: =E41*50% -> 14244.905 | K41: =E41*350% -> 99714.335 | L41: =E41*100% -> 28489.81 | M41: =150000 -> 150000 | O41: =E41*10% -> 2848.981 | P41: 20000 | Q41: 0 | R41: =SUM(E41:Q41) -> 431394.01 | V41: ='[2]Jan 2021'!$H$27 -> 991.55625 | W41: 7709.76 | X41: =W41+T41+U41+V41 -> 8701.3162 | Y41: 414932.99 | Z41: =R41-X41 -> 422692.69
A42: 6 | B42: DR MOHAMMED O. AMALI | C42: RESEARCH FELLOW I | D42: 14(8) | E42: =25854.1 -> 25854.1 | F42: =ARREARS!V12 -> 14304 | G42: =E42*300% -> 77562.3 | H42: =E42*7.5% -> 1939.0575 | J42: =E42*50% -> 12927.05 | K42: =E42*350% -> 90489.35 | L42: =E42*100% -> 25854.1 | M42: =150000 -> 150000 | O42: =E42*10% -> 2585.41 | P42: 20000 | R42: =SUM(E42:Q42) -> 421515.37 | T42: =15000 -> 15000 | U42: =106666.67 -> 106666.67 | W42: 7709.76 | X42: =W42+T42+U42+V42 -> 129376.43 | Y42: 262624.63 | Z42: =R42-X42 -> 292138.94
A43: 7 | B43: YAHAYA SHAMSU | C43: AM LEGAL | D43: 13(11) | E43: =26339.3 -> 26339.3 | G43: =E43*300% -> 79017.9 | H43: =E43*7.5% -> 1975.4475 | J43: =E43*50% -> 13169.65 | K43: =E43*350% -> 92187.55 | L43: =E43*100% -> 26339.3 | M43: =150000 -> 150000 | O43: =E43*10% -> 2633.93 | P43: 15000 | R43: =SUM(E43:Q43) -> 406663.08 | V43: 0 | W43: 7709.76 | X43: =W43+U43+T43+V43 -> 7709.76 | Y43: 398953.32 | Z43: =R43-X43 -> 398953.32
A44: 8 | B44: OFORDEME ADAOBI JULIA | C44: RESEARCH FELLOW 11 | D44: 13(9) | E44: =24741.26 -> 24741.26 | G44: =E44*300% -> 74223.78 | H44: =E44*7.5% -> 1855.5945 | I44: 0 | J44: =E44*50% -> 12370.63 | K44: =E44*350% -> 86594.41 | L44: =E44*100% -> 24741.26 | M44: =150000 -> 150000 | O44: =E44*10% -> 2474.126 | P44: 15000 | Q44: 0 | R44: =SUM(E44:Q44) -> 392001.06 | W44: 7709.76 | X44: =W44+T44+U44+V44 -> 7709.76 | Y44: 376493.27 | Z44: =R44-X44 -> 384291.3
A45: 9 | B45: IKPEAZU CHINEDU ANITA | C45: RESEARCH FELLOW II | D45: 13(10) | E45: =25523.45 -> 25523.45 | G45: =E45*300% -> 76570.35 | H45: =E45*7.5% -> 1914.2587 | I45: 0 | J45: =E45*50% -> 12761.725 | K45: =E45*350% -> 89332.075 | L45: =E45*100% -> 25523.45 | M45: =150000 -> 150000 | O45: =E45*10% -> 2552.345 | P45: 15000 | Q45: 0 | R45: =SUM(E45:Q45) -> 399177.65 | W45: 7709.76 | X45: =W45+T45+U45+V45 -> 7709.76 | Y45: 384291.3 | Z45: =R45-X45 -> 391467.89
A46: 10 | B46: . | C46: RESEARCH FELLOW II | D46: 13(10) | E46: =25523.45 -> 25523.45 | G46: =E46*300% -> 76570.35 | H46: =E46*7.5% -> 1914.2587 | I46: =I20 -> 0 | J46: =E46*50% -> 12761.725 | K46: =E46*350% -> 89332.075 | L46: =E46*100% -> 25523.45 | M46: =150000 -> 150000 | O46: =E46*10% -> 2552.345 | P46: 15000 | Q46: 0 | R46: =SUM(E46:Q46) -> 399177.65 | T46: =30000 -> 30000 | U46: =182107.04 -> 182107.04 | V46: ='[2]Jan 2021'!$H$45 -> 444.6 | W46: 7709.76 | X46: =W46+T46+U46+V46 -> 220261.4 | Y46: 71565.729 | Z46: =R46-X46 -> 178916.25
A47: 11 | B47: DORIS DAKDA AARON | C47: RESEARCH FELLOW II | D47: 13(8) | E47: =23891.12 -> 23891.12 | F47: =ARREARS!V13 -> 244895 | G47: =E47*300% -> 71673.36 | H47: =E47*7.5% -> 1791.834 | J47: =E47*50% -> 11945.56 | K47: =E47*350% -> 83618.92 | L47: =E47*100% -> 23891.12 | M47: =150000 -> 150000 | O47: =E47*10% -> 2389.112 | P47: 15000 | R47: =SUM(E47:Q47) -> 629096.03 | T47: =50000+10000 -> 60000 | V47: ='[2]Jan 2021'!$H$51 -> 597.278 | W47: =7709.76+ARREARS!AJ14 -> 29411.01 | X47: =W47+T47+U47+V47 -> 90008.288 | Y47: 263907.5 | Z47: =R47-X47 -> 539087.74
B48: TOTAL | C48: 11 | E48: =SUM(E37:E47) -> 357607.32 | F48: =SUM(F37:F47) -> 259199 | G48: =SUM(G37:G47) -> 1072822 | H48: =SUM(H37:H47) -> 26820.549 | I48: =SUM(I37:I47) -> 160488.76 | J48: =SUM(J37:J47) -> 178803.66 | K48: =SUM(K37:K47) -> 1251625.6 | L48: =SUM(L37:L47) -> 357607.32 | M48: =SUM(M37:M47) -> 1650000 | O48: =SUM(O37:O47) -> 35760.732 | P48: =SUM(P37:P47) -> 195000 | Q48: =SUM(Q37:Q47) -> 0 | R48: =SUM(R37:R47) -> 5545734.9 | T48: =SUM(T37:T47) -> 330000 | U48: =SUM(U37:U47) -> 982004.38 | V48: =SUM(V37:V47) -> 2033.4343 | W48: =SUM(W37:W47) -> 167252.62 | X48: =SUM(X37:X47) -> 1481290.4 | Y48: =SUM(Y37:Y47) -> 3695472.7 | Z48: =SUM(Z37:Z47) -> 4064444.5
B50: LEGAL SERVICES
A51: 1 | B51: DR SHUIBU DANWANKA | C51: DIRECTOR LEGAL SERVICES | D51: 17(9) | E51: =81740.02 -> 81740.02 | G51: =E51*300% -> 245220.06 | H51: =E51*7.5% -> 6130.5015 | I51: 80244.38 | J51: =E51*50% -> 40870.01 | K51: =E51*350% -> 286090.07 | L51: =E51*100% -> 81740.02 | M51: =150000 -> 150000 | O51: =E51*10% -> 8174.002 | P51: 20000 | Q51: 0 | R51: =SUM(E51:Q51) -> 1000209.1 | V51: 0 | W51: 52776.63 | X51: =T51+U51+V51+W51 -> 52776.63 | Y51: 947432.43 | Z51: =R51-X51 -> 947432.43
B52: TOTAL | C52: 1 | E52: =SUM(E51:E51) -> 81740.02 | F52: =SUM(F51:F51) -> 0 | G52: =SUM(G51:G51) -> 245220.06 | H52: =SUM(H51:H51) -> 6130.5015 | I52: =SUM(I51:I51) -> 80244.38 | J52: =SUM(J51:J51) -> 40870.01 | K52: =SUM(K51:K51) -> 286090.07 | L52: =SUM(L51:L51) -> 81740.02 | M52: =SUM(M51:M51) -> 150000 | O52: =SUM(O51:O51) -> 8174.002 | P52: =SUM(P51:P51) -> 20000 | Q52: =SUM(Q51:Q51) -> 0 | R52: =SUM(R51:R51) -> 1000209.1 | V52: =SUM(V51:V51) -> 0 | W52: =SUM(W51:W51) -> 52776.63 | X52: =SUM(X51:X51) -> 52776.63 | Y52: 947432.43 | Z52: =R52-X52 -> 947432.43
B54: DEMOCRATIC STUDIES
A55: 1 | B55: DR. ADEWALE ADEREMI | C55: DIRECTOR, DEMOCRATIC STUDIES | D55: 17(8) | E55: =79039.64 -> 79039.64 | F55: =0 -> 0 | G55: =E55*300% -> 237118.92 | H55: =E55*7.5% -> 5927.973 | I55: =80244.38 -> 80244.38 | J55: =E55*50% -> 39519.82 | K55: =E55*350% -> 276638.74 | L55: =E55*100% -> 79039.64 | M55: =150000 -> 150000 | O55: =E55*10% -> 7903.964 | P55: 20000 | Q55: 0 | R55: =SUM(E55:Q55) -> 975433.08 | T55: =100000 -> 100000 | W55: =52776.63 -> 52776.63 | X55: =T55+U55+V55+W55 -> 152776.63 | Y55: 797880.83 | Z55: =R55-X55 -> 822656.45
A56: 2 | B56: EMILY EDOISA IKHIDE | C56: RESEARCH FELLOW II | D56: 13(10) | E56: =25523.45 -> 25523.45 | G56: =E56*300% -> 76570.35 | H56: =E56*7.5% -> 1914.2587 | J56: =E56*50% -> 12761.725 | K56: =E56*350% -> 89332.075 | L56: =E56*100% -> 25523.45 | M56: =150000 -> 150000 | O56: =E56*10% -> 2552.345 | P56: 15000 | R56: =SUM(E56:Q56) -> 399177.65 | T56: =50000 -> 50000 | U56: =45833.33 -> 45833.33 | W56: 7709.76 | X56: =SUM(T56:W56) -> 103543.09 | Y56: 288457.97 | Z56: =R56-X56 -> 295634.56
A57: 3 | B57: EJALONIBU GANIYU LAYI | C57: RESEARCH FELLOW 11 | D57: 13(8) | E57: =23891.12 -> 23891.12 | F57: =ARREARS!V18 -> 244895 | G57: =E57*300% -> 71673.36 | H57: =E57*7.5% -> 1791.834 | J57: =E57*50% -> 11945.56 | K57: =E57*350% -> 83618.92 | L57: =E57*100% -> 23891.12 | M57: =150000 -> 150000 | O57: =E57*10% -> 2389.112 | P57: 15000 | R57: =SUM(E57:Q57) -> 629096.03 | T57: =110000 -> 110000 | W57: =7709.76+ARREARS!AJ18 -> 29411.01 | X57: =T57+U57+V57+W57 -> 139411.01 | Y57: 214364.54 | Z57: =R57-X57 -> 489685.02
A58: 4 | B58: UDEFUNA NNADOZIE PATRICK | C58: RESEARCH OFFICER | D58: 10(13) | E58: =19774.62 -> 19774.62 | G58: =E58*300% -> 59323.86 | H58: =E58*7.5% -> 1483.0965 | I58: 0 | J58: =E58*50% -> 9887.31 | K58: =E58*350% -> 69211.17 | L58: =E58*100% -> 19774.62 | M58: =150000 -> 150000 | O58: =E58*10% -> 1977.462 | P58: 10000 | Q58: 0 | R58: =SUM(E58:Q58) -> 341432.14 | T58: =10000 -> 10000 | U58: =131771.66 -> 131771.66 | W58: 3369.51 | X58: =SUM(T58:W58) -> 145141.17 | Y58: 76290.969 | Z58: =R58-X58 -> 196290.97
A59: 5 | B59: OSOLAFIA MUHAMMAD EGYE | C59: PERSONNEL OFFICER | D59: 10(11) | E59: =19276.95 -> 19276.95 | G59: =E59*300% -> 57830.85 | H59: =E59*7.5% -> 1445.7713 | I59: 0 | J59: =E59*50% -> 9638.475 | K59: =E59*350% -> 67469.325 | L59: =E59*100% -> 19276.95 | M59: =150000 -> 150000 | O59: =E59*10% -> 1927.695 | P59: 10000 | Q59: 0 | R59: =SUM(E59:Q59) -> 336866.02 | T59: =20000 -> 20000 | U59: =100000 -> 100000 | V59: ='[2]Jan 2021'!$H$46 -> 668.31625 | W59: =3369.51 -> 3369.51 | X59: =T59+U59+V59+W59 -> 124037.83 | Y59: 108461.08 | Z59: =R59-X59 -> 212828.19
A60: 6 | B60: HAUWA PATE SADIQ | C60: PROGRAMME OFFICER | D60: 10(9) | E60: =18281.64 -> 18281.64 | G60: =E60*300% -> 54844.92 | H60: =E60*7.5% -> 1371.123 | J60: =E60*50% -> 9140.82 | K60: =E60*350% -> 63985.74 | L60: =E60*100% -> 18281.64 | M60: =150000 -> 150000 | O60: =E60*10% -> 1828.164 | P60: 10000 | R60: =SUM(E60:Q60) -> 327734.05 | T60: =70000+20000 -> 90000 | U60: =31500 -> 31500 | W60: 3369.51 | X60: =SUM(T60:W60) -> 124869.51 | Y60: 238298.69 | Z60: =R60-X60 -> 202864.54
B61: TOTAL | C61: 6 | E61: =SUM(E55:E60) -> 185787.42 | F61: =SUM(F55:F60) -> 244895 | G61: =SUM(G55:G60) -> 557362.26 | H61: =SUM(H55:H60) -> 13934.056 | I61: =SUM(I55:I60) -> 80244.38 | J61: =SUM(J55:J60) -> 92893.71 | K61: =SUM(K55:K60) -> 650255.97 | L61: =SUM(L55:L60) -> 185787.42 | M61: =SUM(M55:M60) -> 900000 | O61: =SUM(O55:O60) -> 18578.742 | P61: =SUM(P55:P60) -> 80000 | Q61: =SUM(Q55:Q60) -> 0 | R61: =SUM(R55:R60) -> 3009739 | T61: =SUM(T55:T60) -> 380000 | U61: =SUM(U55:U60) -> 309104.99 | V61: =SUM(V55:V60) -> 668.31625 | W61: =SUM(W55:W60) -> 100005.93 | X61: =SUM(X55:X60) -> 789779.24 | Y61: =SUM(Y55:Y60) -> 1723754.1 | Z61: =SUM(Z55:Z60) -> 2219959.7
B63: POST GRADUATE SCHOOL
A64: 1 | B64: DR ASIMIYU G. ABIOLA | C64: DIRECTOR POST GRADUATE | D64: 17(9) | E64: =81740.02 -> 81740.02 | G64: =E64*300% -> 245220.06 | H64: =E64*7.5% -> 6130.5015 | I64: 80244.38 | J64: =E64*50% -> 40870.01 | K64: =E64*350% -> 286090.07 | L64: =E64*100% -> 81740.02 | M64: =150000 -> 150000 | O64: =E64*10% -> 8174.002 | P64: 20000 | Q64: 0 | R64: =SUM(E64:Q64) -> 1000209.1 | T64: 150000 | U64: =451815.1 -> 451815.1 | V64: 0 | W64: 52776.63 | X64: =SUM(T64:W64) -> 654591.73 | Y64: 345617.33 | Z64: =R64-X64 -> 345617.33
A65: 2 | B65: UZODINMA EMMANUEL EZENWA | C65: RESEARCH FELLOW II | D65: 13(8) | E65: =23891.12 -> 23891.12 | F65: =ARREARS!V23 -> 532956 | G65: =E65*300% -> 71673.36 | H65: =E65*7.5% -> 1791.834 | I65: 0 | J65: =E65*50% -> 11945.56 | K65: =E65*350% -> 83618.92 | L65: =E65*100% -> 23891.12 | M65: =150000 -> 150000 | O65: =E65*10% -> 2389.112 | P65: 15000 | Q65: 0 | R65: =SUM(E65:Q65) -> 917157.03 | T65: =0 -> 0 | U65: =0 -> 0 | V65: ='[2]Jan 2021'!$H$47 -> 481.92375 | W65: =7709.76+ARREARS!AJ23 -> 59792.76 | X65: =T65+U65+V65+W65 -> 60274.684 | Y65: 328461.08 | Z65: =R65-X65 -> 856882.34
B66: TOTAL | C66: 2 | E66: =SUM(E64:E65) -> 105631.14 | F66: =SUM(F64:F65) -> 532956 | G66: =SUM(G64:G65) -> 316893.42 | H66: =SUM(H64:H65) -> 7922.3355 | I66: =SUM(I64:I65) -> 80244.38 | J66: =SUM(J64:J65) -> 52815.57 | K66: =SUM(K64:K65) -> 369708.99 | L66: =SUM(L64:L65) -> 105631.14 | M66: =SUM(M64:M65) -> 300000 | O66: =SUM(O64:O65) -> 10563.114 | P66: =SUM(P64:P65) -> 35000 | Q66: =SUM(Q64:Q65) -> 0 | R66: =SUM(R64:R65) -> 1917366.1 | T66: =SUM(T64:T65) -> 150000 | U66: =SUM(U64:U65) -> 451815.1 | V66: =SUM(V64:V65) -> 481.92375 | W66: =SUM(W64:W65) -> 112569.39 | X66: =SUM(X64:X65) -> 714866.41 | Y66: =SUM(Y64:Y65) -> 674078.42 | Z66: =SUM(Z64:Z65) -> 1202499.7
B68: ECONOMIC AND SOCIAL DEV.
A69: 1 | B69: DR ASEMOTA OMOROGBE JOSEPH | C69: Ag. DEPUTY DIRECTOR, ECO & SOC DEV DEPT | D69: 15(9) | E69: =33507.5 -> 33507.5 | G69: =E69*300% -> 100522.5 | H69: =E69*7.5% -> 2513.0625 | I69: 40122.19 | J69: =E69*50% -> 16753.75 | K69: =E69*350% -> 117276.25 | L69: =E69*100% -> 33507.5 | M69: =150000 -> 150000 | O69: =E69*10% -> 3350.75 | P69: 20000 | R69: =SUM(E69:Q69) -> 517553.5 | W69: 15548.33 | X69: =SUM(T69:W69) -> 15548.33 | Y69: 502005.17 | Z69: =R69-X69 -> 502005.17
A70: 2 | B70: TERFA WILLIAMS ABRAHAM | C70: SNR RESEARCH FELLOW | D70: 15(8) | E70: =32263.2 -> 32263.2 | F70: =ARREARS!V27 -> 189978 | G70: =E70*300% -> 96789.6 | H70: =E70*7.5% -> 2419.74 | I70: =40122.19 -> 40122.19 | J70: =E70*50% -> 16131.6 | K70: =E70*350% -> 112921.2 | L70: =E70*100% -> 32263.2 | M70: =150000 -> 150000 | O70: =E70*10% -> 3226.32 | P70: 20000 | R70: =SUM(E70:Q70) -> 696115.05 | W70: =15548.33+ARREARS!AJ27 -> 39064.04 | X70: =SUM(T70:W70) -> 39064.04 | Y70: 423684.25 | Z70: =R70-X70 -> 657051.01
A71: 3 | B71: DR AUGUSTINE C. OSIGWE | C71: SNR RESEARCH FELLOW | D71: 15(8) | E71: =32263.2 -> 32263.2 | F71: =ARREARS!V22 -> 238344 | G71: =E71*300% -> 96789.6 | H71: =E71*7.5% -> 2419.74 | I71: =40122.19 -> 40122.19 | J71: =E71*50% -> 16131.6 | K71: =E71*350% -> 112921.2 | L71: =E71*100% -> 32263.2 | M71: =150000 -> 150000 | O71: =E71*10% -> 3226.32 | P71: 20000 | R71: =SUM(E71:Q71) -> 744481.05 | T71: =20000 -> 20000 | U71: =150000 -> 150000 | V71: ='[2]Jan 2021'!$H$41 -> 481.92375 | W71: =15548.33+ARREARS!AJ22 -> 39064.04 | X71: =SUM(T71:W71) -> 209545.96 | Y71: 244932.99 | Z71: =R71-X71 -> 534935.09
A72: 4 | B72: JUMARE FADILA | C72: RESEARCH FELLOW I | D72: 14(8) | E72: =25854.1 -> 25854.1 | F72: =ARREARS!V28 -> 96408 | G72: =E72*300% -> 77562.3 | H72: =E72*7.5% -> 1939.0575 | I72: 0 | J72: =E72*50% -> 12927.05 | K72: =E72*350% -> 90489.35 | L72: =E72*100% -> 25854.1 | M72: =150000 -> 150000 | O72: =E72*10% -> 2585.41 | P72: 20000 | Q72: 0 | R72: =SUM(E72:Q72) -> 503619.37 | T72: 5000 | W72: =7709.76 -> 7709.76 | X72: =SUM(T72:W72) -> 12709.76 | Y72: 386467.89 | Z72: =R72-X72 -> 490909.61
A73: 5 | B73: NGARA CHRISTOPHER OCHANJA | C73: RESEARCH FELLOW 1 | D73: 14(9) | E73: =26732.65 -> 26732.65 | F73: =ARREARS!V17 -> 96408 | G73: =E73*300% -> 80197.95 | H73: =E73*7.5% -> 2004.9488 | J73: =E73*50% -> 13366.325 | K73: =E73*350% -> 93564.275 | L73: =E73*100% -> 26732.65 | M73: =150000 -> 150000 | O73: =E73*10% -> 2673.265 | P73: 20000 | Q73: 0 | R73: =SUM(E73:Q73) -> 511680.06 | T73: =20000 -> 20000 | U73: =163103.59 -> 163103.59 | V73: ='[2]Jan 2021'!$H$49 -> 638.08625 | W73: =7709.76 -> 7709.76 | X73: =T73+U73+V73+W73 -> 191451.44 | Y73: 207726.22 | Z73: =R73-X73 -> 320228.63
A74: 6 | B74: OMOJU OLUWASOLA EMMANUEL | C74: RESEARCH FELLOW I | D74: 14(8) | E74: =25854.1 -> 25854.1 | F74: =ARREARS!V29 -> 28608 | G74: =E74*300% -> 77562.3 | H74: =E74*7.5% -> 1939.0575 | J74: =E74*50% -> 12927.05 | K74: =E74*350% -> 90489.35 | L74: =E74*100% -> 25854.1 | M74: =150000 -> 150000 | O74: =E74*10% -> 2585.41 | P74: 20000 | R74: =SUM(E74:Q74) -> 435819.37 | T74: =50000 -> 50000 | U74: =87500 -> 87500 | W74: =7709.76 -> 7709.76 | X74: =SUM(T74:W74) -> 145209.76 | Y74: 246791.3 | Z74: =R74-X74 -> 290609.61
A75: 7 | B75: ONYIMADU C. ONYEBUCHI | C75: RESEARCH FELLOW I | D75: 14(8) | E75: =25854.1 -> 25854.1 | F75: =ARREARS!V30 -> 14304 | G75: =E75*300% -> 77562.3 | H75: =E75*7.5% -> 1939.0575 | J75: =E75*50% -> 12927.05 | K75: =E75*350% -> 90489.35 | L75: =E75*100% -> 25854.1 | M75: =150000 -> 150000 | O75: =E75*10% -> 2585.41 | P75: 20000 | R75: =SUM(E75:Q75) -> 421515.37 | T75: =50000 -> 50000 | V75: ='[2]Jan 2021'!$H$53 -> 638.08625 | W75: 7709.76 | X75: =SUM(T75:W75) -> 58347.846 | Y75: 333672.77 | Z75: =R75-X75 -> 363167.52
A76: 8 | B76: IBE EZECHI CYRIACUS | C76: RESEARCH FELLOW II | D76: 13(8) | E76: =23891.12 -> 23891.12 | F76: =ARREARS!V31 -> 146937 | G76: =E76*300% -> 71673.36 | H76: =E76*7.5% -> 1791.834 | I76: 0 | J76: =E76*50% -> 11945.56 | K76: =E76*350% -> 83618.92 | L76: =E76*100% -> 23891.12 | M76: =150000 -> 150000 | O76: =E76*10% -> 2389.112 | P76: 15000 | Q76: 0 | R76: =SUM(E76:Q76) -> 531138.03 | T76: =50000 -> 50000 | W76: =7709.76+ARREARS!AJ31 -> 20730.51 | X76: =SUM(T76:W76) -> 70730.51 | Y76: 299364.54 | Z76: =R76-X76 -> 460407.52
B77: TOTAL | C77: 8 | E77: =SUM(E69:E76) -> 226219.97 | F77: =SUM(F69:F76) -> 810987 | G77: =SUM(G69:G76) -> 678659.91 | H77: =SUM(H69:H76) -> 16966.498 | I77: =SUM(I69:I76) -> 120366.57 | J77: =SUM(J69:J76) -> 113109.99 | K77: =SUM(K69:K76) -> 791769.9 | L77: =SUM(L69:L76) -> 226219.97 | M77: =SUM(M69:M76) -> 1200000 | O77: =SUM(O69:O76) -> 22621.997 | P77: =SUM(P69:P76) -> 155000 | Q77: =SUM(Q69:Q76) -> 0 | R77: =SUM(R69:R76) -> 4361921.8 | T77: =SUM(T69:T76) -> 195000 | U77: =SUM(U69:U76) -> 400603.59 | V77: =SUM(V69:V76) -> 1758.0963 | W77: =SUM(W69:W76) -> 145245.96 | X77: =SUM(X69:X76) -> 742607.65 | Y77: =SUM(Y69:Y76) -> 2644645.1 | Z77: =SUM(Z69:Z76) -> 3619314.1
B79: TRAINING AND INTERNATIONAL COOP
A80: 1 | B80: DR JAKE DABANG DAN AZUMI | C80: DEPUTY DIRECTOR TRAINING | D80: 16(7) | E80: =39662.25 -> 39662.25 | G80: =E80*300% -> 118986.75 | H80: =E80*7.5% -> 2974.6687 | I80: 40122.19 | J80: =E80*50% -> 19831.125 | K80: =E80*350% -> 138817.88 | L80: =E80*100% -> 39662.25 | M80: 150000 | O80: =E80*10% -> 3966.225 | P80: 20000 | Q80: 150000 | R80: =SUM(E80:Q80) -> 724023.33 | V80: ='[2]Jan 2021'!$H$30 -> 2043.5005 | W80: 15548.33 | X80: =SUM(T80:W80) -> 17591.831 | Y80: 651167.48 | Z80: =R80-X80 -> 706431.5
A81: 2 | B81: DR FRANCIS NDUM OJIE | C81: ASST. MANAGER, TRAINING | D81: 14(8) | E81: =25854.1 -> 25854.1 | F81: =ARREARS!V35 -> 42912 | G81: =E81*300% -> 77562.3 | H81: =E81*7.5% -> 1939.0575 | J81: =E81*50% -> 12927.05 | K81: =E81*350% -> 90489.35 | L81: =E81*100% -> 25854.1 | M81: 100000 | O81: =E81*10% -> 2585.41 | P81: 20000 | R81: =SUM(E81:Q81) -> 400123.37 | W81: =7709.76 -> 7709.76 | X81: =SUM(T81:W81) -> 7709.76 | Y81: 334291.3 | Z81: =R81-X81 -> 392413.61
A82: 3 | B82: OKECHUKWU UCHENNA HULDA | C82: TRAINING OFFICER | D82: 10(9) | E82: =18281.64 -> 18281.64 | G82: =E82*300% -> 54844.92 | H82: =E82*7.5% -> 1371.123 | J82: =E82*50% -> 9140.82 | K82: =E82*350% -> 63985.74 | L82: =E82*100% -> 18281.64 | M82: =100000 -> 100000 | O82: =E82*10% -> 1828.164 | P82: 10000 | R82: =SUM(E82:Q82) -> 277734.05 | T82: =5000 -> 5000 | U82: =0 -> 0 | W82: 3369.51 | X82: =SUM(T82:W82) -> 8369.51 | Y82: 264798.69 | Z82: =R82-X82 -> 269364.54
A83: 4 | B83: HASSANA AHMED IBRAHIM | C83: TRAINING OFFICER | D83: 10(8) | E83: =17784 -> 17784 | F83: =0 -> 0 | G83: =E83*300% -> 53352 | H83: =E83*7.5% -> 1333.8 | J83: =E83*50% -> 8892 | K83: =E83*350% -> 62244 | L83: =E83*100% -> 17784 | M83: 100000 | O83: =E83*10% -> 1778.4 | P83: 10000 | R83: =SUM(E83:Q83) -> 273168.2 | T83: =30000 -> 30000 | V83: ='[2]Jan 2021'!$H$58 -> 0 | W83: 3369.51 | X83: =SUM(T83:W83) -> 33369.51 | Y83: 234787.97 | Z83: =R83-X83 -> 239798.69
B84: TOTAL | C84: 4 | E84: =SUM(E80:E83) -> 101581.99 | F84: =SUM(F80:F83) -> 42912 | G84: =SUM(G80:G83) -> 304745.97 | H84: =SUM(H80:H83) -> 7618.6492 | I84: =SUM(I80:I83) -> 40122.19 | J84: =SUM(J80:J83) -> 50790.995 | K84: =SUM(K80:K83) -> 355536.96 | L84: =SUM(L80:L83) -> 101581.99 | M84: =SUM(M80:M83) -> 450000 | O84: =SUM(O80:O83) -> 10158.199 | P84: =SUM(P80:P83) -> 60000 | Q84: =SUM(Q80:Q83) -> 150000 | R84: =SUM(R80:R83) -> 1675048.9 | T84: =SUM(T80:T83) -> 35000 | U84: =SUM(U80:U83) -> 0 | V84: =SUM(V80:V83) -> 2043.5005 | W84: =SUM(W80:W83) -> 29997.11 | X84: =SUM(X80:X83) -> 67040.611 | Y84: =SUM(Y80:Y83) -> 1485045.4 | Z84: =SUM(Z80:Z83) -> 1608008.3
B86: LIBRARY AND DOCUMENTATION
A87: 1 | B87: DR MAIMUNA IZAH | C87: INSITUTE LIBRARIAN | D87: 17(8) | E87: =79039.64 -> 79039.64 | G87: =E87*300% -> 237118.92 | H87: =E87*7.5% -> 5927.973 | I87: 80244.38 | J87: =E87*50% -> 39519.82 | K87: =E87*350% -> 276638.74 | L87: =E87*100% -> 79039.64 | M87: 150000 | O87: =E87*10% -> 7903.964 | P87: 20000 | Q87: 0 | R87: =SUM(E87:Q87) -> 975433.08 | T87: =100000 -> 100000 | U87: 0 | V87: 0 | W87: =52776.63 -> 52776.63 | X87: =SUM(T87:W87) -> 152776.63 | Y87: 797880.83 | Z87: =R87-X87 -> 822656.45
A88: 2 | B88: CATHERINE E. IKOKOH | C88: SNR RESEARCH FELLOW DOCU | D88: 15(9) | E88: =33507.5 -> 33507.5 | G88: =E88*300% -> 100522.5 | H88: =E88*7.5% -> 2513.0625 | I88: 40122.19 | J88: =E88*50% -> 16753.75 | K88: =E88*350% -> 117276.25 | L88: =E88*100% -> 33507.5 | M88: 150000 | O88: =E88*10% -> 3350.75 | P88: 20000 | Q88: 0 | R88: =SUM(E88:Q88) -> 517553.5 | T88: 40000 | U88: =131250 -> 131250 | V88: ='[2]Jan 2021'!$H$36 -> 658.4825 | W88: 15548.33 | X88: =SUM(T88:W88) -> 187456.81 | Y88: 329917.48 | Z88: =R88-X88 -> 330096.69
A89: 3 | B89: ALIYU SANNI ABUBAKAR | C89: RESEARCH FELLOW 11 DATA & DOCU | D89: 13(11) | E89: =26339.3 -> 26339.3 | G89: =E89*300% -> 79017.9 | H89: =E89*7.5% -> 1975.4475 | I89: 0 | J89: =E89*50% -> 13169.65 | K89: =E89*350% -> 92187.55 | L89: =E89*100% -> 26339.3 | M89: 150000 | O89: =E89*10% -> 2633.93 | P89: 15000 | Q89: 0 | R89: =SUM(E89:Q89) -> 406663.08 | T89: 30000 | U89: =0 -> 0 | V89: ='[2]Jan 2021'!$H$39 -> 597.278 | W89: =7709.76 -> 7709.76 | X89: =SUM(T89:W89) -> 38307.038 | Y89: 360829.81 | Z89: =R89-X89 -> 368356.04
A90: 4 | B90: CHINAKO N. ASOGWA | C90: RESEARCH FELLOW 11 DATA & DOCU | D90: 13(9) | E90: =24741.26 -> 24741.26 | F90: =ARREARS!V40 -> 557219 | G90: =E90*300% -> 74223.78 | H90: =E90*7.5% -> 1855.5945 | I90: 0 | J90: =E90*50% -> 12370.63 | K90: =E90*350% -> 86594.41 | L90: =E90*100% -> 24741.26 | M90: 150000 | O90: =E90*10% -> 2474.126 | P90: 15000 | R90: =SUM(E90:Q90) -> 949220.06 | T90: =50000 -> 50000 | U90: =43083.33 -> 43083.33 | W90: =7709.76+ARREARS!AJ40 -> 81494.01 | X90: =SUM(T90:W90) -> 174577.34 | Y90: 254111.91 | Z90: =R90-X90 -> 774642.72
B91: TOTAL | C91: 4 | E91: =SUM(E87:E90) -> 163627.7 | F91: =SUM(F87:F90) -> 557219 | G91: =SUM(G87:G90) -> 490883.1 | H91: =SUM(H87:H90) -> 12272.077 | I91: =SUM(I87:I90) -> 120366.57 | J91: =SUM(J87:J90) -> 81813.85 | K91: =SUM(K87:K90) -> 572696.95 | L91: =SUM(L87:L90) -> 163627.7 | M91: =SUM(M87:M90) -> 600000 | O91: =SUM(O87:O90) -> 16362.77 | P91: =SUM(P87:P90) -> 70000 | Q91: =SUM(Q87:Q90) -> 0 | R91: =SUM(R87:R90) -> 2848869.7 | T91: =SUM(T87:T90) -> 220000 | U91: =SUM(U87:U90) -> 174333.33 | V91: =SUM(V87:V90) -> 1255.7605 | W91: =SUM(W87:W90) -> 157528.73 | X91: =SUM(X87:X90) -> 553117.82 | Y91: =SUM(Y87:Y90) -> 1742740 | Z91: =SUM(Z87:Z90) -> 2295751.9
B93: FINANCE & ACCOUNT
A94: 1 | B94: IBRAHIM M. MSHELIA | C94: DIR. FINANCE & ACCOUNTS | D94: 17(9) | E94: =81740.02 -> 81740.02 | G94: =E94*300% -> 245220.06 | H94: =E94*7.5% -> 6130.5015 | I94: =80244.38 -> 80244.38 | J94: =E94*50% -> 40870.01 | K94: =E94*350% -> 286090.07 | L94: =E94*100% -> 81740.02 | M94: =100000 -> 100000 | O94: =E94*10% -> 8174.002 | P94: 20000 | Q94: 100000 | R94: =SUM(E94:Q94) -> 1050209.1 | T94: =200000 -> 200000 | U94: =227777.78 -> 227777.78 | V94: ='[2]Jan 2021'!$H$24 -> 712.24525 | W94: =52776.63 -> 52776.63 | X94: =SUM(T94:W94) -> 481266.66 | Y94: 542902.68 | Z94: =R94-X94 -> 568942.41
A95: 2 | B95: KABIR MUHAMMAD SULAIMAN | C95: DD FINANCE & ACCOUNTS | D95: 16(9) | E95: =42653.17 -> 42653.17 | G95: =E95*300% -> 127959.51 | H95: =E95*7.5% -> 3198.9877 | I95: 40122.19 | J95: =E95*50% -> 21326.585 | K95: =E95*350% -> 149286.1 | L95: =E95*100% -> 42653.17 | M95: =100000 -> 100000 | O95: =E95*10% -> 4265.317 | P95: 20000 | Q95: =100000 -> 100000 | R95: =SUM(E95:Q95) -> 651465.02 | T95: =100000 -> 100000 | U95: =0 -> 0 | W95: =21618.09 -> 21618.09 | X95: =SUM(T95:W95) -> 121618.09 | Y95: 516125.91 | Z95: =R95-X95 -> 529846.93
A96: 3 | B96: RAHILA NURUDEEN HABU | C96: MANAGER, ACCOUNTS | D96: 15(9) | E96: =33507.5 -> 33507.5 | G96: =E96*300% -> 100522.5 | H96: =E96*7.5% -> 2513.0625 | I96: 40122.19 | J96: =E96*50% -> 16753.75 | K96: =E96*350% -> 117276.25 | L96: =E96*100% -> 33507.5 | M96: =100000 -> 100000 | O96: =E96*10% -> 3350.75 | P96: 20000 | Q96: 0 | R96: =SUM(E96:Q96) -> 467553.5 | T96: =70000 -> 70000 | U96: =129166.67 -> 129166.67 | V96: ='[2]Jan 2021'!$H$23 -> 1975.991 | W96: 15548.33 | X96: =SUM(T96:W96) -> 216690.99 | Y96: 240615.47 | Z96: =R96-X96 -> 250862.51
A97: 4 | B97: ANDRAWUS MUSA | C97: MGR. STORE | D97: 15(8) | E97: =32263.2 -> 32263.2 | F97: =ARREARS!V43 -> 1146516 | G97: =E97*300% -> 96789.6 | H97: =E97*7.5% -> 2419.74 | I97: =40122.19 -> 40122.19 | J97: =E97*50% -> 16131.6 | K97: =E97*350% -> 112921.2 | L97: =E97*100% -> 32263.2 | M97: =100000 -> 100000 | O97: =E97*10% -> 3226.32 | P97: 20000 | Q97: 0 | R97: =SUM(E97:Q97) -> 1602653.1 | T97: =50000 -> 50000 | U97: =90000 -> 90000 | V97: ='[2]Jan 2021'!$H$32 -> 837.6875 | W97: =15548.33+ARREARS!AJ43 -> 109611.17 | X97: =SUM(T97:W97) -> 250448.86 | Y97: 200829.81 | Z97: =R97-X97 -> 1352204.2
A98: 5 | B98: TONDO IORWUESE EDWARD | C98: MGR ACCOUNTS | D98: 15(8) | E98: =32263.2 -> 32263.2 | F98: =ARREARS!V44 -> 1146516 | G98: =E98*300% -> 96789.6 | H98: =E98*7.5% -> 2419.74 | I98: =40122.19 -> 40122.19 | J98: =E98*50% -> 16131.6 | K98: =E98*350% -> 112921.2 | L98: =E98*100% -> 32263.2 | M98: =100000 -> 100000 | O98: =E98*10% -> 3226.32 | P98: 20000 | Q98: =100000 -> 100000 | R98: =SUM(E98:Q98) -> 1702653.1 | T98: =100000 -> 100000 | U98: =100000 -> 100000 | V98: ='[2]Jan 2021'!$H$25 -> 597.278 | W98: =15548.33+ARREARS!AJ44 -> 109611.17 | X98: =SUM(T98:W98) -> 310208.45 | Y98: 310829.81 | Z98: =R98-X98 -> 1392444.6
A99: 6 | B99: SHEHU ABDULLAHI | C99: ASST. MANAGER, ACCOUNTS | D99: 13(9) | E99: =24741.26 -> 24741.26 | F99: 0 | G99: =E99*300% -> 74223.78 | H99: =E99*7.5% -> 1855.5945 | I99: 0 | J99: =E99*50% -> 12370.63 | K99: =E99*350% -> 86594.41 | L99: =E99*100% -> 24741.26 | M99: =100000 -> 100000 | O99: =E99*10% -> 2474.126 | P99: 15000 | Q99: 0 | R99: =SUM(E99:Q99) -> 342001.06 | T99: =30000 -> 30000 | U99: =75000 -> 75000 | W99: =7709.76 -> 7709.76 | X99: =SUM(T99:W99) -> 112709.76 | Y99: 226491.27 | Z99: =R99-X99 -> 229291.3
A100: 7 | B100: OJOGIWA ABISOLA GANIAT | C100: ASST. MGR ACCOUNT | D100: 13(8) | E100: =23891.12 -> 23891.12 | F100: =ARREARS!V45 -> 532956 | G100: =E100*300% -> 71673.36 | H100: =E100*7.5% -> 1791.834 | J100: =E100*50% -> 11945.56 | K100: =E100*350% -> 83618.92 | L100: =E100*100% -> 23891.12 | M100: =100000 -> 100000 | O100: =E100*10% -> 2389.112 | P100: 15000 | Q100: =30000 -> 30000 | R100: =SUM(E100:Q100) -> 897157.03 | T100: =70000+70000 -> 140000 | U100: =45833.33 -> 45833.33 | V100: ='[2]Jan 2021'!$H$54 -> 218.26975 | W100: =7709.76+ARREARS!AJ46 -> 59792.76 | X100: =SUM(T100:W100) -> 245844.36 | Y100: 132627.75 | Z100: =R100-X100 -> 651312.67
A101: 8 | B101: RAHILA SALIHU | C101: ASST. MGR ACCOUNT | D101: 13(8) | E101: =23891.12 -> 23891.12 | F101: =ARREARS!V46 -> 532956 | G101: =E101*300% -> 71673.36 | H101: =E101*7.5% -> 1791.834 | J101: =E101*50% -> 11945.56 | K101: =E101*350% -> 83618.92 | L101: =E101*100% -> 23891.12 | M101: =100000 -> 100000 | O101: =E101*10% -> 2389.112 | P101: 15000 | R101: =SUM(E101:Q101) -> 867157.03 | T101: =70000+40000 -> 110000 | U101: =95555.56 -> 95555.56 | V101: ='[2]Jan 2021'!$H$28 -> 658.4825 | W101: =7709.76+ARREARS!AJ46 -> 59792.76 | X101: =SUM(T101:W101) -> 266006.8 | Y101: 112905.52 | Z101: =R101-X101 -> 601150.22
A102: 9 | B102: IJEOMA NKOLIKWA | C102: ASSISTANT STORES OFFICER | D102: 8(9) | E102: =13112.16 -> 13112.16 | G102: =E102*300% -> 39336.48 | H102: =E102*7.5% -> 983.412 | J102: =E102*50% -> 6556.08 | K102: =E102*350% -> 45892.56 | L102: =E102*100% -> 13112.16 | M102: =100000 -> 100000 | O102: =E102*10% -> 1311.216 | P102: 10000 | R102: =SUM(E102:Q102) -> 230304.07 | T102: =10000 -> 10000 | W102: 1484.37 | X102: =SUM(T102:W102) -> 11484.37 | Y102: 215331.73 | Z102: =R102-X102 -> 218819.7
A103: 10 | B103: ABDULRAHMAN A SULAIMAN | C103: ASSISTANT STORES OFFICER | D103: 8 (8) | E103: =12732 -> 12732 | F103: =0 -> 0 | G103: =E103*300% -> 38196 | H103: =E103*7.5% -> 954.9 | J103: =E103*50% -> 6366 | K103: =E103*350% -> 44562 | L103: =E103*100% -> 12732 | M103: =100000 -> 100000 | O103: =E103*10% -> 1273.2 | P103: 10000 | R103: =SUM(E103:Q103) -> 226816.1 | T103: =20000 -> 20000 | W103: =(1484.37) -> 1484.37 | X103: =T103+U103+V103+W103 -> 21484.37 | Y103: 201844.68 | Z103: =R103-X103 -> 205331.73
B104: TOTAL | C104: 10 | E104: =SUM(E94:E103) -> 320794.75 | F104: =SUM(F94:F103) -> 3358944 | G104: =SUM(G94:G103) -> 962384.25 | H104: =SUM(H94:H103) -> 24059.606 | I104: =SUM(I94:I103) -> 240733.14 | J104: =SUM(J94:J103) -> 160397.38 | K104: =SUM(K94:K103) -> 1122781.6 | L104: =SUM(L94:L103) -> 320794.75 | M104: =SUM(M94:M103) -> 1000000 | O104: =SUM(O94:O103) -> 32079.475 | P104: =SUM(P94:P103) -> 165000 | Q104: =SUM(Q94:Q103) -> 330000 | R104: =SUM(R94:R103) -> 8037969 | T104: =SUM(T94:T103) -> 830000 | U104: =SUM(U94:U103) -> 763333.34 | V104: =SUM(V94:V103) -> 4999.954 | W104: =SUM(W94:W103) -> 439429.41 | X104: =SUM(X94:X103) -> 2037762.7 | Y104: =SUM(Y94:Y103) -> 2700504.6 | Z104: =SUM(Z94:Z103) -> 6000206.3
B106: ADMINISTRATION & HUMAN RESOURCE
A107: 1 | B107: DR KABIR AHMED | C107: DIR. FINANCE & ADMIN | D107: 17(9) | E107: 81740.02 | F107: 0 | G107: =E107*300% -> 245220.06 | H107: =E107*7.5% -> 6130.5015 | I107: 80244.38 | J107: =E107*50% -> 40870.01 | K107: =E107*350% -> 286090.07 | L107: =E107*100% -> 81740.02 | M107: =100000 -> 100000 | O107: =E107*10% -> 8174.002 | P107: 20000 | Q107: 0 | R107: =SUM(E107:Q107) -> 950209.06 | T107: 50000 | U107: =322916.66 -> 322916.66 | V107: =2043.5 -> 2043.5 | W107: 52776.63 | X107: =SUM(T107:W107) -> 427736.79 | Y107: 522472.27 | Z107: =R107-X107 -> 522472.27
A108: 2 | B108: AMINU BELLO DUKKU | C108: DIR ADMIN/HR | D108: 17(9) | E108: =81740.02 -> 81740.02 | G108: =E108*300% -> 245220.06 | H108: =E108*7.5% -> 6130.5015 | I108: =80244.38 -> 80244.38 | J108: =E108*50% -> 40870.01 | K108: =E108*350% -> 286090.07 | L108: =E108*100% -> 81740.02 | M108: =100000 -> 100000 | O108: =E108*10% -> 8174.002 | P108: 20000 | Q108: 0 | R108: =SUM(E108:Q108) -> 950209.06 | T108: =100000 -> 100000 | W108: =52776.63 -> 52776.63 | X108: =SUM(T108:W108) -> 152776.63 | Y108: 772656.45 | Z108: =R108-X108 -> 797432.43
A109: 3 | B109: MAGAJI BALA | C109: DD ADMIN/HR | D109: 16(9) | E109: =42653.17 -> 42653.17 | G109: =E109*300% -> 127959.51 | H109: =E109*7.5% -> 3198.9877 | I109: 40122.19 | J109: =E109*50% -> 21326.585 | K109: =E109*350% -> 149286.1 | L109: =E109*100% -> 42653.17 | M109: =100000 -> 100000 | O109: =E109*10% -> 4265.317 | P109: 20000 | Q109: 0 | R109: =SUM(E109:Q109) -> 551465.02 | T109: =25000 -> 25000 | U109: =168055.54 -> 168055.54 | W109: =21618.09 -> 21618.09 | X109: =SUM(T109:W109) -> 214673.63 | Y109: 323070.37 | Z109: =R109-X109 -> 336791.39
A110: 4 | B110: ARCH. TIJO ZARA BORYO | C110: MANAGER, ASSETS/MAINT. | D110: 15(9) | E110: 33507.5 | G110: =E110*300% -> 100522.5 | H110: =E110*7.5% -> 2513.0625 | I110: 40122.19 | J110: =E110*50% -> 16753.75 | K110: =E110*350% -> 117276.25 | L110: =E110*100% -> 33507.5 | M110: =100000 -> 100000 | O110: =E110*10% -> 3350.75 | P110: 20000 | Q110: 50000 | R110: =SUM(E110:Q110) -> 517553.5 | T110: =137500 -> 137500 | V110: ='[2]Jan 2021'!$H$55 -> 444.6 | W110: 15548.33 | X110: =SUM(T110:W110) -> 153492.93 | Y110: 363667.48 | Z110: =R110-X110 -> 364060.57
A111: 5 | B111: YUNUSA ABDULLAHI | C111: ASSISTANT MANAGER, HR | D111: 13(10) | E111: =25523.45 -> 25523.45 | G111: =E111*300% -> 76570.35 | H111: =E111*7.5% -> 1914.2587 | J111: =E111*50% -> 12761.725 | K111: =E111*350% -> 89332.075 | L111: =E111*100% -> 25523.45 | M111: =100000 -> 100000 | O111: =E111*10% -> 2552.345 | P111: 15000 | R111: =SUM(E111:Q111) -> 349177.65 | T111: =3000 -> 3000 | U111: =49442.44 -> 49442.44 | W111: =7709.76 -> 7709.76 | X111: =SUM(T111:W111) -> 60152.2 | Y111: 281848.86 | Z111: =R111-X111 -> 289025.45
A112: 6 | B112: EROMOSELE OMONIGBO | C112: PERSONNEL OFFICER | D112: 10(11) | E112: =19276.95 -> 19276.95 | G112: =E112*300% -> 57830.85 | H112: =E112*7.5% -> 1445.7713 | I112: 0 | J112: =E112*50% -> 9638.475 | K112: =E112*350% -> 67469.325 | L112: =E112*100% -> 19276.95 | M112: =100000 -> 100000 | O112: =E112*10% -> 1927.695 | P112: 10000 | Q112: 0 | R112: =SUM(E112:Q112) -> 286866.02 | T112: 10000 | U112: =0 -> 0 | V112: ='[2]Jan 2021'!$H$44 -> 597.278 | W112: =3369.51 -> 3369.51 | X112: =SUM(T112:W112) -> 13966.788 | Y112: 268461.08 | Z112: =R112-X112 -> 272899.23
...

Sheet TAX DIFFERENCES
B3: STAFF PAYROLL FOR THE MONTH OF JANUARY, 2021
F4: ='[1]FEB 08'!E8/'[1]FEB 08'!M8 -> 0.22 | I4: ='[1]FEB 08'!F8/'[1]FEB 08'!Q8 -> 0.3
B5: STAFF NAME | S5: DEDUCTIONS | Y5: NET SALARY
D6: DESIGNATION | E6: SALARY | F6: BASIC | M6: MOTOR/ | N6: RESEARCH | O6: LEAVE | P6: OUT FIT | Q6: LEGISLATIVE | R6: GROSS | X6: DECEMBER,2020 | Y6: JANUARY,2021
E7: LEVEL | F7: SALARY | G7: SALARY/ALLOWCE AREARS | H7: RENT | I7: UTILITY | J7: DOMESTIC | K7: ENTERT. | L7: FURNIT. | M7: FUEL | N7: ALLOWANCE | O7: ALLCE | P7: ALLCE | Q7: DUTY ALLCE | R7: SALARY | S7: COOP SOCIETY | T7: COOP. LOAN RECOVERY | U7: NHF DEDUCTION | V7: PAYE | W7: TOTAL | Z7: DEC. 2020 PAYE | AA7: DIFFERENCE
A8: S/N | B8: DG OFFICE | F8: N | I8: N | R8: N | V8: N
A9: 1 | B9: PROF. ABUBAKAR O. SULAIMAN | D9: DIRECTOR GENERAL | E9: CONSOL | F9: 160488.75 | H9: 320977.5 | I9: 48146.63 | J9: 120366.57 | K9: 72219.94 | L9: 0 | M9: 120366.57 | N9: =200000 -> 200000 | O9: 16048.88 | P9: 25000 | Q9: 25235 | R9: =SUM(F9:Q9) -> 1108849.8 | V9: 113176.97 | W9: =S9+T9+U9+V9 -> 113176.97 | X9: 995672.87 | Y9: =R9-W9 -> 995672.87 | Z9: 113176.97 | AA9: =V9-Z9 -> 0
A10: 2 | B10: AKINSANMI ADEJOKE OLUKEMI | D10: AM INFORMATION | E10: 15(9) | F10: 33507.5 | H10: =F10*300% -> 100522.5 | I10: =F10*7.5% -> 2513.0625 | J10: 40122.19 | K10: =F10*50% -> 16753.75 | L10: =F10*350% -> 117276.25 | M10: =F10*100% -> 33507.5 | N10: =100000 -> 100000 | O10: =F10*10% -> 3350.75 | P10: 20000 | Q10: =100000 -> 100000 | R10: =SUM(F10:Q10) -> 567553.5 | S10: =0 -> 0 | T10: 0 | U10: ='[3]DECEMBER 2019'!$H$29 -> 837.6875 | V10: 15548.33 | W10: =S10+T10+U10+V10 -> 16386.018 | X10: 551167.48 | Y10: =R10-W10 -> 551167.48 | Z10: 15548.33 | AA10: =V10-Z10 -> 0
A11: 3 | B11: DR IKEME ARTHUR J.O | D11: SNR RESEARCH FELLOW | E11: 15(9) | F11: =33507.5 -> 33507.5 | H11: =F11*300% -> 100522.5 | I11: =F11*7.5% -> 2513.0625 | J11: 40122.19 | K11: =F11*50% -> 16753.75 | L11: =F11*350% -> 117276.25 | M11: =F11*100% -> 33507.5 | N11: =100000 -> 100000 | O11: =F11*10% -> 3350.75 | P11: 20000 | Q11: 0 | R11: =SUM(F11:Q11) -> 467553.5 | S11: 50000 | T11: =212642 -> 212642 | U11: ='[3]DECEMBER 2019'!$H$38 -> 837.6875 | V11: 15548.33 | W11: =SUM(S11:V11) -> 279028.02 | X11: 188525.48 | Y11: =R11-W11 -> 188525.48 | Z11: 15548.33 | AA11: =V11-Z11 -> 0
A12: 4 | B12: MOSHOOD M. OLALERE | D12: MANAGER ADMIN DG's OFFICE | E12: 15(9) | F12: =33507.5 -> 33507.5 | H12: =F12*300% -> 100522.5 | I12: =F12*7.5% -> 2513.0625 | J12: 40122.19 | K12: =F12*50% -> 16753.75 | L12: =F12*350% -> 117276.25 | M12: =F12*100% -> 33507.5 | N12: =100000 -> 100000 | O12: =F12*10% -> 3350.75 | P12: 20000 | Q12: 0 | R12: =SUM(F12:Q12) -> 467553.5 | S12: =5000 -> 5000 | T12: =179017.51 -> 179017.51 | U12: ='[3]DECEMBER 2019'!$H$35 -> 837.6875 | V12: 15548.33 | W12: =S12+T12+U12+V12 -> 200403.53 | X12: 267149.97 | Y12: =R12-W12 -> 267149.97 | Z12: 15548.33 | AA12: =V12-Z12 -> 0
A13: 5 | B13: SARAFADEEN ALABELEWE | D13: SA ADMINISTRATION | E13: 16(9) | F13: =42653.17 -> 42653.17 | H13: =F13*300% -> 127959.51 | I13: =F13*7.5% -> 3198.9877 | J13: 40122.19 | K13: =F13*50% -> 21326.585 | L13: =F13*350% -> 149286.1 | M13: =F13*100% -> 42653.17 | N13: =100000 -> 100000 | O13: =F13*10% -> 4265.317 | P13: 20000 | R13: =SUM(F13:Q13) -> 551465.02 | S13: =100000 -> 100000 | T13: =137500 -> 137500 | V13: 21618.09 | W13: =S13+T13+U13+V13 -> 259118.09 | X13: 278625.91 | Y13: =R13-W13 -> 292346.93 | Z13: 21618.09 | AA13: =V13-Z13 -> 0
A14: 6 | B14: DR ABDULSALAM NASIRU NAEEM | D14: SA ACADEMICS | E14: 16(7) | F14: =39662.25 -> 39662.25 | H14: =F14*300% -> 118986.75 | I14: =F14*7.5% -> 2974.6687 | J14: 40122.19 | K14: =F14*50% -> 19831.125 | L14: =F14*350% -> 138817.88 | M14: =F14*100% -> 39662.25 | N14: =150000 -> 150000 | O14: =F14*10% -> 3966.225 | P14: 20000 | Q14: =100000 -> 100000 | R14: =SUM(F14:Q14) -> 674023.33 | V14: 21618.09 | W14: =S14+T14+U14+V14 -> 21618.09 | X14: 590588.72 | Y14: =R14-W14 -> 652405.24 | Z14: 15548.33 | AA14: =V14-Z14 -> 6069.76
A15: 7 | B15: TOKUNBO ALFRED ADULOJU | D15: AM LIAISON OFFICE | E15: 13(10) | F15: =25523.45 -> 25523.45 | H15: =F15*300% -> 76570.35 | I15: =F15*7.5% -> 1914.2587 | K15: =F15*50% -> 12761.725 | L15: =F15*350% -> 89332.075 | M15: =F15*100% -> 25523.45 | N15: =100000 -> 100000 | O15: =F15*10% -> 2552.345 | P15: 15000 | Q15: =100000 -> 100000 | R15: =SUM(F15:Q15) -> 449177.65 | S15: =100000 -> 100000 | T15: =0 -> 0 | U15: ='[3]DECEMBER 2019'!$H$22 -> 618.5315 | V15: 7709.76 | W15: =S15+T15+U15+V15 -> 108328.29 | X15: 333672.77 | Y15: =R15-W15 -> 340849.36 | Z15: 7709.76 | AA15: =V15-Z15 -> 0
A16: 8 | B16: HUSSEIN EGYE MUSA | D16: AM PROTOCOL | E16: 13(10) | F16: =25523.45 -> 25523.45 | H16: =F16*300% -> 76570.35 | I16: =F16*7.5% -> 1914.2587 | K16: =F16*50% -> 12761.725 | L16: =F16*350% -> 89332.075 | M16: =F16*100% -> 25523.45 | N16: =100000 -> 100000 | O16: =F16*10% -> 2552.345 | P16: 15000 | Q16: 50000 | R16: =SUM(F16:Q16) -> 399177.65 | S16: 10000 | T16: =103000 -> 103000 | U16: 0 | V16: 7709.76 | W16: =S16+T16+U16+V16 -> 120709.76 | X16: 271291.3 | Y16: =R16-W16 -> 278467.89 | Z16: 7709.76 | AA16: =V16-Z16 -> 0
A17: 9 | B17: DONALD E. MKPANAM | D17: AM ICT | E17: 13(11) | F17: 26339.3 | H17: =F17*300% -> 79017.9 | I17: =F17*7.5% -> 1975.4475 | K17: =F17*50% -> 13169.65 | L17: =F17*350% -> 92187.55 | M17: =F17*100% -> 26339.3 | N17: =100000 -> 100000 | O17: =F17*10% -> 2633.93 | P17: 15000 | Q17: 0 | R17: =SUM(F17:Q17) -> 356663.08 | U17: ='[3]DECEMBER 2019'!$H$31 -> 658.4825 | V17: 7709.76 | W17: =S17+T17+U17+V17 -> 8368.2425 | X17: 348294.83 | Y17: =R17-W17 -> 348294.83 | Z17: 7709.76 | AA17: =V17-Z17 -> 0
A18: 10 | B18: JOY HARUNA MAKERI | D18: AM TRAINING | E18: 13(10) | F18: =25523.45 -> 25523.45 | H18: =F18*300% -> 76570.35 | I18: =F18*7.5% -> 1914.2587 | K18: =F18*50% -> 12761.725 | L18: =F18*350% -> 89332.075 | M18: =F18*100% -> 25523.45 | N18: 150000 | O18: =F18*10% -> 2552.345 | P18: 15000 | Q18: =50000+100000 -> 150000 | R18: =SUM(F18:Q18) -> 549177.65 | V18: 7709.76 | W18: =SUM(S18:V18) -> 7709.76 | X18: 534291.3 | Y18: =R18-W18 -> 541467.89 | Z18: 7709.76 | AA18: =V18-Z18 -> 0
A19: 11 | B19: ALI ABDULLAHI | D19: AM ICT | E19: 13(11) | F19: =26339.3 -> 26339.3 | G19: 0 | H19: =F19*300% -> 79017.9 | I19: =F19*7.5% -> 1975.4475 | J19: 0 | K19: =F19*50% -> 13169.65 | L19: =F19*350% -> 92187.55 | M19: =F19*100% -> 26339.3 | N19: =100000 -> 100000 | O19: =F19*10% -> 2633.93 | P19: 15000 | Q19: =0 -> 0 | R19: =SUM(F19:Q19) -> 356663.08 | V19: 7709.76 | W19: =S19+T19+U19+V19 -> 7709.76 | X19: 348953.32 | Y19: =R19-W19 -> 348953.32 | Z19: 7709.76 | AA19: =V19-Z19 -> 0
A20: 12 | B20: ADUGBA RICHARD TERSEER | D20: INFORMATION OFFICER | E20: 10(9) | F20: =18281.64 -> 18281.64 | H20: =F20*300% -> 54844.92 | I20: =F20*7.5% -> 1371.123 | K20: =F20*50% -> 9140.82 | L20: =F20*350% -> 63985.74 | M20: =F20*100% -> 18281.64 | N20: =100000 -> 100000 | O20: =F20*10% -> 1828.164 | P20: 10000 | R20: =SUM(F20:Q20) -> 277734.05 | S20: =50000 -> 50000 | T20: =111833.33 -> 111833.33 | V20: 3369.51 | W20: =S20+T20+U20+V20 -> 165202.84 | X20: 107965.36 | Y20: =R20-W20 -> 112531.21 | Z20: 3369.51 | AA20: =V20-Z20 -> 0
A21: 13 | B21: CHRISTIAN MADUABUCHI ODO | D21: ICT OFFICER | E21: 10(11) | F21: =19276.95 -> 19276.95 | H21: =F21*300% -> 57830.85 | I21: =F21*7.5% -> 1445.7713 | K21: =F21*50% -> 9638.475 | L21: =F21*350% -> 67469.325 | M21: =F21*100% -> 19276.95 | N21: =100000 -> 100000 | O21: =F21*10% -> 1927.695 | P21: 10000 | R21: =SUM(F21:Q21) -> 286866.02 | S21: =20000 -> 20000 | T21: =82500 -> 82500 | U21: ='[3]DECEMBER 2019'!$H$51 -> 469.4825 | V21: 3369.51 | W21: =S21+T21+U21+V21 -> 106338.99 | X21: 175961.08 | Y21: =R21-W21 -> 180527.02 | Z21: 3369.51 | AA21: =V21-Z21 -> 0
A22: 14 | B22: VICTOR ASUKWO | D22: ICT OFFICER | E22: 8 (9) | F22: =13112.16 -> 13112.16 | H22: =F22*300% -> 39336.48 | I22: =F22*7.5% -> 983.412 | K22: =F22*50% -> 6556.08 | L22: =F22*350% -> 45892.56 | M22: =F22*100% -> 13112.16 | N22: =100000 -> 100000 | O22: =F22*10% -> 1311.216 | P22: 10000 | R22: =SUM(F22:Q22) -> 230304.07 | S22: =10000 -> 10000 | V22: 1484.37 | W22: =S22+T22+U22+V22 -> 11484.37 | X22: 215331.73 | Y22: =R22-W22 -> 218819.7 | Z22: 1484.37 | AA22: =V22-Z22 -> 0
A23: 15 | B23: SULEIMAN ABUBAKAR SODEEQ | E23: 8(7) | F23: =12351.94 -> 12351.94 | G23: =0 -> 0 | H23: =F23*300% -> 37055.82 | I23: =F23*7.5% -> 926.3955 | K23: =F23*50% -> 6175.97 | L23: =F23*350% -> 43231.79 | M23: =F23*100% -> 12351.94 | N23: =100000 -> 100000 | O23: =F23*10% -> 1235.194 | P23: 10000 | R23: =SUM(F23:Q23) -> 223329.05 | V23: 1235.19 | W23: =SUM(S23:V23) -> 1235.19 | X23: 222093.86 | Y23: =R23-W23 -> 222093.86 | Z23: 1235.19 | AA23: =V23-Z23 -> 0
A24: 16 | B24: YAKUB OLUWATOYIN USMAN | E24: 8(7) | F24: =12351.94 -> 12351.94 | G24: =0 -> 0 | H24: =F24*300% -> 37055.82 | I24: =F24*7.5% -> 926.3955 | K24: =F24*50% -> 6175.97 | L24: =F24*350% -> 43231.79 | M24: =F24*100% -> 12351.94 | N24: =100000 -> 100000 | O24: =F24*10% -> 1235.194 | P24: 10000 | R24: =SUM(F24:Q24) -> 223329.05 | S24: =10000 -> 10000 | V24: 1235.19 | W24: =SUM(S24:V24) -> 11235.19 | X24: 112093.86 | Y24: =R24-W24 -> 212093.86 | Z24: 1235.19 | AA24: =V24-Z24 -> 0
A25: 17 | B25: ANTHONY EDET | D25: ASST. MGR M&E | E25: 13(8) | F25: =23891.12 -> 23891.12 | H25: =F25*300% -> 71673.36 | I25: =F25*7.5% -> 1791.834 | J25: 0 | K25: =F25*50% -> 11945.56 | L25: =F25*350% -> 83618.92 | M25: =F25*100% -> 23891.12 | N25: =100000 -> 100000 | O25: =F25*10% -> 2389.112 | P25: 15000 | Q25: 0 | R25: =SUM(F25:Q25) -> 334201.03 | S25: 10000 | U25: ='[3]DECEMBER 2019'!$H$43 -> 494.3655 | V25: 7709.76 | W25: =SUM(S25:V25) -> 18204.126 | X25: 277568.26 | Y25: =R25-W25 -> 315996.9 | Z25: 3369.51 | AA25: =V25-Z25 -> 4340.25
A26: 18 | B26: EGUATU U. ONYEJELEM | D26: OFFICER M&E | E26: 10(9) | F26: =18281.64 -> 18281.64 | H26: =F26*300% -> 54844.92 | I26: =F26*7.5% -> 1371.123 | K26: =F26*50% -> 9140.82 | L26: =F26*350% -> 63985.74 | M26: =F26*100% -> 18281.64 | N26: =100000 -> 100000 | O26: =F26*10% -> 1828.164 | P26: 10000 | R26: =SUM(F26:Q26) -> 277734.05 | S26: =20000 -> 20000 | T26: =87500+43750 -> 131250 | V26: 3369.51 | W26: =SUM(S26:V26) -> 154619.51 | X26: 118548.69 | Y26: =R26-W26 -> 123114.54 | Z26: 3369.51 | AA26: =V26-Z26 -> 0
A27: 19 | B27: ODEH SUZIE | D27: ADMIN. OFFICER, LIASION OFFICE | E27: 10(8) | F27: =17784 -> 17784 | G27: =0 -> 0 | H27: =F27*300% -> 53352 | I27: =F27*7.5% -> 1333.8 | K27: =F27*50% -> 8892 | L27: =F27*350% -> 62244 | M27: =F27*100% -> 17784 | N27: 100000 | O27: =F27*10% -> 1778.4 | P27: 10000 | R27: =SUM(F27:Q27) -> 273168.2 | S27: =30000+20000 -> 50000 | U27: =0 -> 0 | V27: 3369.51 | W27: =S27+T27+U27+V27 -> 53369.51 | X27: 255232.57 | Y27: =R27-W27 -> 219798.69 | Z27: 3369.51 | AA27: =V27-Z27 -> 0
B28: TOTAL | D28: 19 | F28: =SUM(F9:F27) -> 607907.01 | G28: =SUM(G9:G27) -> 0 | H28: =SUM(H9:H27) -> 1663232.3 | I28: =SUM(I9:I27) -> 81702.999 | J28: =SUM(J9:J27) -> 320977.52 | K28: =SUM(K9:K27) -> 295929.07 | L28: =SUM(L9:L27) -> 1565963.9 | M28: =SUM(M9:M27) -> 567784.83 | ... U28: =SUM(U9:U27) -> 4753.9245 | V28: 266749.49 | W28: =SUM(W9:W27) -> 1664246.3 | X28: 6193029.4 | Y28: =SUM(Y9:Y27) -> 6410277.1 | Z28: 256339.48 | AA28: =V28-Z28 -> 10410.01
AA29: =V29-Z29 -> 0
B30: INTERNAL AUDIT | AA30: =V30-Z30 -> 0
A31: 1 | B31: NWOSU MATHEW EZE | D31: Ag. DIRECTOR INT. AUDIT | E31: 17(8) | F31: =79039.64 -> 79039.64 | H31: =F31*300% -> 237118.92 | I31: =F31*7.5% -> 5927.973 | J31: =80244.38 -> 80244.38 | K31: =F31*50% -> 39519.82 | L31: =F31*350% -> 276638.74 | M31: =F31*100% -> 79039.64 | N31: =100000 -> 100000 | O31: =F31*10% -> 7903.964 | P31: 20000 | Q31: 0 | R31: =SUM(F31:Q31) -> 925433.08 | S31: =100000 -> 100000 | T31: =287500 -> 287500 | U31: ='[3]DECEMBER 2019'!$H$26 -> 1028.9423 | V31: 52776.63 | W31: =S31+T31+U31+V31 -> 441305.57 | X31: 459351.89 | Y31: =R31-W31 -> 484127.5 | Z31: 52776.63 | AA31: =V31-Z31 -> 0
A32: 2 | B32: BASHIRU ABBA WALI | D32: OFF. INT. AUDIT | E32: 10(10) | F32: =18779.3 -> 18779.3 | H32: =F32*300% -> 56337.9 | I32: =F32*7.5% -> 1408.4475 | J32: 0 | K32: =F32*50% -> 9389.65 | L32: =F32*350% -> 65727.55 | M32: =F32*100% -> 18779.3 | N32: =100000 -> 100000 | O32: =F32*10% -> 1877.93 | P32: 10000 | Q32: 0 | R32: =0 -> 0 | S32: =0 -> 0 | T32: =0 -> 0 | V32: 0 | W32: =S32+T32+U32+V32 -> 0 | X32: 278930.57 | Y32: =R32-W32 -> 0 | Z32: 0 | AA32: =V32-Z32 -> 0
C33: TOTAL | D33: 2 | F33: =SUM(F31:F32) -> 97818.94 | G33: =SUM(G31:G32) -> 0 | H33: =SUM(H31:H32) -> 293456.82 | I33: =SUM(I31:I32) -> 7336.4205 | J33: =SUM(J31:J32) -> 80244.38 | K33: =SUM(K31:K32) -> 48909.47 | L33: =SUM(L31:L32) -> 342366.29 | M33: =SUM(M31:M32) -> 97818.94 | ... U33: =SUM(U31:U32) -> 1028.9423 | V33: 52776.63 | W33: =SUM(W31:W32) -> 441305.57 | X33: 738282.45 | Y33: =R33-W33 -> 484127.5 | Z33: 52776.63 | AA33: =V33-Z33 -> 0
AA34: =V34-Z34 -> 0
B35: LEG. SUPPORT SEVICES | AA35: =V35-Z35 -> 0
A36: 1 | B36: PROF. EDOBA BRIGHT OMOREGBE | D36: AG. DLSS | E36: 17(9) | F36: =81740.02 -> 81740.02 | H36: =F36*300% -> 245220.06 | I36: =F36*7.5% -> 6130.5015 | J36: 80244.38 | K36: =F36*50% -> 40870.01 | L36: =F36*350% -> 286090.07 | M36: =F36*100% -> 81740.02 | N36: =150000 -> 150000 | O36: =F36*10% -> 8174.002 | P36: 20000 | R36: =SUM(F36:Q36) -> 1000209.1 | S36: =100000+2000 -> 102000 | V36: 52776.63 | W36: =V36+S36+T36+U36 -> 154776.63 | X36: 922656.45 | Y36: =R36-W36 -> 845432.43 | Z36: 52776.63 | AA36: =V36-Z36 -> 0
A37: 2 | B37: DR CLINTON JAJA | D37: SENIOR RESEARCH FELLOW | E37: 15(9) | F37: =33507.5 -> 33507.5 | H37: =F37*300% -> 100522.5 | I37: =F37*7.5% -> 2513.0625 | J37: 40122.19 | K37: =F37*50% -> 16753.75 | L37: =F37*350% -> 117276.25 | M37: =F37*100% -> 33507.5 | N37: =150000 -> 150000 | O37: =F37*10% -> 3350.75 | P37: 20000 | Q37: 0 | R37: =SUM(F37:Q37) -> 517553.5 | S37: 50000 | T37: =240909.11 -> 240909.11 | V37: 15548.33 | W37: =SUM(S37:V37) -> 306457.44 | X37: 211096.06 | Y37: =R37-W37 -> 211096.06 | Z37: 15548.33 | AA37: =V37-Z37 -> 0
A38: 3 | B38: BETHEL UZOMA IHUGBA | D38: SNR RESEARCH FELLOW | E38: 15(9) | F38: =33507.5 -> 33507.5 | H38: =F38*300% -> 100522.5 | I38: =F38*7.5% -> 2513.0625 | J38: 40122.19 | K38: =F38*50% -> 16753.75 | L38: =F38*350% -> 117276.25 | M38: =F38*100% -> 33507.5 | N38: =150000 -> 150000 | O38: =F38*10% -> 3350.75 | P38: 20000 | R38: =SUM(F38:Q38) -> 517553.5 | S38: =30000+13000 -> 43000 | T38: =246905.96 -> 246905.96 | V38: 15548.33 | W38: =V38+S38+T38+U38 -> 305454.29 | X38: 200682.76 | Y38: =R38-W38 -> 212099.21 | Z38: 15548.33 | AA38: =V38-Z38 -> 0
A39: 4 | B39: OGUCHE SAMUEL | D39: RESEARCH FELLOW I | E39: 14(11) | F39: 28489.81 | H39: =F39*300% -> 85469.43 | I39: =F39*7.5% -> 2136.7357 | K39: =F39*50% -> 14244.905 | L39: =F39*350% -> 99714.335 | M39: =F39*100% -> 28489.81 | N39: =150000 -> 150000 | O39: =F39*10% -> 2848.981 | P39: 20000 | R39: =SUM(F39:Q39) -> 431394.01 | S39: =30000 -> 30000 | T39: =179165.6+26250 -> 205415.6 | V39: 7709.76 | W39: =SUM(S39:V39) -> 243125.36 | X39: 188268.65 | Y39: =R39-W39 -> 188268.65 | Z39: 7709.76 | AA39: =V39-Z39 -> 0
A40: 5 | B40: IBRAHIM USMAN | D40: RESEARCH FELLOW I | E40: 14(11) | F40: =28489.81 -> 28489.81 | H40: =F40*300% -> 85469.43 | I40: =F40*7.5% -> 2136.7357 | J40: 0 | K40: =F40*50% -> 14244.905 | L40: =F40*350% -> 99714.335 | M40: =F40*100% -> 28489.81 | N40: =150000 -> 150000 | O40: =F40*10% -> 2848.981 | P40: 20000 | Q40: 0 | R40: =SUM(F40:Q40) -> 431394.01 | U40: ='[3]DECEMBER 2019'!$H$27 -> 690.28075 | V40: 7709.76 | W40: =V40+S40+T40+U40 -> 8400.0408 | X40: 414932.99 | Y40: =R40-W40 -> 422993.97 | Z40: 7709.76 | AA40: =V40-Z40 -> 0
A41: 6 | B41: DR MOHAMMED O. AMALI | D41: RESEARCH FELLOW I | E41: 14(9) | F41: =27611.23 -> 27611.23 | H41: =F41*300% -> 82833.69 | I41: =F41*7.5% -> 2070.8422 | K41: =F41*50% -> 13805.615 | L41: =F41*350% -> 96639.305 | M41: =F41*100% -> 27611.23 | N41: =150000 -> 150000 | O41: =F41*10% -> 2761.123 | P41: 15000 | R41: =SUM(F41:Q41) -> 418333.04 | S41: =15000 -> 15000 | T41: =106666.67 -> 106666.67 | V41: 7709.76 | W41: =V41+S41+T41+U41 -> 129376.43 | X41: 262624.63 | Y41: =R41-W41 -> 288956.61 | Z41: 7709.76 | AA41: =V41-Z41 -> 0
A42: 7 | B42: YAHAYA SHAMSU | D42: AM LEGAL | E42: 13(11) | F42: =26339.3 -> 26339.3 | H42: =F42*300% -> 79017.9 | I42: =F42*7.5% -> 1975.4475 | K42: =F42*50% -> 13169.65 | L42: =F42*350% -> 92187.55 | M42: =F42*100% -> 26339.3 | N42: =150000 -> 150000 | O42: =F42*10% -> 2633.93 | P42: 15000 | R42: =SUM(F42:Q42) -> 406663.08 | U42: 0 | V42: 7709.76 | W42: =V42+T42+S42+U42 -> 7709.76 | X42: 398953.32 | Y42: =R42-W42 -> 398953.32 | Z42: 7709.76 | AA42: =V42-Z42 -> 0
A43: 8 | B43: OFORDEME ADAOBI JULIA | D43: RESEARCH FELLOW 11 | E43: 13(9) | F43: =24741.26 -> 24741.26 | H43: =F43*300% -> 74223.78 | I43: =F43*7.5% -> 1855.5945 | J43: 0 | K43: =F43*50% -> 12370.63 | L43: =F43*350% -> 86594.41 | M43: =F43*100% -> 24741.26 | N43: =150000 -> 150000 | O43: =F43*10% -> 2474.126 | P43: 15000 | Q43: 0 | R43: =SUM(F43:Q43) -> 392001.06 | V43: 7709.76 | W43: =V43+S43+T43+U43 -> 7709.76 | X43: 376493.27 | Y43: =R43-W43 -> 384291.3 | Z43: 7707.76 | AA43: =V43-Z43 -> 2
A44: 9 | B44: IKPEAZU CHINEDU ANITA | D44: RESEARCH FELLOW II | E44: 13(10) | F44: =25523.45 -> 25523.45 | H44: =F44*300% -> 76570.35 | I44: =F44*7.5% -> 1914.2587 | J44: 0 | K44: =F44*50% -> 12761.725 | L44: =F44*350% -> 89332.075 | M44: =F44*100% -> 25523.45 | N44: =150000 -> 150000 | O44: =F44*10% -> 2552.345 | P44: 15000 | Q44: 0 | R44: =SUM(F44:Q44) -> 399177.65 | V44: 7709.76 | W44: =V44+S44+T44+U44 -> 7709.76 | X44: 384291.3 | Y44: =R44-W44 -> 391467.89 | Z44: 7709.76 | AA44: =V44-Z44 -> 0
A45: 10 | B45: ONYEAKU CHUKWUKA EDMOND | D45: RESEARCH FELLOW II | E45: 13(10) | F45: =25523.45 -> 25523.45 | H45: =F45*300% -> 76570.35 | I45: =F45*7.5% -> 1914.2587 | J45: =J19 -> 0 | K45: =F45*50% -> 12761.725 | L45: =F45*350% -> 89332.075 | M45: =F45*100% -> 25523.45 | N45: =150000 -> 150000 | O45: =F45*10% -> 2552.345 | P45: 15000 | Q45: 0 | R45: =SUM(F45:Q45) -> 399177.65 | S45: =30000 -> 30000 | T45: =182107.04 -> 182107.04 | U45: ='[3]DECEMBER 2019'!$H$46 -> 618.5315 | V45: 7709.76 | W45: =V45+S45+T45+U45 -> 220435.33 | X45: 71565.729 | Y45: =R45-W45 -> 178742.32 | Z45: 7709.76 | AA45: =V45-Z45 -> 0
A46: 11 | B46: DORIS DAKDA AARON | D46: RESEARCH FELLOW II | E46: 13(8) | F46: =23891.12 -> 23891.12 | H46: =F46*300% -> 71673.36 | I46: =F46*7.5% -> 1791.834 | K46: =F46*50% -> 11945.56 | L46: =F46*350% -> 83618.92 | M46: =F46*100% -> 23891.12 | N46: =150000 -> 150000 | O46: =F46*10% -> 2389.112 | P46: 15000 | R46: =SUM(F46:Q46) -> 384201.03 | S46: =50000+10000 -> 60000 | U46: ='[3]DECEMBER 2019'!$H$52 -> 457.041 | V46: 7709.76 | W46: =V46+S46+T46+U46 -> 68166.801 | X46: 263907.5 | Y46: =R46-W46 -> 316034.23 | Z46: 3369.51 | AA46: =V46-Z46 -> 4340.25
B47: TOTAL | D47: 11 | F47: =SUM(F36:F46) -> 359364.45 | H47: =SUM(H36:H46) -> 1078093.4 | I47: =SUM(I36:I46) -> 26952.334 | J47: =SUM(J36:J46) -> 160488.76 | K47: =SUM(K36:K46) -> 179682.23 | L47: =SUM(L36:L46) -> 1257775.6 | M47: =SUM(M36:M46) -> 359364.45 | N47: =SUM(N36:N46) -> 1650000 | O47: =SUM(O36:O46) -> 35936.445 | ... U47: =SUM(U36:U46) -> 1765.8532 | V47: 145551.37 | W47: =SUM(W36:W46) -> 1459321.6 | X47: 3695472.7 | Y47: =R47-W47 -> 3838336 | Z47: 141209.12 | AA47: =V47-Z47 -> 4342.25
AA48: =V48-Z48 -> 0
B49: LEGAL SERVICES | AA49: =V49-Z49 -> 0
A50: 1 | B50: DR SHUIBU DANWANKA | D50: DIRECTOR LEGAL SERVICES | E50: 17(9) | F50: =81740.02 -> 81740.02 | H50: =F50*300% -> 245220.06 | I50: =F50*7.5% -> 6130.5015 | J50: 80244.38 | K50: =F50*50% -> 40870.01 | L50: =F50*350% -> 286090.07 | M50: =F50*100% -> 81740.02 | N50: =150000 -> 150000 | O50: =F50*10% -> 8174.002 | P50: 20000 | Q50: 0 | R50: =SUM(F50:Q50) -> 1000209.1 | U50: 0 | V50: 52776.63 | W50: =S50+T50+U50+V50 -> 52776.63 | X50: 947432.43 | Y50: =R50-W50 -> 947432.43 | Z50: 52776.63 | AA50: =V50-Z50 -> 0
B51: TOTAL | D51: 2 | F51: =SUM(F50:F50) -> 81740.02 | G51: =SUM(G50:G50) -> 0 | H51: =SUM(H50:H50) -> 245220.06 | I51: =SUM(I50:I50) -> 6130.5015 | J51: =SUM(J50:J50) -> 80244.38 | K51: =SUM(K50:K50) -> 40870.01 | L51: =SUM(L50:L50) -> 286090.07 | M51: =SUM(M50:M50) -> 81740.02 | ... R51: =SUM(R50:R50) -> 1000209.1 | U51: =SUM(U50:U50) -> 0 | V51: 52776.63 | W51: =SUM(W50:W50) -> 52776.63 | X51: 947432.43 | Y51: =R51-W51 -> 947432.43 | Z51: 52776.63 | AA51: =V51-Z51 -> 0
AA52: =V52-Z52 -> 0
B53: DEMOCRATIC STUDIES | AA53: =V53-Z53 -> 0
A54: 1 | B54: DR. ADEWALE ADEREMI | D54: DIRECTOR, DEMOCRATIC STUDIES | E54: 17(8) | F54: =79039.64 -> 79039.64 | G54: =0 -> 0 | H54: =F54*300% -> 237118.92 | I54: =F54*7.5% -> 5927.973 | J54: =80244.38 -> 80244.38 | K54: =F54*50% -> 39519.82 | L54: =F54*350% -> 276638.74 | M54: =F54*100% -> 79039.64 | N54: =150000 -> 150000 | O54: =F54*10% -> 7903.964 | P54: 20000 | Q54: 0 | R54: =SUM(F54:Q54) -> 975433.08 | S54: =100000 -> 100000 | V54: 52776.63 | W54: =S54+T54+U54+V54 -> 152776.63 | X54: 797880.83 | Y54: =R54-W54 -> 822656.45 | Z54: 52776.63 | AA54: =V54-Z54 -> 0
A55: 2 | B55: NGARA CHRISTOPHER OCHANJA | D55: RESEARCH FELLOW 1 | E55: 14(9) | F55: =27611.23 -> 27611.23 | H55: =F55*300% -> 82833.69 | I55: =F55*7.5% -> 2070.8422 | K55: =F55*50% -> 13805.615 | L55: =F55*350% -> 96639.305 | M55: =F55*100% -> 27611.23 | N55: =150000 -> 150000 | O55: =F55*10% -> 2761.123 | P55: 15000 | Q55: 0 | R55: =SUM(F55:Q55) -> 418333.04 | S55: =20000 -> 20000 | T55: =163103.59 -> 163103.59 | U55: ='[3]DECEMBER 2019'!$H$50 -> 638.08625 | V55: 7709.76 | W55: =S55+T55+U55+V55 -> 191451.44 | X55: 207726.22 | Y55: =R55-W55 -> 226881.6 | Z55: 7709.76 | AA55: =V55-Z55 -> 0
A56: 3 | B56: EJALONIBU GANIYU LAYI | D56: RESEARCH FELLOW 11 | E56: 13(8) | F56: =23891.12 -> 23891.12 | G56: =0 -> 0 | H56: =F56*300% -> 71673.36 | I56: =F56*7.5% -> 1791.834 | K56: =F56*50% -> 11945.56 | L56: =F56*350% -> 83618.92 | M56: =F56*100% -> 23891.12 | N56: =150000 -> 150000 | O56: =F56*10% -> 2389.112 | P56: 15000 | R56: =SUM(F56:Q56) -> 384201.03 | S56: =110000 -> 110000 | V56: 7709.76 | W56: =S56+T56+U56+V56 -> 117709.76 | X56: 214364.54 | Y56: =R56-W56 -> 266491.27 | Z56: 3369.51 | AA56: =V56-Z56 -> 4340.25
A57: 4 | B57: OSOLAFIA MUHAMMAD EGYE | D57: PERSONNEL OFFICER | E57: 10(11) | F57: =19276.95 -> 19276.95 | H57: =F57*300% -> 57830.85 | I57: =F57*7.5% -> 1445.7713 | J57: 0 | K57: =F57*50% -> 9638.475 | L57: =F57*350% -> 67469.325 | M57: =F57*100% -> 19276.95 | N57: =150000 -> 150000 | O57: =F57*10% -> 1927.695 | P57: 10000 | Q57: 0 | R57: =SUM(F57:Q57) -> 336866.02 | S57: =20000 -> 20000 | T57: =100000 -> 100000 | U57: ='[3]DECEMBER 2019'!$H$45 -> 469.4825 | V57: 3369.51 | W57: =S57+T57+U57+V57 -> 123838.99 | X57: 108461.08 | Y57: =R57-W57 -> 213027.02 | Z57: 3369.51 | AA57: =V57-Z57 -> 0
B58: TOTAL | D58: 4 | F58: =SUM(F54:F57) -> 149818.94 | G58: =SUM(G54:G57) -> 0 | H58: =SUM(H54:H57) -> 449456.82 | I58: =SUM(I54:I57) -> 11236.42 | J58: =SUM(J54:J57) -> 80244.38 | K58: =SUM(K54:K57) -> 74909.47 | L58: =SUM(L54:L57) -> 524366.29 | M58: =SUM(M54:M57) -> 149818.94 | ... U58: =SUM(U54:U57) -> 1107.5688 | V58: 71565.66 | W58: =SUM(R58:V58) -> 2700610 | X58: 1328432.7 | Y58: =SUM(Y54:Y57) -> 1529056.3 | Z58: 67225.41 | AA58: =V58-Z58 -> 4340.25
AA59: =V59-Z59 -> 0
B60: POST GRADUATE SCHOOL | AA60: =V60-Z60 -> 0
A61: 1 | B61: DR ASIMIYU G. ABIOLA | D61: DIRECTOR POST GRADUATE | E61: 17(9) | F61: =81740.02 -> 81740.02 | H61: =F61*300% -> 245220.06 | I61: =F61*7.5% -> 6130.5015 | J61: 80244.38 | K61: =F61*50% -> 40870.01 | L61: =F61*350% -> 286090.07 | M61: =F61*100% -> 81740.02 | N61: =150000 -> 150000 | O61: =F61*10% -> 8174.002 | P61: 20000 | Q61: 0 | R61: =SUM(F61:Q61) -> 1000209.1 | S61: 150000 | T61: =451815.1 -> 451815.1 | U61: 0 | V61: 52776.63 | W61: =SUM(S61:V61) -> 654591.73 | X61: 345617.33 | Y61: =R61-W61 -> 345617.33 | Z61: 52776.63 | AA61: =V61-Z61 -> 0
A62: 2 | B62: DR AUGUSTINE C. OSIGWE | D62: SNR RESEARCH FELLOW | E62: 15(8) | F62: =32263.2 -> 32263.2 | H62: =F62*300% -> 96789.6 | I62: =F62*7.5% -> 2419.74 | J62: =40122.19 -> 40122.19 | K62: =F62*50% -> 16131.6 | L62: =F62*350% -> 112921.2 | M62: =F62*100% -> 32263.2 | N62: =150000 -> 150000 | O62: =F62*10% -> 3226.32 | P62: 20000 | R62: =SUM(F62:Q62) -> 506137.05 | S62: =20000 -> 20000 | T62: =150000 -> 150000 | U62: ='[3]DECEMBER 2019'!$H$42 -> 690.28075 | V62: 15548.33 | W62: =SUM(S62:V62) -> 186238.61 | X62: 244932.99 | Y62: =R62-W62 -> 319898.44 | Z62: 7709.76 | AA62: =V62-Z62 -> 7838.57
A63: 3 | B63: HAUWA PATE SADIQ | D63: PROGRAMME OFFICER | E63: 10(9) | F63: =18281.64 -> 18281.64 | H63: =F63*300% -> 54844.92 | I63: =F63*7.5% -> 1371.123 | K63: =F63*50% -> 9140.82 | L63: =F63*350% -> 63985.74 | M63: =F63*100% -> 18281.64 | N63: =150000 -> 150000 | O63: =F63*10% -> 1828.164 | P63: 10000 | R63: =SUM(F63:Q63) -> 327734.05 | S63: =50000+20000 -> 70000 | T63: =31500 -> 31500 | V63: 3369.51 | W63: =SUM(S63:V63) -> 104869.51 | X63: 238298.69 | Y63: =R63-W63 -> 222864.54 | Z63: 3369.51 | AA63: =V63-Z63 -> 0
A64: 4 | B64: UZODINMA EMMANUEL EZENWA | D64: RESEARCH FELLOW II | E64: 13(8) | F64: =23891.12 -> 23891.12 | H64: =F64*300% -> 71673.36 | I64: =F64*7.5% -> 1791.834 | J64: 0 | K64: =F64*50% -> 11945.56 | L64: =F64*350% -> 83618.92 | M64: =F64*100% -> 23891.12 | N64: =150000 -> 150000 | O64: =F64*10% -> 2389.112 | P64: 15000 | Q64: 0 | R64: =SUM(F64:Q64) -> 384201.03 | S64: =0 -> 0 | T64: =0 -> 0 | U64: ='[3]DECEMBER 2019'!$H$48 -> 469.4825 | V64: 7709.76 | W64: =S64+T64+U64+V64 -> 8179.2425 | X64: 328461.08 | Y64: =R64-W64 -> 376021.78 | Z64: 3369.51 | AA64: =V64-Z64 -> 4340.25
B65: TOTAL | D65: 4 | F65: =SUM(F61:F64) -> 156175.98 | H65: =SUM(H61:H64) -> 468527.94 | I65: =SUM(I61:I64) -> 11713.198 | J65: =SUM(J61:J64) -> 120366.57 | K65: =SUM(K61:K64) -> 78087.99 | L65: =SUM(L61:L64) -> 546615.93 | M65: =SUM(M61:M64) -> 156175.98 | N65: =SUM(N61:N64) -> 600000 | O65: =SUM(O61:O64) -> 15617.598 | ... U65: =SUM(U61:U64) -> 1159.7632 | V65: 79404.23 | W65: =SUM(W61:W64) -> 953879.09 | X65: 1157310.1 | Y65: =SUM(Y61:Y64) -> 1264402.1 | Z65: 67225.41 | AA65: =V65-Z65 -> 12178.82
AA66: =V66-Z66 -> 0
B67: ECONOMIC AND SOCIAL DEV. | AA67: =V67-Z67 -> 0
A68: 1 | B68: DR ADEYEMI AKEEB FAJINGBESI | D68: DIR. ECO. & SOCIAL DEV | E68: 17(9) | F68: 81740.02 | H68: =F68*300% -> 245220.06 | I68: =F68*7.5% -> 6130.5015 | J68: 80244.38 | K68: =F68*50% -> 40870.01 | L68: =F68*350% -> 286090.07 | M68: =F68*100% -> 81740.02 | N68: =150000 -> 150000 | O68: =F68*10% -> 8174.002 | P68: 20000 | Q68: 0 | R68: =SUM(F68:Q68) -> 1000209.1 | S68: 200000 | T68: =59722.22 -> 59722.22 | U68: ='[3]DECEMBER 2019'!$H$39 -> 2043.5005 | V68: 52776.63 | W68: =SUM(S68:V68) -> 314542.35 | X68: 685666.71 | Y68: =R68-W68 -> 685666.71 | Z68: 52776.63 | AA68: =V68-Z68 -> 0
A69: 2 | B69: DR ASEMOTA OMOROGBE JOSEPH | D69: SENIOR RESEARCH FELLOW | E69: 15(9) | F69: =33507.5 -> 33507.5 | H69: =F69*300% -> 100522.5 | I69: =F69*7.5% -> 2513.0625 | J69: 40122.19 | K69: =F69*50% -> 16753.75 | L69: =F69*350% -> 117276.25 | M69: =F69*100% -> 33507.5 | N69: =150000 -> 150000 | O69: =F69*10% -> 3350.75 | P69: 20000 | R69: =SUM(F69:Q69) -> 517553.5 | V69: 15548.33 | W69: =SUM(S69:V69) -> 15548.33 | X69: 502005.17 | Y69: =R69-W69 -> 502005.17 | Z69: 15548.33 | AA69: =V69-Z69 -> 0
A70: 3 | B70: TERFA WILLIAMS ABRAHAM | D70: SNR RESEARCH FELLOW | E70: 15(8) | F70: =32263.2 -> 32263.2 | H70: =F70*300% -> 96789.6 | I70: =F70*7.5% -> 2419.74 | J70: =40122.19 -> 40122.19 | K70: =F70*50% -> 16131.6 | L70: =F70*350% -> 112921.2 | M70: =F70*100% -> 32263.2 | N70: =150000 -> 150000 | O70: =F70*10% -> 3226.32 | P70: 20000 | R70: =SUM(F70:Q70) -> 506137.05 | V70: 15548.33 | W70: =SUM(S70:V70) -> 15548.33 | X70: 423684.25 | Y70: =R70-W70 -> 490588.72 | Z70: 7709.76 | AA70: =V70-Z70 -> 7838.57
A71: 4 | B71: JUMARE FADILA | D71: RESEARCH FELLOW I | E71: 14(9) | F71: =27611.23 -> 27611.23 | H71: =F71*300% -> 82833.69 | I71: =F71*7.5% -> 2070.8422 | J71: 0 | K71: =F71*50% -> 13805.615 | L71: =F71*350% -> 96639.305 | M71: =F71*100% -> 27611.23 | N71: =150000 -> 150000 | O71: =F71*10% -> 2761.123 | P71: 15000 | Q71: 0 | R71: =SUM(F71:Q71) -> 418333.04 | S71: 5000 | V71: 7709.76 | W71: =SUM(S71:V71) -> 12709.76 | X71: 386467.89 | Y71: =R71-W71 -> 405623.28 | Z71: 7709.76 | AA71: =V71-Z71 -> 0
A72: 5 | B72: OMOJU OLUWASOLA EMMANUEL | D72: RESEARCH FELLOW I | E72: 14(9) | F72: =27611.23 -> 27611.23 | H72: =F72*300% -> 82833.69 | I72: =F72*7.5% -> 2070.8422 | K72: =F72*50% -> 13805.615 | L72: =F72*350% -> 96639.305 | M72: =F72*100% -> 27611.23 | N72: =150000 -> 150000 | O72: =F72*10% -> 2761.123 | P72: 15000 | R72: =SUM(F72:Q72) -> 418333.04 | S72: =50000 -> 50000 | T72: =87500 -> 87500 | V72: 7709.76 | W72: =SUM(S72:V72) -> 145209.76 | X72: 246791.3 | Y72: =R72-W72 -> 273123.28 | Z72: 7709.76 | AA72: =V72-Z72 -> 0
A73: 6 | B73: UDEFUNA NNADOZIE PATRICK | D73: RESEARCH OFFICER | E73: 10(13) | F73: =19774.62 -> 19774.62 | H73: =F73*300% -> 59323.86 | I73: =F73*7.5% -> 1483.0965 | J73: 0 | K73: =F73*50% -> 9887.31 | L73: =F73*350% -> 69211.17 | M73: =F73*100% -> 19774.62 | N73: =150000 -> 150000 | O73: =F73*10% -> 1977.462 | P73: 10000 | Q73: 0 | R73: =SUM(F73:Q73) -> 341432.14 | S73: =10000 -> 10000 | T73: =131771.66 -> 131771.66 | V73: 3369.51 | W73: =SUM(S73:V73) -> 145141.17 | X73: 76290.969 | Y73: =R73-W73 -> 196290.97 | Z73: 3369.51 | AA73: =V73-Z73 -> 0
A74: 7 | B74: EMILY EDOISA IKHIDE | D74: RESEARCH FELLOW II | E74: 13(10) | F74: =25523.45 -> 25523.45 | H74: =F74*300% -> 76570.35 | I74: =F74*7.5% -> 1914.2587 | K74: =F74*50% -> 12761.725 | L74: =F74*350% -> 89332.075 | M74: =F74*100% -> 25523.45 | N74: =150000 -> 150000 | O74: =F74*10% -> 2552.345 | P74: 15000 | R74: =SUM(F74:Q74) -> 399177.65 | S74: =50000 -> 50000 | T74: =45833.33 -> 45833.33 | V74: 7709.76 | W74: =SUM(S74:V74) -> 103543.09 | X74: 288457.97 | Y74: =R74-W74 -> 295634.56 | Z74: 7709.76 | AA74: =V74-Z74 -> 0
A75: 8 | B75: ONYIMADU C. ONYEBUCHI | D75: RESEARCH FELLOW I | E75: 14(9) | F75: =27611.23 -> 27611.23 | H75: =F75*300% -> 82833.69 | I75: =F75*7.5% -> 2070.8422 | K75: =F75*50% -> 13805.615 | L75: =F75*350% -> 96639.305 | M75: =F75*100% -> 27611.23 | N75: =150000 -> 150000 | O75: =F75*10% -> 2761.123 | P75: 15000 | R75: =SUM(F75:Q75) -> 418333.04 | S75: =50000 -> 50000 | U75: ='[3]DECEMBER 2019'!$H$54 -> 618.5315 | V75: 7709.76 | W75: =SUM(S75:V75) -> 58328.291 | X75: 333672.77 | Y75: =R75-W75 -> 360004.74 | Z75: 7709.76 | AA75: =V75-Z75 -> 0
A76: 9 | B76: IBE EZECHI CYRIACUS | D76: RESEARCH FELLOW II | E76: 13(8) | F76: =23891.12 -> 23891.12 | H76: =F76*300% -> 71673.36 | I76: =F76*7.5% -> 1791.834 | J76: 0 | K76: =F76*50% -> 11945.56 | L76: =F76*350% -> 83618.92 | M76: =F76*100% -> 23891.12 | N76: =150000 -> 150000 | O76: =F76*10% -> 2389.112 | P76: 15000 | Q76: 0 | R76: =SUM(F76:Q76) -> 384201.03 | S76: =50000 -> 50000 | V76: 7709.76 | W76: =SUM(S76:V76) -> 57709.76 | X76: 299364.54 | Y76: =R76-W76 -> 326491.27 | Z76: 3369.51 | AA76: =V76-Z76 -> 4340.25
B77: TOTAL | D77: 9 | F77: =SUM(F68:F76) -> 299533.6 | H77: =SUM(H68:H76) -> 898600.8 | I77: =SUM(I68:I76) -> 22465.02 | J77: =SUM(J68:J76) -> 160488.76 | K77: =SUM(K68:K76) -> 149766.8 | L77: =SUM(L68:L76) -> 1048367.6 | M77: =SUM(M68:M76) -> 299533.6 | N77: =SUM(N68:N76) -> 1350000 | O77: =SUM(O68:O76) -> 29953.36 | ... U77: =SUM(U68:U76) -> 2662.032 | V77: 125791.6 | W77: =SUM(S77:V77) -> 868280.84 | X77: 3242401.6 | Y77: =SUM(Y68:Y76) -> 3535428.7 | Z77: 113612.78 | AA77: =V77-Z77 -> 12178.82
AA78: =V78-Z78 -> 0
B79: TRAINING AND INTERNATIONAL COOP | AA79: =V79-Z79 -> 0
A80: 1 | B80: DR JAKE DABANG DAN AZUMI | D80: DEPUTY DIRECTOR TRAINING | E80: 16(7) | F80: =39662.25 -> 39662.25 | H80: =F80*300% -> 118986.75 | I80: =F80*7.5% -> 2974.6687 | J80: 40122.19 | K80: =F80*50% -> 19831.125 | L80: =F80*350% -> 138817.88 | M80: =F80*100% -> 39662.25 | N80: 150000 | O80: =F80*10% -> 3966.225 | P80: 20000 | Q80: 150000 | R80: =SUM(F80:Q80) -> 724023.33 | U80: ='[3]DECEMBER 2019'!$H$30 -> 837.6875 | V80: 15548.33 | W80: =SUM(S80:V80) -> 16386.018 | X80: 651167.48 | Y80: =R80-W80 -> 707637.32 | Z80: 15548.33 | AA80: =V80-Z80 -> 0
A81: 2 | B81: DR FRANCIS NDUM OJIE | D81: ASST. MANAGER, TRAINING | E81: 14(7) | F81: =27611.23 -> 27611.23 | H81: =F81*300% -> 82833.69 | I81: =F81*7.5% -> 2070.8422 | K81: =F81*50% -> 13805.615 | L81: =F81*350% -> 96639.305 | M81: =F81*100% -> 27611.23 | N81: 100000 | O81: =F81*10% -> 2761.123 | P81: 15000 | R81: =SUM(F81:Q81) -> 368333.04 | V81: 7709.76 | W81: =SUM(S81:V81) -> 7709.76 | X81: 334291.3 | Y81: =R81-W81 -> 360623.28 | Z81: 7709.76 | AA81: =V81-Z81 -> 0
A82: 3 | B82: OKECHUKWU UCHENNA HULDA | D82: ADMIN OFFICER | E82: 10(9) | F82: =18281.64 -> 18281.64 | H82: =F82*300% -> 54844.92 | I82: =F82*7.5% -> 1371.123 | K82: =F82*50% -> 9140.82 | L82: =F82*350% -> 63985.74 | M82: =F82*100% -> 18281.64 | N82: =100000 -> 100000 | O82: =F82*10% -> 1828.164 | P82: 10000 | R82: =SUM(F82:Q82) -> 277734.05 | S82: =5000 -> 5000 | T82: =0 -> 0 | V82: 3369.51 | W82: =SUM(S82:V82) -> 8369.51 | X82: 264798.69 | Y82: =R82-W82 -> 269364.54 | Z82: 3369.51 | AA82: =V82-Z82 -> 0
A83: 4 | B83: HASSANA AHMED IBRAHIM | E83: 10(8) | F83: =17784 -> 17784 | G83: =0 -> 0 | H83: =F83*300% -> 53352 | I83: =F83*7.5% -> 1333.8 | K83: =F83*50% -> 8892 | L83: =F83*350% -> 62244 | M83: =F83*100% -> 17784 | N83: 100000 | O83: =F83*10% -> 1778.4 | P83: 10000 | R83: =SUM(F83:Q83) -> 273168.2 | S83: =30000 -> 30000 | U83: =444.6 -> 444.6 | V83: 3369.51 | W83: =SUM(S83:V83) -> 33814.11 | X83: 234787.97 | Y83: =R83-W83 -> 239354.09 | Z83: 3369.51 | AA83: =V83-Z83 -> 0
B84: TOTAL | D84: 4 | F84: =SUM(F80:F83) -> 103339.12 | G84: =SUM(G80:G83) -> 0 | H84: =SUM(H80:H83) -> 310017.36 | I84: =SUM(I80:I83) -> 7750.434 | J84: =SUM(J80:J83) -> 40122.19 | K84: =SUM(K80:K83) -> 51669.56 | L84: =SUM(L80:L83) -> 361686.92 | M84: =SUM(M80:M83) -> 103339.12 | ... U84: =SUM(U80:U83) -> 1282.2875 | V84: 29997.11 | W84: =SUM(S84:V84) -> 66279.397 | X84: 1485045.4 | Y84: =SUM(Y80:Y83) -> 1576979.2 | Z84: 29997.11 | AA84: =V84-Z84 -> 0
AA85: =V85-Z85 -> 0
B86: LIBRARY AND DOCUMENTATION | AA86: =V86-Z86 -> 0
A87: 1 | B87: DR MAIMUNA IZAH | D87: INSITUTE LIBRARIAN | E87: 17(8) | F87: =79039.64 -> 79039.64 | H87: =F87*300% -> 237118.92 | I87: =F87*7.5% -> 5927.973 | J87: 80244.38 | K87: =F87*50% -> 39519.82 | L87: =F87*350% -> 276638.74 | M87: =F87*100% -> 79039.64 | N87: 150000 | O87: =F87*10% -> 7903.964 | P87: 20000 | Q87: 0 | R87: =SUM(F87:Q87) -> 975433.08 | S87: =100000 -> 100000 | T87: 0 | U87: 0 | V87: 52776.63 | W87: =SUM(S87:V87) -> 152776.63 | X87: 797880.83 | Y87: =R87-W87 -> 822656.45 | Z87: 52776.63 | AA87: =V87-Z87 -> 0
A88: 2 | B88: CATHERINE E. IKOKOH | D88: SNR RESEARCH FELLOW DOCU | E88: 15(9) | F88: =33507.5 -> 33507.5 | H88: =F88*300% -> 100522.5 | I88: =F88*7.5% -> 2513.0625 | J88: 40122.19 | K88: =F88*50% -> 16753.75 | L88: =F88*350% -> 117276.25 | M88: =F88*100% -> 33507.5 | N88: 150000 | O88: =F88*10% -> 3350.75 | P88: 20000 | Q88: 0 | R88: =SUM(F88:Q88) -> 517553.5 | S88: 40000 | T88: =131250 -> 131250 | U88: ='[3]DECEMBER 2019'!$H$37 -> 837.6875 | V88: 15548.33 | W88: =SUM(S88:V88) -> 187636.02 | X88: 329917.48 | Y88: =R88-W88 -> 329917.48 | Z88: 15548.33 | AA88: =V88-Z88 -> 0
A89: 3 | B89: ALIYU SANNI ABUBAKAR | D89: RESEARCH FELLOW 11 DATA & DOCU. OFFICER | E89: 13(11) | F89: =26339.3 -> 26339.3 | H89: =F89*300% -> 79017.9 | I89: =F89*7.5% -> 1975.4475 | J89: 0 | K89: =F89*50% -> 13169.65 | L89: =F89*350% -> 92187.55 | M89: =F89*100% -> 26339.3 | N89: 150000 | O89: =F89*10% -> 2633.93 | P89: 15000 | Q89: 0 | R89: =SUM(F89:Q89) -> 406663.08 | S89: 30000 | T89: =0 -> 0 | U89: ='[3]DECEMBER 2019'!$H$40 -> 638.08625 | V89: 7709.76 | W89: =SUM(S89:V89) -> 38347.846 | X89: 360829.81 | Y89: =R89-W89 -> 368315.23 | Z89: 7709.76 | AA89: =V89-Z89 -> 0
A90: 4 | B90: CHINAKO N. ASOGWA | D90: LIBRARY OFFICER | E90: 13(9) | F90: =24741.26 -> 24741.26 | H90: =F90*300% -> 74223.78 | I90: =F90*7.5% -> 1855.5945 | J90: 0 | K90: =F90*50% -> 12370.63 | L90: =F90*350% -> 86594.41 | M90: =F90*100% -> 24741.26 | N90: 150000 | O90: =F90*10% -> 2474.126 | P90: 15000 | R90: =SUM(F90:Q90) -> 392001.06 | S90: =50000 -> 50000 | T90: =43083.33 -> 43083.33 | V90: 7709.76 | W90: =SUM(S90:V90) -> 100793.09 | X90: 254111.91 | Y90: =R90-W90 -> 291207.97 | Z90: 3369.51 | AA90: =V90-Z90 -> 4340.25
B91: TOTAL | D91: 4 | F91: =SUM(F87:F90) -> 163627.7 | H91: =SUM(H87:H90) -> 490883.1 | I91: =SUM(I87:I90) -> 12272.077 | J91: =SUM(J87:J90) -> 120366.57 | K91: =SUM(K87:K90) -> 81813.85 | L91: =SUM(L87:L90) -> 572696.95 | M91: =SUM(M87:M90) -> 163627.7 | N91: =SUM(N87:N90) -> 600000 | O91: =SUM(O87:O90) -> 16362.77 | ... U91: =SUM(U87:U90) -> 1475.7738 | V91: 83744.48 | W91: =SUM(S91:V91) -> 479553.58 | X91: 1742740 | Y91: =SUM(Y87:Y90) -> 1812097.1 | Z91: 79404.23 | AA91: =V91-Z91 -> 4340.25
AA92: =V92-Z92 -> 0
B93: FINANCE & ACCOUNT | AA93: =V93-Z93 -> 0
A94: 1 | B94: IBRAHIM M. MSHELIA | D94: DIR. FINANCE & ACCOUNTS | E94: 17(9) | F94: =81740.02 -> 81740.02 | H94: =F94*300% -> 245220.06 | I94: =F94*7.5% -> 6130.5015 | J94: =80244.38 -> 80244.38 | K94: =F94*50% -> 40870.01 | L94: =F94*350% -> 286090.07 | M94: =F94*100% -> 81740.02 | N94: =100000 -> 100000 | O94: =F94*10% -> 8174.002 | P94: 20000 | Q94: 100000 | R94: =SUM(F94:Q94) -> 1050209.1 | S94: =200000 -> 200000 | T94: =227777.78 -> 227777.78 | U94: ='[3]DECEMBER 2019'!$H$24 -> 1975.991 | V94: 52776.63 | W94: =SUM(S94:V94) -> 482530.4 | X94: 542902.68 | Y94: =R94-W94 -> 567678.66 | Z94: 52776.63 | AA94: =V94-Z94 -> 0
A95: 2 | B95: KABIR MUHAMMAD SULAIMAN | D95: DD FINANCE & ACCOUNTS | E95: 16(9) | F95: =42653.17 -> 42653.17 | H95: =F95*300% -> 127959.51 | I95: =F95*7.5% -> 3198.9877 | J95: 40122.19 | K95: =F95*50% -> 21326.585 | L95: =F95*350% -> 149286.1 | M95: =F95*100% -> 42653.17 | N95: =100000 -> 100000 | O95: =F95*10% -> 4265.317 | P95: 20000 | Q95: =100000 -> 100000 | R95: =SUM(F95:Q95) -> 651465.02 | S95: =100000 -> 100000 | T95: =0 -> 0 | V95: 21618.09 | W95: =SUM(S95:V95) -> 121618.09 | X95: 516125.91 | Y95: =R95-W95 -> 529846.93 | Z95: 21618.09 | AA95: =V95-Z95 -> 0
A96: 3 | B96: RAHILA NURUDEEN HABU | D96: MANAGER, ACCOUNTS | E96: 15(9) | F96: =33507.5 -> 33507.5 | H96: =F96*300% -> 100522.5 | I96: =F96*7.5% -> 2513.0625 | J96: 40122.19 | K96: =F96*50% -> 16753.75 | L96: =F96*350% -> 117276.25 | M96: =F96*100% -> 33507.5 | N96: =100000 -> 100000 | O96: =F96*10% -> 3350.75 | P96: 20000 | Q96: 0 | R96: =SUM(F96:Q96) -> 467553.5 | S96: =70000 -> 70000 | T96: =129166.67 -> 129166.67 | U96: ='[3]DECEMBER 2019'!$H$23 -> 806.58 | V96: 15548.33 | W96: =SUM(S96:V96) -> 215521.58 | X96: 240615.47 | Y96: =R96-W96 -> 252031.92 | Z96: 15548.33 | AA96: =V96-Z96 -> 0
A97: 4 | B97: ANDRAWUS MUSA | D97: MGR. STORE | E97: 15(8) | F97: =32263.2 -> 32263.2 | H97: =F97*300% -> 96789.6 | I97: =F97*7.5% -> 2419.74 | J97: =40122.19 -> 40122.19 | K97: =F97*50% -> 16131.6 | L97: =F97*350% -> 112921.2 | M97: =F97*100% -> 32263.2 | N97: =100000 -> 100000 | O97: =F97*10% -> 3226.32 | P97: 20000 | Q97: 0 | R97: =SUM(F97:Q97) -> 456137.05 | S97: =50000 -> 50000 | T97: =90000 -> 90000 | U97: ='[3]DECEMBER 2019'!$H$32 -> 638.08625 | V97: 15548.33 | W97: =SUM(S97:V97) -> 156186.42 | X97: 200829.81 | Y97: =R97-W97 -> 299950.63 | Z97: 7709.76 | AA97: =V97-Z97 -> 7838.57
A98: 5 | B98: TONDO IORWUESE EDWARD | D98: MGR ACCOUNTS | E98: 15(8) | F98: =32263.2 -> 32263.2 | H98: =F98*300% -> 96789.6 | I98: =F98*7.5% -> 2419.74 | J98: =40122.19 -> 40122.19 | K98: =F98*50% -> 16131.6 | L98: =F98*350% -> 112921.2 | M98: =F98*100% -> 32263.2 | N98: =100000 -> 100000 | O98: =F98*10% -> 3226.32 | P98: 20000 | Q98: =100000 -> 100000 | R98: =SUM(F98:Q98) -> 556137.05 | S98: =100000 -> 100000 | T98: =100000 -> 100000 | U98: ='[3]DECEMBER 2019'!$H$25 -> 638.08625 | V98: 15548.33 | W98: =SUM(S98:V98) -> 216186.42 | X98: 310829.81 | Y98: =R98-W98 -> 339950.63 | Z98: 7709.76 | AA98: =V98-Z98 -> 7838.57
A99: 6 | B99: SHEHU ABDULLAHI | D99: ASST. MANAGER, ACCOUNTS | E99: 13(9) | F99: =24741.26 -> 24741.26 | G99: 0 | H99: =F99*300% -> 74223.78 | I99: =F99*7.5% -> 1855.5945 | J99: 0 | K99: =F99*50% -> 12370.63 | L99: =F99*350% -> 86594.41 | M99: =F99*100% -> 24741.26 | N99: =100000 -> 100000 | O99: =F99*10% -> 2474.126 | P99: 15000 | Q99: 0 | R99: =SUM(F99:Q99) -> 342001.06 | S99: =30000 -> 30000 | T99: =75000 -> 75000 | V99: 7709.76 | W99: =SUM(S99:V99) -> 112709.76 | X99: 226491.27 | Y99: =R99-W99 -> 229291.3 | Z99: 7709.76 | AA99: =V99-Z99 -> 0
A100: 7 | B100: OJOGIWA ABISOLA GANIAT | D100: ASST. MGR ACCOUNT | E100: 13(8) | F100: =23891.12 -> 23891.12 | H100: =F100*300% -> 71673.36 | I100: =F100*7.5% -> 1791.834 | K100: =F100*50% -> 11945.56 | L100: =F100*350% -> 83618.92 | M100: =F100*100% -> 23891.12 | N100: =100000 -> 100000 | O100: =F100*10% -> 2389.112 | P100: 15000 | Q100: =30000 -> 30000 | R100: =SUM(F100:Q100) -> 364201.03 | S100: =70000+70000 -> 140000 | T100: =45833.33 -> 45833.33 | U100: ='[3]DECEMBER 2019'!$H$55 -> 469.4825 | V100: 7709.76 | W100: =SUM(S100:V100) -> 194012.57 | X100: 132627.75 | Y100: =R100-W100 -> 170188.45 | Z100: 3369.51 | AA100: =V100-Z100 -> 4340.25
A101: 8 | B101: RAHILA SALIHU | D101: ASST. MGR ACCOUNT | E101: 13(8) | F101: =23891.12 -> 23891.12 | H101: =F101*300% -> 71673.36 | I101: =F101*7.5% -> 1791.834 | K101: =F101*50% -> 11945.56 | L101: =F101*350% -> 83618.92 | M101: =F101*100% -> 23891.12 | N101: =100000 -> 100000 | O101: =F101*10% -> 2389.112 | P101: 15000 | R101: =SUM(F101:Q101) -> 334201.03 | S101: =70000+40000 -> 110000 | T101: =95555.56 -> 95555.56 | U101: ='[3]DECEMBER 2019'!$H$28 -> 469.4825 | V101: 7709.76 | W101: =SUM(S101:V101) -> 213734.8 | X101: 112905.52 | Y101: =R101-W101 -> 120466.22 | Z101: 3369.51 | AA101: =V101-Z101 -> 4340.25
A102: 9 | B102: USMAN WAZIRI | D102: PRINCIPAL CONF. SECRETARY | E102: 13(10) | F102: =25523.45 -> 25523.45 | H102: =F102*300% -> 76570.35 | I102: =F102*7.5% -> 1914.2587 | J102: 0 | K102: =F102*50% -> 12761.725 | L102: =F102*350% -> 89332.075 | M102: =F102*100% -> 25523.45 | N102: =100000 -> 100000 | O102: =F102*10% -> 2552.345 | P102: 15000 | Q102: 0 | R102: =SUM(F102:Q102) -> 349177.65 | S102: =3000 -> 3000 | T102: =90000 -> 90000 | V102: 7709.76 | W102: =SUM(S102:V102) -> 100709.76 | X102: 201291.3 | Y102: =R102-W102 -> 248467.89 | Z102: 7709.76 | AA102: =V102-Z102 -> 0
...

Sheet ANNUAL INCREMENT
B3: STAFF PAYROLL FOR THE MONTH OF DECEMBER, 2020
F4: ='[1]FEB 08'!E8/'[1]FEB 08'!M8 -> 0.22 | I4: ='[1]FEB 08'!F8/'[1]FEB 08'!Q8 -> 0.3
B5: STAFF NAME | U5: DEDUCTIONS | AA5: NET SALARY
D6: DESIGNATION | E6: SALARY | F6: BASIC | M6: MOTOR/ | N6: RESEARCH | O6: LEAVE | P6: OUT FIT | Q6: LEGISLATIVE | R6: DECEMBER 2020 GROSS | S6: JANUARY 2021 GROSS | T6: ANNUAL INCREMENT/PROMOTION | Z6: NOVEMBER,2020 | AA6: DECEMBER,2020
E7: LEVEL | F7: SALARY | G7: SALARY/ALLOWCE AREARS | H7: RENT | I7: UTILITY | J7: DOMESTIC | K7: ENTERT. | L7: FURNIT. | M7: FUEL | N7: ALLOWANCE | O7: ALLCE | P7: ALLCE | Q7: DUTY ALLCE | R7: SALARY | S7: SALARY | U7: COOP SOCIETY | V7: COOP. LOAN RECOVERY | W7: NHF DEDUCTION | X7: PAYE | Y7: TOTAL
A8: S/N | B8: DG OFFICE | F8: N | I8: N | R8: N | S8: N | X8: N
A9: 1 | B9: PROF. ABUBAKAR O. SULAIMAN | D9: DIRECTOR GENERAL | E9: CONSOL | F9: 160488.75 | H9: 320977.5 | I9: 48146.63 | J9: 120366.57 | K9: 72219.94 | L9: 0 | M9: 120366.57 | N9: =200000 -> 200000 | O9: 16048.88 | P9: 25000 | Q9: 25235 | R9: =SUM(F9:Q9) -> 1108849.8 | S9: 1108849.8 | T9: =S9-R9 -> 0 | X9: 113176.97 | Y9: =U9+V9+W9+X9 -> 113176.97 | Z9: 995672.87 | AA9: =R9-Y9 -> 995672.87
A10: 2 | B10: AKINSANMI ADEJOKE OLUKEMI | D10: AM INFORMATION | E10: 15(9) | F10: 33507.5 | H10: =F10*300% -> 100522.5 | I10: =F10*7.5% -> 2513.0625 | J10: 40122.19 | K10: =F10*50% -> 16753.75 | L10: =F10*350% -> 117276.25 | M10: =F10*100% -> 33507.5 | N10: =100000 -> 100000 | O10: =F10*10% -> 3350.75 | P10: 20000 | Q10: =100000 -> 100000 | R10: =SUM(F10:Q10) -> 567553.5 | S10: 567553.5 | T10: =S10-R10 -> 0 | U10: =0 -> 0 | V10: 0 | W10: ='[3]DECEMBER 2019'!$H$29 -> 837.6875 | X10: 15548.33 | Y10: =U10+V10+W10+X10 -> 16386.018 | Z10: 551167.48 | AA10: =R10-Y10 -> 551167.48
A11: 3 | B11: DR IKEME ARTHUR J.O | D11: SNR RESEARCH FELLOW | E11: 15(9) | F11: =33507.5 -> 33507.5 | H11: =F11*300% -> 100522.5 | I11: =F11*7.5% -> 2513.0625 | J11: 40122.19 | K11: =F11*50% -> 16753.75 | L11: =F11*350% -> 117276.25 | M11: =F11*100% -> 33507.5 | N11: =100000 -> 100000 | O11: =F11*10% -> 3350.75 | P11: 20000 | Q11: 0 | R11: =SUM(F11:Q11) -> 467553.5 | S11: 467553.5 | T11: =S11-R11 -> 0 | U11: 50000 | V11: =212642 -> 212642 | W11: ='[3]DECEMBER 2019'!$H$38 -> 837.6875 | X11: 15548.33 | Y11: =SUM(U11:X11) -> 279028.02 | Z11: 188525.48 | AA11: =R11-Y11 -> 188525.48
A12: 4 | B12: MOSHOOD M. OLALERE | D12: MANAGER ADMIN DG's OFFICE | E12: 15(9) | F12: =33507.5 -> 33507.5 | H12: =F12*300% -> 100522.5 | I12: =F12*7.5% -> 2513.0625 | J12: 40122.19 | K12: =F12*50% -> 16753.75 | L12: =F12*350% -> 117276.25 | M12: =F12*100% -> 33507.5 | N12: =100000 -> 100000 | O12: =F12*10% -> 3350.75 | P12: 20000 | Q12: 0 | R12: =SUM(F12:Q12) -> 467553.5 | S12: 467553.5 | T12: =S12-R12 -> 0 | U12: =5000 -> 5000 | V12: =179017.51 -> 179017.51 | W12: ='[3]DECEMBER 2019'!$H$35 -> 837.6875 | X12: 15548.33 | Y12: =U12+V12+W12+X12 -> 200403.53 | Z12: 267149.97 | AA12: =R12-Y12 -> 267149.97
A13: 5 | B13: SARAFADEEN ALABELEWE | D13: SA ADMINISTRATION | E13: 16(8) | F13: =41157.69 -> 41157.69 | H13: =F13*300% -> 123473.07 | I13: =F13*7.5% -> 3086.8268 | J13: 40122.19 | K13: =F13*50% -> 20578.845 | L13: =F13*350% -> 144051.92 | M13: =F13*100% -> 41157.69 | N13: =100000 -> 100000 | O13: =F13*10% -> 4115.769 | P13: 20000 | R13: =SUM(F13:Q13) -> 537744 | S13: 551465.02 | T13: =S13-R13 -> 13721.029 | U13: =100000 -> 100000 | V13: =137500 -> 137500 | X13: 21618.09 | Y13: =U13+V13+W13+X13 -> 259118.09 | Z13: 278625.91 | AA13: =R13-Y13 -> 278625.91
A14: 6 | B14: DR ABDULSALAM NASIRU NAEEM | D14: SA ACADEMICS | E14: 15(8) | F14: =32263.2 -> 32263.2 | H14: =F14*300% -> 96789.6 | I14: =F14*7.5% -> 2419.74 | J14: 40122.19 | K14: =F14*50% -> 16131.6 | L14: =F14*350% -> 112921.2 | M14: =F14*100% -> 32263.2 | N14: =150000 -> 150000 | O14: =F14*10% -> 3226.32 | P14: 20000 | Q14: =100000 -> 100000 | R14: =SUM(F14:Q14) -> 606137.05 | S14: 674023.33 | T14: =S14-R14 -> 67886.284 | X14: 15548.33 | Y14: =U14+V14+W14+X14 -> 15548.33 | Z14: 590588.72 | AA14: =R14-Y14 -> 590588.72
A15: 7 | B15: TOKUNBO ALFRED ADULOJU | D15: AM LIAISON OFFICE | E15: 13(9) | F15: =24741.26 -> 24741.26 | H15: =F15*300% -> 74223.78 | I15: =F15*7.5% -> 1855.5945 | K15: =F15*50% -> 12370.63 | L15: =F15*350% -> 86594.41 | M15: =F15*100% -> 24741.26 | N15: =100000 -> 100000 | O15: =F15*10% -> 2474.126 | P15: 15000 | Q15: =100000 -> 100000 | R15: =SUM(F15:Q15) -> 442001.06 | S15: 449177.65 | T15: =S15-R15 -> 7176.5933 | U15: =100000 -> 100000 | V15: =0 -> 0 | W15: ='[3]DECEMBER 2019'!$H$22 -> 618.5315 | X15: 7709.76 | Y15: =U15+V15+W15+X15 -> 108328.29 | Z15: 264922.77 | AA15: =R15-Y15 -> 333672.77
A16: 8 | B16: HUSSEIN EGYE MUSA | D16: AM PROTOCOL | E16: 13(9) | F16: =24741.26 -> 24741.26 | H16: =F16*300% -> 74223.78 | I16: =F16*7.5% -> 1855.5945 | K16: =F16*50% -> 12370.63 | L16: =F16*350% -> 86594.41 | M16: =F16*100% -> 24741.26 | N16: =100000 -> 100000 | O16: =F16*10% -> 2474.126 | P16: 15000 | Q16: 50000 | R16: =SUM(F16:Q16) -> 392001.06 | S16: 399177.65 | T16: =S16-R16 -> 7176.5933 | U16: 10000 | V16: =103000 -> 103000 | W16: 0 | X16: 7709.76 | Y16: =U16+V16+W16+X16 -> 120709.76 | Z16: 271291.3 | AA16: =R16-Y16 -> 271291.3
A17: 9 | B17: DONALD E. MKPANAM | D17: AM ICT | E17: 13(11) | F17: 26339.3 | H17: =F17*300% -> 79017.9 | I17: =F17*7.5% -> 1975.4475 | K17: =F17*50% -> 13169.65 | L17: =F17*350% -> 92187.55 | M17: =F17*100% -> 26339.3 | N17: =100000 -> 100000 | O17: =F17*10% -> 2633.93 | P17: 15000 | Q17: 0 | R17: =SUM(F17:Q17) -> 356663.08 | S17: 356663.08 | T17: =S17-R17 -> 0 | W17: ='[3]DECEMBER 2019'!$H$31 -> 658.4825 | X17: 7709.76 | Y17: =U17+V17+W17+X17 -> 8368.2425 | Z17: 348294.83 | AA17: =R17-Y17 -> 348294.83
A18: 10 | B18: JOY HARUNA MAKERI | D18: AM TRAINING | E18: 13(9) | F18: =24741.26 -> 24741.26 | H18: =F18*300% -> 74223.78 | I18: =F18*7.5% -> 1855.5945 | K18: =F18*50% -> 12370.63 | L18: =F18*350% -> 86594.41 | M18: =F18*100% -> 24741.26 | N18: 150000 | O18: =F18*10% -> 2474.126 | P18: 15000 | Q18: =50000+100000 -> 150000 | R18: =SUM(F18:Q18) -> 542001.06 | S18: 549177.65 | T18: =S18-R18 -> 7176.5933 | X18: =7709.76 -> 7709.76 | Y18: =SUM(U18:X18) -> 7709.76 | Z18: 534291.3 | AA18: =R18-Y18 -> 534291.3
A19: 11 | B19: ALI ABDULLAHI | D19: AM ICT | E19: 13(11) | F19: =26339.3 -> 26339.3 | G19: 0 | H19: =F19*300% -> 79017.9 | I19: =F19*7.5% -> 1975.4475 | J19: 0 | K19: =F19*50% -> 13169.65 | L19: =F19*350% -> 92187.55 | M19: =F19*100% -> 26339.3 | N19: =100000 -> 100000 | O19: =F19*10% -> 2633.93 | P19: 15000 | Q19: =0 -> 0 | R19: =SUM(F19:Q19) -> 356663.08 | S19: 356663.08 | T19: =S19-R19 -> 0 | X19: =7709.76 -> 7709.76 | Y19: =U19+V19+W19+X19 -> 7709.76 | Z19: 348953.32 | AA19: =R19-Y19 -> 348953.32
A20: 12 | B20: ADUGBA RICHARD TERSEER | D20: INFORMATION OFFICER | E20: 10(8) | F20: =17784 -> 17784 | H20: =F20*300% -> 53352 | I20: =F20*7.5% -> 1333.8 | K20: =F20*50% -> 8892 | L20: =F20*350% -> 62244 | M20: =F20*100% -> 17784 | N20: =100000 -> 100000 | O20: =F20*10% -> 1778.4 | P20: 10000 | R20: =SUM(F20:Q20) -> 273168.2 | S20: 277734.05 | T20: =S20-R20 -> 4565.847 | U20: =50000 -> 50000 | V20: =111833.33 -> 111833.33 | X20: 3369.51 | Y20: =U20+V20+W20+X20 -> 165202.84 | Z20: 107965.36 | AA20: =R20-Y20 -> 107965.36
A21: 13 | B21: CHRISTIAN MADUABUCHI ODO | D21: ICT OFFICER | E21: 10(10) | F21: =18779.3 -> 18779.3 | H21: =F21*300% -> 56337.9 | I21: =F21*7.5% -> 1408.4475 | K21: =F21*50% -> 9389.65 | L21: =F21*350% -> 65727.55 | M21: =F21*100% -> 18779.3 | N21: =100000 -> 100000 | O21: =F21*10% -> 1877.93 | P21: 10000 | R21: =SUM(F21:Q21) -> 282300.08 | S21: 286866.02 | T21: =S21-R21 -> 4565.9388 | U21: =20000 -> 20000 | V21: =82500 -> 82500 | W21: ='[3]DECEMBER 2019'!$H$51 -> 469.4825 | X21: 3369.51 | Y21: =U21+V21+W21+X21 -> 106338.99 | Z21: 175961.08 | AA21: =R21-Y21 -> 175961.08
A22: 14 | B22: VICTOR ASUKWO | D22: ICT OFFICER | E22: 8 (8) | F22: =12732 -> 12732 | H22: =F22*300% -> 38196 | I22: =F22*7.5% -> 954.9 | K22: =F22*50% -> 6366 | L22: =F22*350% -> 44562 | M22: =F22*100% -> 12732 | N22: =100000 -> 100000 | O22: =F22*10% -> 1273.2 | P22: 10000 | R22: =SUM(F22:Q22) -> 226816.1 | S22: 230304.07 | T22: =S22-R22 -> 3487.968 | U22: =10000 -> 10000 | X22: 1484.37 | Y22: =U22+V22+W22+X22 -> 11484.37 | Z22: 215331.73 | AA22: =R22-Y22 -> 215331.73
A23: 15 | B23: SULEIMAN ABUBAKAR SODEEQ | E23: 8(7) | F23: =12351.94 -> 12351.94 | G23: =0 -> 0 | H23: =F23*300% -> 37055.82 | I23: =F23*7.5% -> 926.3955 | K23: =F23*50% -> 6175.97 | L23: =F23*350% -> 43231.79 | M23: =F23*100% -> 12351.94 | N23: =100000 -> 100000 | O23: =F23*10% -> 1235.194 | P23: 10000 | R23: =SUM(F23:Q23) -> 223329.05 | S23: 223329.05 | T23: =S23-R23 -> 0 | X23: =1235.19 -> 1235.19 | Y23: =SUM(U23:X23) -> 1235.19 | Z23: 222093.86 | AA23: =R23-Y23 -> 222093.86
A24: 16 | B24: YAKUB OLUWATOYIN USMAN | E24: 8(7) | F24: =12351.94 -> 12351.94 | G24: =0 -> 0 | H24: =F24*300% -> 37055.82 | I24: =F24*7.5% -> 926.3955 | K24: =F24*50% -> 6175.97 | L24: =F24*350% -> 43231.79 | M24: =F24*100% -> 12351.94 | N24: =100000 -> 100000 | O24: =F24*10% -> 1235.194 | P24: 10000 | R24: =SUM(F24:Q24) -> 223329.05 | S24: 223329.05 | T24: =S24-R24 -> 0 | U24: =10000 -> 10000 | V24: =100000 -> 100000 | X24: =1235.19 -> 1235.19 | Y24: =SUM(U24:X24) -> 111235.19 | Z24: 10093.859 | AA24: =R24-Y24 -> 112093.86
A25: 17 | B25: ANTHONY EDET | D25: OFFICER M&E | E25: 10(12) | F25: =19774.62 -> 19774.62 | H25: =F25*300% -> 59323.86 | I25: =F25*7.5% -> 1483.0965 | J25: 0 | K25: =F25*50% -> 9887.31 | L25: =F25*350% -> 69211.17 | M25: =F25*100% -> 19774.62 | N25: =100000 -> 100000 | O25: =F25*10% -> 1977.462 | P25: 10000 | Q25: 0 | R25: =SUM(F25:Q25) -> 291432.14 | S25: 334201.03 | T25: =S25-R25 -> 42768.888 | U25: 10000 | W25: ='[3]DECEMBER 2019'!$H$43 -> 494.3655 | X25: 3369.51 | Y25: =SUM(U25:X25) -> 13863.876 | Z25: 277568.26 | AA25: =R25-Y25 -> 277568.26
A26: 18 | B26: EGUATU U. ONYEJELEM | D26: OFFICER M&E | E26: 10(8) | F26: =17784 -> 17784 | H26: =F26*300% -> 53352 | I26: =F26*7.5% -> 1333.8 | K26: =F26*50% -> 8892 | L26: =F26*350% -> 62244 | M26: =F26*100% -> 17784 | N26: =100000 -> 100000 | O26: =F26*10% -> 1778.4 | P26: 10000 | R26: =SUM(F26:Q26) -> 273168.2 | S26: 277734.05 | T26: =S26-R26 -> 4565.847 | U26: =20000 -> 20000 | V26: =87500+43750 -> 131250 | X26: 3369.51 | Y26: =SUM(U26:X26) -> 154619.51 | Z26: 118548.69 | AA26: =R26-Y26 -> 118548.69
A27: 19 | B27: ODEH SUZIE | D27: ADMIN. OFFICER, LIASION OFFICE | E27: 10(7) | F27: 17286.33 | G27: 0 | H27: 51858.99 | I27: 1296.4748 | K27: 8643.165 | L27: 60502.155 | M27: 17286.33 | N27: 100000 | O27: 1728.633 | P27: 10000 | R27: 268602.08 | S27: 273168.2 | T27: =S27-R27 -> 4566.1222 | U27: 10000 | W27: =0 -> 0 | X27: 3369.51 | Y27: =U27+V27+W27+X27 -> 13369.51 | Z27: 255232.57 | AA27: =R27-Y27 -> 255232.57
B28: TOTAL | D28: 19 | F28: =SUM(F9:F27) -> 590178.65 | G28: =SUM(G9:G27) -> 0 | H28: =SUM(H9:H27) -> 1610047.2 | I28: =SUM(I9:I27) -> 80373.372 | J28: =SUM(J9:J27) -> 320977.52 | K28: =SUM(K9:K27) -> 287064.89 | L28: =SUM(L9:L27) -> 1503914.7 | M28: =SUM(M9:M27) -> 550056.47 | ... R28: =SUM(R9:R27) -> 7906865.6 | S28: 8074523.3 | T28: =SUM(T9:T27) -> 167657.7 | U28: =SUM(U9:U27) -> 395000 | V28: =SUM(V9:V27) -> 1057742.8 | W28: =SUM(W9:W27) -> 4753.9245 | X28: =SUM(X9:X27) -> 256339.48 | Y28: =SUM(Y9:Y27) -> 1713836.2 | Z28: 6022279.4 | AA28: =SUM(AA9:AA27) -> 6193029.4
B30: INTERNAL AUDIT
A31: 1 | B31: NWOSU MATHEW EZE | D31: Ag. DIRECTOR INT. AUDIT | E31: 17(7) | F31: =76339.3 -> 76339.3 | H31: =F31*300% -> 229017.9 | I31: =F31*7.5% -> 5725.4475 | J31: =80244.38 -> 80244.38 | K31: =F31*50% -> 38169.65 | L31: =F31*350% -> 267187.55 | M31: =F31*100% -> 76339.3 | N31: =100000 -> 100000 | O31: =F31*10% -> 7633.93 | P31: 20000 | Q31: 0 | R31: =SUM(F31:Q31) -> 900657.46 | S31: 925433.08 | T31: =S31-R31 -> 24775.619 | U31: =100000 -> 100000 | V31: =287500 -> 287500 | W31: ='[3]DECEMBER 2019'!$H$26 -> 1028.9423 | X31: =52776.63 -> 52776.63 | Y31: =U31+V31+W31+X31 -> 441305.57 | Z31: 459351.89 | AA31: =R31-Y31 -> 459351.89
A32: 2 | B32: BASHIRU ABBA WALI | D32: OFF. INT. AUDIT | E32: 10(10) | F32: =18779.3 -> 18779.3 | H32: =F32*300% -> 56337.9 | I32: =F32*7.5% -> 1408.4475 | J32: 0 | K32: =F32*50% -> 9389.65 | L32: =F32*350% -> 65727.55 | M32: =F32*100% -> 18779.3 | N32: =100000 -> 100000 | O32: =F32*10% -> 1877.93 | P32: 10000 | Q32: 0 | R32: =SUM(F32:Q32) -> 282300.08 | S32: 0 | U32: =0 -> 0 | V32: =0 -> 0 | X32: =3369.51 -> 3369.51 | Y32: =U32+V32+W32+X32 -> 3369.51 | Z32: 245930.57 | AA32: =R32-Y32 -> 278930.57
C33: TOTAL | D33: 2 | F33: =SUM(F31:F32) -> 95118.6 | G33: =SUM(G31:G32) -> 0 | H33: =SUM(H31:H32) -> 285355.8 | I33: =SUM(I31:I32) -> 7133.895 | J33: =SUM(J31:J32) -> 80244.38 | K33: =SUM(K31:K32) -> 47559.3 | L33: =SUM(L31:L32) -> 332915.1 | M33: =SUM(M31:M32) -> 95118.6 | ... R33: =SUM(R31:R32) -> 1182957.5 | S33: 925433.08 | T33: =SUM(T31:T32) -> 24775.619 | U33: =SUM(U31:U32) -> 100000 | V33: =SUM(V31:V32) -> 287500 | W33: =SUM(W31:W32) -> 1028.9423 | X33: =SUM(X31:X32) -> 56146.14 | Y33: =SUM(Y31:Y32) -> 444675.08 | Z33: 705282.45 | AA33: =R33-Y33 -> 738282.45
B35: LEG. SUPPORT SEVICES
A36: 1 | B36: PROF. EDOBA BRIGHT OMOREGBE | D36: AG. DLSS | E36: 17(8) | F36: =79039.64 -> 79039.64 | H36: =F36*300% -> 237118.92 | I36: =F36*7.5% -> 5927.973 | J36: 80244.38 | K36: =F36*50% -> 39519.82 | L36: =F36*350% -> 276638.74 | M36: =F36*100% -> 79039.64 | N36: =150000 -> 150000 | O36: =F36*10% -> 7903.964 | P36: 20000 | R36: =SUM(F36:Q36) -> 975433.08 | S36: 1000209.1 | T36: =S36-R36 -> 24775.986 | U36: 0 | X36: =52776.63 -> 52776.63 | Y36: =X36+U36+V36+W36 -> 52776.63 | Z36: 922656.45 | AA36: =R36-Y36 -> 922656.45
A37: 2 | B37: DR CLINTON JAJA | D37: SENIOR RESEARCH FELLOW | E37: 15(9) | F37: =33507.5 -> 33507.5 | H37: =F37*300% -> 100522.5 | I37: =F37*7.5% -> 2513.0625 | J37: 40122.19 | K37: =F37*50% -> 16753.75 | L37: =F37*350% -> 117276.25 | M37: =F37*100% -> 33507.5 | N37: =150000 -> 150000 | O37: =F37*10% -> 3350.75 | P37: 20000 | Q37: 0 | R37: =SUM(F37:Q37) -> 517553.5 | S37: 517553.5 | T37: =S37-R37 -> 0 | U37: 50000 | V37: =240909.11 -> 240909.11 | X37: 15548.33 | Y37: =SUM(U37:X37) -> 306457.44 | Z37: 211096.06 | AA37: =R37-Y37 -> 211096.06
A38: 3 | B38: BETHEL UZOMA IHUGBA | D38: SNR RESEARCH FELLOW | E38: 15(8) | F38: =32263.2 -> 32263.2 | H38: =F38*300% -> 96789.6 | I38: =F38*7.5% -> 2419.74 | J38: 40122.19 | K38: =F38*50% -> 16131.6 | L38: =F38*350% -> 112921.2 | M38: =F38*100% -> 32263.2 | N38: =150000 -> 150000 | O38: =F38*10% -> 3226.32 | P38: 20000 | R38: =SUM(F38:Q38) -> 506137.05 | S38: 517553.5 | T38: =S38-R38 -> 11416.452 | U38: =30000+13000 -> 43000 | V38: =246905.96 -> 246905.96 | X38: 15548.33 | Y38: =X38+U38+V38+W38 -> 305454.29 | Z38: 200682.76 | AA38: =R38-Y38 -> 200682.76
A39: 4 | B39: OGUCHE SAMUEL | D39: RESEARCH FELLOW I | E39: 14(11) | F39: 28489.81 | H39: =F39*300% -> 85469.43 | I39: =F39*7.5% -> 2136.7357 | K39: =F39*50% -> 14244.905 | L39: =F39*350% -> 99714.335 | M39: =F39*100% -> 28489.81 | N39: =150000 -> 150000 | O39: =F39*10% -> 2848.981 | P39: 20000 | R39: =SUM(F39:Q39) -> 431394.01 | S39: 431394.01 | T39: =S39-R39 -> 0 | U39: =30000 -> 30000 | V39: =179165.6+26250 -> 205415.6 | X39: 7709.76 | Y39: =SUM(U39:X39) -> 243125.36 | Z39: 188268.65 | AA39: =R39-Y39 -> 188268.65
A40: 5 | B40: IBRAHIM USMAN | D40: RESEARCH FELLOW I | E40: 14(10) | F40: =27611.23 -> 27611.23 | H40: =F40*300% -> 82833.69 | I40: =F40*7.5% -> 2070.8422 | J40: 0 | K40: =F40*50% -> 13805.615 | L40: =F40*350% -> 96639.305 | M40: =F40*100% -> 27611.23 | N40: =150000 -> 150000 | O40: =F40*10% -> 2761.123 | P40: 20000 | Q40: 0 | R40: =SUM(F40:Q40) -> 423333.04 | S40: 431394.01 | T40: =S40-R40 -> 8060.9715 | W40: ='[3]DECEMBER 2019'!$H$27 -> 690.28075 | X40: 7709.76 | Y40: =X40+U40+V40+W40 -> 8400.0408 | Z40: 414932.99 | AA40: =R40-Y40 -> 414932.99
A41: 6 | B41: DR MOHAMMED O. AMALI | D41: RESEARCH FELLOW II | E41: 13(9) | F41: =24741.26 -> 24741.26 | H41: =F41*300% -> 74223.78 | I41: =F41*7.5% -> 1855.5945 | K41: =F41*50% -> 12370.63 | L41: =F41*350% -> 86594.41 | M41: =F41*100% -> 24741.26 | N41: =150000 -> 150000 | O41: =F41*10% -> 2474.126 | P41: 15000 | R41: =SUM(F41:Q41) -> 392001.06 | S41: 407211.37 | T41: =S41-R41 -> 15210.307 | U41: =15000 -> 15000 | V41: =106666.67 -> 106666.67 | X41: 7709.76 | Y41: =X41+U41+V41+W41 -> 129376.43 | Z41: 369291.3 | AA41: =R41-Y41 -> 262624.63
A42: 7 | B42: YAHAYA SHAMSU | D42: AM LEGAL | E42: 13(11) | F42: =26339.3 -> 26339.3 | H42: =F42*300% -> 79017.9 | I42: =F42*7.5% -> 1975.4475 | K42: =F42*50% -> 13169.65 | L42: =F42*350% -> 92187.55 | M42: =F42*100% -> 26339.3 | N42: =150000 -> 150000 | O42: =F42*10% -> 2633.93 | P42: 15000 | R42: =SUM(F42:Q42) -> 406663.08 | S42: 406663.08 | T42: =S42-R42 -> 0 | W42: 0 | X42: 7709.76 | Y42: =X42+V42+U42+W42 -> 7709.76 | Z42: 398953.32 | AA42: =R42-Y42 -> 398953.32
A43: 8 | B43: OFORDEME ADAOBI JULIA | D43: RESEARCH FELLOW 11 | E43: 13(8) | F43: 23891.12 | H43: =F43*300% -> 71673.36 | I43: =F43*7.5% -> 1791.834 | J43: 0 | K43: =F43*50% -> 11945.56 | L43: =F43*350% -> 83618.92 | M43: =F43*100% -> 23891.12 | N43: =150000 -> 150000 | O43: =F43*10% -> 2389.112 | P43: 15000 | Q43: 0 | R43: =SUM(F43:Q43) -> 384201.03 | S43: 392001.06 | T43: =S43-R43 -> 7800.0345 | X43: =7707.76 -> 7707.76 | Y43: =X43+U43+V43+W43 -> 7707.76 | Z43: 376493.27 | AA43: =R43-Y43 -> 376493.27
A44: 9 | B44: IKPEAZU CHINEDU ANITA | D44: RESEARCH FELLOW II | E44: 13(9) | F44: =24741.26 -> 24741.26 | H44: =F44*300% -> 74223.78 | I44: =F44*7.5% -> 1855.5945 | J44: 0 | K44: =F44*50% -> 12370.63 | L44: =F44*350% -> 86594.41 | M44: =F44*100% -> 24741.26 | N44: =150000 -> 150000 | O44: =F44*10% -> 2474.126 | P44: 15000 | Q44: 0 | R44: =SUM(F44:Q44) -> 392001.06 | S44: 399177.65 | T44: =S44-R44 -> 7176.5933 | X44: 7709.76 | Y44: =X44+U44+V44+W44 -> 7709.76 | Z44: 384291.3 | AA44: =R44-Y44 -> 384291.3
A45: 10 | B45: ONYEAKU CHUKWUKA EDMOND | D45: RESEARCH FELLOW II | E45: 13(9) | F45: =24741.26 -> 24741.26 | H45: =F45*300% -> 74223.78 | I45: =F45*7.5% -> 1855.5945 | J45: =J19 -> 0 | K45: =F45*50% -> 12370.63 | L45: =F45*350% -> 86594.41 | M45: =F45*100% -> 24741.26 | N45: =150000 -> 150000 | O45: =F45*10% -> 2474.126 | P45: 15000 | Q45: 0 | R45: =SUM(F45:Q45) -> 392001.06 | S45: 399177.65 | T45: =S45-R45 -> 7176.5933 | U45: =30000+100000 -> 130000 | V45: =182107.04 -> 182107.04 | W45: ='[3]DECEMBER 2019'!$H$46 -> 618.5315 | X45: 7709.76 | Y45: =X45+U45+V45+W45 -> 320435.33 | Z45: 171565.73 | AA45: =R45-Y45 -> 71565.729
A46: 11 | B46: DORIS DAKDA AARON | D46: RESEARCH OFFICER | E46: 10(9) | F46: =18281.64 -> 18281.64 | H46: =F46*300% -> 54844.92 | I46: =F46*7.5% -> 1371.123 | K46: =F46*50% -> 9140.82 | L46: =F46*350% -> 63985.74 | M46: =F46*100% -> 18281.64 | N46: =150000 -> 150000 | O46: =F46*10% -> 1828.164 | P46: 10000 | R46: =SUM(F46:Q46) -> 327734.05 | S46: 384201.03 | T46: =S46-R46 -> 56466.979 | U46: =50000+10000 -> 60000 | W46: ='[3]DECEMBER 2019'!$H$52 -> 457.041 | X46: 3369.51 | Y46: =X46+U46+V46+W46 -> 63826.551 | Z46: 263907.5 | AA46: =R46-Y46 -> 263907.5
B47: TOTAL | D47: 11 | F47: =SUM(F36:F46) -> 343647.22 | H47: =SUM(H36:H46) -> 1030941.7 | I47: =SUM(I36:I46) -> 25773.541 | J47: =SUM(J36:J46) -> 160488.76 | K47: =SUM(K36:K46) -> 171823.61 | L47: =SUM(L36:L46) -> 1202765.3 | M47: =SUM(M36:M46) -> 343647.22 | N47: =SUM(N36:N46) -> 1650000 | O47: =SUM(O36:O46) -> 34364.722 | ... R47: =SUM(R36:R46) -> 5148452 | S47: 5297657.6 | T47: =SUM(T36:T46) -> 138083.92 | U47: =SUM(U36:U46) -> 328000 | V47: =SUM(V36:V46) -> 982004.38 | W47: =SUM(W36:W46) -> 1765.8532 | X47: =SUM(X36:X46) -> 141209.12 | Y47: =SUM(Y36:Y46) -> 1452979.4 | Z47: 3902139.3 | AA47: =R47-Y47 -> 3695472.7
B49: LEGAL SERVICES
A50: 1 | B50: DR SHUIBU DANWANKA | D50: DIRECTOR LEGAL SERVICES | E50: 17(9) | F50: =81740.02 -> 81740.02 | H50: =F50*300% -> 245220.06 | I50: =F50*7.5% -> 6130.5015 | J50: 80244.38 | K50: =F50*50% -> 40870.01 | L50: =F50*350% -> 286090.07 | M50: =F50*100% -> 81740.02 | N50: =150000 -> 150000 | O50: =F50*10% -> 8174.002 | P50: 20000 | Q50: 0 | R50: =SUM(F50:Q50) -> 1000209.1 | S50: 1000209.1 | T50: =S50-R50 -> 0 | W50: 0 | X50: 52776.63 | Y50: =U50+V50+W50+X50 -> 52776.63 | Z50: 947432.43 | AA50: =R50-Y50 -> 947432.43
B51: TOTAL | D51: 2 | F51: =SUM(F50:F50) -> 81740.02 | G51: =SUM(G50:G50) -> 0 | H51: =SUM(H50:H50) -> 245220.06 | I51: =SUM(I50:I50) -> 6130.5015 | J51: =SUM(J50:J50) -> 80244.38 | K51: =SUM(K50:K50) -> 40870.01 | L51: =SUM(L50:L50) -> 286090.07 | M51: =SUM(M50:M50) -> 81740.02 | ... R51: =SUM(R50:R50) -> 1000209.1 | S51: 1000209.1 | T51: =SUM(T50:T50) -> 0 | W51: =SUM(W50:W50) -> 0 | X51: =SUM(X50:X50) -> 52776.63 | Y51: =SUM(Y50:Y50) -> 52776.63 | Z51: 1266435.7 | AA51: =R51-Y51 -> 947432.43
B53: DEMOCRATIC STUDIES
A54: 1 | B54: DR. ADEWALE ADEREMI | D54: DIRECTOR, DEMOCRATIC STUDIES | E54: 17(7) | F54: =76339.3 -> 76339.3 | G54: =0 -> 0 | H54: =F54*300% -> 229017.9 | I54: =F54*7.5% -> 5725.4475 | J54: =80244.38 -> 80244.38 | K54: =F54*50% -> 38169.65 | L54: =F54*350% -> 267187.55 | M54: =F54*100% -> 76339.3 | N54: =150000 -> 150000 | O54: =F54*10% -> 7633.93 | P54: 20000 | Q54: 0 | R54: =SUM(F54:Q54) -> 950657.46 | S54: 975433.08 | T54: =S54-R54 -> 24775.619 | U54: =100000 -> 100000 | X54: =52776.63 -> 52776.63 | Y54: =U54+V54+W54+X54 -> 152776.63 | Z54: 797880.83 | AA54: =R54-Y54 -> 797880.83
A55: 2 | B55: NGARA CHRISTOPHER OCHANJA | D55: RESEARCH FELLOW 11 | E55: 13(10) | F55: =25523.45 -> 25523.45 | H55: =F55*300% -> 76570.35 | I55: =F55*7.5% -> 1914.2587 | K55: =F55*50% -> 12761.725 | L55: =F55*350% -> 89332.075 | M55: =F55*100% -> 25523.45 | N55: =150000 -> 150000 | O55: =F55*10% -> 2552.345 | P55: 15000 | Q55: 0 | R55: =SUM(F55:Q55) -> 399177.65 | S55: 415272.06 | T55: =S55-R55 -> 16094.41 | U55: =20000 -> 20000 | V55: =163103.59 -> 163103.59 | W55: ='[3]DECEMBER 2019'!$H$50 -> 638.08625 | X55: =7709.76 -> 7709.76 | Y55: =U55+V55+W55+X55 -> 191451.44 | Z55: 207726.22 | AA55: =R55-Y55 -> 207726.22
A56: 3 | B56: EJALONIBU GANIYU LAYI | D56: RESEARCH OFFICER | E56: 10(9) | F56: =18281.64 -> 18281.64 | G56: =0 -> 0 | H56: =F56*300% -> 54844.92 | I56: =F56*7.5% -> 1371.123 | K56: =F56*50% -> 9140.82 | L56: =F56*350% -> 63985.74 | M56: =F56*100% -> 18281.64 | N56: =150000 -> 150000 | O56: =F56*10% -> 1828.164 | P56: 10000 | R56: =SUM(F56:Q56) -> 327734.05 | S56: 384201.03 | T56: =S56-R56 -> 56466.979 | U56: =110000 -> 110000 | X56: 3369.51 | Y56: =U56+V56+W56+X56 -> 113369.51 | Z56: 214364.54 | AA56: =R56-Y56 -> 214364.54
A57: 4 | B57: OSOLAFIA MUHAMMAD EGYE | D57: PERSONNEL OFFICER | E57: 10(10) | F57: =18779.3 -> 18779.3 | H57: =F57*300% -> 56337.9 | I57: =F57*7.5% -> 1408.4475 | J57: 0 | K57: =F57*50% -> 9389.65 | L57: =F57*350% -> 65727.55 | M57: =F57*100% -> 18779.3 | N57: =150000 -> 150000 | O57: =F57*10% -> 1877.93 | P57: 10000 | Q57: 0 | R57: =SUM(F57:Q57) -> 332300.08 | S57: 336866.02 | T57: =S57-R57 -> 4565.9388 | U57: =20000 -> 20000 | V57: =100000+100000 -> 200000 | W57: ='[3]DECEMBER 2019'!$H$45 -> 469.4825 | X57: =3369.51 -> 3369.51 | Y57: =U57+V57+W57+X57 -> 223838.99 | Z57: 208461.08 | AA57: =R57-Y57 -> 108461.08
B58: TOTAL | D58: 4 | F58: =SUM(F54:F57) -> 138923.69 | G58: =SUM(G54:G57) -> 0 | H58: =SUM(H54:H57) -> 416771.07 | I58: =SUM(I54:I57) -> 10419.277 | J58: =SUM(J54:J57) -> 80244.38 | K58: =SUM(K54:K57) -> 69461.845 | L58: =SUM(L54:L57) -> 486232.91 | M58: =SUM(M54:M57) -> 138923.69 | ... R58: =SUM(R54:R57) -> 2009869.2 | S58: 2114833.2 | T58: =SUM(T54:T57) -> 101902.95 | U58: =SUM(U54:U57) -> 250000 | V58: =SUM(V54:V57) -> 363103.59 | W58: =SUM(W54:W57) -> 1107.5688 | X58: =SUM(X54:X57) -> 67225.41 | Y58: =SUM(R58:X58) -> 4908041.9 | Z58: 1428432.7 | AA58: =SUM(AA54:AA57) -> 1328432.7
B60: POST GRADUATE SCHOOL
A61: 1 | B61: DR ASIMIYU G. ABIOLA | D61: DIRECTOR POST GRADUATE | E61: 17(9) | F61: =81740.02 -> 81740.02 | H61: =F61*300% -> 245220.06 | I61: =F61*7.5% -> 6130.5015 | J61: 80244.38 | K61: =F61*50% -> 40870.01 | L61: =F61*350% -> 286090.07 | M61: =F61*100% -> 81740.02 | N61: =150000 -> 150000 | O61: =F61*10% -> 8174.002 | P61: 20000 | Q61: 0 | R61: =SUM(F61:Q61) -> 1000209.1 | S61: 1000209.1 | T61: =S61-R61 -> 0 | U61: 150000 | V61: =451815.1 -> 451815.1 | W61: 0 | X61: 52776.63 | Y61: =SUM(U61:X61) -> 654591.73 | Z61: 345617.33 | AA61: =R61-Y61 -> 345617.33
A62: 2 | B62: DR AUGUSTINE C. OSIGWE | D62: RESEARCH FELLOW I | E62: 14(9) | F62: =27611.23 -> 27611.23 | H62: =F62*300% -> 82833.69 | I62: =F62*7.5% -> 2070.8422 | K62: =F62*50% -> 13805.615 | L62: =F62*350% -> 96639.305 | M62: =F62*100% -> 27611.23 | N62: =150000 -> 150000 | O62: =F62*10% -> 2761.123 | P62: 20000 | R62: =SUM(F62:Q62) -> 423333.04 | S62: 506137.05 | T62: =S62-R62 -> 82804.015 | U62: =20000 -> 20000 | V62: =150000 -> 150000 | W62: ='[3]DECEMBER 2019'!$H$42 -> 690.28075 | X62: 7709.76 | Y62: =SUM(U62:X62) -> 178400.04 | Z62: 244932.99 | AA62: =R62-Y62 -> 244932.99
A63: 3 | B63: HAUWA PATE SADIQ | D63: PROGRAMME OFFICER | E63: 10(8) | F63: =17784 -> 17784 | H63: =F63*300% -> 53352 | I63: =F63*7.5% -> 1333.8 | K63: =F63*50% -> 8892 | L63: =F63*350% -> 62244 | M63: =F63*100% -> 17784 | N63: =150000 -> 150000 | O63: =F63*10% -> 1778.4 | P63: 10000 | R63: =SUM(F63:Q63) -> 323168.2 | S63: 327734.05 | T63: =S63-R63 -> 4565.847 | U63: =50000 -> 50000 | V63: =31500 -> 31500 | X63: 3369.51 | Y63: =SUM(U63:X63) -> 84869.51 | Z63: 269798.69 | AA63: =R63-Y63 -> 238298.69
A64: 4 | B64: UZODINMA EMMANUEL EZENWA | D64: PROGRAMME OFFICER | E64: 10(10) | F64: =18779.3 -> 18779.3 | H64: =F64*300% -> 56337.9 | I64: =F64*7.5% -> 1408.4475 | J64: 0 | K64: =F64*50% -> 9389.65 | L64: =F64*350% -> 65727.55 | M64: =F64*100% -> 18779.3 | N64: =150000 -> 150000 | O64: =F64*10% -> 1877.93 | P64: 10000 | Q64: 0 | R64: =SUM(F64:Q64) -> 332300.08 | S64: 384201.03 | T64: =S64-R64 -> 51900.949 | U64: =0 -> 0 | V64: =0 -> 0 | W64: ='[3]DECEMBER 2019'!$H$48 -> 469.4825 | X64: 3369.51 | Y64: =U64+V64+W64+X64 -> 3838.9925 | Z64: 328461.08 | AA64: =R64-Y64 -> 328461.08
B65: TOTAL | D65: 4 | F65: =SUM(F61:F64) -> 145914.55 | H65: =SUM(H61:H64) -> 437743.65 | I65: =SUM(I61:I64) -> 10943.591 | J65: =SUM(J61:J64) -> 80244.38 | K65: =SUM(K61:K64) -> 72957.275 | L65: =SUM(L61:L64) -> 510700.92 | M65: =SUM(M61:M64) -> 145914.55 | N65: =SUM(N61:N64) -> 600000 | O65: =SUM(O61:O64) -> 14591.455 | ... R65: =SUM(R61:R64) -> 2079010.4 | S65: 2218281.2 | T65: =SUM(T61:T64) -> 139270.81 | U65: =SUM(U61:U64) -> 220000 | V65: =SUM(V61:V64) -> 633315.1 | W65: =SUM(W61:W64) -> 1159.7632 | X65: =SUM(X61:X64) -> 67225.41 | Y65: =SUM(Y61:Y64) -> 921700.27 | Z65: 1188810.1 | AA65: =SUM(AA61:AA64) -> 1157310.1
B67: ECONOMIC AND SOCIAL DEV.
A68: 1 | B68: DR ADEYEMI AKEEB FAJINGBESI | D68: DIR. ECO. & SOCIAL DEV | E68: 17(9) | F68: 81740.02 | H68: =F68*300% -> 245220.06 | I68: =F68*7.5% -> 6130.5015 | J68: 80244.38 | K68: =F68*50% -> 40870.01 | L68: =F68*350% -> 286090.07 | M68: =F68*100% -> 81740.02 | N68: =150000 -> 150000 | O68: =F68*10% -> 8174.002 | P68: 20000 | Q68: 0 | R68: =SUM(F68:Q68) -> 1000209.1 | S68: 1000209.1 | T68: =S68-R68 -> 0 | U68: 200000 | V68: =59722.22 -> 59722.22 | W68: ='[3]DECEMBER 2019'!$H$39 -> 2043.5005 | X68: 52776.63 | Y68: =SUM(U68:X68) -> 314542.35 | Z68: 685666.71 | AA68: =R68-Y68 -> 685666.71
A69: 2 | B69: DR ASEMOTA OMOROGBE JOSEPH | D69: SENIOR RESEARCH FELLOW | E69: 15(9) | F69: =33507.5 -> 33507.5 | H69: =F69*300% -> 100522.5 | I69: =F69*7.5% -> 2513.0625 | J69: 40122.19 | K69: =F69*50% -> 16753.75 | L69: =F69*350% -> 117276.25 | M69: =F69*100% -> 33507.5 | N69: =150000 -> 150000 | O69: =F69*10% -> 3350.75 | P69: 20000 | R69: =SUM(F69:Q69) -> 517553.5 | S69: 517553.5 | T69: =S69-R69 -> 0 | X69: 15548.33 | Y69: =SUM(U69:X69) -> 15548.33 | Z69: 502005.17 | AA69: =R69-Y69 -> 502005.17
A70: 3 | B70: TERFA WILLIAMS ABRAHAM | D70: RESEARCH FELLOW I | E70: 14(11) | F70: 28489.81 | H70: =F70*300% -> 85469.43 | I70: =F70*7.5% -> 2136.7357 | K70: =F70*50% -> 14244.905 | L70: =F70*350% -> 99714.335 | M70: =F70*100% -> 28489.81 | N70: =150000 -> 150000 | O70: =F70*10% -> 2848.981 | P70: 20000 | R70: =SUM(F70:Q70) -> 431394.01 | S70: 506137.05 | T70: =S70-R70 -> 74743.043 | X70: 7709.76 | Y70: =SUM(U70:X70) -> 7709.76 | Z70: 423684.25 | AA70: =R70-Y70 -> 423684.25
A71: 4 | B71: JUMARE FADILA | D71: RESEARCH FELLOW II | E71: 13(10) | F71: =25523.45 -> 25523.45 | H71: =F71*300% -> 76570.35 | I71: =F71*7.5% -> 1914.2587 | J71: 0 | K71: =F71*50% -> 12761.725 | L71: =F71*350% -> 89332.075 | M71: =F71*100% -> 25523.45 | N71: =150000 -> 150000 | O71: =F71*10% -> 2552.345 | P71: 15000 | Q71: 0 | R71: =SUM(F71:Q71) -> 399177.65 | S71: 407211.37 | T71: =S71-R71 -> 8033.7137 | U71: 5000 | X71: =7709.76 -> 7709.76 | Y71: =SUM(U71:X71) -> 12709.76 | Z71: 386467.89 | AA71: =R71-Y71 -> 386467.89
A72: 5 | B72: OMOJU OLUWASOLA EMMANUEL | D72: RESEARCH FELLOW II | E72: 13(9) | F72: =24741.26 -> 24741.26 | H72: =F72*300% -> 74223.78 | I72: =F72*7.5% -> 1855.5945 | K72: =F72*50% -> 12370.63 | L72: =F72*350% -> 86594.41 | M72: =F72*100% -> 24741.26 | N72: =150000 -> 150000 | O72: =F72*10% -> 2474.126 | P72: 15000 | R72: =SUM(F72:Q72) -> 392001.06 | S72: 407211.37 | T72: =S72-R72 -> 15210.307 | U72: =50000 -> 50000 | V72: =87500 -> 87500 | X72: =7709.76 -> 7709.76 | Y72: =SUM(U72:X72) -> 145209.76 | Z72: 246791.3 | AA72: =R72-Y72 -> 246791.3
A73: 6 | B73: UDEFUNA NNADOZIE PATRICK | D73: RESEARCH OFFICER | E73: 10(12) | F73: =19774.62 -> 19774.62 | H73: =F73*300% -> 59323.86 | I73: =F73*7.5% -> 1483.0965 | J73: 0 | K73: =F73*50% -> 9887.31 | L73: =F73*350% -> 69211.17 | M73: =F73*100% -> 19774.62 | N73: =150000 -> 150000 | O73: =F73*10% -> 1977.462 | P73: 10000 | Q73: 0 | R73: =SUM(F73:Q73) -> 341432.14 | S73: 341432.14 | T73: =S73-R73 -> 0 | U73: =10000 -> 10000 | V73: =131771.66+120000 -> 251771.66 | X73: 3369.51 | Y73: =SUM(U73:X73) -> 265141.17 | Z73: 196290.97 | AA73: =R73-Y73 -> 76290.969
A74: 7 | B74: EMILY EDOISA IKHIDE | D74: RESEARCH FELLOW II | E74: 13(9) | F74: =24741.26 -> 24741.26 | H74: =F74*300% -> 74223.78 | I74: =F74*7.5% -> 1855.5945 | K74: =F74*50% -> 12370.63 | L74: =F74*350% -> 86594.41 | M74: =F74*100% -> 24741.26 | N74: =150000 -> 150000 | O74: =F74*10% -> 2474.126 | P74: 15000 | R74: =SUM(F74:Q74) -> 392001.06 | S74: 399177.65 | T74: =S74-R74 -> 7176.5933 | U74: =50000 -> 50000 | V74: =45833.33 -> 45833.33 | X74: 7709.76 | Y74: =SUM(U74:X74) -> 103543.09 | Z74: 288457.97 | AA74: =R74-Y74 -> 288457.97
A75: 8 | B75: ONYIMADU C. ONYEBUCHI | D75: RESEARCH FELLOWII | E75: 13(9) | F75: =24741.26 -> 24741.26 | H75: =F75*300% -> 74223.78 | I75: =F75*7.5% -> 1855.5945 | K75: =F75*50% -> 12370.63 | L75: =F75*350% -> 86594.41 | M75: =F75*100% -> 24741.26 | N75: =150000 -> 150000 | O75: =F75*10% -> 2474.126 | P75: 15000 | R75: =SUM(F75:Q75) -> 392001.06 | S75: 407211.37 | T75: =S75-R75 -> 15210.307 | U75: =50000 -> 50000 | W75: ='[3]DECEMBER 2019'!$H$54 -> 618.5315 | X75: 7709.76 | Y75: =SUM(U75:X75) -> 58328.291 | Z75: 333672.77 | AA75: =R75-Y75 -> 333672.77
A76: 9 | B76: IBE EZECHI CYRIACUS | D76: RESEARCH OFFICER | E76: 10(9) | F76: =18281.64 -> 18281.64 | H76: =F76*300% -> 54844.92 | I76: =F76*7.5% -> 1371.123 | J76: 0 | K76: =F76*50% -> 9140.82 | L76: =F76*350% -> 63985.74 | M76: =F76*100% -> 18281.64 | N76: =150000 -> 150000 | O76: =F76*10% -> 1828.164 | P76: 10000 | Q76: 0 | R76: =SUM(F76:Q76) -> 327734.05 | S76: 384201.03 | T76: =S76-R76 -> 56466.979 | U76: =25000 -> 25000 | X76: 3369.51 | Y76: =SUM(U76:X76) -> 28369.51 | Z76: 299364.54 | AA76: =R76-Y76 -> 299364.54
B77: TOTAL | D77: 9 | F77: =SUM(F68:F76) -> 281540.82 | H77: =SUM(H68:H76) -> 844622.46 | I77: =SUM(I68:I76) -> 21115.561 | J77: =SUM(J68:J76) -> 120366.57 | K77: =SUM(K68:K76) -> 140770.41 | L77: =SUM(L68:L76) -> 985392.87 | M77: =SUM(M68:M76) -> 281540.82 | N77: =SUM(N68:N76) -> 1350000 | O77: =SUM(O68:O76) -> 28154.082 | ... R77: =SUM(R68:R76) -> 4193503.6 | S77: 4403709.5 | T77: =SUM(T68:T76) -> 176840.94 | U77: =SUM(U68:U76) -> 390000 | V77: =SUM(V68:V76) -> 444827.21 | W77: =SUM(W68:W76) -> 2662.032 | X77: =SUM(X68:X76) -> 113612.78 | Y77: =SUM(U77:X77) -> 951102.02 | Z77: 3362401.6 | AA77: =SUM(AA68:AA76) -> 3242401.6
B79: TRAINING AND INTERNATIONAL COOP
A80: 1 | B80: DR JAKE DABANG DAN AZUMI | D80: SENIOR RESEARCH FELLOW TRAINING | E80: 15(9) | F80: =33507.5 -> 33507.5 | H80: =F80*300% -> 100522.5 | I80: =F80*7.5% -> 2513.0625 | J80: 40122.19 | K80: =F80*50% -> 16753.75 | L80: =F80*350% -> 117276.25 | M80: =F80*100% -> 33507.5 | N80: 150000 | O80: =F80*10% -> 3350.75 | P80: 20000 | Q80: 150000 | R80: =SUM(F80:Q80) -> 667553.5 | S80: 724023.33 | T80: =S80-R80 -> 56469.831 | W80: ='[3]DECEMBER 2019'!$H$30 -> 837.6875 | X80: 15548.33 | Y80: =SUM(U80:X80) -> 16386.018 | Z80: 651167.48 | AA80: =R80-Y80 -> 651167.48
A81: 2 | B81: DR FRANCIS NDUM OJIE | D81: ASST. MANAGER, TRAINING | E81: 13(9) | F81: =24741.26 -> 24741.26 | H81: =F81*300% -> 74223.78 | I81: =F81*7.5% -> 1855.5945 | K81: =F81*50% -> 12370.63 | L81: =F81*350% -> 86594.41 | M81: =F81*100% -> 24741.26 | N81: 100000 | O81: =F81*10% -> 2474.126 | P81: 15000 | R81: =SUM(F81:Q81) -> 342001.06 | S81: 357211.37 | T81: =S81-R81 -> 15210.307 | X81: =7709.76 -> 7709.76 | Y81: =SUM(U81:X81) -> 7709.76 | Z81: 334291.3 | AA81: =R81-Y81 -> 334291.3
A82: 3 | B82: OKECHUKWU UCHENNA HULDA | D82: ADMIN OFFICER | E82: 10(8) | F82: =17784 -> 17784 | H82: =F82*300% -> 53352 | I82: =F82*7.5% -> 1333.8 | K82: =F82*50% -> 8892 | L82: =F82*350% -> 62244 | M82: =F82*100% -> 17784 | N82: =100000 -> 100000 | O82: =F82*10% -> 1778.4 | P82: 10000 | R82: =SUM(F82:Q82) -> 273168.2 | S82: 277734.05 | T82: =S82-R82 -> 4565.847 | U82: =5000 -> 5000 | V82: =0 -> 0 | X82: 3369.51 | Y82: =SUM(U82:X82) -> 8369.51 | Z82: 264798.69 | AA82: =R82-Y82 -> 264798.69
A83: 4 | B83: HASSANA AHMED IBRAHIM | E83: 10(7) | F83: =17286.33 -> 17286.33 | G83: =0 -> 0 | H83: =F83*300% -> 51858.99 | I83: =F83*7.5% -> 1296.4748 | K83: =F83*50% -> 8643.165 | L83: =F83*350% -> 60502.155 | M83: =F83*100% -> 17286.33 | N83: 100000 | O83: =F83*10% -> 1728.633 | P83: 10000 | R83: =SUM(F83:Q83) -> 268602.08 | S83: 273168.2 | T83: =S83-R83 -> 4566.1222 | U83: =30000 -> 30000 | W83: =444.6 -> 444.6 | X83: 3369.51 | Y83: =SUM(U83:X83) -> 33814.11 | Z83: 254787.97 | AA83: =R83-Y83 -> 234787.97
B84: TOTAL | D84: 4 | F84: =SUM(F80:F83) -> 93319.09 | G84: =SUM(G80:G83) -> 0 | H84: =SUM(H80:H83) -> 279957.27 | I84: =SUM(I80:I83) -> 6998.9317 | J84: =SUM(J80:J83) -> 40122.19 | K84: =SUM(K80:K83) -> 46659.545 | L84: =SUM(L80:L83) -> 326616.82 | M84: =SUM(M80:M83) -> 93319.09 | ... R84: =SUM(R80:R83) -> 1551324.8 | S84: 1643258.6 | T84: =SUM(T80:T83) -> 80812.107 | U84: =SUM(U80:U83) -> 35000 | V84: =SUM(V80:V83) -> 0 | W84: =SUM(W80:W83) -> 1282.2875 | X84: =SUM(X80:X83) -> 29997.11 | Y84: =SUM(U84:X84) -> 66279.397 | Z84: 1505045.4 | AA84: =SUM(AA80:AA83) -> 1485045.4
B86: LIBRARY AND DOCUMENTATION
A87: 1 | B87: DR MAIMUNA IZAH | D87: INSITUTE LIBRARIAN | E87: 17(7) | F87: =76339.3 -> 76339.3 | H87: =F87*300% -> 229017.9 | I87: =F87*7.5% -> 5725.4475 | J87: 80244.38 | K87: =F87*50% -> 38169.65 | L87: =F87*350% -> 267187.55 | M87: =F87*100% -> 76339.3 | N87: 150000 | O87: =F87*10% -> 7633.93 | P87: 20000 | Q87: 0 | R87: =SUM(F87:Q87) -> 950657.46 | S87: 975433.08 | T87: =S87-R87 -> 24775.619 | U87: =100000 -> 100000 | V87: 0 | W87: 0 | X87: =52776.63 -> 52776.63 | Y87: =SUM(U87:X87) -> 152776.63 | Z87: 797880.83 | AA87: =R87-Y87 -> 797880.83
A88: 2 | B88: CATHERINE E. IKOKOH | D88: SNR RESEARCH FELLOW DOCU | E88: 15(9) | F88: =33507.5 -> 33507.5 | H88: =F88*300% -> 100522.5 | I88: =F88*7.5% -> 2513.0625 | J88: 40122.19 | K88: =F88*50% -> 16753.75 | L88: =F88*350% -> 117276.25 | M88: =F88*100% -> 33507.5 | N88: 150000 | O88: =F88*10% -> 3350.75 | P88: 20000 | Q88: 0 | R88: =SUM(F88:Q88) -> 517553.5 | S88: 517553.5 | T88: =S88-R88 -> 0 | U88: 40000 | V88: =131250 -> 131250 | W88: ='[3]DECEMBER 2019'!$H$37 -> 837.6875 | X88: 15548.33 | Y88: =SUM(U88:X88) -> 187636.02 | Z88: 329917.48 | AA88: =R88-Y88 -> 329917.48
A89: 3 | B89: ALIYU SANNI ABUBAKAR | D89: RESEARCH FELLOW 11 DATA & DOCU. OFFICER | E89: 13(10) | F89: =25523.45 -> 25523.45 | H89: =F89*300% -> 76570.35 | I89: =F89*7.5% -> 1914.2587 | J89: 0 | K89: =F89*50% -> 12761.725 | L89: =F89*350% -> 89332.075 | M89: =F89*100% -> 25523.45 | N89: 150000 | O89: =F89*10% -> 2552.345 | P89: 15000 | Q89: 0 | R89: =SUM(F89:Q89) -> 399177.65 | S89: 406663.08 | T89: =S89-R89 -> 7485.4237 | U89: 30000 | V89: =0 -> 0 | W89: ='[3]DECEMBER 2019'!$H$40 -> 638.08625 | X89: =7709.76 -> 7709.76 | Y89: =SUM(U89:X89) -> 38347.846 | Z89: 285676.1 | AA89: =R89-Y89 -> 360829.81
A90: 4 | B90: CHINAKO N. ASOGWA | D90: LIBRARY OFFICER | E90: 10(14) | F90: =20770 -> 20770 | H90: =F90*300% -> 62310 | I90: =F90*7.5% -> 1557.75 | J90: 0 | K90: =F90*50% -> 10385 | L90: =F90*350% -> 72695 | M90: =F90*100% -> 20770 | N90: 150000 | O90: =F90*10% -> 2077 | P90: 10000 | R90: =SUM(F90:Q90) -> 350564.75 | S90: 392001.06 | T90: =S90-R90 -> 41436.31 | U90: =50000 -> 50000 | V90: =43083.33 -> 43083.33 | X90: 3369.51 | Y90: =SUM(U90:X90) -> 96452.84 | Z90: 254111.91 | AA90: =R90-Y90 -> 254111.91
B91: TOTAL | D91: 4 | F91: =SUM(F87:F90) -> 156140.25 | H91: =SUM(H87:H90) -> 468420.75 | I91: =SUM(I87:I90) -> 11710.519 | J91: =SUM(J87:J90) -> 120366.57 | K91: =SUM(K87:K90) -> 78070.125 | L91: =SUM(L87:L90) -> 546490.88 | M91: =SUM(M87:M90) -> 156140.25 | N91: =SUM(N87:N90) -> 600000 | O91: =SUM(O87:O90) -> 15614.025 | ... R91: =SUM(R87:R90) -> 2217953.4 | S91: 2291650.7 | T91: =SUM(T87:T90) -> 73697.354 | U91: =SUM(U87:U90) -> 220000 | V91: =SUM(V87:V90) -> 174333.33 | W91: =SUM(W87:W90) -> 1475.7738 | X91: =SUM(X87:X90) -> 79404.23 | Y91: =SUM(U91:X91) -> 475213.33 | Z91: 1667586.3 | AA91: =SUM(AA87:AA90) -> 1742740
B93: FINANCE & ACCOUNT
A94: 1 | B94: IBRAHIM M. MSHELIA | D94: DIR. FINANCE & ACCOUNTS | E94: 17(8) | F94: =79039.64 -> 79039.64 | H94: =F94*300% -> 237118.92 | I94: =F94*7.5% -> 5927.973 | J94: =80244.38 -> 80244.38 | K94: =F94*50% -> 39519.82 | L94: =F94*350% -> 276638.74 | M94: =F94*100% -> 79039.64 | N94: =100000 -> 100000 | O94: =F94*10% -> 7903.964 | P94: 20000 | Q94: 100000 | R94: =SUM(F94:Q94) -> 1025433.1 | S94: 1050209.1 | T94: =S94-R94 -> 24775.987 | U94: =200000 -> 200000 | V94: =227777.78 -> 227777.78 | W94: ='[3]DECEMBER 2019'!$H$24 -> 1975.991 | X94: =52776.63 -> 52776.63 | Y94: =SUM(U94:X94) -> 482530.4 | Z94: 542902.68 | AA94: =R94-Y94 -> 542902.68
A95: 2 | B95: KABIR MUHAMMAD SULAIMAN | D95: DD FINANCE & ACCOUNTS | E95: 16(8) | F95: =41157.69 -> 41157.69 | H95: =F95*300% -> 123473.07 | I95: =F95*7.5% -> 3086.8268 | J95: 40122.19 | K95: =F95*50% -> 20578.845 | L95: =F95*350% -> 144051.92 | M95: =F95*100% -> 41157.69 | N95: =100000 -> 100000 | O95: =F95*10% -> 4115.769 | P95: 20000 | Q95: =100000 -> 100000 | R95: =SUM(F95:Q95) -> 637744 | S95: 651465.02 | T95: =S95-R95 -> 13721.029 | U95: =100000 -> 100000 | V95: =0 -> 0 | X95: =21618.09 -> 21618.09 | Y95: =SUM(U95:X95) -> 121618.09 | Z95: 447792.58 | AA95: =R95-Y95 -> 516125.91
A96: 3 | B96: RAHILA NURUDEEN HABU | D96: MANAGER, ACCOUNTS | E96: 15(8) | F96: 32263.2 | H96: =F96*300% -> 96789.6 | I96: =F96*7.5% -> 2419.74 | J96: 40122.19 | K96: =F96*50% -> 16131.6 | L96: =F96*350% -> 112921.2 | M96: =F96*100% -> 32263.2 | N96: =100000 -> 100000 | O96: =F96*10% -> 3226.32 | P96: 20000 | Q96: 0 | R96: =SUM(F96:Q96) -> 456137.05 | S96: 467553.5 | T96: =S96-R96 -> 11416.452 | U96: =70000 -> 70000 | V96: =129166.67 -> 129166.67 | W96: ='[3]DECEMBER 2019'!$H$23 -> 806.58 | X96: 15548.33 | Y96: =SUM(U96:X96) -> 215521.58 | Z96: 240615.47 | AA96: =R96-Y96 -> 240615.47
A97: 4 | B97: ANDRAWUS MUSA | D97: ASSIST. MGR. STORE | E97: 13(10) | F97: =25523.45 -> 25523.45 | H97: =F97*300% -> 76570.35 | I97: =F97*7.5% -> 1914.2587 | J97: 0 | K97: =F97*50% -> 12761.725 | L97: =F97*350% -> 89332.075 | M97: =F97*100% -> 25523.45 | N97: =100000 -> 100000 | O97: =F97*10% -> 2552.345 | P97: 15000 | Q97: 0 | R97: =SUM(F97:Q97) -> 349177.65 | S97: 456137.05 | T97: =S97-R97 -> 106959.4 | U97: =50000 -> 50000 | V97: =90000 -> 90000 | W97: ='[3]DECEMBER 2019'!$H$32 -> 638.08625 | X97: =7709.76 -> 7709.76 | Y97: =SUM(U97:X97) -> 148347.85 | Z97: 200829.81 | AA97: =R97-Y97 -> 200829.81
A98: 5 | B98: TONDO IORWUESE EDWARD | D98: ASSIST. MGR ACCOUNTS | E98: 13(10) | F98: =25523.45 -> 25523.45 | H98: =F98*300% -> 76570.35 | I98: =F98*7.5% -> 1914.2587 | J98: 0 | K98: =F98*50% -> 12761.725 | L98: =F98*350% -> 89332.075 | M98: =F98*100% -> 25523.45 | N98: =100000 -> 100000 | O98: =F98*10% -> 2552.345 | P98: 15000 | Q98: =100000 -> 100000 | R98: =SUM(F98:Q98) -> 449177.65 | S98: 556137.05 | T98: =S98-R98 -> 106959.4 | U98: =30000 -> 30000 | V98: =100000 -> 100000 | W98: ='[3]DECEMBER 2019'!$H$25 -> 638.08625 | X98: =7709.76 -> 7709.76 | Y98: =SUM(U98:X98) -> 138347.85 | Z98: 310829.81 | AA98: =R98-Y98 -> 310829.81
A99: 6 | B99: SHEHU ABDULLAHI | D99: ASST. MANAGER, ACCOUNTS | E99: 13(8) | F99: 23891.12 | G99: 0 | H99: =F99*300% -> 71673.36 | I99: =F99*7.5% -> 1791.834 | J99: 0 | K99: =F99*50% -> 11945.56 | L99: =F99*350% -> 83618.92 | M99: =F99*100% -> 23891.12 | N99: =100000 -> 100000 | O99: =F99*10% -> 2389.112 | P99: 15000 | Q99: 0 | R99: =SUM(F99:Q99) -> 334201.03 | S99: 342001.06 | T99: =S99-R99 -> 7800.0345 | U99: =25000 -> 25000 | V99: =75000 -> 75000 | X99: =7709.76 -> 7709.76 | Y99: =SUM(U99:X99) -> 107709.76 | Z99: 226491.27 | AA99: =R99-Y99 -> 226491.27
A100: 7 | B100: OJOGIWA ABISOLA GANIAT | D100: ACCOUNT OFFICER | E100: 10(10) | F100: =18779.3 -> 18779.3 | H100: =F100*300% -> 56337.9 | I100: =F100*7.5% -> 1408.4475 | K100: =F100*50% -> 9389.65 | L100: =F100*350% -> 65727.55 | M100: =F100*100% -> 18779.3 | N100: =100000 -> 100000 | O100: =F100*10% -> 1877.93 | P100: 10000 | Q100: =30000 -> 30000 | R100: =SUM(F100:Q100) -> 312300.08 | S100: 364201.03 | T100: =S100-R100 -> 51900.949 | U100: =50000 -> 50000 | V100: =45833.33+80000 -> 125833.33 | W100: ='[3]DECEMBER 2019'!$H$55 -> 469.4825 | X100: =3369.51 -> 3369.51 | Y100: =SUM(U100:X100) -> 179672.32 | Z100: 112627.75 | AA100: =R100-Y100 -> 132627.75
A101: 8 | B101: RAHILA SALIHU | D101: ACCOUNT OFFICER | E101: 10(10) | F101: =18779.3 -> 18779.3 | H101: =F101*300% -> 56337.9 | I101: =F101*7.5% -> 1408.4475 | K101: =F101*50% -> 9389.65 | L101: =F101*350% -> 65727.55 | M101: =F101*100% -> 18779.3 | N101: =100000 -> 100000 | O101: =F101*10% -> 1877.93 | P101: 10000 | R101: =SUM(F101:Q101) -> 282300.08 | S101: 334201.03 | T101: =S101-R101 -> 51900.949 | U101: =70000 -> 70000 | V101: =95555.56 -> 95555.56 | W101: ='[3]DECEMBER 2019'!$H$28 -> 469.4825 | X101: =3369.51 -> 3369.51 | Y101: =SUM(U101:X101) -> 169394.55 | Z101: 112905.52 | AA101: =R101-Y101 -> 112905.52
A102: 9 | B102: USMAN WAZIRI | D102: PRINCIPAL CONF. SECRETARY | E102: 13(9) | F102: 24741.26 | H102: =F102*300% -> 74223.78 | I102: =F102*7.5% -> 1855.5945 | J102: 0 | K102: =F102*50% -> 12370.63 | L102: =F102*350% -> 86594.41 | M102: =F102*100% -> 24741.26 | N102: =100000 -> 100000 | O102: =F102*10% -> 2474.126 | P102: 15000 | Q102: 0 | R102: =SUM(F102:Q102) -> 342001.06 | S102: 349177.65 | T102: =S102-R102 -> 7176.5933 | U102: =3000 -> 3000 | V102: =90000+40000 -> 130000 | X102: 7709.76 | Y102: =SUM(U102:X102) -> 140709.76 | Z102: 241291.3 | AA102: =R102-Y102 -> 201291.3
A103: 10 | B103: IJEOMA NKOLIKWA | D103: ASSISTANT STORES OFFICER | E103: 8(8) | F103: 12732 | H103: =F103*300% -> 38196 | I103: =F103*7.5% -> 954.9 | K103: =F103*50% -> 6366 | L103: =F103*350% -> 44562 | M103: =F103*100% -> 12732 | N103: =100000 -> 100000 | O103: =F103*10% -> 1273.2 | P103: 10000 | R103: =SUM(F103:Q103) -> 226816.1 | S103: 230304.07 | T103: =S103-R103 -> 3487.968 | U103: =10000 -> 10000 | X103: 1484.37 | Y103: =SUM(U103:X103) -> 11484.37 | Z103: 215331.73 | AA103: =R103-Y103 -> 215331.73
A104: 11 | B104: ABDULRAHMAN A SULAIMAN | D104: ASSISTANT STORES OFFICER | E104: 8 (7) | F104: 12351.94 | G104: =0 -> 0 | H104: =F104*300% -> 37055.82 | I104: =F104*7.5% -> 926.3955 | K104: =F104*50% -> 6175.97 | L104: =F104*350% -> 43231.79 | M104: =F104*100% -> 12351.94 | N104: =100000 -> 100000 | O104: =F104*10% -> 1235.194 | P104: 10000 | R104: =SUM(F104:Q104) -> 223329.05 | S104: 226816.1 | T104: =S104-R104 -> 3487.0505 | U104: =20000 -> 20000 | X104: =(1484.37) -> 1484.37 | Y104: =U104+V104+W104+X104 -> 21484.37 | Z104: 201844.68 | AA104: =R104-Y104 -> 201844.68
B105: TOTAL | D105: 11 | F105: =SUM(F94:F104) -> 314782.35 | G105: =SUM(G94:G104) -> 0 | H105: =SUM(H94:H104) -> 944347.05 | I105: =SUM(I94:I104) -> 23608.676 | J105: =SUM(J94:J104) -> 160488.76 | K105: =SUM(K94:K104) -> 157391.18 | L105: =SUM(L94:L104) -> 1101738.2 | M105: =SUM(M94:M104) -> 314782.35 | ... R105: =SUM(R94:R104) -> 4638616.8 | S105: 5028202.6 | T105: =SUM(T94:T104) -> 389585.8 | U105: =SUM(U94:U104) -> 628000 | V105: =SUM(V94:V104) -> 973333.34 | W105: =SUM(W94:W104) -> 4997.7085 | X105: =SUM(X94:X104) -> 130489.85 | Y105: =SUM(Y94:Y104) -> 1736820.9 | Z105: 2853462.6 | AA105: =SUM(AA94:AA104) -> 2901795.9
B107: ADMINISTRATION & HUMAN RESOURCE
A108: 1 | B108: DR KABIR AHMED | D108: DIR. FINANCE & ADMIN | E108: 17(9) | F108: 81740.02 | G108: 0 | H108: =F108*300% -> 245220.06 | I108: =F108*7.5% -> 6130.5015 | J108: 80244.38 | K108: =F108*50% -> 40870.01 | L108: =F108*350% -> 286090.07 | M108: =F108*100% -> 81740.02 | N108: =100000 -> 100000 | O108: =F108*10% -> 8174.002 | P108: 20000 | Q108: 0 | R108: =SUM(F108:Q108) -> 950209.06 | S108: 950209.06 | T108: =S108-R108 -> 0 | U108: 50000 | V108: =322916.66 -> 322916.66 | W108: =2043.5 -> 2043.5 | X108: 52776.63 | Y108: =SUM(U108:X108) -> 427736.79 | Z108: 522472.27 | AA108: =R108-Y108 -> 522472.27
A109: 2 | B109: AMINU BELLO DUKKU | D109: DIR ADMIN/HR | E109: 17(8) | F109: =79039.64 -> 79039.64 | H109: =F109*300% -> 237118.92 | I109: =F109*7.5% -> 5927.973 | J109: =80244.38 -> 80244.38 | K109: =F109*50% -> 39519.82 | L109: =F109*350% -> 276638.74 | M109: =F109*100% -> 79039.64 | N109: =100000 -> 100000 | O109: =F109*10% -> 7903.964 | P109: 20000 | Q109: 0 | R109: =SUM(F109:Q109) -> 925433.08 | S109: 950209.06 | T109: =S109-R109 -> 24775.986 | U109: =100000 -> 100000 | X109: =52776.63 -> 52776.63 | Y109: =SUM(U109:X109) -> 152776.63 | Z109: 772656.45 | AA109: =R109-Y109 -> 772656.45
A110: 3 | B110: MAGAJI BALA | D110: DD ADMIN/HR | E110: 16(8) | F110: =41157.69 -> 41157.69 | H110: =F110*300% -> 123473.07 | I110: =F110*7.5% -> 3086.8268 | J110: 40122.19 | K110: =F110*50% -> 20578.845 | L110: =F110*350% -> 144051.92 | M110: =F110*100% -> 41157.69 | N110: =100000 -> 100000 | O110: =F110*10% -> 4115.769 | P110: 20000 | Q110: 0 | R110: =SUM(F110:Q110) -> 537744 | S110: 551465.02 | T110: =S110-R110 -> 13721.029 | U110: =25000 -> 25000 | V110: =168055.54 -> 168055.54 | X110: =21618.09 -> 21618.09 | Y110: =SUM(U110:X110) -> 214673.63 | Z110: 323070.37 | AA110: =R110-Y110 -> 323070.37
A111: 4 | B111: ARCH. TIJO ZARA BORYO | D111: MANAGER, ASSETS/MAINT. | E111: 15(9) | F111: 33507.5 | H111: =F111*300% -> 100522.5 | I111: =F111*7.5% -> 2513.0625 | J111: 40122.19 | K111: =F111*50% -> 16753.75 | L111: =F111*350% -> 117276.25 | M111: =F111*100% -> 33507.5 | N111: =100000 -> 100000 | O111: =F111*10% -> 3350.75 | P111: 20000 | Q111: 50000 | R111: =SUM(F111:Q111) -> 517553.5 | S111: 517553.5 | T111: =S111-R111 -> 0 | U111: =137500 -> 137500 | W111: ='[3]DECEMBER 2019'!$H$56 -> 837.6875 | X111: 15548.33 | Y111: =SUM(U111:X111) -> 153886.02 | Z111: 363667.48 | AA111: =R111-Y111 -> 363667.48
A112: 5 | B112: YUNUSA ABDULLAHI | D112: ASSISTANT MANAGER, HR | E112: 13(9) | F112: 24741.26 | H112: =F112*300% -> 74223.78 | I112: =F112*7.5% -> 1855.5945 | K112: =F112*50% -> 12370.63 | L112: =F112*350% -> 86594.41 | M112: =F112*100% -> 24741.26 | N112: =100000 -> 100000 | O112: =F112*10% -> 2474.126 | P112: 15000 | R112: =SUM(F112:Q112) -> 342001.06 | S112: 349177.65 | T112: =S112-R112 -> 7176.5933 | U112: =3000 -> 3000 | V112: =49442.44 -> 49442.44 | X112: =7709.76 -> 7709.76 | Y112: =SUM(U112:X112) -> 60152.2 | Z112: 281848.86 | AA112: =R112-Y112 -> 281848.86
...

Sheet ARREARS
B3: STAFF PAYROLL FOR THE MONTH OF DECEMBER, 2020
F4: ='[1]FEB 08'!E8/'[1]FEB 08'!M8 -> 0.22 | I4: ='[1]FEB 08'!F8/'[1]FEB 08'!Q8 -> 0.3
B5: STAFF NAME | W5: DEDUCTIONS | AC5: NET SALARY
D6: DESIGNATION | E6: SALARY | F6: BASIC | M6: MOTOR/ | N6: RESEARCH | O6: LEAVE | P6: OUT FIT | Q6: LEGISLATIVE | R6: MONTHLY SALARY AMOUNT PAID IN 2020 | S6: MONTHLY SALARY SUPPOSED TO BE PAID SUPPOSED TO BE PAID | T6: DIFF. PER MONTH | U6: NUMBER OF MONTHS INVOLVED | V6: TOTAL ARREAS | AB6: NOVEMBER,2020 | AC6: DECEMBER,2020
E7: LEVEL | F7: SALARY | G7: SALARY/ALLOWCE AREARS | H7: RENT | I7: UTILITY | J7: DOMESTIC | K7: ENTERT. | L7: FURNIT. | M7: FUEL | N7: ALLOWANCE | O7: ALLCE | P7: ALLCE | Q7: DUTY ALLCE | R7: SALARY | S7: SALARY | T7: SALARY | V7: SALARY | W7: COOP SOCIETY | X7: COOP. LOAN RECOVERY | Y7: NHF DEDUCTION | Z7: PAYE | AA7: TOTAL
A8: S/N | B8: DG OFFICE | F8: N | I8: N | R8: N | S8: N | T8: N | V8: N | Z8: N
A9: 1 | B9: ANTHONY EDET | D9: OFFICER M&E | E9: 10(12) | F9: =19774.62 -> 19774.62 | H9: =F9*300% -> 59323.86 | I9: =F9*7.5% -> 1483.0965 | J9: 0 | K9: =F9*50% -> 9887.31 | L9: =F9*350% -> 69211.17 | M9: =F9*100% -> 19774.62 | N9: =100000 -> 100000 | O9: =F9*10% -> 1977.462 | P9: 10000 | Q9: 0 | R9: =191432 -> 191432 | S9: =226713 -> 226713 | T9: =S9-R9 -> 35281 | U9: 12 | V9: =T9*U9 -> 423372 | W9: 10000 | Y9: ='[3]DECEMBER 2019'!$H$43 -> 494.3655 | Z9: 3369.51 | AA9: =SUM(W9:Z9) -> 13863.876 | AB9: 277568.26 | AC9: =R9-AA9 -> 177568.12 | AG9: =3369.51 -> 3369.51 | AH9: =7709.76 -> 7709.76 | AI9: =AH9-AG9 -> 4340.25 | AJ9: =AI9*12 -> 52083
B10: TOTAL | D10: 19 | F10: =SUM(F9:F9) -> 19774.62 | G10: =SUM(G9:G9) -> 0 | H10: =SUM(H9:H9) -> 59323.86 | I10: =SUM(I9:I9) -> 1483.0965 | J10: =SUM(J9:J9) -> 0 | K10: =SUM(K9:K9) -> 9887.31 | L10: =SUM(L9:L9) -> 69211.17 | M10: =SUM(M9:M9) -> 19774.62 | ... R10: =SUM(R9:R9) -> 191432 | V10: =SUM(V9) -> 423372 | W10: =SUM(W9:W9) -> 10000 | X10: =SUM(X9:X9) -> 0 | Y10: =SUM(Y9:Y9) -> 494.3655 | Z10: =SUM(Z9:Z9) -> 3369.51 | AA10: =SUM(AA9:AA9) -> 13863.876 | AB10: 6022279.4 | AC10: =SUM(AC9:AC9) -> 177568.12
B11: LEG. SUPPORT SEVICES
A12: 1 | B12: DR MOHAMMED O. AMALI | D12: RESEARCH FELLOW II | E12: 13(9) | F12: =24741.26 -> 24741.26 | H12: =F12*300% -> 74223.78 | I12: =F12*7.5% -> 1855.5945 | K12: =F12*50% -> 12370.63 | L12: =F12*350% -> 86594.41 | M12: =F12*100% -> 24741.26 | N12: =150000 -> 150000 | O12: =F12*10% -> 2474.126 | P12: 15000 | R12: =242001 -> 242001 | S12: =249153 -> 249153 | T12: =S12-R12 -> 7152 | U12: =2 -> 2 | V12: =T12*U12 -> 14304 | W12: =15000 -> 15000 | X12: =106666.67 -> 106666.67 | Z12: 7709.76 | AA12: =Z12+W12+X12+Y12 -> 129376.43 | AB12: 369291.3 | AC12: =R12-AA12 -> 112624.57 | AG12: =7709.76 -> 7709.76 | AH12: =7709.76 -> 7709.76 | AI12: =AH12-AG12 -> 0
A13: 2 | B13: DORIS DAKDA AARON | D13: RESEARCH OFFICER | E13: 10(9) | F13: =18281.64 -> 18281.64 | H13: =F13*300% -> 54844.92 | I13: =F13*7.5% -> 1371.123 | K13: =F13*50% -> 9140.82 | L13: =F13*350% -> 63985.74 | M13: =F13*100% -> 18281.64 | N13: =150000 -> 150000 | O13: =F13*10% -> 1828.164 | P13: 10000 | R13: =177734 -> 177734 | S13: =226713 -> 226713 | T13: =S13-R13 -> 48979 | U13: 5 | V13: =T13*U13 -> 244895 | W13: =50000+10000 -> 60000 | Y13: ='[3]DECEMBER 2019'!$H$52 -> 457.041 | Z13: 3369.51 | AA13: =Z13+W13+X13+Y13 -> 63826.551 | AB13: 263907.5 | AC13: =R13-AA13 -> 113907.45
B14: TOTAL | D14: 11 | F14: =SUM(F12:F13) -> 43022.9 | H14: =SUM(H12:H13) -> 129068.7 | I14: =SUM(I12:I13) -> 3226.7175 | J14: =SUM(J12:J13) -> 0 | K14: =SUM(K12:K13) -> 21511.45 | L14: =SUM(L12:L13) -> 150580.15 | M14: =SUM(M12:M13) -> 43022.9 | N14: =SUM(N12:N13) -> 300000 | O14: =SUM(O12:O13) -> 4302.29 | ... R14: =SUM(R12:R13) -> 419735 | V14: =SUM(V12:V13) -> 259199 | W14: =SUM(W12:W13) -> 75000 | X14: =SUM(X12:X13) -> 106666.67 | Y14: =SUM(Y12:Y13) -> 457.041 | Z14: =SUM(Z12:Z13) -> 11079.27 | AA14: =SUM(AA12:AA13) -> 193202.98 | AB14: 3902139.3 | AC14: =R14-AA14 -> 226532.02 | AG14: =3369.51 -> 3369.51 | AH14: =7709.76 -> 7709.76 | AI14: =AH14-AG14 -> 4340.25 | AJ14: =AI14*5 -> 21701.25
B16: DEMOCRATIC STUDIES
A17: 1 | B17: NGARA CHRISTOPHER OCHANJA | D17: RESEARCH FELLOW 11 | E17: 13(10) | F17: =25523.45 -> 25523.45 | H17: =F17*300% -> 76570.35 | I17: =F17*7.5% -> 1914.2587 | K17: =F17*50% -> 12761.725 | L17: =F17*350% -> 89332.075 | M17: =F17*100% -> 25523.45 | N17: =150000 -> 150000 | O17: =F17*10% -> 2552.345 | P17: 15000 | Q17: 0 | R17: =249177 -> 249177 | S17: =257211 -> 257211 | T17: =S17-R17 -> 8034 | U17: =12 -> 12 | V17: =T17*U17 -> 96408 | W17: =20000 -> 20000 | X17: =163103.59 -> 163103.59 | Y17: ='[3]DECEMBER 2019'!$H$50 -> 638.08625 | Z17: =7709.76 -> 7709.76 | AA17: =W17+X17+Y17+Z17 -> 191451.44 | AB17: 207726.22 | AC17: =R17-AA17 -> 57725.564 | AG17: =7709.76 -> 7709.76 | AH17: =7709.76 -> 7709.76 | AI17: =AH17-AG17 -> 0
A18: 2 | B18: EJALONIBU GANIYU LAYI | D18: RESEARCH OFFICER | E18: 10(9) | F18: =18281.64 -> 18281.64 | G18: =0 -> 0 | H18: =F18*300% -> 54844.92 | I18: =F18*7.5% -> 1371.123 | K18: =F18*50% -> 9140.82 | L18: =F18*350% -> 63985.74 | M18: =F18*100% -> 18281.64 | N18: =150000 -> 150000 | O18: =F18*10% -> 1828.164 | P18: 10000 | R18: =177734 -> 177734 | S18: =226713 -> 226713 | T18: =S18-R18 -> 48979 | U18: 5 | V18: =T18*U18 -> 244895 | W18: =110000 -> 110000 | Z18: 3369.51 | AA18: =W18+X18+Y18+Z18 -> 113369.51 | AB18: 214364.54 | AC18: =R18-AA18 -> 64364.49 | AG18: =3369.51 -> 3369.51 | AH18: =7709.76 -> 7709.76 | AI18: =AH18-AG18 -> 4340.25 | AJ18: =AI18*5 -> 21701.25
B19: TOTAL | D19: 4 | F19: =SUM(F17:F18) -> 43805.09 | G19: =SUM(G17:G18) -> 0 | H19: =SUM(H17:H18) -> 131415.27 | I19: =SUM(I17:I18) -> 3285.3817 | J19: =SUM(J17:J18) -> 0 | K19: =SUM(K17:K18) -> 21902.545 | L19: =SUM(L17:L18) -> 153317.82 | M19: =SUM(M17:M18) -> 43805.09 | ... R19: =SUM(R17:R18) -> 426911 | V19: =SUM(V17:V18) -> 341303 | W19: =SUM(W17:W18) -> 130000 | X19: =SUM(X17:X18) -> 163103.59 | Y19: =SUM(Y17:Y18) -> 638.08625 | Z19: =SUM(Z17:Z18) -> 11079.27 | AA19: =SUM(R19:Z19) -> 1073034.9 | AB19: 1428432.7 | AC19: =SUM(AC17:AC18) -> 122090.05
B21: POST GRADUATE SCHOOL
B22: DR AUGUSTINE C. OSIGWE | D22: RESEARCH FELLOW I | E22: 14(9) | R22: =265272 -> 265272 | S22: =344720 -> 344720 | T22: =S22-R22 -> 79448 | U22: 3 | V22: =T22*U22 -> 238344 | AG22: =7709.76 -> 7709.76 | AH22: =15548.33 -> 15548.33 | AI22: =AH22-AG22 -> 7838.57 | AJ22: =AI22*3 -> 23515.71
A23: 1 | B23: UZODINMA EMMANUEL EZENWA | D23: PROGRAMME OFFICER | E23: 10(10) | F23: =18779.3 -> 18779.3 | H23: =F23*300% -> 56337.9 | I23: =F23*7.5% -> 1408.4475 | J23: 0 | K23: =F23*50% -> 9389.65 | L23: =F23*350% -> 65727.55 | M23: =F23*100% -> 18779.3 | N23: =150000 -> 150000 | O23: =F23*10% -> 1877.93 | P23: 10000 | Q23: 0 | R23: =182300 -> 182300 | S23: =226713 -> 226713 | T23: =S23-R23 -> 44413 | U23: 12 | V23: =T23*U23 -> 532956 | W23: =0 -> 0 | X23: =0 -> 0 | Y23: ='[3]DECEMBER 2019'!$H$48 -> 469.4825 | Z23: 3369.51 | AA23: =W23+X23+Y23+Z23 -> 3838.9925 | AB23: 328461.08 | AC23: =R23-AA23 -> 178461.01 | AG23: =3369.51 -> 3369.51 | AH23: =7709.76 -> 7709.76 | AI23: =AH23-AG23 -> 4340.25 | AJ23: =AI23*12 -> 52083
B24: TOTAL | D24: 4 | F24: =SUM(F23:F23) -> 18779.3 | H24: =SUM(H23:H23) -> 56337.9 | I24: =SUM(I23:I23) -> 1408.4475 | J24: =SUM(J23:J23) -> 0 | K24: =SUM(K23:K23) -> 9389.65 | L24: =SUM(L23:L23) -> 65727.55 | M24: =SUM(M23:M23) -> 18779.3 | N24: =SUM(N23:N23) -> 150000 | O24: =SUM(O23:O23) -> 1877.93 | ... R24: =SUM(R23:R23) -> 182300 | V24: =SUM(V22:V23) -> 771300 | W24: =SUM(W23:W23) -> 0 | X24: =SUM(X23:X23) -> 0 | Y24: =SUM(Y23:Y23) -> 469.4825 | Z24: =SUM(Z23:Z23) -> 3369.51 | AA24: =SUM(AA23:AA23) -> 3838.9925 | AB24: 1188810.1 | AC24: =SUM(AC23:AC23) -> 178461.01 | AJ24: =SUM(AJ22:AJ23) -> 75598.71
B26: ECONOMIC AND SOCIAL DEV.
A27: 1 | B27: TERFA WILLIAMS ABRAHAM | D27: RESEARCH FELLOW I | E27: 14(11) | F27: 28489.81 | H27: =F27*300% -> 85469.43 | I27: =F27*7.5% -> 2136.7357 | K27: =F27*50% -> 14244.905 | L27: =F27*350% -> 99714.335 | M27: =F27*100% -> 28489.81 | N27: =150000 -> 150000 | O27: =F27*10% -> 2848.981 | P27: 20000 | R27: =281394 -> 281394 | S27: =344720 -> 344720 | T27: =S27-R27 -> 63326 | U27: 3 | V27: =T27*U27 -> 189978 | Z27: 7709.76 | AA27: =SUM(W27:Z27) -> 7709.76 | AB27: 423684.25 | AC27: =R27-AA27 -> 273684.24 | AG27: =7709.76 -> 7709.76 | AH27: =15548.33 -> 15548.33 | AI27: =AH27-AG27 -> 7838.57 | AJ27: =AI27*3 -> 23515.71
A28: 2 | B28: JUMARE FADILA | D28: RESEARCH FELLOW II | E28: 13(10) | F28: =25523.45 -> 25523.45 | H28: =F28*300% -> 76570.35 | I28: =F28*7.5% -> 1914.2587 | J28: 0 | K28: =F28*50% -> 12761.725 | L28: =F28*350% -> 89332.075 | M28: =F28*100% -> 25523.45 | N28: =150000 -> 150000 | O28: =F28*10% -> 2552.345 | P28: 15000 | Q28: 0 | R28: =249177 -> 249177 | S28: =257211 -> 257211 | T28: =S28-R28 -> 8034 | U28: 12 | V28: =T28*U28 -> 96408 | W28: 5000 | Z28: =7709.76 -> 7709.76 | AA28: =SUM(W28:Z28) -> 12709.76 | AB28: 386467.89 | AC28: =R28-AA28 -> 236467.24 | AG28: =7709.76 -> 7709.76 | AH28: =7709.76 -> 7709.76 | AI28: =AH28-AG28 -> 0
A29: 3 | B29: OMOJU OLUWASOLA EMMANUEL | D29: RESEARCH FELLOW II | E29: 13(9) | F29: =24741.26 -> 24741.26 | H29: =F29*300% -> 74223.78 | I29: =F29*7.5% -> 1855.5945 | K29: =F29*50% -> 12370.63 | L29: =F29*350% -> 86594.41 | M29: =F29*100% -> 24741.26 | N29: =150000 -> 150000 | O29: =F29*10% -> 2474.126 | P29: 15000 | R29: =242001 -> 242001 | S29: =249153 -> 249153 | T29: =S29-R29 -> 7152 | U29: =4 -> 4 | V29: =T29*U29 -> 28608 | W29: =50000 -> 50000 | X29: =87500 -> 87500 | Z29: =7709.76 -> 7709.76 | AA29: =SUM(W29:Z29) -> 145209.76 | AB29: 246791.3 | AC29: =R29-AA29 -> 96791.24 | AG29: =7709.76 -> 7709.76 | AH29: =7709.76 -> 7709.76 | AI29: =AH29-AG29 -> 0
A30: 4 | B30: ONYIMADU C. ONYEBUCHI | D30: RESEARCH FELLOWII | E30: 13(9) | F30: =24741.26 -> 24741.26 | H30: =F30*300% -> 74223.78 | I30: =F30*7.5% -> 1855.5945 | K30: =F30*50% -> 12370.63 | L30: =F30*350% -> 86594.41 | M30: =F30*100% -> 24741.26 | N30: =150000 -> 150000 | O30: =F30*10% -> 2474.126 | P30: 15000 | R30: =242001 -> 242001 | S30: =249153 -> 249153 | T30: =S30-R30 -> 7152 | U30: 2 | V30: =T30*U30 -> 14304 | W30: =50000 -> 50000 | Y30: ='[3]DECEMBER 2019'!$H$54 -> 618.5315 | Z30: 7709.76 | AA30: =SUM(W30:Z30) -> 58328.291 | AB30: 333672.77 | AC30: =R30-AA30 -> 183672.71 | AG30: =7709.76 -> 7709.76 | AH30: =7709.76 -> 7709.76 | AI30: =AH30-AG30 -> 0
A31: 5 | B31: IBE EZECHI CYRIACUS | D31: RESEARCH OFFICER | E31: 10(9) | F31: =18281.64 -> 18281.64 | H31: =F31*300% -> 54844.92 | I31: =F31*7.5% -> 1371.123 | J31: 0 | K31: =F31*50% -> 9140.82 | L31: =F31*350% -> 63985.74 | M31: =F31*100% -> 18281.64 | N31: =150000 -> 150000 | O31: =F31*10% -> 1828.164 | P31: 10000 | Q31: 0 | R31: 177734 | S31: =226713 -> 226713 | T31: =S31-R31 -> 48979 | U31: 3 | V31: =T31*U31 -> 146937 | W31: =25000 -> 25000 | Z31: 3369.51 | AA31: =SUM(W31:Z31) -> 28369.51 | AB31: 299364.54 | AC31: =R31-AA31 -> 149364.49 | AG31: =3369.51 -> 3369.51 | AH31: =7709.76 -> 7709.76 | AI31: =AH31-AG31 -> 4340.25 | AJ31: =AI31*3 -> 13020.75
B32: TOTAL | D32: 9 | F32: =SUM(F27:F31) -> 121777.42 | H32: =SUM(H27:H31) -> 365332.26 | I32: =SUM(I27:I31) -> 9133.3065 | J32: =SUM(J27:J31) -> 0 | K32: =SUM(K27:K31) -> 60888.71 | L32: =SUM(L27:L31) -> 426220.97 | M32: =SUM(M27:M31) -> 121777.42 | N32: =SUM(N27:N31) -> 750000 | O32: =SUM(O27:O31) -> 12177.742 | ... R32: =SUM(R27:R31) -> 1192307 | V32: =SUM(V27:V31) -> 476235 | W32: =SUM(W27:W31) -> 130000 | X32: =SUM(X27:X31) -> 87500 | Y32: =SUM(Y27:Y31) -> 618.5315 | Z32: =SUM(Z27:Z31) -> 34208.55 | AA32: =SUM(W32:Z32) -> 252327.08 | AB32: 3362401.6 | AC32: =SUM(AC27:AC31) -> 939979.92 | AJ32: =SUM(AJ27:AJ31) -> 36536.46
B34: TRAINING AND INTERNATIONAL COOP
A35: 1 | B35: DR FRANCIS NDUM OJIE | D35: ASST. MANAGER, TRAINING | E35: 13(9) | F35: =24741.26 -> 24741.26 | H35: =F35*300% -> 74223.78 | I35: =F35*7.5% -> 1855.5945 | K35: =F35*50% -> 12370.63 | L35: =F35*350% -> 86594.41 | M35: =F35*100% -> 24741.26 | N35: 100000 | O35: =F35*10% -> 2474.126 | P35: 15000 | R35: =242001 -> 242001 | S35: =249153 -> 249153 | T35: =S35-R35 -> 7152 | U35: 6 | V35: =T35*U35 -> 42912 | Z35: =7709.76 -> 7709.76 | AA35: =SUM(W35:Z35) -> 7709.76 | AB35: 334291.3 | AC35: =R35-AA35 -> 234291.24 | AG35: =7709.76 -> 7709.76 | AH35: =7709.76 -> 7709.76 | AI35: =AH35-AG35 -> 0
B36: TOTAL | D36: 4 | F36: =SUM(F35:F35) -> 24741.26 | G36: =SUM(G35:G35) -> 0 | H36: =SUM(H35:H35) -> 74223.78 | I36: =SUM(I35:I35) -> 1855.5945 | J36: =SUM(J35:J35) -> 0 | K36: =SUM(K35:K35) -> 12370.63 | L36: =SUM(L35:L35) -> 86594.41 | M36: =SUM(M35:M35) -> 24741.26 | ... R36: =SUM(R35:R35) -> 242001 | V36: =SUM(V35) -> 42912 | W36: =SUM(W35:W35) -> 0 | X36: =SUM(X35:X35) -> 0 | Y36: =SUM(Y35:Y35) -> 0 | Z36: =SUM(Z35:Z35) -> 7709.76 | AA36: =SUM(W36:Z36) -> 7709.76 | AB36: 1505045.4 | AC36: =SUM(AC35:AC35) -> 234291.24
B38: LIBRARY AND DOCUMENTATION
A39: 1 | B39: CHINAKO N. ASOGWA | D39: LIBRARY OFFICER | E39: 10(14) | F39: =20770 -> 20770 | H39: =F39*300% -> 62310 | I39: =F39*7.5% -> 1557.75 | J39: 0 | K39: =F39*50% -> 10385 | L39: =F39*350% -> 72695 | M39: =F39*100% -> 20770 | N39: 150000 | O39: =F39*10% -> 2077 | P39: 10000 | R39: =195998 -> 195998 | S39: =226713 -> 226713 | T39: =S39-R39 -> 30715 | U39: =5 -> 5 | V39: =T39*U39 -> 153575 | W39: =50000 -> 50000 | X39: =43083.33 -> 43083.33 | Z39: 3369.51 | AA39: =SUM(W39:Z39) -> 96452.84 | AB39: 254111.91 | AC39: =R39-AA39 -> 99545.16 | AD39: =200564 -> 200564 | AE39: =234201 -> 234201 | AF39: =AE39-AD39 -> 33637 | AG39: 12 | AH39: =AF39*12 -> 403644 | AI39: =V39+AH39 -> 557219
B40: TOTAL | D40: 4 | F40: =SUM(F39:F39) -> 20770 | H40: =SUM(H39:H39) -> 62310 | I40: =SUM(I39:I39) -> 1557.75 | J40: =SUM(J39:J39) -> 0 | K40: =SUM(K39:K39) -> 10385 | L40: =SUM(L39:L39) -> 72695 | M40: =SUM(M39:M39) -> 20770 | N40: =SUM(N39:N39) -> 150000 | O40: =SUM(O39:O39) -> 2077 | ... R40: =SUM(R39:R39) -> 195998 | V40: =AI39 -> 557219 | W40: =SUM(W39:W39) -> 50000 | X40: =SUM(X39:X39) -> 43083.33 | Y40: =SUM(Y39:Y39) -> 0 | Z40: =SUM(Z39:Z39) -> 3369.51 | AA40: =SUM(W40:Z40) -> 96452.84 | AB40: 1667586.3 | AC40: =SUM(AC39:AC39) -> 99545.16 | AG40: =3369.51 -> 3369.51 | AH40: =7709.76 -> 7709.76 | AI40: =AH40-AG40 -> 4340.25 | AJ40: =AI40*17 -> 73784.25
B42: FINANCE & ACCOUNT
A43: 1 | B43: ANDRAWUS MUSA | D43: ASSIST. MGR. STORE | E43: 13(10) | F43: =25523.45 -> 25523.45 | H43: =F43*300% -> 76570.35 | I43: =F43*7.5% -> 1914.2587 | J43: 0 | K43: =F43*50% -> 12761.725 | L43: =F43*350% -> 89332.075 | M43: =F43*100% -> 25523.45 | N43: =100000 -> 100000 | O43: =F43*10% -> 2552.345 | P43: 15000 | Q43: 0 | R43: =249177 -> 249177 | S43: =344720 -> 344720 | T43: =S43-R43 -> 95543 | U43: 12 | V43: =T43*U43 -> 1146516 | W43: =50000 -> 50000 | X43: =90000 -> 90000 | Y43: ='[3]DECEMBER 2019'!$H$32 -> 638.08625 | Z43: =7709.76 -> 7709.76 | AA43: =SUM(W43:Z43) -> 148347.85 | AB43: 200829.81 | AC43: =R43-AA43 -> 100829.15 | AG43: =7709.76 -> 7709.76 | AH43: =15548.33 -> 15548.33 | AI43: =15548.33-7709.76 -> 7838.57 | AJ43: =AI43*12 -> 94062.84
A44: 2 | B44: TONDO IORWUESE EDWARD | D44: ASSIST. MGR ACCOUNTS | E44: 13(10) | F44: =25523.45 -> 25523.45 | H44: =F44*300% -> 76570.35 | I44: =F44*7.5% -> 1914.2587 | J44: 0 | K44: =F44*50% -> 12761.725 | L44: =F44*350% -> 89332.075 | M44: =F44*100% -> 25523.45 | N44: =100000 -> 100000 | O44: =F44*10% -> 2552.345 | P44: 15000 | Q44: =100000 -> 100000 | R44: =249177 -> 249177 | S44: =344720 -> 344720 | T44: =S44-R44 -> 95543 | U44: 12 | V44: =T44*U44 -> 1146516 | W44: =30000 -> 30000 | X44: =100000 -> 100000 | Y44: ='[3]DECEMBER 2019'!$H$25 -> 638.08625 | Z44: =7709.76 -> 7709.76 | AA44: =SUM(W44:Z44) -> 138347.85 | AB44: 310829.81 | AC44: =R44-AA44 -> 110829.15 | AG44: =7709.76 -> 7709.76 | AH44: =15548.33 -> 15548.33 | AI44: =15548.33-7709.76 -> 7838.57 | AJ44: =AI44*12 -> 94062.84
A45: 3 | B45: OJOGIWA ABISOLA GANIAT | D45: ACCOUNT OFFICER | E45: 10(10) | F45: =18779.3 -> 18779.3 | H45: =F45*300% -> 56337.9 | I45: =F45*7.5% -> 1408.4475 | K45: =F45*50% -> 9389.65 | L45: =F45*350% -> 65727.55 | M45: =F45*100% -> 18779.3 | N45: =100000 -> 100000 | O45: =F45*10% -> 1877.93 | P45: 10000 | Q45: =30000 -> 30000 | R45: =182300 -> 182300 | S45: =226713 -> 226713 | T45: =S45-R45 -> 44413 | U45: 12 | V45: =T45*U45 -> 532956 | W45: =50000 -> 50000 | X45: =45833.33+80000 -> 125833.33 | Y45: ='[3]DECEMBER 2019'!$H$55 -> 469.4825 | Z45: =3369.51 -> 3369.51 | AA45: =SUM(W45:Z45) -> 179672.32 | AB45: 112627.75 | AC45: =R45-AA45 -> 2627.6775 | AG45: =3369.51 -> 3369.51 | AH45: =7709.76 -> 7709.76 | AI45: =AH45-AG45 -> 4340.25 | AJ45: =AI45*12 -> 52083
A46: 4 | B46: RAHILA SALIHU | D46: ACCOUNT OFFICER | E46: 10(10) | F46: =18779.3 -> 18779.3 | H46: =F46*300% -> 56337.9 | I46: =F46*7.5% -> 1408.4475 | K46: =F46*50% -> 9389.65 | L46: =F46*350% -> 65727.55 | M46: =F46*100% -> 18779.3 | N46: =100000 -> 100000 | O46: =F46*10% -> 1877.93 | P46: 10000 | R46: =182300 -> 182300 | S46: =226713 -> 226713 | T46: =S46-R46 -> 44413 | U46: 12 | V46: =T46*U46 -> 532956 | W46: =70000 -> 70000 | X46: =95555.56 -> 95555.56 | Y46: ='[3]DECEMBER 2019'!$H$28 -> 469.4825 | Z46: =3369.51 -> 3369.51 | AA46: =SUM(W46:Z46) -> 169394.55 | AB46: 112905.52 | AC46: =R46-AA46 -> 12905.447 | AG46: =3369.51 -> 3369.51 | AH46: =7709.76 -> 7709.76 | AI46: =AH46-AG46 -> 4340.25 | AJ46: =AI46*12 -> 52083
B47: TOTAL | D47: 11 | F47: =SUM(F43:F46) -> 88605.5 | G47: =SUM(G43:G46) -> 0 | H47: =SUM(H43:H46) -> 265816.5 | I47: =SUM(I43:I46) -> 6645.4125 | J47: =SUM(J43:J46) -> 0 | K47: =SUM(K43:K46) -> 44302.75 | L47: =SUM(L43:L46) -> 310119.25 | M47: =SUM(M43:M46) -> 88605.5 | ... R47: =SUM(R43:R46) -> 862954 | V47: =SUM(V43:V46) -> 3358944 | W47: =SUM(W43:W46) -> 200000 | X47: =SUM(X43:X46) -> 411388.89 | Y47: =SUM(Y43:Y46) -> 2215.1375 | Z47: =SUM(Z43:Z46) -> 22158.54 | AA47: =SUM(AA43:AA46) -> 635762.57 | AB47: 2853462.6 | AC47: =SUM(AC43:AC46) -> 227191.43 | AJ47: =SUM(AJ43:AJ46) -> 292291.68
B49: ADMINISTRATION & HUMAN RESOURCE
A50: 1 | B50: MOHAMMED R. ADAMU | D50: SENIOR CONFIDENTIAL SECR | E50: 10(10) | F50: =18779.3 -> 18779.3 | H50: =F50*300% -> 56337.9 | I50: =F50*7.5% -> 1408.4475 | J50: 0 | K50: =F50*50% -> 9389.65 | L50: =F50*350% -> 65727.55 | M50: =F50*100% -> 18779.3 | N50: =100000 -> 100000 | O50: =F50*10% -> 1877.93 | P50: 10000 | Q50: 0 | R50: =182300 -> 182300 | S50: =226713 -> 226713 | T50: =S50-R50 -> 44413 | U50: 10 | V50: =T50*U50 -> 444130 | W50: =50000 -> 50000 | X50: =50000 -> 50000 | Z50: 3369.51 | AA50: =SUM(W50:Z50) -> 103369.51 | AB50: 178930.57 | AC50: =R50-AA50 -> 78930.49 | AG50: =3369.51 -> 3369.51 | AH50: =7709.76 -> 7709.76 | AI50: =AH50-AG50 -> 4340.25 | AJ50: =AI50*10 -> 43402.5
A51: 2 | B51: ABDULWAHAB DAHIRU | D51: ADMIN ASSISTANT | E51: 8(10) | F51: 13492.21 | H51: =F51*300% -> 40476.63 | I51: =F51*7.5% -> 1011.9157 | K51: =F51*50% -> 6746.105 | L51: =F51*350% -> 47222.735 | M51: =F51*100% -> 13492.21 | N51: =100000 -> 100000 | O51: =F51*10% -> 1349.221 | P51: 10000 | R51: =133791 -> 133791 | S51: =168602 -> 168602 | T51: =S51-R51 -> 34811 | U51: 12 | V51: =T51*U51 -> 417732 | W51: =10000 -> 10000 | X51: =81978.38+50000 -> 131978.38 | Y51: ='[3]DECEMBER 2019'!$H$49 -> 337.30525 | Z51: 1484.37 | AA51: =SUM(W51:Z51) -> 143800.06 | AB51: 139990.97 | AC51: =R51-AA51 -> -10009.055
A52: 3 | B52: OLATUNJI OYEDELE YUSUF | D52: SENIOR DRIVER | E52: 5(13) | F52: =5769.6 -> 5769.6 | H52: =F52*300% -> 17308.8 | I52: =F52*7.5% -> 432.72 | J52: 0 | K52: =F52*50% -> 2884.8 | L52: =F52*350% -> 20193.6 | M52: =F52*100% -> 5769.6 | N52: =25000+4000 -> 29000 | O52: =F52*10% -> 576.96 | P52: 5000 | Q52: 0 | R52: =57936 -> 57936 | S52: =85105 -> 85105 | T52: =S52-R52 -> 27169 | U52: 10 | V52: =T52*U52 -> 271690 | W52: =5000+2000 -> 7000 | X52: =24750 -> 24750 | Y52: ='[3]DECEMBER 2019'!$H$44 -> 144.24 | Z52: 236.04 | AA52: =SUM(W52:Z52) -> 32130.28 | AB52: 54805.8 | AC52: =R52-AA52 -> 25805.72
A53: 4 | B53: TASIU MOHAMMED | D53: SENIOR DRIVER | E53: 5(13) | F53: =5769.6 -> 5769.6 | H53: =F53*300% -> 17308.8 | I53: =F53*7.5% -> 432.72 | J53: 0 | K53: =F53*50% -> 2884.8 | L53: =F53*350% -> 20193.6 | M53: =F53*100% -> 5769.6 | N53: =25000+7000 -> 32000 | O53: =F53*10% -> 576.96 | P53: 5000 | Q53: 0 | R53: =57936 -> 57936 | S53: =85105 -> 85105 | T53: =S53-R53 -> 27169 | U53: 10 | V53: =T53*U53 -> 271690 | W53: =5000+2000 -> 7000 | X53: =18578.64 -> 18578.64 | Z53: 236.04 | AA53: =SUM(W53:Z53) -> 25814.68 | AB53: 64121.4 | AC53: =R53-AA53 -> 32121.32
A54: 5 | B54: NAMADI IDRIS UMAR | D54: SENIOR DRIVER | E54: 5(13) | F54: =5769.6 -> 5769.6 | H54: =F54*300% -> 17308.8 | I54: =F54*7.5% -> 432.72 | J54: 0 | K54: =F54*50% -> 2884.8 | L54: =F54*350% -> 20193.6 | M54: =F54*100% -> 5769.6 | N54: =25000+4000 -> 29000 | O54: =F54*10% -> 576.96 | P54: 5000 | Q54: 0 | R54: =57936 -> 57936 | S54: =85105 -> 85105 | T54: =S54-R54 -> 27169 | U54: 10 | V54: =T54*U54 -> 271690 | W54: =5000+2000 -> 7000 | X54: =22916.67 -> 22916.67 | Z54: 236.04 | AA54: =SUM(W54:Z54) -> 30152.71 | AB54: 64700.04 | AC54: =R54-AA54 -> 27783.29
A55: 6 | B55: DANJUMA KAGADAMA | D55: SENIOR DRIVER | E55: 5(13) | F55: =5769.6 -> 5769.6 | H55: =F55*300% -> 17308.8 | I55: =F55*7.5% -> 432.72 | J55: 0 | K55: =F55*50% -> 2884.8 | L55: =F55*350% -> 20193.6 | M55: =F55*100% -> 5769.6 | N55: =25000+4000 -> 29000 | O55: =F55*10% -> 576.96 | P55: 5000 | Q55: 0 | R55: =57936 -> 57936 | S55: =85105 -> 85105 | T55: =S55-R55 -> 27169 | U55: 10 | V55: =T55*U55 -> 271690 | W55: =5000+2000 -> 7000 | X55: =15972.22 -> 15972.22 | Z55: 236.04 | AA55: =SUM(W55:Z55) -> 23208.26 | AB55: 65829.94 | AC55: =R55-AA55 -> 34727.74
A56: 7 | B56: ALFRED ISABU | D56: SENIOR DRIVER | E56: 5(13) | F56: =5769.6 -> 5769.6 | H56: =F56*300% -> 17308.8 | I56: =F56*7.5% -> 432.72 | J56: 0 | K56: =F56*50% -> 2884.8 | L56: =F56*350% -> 20193.6 | M56: =F56*100% -> 5769.6 | N56: =25000+4000 -> 29000 | O56: =F56*10% -> 576.96 | P56: 5000 | Q56: 0 | R56: =57936 -> 57936 | S56: =85105 -> 85105 | T56: =S56-R56 -> 27169 | U56: 10 | V56: =T56*U56 -> 271690 | W56: 5000 | X56: =0 -> 0 | Z56: 236.04 | AA56: =SUM(W56:Z56) -> 5236.04 | AB56: 81700.04 | AC56: =R56-AA56 -> 52699.96
A57: 8 | B57: ALIYU YAKUBU | D57: SENIOR DRIVER | E57: 5(13) | F57: =5769.6 -> 5769.6 | G57: =0 -> 0 | H57: =F57*300% -> 17308.8 | I57: =F57*7.5% -> 432.72 | J57: 0 | K57: =F57*50% -> 2884.8 | L57: =F57*350% -> 20193.6 | M57: =F57*100% -> 5769.6 | N57: =25000+3000 -> 28000 | O57: =F57*10% -> 576.96 | P57: 5000 | Q57: 0 | R57: =57936 -> 57936 | S57: =85105 -> 85105 | T57: =S57-R57 -> 27169 | U57: 10 | V57: =T57*U57 -> 271690 | W57: =10000+2000 -> 12000 | X57: =25704.84 -> 25704.84 | Y57: ='[3]DECEMBER 2019'!$H$58 -> 144.24 | Z57: 236.04 | AA57: =SUM(W57:Z57) -> 38085.12 | AB57: 47850.96 | AC57: =R57-AA57 -> 19850.88
A58: 9 | B58: ABDULLAHI HARUNA | D58: SENIOR DRIVER | E58: 5(13) | F58: =5769.6 -> 5769.6 | H58: =F58*300% -> 17308.8 | I58: =F58*7.5% -> 432.72 | J58: 0 | K58: =F58*50% -> 2884.8 | L58: =F58*350% -> 20193.6 | M58: =F58*100% -> 5769.6 | N58: =25000+7000 -> 32000 | O58: =F58*10% -> 576.96 | P58: 5000 | Q58: 0 | R58: =57936 -> 57936 | S58: =85105 -> 85105 | T58: =S58-R58 -> 27169 | U58: 10 | V58: =T58*U58 -> 271690 | W58: =3000+2000 -> 5000 | X58: =8237.49 -> 8237.49 | Z58: 236.04 | AA58: =SUM(W58:Z58) -> 13473.53 | AB58: 76462.55 | AC58: =R58-AA58 -> 44462.47
A59: 10 | B59: ABUBAKAR MUSA DANLAMI | D59: DRIVER | E59: 4(12) | F59: =4836.3 -> 4836.3 | H59: =F59*300% -> 14508.9 | I59: =F59*7.5% -> 362.7225 | K59: =F59*50% -> 2418.15 | L59: =F59*350% -> 16927.05 | M59: =F59*100% -> 4836.3 | N59: =25000+7000 -> 32000 | O59: =F59*10% -> 483.63 | P59: 5000 | Q59: 0 | R59: =46676 -> 46676 | S59: =50104 -> 50104 | T59: =S59-R59 -> 3428 | U59: 11 | V59: =T59*U59 -> 37708 | W59: =3000+2000 -> 5000 | X59: =48471.28 -> 48471.28 | Z59: 236.04 | AA59: =SUM(W59:Z59) -> 53707.32 | AB59: 50137.013 | AC59: =R59-AA59 -> -7031.32 | AD59: =(51671-48025)+(53237-49373) -> 7510 | AE59: =24 -> 24 | AF59: =AD59*AE59 -> 180240 | AG59: =V59+AF59 -> 217948
A60: 11 | B60: OYINLOLA ISMAHEEL TAIWO | D60: DRIVER | E60: 4(9) | F60: =4395.43 -> 4395.43 | H60: =F60*300% -> 13186.29 | I60: =F60*7.5% -> 329.65725 | K60: =F60*50% -> 2197.715 | L60: =F60*350% -> 15384.005 | M60: =F60*100% -> 4395.43 | N60: =25000+7000 -> 32000 | O60: =F60*10% -> 439.543 | P60: 5000 | Q60: 0 | R60: =45328 -> 45328 | S60: =50104 -> 50104 | T60: =S60-R60 -> 4776 | U60: 1 | V60: =T60*U60 -> 4776 | W60: =20000 -> 20000 | X60: =11458.33+30000 -> 41458.33 | Z60: 236.04 | AA60: =SUM(W60:Z60) -> 61694.37 | AB60: 45633.7 | AC60: =R60-AA60 -> -16366.37
B61: TOTAL | D61: 50 | F61: =SUM(F50:F60) -> 81890.44 | G61: =SUM(G50:G60) -> 0 | H61: =SUM(H50:H60) -> 245671.32 | I61: =SUM(I50:I60) -> 6141.783 | J61: =SUM(J50:J60) -> 0 | K61: =SUM(K50:K60) -> 40945.22 | L61: =SUM(L50:L60) -> 286616.54 | M61: =SUM(M50:M60) -> 81890.44 | ... R61: =SUM(R50:R60) -> 813647 | V61: =SUM(V50:V60) -> 2806176 | W61: =SUM(W50:W60) -> 135000 | X61: =SUM(X50:X60) -> 388067.85 | Y61: =SUM(Y50:Y60) -> 625.78525 | Z61: =SUM(Z50:Z60) -> 6978.24 | AA61: =SUM(AA50:AA60) -> 530671.88 | AB61: 7555318 | AC61: =SUM(AC50:AC60) -> 282975.12
B62: GRAND TOTAL | F62: =F10+#REF!+F14+#REF!+F19+F24+F32+F36+F40+F47+F61 -> #REF! | G62: =G10+#REF!+G14+#REF!+G19+G24+G32+G36+G40+G47+G61 -> #REF! | H62: =H10+#REF!+H14+#REF!+H19+H24+H32+H36+H40+H47+H61 -> #REF! | I62: =I10+#REF!+I14+#REF!+I19+I24+I32+I36+I40+I47+I61 -> #REF! | J62: =J10+#REF!+J14+#REF!+J19+J24+J32+J36+J40+J47+J61 -> #REF! | K62: =K10+#REF!+K14+#REF!+K19+K24+K32+K36+K40+K47+K61 -> #REF! | L62: =L10+#REF!+L14+#REF!+L19+L24+L32+L36+L40+L47+L61 -> #REF! | M62: =M10+#REF!+M14+#REF!+M19+M24+M32+M36+M40+M47+M61 -> #REF! | ... Q62: =Q10+#REF!+Q14+#REF!+Q19+Q24+Q32+Q36+Q40+Q47+Q61 -> #REF! | V62: =V10+V14+V19+V24+V32+V36+V40+V47+V61 -> 9036660 | W62: =W10+#REF!+W14+#REF!+W19+W24+W32+W36+W40+W47+W61 -> #REF! | X62: =X10+#REF!+X14+#REF!+X19+X24+X32+X36+X40+X47+X61 -> #REF! | Y62: =Y10+#REF!+Y14+#REF!+Y19+Y24+Y32+Y36+Y40+Y47+Y61 -> #REF! | Z62: =Z10+#REF!+Z14+#REF!+Z19+Z24+Z32+Z36+Z40+Z47+Z61 -> #REF! | AA62: =AA10+#REF!+AA14+#REF!+AA19+AA24+AA32+AA36+AA40+AA47+AA61 -> #REF! | AB62: 31457194 | AC62: =AC10+#REF!+AC14+#REF!+AC19+AC24+AC32+AC36+AC40+AC47+AC61 -> #REF!
V63: =V62+AF59 -> 9216900 | AJ63: =AJ47+AJ40+AJ32+AJ24+AJ18+AJ14+AJ9+AJ50 -> 617099.1
D64: PREPARED BY: | K64: SIGNATURE | O64: DATE

Sheet Housing 2021
B3: STAFF PAYROLL FOR THE MONTH OF JANUARY, 2021
F4: ='[1]FEB 08'!E8/'[1]FEB 08'!M8 -> 0.22 | I4: ='[1]FEB 08'!F8/'[1]FEB 08'!Q8 -> 0.3
B5: STAFF NAME | S5: DEDUCTIONS | Y5: NET SALARY
D6: DESIGNATION | E6: SALARY | F6: BASIC | M6: MOTOR/ | N6: RESEARCH | O6: LEAVE | P6: OUT FIT | Q6: LEGISLATIVE | R6: GROSS | X6: DECEMBER,2020 | Y6: JANUARY,2021
E7: LEVEL | F7: SALARY | G7: SALARY/ALLOWCE AREARS | H7: RENT | I7: UTILITY | J7: DOMESTIC | K7: ENTERT. | L7: FURNIT. | M7: FUEL | N7: ALLOWANCE | O7: ALLCE | P7: ALLCE | Q7: DUTY ALLCE | R7: SALARY | S7: COOP SOCIETY | T7: COOP. LOAN RECOVERY | U7: NHF DEDUCTION | V7: PAYE | W7: TOTAL
A8: S/N | B8: DG OFFICE | F8: N | I8: N | R8: N | V8: N
A9: 1 | B9: PROF. ABUBAKAR O. SULAIMAN | D9: DIRECTOR GENERAL | E9: CONSOL | F9: 160488.75 | H9: 320977.5 | I9: 48146.63 | J9: 120366.57 | K9: 72219.94 | L9: 0 | M9: 120366.57 | N9: =200000 -> 200000 | O9: 16048.88 | P9: 25000 | Q9: 25235 | R9: =SUM(F9:Q9) -> 1108849.8 | V9: 113176.97 | W9: =S9+T9+U9+V9 -> 113176.97 | X9: 995672.87 | Y9: =2000000 -> 2000000
A10: 2 | B10: AKINSANMI ADEJOKE OLUKEMI | D10: AM INFORMATION | E10: 15(9) | F10: 33507.5 | H10: =F10*300% -> 100522.5 | I10: =F10*7.5% -> 2513.0625 | J10: 40122.19 | K10: =F10*50% -> 16753.75 | L10: =F10*350% -> 117276.25 | M10: =F10*100% -> 33507.5 | N10: =100000 -> 100000 | O10: =F10*10% -> 3350.75 | P10: 20000 | Q10: =100000 -> 100000 | R10: =SUM(F10:Q10) -> 567553.5 | S10: =0 -> 0 | T10: 0 | U10: ='[3]DECEMBER 2019'!$H$29 -> 837.6875 | V10: 15548.33 | W10: =S10+T10+U10+V10 -> 16386.018 | X10: 551167.48 | Y10: =700000 -> 700000
A11: 3 | B11: DR IKEME ARTHUR J.O | D11: SNR RESEARCH FELLOW | E11: 15(9) | F11: =33507.5 -> 33507.5 | H11: =F11*300% -> 100522.5 | I11: =F11*7.5% -> 2513.0625 | J11: 40122.19 | K11: =F11*50% -> 16753.75 | L11: =F11*350% -> 117276.25 | M11: =F11*100% -> 33507.5 | N11: =100000 -> 100000 | O11: =F11*10% -> 3350.75 | P11: 20000 | Q11: 0 | R11: =SUM(F11:Q11) -> 467553.5 | S11: 50000 | T11: =212642 -> 212642 | U11: ='[3]DECEMBER 2019'!$H$38 -> 837.6875 | V11: 15548.33 | W11: =SUM(S11:V11) -> 279028.02 | X11: 188525.48 | Y11: =700000 -> 700000
A12: 4 | B12: MOSHOOD M. OLALERE | D12: MANAGER ADMIN DG's OFFICE | E12: 15(9) | F12: =33507.5 -> 33507.5 | H12: =F12*300% -> 100522.5 | I12: =F12*7.5% -> 2513.0625 | J12: 40122.19 | K12: =F12*50% -> 16753.75 | L12: =F12*350% -> 117276.25 | M12: =F12*100% -> 33507.5 | N12: =100000 -> 100000 | O12: =F12*10% -> 3350.75 | P12: 20000 | Q12: 0 | R12: =SUM(F12:Q12) -> 467553.5 | S12: =5000 -> 5000 | T12: =179017.51 -> 179017.51 | U12: ='[3]DECEMBER 2019'!$H$35 -> 837.6875 | V12: 15548.33 | W12: =S12+T12+U12+V12 -> 200403.53 | X12: 267149.97 | Y12: =700000 -> 700000
A13: 5 | B13: SARAFADEEN ALABELEWE | D13: SA ADMINISTRATION | E13: 16(9) | F13: =42653.17 -> 42653.17 | H13: =F13*300% -> 127959.51 | I13: =F13*7.5% -> 3198.9877 | J13: 40122.19 | K13: =F13*50% -> 21326.585 | L13: =F13*350% -> 149286.1 | M13: =F13*100% -> 42653.17 | N13: =100000 -> 100000 | O13: =F13*10% -> 4265.317 | P13: 20000 | R13: =SUM(F13:Q13) -> 551465.02 | S13: =100000 -> 100000 | T13: =137500 -> 137500 | V13: 21618.09 | W13: =S13+T13+U13+V13 -> 259118.09 | X13: 278625.91 | Y13: =700000 -> 700000
A14: 6 | B14: DR ABDULSALAM NASIRU NAEEM | D14: SA ACADEMICS | E14: 16(7) | F14: =39662.25 -> 39662.25 | H14: =F14*300% -> 118986.75 | I14: =F14*7.5% -> 2974.6687 | J14: 40122.19 | K14: =F14*50% -> 19831.125 | L14: =F14*350% -> 138817.88 | M14: =F14*100% -> 39662.25 | N14: =150000 -> 150000 | O14: =F14*10% -> 3966.225 | P14: 20000 | Q14: =100000 -> 100000 | R14: =SUM(F14:Q14) -> 674023.33 | V14: =21618.09 -> 21618.09 | W14: =S14+T14+U14+V14 -> 21618.09 | X14: 590588.72 | Y14: =350000 -> 350000
A15: 7 | B15: TOKUNBO ALFRED ADULOJU | D15: AM LIAISON OFFICE | E15: 13(10) | F15: =25523.45 -> 25523.45 | H15: =F15*300% -> 76570.35 | I15: =F15*7.5% -> 1914.2587 | K15: =F15*50% -> 12761.725 | L15: =F15*350% -> 89332.075 | M15: =F15*100% -> 25523.45 | N15: =100000 -> 100000 | O15: =F15*10% -> 2552.345 | P15: 15000 | Q15: =100000 -> 100000 | R15: =SUM(F15:Q15) -> 449177.65 | S15: =100000 -> 100000 | T15: =0 -> 0 | U15: ='[3]DECEMBER 2019'!$H$22 -> 618.5315 | V15: 7709.76 | W15: =S15+T15+U15+V15 -> 108328.29 | X15: 333672.77 | Y15: =500000 -> 500000
A16: 8 | B16: HUSSEIN EGYE MUSA | D16: AM PROTOCOL | E16: 13(10) | F16: =25523.45 -> 25523.45 | H16: =F16*300% -> 76570.35 | I16: =F16*7.5% -> 1914.2587 | K16: =F16*50% -> 12761.725 | L16: =F16*350% -> 89332.075 | M16: =F16*100% -> 25523.45 | N16: =100000 -> 100000 | O16: =F16*10% -> 2552.345 | P16: 15000 | Q16: 50000 | R16: =SUM(F16:Q16) -> 399177.65 | S16: 10000 | T16: =103000 -> 103000 | U16: 0 | V16: 7709.76 | W16: =S16+T16+U16+V16 -> 120709.76 | X16: 271291.3 | Y16: =500000 -> 500000
A17: 9 | B17: DONALD E. MKPANAM | D17: AM ICT | E17: 13(11) | F17: 26339.3 | H17: =F17*300% -> 79017.9 | I17: =F17*7.5% -> 1975.4475 | K17: =F17*50% -> 13169.65 | L17: =F17*350% -> 92187.55 | M17: =F17*100% -> 26339.3 | N17: =100000 -> 100000 | O17: =F17*10% -> 2633.93 | P17: 15000 | Q17: 0 | R17: =SUM(F17:Q17) -> 356663.08 | U17: ='[3]DECEMBER 2019'!$H$31 -> 658.4825 | V17: 7709.76 | W17: =S17+T17+U17+V17 -> 8368.2425 | X17: 348294.83 | Y17: =500000 -> 500000
A18: 10 | B18: JOY HARUNA MAKERI | D18: AM TRAINING | E18: 13(10) | F18: =25523.45 -> 25523.45 | H18: =F18*300% -> 76570.35 | I18: =F18*7.5% -> 1914.2587 | K18: =F18*50% -> 12761.725 | L18: =F18*350% -> 89332.075 | M18: =F18*100% -> 25523.45 | N18: 150000 | O18: =F18*10% -> 2552.345 | P18: 15000 | Q18: =50000+100000 -> 150000 | R18: =SUM(F18:Q18) -> 549177.65 | V18: =7709.76 -> 7709.76 | W18: =SUM(S18:V18) -> 7709.76 | X18: 534291.3 | Y18: =500000 -> 500000
A19: 11 | B19: ALI ABDULLAHI | D19: AM ICT | E19: 13(11) | F19: =26339.3 -> 26339.3 | G19: 0 | H19: =F19*300% -> 79017.9 | I19: =F19*7.5% -> 1975.4475 | J19: 0 | K19: =F19*50% -> 13169.65 | L19: =F19*350% -> 92187.55 | M19: =F19*100% -> 26339.3 | N19: =100000 -> 100000 | O19: =F19*10% -> 2633.93 | P19: 15000 | Q19: =0 -> 0 | R19: =SUM(F19:Q19) -> 356663.08 | V19: =7709.76 -> 7709.76 | W19: =S19+T19+U19+V19 -> 7709.76 | X19: 348953.32 | Y19: =500000 -> 500000
A20: 12 | B20: ADUGBA RICHARD TERSEER | D20: INFORMATION OFFICER | E20: 10(9) | F20: =18281.64 -> 18281.64 | H20: =F20*300% -> 54844.92 | I20: =F20*7.5% -> 1371.123 | K20: =F20*50% -> 9140.82 | L20: =F20*350% -> 63985.74 | M20: =F20*100% -> 18281.64 | N20: =100000 -> 100000 | O20: =F20*10% -> 1828.164 | P20: 10000 | R20: =SUM(F20:Q20) -> 277734.05 | S20: =50000 -> 50000 | T20: =111833.33 -> 111833.33 | V20: 3369.51 | W20: =S20+T20+U20+V20 -> 165202.84 | X20: 107965.36 | Y20: =300000 -> 300000
A21: 13 | B21: CHRISTIAN MADUABUCHI ODO | D21: ICT OFFICER | E21: 10(11) | F21: =19276.95 -> 19276.95 | H21: =F21*300% -> 57830.85 | I21: =F21*7.5% -> 1445.7713 | K21: =F21*50% -> 9638.475 | L21: =F21*350% -> 67469.325 | M21: =F21*100% -> 19276.95 | N21: =100000 -> 100000 | O21: =F21*10% -> 1927.695 | P21: 10000 | R21: =SUM(F21:Q21) -> 286866.02 | S21: =20000 -> 20000 | T21: =82500 -> 82500 | U21: ='[3]DECEMBER 2019'!$H$51 -> 469.4825 | V21: 3369.51 | W21: =S21+T21+U21+V21 -> 106338.99 | X21: 175961.08 | Y21: =300000 -> 300000
A22: 14 | B22: VICTOR ASUKWO | D22: ICT OFFICER | E22: 8 (9) | F22: =13112.16 -> 13112.16 | H22: =F22*300% -> 39336.48 | I22: =F22*7.5% -> 983.412 | K22: =F22*50% -> 6556.08 | L22: =F22*350% -> 45892.56 | M22: =F22*100% -> 13112.16 | N22: =100000 -> 100000 | O22: =F22*10% -> 1311.216 | P22: 10000 | R22: =SUM(F22:Q22) -> 230304.07 | S22: =10000 -> 10000 | V22: 1484.37 | W22: =S22+T22+U22+V22 -> 11484.37 | X22: 215331.73 | Y22: =300000 -> 300000
A23: 15 | B23: SULEIMAN ABUBAKAR SODEEQ | D23: ADMIN. ASST. | E23: 8(7) | F23: =12351.94 -> 12351.94 | G23: =0 -> 0 | H23: =F23*300% -> 37055.82 | I23: =F23*7.5% -> 926.3955 | K23: =F23*50% -> 6175.97 | L23: =F23*350% -> 43231.79 | M23: =F23*100% -> 12351.94 | N23: =100000 -> 100000 | O23: =F23*10% -> 1235.194 | P23: 10000 | R23: =SUM(F23:Q23) -> 223329.05 | V23: =1235.19 -> 1235.19 | W23: =SUM(S23:V23) -> 1235.19 | X23: 222093.86 | Y23: =300000 -> 300000
A24: 16 | B24: YAKUB OLUWATOYIN USMAN | D24: ADMIN. ASST. | E24: 8(7) | F24: =12351.94 -> 12351.94 | G24: =0 -> 0 | H24: =F24*300% -> 37055.82 | I24: =F24*7.5% -> 926.3955 | K24: =F24*50% -> 6175.97 | L24: =F24*350% -> 43231.79 | M24: =F24*100% -> 12351.94 | N24: =100000 -> 100000 | O24: =F24*10% -> 1235.194 | P24: 10000 | R24: =SUM(F24:Q24) -> 223329.05 | S24: =10000 -> 10000 | V24: =1235.19 -> 1235.19 | W24: =SUM(S24:V24) -> 11235.19 | X24: 112093.86 | Y24: =300000 -> 300000
A25: 17 | B25: ANTHONY EDET | D25: ASST. MGR M&E | E25: 13(8) | F25: =23891.12 -> 23891.12 | H25: =F25*300% -> 71673.36 | I25: =F25*7.5% -> 1791.834 | J25: 0 | K25: =F25*50% -> 11945.56 | L25: =F25*350% -> 83618.92 | M25: =F25*100% -> 23891.12 | N25: =100000 -> 100000 | O25: =F25*10% -> 2389.112 | P25: 15000 | Q25: 0 | R25: =SUM(F25:Q25) -> 334201.03 | S25: 10000 | U25: ='[3]DECEMBER 2019'!$H$43 -> 494.3655 | V25: =7709.76 -> 7709.76 | W25: =SUM(S25:V25) -> 18204.126 | X25: 277568.26 | Y25: =500000 -> 500000
A26: 18 | B26: EGUATU U. ONYEJELEM | D26: OFFICER M&E | E26: 10(9) | F26: =18281.64 -> 18281.64 | H26: =F26*300% -> 54844.92 | I26: =F26*7.5% -> 1371.123 | K26: =F26*50% -> 9140.82 | L26: =F26*350% -> 63985.74 | M26: =F26*100% -> 18281.64 | N26: =100000 -> 100000 | O26: =F26*10% -> 1828.164 | P26: 10000 | R26: =SUM(F26:Q26) -> 277734.05 | S26: =20000 -> 20000 | T26: =87500+43750 -> 131250 | V26: 3369.51 | W26: =SUM(S26:V26) -> 154619.51 | X26: 118548.69 | Y26: =300000 -> 300000
A27: 19 | B27: ODEH SUZIE | D27: ADMIN. OFFICER, LIASION OFFICE | E27: 10(8) | F27: =17784 -> 17784 | G27: =0 -> 0 | H27: =F27*300% -> 53352 | I27: =F27*7.5% -> 1333.8 | K27: =F27*50% -> 8892 | L27: =F27*350% -> 62244 | M27: =F27*100% -> 17784 | N27: 100000 | O27: =F27*10% -> 1778.4 | P27: 10000 | R27: =SUM(F27:Q27) -> 273168.2 | S27: =30000+20000 -> 50000 | U27: =0 -> 0 | V27: 3369.51 | W27: =S27+T27+U27+V27 -> 53369.51 | X27: 255232.57 | Y27: =300000 -> 300000
B28: TOTAL | D28: 19 | F28: =SUM(F9:F27) -> 607907.01 | G28: =SUM(G9:G27) -> 0 | H28: =SUM(H9:H27) -> 1663232.3 | I28: =SUM(I9:I27) -> 81702.999 | J28: =SUM(J9:J27) -> 320977.52 | K28: =SUM(K9:K27) -> 295929.07 | L28: =SUM(L9:L27) -> 1565963.9 | M28: =SUM(M9:M27) -> 567784.83 | ... W28: =SUM(W9:W27) -> 1664246.3 | X28: 6193029.4 | Y28: =SUM(Y9:Y27) -> 10250000
B30: INTERNAL AUDIT
A31: 1 | B31: NWOSU MATHEW EZE | D31: Ag. DIRECTOR INT. AUDIT | E31: 17(8) | F31: =79039.64 -> 79039.64 | H31: =F31*300% -> 237118.92 | I31: =F31*7.5% -> 5927.973 | J31: =80244.38 -> 80244.38 | K31: =F31*50% -> 39519.82 | L31: =F31*350% -> 276638.74 | M31: =F31*100% -> 79039.64 | N31: =100000 -> 100000 | O31: =F31*10% -> 7903.964 | P31: 20000 | Q31: 0 | R31: =SUM(F31:Q31) -> 925433.08 | S31: =100000 -> 100000 | T31: =287500 -> 287500 | U31: ='[3]DECEMBER 2019'!$H$26 -> 1028.9423 | V31: =52776.63 -> 52776.63 | W31: =S31+T31+U31+V31 -> 441305.57 | X31: 459351.89 | Y31: =500000 -> 500000
A32: 2 | B32: BASHIRU ABBA WALI | D32: OFF. INT. AUDIT | E32: 10(10) | F32: =18779.3 -> 18779.3 | H32: =F32*300% -> 56337.9 | I32: =F32*7.5% -> 1408.4475 | J32: 0 | K32: =F32*50% -> 9389.65 | L32: =F32*350% -> 65727.55 | M32: =F32*100% -> 18779.3 | N32: =100000 -> 100000 | O32: =F32*10% -> 1877.93 | P32: 10000 | Q32: 0 | R32: =0 -> 0 | S32: =0 -> 0 | T32: =0 -> 0 | V32: =0 -> 0 | W32: =S32+T32+U32+V32 -> 0 | X32: 278930.57 | Y32: =R32-W32 -> 0
C33: TOTAL | D33: 2 | F33: =SUM(F31:F32) -> 97818.94 | G33: =SUM(G31:G32) -> 0 | H33: =SUM(H31:H32) -> 293456.82 | I33: =SUM(I31:I32) -> 7336.4205 | J33: =SUM(J31:J32) -> 80244.38 | K33: =SUM(K31:K32) -> 48909.47 | L33: =SUM(L31:L32) -> 342366.29 | M33: =SUM(M31:M32) -> 97818.94 | ... W33: =SUM(W31:W32) -> 441305.57 | X33: 738282.45 | Y33: =SUM(Y31:Y32) -> 500000
B35: LEG. SUPPORT SEVICES
A36: 1 | B36: PROF. EDOBA BRIGHT OMOREGBE | D36: AG. DLSS | E36: 17(9) | F36: =81740.02 -> 81740.02 | H36: =F36*300% -> 245220.06 | I36: =F36*7.5% -> 6130.5015 | J36: 80244.38 | K36: =F36*50% -> 40870.01 | L36: =F36*350% -> 286090.07 | M36: =F36*100% -> 81740.02 | N36: =150000 -> 150000 | O36: =F36*10% -> 8174.002 | P36: 20000 | R36: =SUM(F36:Q36) -> 1000209.1 | S36: =100000+2000 -> 102000 | V36: =52776.63 -> 52776.63 | W36: =V36+S36+T36+U36 -> 154776.63 | X36: 922656.45 | Y36: =1000000 -> 1000000
A37: 2 | B37: DR CLINTON JAJA | D37: SENIOR RESEARCH FELLOW | E37: 15(9) | F37: =33507.5 -> 33507.5 | H37: =F37*300% -> 100522.5 | I37: =F37*7.5% -> 2513.0625 | J37: 40122.19 | K37: =F37*50% -> 16753.75 | L37: =F37*350% -> 117276.25 | M37: =F37*100% -> 33507.5 | N37: =150000 -> 150000 | O37: =F37*10% -> 3350.75 | P37: 20000 | Q37: 0 | R37: =SUM(F37:Q37) -> 517553.5 | S37: 50000 | T37: =240909.11 -> 240909.11 | V37: 15548.33 | W37: =SUM(S37:V37) -> 306457.44 | X37: 211096.06 | Y37: 700000
A38: 3 | B38: BETHEL UZOMA IHUGBA | D38: SNR RESEARCH FELLOW | E38: 15(9) | F38: =33507.5 -> 33507.5 | H38: =F38*300% -> 100522.5 | I38: =F38*7.5% -> 2513.0625 | J38: 40122.19 | K38: =F38*50% -> 16753.75 | L38: =F38*350% -> 117276.25 | M38: =F38*100% -> 33507.5 | N38: =150000 -> 150000 | O38: =F38*10% -> 3350.75 | P38: 20000 | R38: =SUM(F38:Q38) -> 517553.5 | S38: =30000+13000 -> 43000 | T38: =246905.96 -> 246905.96 | V38: 15548.33 | W38: =V38+S38+T38+U38 -> 305454.29 | X38: 200682.76 | Y38: =700000 -> 700000
A39: 4 | B39: OGUCHE SAMUEL | D39: RESEARCH FELLOW I | E39: 14(11) | F39: 28489.81 | H39: =F39*300% -> 85469.43 | I39: =F39*7.5% -> 2136.7357 | K39: =F39*50% -> 14244.905 | L39: =F39*350% -> 99714.335 | M39: =F39*100% -> 28489.81 | N39: =150000 -> 150000 | O39: =F39*10% -> 2848.981 | P39: 20000 | R39: =SUM(F39:Q39) -> 431394.01 | S39: =30000 -> 30000 | T39: =179165.6+26250 -> 205415.6 | V39: 7709.76 | W39: =SUM(S39:V39) -> 243125.36 | X39: 188268.65 | Y39: =500000 -> 500000
A40: 5 | B40: IBRAHIM USMAN | D40: RESEARCH FELLOW I | E40: 14(11) | F40: =28489.81 -> 28489.81 | H40: =F40*300% -> 85469.43 | I40: =F40*7.5% -> 2136.7357 | J40: 0 | K40: =F40*50% -> 14244.905 | L40: =F40*350% -> 99714.335 | M40: =F40*100% -> 28489.81 | N40: =150000 -> 150000 | O40: =F40*10% -> 2848.981 | P40: 20000 | Q40: 0 | R40: =SUM(F40:Q40) -> 431394.01 | U40: ='[3]DECEMBER 2019'!$H$27 -> 690.28075 | V40: 7709.76 | W40: =V40+S40+T40+U40 -> 8400.0408 | X40: 414932.99 | Y40: =500000 -> 500000
A41: 6 | B41: DR MOHAMMED O. AMALI | D41: RESEARCH FELLOW I | E41: 14(9) | F41: =27611.23 -> 27611.23 | H41: =F41*300% -> 82833.69 | I41: =F41*7.5% -> 2070.8422 | K41: =F41*50% -> 13805.615 | L41: =F41*350% -> 96639.305 | M41: =F41*100% -> 27611.23 | N41: =150000 -> 150000 | O41: =F41*10% -> 2761.123 | P41: 15000 | R41: =SUM(F41:Q41) -> 418333.04 | S41: =15000 -> 15000 | T41: =106666.67 -> 106666.67 | V41: 7709.76 | W41: =V41+S41+T41+U41 -> 129376.43 | X41: 262624.63 | Y41: =500000 -> 500000
A42: 7 | B42: YAHAYA SHAMSU | D42: AM LEGAL | E42: 13(11) | F42: =26339.3 -> 26339.3 | H42: =F42*300% -> 79017.9 | I42: =F42*7.5% -> 1975.4475 | K42: =F42*50% -> 13169.65 | L42: =F42*350% -> 92187.55 | M42: =F42*100% -> 26339.3 | N42: =150000 -> 150000 | O42: =F42*10% -> 2633.93 | P42: 15000 | R42: =SUM(F42:Q42) -> 406663.08 | U42: 0 | V42: 7709.76 | W42: =V42+T42+S42+U42 -> 7709.76 | X42: 398953.32 | Y42: =500000 -> 500000
A43: 8 | B43: OFORDEME ADAOBI JULIA | D43: RESEARCH FELLOW 11 | E43: 13(9) | F43: =24741.26 -> 24741.26 | H43: =F43*300% -> 74223.78 | I43: =F43*7.5% -> 1855.5945 | J43: 0 | K43: =F43*50% -> 12370.63 | L43: =F43*350% -> 86594.41 | M43: =F43*100% -> 24741.26 | N43: =150000 -> 150000 | O43: =F43*10% -> 2474.126 | P43: 15000 | Q43: 0 | R43: =SUM(F43:Q43) -> 392001.06 | V43: 7709.76 | W43: =V43+S43+T43+U43 -> 7709.76 | X43: 376493.27 | Y43: =500000 -> 500000
A44: 9 | B44: IKPEAZU CHINEDU ANITA | D44: RESEARCH FELLOW II | E44: 13(10) | F44: =25523.45 -> 25523.45 | H44: =F44*300% -> 76570.35 | I44: =F44*7.5% -> 1914.2587 | J44: 0 | K44: =F44*50% -> 12761.725 | L44: =F44*350% -> 89332.075 | M44: =F44*100% -> 25523.45 | N44: =150000 -> 150000 | O44: =F44*10% -> 2552.345 | P44: 15000 | Q44: 0 | R44: =SUM(F44:Q44) -> 399177.65 | V44: 7709.76 | W44: =V44+S44+T44+U44 -> 7709.76 | X44: 384291.3 | Y44: =500000 -> 500000
A45: 10 | B45: ONYEAKU CHUKWUKA EDMOND | D45: RESEARCH FELLOW II | E45: 13(10) | F45: =25523.45 -> 25523.45 | H45: =F45*300% -> 76570.35 | I45: =F45*7.5% -> 1914.2587 | J45: =J19 -> 0 | K45: =F45*50% -> 12761.725 | L45: =F45*350% -> 89332.075 | M45: =F45*100% -> 25523.45 | N45: =150000 -> 150000 | O45: =F45*10% -> 2552.345 | P45: 15000 | Q45: 0 | R45: =SUM(F45:Q45) -> 399177.65 | S45: =30000 -> 30000 | T45: =182107.04 -> 182107.04 | U45: ='[3]DECEMBER 2019'!$H$46 -> 618.5315 | V45: 7709.76 | W45: =V45+S45+T45+U45 -> 220435.33 | X45: 71565.729 | Y45: =500000 -> 500000
A46: 11 | B46: DORIS DAKDA AARON | D46: RESEARCH FELLOW II | E46: 13(8) | F46: =23891.12 -> 23891.12 | H46: =F46*300% -> 71673.36 | I46: =F46*7.5% -> 1791.834 | K46: =F46*50% -> 11945.56 | L46: =F46*350% -> 83618.92 | M46: =F46*100% -> 23891.12 | N46: =150000 -> 150000 | O46: =F46*10% -> 2389.112 | P46: 15000 | R46: =SUM(F46:Q46) -> 384201.03 | S46: =50000+10000 -> 60000 | U46: ='[3]DECEMBER 2019'!$H$52 -> 457.041 | V46: =7709.76 -> 7709.76 | W46: =V46+S46+T46+U46 -> 68166.801 | X46: 263907.5 | Y46: =500000 -> 500000
B47: TOTAL | D47: 11 | F47: =SUM(F36:F46) -> 359364.45 | H47: =SUM(H36:H46) -> 1078093.4 | I47: =SUM(I36:I46) -> 26952.334 | J47: =SUM(J36:J46) -> 160488.76 | K47: =SUM(K36:K46) -> 179682.23 | L47: =SUM(L36:L46) -> 1257775.6 | M47: =SUM(M36:M46) -> 359364.45 | N47: =SUM(N36:N46) -> 1650000 | O47: =SUM(O36:O46) -> 35936.445 | ... W47: =SUM(W36:W46) -> 1459321.6 | X47: 3695472.7 | Y47: =SUM(Y36:Y46) -> 6400000
B49: LEGAL SERVICES
A50: 1 | B50: DR SHUIBU DANWANKA | D50: DIRECTOR LEGAL SERVICES | E50: 17(9) | F50: =81740.02 -> 81740.02 | H50: =F50*300% -> 245220.06 | I50: =F50*7.5% -> 6130.5015 | J50: 80244.38 | K50: =F50*50% -> 40870.01 | L50: =F50*350% -> 286090.07 | M50: =F50*100% -> 81740.02 | N50: =150000 -> 150000 | O50: =F50*10% -> 8174.002 | P50: 20000 | Q50: 0 | R50: =SUM(F50:Q50) -> 1000209.1 | U50: 0 | V50: 52776.63 | W50: =S50+T50+U50+V50 -> 52776.63 | X50: 947432.43 | Y50: =500000 -> 500000
B51: TOTAL | D51: 2 | F51: =SUM(F50:F50) -> 81740.02 | G51: =SUM(G50:G50) -> 0 | H51: =SUM(H50:H50) -> 245220.06 | I51: =SUM(I50:I50) -> 6130.5015 | J51: =SUM(J50:J50) -> 80244.38 | K51: =SUM(K50:K50) -> 40870.01 | L51: =SUM(L50:L50) -> 286090.07 | M51: =SUM(M50:M50) -> 81740.02 | ... R51: =SUM(R50:R50) -> 1000209.1 | U51: =SUM(U50:U50) -> 0 | V51: =SUM(V50:V50) -> 52776.63 | W51: =SUM(W50:W50) -> 52776.63 | X51: 947432.43 | Y51: =SUM(Y50) -> 500000
B53: DEMOCRATIC STUDIES
A54: 1 | B54: DR. ADEWALE ADEREMI | D54: DIRECTOR, DEMOCRATIC STUDIES | E54: 17(8) | F54: =79039.64 -> 79039.64 | G54: =0 -> 0 | H54: =F54*300% -> 237118.92 | I54: =F54*7.5% -> 5927.973 | J54: =80244.38 -> 80244.38 | K54: =F54*50% -> 39519.82 | L54: =F54*350% -> 276638.74 | M54: =F54*100% -> 79039.64 | N54: =150000 -> 150000 | O54: =F54*10% -> 7903.964 | P54: 20000 | Q54: 0 | R54: =SUM(F54:Q54) -> 975433.08 | S54: =100000 -> 100000 | V54: =52776.63 -> 52776.63 | W54: =S54+T54+U54+V54 -> 152776.63 | X54: 797880.83 | Y54: =500000 -> 500000
A55: 2 | B55: NGARA CHRISTOPHER OCHANJA | D55: RESEARCH FELLOW 1 | E55: 14(9) | F55: =27611.23 -> 27611.23 | H55: =F55*300% -> 82833.69 | I55: =F55*7.5% -> 2070.8422 | K55: =F55*50% -> 13805.615 | L55: =F55*350% -> 96639.305 | M55: =F55*100% -> 27611.23 | N55: =150000 -> 150000 | O55: =F55*10% -> 2761.123 | P55: 15000 | Q55: 0 | R55: =SUM(F55:Q55) -> 418333.04 | S55: =20000 -> 20000 | T55: =163103.59 -> 163103.59 | U55: ='[3]DECEMBER 2019'!$H$50 -> 638.08625 | V55: =7709.76 -> 7709.76 | W55: =S55+T55+U55+V55 -> 191451.44 | X55: 207726.22 | Y55: =500000 -> 500000
A56: 3 | B56: EJALONIBU GANIYU LAYI | D56: RESEARCH FELLOW 11 | E56: 13(8) | F56: =23891.12 -> 23891.12 | G56: =0 -> 0 | H56: =F56*300% -> 71673.36 | I56: =F56*7.5% -> 1791.834 | K56: =F56*50% -> 11945.56 | L56: =F56*350% -> 83618.92 | M56: =F56*100% -> 23891.12 | N56: =150000 -> 150000 | O56: =F56*10% -> 2389.112 | P56: 15000 | R56: =SUM(F56:Q56) -> 384201.03 | S56: =110000 -> 110000 | V56: =7709.76 -> 7709.76 | W56: =S56+T56+U56+V56 -> 117709.76 | X56: 214364.54 | Y56: =500000 -> 500000
A57: 4 | B57: OSOLAFIA MUHAMMAD EGYE | D57: PERSONNEL OFFICER | E57: 10(11) | F57: =19276.95 -> 19276.95 | H57: =F57*300% -> 57830.85 | I57: =F57*7.5% -> 1445.7713 | J57: 0 | K57: =F57*50% -> 9638.475 | L57: =F57*350% -> 67469.325 | M57: =F57*100% -> 19276.95 | N57: =150000 -> 150000 | O57: =F57*10% -> 1927.695 | P57: 10000 | Q57: 0 | R57: =SUM(F57:Q57) -> 336866.02 | S57: =20000 -> 20000 | T57: =100000 -> 100000 | U57: ='[3]DECEMBER 2019'!$H$45 -> 469.4825 | V57: =3369.51 -> 3369.51 | W57: =S57+T57+U57+V57 -> 123838.99 | X57: 108461.08 | Y57: =300000 -> 300000
B58: TOTAL | D58: 4 | F58: =SUM(F54:F57) -> 149818.94 | G58: =SUM(G54:G57) -> 0 | H58: =SUM(H54:H57) -> 449456.82 | I58: =SUM(I54:I57) -> 11236.42 | J58: =SUM(J54:J57) -> 80244.38 | K58: =SUM(K54:K57) -> 74909.47 | L58: =SUM(L54:L57) -> 524366.29 | M58: =SUM(M54:M57) -> 149818.94 | ... V58: =SUM(V54:V57) -> 71565.66 | W58: =SUM(R58:V58) -> 2700610 | X58: 1328432.7 | Y58: =SUM(Y54:Y57) -> 1800000
B60: POST GRADUATE SCHOOL
A61: 1 | B61: DR ASIMIYU G. ABIOLA | D61: DIRECTOR POST GRADUATE | E61: 17(9) | F61: =81740.02 -> 81740.02 | H61: =F61*300% -> 245220.06 | I61: =F61*7.5% -> 6130.5015 | J61: 80244.38 | K61: =F61*50% -> 40870.01 | L61: =F61*350% -> 286090.07 | M61: =F61*100% -> 81740.02 | N61: =150000 -> 150000 | O61: =F61*10% -> 8174.002 | P61: 20000 | Q61: 0 | R61: =SUM(F61:Q61) -> 1000209.1 | S61: 150000 | T61: =451815.1 -> 451815.1 | U61: 0 | V61: 52776.63 | W61: =SUM(S61:V61) -> 654591.73 | X61: 345617.33 | Y61: =1000000 -> 1000000
A62: 2 | B62: DR AUGUSTINE C. OSIGWE | D62: SNR RESEARCH FELLOW | E62: 15(8) | F62: =32263.2 -> 32263.2 | H62: =F62*300% -> 96789.6 | I62: =F62*7.5% -> 2419.74 | J62: =40122.19 -> 40122.19 | K62: =F62*50% -> 16131.6 | L62: =F62*350% -> 112921.2 | M62: =F62*100% -> 32263.2 | N62: =150000 -> 150000 | O62: =F62*10% -> 3226.32 | P62: 20000 | R62: =SUM(F62:Q62) -> 506137.05 | S62: =20000 -> 20000 | T62: =150000 -> 150000 | U62: ='[3]DECEMBER 2019'!$H$42 -> 690.28075 | V62: 15548.33 | W62: =SUM(S62:V62) -> 186238.61 | X62: 244932.99 | Y62: =700000 -> 700000
A63: 3 | B63: HAUWA PATE SADIQ | D63: PROGRAMME OFFICER | E63: 10(9) | F63: =18281.64 -> 18281.64 | H63: =F63*300% -> 54844.92 | I63: =F63*7.5% -> 1371.123 | K63: =F63*50% -> 9140.82 | L63: =F63*350% -> 63985.74 | M63: =F63*100% -> 18281.64 | N63: =150000 -> 150000 | O63: =F63*10% -> 1828.164 | P63: 10000 | R63: =SUM(F63:Q63) -> 327734.05 | S63: =50000+20000 -> 70000 | T63: =31500 -> 31500 | V63: 3369.51 | W63: =SUM(S63:V63) -> 104869.51 | X63: 238298.69 | Y63: =300000 -> 300000
A64: 4 | B64: UZODINMA EMMANUEL EZENWA | D64: RESEARCH FELLOW II | E64: 13(8) | F64: =23891.12 -> 23891.12 | H64: =F64*300% -> 71673.36 | I64: =F64*7.5% -> 1791.834 | J64: 0 | K64: =F64*50% -> 11945.56 | L64: =F64*350% -> 83618.92 | M64: =F64*100% -> 23891.12 | N64: =150000 -> 150000 | O64: =F64*10% -> 2389.112 | P64: 15000 | Q64: 0 | R64: =SUM(F64:Q64) -> 384201.03 | S64: =0 -> 0 | T64: =0 -> 0 | U64: ='[3]DECEMBER 2019'!$H$48 -> 469.4825 | V64: =7709.76 -> 7709.76 | W64: =S64+T64+U64+V64 -> 8179.2425 | X64: 328461.08 | Y64: =500000 -> 500000
B65: TOTAL | D65: 4 | F65: =SUM(F61:F64) -> 156175.98 | H65: =SUM(H61:H64) -> 468527.94 | I65: =SUM(I61:I64) -> 11713.198 | J65: =SUM(J61:J64) -> 120366.57 | K65: =SUM(K61:K64) -> 78087.99 | L65: =SUM(L61:L64) -> 546615.93 | M65: =SUM(M61:M64) -> 156175.98 | N65: =SUM(N61:N64) -> 600000 | O65: =SUM(O61:O64) -> 15617.598 | ... W65: =SUM(W61:W64) -> 953879.09 | X65: 1157310.1 | Y65: =SUM(Y61:Y64) -> 2500000
B67: ECONOMIC AND SOCIAL DEV.
A68: 1 | B68: DR ADEYEMI AKEEB FAJINGBESI | D68: DIR. ECO. & SOCIAL DEV | E68: 17(9) | F68: 81740.02 | H68: =F68*300% -> 245220.06 | I68: =F68*7.5% -> 6130.5015 | J68: 80244.38 | K68: =F68*50% -> 40870.01 | L68: =F68*350% -> 286090.07 | M68: =F68*100% -> 81740.02 | N68: =150000 -> 150000 | O68: =F68*10% -> 8174.002 | P68: 20000 | Q68: 0 | R68: =SUM(F68:Q68) -> 1000209.1 | S68: 200000 | T68: =59722.22 -> 59722.22 | U68: ='[3]DECEMBER 2019'!$H$39 -> 2043.5005 | V68: 52776.63 | W68: =SUM(S68:V68) -> 314542.35 | X68: 685666.71 | Y68: =1000000 -> 1000000
A69: 2 | B69: DR ASEMOTA OMOROGBE JOSEPH | D69: SENIOR RESEARCH FELLOW | E69: 15(9) | F69: =33507.5 -> 33507.5 | H69: =F69*300% -> 100522.5 | I69: =F69*7.5% -> 2513.0625 | J69: 40122.19 | K69: =F69*50% -> 16753.75 | L69: =F69*350% -> 117276.25 | M69: =F69*100% -> 33507.5 | N69: =150000 -> 150000 | O69: =F69*10% -> 3350.75 | P69: 20000 | R69: =SUM(F69:Q69) -> 517553.5 | V69: 15548.33 | W69: =SUM(S69:V69) -> 15548.33 | X69: 502005.17 | Y69: =700000 -> 700000
A70: 3 | B70: TERFA WILLIAMS ABRAHAM | D70: SNR RESEARCH FELLOW | E70: 15(8) | F70: =32263.2 -> 32263.2 | H70: =F70*300% -> 96789.6 | I70: =F70*7.5% -> 2419.74 | J70: =40122.19 -> 40122.19 | K70: =F70*50% -> 16131.6 | L70: =F70*350% -> 112921.2 | M70: =F70*100% -> 32263.2 | N70: =150000 -> 150000 | O70: =F70*10% -> 3226.32 | P70: 20000 | R70: =SUM(F70:Q70) -> 506137.05 | V70: =15548.33 -> 15548.33 | W70: =SUM(S70:V70) -> 15548.33 | X70: 423684.25 | Y70: =700000 -> 700000
A71: 4 | B71: JUMARE FADILA | D71: RESEARCH FELLOW I | E71: 14(9) | F71: =27611.23 -> 27611.23 | H71: =F71*300% -> 82833.69 | I71: =F71*7.5% -> 2070.8422 | J71: 0 | K71: =F71*50% -> 13805.615 | L71: =F71*350% -> 96639.305 | M71: =F71*100% -> 27611.23 | N71: =150000 -> 150000 | O71: =F71*10% -> 2761.123 | P71: 15000 | Q71: 0 | R71: =SUM(F71:Q71) -> 418333.04 | S71: 5000 | V71: =7709.76 -> 7709.76 | W71: =SUM(S71:V71) -> 12709.76 | X71: 386467.89 | Y71: =500000 -> 500000
A72: 5 | B72: OMOJU OLUWASOLA EMMANUEL | D72: RESEARCH FELLOW I | E72: 14(9) | F72: =27611.23 -> 27611.23 | H72: =F72*300% -> 82833.69 | I72: =F72*7.5% -> 2070.8422 | K72: =F72*50% -> 13805.615 | L72: =F72*350% -> 96639.305 | M72: =F72*100% -> 27611.23 | N72: =150000 -> 150000 | O72: =F72*10% -> 2761.123 | P72: 15000 | R72: =SUM(F72:Q72) -> 418333.04 | S72: =50000 -> 50000 | T72: =87500 -> 87500 | V72: =7709.76 -> 7709.76 | W72: =SUM(S72:V72) -> 145209.76 | X72: 246791.3 | Y72: =500000 -> 500000
A73: 6 | B73: UDEFUNA NNADOZIE PATRICK | D73: RESEARCH OFFICER | E73: 10(13) | F73: =19774.62 -> 19774.62 | H73: =F73*300% -> 59323.86 | I73: =F73*7.5% -> 1483.0965 | J73: 0 | K73: =F73*50% -> 9887.31 | L73: =F73*350% -> 69211.17 | M73: =F73*100% -> 19774.62 | N73: =150000 -> 150000 | O73: =F73*10% -> 1977.462 | P73: 10000 | Q73: 0 | R73: =SUM(F73:Q73) -> 341432.14 | S73: =10000 -> 10000 | T73: =131771.66 -> 131771.66 | V73: 3369.51 | W73: =SUM(S73:V73) -> 145141.17 | X73: 76290.969 | Y73: =300000 -> 300000
A74: 7 | B74: EMILY EDOISA IKHIDE | D74: RESEARCH FELLOW II | E74: 13(10) | F74: =25523.45 -> 25523.45 | H74: =F74*300% -> 76570.35 | I74: =F74*7.5% -> 1914.2587 | K74: =F74*50% -> 12761.725 | L74: =F74*350% -> 89332.075 | M74: =F74*100% -> 25523.45 | N74: =150000 -> 150000 | O74: =F74*10% -> 2552.345 | P74: 15000 | R74: =SUM(F74:Q74) -> 399177.65 | S74: =50000 -> 50000 | T74: =45833.33 -> 45833.33 | V74: 7709.76 | W74: =SUM(S74:V74) -> 103543.09 | X74: 288457.97 | Y74: =500000 -> 500000
A75: 8 | B75: ONYIMADU C. ONYEBUCHI | D75: RESEARCH FELLOW I | E75: 14(9) | F75: =27611.23 -> 27611.23 | H75: =F75*300% -> 82833.69 | I75: =F75*7.5% -> 2070.8422 | K75: =F75*50% -> 13805.615 | L75: =F75*350% -> 96639.305 | M75: =F75*100% -> 27611.23 | N75: =150000 -> 150000 | O75: =F75*10% -> 2761.123 | P75: 15000 | R75: =SUM(F75:Q75) -> 418333.04 | S75: =50000 -> 50000 | U75: ='[3]DECEMBER 2019'!$H$54 -> 618.5315 | V75: 7709.76 | W75: =SUM(S75:V75) -> 58328.291 | X75: 333672.77 | Y75: =500000 -> 500000
A76: 9 | B76: IBE EZECHI CYRIACUS | D76: RESEARCH FELLOW II | E76: 13(8) | F76: =23891.12 -> 23891.12 | H76: =F76*300% -> 71673.36 | I76: =F76*7.5% -> 1791.834 | J76: 0 | K76: =F76*50% -> 11945.56 | L76: =F76*350% -> 83618.92 | M76: =F76*100% -> 23891.12 | N76: =150000 -> 150000 | O76: =F76*10% -> 2389.112 | P76: 15000 | Q76: 0 | R76: =SUM(F76:Q76) -> 384201.03 | S76: =50000 -> 50000 | V76: =7709.76 -> 7709.76 | W76: =SUM(S76:V76) -> 57709.76 | X76: 299364.54 | Y76: =500000 -> 500000
B77: TOTAL | D77: 9 | F77: =SUM(F68:F76) -> 299533.6 | H77: =SUM(H68:H76) -> 898600.8 | I77: =SUM(I68:I76) -> 22465.02 | J77: =SUM(J68:J76) -> 160488.76 | K77: =SUM(K68:K76) -> 149766.8 | L77: =SUM(L68:L76) -> 1048367.6 | M77: =SUM(M68:M76) -> 299533.6 | N77: =SUM(N68:N76) -> 1350000 | O77: =SUM(O68:O76) -> 29953.36 | ... V77: =SUM(V68:V76) -> 125791.6 | W77: =SUM(S77:V77) -> 868280.84 | X77: 3242401.6 | Y77: =SUM(Y68:Y76) -> 5200000
B79: TRAINING AND INTERNATIONAL COOP
A80: 1 | B80: DR JAKE DABANG DAN AZUMI | D80: DEPUTY DIRECTOR TRAINING | E80: 16(7) | F80: =39662.25 -> 39662.25 | H80: =F80*300% -> 118986.75 | I80: =F80*7.5% -> 2974.6687 | J80: 40122.19 | K80: =F80*50% -> 19831.125 | L80: =F80*350% -> 138817.88 | M80: =F80*100% -> 39662.25 | N80: 150000 | O80: =F80*10% -> 3966.225 | P80: 20000 | Q80: 150000 | R80: =SUM(F80:Q80) -> 724023.33 | U80: ='[3]DECEMBER 2019'!$H$30 -> 837.6875 | V80: 15548.33 | W80: =SUM(S80:V80) -> 16386.018 | X80: 651167.48 | Y80: =700000 -> 700000
A81: 2 | B81: DR FRANCIS NDUM OJIE | D81: ASST. MANAGER, TRAINING | E81: 14(7) | F81: =27611.23 -> 27611.23 | H81: =F81*300% -> 82833.69 | I81: =F81*7.5% -> 2070.8422 | K81: =F81*50% -> 13805.615 | L81: =F81*350% -> 96639.305 | M81: =F81*100% -> 27611.23 | N81: 100000 | O81: =F81*10% -> 2761.123 | P81: 15000 | R81: =SUM(F81:Q81) -> 368333.04 | V81: =7709.76 -> 7709.76 | W81: =SUM(S81:V81) -> 7709.76 | X81: 334291.3 | Y81: =500000 -> 500000
A82: 3 | B82: OKECHUKWU UCHENNA HULDA | D82: ADMIN OFFICER | E82: 10(9) | F82: =18281.64 -> 18281.64 | H82: =F82*300% -> 54844.92 | I82: =F82*7.5% -> 1371.123 | K82: =F82*50% -> 9140.82 | L82: =F82*350% -> 63985.74 | M82: =F82*100% -> 18281.64 | N82: =100000 -> 100000 | O82: =F82*10% -> 1828.164 | P82: 10000 | R82: =SUM(F82:Q82) -> 277734.05 | S82: =5000 -> 5000 | T82: =0 -> 0 | V82: 3369.51 | W82: =SUM(S82:V82) -> 8369.51 | X82: 264798.69 | Y82: =300000 -> 300000
A83: 4 | B83: HASSANA AHMED IBRAHIM | E83: 10(8) | F83: =17784 -> 17784 | G83: =0 -> 0 | H83: =F83*300% -> 53352 | I83: =F83*7.5% -> 1333.8 | K83: =F83*50% -> 8892 | L83: =F83*350% -> 62244 | M83: =F83*100% -> 17784 | N83: 100000 | O83: =F83*10% -> 1778.4 | P83: 10000 | R83: =SUM(F83:Q83) -> 273168.2 | S83: =30000 -> 30000 | U83: =444.6 -> 444.6 | V83: 3369.51 | W83: =SUM(S83:V83) -> 33814.11 | X83: 234787.97 | Y83: =300000 -> 300000
B84: TOTAL | D84: 4 | F84: =SUM(F80:F83) -> 103339.12 | G84: =SUM(G80:G83) -> 0 | H84: =SUM(H80:H83) -> 310017.36 | I84: =SUM(I80:I83) -> 7750.434 | J84: =SUM(J80:J83) -> 40122.19 | K84: =SUM(K80:K83) -> 51669.56 | L84: =SUM(L80:L83) -> 361686.92 | M84: =SUM(M80:M83) -> 103339.12 | ... V84: =SUM(V80:V83) -> 29997.11 | W84: =SUM(S84:V84) -> 66279.397 | X84: 1485045.4 | Y84: =SUM(Y80:Y83) -> 1800000
B86: LIBRARY AND DOCUMENTATION
A87: 1 | B87: DR MAIMUNA IZAH | D87: INSITUTE LIBRARIAN | E87: 17(8) | F87: =79039.64 -> 79039.64 | H87: =F87*300% -> 237118.92 | I87: =F87*7.5% -> 5927.973 | J87: 80244.38 | K87: =F87*50% -> 39519.82 | L87: =F87*350% -> 276638.74 | M87: =F87*100% -> 79039.64 | N87: 150000 | O87: =F87*10% -> 7903.964 | P87: 20000 | Q87: 0 | R87: =SUM(F87:Q87) -> 975433.08 | S87: =100000 -> 100000 | T87: 0 | U87: 0 | V87: =52776.63 -> 52776.63 | W87: =SUM(S87:V87) -> 152776.63 | X87: 797880.83 | Y87: =1000000 -> 1000000
A88: 2 | B88: CATHERINE E. IKOKOH | D88: SNR RESEARCH FELLOW DOCU | E88: 15(9) | F88: =33507.5 -> 33507.5 | H88: =F88*300% -> 100522.5 | I88: =F88*7.5% -> 2513.0625 | J88: 40122.19 | K88: =F88*50% -> 16753.75 | L88: =F88*350% -> 117276.25 | M88: =F88*100% -> 33507.5 | N88: 150000 | O88: =F88*10% -> 3350.75 | P88: 20000 | Q88: 0 | R88: =SUM(F88:Q88) -> 517553.5 | S88: 40000 | T88: =131250 -> 131250 | U88: ='[3]DECEMBER 2019'!$H$37 -> 837.6875 | V88: 15548.33 | W88: =SUM(S88:V88) -> 187636.02 | X88: 329917.48 | Y88: =700000 -> 700000
A89: 3 | B89: ALIYU SANNI ABUBAKAR | D89: RESEARCH FELLOW 11 DATA & DOCU. OFFICER | E89: 13(11) | F89: =26339.3 -> 26339.3 | H89: =F89*300% -> 79017.9 | I89: =F89*7.5% -> 1975.4475 | J89: 0 | K89: =F89*50% -> 13169.65 | L89: =F89*350% -> 92187.55 | M89: =F89*100% -> 26339.3 | N89: 150000 | O89: =F89*10% -> 2633.93 | P89: 15000 | Q89: 0 | R89: =SUM(F89:Q89) -> 406663.08 | S89: 30000 | T89: =0 -> 0 | U89: ='[3]DECEMBER 2019'!$H$40 -> 638.08625 | V89: =7709.76 -> 7709.76 | W89: =SUM(S89:V89) -> 38347.846 | X89: 360829.81 | Y89: 500000
A90: 4 | B90: CHINAKO N. ASOGWA | D90: LIBRARY OFFICER | E90: 13(9) | F90: =24741.26 -> 24741.26 | H90: =F90*300% -> 74223.78 | I90: =F90*7.5% -> 1855.5945 | J90: 0 | K90: =F90*50% -> 12370.63 | L90: =F90*350% -> 86594.41 | M90: =F90*100% -> 24741.26 | N90: 150000 | O90: =F90*10% -> 2474.126 | P90: 15000 | R90: =SUM(F90:Q90) -> 392001.06 | S90: =50000 -> 50000 | T90: =43083.33 -> 43083.33 | V90: =7709.76 -> 7709.76 | W90: =SUM(S90:V90) -> 100793.09 | X90: 254111.91 | Y90: =500000 -> 500000
B91: TOTAL | D91: 4 | F91: =SUM(F87:F90) -> 163627.7 | H91: =SUM(H87:H90) -> 490883.1 | I91: =SUM(I87:I90) -> 12272.077 | J91: =SUM(J87:J90) -> 120366.57 | K91: =SUM(K87:K90) -> 81813.85 | L91: =SUM(L87:L90) -> 572696.95 | M91: =SUM(M87:M90) -> 163627.7 | N91: =SUM(N87:N90) -> 600000 | O91: =SUM(O87:O90) -> 16362.77 | ... V91: =SUM(V87:V90) -> 83744.48 | W91: =SUM(S91:V91) -> 479553.58 | X91: 1742740 | Y91: =SUM(Y87:Y90) -> 2700000
B93: FINANCE & ACCOUNT
A94: 1 | B94: IBRAHIM M. MSHELIA | D94: DIR. FINANCE & ACCOUNTS | E94: 17(9) | F94: =81740.02 -> 81740.02 | H94: =F94*300% -> 245220.06 | I94: =F94*7.5% -> 6130.5015 | J94: =80244.38 -> 80244.38 | K94: =F94*50% -> 40870.01 | L94: =F94*350% -> 286090.07 | M94: =F94*100% -> 81740.02 | N94: =100000 -> 100000 | O94: =F94*10% -> 8174.002 | P94: 20000 | Q94: 100000 | R94: =SUM(F94:Q94) -> 1050209.1 | S94: =200000 -> 200000 | T94: =227777.78 -> 227777.78 | U94: ='[3]DECEMBER 2019'!$H$24 -> 1975.991 | V94: =52776.63 -> 52776.63 | W94: =SUM(S94:V94) -> 482530.4 | X94: 542902.68 | Y94: =1000000 -> 1000000
A95: 2 | B95: KABIR MUHAMMAD SULAIMAN | D95: DD FINANCE & ACCOUNTS | E95: 16(9) | F95: =42653.17 -> 42653.17 | H95: =F95*300% -> 127959.51 | I95: =F95*7.5% -> 3198.9877 | J95: 40122.19 | K95: =F95*50% -> 21326.585 | L95: =F95*350% -> 149286.1 | M95: =F95*100% -> 42653.17 | N95: =100000 -> 100000 | O95: =F95*10% -> 4265.317 | P95: 20000 | Q95: =100000 -> 100000 | R95: =SUM(F95:Q95) -> 651465.02 | S95: =100000 -> 100000 | T95: =0 -> 0 | V95: =21618.09 -> 21618.09 | W95: =SUM(S95:V95) -> 121618.09 | X95: 516125.91 | Y95: =700000 -> 700000
A96: 3 | B96: RAHILA NURUDEEN HABU | D96: MANAGER, ACCOUNTS | E96: 15(9) | F96: =33507.5 -> 33507.5 | H96: =F96*300% -> 100522.5 | I96: =F96*7.5% -> 2513.0625 | J96: 40122.19 | K96: =F96*50% -> 16753.75 | L96: =F96*350% -> 117276.25 | M96: =F96*100% -> 33507.5 | N96: =100000 -> 100000 | O96: =F96*10% -> 3350.75 | P96: 20000 | Q96: 0 | R96: =SUM(F96:Q96) -> 467553.5 | S96: =70000 -> 70000 | T96: =129166.67 -> 129166.67 | U96: ='[3]DECEMBER 2019'!$H$23 -> 806.58 | V96: 15548.33 | W96: =SUM(S96:V96) -> 215521.58 | X96: 240615.47 | Y96: =700000 -> 700000
A97: 4 | B97: ANDRAWUS MUSA | D97: MGR. STORE | E97: 15(8) | F97: =32263.2 -> 32263.2 | H97: =F97*300% -> 96789.6 | I97: =F97*7.5% -> 2419.74 | J97: =40122.19 -> 40122.19 | K97: =F97*50% -> 16131.6 | L97: =F97*350% -> 112921.2 | M97: =F97*100% -> 32263.2 | N97: =100000 -> 100000 | O97: =F97*10% -> 3226.32 | P97: 20000 | Q97: 0 | R97: =SUM(F97:Q97) -> 456137.05 | S97: =50000 -> 50000 | T97: =90000 -> 90000 | U97: ='[3]DECEMBER 2019'!$H$32 -> 638.08625 | V97: =15548.33 -> 15548.33 | W97: =SUM(S97:V97) -> 156186.42 | X97: 200829.81 | Y97: =700000 -> 700000
A98: 5 | B98: TONDO IORWUESE EDWARD | D98: MGR ACCOUNTS | E98: 15(8) | F98: =32263.2 -> 32263.2 | H98: =F98*300% -> 96789.6 | I98: =F98*7.5% -> 2419.74 | J98: =40122.19 -> 40122.19 | K98: =F98*50% -> 16131.6 | L98: =F98*350% -> 112921.2 | M98: =F98*100% -> 32263.2 | N98: =100000 -> 100000 | O98: =F98*10% -> 3226.32 | P98: 20000 | Q98: =100000 -> 100000 | R98: =SUM(F98:Q98) -> 556137.05 | S98: =100000 -> 100000 | T98: =100000 -> 100000 | U98: ='[3]DECEMBER 2019'!$H$25 -> 638.08625 | V98: =15548.33 -> 15548.33 | W98: =SUM(S98:V98) -> 216186.42 | X98: 310829.81 | Y98: =700000 -> 700000
