Workbook

Sheet April, 2022
B3: STAFF PAYROLL FOR THE MONTH OF APRIL 2022
E4: ='[1]FEB 08'!E8/'[1]FEB 08'!M8 -> 0.22 | H4: ='[1]FEB 08'!F8/'[1]FEB 08'!Q8 -> 0.3
B5: STAFF NAME | T5: DEDUCTIONS | Z5: NET SALARY
C6: DESIGNATION | D6: SALARY | E6: BASIC | L6: MOTOR/ | M6: RESEARCH | N6: HARDSHIP | O6: LEAVE | P6: OUT FIT | Q6: LEGISLATIVE | R6: GROSS | Y6: MARCH,2022 | Z6: APRIL,2022
D7: LEVEL | E7: SALARY | F7: SALARY/ALLOWCE AREARS | G7: RENT | H7: UTILITY | I7: DOMESTIC | J7: ENTERT. | K7: FURNIT. | L7: FUEL | M7: ALLOWANCE | N7: ALLOWANCE | O7: ALLCE | P7: ALLCE | Q7: DUTY ALLCE | R7: SALARY | S7: AUCTION | T7: COOP SOCIETY | U7: COOP. LOAN RECOVERY | V7: NHF DEDUCTION | W7: PAYE | X7: TOTAL
A8: S/N | B8: DG OFFICE | E8: N | H8: N | R8: N | W8: N
A9: 1 | B9: PROF. ABUBAKAR O. SULAIMAN | C9: DIRECTOR GENERAL | D9: CONSOL | E9: 160488.75 | G9: 320977.5 | H9: 48146.63 | I9: 120366.57 | J9: 72219.94 | K9: 0 | L9: 120366.57 | M9: =250000 -> 250000 | O9: 16048.88 | P9: 25000 | Q9: 25235 | R9: =Q9+P9+O9+N9+M9+L9+K9+J9+I9+H9+G9+F9+E9 -> 1158849.8 | W9: 113176.97 | X9: =W9+V9+U9+T9+S9 -> 113176.97 | Y9: 1045672.9 | Z9: =R9-X9 -> 1045672.9
A10: 2 | B10: DR ADEYEMI AKEEB FAJINGBESI | C10: DIR. SPECIAL DUTIES, DG OFFICE | D10: 17(9) | E10: 81740.02 | G10: =E10*300% -> 245220.06 | H10: =E10*7.5% -> 6130.5015 | I10: 80244.38 | J10: =E10*50% -> 40870.01 | K10: =E10*350% -> 286090.07 | L10: =E10*100% -> 81740.02 | M10: =200000 -> 200000 | O10: =E10*10% -> 8174.002 | P10: 20000 | Q10: 0 | R10: =Q10+P10+O10+N10+M10+L10+K10+J10+I10+H10+G10+F10+E10 -> 1050209.1 | T10: 200000 | U10: =59722.22 -> 59722.22 | V10: ='[2]April 2022'!$H$34 -> 2043.5005 | W10: 52776.63 | X10: =W10+V10+U10+T10+S10 -> 314542.35 | Y10: 735666.71 | Z10: =R10-X10 -> 735666.71
A11: 3 | B11: DR JAKE DABANG DAN AZUMI | C11: DEPUTY DIRECTOR TRAINING | D11: 16(8) | E11: 41157.69 | G11: =E11*300% -> 123473.07 | H11: =E11*7.5% -> 3086.8268 | I11: 40122.19 | J11: =E11*50% -> 20578.845 | K11: =E11*350% -> 144051.92 | L11: =E11*100% -> 41157.69 | M11: =180000 -> 180000 | O11: =E11*10% -> 4115.769 | P11: 20000 | Q11: 150000 | R11: =Q11+P11+O11+N11+M11+L11+K11+J11+I11+H11+G11+F11+E11 -> 767744 | V11: ='[2]April 2022'!$H$26 -> 1028.9423 | W11: =21618.09 -> 21618.09 | X11: =W11+V11+U11+T11+S11 -> 22647.032 | Y11: 745134.35 | Z11: =R11-X11 -> 745096.96
A12: 4 | B12: DR ABDULSALAM NASIRU NAEEM | C12: SA ACADEMICS | D12: 16(8) | E12: 41157.69 | G12: =E12*300% -> 123473.07 | H12: =E12*7.5% -> 3086.8268 | I12: 40122.19 | J12: =E12*50% -> 20578.845 | K12: =E12*350% -> 144051.92 | L12: =E12*100% -> 41157.69 | M12: =180000 -> 180000 | O12: =E12*10% -> 4115.769 | P12: 20000 | Q12: =100000 -> 100000 | R12: =Q12+P12+O12+N12+M12+L12+K12+J12+I12+H12+G12+F12+E12 -> 717744 | W12: =21618.09 -> 21618.09 | X12: =W12+V12+U12+T12+S12 -> 21618.09 | Y12: 696125.91 | Z12: =R12-X12 -> 696125.91
A13: 5 | B13: RAHEEM USMAN AYIGORO | C13: SA-INFRASTRUCTURE | D13: 16 (8) | E13: 41157.69 | G13: =E13*300% -> 123473.07 | H13: =E13*7.5% -> 3086.8268 | I13: 40122.19 | J13: =E13*50% -> 20578.845 | K13: =E13*350% -> 144051.92 | L13: =E13*100% -> 41157.69 | N13: =90000 -> 90000 | O13: =E13*10% -> 4115.769 | P13: 20000 | Q13: 0 | R13: =Q13+P13+O13+N13+M13+L13+K13+J13+I13+H13+G13+F13+E13 -> 527744 | T13: =100000+2000 -> 102000 | W13: =21618.09 -> 21618.09 | X13: =W13+V13+U13+T13+S13 -> 123618.09 | Y13: 506125.91 | Z13: =R13-X13 -> 404125.91
A14: 6 | B14: AKINSANMI ADEJOKE OLUKEMI | C14: HEAD INFORMATION/PROTOCOL | D14: 15(9) | E14: 33507.5 | G14: =E14*300% -> 100522.5 | H14: =E14*7.5% -> 2513.0625 | I14: 40122.19 | J14: =E14*50% -> 16753.75 | K14: =E14*350% -> 117276.25 | L14: =E14*100% -> 33507.5 | N14: =80000 -> 80000 | O14: =E14*10% -> 3350.75 | P14: 20000 | Q14: =100000 -> 100000 | R14: =Q14+P14+O14+N14+M14+L14+K14+J14+I14+H14+G14+F14+E14 -> 547553.5 | T14: =0 -> 0 | U14: 0 | V14: ='[2]April 2022'!$H$25 -> 837.6875 | W14: 15548.33 | X14: =W14+V14+U14+T14+S14 -> 16386.018 | Y14: 531167.48 | Z14: =R14-X14 -> 531167.48
A15: 7 | B15: DR IKEME ARTHUR J.O | C15: SNR RESEARCH FELLOW | D15: 15(9) | E15: 33507.5 | G15: =E15*300% -> 100522.5 | H15: =E15*7.5% -> 2513.0625 | I15: 40122.19 | J15: =E15*50% -> 16753.75 | K15: =E15*350% -> 117276.25 | L15: =E15*100% -> 33507.5 | N15: =80000 -> 80000 | O15: =E15*10% -> 3350.75 | P15: 20000 | Q15: 0 | R15: =Q15+P15+O15+N15+M15+L15+K15+J15+I15+H15+G15+F15+E15 -> 447553.5 | T15: =50000 -> 50000 | U15: =160416.67 -> 160416.67 | V15: ='[3]DECEMBER 2019'!$H$38 -> 837.6875 | W15: 15548.33 | X15: =W15+V15+U15+T15+S15 -> 226802.69 | Y15: 220750.82 | Z15: =R15-X15 -> 220750.82
A16: 8 | B16: MOSHOOD M. OLALERE | C16: MANAGER ADMIN DG's OFFICE | D16: 15(9) | E16: 33507.5 | G16: =E16*300% -> 100522.5 | H16: =E16*7.5% -> 2513.0625 | I16: 40122.19 | J16: =E16*50% -> 16753.75 | K16: =E16*350% -> 117276.25 | L16: =E16*100% -> 33507.5 | N16: =80000 -> 80000 | O16: =E16*10% -> 3350.75 | P16: 20000 | Q16: 0 | R16: =Q16+P16+O16+N16+M16+L16+K16+J16+I16+H16+G16+F16+E16 -> 447553.5 | T16: =20000 -> 20000 | U16: =179017.51 -> 179017.51 | V16: ='[3]DECEMBER 2019'!$H$35 -> 837.6875 | W16: 15548.33 | X16: =W16+V16+U16+T16+S16 -> 215403.53 | Y16: 232149.97 | Z16: =R16-X16 -> 232149.97
A17: 9 | B17: ANDRAWUS MUSA | C17: ASST. DIRECTOR, STORE | D17: 15(9) | E17: 33507.5 | G17: =E17*300% -> 100522.5 | H17: =E17*7.5% -> 2513.0625 | I17: =40122.19 -> 40122.19 | J17: =E17*50% -> 16753.75 | K17: =E17*350% -> 117276.25 | L17: =E17*100% -> 33507.5 | N17: =80000 -> 80000 | O17: =E17*10% -> 3350.75 | P17: 20000 | Q17: 0 | R17: =SUM(E17:Q17) -> 447553.5 | T17: =50000 -> 50000 | U17: =90000 -> 90000 | V17: ='[2]April 2022'!$H$28 -> 837.6875 | W17: =15548.33 -> 15548.33 | X17: =W17+V17+U17+T17+S17 -> 156386.02 | Y17: 291198.59 | Z17: =R17-X17 -> 291167.48
A18: 10 | B18: AYOBOLU OLAJIDE OLUFUNSHO | C18: ASST.DIR., INFORMATION | D18: 15 (7) | E18: 31018.84 | G18: =E18*300% -> 93056.52 | H18: =E18*7.5% -> 2326.413 | I18: 40122.19 | J18: =E18*50% -> 15509.42 | K18: =E18*350% -> 108565.94 | L18: =E18*100% -> 31018.84 | N18: =80000 -> 80000 | O18: =E18*10% -> 3101.884 | P18: 20000 | Q18: 0 | R18: =Q18+P18+O18+N18+M18+L18+K18+J18+I18+H18+G18+F18+E18 -> 424720.05 | T18: =50000 -> 50000 | U18: =59583.33 -> 59583.33 | W18: 15548.33 | X18: =W18+V18+U18+T18+S18 -> 125131.66 | Y18: 299588.39 | Z18: =R18-X18 -> 299588.39
A19: 11 | B19: HUSSEIN EGYE MUSA | C19: CHIEF PROTOCOL OFFICER | D19: 14(9) | E19: 26732.65 | G19: =E19*300% -> 80197.95 | H19: =E19*7.5% -> 2004.9488 | J19: =E19*50% -> 13366.325 | K19: =E19*350% -> 93564.275 | L19: =E19*100% -> 26732.65 | N19: =70000 -> 70000 | O19: =E19*10% -> 2673.265 | P19: 20000 | Q19: 50000 | R19: =Q19+P19+O19+N19+M19+L19+K19+J19+I19+H19+G19+F19+E19 -> 385272.06 | T19: 50000 | U19: =150000 -> 150000 | V19: 0 | W19: 7709.76 | X19: =W19+V19+U19+T19+S19 -> 207709.76 | Y19: 177562.3 | Z19: =R19-X19 -> 177562.3
A20: 12 | B20: DONALD E. MKPANAM | C20: CHIEF ICT OFFICER | D20: 14(9) | E20: 26732.65 | G20: =E20*300% -> 80197.95 | H20: =E20*7.5% -> 2004.9488 | J20: =E20*50% -> 13366.325 | K20: =E20*350% -> 93564.275 | L20: =E20*100% -> 26732.65 | N20: =70000 -> 70000 | O20: =E20*10% -> 2673.265 | P20: 20000 | Q20: 0 | R20: =Q20+P20+O20+N20+M20+L20+K20+J20+I20+H20+G20+F20+E20 -> 335272.06 | V20: ='[2]April 2022'!$H$27 -> 668.31625 | W20: 7709.76 | X20: =W20+V20+U20+T20+S20 -> 8378.0763 | Y20: 326903.82 | Z20: =R20-X20 -> 326893.99
A21: 13 | B21: JOY HARUNA MAKERI | C21: RESEARCH FELLOW 1 TRAINING | D21: 14(9) | E21: 26732.65 | G21: =E21*300% -> 80197.95 | H21: =E21*7.5% -> 2004.9488 | J21: =E21*50% -> 13366.325 | K21: =E21*350% -> 93564.275 | L21: =E21*100% -> 26732.65 | M21: =140000 -> 140000 | O21: =E21*10% -> 2673.265 | P21: 20000 | Q21: =50000+100000 -> 150000 | R21: =Q21+P21+O21+N21+M21+L21+K21+J21+I21+H21+G21+F21+E21 -> 555272.06 | W21: =7709.76 -> 7709.76 | X21: =W21+V21+U21+T21+S21 -> 7709.76 | Y21: 547562.3 | Z21: =R21-X21 -> 547562.3
A22: 14 | B22: ALI ABDULLAHI | C22: ASST. CHIEF ICT OFFICER | D22: 13(11) | E22: 26339.3 | G22: =E22*300% -> 79017.9 | H22: =E22*7.5% -> 1975.4475 | I22: 0 | J22: =E22*50% -> 13169.65 | K22: =E22*350% -> 92187.55 | L22: =E22*100% -> 26339.3 | N22: =70000 -> 70000 | O22: =E22*10% -> 2633.93 | P22: 15000 | Q22: =0 -> 0 | R22: =Q22+P22+O22+N22+M22+L22+K22+J22+I22+H22+G22+F22+E22 -> 326663.08 | W22: =7709.76 -> 7709.76 | X22: =W22+V22+U22+T22+S22 -> 7709.76 | Y22: 318953.32 | Z22: =R22-X22 -> 318953.32
A23: 15 | B23: MARIAM MOHAMMED BELLO | C23: SA- SPECIAL DUTIES | D23: 13 (7) | E23: =39662.25 -> 39662.25 | G23: =E23*300% -> 118986.75 | H23: =E23*7.5% -> 2974.6687 | I23: 0 | J23: =E23*50% -> 19831.125 | K23: =E23*350% -> 138817.88 | L23: =E23*100% -> 39662.25 | N23: =90000 -> 90000 | O23: =E23*10% -> 3966.225 | P23: 15000 | Q23: =100000+100000 -> 200000 | R23: =Q23+P23+O23+N23+M23+L23+K23+J23+I23+H23+G23+F23+E23 -> 668901.14 | W23: 21618.09 | X23: =W23+V23+U23+T23+S23 -> 21618.09 | Y23: 489003.27 | Z23: =R23-X23 -> 647283.05
A24: 16 | B24: PERCY TERFA GBAHABO | C24: HEAD, NILDS LIAISON OFFICE | D24: 13(8) | E24: 23891.12 | G24: =E24*300% -> 71673.36 | H24: =E24*7.5% -> 1791.834 | I24: 0 | J24: =E24*50% -> 11945.56 | K24: =E24*350% -> 83618.92 | L24: =E24*100% -> 23891.12 | M24: =120000 -> 120000 | O24: =E24*10% -> 2389.112 | P24: 15000 | Q24: 0 | R24: =Q24+P24+O24+N24+M24+L24+K24+J24+I24+H24+G24+F24+E24 -> 354201.03 | T24: =70000 -> 70000 | U24: =98464.26 -> 98464.26 | W24: =7709.76 -> 7709.76 | X24: =W24+V24+U24+T24+S24 -> 176174.02 | Y24: 238027.01 | Z24: =R24-X24 -> 178027.01
A25: 17 | B25: ADUGBA RICHARD TERSEER | C25: INFORMATION OFFICER | D25: 10(10) | E25: 18779.3 | G25: =E25*300% -> 56337.9 | H25: =E25*7.5% -> 1408.4475 | J25: =E25*50% -> 9389.65 | K25: =E25*350% -> 65727.55 | L25: =E25*100% -> 18779.3 | N25: =60000 -> 60000 | O25: =E25*10% -> 1877.93 | P25: 10000 | R25: =Q25+P25+O25+N25+M25+L25+K25+J25+I25+H25+G25+F25+E25 -> 242300.08 | T25: =20000 -> 20000 | U25: =111833.33 -> 111833.33 | W25: 3369.51 | X25: =W25+V25+U25+T25+S25 -> 135202.84 | Y25: 107097.24 | Z25: =R25-X25 -> 107097.24
A26: 18 | B26: CHRISTIAN MADUABUCHI ODO | C26: PRINCIPAL ICT OFFICER | D26: 12(8) | E26: =21520.88 -> 21520.88 | G26: =E26*300% -> 64562.64 | H26: =E26*7.5% -> 1614.066 | J26: =E26*50% -> 10760.44 | K26: =E26*350% -> 75323.08 | L26: =E26*100% -> 21520.88 | N26: =60000 -> 60000 | O26: =E26*10% -> 2152.088 | P26: 15000 | R26: =Q26+P26+O26+N26+M26+L26+K26+J26+I26+H26+G26+F26+E26 -> 272454.07 | T26: =20000 -> 20000 | U26: =82500 -> 82500 | V26: ='[2]April 2022'!$H$45 -> 538.022 | W26: 3369.51 | X26: =W26+V26+U26+T26+S26 -> 106407.53 | Y26: 166102.64 | Z26: =R26-X26 -> 166046.54
A27: 19 | B27: HASSANA AHMED IBRAHIM | C27: PA- TO DG | D27: 13 (7) | E27: 23074.99 | G27: =E27*300% -> 69224.97 | H27: =E27*7.5% -> 1730.6243 | J27: =E27*50% -> 11537.495 | K27: =E27*350% -> 80762.465 | L27: =E27*100% -> 23074.99 | M27: =100000 -> 100000 | O27: =E27*10% -> 2307.499 | P27: 10000 | Q27: =100000 -> 100000 | R27: =Q27+P27+O27+N27+M27+L27+K27+J27+I27+H27+G27+F27+E27 -> 421713.03 | T27: =30000 -> 30000 | V27: ='[2]April 2022'!$H$52 -> 576.87475 | W27: =7709.76 -> 7709.76 | X27: =W27+V27+U27+T27+S27 -> 38286.635 | Y27: 383558.67 | Z27: =R27-X27 -> 383426.4
A28: 20 | B28: VICTOR ASUKWO | C28: ICT OFFICER | D28: 8 (10) | E28: 13492.21 | G28: =E28*300% -> 40476.63 | H28: =E28*7.5% -> 1011.9157 | J28: =E28*50% -> 6746.105 | K28: =E28*350% -> 47222.735 | L28: =E28*100% -> 13492.21 | N28: =50000 -> 50000 | O28: =E28*10% -> 1349.221 | P28: 10000 | R28: =Q28+P28+O28+N28+M28+L28+K28+J28+I28+H28+G28+F28+E28 -> 183791.03 | W28: 1484.37 | X28: =W28+V28+U28+T28+S28 -> 1484.37 | Y28: 182306.66 | Z28: =R28-X28 -> 182306.66
A29: 21 | B29: SULEIMAN ABUBAKAR SODEEQ | C29: ASST. ADMIN. OFFICER | D29: 8(7) | E29: 12351.94 | G29: =E29*300% -> 37055.82 | H29: =E29*7.5% -> 926.3955 | J29: =E29*50% -> 6175.97 | K29: =E29*350% -> 43231.79 | L29: =E29*100% -> 12351.94 | N29: =50000 -> 50000 | O29: =E29*10% -> 1235.194 | P29: 10000 | R29: =Q29+P29+O29+N29+M29+L29+K29+J29+I29+H29+G29+F29+E29 -> 173329.05 | W29: =1484.37 -> 1484.37 | X29: =W29+V29+U29+T29+S29 -> 1484.37 | Y29: 171844.68 | Z29: =R29-X29 -> 171844.68
A30: 22 | B30: YAKUB OLUWATOYIN USMAN | C30: ASST. ADMIN. OFFICER | D30: 10(8) | E30: 17784.1 | G30: =E30*300% -> 53352.3 | H30: =E30*7.5% -> 1333.8075 | J30: =E30*50% -> 8892.05 | K30: =E30*350% -> 62244.35 | L30: =E30*100% -> 17784.1 | N30: =60000 -> 60000 | O30: =E30*10% -> 1778.41 | P30: 10000 | R30: =Q30+P30+O30+N30+M30+L30+K30+J30+I30+H30+G30+F30+E30 -> 233169.12 | T30: =10000 -> 10000 | U30: =34333.33 -> 34333.33 | W30: =1484.37 -> 1484.37 | X30: =W30+V30+U30+T30+S30 -> 45817.7 | Y30: 187351.42 | Z30: =R30-X30 -> 187351.42
A31: 23 | B31: ANTHONY EDET | C31: ASST. MGR M&E | D31: 13(9) | E31: 24741.26 | G31: =E31*300% -> 74223.78 | H31: =E31*7.5% -> 1855.5945 | I31: 0 | J31: =E31*50% -> 12370.63 | K31: =E31*350% -> 86594.41 | L31: =E31*100% -> 24741.26 | N31: =70000 -> 70000 | O31: =E31*10% -> 2474.126 | P31: 15000 | Q31: 0 | R31: =Q31+P31+O31+N31+M31+L31+K31+J31+I31+H31+G31+F31+E31 -> 312001.06 | T31: 20000 | U31: =68750 -> 68750 | V31: ='[2]April 2022'!$H$38 -> 618.5315 | W31: =7709.76 -> 7709.76 | X31: =W31+V31+U31+T31+S31 -> 97078.291 | Y31: 214944.02 | Z31: =R31-X31 -> 214922.77
A32: 24 | B32: EGUATU U. ONYEJELEM | C32: OFFICER M&E | D32: 10(10) | E32: 18779.3 | G32: =E32*300% -> 56337.9 | H32: =E32*7.5% -> 1408.4475 | J32: =E32*50% -> 9389.65 | K32: =E32*350% -> 65727.55 | L32: =E32*100% -> 18779.3 | N32: =60000 -> 60000 | O32: =E32*10% -> 1877.93 | P32: 10000 | R32: =Q32+P32+O32+N32+M32+L32+K32+J32+I32+H32+G32+F32+E32 -> 242300.08 | T32: =20000 -> 20000 | U32: =87500+43750 -> 131250 | W32: 3369.51 | X32: =W32+V32+U32+T32+S32 -> 154619.51 | Y32: 87680.567 | Z32: =R32-X32 -> 87680.567
A33: 25 | B33: ODEH SUZIE | C33: ADMIN. OFFICER, LIASION OFFICE | D33: 10(9) | E33: 18281.64 | G33: =E33*300% -> 54844.92 | H33: =E33*7.5% -> 1371.123 | J33: =E33*50% -> 9140.82 | K33: =E33*350% -> 63985.74 | L33: =E33*100% -> 18281.64 | N33: 60000 | O33: =E33*10% -> 1828.164 | P33: 10000 | R33: =Q33+P33+O33+N33+M33+L33+K33+J33+I33+H33+G33+F33+E33 -> 237734.05 | T33: =30000 -> 30000 | V33: =0 -> 0 | W33: 3369.51 | X33: =W33+V33+U33+T33+S33 -> 33369.51 | Y33: 204364.54 | Z33: =R33-X33 -> 204364.54
A34: 26 | B34: IJEOMA NKOLIKWA | C34: ASSISTANT STORES OFFICER | D34: 8(10) | E34: 13492.21 | G34: =E34*300% -> 40476.63 | H34: =E34*7.5% -> 1011.9157 | J34: =E34*50% -> 6746.105 | K34: =E34*350% -> 47222.735 | L34: =E34*100% -> 13492.21 | N34: =50000 -> 50000 | O34: =E34*10% -> 1349.221 | P34: 10000 | R34: =SUM(E34:Q34) -> 183791.03 | T34: =10000 -> 10000 | W34: 1484.37 | X34: =W34+V34+U34+T34+S34 -> 11484.37 | Y34: 172306.66 | Z34: =R34-X34 -> 172306.66
A35: 27 | B35: ABDULRAHMAN A SULAIMAN | C35: ASSISTANT STORES OFFICER | D35: 8 (9) | E35: 13112.16 | G35: =E35*300% -> 39336.48 | H35: =E35*7.5% -> 983.412 | J35: =E35*50% -> 6556.08 | K35: =E35*350% -> 45892.56 | L35: =E35*100% -> 13112.16 | N35: =50000 -> 50000 | O35: =E35*10% -> 1311.216 | P35: 10000 | R35: =SUM(E35:Q35) -> 180304.07 | T35: =20000 -> 20000 | W35: =(1484.37) -> 1484.37 | X35: =W35+V35+U35+T35+S35 -> 21484.37 | Y35: 158819.7 | Z35: =R35-X35 -> 158819.7
A36: 28 | B36: TASSNEEM IBRAHIM | C36: ASSIST. INFORMATION | D36: 8(9) | E36: 13112.16 | G36: =E36*300% -> 39336.48 | H36: =E36*7.5% -> 983.412 | J36: =E36*50% -> 6556.08 | K36: =E36*350% -> 45892.56 | L36: =E36*100% -> 13112.16 | N36: =50000 -> 50000 | O36: =E36*10% -> 1311.216 | P36: 10000 | R36: =Q36+P36+O36+N36+M36+L36+K36+J36+I36+H36+G36+F36+E36 -> 180304.07 | T36: =50000 -> 50000 | U36: =17166.67 -> 17166.67 | V36: =0 -> 0 | W36: =1484.37 -> 1484.37 | X36: =W36+V36+U36+T36+S36 -> 68651.04 | Y36: 111653.03 | Z36: =R36-X36 -> 111653.03
A37: 29 | B37: JIMOH ADEBAYO ZAKA | C37: ASST. OFFICER/COMM | D37: 8(7) | E37: 12351.94 | G37: =E37*300% -> 37055.82 | H37: =E37*7.5% -> 926.3955 | J37: =E37*50% -> 6175.97 | K37: =E37*350% -> 43231.79 | L37: =E37*100% -> 12351.94 | N37: =50000 -> 50000 | O37: =E37*10% -> 1235.194 | P37: 10000 | R37: =Q37+P37+O37+N37+M37+L37+K37+J37+I37+H37+G37+F37+E37 -> 173329.05 | T37: =50000 -> 50000 | V37: =0 -> 0 | W37: =1484.37 -> 1484.37 | X37: =W37+V37+U37+T37+S37 -> 51484.37 | Y37: 121844.68 | Z37: =R37-X37 -> 121844.68
A38: 30 | B38: HABEEBA K MUHAMMAD SALIHU | C38: ASST. OFFICER/COMM | D38: 8(7) | E38: 12351.94 | G38: =E38*300% -> 37055.82 | H38: =E38*7.5% -> 926.3955 | J38: =E38*50% -> 6175.97 | K38: =E38*350% -> 43231.79 | L38: =E38*100% -> 12351.94 | N38: =50000 -> 50000 | O38: =E38*10% -> 1235.194 | P38: 10000 | R38: =Q38+P38+O38+N38+M38+L38+K38+J38+I38+H38+G38+F38+E38 -> 173329.05 | V38: =0 -> 0 | W38: =1484.37 -> 1484.37 | X38: =W38+V38+U38+T38+S38 -> 1484.37 | Y38: 171844.68 | Z38: =R38-X38 -> 171844.68
B39: TOTAL | C39: 30 | E39: =SUM(E9:E38) -> 934067.33 | G39: =SUM(G9:G38) -> 2641713.2 | H39: =SUM(H9:H38) -> 106165.02 | I39: =SUM(I9:I38) -> 521588.47 | J39: =SUM(J9:J38) -> 459009.23 | K39: =SUM(K9:K38) -> 2707525 | L39: =SUM(L9:L38) -> 893945.15 | M39: =SUM(M9:M38) -> 1170000 | N39: =SUM(N9:N38) -> 1510000 | ... R39: =SUM(R9:R38) -> 12372655 | T39: =SUM(T9:T38) -> 872000 | U39: =SUM(U9:U38) -> 1243037.3 | V39: =SUM(V9:V38) -> 8824.9372 | W39: =SUM(W9:W38) -> 409488.93 | X39: =SUM(X9:X38) -> 2533351.2 | Y39: 9843312.2 | Z39: =SUM(Z9:Z38) -> 9839304
B41: INTERNAL AUDIT
A42: 1 | B42: OSANAIYE DAVID AKINYEMI | C42: DIRECTOR INTERNAL AUDIT | D42: 17(8) | E42: 79039.64 | G42: =E42*300% -> 237118.92 | H42: =E42*7.5% -> 5927.973 | I42: 80244.38 | J42: =E42*50% -> 39519.82 | K42: =E42*350% -> 276638.74 | L42: =E42*100% -> 79039.64 | N42: =100000 -> 100000 | O42: =E42*10% -> 7903.964 | P42: 20000 | R42: =SUM(E42:Q42) -> 925433.08 | T42: =100000 -> 100000 | W42: =(52776.63) -> 52776.63 | X42: =W42+V42+U42+T42+S42 -> 152776.63 | Y42: 772656.45 | Z42: =R42-X42 -> 772656.45
A43: 2 | B43: JAMILA ABDUL | C43: AUDITOR II | D43: 8(7) | E43: 12351.94 | G43: =E43*300% -> 37055.82 | H43: =E43*7.5% -> 926.3955 | J43: =E43*50% -> 6175.97 | K43: =E43*350% -> 43231.79 | L43: =E43*100% -> 12351.94 | N43: =50000 -> 50000 | O43: =E43*10% -> 1235.194 | P43: 10000 | R43: =(Q43+P43+O43+N43+M43+L43+K43+J43+I43+H43+G43+F43+E43)*12/30 -> 69331.62 | V43: =0 -> 0 | W43: 1484.37 | X43: =W43+V43+U43+T43+S43 -> 1484.37 | Z43: =R43-X43 -> 67847.25
C44: 2 | E44: =SUM(E42:E43) -> 91391.58 | G44: =SUM(G42:G43) -> 274174.74 | H44: =SUM(H42:H43) -> 6854.3685 | I44: =SUM(I42:I43) -> 80244.38 | J44: =SUM(J42:J43) -> 45695.79 | K44: =SUM(K42:K43) -> 319870.53 | L44: =SUM(L42:L43) -> 91391.58 | N44: =SUM(N42:N43) -> 150000 | O44: =SUM(O42:O43) -> 9139.158 | P44: =SUM(P42:P43) -> 30000 | R44: =SUM(R42:R43) -> 994764.7 | T44: =SUM(T42:T43) -> 100000 | V44: =SUM(V42:V43) -> 0 | W44: =SUM(W42:W43) -> 54261 | X44: =SUM(X42:X43) -> 154261 | Y44: =SUM(Y42:Y43) -> 772656.45 | Z44: =SUM(Z42:Z43) -> 840503.7
B46: LEG. SUPPORT SEVICES
A47: 1 | B47: PROF. EDOBA BRIGHT OMOREGBE | C47: AG. DLSS | D47: 17(9) | E47: 81740.02 | G47: =E47*300% -> 245220.06 | H47: =E47*7.5% -> 6130.5015 | I47: 80244.38 | J47: =E47*50% -> 40870.01 | K47: =E47*350% -> 286090.07 | L47: =E47*100% -> 81740.02 | M47: =200000 -> 200000 | O47: =E47*10% -> 8174.002 | P47: 20000 | R47: =SUM(E47:Q47) -> 1050209.1 | T47: =200000 -> 200000 | U47: =52500*2 -> 105000 | W47: =52776.63 -> 52776.63 | X47: =W47+V47+U47+T47+S47 -> 357776.63 | Y47: 692432.43 | Z47: =R47-X47 -> 692432.43
A48: 2 | B48: DR CLINTON JAJA | C48: SENIOR RESEARCH FELLOW | D48: 15(9) | E48: 33507.5 | G48: =E48*300% -> 100522.5 | H48: =E48*7.5% -> 2513.0625 | I48: 40122.19 | J48: =E48*50% -> 16753.75 | K48: =E48*350% -> 117276.25 | L48: =E48*100% -> 33507.5 | M48: =160000 -> 160000 | O48: =E48*10% -> 3350.75 | P48: 20000 | Q48: 0 | R48: =SUM(E48:Q48) -> 527553.5 | T48: 50000 | U48: =0 -> 0 | W48: 15548.33 | X48: =W48+V48+U48+T48+S48 -> 65548.33 | Y48: 462005.17 | Z48: =R48-X48 -> 462005.17
A49: 3 | B49: BETHEL UZOMA IHUGBA | C49: SNR RESEARCH FELLOW | D49: 15(9) | E49: 33507.5 | G49: =E49*300% -> 100522.5 | H49: =E49*7.5% -> 2513.0625 | I49: 40122.19 | J49: =E49*50% -> 16753.75 | K49: =E49*350% -> 117276.25 | L49: =E49*100% -> 33507.5 | M49: =160000 -> 160000 | O49: =E49*10% -> 3350.75 | P49: 20000 | R49: =SUM(E49:Q49) -> 527553.5 | T49: =80000+23000 -> 103000 | U49: =246905.96 -> 246905.96 | W49: 15548.33 | X49: =W49+V49+U49+T49+S49 -> 365454.29 | Y49: 162099.21 | Z49: =R49-X49 -> 162099.21
A50: 4 | B50: OGUCHE SAMUEL | C50: SNR RESEARCH FELLOW | D50: 15(8) | E50: 32263.2 | G50: =E50*300% -> 96789.6 | H50: =E50*7.5% -> 2419.74 | I50: 40122.19 | J50: =E50*50% -> 16131.6 | K50: =E50*350% -> 112921.2 | L50: =E50*100% -> 32263.2 | M50: =160000 -> 160000 | O50: =E50*10% -> 3226.32 | P50: 20000 | R50: =SUM(E50:Q50) -> 516137.05 | T50: =30000 -> 30000 | U50: =176288.88 -> 176288.88 | W50: =15548.33 -> 15548.33 | X50: =W50+V50+U50+T50+S50 -> 221837.21 | Y50: 294299.84 | Z50: =R50-X50 -> 294299.84
A51: 5 | B51: IBRAHIM USMAN | C51: RESEARCH FELLOW I | D51: 14(11) | E51: 28489.81 | G51: =E51*300% -> 85469.43 | H51: =E51*7.5% -> 2136.7357 | I51: 0 | J51: =E51*50% -> 14244.905 | K51: =E51*350% -> 99714.335 | L51: =E51*100% -> 28489.81 | M51: =140000 -> 140000 | O51: =E51*10% -> 2848.981 | P51: 20000 | Q51: 0 | R51: =SUM(E51:Q51) -> 421394.01 | V51: ='[2]April 2022'!$H$23 -> 712.24525 | W51: 7709.76 | X51: =W51+V51+U51+T51+S51 -> 8422.0053 | Y51: 412972 | Z51: =R51-X51 -> 412972
A52: 6 | B52: DR MOHAMMED O. AMALI | C52: RESEARCH FELLOW I | D52: 14(9) | E52: 26732.65 | G52: =E52*300% -> 80197.95 | H52: =E52*7.5% -> 2004.9488 | J52: =E52*50% -> 13366.325 | K52: =E52*350% -> 93564.275 | L52: =E52*100% -> 26732.65 | M52: =140000 -> 140000 | O52: =E52*10% -> 2673.265 | P52: 20000 | R52: =SUM(E52:Q52) -> 405272.06 | T52: =15000 -> 15000 | U52: =133333.34 -> 133333.34 | W52: 7709.76 | X52: =W52+V52+U52+T52+S52 -> 156043.1 | Y52: 249228.96 | Z52: =R52-X52 -> 249228.96
A53: 7 | B53: YAHAYA SHAMSU | C53: RESEARCH FELLOW 1 | D53: 14(9) | E53: 26732.65 | G53: =E53*300% -> 80197.95 | H53: =E53*7.5% -> 2004.9488 | J53: =E53*50% -> 13366.325 | K53: =E53*350% -> 93564.275 | L53: =E53*100% -> 26732.65 | M53: =140000 -> 140000 | O53: =E53*10% -> 2673.265 | P53: 20000 | R53: =SUM(E53:Q53) -> 405272.06 | V53: 0 | W53: 7709.76 | X53: =W53+V53+U53+T53+S53 -> 7709.76 | Y53: 397562.3 | Z53: =R53-X53 -> 397562.3
A54: 8 | B54: OFORDEME ADAOBI JULIA | C54: RESEARCH FELLOW 11 | D54: 13(10) | E54: 25523.45 | G54: =E54*300% -> 76570.35 | H54: =E54*7.5% -> 1914.2587 | I54: 0 | J54: =E54*50% -> 12761.725 | K54: =E54*350% -> 89332.075 | L54: =E54*100% -> 25523.45 | M54: =120000 -> 120000 | O54: =E54*10% -> 2552.345 | P54: 15000 | Q54: 0 | R54: =SUM(E54:Q54) -> 369177.65 | W54: 7709.76 | X54: =W54+V54+U54+T54+S54 -> 7709.76 | Y54: 361467.89 | Z54: =R54-X54 -> 361467.89
A55: 9 | B55: DORIS DAKDA AARON | C55: RESEARCH FELLOW II | D55: 13(9) | E55: 24741.26 | G55: =E55*300% -> 74223.78 | H55: =E55*7.5% -> 1855.5945 | J55: =E55*50% -> 12370.63 | K55: =E55*350% -> 86594.41 | L55: =E55*100% -> 24741.26 | M55: =120000 -> 120000 | O55: =E55*10% -> 2474.126 | P55: 15000 | R55: =SUM(E55:Q55) -> 362001.06 | T55: =50000+10000 -> 60000 | U55: =91666.67 -> 91666.67 | V55: ='[2]April 2022'!$H$46 -> 618.5315 | W55: =7709.76 -> 7709.76 | X55: =W55+V55+U55+T55+S55 -> 159994.96 | Y55: 202027.35 | Z55: =R55-X55 -> 202006.1
A56: 10 | B56: ZAINAB AKINDE | C56: RESEARCH OFFICER | D56: 9(7) | E56: =14736.14 -> 14736.14 | G56: =E56*300% -> 44208.42 | H56: =E56*7.5% -> 1105.2105 | J56: =E56*50% -> 7368.07 | K56: =E56*350% -> 51576.49 | L56: =E56*100% -> 14736.14 | M56: =100000 -> 100000 | O56: =E56*10% -> 1473.614 | P56: 10000 | R56: =SUM(E56:Q56)*12/30 -> 98081.634 | W56: 1484.37 | X56: =W56+V56+U56+T56 -> 1484.37 | Z56: =R56-X56 -> 96597.264
B57: TOTAL | C57: 10 | E57: =SUM(E47:E56) -> 327974.18 | F57: =SUM(F47:F56) -> 0 | G57: =SUM(G47:G56) -> 983922.54 | H57: =SUM(H47:H56) -> 24598.064 | I57: =SUM(I47:I56) -> 200610.95 | J57: =SUM(J47:J56) -> 163987.09 | K57: =SUM(K47:K56) -> 1147909.6 | L57: =SUM(L47:L56) -> 327974.18 | M57: =SUM(M47:M56) -> 1440000 | O57: =SUM(O47:O56) -> 32797.418 | P57: =SUM(P47:P56) -> 180000 | Q57: =SUM(Q47:Q56) -> 0 | R57: =SUM(R47:R56) -> 4682651.6 | T57: =SUM(T47:T56) -> 458000 | U57: =SUM(U47:U56) -> 753194.85 | V57: =SUM(V47:V56) -> 1330.7767 | W57: =SUM(W47:W56) -> 139454.79 | X57: =SUM(X47:X56) -> 1351980.4 | Y57: =SUM(Y47:Y56) -> 3234095.2 | Z57: =SUM(Z47:Z56) -> 3330671.2
B59: LEGAL SERVICES
A60: 1 | B60: DR SHUIBU DANWANKA | C60: DIRECTOR LEGAL SERVICES | D60: 17(9) | E60: 81740.02 | G60: =E60*300% -> 245220.06 | H60: =E60*7.5% -> 6130.5015 | I60: 80244.38 | J60: =E60*50% -> 40870.01 | K60: =E60*350% -> 286090.07 | L60: =E60*100% -> 81740.02 | M60: =200000 -> 200000 | O60: =E60*10% -> 8174.002 | P60: 20000 | Q60: 0 | R60: =SUM(E60:Q60) -> 1050209.1 | V60: 0 | W60: 52776.63 | X60: =W60+V60+U60+T60+S60 -> 52776.63 | Y60: 997432.43 | Z60: =R60-X60 -> 997432.43
A61: 2 | B61: ABDULSALAM BAKO | C61: MANAGER, LEGAL SERVICES | D61: 15 (8) | E61: 32263.2 | G61: =E61*300% -> 96789.6 | H61: =E61*7.5% -> 2419.74 | I61: 40122.19 | J61: =E61*50% -> 16131.6 | K61: =E61*350% -> 112921.2 | L61: =E61*100% -> 32263.2 | N61: =80000 -> 80000 | O61: =E61*10% -> 3226.32 | P61: 20000 | Q61: 0 | R61: =SUM(E61:Q61) -> 436137.05 | T61: =50000 -> 50000 | U61: =95000 -> 95000 | V61: 0 | W61: =15548.33 -> 15548.33 | X61: =W61+V61+U61+T61+S61 -> 160548.33 | Y61: 275588.72 | Z61: =R61-X61 -> 275588.72
B62: TOTAL | C62: 2 | E62: 114003.22 | G62: =SUM(G60:G61) -> 342009.66 | H62: =SUM(H60:H61) -> 8550.2415 | I62: =SUM(I60:I61) -> 120366.57 | J62: =SUM(J60:J61) -> 57001.61 | K62: =SUM(K60:K61) -> 399011.27 | L62: =SUM(L60:L61) -> 114003.22 | M62: =SUM(M60:M61) -> 200000 | N62: =SUM(N60:N61) -> 80000 | ... R62: =SUM(R60:R61) -> 1486346.1 | T62: =SUM(T60:T61) -> 50000 | U62: =SUM(U61) -> 95000 | V62: =SUM(V60:V61) -> 0 | W62: =SUM(W60:W61) -> 68324.96 | X62: =SUM(X60:X61) -> 213324.96 | Y62: 1273021.2 | Z62: =SUM(Z60:Z61) -> 1273021.2
B64: DEMOCRACY AND GOVERNANCE
A65: 1 | B65: DR. ADEWALE ADEREMI | C65: DIRECTOR, DEMOCRATIC STUDIES | D65: 17(9) | E65: 81740.02 | G65: =E65*300% -> 245220.06 | H65: =E65*7.5% -> 6130.5015 | I65: =80244.38 -> 80244.38 | J65: =E65*50% -> 40870.01 | K65: =E65*350% -> 286090.07 | L65: =E65*100% -> 81740.02 | M65: =200000 -> 200000 | O65: =E65*10% -> 8174.002 | P65: 20000 | Q65: 0 | R65: =SUM(E65:Q65) -> 1050209.1 | T65: =100000+100000 -> 200000 | W65: =52776.63 -> 52776.63 | X65: =W65+V65+U65+T65+S65 -> 252776.63 | Y65: 797432.43 | Z65: =R65-X65 -> 797432.43
A66: 2 | B66: NDANUSA MOHAMMED MANZUMA | C66: SNR RESEARCH FELLOW | D66: 15 (7) | E66: 31018.84 | G66: =E66*300% -> 93056.52 | H66: =E66*7.5% -> 2326.413 | I66: 40122.19 | J66: =E66*50% -> 15509.42 | K66: =E66*350% -> 108565.94 | L66: =E66*100% -> 31018.84 | M66: =160000 -> 160000 | O66: =E66*10% -> 3101.884 | P66: 20000 | Q66: 0 | R66: =SUM(E66:Q66) -> 504720.05 | T66: =100000 -> 100000 | U66: =131250 -> 131250 | V66: 0 | W66: =15548.33 -> 15548.33 | X66: =W66+V66+U66+T66+S66 -> 246798.33 | Y66: 257921.72 | Z66: =R66-X66 -> 257921.72
A67: 3 | B67: EMILY EDOISA IKHIDE | C67: RESEARCH FELLOW II | D67: 13(11) | E67: 26339.3 | G67: =E67*300% -> 79017.9 | H67: =E67*7.5% -> 1975.4475 | J67: =E67*50% -> 13169.65 | K67: =E67*350% -> 92187.55 | L67: =E67*100% -> 26339.3 | M67: =120000 -> 120000 | O67: =E67*10% -> 2633.93 | P67: 15000 | X67: =W67+V67+U67+T67+S67 -> 0 | Y67: 70790.749 | Z67: =R67-X67 -> 0
A68: 4 | B68: EJALONIBU GANIYU LAYI | C68: RESEARCH FELLOW 11 | D68: 13(9) | E68: 24741.26 | G68: =E68*300% -> 74223.78 | H68: =E68*7.5% -> 1855.5945 | J68: =E68*50% -> 12370.63 | K68: =E68*350% -> 86594.41 | L68: =E68*100% -> 24741.26 | M68: =120000 -> 120000 | O68: =E68*10% -> 2474.126 | P68: 15000 | R68: =SUM(E68:Q68) -> 362001.06 | T68: =110000 -> 110000 | W68: =7709.76 -> 7709.76 | X68: =W68+V68+U68+T68+S68 -> 117709.76 | Y68: 244291.3 | Z68: =R68-X68 -> 244291.3
A69: 5 | B69: LONA POLIT BONKAT | C69: RESEARCH FELLOW 11 | D69: 13(8) | E69: 23891.12 | G69: =E69*300% -> 71673.36 | H69: =E69*7.5% -> 1791.834 | I69: 0 | J69: =E69*50% -> 11945.56 | K69: =E69*350% -> 83618.92 | L69: =E69*100% -> 23891.12 | M69: =120000 -> 120000 | O69: =E69*10% -> 2389.112 | P69: 15000 | Q69: 0 | R69: =SUM(E69:Q69) -> 354201.03 | T69: =20000 -> 20000 | U69: =119444.44 -> 119444.44 | V69: =0 -> 0 | W69: 7709.76 | X69: =W69+V69+U69+T69+S69 -> 147154.2 | Y69: 207046.83 | Z69: =R69-X69 -> 207046.83
A70: 6 | B70: YUNUSA ABDULLAHI | C70: RESEARCH FELLOW 1 | D70: 14(9) | E70: 26732.65 | G70: =E70*300% -> 80197.95 | H70: =E70*7.5% -> 2004.9488 | J70: =E70*50% -> 13366.325 | K70: =E70*350% -> 93564.275 | L70: =E70*100% -> 26732.65 | M70: =140000 -> 140000 | O70: =E70*10% -> 2673.265 | P70: 20000 | R70: =SUM(E70:Q70) -> 405272.06 | T70: =10000 -> 10000 | U70: =54585.66 -> 54585.66 | W70: =7709.76 -> 7709.76 | X70: =W70+V70+U70+T70+S70 -> 72295.42 | Y70: 332976.64 | Z70: =R70-X70 -> 332976.64
A71: 7 | B71: UDEFUNA NNADOZIE PATRICK | C71: RESEARCH OFFICER | D71: 10(13) | E71: 19774.62 | G71: =E71*300% -> 59323.86 | H71: =E71*7.5% -> 1483.0965 | I71: 0 | J71: =E71*50% -> 9887.31 | K71: =E71*350% -> 69211.17 | L71: =E71*100% -> 19774.62 | M71: =100000 -> 100000 | O71: =E71*10% -> 1977.462 | P71: 10000 | Q71: 0 | R71: =SUM(E71:Q71) -> 291432.14 | T71: =10000 -> 10000 | U71: =131771.66 -> 131771.66 | W71: 3369.51 | X71: =W71+V71+U71+T71+S71 -> 145141.17 | Y71: 146290.97 | Z71: =R71-X71 -> 146290.97
A72: 8 | B72: OSOLAFIA MUHAMMAD EGYE | C72: PRINCIPAL RESEARCH OFFICER | D72: 12(8) | E72: =21520.88 -> 21520.88 | G72: =E72*300% -> 64562.64 | H72: =E72*7.5% -> 1614.066 | I72: 0 | J72: =E72*50% -> 10760.44 | K72: =E72*350% -> 75323.08 | L72: =E72*100% -> 21520.88 | M72: =110000 -> 110000 | O72: =E72*10% -> 2152.088 | P72: 15000 | Q72: 0 | R72: =SUM(E72:Q72) -> 322454.07 | T72: =10000+20000 -> 30000 | U72: =130000 -> 130000 | V72: ='[2]April 2022'!$H$41 -> 538.022 | W72: =3369.51 -> 3369.51 | X72: =W72+V72+U72+T72+S72 -> 163907.53 | Y72: 158602.64 | Z72: =R72-X72 -> 158546.54
A73: 9 | B73: SHAFIU YAHYA MIKAIL | C73: PRINCIPAL RESEARCH OFFICER | D73: 12(7) | E73: =20749 -> 20749 | G73: =E73*300% -> 62247 | H73: =E73*7.5% -> 1556.175 | I73: 0 | J73: =E73*50% -> 10374.5 | K73: =E73*350% -> 72621.5 | L73: =E73*100% -> 20749 | M73: =110000 -> 110000 | O73: =E73*10% -> 2074.9 | P73: 15000 | Q73: 0 | R73: =SUM(E73:Q73)*12/30 -> 126148.83 | W73: =3369.51 -> 3369.51 | X73: =W73+V73+U73+T73+S73 -> 3369.51 | Z73: =R73-X73 -> 122779.32
A74: 10 | B74: HASSAN YERIMA | C74: PRINCIPAL RESEARCH OFFICER | D74: 12(7) | E74: =20749 -> 20749 | G74: =E74*300% -> 62247 | H74: =E74*7.5% -> 1556.175 | I74: 0 | J74: =E74*50% -> 10374.5 | K74: =E74*350% -> 72621.5 | L74: =E74*100% -> 20749 | M74: =110000 -> 110000 | O74: =E74*10% -> 2074.9 | P74: 15000 | Q74: 0 | R74: =SUM(E74:Q74)*12/30 -> 126148.83 | W74: =3369.51 -> 3369.51 | X74: =W74+V74+U74+T74+S74 -> 3369.51 | Z74: =R74-X74 -> 122779.32
A75: 11 | B75: HAUWA PATE SADIQ | C75: PROGRAMME OFFICER | D75: 10(10) | E75: 18779.3 | G75: =E75*300% -> 56337.9 | H75: =E75*7.5% -> 1408.4475 | J75: =E75*50% -> 9389.65 | K75: =E75*350% -> 65727.55 | L75: =E75*100% -> 18779.3 | M75: =100000 -> 100000 | O75: =E75*10% -> 1877.93 | P75: 10000 | R75: =SUM(E75:Q75) -> 282300.08 | T75: =70000+20000 -> 90000 | W75: 3369.51 | X75: =W75+V75+U75+T75+S75 -> 93369.51 | Y75: 188930.57 | Z75: =R75-X75 -> 188930.57
A76: 12 | B76: ABAYOMI KAYODE QUADRI | C76: RESEARCH OFFICER | D76: 10(7) | E76: 17286.33 | G76: =E76*300% -> 51858.99 | H76: =E76*7.5% -> 1296.4748 | J76: =E76*50% -> 8643.165 | K76: =E76*350% -> 60502.155 | L76: =E76*100% -> 17286.33 | M76: =100000 -> 100000 | O76: =E76*10% -> 1728.633 | P76: 10000 | R76: =SUM(E76:Q76) -> 268602.08 | T76: =50000 -> 50000 | U76: 0 | W76: 3369.51 | X76: =W76+V76+U76+T76+S76 -> 53369.51 | Y76: 215232.57 | Z76: =R76-X76 -> 215232.57
A77: 13 | B77: NNANDI LIVINUS ATURE | C77: RESEARCH ASSISTANT | D77: 9(7) | E77: =14736.14 -> 14736.14 | F77: =21875*2 -> 43750 | G77: =E77*300% -> 44208.42 | H77: =E77*7.5% -> 1105.2105 | J77: =E77*50% -> 7368.07 | K77: =E77*350% -> 51576.49 | L77: =E77*100% -> 14736.14 | M77: =100000 -> 100000 | O77: =E77*10% -> 1473.614 | P77: 10000 | R77: =SUM(E77:Q77) -> 288954.08 | T77: =10000 -> 10000 | U77: =95833.33 -> 95833.33 | W77: 1484.37 | X77: =W77+V77+U77+T77+S77 -> 107317.7 | Y77: 116011.35 | Z77: =R77-X77 -> 181636.38
A78: 14 | B78: LUCKY AGWOM | C78: RESEARCH ASSISTANT | D78: 8(7) | E78: 12351.94 | G78: =E78*300% -> 37055.82 | H78: =E78*7.5% -> 926.3955 | J78: =E78*50% -> 6175.97 | K78: =E78*350% -> 43231.79 | L78: =E78*100% -> 12351.94 | M78: =100000 -> 100000 | O78: =E78*10% -> 1235.194 | P78: 10000 | R78: =SUM(E78:Q78) -> 223329.05 | W78: 1484.37 | X78: =W78+V78+U78+T78+S78 -> 1484.37 | Y78: 221844.68 | Z78: =R78-X78 -> 221844.68
B79: TOTAL | C79: 14 | E79: =SUM(E65:E78) -> 360410.4 | F79: =SUM(F65:F78) -> 43750 | G79: =SUM(G65:G78) -> 1081231.2 | H79: =SUM(H65:H78) -> 27030.78 | I79: =SUM(I65:I78) -> 120366.57 | J79: =SUM(J65:J78) -> 180205.2 | K79: =SUM(K65:K78) -> 1261436.4 | L79: =SUM(L65:L78) -> 360410.4 | M79: =SUM(M65:M78) -> 1690000 | O79: =SUM(O65:O78) -> 36041.04 | P79: =SUM(P65:P78) -> 200000 | Q79: =SUM(Q65:Q78) -> 0 | R79: =SUM(R65:R78) -> 4605772.4 | T79: =SUM(T65:T78) -> 630000 | U79: =SUM(U65:U78) -> 662885.09 | V79: =SUM(V65:V78) -> 538.022 | W79: =SUM(W65:W78) -> 114640.04 | X79: =SUM(X65:X78) -> 1408063.2 | Y79: =SUM(Y65:Y78) -> 2957372.4 | Z79: =SUM(Z65:Z78) -> 3197709.3
B81: STUDIES
A82: 1 | B82: DR ASIMIYU G. ABIOLA | C82: DIRECTOR POST GRADUATE | D82: 17(9) | E82: 81740.02 | G82: =E82*300% -> 245220.06 | H82: =E82*7.5% -> 6130.5015 | I82: 80244.38 | J82: =E82*50% -> 40870.01 | K82: =E82*350% -> 286090.07 | L82: =E82*100% -> 81740.02 | M82: =200000 -> 200000 | O82: =E82*10% -> 8174.002 | P82: 20000 | Q82: 0 | R82: =SUM(E82:Q82) -> 1050209.1 | T82: 250000 | U82: =0 -> 0 | V82: 0 | W82: 52776.63 | X82: =W82+V82+U82+T82+S82 -> 302776.63 | Y82: 747432.43 | Z82: =R82-X82 -> 747432.43
A83: 2 | B83: USMAN WALI | C83: SENIOR RESEARCH FELLOW | D83: 15 (7) | E83: 31018.84 | G83: =E83*300% -> 93056.52 | H83: =E83*7.5% -> 2326.413 | I83: 40122.19 | J83: =E83*50% -> 15509.42 | K83: =E83*350% -> 108565.94 | L83: =E83*100% -> 31018.84 | M83: =160000 -> 160000 | O83: =E83*10% -> 3101.884 | P83: 20000 | Q83: 0 | R83: =SUM(E83:Q83) -> 504720.05 | V83: 0 | W83: =15548.33 -> 15548.33 | X83: =W83+V83+U83+T83+S83 -> 15548.33 | Y83: 489171.72 | Z83: =R83-X83 -> 489171.72
A84: 3 | B84: MOSHOOD TOSHO AMUDA | C84: MANAGER, EXAMS & RECORDS | D84: 15 (7) | E84: 31018.84 | G84: =E84*300% -> 93056.52 | H84: =E84*7.5% -> 2326.413 | I84: 40122.19 | J84: =E84*50% -> 15509.42 | K84: =E84*350% -> 108565.94 | L84: =E84*100% -> 31018.84 | M84: =160000 -> 160000 | O84: =E84*10% -> 3101.884 | P84: 20000 | Q84: 0 | R84: =SUM(E84:Q84) -> 504720.05 | V84: 0 | W84: =15548.33 -> 15548.33 | X84: =W84+V84+U84+T84+S84 -> 15548.33 | Y84: 489171.72 | Z84: =R84-X84 -> 489171.72
A85: 4 | B85: UZODINMA EMMANUEL EZENWA | C85: RESEARCH FELLOW II | D85: 13(9) | E85: 24741.26 | G85: =E85*300% -> 74223.78 | H85: =E85*7.5% -> 1855.5945 | I85: 0 | J85: =E85*50% -> 12370.63 | K85: =E85*350% -> 86594.41 | L85: =E85*100% -> 24741.26 | M85: =120000 -> 120000 | O85: =E85*10% -> 2474.126 | P85: 15000 | Q85: 0 | R85: =SUM(E85:Q85) -> 362001.06 | T85: =0 -> 0 | U85: =0 -> 0 | V85: ='[2]April 2022'!$H$42 -> 618.5315 | W85: =7709.76 -> 7709.76 | X85: =W85+V85+U85+T85+S85 -> 8328.2915 | Y85: 353694.02 | Z85: =R85-X85 -> 353672.77
A86: 5 | B86: IGWE STACY | C86: PROGRAMME OFFICER | D86: 10(7) | E86: 17286.33 | G86: =E86*300% -> 51858.99 | H86: =E86*7.5% -> 1296.4748 | J86: =E86*50% -> 8643.165 | K86: =E86*350% -> 60502.155 | L86: =E86*100% -> 17286.33 | M86: =100000 -> 100000 | O86: =E86*10% -> 1728.633 | P86: 10000 | R86: =SUM(E86:Q86) -> 268602.08 | T86: =50000 -> 50000 | U86: =50000 -> 50000 | W86: 3369.51 | X86: =W86+V86+U86+T86+S86 -> 103369.51 | Y86: 165232.57 | Z86: =R86-X86 -> 165232.57
A87: 6 | B87: DARE SHEU MAGBON | C87: ASSIST. PG | D87: 8(9) | E87: 13112.16 | G87: =E87*300% -> 39336.48 | H87: =E87*7.5% -> 983.412 | J87: =E87*50% -> 6556.08 | K87: =E87*350% -> 45892.56 | L87: =E87*100% -> 13112.16 | M87: =100000 -> 100000 | O87: =E87*10% -> 1311.216 | P87: 10000 | R87: =SUM(E87:Q87) -> 230304.07 | T87: =30000+20000 -> 50000 | U87: 0 | W87: 1484.37 | X87: =W87+V87+U87+T87+S87 -> 51484.37 | Y87: 178819.7 | Z87: =R87-X87 -> 178819.7
A88: 7 | B88: MOHAMMED BELLO | C88: RESEARCH ASSITANT PG | D88: 8(7) | E88: 12351.94 | G88: =E88*300% -> 37055.82 | H88: =E88*7.5% -> 926.3955 | J88: =E88*50% -> 6175.97 | K88: =E88*350% -> 43231.79 | L88: =E88*100% -> 12351.94 | M88: =100000 -> 100000 | O88: =E88*10% -> 1235.194 | P88: 10000 | R88: =SUM(E88:Q88) -> 223329.05 | T88: =0 -> 0 | U88: =26666.67 -> 26666.67 | W88: 1484.37 | X88: =W88+V88+U88+T88+S88 -> 28151.04 | Y88: 195178.01 | Z88: =R88-X88 -> 195178.01
B89: TOTAL | C89: 7 | E89: =SUM(E82:E88) -> 211269.39 | G89: =SUM(G82:G88) -> 633808.17 | H89: =SUM(H82:H88) -> 15845.204 | I89: =SUM(I82:I88) -> 160488.76 | J89: =SUM(J82:J88) -> 105634.7 | K89: =SUM(K82:K88) -> 739442.86 | L89: =SUM(L82:L88) -> 211269.39 | M89: =SUM(M82:M88) -> 940000 | O89: =SUM(O82:O88) -> 21126.939 | P89: =SUM(P82:P88) -> 105000 | Q89: =SUM(Q82:Q88) -> 0 | R89: =SUM(R82:R88) -> 3143885.4 | T89: =SUM(T82:T88) -> 350000 | U89: =SUM(U82:U88) -> 76666.67 | V89: =SUM(V82:V88) -> 618.5315 | W89: =SUM(W82:W88) -> 97921.3 | X89: =SUM(X82:X88) -> 525206.5 | Y89: =SUM(Y82:Y88) -> 2618700.2 | Z89: =SUM(Z82:Z88) -> 2618678.9
B91: ECONOMIC DEV. AND SOCIAL RESEARCH
A92: 1 | B92: DR ASEMOTA OMOROGBE JOSEPH | C92: Ag. DEPUTY DIRECTOR, ECO & SOC DEV DEPT | D92: 16(8) | E92: 41157.69 | G92: =E92*300% -> 123473.07 | H92: =E92*7.5% -> 3086.8268 | I92: 40122.19 | J92: =E92*50% -> 20578.845 | K92: =E92*350% -> 144051.92 | L92: =E92*100% -> 41157.69 | M92: =180000 -> 180000 | O92: =E92*10% -> 4115.769 | P92: 20000 | R92: =SUM(E92:Q92) -> 617744 | W92: =21618.09 -> 21618.09 | X92: =W92+V92+U92+T92+S92 -> 21618.09 | Y92: 596125.91 | Z92: =R92-X92 -> 596125.91
A93: 2 | B93: TERFA WILLIAMS ABRAHAM | C93: SNR RESEARCH FELLOW | D93: 15(9) | E93: 33507.5 | G93: =E93*300% -> 100522.5 | H93: =E93*7.5% -> 2513.0625 | I93: =40122.19 -> 40122.19 | J93: =E93*50% -> 16753.75 | K93: =E93*350% -> 117276.25 | L93: =E93*100% -> 33507.5 | M93: =160000 -> 160000 | O93: =E93*10% -> 3350.75 | P93: 20000 | R93: =SUM(E93:Q93) -> 527553.5 | W93: =15548.33 -> 15548.33 | X93: =W93+V93+U93+T93+S93 -> 15548.33 | Y93: 512005.17 | Z93: =R93-X93 -> 512005.17
A94: 3 | B94: DR AUGUSTINE C. OSIGWE | C94: SNR RESEARCH FELLOW | D94: 15(9) | E94: 33507.5 | G94: =E94*300% -> 100522.5 | H94: =E94*7.5% -> 2513.0625 | I94: =40122.19 -> 40122.19 | J94: =E94*50% -> 16753.75 | K94: =E94*350% -> 117276.25 | L94: =E94*100% -> 33507.5 | M94: =160000 -> 160000 | O94: =E94*10% -> 3350.75 | P94: 20000 | R94: =SUM(E94:Q94) -> 527553.5 | T94: =30000 -> 30000 | U94: =98750 -> 98750 | V94: ='[2]April 2022'!$H$37 -> 837.6875 | W94: =15548.33 -> 15548.33 | X94: =W94+V94+U94+T94+S94 -> 145136.02 | Y94: 382448.59 | Z94: =R94-X94 -> 382417.48
A95: 4 | B95: NGARA CHRISTOPHER OCHANJA | C95: RESEARCH FELLOW 1 | D95: 14(10) | E95: 27611.23 | G95: =E95*300% -> 82833.69 | H95: =E95*7.5% -> 2070.8422 | J95: =E95*50% -> 13805.615 | K95: =E95*350% -> 96639.305 | L95: =E95*100% -> 27611.23 | M95: 140000 | O95: =E95*10% -> 2761.123 | P95: 20000 | Q95: 0 | R95: =SUM(E95:Q95) -> 413333.04 | T95: =20000 -> 20000 | U95: =163103.59 -> 163103.59 | V95: ='[2]April 2022'!$H$44 -> 690.28075 | W95: =7709.76 -> 7709.76 | X95: =W95+V95+U95+T95+S95 -> 191503.63 | Y95: 221851.37 | Z95: =R95-X95 -> 221829.4
A96: 5 | B96: OMOJU OLUWASOLA EMMANUEL | C96: RESEARCH FELLOW I | D96: 14(9) | E96: 26732.65 | G96: =E96*300% -> 80197.95 | H96: =E96*7.5% -> 2004.9488 | J96: =E96*50% -> 13366.325 | K96: =E96*350% -> 93564.275 | L96: =E96*100% -> 26732.65 | M96: 140000 | O96: =E96*10% -> 2673.265 | P96: 20000 | R96: =SUM(E96:Q96) -> 405272.06 | T96: =50000 -> 50000 | U96: =79861.11 -> 79861.11 | W96: =7709.76 -> 7709.76 | X96: =W96+V96+U96+T96+S96 -> 137570.87 | Y96: 267701.19 | Z96: =R96-X96 -> 267701.19
A97: 6 | B97: FESTUS OSAGU NDIDI | C97: RESEARCH FELLOW I | D97: 14(7) | E97: =24975.81 -> 24975.81 | G97: =E97*300% -> 74927.43 | H97: =E97*7.5% -> 1873.1858 | J97: =E97*50% -> 12487.905 | K97: =E97*350% -> 87415.335 | L97: =E97*100% -> 24975.81 | M97: 140000 | O97: =E97*10% -> 2497.581 | P97: 20000 | R97: =SUM(E97:Q97)*12/30 -> 155661.22 | W97: =7709.76 -> 7709.76 | X97: =W97+V97+U97+T97+S97 -> 7709.76 | Z97: =R97-X97 -> 147951.46
A98: 7 | B98: IBE EZECHI CYRIACUS | C98: RESEARCH FELLOW II | D98: 13(9) | E98: 24741.26 | G98: =E98*300% -> 74223.78 | H98: =E98*7.5% -> 1855.5945 | I98: 0 | J98: =E98*50% -> 12370.63 | K98: =E98*350% -> 86594.41 | L98: =E98*100% -> 24741.26 | M98: =120000 -> 120000 | O98: =E98*10% -> 2474.126 | P98: 15000 | Q98: 0 | R98: =SUM(E98:Q98) -> 362001.06 | T98: =50000 -> 50000 | W98: =7709.76 -> 7709.76 | X98: =W98+V98+U98+T98+S98 -> 57709.76 | Y98: 257624.65 | Z98: =R98-X98 -> 304291.3
A99: 8 | B99: OSIKHEN LEO IGBANOI | C99: RESEARCH FELLOW 11 | D99: 13(8) | E99: 23891.12 | G99: =E99*300% -> 71673.36 | H99: =E99*7.5% -> 1791.834 | I99: 0 | J99: =E99*50% -> 11945.56 | K99: =E99*350% -> 83618.92 | L99: =E99*100% -> 23891.12 | M99: =120000 -> 120000 | O99: =E99*10% -> 2389.112 | P99: 15000 | Q99: 0 | R99: =SUM(E99:Q99) -> 354201.03 | W99: =7709.76 -> 7709.76 | X99: =W99+V99+U99+T99+S99 -> 7709.76 | Y99: 227229.12 | Z99: =R99-X99 -> 346491.27
A100: 9 | B100: OKUNGBOWA OSARETIN GODSPOWER | C100: RESEARCH FELLOW 11 | D100: 13(8) | E100: 23891.12 | G100: =E100*300% -> 71673.36 | H100: =E100*7.5% -> 1791.834 | I100: 0 | J100: =E100*50% -> 11945.56 | K100: =E100*350% -> 83618.92 | L100: =E100*100% -> 23891.12 | M100: =120000 -> 120000 | O100: =E100*10% -> 2389.112 | P100: 15000 | Q100: 0 | R100: =SUM(E100:Q100) -> 354201.03 | T100: =100000 -> 100000 | W100: =7709.76 -> 7709.76 | X100: =W100+V100+U100+T100+S100 -> 107709.76 | Y100: 246491.27 | Z100: =R100-X100 -> 246491.27
A101: 10 | B101: YUSUF IBRAHIM | C101: PRINCIPAL RESEARCH OFFICER | D101: 12(7) | E101: =20749 -> 20749 | G101: =E101*300% -> 62247 | H101: =E101*7.5% -> 1556.175 | I101: 0 | J101: =E101*50% -> 10374.5 | K101: =E101*350% -> 72621.5 | L101: =E101*100% -> 20749 | M101: =110000 -> 110000 | O101: =E101*10% -> 2074.9 | P101: 15000 | Q101: 0 | R101: =SUM(E101:Q101)*9/30 -> 94611.623 | W101: =3369.51 -> 3369.51 | X101: =W101+V101+U101+T101+S101 -> 3369.51 | Z101: =R101-X101 -> 91242.113
B102: TOTAL | C102: 10 | E102: =SUM(E92:E101) -> 280764.88 | G102: =SUM(G92:G101) -> 842294.64 | H102: =SUM(H92:H101) -> 21057.366 | I102: =SUM(I92:I101) -> 120366.57 | J102: =SUM(J92:J101) -> 140382.44 | K102: =SUM(K92:K101) -> 982677.08 | L102: =SUM(L92:L101) -> 280764.88 | M102: =SUM(M92:M101) -> 1390000 | O102: =SUM(O92:O101) -> 28076.488 | P102: =SUM(P92:P101) -> 180000 | Q102: =SUM(Q92:Q101) -> 0 | R102: =SUM(R92:R101) -> 3812132.1 | T102: =SUM(T92:T101) -> 250000 | U102: =SUM(U92:U101) -> 341714.7 | V102: =SUM(V92:V101) -> 1527.9682 | W102: =SUM(W92:W101) -> 102342.82 | X102: =SUM(X92:X101) -> 695585.49 | Y102: =SUM(Y92:Y101) -> 2711477.3 | Z102: =SUM(Z92:Z101) -> 3116546.6
B104: TRAINING AND INTERNATIONAL COOP
A105: 1 | B105: REKIYA IBRAHIM ATTAH | C105: DEPUTY DIRECTOR TRAINING | D105: 16(8) | E105: 41157.69 | G105: =E105*300% -> 123473.07 | H105: =E105*7.5% -> 3086.8268 | I105: 40122.19 | J105: =E105*50% -> 20578.845 | K105: =E105*350% -> 144051.92 | L105: =E105*100% -> 41157.69 | N105: =90000 -> 90000 | O105: =E105*10% -> 4115.769 | P105: 20000 | R105: =SUM(E105:Q105) -> 527744 | U105: =0 -> 0 | W105: =21618.09 -> 21618.09 | X105: =W105+V105+U105+T105+S105 -> 21618.09 | Y105: 506125.91 | Z105: =R105-X105 -> 506125.91
A106: 2 | B106: DR FRANCIS NDUM OJIE | C106: CHIEF TRAINING OFFICER | D106: 14(9) | E106: 26732.65 | G106: =E106*300% -> 80197.95 | H106: =E106*7.5% -> 2004.9488 | J106: =E106*50% -> 13366.325 | K106: =E106*350% -> 93564.275 | L106: =E106*100% -> 26732.65 | N106: =70000 -> 70000 | O106: =E106*10% -> 2673.265 | P106: 20000 | R106: =SUM(E106:Q106) -> 335272.06 | V106: ='[2]April 2022'!$H$54 -> 668.31625 | W106: =7709.76 -> 7709.76 | X106: =W106+V106+U106+T106+S106 -> 8378.0763 | Y106: 326915.95 | Z106: =R106-X106 -> 326893.99
A107: 3 | B107: ABUBAKAR MOHAMMED BASHIR | C107: ASST. CHIEF TRAINING OFFICER | D107: 13(8) | E107: 23891.12 | G107: =E107*300% -> 71673.36 | H107: =E107*7.5% -> 1791.834 | I107: 0 | J107: =E107*50% -> 11945.56 | K107: =E107*350% -> 83618.92 | L107: =E107*100% -> 23891.12 | N107: 70000 | O107: =E107*10% -> 2389.112 | P107: 15000 | Q107: 0 | R107: =SUM(E107:Q107) -> 304201.03 | W107: =7709.76 -> 7709.76 | X107: =W107+V107+U107+T107+S107 -> 7709.76 | Y107: 296491.27 | Z107: =R107-X107 -> 296491.27
A108: 4 | B108: OKECHUKWU UCHENNA HULDA | C108: TRAINING OFFICER | D108: 10(11) | E108: 19276.95 | G108: =E108*300% -> 57830.85 | H108: =E108*7.5% -> 1445.7713 | J108: =E108*50% -> 9638.475 | K108: =E108*350% -> 67469.325 | L108: =E108*100% -> 19276.95 | N108: =60000 -> 60000 | O108: =E108*10% -> 1927.695 | P108: 10000 | R108: =SUM(E108:Q108) -> 246866.02 | T108: =5000 -> 5000 | U108: =64806.29 -> 64806.29 | W108: 3369.51 | X108: =W108+V108+U108+T108+S108 -> 73175.8 | Y108: 173690.22 | Z108: =R108-X108 -> 173690.22
B109: TOTAL | C109: 4 | E109: 111058.41 | G109: =SUM(G105:G108) -> 333175.23 | H109: =SUM(H105:H108) -> 8329.3808 | I109: =SUM(I105:I108) -> 40122.19 | J109: =SUM(J105:J108) -> 55529.205 | K109: =SUM(K105:K108) -> 388704.43 | L109: =SUM(L105:L108) -> 111058.41 | N109: =SUM(N105:N108) -> 290000 | O109: =SUM(O105:O108) -> 11105.841 | P109: =SUM(P105:P108) -> 65000 | Q109: =SUM(Q105:Q108) -> 0 | R109: =SUM(R105:R108) -> 1414083.1 | T109: =SUM(T105:T108) -> 5000 | U109: =SUM(U105:U108) -> 64806.29 | V109: =SUM(V105:V108) -> 668.31625 | W109: =SUM(W105:W108) -> 40407.12 | X109: =SUM(X105:X108) -> 110881.73 | Y109: 1303223.3 | Z109: =SUM(Z105:Z108) -> 1303201.4
...

Sheet List
B3: STAFF PAYROLL FOR THE MONTH OF APRIL 2022
E4: ='[1]FEB 08'!E8/'[1]FEB 08'!M8 -> 0.22 | H4: ='[1]FEB 08'!F8/'[1]FEB 08'!Q8 -> 0.3
B5: STAFF NAME | T5: DEDUCTIONS | Z5: NET SALARY
C6: DESIGNATION | D6: SALARY | E6: BASIC | L6: MOTOR/ | M6: RESEARCH | N6: HARDSHIP | O6: LEAVE | P6: OUT FIT | Q6: LEGISLATIVE | R6: GROSS | Y6: MARCH,2022 | Z6: APRIL,2022
D7: LEVEL | E7: SALARY | F7: SALARY/ALLOWCE AREARS | G7: RENT | H7: UTILITY | I7: DOMESTIC | J7: ENTERT. | K7: FURNIT. | L7: FUEL | M7: ALLOWANCE | N7: ALLOWANCE | O7: ALLCE | P7: ALLCE | Q7: DUTY ALLCE | R7: SALARY | S7: AUCTION | T7: COOP SOCIETY | U7: COOP. LOAN RECOVERY | V7: NHF DEDUCTION | W7: PAYE | X7: TOTAL
A8: S/N | B8: DG OFFICE | E8: N | H8: N | R8: N | W8: N
A9: 1 | B9: PROF. ABUBAKAR O. SULAIMAN | C9: DIRECTOR GENERAL | D9: CONSOL | E9: 160488.75 | G9: 320977.5 | H9: 48146.63 | I9: 120366.57 | J9: 72219.94 | K9: 0 | L9: 120366.57 | M9: =250000 -> 250000 | O9: 16048.88 | P9: 25000 | Q9: 25235 | R9: =Q9+P9+O9+N9+M9+L9+K9+J9+I9+H9+G9+F9+E9 -> 1158849.8 | W9: 113176.97 | X9: =W9+V9+U9+T9+S9 -> 113176.97 | Y9: 1045672.9 | Z9: =R9-X9 -> 1045672.9
A10: 2 | B10: DR ADEYEMI AKEEB FAJINGBESI | C10: DIR. SPECIAL DUTIES, DG OFFICE | D10: 17(9) | E10: 81740.02 | G10: =E10*300% -> 245220.06 | H10: =E10*7.5% -> 6130.5015 | I10: 80244.38 | J10: =E10*50% -> 40870.01 | K10: =E10*350% -> 286090.07 | L10: =E10*100% -> 81740.02 | M10: =200000 -> 200000 | O10: =E10*10% -> 8174.002 | P10: 20000 | Q10: 0 | R10: =Q10+P10+O10+N10+M10+L10+K10+J10+I10+H10+G10+F10+E10 -> 1050209.1 | T10: 200000 | U10: =59722.22 -> 59722.22 | V10: ='[2]April 2022'!$H$34 -> 2043.5005 | W10: 52776.63 | X10: =W10+V10+U10+T10+S10 -> 314542.35 | Y10: 735666.71 | Z10: =R10-X10 -> 735666.71
A11: 3 | B11: DR JAKE DABANG DAN AZUMI | C11: DEPUTY DIRECTOR TRAINING | D11: 16(8) | E11: 41157.69 | G11: =E11*300% -> 123473.07 | H11: =E11*7.5% -> 3086.8268 | I11: 40122.19 | J11: =E11*50% -> 20578.845 | K11: =E11*350% -> 144051.92 | L11: =E11*100% -> 41157.69 | M11: =180000 -> 180000 | O11: =E11*10% -> 4115.769 | P11: 20000 | Q11: 150000 | R11: =Q11+P11+O11+N11+M11+L11+K11+J11+I11+H11+G11+F11+E11 -> 767744 | V11: ='[2]April 2022'!$H$26 -> 1028.9423 | W11: =21618.09 -> 21618.09 | X11: =W11+V11+U11+T11+S11 -> 22647.032 | Y11: 745134.35 | Z11: =R11-X11 -> 745096.96
A12: 4 | B12: DR ABDULSALAM NASIRU NAEEM | C12: SA ACADEMICS | D12: 16(8) | E12: 41157.69 | G12: =E12*300% -> 123473.07 | H12: =E12*7.5% -> 3086.8268 | I12: 40122.19 | J12: =E12*50% -> 20578.845 | K12: =E12*350% -> 144051.92 | L12: =E12*100% -> 41157.69 | M12: =180000 -> 180000 | O12: =E12*10% -> 4115.769 | P12: 20000 | Q12: =100000 -> 100000 | R12: =Q12+P12+O12+N12+M12+L12+K12+J12+I12+H12+G12+F12+E12 -> 717744 | W12: =21618.09 -> 21618.09 | X12: =W12+V12+U12+T12+S12 -> 21618.09 | Y12: 696125.91 | Z12: =R12-X12 -> 696125.91
A13: 5 | B13: RAHEEM USMAN AYIGORO | C13: SA-INFRASTRUCTURE | D13: 16 (8) | E13: 41157.69 | G13: =E13*300% -> 123473.07 | H13: =E13*7.5% -> 3086.8268 | I13: 40122.19 | J13: =E13*50% -> 20578.845 | K13: =E13*350% -> 144051.92 | L13: =E13*100% -> 41157.69 | N13: =90000 -> 90000 | O13: =E13*10% -> 4115.769 | P13: 20000 | Q13: 0 | R13: =Q13+P13+O13+N13+M13+L13+K13+J13+I13+H13+G13+F13+E13 -> 527744 | T13: =100000+2000 -> 102000 | W13: =21618.09 -> 21618.09 | X13: =W13+V13+U13+T13+S13 -> 123618.09 | Y13: 506125.91 | Z13: =R13-X13 -> 404125.91
A14: 6 | B14: AKINSANMI ADEJOKE OLUKEMI | C14: HEAD INFORMATION/PROTOCOL | D14: 15(9) | E14: 33507.5 | G14: =E14*300% -> 100522.5 | H14: =E14*7.5% -> 2513.0625 | I14: 40122.19 | J14: =E14*50% -> 16753.75 | K14: =E14*350% -> 117276.25 | L14: =E14*100% -> 33507.5 | N14: =80000 -> 80000 | O14: =E14*10% -> 3350.75 | P14: 20000 | Q14: =100000 -> 100000 | R14: =Q14+P14+O14+N14+M14+L14+K14+J14+I14+H14+G14+F14+E14 -> 547553.5 | T14: =0 -> 0 | U14: 0 | V14: ='[2]April 2022'!$H$25 -> 837.6875 | W14: 15548.33 | X14: =W14+V14+U14+T14+S14 -> 16386.018 | Y14: 531167.48 | Z14: =R14-X14 -> 531167.48
A15: 7 | B15: DR IKEME ARTHUR J.O | C15: SNR RESEARCH FELLOW | D15: 15(9) | E15: 33507.5 | G15: =E15*300% -> 100522.5 | H15: =E15*7.5% -> 2513.0625 | I15: 40122.19 | J15: =E15*50% -> 16753.75 | K15: =E15*350% -> 117276.25 | L15: =E15*100% -> 33507.5 | N15: =80000 -> 80000 | O15: =E15*10% -> 3350.75 | P15: 20000 | Q15: 0 | R15: =Q15+P15+O15+N15+M15+L15+K15+J15+I15+H15+G15+F15+E15 -> 447553.5 | T15: =50000 -> 50000 | U15: =160416.67 -> 160416.67 | V15: ='[3]DECEMBER 2019'!$H$38 -> 837.6875 | W15: 15548.33 | X15: =W15+V15+U15+T15+S15 -> 226802.69 | Y15: 220750.82 | Z15: =R15-X15 -> 220750.82
A16: 8 | B16: MOSHOOD M. OLALERE | C16: MANAGER ADMIN DG's OFFICE | D16: 15(9) | E16: 33507.5 | G16: =E16*300% -> 100522.5 | H16: =E16*7.5% -> 2513.0625 | I16: 40122.19 | J16: =E16*50% -> 16753.75 | K16: =E16*350% -> 117276.25 | L16: =E16*100% -> 33507.5 | N16: =80000 -> 80000 | O16: =E16*10% -> 3350.75 | P16: 20000 | Q16: 0 | R16: =Q16+P16+O16+N16+M16+L16+K16+J16+I16+H16+G16+F16+E16 -> 447553.5 | T16: =20000 -> 20000 | U16: =179017.51 -> 179017.51 | V16: ='[3]DECEMBER 2019'!$H$35 -> 837.6875 | W16: 15548.33 | X16: =W16+V16+U16+T16+S16 -> 215403.53 | Y16: 232149.97 | Z16: =R16-X16 -> 232149.97
A17: 9 | B17: ANDRAWUS MUSA | C17: ASST. DIRECTOR, STORE | D17: 15(9) | E17: 33507.5 | G17: =E17*300% -> 100522.5 | H17: =E17*7.5% -> 2513.0625 | I17: =40122.19 -> 40122.19 | J17: =E17*50% -> 16753.75 | K17: =E17*350% -> 117276.25 | L17: =E17*100% -> 33507.5 | N17: =80000 -> 80000 | O17: =E17*10% -> 3350.75 | P17: 20000 | Q17: 0 | R17: =SUM(E17:Q17) -> 447553.5 | T17: =50000 -> 50000 | U17: =90000 -> 90000 | V17: ='[2]April 2022'!$H$28 -> 837.6875 | W17: =15548.33 -> 15548.33 | X17: =W17+V17+U17+T17+S17 -> 156386.02 | Y17: 291198.59 | Z17: =R17-X17 -> 291167.48
A18: 10 | B18: AYOBOLU OLAJIDE OLUFUNSHO | C18: ASST.DIR., INFORMATION | D18: 15 (7) | E18: 31018.84 | G18: =E18*300% -> 93056.52 | H18: =E18*7.5% -> 2326.413 | I18: 40122.19 | J18: =E18*50% -> 15509.42 | K18: =E18*350% -> 108565.94 | L18: =E18*100% -> 31018.84 | N18: =80000 -> 80000 | O18: =E18*10% -> 3101.884 | P18: 20000 | Q18: 0 | R18: =Q18+P18+O18+N18+M18+L18+K18+J18+I18+H18+G18+F18+E18 -> 424720.05 | T18: =50000 -> 50000 | U18: =59583.33 -> 59583.33 | W18: 15548.33 | X18: =W18+V18+U18+T18+S18 -> 125131.66 | Y18: 299588.39 | Z18: =R18-X18 -> 299588.39
A19: 11 | B19: HUSSEIN EGYE MUSA | C19: CHIEF PROTOCOL OFFICER | D19: 14(9) | E19: 26732.65 | G19: =E19*300% -> 80197.95 | H19: =E19*7.5% -> 2004.9488 | J19: =E19*50% -> 13366.325 | K19: =E19*350% -> 93564.275 | L19: =E19*100% -> 26732.65 | N19: =70000 -> 70000 | O19: =E19*10% -> 2673.265 | P19: 20000 | Q19: 50000 | R19: =Q19+P19+O19+N19+M19+L19+K19+J19+I19+H19+G19+F19+E19 -> 385272.06 | T19: 50000 | U19: =150000 -> 150000 | V19: 0 | W19: 7709.76 | X19: =W19+V19+U19+T19+S19 -> 207709.76 | Y19: 177562.3 | Z19: =R19-X19 -> 177562.3
A20: 12 | B20: DONALD E. MKPANAM | C20: CHIEF ICT OFFICER | D20: 14(9) | E20: 26732.65 | G20: =E20*300% -> 80197.95 | H20: =E20*7.5% -> 2004.9488 | J20: =E20*50% -> 13366.325 | K20: =E20*350% -> 93564.275 | L20: =E20*100% -> 26732.65 | N20: =70000 -> 70000 | O20: =E20*10% -> 2673.265 | P20: 20000 | Q20: 0 | R20: =Q20+P20+O20+N20+M20+L20+K20+J20+I20+H20+G20+F20+E20 -> 335272.06 | V20: ='[2]April 2022'!$H$27 -> 668.31625 | W20: 7709.76 | X20: =W20+V20+U20+T20+S20 -> 8378.0763 | Y20: 326903.82 | Z20: =R20-X20 -> 326893.99
A21: 13 | B21: JOY HARUNA MAKERI | C21: RESEARCH FELLOW 1 TRAINING | D21: 14(9) | E21: 26732.65 | G21: =E21*300% -> 80197.95 | H21: =E21*7.5% -> 2004.9488 | J21: =E21*50% -> 13366.325 | K21: =E21*350% -> 93564.275 | L21: =E21*100% -> 26732.65 | M21: =140000 -> 140000 | O21: =E21*10% -> 2673.265 | P21: 20000 | Q21: =50000+100000 -> 150000 | R21: =Q21+P21+O21+N21+M21+L21+K21+J21+I21+H21+G21+F21+E21 -> 555272.06 | W21: =7709.76 -> 7709.76 | X21: =W21+V21+U21+T21+S21 -> 7709.76 | Y21: 547562.3 | Z21: =R21-X21 -> 547562.3
A22: 14 | B22: ALI ABDULLAHI | C22: ASST. CHIEF ICT OFFICER | D22: 13(11) | E22: 26339.3 | G22: =E22*300% -> 79017.9 | H22: =E22*7.5% -> 1975.4475 | I22: 0 | J22: =E22*50% -> 13169.65 | K22: =E22*350% -> 92187.55 | L22: =E22*100% -> 26339.3 | N22: =70000 -> 70000 | O22: =E22*10% -> 2633.93 | P22: 15000 | Q22: =0 -> 0 | R22: =Q22+P22+O22+N22+M22+L22+K22+J22+I22+H22+G22+F22+E22 -> 326663.08 | W22: =7709.76 -> 7709.76 | X22: =W22+V22+U22+T22+S22 -> 7709.76 | Y22: 318953.32 | Z22: =R22-X22 -> 318953.32
A23: 15 | B23: MARIAM MOHAMMED BELLO | C23: SA- SPECIAL DUTIES | D23: 13 (7) | E23: =39662.25 -> 39662.25 | G23: =E23*300% -> 118986.75 | H23: =E23*7.5% -> 2974.6687 | I23: 0 | J23: =E23*50% -> 19831.125 | K23: =E23*350% -> 138817.88 | L23: =E23*100% -> 39662.25 | N23: =90000 -> 90000 | O23: =E23*10% -> 3966.225 | P23: 15000 | Q23: =100000+100000 -> 200000 | R23: =Q23+P23+O23+N23+M23+L23+K23+J23+I23+H23+G23+F23+E23 -> 668901.14 | W23: 21618.09 | X23: =W23+V23+U23+T23+S23 -> 21618.09 | Y23: 489003.27 | Z23: =R23-X23 -> 647283.05
A24: 16 | B24: PERCY TERFA GBAHABO | C24: HEAD, NILDS LIAISON OFFICE | D24: 13(8) | E24: 23891.12 | G24: =E24*300% -> 71673.36 | H24: =E24*7.5% -> 1791.834 | I24: 0 | J24: =E24*50% -> 11945.56 | K24: =E24*350% -> 83618.92 | L24: =E24*100% -> 23891.12 | M24: =120000 -> 120000 | O24: =E24*10% -> 2389.112 | P24: 15000 | Q24: 0 | R24: =Q24+P24+O24+N24+M24+L24+K24+J24+I24+H24+G24+F24+E24 -> 354201.03 | T24: =70000 -> 70000 | U24: =98464.26 -> 98464.26 | W24: =7709.76 -> 7709.76 | X24: =W24+V24+U24+T24+S24 -> 176174.02 | Y24: 238027.01 | Z24: =R24-X24 -> 178027.01
A25: 17 | B25: ADUGBA RICHARD TERSEER | C25: INFORMATION OFFICER | D25: 10(10) | E25: 18779.3 | G25: =E25*300% -> 56337.9 | H25: =E25*7.5% -> 1408.4475 | J25: =E25*50% -> 9389.65 | K25: =E25*350% -> 65727.55 | L25: =E25*100% -> 18779.3 | N25: =60000 -> 60000 | O25: =E25*10% -> 1877.93 | P25: 10000 | R25: =Q25+P25+O25+N25+M25+L25+K25+J25+I25+H25+G25+F25+E25 -> 242300.08 | T25: =20000 -> 20000 | U25: =111833.33 -> 111833.33 | W25: 3369.51 | X25: =W25+V25+U25+T25+S25 -> 135202.84 | Y25: 107097.24 | Z25: =R25-X25 -> 107097.24
A26: 18 | B26: CHRISTIAN MADUABUCHI ODO | C26: PRINCIPAL ICT OFFICER | D26: 12(8) | E26: =21520.88 -> 21520.88 | G26: =E26*300% -> 64562.64 | H26: =E26*7.5% -> 1614.066 | J26: =E26*50% -> 10760.44 | K26: =E26*350% -> 75323.08 | L26: =E26*100% -> 21520.88 | N26: =60000 -> 60000 | O26: =E26*10% -> 2152.088 | P26: 15000 | R26: =Q26+P26+O26+N26+M26+L26+K26+J26+I26+H26+G26+F26+E26 -> 272454.07 | T26: =20000 -> 20000 | U26: =82500 -> 82500 | V26: ='[2]April 2022'!$H$45 -> 538.022 | W26: 3369.51 | X26: =W26+V26+U26+T26+S26 -> 106407.53 | Y26: 166102.64 | Z26: =R26-X26 -> 166046.54
A27: 19 | B27: HASSANA AHMED IBRAHIM | C27: PA- TO DG | D27: 13 (7) | E27: 23074.99 | G27: =E27*300% -> 69224.97 | H27: =E27*7.5% -> 1730.6243 | J27: =E27*50% -> 11537.495 | K27: =E27*350% -> 80762.465 | L27: =E27*100% -> 23074.99 | M27: =100000 -> 100000 | O27: =E27*10% -> 2307.499 | P27: 10000 | Q27: =100000 -> 100000 | R27: =Q27+P27+O27+N27+M27+L27+K27+J27+I27+H27+G27+F27+E27 -> 421713.03 | T27: =30000 -> 30000 | V27: ='[2]April 2022'!$H$52 -> 576.87475 | W27: =7709.76 -> 7709.76 | X27: =W27+V27+U27+T27+S27 -> 38286.635 | Y27: 383558.67 | Z27: =R27-X27 -> 383426.4
A28: 20 | B28: VICTOR ASUKWO | C28: ICT OFFICER | D28: 8 (10) | E28: 13492.21 | G28: =E28*300% -> 40476.63 | H28: =E28*7.5% -> 1011.9157 | J28: =E28*50% -> 6746.105 | K28: =E28*350% -> 47222.735 | L28: =E28*100% -> 13492.21 | N28: =50000 -> 50000 | O28: =E28*10% -> 1349.221 | P28: 10000 | R28: =Q28+P28+O28+N28+M28+L28+K28+J28+I28+H28+G28+F28+E28 -> 183791.03 | W28: 1484.37 | X28: =W28+V28+U28+T28+S28 -> 1484.37 | Y28: 182306.66 | Z28: =R28-X28 -> 182306.66
A29: 21 | B29: SULEIMAN ABUBAKAR SODEEQ | C29: ASST. ADMIN. OFFICER | D29: 8(7) | E29: 12351.94 | G29: =E29*300% -> 37055.82 | H29: =E29*7.5% -> 926.3955 | J29: =E29*50% -> 6175.97 | K29: =E29*350% -> 43231.79 | L29: =E29*100% -> 12351.94 | N29: =50000 -> 50000 | O29: =E29*10% -> 1235.194 | P29: 10000 | R29: =Q29+P29+O29+N29+M29+L29+K29+J29+I29+H29+G29+F29+E29 -> 173329.05 | W29: =1484.37 -> 1484.37 | X29: =W29+V29+U29+T29+S29 -> 1484.37 | Y29: 171844.68 | Z29: =R29-X29 -> 171844.68
A30: 22 | B30: YAKUB OLUWATOYIN USMAN | C30: ASST. ADMIN. OFFICER | D30: 10(8) | E30: 17784.1 | G30: =E30*300% -> 53352.3 | H30: =E30*7.5% -> 1333.8075 | J30: =E30*50% -> 8892.05 | K30: =E30*350% -> 62244.35 | L30: =E30*100% -> 17784.1 | N30: =60000 -> 60000 | O30: =E30*10% -> 1778.41 | P30: 10000 | R30: =Q30+P30+O30+N30+M30+L30+K30+J30+I30+H30+G30+F30+E30 -> 233169.12 | T30: =10000 -> 10000 | U30: =34333.33 -> 34333.33 | W30: =1484.37 -> 1484.37 | X30: =W30+V30+U30+T30+S30 -> 45817.7 | Y30: 187351.42 | Z30: =R30-X30 -> 187351.42
A31: 23 | B31: ANTHONY EDET | C31: ASST. MGR M&E | D31: 13(9) | E31: 24741.26 | G31: =E31*300% -> 74223.78 | H31: =E31*7.5% -> 1855.5945 | I31: 0 | J31: =E31*50% -> 12370.63 | K31: =E31*350% -> 86594.41 | L31: =E31*100% -> 24741.26 | N31: =70000 -> 70000 | O31: =E31*10% -> 2474.126 | P31: 15000 | Q31: 0 | R31: =Q31+P31+O31+N31+M31+L31+K31+J31+I31+H31+G31+F31+E31 -> 312001.06 | T31: 20000 | U31: =68750 -> 68750 | V31: ='[2]April 2022'!$H$38 -> 618.5315 | W31: =7709.76 -> 7709.76 | X31: =W31+V31+U31+T31+S31 -> 97078.291 | Y31: 214944.02 | Z31: =R31-X31 -> 214922.77
A32: 24 | B32: EGUATU U. ONYEJELEM | C32: OFFICER M&E | D32: 10(10) | E32: 18779.3 | G32: =E32*300% -> 56337.9 | H32: =E32*7.5% -> 1408.4475 | J32: =E32*50% -> 9389.65 | K32: =E32*350% -> 65727.55 | L32: =E32*100% -> 18779.3 | N32: =60000 -> 60000 | O32: =E32*10% -> 1877.93 | P32: 10000 | R32: =Q32+P32+O32+N32+M32+L32+K32+J32+I32+H32+G32+F32+E32 -> 242300.08 | T32: =20000 -> 20000 | U32: =87500+43750 -> 131250 | W32: 3369.51 | X32: =W32+V32+U32+T32+S32 -> 154619.51 | Y32: 87680.567 | Z32: =R32-X32 -> 87680.567
A33: 25 | B33: ODEH SUZIE | C33: ADMIN. OFFICER, LIASION OFFICE | D33: 10(9) | E33: 18281.64 | G33: =E33*300% -> 54844.92 | H33: =E33*7.5% -> 1371.123 | J33: =E33*50% -> 9140.82 | K33: =E33*350% -> 63985.74 | L33: =E33*100% -> 18281.64 | N33: 60000 | O33: =E33*10% -> 1828.164 | P33: 10000 | R33: =Q33+P33+O33+N33+M33+L33+K33+J33+I33+H33+G33+F33+E33 -> 237734.05 | T33: =30000 -> 30000 | V33: =0 -> 0 | W33: 3369.51 | X33: =W33+V33+U33+T33+S33 -> 33369.51 | Y33: 204364.54 | Z33: =R33-X33 -> 204364.54
A34: 26 | B34: IJEOMA NKOLIKWA | C34: ASSISTANT STORES OFFICER | D34: 8(10) | E34: 13492.21 | G34: =E34*300% -> 40476.63 | H34: =E34*7.5% -> 1011.9157 | J34: =E34*50% -> 6746.105 | K34: =E34*350% -> 47222.735 | L34: =E34*100% -> 13492.21 | N34: =50000 -> 50000 | O34: =E34*10% -> 1349.221 | P34: 10000 | R34: =SUM(E34:Q34) -> 183791.03 | T34: =10000 -> 10000 | W34: 1484.37 | X34: =W34+V34+U34+T34+S34 -> 11484.37 | Y34: 172306.66 | Z34: =R34-X34 -> 172306.66
A35: 27 | B35: ABDULRAHMAN A SULAIMAN | C35: ASSISTANT STORES OFFICER | D35: 8 (9) | E35: 13112.16 | G35: =E35*300% -> 39336.48 | H35: =E35*7.5% -> 983.412 | J35: =E35*50% -> 6556.08 | K35: =E35*350% -> 45892.56 | L35: =E35*100% -> 13112.16 | N35: =50000 -> 50000 | O35: =E35*10% -> 1311.216 | P35: 10000 | R35: =SUM(E35:Q35) -> 180304.07 | T35: =20000 -> 20000 | W35: =(1484.37) -> 1484.37 | X35: =W35+V35+U35+T35+S35 -> 21484.37 | Y35: 158819.7 | Z35: =R35-X35 -> 158819.7
A36: 28 | B36: TASSNEEM IBRAHIM | C36: ASSIST. INFORMATION | D36: 8(9) | E36: 13112.16 | G36: =E36*300% -> 39336.48 | H36: =E36*7.5% -> 983.412 | J36: =E36*50% -> 6556.08 | K36: =E36*350% -> 45892.56 | L36: =E36*100% -> 13112.16 | N36: =50000 -> 50000 | O36: =E36*10% -> 1311.216 | P36: 10000 | R36: =Q36+P36+O36+N36+M36+L36+K36+J36+I36+H36+G36+F36+E36 -> 180304.07 | T36: =50000 -> 50000 | U36: =17166.67 -> 17166.67 | V36: =0 -> 0 | W36: =1484.37 -> 1484.37 | X36: =W36+V36+U36+T36+S36 -> 68651.04 | Y36: 111653.03 | Z36: =R36-X36 -> 111653.03
A37: 29 | B37: JIMOH ADEBAYO ZAKA | C37: ASST. OFFICER/COMM | D37: 8(7) | E37: 12351.94 | G37: =E37*300% -> 37055.82 | H37: =E37*7.5% -> 926.3955 | J37: =E37*50% -> 6175.97 | K37: =E37*350% -> 43231.79 | L37: =E37*100% -> 12351.94 | N37: =50000 -> 50000 | O37: =E37*10% -> 1235.194 | P37: 10000 | R37: =Q37+P37+O37+N37+M37+L37+K37+J37+I37+H37+G37+F37+E37 -> 173329.05 | T37: =50000 -> 50000 | V37: =0 -> 0 | W37: =1484.37 -> 1484.37 | X37: =W37+V37+U37+T37+S37 -> 51484.37 | Y37: 121844.68 | Z37: =R37-X37 -> 121844.68
A38: 30 | B38: HABEEBA K MUHAMMAD SALIHU | C38: ASST. OFFICER/COMM | D38: 8(7) | E38: 12351.94 | G38: =E38*300% -> 37055.82 | H38: =E38*7.5% -> 926.3955 | J38: =E38*50% -> 6175.97 | K38: =E38*350% -> 43231.79 | L38: =E38*100% -> 12351.94 | N38: =50000 -> 50000 | O38: =E38*10% -> 1235.194 | P38: 10000 | R38: =Q38+P38+O38+N38+M38+L38+K38+J38+I38+H38+G38+F38+E38 -> 173329.05 | V38: =0 -> 0 | W38: =1484.37 -> 1484.37 | X38: =W38+V38+U38+T38+S38 -> 1484.37 | Y38: 171844.68 | Z38: =R38-X38 -> 171844.68
B39: TOTAL | C39: 30 | E39: =SUM(E9:E38) -> 934067.33 | G39: =SUM(G9:G38) -> 2641713.2 | H39: =SUM(H9:H38) -> 106165.02 | I39: =SUM(I9:I38) -> 521588.47 | J39: =SUM(J9:J38) -> 459009.23 | K39: =SUM(K9:K38) -> 2707525 | L39: =SUM(L9:L38) -> 893945.15 | M39: =SUM(M9:M38) -> 1170000 | N39: =SUM(N9:N38) -> 1510000 | ... R39: =SUM(R9:R38) -> 12372655 | T39: =SUM(T9:T38) -> 872000 | U39: =SUM(U9:U38) -> 1243037.3 | V39: =SUM(V9:V38) -> 8824.9372 | W39: =SUM(W9:W38) -> 409488.93 | X39: =SUM(X9:X38) -> 2533351.2 | Y39: 9843312.2 | Z39: =SUM(Z9:Z38) -> 9839304
B41: INTERNAL AUDIT
A42: 1 | B42: OSANAIYE DAVID AKINYEMI | C42: DIRECTOR INTERNAL AUDIT | D42: 17(8) | E42: 79039.64 | G42: =E42*300% -> 237118.92 | H42: =E42*7.5% -> 5927.973 | I42: 80244.38 | J42: =E42*50% -> 39519.82 | K42: =E42*350% -> 276638.74 | L42: =E42*100% -> 79039.64 | N42: =100000 -> 100000 | O42: =E42*10% -> 7903.964 | P42: 20000 | R42: =SUM(E42:Q42) -> 925433.08 | T42: =100000 -> 100000 | W42: =(52776.63) -> 52776.63 | X42: =W42+V42+U42+T42+S42 -> 152776.63 | Y42: 772656.45 | Z42: =R42-X42 -> 772656.45
A43: 2 | B43: JAMILA ABDUL | C43: AUDITOR II | D43: 8(7) | E43: 12351.94 | G43: =E43*300% -> 37055.82 | H43: =E43*7.5% -> 926.3955 | J43: =E43*50% -> 6175.97 | K43: =E43*350% -> 43231.79 | L43: =E43*100% -> 12351.94 | N43: =50000 -> 50000 | O43: =E43*10% -> 1235.194 | P43: 10000 | R43: =(Q43+P43+O43+N43+M43+L43+K43+J43+I43+H43+G43+F43+E43)*12/30 -> 69331.62 | V43: =0 -> 0 | W43: 1484.37 | X43: =W43+V43+U43+T43+S43 -> 1484.37 | Z43: =R43-X43 -> 67847.25
C44: 2 | E44: =SUM(E42:E43) -> 91391.58 | G44: =SUM(G42:G43) -> 274174.74 | H44: =SUM(H42:H43) -> 6854.3685 | I44: =SUM(I42:I43) -> 80244.38 | J44: =SUM(J42:J43) -> 45695.79 | K44: =SUM(K42:K43) -> 319870.53 | L44: =SUM(L42:L43) -> 91391.58 | N44: =SUM(N42:N43) -> 150000 | O44: =SUM(O42:O43) -> 9139.158 | P44: =SUM(P42:P43) -> 30000 | R44: =SUM(R42:R43) -> 994764.7 | T44: =SUM(T42:T43) -> 100000 | V44: =SUM(V42:V43) -> 0 | W44: =SUM(W42:W43) -> 54261 | X44: =SUM(X42:X43) -> 154261 | Y44: =SUM(Y42:Y43) -> 772656.45 | Z44: =SUM(Z42:Z43) -> 840503.7
B46: LEG. SUPPORT SEVICES
A47: 1 | B47: PROF. EDOBA BRIGHT OMOREGBE | C47: AG. DLSS | D47: 17(9) | E47: 81740.02 | G47: =E47*300% -> 245220.06 | H47: =E47*7.5% -> 6130.5015 | I47: 80244.38 | J47: =E47*50% -> 40870.01 | K47: =E47*350% -> 286090.07 | L47: =E47*100% -> 81740.02 | M47: =200000 -> 200000 | O47: =E47*10% -> 8174.002 | P47: 20000 | R47: =SUM(E47:Q47) -> 1050209.1 | T47: =200000 -> 200000 | U47: =52500*2 -> 105000 | W47: =52776.63 -> 52776.63 | X47: =W47+V47+U47+T47+S47 -> 357776.63 | Y47: 692432.43 | Z47: =R47-X47 -> 692432.43
A48: 2 | B48: DR CLINTON JAJA | C48: SENIOR RESEARCH FELLOW | D48: 15(9) | E48: 33507.5 | G48: =E48*300% -> 100522.5 | H48: =E48*7.5% -> 2513.0625 | I48: 40122.19 | J48: =E48*50% -> 16753.75 | K48: =E48*350% -> 117276.25 | L48: =E48*100% -> 33507.5 | M48: =160000 -> 160000 | O48: =E48*10% -> 3350.75 | P48: 20000 | Q48: 0 | R48: =SUM(E48:Q48) -> 527553.5 | T48: 50000 | U48: =0 -> 0 | W48: 15548.33 | X48: =W48+V48+U48+T48+S48 -> 65548.33 | Y48: 462005.17 | Z48: =R48-X48 -> 462005.17
A49: 3 | B49: BETHEL UZOMA IHUGBA | C49: SNR RESEARCH FELLOW | D49: 15(9) | E49: 33507.5 | G49: =E49*300% -> 100522.5 | H49: =E49*7.5% -> 2513.0625 | I49: 40122.19 | J49: =E49*50% -> 16753.75 | K49: =E49*350% -> 117276.25 | L49: =E49*100% -> 33507.5 | M49: =160000 -> 160000 | O49: =E49*10% -> 3350.75 | P49: 20000 | R49: =SUM(E49:Q49) -> 527553.5 | T49: =80000+23000 -> 103000 | U49: =246905.96 -> 246905.96 | W49: 15548.33 | X49: =W49+V49+U49+T49+S49 -> 365454.29 | Y49: 162099.21 | Z49: =R49-X49 -> 162099.21
A50: 4 | B50: OGUCHE SAMUEL | C50: SNR RESEARCH FELLOW | D50: 15(8) | E50: 32263.2 | G50: =E50*300% -> 96789.6 | H50: =E50*7.5% -> 2419.74 | I50: 40122.19 | J50: =E50*50% -> 16131.6 | K50: =E50*350% -> 112921.2 | L50: =E50*100% -> 32263.2 | M50: =160000 -> 160000 | O50: =E50*10% -> 3226.32 | P50: 20000 | R50: =SUM(E50:Q50) -> 516137.05 | T50: =30000 -> 30000 | U50: =176288.88 -> 176288.88 | W50: =15548.33 -> 15548.33 | X50: =W50+V50+U50+T50+S50 -> 221837.21 | Y50: 294299.84 | Z50: =R50-X50 -> 294299.84
A51: 5 | B51: IBRAHIM USMAN | C51: RESEARCH FELLOW I | D51: 14(11) | E51: 28489.81 | G51: =E51*300% -> 85469.43 | H51: =E51*7.5% -> 2136.7357 | I51: 0 | J51: =E51*50% -> 14244.905 | K51: =E51*350% -> 99714.335 | L51: =E51*100% -> 28489.81 | M51: =140000 -> 140000 | O51: =E51*10% -> 2848.981 | P51: 20000 | Q51: 0 | R51: =SUM(E51:Q51) -> 421394.01 | V51: ='[2]April 2022'!$H$23 -> 712.24525 | W51: 7709.76 | X51: =W51+V51+U51+T51+S51 -> 8422.0053 | Y51: 412972 | Z51: =R51-X51 -> 412972
A52: 6 | B52: DR MOHAMMED O. AMALI | C52: RESEARCH FELLOW I | D52: 14(9) | E52: 26732.65 | G52: =E52*300% -> 80197.95 | H52: =E52*7.5% -> 2004.9488 | J52: =E52*50% -> 13366.325 | K52: =E52*350% -> 93564.275 | L52: =E52*100% -> 26732.65 | M52: =140000 -> 140000 | O52: =E52*10% -> 2673.265 | P52: 20000 | R52: =SUM(E52:Q52) -> 405272.06 | T52: =15000 -> 15000 | U52: =133333.34 -> 133333.34 | W52: 7709.76 | X52: =W52+V52+U52+T52+S52 -> 156043.1 | Y52: 249228.96 | Z52: =R52-X52 -> 249228.96
A53: 7 | B53: YAHAYA SHAMSU | C53: RESEARCH FELLOW 1 | D53: 14(9) | E53: 26732.65 | G53: =E53*300% -> 80197.95 | H53: =E53*7.5% -> 2004.9488 | J53: =E53*50% -> 13366.325 | K53: =E53*350% -> 93564.275 | L53: =E53*100% -> 26732.65 | M53: =140000 -> 140000 | O53: =E53*10% -> 2673.265 | P53: 20000 | R53: =SUM(E53:Q53) -> 405272.06 | V53: 0 | W53: 7709.76 | X53: =W53+V53+U53+T53+S53 -> 7709.76 | Y53: 397562.3 | Z53: =R53-X53 -> 397562.3
A54: 8 | B54: OFORDEME ADAOBI JULIA | C54: RESEARCH FELLOW 11 | D54: 13(10) | E54: 25523.45 | G54: =E54*300% -> 76570.35 | H54: =E54*7.5% -> 1914.2587 | I54: 0 | J54: =E54*50% -> 12761.725 | K54: =E54*350% -> 89332.075 | L54: =E54*100% -> 25523.45 | M54: =120000 -> 120000 | O54: =E54*10% -> 2552.345 | P54: 15000 | Q54: 0 | R54: =SUM(E54:Q54) -> 369177.65 | W54: 7709.76 | X54: =W54+V54+U54+T54+S54 -> 7709.76 | Y54: 361467.89 | Z54: =R54-X54 -> 361467.89
A55: 9 | B55: DORIS DAKDA AARON | C55: RESEARCH FELLOW II | D55: 13(9) | E55: 24741.26 | G55: =E55*300% -> 74223.78 | H55: =E55*7.5% -> 1855.5945 | J55: =E55*50% -> 12370.63 | K55: =E55*350% -> 86594.41 | L55: =E55*100% -> 24741.26 | M55: =120000 -> 120000 | O55: =E55*10% -> 2474.126 | P55: 15000 | R55: =SUM(E55:Q55) -> 362001.06 | T55: =50000+10000 -> 60000 | U55: =91666.67 -> 91666.67 | V55: ='[2]April 2022'!$H$46 -> 618.5315 | W55: =7709.76 -> 7709.76 | X55: =W55+V55+U55+T55+S55 -> 159994.96 | Y55: 202027.35 | Z55: =R55-X55 -> 202006.1
A56: 10 | B56: ZAINAB AKINDE | C56: RESEARCH OFFICER | D56: 9(7) | E56: =14736.14 -> 14736.14 | G56: =E56*300% -> 44208.42 | H56: =E56*7.5% -> 1105.2105 | J56: =E56*50% -> 7368.07 | K56: =E56*350% -> 51576.49 | L56: =E56*100% -> 14736.14 | M56: =100000 -> 100000 | O56: =E56*10% -> 1473.614 | P56: 10000 | R56: =SUM(E56:Q56)*12/30 -> 98081.634 | W56: 1484.37 | X56: =W56+V56+U56+T56 -> 1484.37 | Z56: =R56-X56 -> 96597.264
B57: TOTAL | C57: 10 | E57: =SUM(E47:E56) -> 327974.18 | F57: =SUM(F47:F56) -> 0 | G57: =SUM(G47:G56) -> 983922.54 | H57: =SUM(H47:H56) -> 24598.064 | I57: =SUM(I47:I56) -> 200610.95 | J57: =SUM(J47:J56) -> 163987.09 | K57: =SUM(K47:K56) -> 1147909.6 | L57: =SUM(L47:L56) -> 327974.18 | M57: =SUM(M47:M56) -> 1440000 | O57: =SUM(O47:O56) -> 32797.418 | P57: =SUM(P47:P56) -> 180000 | Q57: =SUM(Q47:Q56) -> 0 | R57: =SUM(R47:R56) -> 4682651.6 | T57: =SUM(T47:T56) -> 458000 | U57: =SUM(U47:U56) -> 753194.85 | V57: =SUM(V47:V56) -> 1330.7767 | W57: =SUM(W47:W56) -> 139454.79 | X57: =SUM(X47:X56) -> 1351980.4 | Y57: =SUM(Y47:Y56) -> 3234095.2 | Z57: =SUM(Z47:Z56) -> 3330671.2
B59: LEGAL SERVICES
A60: 1 | B60: DR SHUIBU DANWANKA | C60: DIRECTOR LEGAL SERVICES | D60: 17(9) | E60: 81740.02 | G60: =E60*300% -> 245220.06 | H60: =E60*7.5% -> 6130.5015 | I60: 80244.38 | J60: =E60*50% -> 40870.01 | K60: =E60*350% -> 286090.07 | L60: =E60*100% -> 81740.02 | M60: =200000 -> 200000 | O60: =E60*10% -> 8174.002 | P60: 20000 | Q60: 0 | R60: =SUM(E60:Q60) -> 1050209.1 | V60: 0 | W60: 52776.63 | X60: =W60+V60+U60+T60+S60 -> 52776.63 | Y60: 997432.43 | Z60: =R60-X60 -> 997432.43
A61: 2 | B61: ABDULSALAM BAKO | C61: MANAGER, LEGAL SERVICES | D61: 15 (8) | E61: 32263.2 | G61: =E61*300% -> 96789.6 | H61: =E61*7.5% -> 2419.74 | I61: 40122.19 | J61: =E61*50% -> 16131.6 | K61: =E61*350% -> 112921.2 | L61: =E61*100% -> 32263.2 | N61: =80000 -> 80000 | O61: =E61*10% -> 3226.32 | P61: 20000 | Q61: 0 | R61: =SUM(E61:Q61) -> 436137.05 | T61: =50000 -> 50000 | U61: =95000 -> 95000 | V61: 0 | W61: =15548.33 -> 15548.33 | X61: =W61+V61+U61+T61+S61 -> 160548.33 | Y61: 275588.72 | Z61: =R61-X61 -> 275588.72
B62: TOTAL | C62: 2 | E62: 114003.22 | G62: =SUM(G60:G61) -> 342009.66 | H62: =SUM(H60:H61) -> 8550.2415 | I62: =SUM(I60:I61) -> 120366.57 | J62: =SUM(J60:J61) -> 57001.61 | K62: =SUM(K60:K61) -> 399011.27 | L62: =SUM(L60:L61) -> 114003.22 | M62: =SUM(M60:M61) -> 200000 | N62: =SUM(N60:N61) -> 80000 | ... R62: =SUM(R60:R61) -> 1486346.1 | T62: =SUM(T60:T61) -> 50000 | U62: =SUM(U61) -> 95000 | V62: =SUM(V60:V61) -> 0 | W62: =SUM(W60:W61) -> 68324.96 | X62: =SUM(X60:X61) -> 213324.96 | Y62: 1273021.2 | Z62: =SUM(Z60:Z61) -> 1273021.2
B64: DEMOCRACY AND GOVERNANCE
A65: 1 | B65: DR. ADEWALE ADEREMI | C65: DIRECTOR, DEMOCRATIC STUDIES | D65: 17(9) | E65: 81740.02 | G65: =E65*300% -> 245220.06 | H65: =E65*7.5% -> 6130.5015 | I65: =80244.38 -> 80244.38 | J65: =E65*50% -> 40870.01 | K65: =E65*350% -> 286090.07 | L65: =E65*100% -> 81740.02 | M65: =200000 -> 200000 | O65: =E65*10% -> 8174.002 | P65: 20000 | Q65: 0 | R65: =SUM(E65:Q65) -> 1050209.1 | T65: =100000+100000 -> 200000 | W65: =52776.63 -> 52776.63 | X65: =W65+V65+U65+T65+S65 -> 252776.63 | Y65: 797432.43 | Z65: =R65-X65 -> 797432.43
A66: 2 | B66: NDANUSA MOHAMMED MANZUMA | C66: SNR RESEARCH FELLOW | D66: 15 (7) | E66: 31018.84 | G66: =E66*300% -> 93056.52 | H66: =E66*7.5% -> 2326.413 | I66: 40122.19 | J66: =E66*50% -> 15509.42 | K66: =E66*350% -> 108565.94 | L66: =E66*100% -> 31018.84 | M66: =160000 -> 160000 | O66: =E66*10% -> 3101.884 | P66: 20000 | Q66: 0 | R66: =SUM(E66:Q66) -> 504720.05 | T66: =100000 -> 100000 | U66: =131250 -> 131250 | V66: 0 | W66: =15548.33 -> 15548.33 | X66: =W66+V66+U66+T66+S66 -> 246798.33 | Y66: 257921.72 | Z66: =R66-X66 -> 257921.72
A67: 3 | B67: EMILY EDOISA IKHIDE | C67: RESEARCH FELLOW II | D67: 13(11) | E67: 26339.3 | G67: =E67*300% -> 79017.9 | H67: =E67*7.5% -> 1975.4475 | J67: =E67*50% -> 13169.65 | K67: =E67*350% -> 92187.55 | L67: =E67*100% -> 26339.3 | M67: =120000 -> 120000 | O67: =E67*10% -> 2633.93 | P67: 15000 | X67: =W67+V67+U67+T67+S67 -> 0 | Y67: 70790.749 | Z67: =R67-X67 -> 0
A68: 4 | B68: EJALONIBU GANIYU LAYI | C68: RESEARCH FELLOW 11 | D68: 13(9) | E68: 24741.26 | G68: =E68*300% -> 74223.78 | H68: =E68*7.5% -> 1855.5945 | J68: =E68*50% -> 12370.63 | K68: =E68*350% -> 86594.41 | L68: =E68*100% -> 24741.26 | M68: =120000 -> 120000 | O68: =E68*10% -> 2474.126 | P68: 15000 | R68: =SUM(E68:Q68) -> 362001.06 | T68: =110000 -> 110000 | W68: =7709.76 -> 7709.76 | X68: =W68+V68+U68+T68+S68 -> 117709.76 | Y68: 244291.3 | Z68: =R68-X68 -> 244291.3
A69: 5 | B69: LONA POLIT BONKAT | C69: RESEARCH FELLOW 11 | D69: 13(8) | E69: 23891.12 | G69: =E69*300% -> 71673.36 | H69: =E69*7.5% -> 1791.834 | I69: 0 | J69: =E69*50% -> 11945.56 | K69: =E69*350% -> 83618.92 | L69: =E69*100% -> 23891.12 | M69: =120000 -> 120000 | O69: =E69*10% -> 2389.112 | P69: 15000 | Q69: 0 | R69: =SUM(E69:Q69) -> 354201.03 | T69: =20000 -> 20000 | U69: =119444.44 -> 119444.44 | V69: =0 -> 0 | W69: 7709.76 | X69: =W69+V69+U69+T69+S69 -> 147154.2 | Y69: 207046.83 | Z69: =R69-X69 -> 207046.83
A70: 6 | B70: YUNUSA ABDULLAHI | C70: RESEARCH FELLOW 1 | D70: 14(9) | E70: 26732.65 | G70: =E70*300% -> 80197.95 | H70: =E70*7.5% -> 2004.9488 | J70: =E70*50% -> 13366.325 | K70: =E70*350% -> 93564.275 | L70: =E70*100% -> 26732.65 | M70: =140000 -> 140000 | O70: =E70*10% -> 2673.265 | P70: 20000 | R70: =SUM(E70:Q70) -> 405272.06 | T70: =10000 -> 10000 | U70: =54585.66 -> 54585.66 | W70: =7709.76 -> 7709.76 | X70: =W70+V70+U70+T70+S70 -> 72295.42 | Y70: 332976.64 | Z70: =R70-X70 -> 332976.64
A71: 7 | B71: UDEFUNA NNADOZIE PATRICK | C71: RESEARCH OFFICER | D71: 10(13) | E71: 19774.62 | G71: =E71*300% -> 59323.86 | H71: =E71*7.5% -> 1483.0965 | I71: 0 | J71: =E71*50% -> 9887.31 | K71: =E71*350% -> 69211.17 | L71: =E71*100% -> 19774.62 | M71: =100000 -> 100000 | O71: =E71*10% -> 1977.462 | P71: 10000 | Q71: 0 | R71: =SUM(E71:Q71) -> 291432.14 | T71: =10000 -> 10000 | U71: =131771.66 -> 131771.66 | W71: 3369.51 | X71: =W71+V71+U71+T71+S71 -> 145141.17 | Y71: 146290.97 | Z71: =R71-X71 -> 146290.97
A72: 8 | B72: OSOLAFIA MUHAMMAD EGYE | C72: PRINCIPAL RESEARCH OFFICER | D72: 12(8) | E72: =21520.88 -> 21520.88 | G72: =E72*300% -> 64562.64 | H72: =E72*7.5% -> 1614.066 | I72: 0 | J72: =E72*50% -> 10760.44 | K72: =E72*350% -> 75323.08 | L72: =E72*100% -> 21520.88 | M72: =110000 -> 110000 | O72: =E72*10% -> 2152.088 | P72: 15000 | Q72: 0 | R72: =SUM(E72:Q72) -> 322454.07 | T72: =10000+20000 -> 30000 | U72: =130000 -> 130000 | V72: ='[2]April 2022'!$H$41 -> 538.022 | W72: =3369.51 -> 3369.51 | X72: =W72+V72+U72+T72+S72 -> 163907.53 | Y72: 158602.64 | Z72: =R72-X72 -> 158546.54
A73: 9 | B73: SHAFIU YAHYA MIKAIL | C73: PRINCIPAL RESEARCH OFFICER | D73: 12(7) | E73: =20749 -> 20749 | G73: =E73*300% -> 62247 | H73: =E73*7.5% -> 1556.175 | I73: 0 | J73: =E73*50% -> 10374.5 | K73: =E73*350% -> 72621.5 | L73: =E73*100% -> 20749 | M73: =110000 -> 110000 | O73: =E73*10% -> 2074.9 | P73: 15000 | Q73: 0 | R73: =SUM(E73:Q73)*12/30 -> 126148.83 | W73: =3369.51 -> 3369.51 | X73: =W73+V73+U73+T73+S73 -> 3369.51 | Z73: =R73-X73 -> 122779.32
A74: 10 | B74: HASSAN YERIMA | C74: PRINCIPAL RESEARCH OFFICER | D74: 12(7) | E74: =20749 -> 20749 | G74: =E74*300% -> 62247 | H74: =E74*7.5% -> 1556.175 | I74: 0 | J74: =E74*50% -> 10374.5 | K74: =E74*350% -> 72621.5 | L74: =E74*100% -> 20749 | M74: =110000 -> 110000 | O74: =E74*10% -> 2074.9 | P74: 15000 | Q74: 0 | R74: =SUM(E74:Q74)*12/30 -> 126148.83 | W74: =3369.51 -> 3369.51 | X74: =W74+V74+U74+T74+S74 -> 3369.51 | Z74: =R74-X74 -> 122779.32
A75: 11 | B75: HAUWA PATE SADIQ | C75: PROGRAMME OFFICER | D75: 10(10) | E75: 18779.3 | G75: =E75*300% -> 56337.9 | H75: =E75*7.5% -> 1408.4475 | J75: =E75*50% -> 9389.65 | K75: =E75*350% -> 65727.55 | L75: =E75*100% -> 18779.3 | M75: =100000 -> 100000 | O75: =E75*10% -> 1877.93 | P75: 10000 | R75: =SUM(E75:Q75) -> 282300.08 | T75: =70000+20000 -> 90000 | W75: 3369.51 | X75: =W75+V75+U75+T75+S75 -> 93369.51 | Y75: 188930.57 | Z75: =R75-X75 -> 188930.57
A76: 12 | B76: ABAYOMI KAYODE QUADRI | C76: RESEARCH OFFICER | D76: 10(7) | E76: 17286.33 | G76: =E76*300% -> 51858.99 | H76: =E76*7.5% -> 1296.4748 | J76: =E76*50% -> 8643.165 | K76: =E76*350% -> 60502.155 | L76: =E76*100% -> 17286.33 | M76: =100000 -> 100000 | O76: =E76*10% -> 1728.633 | P76: 10000 | R76: =SUM(E76:Q76) -> 268602.08 | T76: =50000 -> 50000 | U76: 0 | W76: 3369.51 | X76: =W76+V76+U76+T76+S76 -> 53369.51 | Y76: 215232.57 | Z76: =R76-X76 -> 215232.57
A77: 13 | B77: NNANDI LIVINUS ATURE | C77: RESEARCH ASSISTANT | D77: 9(7) | E77: =14736.14 -> 14736.14 | F77: =21875*2 -> 43750 | G77: =E77*300% -> 44208.42 | H77: =E77*7.5% -> 1105.2105 | J77: =E77*50% -> 7368.07 | K77: =E77*350% -> 51576.49 | L77: =E77*100% -> 14736.14 | M77: =100000 -> 100000 | O77: =E77*10% -> 1473.614 | P77: 10000 | R77: =SUM(E77:Q77) -> 288954.08 | T77: =10000 -> 10000 | U77: =95833.33 -> 95833.33 | W77: 1484.37 | X77: =W77+V77+U77+T77+S77 -> 107317.7 | Y77: 116011.35 | Z77: =R77-X77 -> 181636.38
A78: 14 | B78: LUCKY AGWOM | C78: RESEARCH ASSISTANT | D78: 8(7) | E78: 12351.94 | G78: =E78*300% -> 37055.82 | H78: =E78*7.5% -> 926.3955 | J78: =E78*50% -> 6175.97 | K78: =E78*350% -> 43231.79 | L78: =E78*100% -> 12351.94 | M78: =100000 -> 100000 | O78: =E78*10% -> 1235.194 | P78: 10000 | R78: =SUM(E78:Q78) -> 223329.05 | W78: 1484.37 | X78: =W78+V78+U78+T78+S78 -> 1484.37 | Y78: 221844.68 | Z78: =R78-X78 -> 221844.68
B79: TOTAL | C79: 14 | E79: =SUM(E65:E78) -> 360410.4 | F79: =SUM(F65:F78) -> 43750 | G79: =SUM(G65:G78) -> 1081231.2 | H79: =SUM(H65:H78) -> 27030.78 | I79: =SUM(I65:I78) -> 120366.57 | J79: =SUM(J65:J78) -> 180205.2 | K79: =SUM(K65:K78) -> 1261436.4 | L79: =SUM(L65:L78) -> 360410.4 | M79: =SUM(M65:M78) -> 1690000 | O79: =SUM(O65:O78) -> 36041.04 | P79: =SUM(P65:P78) -> 200000 | Q79: =SUM(Q65:Q78) -> 0 | R79: =SUM(R65:R78) -> 4605772.4 | T79: =SUM(T65:T78) -> 630000 | U79: =SUM(U65:U78) -> 662885.09 | V79: =SUM(V65:V78) -> 538.022 | W79: =SUM(W65:W78) -> 114640.04 | X79: =SUM(X65:X78) -> 1408063.2 | Y79: =SUM(Y65:Y78) -> 2957372.4 | Z79: =SUM(Z65:Z78) -> 3197709.3
B81: STUDIES
A82: 1 | B82: DR ASIMIYU G. ABIOLA | C82: DIRECTOR POST GRADUATE | D82: 17(9) | E82: 81740.02 | G82: =E82*300% -> 245220.06 | H82: =E82*7.5% -> 6130.5015 | I82: 80244.38 | J82: =E82*50% -> 40870.01 | K82: =E82*350% -> 286090.07 | L82: =E82*100% -> 81740.02 | M82: =200000 -> 200000 | O82: =E82*10% -> 8174.002 | P82: 20000 | Q82: 0 | R82: =SUM(E82:Q82) -> 1050209.1 | T82: 250000 | U82: =0 -> 0 | V82: 0 | W82: 52776.63 | X82: =W82+V82+U82+T82+S82 -> 302776.63 | Y82: 747432.43 | Z82: =R82-X82 -> 747432.43
A83: 2 | B83: USMAN WALI | C83: SENIOR RESEARCH FELLOW | D83: 15 (7) | E83: 31018.84 | G83: =E83*300% -> 93056.52 | H83: =E83*7.5% -> 2326.413 | I83: 40122.19 | J83: =E83*50% -> 15509.42 | K83: =E83*350% -> 108565.94 | L83: =E83*100% -> 31018.84 | M83: =160000 -> 160000 | O83: =E83*10% -> 3101.884 | P83: 20000 | Q83: 0 | R83: =SUM(E83:Q83) -> 504720.05 | V83: 0 | W83: =15548.33 -> 15548.33 | X83: =W83+V83+U83+T83+S83 -> 15548.33 | Y83: 489171.72 | Z83: =R83-X83 -> 489171.72
A84: 3 | B84: MOSHOOD TOSHO AMUDA | C84: MANAGER, EXAMS & RECORDS | D84: 15 (7) | E84: 31018.84 | G84: =E84*300% -> 93056.52 | H84: =E84*7.5% -> 2326.413 | I84: 40122.19 | J84: =E84*50% -> 15509.42 | K84: =E84*350% -> 108565.94 | L84: =E84*100% -> 31018.84 | M84: =160000 -> 160000 | O84: =E84*10% -> 3101.884 | P84: 20000 | Q84: 0 | R84: =SUM(E84:Q84) -> 504720.05 | V84: 0 | W84: =15548.33 -> 15548.33 | X84: =W84+V84+U84+T84+S84 -> 15548.33 | Y84: 489171.72 | Z84: =R84-X84 -> 489171.72
A85: 4 | B85: UZODINMA EMMANUEL EZENWA | C85: RESEARCH FELLOW II | D85: 13(9) | E85: 24741.26 | G85: =E85*300% -> 74223.78 | H85: =E85*7.5% -> 1855.5945 | I85: 0 | J85: =E85*50% -> 12370.63 | K85: =E85*350% -> 86594.41 | L85: =E85*100% -> 24741.26 | M85: =120000 -> 120000 | O85: =E85*10% -> 2474.126 | P85: 15000 | Q85: 0 | R85: =SUM(E85:Q85) -> 362001.06 | T85: =0 -> 0 | U85: =0 -> 0 | V85: ='[2]April 2022'!$H$42 -> 618.5315 | W85: =7709.76 -> 7709.76 | X85: =W85+V85+U85+T85+S85 -> 8328.2915 | Y85: 353694.02 | Z85: =R85-X85 -> 353672.77
A86: 5 | B86: IGWE STACY | C86: PROGRAMME OFFICER | D86: 10(7) | E86: 17286.33 | G86: =E86*300% -> 51858.99 | H86: =E86*7.5% -> 1296.4748 | J86: =E86*50% -> 8643.165 | K86: =E86*350% -> 60502.155 | L86: =E86*100% -> 17286.33 | M86: =100000 -> 100000 | O86: =E86*10% -> 1728.633 | P86: 10000 | R86: =SUM(E86:Q86) -> 268602.08 | T86: =50000 -> 50000 | U86: =50000 -> 50000 | W86: 3369.51 | X86: =W86+V86+U86+T86+S86 -> 103369.51 | Y86: 165232.57 | Z86: =R86-X86 -> 165232.57
A87: 6 | B87: DARE SHEU MAGBON | C87: ASSIST. PG | D87: 8(9) | E87: 13112.16 | G87: =E87*300% -> 39336.48 | H87: =E87*7.5% -> 983.412 | J87: =E87*50% -> 6556.08 | K87: =E87*350% -> 45892.56 | L87: =E87*100% -> 13112.16 | M87: =100000 -> 100000 | O87: =E87*10% -> 1311.216 | P87: 10000 | R87: =SUM(E87:Q87) -> 230304.07 | T87: =30000+20000 -> 50000 | U87: 0 | W87: 1484.37 | X87: =W87+V87+U87+T87+S87 -> 51484.37 | Y87: 178819.7 | Z87: =R87-X87 -> 178819.7
A88: 7 | B88: MOHAMMED BELLO | C88: RESEARCH ASSITANT PG | D88: 8(7) | E88: 12351.94 | G88: =E88*300% -> 37055.82 | H88: =E88*7.5% -> 926.3955 | J88: =E88*50% -> 6175.97 | K88: =E88*350% -> 43231.79 | L88: =E88*100% -> 12351.94 | M88: =100000 -> 100000 | O88: =E88*10% -> 1235.194 | P88: 10000 | R88: =SUM(E88:Q88) -> 223329.05 | T88: =0 -> 0 | U88: =26666.67 -> 26666.67 | W88: 1484.37 | X88: =W88+V88+U88+T88+S88 -> 28151.04 | Y88: 195178.01 | Z88: =R88-X88 -> 195178.01
B89: TOTAL | C89: 7 | E89: =SUM(E82:E88) -> 211269.39 | G89: =SUM(G82:G88) -> 633808.17 | H89: =SUM(H82:H88) -> 15845.204 | I89: =SUM(I82:I88) -> 160488.76 | J89: =SUM(J82:J88) -> 105634.7 | K89: =SUM(K82:K88) -> 739442.86 | L89: =SUM(L82:L88) -> 211269.39 | M89: =SUM(M82:M88) -> 940000 | O89: =SUM(O82:O88) -> 21126.939 | P89: =SUM(P82:P88) -> 105000 | Q89: =SUM(Q82:Q88) -> 0 | R89: =SUM(R82:R88) -> 3143885.4 | T89: =SUM(T82:T88) -> 350000 | U89: =SUM(U82:U88) -> 76666.67 | V89: =SUM(V82:V88) -> 618.5315 | W89: =SUM(W82:W88) -> 97921.3 | X89: =SUM(X82:X88) -> 525206.5 | Y89: =SUM(Y82:Y88) -> 2618700.2 | Z89: =SUM(Z82:Z88) -> 2618678.9
B91: ECONOMIC DEV. AND SOCIAL RESEARCH
A92: 1 | B92: DR ASEMOTA OMOROGBE JOSEPH | C92: Ag. DEPUTY DIRECTOR, ECO & SOC DEV DEPT | D92: 16(8) | E92: 41157.69 | G92: =E92*300% -> 123473.07 | H92: =E92*7.5% -> 3086.8268 | I92: 40122.19 | J92: =E92*50% -> 20578.845 | K92: =E92*350% -> 144051.92 | L92: =E92*100% -> 41157.69 | M92: =180000 -> 180000 | O92: =E92*10% -> 4115.769 | P92: 20000 | R92: =SUM(E92:Q92) -> 617744 | W92: =21618.09 -> 21618.09 | X92: =W92+V92+U92+T92+S92 -> 21618.09 | Y92: 596125.91 | Z92: =R92-X92 -> 596125.91
A93: 2 | B93: TERFA WILLIAMS ABRAHAM | C93: SNR RESEARCH FELLOW | D93: 15(9) | E93: 33507.5 | G93: =E93*300% -> 100522.5 | H93: =E93*7.5% -> 2513.0625 | I93: =40122.19 -> 40122.19 | J93: =E93*50% -> 16753.75 | K93: =E93*350% -> 117276.25 | L93: =E93*100% -> 33507.5 | M93: =160000 -> 160000 | O93: =E93*10% -> 3350.75 | P93: 20000 | R93: =SUM(E93:Q93) -> 527553.5 | W93: =15548.33 -> 15548.33 | X93: =W93+V93+U93+T93+S93 -> 15548.33 | Y93: 512005.17 | Z93: =R93-X93 -> 512005.17
A94: 3 | B94: DR AUGUSTINE C. OSIGWE | C94: SNR RESEARCH FELLOW | D94: 15(9) | E94: 33507.5 | G94: =E94*300% -> 100522.5 | H94: =E94*7.5% -> 2513.0625 | I94: =40122.19 -> 40122.19 | J94: =E94*50% -> 16753.75 | K94: =E94*350% -> 117276.25 | L94: =E94*100% -> 33507.5 | M94: =160000 -> 160000 | O94: =E94*10% -> 3350.75 | P94: 20000 | R94: =SUM(E94:Q94) -> 527553.5 | T94: =30000 -> 30000 | U94: =98750 -> 98750 | V94: ='[2]April 2022'!$H$37 -> 837.6875 | W94: =15548.33 -> 15548.33 | X94: =W94+V94+U94+T94+S94 -> 145136.02 | Y94: 382448.59 | Z94: =R94-X94 -> 382417.48
A95: 4 | B95: NGARA CHRISTOPHER OCHANJA | C95: RESEARCH FELLOW 1 | D95: 14(10) | E95: 27611.23 | G95: =E95*300% -> 82833.69 | H95: =E95*7.5% -> 2070.8422 | J95: =E95*50% -> 13805.615 | K95: =E95*350% -> 96639.305 | L95: =E95*100% -> 27611.23 | M95: 140000 | O95: =E95*10% -> 2761.123 | P95: 20000 | Q95: 0 | R95: =SUM(E95:Q95) -> 413333.04 | T95: =20000 -> 20000 | U95: =163103.59 -> 163103.59 | V95: ='[2]April 2022'!$H$44 -> 690.28075 | W95: =7709.76 -> 7709.76 | X95: =W95+V95+U95+T95+S95 -> 191503.63 | Y95: 221851.37 | Z95: =R95-X95 -> 221829.4
A96: 5 | B96: OMOJU OLUWASOLA EMMANUEL | C96: RESEARCH FELLOW I | D96: 14(9) | E96: 26732.65 | G96: =E96*300% -> 80197.95 | H96: =E96*7.5% -> 2004.9488 | J96: =E96*50% -> 13366.325 | K96: =E96*350% -> 93564.275 | L96: =E96*100% -> 26732.65 | M96: 140000 | O96: =E96*10% -> 2673.265 | P96: 20000 | R96: =SUM(E96:Q96) -> 405272.06 | T96: =50000 -> 50000 | U96: =79861.11 -> 79861.11 | W96: =7709.76 -> 7709.76 | X96: =W96+V96+U96+T96+S96 -> 137570.87 | Y96: 267701.19 | Z96: =R96-X96 -> 267701.19
A97: 6 | B97: FESTUS OSAGU NDIDI | C97: RESEARCH FELLOW I | D97: 14(7) | E97: =24975.81 -> 24975.81 | G97: =E97*300% -> 74927.43 | H97: =E97*7.5% -> 1873.1858 | J97: =E97*50% -> 12487.905 | K97: =E97*350% -> 87415.335 | L97: =E97*100% -> 24975.81 | M97: 140000 | O97: =E97*10% -> 2497.581 | P97: 20000 | R97: =SUM(E97:Q97)*12/30 -> 155661.22 | W97: =7709.76 -> 7709.76 | X97: =W97+V97+U97+T97+S97 -> 7709.76 | Z97: =R97-X97 -> 147951.46
A98: 7 | B98: IBE EZECHI CYRIACUS | C98: RESEARCH FELLOW II | D98: 13(9) | E98: 24741.26 | G98: =E98*300% -> 74223.78 | H98: =E98*7.5% -> 1855.5945 | I98: 0 | J98: =E98*50% -> 12370.63 | K98: =E98*350% -> 86594.41 | L98: =E98*100% -> 24741.26 | M98: =120000 -> 120000 | O98: =E98*10% -> 2474.126 | P98: 15000 | Q98: 0 | R98: =SUM(E98:Q98) -> 362001.06 | T98: =50000 -> 50000 | W98: =7709.76 -> 7709.76 | X98: =W98+V98+U98+T98+S98 -> 57709.76 | Y98: 257624.65 | Z98: =R98-X98 -> 304291.3
A99: 8 | B99: OSIKHEN LEO IGBANOI | C99: RESEARCH FELLOW 11 | D99: 13(8) | E99: 23891.12 | G99: =E99*300% -> 71673.36 | H99: =E99*7.5% -> 1791.834 | I99: 0 | J99: =E99*50% -> 11945.56 | K99: =E99*350% -> 83618.92 | L99: =E99*100% -> 23891.12 | M99: =120000 -> 120000 | O99: =E99*10% -> 2389.112 | P99: 15000 | Q99: 0 | R99: =SUM(E99:Q99) -> 354201.03 | W99: =7709.76 -> 7709.76 | X99: =W99+V99+U99+T99+S99 -> 7709.76 | Y99: 227229.12 | Z99: =R99-X99 -> 346491.27
A100: 9 | B100: OKUNGBOWA OSARETIN GODSPOWER | C100: RESEARCH FELLOW 11 | D100: 13(8) | E100: 23891.12 | G100: =E100*300% -> 71673.36 | H100: =E100*7.5% -> 1791.834 | I100: 0 | J100: =E100*50% -> 11945.56 | K100: =E100*350% -> 83618.92 | L100: =E100*100% -> 23891.12 | M100: =120000 -> 120000 | O100: =E100*10% -> 2389.112 | P100: 15000 | Q100: 0 | R100: =SUM(E100:Q100) -> 354201.03 | T100: =100000 -> 100000 | W100: =7709.76 -> 7709.76 | X100: =W100+V100+U100+T100+S100 -> 107709.76 | Y100: 246491.27 | Z100: =R100-X100 -> 246491.27
A101: 10 | B101: YUSUF IBRAHIM | C101: PRINCIPAL RESEARCH OFFICER | D101: 12(7) | E101: =20749 -> 20749 | G101: =E101*300% -> 62247 | H101: =E101*7.5% -> 1556.175 | I101: 0 | J101: =E101*50% -> 10374.5 | K101: =E101*350% -> 72621.5 | L101: =E101*100% -> 20749 | M101: =110000 -> 110000 | O101: =E101*10% -> 2074.9 | P101: 15000 | Q101: 0 | R101: =SUM(E101:Q101)*9/30 -> 94611.623 | W101: =3369.51 -> 3369.51 | X101: =W101+V101+U101+T101+S101 -> 3369.51 | Z101: =R101-X101 -> 91242.113
B102: TOTAL | C102: 10 | E102: =SUM(E92:E101) -> 280764.88 | G102: =SUM(G92:G101) -> 842294.64 | H102: =SUM(H92:H101) -> 21057.366 | I102: =SUM(I92:I101) -> 120366.57 | J102: =SUM(J92:J101) -> 140382.44 | K102: =SUM(K92:K101) -> 982677.08 | L102: =SUM(L92:L101) -> 280764.88 | M102: =SUM(M92:M101) -> 1390000 | O102: =SUM(O92:O101) -> 28076.488 | P102: =SUM(P92:P101) -> 180000 | Q102: =SUM(Q92:Q101) -> 0 | R102: =SUM(R92:R101) -> 3812132.1 | T102: =SUM(T92:T101) -> 250000 | U102: =SUM(U92:U101) -> 341714.7 | V102: =SUM(V92:V101) -> 1527.9682 | W102: =SUM(W92:W101) -> 102342.82 | X102: =SUM(X92:X101) -> 695585.49 | Y102: =SUM(Y92:Y101) -> 2711477.3 | Z102: =SUM(Z92:Z101) -> 3116546.6
B104: TRAINING AND INTERNATIONAL COOP
A105: 1 | B105: REKIYA IBRAHIM ATTAH | C105: DEPUTY DIRECTOR TRAINING | D105: 16(8) | E105: 41157.69 | G105: =E105*300% -> 123473.07 | H105: =E105*7.5% -> 3086.8268 | I105: 40122.19 | J105: =E105*50% -> 20578.845 | K105: =E105*350% -> 144051.92 | L105: =E105*100% -> 41157.69 | N105: =90000 -> 90000 | O105: =E105*10% -> 4115.769 | P105: 20000 | R105: =SUM(E105:Q105) -> 527744 | U105: =0 -> 0 | W105: =21618.09 -> 21618.09 | X105: =W105+V105+U105+T105+S105 -> 21618.09 | Y105: 506125.91 | Z105: =R105-X105 -> 506125.91
A106: 2 | B106: DR FRANCIS NDUM OJIE | C106: CHIEF TRAINING OFFICER | D106: 14(9) | E106: 26732.65 | G106: =E106*300% -> 80197.95 | H106: =E106*7.5% -> 2004.9488 | J106: =E106*50% -> 13366.325 | K106: =E106*350% -> 93564.275 | L106: =E106*100% -> 26732.65 | N106: =70000 -> 70000 | O106: =E106*10% -> 2673.265 | P106: 20000 | R106: =SUM(E106:Q106) -> 335272.06 | V106: ='[2]April 2022'!$H$54 -> 668.31625 | W106: =7709.76 -> 7709.76 | X106: =W106+V106+U106+T106+S106 -> 8378.0763 | Y106: 326915.95 | Z106: =R106-X106 -> 326893.99
A107: 3 | B107: ABUBAKAR MOHAMMED BASHIR | C107: ASST. CHIEF TRAINING OFFICER | D107: 13(8) | E107: 23891.12 | G107: =E107*300% -> 71673.36 | H107: =E107*7.5% -> 1791.834 | I107: 0 | J107: =E107*50% -> 11945.56 | K107: =E107*350% -> 83618.92 | L107: =E107*100% -> 23891.12 | N107: 70000 | O107: =E107*10% -> 2389.112 | P107: 15000 | Q107: 0 | R107: =SUM(E107:Q107) -> 304201.03 | W107: =7709.76 -> 7709.76 | X107: =W107+V107+U107+T107+S107 -> 7709.76 | Y107: 296491.27 | Z107: =R107-X107 -> 296491.27
A108: 4 | B108: OKECHUKWU UCHENNA HULDA | C108: TRAINING OFFICER | D108: 10(11) | E108: 19276.95 | G108: =E108*300% -> 57830.85 | H108: =E108*7.5% -> 1445.7713 | J108: =E108*50% -> 9638.475 | K108: =E108*350% -> 67469.325 | L108: =E108*100% -> 19276.95 | N108: =60000 -> 60000 | O108: =E108*10% -> 1927.695 | P108: 10000 | R108: =SUM(E108:Q108) -> 246866.02 | T108: =5000 -> 5000 | U108: =64806.29 -> 64806.29 | W108: 3369.51 | X108: =W108+V108+U108+T108+S108 -> 73175.8 | Y108: 173690.22 | Z108: =R108-X108 -> 173690.22
B109: TOTAL | C109: 4 | E109: 111058.41 | G109: =SUM(G105:G108) -> 333175.23 | H109: =SUM(H105:H108) -> 8329.3808 | I109: =SUM(I105:I108) -> 40122.19 | J109: =SUM(J105:J108) -> 55529.205 | K109: =SUM(K105:K108) -> 388704.43 | L109: =SUM(L105:L108) -> 111058.41 | N109: =SUM(N105:N108) -> 290000 | O109: =SUM(O105:O108) -> 11105.841 | P109: =SUM(P105:P108) -> 65000 | Q109: =SUM(Q105:Q108) -> 0 | R109: =SUM(R105:R108) -> 1414083.1 | T109: =SUM(T105:T108) -> 5000 | U109: =SUM(U105:U108) -> 64806.29 | V109: =SUM(V105:V108) -> 668.31625 | W109: =SUM(W105:W108) -> 40407.12 | X109: =SUM(X105:X108) -> 110881.73 | Y109: 1303223.3 | Z109: =SUM(Z105:Z108) -> 1303201.4
...

Sheet MEMO 1
A2: NATIONAL INSTITUTE FOR LEGISLATIVE AND DEMOCRATIC STUDIES
B3: INTERNAL MEMO
A4: INTERNAL MEMO
A6: FROM : DEPUTY DIRECTOR, FINANCE AND ACCOUNTS
A7: THRU: DIRECTOR, FINANCE AND ACCOUNTS
A8: TO: DG
A9: 29TH JANUARY , 2021
A11: SUBJECT: PAYROLL FOR THE MONTH OF JANUARY, 2021
A12: Find below the details of NILDS Staff Payroll for the month of January, 2021
A14: TO: | C14: DIRECTOR, GENERAL
A15: THRU: | C15: DIRECTOR, FINANCE AND ACCOUNT
A16: FROM: | C16: ASST. DIRECTOR, FINANCE AND ACCOUNTS
A17: DATE: | C17: 30th APRIL, 2022
A18: SUBJECT: PAYROLL FOR THE MONTH OF APRIL, 2022
A19: Find below the details of NILDS Staff Payroll for the month of March, 2022
A20: GROSS SALARY FOR APRIL, 2022 | H20: ='April, 2022'!R192 -> 51044021
A21: DEDUCTIONS
A22: COOP SOCIETY DEDUCTIONS | G22: ='April, 2022'!T192 -> 5074500
A23: COOP LOAN RECOVERY | G23: ='April, 2022'!U192 -> 6538580.7
A24: PAYE DEDUCTIONS | G24: ='April, 2022'!W192 -> 1499928.3
A25: NHF DEDUCTIONS | G25: ='April, 2022'!V192 -> 26877.441
A26: TOTAL DEDUCTIONS FOR APRIL, 2022 | H26: =G22+G23+G24+G25 -> 13139886
A27: NET PAY AS PER APRIL, 2022 PAYROLL | H27: =H20-H26 -> 37904134
A28: NET PAY AS PER MARCH, 2022 PAYROLL | H28: ='April, 2022'!Y192 -> 37262687
A29: NET INCREASE/ (DECREASE) IN PAY FOR APRIL, 2022 | H29: =H27-H28 -> 641447.78
A30: ANALYSED AS FOLLOWS:
A31: Effect of Cooperative adjustment for April 2022 | H31: =162612.64+107638.89 -> 270251.53
A32: Net effect of removal of payment of 14 days salary to Emily Ekhide | H32: =70790.75 -> 70790.75
A33: Net effect of NHF adjustment | H33: =809.41 -> 809.41
A34: Net effect of salary adjustment of Maryam Bello from PA to SA | H34: =-158279.78 -> -158279.78
A35: Net effect of salary adjustment of Livinus Nnandi from grade 8 to 9 & 2 months arrears | H35: =-65625 -> -65625
A36: Net effect of enrolment of new Staff Jamila Abdul & 7 others in payrol on pro-rata | H36: =-759394.69 -> -759394.69
H37: =SUM(H31:H36) -> -641447.78
E38: MARCH, 2022 | G38: APRIL, 2022
E39: No. of Staff | F39: N | G39: No. of Staff | H39: N
A40: 1 | B40: Director General's Office | E40: 31 | F40: ='April, 2022'!Y39 -> 9843312.2 | G40: 30 | H40: ='April, 2022'!Z39 -> 9839304
A41: 2 | B41: Internal Audit | E41: 1 | F41: ='April, 2022'!Y44 -> 772656.45 | G41: 2 | H41: ='April, 2022'!Z44 -> 840503.7
A42: 3 | B42: Legis. Support Services | E42: 9 | F42: ='April, 2022'!Y57 -> 3234095.2 | G42: 10 | H42: ='April, 2022'!Z57 -> 3330671.2
A43: 4 | B43: Legal Services | E43: 2 | F43: ='April, 2022'!Y62 -> 1273021.2 | G43: 2 | H43: ='April, 2022'!Z62 -> 1273021.2
A44: 5 | B44: Democracy and Governance | E44: 12 | F44: ='April, 2022'!Y79 -> 2957372.4 | G44: 14 | H44: ='April, 2022'!Z79 -> 3197709.3
A45: 6 | B45: Studies | E45: =7 -> 7 | F45: ='April, 2022'!Y89 -> 2618700.2 | G45: =7 -> 7 | H45: ='April, 2022'!Z89 -> 2618678.9
A46: 7 | B46: Economic Dev. & Social Research | E46: 10 | F46: ='April, 2022'!Y102 -> 2711477.3 | G46: 10 | H46: ='April, 2022'!Z102 -> 3116546.6
A47: 8 | B47: Training & International | E47: 4 | F47: ='April, 2022'!Y109 -> 1303223.3 | G47: 4 | H47: ='April, 2022'!Z109 -> 1303201.4
A48: 9 | B48: Library & Documentation | E48: 8 | F48: ='April, 2022'!Y120 -> 2583235.9 | G48: 8 | H48: ='April, 2022'!Z120 -> 2475597
A49: 10 | B49: Finance and Accounts | E49: 9 | F49: ='April, 2022'!Y132 -> 2688787.5 | G49: 9 | H49: ='April, 2022'!Z132 -> 2688713.9
A50: 11 | B50: Admin & HR | E50: 54 | F50: ='April, 2022'!Y191 -> 7276805.1 | G50: 56 | H50: ='April, 2022'!Z191 -> 7220187.4
E51: =SUM(E40:E50) -> 147 | F51: =SUM(F40:F50) -> 37262687 | G51: =SUM(G40:G50) -> 152 | H51: =SUM(H40:H50) -> 37904134
A52: The Director General is requested to consider and approve payment of N37,904,134.49 to Guaranty Trust Bank being April 2022 Salary, N11,613,080.74 being NILDS Coop Society deductions for April 2022 N1,499,928.27 being PAYE Tax Deductions from Staff Salary for the month of April 2022 and N26,877.44 being NHF deductions from staff for April 2022
A55: IORWUESE TONDO
A56: Asst. Director, Finance and Accounts
C160: =10000 -> 10000

Sheet Annual Increement
B3: STAFF PAYROLL FOR THE MONTH OF DECEMBER, 2021
F4: ='[1]FEB 08'!E8/'[1]FEB 08'!M8 -> 0.22 | I4: ='[1]FEB 08'!F8/'[1]FEB 08'!Q8 -> 0.3
B5: STAFF NAME
D6: DESIGNATION | E6: SALARY | F6: BASIC | M6: MOTOR/ | N6: RESEARCH | O6: HARDSHIP | P6: LEAVE | Q6: OUT FIT | R6: LEGISLATIVE | S6: NEW GROSS | T6: OLD GROSS | U6: DIFFERENCE
E7: LEVEL | F7: SALARY | G7: SALARY/ALLOWCE AREARS | H7: RENT | I7: UTILITY | J7: DOMESTIC | K7: ENTERT. | L7: FURNIT. | M7: FUEL | N7: ALLOWANCE | O7: ALLOWANCE | P7: ALLCE | Q7: ALLCE | R7: DUTY ALLCE | S7: SALARY | T7: SALARY | W7: OLD PAYE | X7: NEW PAYE | Y7: DIFFERENCE
A8: S/N | B8: DG OFFICE | F8: N | I8: N | S8: N | T8: N | U8: N | W8: N | X8: N | Y8: N
A9: 1 | B9: PROF. ABUBAKAR O. SULAIMAN | D9: DIRECTOR GENERAL | E9: CONSOL | F9: 160488.75 | H9: 320977.5 | I9: 48146.63 | J9: 120366.57 | K9: 72219.94 | L9: 0 | M9: 120366.57 | N9: =250000 -> 250000 | P9: 16048.88 | Q9: 25000 | R9: 25235 | S9: =R9+Q9+P9+O9+N9+M9+L9+K9+J9+I9+H9+G9+F9 -> 1158849.8 | T9: 1158849.8 | U9: =S9-T9 -> 0 | W9: 113176.97 | X9: 113176.97 | Y9: =X9-W9 -> 0
A10: 2 | B10: DR ADEYEMI AKEEB FAJINGBESI | D10: DIR. SPECIAL DUTIES, DG OFFICE | E10: 17(9) | F10: 81740.02 | H10: =F10*300% -> 245220.06 | I10: =F10*7.5% -> 6130.5015 | J10: 80244.38 | K10: =F10*50% -> 40870.01 | L10: =F10*350% -> 286090.07 | M10: =F10*100% -> 81740.02 | N10: =200000 -> 200000 | P10: =F10*10% -> 8174.002 | Q10: 20000 | R10: 0 | S10: =R10+Q10+P10+O10+N10+M10+L10+K10+J10+I10+H10+G10+F10 -> 1050209.1 | T10: 1050209.1 | U10: =S10-T10 -> 0 | W10: 52776.63 | X10: 52776.63 | Y10: =X10-W10 -> 0
A11: 3 | B11: SARAFADEEN ALABELEWE | D11: SA- ADMIN | E11: 16(9) | F11: =42653.17 -> 42653.17 | H11: =F11*300% -> 127959.51 | I11: =F11*7.5% -> 3198.9877 | J11: 40122.19 | K11: =F11*50% -> 21326.585 | L11: =F11*350% -> 149286.1 | M11: =F11*100% -> 42653.17 | O11: =90000 -> 90000 | P11: =F11*10% -> 4265.317 | Q11: 20000 | S11: =R11+Q11+P11+O11+N11+M11+L11+K11+J11+I11+H11+G11+F11 -> 541465.02 | T11: 541465.02 | U11: =S11-T11 -> 0 | W11: 21618.09 | X11: 21618.09 | Y11: =X11-W11 -> 0
A12: 4 | B12: DR JAKE DABANG DAN AZUMI | D12: DEPUTY DIRECTOR TRAINING | E12: 16(8) | F12: =41157.69 -> 41157.69 | H12: =F12*300% -> 123473.07 | I12: =F12*7.5% -> 3086.8268 | J12: 40122.19 | K12: =F12*50% -> 20578.845 | L12: =F12*350% -> 144051.92 | M12: =F12*100% -> 41157.69 | N12: =180000 -> 180000 | P12: =F12*10% -> 4115.769 | Q12: 20000 | R12: 150000 | S12: =R12+Q12+P12+O12+N12+M12+L12+K12+J12+I12+H12+G12+F12 -> 767744 | T12: 754023.33 | U12: =S12-T12 -> 13720.662 | W12: =21618.09 -> 21618.09 | X12: 21618.09 | Y12: =X12-W12 -> 0
A13: 5 | B13: DR ABDULSALAM NASIRU NAEEM | D13: SA ACADEMICS | E13: 16(8) | F13: =41157.69 -> 41157.69 | H13: =F13*300% -> 123473.07 | I13: =F13*7.5% -> 3086.8268 | J13: 40122.19 | K13: =F13*50% -> 20578.845 | L13: =F13*350% -> 144051.92 | M13: =F13*100% -> 41157.69 | N13: =180000 -> 180000 | P13: =F13*10% -> 4115.769 | Q13: 20000 | R13: =100000 -> 100000 | S13: =R13+Q13+P13+O13+N13+M13+L13+K13+J13+I13+H13+G13+F13 -> 717744 | T13: 704023.33 | U13: =S13-T13 -> 13720.662 | W13: =21618.09 -> 21618.09 | X13: 21618.09 | Y13: =X13-W13 -> 0
A14: 6 | B14: RAHEEM USMAN AYIGORO | D14: SA-INFRASTRUCTURE | E14: 16 (8) | F14: =41157.69 -> 41157.69 | H14: =F14*300% -> 123473.07 | I14: =F14*7.5% -> 3086.8268 | J14: 40122.19 | K14: =F14*50% -> 20578.845 | L14: =F14*350% -> 144051.92 | M14: =F14*100% -> 41157.69 | O14: =90000 -> 90000 | P14: =F14*10% -> 4115.769 | Q14: 20000 | R14: 0 | S14: =R14+Q14+P14+O14+N14+M14+L14+K14+J14+I14+H14+G14+F14 -> 527744 | T14: 514023.33 | U14: =S14-T14 -> 13720.662 | W14: =21618.09 -> 21618.09 | X14: 21618.09 | Y14: =X14-W14 -> 0
A15: 7 | B15: AKINSANMI ADEJOKE OLUKEMI | D15: HEAD INFORMATION/PROTOCOL | E15: 15(9) | F15: 33507.5 | H15: =F15*300% -> 100522.5 | I15: =F15*7.5% -> 2513.0625 | J15: 40122.19 | K15: =F15*50% -> 16753.75 | L15: =F15*350% -> 117276.25 | M15: =F15*100% -> 33507.5 | O15: =80000 -> 80000 | P15: =F15*10% -> 3350.75 | Q15: 20000 | R15: =100000 -> 100000 | S15: =R15+Q15+P15+O15+N15+M15+L15+K15+J15+I15+H15+G15+F15 -> 547553.5 | T15: 547553.5 | U15: =S15-T15 -> 0 | W15: 15548.33 | X15: 15548.33 | Y15: =X15-W15 -> 0
A16: 8 | B16: DR IKEME ARTHUR J.O | D16: SNR RESEARCH FELLOW | E16: 15(9) | F16: =33507.5 -> 33507.5 | H16: =F16*300% -> 100522.5 | I16: =F16*7.5% -> 2513.0625 | J16: 40122.19 | K16: =F16*50% -> 16753.75 | L16: =F16*350% -> 117276.25 | M16: =F16*100% -> 33507.5 | O16: =80000 -> 80000 | P16: =F16*10% -> 3350.75 | Q16: 20000 | R16: 0 | S16: =R16+Q16+P16+O16+N16+M16+L16+K16+J16+I16+H16+G16+F16 -> 447553.5 | T16: 447553.5 | U16: =S16-T16 -> 0 | W16: 15548.33 | X16: 15548.33 | Y16: =X16-W16 -> 0
A17: 9 | B17: MOSHOOD M. OLALERE | D17: MANAGER ADMIN DG's OFFICE | E17: 15(9) | F17: =33507.5 -> 33507.5 | H17: =F17*300% -> 100522.5 | I17: =F17*7.5% -> 2513.0625 | J17: 40122.19 | K17: =F17*50% -> 16753.75 | L17: =F17*350% -> 117276.25 | M17: =F17*100% -> 33507.5 | O17: =80000 -> 80000 | P17: =F17*10% -> 3350.75 | Q17: 20000 | R17: 0 | S17: =R17+Q17+P17+O17+N17+M17+L17+K17+J17+I17+H17+G17+F17 -> 447553.5 | T17: 447553.5 | U17: =S17-T17 -> 0 | W17: 15548.33 | X17: 15548.33 | Y17: =X17-W17 -> 0
A18: 10 | B18: ANDRAWUS MUSA | D18: ASST. DIRECTOR, STORE | E18: 15(9) | F18: =33507.5 -> 33507.5 | H18: =F18*300% -> 100522.5 | I18: =F18*7.5% -> 2513.0625 | J18: =40122.19 -> 40122.19 | K18: =F18*50% -> 16753.75 | L18: =F18*350% -> 117276.25 | M18: =F18*100% -> 33507.5 | O18: =80000 -> 80000 | P18: =F18*10% -> 3350.75 | Q18: 20000 | R18: 0 | S18: =SUM(F18:R18) -> 447553.5 | T18: 436137.05 | U18: =S18-T18 -> 11416.452 | W18: =15548.33 -> 15548.33 | X18: 15548.33 | Y18: =X18-W18 -> 0
A19: 11 | B19: AYOBOLU OLAJIDE OLUFUNSHO | D19: ASST.DIR., INFORMATION | E19: 15 (7) | F19: 31018.84 | H19: =F19*300% -> 93056.52 | I19: =F19*7.5% -> 2326.413 | J19: 40122.19 | K19: =F19*50% -> 15509.42 | L19: =F19*350% -> 108565.94 | M19: =F19*100% -> 31018.84 | O19: =80000 -> 80000 | P19: =F19*10% -> 3101.884 | Q19: 20000 | R19: 0 | S19: =R19+Q19+P19+O19+N19+M19+L19+K19+J19+I19+H19+G19+F19 -> 424720.05 | T19: 424720.05 | U19: =S19-T19 -> 0 | W19: 15548.33 | X19: 15548.33 | Y19: =X19-W19 -> 0
A20: 12 | B20: HUSSEIN EGYE MUSA | D20: CHIEF PROTOCOL OFFICER | E20: 14(9) | F20: =26732.65 -> 26732.65 | H20: =F20*300% -> 80197.95 | I20: =F20*7.5% -> 2004.9488 | K20: =F20*50% -> 13366.325 | L20: =F20*350% -> 93564.275 | M20: =F20*100% -> 26732.65 | O20: =70000 -> 70000 | P20: =F20*10% -> 2673.265 | Q20: 20000 | R20: 50000 | S20: =R20+Q20+P20+O20+N20+M20+L20+K20+J20+I20+H20+G20+F20 -> 385272.06 | T20: 377211.37 | U20: =S20-T20 -> 8060.6963 | W20: 7709.76 | X20: 7709.76 | Y20: =X20-W20 -> 0
A21: 13 | B21: DONALD E. MKPANAM | D21: CHIEF ICT OFFICER | E21: 14(9) | F21: =26732.65 -> 26732.65 | H21: =F21*300% -> 80197.95 | I21: =F21*7.5% -> 2004.9488 | K21: =F21*50% -> 13366.325 | L21: =F21*350% -> 93564.275 | M21: =F21*100% -> 26732.65 | O21: =70000 -> 70000 | P21: =F21*10% -> 2673.265 | Q21: 20000 | R21: 0 | S21: =R21+Q21+P21+O21+N21+M21+L21+K21+J21+I21+H21+G21+F21 -> 335272.06 | T21: 327211.37 | U21: =S21-T21 -> 8060.6963 | W21: 7709.76 | X21: 7709.76 | Y21: =X21-W21 -> 0
A22: 14 | B22: JOY HARUNA MAKERI | D22: RESEARCH FELLOW 1 TRAINING | E22: 14(9) | F22: =26732.65 -> 26732.65 | H22: =F22*300% -> 80197.95 | I22: =F22*7.5% -> 2004.9488 | K22: =F22*50% -> 13366.325 | L22: =F22*350% -> 93564.275 | M22: =F22*100% -> 26732.65 | N22: =140000 -> 140000 | P22: =F22*10% -> 2673.265 | Q22: 20000 | R22: =50000+100000 -> 150000 | S22: =R22+Q22+P22+O22+N22+M22+L22+K22+J22+I22+H22+G22+F22 -> 555272.06 | T22: 547211.37 | U22: =S22-T22 -> 8060.6963 | W22: =7709.76 -> 7709.76 | X22: 7709.76 | Y22: =X22-W22 -> 0
A23: 15 | B23: ALI ABDULLAHI | D23: ASST. CHIEF ICT OFFICER | E23: 13(11) | F23: =26339.3 -> 26339.3 | H23: =F23*300% -> 79017.9 | I23: =F23*7.5% -> 1975.4475 | J23: 0 | K23: =F23*50% -> 13169.65 | L23: =F23*350% -> 92187.55 | M23: =F23*100% -> 26339.3 | O23: =70000 -> 70000 | P23: =F23*10% -> 2633.93 | Q23: 15000 | R23: =0 -> 0 | S23: =R23+Q23+P23+O23+N23+M23+L23+K23+J23+I23+H23+G23+F23 -> 326663.08 | T23: 326663.08 | U23: =S23-T23 -> 0 | W23: =7709.76 -> 7709.76 | X23: 7709.76 | Y23: =X23-W23 -> 0
A24: 16 | B24: MARIAM MOHAMMED BELLO | D24: PA- SPECIAL DUTIES | E24: 13 (7) | F24: =23074.99 -> 23074.99 | H24: =F24*300% -> 69224.97 | I24: =F24*7.5% -> 1730.6243 | J24: =265272 -> 265272 | K24: =F24*50% -> 11537.495 | L24: =F24*350% -> 80762.465 | M24: =F24*100% -> 23074.99 | O24: =70000 -> 70000 | P24: =F24*10% -> 2307.499 | Q24: 15000 | R24: =100000+100000 -> 200000 | S24: =R24+Q24+P24+O24+N24+M24+L24+K24+J24+I24+H24+G24+F24 -> 761985.03 | T24: 761985.03 | U24: =S24-T24 -> 0 | W24: =7709.76 -> 7709.76 | X24: 7709.76 | Y24: =X24-W24 -> 0
A25: 17 | B25: PERCY TERFA GBAHABO | D25: HEAD, NILDS LIAISON OFFICE | E25: 13(8) | F25: =23891.12 -> 23891.12 | H25: =F25*300% -> 71673.36 | I25: =F25*7.5% -> 1791.834 | J25: 0 | K25: =F25*50% -> 11945.56 | L25: =F25*350% -> 83618.92 | M25: =F25*100% -> 23891.12 | N25: =120000 -> 120000 | P25: =F25*10% -> 2389.112 | Q25: 15000 | R25: 0 | S25: =R25+Q25+P25+O25+N25+M25+L25+K25+J25+I25+H25+G25+F25 -> 354201.03 | T25: 346713.03 | U25: =S25-T25 -> 7487.9928 | W25: =7709.76 -> 7709.76 | X25: 7709.76 | Y25: =X25-W25 -> 0
A26: 18 | B26: ADUGBA RICHARD TERSEER | D26: INFORMATION OFFICER | E26: 10(10) | F26: =18779.3 -> 18779.3 | H26: =F26*300% -> 56337.9 | I26: =F26*7.5% -> 1408.4475 | K26: =F26*50% -> 9389.65 | L26: =F26*350% -> 65727.55 | M26: =F26*100% -> 18779.3 | O26: =60000 -> 60000 | P26: =F26*10% -> 1877.93 | Q26: 10000 | S26: =R26+Q26+P26+O26+N26+M26+L26+K26+J26+I26+H26+G26+F26 -> 242300.08 | T26: 237734.05 | U26: =S26-T26 -> 4566.0305 | W26: 3369.51 | X26: 3369.51 | Y26: =X26-W26 -> 0
A27: 19 | B27: CHRISTIAN MADUABUCHI ODO | D27: PRINCIPAL ICT OFFICER | E27: 12(8) | F27: =21520.88 -> 21520.88 | H27: =F27*300% -> 64562.64 | I27: =F27*7.5% -> 1614.066 | K27: =F27*50% -> 10760.44 | L27: =F27*350% -> 75323.08 | M27: =F27*100% -> 21520.88 | O27: =60000 -> 60000 | P27: =F27*10% -> 2152.088 | Q27: 15000 | S27: =R27+Q27+P27+O27+N27+M27+L27+K27+J27+I27+H27+G27+F27 -> 272454.07 | T27: 265372.07 | U27: =S27-T27 -> 7081.999 | W27: 3369.51 | X27: 3369.51 | Y27: =X27-W27 -> 0
A28: 20 | B28: HASSANA AHMED IBRAHIM | D28: PA- TO DG | E28: 10(9) | F28: =18281.64 -> 18281.64 | H28: =F28*300% -> 54844.92 | I28: =F28*7.5% -> 1371.123 | K28: =F28*50% -> 9140.82 | L28: =F28*350% -> 63985.74 | M28: =F28*100% -> 18281.64 | N28: =100000 -> 100000 | P28: =F28*10% -> 1828.164 | Q28: 10000 | R28: =100000 -> 100000 | S28: =R28+Q28+P28+O28+N28+M28+L28+K28+J28+I28+H28+G28+F28 -> 377734.05 | T28: 373168.2 | U28: =S28-T28 -> 4565.847 | W28: 3369.51 | X28: 3369.51 | Y28: =X28-W28 -> 0
A29: 21 | B29: VICTOR ASUKWO | D29: ICT OFFICER | E29: 8 (10) | F29: =13492.21 -> 13492.21 | H29: =F29*300% -> 40476.63 | I29: =F29*7.5% -> 1011.9157 | K29: =F29*50% -> 6746.105 | L29: =F29*350% -> 47222.735 | M29: =F29*100% -> 13492.21 | O29: =50000 -> 50000 | P29: =F29*10% -> 1349.221 | Q29: 10000 | S29: =R29+Q29+P29+O29+N29+M29+L29+K29+J29+I29+H29+G29+F29 -> 183791.03 | T29: 180304.07 | U29: =S29-T29 -> 3486.9587 | W29: 1484.37 | X29: 1484.37 | Y29: =X29-W29 -> 0
A30: 22 | B30: SULEIMAN ABUBAKAR SODEEQ | D30: ASST. ADMIN. OFFICER | E30: 8(7) | F30: =12351.94 -> 12351.94 | H30: =F30*300% -> 37055.82 | I30: =F30*7.5% -> 926.3955 | K30: =F30*50% -> 6175.97 | L30: =F30*350% -> 43231.79 | M30: =F30*100% -> 12351.94 | O30: =50000 -> 50000 | P30: =F30*10% -> 1235.194 | Q30: 10000 | S30: =R30+Q30+P30+O30+N30+M30+L30+K30+J30+I30+H30+G30+F30 -> 173329.05 | T30: 173329.05 | U30: =S30-T30 -> 0 | W30: =1484.37 -> 1484.37 | X30: 1484.37 | Y30: =X30-W30 -> 0
A31: 23 | B31: YAKUB OLUWATOYIN USMAN | D31: ASST. ADMIN. OFFICER | E31: 10(8) | F31: =17784.1 -> 17784.1 | H31: =F31*300% -> 53352.3 | I31: =F31*7.5% -> 1333.8075 | K31: =F31*50% -> 8892.05 | L31: =F31*350% -> 62244.35 | M31: =F31*100% -> 17784.1 | O31: =60000 -> 60000 | P31: =F31*10% -> 1778.41 | Q31: 10000 | S31: =R31+Q31+P31+O31+N31+M31+L31+K31+J31+I31+H31+G31+F31 -> 233169.12 | T31: 228602.08 | U31: =S31-T31 -> 4567.0397 | W31: =1484.37 -> 1484.37 | X31: 1484.37 | Y31: =X31-W31 -> 0
A32: 24 | B32: ANTHONY EDET | D32: ASST. MGR M&E | E32: 13(9) | F32: =24741.26 -> 24741.26 | H32: =F32*300% -> 74223.78 | I32: =F32*7.5% -> 1855.5945 | J32: 0 | K32: =F32*50% -> 12370.63 | L32: =F32*350% -> 86594.41 | M32: =F32*100% -> 24741.26 | O32: =70000 -> 70000 | P32: =F32*10% -> 2474.126 | Q32: 15000 | R32: 0 | S32: =R32+Q32+P32+O32+N32+M32+L32+K32+J32+I32+H32+G32+F32 -> 312001.06 | T32: 304201.03 | U32: =S32-T32 -> 7800.0345 | W32: =7709.76 -> 7709.76 | X32: 7709.76 | Y32: =X32-W32 -> 0
A33: 25 | B33: EGUATU U. ONYEJELEM | D33: OFFICER M&E | E33: 10(10) | F33: =18779.3 -> 18779.3 | H33: =F33*300% -> 56337.9 | I33: =F33*7.5% -> 1408.4475 | K33: =F33*50% -> 9389.65 | L33: =F33*350% -> 65727.55 | M33: =F33*100% -> 18779.3 | O33: =60000 -> 60000 | P33: =F33*10% -> 1877.93 | Q33: 10000 | S33: =R33+Q33+P33+O33+N33+M33+L33+K33+J33+I33+H33+G33+F33 -> 242300.08 | T33: 237734.05 | U33: =S33-T33 -> 4566.0305 | W33: 3369.51 | X33: 3369.51 | Y33: =X33-W33 -> 0
A34: 26 | B34: ODEH SUZIE | D34: ADMIN. OFFICER, LIASION OFFICE | E34: 10(9) | F34: =18281.64 -> 18281.64 | H34: =F34*300% -> 54844.92 | I34: =F34*7.5% -> 1371.123 | K34: =F34*50% -> 9140.82 | L34: =F34*350% -> 63985.74 | M34: =F34*100% -> 18281.64 | O34: 60000 | P34: =F34*10% -> 1828.164 | Q34: 10000 | S34: =R34+Q34+P34+O34+N34+M34+L34+K34+J34+I34+H34+G34+F34 -> 237734.05 | T34: 233168.2 | U34: =S34-T34 -> 4565.847 | W34: 3369.51 | X34: 3369.51 | Y34: =X34-W34 -> 0
A35: 27 | B35: IJEOMA NKOLIKWA | D35: ASSISTANT STORES OFFICER | E35: 8(10) | F35: =13492.21 -> 13492.21 | H35: =F35*300% -> 40476.63 | I35: =F35*7.5% -> 1011.9157 | K35: =F35*50% -> 6746.105 | L35: =F35*350% -> 47222.735 | M35: =F35*100% -> 13492.21 | O35: =50000 -> 50000 | P35: =F35*10% -> 1349.221 | Q35: 10000 | S35: =SUM(F35:R35) -> 183791.03 | T35: 180304.07 | U35: =S35-T35 -> 3486.9587 | W35: 1484.37 | X35: 1484.37 | Y35: =X35-W35 -> 0
A36: 28 | B36: ABDULRAHMAN A SULAIMAN | D36: ASSISTANT STORES OFFICER | E36: 8 (9) | F36: =13112.16 -> 13112.16 | H36: =F36*300% -> 39336.48 | I36: =F36*7.5% -> 983.412 | K36: =F36*50% -> 6556.08 | L36: =F36*350% -> 45892.56 | M36: =F36*100% -> 13112.16 | O36: =50000 -> 50000 | P36: =F36*10% -> 1311.216 | Q36: 10000 | S36: =SUM(F36:R36) -> 180304.07 | T36: 176816.1 | U36: =S36-T36 -> 3487.968 | W36: =(1484.37) -> 1484.37 | X36: 1484.37 | Y36: =X36-W36 -> 0
A37: 29 | B37: TASSNEEM IBRAHIM | D37: ASSIST. INFORMATION | E37: 8(9) | F37: =13112.16 -> 13112.16 | H37: =F37*300% -> 39336.48 | I37: =F37*7.5% -> 983.412 | K37: =F37*50% -> 6556.08 | L37: =F37*350% -> 45892.56 | M37: =F37*100% -> 13112.16 | O37: =50000 -> 50000 | P37: =F37*10% -> 1311.216 | Q37: 10000 | S37: =R37+Q37+P37+O37+N37+M37+L37+K37+J37+I37+H37+G37+F37 -> 180304.07 | T37: 176816.1 | U37: =S37-T37 -> 3487.968 | W37: =1484.37 -> 1484.37 | X37: 1484.37 | Y37: =X37-W37 -> 0
A38: 30 | B38: JIMOH ADEBAYO ZAKA | D38: ASST. OFFICER/COMM | E38: 8(7) | F38: =12351.94 -> 12351.94 | H38: =F38*300% -> 37055.82 | I38: =F38*7.5% -> 926.3955 | K38: =F38*50% -> 6175.97 | L38: =F38*350% -> 43231.79 | M38: =F38*100% -> 12351.94 | O38: =50000 -> 50000 | P38: =F38*10% -> 1235.194 | Q38: 10000 | S38: =R38+Q38+P38+O38+N38+M38+L38+K38+J38+I38+H38+G38+F38 -> 173329.05 | T38: 173329.05 | U38: =S38-T38 -> 0 | W38: =1484.37 -> 1484.37 | X38: 1484.37 | Y38: =X38-W38 -> 0
B39: TOTAL | D39: 30 | F39: =SUM(F9:F38) -> 942987.95 | G39: =SUM(G9:G38) -> 0 | H39: =SUM(H9:H38) -> 2668475.1 | I39: =SUM(I9:I38) -> 106834.07 | J39: =SUM(J9:J38) -> 826982.66 | K39: =SUM(K9:K38) -> 463469.54 | L39: =SUM(L9:L38) -> 2738747.2 | M39: =SUM(M9:M38) -> 902865.77 | ... S39: =SUM(S9:S38) -> 12789896 | T39: 12388713 | U39: =SUM(U9:U38) -> 135911.2 | W39: =SUM(W9:W38) -> 411374.07 | X39: 411374.07 | Y39: =X39-W39 -> 0
U40: =S40-T40 -> 0 | Y40: =X40-W40 -> 0
B41: INTERNAL AUDIT | U41: =S41-T41 -> 0 | Y41: =X41-W41 -> 0
A42: 1 | B42: OSANAIYE DAVID AKINYEMI | D42: DIRECTOR INTERNAL AUDIT | E42: 17(8) | F42: =79039.64 -> 79039.64 | H42: =F42*300% -> 237118.92 | I42: =F42*7.5% -> 5927.973 | J42: 80244.38 | K42: =F42*50% -> 39519.82 | L42: =F42*350% -> 276638.74 | M42: =F42*100% -> 79039.64 | O42: =100000 -> 100000 | P42: =F42*10% -> 7903.964 | Q42: 20000 | S42: =SUM(F42:R42) -> 925433.08 | T42: 900657.46 | U42: =S42-T42 -> 24775.619 | W42: =(52776.63) -> 52776.63 | X42: 52776.63 | Y42: =X42-W42 -> 0
C43: TOTAL | D43: 1 | F43: =SUM(F42:F42) -> 79039.64 | G43: =SUM(G42:G42) -> 0 | H43: =SUM(H42:H42) -> 237118.92 | I43: =SUM(I42:I42) -> 5927.973 | J43: =SUM(J42:J42) -> 80244.38 | K43: =SUM(K42:K42) -> 39519.82 | L43: =SUM(L42:L42) -> 276638.74 | M43: =SUM(M42:M42) -> 79039.64 | O43: =SUM(O42:O42) -> 100000 | P43: =SUM(P42:P42) -> 7903.964 | Q43: =SUM(Q42:Q42) -> 20000 | R43: =SUM(R42:R42) -> 0 | S43: =SUM(S42:S42) -> 925433.08 | T43: 900657.46 | U43: =S43-T43 -> 24775.619 | W43: =SUM(W42:W42) -> 52776.63 | X43: 52776.63 | Y43: =X43-W43 -> 0
U44: =S44-T44 -> 0 | Y44: =X44-W44 -> 0
B45: LEG. SUPPORT SEVICES | U45: =S45-T45 -> 0 | Y45: =X45-W45 -> 0
A46: 1 | B46: PROF. EDOBA BRIGHT OMOREGBE | D46: AG. DLSS | E46: 17(9) | F46: =81740.02 -> 81740.02 | H46: =F46*300% -> 245220.06 | I46: =F46*7.5% -> 6130.5015 | J46: 80244.38 | K46: =F46*50% -> 40870.01 | L46: =F46*350% -> 286090.07 | M46: =F46*100% -> 81740.02 | N46: =200000 -> 200000 | P46: =F46*10% -> 8174.002 | Q46: 20000 | S46: =SUM(F46:R46) -> 1050209.1 | T46: 1050209.1 | U46: =S46-T46 -> 0 | W46: =52776.63 -> 52776.63 | X46: 52776.63 | Y46: =X46-W46 -> 0
A47: 2 | B47: DR CLINTON JAJA | D47: SENIOR RESEARCH FELLOW | E47: 15(9) | F47: =33507.5 -> 33507.5 | H47: =F47*300% -> 100522.5 | I47: =F47*7.5% -> 2513.0625 | J47: 40122.19 | K47: =F47*50% -> 16753.75 | L47: =F47*350% -> 117276.25 | M47: =F47*100% -> 33507.5 | N47: =160000 -> 160000 | P47: =F47*10% -> 3350.75 | Q47: 20000 | R47: 0 | S47: =SUM(F47:R47) -> 527553.5 | T47: 527553.5 | U47: =S47-T47 -> 0 | W47: 15548.33 | X47: 15548.33 | Y47: =X47-W47 -> 0
A48: 3 | B48: BETHEL UZOMA IHUGBA | D48: SNR RESEARCH FELLOW | E48: 15(9) | F48: =33507.5 -> 33507.5 | H48: =F48*300% -> 100522.5 | I48: =F48*7.5% -> 2513.0625 | J48: 40122.19 | K48: =F48*50% -> 16753.75 | L48: =F48*350% -> 117276.25 | M48: =F48*100% -> 33507.5 | N48: =160000 -> 160000 | P48: =F48*10% -> 3350.75 | Q48: 20000 | S48: =SUM(F48:R48) -> 527553.5 | T48: 527553.5 | U48: =S48-T48 -> 0 | W48: 15548.33 | X48: 15548.33 | Y48: =X48-W48 -> 0
A49: 4 | B49: OGUCHE SAMUEL | D49: SNR RESEARCH FELLOW | E49: 15(8) | F49: =32263.2 -> 32263.2 | H49: =F49*300% -> 96789.6 | I49: =F49*7.5% -> 2419.74 | J49: 40122.19 | K49: =F49*50% -> 16131.6 | L49: =F49*350% -> 112921.2 | M49: =F49*100% -> 32263.2 | N49: =160000 -> 160000 | P49: =F49*10% -> 3226.32 | Q49: 20000 | S49: =SUM(F49:R49) -> 516137.05 | T49: 504720.05 | U49: =S49-T49 -> 11417.003 | W49: =15548.33 -> 15548.33 | X49: 15548.33 | Y49: =X49-W49 -> 0
A50: 5 | B50: IBRAHIM USMAN | D50: RESEARCH FELLOW I | E50: 14(11) | F50: =28489.81 -> 28489.81 | H50: =F50*300% -> 85469.43 | I50: =F50*7.5% -> 2136.7357 | J50: 0 | K50: =F50*50% -> 14244.905 | L50: =F50*350% -> 99714.335 | M50: =F50*100% -> 28489.81 | N50: =140000 -> 140000 | P50: =F50*10% -> 2848.981 | Q50: 20000 | R50: 0 | S50: =SUM(F50:R50) -> 421394.01 | T50: 421394.01 | U50: =S50-T50 -> 0 | W50: 7709.76 | X50: 7709.76 | Y50: =X50-W50 -> 0
A51: 6 | B51: DR MOHAMMED O. AMALI | D51: RESEARCH FELLOW I | E51: 14(9) | F51: =26732.65 -> 26732.65 | H51: =F51*300% -> 80197.95 | I51: =F51*7.5% -> 2004.9488 | K51: =F51*50% -> 13366.325 | L51: =F51*350% -> 93564.275 | M51: =F51*100% -> 26732.65 | N51: =140000 -> 140000 | P51: =F51*10% -> 2673.265 | Q51: 20000 | S51: =SUM(F51:R51) -> 405272.06 | T51: 397211.37 | U51: =S51-T51 -> 8060.6962 | W51: 7709.76 | X51: 7709.76 | Y51: =X51-W51 -> 0
A52: 7 | B52: YAHAYA SHAMSU | D52: RESEARCH FELLOW 1 | E52: 14(9) | F52: =26732.65 -> 26732.65 | H52: =F52*300% -> 80197.95 | I52: =F52*7.5% -> 2004.9488 | K52: =F52*50% -> 13366.325 | L52: =F52*350% -> 93564.275 | M52: =F52*100% -> 26732.65 | N52: =140000 -> 140000 | P52: =F52*10% -> 2673.265 | Q52: 20000 | S52: =SUM(F52:R52) -> 405272.06 | T52: 397211.37 | U52: =S52-T52 -> 8060.6962 | W52: 7709.76 | X52: 7709.76 | Y52: =X52-W52 -> 0
A53: 8 | B53: OFORDEME ADAOBI JULIA | D53: RESEARCH FELLOW 11 | E53: 13(10) | F53: =25523.45 -> 25523.45 | H53: =F53*300% -> 76570.35 | I53: =F53*7.5% -> 1914.2587 | J53: 0 | K53: =F53*50% -> 12761.725 | L53: =F53*350% -> 89332.075 | M53: =F53*100% -> 25523.45 | N53: =120000 -> 120000 | P53: =F53*10% -> 2552.345 | Q53: 15000 | R53: 0 | S53: =SUM(F53:R53) -> 369177.65 | T53: 362001.06 | U53: =S53-T53 -> 7176.5933 | W53: 7709.76 | X53: 7709.76 | Y53: =X53-W53 -> 0
A54: 9 | B54: IKPEAZU CHINEDU ANITA | D54: RESEARCH FELLOW 1 | E54: 14(8) | F54: =25854.1 -> 25854.1 | H54: =F54*300% -> 77562.3 | I54: =F54*7.5% -> 1939.0575 | J54: 0 | K54: =F54*50% -> 12927.05 | L54: =F54*350% -> 90489.35 | M54: =F54*100% -> 25854.1 | N54: 140000 | P54: =F54*10% -> 2585.41 | Q54: 20000 | R54: 0 | S54: =SUM(F54:R54) -> 397211.37 | T54: 397211.37 | U54: =S54-T54 -> 0 | W54: 7709.76 | X54: 7709.76 | Y54: =X54-W54 -> 0
A55: 10 | B55: DORIS DAKDA AARON | D55: RESEARCH FELLOW II | E55: 13(9) | F55: =24741.26 -> 24741.26 | H55: =F55*300% -> 74223.78 | I55: =F55*7.5% -> 1855.5945 | K55: =F55*50% -> 12370.63 | L55: =F55*350% -> 86594.41 | M55: =F55*100% -> 24741.26 | N55: =120000 -> 120000 | P55: =F55*10% -> 2474.126 | Q55: 15000 | S55: =SUM(F55:R55) -> 362001.06 | T55: 354201.03 | U55: =S55-T55 -> 7800.0345 | W55: =7709.76 -> 7709.76 | X55: 7709.76 | Y55: =X55-W55 -> 0
B56: TOTAL | D56: 10 | F56: =SUM(F46:F55) -> 339092.14 | G56: =SUM(G46:G55) -> 0 | H56: =SUM(H46:H55) -> 1017276.4 | I56: =SUM(I46:I55) -> 25431.91 | J56: =SUM(J46:J55) -> 200610.95 | K56: =SUM(K46:K55) -> 169546.07 | L56: =SUM(L46:L55) -> 1186822.5 | M56: =SUM(M46:M55) -> 339092.14 | N56: =SUM(N46:N55) -> 1480000 | P56: =SUM(P46:P55) -> 33909.214 | Q56: =SUM(Q46:Q55) -> 190000 | R56: =SUM(R46:R55) -> 0 | S56: =SUM(S46:S55) -> 4981781.3 | T56: 4939266.3 | U56: =S56-T56 -> 42515.023 | W56: =SUM(W46:W55) -> 145680.18 | X56: 145680.18 | Y56: =X56-W56 -> 0
U57: =S57-T57 -> 0 | Y57: =X57-W57 -> 0
B58: LEGAL SERVICES | U58: =S58-T58 -> 0 | Y58: =X58-W58 -> 0
A59: 1 | B59: DR SHUIBU DANWANKA | D59: DIRECTOR LEGAL SERVICES | E59: 17(9) | F59: =81740.02 -> 81740.02 | H59: =F59*300% -> 245220.06 | I59: =F59*7.5% -> 6130.5015 | J59: 80244.38 | K59: =F59*50% -> 40870.01 | L59: =F59*350% -> 286090.07 | M59: =F59*100% -> 81740.02 | N59: =200000 -> 200000 | P59: =F59*10% -> 8174.002 | Q59: 20000 | R59: 0 | S59: =SUM(F59:R59) -> 1050209.1 | T59: 1050209.1 | U59: =S59-T59 -> 0 | W59: 52776.63 | X59: 52776.63 | Y59: =X59-W59 -> 0
A60: 2 | B60: ABDULSALAM BAKO | D60: MANAGER, LEGAL SERVICES | E60: 15 (8) | F60: =32263.2 -> 32263.2 | H60: =F60*300% -> 96789.6 | I60: =F60*7.5% -> 2419.74 | J60: 40122.19 | K60: =F60*50% -> 16131.6 | L60: =F60*350% -> 112921.2 | M60: =F60*100% -> 32263.2 | O60: =80000 -> 80000 | P60: =F60*10% -> 3226.32 | Q60: 20000 | R60: 0 | S60: =SUM(F60:R60) -> 436137.05 | T60: 424720.05 | U60: =S60-T60 -> 11417.003 | W60: =15548.33 -> 15548.33 | X60: 15548.33 | Y60: =X60-W60 -> 0
B61: TOTAL | D61: 2 | F61: =SUM(F59:F60) -> 114003.22 | H61: =SUM(H59:H60) -> 342009.66 | I61: =SUM(I59:I60) -> 8550.2415 | J61: =SUM(J59:J60) -> 120366.57 | K61: =SUM(K59:K60) -> 57001.61 | L61: =SUM(L59:L60) -> 399011.27 | M61: =SUM(M59:M60) -> 114003.22 | N61: =SUM(N59:N60) -> 200000 | O61: =SUM(O59:O60) -> 80000 | ... S61: =SUM(S59:S60) -> 1486346.1 | T61: 1474929.1 | U61: =S61-T61 -> 11417.003 | W61: =SUM(W59:W60) -> 68324.96 | X61: 68324.96 | Y61: =X61-W61 -> 0
U62: =S62-T62 -> 0 | Y62: =X62-W62 -> 0
B63: DEMOCRACY AND GOVERNANCE | U63: =S63-T63 -> 0 | Y63: =X63-W63 -> 0
A64: 1 | B64: DR. ADEWALE ADEREMI | D64: DIRECTOR, DEMOCRATIC STUDIES | E64: 17(9) | F64: =81740.02 -> 81740.02 | H64: =F64*300% -> 245220.06 | I64: =F64*7.5% -> 6130.5015 | J64: 80244.38 | K64: =F64*50% -> 40870.01 | L64: =F64*350% -> 286090.07 | M64: =F64*100% -> 81740.02 | N64: =200000 -> 200000 | P64: =F64*10% -> 8174.002 | Q64: 20000 | R64: 0 | S64: 1050209.1 | T64: 1025433.1 | U64: =S64-T64 -> 24775.987 | W64: =52776.63 -> 52776.63 | X64: 52776.63 | Y64: =X64-W64 -> 0
A65: 2 | B65: NDANUSA MOHAMMED MANZUMA | D65: SNR RESEARCH FELLOW | E65: 15 (7) | F65: 31018.84 | H65: =F65*300% -> 93056.52 | I65: =F65*7.5% -> 2326.413 | J65: 40122.19 | K65: =F65*50% -> 15509.42 | L65: =F65*350% -> 108565.94 | M65: =F65*100% -> 31018.84 | N65: =160000 -> 160000 | P65: =F65*10% -> 3101.884 | Q65: 20000 | R65: 0 | S65: =SUM(F65:R65) -> 504720.05 | T65: 504720.05 | U65: =S65-T65 -> 0 | W65: =15548.33 -> 15548.33 | X65: 15548.33 | Y65: =X65-W65 -> 0
A66: 3 | B66: EMILY EDOISA IKHIDE | D66: RESEARCH FELLOW II | E66: 13(11) | F66: =26339.3 -> 26339.3 | H66: =F66*300% -> 79017.9 | I66: =F66*7.5% -> 1975.4475 | K66: =F66*50% -> 13169.65 | L66: =F66*350% -> 92187.55 | M66: =F66*100% -> 26339.3 | N66: =120000 -> 120000 | P66: =F66*10% -> 2633.93 | Q66: 15000 | S66: =SUM(F66:R66) -> 376663.08 | T66: 369177.65 | U66: =S66-T66 -> 7485.4237 | W66: 7709.76 | X66: 7709.76 | Y66: =X66-W66 -> 0
A67: 4 | B67: EJALONIBU GANIYU LAYI | D67: RESEARCH FELLOW 11 | E67: 13(9) | F67: =24741.26 -> 24741.26 | H67: =F67*300% -> 74223.78 | I67: =F67*7.5% -> 1855.5945 | K67: =F67*50% -> 12370.63 | L67: =F67*350% -> 86594.41 | M67: =F67*100% -> 24741.26 | N67: =120000 -> 120000 | P67: =F67*10% -> 2474.126 | Q67: 15000 | S67: =SUM(F67:R67) -> 362001.06 | T67: 354201.03 | U67: =S67-T67 -> 7800.0345 | W67: =7709.76 -> 7709.76 | X67: 7709.76 | Y67: =X67-W67 -> 0
A68: 5 | B68: LONA POLIT BONKAT | D68: RESEARCH FELLOW 11 | E68: 13(8) | F68: =23891.12 -> 23891.12 | H68: =F68*300% -> 71673.36 | I68: =F68*7.5% -> 1791.834 | J68: 0 | K68: =F68*50% -> 11945.56 | L68: =F68*350% -> 83618.92 | M68: =F68*100% -> 23891.12 | N68: =120000 -> 120000 | P68: =F68*10% -> 2389.112 | Q68: 15000 | R68: 0 | S68: =SUM(F68:R68) -> 354201.03 | T68: 346713.03 | U68: =S68-T68 -> 7487.9927 | W68: 7709.76 | X68: 7709.76 | Y68: =X68-W68 -> 0
A69: 6 | B69: YUNUSA ABDULLAHI | D69: RESEARCH FELLOW 1 | E69: 14(9) | F69: =26732.65 -> 26732.65 | H69: =F69*300% -> 80197.95 | I69: =F69*7.5% -> 2004.9488 | K69: =F69*50% -> 13366.325 | L69: =F69*350% -> 93564.275 | M69: =F69*100% -> 26732.65 | N69: =140000 -> 140000 | P69: =F69*10% -> 2673.265 | Q69: 20000 | S69: =SUM(F69:R69) -> 405272.06 | T69: 397211.37 | U69: =S69-T69 -> 8060.6962 | W69: =7709.76 -> 7709.76 | X69: 7709.76 | Y69: =X69-W69 -> 0
A70: 7 | B70: UDEFUNA NNADOZIE PATRICK | D70: RESEARCH OFFICER | E70: 10(13) | F70: =19774.62 -> 19774.62 | H70: =F70*300% -> 59323.86 | I70: =F70*7.5% -> 1483.0965 | J70: 0 | K70: =F70*50% -> 9887.31 | L70: =F70*350% -> 69211.17 | M70: =F70*100% -> 19774.62 | N70: =100000 -> 100000 | P70: =F70*10% -> 1977.462 | Q70: 10000 | R70: 0 | S70: =SUM(F70:R70) -> 291432.14 | T70: 291432.14 | U70: =S70-T70 -> 0 | W70: 3369.51 | X70: 3369.51 | Y70: =X70-W70 -> 0
A71: 8 | B71: OSOLAFIA MUHAMMAD EGYE | D71: RESEARCH OFFICER | E71: 12(8) | F71: =21520.88 -> 21520.88 | H71: =F71*300% -> 64562.64 | I71: =F71*7.5% -> 1614.066 | J71: 0 | K71: =F71*50% -> 10760.44 | L71: =F71*350% -> 75323.08 | M71: =F71*100% -> 21520.88 | N71: =110000 -> 110000 | P71: =F71*10% -> 2152.088 | Q71: 15000 | R71: 0 | S71: =SUM(F71:R71) -> 322454.07 | T71: 315372.08 | U71: =S71-T71 -> 7081.999 | W71: =3369.51 -> 3369.51 | X71: 3369.51 | Y71: =X71-W71 -> 0
A72: 9 | B72: HAUWA PATE SADIQ | D72: PROGRAMME OFFICER | E72: 10(10) | F72: =18779.3 -> 18779.3 | H72: =F72*300% -> 56337.9 | I72: =F72*7.5% -> 1408.4475 | K72: =F72*50% -> 9389.65 | L72: =F72*350% -> 65727.55 | M72: =F72*100% -> 18779.3 | N72: =100000 -> 100000 | P72: =F72*10% -> 1877.93 | Q72: 10000 | S72: =SUM(F72:R72) -> 282300.08 | T72: 277734.05 | U72: =S72-T72 -> 4566.0305 | W72: 3369.51 | X72: 3369.51 | Y72: =X72-W72 -> 0
A73: 10 | B73: ABAYOMI KAYODE QUADRI | D73: RESEARCH OFFICER | E73: 10(7) | F73: =17286.33 -> 17286.33 | H73: =F73*300% -> 51858.99 | I73: =F73*7.5% -> 1296.4748 | K73: =F73*50% -> 8643.165 | L73: =F73*350% -> 60502.155 | M73: =F73*100% -> 17286.33 | N73: =100000 -> 100000 | P73: =F73*10% -> 1728.633 | Q73: 10000 | S73: =SUM(F73:R73) -> 268602.08 | T73: 268602.08 | U73: =S73-T73 -> 0 | W73: 3369.51 | X73: 3369.51 | Y73: =X73-W73 -> 0
A74: 11 | B74: NNANDI LIVINUS ATURE | D74: RESEARCH ASSISTANT | E74: 8(7) | F74: =12351.94 -> 12351.94 | H74: =F74*300% -> 37055.82 | I74: =F74*7.5% -> 926.3955 | K74: =F74*50% -> 6175.97 | L74: =F74*350% -> 43231.79 | M74: =F74*100% -> 12351.94 | N74: =100000 -> 100000 | P74: =F74*10% -> 1235.194 | Q74: 10000 | S74: =SUM(F74:R74) -> 223329.05 | T74: 223329.05 | U74: =S74-T74 -> 0 | W74: 1484.37 | X74: 1484.37 | Y74: =X74-W74 -> 0
A75: 12 | B75: LUCKY AGWOM | D75: RESEARCH ASSISTANT | E75: 8(7) | F75: =12351.94 -> 12351.94 | H75: =F75*300% -> 37055.82 | I75: =F75*7.5% -> 926.3955 | K75: =F75*50% -> 6175.97 | L75: =F75*350% -> 43231.79 | M75: =F75*100% -> 12351.94 | N75: =100000 -> 100000 | P75: =F75*10% -> 1235.194 | Q75: 10000 | S75: =SUM(F75:R75) -> 223329.05 | T75: 223329.05 | U75: =S75-T75 -> 0 | W75: 1484.37 | X75: 1484.37 | Y75: =X75-W75 -> 0
B76: TOTAL | D76: 12 | F76: =SUM(F64:F75) -> 316528.2 | G76: =SUM(G64:G75) -> 0 | H76: =SUM(H64:H75) -> 949584.6 | I76: =SUM(I64:I75) -> 23739.615 | J76: =SUM(J64:J75) -> 120366.57 | K76: =SUM(K64:K75) -> 158264.1 | L76: =SUM(L64:L75) -> 1107848.7 | M76: =SUM(M64:M75) -> 316528.2 | N76: =SUM(N64:N75) -> 1470000 | P76: =SUM(P64:P75) -> 31652.82 | Q76: =SUM(Q64:Q75) -> 170000 | R76: =SUM(R64:R75) -> 0 | S76: =SUM(S64:S75) -> 4664512.8 | T76: 4597254.6 | U76: =S76-T76 -> 67258.163 | W76: =SUM(W64:W75) -> 115610.78 | X76: 115610.78 | Y76: =X76-W76 -> 0
U77: =S77-T77 -> 0 | Y77: =X77-W77 -> 0
B78: STUDIES | U78: =S78-T78 -> 0 | Y78: =X78-W78 -> 0
A79: 1 | B79: DR ASIMIYU G. ABIOLA | D79: DIRECTOR POST GRADUATE | E79: 17(9) | F79: =81740.02 -> 81740.02 | H79: =F79*300% -> 245220.06 | I79: =F79*7.5% -> 6130.5015 | J79: 80244.38 | K79: =F79*50% -> 40870.01 | L79: =F79*350% -> 286090.07 | M79: =F79*100% -> 81740.02 | N79: =200000 -> 200000 | P79: =F79*10% -> 8174.002 | Q79: 20000 | R79: 0 | S79: =SUM(F79:R79) -> 1050209.1 | T79: 1050209.1 | U79: =S79-T79 -> 0 | W79: 52776.63 | X79: 52776.63 | Y79: =X79-W79 -> 0
A80: 2 | B80: USMAN WALI | D80: SENIOR RESEARCH FELLOW | E80: 15 (7) | F80: 31018.84 | H80: =F80*300% -> 93056.52 | I80: =F80*7.5% -> 2326.413 | J80: 40122.19 | K80: =F80*50% -> 15509.42 | L80: =F80*350% -> 108565.94 | M80: =F80*100% -> 31018.84 | N80: =160000 -> 160000 | P80: =F80*10% -> 3101.884 | Q80: 20000 | R80: 0 | S80: =SUM(F80:R80) -> 504720.05 | T80: 504720.05 | U80: =S80-T80 -> 0 | W80: =15548.33 -> 15548.33 | X80: 15548.33 | Y80: =X80-W80 -> 0
A81: 3 | B81: MOSHOOD TOSHO AMUDA | D81: MANAGER, EXAMS & RECORDS | E81: 15 (7) | F81: 31018.84 | H81: =F81*300% -> 93056.52 | I81: =F81*7.5% -> 2326.413 | J81: 40122.19 | K81: =F81*50% -> 15509.42 | L81: =F81*350% -> 108565.94 | M81: =F81*100% -> 31018.84 | N81: =160000 -> 160000 | P81: =F81*10% -> 3101.884 | Q81: 20000 | R81: 0 | S81: =SUM(F81:R81) -> 504720.05 | T81: 504720.05 | U81: =S81-T81 -> 0 | W81: =15548.33 -> 15548.33 | X81: 15548.33 | Y81: =X81-W81 -> 0
A82: 4 | B82: UZODINMA EMMANUEL EZENWA | D82: RESEARCH FELLOW II | E82: 13(9) | F82: =24741.26 -> 24741.26 | H82: =F82*300% -> 74223.78 | I82: =F82*7.5% -> 1855.5945 | J82: 0 | K82: =F82*50% -> 12370.63 | L82: =F82*350% -> 86594.41 | M82: =F82*100% -> 24741.26 | N82: =120000 -> 120000 | P82: =F82*10% -> 2474.126 | Q82: 15000 | R82: 0 | S82: =SUM(F82:R82) -> 362001.06 | T82: 354201.03 | U82: =S82-T82 -> 7800.0345 | W82: =7709.76 -> 7709.76 | X82: 7709.76 | Y82: =X82-W82 -> 0
A83: 5 | B83: IGWE STACY | D83: PROGRAMME OFFICER | E83: 10(7) | F83: =17286.33 -> 17286.33 | H83: =F83*300% -> 51858.99 | I83: =F83*7.5% -> 1296.4748 | K83: =F83*50% -> 8643.165 | L83: =F83*350% -> 60502.155 | M83: =F83*100% -> 17286.33 | N83: =100000 -> 100000 | P83: =F83*10% -> 1728.633 | Q83: 10000 | S83: =SUM(F83:R83) -> 268602.08 | T83: 268602.08 | U83: =S83-T83 -> 0 | W83: 3369.51 | X83: 3369.51 | Y83: =X83-W83 -> 0
A84: 6 | B84: DARE SHEU MAGBON | D84: ASSIST. PG | E84: 8(9) | F84: =13112.16 -> 13112.16 | H84: =F84*300% -> 39336.48 | I84: =F84*7.5% -> 983.412 | K84: =F84*50% -> 6556.08 | L84: =F84*350% -> 45892.56 | M84: =F84*100% -> 13112.16 | N84: =100000 -> 100000 | P84: =F84*10% -> 1311.216 | Q84: 10000 | S84: =SUM(F84:R84) -> 230304.07 | T84: 226816.1 | U84: =S84-T84 -> 3487.968 | W84: 1484.37 | X84: 1484.37 | Y84: =X84-W84 -> 0
A85: 7 | B85: MOHAMMED BELLO | D85: RESEARCH ASSITANT PG | E85: 8(7) | F85: =12351.94 -> 12351.94 | H85: =F85*300% -> 37055.82 | I85: =F85*7.5% -> 926.3955 | K85: =F85*50% -> 6175.97 | L85: =F85*350% -> 43231.79 | M85: =F85*100% -> 12351.94 | N85: =100000 -> 100000 | P85: =F85*10% -> 1235.194 | Q85: 10000 | S85: =SUM(F85:R85) -> 223329.05 | T85: 223329.05 | U85: =S85-T85 -> 0 | W85: 1484.37 | X85: 1484.37 | Y85: =X85-W85 -> 0
B86: TOTAL | D86: 7 | F86: =SUM(F79:F85) -> 211269.39 | H86: =SUM(H79:H85) -> 633808.17 | I86: =SUM(I79:I85) -> 15845.204 | J86: =SUM(J79:J85) -> 160488.76 | K86: =SUM(K79:K85) -> 105634.7 | L86: =SUM(L79:L85) -> 739442.86 | M86: =SUM(M79:M85) -> 211269.39 | N86: =SUM(N79:N85) -> 940000 | P86: =SUM(P79:P85) -> 21126.939 | Q86: =SUM(Q79:Q85) -> 105000 | R86: =SUM(R79:R85) -> 0 | S86: =SUM(S79:S85) -> 3143885.4 | T86: 3132597.4 | U86: =S86-T86 -> 11288.002 | W86: =SUM(W79:W85) -> 97921.3 | X86: 97921.3 | Y86: =X86-W86 -> 0
U87: =S87-T87 -> 0 | Y87: =X87-W87 -> 0
B88: ECONOMIC DEV. AND SOCIAL RESEARCH | U88: =S88-T88 -> 0 | Y88: =X88-W88 -> 0
A89: 1 | B89: DR ASEMOTA OMOROGBE JOSEPH | D89: Ag. DEPUTY DIRECTOR, ECO & SOC DEV DEPT | E89: 16(8) | F89: =41157.69 -> 41157.69 | H89: =F89*300% -> 123473.07 | I89: =F89*7.5% -> 3086.8268 | J89: 40122.19 | K89: =F89*50% -> 20578.845 | L89: =F89*350% -> 144051.92 | M89: =F89*100% -> 41157.69 | N89: =180000 -> 180000 | P89: =F89*10% -> 4115.769 | Q89: 20000 | S89: =SUM(F89:R89) -> 617744 | T89: 604023.33 | U89: =S89-T89 -> 13720.662 | W89: =21618.09 -> 21618.09 | X89: 21618.09 | Y89: =X89-W89 -> 0
A90: 2 | B90: TERFA WILLIAMS ABRAHAM | D90: SNR RESEARCH FELLOW | E90: 15(9) | F90: =33507.5 -> 33507.5 | H90: =F90*300% -> 100522.5 | I90: =F90*7.5% -> 2513.0625 | J90: =40122.19 -> 40122.19 | K90: =F90*50% -> 16753.75 | L90: =F90*350% -> 117276.25 | M90: =F90*100% -> 33507.5 | N90: =160000 -> 160000 | P90: =F90*10% -> 3350.75 | Q90: 20000 | S90: =SUM(F90:R90) -> 527553.5 | T90: 516137.05 | U90: =S90-T90 -> 11416.452 | W90: =15548.33 -> 15548.33 | X90: 15548.33 | Y90: =X90-W90 -> 0
A91: 3 | B91: DR AUGUSTINE C. OSIGWE | D91: SNR RESEARCH FELLOW | E91: 15(9) | F91: =33507.5 -> 33507.5 | H91: =F91*300% -> 100522.5 | I91: =F91*7.5% -> 2513.0625 | J91: =40122.19 -> 40122.19 | K91: =F91*50% -> 16753.75 | L91: =F91*350% -> 117276.25 | M91: =F91*100% -> 33507.5 | N91: =160000 -> 160000 | P91: =F91*10% -> 3350.75 | Q91: 20000 | S91: =SUM(F91:R91) -> 527553.5 | T91: 516137.05 | U91: =S91-T91 -> 11416.452 | W91: =15548.33 -> 15548.33 | X91: 15548.33 | Y91: =X91-W91 -> 0
A92: 4 | B92: JUMARE FADILA | D92: RESEARCH FELLOW I | E92: 14(9) | F92: =26732.65 -> 26732.65 | H92: =F92*300% -> 80197.95 | I92: =F92*7.5% -> 2004.9488 | J92: 0 | K92: =F92*50% -> 13366.325 | L92: =F92*350% -> 93564.275 | M92: =F92*100% -> 26732.65 | N92: 140000 | P92: =F92*10% -> 2673.265 | Q92: 20000 | R92: 0 | S92: =SUM(F92:R92) -> 405272.06 | T92: 397211.37 | U92: =S92-T92 -> 8060.6962 | W92: =7709.76 -> 7709.76 | X92: 7709.76 | Y92: =X92-W92 -> 0
A93: 5 | B93: NGARA CHRISTOPHER OCHANJA | D93: RESEARCH FELLOW 1 | E93: 14(10) | F93: =27611.23 -> 27611.23 | H93: =F93*300% -> 82833.69 | I93: =F93*7.5% -> 2070.8422 | K93: =F93*50% -> 13805.615 | L93: =F93*350% -> 96639.305 | M93: =F93*100% -> 27611.23 | N93: 140000 | P93: =F93*10% -> 2761.123 | Q93: 20000 | R93: 0 | S93: =SUM(F93:R93) -> 413333.04 | T93: 405272.06 | U93: =S93-T93 -> 8060.9715 | W93: =7709.76 -> 7709.76 | X93: 7709.76 | Y93: =X93-W93 -> 0
A94: 6 | B94: OMOJU OLUWASOLA EMMANUEL | D94: RESEARCH FELLOW I | E94: 14(9) | F94: =26732.65 -> 26732.65 | H94: =F94*300% -> 80197.95 | I94: =F94*7.5% -> 2004.9488 | K94: =F94*50% -> 13366.325 | L94: =F94*350% -> 93564.275 | M94: =F94*100% -> 26732.65 | N94: 140000 | P94: =F94*10% -> 2673.265 | Q94: 20000 | S94: =SUM(F94:R94) -> 405272.06 | T94: 397211.37 | U94: =S94-T94 -> 8060.6962 | W94: =7709.76 -> 7709.76 | X94: 7709.76 | Y94: =X94-W94 -> 0
A95: 7 | B95: RIFKATU NGHARGBU | D95: RESEARCH FELLOW 1 | E95: 14(8) | F95: =25854.1 -> 25854.1 | H95: =F95*300% -> 77562.3 | I95: =F95*7.5% -> 1939.0575 | J95: 0 | K95: =F95*50% -> 12927.05 | L95: =F95*350% -> 90489.35 | M95: =F95*100% -> 25854.1 | N95: 140000 | P95: =F95*10% -> 2585.41 | Q95: 20000 | R95: `12333 | S95: =SUM(F95:R95) -> 397211.37 | T95: 389153.06 | U95: =S95-T95 -> 8058.3108 | W95: =7709.76 -> 7709.76 | X95: 7709.76 | Y95: =X95-W95 -> 0
A96: 8 | B96: IBE EZECHI CYRIACUS | D96: RESEARCH FELLOW II | E96: 13(9) | F96: =24741.26 -> 24741.26 | H96: =F96*300% -> 74223.78 | I96: =F96*7.5% -> 1855.5945 | J96: 0 | K96: =F96*50% -> 12370.63 | L96: =F96*350% -> 86594.41 | M96: =F96*100% -> 24741.26 | N96: =120000 -> 120000 | P96: =F96*10% -> 2474.126 | Q96: 15000 | R96: 0 | S96: =SUM(F96:R96) -> 362001.06 | T96: 354201.03 | U96: =S96-T96 -> 7800.0345 | W96: =7709.76 -> 7709.76 | X96: 7709.76 | Y96: =X96-W96 -> 0
A97: 9 | B97: OSIKHEN LEO IGBANOI | D97: RESEARCH FELLOW 11 | E97: 13(8) | F97: =23891.12 -> 23891.12 | H97: =F97*300% -> 71673.36 | I97: =F97*7.5% -> 1791.834 | J97: 0 | K97: =F97*50% -> 11945.56 | L97: =F97*350% -> 83618.92 | M97: =F97*100% -> 23891.12 | N97: =120000 -> 120000 | P97: =F97*10% -> 2389.112 | Q97: 15000 | R97: 0 | S97: =SUM(F97:R97) -> 354201.03 | T97: 346713.03 | U97: =S97-T97 -> 7487.9927 | W97: =7709.76 -> 7709.76 | X97: 7709.76 | Y97: =X97-W97 -> 0
A98: 10 | B98: OKUNGBOWA OSARETIN GODSPOWER | D98: RESEARCH FELLOW 11 | E98: 13(8) | F98: =23891.12 -> 23891.12 | H98: =F98*300% -> 71673.36 | I98: =F98*7.5% -> 1791.834 | J98: 0 | K98: =F98*50% -> 11945.56 | L98: =F98*350% -> 83618.92 | M98: =F98*100% -> 23891.12 | N98: =120000 -> 120000 | P98: =F98*10% -> 2389.112 | Q98: 15000 | R98: 0 | S98: =SUM(F98:R98) -> 354201.03 | T98: 346713.03 | U98: =S98-T98 -> 7487.9927 | W98: =7709.76 -> 7709.76 | X98: 7709.76 | Y98: =X98-W98 -> 0
B99: TOTAL | D99: 10 | F99: =SUM(F89:F98) -> 287626.82 | H99: =SUM(H89:H98) -> 862880.46 | I99: =SUM(I89:I98) -> 21572.011 | J99: =SUM(J89:J98) -> 120366.57 | K99: =SUM(K89:K98) -> 143813.41 | L99: =SUM(L89:L98) -> 1006693.9 | M99: =SUM(M89:M98) -> 287626.82 | N99: =SUM(N89:N98) -> 1420000 | P99: =SUM(P89:P98) -> 28762.682 | Q99: =SUM(Q89:Q98) -> 185000 | R99: =SUM(R89:R98) -> 0 | S99: =SUM(S89:S98) -> 4364342.6 | T99: 4272772.4 | U99: =S99-T99 -> 91570.262 | W99: =SUM(W89:W98) -> 106683.07 | X99: 106683.07 | Y99: =X99-W99 -> 0
U100: =S100-T100 -> 0 | Y100: =X100-W100 -> 0
B101: TRAINING AND INTERNATIONAL COOP | U101: =S101-T101 -> 0 | Y101: =X101-W101 -> 0
A102: 1 | B102: REKIYA IBRAHIM ATTAH | D102: DEPUTY DIRECTOR TRAINING | E102: 16(8) | F102: =41157.69 -> 41157.69 | H102: =F102*300% -> 123473.07 | I102: =F102*7.5% -> 3086.8268 | J102: 40122.19 | K102: =F102*50% -> 20578.845 | L102: =F102*350% -> 144051.92 | M102: =F102*100% -> 41157.69 | O102: =90000 -> 90000 | P102: =F102*10% -> 4115.769 | Q102: 20000 | S102: =SUM(F102:R102) -> 527744 | T102: 514023.33 | U102: =S102-T102 -> 13720.662 | W102: =21618.09 -> 21618.09 | X102: 21618.09 | Y102: =X102-W102 -> 0
...

Sheet Enhanced Welfare 2022
B3: STAFF PAYROLL FOR THE MONTH OF FEBRUARY 2022
B5: STAFF NAME
D6: DESIGNATION | E6: SALARY
E7: LEVEL | G7: 15 and Above | H7: 9 to 14 | I7: 8 and Below
A8: S/N | B8: DG OFFICE | F8: N | H8: N | I8: N
A9: 1 | B9: PROF. ABUBAKAR O. SULAIMAN | D9: DIRECTOR GENERAL | E9: CONSOL | F9: =2000000 -> 2000000 | G9: =F9 -> 2000000
A10: 2 | B10: DR ADEYEMI AKEEB FAJINGBESI | D10: DIR. SPECIAL DUTIES, DG OFFICE | E10: 17(9) | F10: =1000000 -> 1000000 | G10: =F10 -> 1000000
A11: 3 | B11: DR JAKE DABANG DAN AZUMI | D11: DEPUTY DIRECTOR TRAINING | E11: 16(8) | F11: =700000 -> 700000 | G11: =F11 -> 700000
A12: 4 | B12: DR ABDULSALAM NASIRU NAEEM | D12: SA ACADEMICS | E12: 16(8) | F12: =700000 -> 700000 | G12: =F12 -> 700000
A13: 5 | B13: RAHEEM USMAN AYIGORO | D13: SA-INFRASTRUCTURE | E13: 16 (8) | F13: =350000 -> 350000 | G13: =F13 -> 350000
A14: 6 | B14: AKINSANMI ADEJOKE OLUKEMI | D14: HEAD INFORMATION/PROTOCOL | E14: 15(9) | F14: =700000 -> 700000 | G14: =F14 -> 700000
A15: 7 | B15: DR IKEME ARTHUR J.O | D15: SNR RESEARCH FELLOW | E15: 15(9) | F15: =700000 -> 700000 | G15: =F15 -> 700000
A16: 8 | B16: MOSHOOD M. OLALERE | D16: MANAGER ADMIN DG's OFFICE | E16: 15(9) | F16: =700000 -> 700000 | G16: =F16 -> 700000
A17: 9 | B17: ANDRAWUS MUSA | D17: ASST. DIRECTOR, STORE | E17: 15(9) | F17: =700000 -> 700000 | G17: =F17 -> 700000
A18: 10 | B18: AYOBOLU OLAJIDE OLUFUNSHO | D18: ASST.DIR., INFORMATION | E18: 15 (7) | F18: =700000 -> 700000 | G18: =F18 -> 700000
A19: 11 | B19: HUSSEIN EGYE MUSA | D19: CHIEF PROTOCOL OFFICER | E19: 14(9) | F19: 500000 | H19: 500000
A20: 12 | B20: DONALD E. MKPANAM | D20: CHIEF ICT OFFICER | E20: 14(9) | F20: 500000 | H20: 500000
A21: 13 | B21: JOY HARUNA MAKERI | D21: RESEARCH FELLOW 1 TRAINING | E21: 14(9) | F21: 500000 | H21: 500000
A22: 14 | B22: ALI ABDULLAHI | D22: ASST. CHIEF ICT OFFICER | E22: 13(11) | F22: 500000 | H22: 500000
A23: 15 | B23: MARIAM MOHAMMED BELLO | D23: PA- SPECIAL DUTIES | E23: 13 (7) | F23: 500000 | H23: 500000
A24: 16 | B24: PERCY TERFA GBAHABO | D24: HEAD, NILDS LIAISON OFFICE | E24: 13(8) | F24: 500000 | H24: 500000
A25: 17 | B25: ADUGBA RICHARD TERSEER | D25: INFORMATION OFFICER | E25: 10(10) | F25: 300000 | H25: 300000
A26: 18 | B26: CHRISTIAN MADUABUCHI ODO | D26: PRINCIPAL ICT OFFICER | E26: 12(8) | F26: =400000 -> 400000 | H26: =400000 -> 400000
A27: 19 | B27: HASSANA AHMED IBRAHIM | D27: PA- TO DG | E27: 10(9) | F27: 300000 | H27: =500000 -> 500000
A28: 20 | B28: VICTOR ASUKWO | D28: ICT OFFICER | E28: 8 (10) | F28: 300000 | I28: 300000
A29: 21 | B29: SULEIMAN ABUBAKAR SODEEQ | D29: ASST. ADMIN. OFFICER | E29: 8(7) | F29: 300000 | I29: 300000
A30: 22 | B30: YAKUB OLUWATOYIN USMAN | D30: ASST. ADMIN. OFFICER | E30: 10(8) | F30: 300000 | H30: 300000
A31: 23 | B31: ANTHONY EDET | D31: ASST. MGR M&E | E31: 13(9) | F31: 500000 | H31: 500000
A32: 24 | B32: EGUATU U. ONYEJELEM | D32: OFFICER M&E | E32: 10(10) | F32: 300000 | H32: 300000
A33: 25 | B33: ODEH SUZIE | D33: ADMIN. OFFICER, LIASION OFFICE | E33: 10(9) | F33: 300000 | H33: 300000
A34: 26 | B34: IJEOMA NKOLIKWA | D34: ASSISTANT STORES OFFICER | E34: 8(10) | F34: 300000 | I34: 300000
A35: 27 | B35: ABDULRAHMAN A SULAIMAN | D35: ASSISTANT STORES OFFICER | E35: 8 (9) | F35: 300000 | I35: 300000
A36: 28 | B36: TASSNEEM IBRAHIM | D36: ASSIST. INFORMATION | E36: 8(9) | F36: 300000 | I36: 300000
A37: 29 | B37: JIMOH ADEBAYO ZAKA | D37: ASST. OFFICER/COMM | E37: 8(7) | F37: 300000 | I37: 300000
A38: 30 | B38: HABEEBA K MUHAMMAD SALIHU | D38: ASST. OFFICER/COMM | E38: 8(7) | F38: 300000 | I38: 300000
B39: TOTAL | D39: 30 | F39: =SUM(F9:F38) -> 15750000 | G39: =SUM(G9:G38) -> 8250000 | H39: =SUM(H9:H38) -> 5600000 | I39: =SUM(I9:I38) -> 2100000
B41: INTERNAL AUDIT
A42: 1 | B42: OSANAIYE DAVID AKINYEMI | D42: DIRECTOR INTERNAL AUDIT | E42: 17(8) | F42: =1000000 -> 1000000 | G42: =F42 -> 1000000
C43: TOTAL | D43: 1 | F43: =SUM(F42) -> 1000000 | G43: =SUM(G42) -> 1000000
B45: LEG. SUPPORT SEVICES
A46: 1 | B46: PROF. EDOBA BRIGHT OMOREGBE | D46: AG. DLSS | E46: 17(9) | F46: =1000000 -> 1000000 | G46: =F46 -> 1000000 | I46: 0
A47: 2 | B47: DR CLINTON JAJA | D47: SENIOR RESEARCH FELLOW | E47: 15(9) | F47: 700000 | G47: =F47 -> 700000 | I47: 0
A48: 3 | B48: BETHEL UZOMA IHUGBA | D48: SNR RESEARCH FELLOW | E48: 15(9) | F48: 700000 | G48: =F48 -> 700000 | I48: 0
A49: 4 | B49: OGUCHE SAMUEL | D49: SNR RESEARCH FELLOW | E49: 15(8) | F49: 700000 | G49: =F49 -> 700000 | I49: 0
A50: 5 | B50: IBRAHIM USMAN | D50: RESEARCH FELLOW I | E50: 14(11) | F50: 500000 | H50: 500000 | I50: 0
A51: 6 | B51: DR MOHAMMED O. AMALI | D51: RESEARCH FELLOW I | E51: 14(9) | F51: 500000 | H51: 500000 | I51: 0
A52: 7 | B52: YAHAYA SHAMSU | D52: RESEARCH FELLOW 1 | E52: 14(9) | F52: 500000 | H52: 500000 | I52: 0
A53: 8 | B53: OFORDEME ADAOBI JULIA | D53: RESEARCH FELLOW 11 | E53: 13(10) | F53: 500000 | H53: 500000 | I53: 0
A54: 10 | B54: DORIS DAKDA AARON | D54: RESEARCH FELLOW II | E54: 13(9) | F54: 500000 | H54: 500000 | I54: 0
B55: TOTAL | D55: 10 | F55: =SUM(F46:F54) -> 5600000 | G55: =SUM(G46:G54) -> 3100000 | H55: =SUM(H46:H54) -> 2500000
B57: LEGAL SERVICES
A58: 1 | B58: DR SHUIBU DANWANKA | D58: DIRECTOR LEGAL SERVICES | E58: 17(9) | F58: =500000 -> 500000 | G58: =F58 -> 500000
A59: 2 | B59: ABDULSALAM BAKO | D59: MANAGER, LEGAL SERVICES | E59: 15 (8) | F59: =700000 -> 700000 | G59: =F59 -> 700000
B60: TOTAL | D60: 2 | F60: =SUM(F58:F59) -> 1200000 | G60: =SUM(G58:G59) -> 1200000
B62: DEMOCRACY AND GOVERNANCE
A63: 1 | B63: DR. ADEWALE ADEREMI | D63: DIRECTOR, DEMOCRATIC STUDIES | E63: 17(9) | F63: =500000 -> 500000 | G63: =F63 -> 500000
A64: 2 | B64: NDANUSA MOHAMMED MANZUMA | D64: SNR RESEARCH FELLOW | E64: 15 (7) | F64: 350000 | G64: =F64 -> 350000
A65: 3 | B65: EMILY EDOISA IKHIDE | D65: RESEARCH FELLOW II | E65: 13(11) | F65: 500000 | H65: 500000
A66: 4 | B66: EJALONIBU GANIYU LAYI | D66: RESEARCH FELLOW 11 | E66: 13(9) | F66: 500000 | H66: 500000
A67: 5 | B67: LONA POLIT BONKAT | D67: RESEARCH FELLOW 11 | E67: 13(8) | F67: 500000 | H67: 500000
A68: 6 | B68: YUNUSA ABDULLAHI | D68: RESEARCH FELLOW 1 | E68: 14(9) | F68: 500000 | H68: 500000
A69: 7 | B69: UDEFUNA NNADOZIE PATRICK | D69: RESEARCH OFFICER | E69: 10(13) | F69: =300000 -> 300000 | H69: =300000 -> 300000
A70: 8 | B70: OSOLAFIA MUHAMMAD EGYE | D70: RESEARCH OFFICER | E70: 12(8) | F70: 400000 | H70: 400000
A71: 9 | B71: HAUWA PATE SADIQ | D71: PROGRAMME OFFICER | E71: 10(10) | F71: =300000 -> 300000 | H71: =300000 -> 300000
A72: 10 | B72: ABAYOMI KAYODE QUADRI | D72: RESEARCH OFFICER | E72: 10(7) | F72: =300000 -> 300000 | H72: =300000 -> 300000
A73: 11 | B73: NNANDI LIVINUS ATURE | D73: RESEARCH ASSISTANT | E73: 8(7) | F73: =300000 -> 300000 | I73: =300000 -> 300000
A74: 12 | B74: LUCKY AGWOM | D74: RESEARCH ASSISTANT | E74: 8(7) | F74: =300000 -> 300000 | I74: =300000 -> 300000
B75: TOTAL | D75: 12 | F75: =SUM(F63:F74) -> 4750000 | G75: =SUM(G63:G74) -> 850000 | H75: =SUM(H63:H74) -> 3300000 | I75: =SUM(I63:I74) -> 600000
B77: STUDIES
A78: 1 | B78: DR ASIMIYU G. ABIOLA | D78: DIRECTOR POST GRADUATE | E78: 17(9) | F78: 1000000 | G78: =F78 -> 1000000
A79: 2 | B79: USMAN WALI | D79: SENIOR RESEARCH FELLOW | E79: 15 (7) | F79: =700000 -> 700000 | G79: =F79 -> 700000
A80: 3 | B80: MOSHOOD TOSHO AMUDA | D80: MANAGER, EXAMS & RECORDS | E80: 15 (7) | F80: =350000 -> 350000 | G80: =F80 -> 350000
A81: 4 | B81: UZODINMA EMMANUEL EZENWA | D81: RESEARCH FELLOW II | E81: 13(9) | F81: =500000 -> 500000 | H81: =500000 -> 500000
A82: 5 | B82: IGWE STACY | D82: PROGRAMME OFFICER | E82: 10(7) | F82: 300000 | H82: 300000
A83: 6 | B83: DARE SHEU MAGBON | D83: ASSIST. PG | E83: 8(9) | F83: 300000 | I83: 300000
A84: 7 | B84: MOHAMMED BELLO | D84: RESEARCH ASSITANT PG | E84: 8(7) | F84: 300000 | I84: 300000
B85: TOTAL | D85: 7 | F85: =SUM(F78:F84) -> 3450000 | G85: =SUM(G78:G84) -> 2050000 | H85: =SUM(H78:H84) -> 800000 | I85: =SUM(I78:I84) -> 600000
B87: ECONOMIC DEV. AND SOCIAL RESEARCH
A88: 1 | B88: DR ASEMOTA OMOROGBE JOSEPH | D88: Ag. DEPUTY DIRECTOR, ECO & SOC DEV DEPT | E88: 16(8) | F88: =700000 -> 700000 | G88: =F88 -> 700000
A89: 2 | B89: TERFA WILLIAMS ABRAHAM | D89: SNR RESEARCH FELLOW | E89: 15(9) | F89: =700000 -> 700000 | G89: =F89 -> 700000
A90: 3 | B90: DR AUGUSTINE C. OSIGWE | D90: SNR RESEARCH FELLOW | E90: 15(9) | F90: =700000 -> 700000 | G90: =F90 -> 700000
A91: 5 | B91: NGARA CHRISTOPHER OCHANJA | D91: RESEARCH FELLOW 1 | E91: 14(10) | F91: =500000 -> 500000 | H91: =500000 -> 500000
A92: 6 | B92: OMOJU OLUWASOLA EMMANUEL | D92: RESEARCH FELLOW I | E92: 14(9) | F92: =500000 -> 500000 | H92: =500000 -> 500000
A93: 8 | B93: IBE EZECHI CYRIACUS | D93: RESEARCH FELLOW II | E93: 13(9) | F93: =500000 -> 500000 | H93: =500000 -> 500000
A94: 9 | B94: OSIKHEN LEO IGBANOI | D94: RESEARCH FELLOW 11 | E94: 13(8) | F94: =500000 -> 500000 | H94: =500000 -> 500000
A95: 10 | B95: OKUNGBOWA OSARETIN GODSPOWER | D95: RESEARCH FELLOW 11 | E95: 13(8) | F95: =250000 -> 250000 | H95: =250000 -> 250000
B96: TOTAL | D96: 10 | F96: =SUM(F88:F95) -> 4350000 | G96: =SUM(G88:G95) -> 2100000 | H96: =SUM(H88:H95) -> 2250000
B98: TRAINING AND INTERNATIONAL COOP
A99: 1 | B99: REKIYA IBRAHIM ATTAH | D99: DEPUTY DIRECTOR TRAINING | E99: 16(8) | F99: =700000 -> 700000 | G99: =F99 -> 700000
A100: 2 | B100: DR FRANCIS NDUM OJIE | D100: CHIEF TRAINING OFFICER | E100: 14(9) | F100: 500000 | H100: 500000
A101: 3 | B101: ABUBAKAR MOHAMMED BASHIR | D101: ASST. CHIEF TRAINING OFFICER | E101: 13(8) | F101: 500000 | H101: 500000
A102: 4 | B102: OKECHUKWU UCHENNA HULDA | D102: TRAINING OFFICER | E102: 10(11) | F102: 300000 | H102: 300000
B103: TOTAL | D103: 4 | F103: =SUM(F99:F102) -> 2000000 | G103: =SUM(G99:G102) -> 700000 | H103: =SUM(H99:H102) -> 1300000
B105: LIBRARY AND DOCUMENTATION
A106: 1 | B106: DR MAIMUNA IZAH | D106: INSITUTE LIBRARIAN | E106: 17(9) | F106: =1000000 -> 1000000 | G106: =F106 -> 1000000
A107: 2 | B107: CATHERINE E. IKOKOH | D107: SNR RESEARCH FELLOW DOCU | E107: 15(9) | F107: =700000 -> 700000 | G107: =F107 -> 700000
A108: 3 | B108: ALIYU SANNI ABUBAKAR | D108: RESEARCH FELLOW 11 DATA & DOCU | E108: 13(11) | F108: =500000 -> 500000 | H108: =500000 -> 500000
A109: 4 | B109: CHINAKO N. ASOGWA | D109: RESEARCH FELLOW 11 DATA & DOCU | E109: 13(10) | F109: =500000 -> 500000 | H109: =500000 -> 500000
A110: 5 | B110: AMOS ABA | D110: LIBRARY ASSISTANT | E110: 8(10) | F110: 300000 | I110: 300000
A111: 6 | B111: TITILAYO DANIEL MARVELLOUS | D111: LIBRARY ASSISTANT | E111: 8(9) | F111: 300000 | I111: 300000
...

Sheet 13 month
B3: SCHEDULE OF 13TH MONTH SALARY FOR 3 STAFF FOR YEAR, 2021
F4: ='[1]FEB 08'!E8/'[1]FEB 08'!M8 -> 0.22 | I4: ='[1]FEB 08'!F8/'[1]FEB 08'!Q8 -> 0.3
B5: STAFF NAME | U5: DEDUCTIONS
D6: DESIGNATION | E6: SALARY | F6: BASIC | M6: MOTOR/ | N6: RESEARCH | O6: HARDSHIP | P6: LEAVE | Q6: OUT FIT | R6: LEGISLATIVE | S6: GROSS | Z6: NOVEMBER,2021 | AA6: N
E7: LEVEL | F7: SALARY | G7: SALARY/ALLOWCE AREARS | H7: RENT | I7: UTILITY | J7: DOMESTIC | K7: ENTERT. | L7: FURNIT. | M7: FUEL | N7: ALLOWANCE | O7: ALLOWANCE | P7: ALLCE | Q7: ALLCE | R7: DUTY ALLCE | S7: SALARY | T7: AUCTION | U7: COOP SOCIETY | V7: COOP. LOAN RECOVERY | W7: NHF DEDUCTION | X7: PAYE | Y7: TOTAL
A8: S/N | B8: DG OFFICE | F8: N | I8: N | S8: N | X8: N
B9: LEG. SUPPORT SEVICES
A10: 1 | B10: BETHEL UZOMA IHUGBA | D10: SNR RESEARCH FELLOW | E10: 15(9) | F10: =33507.5 -> 33507.5 | H10: =F10*300% -> 100522.5 | I10: =F10*7.5% -> 2513.0625 | J10: 40122.19 | K10: =F10*50% -> 16753.75 | L10: =F10*350% -> 117276.25 | M10: =F10*100% -> 33507.5 | N10: =160000 -> 160000 | P10: =F10*10% -> 3350.75 | Q10: 20000 | S10: =SUM(F10:R10) -> 527553.5 | Y10: =X10+W10+V10+U10+T10 -> 0 | Z10: 162099.21 | AA10: =S10-Y10 -> 527553.5
B11: TOTAL | D11: 1 | F11: =SUM(F10:F10) -> 33507.5 | G11: =SUM(G10:G10) -> 0 | H11: =SUM(H10:H10) -> 100522.5 | I11: =SUM(I10:I10) -> 2513.0625 | J11: =SUM(J10:J10) -> 40122.19 | K11: =SUM(K10:K10) -> 16753.75 | L11: =SUM(L10:L10) -> 117276.25 | M11: =SUM(M10:M10) -> 33507.5 | N11: =SUM(N10:N10) -> 160000 | P11: =SUM(P10:P10) -> 3350.75 | Q11: =SUM(Q10:Q10) -> 20000 | R11: =SUM(R10:R10) -> 0 | S11: =SUM(S10:S10) -> 527553.5 | W11: =SUM(W10:W10) -> 0 | Y11: =SUM(Y10:Y10) -> 0 | Z11: 3633581.8 | AA11: =SUM(AA10:AA10) -> 527553.5
B13: FINANCE & ACCOUNT
A14: 2 | B14: TONDO IORWUESE EDWARD | D14: ASST. DIRECTOR, ACCOUNTS | E14: 15(8) | F14: =32263.2 -> 32263.2 | H14: =F14*300% -> 96789.6 | I14: =F14*7.5% -> 2419.74 | J14: =40122.19 -> 40122.19 | K14: =F14*50% -> 16131.6 | L14: =F14*350% -> 112921.2 | M14: =F14*100% -> 32263.2 | O14: =80000 -> 80000 | P14: =F14*10% -> 3226.32 | Q14: 20000 | R14: =100000 -> 100000 | S14: =SUM(F14:R14) -> 536137.05 | Y14: =X14+W14+V14+U14+T14 -> 0 | Z14: 339782.14 | AA14: =S14-Y14 -> 536137.05
B15: TOTAL | D15: 1 | F15: =SUM(F14:F14) -> 32263.2 | H15: =SUM(H14:H14) -> 96789.6 | I15: =SUM(I14:I14) -> 2419.74 | J15: =SUM(J14:J14) -> 40122.19 | K15: =SUM(K14:K14) -> 16131.6 | L15: =SUM(L14:L14) -> 112921.2 | M15: =SUM(M14:M14) -> 32263.2 | O15: =SUM(O14:O14) -> 80000 | P15: =SUM(P14:P14) -> 3226.32 | Q15: =SUM(Q14:Q14) -> 20000 | R15: =SUM(R14:R14) -> 100000 | S15: =SUM(S14:S14) -> 536137.05 | Y15: =SUM(Y14:Y14) -> 0 | Z15: 2792106.4 | AA15: =SUM(AA14:AA14) -> 536137.05
B17: ADMINISTRATION & HUMAN RESOURCE
A18: 3 | B18: SALAMATU YAKUBU | D18: CHIEF ADMIN OFFICER | E18: 14(8) | F18: =25854.1 -> 25854.1 | H18: =F18*300% -> 77562.3 | I18: =F18*7.5% -> 1939.0575 | J18: 0 | K18: =F18*50% -> 12927.05 | L18: =F18*350% -> 90489.35 | M18: =F18*100% -> 25854.1 | O18: 70000 | P18: =F18*10% -> 2585.41 | Q18: 20000 | R18: 0 | S18: =SUM(F18:R18) -> 327211.37 | Y18: =X18+W18+V18+U18+T18 -> 0 | Z18: 185530.19 | AA18: =S18-Y18 -> 327211.37
B19: TOTAL | D19: 1 | F19: =SUM(F18:F18) -> 25854.1 | G19: =SUM(G18:G18) -> 0 | H19: =SUM(H18:H18) -> 77562.3 | I19: =SUM(I18:I18) -> 1939.0575 | J19: =SUM(J18:J18) -> 0 | K19: =SUM(K18:K18) -> 12927.05 | L19: =SUM(L18:L18) -> 90489.35 | M19: =SUM(M18:M18) -> 25854.1 | O19: =SUM(O18:O18) -> 70000 | P19: =SUM(P18:P18) -> 2585.41 | Q19: =SUM(Q18:Q18) -> 20000 | R19: =SUM(R18:R18) -> 0 | S19: =SUM(S18:S18) -> 327211.37 | U19: =SUM(U18:U18) -> 0 | V19: =SUM(V18:V18) -> 0 | Y19: =SUM(Y18:Y18) -> 0 | Z19: 8517692.7 | AA19: =SUM(AA18:AA18) -> 327211.37
B20: GRAND TOTAL | D20: 3 | F20: =SUM(F19,F15,F11) -> 91624.8 | G20: =SUM(G19,G11) -> 0 | H20: =SUM(H19,H15,H11) -> 274874.4 | I20: =SUM(I19,I15,I11) -> 6871.86 | J20: =SUM(J19,J15,J11) -> 80244.38 | K20: =SUM(K19,K15,K11) -> 45812.4 | L20: =SUM(L19,L15,L11) -> 320686.8 | M20: =SUM(M19,M15,M11) -> 91624.8 | N20: =SUM(N11) -> 160000 | O20: =SUM(O19,O15) -> 150000 | P20: =SUM(P19,P15,P11) -> 9162.48 | Q20: =SUM(Q19,Q15,Q11) -> 60000 | R20: =SUM(R19,R15,R11) -> 100000 | S20: =SUM(S19,S15,S11) -> 1390901.9 | U20: =SUM(U19,U15,U11) -> 0 | V20: =SUM(V19,V15,V11) -> 0 | W20: =SUM(W19,W15,W11) -> 0 | X20: =SUM(X19,X15,X11) -> 0 | Y20: =SUM(Y19,Y15,Y11) -> 0 | Z20: =SUM(Z10:Z19) -> 15630792 | AA20: =SUM(AA19,AA15,AA11) -> 1390901.9
K22: SIGNATURE | P22: DATE

Sheet Salah Welfare
B3: STAFF PAYROLL FOR THE MONTH OF APRIL 2022
B5: STAFF NAME | E5: NET SALARY
C6: DESIGNATION | D6: SALARY | E6: APRIL,2022
D7: LEVEL
A8: S/N | B8: DG OFFICE
A9: 1 | B9: PROF. ABUBAKAR O. SULAIMAN | C9: DIRECTOR GENERAL | D9: CONSOL | E9: =300000 -> 300000
A10: 2 | B10: DR ADEYEMI AKEEB FAJINGBESI | C10: DIR. SPECIAL DUTIES, DG OFFICE | D10: 17(9) | E10: 150000
A11: 3 | B11: DR JAKE DABANG DAN AZUMI | C11: DEPUTY DIRECTOR TRAINING | D11: 16(8) | E11: 70000
A12: 4 | B12: DR ABDULSALAM NASIRU NAEEM | C12: SA ACADEMICS | D12: 16(8) | E12: 70000
A13: 5 | B13: RAHEEM USMAN AYIGORO | C13: SA-INFRASTRUCTURE | D13: 16 (8) | E13: 70000
A14: 6 | B14: AKINSANMI ADEJOKE OLUKEMI | C14: HEAD INFORMATION/PROTOCOL | D14: 15(9) | E14: 70000
A15: 7 | B15: DR IKEME ARTHUR J.O | C15: SNR RESEARCH FELLOW | D15: 15(9) | E15: 70000
A16: 8 | B16: MOSHOOD M. OLALERE | C16: MANAGER ADMIN DG's OFFICE | D16: 15(9) | E16: 70000
A17: 9 | B17: ANDRAWUS MUSA | C17: ASST. DIRECTOR, STORE | D17: 15(9) | E17: 70000
A18: 10 | B18: AYOBOLU OLAJIDE OLUFUNSHO | C18: ASST.DIR., INFORMATION | D18: 15 (7) | E18: 70000
A19: 11 | B19: HUSSEIN EGYE MUSA | C19: CHIEF PROTOCOL OFFICER | D19: 14(9) | E19: 50000
A20: 12 | B20: DONALD E. MKPANAM | C20: CHIEF ICT OFFICER | D20: 14(9) | E20: 50000
A21: 13 | B21: JOY HARUNA MAKERI | C21: RESEARCH FELLOW 1 TRAINING | D21: 14(9) | E21: 50000
... A38: 30 | B38: HABEEBA K MUHAMMAD SALIHU | C38: ASST. OFFICER/COMM | D38: 8(7) | E38: 30000
B39: TOTAL | C39: 30 | E39: =SUM(E9:E38) -> 1790000
B41: INTERNAL AUDIT
A42: 1 | B42: OSANAIYE DAVID AKINYEMI | C42: DIRECTOR INTERNAL AUDIT | D42: 17(8) | E42: 150000
C43: 1 | E43: =SUM(E42:E42) -> 150000
B45: LEG. SUPPORT SEVICES
A46: 1 | B46: PROF. EDOBA BRIGHT OMOREGBE | C46: AG. DLSS | D46: 17(9) | E46: 150000
A47: 2 | B47: DR CLINTON JAJA | C47: SENIOR RESEARCH FELLOW | D47: 15(9) | E47: 70000
A48: 3 | B48: BETHEL UZOMA IHUGBA | C48: SNR RESEARCH FELLOW | D48: 15(9) | E48: 70000
A49: 4 | B49: OGUCHE SAMUEL | C49: SNR RESEARCH FELLOW | D49: 15(8) | E49: 70000
A50: 5 | B50: IBRAHIM USMAN | C50: RESEARCH FELLOW I | D50: 14(11) | E50: 50000
A51: 6 | B51: DR MOHAMMED O. AMALI | C51: RESEARCH FELLOW I | D51: 14(9) | E51: 50000
A52: 7 | B52: YAHAYA SHAMSU | C52: RESEARCH FELLOW 1 | D52: 14(9) | E52: 50000
A53: 8 | B53: OFORDEME ADAOBI JULIA | C53: RESEARCH FELLOW 11 | D53: 13(10) | E53: 50000
A54: 9 | B54: DORIS DAKDA AARON | C54: RESEARCH FELLOW II | D54: 13(9) | E54: 50000
B55: TOTAL | C55: 9 | E55: =SUM(E46:E54) -> 610000
B57: LEGAL SERVICES
A58: 1 | B58: DR SHUIBU DANWANKA | C58: DIRECTOR LEGAL SERVICES | D58: 17(9) | E58: =150000 -> 150000
A59: 2 | B59: ABDULSALAM BAKO | C59: MANAGER, LEGAL SERVICES | D59: 15 (8) | E59: 70000
B60: TOTAL | C60: 2 | E60: =SUM(E58:E59) -> 220000
B62: DEMOCRACY AND GOVERNANCE
A63: 1 | B63: DR. ADEWALE ADEREMI | C63: DIRECTOR, DEMOCRATIC STUDIES | D63: 17(9) | E63: 150000
A64: 2 | B64: NDANUSA MOHAMMED MANZUMA | C64: SNR RESEARCH FELLOW | D64: 15 (7) | E64: 70000
A65: 3 | B65: EJALONIBU GANIYU LAYI | C65: RESEARCH FELLOW 11 | D65: 13(9) | E65: 50000
A66: 4 | B66: LONA POLIT BONKAT | C66: RESEARCH FELLOW 11 | D66: 13(8) | E66: 50000
A67: 5 | B67: YUNUSA ABDULLAHI | C67: RESEARCH FELLOW 1 | D67: 14(9) | E67: 50000
A68: 6 | B68: UDEFUNA NNADOZIE PATRICK | C68: RESEARCH OFFICER | D68: 10(13) | E68: 30000
A69: 7 | B69: OSOLAFIA MUHAMMAD EGYE | C69: RESEARCH OFFICER | D69: 12(8) | E69: 30000
A70: 8 | B70: HAUWA PATE SADIQ | C70: PROGRAMME OFFICER | D70: 10(10) | E70: 30000
A71: 9 | B71: ABAYOMI KAYODE QUADRI | C71: RESEARCH OFFICER | D71: 10(7) | E71: 30000
A72: 10 | B72: NNANDI LIVINUS ATURE | C72: RESEARCH ASSISTANT | D72: 8(7) | E72: 30000
A73: 11 | B73: LUCKY AGWOM | C73: RESEARCH ASSISTANT | D73: 8(7) | E73: 30000
B74: TOTAL | C74: 11 | E74: =SUM(E63:E73) -> 550000
B76: STUDIES
A77: 1 | B77: DR ASIMIYU G. ABIOLA | C77: DIRECTOR POST GRADUATE | D77: 17(9) | E77: =150000 -> 150000
A78: 2 | B78: USMAN WALI | C78: SENIOR RESEARCH FELLOW | D78: 15 (7) | E78: 70000
A79: 3 | B79: MOSHOOD TOSHO AMUDA | C79: MANAGER, EXAMS & RECORDS | D79: 15 (7) | E79: 70000
A80: 4 | B80: UZODINMA EMMANUEL EZENWA | C80: RESEARCH FELLOW II | D80: 13(9) | E80: 50000
A81: 5 | B81: IGWE STACY | C81: PROGRAMME OFFICER | D81: 10(7) | E81: 30000
A82: 6 | B82: DARE SHEU MAGBON | C82: ASSIST. PG | D82: 8(9) | E82: 30000
A83: 7 | B83: MOHAMMED BELLO | C83: RESEARCH ASSITANT PG | D83: 8(7) | E83: 30000
B84: TOTAL | C84: 7 | E84: =SUM(E77:E83) -> 430000
B86: ECONOMIC DEV. AND SOCIAL RESEARCH
A87: 1 | B87: DR ASEMOTA OMOROGBE JOSEPH | C87: Ag. DEPUTY DIRECTOR, ECO & SOC DEV DEPT | D87: 16(8) | E87: 70000
A88: 2 | B88: TERFA WILLIAMS ABRAHAM | C88: SNR RESEARCH FELLOW | D88: 15(9) | E88: 70000
A89: 3 | B89: DR AUGUSTINE C. OSIGWE | C89: SNR RESEARCH FELLOW | D89: 15(9) | E89: 70000
A90: 4 | B90: NGARA CHRISTOPHER OCHANJA | C90: RESEARCH FELLOW 1 | D90: 14(10) | E90: 50000
A91: 5 | B91: OMOJU OLUWASOLA EMMANUEL | C91: RESEARCH FELLOW I | D91: 14(9) | E91: 50000
A92: 6 | B92: IBE EZECHI CYRIACUS | C92: RESEARCH FELLOW II | D92: 13(9) | E92: 50000
A93: 7 | B93: OSIKHEN LEO IGBANOI | C93: RESEARCH FELLOW 11 | D93: 13(8) | E93: 50000
A94: 8 | B94: OKUNGBOWA OSARETIN GODSPOWER | C94: RESEARCH FELLOW 11 | D94: 13(8) | E94: 50000
B95: TOTAL | C95: 9 | E95: =SUM(E87:E94) -> 460000
B97: TRAINING AND INTERNATIONAL COOP
A98: 1 | B98: REKIYA IBRAHIM ATTAH | C98: DEPUTY DIRECTOR TRAINING | D98: 16(8) | E98: 70000
A99: 2 | B99: DR FRANCIS NDUM OJIE | C99: CHIEF TRAINING OFFICER | D99: 14(9) | E99: 50000
A100: 3 | B100: ABUBAKAR MOHAMMED BASHIR | C100: ASST. CHIEF TRAINING OFFICER | D100: 13(8) | E100: 50000
A101: 4 | B101: OKECHUKWU UCHENNA HULDA | C101: TRAINING OFFICER | D101: 10(11) | E101: 30000
B102: TOTAL | C102: 4 | E102: =SUM(E98:E101) -> 200000
B104: LIBRARY AND DOCUMENTATION
A105: 1 | B105: DR MAIMUNA IZAH | C105: INSITUTE LIBRARIAN | D105: 17(9) | E105: 150000
A106: 2 | B106: CATHERINE E. IKOKOH | C106: SNR RESEARCH FELLOW DOCU | D106: 15(9) | E106: 70000
A107: 3 | B107: ALIYU SANNI ABUBAKAR | C107: RESEARCH FELLOW 11 DATA & DOCU | D107: 13(11) | E107: 50000
A108: 4 | B108: CHINAKO N. ASOGWA | C108: RESEARCH FELLOW 11 DATA & DOCU | D108: 13(10) | E108: 50000
A109: 5 | B109: AMOS ABA | C109: LIBRARY ASSISTANT | D109: 8(10) | E109: 30000
A110: 6 | B110: TITILAYO DANIEL MARVELLOUS | C110: LIBRARY ASSISTANT | D110: 8(9) | E110: 30000
A111: 7 | B111: ENENCHE JEREMIAH AGADA | C111: LIBRARY ASSISTANT | D111: 8(7) | E111: 30000
A112: 8 | B112: ABBAS ZAINAB | C112: LIBRARY ASSISTANT | D112: 8(7) | E112: 30000
B113: TOTAL | C113: 8 | E113: =SUM(E105:E112) -> 440000
B115: FINANCE & ACCOUNT
A116: 1 | B116: IBRAHIM M. MSHELIA | C116: DIR. FINANCE & ACCOUNTS | D116: 17(9) | E116: 150000
A117: 2 | B117: KABIR MUHAMMAD SULAIMAN | C117: DD FINANCE & ACCOUNTS | D117: 16(9) | E117: 70000
A118: 3 | B118: RAHILA NURUDEEN HABU | C118: ASST. DIRECTOR, ACCOUNTS | D118: 15(9) | E118: 70000
A119: 4 | B119: TONDO IORWUESE EDWARD | C119: ASST. DIRECTOR, ACCOUNTS | D119: 15(9) | E119: 70000
A120: 5 | B120: ARAOYE GANIYAT TITILOLA | C120: ASST. DIRECTOR, ACCOUNTS | D120: 15(7) | E120: 70000
A121: 6 | B121: SHEHU ABDULLAHI | C121: ASST. CHIEF ACCOUNT OFFICER | D121: 13(10) | E121: 50000
A122: 7 | B122: OJOGIWA ABISOLA GANIAT | C122: ASST. CHIEF BUDGET OFFICER | D122: 13(9) | E122: 50000
A123: 8 | B123: RAHILA SALIHU | C123: ASST. CHIEF ACCOUNTOFFICER | D123: 13(9) | E123: 50000
A124: 9 | B124: SALMAN RABBIAT BOLATITO | C124: ASST. CHIEF ACCOUNT OFFICER | D124: 13 (8) | E124: 50000
B125: TOTAL | C125: 9 | E125: =SUM(E116:E124) -> 630000
B127: ADMINISTRATION & HUMAN RESOURCE
A128: 1 | B128: DR KABIR AHMED | C128: DIR.ADMIN & HR | D128: 17(9) | E128: 150000
A129: 2 | B129: AMINU BELLO DUKKU | C129: DIR ADMIN | D129: 17(9) | E129: 150000
...

Sheet Sheet3
A2: Research /Hardshi allowances
A4: 1 | B4: Fajingbesi | C4: =100000 -> 100000
A5: 2 | B5: Joy | C5: 50000
A6: 3 | B6: Maryam | C6: 100000
A7: 4 | B7: Terfa Gbahabo | C7: =50000 -> 50000
A8: 5 | B8: Hassana | C8: =140000 -> 140000
A9: 6 | B9: Yakub | C9: =10000 -> 10000
C10: =SUM(C4:C9) -> 450000
B11: Arears
A12: 1 | B12: Yakub | C12: =45283 -> 45283
A13: 2 | B13: Abdullahi | C13: =35436 -> 35436
C14: =SUM(C11:C13) -> 80719
B16: Late Staff
B17: Bashir Auwal | C17: =33074.51 -> 33074.51
B18: Chukwuka Edmond | C18: =148722.77 -> 148722.77
C19: =SUM(C17:C18) -> 181797.28
B21: Dr. Eze
B22: Director Salary | C22: =925433.08 -> 925433.08
B23: DD | C23: =451465+90000 -> 541465
B24: DIFF. | C24: =C22-C23 -> 383968.08
B25: Portion for 12 days | C25: =C24*12/31 -> 148632.81

Sheet Promotion
B3: STAFF PAYROLL FOR THE MONTH OF SEPTEMBER, 2021
F4: ='[1]FEB 08'!E8/'[1]FEB 08'!M8 -> 0.22 | I4: ='[1]FEB 08'!F8/'[1]FEB 08'!Q8 -> 0.3
B5: EFFECT OF PROMOTION | U5: DEDUCTIONS | AA5: NET SALARY
D6: DESIGNATION | E6: OLD SALARY | F6: BASIC | M6: MOTOR/ | N6: RESEARCH | O6: HARDSHIP | P6: LEAVE | Q6: OUT FIT | R6: LEGISLATIVE | S6: OLD GROSS | Z6: AUGUST,2021 | AA6: SEPTEMBER,2021 | AB6: NEW SALARY | AC6: NEWGROSS
E7: LEVEL | F7: SALARY | G7: SALARY/ALLOWCE AREARS | H7: RENT | I7: UTILITY | J7: DOMESTIC | K7: ENTERT. | L7: FURNIT. | M7: FUEL | N7: ALLOWANCE | O7: ALLOWANCE | P7: ALLCE | Q7: ALLCE | R7: DUTY ALLCE | S7: SALARY | T7: AUCTION | U7: COOP SOCIETY | V7: COOP. LOAN RECOVERY | W7: NHF DEDUCTION | X7: PAYE | Y7: TOTAL | AB7: GRADE LEVEL | AC7: SALARY | AD7: DIFFERENCE | AE7: AREARS FOR AUGUST | AF7: TOTAL DIFFERENCE | AG7: OLD PAYE | AH7: NEW PAYE | AI7: DIFF
A8: S/N | B8: DG OFFICE | F8: N | I8: N | S8: N | X8: N
A9: 1 | B9: HUSSEIN EGYE MUSA | D9: AM PROTOCOL | E9: 13(10) | F9: =25523.45 -> 25523.45 | H9: =F9*300% -> 76570.35 | I9: =F9*7.5% -> 1914.2587 | K9: =F9*50% -> 12761.725 | L9: =F9*350% -> 89332.075 | M9: =F9*100% -> 25523.45 | O9: =70000 -> 70000 | P9: =F9*10% -> 2552.345 | Q9: 15000 | R9: 50000 | S9: =R9+Q9+P9+O9+N9+M9+L9+K9+J9+I9+H9+G9+F9 -> 369177.65 | U9: 50000 | V9: =150000 -> 150000 | W9: 0 | X9: 7709.76 | Y9: =X9+W9+V9+U9+T9 -> 207709.76 | Z9: 160467.89 | AA9: =S9-Y9 -> 161467.89 | AB9: 14 (8) | AC9: =257211+70000+50000 -> 377211 | AD9: =AC9-S9 -> 8033.3463 | AE9: =23/31*AD9 -> 5960.2246 | AF9: =AD9+AE9 -> 13993.571 | AG9: 7709.76 | AH9: 7709.76 | AI9: =AH9-AG9 -> 0 | AK9: =AC9+AE9 -> 383171.22
A10: 2 | B10: DONALD E. MKPANAM | D10: AM ICT | E10: 13(11) | F10: 26339.3 | H10: =F10*300% -> 79017.9 | I10: =F10*7.5% -> 1975.4475 | K10: =F10*50% -> 13169.65 | L10: =F10*350% -> 92187.55 | M10: =F10*100% -> 26339.3 | O10: =70000 -> 70000 | P10: =F10*10% -> 2633.93 | Q10: 15000 | R10: 0 | S10: =R10+Q10+P10+O10+N10+M10+L10+K10+J10+I10+H10+G10+F10 -> 326663.08 | W10: ='[5]Jan 2021'!$H$28 -> 658.4825 | X10: 7709.76 | Y10: =X10+W10+V10+U10+T10 -> 8368.2425 | Z10: 318294.83 | AA10: =S10-Y10 -> 318294.83 | AB10: 14 (8) | AC10: =257211+70000 -> 327211 | AD10: =AC10-S10 -> 547.9225 | AE10: =23/31*AD10 -> 406.52315 | AF10: =AD10+AE10 -> 954.44565 | AG10: 7709.76 | AH10: 7709.76 | AI10: =AH10-AG10 -> 0 | AK10: =AC10+AE10 -> 327617.52
A11: 3 | B11: JOY HARUNA MAKERI | D11: AM TRAINING | E11: 13(10) | F11: =25523.45 -> 25523.45 | H11: =F11*300% -> 76570.35 | I11: =F11*7.5% -> 1914.2587 | K11: =F11*50% -> 12761.725 | L11: =F11*350% -> 89332.075 | M11: =F11*100% -> 25523.45 | N11: =120000 -> 120000 | P11: =F11*10% -> 2552.345 | Q11: 15000 | R11: =50000+100000 -> 150000 | S11: =R11+Q11+P11+O11+N11+M11+L11+K11+J11+I11+H11+G11+F11 -> 519177.65 | X11: =7709.76 -> 7709.76 | Y11: =X11+W11+V11+U11+T11 -> 7709.76 | Z11: 546467.89 | AA11: =S11-Y11 -> 511467.89 | AB11: 14 (8) | AC11: =257211+140000+150000 -> 547211 | AD11: =AC11-S11 -> 28033.346 | AE11: =23/31*AD11 -> 20798.934 | AF11: =AD11+AE11 -> 48832.281 | AG11: 7709.76 | AH11: 7709.76 | AI11: =AH11-AG11 -> 0
A12: 4 | B12: CHRISTIAN MADUABUCHI ODO | D12: ICT OFFICER | E12: 10(11) | S12: 246866.02 | AB12: 12(7) | AC12: =205372+60000 -> 265372 | AD12: =AC12-S12 -> 18505.984 | AE12: =23/31*AD12 -> 13730.246 | AF12: =AD12+AE12 -> 32236.23 | AG12: =3369.51 -> 3369.51 | AH12: =3369.51 -> 3369.51 | AI12: =AH12-AG12 -> 0
B13: TOTAL | D13: 4 | F13: =SUM(F9:F11) -> 77386.2 | G13: =SUM(G9:G11) -> 0 | H13: =SUM(H9:H11) -> 232158.6 | I13: =SUM(I9:I11) -> 5803.965 | J13: =SUM(J9:J11) -> 0 | K13: =SUM(K9:K11) -> 38693.1 | L13: =SUM(L9:L11) -> 270851.7 | M13: =SUM(M9:M11) -> 77386.2 | ... S13: =SUM(S9:S11) -> 1215018.4 | U13: =SUM(U9:U11) -> 50000 | V13: =SUM(V9:V11) -> 150000 | W13: =SUM(W9:W11) -> 658.4825 | X13: =SUM(X9:X11) -> 23129.28 | Y13: =SUM(Y9:Y11) -> 223787.76 | Z13: 9309597.9 | AA13: =SUM(AA9:AA11) -> 991230.62 | AC13: =SUM(AC9:AC12) -> 1517005 | AD13: =SUM(AD9:AD12) -> 55120.599 | AE13: =SUM(AE9:AE12) -> 40895.928 | AF13: =SUM(AF9:AF12) -> 96016.527 | AG13: =SUM(AG9:AG12) -> 26498.79 | AH13: =SUM(AH9:AH12) -> 26498.79 | AI13: =SUM(AI9:AI12) -> 0
B15: INTERNAL AUDIT
C16: TOTAL | F16: =SUM(#REF!) -> #REF! | H16: =SUM(#REF!) -> #REF! | I16: =SUM(#REF!) -> #REF! | J16: =SUM(#REF!) -> #REF! | K16: =SUM(#REF!) -> #REF! | L16: =SUM(#REF!) -> #REF! | M16: =SUM(#REF!) -> #REF! | N16: =SUM(#REF!) -> #REF! | O16: =SUM(#REF!) -> #REF! | P16: =SUM(#REF!) -> #REF! | U16: =SUM(#REF!) -> #REF! | V16: =SUM(#REF!) -> #REF! | W16: =SUM(#REF!) -> #REF! | X16: =SUM(#REF!) -> #REF! | Y16: =SUM(#REF!) -> #REF! | Z16: 478180.46 | AA16: =SUM(#REF!) -> #REF!
B17: LEG. SUPPORT SEVICES
A18: 1 | B18: OGUCHE SAMUEL | D18: RESEARCH FELLOW I | E18: 14(11) | F18: 28489.81 | H18: =F18*300% -> 85469.43 | I18: =F18*7.5% -> 2136.7357 | K18: =F18*50% -> 14244.905 | L18: =F18*350% -> 99714.335 | M18: =F18*100% -> 28489.81 | N18: =140000 -> 140000 | P18: =F18*10% -> 2848.981 | Q18: 20000 | S18: =SUM(F18:R18) -> 421394.01 | U18: =30000 -> 30000 | V18: =0 -> 0 | X18: 7709.76 | Y18: =X18+W18+V18+U18+T18 -> 37709.76 | Z18: 383684.25 | AA18: =S18-Y18 -> 383684.25 | AB18: 15(7) | AC18: =344720+160000 -> 504720 | AD18: =AC18-S18 -> 83325.993 | AE18: =23/31*AD18 -> 61822.511 | AF18: =AE18+AD18 -> 145148.5 | AG18: 7709.76 | AH18: 15548.33 | AI18: =AH18-AG18 -> 7838.57
A19: 2 | B19: YAHAYA SHAMSU | D19: RESEARCH FELLOW 11 | E19: 13(11) | F19: =26339.3 -> 26339.3 | H19: =F19*300% -> 79017.9 | I19: =F19*7.5% -> 1975.4475 | K19: =F19*50% -> 13169.65 | L19: =F19*350% -> 92187.55 | M19: =F19*100% -> 26339.3 | N19: =120000 -> 120000 | P19: =F19*10% -> 2633.93 | Q19: 15000 | S19: =SUM(F19:R19) -> 376663.08 | W19: 0 | X19: 7709.76 | Y19: =X19+W19+V19+U19+T19 -> 7709.76 | Z19: 368953.32 | AA19: =S19-Y19 -> 368953.32 | AB19: 14(8) | AC19: =257211+140000 -> 397211 | AD19: =AC19-S19 -> 20547.923 | AE19: =23/31*AD19 -> 15245.233 | AF19: =AE19+AD19 -> 35793.155 | AG19: 7709.76 | AH19: 7709.76 | AI19: =AH19-AG19 -> 0
B20: TOTAL | D20: 2 | F20: =SUM(F18:F19) -> 54829.11 | H20: =SUM(H18:H19) -> 164487.33 | I20: =SUM(I18:I19) -> 4112.1833 | J20: =SUM(J18:J19) -> 0 | K20: =SUM(K18:K19) -> 27414.555 | L20: =SUM(L18:L19) -> 191901.89 | M20: =SUM(M18:M19) -> 54829.11 | N20: =SUM(N18:N19) -> 260000 | P20: =SUM(P18:P19) -> 5482.911 | Q20: =SUM(Q18:Q19) -> 35000 | R20: =SUM(R18:R19) -> 0 | S20: =SUM(S18:S19) -> 798057.08 | U20: =SUM(U18:U19) -> 30000 | V20: =SUM(V18:V19) -> 0 | W20: =SUM(W18:W19) -> 0 | X20: =SUM(X18:X19) -> 15419.52 | Y20: =SUM(Y18:Y19) -> 45419.52 | Z20: 3862557.6 | AA20: =SUM(AA18:AA19) -> 752637.56 | AC20: =SUM(AC18:AC19) -> 901931 | AD20: =SUM(AD18:AD19) -> 103873.92 | AE20: =SUM(AE18:AE19) -> 77067.744 | AF20: =SUM(AF18:AF19) -> 180941.66 | AG20: =SUM(AG18:AG19) -> 15419.52 | AH20: =SUM(AH18:AH19) -> 23258.09 | AI20: =SUM(AI18:AI19) -> 7838.57
B22: LEGAL SERVICES
B23: TOTAL | F23: =SUM(#REF!) -> #REF! | H23: =SUM(#REF!) -> #REF! | I23: =SUM(#REF!) -> #REF! | J23: =SUM(#REF!) -> #REF! | K23: =SUM(#REF!) -> #REF! | L23: =SUM(#REF!) -> #REF! | M23: =SUM(#REF!) -> #REF! | N23: =SUM(#REF!) -> #REF! | O23: =SUM(#REF!) -> #REF! | ... R23: =SUM(#REF!) -> #REF! | S23: =0 -> 0 | U23: =SUM(#REF!) -> #REF! | W23: =SUM(#REF!) -> #REF! | X23: =SUM(#REF!) -> #REF! | Y23: =SUM(#REF!) -> #REF! | Z23: 931604.15 | AA23: =SUM(#REF!) -> #REF!
B25: DEMOCRACY AND GOVERNANCE
A26: 1 | B26: YUNUSA ABDULLAHI | D26: RESEARCH FELLOW 11 | E26: 13(11) | F26: =26339.3 -> 26339.3 | H26: =F26*300% -> 79017.9 | I26: =F26*7.5% -> 1975.4475 | K26: =F26*50% -> 13169.65 | L26: =F26*350% -> 92187.55 | M26: =F26*100% -> 26339.3 | N26: =120000 -> 120000 | P26: =F26*10% -> 2633.93 | Q26: 15000 | S26: =SUM(F26:R26) -> 376663.08 | U26: =10000 -> 10000 | V26: =54585.66 -> 54585.66 | X26: =7709.76 -> 7709.76 | Y26: =X26+W26+V26+U26+T26 -> 72295.42 | Z26: 303367.66 | AA26: =S26-Y26 -> 304367.66 | AB26: 14(8) | AC26: =257211+140000 -> 397211 | AD26: =AC26-S26 -> 20547.923 | AE26: =23/31*AD26 -> 15245.233 | AF26: =AE26+AD26 -> 35793.155 | AG26: 7709.76 | AH26: 7709.76 | AI26: =AH26-AG26 -> 0
A27: 2 | B27: OSOLAFIA MUHAMMAD EGYE | D27: RESEARCH OFFICER | E27: 10(11) | F27: =19276.95 -> 19276.95 | H27: =F27*300% -> 57830.85 | I27: =F27*7.5% -> 1445.7713 | J27: 0 | K27: =F27*50% -> 9638.475 | L27: =F27*350% -> 67469.325 | M27: =F27*100% -> 19276.95 | N27: =100000 -> 100000 | P27: =F27*10% -> 1927.695 | Q27: 10000 | R27: 0 | S27: =SUM(F27:R27) -> 286866.02 | U27: =20000 -> 20000 | V27: =100000 -> 100000 | W27: ='[5]Jan 2021'!$H$43 -> 481.92375 | X27: =3369.51 -> 3369.51 | Y27: =X27+W27+V27+U27+T27 -> 123851.43 | Z27: 163014.58 | AA27: =S27-Y27 -> 163014.58 | AB27: 12(7) | AC27: =205372+110000 -> 315372 | AD27: =AC27-S27 -> 28505.984 | AE27: =23/31*AD27 -> 21149.601 | AF27: =AE27+AD27 -> 49655.585 | AG27: =3369.51 -> 3369.51 | AH27: =3369.51 -> 3369.51 | AI27: =AH27-AG27 -> 0 | AK27: =AC27+AE27 -> 336521.6
B28: TOTAL | D28: 2 | F28: =SUM(F26:F27) -> 45616.25 | H28: =SUM(H26:H27) -> 136848.75 | I28: =SUM(I26:I27) -> 3421.2188 | J28: =SUM(J26:J27) -> 0 | K28: =SUM(K26:K27) -> 22808.125 | L28: =SUM(L26:L27) -> 159656.88 | M28: =SUM(M26:M27) -> 45616.25 | N28: =SUM(N26:N27) -> 220000 | P28: =SUM(P26:P27) -> 4561.625 | Q28: =SUM(Q26:Q27) -> 25000 | R28: =SUM(R26:R27) -> 0 | S28: =SUM(S26:S27) -> 663529.09 | U28: =SUM(U26:U27) -> 30000 | V28: =SUM(V26:V27) -> 154585.66 | W28: =SUM(W26:W27) -> 481.92375 | X28: =SUM(X26:X27) -> 11079.27 | Y28: =SUM(Y26:Y27) -> 196146.85 | Z28: 3477220.9 | AA28: =SUM(AA26:AA27) -> 467382.24 | AC28: =SUM(AC26:AC27) -> 712583 | AD28: =SUM(AD26:AD27) -> 49053.906 | AE28: =SUM(AE26:AE27) -> 36394.834 | AF28: =SUM(AF26:AF27) -> 85448.74 | AG28: =SUM(AG26:AG27) -> 11079.27 | AH28: =SUM(AH26:AH27) -> 11079.27 | AI28: =SUM(AI26:AI27) -> 0
B30: STUDIES
B31: TOTAL | F31: =SUM(#REF!) -> #REF! | H31: =SUM(#REF!) -> #REF! | I31: =SUM(#REF!) -> #REF! | J31: =SUM(#REF!) -> #REF! | K31: =SUM(#REF!) -> #REF! | L31: =SUM(#REF!) -> #REF! | M31: =SUM(#REF!) -> #REF! | N31: =SUM(#REF!) -> #REF! | P31: =SUM(#REF!) -> #REF! | Q31: =SUM(#REF!) -> #REF! | R31: =SUM(#REF!) -> #REF! | S31: =0 -> 0 | U31: =SUM(#REF!) -> #REF! | V31: =SUM(#REF!) -> #REF! | W31: =SUM(#REF!) -> #REF! | X31: =SUM(#REF!) -> #REF! | Y31: =SUM(#REF!) -> #REF! | Z31: 3200748.9 | AA31: =SUM(#REF!) -> #REF!
B33: ECONOMIC DEV. AND SOCIAL RESEARCH
B34: TOTAL | F34: =SUM(#REF!) -> #REF! | G34: =SUM(#REF!) -> #REF! | H34: =SUM(#REF!) -> #REF! | I34: =SUM(#REF!) -> #REF! | J34: =SUM(#REF!) -> #REF! | K34: =SUM(#REF!) -> #REF! | L34: =SUM(#REF!) -> #REF! | M34: =SUM(#REF!) -> #REF! | N34: =SUM(#REF!) -> #REF! | P34: =SUM(#REF!) -> #REF! | Q34: =SUM(#REF!) -> #REF! | R34: =SUM(#REF!) -> #REF! | S34: =0 -> 0 | U34: =SUM(#REF!) -> #REF! | V34: =SUM(#REF!) -> #REF! | W34: =SUM(#REF!) -> #REF! | X34: =SUM(#REF!) -> #REF! | Y34: =SUM(#REF!) -> #REF! | Z34: 3494235.1 | AA34: =SUM(#REF!) -> #REF!
B36: TRAINING AND INTERNATIONAL COOP
B37: TOTAL | F37: =SUM(#REF!) -> #REF! | H37: =SUM(#REF!) -> #REF! | I37: =SUM(#REF!) -> #REF! | J37: =SUM(#REF!) -> #REF! | K37: =SUM(#REF!) -> #REF! | L37: =SUM(#REF!) -> #REF! | M37: =SUM(#REF!) -> #REF! | N37: =SUM(#REF!) -> #REF! | O37: =SUM(#REF!) -> #REF! | ... R37: =SUM(#REF!) -> #REF! | S37: =0 -> 0 | U37: =SUM(#REF!) -> #REF! | V37: =SUM(#REF!) -> #REF! | W37: =SUM(#REF!) -> #REF! | X37: =SUM(#REF!) -> #REF! | Y37: =SUM(#REF!) -> #REF! | Z37: 547219.79 | AA37: =SUM(#REF!) -> #REF!
B39: LIBRARY AND DOCUMENTATION
B40: TOTAL | F40: =SUM(#REF!) -> #REF! | H40: =SUM(#REF!) -> #REF! | I40: =SUM(#REF!) -> #REF! | J40: =SUM(#REF!) -> #REF! | K40: =SUM(#REF!) -> #REF! | L40: =SUM(#REF!) -> #REF! | M40: =SUM(#REF!) -> #REF! | N40: =SUM(#REF!) -> #REF! | P40: =SUM(#REF!) -> #REF! | Q40: =SUM(#REF!) -> #REF! | R40: =SUM(#REF!) -> #REF! | S40: =0 -> 0 | U40: =SUM(#REF!) -> #REF! | V40: =SUM(#REF!) -> #REF! | W40: =SUM(#REF!) -> #REF! | X40: =SUM(#REF!) -> #REF! | Y40: =SUM(#REF!) -> #REF! | Z40: 2082060.7 | AA40: =SUM(#REF!) -> #REF!
B42: FINANCE & ACCOUNT
B43: TOTAL | F43: =SUM(#REF!) -> #REF! | H43: =SUM(#REF!) -> #REF! | I43: =SUM(#REF!) -> #REF! | J43: =SUM(#REF!) -> #REF! | K43: =SUM(#REF!) -> #REF! | L43: =SUM(#REF!) -> #REF! | M43: =SUM(#REF!) -> #REF! | O43: =SUM(#REF!) -> #REF! | P43: =SUM(#REF!) -> #REF! | Q43: =SUM(#REF!) -> #REF! | R43: =SUM(#REF!) -> #REF! | S43: =0 -> 0 | U43: =SUM(#REF!) -> #REF! | V43: =SUM(#REF!) -> #REF! | W43: =SUM(#REF!) -> #REF! | X43: =SUM(#REF!) -> #REF! | Y43: =SUM(#REF!) -> #REF! | Z43: 2761365 | AA43: =SUM(#REF!) -> #REF!
B45: ADMINISTRATION & HUMAN RESOURCE
A46: 1 | B46: SIMON YAKUBU WAKAWA | D46: ASST. MANAGER , ASSETS & MAINT. | E46: 13(10) | F46: =25523.45 -> 25523.45 | H46: =F46*300% -> 76570.35 | I46: =F46*7.5% -> 1914.2587 | J46: 0 | K46: =F46*50% -> 12761.725 | L46: =F46*350% -> 89332.075 | M46: =F46*100% -> 25523.45 | O46: 70000 | P46: =F46*10% -> 2552.345 | Q46: 15000 | S46: =SUM(F46:R46) -> 319177.65 | U46: 30000 | V46: =52500 -> 52500 | W46: ='[5]Jan 2021'!$H$49 -> 638.08625 | X46: 7709.76 | Y46: =X46+W46+V46+U46+T46 -> 90847.846 | Z46: 223329.81 | AA46: =S46-Y46 -> 228329.81 | AB46: 14 (8) | AC46: =257211+70000 -> 327211 | AD46: =AC46-S46 -> 8033.3463 | AE46: =23/31*AD46 -> 5960.2246 | AF46: =AE46+AD46 -> 13993.571 | AG46: 7709.76 | AH46: 7709.76 | AI46: =AH46-AG46 -> 0
A47: 2 | B47: SALAMATU YAKUBU | D47: PRINCIPAL CONF. SECRETARY | E47: 13(10) | F47: =25523.45 -> 25523.45 | H47: =F47*300% -> 76570.35 | I47: =F47*7.5% -> 1914.2587 | J47: 0 | K47: =F47*50% -> 12761.725 | L47: =F47*350% -> 89332.075 | M47: =F47*100% -> 25523.45 | O47: 70000 | P47: =F47*10% -> 2552.345 | Q47: 15000 | R47: 0 | S47: =SUM(F47:R47) -> 319177.65 | U47: =0 -> 0 | V47: =0 -> 0 | W47: ='[5]Jan 2021'!$H$53 -> 638.08625 | X47: 7709.76 | Y47: =X47+W47+V47+U47+T47 -> 8347.8463 | Z47: 308829.81 | AA47: =S47-Y47 -> 310829.81 | AB47: 14 (8) | AC47: =257211+70000 -> 327211 | AD47: =AC47-S47 -> 8033.3463 | AE47: =23/31*AD47 -> 5960.2246 | AF47: =AE47+AD47 -> 13993.571 | AG47: 7709.76 | AH47: 7709.76 | AI47: =AH47-AG47 -> 0
A48: 3 | B48: USMAN WAZIRI | D48: PRINCIPAL CONF. SECRETARY | E48: 13(10) | F48: =25523.45 -> 25523.45 | H48: =F48*300% -> 76570.35 | I48: =F48*7.5% -> 1914.2587 | J48: 0 | K48: =F48*50% -> 12761.725 | L48: =F48*350% -> 89332.075 | M48: =F48*100% -> 25523.45 | O48: 70000 | P48: =F48*10% -> 2552.345 | Q48: 15000 | R48: 0 | S48: =SUM(F48:R48) -> 319177.65 | U48: =3000 -> 3000 | V48: =50000 -> 50000 | X48: 7709.76 | Y48: =X48+W48+V48+U48+T48 -> 60709.76 | Z48: 258467.89 | AA48: =S48-Y48 -> 258467.89 | AB48: 14 (8) | AC48: =257211+70000 -> 327211 | AD48: =AC48-S48 -> 8033.3463 | AE48: =23/31*AD48 -> 5960.2246 | AF48: =AE48+AD48 -> 13993.571 | AG48: 7709.76 | AH48: 7709.76 | AI48: =AH48-AG48 -> 0
A49: 4 | B49: EROMOSELE OMONIGBO | D49: PERSONNEL OFFICER | E49: 10(11) | F49: =19276.95 -> 19276.95 | H49: =F49*300% -> 57830.85 | I49: =F49*7.5% -> 1445.7713 | J49: 0 | K49: =F49*50% -> 9638.475 | L49: =F49*350% -> 67469.325 | M49: =F49*100% -> 19276.95 | O49: =60000 -> 60000 | P49: =F49*10% -> 1927.695 | Q49: 10000 | R49: 0 | S49: =SUM(F49:R49) -> 246866.02 | U49: 10000 | V49: =0 -> 0 | W49: ='[5]Jan 2021'!$H$41 -> 481.92375 | X49: =3369.51 -> 3369.51 | Y49: =X49+W49+V49+U49+T49 -> 13851.434 | Z49: 233014.58 | AA49: =S49-Y49 -> 233014.58 | AB49: 12(7) | AC49: =205372+60000 -> 265372 | AD49: =AC49-S49 -> 18505.984 | AE49: =23/31*AD49 -> 13730.246 | AF49: =AE49+AD49 -> 32236.23 | AG49: =3369.51 -> 3369.51 | AH49: =3369.51 -> 3369.51 | AI49: =AH49-AG49 -> 0
A50: 5 | B50: OGUNYOMI ROTIMI | D50: PERSONNEL OFFICER | E50: 10(10) | F50: =18779.3 -> 18779.3 | H50: =F50*300% -> 56337.9 | I50: =F50*7.5% -> 1408.4475 | J50: 0 | K50: =F50*50% -> 9389.65 | L50: =F50*350% -> 65727.55 | M50: =F50*100% -> 18779.3 | O50: =60000 -> 60000 | P50: =F50*10% -> 1877.93 | Q50: 10000 | R50: 0 | S50: =SUM(F50:R50) -> 242300.08 | V50: =50000 -> 50000 | X50: 3369.51 | Y50: =X50+W50+V50+U50+T50 -> 53369.51 | Z50: 188930.57 | AA50: =S50-Y50 -> 188930.57 | AB50: 12(7) | AC50: =205372+60000 -> 265372 | AD50: =AC50-S50 -> 23071.923 | AE50: =23/31*AD50 -> 17117.878 | AF50: =AE50+AD50 -> 40189.8 | AG50: =3369.51 -> 3369.51 | AH50: =3369.51 -> 3369.51 | AI50: =AH50-AG50 -> 0
A51: 6 | B51: OMOUDU QUEEN PRISCILLA | D51: SECRETARY | E51: 10(11) | F51: =19276.95 -> 19276.95 | H51: =F51*300% -> 57830.85 | I51: =F51*7.5% -> 1445.7713 | K51: =F51*50% -> 9638.475 | L51: =F51*350% -> 67469.325 | M51: =F51*100% -> 19276.95 | O51: =60000 -> 60000 | P51: =F51*10% -> 1927.695 | Q51: 10000 | S51: =SUM(F51:R51) -> 246866.02 | U51: =20000+10000 -> 30000 | X51: 3369.51 | Y51: =X51+W51+V51+U51+T51 -> 33369.51 | Z51: 213496.51 | AA51: =S51-Y51 -> 213496.51 | AB51: 12(7) | AC51: =205372+60000 -> 265372 | AD51: =AC51-S51 -> 18505.984 | AE51: =23/31*AD51 -> 13730.246 | AF51: =AE51+AD51 -> 32236.23 | AG51: =3369.51 -> 3369.51 | AH51: =3369.51 -> 3369.51 | AI51: =AH51-AG51 -> 0
A52: 7 | B52: YUSIF SADIQ SANI | D52: CONFIDENTIAL SECRETARY | E52: 8(10) | F52: =13492.21 -> 13492.21 | H52: =F52*300% -> 40476.63 | I52: =F52*7.5% -> 1011.9157 | K52: =F52*50% -> 6746.105 | L52: =F52*350% -> 47222.735 | M52: =F52*100% -> 13492.21 | O52: =50000 -> 50000 | P52: =F52*10% -> 1349.221 | Q52: 10000 | S52: =SUM(F52:R52) -> 183791.03 | U52: =10000 -> 10000 | V52: 0 | X52: 1484.37 | Y52: =X52+W52+V52+U52+T52 -> 11484.37 | Z52: 172306.66 | AA52: =S52-Y52 -> 172306.66 | AB52: 10 (7) | AC52: =168602+60000 -> 228602 | AD52: =AC52-S52 -> 44810.973 | AE52: =23/31*AD52 -> 33246.851 | AF52: =AE52+AD52 -> 78057.824 | AG52: =3369.51 -> 3369.51 | AH52: =3369.51 -> 3369.51 | AI52: =AH52-AG52 -> 0
A53: 8 | B53: STELLA NGOZI PAUL | D53: CONFIDENTIAL SECRETARY | E53: 8(10) | F53: =13492.21 -> 13492.21 | H53: =F53*300% -> 40476.63 | I53: =F53*7.5% -> 1011.9157 | K53: =F53*50% -> 6746.105 | L53: =F53*350% -> 47222.735 | M53: =F53*100% -> 13492.21 | O53: =50000 -> 50000 | P53: =F53*10% -> 1349.221 | Q53: 10000 | S53: =SUM(F53:R53) -> 183791.03 | U53: =10000+30000 -> 40000 | V53: =7500 -> 7500 | W53: ='[5]Jan 2021'!$H$37 -> 337.30525 | X53: 1484.37 | Y53: =X53+W53+V53+U53+T53 -> 49321.675 | Z53: 134469.35 | AA53: =S53-Y53 -> 134469.35 | AB53: 10 (7) | AC53: =168602+60000 -> 228602 | AD53: =AC53-S53 -> 44810.973 | AE53: =23/31*AD53 -> 33246.851 | AF53: =AE53+AD53 -> 78057.824 | AG53: =3369.51 -> 3369.51 | AH53: =3369.51 -> 3369.51 | AI53: =AH53-AG53 -> 0
A54: 9 | B54: OWOEYE TOSIN KAYODE | D54: CONFIDENTIAL SECRETARY | E54: 8(10) | F54: =13492.21 -> 13492.21 | H54: =F54*300% -> 40476.63 | I54: =F54*7.5% -> 1011.9157 | K54: =F54*50% -> 6746.105 | L54: =F54*350% -> 47222.735 | M54: =F54*100% -> 13492.21 | O54: =50000 -> 50000 | P54: =F54*10% -> 1349.221 | Q54: 10000 | S54: =SUM(F54:R54) -> 183791.03 | X54: 1484.37 | Y54: =X54+W54+V54+U54+T54 -> 1484.37 | Z54: 182306.66 | AA54: =S54-Y54 -> 182306.66 | AB54: 10 (7) | AC54: =168602+60000 -> 228602 | AD54: =AC54-S54 -> 44810.973 | AE54: =23/31*AD54 -> 33246.851 | AF54: =AE54+AD54 -> 78057.824 | AG54: =3369.51 -> 3369.51 | AH54: =3369.51 -> 3369.51 | AI54: =AH54-AG54 -> 0
A55: 10 | B55: IBRAHIM ZAKARI AHMAD | D55: DRIVER | E55: 4(10) | F55: =4836.3 -> 4836.3 | H55: =F55*300% -> 14508.9 | I55: =F55*7.5% -> 362.7225 | K55: =F55*50% -> 2418.15 | L55: =F55*350% -> 16927.05 | M55: =F55*100% -> 4836.3 | O55: =15000 -> 15000 | P55: =F55*10% -> 483.63 | Q55: 5000 | R55: =7000 -> 7000 | S55: =SUM(F55:R55) -> 71373.052 | U55: =5000+3000 -> 8000 | V55: =15000 -> 15000 | X55: 236.04 | Y55: =X55+W55+V55+U55+T55 -> 23236.04 | Z55: 47137.012 | AA55: =S55-Y55 -> 48137.012 | AB55: 5 (7) | AC55: =48538+7000+20000 -> 75538 | AD55: =AC55-S55 -> 4164.9475 | AE55: =23/31*AD55 -> 3090.1223 | AF55: =AE55+AD55 -> 7255.0698 | AG55: 236.04 | AH55: 236.04 | AI55: =AH55-AG55 -> 0
A56: 11 | B56: SHEDRACK NASARA M. | D56: DRIVER | E56: 4(10) | F56: =4836.3 -> 4836.3 | H56: =F56*300% -> 14508.9 | I56: =F56*7.5% -> 362.7225 | K56: =F56*50% -> 2418.15 | L56: =F56*350% -> 16927.05 | M56: =F56*100% -> 4836.3 | O56: =15000 -> 15000 | P56: =F56*10% -> 483.63 | Q56: 5000 | R56: =4000 -> 4000 | S56: =SUM(F56:R56) -> 68373.052 | U56: =10000+3000+5000 -> 18000 | V56: =25555.56 -> 25555.56 | X56: 236.04 | Y56: =X56+W56+V56+U56+T56 -> 43791.6 | Z56: 24581.452 | AA56: =S56-Y56 -> 24581.452 | AB56: 5 (7) | AC56: =48538+4000+20000 -> 72538 | AD56: =AC56-S56 -> 4164.9475 | AE56: =23/31*AD56 -> 3090.1223 | AF56: =AE56+AD56 -> 7255.0698 | AG56: 236.04 | AH56: 236.04 | AI56: =AH56-AG56 -> 0
A57: 12 | B57: IBRAHIM ALIYU | D57: DRIVER | E57: 4(10) | F57: =4836.3 -> 4836.3 | H57: =F57*300% -> 14508.9 | I57: =F57*7.5% -> 362.7225 | K57: =F57*50% -> 2418.15 | L57: =F57*350% -> 16927.05 | M57: =F57*100% -> 4836.3 | O57: =15000 -> 15000 | P57: =F57*10% -> 483.63 | Q57: 5000 | R57: =7000 -> 7000 | S57: =SUM(F57:R57) -> 71373.052 | U57: =5000+3000 -> 8000 | V57: =30087.22 -> 30087.22 | X57: 236.04 | Y57: =X57+W57+V57+U57+T57 -> 38323.26 | Z57: 33049.792 | AA57: =S57-Y57 -> 33049.792 | AB57: 5 (7) | AC57: =48538+7000+20000 -> 75538 | AD57: =AC57-S57 -> 4164.9475 | AE57: =23/31*AD57 -> 3090.1223 | AF57: =AE57+AD57 -> 7255.0698 | AG57: 236.04 | AH57: 236.04 | AI57: =AH57-AG57 -> 0
A58: 13 | B58: ABUBAKAR AMINU DOLE | D58: DRIVER | E58: 4(10) | F58: =4836.3 -> 4836.3 | H58: =F58*300% -> 14508.9 | I58: =F58*7.5% -> 362.7225 | K58: =F58*50% -> 2418.15 | L58: =F58*350% -> 16927.05 | M58: =F58*100% -> 4836.3 | O58: =15000 -> 15000 | P58: =F58*10% -> 483.63 | Q58: 5000 | R58: =4000 -> 4000 | S58: =SUM(F58:R58) -> 68373.052 | U58: =10000+3000 -> 13000 | V58: =8416.67 -> 8416.67 | X58: 236.04 | Y58: =X58+W58+V58+U58+T58 -> 21652.71 | Z58: 46720.342 | AA58: =S58-Y58 -> 46720.342 | AB58: 5 (7) | AC58: =48538+4000+20000 -> 72538 | AD58: =AC58-S58 -> 4164.9475 | AE58: =23/31*AD58 -> 3090.1223 | AF58: =AE58+AD58 -> 7255.0698 | AG58: 236.04 | AH58: 236.04 | AI58: =AH58-AG58 -> 0
A59: 14 | B59: DARAMOLA SANJO SAMSON | D59: DRIVER | E59: 4(10) | F59: =4836.3 -> 4836.3 | H59: =F59*300% -> 14508.9 | I59: =F59*7.5% -> 362.7225 | K59: =F59*50% -> 2418.15 | L59: =F59*350% -> 16927.05 | M59: =F59*100% -> 4836.3 | O59: =15000 -> 15000 | P59: =F59*10% -> 483.63 | Q59: 5000 | R59: =7000 -> 7000 | S59: =SUM(F59:R59) -> 71373.052 | U59: =5000 -> 5000 | V59: =3550.56 -> 3550.56 | X59: 236.04 | Y59: =X59+W59+V59+U59+T59 -> 8786.6 | Z59: 62586.452 | AA59: =S59-Y59 -> 62586.452 | AB59: 5 (7) | AC59: =48538+7000+20000 -> 75538 | AD59: =AC59-S59 -> 4164.9475 | AE59: =23/31*AD59 -> 3090.1223 | AF59: =AE59+AD59 -> 7255.0698 | AG59: 236.04 | AH59: 236.04 | AI59: =AH59-AG59 -> 0
B60: TOTAL | D60: 14 | F60: =SUM(F46:F59) -> 198561.68 | H60: =SUM(H46:H59) -> 595685.04 | I60: =SUM(I46:I59) -> 14892.126 | J60: =SUM(J46:J59) -> 0 | K60: =SUM(K46:K59) -> 99280.84 | L60: =SUM(L46:L59) -> 694965.88 | M60: =SUM(M46:M59) -> 198561.68 | N60: =SUM(N46:N59) -> 0 | O60: =SUM(O46:O59) -> 615000 | ... S60: =SUM(S46:S59) -> 2595803.4 | U60: =SUM(U46:U59) -> 175000 | V60: =SUM(V46:V59) -> 242610.01 | W60: =SUM(W46:W59) -> 2095.4015 | X60: =SUM(X46:X59) -> 38871.12 | Y60: =SUM(Y46:Y59) -> 458576.53 | Z60: 6521425.5 | AA60: =SUM(AA46:AA59) -> 2137226.9 | AC60: =SUM(AC46:AC59) -> 2835245 | AD60: =SUM(AD46:AD59) -> 239441.59 | AE60: =SUM(AE46:AE59) -> 177650.21 | AF60: =SUM(AF46:AF59) -> 417091.79 | AG60: =SUM(AG46:AG59) -> 44526.54 | AH60: =SUM(AH46:AH59) -> 44526.54 | AI60: =SUM(AI46:AI59) -> 0
B61: GRAND TOTAL | D61: =D13+D16+D20+D23+D28+D31+D34+D37+D40+D43+D60 -> 22 | F61: =F13+F16+F20+F23+F28+F31+F34+F37+F40+F43+F60 -> #REF! | G61: =G13+G16+G20+G23+G28+G31+G34+G37+G40+G43+G60 -> #REF! | H61: =H13+H16+H20+H23+H28+H31+H34+H37+H40+H43+H60 -> #REF! | I61: =I13+I16+I20+I23+I28+I31+I34+I37+I40+I43+I60 -> #REF! | J61: =J13+J16+J20+J23+J28+J31+J34+J37+J40+J43+J60 -> #REF! | K61: =K13+K16+K20+K23+K28+K31+K34+K37+K40+K43+K60 -> #REF! | L61: =L13+L16+L20+L23+L28+L31+L34+L37+L40+L43+L60 -> #REF! | M61: =M13+M16+M20+M23+M28+M31+M34+M37+M40+M43+M60 -> #REF! | ... AA61: =AA13+AA16+AA20+AA23+AA28+AA31+AA34+AA37+AA40+AA43+AA60 -> #REF! | AC61: =AC13+AC20+AC28+AC60 -> 5966764 | AD61: =AD13+AD20+AD28+AD60 -> 447490.01 | AE61: =AE13+AE20+AE28+AE60 -> 332008.71 | AF61: =AD61+AE61 -> 779498.72 | AG61: =AG13+AG20+AG28+AG60 -> 97524.12 | AH61: =AH13+AH20+AH28+AH60 -> 105362.69 | AI61: =AI13+AI20+AI28+AI60 -> 7838.57
B63: Net effect of staff promotiton | K63: SIGNATURE | P63: DATE | AI63: =-AF61+AI61 -> -771660.15
AE65: ='April, 2022'!F192-Promotion!AE61 -> -288258.71

Sheet Library
D2: DESIGNATION | E2: GRADE LEVEL | F2: SALARY | G2: SALARY/ALLOWCE AREARS | H2: RENT | I2: UTILITY | J2: DOMESTIC | K2: ENTERT. | L2: FURNIT. | M2: FUEL | N2: ALLOWANCE | O2: ALLOWANCE | P2: ALLCE | Q2: ALLCE | R2: DUTY ALLCE | S2: GROSS SALARY | T2: AUCTION | U2: COOP SOCIETY | V2: COOP. LOAN RECOVERY | W2: NHF DEDUCTION | X2: PAYE | Y2: TOTAL | AB2: SHIFT DUTY ALLOWANCES (11% of GROSS)
B3: LIBRARY AND DOCUMENTATION
A4: 1 | B4: ALIYU SANNI ABUBAKAR | D4: RESEARCH FELLOW 11 DATA & DOCU | E4: 13(11) | F4: =26339.3 -> 26339.3 | H4: =F4*300% -> 79017.9 | I4: =F4*7.5% -> 1975.4475 | J4: 0 | K4: =F4*50% -> 13169.65 | L4: =F4*350% -> 92187.55 | M4: =F4*100% -> 26339.3 | N4: =120000 -> 120000 | P4: =F4*10% -> 2633.93 | Q4: 15000 | R4: 0 | S4: =SUM(F4:R4) -> 376663.08 | U4: 30000 | V4: =43750 -> 43750 | W4: ='[5]Jan 2021'!$H$36 -> 658.4825 | X4: =7709.76 -> 7709.76 | Y4: =X4+W4+V4+U4+T4 -> 82118.242 | Z4: 294544.83 | AA4: =S4-Y4 -> 294544.83 | AB4: =S4*0.11 -> 41432.939
A5: 2 | B5: CHINAKO N. ASOGWA | D5: RESEARCH FELLOW 11 DATA & DOCU | E5: 13(9) | F5: =24741.26 -> 24741.26 | H5: =F5*300% -> 74223.78 | I5: =F5*7.5% -> 1855.5945 | J5: 0 | K5: =F5*50% -> 12370.63 | L5: =F5*350% -> 86594.41 | M5: =F5*100% -> 24741.26 | N5: =120000 -> 120000 | P5: =F5*10% -> 2474.126 | Q5: 15000 | S5: =SUM(F5:R5) -> 362001.06 | U5: =50000 -> 50000 | V5: =68750+45833.33 -> 114583.33 | X5: =7709.76 -> 7709.76 | Y5: =X5+W5+V5+U5+T5 -> 172293.09 | Z5: 235541.3 | AA5: =S5-Y5 -> 189707.97 | AB5: =S5*0.11 -> 39820.117
A6: 3 | B6: AMOS ABA | D6: LIBRARY ASSISTANT | E6: 8(9) | F6: =13112.16 -> 13112.16 | H6: =F6*300% -> 39336.48 | I6: =F6*7.5% -> 983.412 | K6: =F6*50% -> 6556.08 | L6: =F6*350% -> 45892.56 | M6: =F6*100% -> 13112.16 | N6: =100000 -> 100000 | P6: =F6*10% -> 1311.216 | Q6: 10000 | S6: =SUM(F6:R6) -> 230304.07 | U6: 20000 | V6: =50000 -> 50000 | X6: 1484.37 | Y6: =X6+W6+V6+U6+T6 -> 71484.37 | Z6: 158819.7 | AA6: =S6-Y6 -> 158819.7 | AB6: =S6*0.11 -> 25333.447
A7: 4 | B7: TITILAYO DANIEL MARVELLOUS | D7: LIBRARY ASSISTANT | E7: 8(8) | F7: =12732 -> 12732 | H7: =F7*300% -> 38196 | I7: =F7*7.5% -> 954.9 | K7: =F7*50% -> 6366 | L7: =F7*350% -> 44562 | M7: =F7*100% -> 12732 | N7: =100000 -> 100000 | P7: =F7*10% -> 1273.2 | Q7: 10000 | S7: =SUM(F7:R7) -> 226816.1 | U7: =25000 -> 25000 | V7: 0 | X7: 1484.37 | Y7: =X7+W7+V7+U7+T7 -> 26484.37 | Z7: 200580.91 | AA7: =S7-Y7 -> 200331.73 | AB7: =S7*0.11 -> 24949.771
A8: 5 | B8: ENENCHE JEREMIAH AGADA | D8: LIBRARY ASSISTANT | E8: 8(7) | F8: =12351.94 -> 12351.94 | H8: =F8*300% -> 37055.82 | I8: =F8*7.5% -> 926.3955 | K8: =F8*50% -> 6175.97 | L8: =F8*350% -> 43231.79 | M8: =F8*100% -> 12351.94 | N8: =100000 -> 100000 | P8: =F8*10% -> 1235.194 | Q8: 10000 | S8: =SUM(F8:R8) -> 223329.05 | X8: 1484.37 | Y8: =X8+W8+V8+U8+T8 -> 1484.37 | AA8: =S8-Y8 -> 221844.68 | AB8: =S8*0.11 -> 24566.195
A9: 6 | B9: ABBAS ZAINAB | D9: LIBRARY ASSISTANT | E9: 8(7) | F9: =12351.94 -> 12351.94 | H9: =F9*300% -> 37055.82 | I9: =F9*7.5% -> 926.3955 | K9: =F9*50% -> 6175.97 | L9: =F9*350% -> 43231.79 | M9: =F9*100% -> 12351.94 | N9: =100000 -> 100000 | P9: =F9*10% -> 1235.194 | Q9: 10000 | S9: =SUM(F9:R9) -> 223329.05 | X9: 1484.37 | Y9: =X9+W9+V9+U9+T9 -> 1484.37 | AA9: =S9-Y9 -> 221844.68 | AB9: =S9*0.11 -> 24566.195
B10: TOTAL | D10: 6 | F10: =SUM(F4:F9) -> 101628.6 | H10: =SUM(H4:H9) -> 304885.8 | I10: =SUM(I4:I9) -> 7622.145 | J10: =SUM(J4:J9) -> 0 | K10: =SUM(K4:K9) -> 50814.3 | L10: =SUM(L4:L9) -> 355700.1 | M10: =SUM(M4:M9) -> 101628.6 | N10: =SUM(N4:N9) -> 640000 | P10: =SUM(P4:P9) -> 10162.86 | Q10: =SUM(Q4:Q9) -> 70000 | R10: =SUM(R4:R9) -> 0 | S10: =SUM(S4:S9) -> 1642442.4 | U10: =SUM(U4:U9) -> 125000 | V10: =SUM(V4:V9) -> 208333.33 | W10: =SUM(W4:W9) -> 658.4825 | X10: =SUM(X4:X9) -> 21357 | Y10: =SUM(Y4:Y9) -> 355348.81 | Z10: =SUM(Z4:Z9) -> 889486.74 | AA10: =SUM(AA4:AA9) -> 1287093.6 | AB10: =SUM(AB4:AB9) -> 180668.66

Sheet New staff (3)
B3: STAFF PAYROLL FOR THE MONTH OF APRIL, 2022
F4: ='[1]FEB 08'!E8/'[1]FEB 08'!M8 -> 0.22 | I4: ='[1]FEB 08'!F8/'[1]FEB 08'!Q8 -> 0.3
B5: EFFECT OF ADDITION OF NEW STAFF | S5: DEDUCTIONS | Y5: NET SALARY
D6: DESIGNATION | E6: SALARY | F6: BASIC | M6: MOTOR/ | N6: OLD | O6: LEAVE | P6: OUT FIT | Q6: LEGISLATIVE | R6: GROSS | X6: JUNE,2021 | Y6: JULY,2021 | Z6: NEW
E7: LEVEL | F7: SALARY | G7: SALARY/ALLOWCE AREARS | H7: RENT | I7: UTILITY | J7: DOMESTIC | K7: ENTERT. | L7: FURNIT. | M7: FUEL | N7: SALARY | O7: ALLCE | P7: ALLCE | Q7: DUTY ALLCE | R7: SALARY | S7: COOP SOCIETY | T7: COOP. LOAN RECOVERY | U7: NHF DEDUCTION | V7: PAYE | W7: TOTAL | Z7: SALARY | AA7: DIFFERENCE | AB7: OLD TAX | AC7: NEW TAX | AD7: DIFFERENCE
A8: S/N | B8: DG OFFICE | F8: N | I8: N | R8: N | V8: N
B10: TOTAL | F10: =SUM(F9:F9) -> 0 | H10: =SUM(H9:H9) -> 0 | I10: =SUM(I9:I9) -> 0 | J10: =SUM(J9:J9) -> 0 | K10: =SUM(K9:K9) -> 0 | L10: =SUM(L9:L9) -> 0 | M10: =SUM(M9:M9) -> 0 | N10: =SUM(N9:N9) -> 0 | O10: =SUM(O9:O9) -> 0 | ... W10: =SUM(W9:W9) -> 0 | X10: 7468053.9 | Y10: =SUM(Y9:Y9) -> 0 | Z10: =SUM(Z9) -> 0 | AA10: =SUM(AA9) -> 0 | AC10: =SUM(AC9) -> 0 | AD10: =SUM(AD9) -> 0
B12: INTERNAL AUDIT
A13: 1 | B13: JAMILA ABDUL | D13: AUDITOR 11 | E13: 8 (7) | Z13: =(123329+50000)*12/30 -> 69331.6 | AA13: =Z13-N13 -> 69331.6 | AC13: =1484.37 -> 1484.37 | AD13: =AC13-AB13 -> 1484.37
C14: TOTAL | D14: 1 | F14: =SUM(F13:F13) -> 0 | H14: =SUM(H13:H13) -> 0 | I14: =SUM(I13:I13) -> 0 | J14: =SUM(J13:J13) -> 0 | K14: =SUM(K13:K13) -> 0 | L14: =SUM(L13:L13) -> 0 | M14: =SUM(M13:M13) -> 0 | N14: =SUM(N13:N13) -> 0 | O14: =SUM(O13:O13) -> 0 | ... W14: =SUM(W13:W13) -> 0 | X14: 383180.46 | Y14: =SUM(Y13:Y13) -> 0 | Z14: =SUM(Z13:Z13) -> 69331.6 | AA14: =SUM(AA13:AA13) -> 69331.6 | AC14: =SUM(AC13:AC13) -> 1484.37 | AD14: =SUM(AD13:AD13) -> 1484.37
B16: LEG. SUPPORT SEVICES
A17: 1 | B17: ZAINAB AKINDE | D17: RESEARCH OFFICER | E17: 9 (7) | Z17: =(145204+100000)*12/30 -> 98081.6 | AA17: =Z17-N17 -> 98081.6 | AC17: =1484.37 -> 1484.37 | AD17: =AC17-AB17 -> 1484.37
B18: TOTAL | D18: 1 | F18: =SUM(#REF!) -> #REF! | H18: =SUM(#REF!) -> #REF! | I18: =SUM(#REF!) -> #REF! | J18: =SUM(#REF!) -> #REF! | K18: =SUM(#REF!) -> #REF! | L18: =SUM(#REF!) -> #REF! | M18: =SUM(#REF!) -> #REF! | Z18: =SUM(Z17) -> 98081.6 | AA18: =SUM(AA17) -> 98081.6 | AC18: =SUM(AC17) -> 1484.37 | AD18: =SUM(AD17) -> 1484.37
B20: LEGAL SERVICES
B23: TOTAL | F23: =SUM(F21:F22) -> 0 | H23: =SUM(H21:H22) -> 0 | I23: =SUM(I21:I22) -> 0 | J23: =SUM(J21:J22) -> 0 | K23: =SUM(K21:K22) -> 0 | L23: =SUM(L21:L22) -> 0 | M23: =SUM(M21:M22) -> 0 | N23: =SUM(N21:N22) -> 0 | O23: =SUM(O21:O22) -> 0 | ... S23: =SUM(S21:S22) -> 0 | U23: =SUM(U21:U22) -> 0 | V23: =SUM(V21:V22) -> 0 | W23: =SUM(W21:W22) -> 0 | X23: 1126604.2 | Y23: =SUM(Y21:Y22) -> 0 | Z23: =SUM(Z21:Z22) -> 0 | AA23: =SUM(AA21:AA22) -> 0 | AC23: =SUM(AC21:AC22) -> 0 | AD23: =SUM(AD21:AD22) -> 0
B25: DEMOCRATIC STUDIES
A26: 1 | B26: SHAFIU YAHYA MIKAIL | D26: PRINCIPAL RESEARCH OFFICER | E26: 12 (7) | Z26: =(205372+110000)*12/30 -> 126148.8 | AA26: =Z26-N26 -> 126148.8 | AC26: 3369.51 | AD26: =AC26-AB26 -> 3369.51
A27: 2 | B27: HASSAN YERIMA | D27: PRINCIPAL RESEARCH OFFICER | E27: 12 (7) | Z27: =(205372+110000)*12/30 -> 126148.8 | AA27: =Z27-N27 -> 126148.8 | AC27: 3369.51 | AD27: =AC27-AB27 -> 3369.51
B28: TOTAL | D28: 2 | F28: =SUM(#REF!) -> #REF! | H28: =SUM(#REF!) -> #REF! | I28: =SUM(#REF!) -> #REF! | J28: =SUM(#REF!) -> #REF! | K28: =SUM(#REF!) -> #REF! | L28: =SUM(#REF!) -> #REF! | M28: =SUM(#REF!) -> #REF! | Z28: =SUM(Z26:Z27) -> 252297.6 | AA28: =SUM(AA26:AA27) -> 252297.6 | AC28: =SUM(AC26:AC27) -> 6739.02 | AD28: =SUM(AD26:AD27) -> 6739.02
B30: STUDIES
B31: TOTAL | F31: =SUM(#REF!) -> #REF! | H31: =SUM(#REF!) -> #REF! | I31: =SUM(#REF!) -> #REF! | J31: =SUM(#REF!) -> #REF! | K31: =SUM(#REF!) -> #REF! | L31: =SUM(#REF!) -> #REF! | M31: =SUM(#REF!) -> #REF!
B33: ECONOMIC AND SOCIAL DEV.
A34: 1 | B34: FESTUS OSAGU | D34: RESEARCH FELLOW 1 | E34: 14 (7) | Z34: =(249153+140000)*12/30 -> 155661.2 | AA34: =Z34-N34 -> 155661.2 | AC34: =7709.76 -> 7709.76 | AD34: =AC34-AB34 -> 7709.76
A35: 2 | B35: YUSUF IBRAHIM | D35: PRINCIPAL RESEARCH OFFICER | E35: 12 (7) | Z35: =(205372+110000)*9/30 -> 94611.6 | AA35: =Z35-N35 -> 94611.6 | AC35: 3369.51 | AD35: =AC35-AB35 -> 3369.51
B36: TOTAL | D36: 2 | F36: =SUM(#REF!) -> #REF! | H36: =SUM(#REF!) -> #REF! | I36: =SUM(#REF!) -> #REF! | J36: =SUM(#REF!) -> #REF! | K36: =SUM(#REF!) -> #REF! | L36: =SUM(#REF!) -> #REF! | M36: =SUM(#REF!) -> #REF! | Z36: =SUM(Z34:Z35) -> 250272.8 | AA36: =SUM(AA34:AA35) -> 250272.8 | AC36: =SUM(AC34:AC35) -> 11079.27 | AD36: =SUM(AD34:AD35) -> 11079.27
B38: TRAINING AND INTERNATIONAL COOP
B41: TOTAL | F41: =SUM(F39:F40) -> 0 | H41: =SUM(H39:H40) -> 0 | I41: =SUM(I39:I40) -> 0 | J41: =SUM(J39:J40) -> 0 | K41: =SUM(K39:K40) -> 0 | L41: =SUM(L39:L40) -> 0 | M41: =SUM(M39:M40) -> 0 | N41: =SUM(N39:N40) -> 0 | O41: =SUM(O39:O40) -> 0 | ... W41: =SUM(W39:W40) -> 0 | X41: 1259979.1 | Y41: =SUM(Y39:Y40) -> 0 | Z41: =SUM(Z39:Z40) -> 0 | AA41: =SUM(AA39:AA40) -> 0 | AC41: =SUM(AC39:AC40) -> 0 | AD41: =SUM(AD39:AD40) -> 0
B43: LIBRARY AND DOCUMENTATION
B44: TOTAL | F44: =SUM(#REF!) -> #REF! | H44: =SUM(#REF!) -> #REF! | I44: =SUM(#REF!) -> #REF! | J44: =SUM(#REF!) -> #REF! | K44: =SUM(#REF!) -> #REF! | L44: =SUM(#REF!) -> #REF! | M44: =SUM(#REF!) -> #REF!
B46: FINANCE & ACCOUNT
B49: TOTAL | F49: =SUM(F47:F48) -> 0 | H49: =SUM(H47:H48) -> 0 | I49: =SUM(I47:I48) -> 0 | J49: =SUM(J47:J48) -> 0 | K49: =SUM(K47:K48) -> 0 | L49: =SUM(L47:L48) -> 0 | M49: =SUM(M47:M48) -> 0 | N49: =SUM(N47:N48) -> 0 | O49: =SUM(O47:O48) -> 0 | ... W49: =SUM(W47:W48) -> 0 | X49: 2217865 | Y49: =SUM(Y47:Y48) -> 0 | Z49: =SUM(Z47:Z48) -> 0 | AA49: =SUM(AA47:AA48) -> 0 | AC49: =SUM(AC47:AC48) -> 0 | AD49: =SUM(AD47:AD48) -> 0
B51: ADMINISTRATION & HUMAN RESOURCE
A52: 1 | B52: ISERE RICHARD KANTEE | D52: SNR ADMIN/HR OFFICER | E52: 10(7) | Z52: =(168602+60000)*6/30 -> 45720.4 | AA52: =Z52-N52 -> 45720.4 | AC52: 3369.51 | AD52: =AC52-AB52 -> 3369.51
A53: 2 | B53: HARUNA MUSA | D53: ASST. ADMIN/HR | E53: 8 (7) | Z53: =(123329+50000)*12/30 -> 69331.6 | AA53: =Z53-N53 -> 69331.6 | AC53: =1484.37 -> 1484.37 | AD53: =AC53-AB53 -> 1484.37
B54: TOTAL | D54: 2 | F54: =SUM(#REF!) -> #REF! | H54: =SUM(#REF!) -> #REF! | I54: =SUM(#REF!) -> #REF! | J54: =SUM(#REF!) -> #REF! | K54: =SUM(#REF!) -> #REF! | L54: =SUM(#REF!) -> #REF! | M54: =SUM(#REF!) -> #REF! | Z54: =SUM(Z52:Z53) -> 115052 | AA54: =SUM(AA52:AA53) -> 115052 | AC54: =SUM(AC52:AC53) -> 4853.88 | AD54: =SUM(AD52:AD53) -> 4853.88
B55: GRAND TOTAL | D55: =D10+D14+D18+D23+D28+D31+D36+D41+D44+D49+D54 -> 8 | F55: =F10+F14+F18+F23+F28+F31+F36+F41+F44+F49+F54 -> #REF! | G55: =G10+G14+G18+G23+G28+G31+G36+G41+G44+G49+G54 -> 0 | H55: =H10+H14+H18+H23+H28+H31+H36+H41+H44+H49+H54 -> #REF! | I55: =I10+I14+I18+I23+I28+I31+I36+I41+I44+I49+I54 -> #REF! | J55: =J10+J14+J18+J23+J28+J31+J36+J41+J44+J49+J54 -> #REF! | K55: =K10+K14+K18+K23+K28+K31+K36+K41+K44+K49+K54 -> #REF! | L55: =L10+L14+L18+L23+L28+L31+L36+L41+L44+L49+L54 -> #REF! | M55: =M10+M14+M18+M23+M28+M31+M36+M41+M44+M49+M54 -> #REF! | ... AA55: =AA10+AA14+AA18+AA23+AA28+AA31+AA36+AA41+AA44+AA49+AA54 -> 785035.6 | AC55: =AC10+AC14+AC18+AC23+AC28+AC31+AC36+AC41+AC44+AC49+AC54 -> 25640.91 | AD55: =AD10+AD14+AD18+AD23+AD28+AD31+AD36+AD41+AD44+AD49+AD54 -> 25640.91
C56: GRAND NET EFFECT
AD57: =AA55-AD55 -> 759394.69

Sheet Welfare 2
B3: WELFARE FOR JULY, 2021
F4: ='[1]FEB 08'!E8/'[1]FEB 08'!M8 -> 0.22 | I4: ='[1]FEB 08'!F8/'[1]FEB 08'!Q8 -> 0.3
B5: STAFF NAME | S5: DEDUCTIONS | Y5: WELFARE
D6: DESIGNATION | E6: SALARY | F6: BASIC | M6: MOTOR/ | N6: RESEARCH | O6: LEAVE | P6: OUT FIT | Q6: LEGISLATIVE | R6: GROSS | X6: JUNE,2021 | Y6: JULY,2021
E7: LEVEL | F7: SALARY | G7: SALARY/ALLOWCE AREARS | H7: RENT | I7: UTILITY | J7: DOMESTIC | K7: ENTERT. | L7: FURNIT. | M7: FUEL | N7: ALLOWANCE | O7: ALLCE | P7: ALLCE | Q7: DUTY ALLCE | R7: SALARY | S7: COOP SOCIETY | T7: COOP. LOAN RECOVERY | U7: NHF DEDUCTION | V7: PAYE | W7: TOTAL
A8: S/N | B8: DG OFFICE | F8: N | I8: N | R8: N | V8: N
A9: 1 | B9: PROF. ABUBAKAR O. SULAIMAN | D9: DIRECTOR GENERAL | E9: CONSOL | F9: 160488.75 | H9: 320977.5 | I9: 48146.63 | J9: 120366.57 | K9: 72219.94 | L9: 0 | M9: 120366.57 | N9: =100000 -> 100000 | O9: 16048.88 | P9: 25000 | Q9: 25235 | R9: =SUM(F9:Q9) -> 1008849.8 | V9: 113176.97 | W9: =S9+T9+U9+V9 -> 113176.97 | X9: 895672.87 | Y9: =300000 -> 300000
A10: 2 | B10: DR ADEYEMI AKEEB FAJINGBESI | D10: DIR. SPECIAL DUTIES, DG OFFICE | E10: 17(9) | F10: 81740.02 | H10: =F10*300% -> 245220.06 | I10: =F10*7.5% -> 6130.5015 | J10: 80244.38 | K10: =F10*50% -> 40870.01 | L10: =F10*350% -> 286090.07 | M10: =F10*100% -> 81740.02 | N10: =100000 -> 100000 | O10: =F10*10% -> 8174.002 | P10: 20000 | Q10: 0 | R10: =SUM(F10:Q10) -> 950209.06 | S10: 200000 | T10: =59722.22 -> 59722.22 | U10: ='[5]Jan 2021'!$H$35 -> 2043.5005 | V10: 52776.63 | W10: =SUM(S10:V10) -> 314542.35 | X10: 635666.71 | Y10: =150000 -> 150000
A11: 3 | B11: SARAFADEEN ALABELEWE | D11: SA ADMINISTRATION | E11: 16(9) | F11: =42653.17 -> 42653.17 | H11: =F11*300% -> 127959.51 | I11: =F11*7.5% -> 3198.9877 | J11: 40122.19 | K11: =F11*50% -> 21326.585 | L11: =F11*350% -> 149286.1 | M11: =F11*100% -> 42653.17 | O11: =F11*10% -> 4265.317 | P11: 20000 | R11: =SUM(F11:Q11) -> 451465.02 | S11: =100000 -> 100000 | T11: =137500 -> 137500 | V11: 21618.09 | W11: =S11+T11+U11+V11 -> 259118.09 | X11: 192346.93 | Y11: =70000 -> 70000
A12: 4 | B12: DR JAKE DABANG DAN AZUMI | D12: DEPUTY DIRECTOR TRAINING | E12: 16(7) | F12: =39662.25 -> 39662.25 | H12: =F12*300% -> 118986.75 | I12: =F12*7.5% -> 2974.6687 | J12: 40122.19 | K12: =F12*50% -> 19831.125 | L12: =F12*350% -> 138817.88 | M12: =F12*100% -> 39662.25 | N12: =100000 -> 100000 | O12: =F12*10% -> 3966.225 | P12: 20000 | Q12: 150000 | R12: =SUM(F12:Q12) -> 674023.33 | U12: ='[5]Jan 2021'!$H$27 -> 991.55625 | V12: =21618.09 -> 21618.09 | W12: =SUM(S12:V12) -> 22609.646 | X12: 651413.69 | Y12: =70000 -> 70000
A13: 5 | B13: DR ABDULSALAM NASIRU NAEEM | D13: SA ACADEMICS | E13: 16(7) | F13: =39662.25 -> 39662.25 | H13: =F13*300% -> 118986.75 | I13: =F13*7.5% -> 2974.6687 | J13: 40122.19 | K13: =F13*50% -> 19831.125 | L13: =F13*350% -> 138817.88 | M13: =F13*100% -> 39662.25 | N13: =100000 -> 100000 | O13: =F13*10% -> 3966.225 | P13: 20000 | Q13: =100000 -> 100000 | R13: =SUM(F13:Q13) -> 624023.33 | V13: =21618.09 -> 21618.09 | W13: =S13+T13+U13+V13 -> 21618.09 | X13: 602405.24 | Y13: =70000 -> 70000
A14: 6 | B14: RAHEEM USMAN AYIGORO | D14: SA-INFRASTRUCTURE | E14: 16 (7) | F14: =39662.25 -> 39662.25 | H14: =F14*300% -> 118986.75 | I14: =F14*7.5% -> 2974.6687 | J14: 40122.19 | K14: =F14*50% -> 19831.125 | L14: =F14*350% -> 138817.88 | M14: =F14*100% -> 39662.25 | O14: =F14*10% -> 3966.225 | P14: 20000 | Q14: 0 | R14: =SUM(F14:Q14) -> 424023.33 | V14: =21618.09 -> 21618.09 | W14: =S14+T14+U14+V14 -> 21618.09 | X14: 402405.24 | Y14: =70000 -> 70000
A15: 7 | B15: AKINSANMI ADEJOKE OLUKEMI | D15: HEAD INFORMATION/PROTOCOL | E15: 15(9) | F15: 33507.5 | H15: =F15*300% -> 100522.5 | I15: =F15*7.5% -> 2513.0625 | J15: 40122.19 | K15: =F15*50% -> 16753.75 | L15: =F15*350% -> 117276.25 | M15: =F15*100% -> 33507.5 | O15: =F15*10% -> 3350.75 | P15: 20000 | Q15: =100000 -> 100000 | R15: =SUM(F15:Q15) -> 467553.5 | S15: =0 -> 0 | T15: 0 | U15: =837.69 -> 837.69 | V15: 15548.33 | W15: =S15+T15+U15+V15 -> 16386.02 | X15: 451167.48 | Y15: =70000 -> 70000
A16: 8 | B16: DR IKEME ARTHUR J.O | D16: SNR RESEARCH FELLOW | E16: 15(9) | F16: =33507.5 -> 33507.5 | H16: =F16*300% -> 100522.5 | I16: =F16*7.5% -> 2513.0625 | J16: 40122.19 | K16: =F16*50% -> 16753.75 | L16: =F16*350% -> 117276.25 | M16: =F16*100% -> 33507.5 | N16: =100000 -> 100000 | O16: =F16*10% -> 3350.75 | P16: 20000 | Q16: 0 | R16: =SUM(F16:Q16) -> 467553.5 | S16: 50000 | T16: =212642 -> 212642 | U16: ='[3]DECEMBER 2019'!$H$38 -> 837.6875 | V16: 15548.33 | W16: =SUM(S16:V16) -> 279028.02 | X16: 188525.48 | Y16: =70000 -> 70000
