Workbook

Sheet AUGUST 2025
A1: NATIONAL INSTITUTE FOR LEGISLATIVE AND DEMOCRATIC STUDIES
A2: STAFF PAYROLL FOR THE MONTH OF AUGUST 2025
E3: ='[1]FEB 08'!E11/'[1]FEB 08'!M11 -> #REF!
B4: STAFF NAME | C4: DESIGNATION | D4: GRADE LEVEL | E4: BASIC SALARY | F4: ALLCE/ AREARS | G4: ALLOWANCE | H4: ALLOWANCE | I4: DUTY ALLCE | J4: GROSS SALARY | K4: AUCTION | L4: COOP 1 CONTR/SPEC SAVINGS | M4: COOP. LOAN RECOVERY | N4: COOP 2 CONTR/SPEC SAVINGS | O4: NHF DED. | P4: PAYE | Q4: EMPLOYEE PENSIONS | R4: TOTAL DEDUCTION | S4: JULY, 2025 | T4: AUGUST, 2025
E5: N | F5: N | G5: N | H5: N | I5: N | J5: N | K5: N | L5: N | M5: N | O5: N | P5: N | Q5: N | R5: N | S5: N | T5: N
A6: S/N | B6: DG'S OFFICE
A7: 1 | B7: PROF. ABUBAKAR O. SULAIMAN | C7: DIRECTOR GENERAL | D7: CONSOL | E7: 1971137.1 | G7: =250000 -> 250000 | I7: 25235 | J7: =E7+F7+G7+H7+I7 -> 2246372.1 | P7: 409970.11 | Q7: 0 | R7: =P7+O7+M7+N7+L7+K7+Q7 -> 409970.11 | S7: 1836402 | T7: =J7-R7 -> 1836402
A8: 2 | B8: RAHEEM USMAN AYIGORO | C8: SA-INFRASTRUCTURE | D8: 16 (9) | E8: 905306.75 | H8: =90000 -> 90000 | I8: =100000 -> 100000 | J8: =E8+F8+G8+H8+I8 -> 1095306.8 | L8: =250000 -> 250000 | N8: 102000 | P8: 175060.05 | Q8: 72424.54 | R8: =P8+O8+M8+N8+L8+K8+Q8 -> 599484.59 | S8: 597822.16 | T8: =J8-R8 -> 495822.16
A9: 3 | B9: MARIAM MOHAMMED BELLO | C9: SA- SPECIAL DUTIES | D9: 16 (9) | E9: 905306.75 | H9: =90000 -> 90000 | I9: =200000+100000 -> 300000 | J9: =E9+F9+G9+H9+I9 -> 1295306.8 | P9: 227365.56 | R9: =P9+O9+M9+N9+L9+K9+Q9 -> 227365.56 | S9: 1067941.2 | T9: =J9-R9 -> 1067941.2
A10: 4 | B10: DR IKEME ARTHUR J.O | C10: DEPUTY DIRECTOR, M&E | D10: 16 (9) | E10: 905306.75 | G10: 180000 | I10: 0 | J10: =E10+F10+G10+H10+I10 -> 1085306.8 | L10: =50000 -> 50000 | M10: 206000 | O10: 13866.737 | P10: 170477.64 | Q10: 72424.54 | R10: =P10+O10+M10+N10+L10+K10+Q10 -> 512768.91 | S10: 572537.84 | T10: =J10-R10 -> 572537.84
A11: 5 | B11: ANDRAWUS MUSA | C11: DEP. DIRECTOR, STORES & PROCUREMENT | D11: 16(8) | E11: 879008.92 | H11: =90000 -> 90000 | I11: 50000 | J11: =E11+F11+G11+H11+I11 -> 1019008.9 | L11: =50000-40000 -> 10000 | M11: =90000+110000 -> 200000 | O11: 13084.663 | P11: 158706.48 | Q11: 68216.887 | R11: =P11+O11+M11+N11+L11+K11+Q11 -> 450008.03 | S11: 611498.18 | T11: =J11-R11 -> 569000.89
A12: 6 | B12: DR FRANCIS NDUM OJIE | C12: AD, TRAINING & IC./SA TO DG | D12: 15(8) | E12: 722595.5 | G12: 160000 | I12: =100000+100000 -> 200000 | J12: =E12+F12+G12+H12+I12 -> 1082595.5 | O12: 11149.896 | P12: 173285.16 | Q12: 57807.64 | R12: =P12+O12+M12+N12+L12+K12+Q12 -> 242242.69 | S12: 840352.81 | T12: =J12-R12 -> 840352.81
A13: 7 | B13: ALI ABDULLAHI | C13: CHIEF ICT OFFICER | D13: 14(11) | E13: 589657 | H13: =70000 -> 70000 | I13: =0 -> 0 | J13: =E13+F13+G13+H13+I13 -> 659657 | P13: 96263.679 | Q13: 47172.56 | R13: =P13+O13+M13+N13+L13+K13+Q13 -> 143436.24 | S13: 516220.76 | T13: =J13-R13 -> 516220.76
A14: 8 | B14: EMILY EKHIDE | C14: SENIOR RESEARCH FELLOW | D14: 15(8) | E14: 722595.5 | G14: 160000 | I14: =50000 -> 50000 | J14: =E14+F14+G14+H14+I14 -> 932595.5 | L14: =50000 -> 50000 | P14: 146625.94 | Q14: 57807.64 | R14: =P14+O14+M14+N14+L14+K14+Q14 -> 254433.58 | S14: 678161.92 | T14: =J14-R14 -> 678161.92
A15: 9 | B15: DORIS DAKDA AARON | C15: RESEARCH FELLOW I | D15: 14(9) | E15: 558165.25 | G15: =140000 -> 140000 | I15: =150000+100000 -> 250000 | J15: =E15+F15+G15+H15+I15 -> 948165.25 | L15: 70000 | M15: 175000 | P15: 152140.98 | Q15: 44653.22 | R15: =P15+O15+M15+N15+L15+K15+Q15 -> 441794.2 | S15: 506371.05 | T15: =J15-R15 -> 506371.05
A16: 10 | B16: ABDULSALAM S. MUSTAPHA | C16: ASST. DIRECTOR ICT | D16: 15(7) | E16: 700713.92 | H16: 80000 | I16: 50000 | J16: =E16+F16+G16+H16+I16 -> 830713.92 | N16: 10000 | P16: 127400.77 | Q16: 56057.113 | R16: =P16+O16+M16+N16+L16+K16+Q16 -> 193457.89 | S16: 635256.03 | T16: =J16-R16 -> 637256.03
A17: 11 | B17: PERCY TERFA GBAHABO | C17: HEAD, NILDS LIAISON OFFICE | D17: 13(11) | E17: 541351.33 | G17: =120000 -> 120000 | I17: 0 | J17: =E17+F17+G17+H17+I17 -> 661351.33 | P17: 97330.966 | Q17: 43308.107 | R17: =P17+O17+M17+N17+L17+K17+Q17 -> 140639.07 | S17: 520712.26 | T17: =J17-R17 -> 520712.26
A18: 12 | B18: HASSANA AHMED IBRAHIM | C18: PA- TO DG | D18: 13 (10) | E18: 526725.08 | G18: =120000 -> 120000 | I18: =100000+100000 -> 200000 | J18: =E18+F18+G18+H18+I18 -> 846725.08 | L18: =30000-20000 -> 10000 | M18: =127777.78 -> 127777.78 | O18: 8226.1229 | P18: 131567.97 | Q18: 42138.007 | R18: =P18+O18+M18+N18+L18+K18+Q18 -> 319709.88 | S18: 527015.2 | T18: =J18-R18 -> 527015.2
A19: 13 | B19: IKIP LEBO | C19: ASST CHIEF PROC. OFFICER | D19: 13 (8) | E19: 497472.75 | H19: 70000 | J19: =E19+F19+G19+H19+I19 -> 567472.75 | L19: 50000 | O19: 7791.8313 | P19: 78484.222 | Q19: 39797.82 | R19: =P19+O19+M19+N19+L19+K19+Q19 -> 176073.87 | S19: 391398.88 | T19: =J19-R19 -> 391398.88
A20: 14 | B20: ALABI ADESINA MUHYDEEN | C20: HEAD, NILDS LIAISON OFFICE | D20: 13 (8) | E20: 497472.75 | G20: 120000 | J20: =E20+F20+G20+H20+I20 -> 617472.75 | P20: 89580.253 | Q20: 39797.82 | R20: =P20+O20+M20+N20+L20+K20+Q20 -> 129378.07 | S20: 488094.68 | T20: =J20-R20 -> 488094.68
A21: 15 | B21: BASSEY NSONGURUA UDOFIA | C21: PRINC.CONF SEC/PPS | D21: 12(11) | E21: 496497.17 | H21: =60000 -> 60000 | I21: =250000 -> 250000 | J21: =SUM(E21:I21) -> 806497.17 | L21: 20000 | M21: =68750 -> 68750 | O21: 7777.3604 | P21: 124394.67 | Q21: 39719.773 | R21: =P21+O21+M21+N21+L21+K21+Q21 -> 260641.81 | S21: 545855.36 | T21: =J21-R21 -> 545855.36
A22: 16 | B22: ADUGBA RICHARD TERSEER | C22: PRINCIPAL INFO. OFFICER | D22: 12(10) | E22: 482662.67 | H22: =60000 -> 60000 | I22: =100000+50000 -> 150000 | J22: =E22+F22+G22+H22+I22 -> 692662.67 | L22: =10000 -> 10000 | M22: 292813.77 | O22: 7571.9667 | P22: 104244.2 | Q22: 38613.013 | R22: =P22+O22+M22+N22+L22+K22+Q22 -> 453242.95 | S22: 239419.72 | T22: =J22-R22 -> 239419.72
A23: 17 | B23: LUCKY AGWOM | C23: RESEARCH ASSISTANT | D23: 12(8) | E23: 454993.58 | G23: =100000 -> 100000 | I23: =100000+100000 -> 200000 | J23: =E23+F23+G23+H23+I23 -> 754993.58 | L23: =50000+100000 -> 150000 | P23: 116636.73 | Q23: 36399.487 | R23: =P23+O23+M23+N23+L23+K23+Q23 -> 303036.22 | S23: 451957.36 | T23: =J23-R23 -> 451957.36
A24: 18 | B24: IDRIS IBRAHIM | C24: PRINCIPAL RESEARCH OFFICER | D24: 12(8) | E24: 454993.58 | G24: 110000 | I24: 0 | J24: =E24+F24+G24+H24+I24 -> 564993.58 | L24: 0 | N24: 30000 | P24: 80156.733 | Q24: 36399.487 | R24: =P24+O24+M24+N24+L24+K24+Q24 -> 146556.22 | S24: 416437.36 | T24: =J24-R24 -> 418437.36
A25: 19 | B25: FARUQ ATOFARATI | C25: PA (SPECIAL DUTIES) TO DG | D25: 10(7) | E25: 381140.67 | H25: =50000+10000 -> 60000 | I25: =100000+100000 -> 200000 | J25: =E25+F25+G25+H25+I25 -> 641140.67 | L25: 150000 | P25: 95911.354 | Q25: 30491.253 | R25: =P25+O25+M25+N25+L25+K25+Q25 -> 276402.61 | S25: 364738.06 | T25: =J25-R25 -> 364738.06
A26: 20 | B26: RASHEEDAT DAIBU | C26: SENIOR INFO. OFFICER | D26: 10(8) | E26: 381140.67 | H26: 60000 | J26: =E26+F26+G26+H26+I26 -> 441140.67 | L26: 50000 | N26: 10000 | O26: 6021.8646 | P26: 57511.354 | Q26: 30491.253 | R26: =P26+O26+M26+N26+L26+K26+Q26 -> 154024.47 | S26: 285116.19 | T26: =J26-R26 -> 287116.19
A27: 21 | B27: ELIZABETH OGECHUKWU ONYEAKU | C27: ICT OFFICER | D27: 9(10) | E27: 355320.67 | H27: =50000+10000 -> 60000 | J27: =E27+F27+G27+H27+I27 -> 415320.67 | L27: 10000 | M27: 43750 | O27: 5690.3938 | P27: 52950.509 | Q27: 28425.653 | R27: =P27+O27+M27+N27+L27+K27+Q27 -> 140816.56 | S27: 274504.11 | T27: =J27-R27 -> 274504.11
A28: 22 | B28: VICTOR ASUKWO | C28: ICT OFFICER | D28: 9(10) | E28: 355320.67 | H28: =50000+10000 -> 60000 | J28: =E28+F28+G28+H28+I28 -> 415320.67 | O28: 5690.3938 | P28: 52950.509 | Q28: 28425.653 | R28: =P28+O28+M28+N28+L28+K28+Q28 -> 87066.556 | S28: 328254.11 | T28: =J28-R28 -> 328254.11
A29: 23 | B29: NNANDI LIVINUS ATURE | C29: RESEARCH ASSISTANT | D29: 9(10) | E29: 355320.67 | G29: =100000 -> 100000 | J29: =E29+F29+G29+H29+I29 -> 455320.67 | L29: =10000 -> 10000 | M29: 127777.78 | P29: 60630.509 | Q29: 28425.653 | R29: =P29+O29+M29+N29+L29+K29+Q29 -> 226833.94 | S29: 228486.72 | T29: =J29-R29 -> 228486.72
A30: 24 | B30: ABDULRAHMAN A SULAIMAN | C30: STORE OFFICER | D30: 9(9) | E30: 347016.17 | H30: =60000 -> 60000 | J30: =E30+F30+G30+H30+I30 -> 407016.17 | L30: =20000 -> 20000 | M30: =17500 -> 17500 | P30: 51483.602 | Q30: 27761.293 | R30: =P30+O30+M30+N30+L30+K30+Q30 -> 116744.9 | S30: 290271.27 | T30: =J30-R30 -> 290271.27
A31: 25 | B31: DARE SHEU MAGBON | C31: ADMINISTRATION OFFICER | D31: 9(8) | E31: 338711.67 | H31: =60000 -> 60000 | J31: =E31+F31+G31+H31+I31 -> 398711.67 | L31: =30000+20000 -> 50000 | M31: 0 | P31: 50016.695 | Q31: 27096.933 | R31: =P31+O31+M31+N31+L31+K31+Q31 -> 127113.63 | S31: 271598.04 | T31: =J31-R31 -> 271598.04
A32: 26 | B32: ABUBAKAR SULAIMAN SODEEQ | C32: ADMINISTRATION OFFICER | D32: 9(8) | E32: 338711.67 | H32: =60000 -> 60000 | J32: =E32+F32+G32+H32+I32 -> 398711.67 | M32: 0 | P32: 50016.695 | Q32: 27096.933 | R32: =P32+O32+M32+N32+L32+K32+Q32 -> 77113.629 | S32: 321598.04 | T32: =J32-R32 -> 321598.04
A33: 27 | B33: JIMOH ADEBAYO ZAKA | C33: ASST. OFFICER/COMM | D33: 9(10) | E33: 355320.67 | H33: =60000 -> 60000 | J33: =E33+F33+G33+H33+I33 -> 415320.67 | L33: =20000 -> 20000 | M33: =161429.76+39000 -> 200429.76 | O33: 5690.3938 | P33: 52950.509 | Q33: 28425.653 | R33: =P33+O33+M33+N33+L33+K33+Q33 -> 307496.32 | S33: 156824.35 | T33: =J33-R33 -> 107824.35
A34: 28 | B34: ABDULMUSHIN TAWFIQ LADAN | C34: ICT OFFICER | D34: 9(8) | E34: 338711.67 | H34: =60000 -> 60000 | J34: =E34+F34+G34+H34+I34 -> 398711.67 | M34: 0 | P34: 49761.581 | Q34: 27096.933 | R34: =P34+O34+M34+N34+L34+K34+Q34 -> 76858.515 | S34: 321853.15 | T34: =J34-R34 -> 321853.15
A35: 29 | B35: MOHAMMED BELLO | C35: PROTOCOL ASSISTANT | D35: 9(8) | E35: 338711.67 | H35: =60000 -> 60000 | J35: =E35+F35+G35+H35+I35 -> 398711.67 | L35: =0 -> 0 | P35: 49761.581 | Q35: 27096.933 | R35: =P35+O35+M35+N35+L35+K35+Q35 -> 76858.515 | S35: 321853.15 | T35: =J35-R35 -> 321853.15
A36: 30 | B36: HOLINESS PAUL UDO | C36: ADMINISTRATION OFFICER, M&E | D36: 9(7) | E36: 330407.08 | H36: =60000 -> 60000 | J36: =E36+F36+G36+H36+I36 -> 390407.08 | L36: 50000 | P36: 48549.774 | Q36: 26432.567 | R36: =P36+O36+M36+N36+L36+K36+Q36 -> 124982.34 | S36: 265424.74 | T36: =J36-R36 -> 265424.74
A37: 31 | B37: CHARITY UDO AKAN | C37: ADMINISTRATION OFFICER, M&E | D37: 9(7) | E37: 330408.08 | H37: =60000 -> 60000 | J37: =E37+F37+G37+H37+I37 -> 390408.08 | L37: 50000 | M37: 15000 | P37: 48549.951 | Q37: 26432.647 | R37: =P37+O37+M37+N37+L37+K37+Q37 -> 139982.6 | S37: 250425.49 | T37: =J37-R37 -> 250425.49
A38: 32 | B38: SANI UMAR IBRAHIM | C38: STORE OFFICER | D38: 9(7) | E38: 330409.08 | H38: =60000 -> 60000 | J38: =E38+F38+G38+H38+I38 -> 390409.08 | P38: 48550.127 | Q38: 26432.727 | R38: =P38+O38+M38+N38+L38+K38+Q38 -> 74982.854 | S38: 315426.23 | T38: =J38-R38 -> 315426.23
A39: 33 | B39: FAHAD ABUBUKAR LONGMAN | C39: ICT OFFICER | D39: 9(7) | E39: 330409.08 | H39: =60000 -> 60000 | J39: =E39+F39+G39+H39+I39 -> 390409.08 | P39: 48550.127 | Q39: 26432.727 | R39: =P39+O39+M39+N39+L39+K39+Q39 -> 74982.854 | S39: 315426.23 | T39: =J39-R39 -> 315426.23
A40: 34 | B40: HARUNA JIBRIL AMEH | C40: ASST. ADMIN. OFFICER | D40: 8(9) | E40: 301910.75 | H40: 50000 | J40: =E40+F40+G40+H40+I40 -> 351910.75 | L40: 20000 | M40: 0 | O40: 4909.1104 | P40: 42229.992 | Q40: 24152.86 | R40: =P40+O40+M40+N40+L40+K40+Q40 -> 91291.963 | S40: 260618.79 | T40: =J40-R40 -> 260618.79
A41: 35 | B41: RAMATU IBRAHIM ABDULRAHEEM | C41: INFORMATION OFFICER | D41: 8(8) | E41: 294900.83 | H41: 50000 | J41: =E41+F41+G41+H41+I41 -> 344900.83 | L41: 50000 | M41: 45833.33 | N41: 50000 | O41: 4804.4854 | P41: 41146.539 | Q41: 23592.067 | R41: =P41+O41+M41+N41+L41+K41+Q41 -> 215376.42 | S41: 127524.41 | T41: =J41-R41 -> 129524.41
A42: 36 | B42: EDIDIONG EZEKIEL ATAT | C42: ASSIST PROCUREMENT OFFICER | D42: 8(7) | E42: 287890.92 | H42: =50000 -> 50000 | J42: =SUM(E42:I42) -> 337890.92 | L42: 10000 | O42: =4699.86 -> 4699.86 | P42: 39273.51 | Q42: 23031.273 | R42: =P42+O42+M42+N42+L42+K42+Q42 -> 77004.644 | S42: 260886.27 | T42: =J42-R42 -> 260886.27
A43: 37 | B43: ALIYU GARBA LERE | C43: ASSIST INFORMATION OFFICER | D43: 8(7) | E43: 287891.92 | H43: =50000 -> 50000 | J43: =SUM(E43:I43) -> 337891.92 | P43: 40063.241 | Q43: 23031.353 | R43: =P43+O43+M43+N43+L43+K43+Q43 -> 63094.595 | S43: 274797.32 | T43: =J43-R43 -> 274797.32
B44: TOTAL | C44: 37 | E44: =SUM(E7:E43) -> 19191617 | F44: =SUM(F7:F43) -> 0 | G44: =SUM(G7:G43) -> 1560000 | H44: =SUM(H7:H43) -> 1650000 | I44: =SUM(I7:I43) -> 2025235 | J44: =SUM(J7:J43) -> 24426852 | K44: =SUM(K7:K43) -> 0 | L44: =SUM(L7:L43) -> 1160000 | ... R44: =SUM(R7:R43) -> 7933267.8 | S44: 16679081 | T44: =SUM(T7:T43) -> 16493584
B46: INTERNAL AUDIT
A47: 1 | B47: OSANAIYE DAVID AKINYEMI | C47: DIRECTOR INTERNAL AUDIT | D47: 17(9) | E47: 1747106.4 | H47: =100000 -> 100000 | J47: =SUM(E47:I47) -> 1847106.4 | K47: ='AUGUST 2025'!F228 -> 0 | L47: =300000 -> 300000 | M47: =458333.33 -> 458333.33 | P47: 306475.54 | Q47: 139768.51 | R47: =P47+O47+M47+N47+L47+K47+Q47 -> 1204577.4 | S47: 642529.03 | T47: =J47-R47 -> 642529.03
A48: 2 | B48: JAMILA ABDUL | C48: SENIOR INTERNAL AUDITOR | D48: 10(8) | E48: 381140.67 | H48: =60000 -> 60000 | J48: =SUM(E48:I48) -> 441140.67 | L48: =20000 -> 20000 | M48: 73333.33 | N48: 20000 | O48: 6021.8646 | P48: 57511.354 | Q48: 30491.253 | R48: =P48+O48+M48+N48+L48+K48+Q48 -> 207357.8 | S48: 231782.86 | T48: =J48-R48 -> 233782.86
A49: 3 | B49: IJEOMA EWELUKWA | C49: SENIOR INTERNAL AUDITOR | D49: 10(9) | E49: 390135.83 | H49: =50000+10000 -> 60000 | J49: =SUM(E49:I49) -> 450135.83 | L49: =10000 -> 10000 | P49: 59100.26 | Q49: 31210.867 | R49: =P49+O49+M49+N49+L49+K49+Q49 -> 100311.13 | S49: 349824.71 | T49: =J49-R49 -> 349824.71
A50: 4 | B50: HASSAN ABDULHADI | C50: SENIOR INTERNAL AUDITOR | D50: 10(7) | E50: 372145.33 | H50: 60000 | J50: =SUM(E50:I50) -> 432145.33 | L50: =100000 -> 100000 | P50: 55922.418 | Q50: 29771.627 | R50: =P50+O50+M50+N50+L50+K50+Q50 -> 185694.05 | S50: 246451.29 | T50: =J50-R50 -> 246451.29
A51: 5 | B51: YUSUF YUSUF DAYYABU | C51: INERNAL AUDIT OFFICER | D51: 9(8) | E51: 338711.67 | H51: 60000 | J51: =SUM(E51:I51) -> 398711.67 | L51: 20000 | M51: 98878.69 | O51: 5443.3354 | P51: 50016.695 | Q51: 27096.933 | R51: =P51+O51+M51+N51+L51+K51+Q51 -> 201435.65 | S51: 167276.01 | T51: =J51-R51 -> 197276.01
A52: 6 | B52: UDONSI QUEENETH CHIWENDU | C52: ASSIST PROGRAMME OFFICER | D52: 8(7) | E52: 287890.92 | H52: 50000 | J52: =SUM(E52:I52) -> 337890.92 | P52: 40063.087 | Q52: 23031.273 | R52: =P52+O52+M52+N52+L52+K52+Q52 -> 63094.36 | S52: 274796.56 | T52: =J52-R52 -> 274796.56
C53: 6 | E53: =SUM(E47:E52) -> 3517130.8 | F53: =SUM(F47:F52) -> 0 | G53: =SUM(G47:G52) -> 0 | H53: =SUM(H47:H52) -> 390000 | I53: =SUM(I47:I52) -> 0 | J53: =SUM(J47:J52) -> 3907130.8 | K53: =SUM(K47:K52) -> 0 | L53: =SUM(L47:L52) -> 450000 | ... R53: =SUM(R47:R52) -> 1962470.4 | S53: 1912660.5 | T53: =SUM(T47:T52) -> 1944660.5
B55: LEG. SUPPORT SEVICES
A56: 1 | B56: BETHEL UZOMA IHUGBA | C56: DEPUTY DIRECTOR, LEGAL RESEARCH | D56: 17(7) | E56: 1647612 | G56: =200000 -> 200000 | J56: =SUM(E56:I56) -> 1847612 | L56: =80000+23000 -> 103000 | M56: =246905.96 -> 246905.96 | P56: 319502.66 | Q56: 131808.96 | R56: =P56+O56+M56+N56+L56+K56+Q56 -> 801217.58 | S56: 3075579 | T56: =J56-R56 -> 1046394.4
A57: 2 | B57: OGUCHE SAMUEL | C57: SNR RESEARCH FELLOW | D57: 15(9) | E57: 744477 | G57: =160000 -> 160000 | J57: =SUM(E57:I57) -> 904477 | L57: =30000 -> 30000 | M57: 223059.88 | P57: 140891.08 | Q57: 59558.16 | R57: =P57+O57+M57+N57+L57+K57+Q57 -> 453509.12 | S57: 450967.88 | T57: =J57-R57 -> 450967.88
A58: 3 | B58: IBRAHIM USMAN | C58: SNR RESEARCH FELLOW | D58: 15(9) | E58: 744477 | G58: =140000+20000 -> 160000 | I58: 0 | J58: =SUM(E58:I58) -> 904477 | N58: 50000 | O58: 11475.263 | P58: 138687.83 | Q58: 59558.16 | R58: =P58+O58+M58+N58+L58+K58+Q58 -> 259721.26 | S58: 642755.74 | T58: =J58-R58 -> 644755.74
A59: 4 | B59: DR MOHAMMED O. AMALI | C59: SNR RESEARCH FELLOW | D59: 15(8) | E59: 722595.5 | G59: =140000+20000 -> 160000 | J59: =SUM(E59:I59) -> 882595.5 | L59: =15000 -> 15000 | M59: 99000 | P59: 137025.94 | Q59: 57807.64 | R59: =P59+O59+M59+N59+L59+K59+Q59 -> 308833.58 | S59: 573761.92 | T59: =J59-R59 -> 573761.92
A60: 5 | B60: YAHAYA SHAMSU | C60: SNR RESEARCH FELLOW | D60: 15(7) | E60: 700713.92 | G60: =160000 -> 160000 | J60: =SUM(E60:I60) -> 860713.92 | N60: 20000 | O60: 0 | P60: 133160.77 | Q60: 56057.113 | R60: =P60+O60+M60+N60+L60+K60+Q60 -> 209217.89 | S60: 649496.03 | T60: =J60-R60 -> 651496.03
A61: 6 | B61: UMAR MUSA PADAH | C61: PRINC. RESEARCH OFFICER | D61: 12(7) | E61: 441159 | G61: =110000 -> 110000 | J61: =SUM(E61:I61) -> 551159 | N61: 20000 | P61: 77712.992 | Q61: 35292.72 | R61: =P61+O61+M61+N61+L61+K61+Q61 -> 133005.71 | S61: 416153.29 | T61: =J61-R61 -> 418153.29
A62: 7 | B62: BILKIS S. LAWAL-GAMBARI | C62: RESEARCH OFFICER | D62: 10(9) | E62: 390135.83 | G62: 100000 | J62: =SUM(E62:I62) -> 490135.83 | P62: 66780.26 | Q62: 31210.867 | R62: =P62+O62+M62+N62+L62+K62+Q62 -> 97991.127 | S62: 392144.71 | T62: =J62-R62 -> 392144.71
A63: 8 | B63: UMOH USENOBONG EMMANUEL | C63: SENIOR RESEARCH OFFICER | D63: 10(7) | E63: 372145.33 | G63: =100000 -> 100000 | J63: =SUM(E63:I63) -> 472145.33 | P63: 63602.418 | Q63: 29771.627 | R63: =P63+O63+M63+N63+L63+K63+Q63 -> 93374.045 | S63: 378771.29 | T63: =J63-R63 -> 378771.29
A64: 9 | B64: ZAINAB AKINDE | C64: RESEARCH OFFICER | D64: 9(9) | E64: 347016.17 | G64: =100000 -> 100000 | J64: =SUM(E64:I64) -> 447016.17 | P64: 59163.602 | Q64: 27761.293 | R64: =P64+O64+M64+N64+L64+K64+Q64 -> 86924.896 | S64: 360091.27 | T64: =J64-R64 -> 360091.27
A65: 10 | B65: GUNAT NANSAK MARK | C65: RESEARCH OFFICER | D65: 9(9) | E65: 347016.17 | G65: =100000 -> 100000 | J65: =SUM(E65:I65) -> 447016.17 | P65: 59163.602 | Q65: 27761.293 | R65: =P65+O65+M65+N65+L65+K65+Q65 -> 86924.896 | S65: 360091.27 | T65: =J65-R65 -> 360091.27
A66: 11 | B66: MANDU ESSIEN NDEM | C66: RESEARCH OFFICER | D66: 9(7) | E66: 330407.08 | G66: =100000 -> 100000 | J66: =E66+F66+G66+H66+I66 -> 430407.08 | P66: =56229.7738666667+13919.3 -> 70149.074 | Q66: 26432.567 | R66: =P66+O66+M66+N66+L66+K66+Q66 -> 96581.641 | S66: 333825.44 | T66: =J66-R66 -> 333825.44
B67: TOTAL | C67: 11 | E67: =SUM(E56:E66) -> 6787755 | F67: =SUM(F56:F66) -> 0 | G67: =SUM(G56:G66) -> 1450000 | H67: =SUM(H56:H66) -> 0 | I67: =SUM(I56:I66) -> 0 | J67: =SUM(J56:J66) -> 8237755 | K67: =SUM(K56:K66) -> 0 | L67: =SUM(L56:L66) -> 148000 | ... R67: =SUM(R56:R66) -> 2627301.7 | S67: 7633637.9 | T67: =SUM(T56:T66) -> 5610453.3
B69: LEGAL SERVICES
A70: 1 | B70: DR SHUAIBU DANWANKA | C70: DIRECTOR LEGAL SERVICES | D70: 17(9) | E70: 1747106.4 | G70: =200000 -> 200000 | I70: 0 | J70: =SUM(E70:I70) -> 1947106.4 | L70: 250000 | N70: 500000 | O70: 0 | P70: 325675.54 | Q70: 139768.51 | R70: =P70+O70+M70+N70+L70+K70+Q70 -> 1215444.1 | S70: 729662.36 | T70: =J70-R70 -> 731662.36
A71: 2 | B71: ABDULSALAM BAKO | C71: MANAGER, LEGAL SERVICES | D71: 15 (9) | E71: 744477 | H71: 80000 | J71: =SUM(E71:I71) -> 824477 | L71: 50000 | M71: 345000 | O71: 0 | P71: 125531.08 | Q71: 59558.16 | R71: =P71+O71+M71+N71+L71+K71+Q71 -> 580089.24 | S71: 244387.76 | T71: =J71-R71 -> 244387.76
B72: TOTAL | C72: 2 | E72: =SUM(E70:E71) -> 2491583.4 | F72: =SUM(F70:F71) -> 0 | G72: =SUM(G70:G71) -> 200000 | H72: =SUM(H70:H71) -> 80000 | I72: =SUM(I70:I71) -> 0 | J72: =SUM(J70:J71) -> 2771583.4 | K72: =SUM(K70:K71) -> 0 | L72: =SUM(L70:L71) -> 300000 | ... R72: =SUM(R70:R71) -> 1795533.3 | S72: 974050.12 | T72: =SUM(T70:T71) -> 976050.12
B74: DEMOCRACY & GOVERNANCE
A75: 1 | B75: NGARA CHRISTOPHER OCHANJA | C75: DEP DIR DEM & GOVERNANCE | D75: 16(9) | E75: 905306.75 | G75: 180000 | I75: 0 | J75: =SUM(E75:I75) -> 1085306.8 | L75: =60000 -> 60000 | M75: =163103.59 -> 163103.59 | O75: 13866.737 | P75: 170477.64 | Q75: 72424.54 | R75: =P75+O75+M75+N75+L75+K75+Q75 -> 479872.5 | S75: 605434.25 | T75: =J75-R75 -> 605434.25
A76: 2 | B76: EJALONIBU GANIYU LAYI | C76: RESEARCH FELLOW 1 | D76: 14(9) | E76: 558165.25 | G76: 140000 | J76: =SUM(E76:I76) -> 698165.25 | L76: =110000+90000 -> 200000 | N76: 80000 | P76: 104140.98 | Q76: 44653.22 | R76: =P76+O76+M76+N76+L76+K76+Q76 -> 428794.2 | S76: 267371.05 | T76: =J76-R76 -> 269371.05
A77: 3 | B77: MARTINS SOLOMON UDOM | C77: RESEARCH FELLOW 11 | D77: 13(7) | E77: 482846.58 | G77: =120000 -> 120000 | I77: 0 | J77: =SUM(E77:I77) -> 602846.58 | L77: 30000 | M77: 15000 | P77: 86996.687 | Q77: 38627.727 | R77: =P77+O77+M77+N77+L77+K77+Q77 -> 170624.41 | S77: 432222.17 | T77: =J77-R77 -> 432222.17
A78: 4 | B78: ISHAKA DELE | C78: RESEARCH FELLOW 11 | D78: 13(7) | E78: 482846.58 | G78: =120000 -> 120000 | I78: 0 | J78: =SUM(E78:I78) -> 602846.58 | L78: 100000 | P78: 86996.687 | Q78: 38627.727 | R78: =P78+O78+M78+N78+L78+K78+Q78 -> 225624.41 | S78: 377222.17 | T78: =J78-R78 -> 377222.17
A79: 5 | B79: UDEFUNA NNADOZIE PATRICK | C79: RESEARCH OFFICER | D79: 12(9) | E79: 468828.17 | G79: =110000 -> 110000 | I79: 0 | J79: =SUM(E79:I79) -> 578828.17 | L79: 10000 | M79: =163196.67 -> 163196.67 | P79: 82600.474 | Q79: 37506.253 | R79: =P79+O79+M79+N79+L79+K79+Q79 -> 293303.4 | S79: 285524.77 | T79: =J79-R79 -> 285524.77
A80: 6 | B80: SHAFIU YAHYA MIKAIL | C80: PRINCIPAL RESEARCH OFFICER | D80: 12(9) | E80: 468828.17 | G80: =110000 -> 110000 | I80: 0 | J80: =SUM(E80:I80) -> 578828.17 | N80: 50000 | P80: 82600.474 | Q80: 37506.253 | R80: =P80+O80+M80+N80+L80+K80+Q80 -> 170106.73 | S80: 356721.44 | T80: =J80-R80 -> 408721.44
A81: 7 | B81: HASSAN YERIMA | C81: PRINCIPAL RESEARCH OFFICER | D81: 12(9) | E81: 468828.17 | G81: =110000 -> 110000 | I81: 0 | J81: =SUM(E81:I81) -> 578828.17 | L81: =67000-2000 -> 65000 | N81: 40000 | P81: 82600.474 | Q81: 37506.253 | R81: =P81+O81+M81+N81+L81+K81+Q81 -> 225106.73 | S81: 351721.44 | T81: =J81-R81 -> 353721.44
A82: 8 | B82: HAUWA PATE SADIQ | C82: PRINCIPAL PROGRAMME OFFICER | D82: 12(10) | E82: 482662.67 | G82: =110000 -> 110000 | J82: =SUM(E82:I82) -> 592662.67 | L82: =80000+20000 -> 100000 | N82: 100000 | P82: 85044.2 | Q82: 38613.013 | R82: =P82+O82+M82+N82+L82+K82+Q82 -> 323657.21 | S82: 267005.45 | T82: =J82-R82 -> 269005.45
A83: 9 | B83: OBOT ETIMBUK EMMANUEL | C83: PRINCIPAL INFO. OFFICER | D83: 12(7) | E83: 441159 | G83: 110000 | J83: =E83+F83+G83+H83+I83 -> 551159 | L83: 20000 | M83: 50000 | P83: 77712.992 | Q83: 35292.72 | R83: =P83+O83+M83+N83+L83+K83+Q83 -> 183005.71 | S83: 368153.29 | T83: =J83-R83 -> 368153.29
A84: 10 | B84: KOLAPO Q. ABAYOMI | C84: RESEARCH OFFICER | D84: 10(9) | E84: 390135.83 | G84: 100000 | J84: =SUM(E84:I84) -> 490135.83 | N84: 30000 | O84: 6154.2792 | P84: 65598.639 | Q84: 31210.867 | R84: =P84+O84+M84+N84+L84+K84+Q84 -> 132963.78 | S84: 355172.05 | T84: =J84-R84 -> 357172.05
B85: TOTAL | C85: 10 | E85: =SUM(E75:E84) -> 5149607.2 | F85: =SUM(F75:F84) -> 0 | G85: =SUM(G75:G84) -> 1210000 | H85: =SUM(H75:H84) -> 0 | I85: =SUM(I75:I84) -> 0 | J85: =SUM(J75:J84) -> 6359607.2 | K85: =SUM(K75:K84) -> 0 | L85: =SUM(L75:L84) -> 585000 | ... R85: =SUM(R75:R84) -> 2633059.1 | S85: 3666548.1 | T85: =SUM(T75:T84) -> 3726548.1
B87: DEPARTMENT OF STUDIES
A88: 1 | B88: DR ASIMIYU G. ABIOLA | C88: DIRECTOR POST GRADUATE | D88: 17(9) | E88: 1747106.4 | G88: =200000 -> 200000 | I88: 0 | J88: =SUM(E88:I88) -> 1947106.4 | L88: 350000 | M88: =0 -> 0 | N88: 102000 | O88: 0 | P88: 325675.54 | Q88: 139768.51 | R88: =P88+O88+M88+N88+L88+K88+Q88 -> 917444.06 | S88: 1131662.4 | T88: =J88-R88 -> 1029662.4
A89: 2 | B89: AYOBOLU OLAJIDE OLUFUNSHO | C89: ASSISTANT DIR. EXXAMS & RECORD | D89: 15(7) | E89: 722595.5 | G89: 160000 | J89: =SUM(E89:I89) -> 882595.5 | L89: =50000 -> 50000 | M89: =144081 -> 144081 | P89: 137025.94 | Q89: 57807.64 | R89: =P89+O89+M89+N89+L89+K89+Q89 -> 388914.58 | T89: =J89-R89 -> 493680.92
A90: 3 | B90: DR. HADIZA SAIDU | C90: ASSISTANT DIRECTOR | D90: 15(7) | E90: 722595.5 | G90: 160000 | J90: =SUM(E90:I90) -> 882595.5 | P90: 137025.94 | Q90: 57807.64 | R90: =P90+O90+M90+N90+L90+K90+Q90 -> 194833.58 | S90: 687761.92 | T90: =J90-R90 -> 687761.92
A91: 4 | B91: ANTHONY EDET | C91: CHIEF PROGRAMMES OFFICER | D91: 14(10) | E91: 573911.08 | G91: =140000 -> 140000 | I91: 0 | J91: =SUM(E91:I91) -> 713911.08 | L91: 20000 | M91: 210785.51 | O91: 8926.6667 | P91: 105208.4 | Q91: 45912.887 | R91: =P91+O91+M91+N91+L91+K91+Q91 -> 390833.46 | S91: 323077.62 | T91: =J91-R91 -> 323077.62
A92: 5 | B92: CHRISTIAN MADUABUCHI ODO | C92: ASSIST. CHIEF ICT OFFICER | D92: 13(7) | E92: 482846.58 | G92: 120000 | J92: =SUM(E92:I92) -> 602846.58 | O92: 7574.6854 | P92: 86996.687 | Q92: 38627.727 | R92: =P92+O92+M92+N92+L92+K92+Q92 -> 133199.1 | S92: 776929.82 | T92: =J92-R92 -> 469647.48
A93: 6 | B93: DR. IBANGA ISSAC JONAH | C93: ASSIST. CHIEF PROGRM OFFICER | D93: 13(7) | E93: 482846.58 | G93: =120000 -> 120000 | I93: 0 | J93: =SUM(E93:I93) -> 602846.58 | L93: 100000 | M93: 50000 | N93: 100000 | P93: 86996.687 | Q93: 38627.727 | R93: =P93+O93+M93+N93+L93+K93+Q93 -> 375624.41 | S93: 225222.17 | T93: =J93-R93 -> 227222.17
A94: 7 | B94: IGWE STACY | C94: PRINC. PROGRAMME OFFICER | D94: 12(8) | E94: 454993.58 | G94: =110000 -> 110000 | J94: =SUM(E94:I94) -> 564993.58 | L94: =50000 -> 50000 | M94: =50000 -> 50000 | P94: 80156.733 | Q94: 36399.487 | R94: =P94+O94+M94+N94+L94+K94+Q94 -> 216556.22 | S94: 348437.36 | T94: =J94-R94 -> 348437.36
A95: 8 | B95: OLANIYAN TAIWO ABINBOLA | C95: PROGRAMME OFFICER | D95: 9(8) | E95: 347016.17 | G95: 100000 | J95: =SUM(E95:I95) -> 447016.17 | O95: 5566.8646 | P95: 59163.602 | Q95: 27761.293 | R95: =P95+O95+M95+N95+L95+K95+Q95 -> 92491.76 | S95: 354524.41 | T95: =J95-R95 -> 354524.41
A96: 9 | B96: AMINAT JUMOKE SULAIMON | C96: AST. PROGRAMME OFFICER | D96: 8(9) | E96: 301910.75 | G96: 100000 | H96: 0 | J96: =SUM(E96:I96) -> 401910.75 | L96: 80000 | M96: 50000 | O96: 0 | P96: 51196.182 | Q96: 24152.86 | R96: =P96+O96+M96+N96+L96+K96+Q96 -> 205349.04 | S96: 246561.71 | T96: =J96-R96 -> 196561.71
B97: TOTAL | C97: 9 | E97: =SUM(E88:E96) -> 5835822.2 | F97: =SUM(F88:F96) -> 0 | G97: =SUM(G88:G96) -> 1210000 | H97: =SUM(H88:H96) -> 0 | I97: =SUM(I88:I96) -> 0 | J97: =SUM(J88:J96) -> 7045822.2 | K97: =SUM(K88:K96) -> 0 | L97: =SUM(L88:L96) -> 650000 | ... R97: =SUM(R88:R96) -> 2915246.2 | S97: 4094177.4 | T97: =SUM(T88:T96) -> 4130576
B99: ECON. DEV. & SOC. RESEARCH
A100: 1 | B100: DR AUGUSTINE C. OSIGWE | C100: AG. DIRECTOR, ESR | D100: 17(7) | E100: 1647612 | G100: =200000 -> 200000 | J100: =SUM(E100:I100) -> 1847612 | L100: =30000 -> 30000 | M100: 98750 | O100: 25644.208 | P100: 303177.16 | Q100: 131808.96 | R100: =P100+O100+M100+N100+L100+K100+Q100 -> 589380.33 | S100: 1258231.7 | T100: =J100-R100 -> 1258231.7
A101: 2 | B101: TERFA WILLIAMS ABRAHAM | C101: DEP. DIRECTOR ECON & SOCIAL RES | D101: 16(7) | E101: 852711.08 | G101: =180000 -> 180000 | I101: =100000+100000 -> 200000 | J101: =SUM(E101:I101) -> 1232711.1 | P101: 202249.55 | Q101: 68216.887 | R101: =P101+O101+M101+N101+L101+K101+Q101 -> 270466.44 | S101: 962244.64 | T101: =J101-R101 -> 962244.64
A102: 3 | B102: OMOJU OLUWASOLA EMMANUEL | C102: SNR RESEARCH FELLOW | D102: 15(8) | E102: 722595.5 | G102: 160000 | J102: =SUM(E102:I102) -> 882595.5 | L102: =50000 -> 50000 | P102: 137025.94 | Q102: 57807.64 | R102: =P102+O102+M102+N102+L102+K102+Q102 -> 244833.58 | S102: 637761.92 | T102: =J102-R102 -> 637761.92
A103: 4 | B103: IBE EZECHI CYRIACUS | C103: RESEARCH FELLOW 1 | D103: 14(9) | E103: 558165.25 | G103: =140000 -> 140000 | I103: 0 | J103: =SUM(E103:I103) -> 698165.25 | L103: =50000 -> 50000 | M103: =77638.89 -> 77638.89 | O103: 8692.9229 | P103: 102472.11 | Q103: 44653.22 | R103: =P103+O103+M103+N103+L103+K103+Q103 -> 283457.14 | S103: 421732.16 | T103: =J103-R103 -> 414708.11
A104: 5 | B104: OSIKHEN LEO IGBANOI | C104: RESEARCH FELLOW 1 | D104: 14(9) | E104: 558166.25 | G104: =140000 -> 140000 | I104: 0 | J104: =SUM(E104:I104) -> 698166.25 | L104: 0 | M104: 0 | O104: 8692.9229 | P104: 102472.11 | Q104: 44653.3 | R104: =P104+O104+M104+N104+L104+K104+Q104 -> 155818.33 | S104: 542347.92 | T104: =J104-R104 -> 542347.92
A105: 6 | B105: OKUNGBOWA OSARETIN GODSPOWER | C105: RESEARCH FELLOW 1 | D105: 14(8) | E105: 542419.5 | G105: =140000 -> 140000 | I105: 0 | J105: =SUM(E105:I105) -> 682419.5 | L105: =100000-100000 -> 0 | P105: 101359.65 | Q105: 43393.56 | R105: =P105+O105+M105+N105+L105+K105+Q105 -> 144753.21 | S105: 537666.29 | T105: =J105-R105 -> 537666.29
A106: 7 | B106: YUSUF IBRAHIM | C106: PRINCIPAL RESEARCH OFFICER | D106: 12(9) | E106: 468828.17 | G106: =110000 -> 110000 | I106: 0 | J106: =SUM(E106:I106) -> 578828.17 | L106: =20000 -> 20000 | M106: 43750 | N106: 20000 | P106: 82600.474 | Q106: 37506.253 | R106: =P106+O106+M106+N106+L106+K106+Q106 -> 203856.73 | S106: 372971.44 | T106: =J106-R106 -> 374971.44
...

Sheet MEMO
A2: NATIONAL INSTITUTE FOR LEGISLATIVE AND DEMOCRATIC STUDIES
A3: INTERNAL MEMO
A4: FROM : DEPUTY DIRECTOR, FINANCE AND ACCOUNTS
A5: THRU: DIRECTOR, FINANCE AND ACCOUNTS
A6: TO: DG
A7: 29TH JANUARY , 2021
A9: SUBJECT: PAYROLL FOR THE MONTH OF JANUARY, 2021
A10: Find below the details of NILDS Staff Payroll for the month of January, 2021
A13: TO: | C13: DIRECTOR, GENERAL
A14: THRU: | C14: DIRECTOR, FINANCE AND ACCOUNT
A15: FROM: | C15: DEPUTY DIRECTOR, FINANCE AND ACCOUNTS
A16: DATE: | C16: 25TH AUGUST 2025
A18: SUBJECT: PAYROLL FOR THE MONTH OF AUGUST 2025
A19: Find below the details of NILDS Staff Payroll for the Month of August 2025: | G19: NGN | H19: NGN
A20: GROSS SALARY FOR AUGUST 2025 | H20: ='AUGUST 2025'!J226 -> 1.0713229e+08
A22: DEDUCTIONS
A23: COOP SOCIETY 1 DEDUCTIONS ( CONTR.& SPEC. SAVINGS) | G23: ='AUGUST 2025'!L226 -> 6778500
A24: COOP 1 LOAN RECOVERY | G24: ='AUGUST 2025'!M226 -> 9340785.7
A25: COOP SOCIETY 2 DEDUCTIONS ( CONTR.& SPEC. SAVINGS) | G25: ='AUGUST 2025'!N226 -> 2294000
A26: NHF DEDUCTIONS | G26: ='AUGUST 2025'!O226 -> 534448.5
A27: PAYE DEDUCTIONS | G27: ='AUGUST 2025'!P226 -> 15457719
A28: PENSION DEDUCTIONS | G28: ='AUGUST 2025'!Q226 -> 6913755.7
A29: TOTAL DEDUCTIONS FOR AUGUST 2025 | H29: =G23+G24+G25+G27+G26+G28 -> 41319208
A30: NET PAY AS PER AUGUST 2025 PAYROLL | H30: =H20-H29 -> 65813085
A31: NET PAY AS PER JULY, 2025 PAYROLL | H31: ='AUGUST 2025'!S226 -> 68876986
A32: NET INCREASE/ (DECREASE) IN PAY FOR AUGUST, 2025 | H32: =H30-H31 -> -3063900.9
A33: ANALYSED AS FOLLOWS:
A34: Effect of Cooperative 1 Adjustments for August, 2025 | H34: -46750
A35: Effect of Cooperative 2 Adjustments for August, 2025 | H35: 280000
A36: Effect of removal of Arrears of Bethel Ihugba as Ag. Director | H36: =2029184.6 -> 2029184.6
A37: Effect of removal of Arrears for Mohammed Umar Ali & 2 others | H37: =857219.6+307282.34 -> 1164501.9
A38: Effect of removal of Arrears of Step Regularisation of Andrawus Musa & 1 other | H38: =84994.6 -> 84994.6
A39: Effect of removal of Arrears on Regularisation of PAYE Tax & REs. Allow of Titilayo Marvelous & 1 other | H39: =76850.56+8080 -> 84930.56
A40: Effect of Promotion & Arrears ifo Abubakar Sanni Aliyu | H40: =-46303.96 -> -46303.96
A41: Effect of NHF Deduction from Ibeh Cyriacus | H41: 7024.05
A42: Effect of enrolment of Ayobolu Olufunsho as Permanent Staff | H42: -493680.92
H43: =SUM(H34:H42) -> 3063900.9
E46: JULY, 2025 | G46: AUGUST, 2025
E47: No. of Staff | F47: N | G47: No. of Staff | H47: N
A48: 1 | B48: Director General's Office | E48: 32 | F48: ='AUGUST 2025'!S44 -> 16679081 | G48: ='AUGUST 2025'!C44 -> 37 | H48: ='AUGUST 2025'!T44 -> 16493584
A49: 2 | B49: Internal Audit | E49: 3 | F49: ='AUGUST 2025'!S53 -> 1912660.5 | G49: ='AUGUST 2025'!C53 -> 6 | H49: ='AUGUST 2025'!T53 -> 1944660.5
A50: 3 | B50: Legis. Support Services | E50: 11 | F50: ='AUGUST 2025'!S67 -> 7633637.9 | G50: ='AUGUST 2025'!C67 -> 11 | H50: ='AUGUST 2025'!T67 -> 5610453.3
A51: 4 | B51: Legal Services | E51: 2 | F51: ='AUGUST 2025'!S72 -> 974050.12 | G51: ='AUGUST 2025'!C72 -> 2 | H51: ='AUGUST 2025'!T72 -> 976050.12
A52: 5 | B52: Democracy and Governance | E52: 12 | F52: ='AUGUST 2025'!S85 -> 3666548.1 | G52: ='AUGUST 2025'!C85 -> 10 | H52: ='AUGUST 2025'!T85 -> 3726548.1
A53: 6 | B53: Studies | E53: 6 | F53: ='AUGUST 2025'!S97 -> 4094177.4 | G53: ='AUGUST 2025'!C97 -> 9 | H53: ='AUGUST 2025'!T97 -> 4130576
A54: 7 | B54: Economic Dev. & Social Research | E54: 11 | F54: ='AUGUST 2025'!S111 -> 6189811.8 | G54: ='AUGUST 2025'!C111 -> 11 | H54: ='AUGUST 2025'!T111 -> 6186787.7
A55: 8 | B55: Training & Int'l Cooperation | E55: 4 | F55: ='AUGUST 2025'!S120 -> 2406629.4 | G55: ='AUGUST 2025'!C120 -> 6 | H55: ='AUGUST 2025'!T120 -> 2367629.4
A56: 9 | B56: Library & Documentation | E56: 7 | F56: ='AUGUST 2025'!S130 -> 4129195.6 | G56: ='AUGUST 2025'!C130 -> 7 | H56: ='AUGUST 2025'!T130 -> 4090569
A57: 10 | B57: Leg. Center for Security Analysis | E57: 2 | F57: ='AUGUST 2025'!S138 -> 1454720.9 | G57: ='AUGUST 2025'!C138 -> 6 | H57: ='AUGUST 2025'!T138 -> 1442720.9
A58: 11 | B58: Democracy Radio 104.9 | E58: 3 | F58: ='AUGUST 2025'!S144 -> 1430208.8 | G58: 3 | H58: ='AUGUST 2025'!T144 -> 865017.86
A59: 12 | B59: Finance and Accounts | E59: 10 | F59: ='AUGUST 2025'!S158 -> 4059406.6 | G59: ='AUGUST 2025'!C158 -> 11 | H59: ='AUGUST 2025'!T158 -> 3936909.3
A60: 13 | B60: Admin & Human Resource | E60: 61 | F60: ='AUGUST 2025'!S225 -> 14246857 | G60: ='AUGUST 2025'!C225 -> 64 | H60: ='AUGUST 2025'!T225 -> 14041579
E61: =SUM(E48:E60) -> 164 | F61: =SUM(F48:F60) -> 68876986 | G61: 155 | H61: =SUM(H48:H60) -> 65813085
A63: The Director General is requested to consider and approve the payment of N65,813,084.67 to Guaranty Trust Bank, being the August 2025 Net Salary, N16,119,285.72 and N2,294,000.00 being NILDS Coop Society 1 and Coop Society 2 deductions for August 2025. N15,457,718.52 PAYE Tax Deductions from Staff Salary for the month of August 2025 and N534,448.50 being NHF deductions from staff for August 2025
A67: RAHILA NURUDEEN HABU
C171: =10000 -> 10000

Sheet Changes in Aug.
A1: STAFF NAME | B1: DESIGNATION | C1: GRADE LEVEL | D1: BASIC SALARY | E1: ALLCE/ AREARS | F1: ALLOWANCE | G1: ALLOWANCE | H1: DUTY ALLCE | I1: GROSS SALARY | J1: NHF DED. | K1: PAYE | L1: EMPLOYEE PENSIONS | N1: NET SALARY | O1: ARREARS OF JUNE & JULY
D2: N | E2: N | F2: N | G2: N | H2: N | I2: N | J2: N | K2: N | L2: N
A3: ALIYU SANNI ABUBAKAR | B3: RESEARCH FELLOW 11 DATA & DOCU | C3: 13(11) | D3: 541351.33 | F3: =120000 -> 120000 | H3: 59548.647 | I3: =SUM(D3:H3) -> 720899.98 | J3: 8443.2708 | K3: 107143.2 | L3: 43308.107 | M3: =SUM(J3:L3) -> 158894.58 | N3: =I3-M3 -> 562005.4
A4: ALIYU SANNI ABUBAKAR | B4: RESEARCH FELLOW 1 DATA & DOCU | C4: 14(7) | D4: 542419.5 | F4: =140000 -> 140000 | H4: 59666.145 | I4: =SUM(D4:H4) -> 742085.65 | J4: =338365.25*0.025 -> 8459.1313 | K4: 112831.95 | L4: =D4*0.08 -> 43393.56 | M4: =SUM(J4:L4) -> 164684.65 | N4: =I4-M4 -> 577401
A5: Difference | D5: =D4-D3 -> 1068.1667 | E5: =E4-E3 -> 0 | F5: =F4-F3 -> 20000 | G5: =G4-G3 -> 0 | H5: =H4-H3 -> 117.49833 | I5: =I4-I3 -> 21185.665 | J5: =J4-J3 -> 15.860417 | K5: =K4-K3 -> 5688.7557 | L5: =L4-L3 -> 85.453333 | M5: =SUM(J5:L5) -> 5790.0694 | N5: =I5-M5 -> 15395.596 | O5: =I5*2 -> 42371.33
I6: =I5*2 -> 42371.33 | K6: =K5*2 -> 11377.511

Sheet Shift duty
B1: STAFF NAME | C1: DESIGNATION | D1: GRADE LEVEL | E1: CONS. SALARY | F1: NEW SHIFT DUTY 11% | G1: OLD SHIFT DUTY ALLCE | H1: INCREASE
E2: N | F2: N | G2: N | H2: N
A4: 1 | B4: ALIYU SANNI ABUBAKAR | C4: RESEARCH FELLOW 11 DATA & DOCU | D4: 13(11) | E4: 541351.33 | F4: =E4*0.11 -> 59548.647 | G4: 41432.939 | H4: =F4-G4 -> 18115.708
A5: 2 | B5: CHINAKO N. ASOGWA | C5: RESEARCH FELLOW 11 DATA & DOCU | D5: 14(7) | E5: 542419.5 | F5: =E5*0.11 -> 59666.145 | G5: 42433.939 | H5: =F5-G5 -> 17232.206
A6: 3 | B6: AMOS ABA | C6: LIBRARY ASSISTANT | D6: 8(13) | E6: 329950.42 | F6: =E6*0.11 -> 36294.546 | G6: 25333.447 | H6: =F6-G6 -> 10961.098
A7: 4 | B7: TITILAYO DANIEL MARVELLOUS | C7: LIBRARY ASSISTANT | D7: 9(7) | E7: 330407.08 | F7: =E7*0.11 -> 36344.779 | G7: 26334.447 | H7: =F7-G7 -> 10010.332
A8: 5 | B8: ENENCHE JEREMIAH AGADA | C8: LIBRARY ASSISTANT | D8: 8(10) | E8: 308920.67 | F8: =E8*0.11 -> 33981.273 | G8: 24566.195 | H8: =F8-G8 -> 9415.0779
B9: TOTAL | H9: =SUM(H4:H8) -> 65734.423

Sheet Changes in July
B1: STAFF NAME | C1: DESIGNATION | D1: GRADE LEVEL | E1: BASIC SALARY | F1: ALLCE/ AREARS | G1: ALLOWANCE | H1: ALLOWANCE | I1: DUTY ALLCE | J1: GROSS SALARY | K1: AUCTION | L1: COOP CONTR/SPEC SAVINGS | M1: COOP. LOAN RECOVERY | N1: NHF DED. | O1: PAYE | P1: EMPLOYEE PENSIONS | Q1: TOTAL DEDUCTION | R1: JULY, 2025
E2: N | F2: N | G2: N | H2: N | I2: N | J2: N | K2: N | L2: N | M2: N | N2: N | O2: N | P2: N | Q2: N | R2: N
A3: 1 | B3: BETHEL UZOMA IHUGBA | C3: Acting Director | D3: 17(7) | E3: 1647612 | G3: =200000 -> 200000 | J3: =SUM(E3:I3) -> 1847612 | O3: 303177.16 | P3: 131808.96 | Q3: =O3+N3+M3+L3+K3+P3 -> 434986.12 | R3: =J3-Q3 -> 1412625.9
A4: 1 | B4: BETHEL UZOMA IHUGBA | C4: DEPUTY DIRECTOR, LEGAL RESEARCH | D4: 16(9) | E4: 905306.75 | G4: =180000 -> 180000 | I4: 100000 | J4: =SUM(E4:I4) -> 1185306.8 | O4: 192340.05 | P4: 72424.54 | Q4: =O4+N4+M4+L4+K4+P4 -> 264764.59 | R4: =J4-Q4 -> 920542.16
B5: Diference in July | J5: =J3-J4 -> 662305.25 | O5: =O3-O4 -> 110837.11 | P5: =P3-P4 -> 59384.42 | Q5: =Q3-Q4 -> 170221.53 | R5: =R3-R4 -> 492083.72
B6: Arrears for 3.65 Months | J6: =J5*3.65 -> 2417414.2 | O6: =O5*3.65 -> 404555.46 | Q6: =O6 -> 404555.46 | R6: =J6-Q6 -> 2012858.7
R7: =SUM(R5:R6) -> 2504942.4
A9: Old | B9: Mohammed Umar Ali | C9: PRINCIPAL ADMIN OFFICER | D9: 12(7) | E9: =353512.5 -> 353512.5 | H9: 60000 | J9: =E9+F9+G9+H9+I9 -> 413512.5 | O9: 52068.58 | P9: 28281 | Q9: =O9+N9+M9+L9+K9+P9 -> 80349.58 | R9: =J9-Q9 -> 333162.92
A10: New | B10: Mohammed Umar Ali | C10: PRINCIPAL ADMIN OFFICER | D10: 12(7) | E10: 441159 | H10: =60000 -> 60000 | J10: =SUM(E10:I10) -> 501159 | O10: 68112.992 | P10: 35292.72 | Q10: =O10+N10+M10+L10+K10+P10 -> 103405.71 | R10: =J10-Q10 -> 397753.29
B11: Difference | E11: =E10-E9 -> 87646.5 | J11: =J10-J9 -> 87646.5 | O11: =O10-O9 -> 16044.412 | Q11: =Q10-Q9 -> 23056.132 | R11: =R10-R9 -> 64590.368
B12: Arrears for 4 Months | E12: =J12 -> 350586 | J12: =J11*4 -> 350586 | O12: =O11*4 -> 64177.65 | Q12: =O12 -> 64177.65 | R12: =J12-Q12 -> 286408.35
R13: =R10+R12 -> 684161.64
A15: New | B15: OLUFEMI E. OYEGOKE | C15: MARKETER | D15: 9(7) | E15: 330407.08 | H15: =60000 -> 60000 | J15: =E15+F15+G15+H15+I15 -> 390407.08 | O15: 48549.774 | P15: 26432.567 | Q15: =O15+N15+M15+L15+K15+P15 -> 74982.341 | R15: =J15-Q15 -> 315424.74
A16: Old | B16: OLUFEMI E. OYEGOKE | C16: MARKETER | D16: 9(7) | E16: =255849 -> 255849 | H16: 60000 | J16: =E16+F16+G16+H16+I16 -> 315849 | O16: 36790.688 | Q16: =O16+N16+M16+L16+K16+P16 -> 36790.688 | R16: =J16-Q16 -> 279058.31
E17: =E15-E16 -> 74558.083 | J17: =J15-J16 -> 74558.083 | O17: =O15-O16 -> 11759.086 | Q17: =Q15-Q16 -> 38191.652 | R17: =R15-R16 -> 36366.431
B18: Arrears for 9 Months | E18: =E17*9 -> 671022.75 | J18: =J17*9 -> 671022.75 | O18: =O17*9 -> 105831.77 | P18: =P17*9 -> 0 | Q18: =O18 -> 105831.77 | R18: =R17*9 -> 327297.88
R19: =R15+R18 -> 642722.62

Sheet JULY 2025 (2)
A1: NATIONAL INSTITUTE FOR LEGISLATIVE AND DEMOCRATIC STUDIES
A2: STAFF PAYROLL FOR THE MONTH OF JULY, 2025
E3: ='[1]FEB 08'!E11/'[1]FEB 08'!M11 -> #REF!
B4: STAFF NAME | C4: DESIGNATION | D4: GRADE LEVEL | E4: BASIC SALARY
E5: N
A6: S/N | B6: DG'S OFFICE
A7: 1 | B7: PROF. ABUBAKAR O. SULAIMAN | C7: DIRECTOR GENERAL | D7: CONSOL | E7: 1971137.1
A8: 2 | B8: RAHEEM USMAN AYIGORO | C8: SA-INFRASTRUCTURE | D8: 16 (9) | E8: 905306.75
A9: 3 | B9: MARIAM MOHAMMED BELLO | C9: SA- SPECIAL DUTIES | D9: 16 (9) | E9: 905306.75
A10: 4 | B10: DR IKEME ARTHUR J.O | C10: DEPUTY DIRECTOR, M&E | D10: 16 (9) | E10: 905306.75
A11: 5 | B11: ANDRAWUS MUSA | C11: DEP. DIRECTOR, STORES & PROCUREMENT | D11: 16(8) | E11: 879008.92
A12: 6 | B12: DR FRANCIS NDUM OJIE | C12: AD, TRAINING & IC./SA TO DG | D12: 15(8) | E12: 722595.5
A13: 7 | B13: ALI ABDULLAHI | C13: CHIEF ICT OFFICER | D13: 14(11) | E13: 589657
A14: 8 | B14: EMILY EKHIDE | C14: SENIOR RESEARCH FELLOW | D14: 15(8) | E14: 722595.5
A15: 9 | B15: DORIS DAKDA AARON | C15: RESEARCH FELLOW I | D15: 14(9) | E15: 558165.25
A16: 10 | B16: ABDULSALAM S. MUSTAPHA | C16: ASST. DIRECTOR ICT | D16: 15(7) | E16: 700713.92
A17: 11 | B17: PERCY TERFA GBAHABO | C17: HEAD, NILDS LIAISON OFFICE | D17: 13(11) | E17: 541351.33
A18: 12 | B18: HASSANA AHMED IBRAHIM | C18: PA- TO DG | D18: 13(10) | E18: 526725.08
... A43: 37 | B43: ALIYU GARBA LERE | C43: ASSIST INFORMATION OFFICER | D43: 8(7) | E43: 287891.92
B44: TOTAL | C44: 37 | E44: =SUM(E7:E43) -> 19191617
B46: INTERNAL AUDIT
A47: 1 | B47: OSANAIYE DAVID AKINYEMI | C47: DIRECTOR INTERNAL AUDIT | D47: 17(9) | E47: 1747106.4
A48: 2 | B48: JAMILA ABDUL | C48: SENIOR INTERNAL AUDITOR | D48: 10(8) | E48: 381140.67
A49: 3 | B49: IJEOMA EWELUKWA | C49: SENIOR INTERNAL AUDITOR | D49: 10(9) | E49: 390135.83
A50: 4 | B50: HASSAN ABDULHADI | C50: SENIOR INTERNAL AUDITOR | D50: 10(7) | E50: 372145.33
A51: 5 | B51: YUSUF YUSUF DAYYABU | C51: INERNAL AUDIT OFFICER | D51: 9(8) | E51: 338711.67
A52: 6 | B52: UDONSI QUEENETH CHIWENDU | C52: ASSIST PROGRAMME OFFICER | D52: 8(7) | E52: 287890.92
C53: 6 | E53: =SUM(E47:E52) -> 3517130.8
B55: LEG. SUPPORT SEVICES
A56: 1 | B56: BETHEL UZOMA IHUGBA | C56: DEPUTY DIRECTOR, LEGAL RESEARCH | D56: 17(7) | E56: 1647612
A57: 2 | B57: OGUCHE SAMUEL | C57: SNR RESEARCH FELLOW | D57: 15(9) | E57: 744477
A58: 3 | B58: IBRAHIM USMAN | C58: SNR RESEARCH FELLOW | D58: 15(9) | E58: 744477
A59: 4 | B59: DR MOHAMMED O. AMALI | C59: SNR RESEARCH FELLOW | D59: 15(8) | E59: 722595.5
A60: 5 | B60: YAHAYA SHAMSU | C60: SNR RESEARCH FELLOW | D60: 15(7) | E60: 700713.92
A61: 6 | B61: UMAR MUSA PADAH | C61: PRINC. RESEARCH OFFICER | D61: 12(7) | E61: 441159
A62: 7 | B62: BILKIS S. LAWAL-GAMBARI | C62: RESEARCH OFFICER | D62: 10(9) | E62: 390135.83
A63: 8 | B63: UMOH USENOBONG EMMANUEL | C63: SENIOR RESEARCH OFFICER | D63: 10(7) | E63: 372145.33
A64: 9 | B64: ZAINAB AKINDE | C64: RESEARCH OFFICER | D64: 9(9) | E64: 347016.17
A65: 10 | B65: GUNAT NANSAK MARK | C65: RESEARCH OFFICER | D65: 9(9) | E65: 347016.17
A66: 11 | B66: MANDU ESSIEN NDEM | C66: RESEARCH OFFICER | D66: 9(7) | E66: 330407.08
B67: TOTAL | C67: 11 | E67: =SUM(E56:E66) -> 6787755
B69: LEGAL SERVICES
A70: 1 | B70: DR SHUAIBU DANWANKA | C70: DIRECTOR LEGAL SERVICES | D70: 17(9) | E70: 1747106.4
A71: 2 | B71: ABDULSALAM BAKO | C71: MANAGER, LEGAL SERVICES | D71: 15 (9) | E71: 744477
B72: TOTAL | C72: 2 | E72: =SUM(E70:E71) -> 2491583.4
B74: DEMOCRACY & GOVERNANCE
A75: 1 | B75: NGARA CHRISTOPHER OCHANJA | C75: DEP DIR DEM & GOVERNANCE | D75: 16(9) | E75: 905306.75
A76: 2 | B76: EJALONIBU GANIYU LAYI | C76: RESEARCH FELLOW 1 | D76: 14(9) | E76: 558165.25
A77: 3 | B77: MARTINS SOLOMON UDOM | C77: RESEARCH FELLOW 11 | D77: 13(7) | E77: 482846.58
A78: 4 | B78: ISHAKA DELE | C78: RESEARCH FELLOW 11 | D78: 13(7) | E78: 482846.58
A79: 5 | B79: UDEFUNA NNADOZIE PATRICK | C79: RESEARCH OFFICER | D79: 12(9) | E79: 468828.17
A80: 6 | B80: SHAFIU YAHYA MIKAIL | C80: PRINCIPAL RESEARCH OFFICER | D80: 12(9) | E80: 468828.17
A81: 7 | B81: HASSAN YERIMA | C81: PRINCIPAL RESEARCH OFFICER | D81: 12(9) | E81: 468828.17
A82: 8 | B82: HAUWA PATE SADIQ | C82: PRINCIPAL PROGRAMME OFFICER | D82: 12(10) | E82: 482662.67
A83: 9 | B83: OBOT ETIMBUK EMMANUEL | C83: PRINCIPAL INFO. OFFICER | D83: 12(7) | E83: 441159
A84: 10 | B84: KOLAPO Q. ABAYOMI | C84: RESEARCH OFFICER | D84: 10(9) | E84: 390135.83
B85: TOTAL | C85: 10 | E85: =SUM(E75:E84) -> 5149607.2
B87: DEPARTMENT OF STUDIES
A88: 1 | B88: DR ASIMIYU G. ABIOLA | C88: DIRECTOR POST GRADUATE | D88: 17(9) | E88: 1747106.4
A89: 2 | B89: DR. HADIZA SAIDU | C89: ASSISTANT DIRECTOR | D89: 15(7) | E89: 722595.5
A90: 3 | B90: ANTHONY EDET | C90: CHIEF PROGRAMMES OFFICER | D90: 14(10) | E90: 573911.08
A91: 3 | B91: CHRISTIAN MADUABUCHI ODO | C91: ASSIST. CHIEF ICT OFFICER | D91: 13(7) | E91: 482846.58
A92: 4 | B92: DR. IBANGA ISSAC JONAH | C92: ASSIST. CHIEF PROGRM OFFICER | D92: 13(7) | E92: 482846.58
A93: 5 | B93: IGWE STACY | C93: PRINC. PROGRAMME OFFICER | D93: 12(8) | E93: 454993.58
A94: 6 | B94: OLANIYAN TAIWO ABINBOLA | C94: PROGRAMME OFFICER | D94: 9(8) | E94: 347016.17
A95: 7 | B95: AMINAT JUMOKE SULAIMON | C95: AST. PROGRAMME OFFICER | D95: 8(9) | E95: 301910.75
B96: TOTAL | C96: 7 | E96: =SUM(E88:E95) -> 5113226.7
B98: ECON. DEV. & SOC. RESEARCH
A99: 1 | B99: DR AUGUSTINE C. OSIGWE | C99: AG. DIRECTOR, ESR | D99: 17(7) | E99: 1647612
A100: 2 | B100: TERFA WILLIAMS ABRAHAM | C100: DEP. DIRECTOR ECON & SOCIAL RES | D100: 16(7) | E100: 852711.08
A101: 3 | B101: OMOJU OLUWASOLA EMMANUEL | C101: SNR RESEARCH FELLOW | D101: 15(8) | E101: 722595.5
A102: 4 | B102: IBE EZECHI CYRIACUS | C102: RESEARCH FELLOW 1 | D102: 14(9) | E102: 558165.25
A103: 5 | B103: OSIKHEN LEO IGBANOI | C103: RESEARCH FELLOW 1 | D103: 14(9) | E103: 558166.25
A104: 6 | B104: OKUNGBOWA OSARETIN GODSPOWER | C104: RESEARCH FELLOW 1 | D104: 14(8) | E104: 542419.5
A105: 7 | B105: YUSUF IBRAHIM | C105: PRINCIPAL RESEARCH OFFICER | D105: 12(9) | E105: 468828.17
A106: 8 | B106: MUSTAPHA RAFIU AYOBANJI | C106: RESEARCH FELLOW 11 | D106: 13(8) | E106: 497472.75
A107: 9 | B107: UDOKANG NSISONG BONIFACE | C107: PRINC. RESEARCH OFFICER | D107: 12(7) | E107: 441159
A108: 10 | B108: MARYAM MUSA SADA | C108: ASSIT. RESEARCH OFFICER | D108: 10(9) | E108: 390135.83
A109: 11 | B109: CHARITY EZENWAJIOBI | C109: REASEARCH. ASST. | D109: 8(10) | E109: 308920.67
B110: TOTAL | C110: 11 | E110: =SUM(E99:E109) -> 6988186
B112: TRAINING & INT''L COOP
A113: 1 | B113: AKINSANMI ADEJOKE OLUKEMI | C113: Ag. DIR. TRAINING & IC | D113: 17(8) | E113: 1697359.3
A114: 2 | B114: MOHAMMED R. ADAMU | C114: CHIEF TRAINING OFFICER | D114: 14(10) | E114: 573911.08
A115: 3 | B115: EROMOSELE OMONIGBO | C115: ASSIST. CHIEF PERSONNEL OFFICER | D115: 13(8) | E115: 497472.75
A116: 4 | B116: DR. SAMUEL AKPAN MBADAH | C116: ASSIST. CHIEF TRAINING OFFICER | D116: 13(7) | E116: 482846.58
A117: 5 | B117: OKECHUKWU UCHENNA HULDA | C117: PRINCIPALTRAINING OFFICER | D117: 12(10) | E117: 482662.67
A118: 6 | B118: TASSNEEM IBRAHIM | C118: SENIOR PROGRAMME OFFICER | D118: 10(9) | E118: 390135.83
B119: TOTAL | C119: 6 | E119: =SUM(E113:E118) -> 4124388.2
B121: LIBRARY & DOCUMENTATION
A122: 1 | B122: DR MAIMUNA IZAH | C122: INSITUTE LIBRARIAN | D122: 17(9) | E122: 1747106.4
A123: 2 | B123: CATHERINE E. IKOKOH | C123: SNR RESEARCH FELLOW DOCU | D123: 16(9) | E123: 905306.75
A124: 3 | B124: ALIYU SANNI ABUBAKAR | C124: RESEARCH FELLOW 11 DATA & DOCU | D124: 13(11) | E124: 541351.33
A125: 4 | B125: CHINAKO N. ASOGWA | C125: RESEARCH FELLOW 11 DATA & DOCU | D125: 14(7) | E125: 542419.5
A126: 5 | B126: AMOS ABA | C126: LIBRARY ASSISTANT | D126: 8(13) | E126: 329950.42
A127: 6 | B127: TITILAYO DANIEL MARVELLOUS | C127: LIBRARY ASSISTANT | D127: 9(7) | E127: 330407.08
A128: 7 | B128: ENENCHE JEREMIAH AGADA | C128: LIBRARY ASSISTANT | D128: 8(10) | E128: 308920.67
B129: TOTAL | C129: 7 | E129: =SUM(E122:E128) -> 4705462.2
B131: LEG, CTRE FOR SEC. ANALYSIS
A132: 1 | B132: EGUATU U. ONYEJELEM | C132: PRINCIPAL M&E OFFICER | D132: 12(10) | E132: 482662.67
A133: 2 | B133: MUHAMMED AGYE OSOLAFIA | C133: PRINCIPAL RESEARCH OFFICER | D133: 12(9) | E133: 468828.17
...

Sheet Sheet13

Sheet Basic & Pensions
A1: NATIONAL INSTITUTE FOR LEGISLATIVE AND DEMOCRATIC STUDIES
A2: STAFF PAYROLL FOR THE MONTH OF JUNE, 2025
E3: ='[1]FEB 08'!E11/'[1]FEB 08'!M11 -> #REF!
B4: STAFF NAME | C4: DESIGNATION | D4: GRADE LEVEL | E4: OLD CUM BASIC SALARY | F4: NEW BASIC SALARY | G4: PECULIAR ALLOW | H4: NEW CUM BASIC SALARY | I4: INCREASE IN CUM BASIC SALARY | J4: OLD EMPLOYEE PENSION 8% | K4: NEW EMPLOYEE PENSION 8% | L4: INCREASE IN DEDUCTION | M4: OLD NHF | N4: NEW NHF | O4: INCREASE IN NHF | P4: ANNUAL NEW EMPLOYEE PENSIONS | Q4: ANNUAL NEW NHF
E5: N | F5: N | G5: N | H5: N | I5: N | J5: N | K5: N | L5: N | M5: N | N5: N | O5: N | P5: N | Q5: N
E6: A | F6: B | G6: C | H6: D | I6: E | J6: F | K6: G | L6: H | M6: I | N6: J | O6: K | P6: L | Q6: M
A7: S/N | B7: DG'S OFFICE | H7: (B+C) | I7: (D-A) | J7: (8% of A) | K7: (8% of D) | L7: (G-F) | N7: (2.5% of B) | O7: (J-I) | P7: (J-I) | Q7: (J-I)
A8: 1 | B8: PROF. ABUBAKAR O. SULAIMAN | C8: DIRECTOR GENERAL | D8: CONSOL | E8: 1659751.2 | F8: 1086777.1 | G8: 884360 | H8: =F8+G8 -> 1971137.1 | I8: =H8-E8 -> 311385.92 | L8: =K8-J8 -> 0 | O8: =N8-M8 -> 0 | P8: =K8*12 -> 0 | Q8: =N8*12 -> 0
A9: 2 | B9: RAHEEM USMAN AYIGORO | C9: SA-INFRASTRUCTURE | D9: 16 (9) | E9: 762373.17 | F9: 554669.5 | G9: 350637.25 | H9: =F9+G9 -> 905306.75 | I9: =H9-E9 -> 142933.58 | J9: 60989.853 | K9: =H9*0.08 -> 72424.54 | L9: =K9-J9 -> 11434.687 | O9: =N9-M9 -> 0 | P9: =K9*12 -> 869094.48 | Q9: =N9*12 -> 0
A10: 3 | B10: MARIAM MOHAMMED BELLO | C10: SA- SPECIAL DUTIES | D10: 16 (9) | E10: 762373.17 | F10: 554669.5 | G10: 350637.25 | H10: =F10+G10 -> 905306.75 | I10: =H10-E10 -> 142933.58 | L10: =K10-J10 -> 0 | O10: =N10-M10 -> 0 | P10: =K10*12 -> 0 | Q10: =N10*12 -> 0
A11: 4 | B11: DR IKEME ARTHUR J.O | C11: DEPUTY DIRECTOR, M&E | D11: 16 (9) | E11: 762373.17 | F11: 554669.5 | G11: 350637.25 | H11: =F11+G11 -> 905306.75 | I11: =H11-E11 -> 142933.58 | J11: 60989.853 | K11: =H11*0.08 -> 72424.54 | L11: =K11-J11 -> 11434.687 | M11: 10293.398 | N11: =0.025*F11 -> 13866.737 | O11: =N11-M11 -> 3573.3396 | P11: =K11*12 -> 869094.48 | Q11: =N11*12 -> 166400.85
A12: 5 | B12: ANDRAWUS MUSA | C12: DEP. DIRECTOR, STORES & PROCUREMENT | D12: 16(8) | E12: 716034 | F12: ='[2] FGN 2024 MGT Monthly'!$I$44 -> 539028 | G12: ='[2]Peculiar Allowance'!$I$44 -> 339980.92 | H12: =F12+G12 -> 879008.92 | I12: =H12-E12 -> 162974.92 | J12: 59136.287 | K12: =H12*0.08 -> 70320.713 | L12: =K12-J12 -> 11184.427 | M12: 10293.398 | N12: =0.025*F12 -> 13475.7 | O12: =N12-M12 -> 3182.3021 | P12: =K12*12 -> 843848.56 | Q12: =N12*12 -> 161708.4
A13: 6 | B13: DR FRANCIS NDUM OJIE | C13: AD, TRAINING & IC./SA TO DG | D13: 15(8) | E13: 601396.83 | F13: 445995.83 | G13: 276599.67 | H13: =F13+G13 -> 722595.5 | I13: =H13-E13 -> 121198.67 | J13: 46569.447 | K13: =H13*0.08 -> 57807.64 | L13: =K13-J13 -> 11238.193 | M13: 7859.6313 | N13: =0.025*F13 -> 11149.896 | O13: =N13-M13 -> 3290.2646 | P13: =K13*12 -> 693691.68 | Q13: =N13*12 -> 133798.75
A14: 7 | B14: ALI ABDULLAHI | C14: CHIEF ICT OFFICER | D14: 14(11) | E14: 484373.75 | F14: 366417.5 | G14: 223239.5 | H14: =F14+G14 -> 589657 | I14: =H14-E14 -> 105283.25 | J14: 38749.9 | K14: =H14*0.08 -> 47172.56 | L14: =K14-J14 -> 8422.66 | O14: =N14-M14 -> 0 | P14: =K14*12 -> 566070.72 | Q14: =N14*12 -> 0
A15: 8 | B15: EMILY EKHIDE | C15: SENIOR RESEARCH FELLOW | D15: 15(8) | E15: 601396.83 | F15: ='[3] FGN 2024 MGT Monthly'!$I$43 -> 445995.83 | G15: 276599.67 | H15: =F15+G15 -> 722595.5 | I15: =H15-E15 -> 121198.67 | J15: 46569.45 | K15: =H15*0.08 -> 57807.64 | L15: =K15-J15 -> 11238.19 | O15: =N15-M15 -> 0 | P15: =K15*12 -> 693691.68 | Q15: =N15*12 -> 0
A16: 9 | B16: DORIS DAKDA AARON | C16: RESEARCH FELLOW I | D16: 14(9) | E16: 456622.25 | F16: 347715.92 | G16: 210449.33 | H16: =F16+G16 -> 558165.25 | I16: =H16-E16 -> 101543 | J16: 35419.72 | K16: =H16*0.08 -> 44653.22 | L16: =K16-J16 -> 9233.5 | O16: =N16-M16 -> 0 | P16: =K16*12 -> 535838.64 | Q16: =N16*12 -> 0
A17: 10 | B17: ABDULSALAM S. MUSTAPHA | C17: ASST. DIRECTOR ICT | D17: 15(7) | E17: 582118.08 | F17: 432981.08 | G17: 267732.83 | H17: =F17+G17 -> 700713.92 | I17: =H17-E17 -> 118595.83 | J17: 46569.45 | K17: =H17*0.08 -> 56057.113 | L17: =K17-J17 -> 9487.6633 | O17: =N17-M17 -> 0 | P17: =K17*12 -> 672685.36 | Q17: =N17*12 -> 0
A18: 11 | B18: PERCY TERFA GBAHABO | C18: HEAD, NILDS LIAISON OFFICE | D18: 13(11) | E18: 441804.92 | F18: 337730.83 | G18: 203620.5 | H18: =F18+G18 -> 541351.33 | I18: =H18-E18 -> 99546.417 | J18: 34313.273 | K18: =H18*0.08 -> 43308.107 | L18: =K18-J18 -> 8994.8333 | O18: =N18-M18 -> 0 | P18: =K18*12 -> 519697.28 | Q18: =N18*12 -> 0
A19: 12 | B19: HASSANA AHMED IBRAHIM | C19: PA- TO DG | D19: 13 (10) | E19: 428915.92 | F19: 329044.92 | G19: 197680.17 | H19: =F19+G19 -> 526725.08 | I19: =H19-E19 -> 97809.167 | J19: 33282.153 | K19: =H19*0.08 -> 42138.007 | L19: =K19-J19 -> 8855.8533 | M19: 5607.1771 | N19: =0.025*F19 -> 8226.1229 | O19: =N19-M19 -> 2618.9458 | P19: =K19*12 -> 505656.08 | Q19: =N19*12 -> 98713.475
A20: 13 | B20: IKIP LEBO | C20: ASST CHIEF PROC. OFFICER | D20: 13 (8) | E20: 403138 | F20: 311673.25 | G20: 185799.5 | H20: =F20+G20 -> 497472.75 | I20: =H20-E20 -> 94334.75 | J20: 31219.913 | K20: =H20*0.08 -> 39797.82 | L20: =K20-J20 -> 8577.9067 | M20: 5967.3062 | N20: =0.025*F20 -> 7791.8313 | O20: =N20-M20 -> 1824.525 | P20: =K20*12 -> 477573.84 | Q20: =N20*12 -> 93501.975
A21: 14 | B21: ALABI ADESINA MUHYDEEN | C21: HEAD, NILDS LIAISON OFFICE | D21: 13 (8) | E21: 403138 | F21: 311673.25 | G21: 185799.5 | H21: =F21+G21 -> 497472.75 | I21: =H21-E21 -> 94334.75 | J21: 31219.913 | K21: =H21*0.08 -> 39797.82 | L21: =K21-J21 -> 8577.9067 | O21: =N21-M21 -> 0 | P21: =K21*12 -> 477573.84 | Q21: =N21*12 -> 0
A22: 15 | B22: BASSEY NSONGURUA UDOFIA | C22: PRINC.CONF SEC/PPS | D22: 12(11) | E22: 402278 | F22: ='[3] FGN 2024 MGT Monthly'!$L$40 -> 311094.42 | G22: 185402.75 | H22: =F22+G22 -> 496497.17 | I22: =H22-E22 -> 94219.167 | J22: 31206.92 | K22: =H22*0.08 -> 39719.773 | L22: =K22-J22 -> 8512.8533 | M22: 5257.5625 | N22: =0.025*F22 -> 7777.3604 | O22: =N22-M22 -> 2519.7979 | P22: =K22*12 -> 476637.28 | Q22: =N22*12 -> 93328.325
A23: 16 | B23: ADUGBA RICHARD TERSEER | C23: PRINCIPAL INFO. OFFICER | D23: 12(10) | E23: 390086.5 | F23: 302878.67 | G23: 179784 | H23: =F23+G23 -> 482662.67 | I23: =H23-E23 -> 92576.167 | J23: 30231.613 | K23: =H23*0.08 -> 38613.013 | L23: =K23-J23 -> 8381.4 | N23: =0.025*F23 -> 7571.9667 | O23: =N23-M23 -> 7571.9667 | P23: =K23*12 -> 463356.16 | Q23: =N23*12 -> 90863.6
A24: 17 | B24: LUCKY AGWOM | C24: RESEARCH ASSISTANT | D24: 12(8) | E24: 365704 | F24: 286447.08 | G24: 168546.5 | H24: =F24+G24 -> 454993.58 | I24: =H24-E24 -> 89289.583 | J24: 28281 | K24: =H24*0.08 -> 36399.487 | L24: =K24-J24 -> 8118.4867 | O24: =N24-M24 -> 0 | P24: =K24*12 -> 436793.84 | Q24: =N24*12 -> 0
A25: 18 | B25: IDRIS IBRAHIM | C25: PRINCIPAL RESEARCH OFFICER | D25: 12(8) | E25: 365704 | F25: 286447.08 | G25: 168546.5 | H25: =F25+G25 -> 454993.58 | I25: =H25-E25 -> 89289.583 | J25: 28281 | K25: =H25*0.08 -> 36399.487 | L25: =K25-J25 -> 8118.4867 | O25: =N25-M25 -> 0 | P25: =K25*12 -> 436793.84 | Q25: =N25*12 -> 0
A26: 19 | B26: FARUQ ATOFARATI | C26: PA (SPECIAL DUTIES) TO DG | D26: 10(7) | E26: 293029.67 | F26: 240874.58 | G26: 140266.08 | H26: =F26+G26 -> 381140.67 | I26: =H26-E26 -> 88111 | J26: 23442.373 | K26: =H26*0.08 -> 30491.253 | L26: =K26-J26 -> 7048.88 | O26: =N26-M26 -> 0 | P26: =K26*12 -> 365895.04 | Q26: =N26*12 -> 0
A27: 20 | B27: RASHEEDAT DAIBU | C27: SENIOR INFO. OFFICER | D27: 10(8) | E27: 300965.58 | F27: 240874.58 | G27: 140266.08 | H27: =F27+G27 -> 381140.67 | I27: =H27-E27 -> 80175.083 | J27: 23442.373 | K27: =H27*0.08 -> 30491.253 | L27: =K27-J27 -> 7048.88 | N27: =0.025*F27 -> 6021.8646 | O27: =N27-M27 -> 6021.8646 | P27: =K27*12 -> 365895.04 | Q27: =N27*12 -> 72262.375
A28: 21 | B28: ELIZABETH OGECHUKWU ONYEAKU | C28: ICT OFFICER | D28: 9(10) | E28: 277798 | F28: 227615.75 | G28: 127704.92 | H28: =F28+G28 -> 355320.67 | I28: =H28-E28 -> 77522.667 | J28: 21638.533 | K28: =H28*0.08 -> 28425.653 | L28: =K28-J28 -> 6787.12 | N28: =0.025*F28 -> 5690.3938 | O28: =N28-M28 -> 5690.3938 | P28: =K28*12 -> 341107.84 | Q28: =N28*12 -> 68284.725
A29: 22 | B29: VICTOR ASUKWO | C29: ICT OFFICER | D29: 9(10) | E29: 277798 | F29: 227615.75 | G29: 127704.92 | H29: =F29+G29 -> 355320.67 | I29: =H29-E29 -> 77522.667 | J29: 21638.533 | K29: =H29*0.08 -> 28425.653 | L29: =K29-J29 -> 6787.12 | N29: =0.025*F29 -> 5690.3938 | O29: =N29-M29 -> 5690.3938 | P29: =K29*12 -> 341107.84 | Q29: =N29*12 -> 68284.725
A30: 23 | B30: NNANDI LIVINUS ATURE | C30: RESEARCH ASSISTANT | D30: 9(10) | E30: 277798 | F30: 227615.75 | G30: 127704.92 | H30: =F30+G30 -> 355320.67 | I30: =H30-E30 -> 77522.667 | J30: 21638.533 | K30: =H30*0.08 -> 28425.653 | L30: =K30-J30 -> 6787.12 | O30: =N30-M30 -> 0 | P30: =K30*12 -> 341107.84 | Q30: =N30*12 -> 0
A31: 24 | B31: ABDULRAHMAN A SULAIMAN | C31: STORE OFFICER | D31: 9(9) | E31: 270481.67 | F31: 222674.58 | G31: 124341.58 | H31: =F31+G31 -> 347016.17 | I31: =H31-E31 -> 76534.5 | J31: 21053.227 | K31: =H31*0.08 -> 27761.293 | L31: =K31-J31 -> 6708.0667 | O31: =N31-M31 -> 0 | P31: =K31*12 -> 333135.52 | Q31: =N31*12 -> 0
A32: 25 | B32: DARE SHEU MAGBON | C32: ADMINISTRATION OFFICER | D32: 9(8) | E32: 263165.33 | F32: 217733.42 | G32: 120978.25 | H32: =F32+G32 -> 338711.67 | I32: =H32-E32 -> 75546.333 | J32: 20467.92 | K32: =H32*0.08 -> 27096.933 | L32: =K32-J32 -> 6629.0133 | O32: =N32-M32 -> 0 | P32: =K32*12 -> 325163.2 | Q32: =N32*12 -> 0
A33: 26 | B33: ABUBAKAR SULAIMAN SODEEQ | C33: ADMINISTRATION OFFICER | D33: 9(8) | E33: 263165.33 | F33: 217733.42 | G33: 120978.25 | H33: =F33+G33 -> 338711.67 | I33: =H33-E33 -> 75546.333 | J33: 20467.92 | K33: =H33*0.08 -> 27096.933 | L33: =K33-J33 -> 6629.0133 | O33: =N33-M33 -> 0 | P33: =K33*12 -> 325163.2 | Q33: =N33*12 -> 0
A34: 27 | B34: JIMOH ADEBAYO ZAKA | C34: ASST. OFFICER/COMM | D34: 9(10) | E34: 277798 | F34: 227615.75 | G34: 127704.92 | H34: =F34+G34 -> 355320.67 | I34: =H34-E34 -> 77522.667 | J34: 21638.533 | K34: =H34*0.08 -> 28425.653 | L34: =K34-J34 -> 6787.12 | M34: 3653.5 | N34: =0.025*F34 -> 5690.3938 | O34: =N34-M34 -> 2036.8937 | P34: =K34*12 -> 341107.84 | Q34: =N34*12 -> 68284.725
A35: 28 | B35: ABDULMUSHIN TAWFIQ LADAN | C35: ICT OFFICER | D35: 9(8) | E35: 263165.33 | F35: 217733.42 | G35: 120978.25 | H35: =F35+G35 -> 338711.67 | I35: =H35-E35 -> 75546.333 | J35: 20467.92 | K35: =H35*0.08 -> 27096.933 | L35: =K35-J35 -> 6629.0133 | O35: =N35-M35 -> 0 | P35: =K35*12 -> 325163.2 | Q35: =N35*12 -> 0
A36: 29 | B36: MOHAMMED BELLO | C36: PROTOCOL ASSISTANT | D36: 9(8) | E36: 263165.33 | F36: 217733.42 | G36: 120978.25 | H36: =F36+G36 -> 338711.67 | I36: =H36-E36 -> 75546.333 | J36: 20467.92 | K36: =H36*0.08 -> 27096.933 | L36: =K36-J36 -> 6629.0133 | O36: =N36-M36 -> 0 | P36: =K36*12 -> 325163.2 | Q36: =N36*12 -> 0
A37: 30 | B37: HARUNA JIBRIL AMEH | C37: ASST. ADMIN. OFFICER | D37: 8(9) | E37: 230631.92 | F37: 196364.42 | G37: 105546.33 | H37: =F37+G37 -> 301910.75 | I37: =H37-E37 -> 71278.833 | J37: 17956.78 | K37: =H37*0.08 -> 24152.86 | L37: =K37-J37 -> 6196.08 | N37: =0.025*F37 -> 4909.1104 | O37: =N37-M37 -> 4909.1104 | P37: =K37*12 -> 289834.32 | Q37: =N37*12 -> 58909.325
A38: 31 | B38: RAMATU IBRAHIM ABDULRAHEEM | C38: INFORMATION OFFICER | D38: 8(8) | E38: 224459.75 | F38: 192179.42 | G38: 102721.42 | H38: =F38+G38 -> 294900.83 | I38: =H38-E38 -> 70441.083 | J38: 17463.007 | K38: =H38*0.08 -> 23592.067 | L38: =K38-J38 -> 6129.06 | N38: =0.025*F38 -> 4804.4854 | O38: =N38-M38 -> 4804.4854 | P38: =K38*12 -> 283104.8 | Q38: =N38*12 -> 57653.825
B39: TOTAL | C39: 31 | E39: =SUM(E8:E38) -> 14073004 | F39: =SUM(F8:F38) -> 10680274 | G39: =SUM(G8:G38) -> 6613927.3 | H39: =SUM(H8:H38) -> 17294201 | I39: =SUM(I8:I38) -> 3221197.1 | J39: =SUM(J8:J38) -> 914813.32 | K39: =SUM(K8:K38) -> 1153420.6 | L39: =SUM(L8:L38) -> 238607.23 | ... Q39: =SUM(Q8:Q38) -> 1231995.1
B41: INTERNAL AUDIT
A42: 1 | B42: OSANAIYE DAVID AKINYEMI | C42: DIRECTOR INTERNAL AUDIT | D42: 17(9) | E42: 1435720 | F42: 1086777.1 | G42: 660329.33 | H42: =F42+G42 -> 1747106.4 | I42: =H42-E42 -> 311386.42 | J42: 114857.6 | K42: =H42*0.08 -> 139768.51 | L42: =K42-J42 -> 24910.913 | O42: =N42-M42 -> 0 | P42: =K42*12 -> 1677222.2
A43: 2 | B43: JAMILA ABDUL | C43: SENIOR INTERNAL AUDITOR | D43: 10(8) | E43: 300965.58 | F43: 240874.58 | G43: 140266.08 | H43: =F43+G43 -> 381140.67 | I43: =H43-E43 -> 80175.083 | J43: 23442.373 | K43: =H43*0.08 -> 30491.253 | L43: =K43-J43 -> 7048.88 | N43: =0.025*F43 -> 6021.8646 | O43: =N43-M43 -> 6021.8646 | P43: =K43*12 -> 365895.04
A44: 3 | B44: IJEOMA EWELUKWA | C44: SENIOR INTERNAL AUDITOR | D44: 10(9) | E44: 308901.5 | F44: 246171.17 | G44: 143964.67 | H44: =F44+G44 -> 390135.83 | I44: =H44-E44 -> 81234.333 | J44: 24077.247 | K44: =H44*0.08 -> 31210.867 | L44: =K44-J44 -> 7133.62 | O44: =N44-M44 -> 0 | P44: =K44*12 -> 374530.4
A45: 4 | B45: YUSUF YUSUF DAYYABU | C45: INERNAL AUDIT OFFICER | D45: 9(8) | E45: 263165.33 | F45: 217733.42 | G45: 120978.25 | H45: =F45+G45 -> 338711.67 | I45: =H45-E45 -> 75546.333 | J45: 20467.92 | K45: =H45*0.08 -> 27096.933 | L45: =K45-J45 -> 6629.0133 | N45: =0.025*F45 -> 5443.3354 | O45: =N45-M45 -> 5443.3354 | P45: =K45*12 -> 325163.2
C46: 4 | E46: =SUM(E42:E45) -> 2308752.4 | F46: =SUM(F42:F45) -> 1791556.2 | G46: =SUM(G42:G45) -> 1065538.3 | H46: =SUM(H42:H45) -> 2857094.6 | I46: =SUM(I42:I45) -> 548342.17 | J46: =SUM(J42:J45) -> 182845.14 | K46: =SUM(K42:K45) -> 228567.57 | L46: =SUM(L42:L45) -> 45722.427 | ... Q46: =SUM(Q42:Q45) -> 0
B48: LEG. SUPPORT SEVICES
A49: 1 | B49: BETHEL UZOMA IHUGBA | C49: DEPUTY DIRECTOR, LEGAL RESEARCH | D49: 16(9) | E49: 762373.17 | F49: 554669.5 | G49: 350637.25 | H49: =F49+G49 -> 905306.75 | I49: =H49-E49 -> 142933.58 | J49: 59136.287 | K49: =H49*0.08 -> 72424.54 | L49: =K49-J49 -> 13288.253 | O49: =N49-M49 -> 0 | P49: =K49*12 -> 869094.48
A50: 2 | B50: OGUCHE SAMUEL | C50: SNR RESEARCH FELLOW | D50: 15(9) | E50: 620675.58 | F50: 459010.5 | G50: 285466.5 | H50: =F50+G50 -> 744477 | I50: =H50-E50 -> 123801.42 | J50: 49654.047 | K50: =H50*0.08 -> 59558.16 | L50: =K50-J50 -> 9904.1133 | O50: =N50-M50 -> 0 | P50: =K50*12 -> 714697.92
A51: 3 | B51: IBRAHIM USMAN | C51: SNR RESEARCH FELLOW | D51: 15(9) | E51: 620675.58 | F51: 459010.5 | G51: 285466.5 | H51: =F51+G51 -> 744477 | I51: =H51-E51 -> 123801.42 | J51: 49654.047 | K51: =H51*0.08 -> 59558.16 | L51: =K51-J51 -> 9904.1133 | M51: 8380.2271 | N51: =0.025*F51 -> 11475.263 | O51: =N51-M51 -> 3095.0354 | P51: =K51*12 -> 714697.92 | Q51: =N51*12 -> 137703.15
A52: 4 | B52: DR MOHAMMED O. AMALI | C52: SNR RESEARCH FELLOW | D52: 15(8) | E52: 601396.83 | F52: 445995.83 | G52: 276599.67 | H52: =F52+G52 -> 722595.5 | I52: =H52-E52 -> 121198.67 | J52: 46569.447 | K52: =H52*0.08 -> 57807.64 | L52: =K52-J52 -> 11238.193 | O52: =N52-M52 -> 0 | P52: =K52*12 -> 693691.68
A53: 5 | B53: YAHAYA SHAMSU | C53: SNR RESEARCH FELLOW | D53: 15(7) | E53: 582118.08 | F53: 432981.08 | G53: 267732.83 | H53: =F53+G53 -> 700713.92 | I53: =H53-E53 -> 118595.83 | J53: 46569.45 | K53: =H53*0.08 -> 56057.113 | L53: =K53-J53 -> 9487.6633 | O53: =N53-M53 -> 0 | P53: =K53*12 -> 672685.36
A54: 6 | B54: BILKIS S. LAWAL-GAMBARI | C54: RESEARCH OFFICER | D54: 10(9) | E54: 308901.5 | F54: 246171.17 | G54: 143964.67 | H54: =F54+G54 -> 390135.83 | I54: =H54-E54 -> 81234.333 | J54: 24077.247 | K54: =H54*0.08 -> 31210.867 | L54: =K54-J54 -> 7133.62 | O54: =N54-M54 -> 0 | P54: =K54*12 -> 374530.4
A55: 7 | B55: ZAINAB AKINDE | C55: RESEARCH OFFICER | D55: 9(9) | E55: 270481.67 | F55: 222674.58 | G55: 124341.58 | H55: =F55+G55 -> 347016.17 | I55: =H55-E55 -> 76534.5 | J55: 21053.227 | K55: =H55*0.08 -> 27761.293 | L55: =K55-J55 -> 6708.0667 | O55: =N55-M55 -> 0 | P55: =K55*12 -> 333135.52
A56: 8 | B56: GUNAT NANSAK MARK | C56: RESEARCH OFFICER | D56: 9(9) | E56: 270481.67 | F56: 222674.58 | G56: 124341.58 | H56: =F56+G56 -> 347016.17 | I56: =H56-E56 -> 76534.5 | J56: 21053.227 | K56: =H56*0.08 -> 27761.293 | L56: =K56-J56 -> 6708.0667 | O56: =N56-M56 -> 0 | P56: =K56*12 -> 333135.52
B57: TOTAL | C57: 8 | E57: =SUM(E49:E56) -> 4037104.1 | F57: =SUM(F49:F56) -> 3043187.8 | G57: =SUM(G49:G56) -> 1858550.6 | H57: =SUM(H49:H56) -> 4901738.3 | I57: =SUM(I49:I56) -> 864634.25 | J57: =SUM(J49:J56) -> 317766.98 | K57: =SUM(K49:K56) -> 392139.07 | L57: =SUM(L49:L56) -> 74372.09 | ... Q57: =SUM(Q49:Q56) -> 137703.15
B59: LEGAL SERVICES
A60: 1 | B60: DR SHUAIBU DANWANKA | C60: DIRECTOR LEGAL SERVICES | D60: 17(9) | E60: 1435720 | F60: 1086777.1 | G60: 660329.33 | H60: =F60+G60 -> 1747106.4 | I60: =H60-E60 -> 311386.42 | J60: 114857.6 | K60: =H60*0.08 -> 139768.51 | L60: =K60-J60 -> 24910.913 | O60: =N60-M60 -> 0 | P60: =K60*12 -> 1677222.2
A61: 2 | B61: ABDULSALAM BAKO | C61: MANAGER, LEGAL SERVICES | D61: 15 (9) | E61: 620675.58 | F61: 459010.5 | G61: 285466.5 | H61: =F61+G61 -> 744477 | I61: =H61-E61 -> 123801.42 | J61: 49654.047 | K61: =H61*0.08 -> 59558.16 | L61: =K61-J61 -> 9904.1133 | O61: =N61-M61 -> 0 | P61: =K61*12 -> 714697.92
B62: TOTAL | C62: 2 | E62: =SUM(E60:E61) -> 2056395.6 | F62: =SUM(F60:F61) -> 1545787.6 | G62: =SUM(G60:G61) -> 945795.83 | H62: =SUM(H60:H61) -> 2491583.4 | I62: =SUM(I60:I61) -> 435187.83 | J62: =SUM(J60:J61) -> 164511.65 | K62: =SUM(K60:K61) -> 199326.67 | L62: =SUM(L60:L61) -> 34815.027 | ... Q62: =SUM(Q60:Q61) -> 0
B64: DEMOCRACY & GOVERNANCE
A65: 1 | B65: NGARA CHRISTOPHER OCHANJA | C65: DEP DIR DEM & GOVERNANCE | D65: 16(9) | E65: 762373.17 | F65: 554669.5 | G65: 350637.25 | H65: =F65+G65 -> 905306.75 | I65: =H65-E65 -> 142933.58 | J65: 60989.853 | K65: =H65*0.08 -> 72424.54 | L65: =K65-J65 -> 11434.687 | M65: 10293.398 | N65: =0.025*F65 -> 13866.737 | O65: =N65-M65 -> 3573.3396 | P65: =K65*12 -> 869094.48 | Q65: =N65*12 -> 166400.85
A66: 2 | B66: EJALONIBU GANIYU LAYI | C66: RESEARCH FELLOW 1 | D66: 14(9) | E66: 456622.25 | F66: 347715.92 | G66: 210449.33 | H66: =F66+G66 -> 558165.25 | I66: =H66-E66 -> 101543 | J66: 35419.72 | K66: =H66*0.08 -> 44653.22 | L66: =K66-J66 -> 9233.5 | O66: =N66-M66 -> 0 | P66: =K66*12 -> 535838.64
A67: 3 | B67: UDEFUNA NNADOZIE PATRICK | C67: RESEARCH OFFICER | D67: 12(9) | E67: 377895.17 | F67: 294662.92 | G67: 174165.25 | H67: =F67+G67 -> 468828.17 | I67: =H67-E67 -> 90933 | J67: 29256.307 | K67: =H67*0.08 -> 37506.253 | L67: =K67-J67 -> 8249.9467 | O67: =N67-M67 -> 0 | P67: =K67*12 -> 450075.04
A68: 4 | B68: SHAFIU YAHYA MIKAIL | C68: PRINCIPAL RESEARCH OFFICER | D68: 12(9) | E68: 377895.17 | F68: 294662.92 | G68: 174165.25 | H68: =F68+G68 -> 468828.17 | I68: =H68-E68 -> 90933 | J68: 29256.307 | K68: =H68*0.08 -> 37506.253 | L68: =K68-J68 -> 8249.9467 | O68: =N68-M68 -> 0 | P68: =K68*12 -> 450075.04
A69: 5 | B69: HASSAN YERIMA | C69: PRINCIPAL RESEARCH OFFICER | D69: 12(9) | E69: 377895.17 | F69: 294662.92 | G69: 174165.25 | H69: =F69+G69 -> 468828.17 | I69: =H69-E69 -> 90933 | J69: 29256.307 | K69: =H69*0.08 -> 37506.253 | L69: =K69-J69 -> 8249.9467 | O69: =N69-M69 -> 0 | P69: =K69*12 -> 450075.04
A70: 6 | B70: HAUWA PATE SADIQ | C70: PRINCIPAL PROGRAMME OFFICER | D70: 12(10) | E70: 390086.5 | F70: 302878.67 | G70: 179784 | H70: =F70+G70 -> 482662.67 | I70: =H70-E70 -> 92576.167 | J70: 30231.613 | K70: =H70*0.08 -> 38613.013 | L70: =K70-J70 -> 8381.4 | O70: =N70-M70 -> 0 | P70: =K70*12 -> 463356.16
A71: 7 | B71: KOLAPO Q. ABAYOMI | C71: RESEARCH OFFICER | D71: 10(9) | E71: 308901.5 | F71: 246171.17 | G71: 143964.67 | H71: =F71+G71 -> 390135.83 | I71: =H71-E71 -> 81234.333 | J71: 24077.247 | K71: =H71*0.08 -> 31210.867 | L71: =K71-J71 -> 7133.62 | N71: =0.025*F71 -> 6154.2792 | O71: =N71-M71 -> 6154.2792 | P71: =K71*12 -> 374530.4
B72: TOTAL | C72: 7 | E72: =SUM(E65:E71) -> 3051668.9 | F72: =SUM(F65:F71) -> 2335424 | G72: =SUM(G65:G71) -> 1407331 | H72: =SUM(H65:H71) -> 3742755 | I72: =SUM(I65:I71) -> 691086.08 | J72: =SUM(J65:J71) -> 238487.35 | K72: =SUM(K65:K71) -> 299420.4 | L72: =SUM(L65:L71) -> 60933.047 | ... Q72: =SUM(Q65:Q71) -> 166400.85
B74: DEPARTMENT OF STUDIES
A75: 1 | B75: DR ASIMIYU G. ABIOLA | C75: DIRECTOR POST GRADUATE | D75: 17(9) | E75: 1435720 | F75: 1086777.1 | G75: 660329.33 | H75: =F75+G75 -> 1747106.4 | I75: =H75-E75 -> 311386.42 | J75: 114857.6 | K75: =H75*0.08 -> 139768.51 | L75: =K75-J75 -> 24910.913 | O75: =N75-M75 -> 0 | P75: =K75*12 -> 1677222.2
A76: 2 | B76: DR. HADIZA SAIDU | C76: ASSISTANT DIRECTOR | D76: 15(7) | E76: 582118.08 | F76: 445995.83 | G76: 276599.67 | H76: =F76+G76 -> 722595.5 | I76: =H76-E76 -> 140477.42 | J76: 46569.447 | K76: =H76*0.08 -> 57807.64 | L76: =K76-J76 -> 11238.193 | O76: =N76-M76 -> 0 | P76: =K76*12 -> 693691.68
A77: 3 | B77: ANTHONY EDET | C77: CHIEF PROGRAMMES OFFICER | D77: 14(10) | E77: 470498 | F77: 357066.67 | G77: 216844.42 | H77: =F77+G77 -> 573911.08 | I77: =H77-E77 -> 103413.08 | J77: 36529.78 | K77: =H77*0.08 -> 45912.887 | L77: =K77-J77 -> 9383.1067 | M77: 6154.3229 | N77: =0.025*F77 -> 8926.6667 | O77: =N77-M77 -> 2772.3438 | P77: =K77*12 -> 550954.64 | Q77: =N77*12 -> 107120
A78: 4 | B78: IGWE STACY | C78: PRINC. PROGRAMME OFFICER | D78: 12(8) | E78: 365703.83 | F78: 286447.08 | G78: 168546.5 | H78: =F78+G78 -> 454993.58 | I78: =H78-E78 -> 89289.75 | J78: 28281 | K78: =H78*0.08 -> 36399.487 | L78: =K78-J78 -> 8118.4867 | O78: =N78-M78 -> 0 | P78: =K78*12 -> 436793.84
A79: 5 | B79: OLANIYAN TAIWO ABINBOLA | C79: PROGRAMME OFFICER | D79: 9(8) | E79: 263165.33 | F79: 222674.58 | G79: 124341.58 | H79: =F79+G79 -> 347016.17 | I79: =H79-E79 -> 83850.833 | J79: 21053.227 | K79: =H79*0.08 -> 27761.293 | L79: =K79-J79 -> 6708.0667 | N79: =0.025*F79 -> 5566.8646 | O79: =N79-M79 -> 5566.8646 | P79: =K79*12 -> 333135.52
A80: 6 | B80: AMINAT JUMOKE SULAIMON | C80: AST. PROGRAMME OFFICER | D80: 8(9) | E80: 230631.92 | F80: 196364.42 | G80: 105546.33 | H80: =F80+G80 -> 301910.75 | I80: =H80-E80 -> 71278.833 | J80: 17956.78 | K80: =H80*0.08 -> 24152.86 | L80: =K80-J80 -> 6196.08 | O80: =N80-M80 -> 0 | P80: =K80*12 -> 289834.32
B81: TOTAL | C81: 6 | E81: =SUM(E75:E80) -> 3347837.2 | F81: =SUM(F75:F80) -> 2595325.7 | G81: =SUM(G75:G80) -> 1552207.8 | H81: =SUM(H75:H80) -> 4147533.5 | I81: =SUM(I75:I80) -> 799696.33 | J81: =SUM(J75:J80) -> 265247.83 | K81: =SUM(K75:K80) -> 331802.68 | L81: =SUM(L75:L80) -> 66554.847 | ... Q81: =SUM(Q75:Q80) -> 107120
B83: ECON. DEV. & SOC. RESEARCH
A84: 1 | B84: DR AUGUSTINE C. OSIGWE | C84: SNR RESEARCH FELLOW | D84: 17(7) | E84: ='[4]Annual & Monthly'!$H$44 -> 1352042.7 | F84: 1025768.3 | G84: 621843.67 | H84: =F84+G84 -> 1647612 | I84: =H84-E84 -> 295569.33 | J84: 114857.6 | K84: =H84*0.08 -> 131808.96 | L84: =K84-J84 -> 16951.36 | M84: 18254.975 | N84: =0.025*F84 -> 25644.208 | O84: =N84-M84 -> 7389.2333 | P84: =12*K84 -> 1581707.5 | Q84: =N84*12 -> 307730.5
A85: 2 | B85: TERFA WILLIAMS ABRAHAM | C85: DEP. DIRECTOR ECON & SOCIAL RES | D85: 16(7) | E85: 716034 | F85: 523386.5 | G85: 329324.58 | H85: =F85+G85 -> 852711.08 | I85: =H85-E85 -> 136677.08 | J85: 59136.287 | K85: =H85*0.08 -> 68216.887 | L85: =K85-J85 -> 9080.6 | O85: =N85-M85 -> 0 | P85: =12*K85 -> 818602.64
A86: 3 | B86: OMOJU OLUWASOLA EMMANUEL | C86: SNR RESEARCH FELLOW | D86: 15(8) | E86: 601396.83 | F86: 445995.83 | G86: 276599.67 | H86: =F86+G86 -> 722595.5 | I86: =H86-E86 -> 121198.67 | J86: 46569.447 | K86: =H86*0.08 -> 57807.64 | L86: =K86-J86 -> 11238.193 | O86: =N86-M86 -> 0 | P86: =12*K86 -> 693691.68
A87: 4 | B87: IBE EZECHI CYRIACUS | C87: RESEARCH FELLOW 1 | D87: 14(9) | E87: 456622.25 | F87: 347715.92 | G87: 210449.33 | H87: =F87+G87 -> 558165.25 | I87: =H87-E87 -> 101543 | J87: 35344.393 | K87: =H87*0.08 -> 44653.22 | L87: =K87-J87 -> 9308.8267 | O87: =N87-M87 -> 0 | P87: =12*K87 -> 535838.64
A88: 5 | B88: OSIKHEN LEO IGBANOI | C88: RESEARCH FELLOW 1 | D88: 14(9) | E88: 456622.25 | F88: 347716.92 | G88: 210449.33 | H88: =F88+G88 -> 558166.25 | I88: =H88-E88 -> 101544 | J88: 35419.72 | K88: =H88*0.08 -> 44653.3 | L88: =K88-J88 -> 9233.58 | N88: =0.025*F88 -> 8692.9229 | O88: =N88-M88 -> 8692.9229 | P88: =12*K88 -> 535839.6 | Q88: =N88*12 -> 104315.07
A89: 6 | B89: OKUNGBOWA OSARETIN GODSPOWER | C89: RESEARCH FELLOW 1 | D89: 14(8) | E89: 442746.5 | F89: 338365.25 | G89: 204054.25 | H89: =F89+G89 -> 542419.5 | I89: =H89-E89 -> 99673 | J89: 34309.66 | K89: =H89*0.08 -> 43393.56 | L89: =K89-J89 -> 9083.9 | O89: =N89-M89 -> 0 | P89: =12*K89 -> 520722.72
A90: 7 | B90: YUSUF IBRAHIM | C90: PRINCIPAL RESEARCH OFFICER | D90: 12(9) | E90: 377895.17 | F90: 294662.92 | G90: 174165.25 | H90: =F90+G90 -> 468828.17 | I90: =H90-E90 -> 90933 | J90: 29256.307 | K90: =H90*0.08 -> 37506.253 | L90: =K90-J90 -> 8249.9467 | O90: =N90-M90 -> 0 | P90: =12*K90 -> 450075.04
A91: 8 | B91: MUSTAPHA RAFIU AYOBANJI | C91: RESEARCH FELLOW 11 | D91: 13(8) | E91: 403137.92 | F91: 311673.25 | G91: 185799.5 | H91: =F91+G91 -> 497472.75 | I91: =H91-E91 -> 94334.833 | J91: 31219.913 | K91: =H91*0.08 -> 39797.82 | L91: =K91-J91 -> 8577.9067 | M91: 5259.7437 | N91: =0.025*F91 -> 7791.8313 | O91: =N91-M91 -> 2532.0875 | P91: =12*K91 -> 477573.84 | Q91: =N91*12 -> 93501.975
A92: 9 | B92: MARYAM MUSA SADA | C92: ASSIT. RESEARCH OFFICER | D92: 10(9) | E92: 308901.5 | F92: 246171.17 | G92: 143964.67 | H92: =F92+G92 -> 390135.83 | I92: =H92-E92 -> 81234.333 | J92: 24077.247 | K92: =H92*0.08 -> 31210.867 | L92: =K92-J92 -> 7133.62 | O92: =N92-M92 -> 0 | P92: =12*K92 -> 374530.4
A93: 10 | B93: CHARITY EZENWAJIOBI | C93: REASEARCH. ASST. | D93: 8(10) | E93: 236804.08 | F93: 200549.42 | G93: 108371.25 | H93: =F93+G93 -> 308920.67 | I93: =H93-E93 -> 72116.583 | J93: 18450.553 | K93: =H93*0.08 -> 24713.653 | L93: =K93-J93 -> 6263.1 | N93: =0.025*F93 -> 5013.7354 | O93: =N93-M93 -> 5013.7354 | P93: =12*K93 -> 296563.84
B94: TOTAL | C94: 10 | E94: =SUM(E84:E93) -> 5352203.2 | F94: =SUM(F84:F93) -> 4082005.5 | G94: =SUM(G84:G93) -> 2465021.5 | H94: =SUM(H84:H93) -> 6547027 | I94: =SUM(I84:I93) -> 1194823.8 | J94: =SUM(J84:J93) -> 428641.13 | K94: =SUM(K84:K93) -> 523762.16 | L94: =SUM(L84:L93) -> 95121.033 | ... Q94: =SUM(Q84:Q93) -> 505547.55
B96: TRAINING & INT''L COOP
A97: 1 | B97: AKINSANMI ADEJOKE OLUKEMI | C97: Ag. DIR. TRAINING & IC | D97: 17(8) | E97: 1393881.3 | F97: 1056272.8 | G97: 641086.5 | H97: =F97+G97 -> 1697359.3 | I97: =H97-E97 -> 303478 | J97: 114857.6 | K97: =H97*0.08 -> 135788.75 | L97: =K97-J97 -> 20931.147 | M97: 18254.975 | N97: =0.025*F97 -> 26406.821 | O97: =N97-M97 -> 8151.8458 | P97: =12*K97 -> 1629465 | Q97: =N97*12 -> 316881.85
A98: 2 | B98: MOHAMMED R. ADAMU | C98: CHIEF TRAINING OFFICER | D98: 14(10) | E98: 470498 | F98: 357066.67 | G98: 216844.42 | H98: =F98+G98 -> 573911.08 | I98: =H98-E98 -> 103413.08 | J98: 36529.78 | K98: =H98*0.08 -> 45912.887 | L98: =K98-J98 -> 9383.1067 | O98: =N98-M98 -> 0 | P98: =12*K98 -> 550954.64 | Q98: =N98*12 -> 0
A99: 3 | B99: EROMOSELE OMONIGBO | C99: ASSIST. CHIEF PERSONNEL OFFICER | D99: 13(8) | E99: 403137.92 | F99: 311673.25 | G99: 185799.5 | H99: =F99+G99 -> 497472.75 | I99: =H99-E99 -> 94334.833 | J99: 31219.91 | K99: =H99*0.08 -> 39797.82 | L99: =K99-J99 -> 8577.91 | M99: 5967.3062 | N99: =0.025*F99 -> 7791.8313 | O99: =N99-M99 -> 1824.525 | P99: =12*K99 -> 477573.84 | Q99: =N99*12 -> 93501.975
A100: 4 | B100: OKECHUKWU UCHENNA HULDA | C100: PRINCIPALTRAINING OFFICER | D100: 12(10) | E100: 390086.5 | F100: 302878.67 | G100: 179784 | H100: =F100+G100 -> 482662.67 | I100: =H100-E100 -> 92576.167 | J100: 30231.613 | K100: =H100*0.08 -> 38613.013 | L100: =K100-J100 -> 8381.4 | O100: =N100-M100 -> 0 | P100: =12*K100 -> 463356.16 | Q100: =N100*12 -> 0
A101: 5 | B101: TASSNEEM IBRAHIM | C101: SENIOR PROGRAMME OFFICER | D101: 10(9) | E101: 308901.5 | F101: 246171.17 | G101: 143964.67 | H101: =F101+G101 -> 390135.83 | I101: =H101-E101 -> 81234.333 | J101: 24077.247 | K101: =H101*0.08 -> 31210.867 | L101: =K101-J101 -> 7133.62 | O101: =N101-M101 -> 0 | P101: =12*K101 -> 374530.4 | Q101: =N101*12 -> 0
B102: TOTAL | C102: 5 | E102: =SUM(E97:E101) -> 2966505.2 | F102: =SUM(F97:F101) -> 2274062.6 | G102: =SUM(G97:G101) -> 1367479.1 | H102: =SUM(H97:H101) -> 3641541.7 | I102: =SUM(I97:I101) -> 675036.42 | J102: =SUM(J97:J101) -> 236916.15 | K102: =SUM(K97:K101) -> 291323.33 | L102: =SUM(L97:L101) -> 54407.183 | ... Q102: =SUM(Q97:Q101) -> 410383.82
B104: LIBRARY & DOCUMENTATION
A105: 1 | B105: DR MAIMUNA IZAH | C105: INSITUTE LIBRARIAN | D105: 17(9) | E105: 1435720 | F105: 1086777.1 | G105: 660329.33 | H105: =F105+G105 -> 1747106.4 | I105: =H105-E105 -> 311386.42 | J105: 114857.6 | K105: =H105*0.08 -> 139768.51 | L105: =K105-J105 -> 24910.913 | M105: 0 | O105: =N105-M105 -> 0 | P105: =K105*12 -> 1677222.2
A106: 2 | B106: CATHERINE E. IKOKOH | C106: SNR RESEARCH FELLOW DOCU | D106: 16(9) | E106: 762373.17 | F106: 554669.5 | G106: 350637.25 | H106: =F106+G106 -> 905306.75 | I106: =H106-E106 -> 142933.58 | J106: 60989.853 | K106: =H106*0.08 -> 72424.54 | L106: =K106-J106 -> 11434.687 | M106: 10293.398 | N106: =0.025*F106 -> 13866.737 | O106: =N106-M106 -> 3573.3396 | P106: =K106*12 -> 869094.48 | Q106: =N106*12 -> 166400.85
A107: 3 | B107: ALIYU SANNI ABUBAKAR | C107: RESEARCH FELLOW 11 DATA & DOCU | D107: 13(11) | E107: 441804.92 | F107: 337730.83 | G107: 203620.5 | H107: =F107+G107 -> 541351.33 | I107: =H107-E107 -> 99546.417 | J107: 35344.393 | K107: =H107*0.08 -> 43308.107 | L107: =K107-J107 -> 7963.7133 | M107: 5954.6104 | N107: =0.025*F107 -> 8443.2708 | O107: =N107-M107 -> 2488.6604 | P107: =K107*12 -> 519697.28 | Q107: =N107*12 -> 101319.25
A108: 4 | B108: CHINAKO N. ASOGWA | C108: RESEARCH FELLOW 11 DATA & DOCU | D108: 14(7) | E108: 441804.92 | F108: 338365.25 | G108: 204054.25 | H108: =F108+G108 -> 542419.5 | I108: =H108-E108 -> 100614.58 | J108: 35344.393 | K108: =H108*0.08 -> 43393.56 | L108: =K108-J108 -> 8049.1667 | O108: =N108-M108 -> 0 | P108: =K108*12 -> 520722.72
...

Sheet Changes in PAYE
A1: NATIONAL INSTITUTE FOR LEGISLATIVE AND DEMOCRATIC STUDIES
A2: NATIONAL ASSEMBLY ABUJA
A3: TAX COMPUTATION FOR 2022
A4: S/NO | B4: NAME | C4: MONTHLY TOTAL SALARY | D4: NO OF MONTHS | E4: ANNUAL SALARY GROSSED UP | F4: NATIONAL HOUSING SCHEME = 2.5% OF BASIC SALARY | G4: PENSION CONTRIBUTION = 8% OF CONSOLIDATED | H4: NHIS | I4: NET SALARY (EXC OF CRA) | M4: CRA=#200,000+(20% 0F NET SALARY (EXC OF CRA) | N4: TOTAL RELIEF | O4: CHARGEABLE INCOME | P4: FIRST N300,000 @ 7% | Q4: NEXT N300,000 @ 11% | R4: NEXT N500,000 @ 15% | S4: NEXT N500,000@ 19% | T4: NEXT N1,600,000 @ 21% | U4: ABOVE N3,200,000 @ 24% | V4: ANNUAL TAX PAYABLE | X4: MONTHLY TAX PAYABLE | Y4: MINIMUM TAX PAYABLE | Z4: NEW ACTUAL TAX PAYABLE | AA4: OLD ACTUAL TAX PAYABLE | AB4: INCREASE IN PAYE
A5: 1 | B5: DG'S OFFICE
A6: 3 | B6: PROF. ABUBAKAR O. SULAIMAN | C6: 2246372.1 | D6: 12 | E6: =C6*D6 -> 26956465 | G6: 0 | I6: =E6-F6-G6-H6 -> 26956465 | J6: 200000 | K6: 0.2 | L6: =I6*K6 -> 5391293 | M6: =J6+L6 -> 5591293 | N6: =F6+G6+H6+M6 -> 5591293 | O6: =E6-N6 -> 21365172 | P6: =IF(O6<300000,0.07*O6,21000) -> 21000 | Q6: =IF((O6-300000)<0,0,IF((O6-300000)<300000,0.11*(O6-300000),33000)) -> 33000 | R6: =IF((O6-600000)<0,0,IF((O6-600000)<500000,0.15*(O6-600000),75000)) -> 75000 | S6: =IF((O6-1100000)<0,0,IF((O6-1100000)<500000,0.19*(O6-1100000),95000)) -> 95000 | T6: =IF((O6-1600000)<0,0,IF((O6-1600000)<1600000,0.21*(O6-1600000),336000)) -> 336000 | U6: =24%*(O6-3200000) -> 4359641.3 | V6: =P6+Q6+R6+S6+T6+U6 -> 4919641.3 | W6: 12 | X6: =V6/W6 -> 409970.11 | Z6: =X6 -> 409970.11 | AA6: 350184.01 | AB6: =Z6-AA6 -> 59786.096
A7: 4 | B7: RAHEEM USMAN AYIGORO | C7: 1095306.8 | D7: 12 | E7: =C7*D7 -> 13143681 | G7: 869094.48 | I7: =E7-F7-G7-H7 -> 12274587 | J7: 200000 | K7: 0.2 | L7: =I7*K7 -> 2454917.3 | M7: =J7+L7 -> 2654917.3 | N7: =F7+G7+H7+M7 -> 3524011.8 | O7: =E7-N7 -> 9619669.2 | P7: =IF(O7<300000,0.07*O7,21000) -> 21000 | Q7: =IF((O7-300000)<0,0,IF((O7-300000)<300000,0.11*(O7-300000),33000)) -> 33000 | R7: =IF((O7-600000)<0,0,IF((O7-600000)<500000,0.15*(O7-600000),75000)) -> 75000 | S7: =IF((O7-1100000)<0,0,IF((O7-1100000)<500000,0.19*(O7-1100000),95000)) -> 95000 | T7: =IF((O7-1600000)<0,0,IF((O7-1600000)<1600000,0.21*(O7-1600000),336000)) -> 336000 | U7: =24%*(O7-3200000) -> 1540720.6 | V7: =P7+Q7+R7+S7+T7+U7 -> 2100720.6 | W7: 12 | X7: =V7/W7 -> 175060.05 | Z7: =X7 -> 175060.05 | AA7: 149812.26 | AB7: =Z7-AA7 -> 25247.788
A8: 5 | B8: MARIAM MOHAMMED BELLO | C8: 1295306.8 | D8: 12 | E8: =C8*D8 -> 15543681 | G8: 0 | I8: =E8-F8-G8-H8 -> 15543681 | J8: 200000 | K8: 0.2 | L8: =I8*K8 -> 3108736.2 | M8: =J8+L8 -> 3308736.2 | N8: =F8+G8+H8+M8 -> 3308736.2 | O8: =E8-N8 -> 12234945 | P8: =IF(O8<300000,0.07*O8,21000) -> 21000 | Q8: =IF((O8-300000)<0,0,IF((O8-300000)<300000,0.11*(O8-300000),33000)) -> 33000 | R8: =IF((O8-600000)<0,0,IF((O8-600000)<500000,0.15*(O8-600000),75000)) -> 75000 | S8: =IF((O8-1100000)<0,0,IF((O8-1100000)<500000,0.19*(O8-1100000),95000)) -> 95000 | T8: =IF((O8-1600000)<0,0,IF((O8-1600000)<1600000,0.21*(O8-1600000),336000)) -> 336000 | U8: =24%*(O8-3200000) -> 2168386.8 | V8: =P8+Q8+R8+S8+T8+U8 -> 2728386.8 | W8: 12 | X8: =V8/W8 -> 227365.56 | Z8: =X8 -> 227365.56 | AA8: 199922.31 | AB8: =Z8-AA8 -> 27443.248
A9: 6 | B9: DR IKEME ARTHUR J.O | C9: 1085306.8 | D9: 12 | E9: =C9*D9 -> 13023681 | F9: 166400.85 | G9: 869094.48 | I9: =E9-F9-G9-H9 -> 11988186 | J9: 200000 | K9: 0.2 | L9: =I9*K9 -> 2397637.1 | M9: =J9+L9 -> 2597637.1 | N9: =F9+G9+H9+M9 -> 3633132.5 | O9: =E9-N9 -> 9390548.5 | P9: =IF(O9<300000,0.07*O9,21000) -> 21000 | Q9: =IF((O9-300000)<0,0,IF((O9-300000)<300000,0.11*(O9-300000),33000)) -> 33000 | R9: =IF((O9-600000)<0,0,IF((O9-600000)<500000,0.15*(O9-600000),75000)) -> 75000 | S9: =IF((O9-1100000)<0,0,IF((O9-1100000)<500000,0.19*(O9-1100000),95000)) -> 95000 | T9: =IF((O9-1600000)<0,0,IF((O9-1600000)<1600000,0.21*(O9-1600000),336000)) -> 336000 | U9: =24%*(O9-3200000) -> 1485731.6 | V9: =P9+Q9+R9+S9+T9+U9 -> 2045731.6 | W9: 12 | X9: =V9/W9 -> 170477.64 | Z9: =X9 -> 170477.64 | AA9: 147687.53 | AB9: =Z9-AA9 -> 22790.11
A10: 7 | B10: ANDRAWUS MUSA | C10: 1019008.9 | D10: 12 | E10: =C10*D10 -> 12228107 | F10: 157015.95 | G10: 818602.64 | I10: =E10-F10-G10-H10 -> 11252488 | J10: 200000 | K10: 0.2 | L10: =I10*K10 -> 2250497.7 | M10: =J10+L10 -> 2450497.7 | N10: =F10+G10+H10+M10 -> 3426116.3 | O10: =E10-N10 -> 8801990.7 | P10: =IF(O10<300000,0.07*O10,21000) -> 21000 | Q10: =IF((O10-300000)<0,0,IF((O10-300000)<300000,0.11*(O10-300000),33000)) -> 33000 | R10: =IF((O10-600000)<0,0,IF((O10-600000)<500000,0.15*(O10-600000),75000)) -> 75000 | S10: =IF((O10-1100000)<0,0,IF((O10-1100000)<500000,0.19*(O10-1100000),95000)) -> 95000 | T10: =IF((O10-1600000)<0,0,IF((O10-1600000)<1600000,0.21*(O10-1600000),336000)) -> 336000 | U10: =24%*(O10-3200000) -> 1344477.8 | V10: =P10+Q10+R10+S10+T10+U10 -> 1904477.8 | W10: 12 | X10: =V10/W10 -> 158706.48 | Z10: =X10 -> 158706.48 | AA10: 129694.7 | AB10: =Z10-AA10 -> 29011.786
A11: 8 | B11: DR FRANCIS NDUM OJIE | C11: 1082595.5 | D11: 12 | E11: =C11*D11 -> 12991146 | F11: 133798.75 | G11: 693691.68 | I11: =E11-F11-G11-H11 -> 12163656 | J11: 200000 | K11: 0.2 | L11: =I11*K11 -> 2432731.1 | M11: =J11+L11 -> 2632731.1 | N11: =F11+G11+H11+M11 -> 3460221.5 | O11: =E11-N11 -> 9530924.5 | P11: =IF(O11<300000,0.07*O11,21000) -> 21000 | Q11: =IF((O11-300000)<0,0,IF((O11-300000)<300000,0.11*(O11-300000),33000)) -> 33000 | R11: =IF((O11-600000)<0,0,IF((O11-600000)<500000,0.15*(O11-600000),75000)) -> 75000 | S11: =IF((O11-1100000)<0,0,IF((O11-1100000)<500000,0.19*(O11-1100000),95000)) -> 95000 | T11: =IF((O11-1600000)<0,0,IF((O11-1600000)<1600000,0.21*(O11-1600000),336000)) -> 336000 | U11: =24%*(O11-3200000) -> 1519421.9 | V11: =P11+Q11+R11+S11+T11+U11 -> 2079421.9 | W11: 12 | X11: =V11/W11 -> 173285.16 | Z11: =X11 -> 173285.16 | AA11: 150463.11 | AB11: =Z11-AA11 -> 22822.046
A12: 9 | B12: ALI ABDULLAHI | C12: 659657 | D12: 12 | E12: =C12*D12 -> 7915884 | G12: 566070.72 | I12: =E12-F12-G12-H12 -> 7349813.3 | J12: 200000 | K12: 0.2 | L12: =I12*K12 -> 1469962.7 | M12: =J12+L12 -> 1669962.7 | N12: =F12+G12+H12+M12 -> 2236033.4 | O12: =E12-N12 -> 5679850.6 | P12: =IF(O12<300000,0.07*O12,21000) -> 21000 | Q12: =IF((O12-300000)<0,0,IF((O12-300000)<300000,0.11*(O12-300000),33000)) -> 33000 | R12: =IF((O12-600000)<0,0,IF((O12-600000)<500000,0.15*(O12-600000),75000)) -> 75000 | S12: =IF((O12-1100000)<0,0,IF((O12-1100000)<500000,0.19*(O12-1100000),95000)) -> 95000 | T12: =IF((O12-1600000)<0,0,IF((O12-1600000)<1600000,0.21*(O12-1600000),336000)) -> 336000 | U12: =24%*(O12-3200000) -> 595164.15 | V12: =P12+Q12+R12+S12+T12+U12 -> 1155164.1 | W12: 12 | X12: =V12/W12 -> 96263.679 | Z12: =X12 -> 96263.679 | AA12: 77666.446 | AB12: =Z12-AA12 -> 18597.233
A13: 10 | B13: EMILY EKHIDE | C13: 932595.5 | D13: 12 | E13: =C13*D13 -> 11191146 | G13: 693691.68 | I13: =E13-F13-G13-H13 -> 10497454 | J13: 200000 | K13: 0.2 | L13: =I13*K13 -> 2099490.9 | M13: =J13+L13 -> 2299490.9 | N13: =F13+G13+H13+M13 -> 2993182.5 | O13: =E13-N13 -> 8197963.5 | P13: =IF(O13<300000,0.07*O13,21000) -> 21000 | Q13: =IF((O13-300000)<0,0,IF((O13-300000)<300000,0.11*(O13-300000),33000)) -> 33000 | R13: =IF((O13-600000)<0,0,IF((O13-600000)<500000,0.15*(O13-600000),75000)) -> 75000 | S13: =IF((O13-1100000)<0,0,IF((O13-1100000)<500000,0.19*(O13-1100000),95000)) -> 95000 | T13: =IF((O13-1600000)<0,0,IF((O13-1600000)<1600000,0.21*(O13-1600000),336000)) -> 336000 | U13: =24%*(O13-3200000) -> 1199511.2 | V13: =P13+Q13+R13+S13+T13+U13 -> 1759511.2 | W13: 12 | X13: =V13/W13 -> 146625.94 | Z13: =X13 -> 146625.94 | AA13: 141011.99 | AB13: =Z13-AA13 -> 5613.9468
A14: 11 | B14: DORIS DAKDA AARON | C14: 948165.25 | D14: 12 | E14: =C14*D14 -> 11377983 | G14: 535838.64 | I14: =E14-F14-G14-H14 -> 10842144 | J14: 200000 | K14: 0.2 | L14: =I14*K14 -> 2168428.9 | M14: =J14+L14 -> 2368428.9 | N14: =F14+G14+H14+M14 -> 2904267.5 | O14: =E14-N14 -> 8473715.5 | P14: =IF(O14<300000,0.07*O14,21000) -> 21000 | Q14: =IF((O14-300000)<0,0,IF((O14-300000)<300000,0.11*(O14-300000),33000)) -> 33000 | R14: =IF((O14-600000)<0,0,IF((O14-600000)<500000,0.15*(O14-600000),75000)) -> 75000 | S14: =IF((O14-1100000)<0,0,IF((O14-1100000)<500000,0.19*(O14-1100000),95000)) -> 95000 | T14: =IF((O14-1600000)<0,0,IF((O14-1600000)<1600000,0.21*(O14-1600000),336000)) -> 336000 | U14: =24%*(O14-3200000) -> 1265691.7 | V14: =P14+Q14+R14+S14+T14+U14 -> 1825691.7 | W14: 12 | X14: =V14/W14 -> 152140.98 | Z14: =X14 -> 152140.98 | AA14: 131753.41 | AB14: =Z14-AA14 -> 20387.568
A15: 12 | B15: ABDULSALAM S. MUSTAPHA | C15: 830713.92 | D15: 12 | E15: =C15*D15 -> 9968567 | G15: 672685.36 | I15: =E15-F15-G15-H15 -> 9295881.6 | J15: 200000 | K15: 0.2 | L15: =I15*K15 -> 1859176.3 | M15: =J15+L15 -> 2059176.3 | N15: =F15+G15+H15+M15 -> 2731861.7 | O15: =E15-N15 -> 7236705.3 | P15: =IF(O15<300000,0.07*O15,21000) -> 21000 | Q15: =IF((O15-300000)<0,0,IF((O15-300000)<300000,0.11*(O15-300000),33000)) -> 33000 | R15: =IF((O15-600000)<0,0,IF((O15-600000)<500000,0.15*(O15-600000),75000)) -> 75000 | S15: =IF((O15-1100000)<0,0,IF((O15-1100000)<500000,0.19*(O15-1100000),95000)) -> 95000 | T15: =IF((O15-1600000)<0,0,IF((O15-1600000)<1600000,0.21*(O15-1600000),336000)) -> 336000 | U15: =24%*(O15-3200000) -> 968809.27 | V15: =P15+Q15+R15+S15+T15+U15 -> 1528809.3 | W15: 12 | X15: =V15/W15 -> 127400.77 | Z15: =X15 -> 127400.77 | AA15: 106452 | AB15: =Z15-AA15 -> 20948.773
A16: 13 | B16: PERCY TERFA GBAHABO | C16: 661351.33 | D16: 12 | E16: =C16*D16 -> 7936216 | G16: 519697.28 | I16: =E16-F16-G16-H16 -> 7416518.7 | J16: 200000 | K16: 0.2 | L16: =I16*K16 -> 1483303.7 | M16: =J16+L16 -> 1683303.7 | N16: =F16+G16+H16+M16 -> 2203001 | O16: =E16-N16 -> 5733215 | P16: =IF(O16<300000,0.07*O16,21000) -> 21000 | Q16: =IF((O16-300000)<0,0,IF((O16-300000)<300000,0.11*(O16-300000),33000)) -> 33000 | R16: =IF((O16-600000)<0,0,IF((O16-600000)<500000,0.15*(O16-600000),75000)) -> 75000 | S16: =IF((O16-1100000)<0,0,IF((O16-1100000)<500000,0.19*(O16-1100000),95000)) -> 95000 | T16: =IF((O16-1600000)<0,0,IF((O16-1600000)<1600000,0.21*(O16-1600000),336000)) -> 336000 | U16: =24%*(O16-3200000) -> 607971.59 | V16: =P16+Q16+R16+S16+T16+U16 -> 1167971.6 | W16: 12 | X16: =V16/W16 -> 97330.966 | Z16: =X16 -> 97330.966 | AA16: 77470.374 | AB16: =Z16-AA16 -> 19860.592
A17: 14 | B17: HASSANA AHMED IBRAHIM | C17: 846725.08 | D17: 12 | E17: =C17*D17 -> 10160701 | F17: 98713.475 | G17: 505656.08 | I17: =E17-F17-G17-H17 -> 9556331.4 | J17: 200000 | K17: 0.2 | L17: =I17*K17 -> 1911266.3 | M17: =J17+L17 -> 2111266.3 | N17: =F17+G17+H17+M17 -> 2715635.8 | O17: =E17-N17 -> 7445065.2 | P17: =IF(O17<300000,0.07*O17,21000) -> 21000 | Q17: =IF((O17-300000)<0,0,IF((O17-300000)<300000,0.11*(O17-300000),33000)) -> 33000 | R17: =IF((O17-600000)<0,0,IF((O17-600000)<500000,0.15*(O17-600000),75000)) -> 75000 | S17: =IF((O17-1100000)<0,0,IF((O17-1100000)<500000,0.19*(O17-1100000),95000)) -> 95000 | T17: =IF((O17-1600000)<0,0,IF((O17-1600000)<1600000,0.21*(O17-1600000),336000)) -> 336000 | U17: =24%*(O17-3200000) -> 1018815.6 | V17: =P17+Q17+R17+S17+T17+U17 -> 1578815.6 | W17: 12 | X17: =V17/W17 -> 131567.97 | Z17: =X17 -> 131567.97 | AA17: 113474.9 | AB17: =Z17-AA17 -> 18093.066
A18: 15 | B18: IKIP LEBO | C18: 567472.75 | D18: 12 | E18: =C18*D18 -> 6809673 | F18: 93501.975 | G18: 477573.84 | I18: =E18-F18-G18-H18 -> 6238597.2 | J18: 200000 | K18: 0.2 | L18: =I18*K18 -> 1247719.4 | M18: =J18+L18 -> 1447719.4 | N18: =F18+G18+H18+M18 -> 2018795.3 | O18: =E18-N18 -> 4790877.7 | P18: =IF(O18<300000,0.07*O18,21000) -> 21000 | Q18: =IF((O18-300000)<0,0,IF((O18-300000)<300000,0.11*(O18-300000),33000)) -> 33000 | R18: =IF((O18-600000)<0,0,IF((O18-600000)<500000,0.15*(O18-600000),75000)) -> 75000 | S18: =IF((O18-1100000)<0,0,IF((O18-1100000)<500000,0.19*(O18-1100000),95000)) -> 95000 | T18: =IF((O18-1600000)<0,0,IF((O18-1600000)<1600000,0.21*(O18-1600000),336000)) -> 336000 | U18: =24%*(O18-3200000) -> 381810.66 | V18: =P18+Q18+R18+S18+T18+U18 -> 941810.66 | W18: 12 | X18: =V18/W18 -> 78484.222 | Z18: =X18 -> 78484.222 | AA18: 61040.235 | AB18: =Z18-AA18 -> 17443.986
A19: 16 | B19: ALABI ADESINA MUHYDEEN | C19: 617472.75 | D19: 12 | E19: =C19*D19 -> 7409673 | F19: 0 | G19: 477573.84 | I19: =E19-F19-G19-H19 -> 6932099.2 | J19: 200000 | K19: 0.2 | L19: =I19*K19 -> 1386419.8 | M19: =J19+L19 -> 1586419.8 | N19: =F19+G19+H19+M19 -> 2063993.7 | O19: =E19-N19 -> 5345679.3 | P19: =IF(O19<300000,0.07*O19,21000) -> 21000 | Q19: =IF((O19-300000)<0,0,IF((O19-300000)<300000,0.11*(O19-300000),33000)) -> 33000 | R19: =IF((O19-600000)<0,0,IF((O19-600000)<500000,0.15*(O19-600000),75000)) -> 75000 | S19: =IF((O19-1100000)<0,0,IF((O19-1100000)<500000,0.19*(O19-1100000),95000)) -> 95000 | T19: =IF((O19-1600000)<0,0,IF((O19-1600000)<1600000,0.21*(O19-1600000),336000)) -> 336000 | U19: =24%*(O19-3200000) -> 514963.04 | V19: =P19+Q19+R19+S19+T19+U19 -> 1074963 | W19: 12 | X19: =V19/W19 -> 89580.253 | Z19: =X19 -> 89580.253 | AA19: 70640.235 | AB19: =Z19-AA19 -> 18940.018
A20: 17 | B20: BASSEY NSONGURUA UDOFIA | C20: 806497.17 | D20: 12 | E20: =C20*D20 -> 9677966 | F20: 93328.325 | G20: 476637.28 | I20: =E20-F20-G20-H20 -> 9108000.4 | J20: 200000 | K20: 0.2 | L20: =I20*K20 -> 1821600.1 | M20: =J20+L20 -> 2021600.1 | N20: =F20+G20+H20+M20 -> 2591565.7 | O20: =E20-N20 -> 7086400.3 | P20: =IF(O20<300000,0.07*O20,21000) -> 21000 | Q20: =IF((O20-300000)<0,0,IF((O20-300000)<300000,0.11*(O20-300000),33000)) -> 33000 | R20: =IF((O20-600000)<0,0,IF((O20-600000)<500000,0.15*(O20-600000),75000)) -> 75000 | S20: =IF((O20-1100000)<0,0,IF((O20-1100000)<500000,0.19*(O20-1100000),95000)) -> 95000 | T20: =IF((O20-1600000)<0,0,IF((O20-1600000)<1600000,0.21*(O20-1600000),336000)) -> 336000 | U20: =24%*(O20-3200000) -> 932736.08 | V20: =P20+Q20+R20+S20+T20+U20 -> 1492736.1 | W20: 12 | X20: =V20/W20 -> 124394.67 | Z20: =X20 -> 124394.67 | AA20: 106297.15 | AB20: =Z20-AA20 -> 18097.523
A21: 18 | B21: ADUGBA RICHARD TERSEER | C21: 692662.67 | D21: 12 | E21: =C21*D21 -> 8311952 | G21: 463356.16 | I21: =E21-F21-G21-H21 -> 7848595.8 | J21: 200000 | K21: 0.2 | L21: =I21*K21 -> 1569719.2 | M21: =J21+L21 -> 1769719.2 | N21: =F21+G21+H21+M21 -> 2233075.3 | O21: =E21-N21 -> 6078876.7 | P21: =IF(O21<300000,0.07*O21,21000) -> 21000 | Q21: =IF((O21-300000)<0,0,IF((O21-300000)<300000,0.11*(O21-300000),33000)) -> 33000 | R21: =IF((O21-600000)<0,0,IF((O21-600000)<500000,0.15*(O21-600000),75000)) -> 75000 | S21: =IF((O21-1100000)<0,0,IF((O21-1100000)<500000,0.19*(O21-1100000),95000)) -> 95000 | T21: =IF((O21-1600000)<0,0,IF((O21-1600000)<1600000,0.21*(O21-1600000),336000)) -> 336000 | U21: =24%*(O21-3200000) -> 690930.4 | V21: =P21+Q21+R21+S21+T21+U21 -> 1250930.4 | W21: 12 | X21: =V21/W21 -> 104244.2 | Z21: =X21 -> 104244.2 | AA21: 82601.205 | AB21: =Z21-AA21 -> 21642.995
A22: 19 | B22: LUCKY AGWOM | C22: 754993.58 | D22: 12 | E22: =C22*D22 -> 9059923 | G22: 436793.84 | I22: =E22-F22-G22-H22 -> 8623129.2 | J22: 200000 | K22: 0.2 | L22: =I22*K22 -> 1724625.8 | M22: =J22+L22 -> 1924625.8 | N22: =F22+G22+H22+M22 -> 2361419.7 | O22: =E22-N22 -> 6698503.3 | P22: =IF(O22<300000,0.07*O22,21000) -> 21000 | Q22: =IF((O22-300000)<0,0,IF((O22-300000)<300000,0.11*(O22-300000),33000)) -> 33000 | R22: =IF((O22-600000)<0,0,IF((O22-600000)<500000,0.15*(O22-600000),75000)) -> 75000 | S22: =IF((O22-1100000)<0,0,IF((O22-1100000)<500000,0.19*(O22-1100000),95000)) -> 95000 | T22: =IF((O22-1600000)<0,0,IF((O22-1600000)<1600000,0.21*(O22-1600000),336000)) -> 336000 | U22: =24%*(O22-3200000) -> 839640.8 | V22: =P22+Q22+R22+S22+T22+U22 -> 1399640.8 | W22: 12 | X22: =V22/W22 -> 116636.73 | Z22: =X22 -> 116636.73 | AA22: 98711.115 | AB22: =Z22-AA22 -> 17925.619
A23: 20 | B23: IDRIS IBRAHIM | C23: 564993.58 | D23: 12 | E23: =C23*D23 -> 6779923 | G23: 436793.84 | I23: =E23-F23-G23-H23 -> 6343129.2 | J23: 200000 | K23: 0.2 | L23: =I23*K23 -> 1268625.8 | M23: =J23+L23 -> 1468625.8 | N23: =F23+G23+H23+M23 -> 1905419.7 | O23: =E23-N23 -> 4874503.3 | P23: =IF(O23<300000,0.07*O23,21000) -> 21000 | Q23: =IF((O23-300000)<0,0,IF((O23-300000)<300000,0.11*(O23-300000),33000)) -> 33000 | R23: =IF((O23-600000)<0,0,IF((O23-600000)<500000,0.15*(O23-600000),75000)) -> 75000 | S23: =IF((O23-1100000)<0,0,IF((O23-1100000)<500000,0.19*(O23-1100000),95000)) -> 95000 | T23: =IF((O23-1600000)<0,0,IF((O23-1600000)<1600000,0.21*(O23-1600000),336000)) -> 336000 | U23: =24%*(O23-3200000) -> 401880.8 | V23: =P23+Q23+R23+S23+T23+U23 -> 961880.8 | W23: 12 | X23: =V23/W23 -> 80156.733 | Z23: =X23 -> 80156.733 | AA23: 62231.115 | AB23: =Z23-AA23 -> 17925.619
A24: 21 | B24: FARUQ ATOFARATI | C24: 641140.67 | D24: 12 | E24: =C24*D24 -> 7693688 | G24: 365895.04 | I24: =E24-F24-G24-H24 -> 7327793 | J24: 200000 | K24: 0.2 | L24: =I24*K24 -> 1465558.6 | M24: =J24+L24 -> 1665558.6 | N24: =F24+G24+H24+M24 -> 2031453.6 | O24: =E24-N24 -> 5662234.4 | P24: =IF(O24<300000,0.07*O24,21000) -> 21000 | Q24: =IF((O24-300000)<0,0,IF((O24-300000)<300000,0.11*(O24-300000),33000)) -> 33000 | R24: =IF((O24-600000)<0,0,IF((O24-600000)<500000,0.15*(O24-600000),75000)) -> 75000 | S24: =IF((O24-1100000)<0,0,IF((O24-1100000)<500000,0.19*(O24-1100000),95000)) -> 95000 | T24: =IF((O24-1600000)<0,0,IF((O24-1600000)<1600000,0.21*(O24-1600000),336000)) -> 336000 | U24: =24%*(O24-3200000) -> 590936.25 | V24: =P24+Q24+R24+S24+T24+U24 -> 1150936.2 | W24: 12 | X24: =V24/W24 -> 95911.354 | Z24: =X24 -> 95911.354 | AA24: 80347.427 | AB24: =Z24-AA24 -> 15563.927
A25: 22 | B25: RASHEEDAT DAIBU | C25: 441140.67 | D25: 12 | E25: =C25*D25 -> 5293688 | G25: 365895.04 | I25: =E25-F25-G25-H25 -> 4927793 | J25: 200000 | K25: 0.2 | L25: =I25*K25 -> 985558.59 | M25: =J25+L25 -> 1185558.6 | N25: =F25+G25+H25+M25 -> 1551453.6 | O25: =E25-N25 -> 3742234.4 | P25: =IF(O25<300000,0.07*O25,21000) -> 21000 | Q25: =IF((O25-300000)<0,0,IF((O25-300000)<300000,0.11*(O25-300000),33000)) -> 33000 | R25: =IF((O25-600000)<0,0,IF((O25-600000)<500000,0.15*(O25-600000),75000)) -> 75000 | S25: =IF((O25-1100000)<0,0,IF((O25-1100000)<500000,0.19*(O25-1100000),95000)) -> 95000 | T25: =IF((O25-1600000)<0,0,IF((O25-1600000)<1600000,0.21*(O25-1600000),336000)) -> 336000 | U25: =24%*(O25-3200000) -> 130136.25 | V25: =P25+Q25+R25+S25+T25+U25 -> 690136.25 | W25: 12 | X25: =V25/W25 -> 57511.354 | Z25: =X25 -> 57511.354 | AA25: 42537.332 | AB25: =Z25-AA25 -> 14974.022
A26: 23 | B26: ELIZABETH OGECHUKWU ONYEAKU | C26: 415320.67 | D26: 12 | E26: =C26*D26 -> 4983848 | G26: 341107.84 | I26: =E26-F26-G26-H26 -> 4642740.2 | J26: 200000 | K26: 0.2 | L26: =I26*K26 -> 928548.03 | M26: =J26+L26 -> 1128548 | N26: =F26+G26+H26+M26 -> 1469655.9 | O26: =E26-N26 -> 3514192.1 | P26: =IF(O26<300000,0.07*O26,21000) -> 21000 | Q26: =IF((O26-300000)<0,0,IF((O26-300000)<300000,0.11*(O26-300000),33000)) -> 33000 | R26: =IF((O26-600000)<0,0,IF((O26-600000)<500000,0.15*(O26-600000),75000)) -> 75000 | S26: =IF((O26-1100000)<0,0,IF((O26-1100000)<500000,0.19*(O26-1100000),95000)) -> 95000 | T26: =IF((O26-1600000)<0,0,IF((O26-1600000)<1600000,0.21*(O26-1600000),336000)) -> 336000 | U26: =24%*(O26-3200000) -> 75406.111 | V26: =P26+Q26+R26+S26+T26+U26 -> 635406.11 | W26: 12 | X26: =V26/W26 -> 52950.509 | Z26: =X26 -> 52950.509 | AA26: 39052.313 | AB26: =Z26-AA26 -> 13898.196
A27: 24 | B27: VICTOR ASUKWO | C27: 415320.67 | D27: 12 | E27: =C27*D27 -> 4983848 | G27: 341107.84 | I27: =E27-F27-G27-H27 -> 4642740.2 | J27: 200000 | K27: 0.2 | L27: =I27*K27 -> 928548.03 | M27: =J27+L27 -> 1128548 | N27: =F27+G27+H27+M27 -> 1469655.9 | O27: =E27-N27 -> 3514192.1 | P27: =IF(O27<300000,0.07*O27,21000) -> 21000 | Q27: =IF((O27-300000)<0,0,IF((O27-300000)<300000,0.11*(O27-300000),33000)) -> 33000 | R27: =IF((O27-600000)<0,0,IF((O27-600000)<500000,0.15*(O27-600000),75000)) -> 75000 | S27: =IF((O27-1100000)<0,0,IF((O27-1100000)<500000,0.19*(O27-1100000),95000)) -> 95000 | T27: =IF((O27-1600000)<0,0,IF((O27-1600000)<1600000,0.21*(O27-1600000),336000)) -> 336000 | U27: =24%*(O27-3200000) -> 75406.111 | V27: =P27+Q27+R27+S27+T27+U27 -> 635406.11 | W27: 12 | X27: =V27/W27 -> 52950.509 | Z27: =X27 -> 52950.509 | AA27: 39052.313 | AB27: =Z27-AA27 -> 13898.196
A28: 25 | B28: NNANDI LIVINUS ATURE | C28: 455320.67 | D28: 12 | E28: =C28*D28 -> 5463848 | G28: 341107.84 | I28: =E28-F28-G28-H28 -> 5122740.2 | J28: 200000 | K28: 0.2 | L28: =I28*K28 -> 1024548 | M28: =J28+L28 -> 1224548 | N28: =F28+G28+H28+M28 -> 1565655.9 | O28: =E28-N28 -> 3898192.1 | P28: =IF(O28<300000,0.07*O28,21000) -> 21000 | Q28: =IF((O28-300000)<0,0,IF((O28-300000)<300000,0.11*(O28-300000),33000)) -> 33000 | R28: =IF((O28-600000)<0,0,IF((O28-600000)<500000,0.15*(O28-600000),75000)) -> 75000 | S28: =IF((O28-1100000)<0,0,IF((O28-1100000)<500000,0.19*(O28-1100000),95000)) -> 95000 | T28: =IF((O28-1600000)<0,0,IF((O28-1600000)<1600000,0.21*(O28-1600000),336000)) -> 336000 | U28: =24%*(O28-3200000) -> 167566.11 | V28: =P28+Q28+R28+S28+T28+U28 -> 727566.11 | W28: 12 | X28: =V28/W28 -> 60630.509 | Z28: =X28 -> 60630.509 | AA28: 45772.313 | AB28: =Z28-AA28 -> 14858.196
A29: 26 | B29: ABDULRAHMAN A SULAIMAN | C29: 407016.17 | D29: 12 | E29: =C29*D29 -> 4884194 | G29: 333135.52 | I29: =E29-F29-G29-H29 -> 4551058.5 | J29: 200000 | K29: 0.2 | L29: =I29*K29 -> 910211.7 | M29: =J29+L29 -> 1110211.7 | N29: =F29+G29+H29+M29 -> 1443347.2 | O29: =E29-N29 -> 3440846.8 | P29: =IF(O29<300000,0.07*O29,21000) -> 21000 | Q29: =IF((O29-300000)<0,0,IF((O29-300000)<300000,0.11*(O29-300000),33000)) -> 33000 | R29: =IF((O29-600000)<0,0,IF((O29-600000)<500000,0.15*(O29-600000),75000)) -> 75000 | S29: =IF((O29-1100000)<0,0,IF((O29-1100000)<500000,0.19*(O29-1100000),95000)) -> 95000 | T29: =IF((O29-1600000)<0,0,IF((O29-1600000)<1600000,0.21*(O29-1600000),336000)) -> 336000 | U29: =24%*(O29-3200000) -> 57803.228 | V29: =P29+Q29+R29+S29+T29+U29 -> 617803.23 | W29: 12 | X29: =V29/W29 -> 51483.602 | Z29: =X29 -> 51483.602 | AA29: 37921.501 | AB29: =Z29-AA29 -> 13562.102
A30: 27 | B30: DARE SHEU MAGBON | C30: 398711.67 | D30: 12 | E30: =C30*D30 -> 4784540 | G30: 325163.2 | I30: =E30-F30-G30-H30 -> 4459376.8 | J30: 200000 | K30: 0.2 | L30: =I30*K30 -> 891875.36 | M30: =J30+L30 -> 1091875.4 | N30: =F30+G30+H30+M30 -> 1417038.6 | O30: =E30-N30 -> 3367501.4 | P30: =IF(O30<300000,0.07*O30,21000) -> 21000 | Q30: =IF((O30-300000)<0,0,IF((O30-300000)<300000,0.11*(O30-300000),33000)) -> 33000 | R30: =IF((O30-600000)<0,0,IF((O30-600000)<500000,0.15*(O30-600000),75000)) -> 75000 | S30: =IF((O30-1100000)<0,0,IF((O30-1100000)<500000,0.19*(O30-1100000),95000)) -> 95000 | T30: =IF((O30-1600000)<0,0,IF((O30-1600000)<1600000,0.21*(O30-1600000),336000)) -> 336000 | U30: =24%*(O30-3200000) -> 40200.346 | V30: =P30+Q30+R30+S30+T30+U30 -> 600200.35 | W30: 12 | X30: =V30/W30 -> 50016.695 | Z30: =X30 -> 50016.695 | AA30: 36790.688 | AB30: =Z30-AA30 -> 13226.007
A31: 28 | B31: ABUBAKAR SULAIMAN SODEEQ | C31: 398711.67 | D31: 12 | E31: =C31*D31 -> 4784540 | G31: 325163.2 | I31: =E31-F31-G31-H31 -> 4459376.8 | J31: 200000 | K31: 0.2 | L31: =I31*K31 -> 891875.36 | M31: =J31+L31 -> 1091875.4 | N31: =F31+G31+H31+M31 -> 1417038.6 | O31: =E31-N31 -> 3367501.4 | P31: =IF(O31<300000,0.07*O31,21000) -> 21000 | Q31: =IF((O31-300000)<0,0,IF((O31-300000)<300000,0.11*(O31-300000),33000)) -> 33000 | R31: =IF((O31-600000)<0,0,IF((O31-600000)<500000,0.15*(O31-600000),75000)) -> 75000 | S31: =IF((O31-1100000)<0,0,IF((O31-1100000)<500000,0.19*(O31-1100000),95000)) -> 95000 | T31: =IF((O31-1600000)<0,0,IF((O31-1600000)<1600000,0.21*(O31-1600000),336000)) -> 336000 | U31: =24%*(O31-3200000) -> 40200.346 | V31: =P31+Q31+R31+S31+T31+U31 -> 600200.35 | W31: 12 | X31: =V31/W31 -> 50016.695 | Z31: =X31 -> 50016.695 | AA31: 36790.688 | AB31: =Z31-AA31 -> 13226.007
A32: 29 | B32: JIMOH ADEBAYO ZAKA | C32: 415320.67 | D32: 12 | E32: =C32*D32 -> 4983848 | G32: 341107.84 | I32: =E32-F32-G32-H32 -> 4642740.2 | J32: 200000 | K32: 0.2 | L32: =I32*K32 -> 928548.03 | M32: =J32+L32 -> 1128548 | N32: =F32+G32+H32+M32 -> 1469655.9 | O32: =E32-N32 -> 3514192.1 | P32: =IF(O32<300000,0.07*O32,21000) -> 21000 | Q32: =IF((O32-300000)<0,0,IF((O32-300000)<300000,0.11*(O32-300000),33000)) -> 33000 | R32: =IF((O32-600000)<0,0,IF((O32-600000)<500000,0.15*(O32-600000),75000)) -> 75000 | S32: =IF((O32-1100000)<0,0,IF((O32-1100000)<500000,0.19*(O32-1100000),95000)) -> 95000 | T32: =IF((O32-1600000)<0,0,IF((O32-1600000)<1600000,0.21*(O32-1600000),336000)) -> 336000 | U32: =24%*(O32-3200000) -> 75406.111 | V32: =P32+Q32+R32+S32+T32+U32 -> 635406.11 | W32: 12 | X32: =V32/W32 -> 52950.509 | Z32: =X32 -> 52950.509 | AA32: 39052.313 | AB32: =Z32-AA32 -> 13898.196
... A34: 32 | B34: MOHAMMED BELLO | C34: 398711.67 | D34: 12 | E34: =C34*D34 -> 4784540 | G34: 341107.84 | I34: =E34-F34-G34-H34 -> 4443432.2 | J34: 200000 | K34: 0.2 | L34: =I34*K34 -> 888686.43 | M34: =J34+L34 -> 1088686.4 | N34: =F34+G34+H34+M34 -> 1429794.3 | O34: =E34-N34 -> 3354745.7 | P34: =IF(O34<300000,0.07*O34,21000) -> 21000 | Q34: =IF((O34-300000)<0,0,IF((O34-300000)<300000,0.11*(O34-300000),33000)) -> 33000 | R34: =IF((O34-600000)<0,0,IF((O34-600000)<500000,0.15*(O34-600000),75000)) -> 75000 | S34: =IF((O34-1100000)<0,0,IF((O34-1100000)<500000,0.19*(O34-1100000),95000)) -> 95000 | T34: =IF((O34-1600000)<0,0,IF((O34-1600000)<1600000,0.21*(O34-1600000),336000)) -> 336000 | U34: =24%*(O34-3200000) -> 37138.975 | V34: =P34+Q34+R34+S34+T34+U34 -> 597138.97 | W34: 12 | X34: =V34/W34 -> 49761.581 | Z34: =X34 -> 49761.581 | AA34: 36790.688 | AB34: =Z34-AA34 -> 12970.893
A35: 33 | B35: HARUNA JIBRIL AMEH | C35: 351910.75 | D35: 12 | E35: =C35*D35 -> 4222929 | G35: 289834.32 | I35: =E35-F35-G35-H35 -> 3933094.7 | J35: 200000 | K35: 0.2 | L35: =I35*K35 -> 786618.94 | M35: =J35+L35 -> 986618.94 | N35: =F35+G35+H35+M35 -> 1276453.3 | O35: =E35-N35 -> 2946475.7 | P35: =IF(O35<300000,0.07*O35,21000) -> 21000 | Q35: =IF((O35-300000)<0,0,IF((O35-300000)<300000,0.11*(O35-300000),33000)) -> 33000 | R35: =IF((O35-600000)<0,0,IF((O35-600000)<500000,0.15*(O35-600000),75000)) -> 75000 | S35: =IF((O35-1100000)<0,0,IF((O35-1100000)<500000,0.19*(O35-1100000),95000)) -> 95000 | T35: =IF((O35-1600000)<0,0,IF((O35-1600000)<1600000,0.21*(O35-1600000),336000)) -> 282759.91 | V35: =P35+Q35+R35+S35+T35+U35 -> 506759.91 | W35: 12 | X35: =V35/W35 -> 42229.992 | Z35: =X35 -> 42229.992 | AA35: 30259.166 | AB35: =Z35-AA35 -> 11970.827
A36: 34 | B36: RAMATU IBRAHIM ABDULRAHEEM | C36: 344900.83 | D36: 12 | E36: =C36*D36 -> 4138810 | G36: 283104.8 | I36: =E36-F36-G36-H36 -> 3855705.2 | J36: 200000 | K36: 0.2 | L36: =I36*K36 -> 771141.04 | M36: =J36+L36 -> 971141.04 | N36: =F36+G36+H36+M36 -> 1254245.8 | O36: =E36-N36 -> 2884564.2 | P36: =IF(O36<300000,0.07*O36,21000) -> 21000 | Q36: =IF((O36-300000)<0,0,IF((O36-300000)<300000,0.11*(O36-300000),33000)) -> 33000 | R36: =IF((O36-600000)<0,0,IF((O36-600000)<500000,0.15*(O36-600000),75000)) -> 75000 | S36: =IF((O36-1100000)<0,0,IF((O36-1100000)<500000,0.19*(O36-1100000),95000)) -> 95000 | T36: =IF((O36-1600000)<0,0,IF((O36-1600000)<1600000,0.21*(O36-1600000),336000)) -> 269758.47 | V36: =P36+Q36+R36+S36+T36+U36 -> 493758.47 | W36: 12 | X36: =V36/W36 -> 41146.539 | Z36: =X36 -> 41146.539 | AA36: 29305.196 | AB36: =Z36-AA36 -> 11841.344
B38: INTERNAL AUDIT
B39: OSANAIYE DAVID AKINYEMI | C39: 1847106.4 | D39: 12 | E39: =C39*D39 -> 22165277 | G39: 1677222.2 | I39: =E39-F39-G39-H39 -> 20488055 | J39: 200000 | K39: 0.2 | L39: =I39*K39 -> 4097611 | M39: =J39+L39 -> 4297611 | N39: =F39+G39+H39+M39 -> 5974833.1 | O39: =E39-N39 -> 16190444 | P39: =IF(O39<300000,0.07*O39,21000) -> 21000 | Q39: =IF((O39-300000)<0,0,IF((O39-300000)<300000,0.11*(O39-300000),33000)) -> 33000 | R39: =IF((O39-600000)<0,0,IF((O39-600000)<500000,0.15*(O39-600000),75000)) -> 75000 | S39: =IF((O39-1100000)<0,0,IF((O39-1100000)<500000,0.19*(O39-1100000),95000)) -> 95000 | T39: =IF((O39-1600000)<0,0,IF((O39-1600000)<1600000,0.21*(O39-1600000),336000)) -> 336000 | U39: =24%*(O39-3200000) -> 3117706.5 | V39: =P39+Q39+R39+S39+T39+U39 -> 3677706.5 | W39: 12 | X39: =V39/W39 -> 306475.54 | Z39: =X39 -> 306475.54 | AA39: 251472.25 | AB39: =Z39-AA39 -> 55003.297
B40: JAMILA ABDUL | C40: 441140.67 | D40: 12 | E40: =C40*D40 -> 5293688 | G40: 365895.04 | I40: =E40-F40-G40-H40 -> 4927793 | J40: 200000 | K40: 0.2 | L40: =I40*K40 -> 985558.59 | M40: =J40+L40 -> 1185558.6 | N40: =F40+G40+H40+M40 -> 1551453.6 | O40: =E40-N40 -> 3742234.4 | P40: =IF(O40<300000,0.07*O40,21000) -> 21000 | Q40: =IF((O40-300000)<0,0,IF((O40-300000)<300000,0.11*(O40-300000),33000)) -> 33000 | R40: =IF((O40-600000)<0,0,IF((O40-600000)<500000,0.15*(O40-600000),75000)) -> 75000 | S40: =IF((O40-1100000)<0,0,IF((O40-1100000)<500000,0.19*(O40-1100000),95000)) -> 95000 | T40: =IF((O40-1600000)<0,0,IF((O40-1600000)<1600000,0.21*(O40-1600000),336000)) -> 336000 | U40: =24%*(O40-3200000) -> 130136.25 | V40: =P40+Q40+R40+S40+T40+U40 -> 690136.25 | W40: 12 | X40: =V40/W40 -> 57511.354 | Z40: =X40 -> 57511.354 | AA40: 42537.332 | AB40: =Z40-AA40 -> 14974.022
B41: IJEOMA EWELUKWA | C41: 450135.83 | D41: 12 | E41: =C41*D41 -> 5401630 | G41: 374530.4 | I41: =E41-F41-G41-H41 -> 5027099.6 | J41: 200000 | K41: 0.2 | L41: =I41*K41 -> 1005419.9 | M41: =J41+L41 -> 1205419.9 | N41: =F41+G41+H41+M41 -> 1579950.3 | O41: =E41-N41 -> 3821679.7 | P41: =IF(O41<300000,0.07*O41,21000) -> 21000 | Q41: =IF((O41-300000)<0,0,IF((O41-300000)<300000,0.11*(O41-300000),33000)) -> 33000 | R41: =IF((O41-600000)<0,0,IF((O41-600000)<500000,0.15*(O41-600000),75000)) -> 75000 | S41: =IF((O41-1100000)<0,0,IF((O41-1100000)<500000,0.19*(O41-1100000),95000)) -> 95000 | T41: =IF((O41-1600000)<0,0,IF((O41-1600000)<1600000,0.21*(O41-1600000),336000)) -> 336000 | U41: =24%*(O41-3200000) -> 149203.12 | V41: =P41+Q41+R41+S41+T41+U41 -> 709203.12 | W41: 12 | X41: =V41/W41 -> 59100.26 | Z41: =X41 -> 59100.26 | AA41: 43763.907 | AB41: =Z41-AA41 -> 15336.353
B42: YUSUF YUSUF DAYYABU | C42: 398711.67 | D42: 12 | E42: =C42*D42 -> 4784540 | G42: 325163.2 | I42: =E42-F42-G42-H42 -> 4459376.8 | J42: 200000 | K42: 0.2 | L42: =I42*K42 -> 891875.36 | M42: =J42+L42 -> 1091875.4 | N42: =F42+G42+H42+M42 -> 1417038.6 | O42: =E42-N42 -> 3367501.4 | P42: =IF(O42<300000,0.07*O42,21000) -> 21000 | Q42: =IF((O42-300000)<0,0,IF((O42-300000)<300000,0.11*(O42-300000),33000)) -> 33000 | R42: =IF((O42-600000)<0,0,IF((O42-600000)<500000,0.15*(O42-600000),75000)) -> 75000 | S42: =IF((O42-1100000)<0,0,IF((O42-1100000)<500000,0.19*(O42-1100000),95000)) -> 95000 | T42: =IF((O42-1600000)<0,0,IF((O42-1600000)<1600000,0.21*(O42-1600000),336000)) -> 336000 | U42: =24%*(O42-3200000) -> 40200.346 | V42: =P42+Q42+R42+S42+T42+U42 -> 600200.35 | W42: 12 | X42: =V42/W42 -> 50016.695 | Z42: =X42 -> 50016.695 | AA42: 36790.688 | AB42: =Z42-AA42 -> 13226.007
B44: LEG. SUPPORT SEVICES
A45: 35 | B45: BETHEL UZOMA IHUGBA | C45: 1847612 | D45: 12 | E45: =C45*D45 -> 22171344 | G45: 869094.48 | I45: =E45-F45-G45-H45 -> 21302250 | J45: 200000 | K45: 0.2 | L45: =I45*K45 -> 4260449.9 | M45: =J45+L45 -> 4460449.9 | N45: =F45+G45+H45+M45 -> 5329544.4 | O45: =E45-N45 -> 16841800 | P45: =IF(O45<300000,0.07*O45,21000) -> 21000 | Q45: =IF((O45-300000)<0,0,IF((O45-300000)<300000,0.11*(O45-300000),33000)) -> 33000 | R45: =IF((O45-600000)<0,0,IF((O45-600000)<500000,0.15*(O45-600000),75000)) -> 75000 | S45: =IF((O45-1100000)<0,0,IF((O45-1100000)<500000,0.19*(O45-1100000),95000)) -> 95000 | T45: =IF((O45-1600000)<0,0,IF((O45-1600000)<1600000,0.21*(O45-1600000),336000)) -> 336000 | U45: =0.24*(O45-3200000) -> 3274031.9 | V45: =P45+Q45+R45+S45+T45+U45 -> 3834031.9 | W45: 12 | X45: =V45/W45 -> 319502.66 | Z45: =X45 -> 319502.66 | AA45: 162999.59 | AB45: =Z45-AA45 -> 156503.07
A46: 36 | B46: OGUCHE SAMUEL | C46: 904477 | D46: 12 | E46: =C46*D46 -> 10853724 | G46: 714697.92 | I46: =E46-F46-G46-H46 -> 10139026 | J46: 200000 | K46: 0.2 | L46: =I46*K46 -> 2027805.2 | M46: =J46+L46 -> 2227805.2 | N46: =F46+G46+H46+M46 -> 2942503.1 | O46: =E46-N46 -> 7911220.9 | P46: =IF(O46<300000,0.07*O46,21000) -> 21000 | Q46: =IF((O46-300000)<0,0,IF((O46-300000)<300000,0.11*(O46-300000),33000)) -> 33000 | R46: =IF((O46-600000)<0,0,IF((O46-600000)<500000,0.15*(O46-600000),75000)) -> 75000 | S46: =IF((O46-1100000)<0,0,IF((O46-1100000)<500000,0.19*(O46-1100000),95000)) -> 95000 | T46: =IF((O46-1600000)<0,0,IF((O46-1600000)<1600000,0.21*(O46-1600000),336000)) -> 336000 | U46: =24%*(O46-3200000) -> 1130693 | V46: =P46+Q46+R46+S46+T46+U46 -> 1690693 | W46: 12 | X46: =V46/W46 -> 140891.08 | Z46: =X46 -> 140891.08 | AA46: 119022.8 | AB46: =Z46-AA46 -> 21868.282
A47: 37 | B47: IBRAHIM USMAN | C47: 968360 | D47: 12 | E47: =C47*D47 -> 11620320 | I47: =E47-F47-G47-H47 -> 11620320 | J47: 200000 | K47: 0.2 | L47: =I47*K47 -> 2324064 | M47: =J47+L47 -> 2524064 | N47: =F47+G47+H47+M47 -> 2524064 | O47: =E47-N47 -> 9096256 | P47: =IF(O47<300000,0.07*O47,21000) -> 21000 | Q47: =IF((O47-300000)<0,0,IF((O47-300000)<300000,0.11*(O47-300000),33000)) -> 33000 | R47: =IF((O47-600000)<0,0,IF((O47-600000)<500000,0.15*(O47-600000),75000)) -> 75000 | S47: =IF((O47-1100000)<0,0,IF((O47-1100000)<500000,0.19*(O47-1100000),95000)) -> 95000 | T47: =IF((O47-1600000)<0,0,IF((O47-1600000)<1600000,0.21*(O47-1600000),336000)) -> 336000 | U47: =24%*(O47-3200000) -> 1415101.4 | V47: =P47+Q47+R47+S47+T47+U47 -> 1975101.4 | W47: 12 | X47: =V47/W47 -> 164591.79 | Z47: =X47 -> 164591.79 | AA47: 118861.97 | AB47: =Z47-AA47 -> 45729.821
A48: 38 | B48: DR MOHAMMED O. AMALI | C48: 882595.5 | D48: 12 | E48: =C48*D48 -> 10591146 | G48: 693691.68 | I48: =E48-F48-G48-H48 -> 9897454.3 | J48: 200000 | K48: 0.2 | L48: =I48*K48 -> 1979490.9 | M48: =J48+L48 -> 2179490.9 | N48: =F48+G48+H48+M48 -> 2873182.5 | O48: =E48-N48 -> 7717963.5 | P48: =IF(O48<300000,0.07*O48,21000) -> 21000 | Q48: =IF((O48-300000)<0,0,IF((O48-300000)<300000,0.11*(O48-300000),33000)) -> 33000 | R48: =IF((O48-600000)<0,0,IF((O48-600000)<500000,0.15*(O48-600000),75000)) -> 75000 | S48: =IF((O48-1100000)<0,0,IF((O48-1100000)<500000,0.19*(O48-1100000),95000)) -> 95000 | T48: =IF((O48-1600000)<0,0,IF((O48-1600000)<1600000,0.21*(O48-1600000),336000)) -> 336000 | U48: =24%*(O48-3200000) -> 1084311.2 | V48: =P48+Q48+R48+S48+T48+U48 -> 1644311.2 | W48: 12 | X48: =V48/W48 -> 137025.94 | Z48: =X48 -> 137025.94 | AA48: 112212 | AB48: =Z48-AA48 -> 24813.931
A49: 39 | B49: YAHAYA SHAMSU | C49: 860713.92 | D49: 12 | E49: =C49*D49 -> 10328567 | G49: 672685.36 | I49: =E49-F49-G49-H49 -> 9655881.6 | J49: 200000 | K49: 0.2 | L49: =I49*K49 -> 1931176.3 | M49: =J49+L49 -> 2131176.3 | N49: =F49+G49+H49+M49 -> 2803861.7 | O49: =E49-N49 -> 7524705.3 | P49: =IF(O49<300000,0.07*O49,21000) -> 21000 | Q49: =IF((O49-300000)<0,0,IF((O49-300000)<300000,0.11*(O49-300000),33000)) -> 33000 | R49: =IF((O49-600000)<0,0,IF((O49-600000)<500000,0.15*(O49-600000),75000)) -> 75000 | S49: =IF((O49-1100000)<0,0,IF((O49-1100000)<500000,0.19*(O49-1100000),95000)) -> 95000 | T49: =IF((O49-1600000)<0,0,IF((O49-1600000)<1600000,0.21*(O49-1600000),336000)) -> 336000 | U49: =24%*(O49-3200000) -> 1037929.3 | V49: =P49+Q49+R49+S49+T49+U49 -> 1597929.3 | W49: 12 | X49: =V49/W49 -> 133160.77 | Z49: =X49 -> 133160.77 | AA49: 112211.99 | AB49: =Z49-AA49 -> 20948.784
A50: 40 | B50: BILKIS S. LAWAL-GAMBARI | C50: 490135.83 | D50: 12 | E50: =C50*D50 -> 5881630 | G50: 374530.4 | I50: =E50-F50-G50-H50 -> 5507099.6 | J50: 200000 | K50: 0.2 | L50: =I50*K50 -> 1101419.9 | M50: =J50+L50 -> 1301419.9 | N50: =F50+G50+H50+M50 -> 1675950.3 | O50: =E50-N50 -> 4205679.7 | P50: =IF(O50<300000,0.07*O50,21000) -> 21000 | Q50: =IF((O50-300000)<0,0,IF((O50-300000)<300000,0.11*(O50-300000),33000)) -> 33000 | R50: =IF((O50-600000)<0,0,IF((O50-600000)<500000,0.15*(O50-600000),75000)) -> 75000 | S50: =IF((O50-1100000)<0,0,IF((O50-1100000)<500000,0.19*(O50-1100000),95000)) -> 95000 | T50: =IF((O50-1600000)<0,0,IF((O50-1600000)<1600000,0.21*(O50-1600000),336000)) -> 336000 | U50: =24%*(O50-3200000) -> 241363.12 | V50: =P50+Q50+R50+S50+T50+U50 -> 801363.12 | W50: 12 | X50: =V50/W50 -> 66780.26 | Z50: =X50 -> 66780.26 | AA50: 51029.227 | AB50: =Z50-AA50 -> 15751.033
A51: 41 | B51: ZAINAB AKINDE | C51: 447016.17 | D51: 12 | E51: =C51*D51 -> 5364194 | G51: 333135.52 | I51: =E51-F51-G51-H51 -> 5031058.5 | J51: 200000 | K51: 0.2 | L51: =I51*K51 -> 1006211.7 | M51: =J51+L51 -> 1206211.7 | N51: =F51+G51+H51+M51 -> 1539347.2 | O51: =E51-N51 -> 3824846.8 | P51: =IF(O51<300000,0.07*O51,21000) -> 21000 | Q51: =IF((O51-300000)<0,0,IF((O51-300000)<300000,0.11*(O51-300000),33000)) -> 33000 | R51: =IF((O51-600000)<0,0,IF((O51-600000)<500000,0.15*(O51-600000),75000)) -> 75000 | S51: =IF((O51-1100000)<0,0,IF((O51-1100000)<500000,0.19*(O51-1100000),95000)) -> 95000 | T51: =IF((O51-1600000)<0,0,IF((O51-1600000)<1600000,0.21*(O51-1600000),336000)) -> 336000 | U51: =24%*(O51-3200000) -> 149963.23 | V51: =P51+Q51+R51+S51+T51+U51 -> 709963.23 | W51: 12 | X51: =V51/W51 -> 59163.602 | Z51: =X51 -> 59163.602 | AA51: 44641.501 | AB51: =Z51-AA51 -> 14522.102
A52: 42 | B52: GUNAT NANSAK MARK | C52: 447016.17 | D52: 12 | E52: =C52*D52 -> 5364194 | G52: 333135.52 | I52: =E52-F52-G52-H52 -> 5031058.5 | J52: 200000 | K52: 0.2 | L52: =I52*K52 -> 1006211.7 | M52: =J52+L52 -> 1206211.7 | N52: =F52+G52+H52+M52 -> 1539347.2 | O52: =E52-N52 -> 3824846.8 | P52: =IF(O52<300000,0.07*O52,21000) -> 21000 | Q52: =IF((O52-300000)<0,0,IF((O52-300000)<300000,0.11*(O52-300000),33000)) -> 33000 | R52: =IF((O52-600000)<0,0,IF((O52-600000)<500000,0.15*(O52-600000),75000)) -> 75000 | S52: =IF((O52-1100000)<0,0,IF((O52-1100000)<500000,0.19*(O52-1100000),95000)) -> 95000 | T52: =IF((O52-1600000)<0,0,IF((O52-1600000)<1600000,0.21*(O52-1600000),336000)) -> 336000 | U52: =24%*(O52-3200000) -> 149963.23 | V52: =P52+Q52+R52+S52+T52+U52 -> 709963.23 | W52: 12 | X52: =V52/W52 -> 59163.602 | Z52: =X52 -> 59163.602 | AA52: 44641.501 | AB52: =Z52-AA52 -> 14522.102
B54: LEGAL SERVICES
A55: 47 | B55: DR SHUAIBU DANWANKA | C55: 1947106.4 | D55: 12 | E55: =C55*D55 -> 23365277 | G55: 1677222.2 | I55: =E55-F55-G55-H55 -> 21688055 | J55: 200000 | K55: 0.2 | L55: =I55*K55 -> 4337611 | M55: =J55+L55 -> 4537611 | N55: =F55+G55+H55+M55 -> 6214833.1 | O55: =E55-N55 -> 17150444 | P55: =IF(O55<300000,0.07*O55,21000) -> 21000 | Q55: =IF((O55-300000)<0,0,IF((O55-300000)<300000,0.11*(O55-300000),33000)) -> 33000 | R55: =IF((O55-600000)<0,0,IF((O55-600000)<500000,0.15*(O55-600000),75000)) -> 75000 | S55: =IF((O55-1100000)<0,0,IF((O55-1100000)<500000,0.19*(O55-1100000),95000)) -> 95000 | T55: =IF((O55-1600000)<0,0,IF((O55-1600000)<1600000,0.21*(O55-1600000),336000)) -> 336000 | U55: =24%*(O55-3200000) -> 3348106.5 | V55: =P55+Q55+R55+S55+T55+U55 -> 3908106.5 | W55: 12 | X55: =V55/W55 -> 325675.54 | Z55: =X55 -> 325675.54 | AA55: 270672.25 | AB55: =Z55-AA55 -> 55003.297
A56: 48 | B56: ABDULSALAM BAKO | C56: 824477 | D56: 12 | E56: =C56*D56 -> 9893724 | G56: 714697.92 | I56: =E56-F56-G56-H56 -> 9179026.1 | J56: 200000 | K56: 0.2 | L56: =I56*K56 -> 1835805.2 | M56: =J56+L56 -> 2035805.2 | N56: =F56+G56+H56+M56 -> 2750503.1 | O56: =E56-N56 -> 7143220.9 | P56: =IF(O56<300000,0.07*O56,21000) -> 21000 | Q56: =IF((O56-300000)<0,0,IF((O56-300000)<300000,0.11*(O56-300000),33000)) -> 33000 | R56: =IF((O56-600000)<0,0,IF((O56-600000)<500000,0.15*(O56-600000),75000)) -> 75000 | S56: =IF((O56-1100000)<0,0,IF((O56-1100000)<500000,0.19*(O56-1100000),95000)) -> 95000 | T56: =IF((O56-1600000)<0,0,IF((O56-1600000)<1600000,0.21*(O56-1600000),336000)) -> 336000 | U56: =24%*(O56-3200000) -> 946373.01 | V56: =P56+Q56+R56+S56+T56+U56 -> 1506373 | W56: 12 | X56: =V56/W56 -> 125531.08 | Z56: =X56 -> 125531.08 | AA56: 103662.8 | AB56: =Z56-AA56 -> 21868.282
A58: 49 | B58: DEMOCRACY & GOVERNANCE
A59: 50 | B59: NGARA CHRISTOPHER OCHANJA | C59: 1085306.8 | D59: 12 | E59: =C59*D59 -> 13023681 | F59: 166400.85 | G59: 869094.48 | I59: =E59-F59-G59-H59 -> 11988186 | J59: 200000 | K59: 0.2 | L59: =I59*K59 -> 2397637.1 | M59: =J59+L59 -> 2597637.1 | N59: =F59+G59+H59+M59 -> 3633132.5 | O59: =E59-N59 -> 9390548.5 | P59: =IF(O59<300000,0.07*O59,21000) -> 21000 | Q59: =IF((O59-300000)<0,0,IF((O59-300000)<300000,0.11*(O59-300000),33000)) -> 33000 | R59: =IF((O59-600000)<0,0,IF((O59-600000)<500000,0.15*(O59-600000),75000)) -> 75000 | S59: =IF((O59-1100000)<0,0,IF((O59-1100000)<500000,0.19*(O59-1100000),95000)) -> 95000 | T59: =IF((O59-1600000)<0,0,IF((O59-1600000)<1600000,0.21*(O59-1600000),336000)) -> 336000 | U59: =24%*(O59-3200000) -> 1485731.6 | V59: =P59+Q59+R59+S59+T59+U59 -> 2045731.6 | W59: 12 | X59: =V59/W59 -> 170477.64 | Z59: =X59 -> 170477.64 | AA59: 147687.53 | AB59: =Z59-AA59 -> 22790.11
A60: 51 | B60: EJALONIBU GANIYU LAYI | C60: 698165.25 | D60: 12 | E60: =C60*D60 -> 8377983 | G60: 535838.64 | I60: =E60-F60-G60-H60 -> 7842144.4 | J60: 200000 | K60: 0.2 | L60: =I60*K60 -> 1568428.9 | M60: =J60+L60 -> 1768428.9 | N60: =F60+G60+H60+M60 -> 2304267.5 | O60: =E60-N60 -> 6073715.5 | P60: =IF(O60<300000,0.07*O60,21000) -> 21000 | Q60: =IF((O60-300000)<0,0,IF((O60-300000)<300000,0.11*(O60-300000),33000)) -> 33000 | R60: =IF((O60-600000)<0,0,IF((O60-600000)<500000,0.15*(O60-600000),75000)) -> 75000 | S60: =IF((O60-1100000)<0,0,IF((O60-1100000)<500000,0.19*(O60-1100000),95000)) -> 95000 | T60: =IF((O60-1600000)<0,0,IF((O60-1600000)<1600000,0.21*(O60-1600000),336000)) -> 336000 | U60: =24%*(O60-3200000) -> 689691.72 | V60: =P60+Q60+R60+S60+T60+U60 -> 1249691.7 | W60: 12 | X60: =V60/W60 -> 104140.98 | Z60: =X60 -> 104140.98 | AA60: 83753.408 | AB60: =Z60-AA60 -> 20387.568
A61: 52 | B61: UDEFUNA NNADOZIE PATRICK | C61: 578828.17 | D61: 12 | E61: =C61*D61 -> 6945938 | G61: 450075.04 | I61: =E61-F61-G61-H61 -> 6495863 | J61: 200000 | K61: 0.2 | L61: =I61*K61 -> 1299172.6 | M61: =J61+L61 -> 1499172.6 | N61: =F61+G61+H61+M61 -> 1949247.6 | O61: =E61-N61 -> 4996690.4 | P61: =IF(O61<300000,0.07*O61,21000) -> 21000 | Q61: =IF((O61-300000)<0,0,IF((O61-300000)<300000,0.11*(O61-300000),33000)) -> 33000 | R61: =IF((O61-600000)<0,0,IF((O61-600000)<500000,0.15*(O61-600000),75000)) -> 75000 | S61: =IF((O61-1100000)<0,0,IF((O61-1100000)<500000,0.19*(O61-1100000),95000)) -> 95000 | T61: =IF((O61-1600000)<0,0,IF((O61-1600000)<1600000,0.21*(O61-1600000),336000)) -> 336000 | U61: =24%*(O61-3200000) -> 431205.69 | V61: =P61+Q61+R61+S61+T61+U61 -> 991205.69 | W61: 12 | X61: =V61/W61 -> 82600.474 | Z61: =X61 -> 82600.474 | AA61: 64384.592 | AB61: =Z61-AA61 -> 18215.882
A62: 53 | B62: SHAFIU YAHYA MIKAIL | C62: 578828.17 | D62: 12 | E62: =C62*D62 -> 6945938 | G62: 450075.04 | I62: =E62-F62-G62-H62 -> 6495863 | J62: 200000 | K62: 0.2 | L62: =I62*K62 -> 1299172.6 | M62: =J62+L62 -> 1499172.6 | N62: =F62+G62+H62+M62 -> 1949247.6 | O62: =E62-N62 -> 4996690.4 | P62: =IF(O62<300000,0.07*O62,21000) -> 21000 | Q62: =IF((O62-300000)<0,0,IF((O62-300000)<300000,0.11*(O62-300000),33000)) -> 33000 | R62: =IF((O62-600000)<0,0,IF((O62-600000)<500000,0.15*(O62-600000),75000)) -> 75000 | S62: =IF((O62-1100000)<0,0,IF((O62-1100000)<500000,0.19*(O62-1100000),95000)) -> 95000 | T62: =IF((O62-1600000)<0,0,IF((O62-1600000)<1600000,0.21*(O62-1600000),336000)) -> 336000 | U62: =24%*(O62-3200000) -> 431205.69 | V62: =P62+Q62+R62+S62+T62+U62 -> 991205.69 | W62: 12 | X62: =V62/W62 -> 82600.474 | Z62: =X62 -> 82600.474 | AA62: 64384.592 | AB62: =Z62-AA62 -> 18215.882
A63: 54 | B63: HASSAN YERIMA | C63: 578828.17 | D63: 12 | E63: =C63*D63 -> 6945938 | G63: 450075.04 | I63: =E63-F63-G63-H63 -> 6495863 | J63: 200000 | K63: 0.2 | L63: =I63*K63 -> 1299172.6 | M63: =J63+L63 -> 1499172.6 | N63: =F63+G63+H63+M63 -> 1949247.6 | O63: =E63-N63 -> 4996690.4 | P63: =IF(O63<300000,0.07*O63,21000) -> 21000 | Q63: =IF((O63-300000)<0,0,IF((O63-300000)<300000,0.11*(O63-300000),33000)) -> 33000 | R63: =IF((O63-600000)<0,0,IF((O63-600000)<500000,0.15*(O63-600000),75000)) -> 75000 | S63: =IF((O63-1100000)<0,0,IF((O63-1100000)<500000,0.19*(O63-1100000),95000)) -> 95000 | T63: =IF((O63-1600000)<0,0,IF((O63-1600000)<1600000,0.21*(O63-1600000),336000)) -> 336000 | U63: =24%*(O63-3200000) -> 431205.69 | V63: =P63+Q63+R63+S63+T63+U63 -> 991205.69 | W63: 12 | X63: =V63/W63 -> 82600.474 | Z63: =X63 -> 82600.474 | AA63: 64384.592 | AB63: =Z63-AA63 -> 18215.882
A64: 55 | B64: HAUWA PATE SADIQ | C64: 592662.67 | D64: 12 | E64: =C64*D64 -> 7111952 | G64: 463356.16 | I64: =E64-F64-G64-H64 -> 6648595.8 | J64: 200000 | K64: 0.2 | L64: =I64*K64 -> 1329719.2 | M64: =J64+L64 -> 1529719.2 | N64: =F64+G64+H64+M64 -> 1993075.3 | O64: =E64-N64 -> 5118876.7 | P64: =IF(O64<300000,0.07*O64,21000) -> 21000 | Q64: =IF((O64-300000)<0,0,IF((O64-300000)<300000,0.11*(O64-300000),33000)) -> 33000 | R64: =IF((O64-600000)<0,0,IF((O64-600000)<500000,0.15*(O64-600000),75000)) -> 75000 | S64: =IF((O64-1100000)<0,0,IF((O64-1100000)<500000,0.19*(O64-1100000),95000)) -> 95000 | T64: =IF((O64-1600000)<0,0,IF((O64-1600000)<1600000,0.21*(O64-1600000),336000)) -> 336000 | U64: =24%*(O64-3200000) -> 460530.4 | V64: =P64+Q64+R64+S64+T64+U64 -> 1020530.4 | W64: 12 | X64: =V64/W64 -> 85044.2 | Z64: =X64 -> 85044.2 | AA64: 66538.069 | AB64: =Z64-AA64 -> 18506.131
A65: 56 | B65: KOLAPO Q. ABAYOMI | C65: 490135.83 | D65: 12 | E65: =C65*D65 -> 5881630 | F65: =6154.27916666668*12 -> 73851.35 | G65: 374530.4 | I65: =E65-F65-G65-H65 -> 5433248.3 | J65: 200000 | K65: 0.2 | L65: =I65*K65 -> 1086649.6 | M65: =J65+L65 -> 1286649.6 | N65: =F65+G65+H65+M65 -> 1735031.4 | O65: =E65-N65 -> 4146598.6 | P65: =IF(O65<300000,0.07*O65,21000) -> 21000 | Q65: =IF((O65-300000)<0,0,IF((O65-300000)<300000,0.11*(O65-300000),33000)) -> 33000 | R65: =IF((O65-600000)<0,0,IF((O65-600000)<500000,0.15*(O65-600000),75000)) -> 75000 | S65: =IF((O65-1100000)<0,0,IF((O65-1100000)<500000,0.19*(O65-1100000),95000)) -> 95000 | T65: =IF((O65-1600000)<0,0,IF((O65-1600000)<1600000,0.21*(O65-1600000),336000)) -> 336000 | U65: =24%*(O65-3200000) -> 227183.66 | V65: =P65+Q65+R65+S65+T65+U65 -> 787183.66 | W65: 12 | X65: =V65/W65 -> 65598.639 | Z65: =X65 -> 65598.639 | AA65: 51029.227 | AB65: =Z65-AA65 -> 14569.411
A66: 60
B67: DEPARTMENT OF STUDIES
B68: DR ASIMIYU G. ABIOLA | C68: 1947106.4 | D68: 12 | E68: =C68*D68 -> 23365277 | G68: 1677222.2 | I68: =E68-F68-G68-H68 -> 21688055 | J68: 200000 | K68: 0.2 | L68: =I68*K68 -> 4337611 | M68: =J68+L68 -> 4537611 | N68: =F68+G68+H68+M68 -> 6214833.1 | O68: =E68-N68 -> 17150444 | P68: =IF(O68<300000,0.07*O68,21000) -> 21000 | Q68: =IF((O68-300000)<0,0,IF((O68-300000)<300000,0.11*(O68-300000),33000)) -> 33000 | R68: =IF((O68-600000)<0,0,IF((O68-600000)<500000,0.15*(O68-600000),75000)) -> 75000 | S68: =IF((O68-1100000)<0,0,IF((O68-1100000)<500000,0.19*(O68-1100000),95000)) -> 95000 | T68: =IF((O68-1600000)<0,0,IF((O68-1600000)<1600000,0.21*(O68-1600000),336000)) -> 336000 | U68: =24%*(O68-3200000) -> 3348106.5 | V68: =P68+Q68+R68+S68+T68+U68 -> 3908106.5 | W68: 12 | X68: =V68/W68 -> 325675.54 | Z68: =X68 -> 325675.54 | AA68: 270672.25 | AB68: =Z68-AA68 -> 55003.297
A69: 62 | B69: DR. HADIZA SAIDU | C69: 882595.5 | D69: 12 | E69: =C69*D69 -> 10591146 | G69: 693691.68 | I69: =E69-F69-G69-H69 -> 9897454.3 | J69: 200000 | K69: 0.2 | L69: =I69*K69 -> 1979490.9 | M69: =J69+L69 -> 2179490.9 | N69: =F69+G69+H69+M69 -> 2873182.5 | O69: =E69-N69 -> 7717963.5 | P69: =IF(O69<300000,0.07*O69,21000) -> 21000 | Q69: =IF((O69-300000)<0,0,IF((O69-300000)<300000,0.11*(O69-300000),33000)) -> 33000 | R69: =IF((O69-600000)<0,0,IF((O69-600000)<500000,0.15*(O69-600000),75000)) -> 75000 | S69: =IF((O69-1100000)<0,0,IF((O69-1100000)<500000,0.19*(O69-1100000),95000)) -> 95000 | T69: =IF((O69-1600000)<0,0,IF((O69-1600000)<1600000,0.21*(O69-1600000),336000)) -> 336000 | U69: =24%*(O69-3200000) -> 1084311.2 | V69: =P69+Q69+R69+S69+T69+U69 -> 1644311.2 | W69: 12 | X69: =V69/W69 -> 137025.94 | Z69: =X69 -> 137025.94 | AA69: 112212 | AB69: =Z69-AA69 -> 24813.931
A70: 63 | B70: ANTHONY EDET | C70: 713911.08 | D70: 12 | E70: =C70*D70 -> 8566933 | F70: 107120 | G70: 550954.64 | I70: =E70-F70-G70-H70 -> 7908858.4 | J70: 200000 | K70: 0.2 | L70: =I70*K70 -> 1581771.7 | M70: =J70+L70 -> 1781771.7 | N70: =F70+G70+H70+M70 -> 2439846.3 | O70: =E70-N70 -> 6127086.7 | P70: =IF(O70<300000,0.07*O70,21000) -> 21000 | Q70: =IF((O70-300000)<0,0,IF((O70-300000)<300000,0.11*(O70-300000),33000)) -> 33000 | R70: =IF((O70-600000)<0,0,IF((O70-600000)<500000,0.15*(O70-600000),75000)) -> 75000 | S70: =IF((O70-1100000)<0,0,IF((O70-1100000)<500000,0.19*(O70-1100000),95000)) -> 95000 | T70: =IF((O70-1600000)<0,0,IF((O70-1600000)<1600000,0.21*(O70-1600000),336000)) -> 336000 | U70: =24%*(O70-3200000) -> 702500.81 | V70: =P70+Q70+R70+S70+T70+U70 -> 1262500.8 | W70: 12 | X70: =V70/W70 -> 105208.4 | Z70: =X70 -> 105208.4 | AA70: 86076.104 | AB70: =Z70-AA70 -> 19132.296
A71: 64 | B71: IGWE STACY | C71: 564993.58 | D71: 12 | E71: =C71*D71 -> 6779923 | G71: 436793.84 | I71: =E71-F71-G71-H71 -> 6343129.2 | J71: 200000 | K71: 0.2 | L71: =I71*K71 -> 1268625.8 | M71: =J71+L71 -> 1468625.8 | N71: =F71+G71+H71+M71 -> 1905419.7 | O71: =E71-N71 -> 4874503.3 | P71: =IF(O71<300000,0.07*O71,21000) -> 21000 | Q71: =IF((O71-300000)<0,0,IF((O71-300000)<300000,0.11*(O71-300000),33000)) -> 33000 | R71: =IF((O71-600000)<0,0,IF((O71-600000)<500000,0.15*(O71-600000),75000)) -> 75000 | S71: =IF((O71-1100000)<0,0,IF((O71-1100000)<500000,0.19*(O71-1100000),95000)) -> 95000 | T71: =IF((O71-1600000)<0,0,IF((O71-1600000)<1600000,0.21*(O71-1600000),336000)) -> 336000 | U71: =24%*(O71-3200000) -> 401880.8 | V71: =P71+Q71+R71+S71+T71+U71 -> 961880.8 | W71: 12 | X71: =V71/W71 -> 80156.733 | Z71: =X71 -> 80156.733 | AA71: 62231.115 | AB71: =Z71-AA71 -> 17925.619
A72: 65 | B72: OLANIYAN TAIWO ABINBOLA | C72: 447016.17 | D72: 12 | E72: =C72*D72 -> 5364194 | G72: 333135.52 | I72: =E72-F72-G72-H72 -> 5031058.5 | J72: 200000 | K72: 0.2 | L72: =I72*K72 -> 1006211.7 | M72: =J72+L72 -> 1206211.7 | N72: =F72+G72+H72+M72 -> 1539347.2 | O72: =E72-N72 -> 3824846.8 | P72: =IF(O72<300000,0.07*O72,21000) -> 21000 | Q72: =IF((O72-300000)<0,0,IF((O72-300000)<300000,0.11*(O72-300000),33000)) -> 33000 | R72: =IF((O72-600000)<0,0,IF((O72-600000)<500000,0.15*(O72-600000),75000)) -> 75000 | S72: =IF((O72-1100000)<0,0,IF((O72-1100000)<500000,0.19*(O72-1100000),95000)) -> 95000 | T72: =IF((O72-1600000)<0,0,IF((O72-1600000)<1600000,0.21*(O72-1600000),336000)) -> 336000 | U72: =0.24*(O72-3200000) -> 149963.23 | V72: =P72+Q72+R72+S72+T72+U72 -> 709963.23 | W72: 12 | X72: =V72/W72 -> 59163.602 | Z72: =X72 -> 59163.602 | AA72: 44641.501 | AB72: =Z72-AA72 -> 14522.102
B73: AMINAT JUMOKE SULAIMON | C73: 401910.75 | D73: 12 | E73: =C73*D73 -> 4822929 | G73: 289834.32 | I73: =E73-F73-G73-H73 -> 4533094.7 | J73: 200000 | K73: 0.2 | L73: =I73*K73 -> 906618.94 | M73: =J73+L73 -> 1106618.9 | N73: =F73+G73+H73+M73 -> 1396453.3 | O73: =E73-N73 -> 3426475.7 | P73: =IF(O73<300000,0.07*O73,21000) -> 21000 | Q73: =IF((O73-300000)<0,0,IF((O73-300000)<300000,0.11*(O73-300000),33000)) -> 33000 | R73: =IF((O73-600000)<0,0,IF((O73-600000)<500000,0.15*(O73-600000),75000)) -> 75000 | S73: =IF((O73-1100000)<0,0,IF((O73-1100000)<500000,0.19*(O73-1100000),95000)) -> 95000 | T73: =IF((O73-1600000)<0,0,IF((O73-1600000)<1600000,0.21*(O73-1600000),336000)) -> 336000 | U73: =0.24*(O73-3200000) -> 54354.179 | V73: =P73+Q73+R73+S73+T73+U73 -> 614354.18 | W73: 12 | X73: =V73/W73 -> 51196.182 | Z73: =X73 -> 51196.182 | AA73: 38659.166 | AB73: =Z73-AA73 -> 12537.016
A74: 66
A75: 67 | B75: ECON. DEV. & SOC. RESEARCH
A76: 68 | B76: DR AUGUSTINE C. OSIGWE | C76: 1847612 | D76: 12 | E76: =C76*D76 -> 22171344 | F76: 307730.5 | G76: 1581707.5 | I76: =E76-F76-G76-H76 -> 20281906 | J76: 200000 | K76: 0.2 | L76: =I76*K76 -> 4056381.2 | M76: =J76+L76 -> 4256381.2 | N76: =F76+G76+H76+M76 -> 6145819.2 | O76: =E76-N76 -> 16025525 | P76: =IF(O76<300000,0.07*O76,21000) -> 21000 | Q76: =IF((O76-300000)<0,0,IF((O76-300000)<300000,0.11*(O76-300000),33000)) -> 33000 | R76: =IF((O76-600000)<0,0,IF((O76-600000)<500000,0.15*(O76-600000),75000)) -> 75000 | S76: =IF((O76-1100000)<0,0,IF((O76-1100000)<500000,0.19*(O76-1100000),95000)) -> 95000 | T76: =IF((O76-1600000)<0,0,IF((O76-1600000)<1600000,0.21*(O76-1600000),336000)) -> 336000 | U76: =24%*(O76-3200000) -> 3078125.9 | V76: =P76+Q76+R76+S76+T76+U76 -> 3638125.9 | W76: 12 | X76: =V76/W76 -> 303177.16 | Z76: =X76 -> 303177.16 | AA76: 251101.24 | AB76: =Z76-AA76 -> 52075.922
A77: 69 | B77: TERFA WILLIAMS ABRAHAM | C77: 1232711.1 | D77: 12 | E77: =C77*D77 -> 14792533 | G77: 818602.64 | I77: =E77-F77-G77-H77 -> 13973930 | J77: 200000 | K77: 0.2 | L77: =I77*K77 -> 2794786.1 | M77: =J77+L77 -> 2994786.1 | N77: =F77+G77+H77+M77 -> 3813388.7 | O77: =E77-N77 -> 10979144 | P77: =IF(O77<300000,0.07*O77,21000) -> 21000 | Q77: =IF((O77-300000)<0,0,IF((O77-300000)<300000,0.11*(O77-300000),33000)) -> 33000 | R77: =IF((O77-600000)<0,0,IF((O77-600000)<500000,0.15*(O77-600000),75000)) -> 75000 | S77: =IF((O77-1100000)<0,0,IF((O77-1100000)<500000,0.19*(O77-1100000),95000)) -> 95000 | T77: =IF((O77-1600000)<0,0,IF((O77-1600000)<1600000,0.21*(O77-1600000),336000)) -> 336000 | U77: =24%*(O77-3200000) -> 1866994.6 | V77: =P77+Q77+R77+S77+T77+U77 -> 2426994.6 | W77: 12 | X77: =V77/W77 -> 202249.55 | Z77: =X77 -> 202249.55 | AA77: 177751.03 | AB77: =Z77-AA77 -> 24498.522
A78: 70 | B78: OMOJU OLUWASOLA EMMANUEL | C78: 882595.5 | D78: 12 | E78: =C78*D78 -> 10591146 | G78: 693691.68 | I78: =E78-F78-G78-H78 -> 9897454.3 | J78: 200000 | K78: 0.2 | L78: =I78*K78 -> 1979490.9 | M78: =J78+L78 -> 2179490.9 | N78: =F78+G78+H78+M78 -> 2873182.5 | O78: =E78-N78 -> 7717963.5 | P78: =IF(O78<300000,0.07*O78,21000) -> 21000 | Q78: =IF((O78-300000)<0,0,IF((O78-300000)<300000,0.11*(O78-300000),33000)) -> 33000 | R78: =IF((O78-600000)<0,0,IF((O78-600000)<500000,0.15*(O78-600000),75000)) -> 75000 | S78: =IF((O78-1100000)<0,0,IF((O78-1100000)<500000,0.19*(O78-1100000),95000)) -> 95000 | T78: =IF((O78-1600000)<0,0,IF((O78-1600000)<1600000,0.21*(O78-1600000),336000)) -> 336000 | U78: =24%*(O78-3200000) -> 1084311.2 | V78: =P78+Q78+R78+S78+T78+U78 -> 1644311.2 | W78: 12 | X78: =V78/W78 -> 137025.94 | Z78: =X78 -> 137025.94 | AA78: 112212 | AB78: =Z78-AA78 -> 24813.931
A79: 71 | B79: IBE EZECHI CYRIACUS | C79: 698165.25 | D79: 12 | E79: =C79*D79 -> 8377983 | G79: 535838.64 | I79: =E79-F79-G79-H79 -> 7842144.4 | J79: 200000 | K79: 0.2 | L79: =I79*K79 -> 1568428.9 | M79: =J79+L79 -> 1768428.9 | N79: =F79+G79+H79+M79 -> 2304267.5 | O79: =E79-N79 -> 6073715.5 | P79: =IF(O79<300000,0.07*O79,21000) -> 21000 | Q79: =IF((O79-300000)<0,0,IF((O79-300000)<300000,0.11*(O79-300000),33000)) -> 33000 | R79: =IF((O79-600000)<0,0,IF((O79-600000)<500000,0.15*(O79-600000),75000)) -> 75000 | S79: =IF((O79-1100000)<0,0,IF((O79-1100000)<500000,0.19*(O79-1100000),95000)) -> 95000 | T79: =IF((O79-1600000)<0,0,IF((O79-1600000)<1600000,0.21*(O79-1600000),336000)) -> 336000 | U79: =24%*(O79-3200000) -> 689691.72 | V79: =P79+Q79+R79+S79+T79+U79 -> 1249691.7 | W79: 12 | X79: =V79/W79 -> 104140.98 | Z79: =X79 -> 104140.98 | AA79: 83767.87 | AB79: =Z79-AA79 -> 20373.106
A80: 72 | B80: OSIKHEN LEO IGBANOI | C80: 698166.25 | D80: 12 | E80: =C80*D80 -> 8377995 | F80: 104315.07 | G80: 535839.6 | I80: =E80-F80-G80-H80 -> 7737840.3 | J80: 200000 | K80: 0.2 | L80: =I80*K80 -> 1547568.1 | M80: =J80+L80 -> 1747568.1 | N80: =F80+G80+H80+M80 -> 2387722.7 | O80: =E80-N80 -> 5990272.3 | P80: =IF(O80<300000,0.07*O80,21000) -> 21000 | Q80: =IF((O80-300000)<0,0,IF((O80-300000)<300000,0.11*(O80-300000),33000)) -> 33000 | R80: =IF((O80-600000)<0,0,IF((O80-600000)<500000,0.15*(O80-600000),75000)) -> 75000 | S80: =IF((O80-1100000)<0,0,IF((O80-1100000)<500000,0.19*(O80-1100000),95000)) -> 95000 | T80: =IF((O80-1600000)<0,0,IF((O80-1600000)<1600000,0.21*(O80-1600000),336000)) -> 336000 | U80: =24%*(O80-3200000) -> 669665.34 | V80: =P80+Q80+R80+S80+T80+U80 -> 1229665.3 | W80: 12 | X80: =V80/W80 -> 102472.11 | Z80: =X80 -> 102472.11 | AA80: 83753.408 | AB80: =Z80-AA80 -> 18718.703
A81: 73 | B81: OKUNGBOWA OSARETIN GODSPOWER | C81: 682419.5 | D81: 12 | E81: =C81*D81 -> 8189034 | G81: 520722.72 | I81: =E81-F81-G81-H81 -> 7668311.3 | J81: 200000 | K81: 0.2 | L81: =I81*K81 -> 1533662.3 | M81: =J81+L81 -> 1733662.3 | N81: =F81+G81+H81+M81 -> 2254385 | O81: =E81-N81 -> 5934649 | P81: =IF(O81<300000,0.07*O81,21000) -> 21000 | Q81: =IF((O81-300000)<0,0,IF((O81-300000)<300000,0.11*(O81-300000),33000)) -> 33000 | R81: =IF((O81-600000)<0,0,IF((O81-600000)<500000,0.15*(O81-600000),75000)) -> 75000 | S81: =IF((O81-1100000)<0,0,IF((O81-1100000)<500000,0.19*(O81-1100000),95000)) -> 95000 | T81: =IF((O81-1600000)<0,0,IF((O81-1600000)<1600000,0.21*(O81-1600000),336000)) -> 336000 | U81: =24%*(O81-3200000) -> 656315.77 | V81: =P81+Q81+R81+S81+T81+U81 -> 1216315.8 | W81: 12 | X81: =V81/W81 -> 101359.65 | Z81: =X81 -> 101359.65 | AA81: 81302.396 | AB81: =Z81-AA81 -> 20057.251
A82: 74 | B82: YUSUF IBRAHIM | C82: 578828.17 | D82: 12 | E82: =C82*D82 -> 6945938 | G82: 450075.04 | I82: =E82-F82-G82-H82 -> 6495863 | J82: 200000 | K82: 0.2 | L82: =I82*K82 -> 1299172.6 | M82: =J82+L82 -> 1499172.6 | N82: =F82+G82+H82+M82 -> 1949247.6 | O82: =E82-N82 -> 4996690.4 | P82: =IF(O82<300000,0.07*O82,21000) -> 21000 | Q82: =IF((O82-300000)<0,0,IF((O82-300000)<300000,0.11*(O82-300000),33000)) -> 33000 | R82: =IF((O82-600000)<0,0,IF((O82-600000)<500000,0.15*(O82-600000),75000)) -> 75000 | S82: =IF((O82-1100000)<0,0,IF((O82-1100000)<500000,0.19*(O82-1100000),95000)) -> 95000 | T82: =IF((O82-1600000)<0,0,IF((O82-1600000)<1600000,0.21*(O82-1600000),336000)) -> 336000 | U82: =24%*(O82-3200000) -> 431205.69 | V82: =P82+Q82+R82+S82+T82+U82 -> 991205.69 | W82: 12 | X82: =V82/W82 -> 82600.474 | Z82: =X82 -> 82600.474 | AA82: 64384.592 | AB82: =Z82-AA82 -> 18215.882
A83: 75 | B83: MUSTAPHA RAFIU AYOBANJI | C83: 617472.75 | D83: 12 | E83: =C83*D83 -> 7409673 | F83: 93501.975 | G83: 477573.84 | I83: =E83-F83-G83-H83 -> 6838597.2 | J83: 200000 | K83: 0.2 | L83: =I83*K83 -> 1367719.4 | M83: =J83+L83 -> 1567719.4 | N83: =F83+G83+H83+M83 -> 2138795.3 | O83: =E83-N83 -> 5270877.7 | P83: =IF(O83<300000,0.07*O83,21000) -> 21000 | Q83: =IF((O83-300000)<0,0,IF((O83-300000)<300000,0.11*(O83-300000),33000)) -> 33000 | R83: =IF((O83-600000)<0,0,IF((O83-600000)<500000,0.15*(O83-600000),75000)) -> 75000 | S83: =IF((O83-1100000)<0,0,IF((O83-1100000)<500000,0.19*(O83-1100000),95000)) -> 95000 | T83: =IF((O83-1600000)<0,0,IF((O83-1600000)<1600000,0.21*(O83-1600000),336000)) -> 336000 | U83: =24%*(O83-3200000) -> 497010.66 | V83: =P83+Q83+R83+S83+T83+U83 -> 1057010.7 | W83: 12 | X83: =V83/W83 -> 88084.222 | Z83: =X83 -> 88084.222 | AA83: 70529.475 | AB83: =Z83-AA83 -> 17554.746
A84: 76 | B84: MARYAM MUSA SADA | C84: 490135.83 | D84: 12 | E84: =C84*D84 -> 5881630 | G84: 374530.4 | I84: =E84-F84-G84-H84 -> 5507099.6 | J84: 200000 | K84: 0.2 | L84: =I84*K84 -> 1101419.9 | M84: =J84+L84 -> 1301419.9 | N84: =F84+G84+H84+M84 -> 1675950.3 | O84: =E84-N84 -> 4205679.7 | P84: =IF(O84<300000,0.07*O84,21000) -> 21000 | Q84: =IF((O84-300000)<0,0,IF((O84-300000)<300000,0.11*(O84-300000),33000)) -> 33000 | R84: =IF((O84-600000)<0,0,IF((O84-600000)<500000,0.15*(O84-600000),75000)) -> 75000 | S84: =IF((O84-1100000)<0,0,IF((O84-1100000)<500000,0.19*(O84-1100000),95000)) -> 95000 | T84: =IF((O84-1600000)<0,0,IF((O84-1600000)<1600000,0.21*(O84-1600000),336000)) -> 336000 | U84: =24%*(O84-3200000) -> 241363.12 | V84: =P84+Q84+R84+S84+T84+U84 -> 801363.12 | W84: 12 | X84: =V84/W84 -> 66780.26 | Z84: =X84 -> 66780.26 | AA84: 51029.227 | AB84: =Z84-AA84 -> 15751.033
B85: CHARITY EZENWAJIOBI | C85: 408920.67 | D85: 12 | E85: =C85*D85 -> 4907048 | G85: 296563.84 | I85: =E85-F85-G85-H85 -> 4610484.2 | J85: 200000 | K85: 0.2 | L85: =I85*K85 -> 922096.83 | M85: =J85+L85 -> 1122096.8 | N85: =F85+G85+H85+M85 -> 1418660.7 | O85: =E85-N85 -> 3488387.3 | P85: =IF(O85<300000,0.07*O85,21000) -> 21000 | Q85: =IF((O85-300000)<0,0,IF((O85-300000)<300000,0.11*(O85-300000),33000)) -> 33000 | R85: =IF((O85-600000)<0,0,IF((O85-600000)<500000,0.15*(O85-600000),75000)) -> 75000 | S85: =IF((O85-1100000)<0,0,IF((O85-1100000)<500000,0.19*(O85-1100000),95000)) -> 95000 | T85: =IF((O85-1600000)<0,0,IF((O85-1600000)<1600000,0.21*(O85-1600000),336000)) -> 336000 | U85: =24%*(O85-3200000) -> 69212.959 | V85: =P85+Q85+R85+S85+T85+U85 -> 629212.96 | W85: 12 | X85: =V85/W85 -> 52434.413 | Z85: =X85 -> 52434.413 | AA85: 39613.136 | AB85: =Z85-AA85 -> 12821.278
A88: 78 | B88: TRAINING & INT''L COOP
A89: 79 | B89: AKINSANMI ADEJOKE OLUKEMI | C89: 1797359.3 | D89: 12 | E89: =C89*D89 -> 21568312 | F89: 316881.85 | G89: 1629465 | I89: =E89-F89-G89-H89 -> 19621965 | J89: 200000 | K89: 0.2 | L89: =I89*K89 -> 3924393 | M89: =J89+L89 -> 4124393 | N89: =F89+G89+H89+M89 -> 6070739.8 | O89: =E89-N89 -> 15497572 | P89: =IF(O89<300000,0.07*O89,21000) -> 21000 | Q89: =IF((O89-300000)<0,0,IF((O89-300000)<300000,0.11*(O89-300000),33000)) -> 33000 | R89: =IF((O89-600000)<0,0,IF((O89-600000)<500000,0.15*(O89-600000),75000)) -> 75000 | S89: =IF((O89-1100000)<0,0,IF((O89-1100000)<500000,0.19*(O89-1100000),95000)) -> 95000 | T89: =IF((O89-1600000)<0,0,IF((O89-1600000)<1600000,0.21*(O89-1600000),336000)) -> 336000 | U89: =24%*(O89-3200000) -> 2951417.3 | V89: =P89+Q89+R89+S89+T89+U89 -> 3511417.3 | W89: 12 | X89: =V89/W89 -> 292618.11 | Z89: =X89 -> 292618.11 | AA89: 236486.75 | AB89: =Z89-AA89 -> 56131.361
A90: 80 | B90: MOHAMMED R. ADAMU | C90: 870286.75 | D90: 12 | E90: =C90*D90 -> 10443441 | G90: 550954.64 | I90: =E90-F90-G90-H90 -> 9892486.4 | J90: 200000 | K90: 0.2 | L90: =I90*K90 -> 1978497.3 | M90: =J90+L90 -> 2178497.3 | N90: =F90+G90+H90+M90 -> 2729451.9 | O90: =E90-N90 -> 7713989.1 | P90: =IF(O90<300000,0.07*O90,21000) -> 21000 | Q90: =IF((O90-300000)<0,0,IF((O90-300000)<300000,0.11*(O90-300000),33000)) -> 33000 | R90: =IF((O90-600000)<0,0,IF((O90-600000)<500000,0.15*(O90-600000),75000)) -> 75000 | S90: =IF((O90-1100000)<0,0,IF((O90-1100000)<500000,0.19*(O90-1100000),95000)) -> 95000 | T90: =IF((O90-1600000)<0,0,IF((O90-1600000)<1600000,0.21*(O90-1600000),336000)) -> 336000 | U90: =24%*(O90-3200000) -> 1083357.4 | V90: =P90+Q90+R90+S90+T90+U90 -> 1643357.4 | W90: 12 | X90: =V90/W90 -> 136946.45 | Z90: =X90 -> 136946.45 | AA90: 72764.421 | AB90: =Z90-AA90 -> 64182.028
A91: 81 | B91: EROMOSELE OMONIGBO | C91: 567472.75 | D91: 12 | E91: =C91*D91 -> 6809673 | F91: 93501.975 | G91: 477573.84 | I91: =E91-F91-G91-H91 -> 6238597.2 | J91: 200000 | K91: 0.2 | L91: =I91*K91 -> 1247719.4 | M91: =J91+L91 -> 1447719.4 | N91: =F91+G91+H91+M91 -> 2018795.3 | O91: =E91-N91 -> 4790877.7 | P91: =IF(O91<300000,0.07*O91,21000) -> 21000 | Q91: =IF((O91-300000)<0,0,IF((O91-300000)<300000,0.11*(O91-300000),33000)) -> 33000 | R91: =IF((O91-600000)<0,0,IF((O91-600000)<500000,0.15*(O91-600000),75000)) -> 75000 | S91: =IF((O91-1100000)<0,0,IF((O91-1100000)<500000,0.19*(O91-1100000),95000)) -> 95000 | T91: =IF((O91-1600000)<0,0,IF((O91-1600000)<1600000,0.21*(O91-1600000),336000)) -> 336000 | U91: =24%*(O91-3200000) -> 381810.66 | V91: =P91+Q91+R91+S91+T91+U91 -> 941810.66 | W91: 12 | X91: =V91/W91 -> 78484.222 | Z91: =X91 -> 78484.222 | AA91: 59711.115 | AB91: =Z91-AA91 -> 18773.106
B92: OKECHUKWU UCHENNA HULDA | C92: 542662.67 | D92: 12 | E92: =C92*D92 -> 6511952 | G92: 463356.16 | I92: =E92-F92-G92-H92 -> 6048595.8 | J92: 200000 | K92: 0.2 | L92: =I92*K92 -> 1209719.2 | M92: =J92+L92 -> 1409719.2 | N92: =F92+G92+H92+M92 -> 1873075.3 | O92: =E92-N92 -> 4638876.7 | P92: =IF(O92<300000,0.07*O92,21000) -> 21000 | Q92: =IF((O92-300000)<0,0,IF((O92-300000)<300000,0.11*(O92-300000),33000)) -> 33000 | R92: =IF((O92-600000)<0,0,IF((O92-600000)<500000,0.15*(O92-600000),75000)) -> 75000 | S92: =IF((O92-1100000)<0,0,IF((O92-1100000)<500000,0.19*(O92-1100000),95000)) -> 95000 | T92: =IF((O92-1600000)<0,0,IF((O92-1600000)<1600000,0.21*(O92-1600000),336000)) -> 336000 | U92: =24%*(O92-3200000) -> 345330.4 | V92: =P92+Q92+R92+S92+T92+U92 -> 905330.4 | W92: 12 | X92: =V92/W92 -> 75444.2 | Z92: =X92 -> 75444.2 | AA92: 56938.069 | AB92: =Z92-AA92 -> 18506.131
B93: TASSNEEM IBRAHIM | C93: 450135.83 | D93: 12 | E93: =C93*D93 -> 5401630 | G93: 374530.4 | I93: =E93-F93-G93-H93 -> 5027099.6 | J93: 200000 | K93: 0.2 | L93: =I93*K93 -> 1005419.9 | M93: =J93+L93 -> 1205419.9 | N93: =F93+G93+H93+M93 -> 1579950.3 | O93: =E93-N93 -> 3821679.7 | P93: =IF(O93<300000,0.07*O93,21000) -> 21000 | Q93: =IF((O93-300000)<0,0,IF((O93-300000)<300000,0.11*(O93-300000),33000)) -> 33000 | R93: =IF((O93-600000)<0,0,IF((O93-600000)<500000,0.15*(O93-600000),75000)) -> 75000 | S93: =IF((O93-1100000)<0,0,IF((O93-1100000)<500000,0.19*(O93-1100000),95000)) -> 95000 | T93: =IF((O93-1600000)<0,0,IF((O93-1600000)<1600000,0.21*(O93-1600000),336000)) -> 336000 | U93: =24%*(O93-3200000) -> 149203.12 | V93: =P93+Q93+R93+S93+T93+U93 -> 709203.12 | W93: 12 | X93: =V93/W93 -> 59100.26 | Z93: =X93 -> 59100.26 | AA93: 43763.907 | AB93: =Z93-AA93 -> 15336.353
A94: 83
A95: 84 | B95: LIBRARY & DOCUMENTATION
A96: 85 | B96: DR MAIMUNA IZAH | C96: 1947106.4 | D96: 12 | E96: =C96*D96 -> 23365277 | G96: 1677222.2 | I96: =E96-F96-G96-H96 -> 21688055 | J96: 200000 | K96: 0.2 | L96: =I96*K96 -> 4337611 | M96: =J96+L96 -> 4537611 | N96: =F96+G96+H96+M96 -> 6214833.1 | O96: =E96-N96 -> 17150444 | P96: =IF(O96<300000,0.07*O96,21000) -> 21000 | Q96: =IF((O96-300000)<0,0,IF((O96-300000)<300000,0.11*(O96-300000),33000)) -> 33000 | R96: =IF((O96-600000)<0,0,IF((O96-600000)<500000,0.15*(O96-600000),75000)) -> 75000 | S96: =IF((O96-1100000)<0,0,IF((O96-1100000)<500000,0.19*(O96-1100000),95000)) -> 95000 | T96: =IF((O96-1600000)<0,0,IF((O96-1600000)<1600000,0.21*(O96-1600000),336000)) -> 336000 | U96: =24%*(O96-3200000) -> 3348106.5 | V96: =P96+Q96+R96+S96+T96+U96 -> 3908106.5 | W96: 12 | X96: =V96/W96 -> 325675.54 | Z96: =X96 -> 325675.54 | AA96: 270672.25 | AB96: =Z96-AA96 -> 55003.297
A97: 86 | B97: CATHERINE E. IKOKOH | C97: 1085306.8 | D97: 12 | E97: =C97*D97 -> 13023681 | F97: 166400.85 | G97: 869094.48 | I97: =E97-F97-G97-H97 -> 11988186 | J97: 200000 | K97: 0.2 | L97: =I97*K97 -> 2397637.1 | M97: =J97+L97 -> 2597637.1 | N97: =F97+G97+H97+M97 -> 3633132.5 | O97: =E97-N97 -> 9390548.5 | P97: =IF(O97<300000,0.07*O97,21000) -> 21000 | Q97: =IF((O97-300000)<0,0,IF((O97-300000)<300000,0.11*(O97-300000),33000)) -> 33000 | R97: =IF((O97-600000)<0,0,IF((O97-600000)<500000,0.15*(O97-600000),75000)) -> 75000 | S97: =IF((O97-1100000)<0,0,IF((O97-1100000)<500000,0.19*(O97-1100000),95000)) -> 95000 | T97: =IF((O97-1600000)<0,0,IF((O97-1600000)<1600000,0.21*(O97-1600000),336000)) -> 336000 | U97: =24%*(O97-3200000) -> 1485731.6 | V97: =P97+Q97+R97+S97+T97+U97 -> 2045731.6 | W97: 12 | X97: =V97/W97 -> 170477.64 | Z97: =X97 -> 170477.64 | AA97: 147687.53 | AB97: =Z97-AA97 -> 22790.11
A98: 87 | B98: ALIYU SANNI ABUBAKAR | C98: 720899.98 | D98: 12 | E98: =C98*D98 -> 8650799.8 | F98: 101319.25 | G98: 519697.28 | I98: =E98-F98-G98-H98 -> 8029783.2 | J98: 200000 | K98: 0.2 | L98: =I98*K98 -> 1605956.6 | M98: =J98+L98 -> 1805956.6 | N98: =F98+G98+H98+M98 -> 2426973.2 | O98: =E98-N98 -> 6223826.6 | P98: =IF(O98<300000,0.07*O98,21000) -> 21000 | Q98: =IF((O98-300000)<0,0,IF((O98-300000)<300000,0.11*(O98-300000),33000)) -> 33000 | R98: =IF((O98-600000)<0,0,IF((O98-600000)<500000,0.15*(O98-600000),75000)) -> 75000 | S98: =IF((O98-1100000)<0,0,IF((O98-1100000)<500000,0.19*(O98-1100000),95000)) -> 95000 | T98: =IF((O98-1600000)<0,0,IF((O98-1600000)<1600000,0.21*(O98-1600000),336000)) -> 336000 | U98: =24%*(O98-3200000) -> 725718.38 | V98: =P98+Q98+R98+S98+T98+U98 -> 1285718.4 | W98: 12 | X98: =V98/W98 -> 107143.2 | Z98: =X98 -> 107143.2 | AA98: 87575.783 | AB98: =Z98-AA98 -> 19567.416
A99: 88 | B99: CHINAKO N. ASOGWA | C99: 742085.65 | D99: 12 | E99: =C99*D99 -> 8905027.7 | G99: 519697.28 | I99: =E99-F99-G99-H99 -> 8385330.5 | J99: 200000 | K99: 0.2 | L99: =I99*K99 -> 1677066.1 | M99: =J99+L99 -> 1877066.1 | N99: =F99+G99+H99+M99 -> 2396763.4 | O99: =E99-N99 -> 6508264.4 | P99: =IF(O99<300000,0.07*O99,21000) -> 21000 | Q99: =IF((O99-300000)<0,0,IF((O99-300000)<300000,0.11*(O99-300000),33000)) -> 33000 | R99: =IF((O99-600000)<0,0,IF((O99-600000)<500000,0.15*(O99-600000),75000)) -> 75000 | S99: =IF((O99-1100000)<0,0,IF((O99-1100000)<500000,0.19*(O99-1100000),95000)) -> 95000 | T99: =IF((O99-1600000)<0,0,IF((O99-1600000)<1600000,0.21*(O99-1600000),336000)) -> 336000 | U99: =0.24*(O99-3200000) -> 793983.45 | V99: =P99+Q99+R99+S99+T99+U99 -> 1353983.4 | W99: 12 | X99: =V99/W99 -> 112831.95 | Z99: =X99 -> 112831.95 | AA99: 87392.55 | AB99: =Z99-AA99 -> 25439.404
A100: 89 | B100: AMOS ABA | C100: 466244.96 | D100: 12 | E100: =C100*D100 -> 5594939.5 | G100: 316752.4 | I100: =E100-F100-G100-H100 -> 5278187.2 | J100: 200000 | K100: 0.2 | L100: =I100*K100 -> 1055637.4 | M100: =J100+L100 -> 1255637.4 | N100: =F100+G100+H100+M100 -> 1572389.8 | O100: =E100-N100 -> 4022549.7 | P100: =IF(O100<300000,0.07*O100,21000) -> 21000 | Q100: =IF((O100-300000)<0,0,IF((O100-300000)<300000,0.11*(O100-300000),33000)) -> 33000 | R100: =IF((O100-600000)<0,0,IF((O100-600000)<500000,0.15*(O100-600000),75000)) -> 75000 | S100: =IF((O100-1100000)<0,0,IF((O100-1100000)<500000,0.19*(O100-1100000),95000)) -> 95000 | T100: =IF((O100-1600000)<0,0,IF((O100-1600000)<1600000,0.21*(O100-1600000),336000)) -> 336000 | U100: =0.24*(O100-3200000) -> 197411.93 | V100: =P100+Q100+R100+S100+T100+U100 -> 757411.93 | W100: 12 | X100: =V100/W100 -> 63117.661 | Z100: =X100 -> 63117.661 | AA100: 46740.265 | AB100: =Z100-AA100 -> 16377.396
B101: TITILAYO DANIEL MARVELLOUS | C101: 466751.86 | D101: 12 | E101: =C101*D101 -> 5601022.3 | G101: 317190.8 | I101: =E101-F101-G101-H101 -> 5283831.5 | J101: 200000 | K101: 0.2 | L101: =I101*K101 -> 1056766.3 | M101: =J101+L101 -> 1256766.3 | N101: =F101+G101+H101+M101 -> 1573957.1 | O101: =E101-N101 -> 4027065.2 | P101: =IF(O101<300000,0.07*O101,21000) -> 21000 | Q101: =IF((O101-300000)<0,0,IF((O101-300000)<300000,0.11*(O101-300000),33000)) -> 33000 | R101: =IF((O101-600000)<0,0,IF((O101-600000)<500000,0.15*(O101-600000),75000)) -> 75000 | S101: =IF((O101-1100000)<0,0,IF((O101-1100000)<500000,0.19*(O101-1100000),95000)) -> 95000 | T101: =IF((O101-1600000)<0,0,IF((O101-1600000)<1600000,0.21*(O101-1600000),336000)) -> 336000 | U101: =0.24*(O101-3200000) -> 198495.66 | V101: =P101+Q101+R101+S101+T101+U101 -> 758495.66 | W101: 12 | X101: =V101/W101 -> 63207.971 | Z101: =X101 -> 63207.971 | AA101: 87883.38 | AB101: =Z101-AA101 -> -24675.409
B102: ENENCHE JEREMIAH AGADA | C102: 442901.94 | D102: 12 | E102: =C102*D102 -> 5314823.3 | G102: 296563.84 | I102: =E102-F102-G102-H102 -> 5018259.4 | J102: 200000 | K102: 0.2 | L102: =I102*K102 -> 1003651.9 | M102: =J102+L102 -> 1203651.9 | N102: =F102+G102+H102+M102 -> 1500215.7 | O102: =E102-N102 -> 3814607.6 | P102: =IF(O102<300000,0.07*O102,21000) -> 21000 | Q102: =IF((O102-300000)<0,0,IF((O102-300000)<300000,0.11*(O102-300000),33000)) -> 33000 | R102: =IF((O102-600000)<0,0,IF((O102-600000)<500000,0.15*(O102-600000),75000)) -> 75000 | S102: =IF((O102-1100000)<0,0,IF((O102-1100000)<500000,0.19*(O102-1100000),95000)) -> 95000 | T102: =IF((O102-1600000)<0,0,IF((O102-1600000)<1600000,0.21*(O102-1600000),336000)) -> 336000 | U102: =0.24*(O102-3200000) -> 147505.81 | V102: =P102+Q102+R102+S102+T102+U102 -> 707505.81 | W102: 12 | X102: =V102/W102 -> 58958.818 | Z102: =X102 -> 58958.818 | AA102: 43740.257 | AB102: =Z102-AA102 -> 15218.561
A103: 90
A104: 91 | B104: LEG, CTRE FOR SEC. ANALYSIS
A105: 92 | B105: EGUATU U. ONYEJELEM | C105: 592662.67 | D105: 12 | E105: =C105*D105 -> 7111952 | G105: 463356.16 | I105: =E105-F105-G105-H105 -> 6648595.8 | J105: 200000 | K105: 0.2 | L105: =I105*K105 -> 1329719.2 | M105: =J105+L105 -> 1529719.2 | N105: =F105+G105+H105+M105 -> 1993075.3 | O105: =E105-N105 -> 5118876.7 | P105: =IF(O105<300000,0.07*O105,21000) -> 21000 | Q105: =IF((O105-300000)<0,0,IF((O105-300000)<300000,0.11*(O105-300000),33000)) -> 33000 | R105: =IF((O105-600000)<0,0,IF((O105-600000)<500000,0.15*(O105-600000),75000)) -> 75000 | S105: =IF((O105-1100000)<0,0,IF((O105-1100000)<500000,0.19*(O105-1100000),95000)) -> 95000 | T105: =IF((O105-1600000)<0,0,IF((O105-1600000)<1600000,0.21*(O105-1600000),336000)) -> 336000 | U105: =0.24*(O105-3200000) -> 460530.4 | V105: =P105+Q105+R105+S105+T105+U105 -> 1020530.4 | W105: 12 | X105: =V105/W105 -> 85044.2 | Z105: =X105 -> 85044.2 | AA105: 66538.069 | AB105: =Z105-AA105 -> 18506.131
A106: 93 | B106: MUHAMMED AGYE OSOLAFIA | C106: 578828.17 | D106: 12 | E106: =C106*D106 -> 6945938 | G106: 450075.04 | I106: =E106-F106-G106-H106 -> 6495863 | J106: 200000 | K106: 0.2 | L106: =I106*K106 -> 1299172.6 | M106: =J106+L106 -> 1499172.6 | N106: =F106+G106+H106+M106 -> 1949247.6 | O106: =E106-N106 -> 4996690.4 | P106: =IF(O106<300000,0.07*O106,21000) -> 21000 | Q106: =IF((O106-300000)<0,0,IF((O106-300000)<300000,0.11*(O106-300000),33000)) -> 33000 | R106: =IF((O106-600000)<0,0,IF((O106-600000)<500000,0.15*(O106-600000),75000)) -> 75000 | S106: =IF((O106-1100000)<0,0,IF((O106-1100000)<500000,0.19*(O106-1100000),95000)) -> 95000 | T106: =IF((O106-1600000)<0,0,IF((O106-1600000)<1600000,0.21*(O106-1600000),336000)) -> 336000 | U106: =0.24*(O106-3200000) -> 431205.69 | V106: =P106+Q106+R106+S106+T106+U106 -> 991205.69 | W106: 12 | X106: =V106/W106 -> 82600.474 | Z106: =X106 -> 82600.474 | AA106: 66538.069 | AB106: =Z106-AA106 -> 16062.405
A107: 94 | B107: CHRISTIAN MADUABUCHI ODO | C107: 981346.58 | D107: 12 | E107: =C107*D107 -> 11776159 | F107: 90896.225 | G107: 463532.72 | I107: =E107-F107-G107-H107 -> 11221730 | J107: 200000 | K107: 0.2 | L107: =I107*K107 -> 2244346 | M107: =J107+L107 -> 2444346 | N107: =F107+G107+H107+M107 -> 2998775 | O107: =E107-N107 -> 8777384 | P107: =IF(O107<300000,0.07*O107,21000) -> 21000 | Q107: =IF((O107-300000)<0,0,IF((O107-300000)<300000,0.11*(O107-300000),33000)) -> 33000 | R107: =IF((O107-600000)<0,0,IF((O107-600000)<500000,0.15*(O107-600000),75000)) -> 75000 | S107: =IF((O107-1100000)<0,0,IF((O107-1100000)<500000,0.19*(O107-1100000),95000)) -> 95000 | T107: =IF((O107-1600000)<0,0,IF((O107-1600000)<1600000,0.21*(O107-1600000),336000)) -> 336000 | U107: =0.24*(O107-3200000) -> 1338572.2 | V107: =P107+Q107+R107+S107+T107+U107 -> 1898572.2 | W107: 12 | X107: =V107/W107 -> 158214.35 | Z107: =X107 -> 158214.35 | AA107: 59711.115 | AB107: =Z107-AA107 -> 98503.232
...

Sheet New NHF Enrolment
A1: NATIONAL INSTITUTE FOR LEGISLATIVE AND DEMOCRATIC STUDIES
A2: STAFF PAYROLL FOR THE MONTH OF JUNE, 2025
E3: ='[1]FEB 08'!E11/'[1]FEB 08'!M11 -> #REF!
B4: STAFF NAME | C4: DESIGNATION | D4: GRADE LEVEL | E4: OLD CUM BASIC SALARY | F4: NEW BASIC SALARY | G4: OLD NHF | H4: NEW NHF | I4: INCREASE IN NHF | J4: ANNUAL NEW NHF
E5: N | F5: N | G5: N | H5: N | I5: N | J5: N
E6: A | F6: B | G6: I | H6: J | I6: K | J6: M
A7: S/N | B7: DG'S OFFICE | H7: (2.5% of B) | I7: (J-I) | J7: (J-I)
A8: 1 | B8: PROF. ABUBAKAR O. SULAIMAN | C8: DIRECTOR GENERAL | D8: CONSOL | E8: 1659751.2 | F8: 1086777.1 | I8: =H8-G8 -> 0 | J8: =H8*12 -> 0
A9: 2 | B9: RAHEEM USMAN AYIGORO | C9: SA-INFRASTRUCTURE | D9: 16 (9) | E9: 762373.17 | F9: 554669.5 | I9: =H9-G9 -> 0 | J9: =H9*12 -> 0
A10: 3 | B10: MARIAM MOHAMMED BELLO | C10: SA- SPECIAL DUTIES | D10: 16 (9) | E10: 762373.17 | F10: 554669.5 | I10: =H10-G10 -> 0 | J10: =H10*12 -> 0
A11: 4 | B11: DR IKEME ARTHUR J.O | C11: DEPUTY DIRECTOR, M&E | D11: 16 (9) | E11: 762373.17 | F11: 554669.5 | G11: 10293.398 | H11: =0.025*F11 -> 13866.737 | I11: =H11-G11 -> 3573.3396 | J11: =H11*12 -> 166400.85
A12: 5 | B12: ANDRAWUS MUSA | C12: DEP. DIRECTOR, STORES & PROCUREMENT | D12: 16(7) | E12: 716034 | F12: ='[3] FGN 2024 MGT Monthly'!$H$44 -> 523386.5 | G12: 10293.398 | H12: =0.025*F12 -> 13084.663 | I12: =H12-G12 -> 2791.2646 | J12: =H12*12 -> 157015.95
A13: 6 | B13: DR FRANCIS NDUM OJIE | C13: AD, TRAINING & IC./SA TO DG | D13: 15(8) | E13: 601396.83 | F13: 445995.83 | G13: 7859.6313 | H13: =0.025*F13 -> 11149.896 | I13: =H13-G13 -> 3290.2646 | J13: =H13*12 -> 133798.75
A14: 7 | B14: ALI ABDULLAHI | C14: CHIEF ICT OFFICER | D14: 14(11) | E14: 484373.75 | F14: 366417.5 | I14: =H14-G14 -> 0 | J14: =H14*12 -> 0
A15: 8 | B15: EMILY EKHIDE | C15: SENIOR RESEARCH FELLOW | D15: 15(8) | E15: 601396.83 | F15: ='[3] FGN 2024 MGT Monthly'!$I$43 -> 445995.83 | I15: =H15-G15 -> 0 | J15: =H15*12 -> 0
A16: 9 | B16: DORIS DAKDA AARON | C16: RESEARCH FELLOW I | D16: 14(9) | E16: 456622.25 | F16: 347715.92 | I16: =H16-G16 -> 0 | J16: =H16*12 -> 0
A17: 10 | B17: ABDULSALAM S. MUSTAPHA | C17: ASST. DIRECTOR ICT | D17: 15(7) | E17: 582118.08 | F17: 432981.08 | I17: =H17-G17 -> 0 | J17: =H17*12 -> 0
A18: 11 | B18: PERCY TERFA GBAHABO | C18: HEAD, NILDS LIAISON OFFICE | D18: 13(11) | E18: 441804.92 | F18: 337730.83 | I18: =H18-G18 -> 0 | J18: =H18*12 -> 0
A19: 12 | B19: HASSANA AHMED IBRAHIM | C19: PA- TO DG | D19: 13 (10) | E19: 428915.92 | F19: 329044.92 | G19: 5607.1771 | H19: =0.025*F19 -> 8226.1229 | I19: =H19-G19 -> 2618.9458 | J19: =H19*12 -> 98713.475
A20: 13 | B20: IKIP LEBO | C20: ASST CHIEF PROC. OFFICER | D20: 13 (8) | E20: 403138 | F20: 311673.25 | G20: 5967.3062 | H20: =0.025*F20 -> 7791.8313 | I20: =H20-G20 -> 1824.525 | J20: =H20*12 -> 93501.975
A21: 14 | B21: ALABI ADESINA MUHYDEEN | C21: HEAD, NILDS LIAISON OFFICE | D21: 13 (8) | E21: 403138 | F21: 311673.25 | I21: =H21-G21 -> 0 | J21: =H21*12 -> 0
A22: 15 | B22: BASSEY NSONGURUA UDOFIA | C22: PRINC.CONF SEC/PPS | D22: 12(11) | E22: 402278 | F22: ='[3] FGN 2024 MGT Monthly'!$L$40 -> 311094.42 | G22: 5257.5625 | H22: =0.025*F22 -> 7777.3604 | I22: =H22-G22 -> 2519.7979 | J22: =H22*12 -> 93328.325
A23: 16 | B23: ADUGBA RICHARD TERSEER | C23: PRINCIPAL INFO. OFFICER | D23: 12(10) | E23: 390086.5 | F23: 302878.67 | I23: =H23-G23 -> 0 | J23: =H23*12 -> 0
A24: 17 | B24: LUCKY AGWOM | C24: RESEARCH ASSISTANT | D24: 12(8) | E24: 365704 | F24: 286447.08 | I24: =H24-G24 -> 0 | J24: =H24*12 -> 0
A25: 18 | B25: IDRIS IBRAHIM | C25: PRINCIPAL RESEARCH OFFICER | D25: 12(8) | E25: 365704 | F25: 286447.08 | I25: =H25-G25 -> 0 | J25: =H25*12 -> 0
A26: 19 | B26: FARUQ ATOFARATI | C26: PA (SPECIAL DUTIES) TO DG | D26: 10(7) | E26: 293029.67 | F26: 240874.58 | I26: =H26-G26 -> 0 | J26: =H26*12 -> 0
A27: 20 | B27: RASHEEDAT DAIBU | C27: SENIOR INFO. OFFICER | D27: 10(8) | E27: 300965.58 | F27: 240874.58 | I27: =H27-G27 -> 0 | J27: =H27*12 -> 0
A28: 21 | B28: ELIZABETH OGECHUKWU ONYEAKU | C28: ICT OFFICER | D28: 9(10) | E28: 277798 | F28: 227615.75 | I28: =H28-G28 -> 0 | J28: =H28*12 -> 0
A29: 22 | B29: VICTOR ASUKWO | C29: ICT OFFICER | D29: 9(10) | E29: 277798 | F29: 227615.75 | I29: =H29-G29 -> 0 | J29: =H29*12 -> 0
A30: 23 | B30: NNANDI LIVINUS ATURE | C30: RESEARCH ASSISTANT | D30: 9(10) | E30: 277798 | F30: 227615.75 | I30: =H30-G30 -> 0 | J30: =H30*12 -> 0
A31: 24 | B31: ABDULRAHMAN A SULAIMAN | C31: STORE OFFICER | D31: 9(9) | E31: 270481.67 | F31: 222674.58 | I31: =H31-G31 -> 0 | J31: =H31*12 -> 0
A32: 25 | B32: DARE SHEU MAGBON | C32: ADMINISTRATION OFFICER | D32: 9(8) | E32: 263165.33 | F32: 217733.42 | I32: =H32-G32 -> 0 | J32: =H32*12 -> 0
A33: 26 | B33: ABUBAKAR SULAIMAN SODEEQ | C33: ADMINISTRATION OFFICER | D33: 9(8) | E33: 263165.33 | F33: 217733.42 | I33: =H33-G33 -> 0 | J33: =H33*12 -> 0
A34: 27 | B34: JIMOH ADEBAYO ZAKA | C34: ASST. OFFICER/COMM | D34: 9(10) | E34: 277798 | F34: 227615.75 | G34: 3653.5 | H34: =0.025*F34 -> 5690.3938 | I34: =H34-G34 -> 2036.8937 | J34: =H34*12 -> 68284.725
A35: 28 | B35: ABDULMUSHIN TAWFIQ LADAN | C35: ICT OFFICER | D35: 9(8) | E35: 263165.33 | F35: 217733.42 | I35: =H35-G35 -> 0 | J35: =H35*12 -> 0
A36: 29 | B36: MOHAMMED BELLO | C36: PROTOCOL ASSISTANT | D36: 9(8) | E36: 263165.33 | F36: 217733.42 | I36: =H36-G36 -> 0 | J36: =H36*12 -> 0
A37: 30 | B37: HARUNA JIBRIL AMEH | C37: ASST. ADMIN. OFFICER | D37: 8(9) | E37: 230631.92 | F37: 196364.42 | I37: =H37-G37 -> 0 | J37: =H37*12 -> 0
A38: 31 | B38: RAMATU IBRAHIM ABDULRAHEEM | C38: INFORMATION OFFICER | D38: 8(8) | E38: 224459.75 | F38: 192179.42 | I38: =H38-G38 -> 0 | J38: =H38*12 -> 0
B39: TOTAL | C39: 31 | E39: =SUM(E8:E38) -> 14073004 | F39: =SUM(F8:F38) -> 10664632 | G39: =SUM(G8:G38) -> 48931.973 | H39: =SUM(H8:H38) -> 67587.004 | I39: =SUM(I8:I38) -> 18655.031 | J39: =SUM(J8:J38) -> 811044.05
B41: INTERNAL AUDIT
A42: 1 | B42: OSANAIYE DAVID AKINYEMI | C42: DIRECTOR INTERNAL AUDIT | D42: 17(9) | E42: 1435720 | F42: 1086777.1 | I42: =H42-G42 -> 0
A43: 2 | B43: JAMILA ABDUL | C43: SENIOR INTERNAL AUDITOR | D43: 10(8) | E43: 300965.58 | F43: 240874.58 | I43: =H43-G43 -> 0
A44: 3 | B44: IJEOMA EWELUKWA | C44: SENIOR INTERNAL AUDITOR | D44: 10(9) | E44: 308901.5 | F44: 246171.17 | I44: =H44-G44 -> 0
A45: 4 | B45: YUSUF YUSUF DAYYABU | C45: INERNAL AUDIT OFFICER | D45: 9(8) | E45: 263165.33 | F45: 217733.42 | I45: =H45-G45 -> 0
C46: 4 | E46: =SUM(E42:E45) -> 2308752.4 | F46: =SUM(F42:F45) -> 1791556.2 | G46: =SUM(G42:G45) -> 0 | H46: =SUM(H42:H45) -> 0 | I46: =SUM(I42:I45) -> 0 | J46: =SUM(J42:J45) -> 0
B48: LEG. SUPPORT SEVICES
A49: 1 | B49: BETHEL UZOMA IHUGBA | C49: DEPUTY DIRECTOR, LEGAL RESEARCH | D49: 16(9) | E49: 762373.17 | F49: 554669.5 | I49: =H49-G49 -> 0
A50: 2 | B50: OGUCHE SAMUEL | C50: SNR RESEARCH FELLOW | D50: 15(9) | E50: 620675.58 | F50: 459010.5 | I50: =H50-G50 -> 0
A51: 3 | B51: IBRAHIM USMAN | C51: SNR RESEARCH FELLOW | D51: 15(9) | E51: 620675.58 | F51: 459010.5 | G51: 8380.2271 | H51: =0.025*F51 -> 11475.263 | I51: =H51-G51 -> 3095.0354 | J51: =H51*12 -> 137703.15
A52: 4 | B52: DR MOHAMMED O. AMALI | C52: SNR RESEARCH FELLOW | D52: 15(8) | E52: 601396.83 | F52: 445995.83 | I52: =H52-G52 -> 0
A53: 5 | B53: YAHAYA SHAMSU | C53: SNR RESEARCH FELLOW | D53: 15(7) | E53: 582118.08 | F53: 432981.08 | I53: =H53-G53 -> 0
A54: 6 | B54: BILKIS S. LAWAL-GAMBARI | C54: RESEARCH OFFICER | D54: 10(9) | E54: 308901.5 | F54: 246171.17 | I54: =H54-G54 -> 0
A55: 7 | B55: ZAINAB AKINDE | C55: RESEARCH OFFICER | D55: 9(9) | E55: 270481.67 | F55: 222674.58 | I55: =H55-G55 -> 0
A56: 8 | B56: GUNAT NANSAK MARK | C56: RESEARCH OFFICER | D56: 9(9) | E56: 270481.67 | F56: 222674.58 | I56: =H56-G56 -> 0
B57: TOTAL | C57: 8 | E57: =SUM(E49:E56) -> 4037104.1 | F57: =SUM(F49:F56) -> 3043187.8 | G57: =SUM(G49:G56) -> 8380.2271 | H57: =SUM(H49:H56) -> 11475.263 | I57: =SUM(I49:I56) -> 3095.0354 | J57: =SUM(J49:J56) -> 137703.15
B59: LEGAL SERVICES
A60: 1 | B60: DR SHUAIBU DANWANKA | C60: DIRECTOR LEGAL SERVICES | D60: 17(9) | E60: 1435720 | F60: 1086777.1 | I60: =H60-G60 -> 0
A61: 2 | B61: ABDULSALAM BAKO | C61: MANAGER, LEGAL SERVICES | D61: 15 (9) | E61: 620675.58 | F61: 459010.5 | I61: =H61-G61 -> 0
B62: TOTAL | C62: 2 | E62: =SUM(E60:E61) -> 2056395.6 | F62: =SUM(F60:F61) -> 1545787.6 | G62: =SUM(G60:G61) -> 0 | H62: =SUM(H60:H61) -> 0 | I62: =SUM(I60:I61) -> 0 | J62: =SUM(J60:J61) -> 0
B64: DEMOCRACY & GOVERNANCE
A65: 1 | B65: NGARA CHRISTOPHER OCHANJA | C65: DEP DIR DEM & GOVERNANCE | D65: 16(9) | E65: 762373.17 | F65: 554669.5 | G65: 10293.398 | H65: =0.025*F65 -> 13866.737 | I65: =H65-G65 -> 3573.3396 | J65: =H65*12 -> 166400.85
A66: 2 | B66: EJALONIBU GANIYU LAYI | C66: RESEARCH FELLOW 1 | D66: 14(9) | E66: 456622.25 | F66: 347715.92 | I66: =H66-G66 -> 0
A67: 3 | B67: UDEFUNA NNADOZIE PATRICK | C67: RESEARCH OFFICER | D67: 12(9) | E67: 377895.17 | F67: 294662.92 | I67: =H67-G67 -> 0
A68: 4 | B68: SHAFIU YAHYA MIKAIL | C68: PRINCIPAL RESEARCH OFFICER | D68: 12(9) | E68: 377895.17 | F68: 294662.92 | I68: =H68-G68 -> 0
A69: 5 | B69: HASSAN YERIMA | C69: PRINCIPAL RESEARCH OFFICER | D69: 12(9) | E69: 377895.17 | F69: 294662.92 | I69: =H69-G69 -> 0
A70: 6 | B70: HAUWA PATE SADIQ | C70: PRINCIPAL PROGRAMME OFFICER | D70: 12(10) | E70: 390086.5 | F70: 302878.67 | I70: =H70-G70 -> 0
A71: 7 | B71: KOLAPO Q. ABAYOMI | C71: RESEARCH OFFICER | D71: 10(9) | E71: 308901.5 | F71: 246171.17 | I71: =H71-G71 -> 0
B72: TOTAL | C72: 7 | E72: =SUM(E65:E71) -> 3051668.9 | F72: =SUM(F65:F71) -> 2335424 | G72: =SUM(G65:G71) -> 10293.398 | H72: =SUM(H65:H71) -> 13866.737 | I72: =SUM(I65:I71) -> 3573.3396 | J72: =SUM(J65:J71) -> 166400.85
B74: DEPARTMENT OF STUDIES
A75: 1 | B75: DR ASIMIYU G. ABIOLA | C75: DIRECTOR POST GRADUATE | D75: 17(9) | E75: 1435720 | F75: 1086777.1 | I75: =H75-G75 -> 0
A76: 2 | B76: DR. HADIZA SAIDU | C76: ASSISTANT DIRECTOR | D76: 15(7) | E76: 582118.08 | F76: 445995.83 | I76: =H76-G76 -> 0
A77: 3 | B77: ANTHONY EDET | C77: CHIEF PROGRAMMES OFFICER | D77: 14(10) | E77: 470498 | F77: 357066.67 | G77: 6154.3229 | H77: =0.025*F77 -> 8926.6667 | I77: =H77-G77 -> 2772.3438 | J77: =H77*12 -> 107120
A78: 4 | B78: IGWE STACY | C78: PRINC. PROGRAMME OFFICER | D78: 12(8) | E78: 365703.83 | F78: 286447.08 | I78: =H78-G78 -> 0
A79: 5 | B79: OLANIYAN TAIWO ABINBOLA | C79: PROGRAMME OFFICER | D79: 9(8) | E79: 263165.33 | F79: 222674.58 | I79: =H79-G79 -> 0
A80: 6 | B80: AMINAT JUMOKE SULAIMON | C80: AST. PROGRAMME OFFICER | D80: 8(9) | E80: 230631.92 | F80: 196364.42 | I80: =H80-G80 -> 0
B81: TOTAL | C81: 6 | E81: =SUM(E75:E80) -> 3347837.2 | F81: =SUM(F75:F80) -> 2595325.7 | G81: =SUM(G75:G80) -> 6154.3229 | H81: =SUM(H75:H80) -> 8926.6667 | I81: =SUM(I75:I80) -> 2772.3438 | J81: =SUM(J75:J80) -> 107120
B83: ECON. DEV. & SOC. RESEARCH
A84: 1 | B84: DR AUGUSTINE C. OSIGWE | C84: SNR RESEARCH FELLOW | D84: 17(7) | E84: ='[4]Annual & Monthly'!$H$44 -> 1352042.7 | F84: 1025768.3 | G84: 18254.975 | H84: =0.025*F84 -> 25644.208 | I84: =H84-G84 -> 7389.2333 | J84: =H84*12 -> 307730.5
A85: 2 | B85: TERFA WILLIAMS ABRAHAM | C85: DEP. DIRECTOR ECON & SOCIAL RES | D85: 16(7) | E85: 716034 | F85: 523386.5 | I85: =H85-G85 -> 0
A86: 3 | B86: OMOJU OLUWASOLA EMMANUEL | C86: SNR RESEARCH FELLOW | D86: 15(8) | E86: 601396.83 | F86: 445995.83 | I86: =H86-G86 -> 0
A87: 4 | B87: IBE EZECHI CYRIACUS | C87: RESEARCH FELLOW 1 | D87: 14(9) | E87: 456622.25 | F87: 442746.5 | I87: =H87-G87 -> 0
A88: 5 | B88: OSIKHEN LEO IGBANOI | C88: RESEARCH FELLOW 1 | D88: 14(9) | E88: 456622.25 | F88: 442746.5 | I88: =H88-G88 -> 0
A89: 6 | B89: OKUNGBOWA OSARETIN GODSPOWER | C89: RESEARCH FELLOW 1 | D89: 14(8) | E89: 442746.5 | F89: 428870.75 | I89: =H89-G89 -> 0
A90: 7 | B90: YUSUF IBRAHIM | C90: PRINCIPAL RESEARCH OFFICER | D90: 12(9) | E90: 377895.17 | F90: 294662.92 | I90: =H90-G90 -> 0
A91: 8 | B91: MUSTAPHA RAFIU AYOBANJI | C91: RESEARCH FELLOW 11 | D91: 13(8) | E91: 403137.92 | F91: 311673.25 | G91: 5259.7437 | H91: =0.025*F91 -> 7791.8313 | I91: =H91-G91 -> 2532.0875 | J91: =H91*12 -> 93501.975
A92: 9 | B92: MARYAM MUSA SADA | C92: ASSIT. RESEARCH OFFICER | D92: 10(9) | E92: 308901.5 | F92: 246171.17 | I92: =H92-G92 -> 0
A93: 10 | B93: CHARITY EZENWAJIOBI | C93: REASEARCH. ASST. | D93: 8(10) | E93: 236804.08 | F93: 200549.42 | I93: =H93-G93 -> 0
B94: TOTAL | C94: 10 | E94: =SUM(E84:E93) -> 5352203.2 | F94: =SUM(F84:F93) -> 4362571.2 | G94: =SUM(G84:G93) -> 23514.719 | H94: =SUM(H84:H93) -> 33436.04 | I94: =SUM(I84:I93) -> 9921.3208 | J94: =SUM(J84:J93) -> 401232.47
B96: TRAINING & INT''L COOP
A97: 1 | B97: AKINSANMI ADEJOKE OLUKEMI | C97: Ag. DIR. TRAINING & IC | D97: 17(8) | E97: 1393881.3 | F97: 1056272.8 | G97: 18254.975 | H97: =0.025*F97 -> 26406.821 | I97: =H97-G97 -> 8151.8458 | J97: =H97*12 -> 316881.85
A98: 2 | B98: MOHAMMED R. ADAMU | C98: CHIEF TRAINING OFFICER | D98: 14(10) | E98: 470498 | F98: 357066.67 | I98: =H98-G98 -> 0 | J98: =H98*12 -> 0
A99: 3 | B99: EROMOSELE OMONIGBO | C99: ASSIST. CHIEF PERSONNEL OFFICER | D99: 13(8) | E99: 403137.92 | F99: 311673.25 | G99: 5967.3062 | H99: =0.025*F99 -> 7791.8313 | I99: =H99-G99 -> 1824.525 | J99: =H99*12 -> 93501.975
A100: 4 | B100: OKECHUKWU UCHENNA HULDA | C100: PRINCIPALTRAINING OFFICER | D100: 12(10) | E100: 390086.5 | F100: 302878.67 | I100: =H100-G100 -> 0 | J100: =H100*12 -> 0
A101: 5 | B101: TASSNEEM IBRAHIM | C101: SENIOR PROGRAMME OFFICER | D101: 10(9) | E101: 308901.5 | F101: 246171.17 | I101: =H101-G101 -> 0 | J101: =H101*12 -> 0
B102: TOTAL | C102: 5 | E102: =SUM(E97:E101) -> 2966505.2 | F102: =SUM(F97:F101) -> 2274062.6 | G102: =SUM(G97:G101) -> 24222.281 | H102: =SUM(H97:H101) -> 34198.652 | I102: =SUM(I97:I101) -> 9976.3708 | J102: =SUM(J97:J101) -> 410383.82
B104: LIBRARY & DOCUMENTATION
A105: 1 | B105: DR MAIMUNA IZAH | C105: INSITUTE LIBRARIAN | D105: 17(9) | E105: 1435720 | F105: 1086777.1 | G105: 0 | I105: =H105-G105 -> 0
A106: 2 | B106: CATHERINE E. IKOKOH | C106: SNR RESEARCH FELLOW DOCU | D106: 16(9) | E106: 762373.17 | F106: 554669.5 | G106: 10293.398 | H106: =0.025*F106 -> 13866.737 | I106: =H106-G106 -> 3573.3396 | J106: =H106*12 -> 166400.85
A107: 3 | B107: ALIYU SANNI ABUBAKAR | C107: RESEARCH FELLOW 11 DATA & DOCU | D107: 13(11) | E107: 441804.92 | F107: 337730.83 | G107: 5954.6104 | H107: =0.025*F107 -> 8443.2708 | I107: =H107-G107 -> 2488.6604 | J107: =H107*12 -> 101319.25
A108: 4 | B108: CHINAKO N. ASOGWA | C108: RESEARCH FELLOW 11 DATA & DOCU | D108: 13(11) | E108: 441804.92 | F108: 337730.83 | I108: =H108-G108 -> 0
...

Sheet PAYE of NHF Enrol
A1: NATIONAL INSTITUTE FOR LEGISLATIVE AND DEMOCRATIC STUDIES
A2: NATIONAL ASSEMBLY ABUJA
A3: TAX COMPUTATION FOR 2022
A4: S/NO | B4: NAME | C4: MONTHLY TOTAL SALARY | D4: NO OF MONTHS | E4: ANNUAL SALARY GROSSED UP | F4: NATIONAL HOUSING SCHEME = 2.5% OF BASIC SALARY | G4: PENSION CONTRIBUTION = 8% OF CONSOLIDATED | H4: NHIS | I4: NET SALARY (EXC OF CRA) | M4: CRA=#200,000+(20% 0F NET SALARY (EXC OF CRA) | N4: TOTAL RELIEF | O4: CHARGEABLE INCOME | P4: FIRST N300,000 @ 7% | Q4: NEXT N300,000 @ 11% | R4: NEXT N500,000 @ 15% | S4: NEXT N500,000@ 19% | T4: NEXT N1,600,000 @ 21% | U4: ABOVE N3,200,000 @ 24% | V4: ANNUAL TAX PAYABLE | X4: MONTHLY TAX PAYABLE | Y4: MINIMUM TAX PAYABLE | Z4: NEW ACTUAL TAX PAYABLE | AA4: OLD ACTUAL TAX PAYABLE | AB4: INCREASE IN PAYE
A5: 1 | B5: DG'S OFFICE
A6: 3 | B6: PROF. ABUBAKAR O. SULAIMAN | C6: 2246372.1 | D6: 12 | E6: =C6*D6 -> 26956465 | G6: 0 | I6: =E6-F6-G6-H6 -> 26956465 | J6: 200000 | K6: 0.2 | L6: =I6*K6 -> 5391293 | M6: =J6+L6 -> 5591293 | N6: =F6+G6+H6+M6 -> 5591293 | O6: =E6-N6 -> 21365172 | P6: =IF(O6<300000,0.07*O6,21000) -> 21000 | Q6: =IF((O6-300000)<0,0,IF((O6-300000)<300000,0.11*(O6-300000),33000)) -> 33000 | R6: =IF((O6-600000)<0,0,IF((O6-600000)<500000,0.15*(O6-600000),75000)) -> 75000 | S6: =IF((O6-1100000)<0,0,IF((O6-1100000)<500000,0.19*(O6-1100000),95000)) -> 95000 | T6: =IF((O6-1600000)<0,0,IF((O6-1600000)<1600000,0.21*(O6-1600000),336000)) -> 336000 | U6: =24%*(O6-3200000) -> 4359641.3 | V6: =P6+Q6+R6+S6+T6+U6 -> 4919641.3 | W6: 12 | X6: =V6/W6 -> 409970.11 | Z6: =X6 -> 409970.11 | AA6: 350184.01 | AB6: =Z6-AA6 -> 59786.096
A7: 4 | B7: RAHEEM USMAN AYIGORO | C7: 1095306.8 | D7: 12 | E7: =C7*D7 -> 13143681 | G7: 869094.48 | I7: =E7-F7-G7-H7 -> 12274587 | J7: 200000 | K7: 0.2 | L7: =I7*K7 -> 2454917.3 | M7: =J7+L7 -> 2654917.3 | N7: =F7+G7+H7+M7 -> 3524011.8 | O7: =E7-N7 -> 9619669.2 | P7: =IF(O7<300000,0.07*O7,21000) -> 21000 | Q7: =IF((O7-300000)<0,0,IF((O7-300000)<300000,0.11*(O7-300000),33000)) -> 33000 | R7: =IF((O7-600000)<0,0,IF((O7-600000)<500000,0.15*(O7-600000),75000)) -> 75000 | S7: =IF((O7-1100000)<0,0,IF((O7-1100000)<500000,0.19*(O7-1100000),95000)) -> 95000 | T7: =IF((O7-1600000)<0,0,IF((O7-1600000)<1600000,0.21*(O7-1600000),336000)) -> 336000 | U7: =24%*(O7-3200000) -> 1540720.6 | V7: =P7+Q7+R7+S7+T7+U7 -> 2100720.6 | W7: 12 | X7: =V7/W7 -> 175060.05 | Z7: =X7 -> 175060.05 | AA7: 149812.26 | AB7: =Z7-AA7 -> 25247.788
A8: 5 | B8: MARIAM MOHAMMED BELLO | C8: 1295306.8 | D8: 12 | E8: =C8*D8 -> 15543681 | G8: 0 | I8: =E8-F8-G8-H8 -> 15543681 | J8: 200000 | K8: 0.2 | L8: =I8*K8 -> 3108736.2 | M8: =J8+L8 -> 3308736.2 | N8: =F8+G8+H8+M8 -> 3308736.2 | O8: =E8-N8 -> 12234945 | P8: =IF(O8<300000,0.07*O8,21000) -> 21000 | Q8: =IF((O8-300000)<0,0,IF((O8-300000)<300000,0.11*(O8-300000),33000)) -> 33000 | R8: =IF((O8-600000)<0,0,IF((O8-600000)<500000,0.15*(O8-600000),75000)) -> 75000 | S8: =IF((O8-1100000)<0,0,IF((O8-1100000)<500000,0.19*(O8-1100000),95000)) -> 95000 | T8: =IF((O8-1600000)<0,0,IF((O8-1600000)<1600000,0.21*(O8-1600000),336000)) -> 336000 | U8: =24%*(O8-3200000) -> 2168386.8 | V8: =P8+Q8+R8+S8+T8+U8 -> 2728386.8 | W8: 12 | X8: =V8/W8 -> 227365.56 | Z8: =X8 -> 227365.56 | AA8: 199922.31 | AB8: =Z8-AA8 -> 27443.248
A9: 6 | B9: DR IKEME ARTHUR J.O | C9: 1085306.8 | D9: 12 | E9: =C9*D9 -> 13023681 | F9: 166400.85 | G9: 869094.48 | I9: =E9-F9-G9-H9 -> 11988186 | J9: 200000 | K9: 0.2 | L9: =I9*K9 -> 2397637.1 | M9: =J9+L9 -> 2597637.1 | N9: =F9+G9+H9+M9 -> 3633132.5 | O9: =E9-N9 -> 9390548.5 | P9: =IF(O9<300000,0.07*O9,21000) -> 21000 | Q9: =IF((O9-300000)<0,0,IF((O9-300000)<300000,0.11*(O9-300000),33000)) -> 33000 | R9: =IF((O9-600000)<0,0,IF((O9-600000)<500000,0.15*(O9-600000),75000)) -> 75000 | S9: =IF((O9-1100000)<0,0,IF((O9-1100000)<500000,0.19*(O9-1100000),95000)) -> 95000 | T9: =IF((O9-1600000)<0,0,IF((O9-1600000)<1600000,0.21*(O9-1600000),336000)) -> 336000 | U9: =24%*(O9-3200000) -> 1485731.6 | V9: =P9+Q9+R9+S9+T9+U9 -> 2045731.6 | W9: 12 | X9: =V9/W9 -> 170477.64 | Z9: =X9 -> 170477.64 | AA9: 147687.53 | AB9: =Z9-AA9 -> 22790.11
A10: 7 | B10: ANDRAWUS MUSA | C10: 992711.08 | D10: 12 | E10: =C10*D10 -> 11912533 | F10: 157015.95 | G10: 818602.64 | I10: =E10-F10-G10-H10 -> 10936914 | J10: 200000 | K10: 0.2 | L10: =I10*K10 -> 2187382.9 | M10: =J10+L10 -> 2387382.9 | N10: =F10+G10+H10+M10 -> 3363001.5 | O10: =E10-N10 -> 8549531.5 | P10: =IF(O10<300000,0.07*O10,21000) -> 21000 | Q10: =IF((O10-300000)<0,0,IF((O10-300000)<300000,0.11*(O10-300000),33000)) -> 33000 | R10: =IF((O10-600000)<0,0,IF((O10-600000)<500000,0.15*(O10-600000),75000)) -> 75000 | S10: =IF((O10-1100000)<0,0,IF((O10-1100000)<500000,0.19*(O10-1100000),95000)) -> 95000 | T10: =IF((O10-1600000)<0,0,IF((O10-1600000)<1600000,0.21*(O10-1600000),336000)) -> 336000 | U10: =24%*(O10-3200000) -> 1283887.6 | V10: =P10+Q10+R10+S10+T10+U10 -> 1843887.6 | W10: 12 | X10: =V10/W10 -> 153657.3 | Z10: =X10 -> 153657.3 | AA10: 129694.7 | AB10: =Z10-AA10 -> 23962.602
A11: 8 | B11: DR FRANCIS NDUM OJIE | C11: 1082595.5 | D11: 12 | E11: =C11*D11 -> 12991146 | F11: 133798.75 | G11: 693691.68 | I11: =E11-F11-G11-H11 -> 12163656 | J11: 200000 | K11: 0.2 | L11: =I11*K11 -> 2432731.1 | M11: =J11+L11 -> 2632731.1 | N11: =F11+G11+H11+M11 -> 3460221.5 | O11: =E11-N11 -> 9530924.5 | P11: =IF(O11<300000,0.07*O11,21000) -> 21000 | Q11: =IF((O11-300000)<0,0,IF((O11-300000)<300000,0.11*(O11-300000),33000)) -> 33000 | R11: =IF((O11-600000)<0,0,IF((O11-600000)<500000,0.15*(O11-600000),75000)) -> 75000 | S11: =IF((O11-1100000)<0,0,IF((O11-1100000)<500000,0.19*(O11-1100000),95000)) -> 95000 | T11: =IF((O11-1600000)<0,0,IF((O11-1600000)<1600000,0.21*(O11-1600000),336000)) -> 336000 | U11: =24%*(O11-3200000) -> 1519421.9 | V11: =P11+Q11+R11+S11+T11+U11 -> 2079421.9 | W11: 12 | X11: =V11/W11 -> 173285.16 | Z11: =X11 -> 173285.16 | AA11: 150463.11 | AB11: =Z11-AA11 -> 22822.046
A12: 9 | B12: ALI ABDULLAHI | C12: 659657 | D12: 12 | E12: =C12*D12 -> 7915884 | G12: 566070.72 | I12: =E12-F12-G12-H12 -> 7349813.3 | J12: 200000 | K12: 0.2 | L12: =I12*K12 -> 1469962.7 | M12: =J12+L12 -> 1669962.7 | N12: =F12+G12+H12+M12 -> 2236033.4 | O12: =E12-N12 -> 5679850.6 | P12: =IF(O12<300000,0.07*O12,21000) -> 21000 | Q12: =IF((O12-300000)<0,0,IF((O12-300000)<300000,0.11*(O12-300000),33000)) -> 33000 | R12: =IF((O12-600000)<0,0,IF((O12-600000)<500000,0.15*(O12-600000),75000)) -> 75000 | S12: =IF((O12-1100000)<0,0,IF((O12-1100000)<500000,0.19*(O12-1100000),95000)) -> 95000 | T12: =IF((O12-1600000)<0,0,IF((O12-1600000)<1600000,0.21*(O12-1600000),336000)) -> 336000 | U12: =24%*(O12-3200000) -> 595164.15 | V12: =P12+Q12+R12+S12+T12+U12 -> 1155164.1 | W12: 12 | X12: =V12/W12 -> 96263.679 | Z12: =X12 -> 96263.679 | AA12: 77666.446 | AB12: =Z12-AA12 -> 18597.233
A13: 10 | B13: EMILY EKHIDE | C13: 1032595.5 | D13: 12 | E13: =C13*D13 -> 12391146 | G13: 693691.68 | I13: =E13-F13-G13-H13 -> 11697454 | J13: 200000 | K13: 0.2 | L13: =I13*K13 -> 2339490.9 | M13: =J13+L13 -> 2539490.9 | N13: =F13+G13+H13+M13 -> 3233182.5 | O13: =E13-N13 -> 9157963.5 | P13: =IF(O13<300000,0.07*O13,21000) -> 21000 | Q13: =IF((O13-300000)<0,0,IF((O13-300000)<300000,0.11*(O13-300000),33000)) -> 33000 | R13: =IF((O13-600000)<0,0,IF((O13-600000)<500000,0.15*(O13-600000),75000)) -> 75000 | S13: =IF((O13-1100000)<0,0,IF((O13-1100000)<500000,0.19*(O13-1100000),95000)) -> 95000 | T13: =IF((O13-1600000)<0,0,IF((O13-1600000)<1600000,0.21*(O13-1600000),336000)) -> 336000 | U13: =24%*(O13-3200000) -> 1429911.2 | V13: =P13+Q13+R13+S13+T13+U13 -> 1989911.2 | W13: 12 | X13: =V13/W13 -> 165825.94 | Z13: =X13 -> 165825.94 | AA13: 141011.99 | AB13: =Z13-AA13 -> 24813.947
A14: 11 | B14: DORIS DAKDA AARON | C14: 948165.25 | D14: 12 | E14: =C14*D14 -> 11377983 | G14: 535838.64 | I14: =E14-F14-G14-H14 -> 10842144 | J14: 200000 | K14: 0.2 | L14: =I14*K14 -> 2168428.9 | M14: =J14+L14 -> 2368428.9 | N14: =F14+G14+H14+M14 -> 2904267.5 | O14: =E14-N14 -> 8473715.5 | P14: =IF(O14<300000,0.07*O14,21000) -> 21000 | Q14: =IF((O14-300000)<0,0,IF((O14-300000)<300000,0.11*(O14-300000),33000)) -> 33000 | R14: =IF((O14-600000)<0,0,IF((O14-600000)<500000,0.15*(O14-600000),75000)) -> 75000 | S14: =IF((O14-1100000)<0,0,IF((O14-1100000)<500000,0.19*(O14-1100000),95000)) -> 95000 | T14: =IF((O14-1600000)<0,0,IF((O14-1600000)<1600000,0.21*(O14-1600000),336000)) -> 336000 | U14: =24%*(O14-3200000) -> 1265691.7 | V14: =P14+Q14+R14+S14+T14+U14 -> 1825691.7 | W14: 12 | X14: =V14/W14 -> 152140.98 | Z14: =X14 -> 152140.98 | AA14: 131753.41 | AB14: =Z14-AA14 -> 20387.568
A15: 12 | B15: ABDULSALAM S. MUSTAPHA | C15: 830713.92 | D15: 12 | E15: =C15*D15 -> 9968567 | G15: 672685.36 | I15: =E15-F15-G15-H15 -> 9295881.6 | J15: 200000 | K15: 0.2 | L15: =I15*K15 -> 1859176.3 | M15: =J15+L15 -> 2059176.3 | N15: =F15+G15+H15+M15 -> 2731861.7 | O15: =E15-N15 -> 7236705.3 | P15: =IF(O15<300000,0.07*O15,21000) -> 21000 | Q15: =IF((O15-300000)<0,0,IF((O15-300000)<300000,0.11*(O15-300000),33000)) -> 33000 | R15: =IF((O15-600000)<0,0,IF((O15-600000)<500000,0.15*(O15-600000),75000)) -> 75000 | S15: =IF((O15-1100000)<0,0,IF((O15-1100000)<500000,0.19*(O15-1100000),95000)) -> 95000 | T15: =IF((O15-1600000)<0,0,IF((O15-1600000)<1600000,0.21*(O15-1600000),336000)) -> 336000 | U15: =24%*(O15-3200000) -> 968809.27 | V15: =P15+Q15+R15+S15+T15+U15 -> 1528809.3 | W15: 12 | X15: =V15/W15 -> 127400.77 | Z15: =X15 -> 127400.77 | AA15: 106452 | AB15: =Z15-AA15 -> 20948.773
A16: 13 | B16: PERCY TERFA GBAHABO | C16: 661351.33 | D16: 12 | E16: =C16*D16 -> 7936216 | G16: 519697.28 | I16: =E16-F16-G16-H16 -> 7416518.7 | J16: 200000 | K16: 0.2 | L16: =I16*K16 -> 1483303.7 | M16: =J16+L16 -> 1683303.7 | N16: =F16+G16+H16+M16 -> 2203001 | O16: =E16-N16 -> 5733215 | P16: =IF(O16<300000,0.07*O16,21000) -> 21000 | Q16: =IF((O16-300000)<0,0,IF((O16-300000)<300000,0.11*(O16-300000),33000)) -> 33000 | R16: =IF((O16-600000)<0,0,IF((O16-600000)<500000,0.15*(O16-600000),75000)) -> 75000 | S16: =IF((O16-1100000)<0,0,IF((O16-1100000)<500000,0.19*(O16-1100000),95000)) -> 95000 | T16: =IF((O16-1600000)<0,0,IF((O16-1600000)<1600000,0.21*(O16-1600000),336000)) -> 336000 | U16: =24%*(O16-3200000) -> 607971.59 | V16: =P16+Q16+R16+S16+T16+U16 -> 1167971.6 | W16: 12 | X16: =V16/W16 -> 97330.966 | Z16: =X16 -> 97330.966 | AA16: 77470.374 | AB16: =Z16-AA16 -> 19860.592
A17: 14 | B17: HASSANA AHMED IBRAHIM | C17: 846725.08 | D17: 12 | E17: =C17*D17 -> 10160701 | F17: 98713.475 | G17: 505656.08 | I17: =E17-F17-G17-H17 -> 9556331.4 | J17: 200000 | K17: 0.2 | L17: =I17*K17 -> 1911266.3 | M17: =J17+L17 -> 2111266.3 | N17: =F17+G17+H17+M17 -> 2715635.8 | O17: =E17-N17 -> 7445065.2 | P17: =IF(O17<300000,0.07*O17,21000) -> 21000 | Q17: =IF((O17-300000)<0,0,IF((O17-300000)<300000,0.11*(O17-300000),33000)) -> 33000 | R17: =IF((O17-600000)<0,0,IF((O17-600000)<500000,0.15*(O17-600000),75000)) -> 75000 | S17: =IF((O17-1100000)<0,0,IF((O17-1100000)<500000,0.19*(O17-1100000),95000)) -> 95000 | T17: =IF((O17-1600000)<0,0,IF((O17-1600000)<1600000,0.21*(O17-1600000),336000)) -> 336000 | U17: =24%*(O17-3200000) -> 1018815.6 | V17: =P17+Q17+R17+S17+T17+U17 -> 1578815.6 | W17: 12 | X17: =V17/W17 -> 131567.97 | Z17: =X17 -> 131567.97 | AA17: 113474.9 | AB17: =Z17-AA17 -> 18093.066
A18: 15 | B18: IKIP LEBO | C18: 567472.75 | D18: 12 | E18: =C18*D18 -> 6809673 | F18: 93501.975 | G18: 477573.84 | I18: =E18-F18-G18-H18 -> 6238597.2 | J18: 200000 | K18: 0.2 | L18: =I18*K18 -> 1247719.4 | M18: =J18+L18 -> 1447719.4 | N18: =F18+G18+H18+M18 -> 2018795.3 | O18: =E18-N18 -> 4790877.7 | P18: =IF(O18<300000,0.07*O18,21000) -> 21000 | Q18: =IF((O18-300000)<0,0,IF((O18-300000)<300000,0.11*(O18-300000),33000)) -> 33000 | R18: =IF((O18-600000)<0,0,IF((O18-600000)<500000,0.15*(O18-600000),75000)) -> 75000 | S18: =IF((O18-1100000)<0,0,IF((O18-1100000)<500000,0.19*(O18-1100000),95000)) -> 95000 | T18: =IF((O18-1600000)<0,0,IF((O18-1600000)<1600000,0.21*(O18-1600000),336000)) -> 336000 | U18: =24%*(O18-3200000) -> 381810.66 | V18: =P18+Q18+R18+S18+T18+U18 -> 941810.66 | W18: 12 | X18: =V18/W18 -> 78484.222 | Z18: =X18 -> 78484.222 | AA18: 61040.235 | AB18: =Z18-AA18 -> 17443.986
A19: 16 | B19: ALABI ADESINA MUHYDEEN | C19: 617472.75 | D19: 12 | E19: =C19*D19 -> 7409673 | F19: 0 | G19: 477573.84 | I19: =E19-F19-G19-H19 -> 6932099.2 | J19: 200000 | K19: 0.2 | L19: =I19*K19 -> 1386419.8 | M19: =J19+L19 -> 1586419.8 | N19: =F19+G19+H19+M19 -> 2063993.7 | O19: =E19-N19 -> 5345679.3 | P19: =IF(O19<300000,0.07*O19,21000) -> 21000 | Q19: =IF((O19-300000)<0,0,IF((O19-300000)<300000,0.11*(O19-300000),33000)) -> 33000 | R19: =IF((O19-600000)<0,0,IF((O19-600000)<500000,0.15*(O19-600000),75000)) -> 75000 | S19: =IF((O19-1100000)<0,0,IF((O19-1100000)<500000,0.19*(O19-1100000),95000)) -> 95000 | T19: =IF((O19-1600000)<0,0,IF((O19-1600000)<1600000,0.21*(O19-1600000),336000)) -> 336000 | U19: =24%*(O19-3200000) -> 514963.04 | V19: =P19+Q19+R19+S19+T19+U19 -> 1074963 | W19: 12 | X19: =V19/W19 -> 89580.253 | Z19: =X19 -> 89580.253 | AA19: 70640.235 | AB19: =Z19-AA19 -> 18940.018
A20: 17 | B20: BASSEY NSONGURUA UDOFIA | C20: 806497.17 | D20: 12 | E20: =C20*D20 -> 9677966 | F20: 93328.325 | G20: 476637.28 | I20: =E20-F20-G20-H20 -> 9108000.4 | J20: 200000 | K20: 0.2 | L20: =I20*K20 -> 1821600.1 | M20: =J20+L20 -> 2021600.1 | N20: =F20+G20+H20+M20 -> 2591565.7 | O20: =E20-N20 -> 7086400.3 | P20: =IF(O20<300000,0.07*O20,21000) -> 21000 | Q20: =IF((O20-300000)<0,0,IF((O20-300000)<300000,0.11*(O20-300000),33000)) -> 33000 | R20: =IF((O20-600000)<0,0,IF((O20-600000)<500000,0.15*(O20-600000),75000)) -> 75000 | S20: =IF((O20-1100000)<0,0,IF((O20-1100000)<500000,0.19*(O20-1100000),95000)) -> 95000 | T20: =IF((O20-1600000)<0,0,IF((O20-1600000)<1600000,0.21*(O20-1600000),336000)) -> 336000 | U20: =24%*(O20-3200000) -> 932736.08 | V20: =P20+Q20+R20+S20+T20+U20 -> 1492736.1 | W20: 12 | X20: =V20/W20 -> 124394.67 | Z20: =X20 -> 124394.67 | AA20: 106297.15 | AB20: =Z20-AA20 -> 18097.523
A21: 18 | B21: ADUGBA RICHARD TERSEER | C21: 692662.67 | D21: 12 | E21: =C21*D21 -> 8311952 | G21: 463356.16 | I21: =E21-F21-G21-H21 -> 7848595.8 | J21: 200000 | K21: 0.2 | L21: =I21*K21 -> 1569719.2 | M21: =J21+L21 -> 1769719.2 | N21: =F21+G21+H21+M21 -> 2233075.3 | O21: =E21-N21 -> 6078876.7 | P21: =IF(O21<300000,0.07*O21,21000) -> 21000 | Q21: =IF((O21-300000)<0,0,IF((O21-300000)<300000,0.11*(O21-300000),33000)) -> 33000 | R21: =IF((O21-600000)<0,0,IF((O21-600000)<500000,0.15*(O21-600000),75000)) -> 75000 | S21: =IF((O21-1100000)<0,0,IF((O21-1100000)<500000,0.19*(O21-1100000),95000)) -> 95000 | T21: =IF((O21-1600000)<0,0,IF((O21-1600000)<1600000,0.21*(O21-1600000),336000)) -> 336000 | U21: =24%*(O21-3200000) -> 690930.4 | V21: =P21+Q21+R21+S21+T21+U21 -> 1250930.4 | W21: 12 | X21: =V21/W21 -> 104244.2 | Z21: =X21 -> 104244.2 | AA21: 82601.205 | AB21: =Z21-AA21 -> 21642.995
A22: 19 | B22: LUCKY AGWOM | C22: 754993.58 | D22: 12 | E22: =C22*D22 -> 9059923 | G22: 436793.84 | I22: =E22-F22-G22-H22 -> 8623129.2 | J22: 200000 | K22: 0.2 | L22: =I22*K22 -> 1724625.8 | M22: =J22+L22 -> 1924625.8 | N22: =F22+G22+H22+M22 -> 2361419.7 | O22: =E22-N22 -> 6698503.3 | P22: =IF(O22<300000,0.07*O22,21000) -> 21000 | Q22: =IF((O22-300000)<0,0,IF((O22-300000)<300000,0.11*(O22-300000),33000)) -> 33000 | R22: =IF((O22-600000)<0,0,IF((O22-600000)<500000,0.15*(O22-600000),75000)) -> 75000 | S22: =IF((O22-1100000)<0,0,IF((O22-1100000)<500000,0.19*(O22-1100000),95000)) -> 95000 | T22: =IF((O22-1600000)<0,0,IF((O22-1600000)<1600000,0.21*(O22-1600000),336000)) -> 336000 | U22: =24%*(O22-3200000) -> 839640.8 | V22: =P22+Q22+R22+S22+T22+U22 -> 1399640.8 | W22: 12 | X22: =V22/W22 -> 116636.73 | Z22: =X22 -> 116636.73 | AA22: 98711.115 | AB22: =Z22-AA22 -> 17925.619
A23: 20 | B23: IDRIS IBRAHIM | C23: 564993.58 | D23: 12 | E23: =C23*D23 -> 6779923 | G23: 436793.84 | I23: =E23-F23-G23-H23 -> 6343129.2 | J23: 200000 | K23: 0.2 | L23: =I23*K23 -> 1268625.8 | M23: =J23+L23 -> 1468625.8 | N23: =F23+G23+H23+M23 -> 1905419.7 | O23: =E23-N23 -> 4874503.3 | P23: =IF(O23<300000,0.07*O23,21000) -> 21000 | Q23: =IF((O23-300000)<0,0,IF((O23-300000)<300000,0.11*(O23-300000),33000)) -> 33000 | R23: =IF((O23-600000)<0,0,IF((O23-600000)<500000,0.15*(O23-600000),75000)) -> 75000 | S23: =IF((O23-1100000)<0,0,IF((O23-1100000)<500000,0.19*(O23-1100000),95000)) -> 95000 | T23: =IF((O23-1600000)<0,0,IF((O23-1600000)<1600000,0.21*(O23-1600000),336000)) -> 336000 | U23: =24%*(O23-3200000) -> 401880.8 | V23: =P23+Q23+R23+S23+T23+U23 -> 961880.8 | W23: 12 | X23: =V23/W23 -> 80156.733 | Z23: =X23 -> 80156.733 | AA23: 62231.115 | AB23: =Z23-AA23 -> 17925.619
A24: 21 | B24: FARUQ ATOFARATI | C24: 641140.67 | D24: 12 | E24: =C24*D24 -> 7693688 | G24: 365895.04 | I24: =E24-F24-G24-H24 -> 7327793 | J24: 200000 | K24: 0.2 | L24: =I24*K24 -> 1465558.6 | M24: =J24+L24 -> 1665558.6 | N24: =F24+G24+H24+M24 -> 2031453.6 | O24: =E24-N24 -> 5662234.4 | P24: =IF(O24<300000,0.07*O24,21000) -> 21000 | Q24: =IF((O24-300000)<0,0,IF((O24-300000)<300000,0.11*(O24-300000),33000)) -> 33000 | R24: =IF((O24-600000)<0,0,IF((O24-600000)<500000,0.15*(O24-600000),75000)) -> 75000 | S24: =IF((O24-1100000)<0,0,IF((O24-1100000)<500000,0.19*(O24-1100000),95000)) -> 95000 | T24: =IF((O24-1600000)<0,0,IF((O24-1600000)<1600000,0.21*(O24-1600000),336000)) -> 336000 | U24: =24%*(O24-3200000) -> 590936.25 | V24: =P24+Q24+R24+S24+T24+U24 -> 1150936.2 | W24: 12 | X24: =V24/W24 -> 95911.354 | Z24: =X24 -> 95911.354 | AA24: 80347.427 | AB24: =Z24-AA24 -> 15563.927
A25: 22 | B25: RASHEEDAT DAIBU | C25: 441140.67 | D25: 12 | E25: =C25*D25 -> 5293688 | G25: 365895.04 | I25: =E25-F25-G25-H25 -> 4927793 | J25: 200000 | K25: 0.2 | L25: =I25*K25 -> 985558.59 | M25: =J25+L25 -> 1185558.6 | N25: =F25+G25+H25+M25 -> 1551453.6 | O25: =E25-N25 -> 3742234.4 | P25: =IF(O25<300000,0.07*O25,21000) -> 21000 | Q25: =IF((O25-300000)<0,0,IF((O25-300000)<300000,0.11*(O25-300000),33000)) -> 33000 | R25: =IF((O25-600000)<0,0,IF((O25-600000)<500000,0.15*(O25-600000),75000)) -> 75000 | S25: =IF((O25-1100000)<0,0,IF((O25-1100000)<500000,0.19*(O25-1100000),95000)) -> 95000 | T25: =IF((O25-1600000)<0,0,IF((O25-1600000)<1600000,0.21*(O25-1600000),336000)) -> 336000 | U25: =24%*(O25-3200000) -> 130136.25 | V25: =P25+Q25+R25+S25+T25+U25 -> 690136.25 | W25: 12 | X25: =V25/W25 -> 57511.354 | Z25: =X25 -> 57511.354 | AA25: 42537.332 | AB25: =Z25-AA25 -> 14974.022
A26: 23 | B26: ELIZABETH OGECHUKWU ONYEAKU | C26: 415320.67 | D26: 12 | E26: =C26*D26 -> 4983848 | G26: 341107.84 | I26: =E26-F26-G26-H26 -> 4642740.2 | J26: 200000 | K26: 0.2 | L26: =I26*K26 -> 928548.03 | M26: =J26+L26 -> 1128548 | N26: =F26+G26+H26+M26 -> 1469655.9 | O26: =E26-N26 -> 3514192.1 | P26: =IF(O26<300000,0.07*O26,21000) -> 21000 | Q26: =IF((O26-300000)<0,0,IF((O26-300000)<300000,0.11*(O26-300000),33000)) -> 33000 | R26: =IF((O26-600000)<0,0,IF((O26-600000)<500000,0.15*(O26-600000),75000)) -> 75000 | S26: =IF((O26-1100000)<0,0,IF((O26-1100000)<500000,0.19*(O26-1100000),95000)) -> 95000 | T26: =IF((O26-1600000)<0,0,IF((O26-1600000)<1600000,0.21*(O26-1600000),336000)) -> 336000 | U26: =24%*(O26-3200000) -> 75406.111 | V26: =P26+Q26+R26+S26+T26+U26 -> 635406.11 | W26: 12 | X26: =V26/W26 -> 52950.509 | Z26: =X26 -> 52950.509 | AA26: 39052.313 | AB26: =Z26-AA26 -> 13898.196
A27: 24 | B27: VICTOR ASUKWO | C27: 415320.67 | D27: 12 | E27: =C27*D27 -> 4983848 | G27: 341107.84 | I27: =E27-F27-G27-H27 -> 4642740.2 | J27: 200000 | K27: 0.2 | L27: =I27*K27 -> 928548.03 | M27: =J27+L27 -> 1128548 | N27: =F27+G27+H27+M27 -> 1469655.9 | O27: =E27-N27 -> 3514192.1 | P27: =IF(O27<300000,0.07*O27,21000) -> 21000 | Q27: =IF((O27-300000)<0,0,IF((O27-300000)<300000,0.11*(O27-300000),33000)) -> 33000 | R27: =IF((O27-600000)<0,0,IF((O27-600000)<500000,0.15*(O27-600000),75000)) -> 75000 | S27: =IF((O27-1100000)<0,0,IF((O27-1100000)<500000,0.19*(O27-1100000),95000)) -> 95000 | T27: =IF((O27-1600000)<0,0,IF((O27-1600000)<1600000,0.21*(O27-1600000),336000)) -> 336000 | U27: =24%*(O27-3200000) -> 75406.111 | V27: =P27+Q27+R27+S27+T27+U27 -> 635406.11 | W27: 12 | X27: =V27/W27 -> 52950.509 | Z27: =X27 -> 52950.509 | AA27: 39052.313 | AB27: =Z27-AA27 -> 13898.196
A28: 25 | B28: NNANDI LIVINUS ATURE | C28: 455320.67 | D28: 12 | E28: =C28*D28 -> 5463848 | G28: 341107.84 | I28: =E28-F28-G28-H28 -> 5122740.2 | J28: 200000 | K28: 0.2 | L28: =I28*K28 -> 1024548 | M28: =J28+L28 -> 1224548 | N28: =F28+G28+H28+M28 -> 1565655.9 | O28: =E28-N28 -> 3898192.1 | P28: =IF(O28<300000,0.07*O28,21000) -> 21000 | Q28: =IF((O28-300000)<0,0,IF((O28-300000)<300000,0.11*(O28-300000),33000)) -> 33000 | R28: =IF((O28-600000)<0,0,IF((O28-600000)<500000,0.15*(O28-600000),75000)) -> 75000 | S28: =IF((O28-1100000)<0,0,IF((O28-1100000)<500000,0.19*(O28-1100000),95000)) -> 95000 | T28: =IF((O28-1600000)<0,0,IF((O28-1600000)<1600000,0.21*(O28-1600000),336000)) -> 336000 | U28: =24%*(O28-3200000) -> 167566.11 | V28: =P28+Q28+R28+S28+T28+U28 -> 727566.11 | W28: 12 | X28: =V28/W28 -> 60630.509 | Z28: =X28 -> 60630.509 | AA28: 45772.313 | AB28: =Z28-AA28 -> 14858.196
A29: 26 | B29: ABDULRAHMAN A SULAIMAN | C29: 407016.17 | D29: 12 | E29: =C29*D29 -> 4884194 | G29: 333135.52 | I29: =E29-F29-G29-H29 -> 4551058.5 | J29: 200000 | K29: 0.2 | L29: =I29*K29 -> 910211.7 | M29: =J29+L29 -> 1110211.7 | N29: =F29+G29+H29+M29 -> 1443347.2 | O29: =E29-N29 -> 3440846.8 | P29: =IF(O29<300000,0.07*O29,21000) -> 21000 | Q29: =IF((O29-300000)<0,0,IF((O29-300000)<300000,0.11*(O29-300000),33000)) -> 33000 | R29: =IF((O29-600000)<0,0,IF((O29-600000)<500000,0.15*(O29-600000),75000)) -> 75000 | S29: =IF((O29-1100000)<0,0,IF((O29-1100000)<500000,0.19*(O29-1100000),95000)) -> 95000 | T29: =IF((O29-1600000)<0,0,IF((O29-1600000)<1600000,0.21*(O29-1600000),336000)) -> 336000 | U29: =24%*(O29-3200000) -> 57803.228 | V29: =P29+Q29+R29+S29+T29+U29 -> 617803.23 | W29: 12 | X29: =V29/W29 -> 51483.602 | Z29: =X29 -> 51483.602 | AA29: 37921.501 | AB29: =Z29-AA29 -> 13562.102
A30: 27 | B30: DARE SHEU MAGBON | C30: 398711.67 | D30: 12 | E30: =C30*D30 -> 4784540 | G30: 325163.2 | I30: =E30-F30-G30-H30 -> 4459376.8 | J30: 200000 | K30: 0.2 | L30: =I30*K30 -> 891875.36 | M30: =J30+L30 -> 1091875.4 | N30: =F30+G30+H30+M30 -> 1417038.6 | O30: =E30-N30 -> 3367501.4 | P30: =IF(O30<300000,0.07*O30,21000) -> 21000 | Q30: =IF((O30-300000)<0,0,IF((O30-300000)<300000,0.11*(O30-300000),33000)) -> 33000 | R30: =IF((O30-600000)<0,0,IF((O30-600000)<500000,0.15*(O30-600000),75000)) -> 75000 | S30: =IF((O30-1100000)<0,0,IF((O30-1100000)<500000,0.19*(O30-1100000),95000)) -> 95000 | T30: =IF((O30-1600000)<0,0,IF((O30-1600000)<1600000,0.21*(O30-1600000),336000)) -> 336000 | U30: =24%*(O30-3200000) -> 40200.346 | V30: =P30+Q30+R30+S30+T30+U30 -> 600200.35 | W30: 12 | X30: =V30/W30 -> 50016.695 | Z30: =X30 -> 50016.695 | AA30: 36790.688 | AB30: =Z30-AA30 -> 13226.007
A31: 28 | B31: ABUBAKAR SULAIMAN SODEEQ | C31: 398711.67 | D31: 12 | E31: =C31*D31 -> 4784540 | G31: 325163.2 | I31: =E31-F31-G31-H31 -> 4459376.8 | J31: 200000 | K31: 0.2 | L31: =I31*K31 -> 891875.36 | M31: =J31+L31 -> 1091875.4 | N31: =F31+G31+H31+M31 -> 1417038.6 | O31: =E31-N31 -> 3367501.4 | P31: =IF(O31<300000,0.07*O31,21000) -> 21000 | Q31: =IF((O31-300000)<0,0,IF((O31-300000)<300000,0.11*(O31-300000),33000)) -> 33000 | R31: =IF((O31-600000)<0,0,IF((O31-600000)<500000,0.15*(O31-600000),75000)) -> 75000 | S31: =IF((O31-1100000)<0,0,IF((O31-1100000)<500000,0.19*(O31-1100000),95000)) -> 95000 | T31: =IF((O31-1600000)<0,0,IF((O31-1600000)<1600000,0.21*(O31-1600000),336000)) -> 336000 | U31: =24%*(O31-3200000) -> 40200.346 | V31: =P31+Q31+R31+S31+T31+U31 -> 600200.35 | W31: 12 | X31: =V31/W31 -> 50016.695 | Z31: =X31 -> 50016.695 | AA31: 36790.688 | AB31: =Z31-AA31 -> 13226.007
A32: 29 | B32: JIMOH ADEBAYO ZAKA | C32: 415320.67 | D32: 12 | E32: =C32*D32 -> 4983848 | G32: 341107.84 | I32: =E32-F32-G32-H32 -> 4642740.2 | J32: 200000 | K32: 0.2 | L32: =I32*K32 -> 928548.03 | M32: =J32+L32 -> 1128548 | N32: =F32+G32+H32+M32 -> 1469655.9 | O32: =E32-N32 -> 3514192.1 | P32: =IF(O32<300000,0.07*O32,21000) -> 21000 | Q32: =IF((O32-300000)<0,0,IF((O32-300000)<300000,0.11*(O32-300000),33000)) -> 33000 | R32: =IF((O32-600000)<0,0,IF((O32-600000)<500000,0.15*(O32-600000),75000)) -> 75000 | S32: =IF((O32-1100000)<0,0,IF((O32-1100000)<500000,0.19*(O32-1100000),95000)) -> 95000 | T32: =IF((O32-1600000)<0,0,IF((O32-1600000)<1600000,0.21*(O32-1600000),336000)) -> 336000 | U32: =24%*(O32-3200000) -> 75406.111 | V32: =P32+Q32+R32+S32+T32+U32 -> 635406.11 | W32: 12 | X32: =V32/W32 -> 52950.509 | Z32: =X32 -> 52950.509 | AA32: 39052.313 | AB32: =Z32-AA32 -> 13898.196
... A34: 32 | B34: MOHAMMED BELLO | C34: 398711.67 | D34: 12 | E34: =C34*D34 -> 4784540 | G34: 341107.84 | I34: =E34-F34-G34-H34 -> 4443432.2 | J34: 200000 | K34: 0.2 | L34: =I34*K34 -> 888686.43 | M34: =J34+L34 -> 1088686.4 | N34: =F34+G34+H34+M34 -> 1429794.3 | O34: =E34-N34 -> 3354745.7 | P34: =IF(O34<300000,0.07*O34,21000) -> 21000 | Q34: =IF((O34-300000)<0,0,IF((O34-300000)<300000,0.11*(O34-300000),33000)) -> 33000 | R34: =IF((O34-600000)<0,0,IF((O34-600000)<500000,0.15*(O34-600000),75000)) -> 75000 | S34: =IF((O34-1100000)<0,0,IF((O34-1100000)<500000,0.19*(O34-1100000),95000)) -> 95000 | T34: =IF((O34-1600000)<0,0,IF((O34-1600000)<1600000,0.21*(O34-1600000),336000)) -> 336000 | U34: =24%*(O34-3200000) -> 37138.975 | V34: =P34+Q34+R34+S34+T34+U34 -> 597138.97 | W34: 12 | X34: =V34/W34 -> 49761.581 | Z34: =X34 -> 49761.581 | AA34: 36790.688 | AB34: =Z34-AA34 -> 12970.893
B35: HARUNA JIBRIL AMEH | C35: 351910.75 | D35: 12 | E35: =C35*D35 -> 4222929 | G35: 289834.32 | I35: =E35-F35-G35-H35 -> 3933094.7 | J35: 200000 | K35: 0.2 | L35: =I35*K35 -> 786618.94 | M35: =J35+L35 -> 986618.94 | N35: =F35+G35+H35+M35 -> 1276453.3 | O35: =E35-N35 -> 2946475.7 | P35: =IF(O35<300000,0.07*O35,21000) -> 21000 | Q35: =IF((O35-300000)<0,0,IF((O35-300000)<300000,0.11*(O35-300000),33000)) -> 33000 | R35: =IF((O35-600000)<0,0,IF((O35-600000)<500000,0.15*(O35-600000),75000)) -> 75000 | S35: =IF((O35-1100000)<0,0,IF((O35-1100000)<500000,0.19*(O35-1100000),95000)) -> 95000 | T35: =IF((O35-1600000)<0,0,IF((O35-1600000)<1600000,0.21*(O35-1600000),336000)) -> 282759.91 | V35: =P35+Q35+R35+S35+T35+U35 -> 506759.91 | W35: 12 | X35: =V35/W35 -> 42229.992 | Z35: =X35 -> 42229.992 | AA35: 30259.166 | AB35: =Z35-AA35 -> 11970.827
B36: RAMATU IBRAHIM ABDULRAHEEM | C36: 344900.83 | D36: 12 | E36: =C36*D36 -> 4138810 | G36: 283104.8 | I36: =E36-F36-G36-H36 -> 3855705.2 | J36: 200000 | K36: 0.2 | L36: =I36*K36 -> 771141.04 | M36: =J36+L36 -> 971141.04 | N36: =F36+G36+H36+M36 -> 1254245.8 | O36: =E36-N36 -> 2884564.2 | P36: =IF(O36<300000,0.07*O36,21000) -> 21000 | Q36: =IF((O36-300000)<0,0,IF((O36-300000)<300000,0.11*(O36-300000),33000)) -> 33000 | R36: =IF((O36-600000)<0,0,IF((O36-600000)<500000,0.15*(O36-600000),75000)) -> 75000 | S36: =IF((O36-1100000)<0,0,IF((O36-1100000)<500000,0.19*(O36-1100000),95000)) -> 95000 | T36: =IF((O36-1600000)<0,0,IF((O36-1600000)<1600000,0.21*(O36-1600000),336000)) -> 269758.47 | V36: =P36+Q36+R36+S36+T36+U36 -> 493758.47 | W36: 12 | X36: =V36/W36 -> 41146.539 | Z36: =X36 -> 41146.539 | AA36: 29305.196 | AB36: =Z36-AA36 -> 11841.344
B38: INTERNAL AUDIT
B39: OSANAIYE DAVID AKINYEMI | C39: 1847106.4 | D39: 12 | E39: =C39*D39 -> 22165277 | G39: 1677222.2 | I39: =E39-F39-G39-H39 -> 20488055 | J39: 200000 | K39: 0.2 | L39: =I39*K39 -> 4097611 | M39: =J39+L39 -> 4297611 | N39: =F39+G39+H39+M39 -> 5974833.1 | O39: =E39-N39 -> 16190444 | P39: =IF(O39<300000,0.07*O39,21000) -> 21000 | Q39: =IF((O39-300000)<0,0,IF((O39-300000)<300000,0.11*(O39-300000),33000)) -> 33000 | R39: =IF((O39-600000)<0,0,IF((O39-600000)<500000,0.15*(O39-600000),75000)) -> 75000 | S39: =IF((O39-1100000)<0,0,IF((O39-1100000)<500000,0.19*(O39-1100000),95000)) -> 95000 | T39: =IF((O39-1600000)<0,0,IF((O39-1600000)<1600000,0.21*(O39-1600000),336000)) -> 336000 | U39: =24%*(O39-3200000) -> 3117706.5 | V39: =P39+Q39+R39+S39+T39+U39 -> 3677706.5 | W39: 12 | X39: =V39/W39 -> 306475.54 | Z39: =X39 -> 306475.54 | AA39: 251472.25 | AB39: =Z39-AA39 -> 55003.297
B40: JAMILA ABDUL | C40: 441140.67 | D40: 12 | E40: =C40*D40 -> 5293688 | G40: 365895.04 | I40: =E40-F40-G40-H40 -> 4927793 | J40: 200000 | K40: 0.2 | L40: =I40*K40 -> 985558.59 | M40: =J40+L40 -> 1185558.6 | N40: =F40+G40+H40+M40 -> 1551453.6 | O40: =E40-N40 -> 3742234.4 | P40: =IF(O40<300000,0.07*O40,21000) -> 21000 | Q40: =IF((O40-300000)<0,0,IF((O40-300000)<300000,0.11*(O40-300000),33000)) -> 33000 | R40: =IF((O40-600000)<0,0,IF((O40-600000)<500000,0.15*(O40-600000),75000)) -> 75000 | S40: =IF((O40-1100000)<0,0,IF((O40-1100000)<500000,0.19*(O40-1100000),95000)) -> 95000 | T40: =IF((O40-1600000)<0,0,IF((O40-1600000)<1600000,0.21*(O40-1600000),336000)) -> 336000 | U40: =24%*(O40-3200000) -> 130136.25 | V40: =P40+Q40+R40+S40+T40+U40 -> 690136.25 | W40: 12 | X40: =V40/W40 -> 57511.354 | Z40: =X40 -> 57511.354 | AA40: 42537.332 | AB40: =Z40-AA40 -> 14974.022
B41: IJEOMA EWELUKWA | C41: 450135.83 | D41: 12 | E41: =C41*D41 -> 5401630 | G41: 374530.4 | I41: =E41-F41-G41-H41 -> 5027099.6 | J41: 200000 | K41: 0.2 | L41: =I41*K41 -> 1005419.9 | M41: =J41+L41 -> 1205419.9 | N41: =F41+G41+H41+M41 -> 1579950.3 | O41: =E41-N41 -> 3821679.7 | P41: =IF(O41<300000,0.07*O41,21000) -> 21000 | Q41: =IF((O41-300000)<0,0,IF((O41-300000)<300000,0.11*(O41-300000),33000)) -> 33000 | R41: =IF((O41-600000)<0,0,IF((O41-600000)<500000,0.15*(O41-600000),75000)) -> 75000 | S41: =IF((O41-1100000)<0,0,IF((O41-1100000)<500000,0.19*(O41-1100000),95000)) -> 95000 | T41: =IF((O41-1600000)<0,0,IF((O41-1600000)<1600000,0.21*(O41-1600000),336000)) -> 336000 | U41: =24%*(O41-3200000) -> 149203.12 | V41: =P41+Q41+R41+S41+T41+U41 -> 709203.12 | W41: 12 | X41: =V41/W41 -> 59100.26 | Z41: =X41 -> 59100.26 | AA41: 43763.907 | AB41: =Z41-AA41 -> 15336.353
B42: YUSUF YUSUF DAYYABU | C42: 398711.67 | D42: 12 | E42: =C42*D42 -> 4784540 | G42: 325163.2 | I42: =E42-F42-G42-H42 -> 4459376.8 | J42: 200000 | K42: 0.2 | L42: =I42*K42 -> 891875.36 | M42: =J42+L42 -> 1091875.4 | N42: =F42+G42+H42+M42 -> 1417038.6 | O42: =E42-N42 -> 3367501.4 | P42: =IF(O42<300000,0.07*O42,21000) -> 21000 | Q42: =IF((O42-300000)<0,0,IF((O42-300000)<300000,0.11*(O42-300000),33000)) -> 33000 | R42: =IF((O42-600000)<0,0,IF((O42-600000)<500000,0.15*(O42-600000),75000)) -> 75000 | S42: =IF((O42-1100000)<0,0,IF((O42-1100000)<500000,0.19*(O42-1100000),95000)) -> 95000 | T42: =IF((O42-1600000)<0,0,IF((O42-1600000)<1600000,0.21*(O42-1600000),336000)) -> 336000 | U42: =24%*(O42-3200000) -> 40200.346 | V42: =P42+Q42+R42+S42+T42+U42 -> 600200.35 | W42: 12 | X42: =V42/W42 -> 50016.695 | Z42: =X42 -> 50016.695 | AA42: 36790.688 | AB42: =Z42-AA42 -> 13226.007
B44: LEG. SUPPORT SEVICES
A45: 35 | B45: BETHEL UZOMA IHUGBA | C45: 1185306.8 | D45: 12 | E45: =C45*D45 -> 14223681 | G45: 869094.48 | I45: =E45-F45-G45-H45 -> 13354587 | J45: 200000 | K45: 0.2 | L45: =I45*K45 -> 2670917.3 | M45: =J45+L45 -> 2870917.3 | N45: =F45+G45+H45+M45 -> 3740011.8 | O45: =E45-N45 -> 10483669 | P45: =IF(O45<300000,0.07*O45,21000) -> 21000 | Q45: =IF((O45-300000)<0,0,IF((O45-300000)<300000,0.11*(O45-300000),33000)) -> 33000 | R45: =IF((O45-600000)<0,0,IF((O45-600000)<500000,0.15*(O45-600000),75000)) -> 75000 | S45: =IF((O45-1100000)<0,0,IF((O45-1100000)<500000,0.19*(O45-1100000),95000)) -> 95000 | T45: =IF((O45-1600000)<0,0,IF((O45-1600000)<1600000,0.21*(O45-1600000),336000)) -> 336000 | U45: =0.24*(O45-3200000) -> 1748080.6 | V45: =P45+Q45+R45+S45+T45+U45 -> 2308080.6 | W45: 12 | X45: =V45/W45 -> 192340.05 | Z45: =X45 -> 192340.05 | AA45: 162999.59 | AB45: =Z45-AA45 -> 29340.461
A46: 36 | B46: OGUCHE SAMUEL | C46: 904477 | D46: 12 | E46: =C46*D46 -> 10853724 | G46: 714697.92 | I46: =E46-F46-G46-H46 -> 10139026 | J46: 200000 | K46: 0.2 | L46: =I46*K46 -> 2027805.2 | M46: =J46+L46 -> 2227805.2 | N46: =F46+G46+H46+M46 -> 2942503.1 | O46: =E46-N46 -> 7911220.9 | P46: =IF(O46<300000,0.07*O46,21000) -> 21000 | Q46: =IF((O46-300000)<0,0,IF((O46-300000)<300000,0.11*(O46-300000),33000)) -> 33000 | R46: =IF((O46-600000)<0,0,IF((O46-600000)<500000,0.15*(O46-600000),75000)) -> 75000 | S46: =IF((O46-1100000)<0,0,IF((O46-1100000)<500000,0.19*(O46-1100000),95000)) -> 95000 | T46: =IF((O46-1600000)<0,0,IF((O46-1600000)<1600000,0.21*(O46-1600000),336000)) -> 336000 | U46: =24%*(O46-3200000) -> 1130693 | V46: =P46+Q46+R46+S46+T46+U46 -> 1690693 | W46: 12 | X46: =V46/W46 -> 140891.08 | Z46: =X46 -> 140891.08 | AA46: 119022.8 | AB46: =Z46-AA46 -> 21868.282
A47: 37 | B47: IBRAHIM USMAN | C47: 904477 | D47: 12 | E47: =C47*D47 -> 10853724 | F47: 137703.15 | G47: 714697.92 | I47: =E47-F47-G47-H47 -> 10001323 | J47: 200000 | K47: 0.2 | L47: =I47*K47 -> 2000264.6 | M47: =J47+L47 -> 2200264.6 | N47: =F47+G47+H47+M47 -> 3052665.7 | O47: =E47-N47 -> 7801058.3 | P47: =IF(O47<300000,0.07*O47,21000) -> 21000 | Q47: =IF((O47-300000)<0,0,IF((O47-300000)<300000,0.11*(O47-300000),33000)) -> 33000 | R47: =IF((O47-600000)<0,0,IF((O47-600000)<500000,0.15*(O47-600000),75000)) -> 75000 | S47: =IF((O47-1100000)<0,0,IF((O47-1100000)<500000,0.19*(O47-1100000),95000)) -> 95000 | T47: =IF((O47-1600000)<0,0,IF((O47-1600000)<1600000,0.21*(O47-1600000),336000)) -> 336000 | U47: =24%*(O47-3200000) -> 1104254 | V47: =P47+Q47+R47+S47+T47+U47 -> 1664254 | W47: 12 | X47: =V47/W47 -> 138687.83 | Z47: =X47 -> 138687.83 | AA47: 118861.97 | AB47: =Z47-AA47 -> 19825.868
