Workbook

Sheet JUNE 2023
A1: NATIONAL INSTITUTE FOR LEGISLATIVE AND DEMOCRATIC STUDIES | H1: ='[1]FEB 08'!F8/'[1]FEB 08'!Q8 -> 0.3
A2: STAFF PAYROLL FOR THE MONTH OF MAY 2023
E3: ='[1]FEB 08'!E11/'[1]FEB 08'!M11 -> #REF! | H3: ='[1]FEB 08'!F11/'[1]FEB 08'!Q11 -> #REF!
B4: STAFF NAME | C4: DESIGNATION | D4: GRADE LEVEL | E4: BASIC SALARY | F4: ALLCE/ AREARS | G4: RENT | H4: UTILITY | I4: DOMESTIC | J4: ENTERT. | K4: FURNIT. | L4: FUEL | M4: ALLOWANCE | N4: ALLOWANCE | O4: ALLCE | P4: ALLCE | Q4: DUTY ALLCE | R4: GROSS SALARY | S4: AUCTION | T4: COOP CONTR/SPEC SAVINGS | U4: COOP. LOAN RECOVERY | V4: NHF DED. | W4: PAYE | X4: TOTAL DEDUCTION | Y4: MAY, 2023 | Z4: JUNE, 2023
E5: N | G5: N | H5: N | I5: N | J5: N | K5: N | L5: N | M5: N | N5: N | O5: N | P5: N | Q5: N | R5: N | S5: N | T5: N | U5: N | V5: N | W5: N | X5: N | Y5: N | Z5: N
A6: S/N | B6: DG'S OFFICE
A7: 1 | B7: PROF. ABUBAKAR O. SULAIMAN | C7: DIRECTOR GENERAL | D7: CONSOL | E7: 160488.75 | G7: 320977.5 | H7: 48146.63 | I7: 120366.57 | J7: 72219.94 | K7: 0 | L7: 120366.57 | M7: =250000 -> 250000 | O7: 16048.88 | P7: 25000 | Q7: 25235 | R7: =Q7+P7+O7+N7+M7+L7+K7+J7+I7+H7+G7+F7+E7 -> 1158849.8 | W7: 201165.84 | X7: =W7+V7+U7+T7+S7 -> 201165.84 | Y7: 957684 | Z7: =R7-X7 -> 957684
A8: 2 | B8: DR JAKE DABANG DAN AZUMI | C8: DEPUTY DIR. TECHNICAL | D8: 16(9) | E8: =42653.17 -> 42653.17 | G8: =E8*300% -> 127959.51 | H8: =E8*7.5% -> 3198.9877 | I8: 40122.19 | J8: =E8*50% -> 21326.585 | K8: =E8*350% -> 149286.1 | L8: =E8*100% -> 42653.17 | M8: =180000 -> 180000 | O8: =E8*10% -> 4265.317 | P8: 20000 | Q8: 150000 | R8: =Q8+P8+O8+N8+M8+L8+K8+J8+I8+H8+G8+F8+E8 -> 781465.02 | V8: 1066.3293 | W8: 128510.39 | X8: =W8+V8+U8+T8+S8 -> 129576.72 | Y8: 651888.3 | Z8: =R8-X8 -> 651888.3
A9: 3 | B9: DR ABDULSALAM NASIRU NAEEM | C9: SA ACADEMICS | D9: 16(9) | E9: =42653.17 -> 42653.17 | G9: =E9*300% -> 127959.51 | H9: =E9*7.5% -> 3198.9877 | I9: 40122.19 | J9: =E9*50% -> 21326.585 | K9: =E9*350% -> 149286.1 | L9: =E9*100% -> 42653.17 | M9: =180000 -> 180000 | O9: =E9*10% -> 4265.317 | P9: 20000 | Q9: =100000 -> 100000 | R9: 0 | W9: 0 | X9: =W9+V9+U9+T9+S9 -> 0 | Y9: 612357.07 | Z9: =R9-X9 -> 0
A10: 4 | B10: RAHEEM USMAN AYIGORO | C10: SA-INFRASTRUCTURE | D10: 16 (9) | E10: =42653.17 -> 42653.17 | G10: =E10*300% -> 127959.51 | H10: =E10*7.5% -> 3198.9877 | I10: 40122.19 | J10: =E10*50% -> 21326.585 | K10: =E10*350% -> 149286.1 | L10: =E10*100% -> 42653.17 | N10: =90000 -> 90000 | O10: =E10*10% -> 4265.317 | P10: 20000 | Q10: 0 | R10: =Q10+P10+O10+N10+M10+L10+K10+J10+I10+H10+G10+F10+E10 -> 541465.02 | T10: =100000 -> 100000 | W10: 82627.951 | X10: =W10+V10+U10+T10+S10 -> 182627.95 | Y10: 358837.07 | Z10: =R10-X10 -> 358837.07
A11: 5 | B11: MARIAM MOHAMMED BELLO | C11: SA- SPECIAL DUTIES | D11: 16(8) | E11: 41157.69 | G11: =E11*300% -> 123473.07 | H11: =E11*7.5% -> 3086.8268 | I11: 40122.19 | J11: =E11*50% -> 20578.845 | K11: =E11*350% -> 144051.92 | L11: =E11*100% -> 41157.69 | N11: =90000 -> 90000 | O11: =E11*10% -> 4115.769 | P11: 15000 | Q11: =100000+100000 -> 200000 | R11: =Q11+P11+O11+N11+M11+L11+K11+J11+I11+H11+G11+F11+E11 -> 722744 | W11: 117433.51 | X11: =W11+V11+U11+T11+S11 -> 117433.51 | Y11: 605310.49 | Z11: =R11-X11 -> 605310.49
A12: 6 | B12: AKINSANMI ADEJOKE OLUKEMI | C12: DEPUTY DIR. INFO/PROTOCOL | D12: 16(8) | E12: =41157.69 -> 41157.69 | G12: =E12*300% -> 123473.07 | H12: =E12*7.5% -> 3086.8268 | I12: 40122.19 | J12: =E12*50% -> 20578.845 | K12: =E12*350% -> 144051.92 | L12: =E12*100% -> 41157.69 | N12: =80000+10000 -> 90000 | O12: =E12*10% -> 4115.769 | P12: 20000 | Q12: =100000 -> 100000 | R12: =Q12+P12+O12+N12+M12+L12+K12+J12+I12+H12+G12+F12+E12 -> 627744 | T12: =0 -> 0 | U12: 0 | V12: 1028.9423 | W12: 99032.678 | X12: =W12+V12+U12+T12+S12 -> 100061.62 | Y12: 527682.38 | Z12: =R12-X12 -> 527682.38
A13: 7 | B13: DR IKEME ARTHUR J.O | C13: DEPUTY DIRECTOR, M&E | D13: 16(8) | E13: =41157.69 -> 41157.69 | G13: =E13*300% -> 123473.07 | H13: =E13*7.5% -> 3086.8268 | I13: 40122.19 | J13: =E13*50% -> 20578.845 | K13: =E13*350% -> 144051.92 | L13: =E13*100% -> 41157.69 | N13: =80000+10000 -> 90000 | O13: =E13*10% -> 4115.769 | P13: 20000 | Q13: 0 | R13: =Q13+P13+O13+N13+M13+L13+K13+J13+I13+H13+G13+F13+E13 -> 527744 | T13: =50000 -> 50000 | U13: =160416.67 -> 160416.67 | V13: 1028.9423 | W13: 79832.678 | X13: =W13+V13+U13+T13+S13 -> 291278.29 | Y13: 236465.71 | Z13: =R13-X13 -> 236465.71
A14: 8 | B14: MOSHOOD M. OLALERE | C14: DEPUTY DIR. GENERAL SERVICE | D14: 16(8) | E14: =41157.69 -> 41157.69 | G14: =E14*300% -> 123473.07 | H14: =E14*7.5% -> 3086.8268 | I14: 40122.19 | J14: =E14*50% -> 20578.845 | K14: =E14*350% -> 144051.92 | L14: =E14*100% -> 41157.69 | N14: =80000+10000 -> 90000 | O14: =E14*10% -> 4115.769 | P14: 20000 | Q14: 0 | R14: =Q14+P14+O14+N14+M14+L14+K14+J14+I14+H14+G14+F14+E14 -> 527744 | T14: =20000 -> 20000 | U14: =179017.51 -> 179017.51 | V14: 1028.9423 | W14: 79832.678 | X14: =W14+V14+U14+T14+S14 -> 279879.13 | Y14: 247864.87 | Z14: =R14-X14 -> 247864.87
A15: 9 | B15: ANDRAWUS MUSA | C15: ASST. DIRECTOR, STORES | D15: 15(9) | E15: 33507.5 | G15: =E15*300% -> 100522.5 | H15: =E15*7.5% -> 2513.0625 | I15: =40122.19 -> 40122.19 | J15: =E15*50% -> 16753.75 | K15: =E15*350% -> 117276.25 | L15: =E15*100% -> 33507.5 | N15: =80000 -> 80000 | O15: =E15*10% -> 3350.75 | P15: 20000 | Q15: 0 | R15: =SUM(E15:Q15) -> 447553.5 | T15: =50000-40000 -> 10000 | U15: =90000+110000 -> 200000 | V15: 837.6875 | W15: 64436.103 | X15: =W15+V15+U15+T15+S15 -> 275273.79 | Y15: 172279.71 | Z15: =R15-X15 -> 172279.71
A16: 10 | B16: AYOBOLU OLAJIDE OLUFUNSHO | C16: ASST.DIR., INFORMATION | D16: 15 (8) | E16: 32263.2 | G16: =E16*300% -> 96789.6 | H16: =E16*7.5% -> 2419.74 | I16: 40122.19 | J16: =E16*50% -> 16131.6 | K16: =E16*350% -> 112921.2 | L16: =E16*100% -> 32263.2 | N16: =80000 -> 80000 | O16: =E16*10% -> 3226.32 | P16: 20000 | Q16: 0 | R16: =Q16+P16+O16+N16+M16+L16+K16+J16+I16+H16+G16+F16+E16 -> 436137.05 | T16: =50000 -> 50000 | U16: =59583.33 -> 59583.33 | W16: 62404.98 | X16: =W16+V16+U16+T16+S16 -> 171988.31 | Y16: 264148.74 | Z16: =R16-X16 -> 264148.74
A17: 11 | B17: HUSSEIN EGYE MUSA | C17: CHIEF PROTOCOL OFFICER | D17: 14(10) | E17: 27611.23 | G17: =E17*300% -> 82833.69 | H17: =E17*7.5% -> 2070.8422 | J17: =E17*50% -> 13805.615 | K17: =E17*350% -> 96639.305 | L17: =E17*100% -> 27611.23 | N17: =70000 -> 70000 | O17: =E17*10% -> 2761.123 | P17: 20000 | Q17: 50000 | R17: =Q17+P17+O17+N17+M17+L17+K17+J17+I17+H17+G17+F17+E17 -> 393333.04 | T17: 50000 | U17: =150000 -> 150000 | V17: 0 | W17: 54186.609 | X17: =W17+V17+U17+T17+S17 -> 254186.61 | Y17: 139146.43 | Z17: =R17-X17 -> 139146.43
A18: 12 | B18: DONALD E. MKPANAM | C18: CHIEF ICT OFFICER | D18: 14(10) | E18: 27611.23 | G18: =E18*300% -> 82833.69 | H18: =E18*7.5% -> 2070.8422 | J18: =E18*50% -> 13805.615 | K18: =E18*350% -> 96639.305 | L18: =E18*100% -> 27611.23 | N18: =70000 -> 70000 | O18: =E18*10% -> 2761.123 | P18: 20000 | Q18: 0 | R18: =Q18+P18+O18+N18+M18+L18+K18+J18+I18+H18+G18+F18+E18 -> 343333.04 | V18: 690.28075 | W18: 44734.339 | X18: =W18+V18+U18+T18+S18 -> 45424.62 | Y18: 297908.42 | Z18: =R18-X18 -> 297908.42
A19: 13 | B19: JOY HARUNA MAKERI | C19: RESEARCH FELLOW 1 TRAINING | D19: 14(10) | E19: 27611.23 | G19: =E19*300% -> 82833.69 | H19: =E19*7.5% -> 2070.8422 | J19: =E19*50% -> 13805.615 | K19: =E19*350% -> 96639.305 | L19: =E19*100% -> 27611.23 | M19: =140000 -> 140000 | O19: =E19*10% -> 2761.123 | P19: 20000 | Q19: =50000+100000 -> 150000 | R19: =Q19+P19+O19+N19+M19+L19+K19+J19+I19+H19+G19+F19+E19 -> 563333.04 | W19: 86826.609 | X19: =W19+V19+U19+T19+S19 -> 86826.609 | Y19: 476506.43 | Z19: =R19-X19 -> 476506.43
A20: 14 | B20: ALI ABDULLAHI | C20: CHIEF ICT OFFICER | D20: 14(10) | E20: 27611.23 | G20: =E20*300% -> 82833.69 | H20: =E20*7.5% -> 2070.8422 | I20: 0 | J20: =E20*50% -> 13805.615 | K20: =E20*350% -> 96639.305 | L20: =E20*100% -> 27611.23 | N20: =70000 -> 70000 | O20: =E20*10% -> 2761.123 | P20: 15000 | Q20: =0 -> 0 | R20: =Q20+P20+O20+N20+M20+L20+K20+J20+I20+H20+G20+F20+E20 -> 338333.04 | W20: 44006.617 | X20: =W20+V20+U20+T20+S20 -> 44006.617 | Y20: 294326.42 | Z20: =R20-X20 -> 294326.42
A21: 15 | B21: PERCY TERFA GBAHABO | C21: HEAD, NILDS LIAISON OFFICE | D21: 13(9) | E21: 24741.26 | G21: =E21*300% -> 74223.78 | H21: =E21*7.5% -> 1855.5945 | I21: 0 | J21: =E21*50% -> 12370.63 | K21: =E21*350% -> 86594.41 | L21: =E21*100% -> 24741.26 | M21: =120000 -> 120000 | O21: =E21*10% -> 2474.126 | P21: 15000 | Q21: 0 | R21: =Q21+P21+O21+N21+M21+L21+K21+J21+I21+H21+G21+F21+E21 -> 362001.06 | T21: =50000 -> 50000 | U21: 52500 | W21: 46666.667 | X21: =W21+V21+U21+T21+S21 -> 149166.67 | Y21: 212834.39 | Z21: =R21-X21 -> 212834.39
A22: 16 | B22: HASSANA AHMED IBRAHIM | C22: PA- TO DG | D22: 13 (8) | E22: =23891.12 -> 23891.12 | G22: =E22*300% -> 71673.36 | H22: =E22*7.5% -> 1791.834 | J22: =E22*50% -> 11945.56 | K22: =E22*350% -> 83618.92 | L22: =E22*100% -> 23891.12 | M22: =120000 -> 120000 | O22: =E22*10% -> 2389.112 | P22: 10000 | Q22: =100000 -> 100000 | R22: =Q22+P22+O22+N22+M22+L22+K22+J22+I22+H22+G22+F22+E22 -> 449201.03 | T22: =30000-20000 -> 10000 | U22: =95833.33 -> 95833.33 | V22: 597.278 | W22: 64913.264 | X22: =W22+V22+U22+T22+S22 -> 171343.87 | Y22: 277857.15 | Z22: =R22-X22 -> 277857.15
A23: 17 | B23: CHRISTIAN MADUABUCHI ODO | C23: PRINCIPAL ICT OFFICER | D23: 12(9) | E23: =22837.82 -> 22837.82 | G23: =E23*300% -> 68513.46 | H23: =E23*7.5% -> 1712.8365 | J23: =E23*50% -> 11418.91 | K23: =E23*350% -> 79932.37 | L23: =E23*100% -> 22837.82 | N23: =60000 -> 60000 | O23: =E23*10% -> 2283.782 | P23: 15000 | R23: =Q23+P23+O23+N23+M23+L23+K23+J23+I23+H23+G23+F23+E23 -> 284537 | V23: 570.9455 | W23: 34871.967 | X23: =W23+V23+U23+T23+S23 -> 35442.913 | Y23: 249094.09 | Z23: =R23-X23 -> 249094.09
A24: 18 | B24: ADUGBA RICHARD TERSEER | C24: PRINCIPAL INFO. OFFICER | D24: 12(8) | E24: 21520.88 | G24: =E24*300% -> 64562.64 | H24: =E24*7.5% -> 1614.066 | J24: =E24*50% -> 10760.44 | K24: =E24*350% -> 75323.08 | L24: =E24*100% -> 21520.88 | N24: =60000 -> 60000 | O24: =E24*10% -> 2152.088 | P24: 10000 | R24: =Q24+P24+O24+N24+M24+L24+K24+J24+I24+H24+G24+F24+E24 -> 267454.07 | T24: =20000 -> 20000 | U24: =111833.33 -> 111833.33 | W24: 32008.563 | X24: =W24+V24+U24+T24+S24 -> 163841.89 | Y24: 103612.18 | Z24: =R24-X24 -> 103612.18
A25: 19 | B25: YAKUB OLUWATOYIN USMAN | C25: ASST. ADMIN. OFFICER | D25: 10(9) | E25: 18281.64 | G25: =E25*300% -> 54844.92 | H25: =E25*7.5% -> 1371.123 | J25: =E25*50% -> 9140.82 | K25: =E25*350% -> 63985.74 | L25: =E25*100% -> 18281.64 | N25: =60000 -> 60000 | O25: =E25*10% -> 1828.164 | P25: 10000 | R25: =Q25+P25+O25+N25+M25+L25+K25+J25+I25+H25+G25+F25+E25 -> 237734.05 | T25: 0 | U25: 0 | W25: 27105.987 | X25: =W25+V25+U25+T25+S25 -> 27105.987 | Y25: 210628.06 | Z25: =R25-X25 -> 210628.06
A26: 20 | B26: ELIZABETH OGECHUKWU ONYEAKU | C26: ICT OFFICER | D26: 9(8) | E26: 14736.14 | G26: 44208.42 | H26: 1105.2105 | J26: 7368.07 | K26: 51576.49 | L26: 14736.14 | N26: 60000 | O26: 1473.614 | P26: 10000 | R26: 205204.08 | T26: 10000 | U26: =20000 -> 20000 | W26: 21640.953 | X26: =W26+V26+U26+T26+S26 -> 51640.953 | Y26: 153563.13 | Z26: =R26-X26 -> 153563.13
A27: 21 | B27: VICTOR ASUKWO | C27: ICT OFFICER | D27: 9(8) | E27: =15188.67 -> 15188.67 | G27: =E27*300% -> 45566.01 | H27: =E27*7.5% -> 1139.1502 | J27: =E27*50% -> 7594.335 | K27: =E27*350% -> 53160.345 | L27: =E27*100% -> 15188.67 | N27: =50000+10000 -> 60000 | O27: =E27*10% -> 1518.867 | P27: 10000 | R27: =Q27+P27+O27+N27+M27+L27+K27+J27+I27+H27+G27+F27+E27 -> 209356.05 | W27: 22338.483 | X27: =W27+V27+U27+T27+S27 -> 22338.483 | Y27: 187017.56 | Z27: =R27-X27 -> 187017.56
A28: 22 | B28: IJEOMA NKOLIKWA | C28: STORES OFFICER | D28: 9(8) | E28: =15188.67 -> 15188.67 | G28: =E28*300% -> 45566.01 | H28: =E28*7.5% -> 1139.1502 | J28: =E28*50% -> 7594.335 | K28: =E28*350% -> 53160.345 | L28: =E28*100% -> 15188.67 | N28: =50000+10000 -> 60000 | O28: =E28*10% -> 1518.867 | P28: 10000 | R28: =SUM(E28:Q28) -> 209356.05 | T28: =10000 -> 10000 | W28: 22338.483 | X28: =W28+V28+U28+T28+S28 -> 32338.483 | Y28: 177017.56 | Z28: =R28-X28 -> 177017.56
A29: 23 | B29: ABDULRAHMAN A SULAIMAN | C29: ASSISTANT STORES OFFICER | D29: 8(10) | E29: 13492.21 | G29: =E29*300% -> 40476.63 | H29: =E29*7.5% -> 1011.9157 | J29: =E29*50% -> 6746.105 | K29: =E29*350% -> 47222.735 | L29: =E29*100% -> 13492.21 | N29: =50000 -> 50000 | O29: =E29*10% -> 1349.221 | P29: 10000 | R29: =SUM(E29:Q29) -> 183791.03 | T29: =20000 -> 20000 | U29: =17500 -> 17500 | W29: 18102.903 | X29: =W29+V29+U29+T29+S29 -> 55602.903 | Y29: 128188.12 | Z29: =R29-X29 -> 128188.12
A30: 24 | B30: DARE SHEU MAGBON | C30: ASSIST. PG | D30: 8(10) | E30: 13492.21 | G30: =E30*300% -> 40476.63 | H30: =E30*7.5% -> 1011.9157 | J30: =E30*50% -> 6746.105 | K30: =E30*350% -> 47222.735 | L30: =E30*100% -> 13492.21 | N30: =50000 -> 50000 | O30: =E30*10% -> 1349.221 | P30: 10000 | R30: =SUM(E30:Q30) -> 183791.03 | T30: =30000+20000 -> 50000 | U30: 0 | W30: 18102.903 | X30: =W30+V30+U30+T30+S30 -> 68102.903 | Y30: 115688.12 | Z30: =R30-X30 -> 115688.12
A31: 25 | B31: JIMOH ADEBAYO ZAKA | C31: ASST. OFFICER/COMM | D31: 9(8) | E31: 15188.67 | G31: =E31*300% -> 45566.01 | H31: =E31*7.5% -> 1139.1502 | J31: =E31*50% -> 7594.335 | K31: =E31*350% -> 53160.345 | L31: =E31*100% -> 15188.67 | N31: =60000 -> 60000 | O31: =E31*10% -> 1518.867 | P31: 10000 | R31: =Q31+P31+O31+N31+M31+L31+K31+J31+I31+H31+G31+F31+E31 -> 209356.05 | T31: =50000 -> 50000 | U31: 50000 | V31: 0 | W31: 22338.483 | X31: =W31+V31+U31+T31+S31 -> 122338.48 | Y31: 87017.565 | Z31: =R31-X31 -> 87017.565
A32: 26 | B32: MOHAMMED BELLO | C32: PROTOCOL ASSISTANT | D32: 8(8) | E32: =12732 -> 12732 | G32: =E32*300% -> 38196 | H32: =E32*7.5% -> 954.9 | J32: =E32*50% -> 6366 | K32: =E32*350% -> 44562 | L32: =E32*100% -> 12732 | N32: =50000 -> 50000 | O32: =E32*10% -> 1273.2 | P32: 10000 | R32: =SUM(E32:Q32) -> 176816.1 | T32: =0 -> 0 | U32: =26666.67 -> 26666.67 | W32: 17042.714 | X32: =W32+V32+U32+T32+S32 -> 43709.384 | Y32: 133106.72 | Z32: =R32-X32 -> 133106.72
A33: 27 | B33: SULEIMAN ABUBAKAR SODEEQ | C33: ASST. ADMIN. OFFICER | D33: 8(8) | E33: =12732 -> 12732 | G33: =E33*300% -> 38196 | H33: =E33*7.5% -> 954.9 | J33: =E33*50% -> 6366 | K33: =E33*350% -> 44562 | L33: =E33*100% -> 12732 | N33: =50000 -> 50000 | O33: =E33*10% -> 1273.2 | P33: 10001 | R33: =SUM(E33:Q33) -> 176817.1 | T33: =0 -> 0 | W33: 17042.866 | X33: =W33+V33+U33+T33+S33 -> 17042.866 | Y33: 159774.23 | Z33: =R33-X33 -> 159774.23
A34: 28 | B34: HARUNA JIBRIL A. | C34: ASST. ADMIN. OFFICER | D34: 8(8) | E34: =12732 -> 12732 | G34: =E34*300% -> 38196 | H34: =E34*7.5% -> 954.9 | J34: =E34*50% -> 6366 | K34: =E34*350% -> 44562 | L34: =E34*100% -> 12732 | N34: =50000 -> 50000 | O34: =E34*10% -> 1273.2 | P34: 10002 | R34: =SUM(E34:Q34) -> 176818.1 | T34: 20000 | W34: 17043.018 | X34: =W34+V34+U34+T34+S34 -> 37043.018 | Y34: 139775.08 | Z34: =R34-X34 -> 139775.08
A35: 29 | B35: SHOLAGBERU T. SOFIAT | C35: ASST. ACCOUNT. OFFICER | D35: 8(7) | E35: 12351.94 | G35: 37055.82 | H35: 926.3955 | J35: 6175.97 | K35: 43231.79 | L35: 12351.94 | N35: 50000 | O35: 1235.194 | P35: 10000 | R35: 173329.05 | T35: 10000 | U35: 63888.89 | V35: 0 | W35: 16512.682 | X35: =W35+V35+U35+T35+S35 -> 90401.572 | Y35: 82927.477 | Z35: =R35-X35 -> 82927.477
B36: TOTAL | C36: 29 | E36: =SUM(E7:E35) -> 878401.87 | F36: =SUM(F7:F35) -> 0 | G36: =SUM(G7:G35) -> 2474716.9 | H36: =SUM(H7:H35) -> 101990.11 | I36: =SUM(I7:I35) -> 481466.28 | J36: =SUM(J7:J35) -> 431176.5 | K36: =SUM(K7:K35) -> 2512695.9 | L36: =SUM(L7:L35) -> 838279.69 | ... X36: =SUM(X7:X35) -> 3267190 | Y36: 8260507.5 | Z36: =SUM(Z7:Z35) -> 7648150.4
B38: INTERNAL AUDIT
A39: 1 | B39: OSANAIYE DAVID AKINYEMI | C39: DIRECTOR INTERNAL AUDIT | D39: 17(9) | E39: 81740.02 | G39: =E39*300% -> 245220.06 | H39: =E39*7.5% -> 6130.5015 | I39: 80244.38 | J39: =E39*50% -> 40870.01 | K39: =E39*350% -> 286090.07 | L39: =E39*100% -> 81740.02 | N39: =100000 -> 100000 | O39: =E39*10% -> 8174.002 | P39: 20000 | R39: =SUM(E39:Q39) -> 950209.06 | S39: ='JUNE 2023'!F194 -> 0 | T39: =100000 -> 100000 | U39: ='[2]OCT 2022 '!$D$182 -> 175000 | W39: 161106.81 | X39: =W39+V39+U39+T39+S39 -> 436106.81 | Y39: 514102.26 | Z39: =R39-X39 -> 514102.26
A40: 2 | B40: JAMILA ABDUL | C40: AUDITOR II | D40: 8(7) | E40: 12351.94 | G40: =E40*300% -> 37055.82 | H40: =E40*7.5% -> 926.3955 | J40: =E40*50% -> 6175.97 | K40: =E40*350% -> 43231.79 | L40: =E40*100% -> 12351.94 | N40: =50000 -> 50000 | O40: =E40*10% -> 1235.194 | P40: 10000 | R40: =(Q40+P40+O40+N40+M40+L40+K40+J40+I40+H40+G40+F40+E40) -> 173329.05 | T40: =20000 -> 20000 | V40: 0 | W40: 16512.682 | X40: =W40+V40+U40+T40+S40 -> 36512.682 | Y40: 136816.37 | Z40: =R40-X40 -> 136816.37
C41: 2 | E41: =SUM(E39:E40) -> 94091.96 | G41: =SUM(G39:G40) -> 282275.88 | H41: =SUM(H39:H40) -> 7056.897 | I41: =SUM(I39:I40) -> 80244.38 | J41: =SUM(J39:J40) -> 47045.98 | K41: =SUM(K39:K40) -> 329321.86 | L41: =SUM(L39:L40) -> 94091.96 | N41: =SUM(N39:N40) -> 150000 | O41: =SUM(O39:O40) -> 9409.196 | P41: =SUM(P39:P40) -> 30000 | R41: =SUM(R39:R40) -> 1123538.1 | T41: =SUM(T39:T40) -> 120000 | U41: =SUM(U39:U40) -> 175000 | V41: =SUM(V39:V40) -> 0 | W41: =SUM(W39:W40) -> 177619.49 | X41: =SUM(X39:X40) -> 472619.49 | Y41: 650918.62 | Z41: =SUM(Z39:Z40) -> 650918.62
B43: LEG. SUPPORT SEVICES
A44: 1 | B44: PROF. EDOBA BRIGHT OMOREGBE | C44: AG. DLSS | D44: 17(9) | E44: 81740.02 | G44: =E44*300% -> 245220.06 | H44: =E44*7.5% -> 6130.5015 | I44: 80244.38 | J44: =E44*50% -> 40870.01 | K44: =E44*350% -> 286090.07 | L44: =E44*100% -> 81740.02 | M44: =200000 -> 200000 | O44: =E44*10% -> 8174.002 | P44: 20000 | R44: =SUM(E44:Q44) -> 1050209.1 | T44: =200000 -> 200000 | U44: =380000 -> 380000 | W44: 180306.81 | X44: =W44+V44+U44+T44+S44 -> 760306.81 | Y44: 289902.26 | Z44: =R44-X44 -> 289902.26
A45: 2 | B45: DR CLINTON JAJA | C45: SENIOR RESEARCH FELLOW | D45: 15(9) | E45: 33507.5 | G45: =E45*300% -> 100522.5 | H45: =E45*7.5% -> 2513.0625 | I45: 40122.19 | J45: =E45*50% -> 16753.75 | K45: =E45*350% -> 117276.25 | L45: =E45*100% -> 33507.5 | M45: =160000 -> 160000 | O45: =E45*10% -> 3350.75 | P45: 20000 | Q45: 0 | R45: =SUM(E45:Q45) -> 527553.5 | T45: 50000 | U45: 385000 | W45: 79956.939 | X45: =W45+V45+U45+T45+S45 -> 514956.94 | Y45: 12596.563 | Z45: =R45-X45 -> 12596.563
A46: 3 | B46: BETHEL UZOMA IHUGBA | C46: SNR RESEARCH FELLOW | D46: 15(9) | E46: 33507.5 | G46: =E46*300% -> 100522.5 | H46: =E46*7.5% -> 2513.0625 | I46: 40122.19 | J46: =E46*50% -> 16753.75 | K46: =E46*350% -> 117276.25 | L46: =E46*100% -> 33507.5 | M46: =160000 -> 160000 | O46: =E46*10% -> 3350.75 | P46: 20000 | R46: =SUM(E46:Q46) -> 527553.5 | T46: =80000+23000 -> 103000 | U46: =246905.96 -> 246905.96 | W46: 79956.939 | X46: =W46+V46+U46+T46+S46 -> 429862.9 | Y46: 97690.603 | Z46: =R46-X46 -> 97690.603
A47: 4 | B47: OGUCHE SAMUEL | C47: SNR RESEARCH FELLOW | D47: 15(9) | E47: 33507.5 | G47: =E47*300% -> 100522.5 | H47: =E47*7.5% -> 2513.0625 | I47: 40122.19 | J47: =E47*50% -> 16753.75 | K47: =E47*350% -> 117276.25 | L47: =E47*100% -> 33507.5 | M47: =160000 -> 160000 | O47: =E47*10% -> 3350.75 | P47: 20000 | R47: =SUM(E47:Q47) -> 527553.5 | T47: =30000 -> 30000 | U47: =176288.88 -> 176288.88 | W47: 79956.939 | X47: =W47+V47+U47+T47+S47 -> 286245.82 | Y47: 241307.68 | Z47: =R47-X47 -> 241307.68
A48: 5 | B48: IBRAHIM USMAN | C48: SNR RESEARCH FELLOW | D48: 15(8) | E48: 32263.2 | G48: =E48*300% -> 96789.6 | H48: =E48*7.5% -> 2419.74 | I48: =40122.19 -> 40122.19 | J48: =E48*50% -> 16131.6 | K48: =E48*350% -> 112921.2 | L48: =E48*100% -> 32263.2 | M48: =140000+20000 -> 160000 | O48: =E48*10% -> 3226.32 | P48: 20000 | Q48: 0 | R48: =SUM(E48:Q48) -> 516137.05 | V48: 806.58 | W48: =77764.98 -> 77764.98 | X48: =W48+V48+U48+T48+S48 -> 78571.56 | Y48: 437565.49 | Z48: =R48-X48 -> 437565.49
A49: 6 | B49: DR MOHAMMED O. AMALI | C49: RESEARCH FELLOW I | D49: 14(10) | E49: 27611.23 | G49: =E49*300% -> 82833.69 | H49: =E49*7.5% -> 2070.8422 | J49: =E49*50% -> 13805.615 | K49: =E49*350% -> 96639.305 | L49: =E49*100% -> 27611.23 | M49: =140000 -> 140000 | O49: =E49*10% -> 2761.123 | P49: 20000 | R49: =SUM(E49:Q49) -> 413333.04 | T49: =15000 -> 15000 | U49: =216666.67 -> 216666.67 | W49: 57889.865 | X49: =W49+V49+U49+T49+S49 -> 289556.53 | Y49: 123776.5 | Z49: =R49-X49 -> 123776.5
A50: 7 | B50: YAHAYA SHAMSU | C50: RESEARCH FELLOW 1 | D50: 14(10) | E50: 27611.23 | G50: =E50*300% -> 82833.69 | H50: =E50*7.5% -> 2070.8422 | J50: =E50*50% -> 13805.615 | K50: =E50*350% -> 96639.305 | L50: =E50*100% -> 27611.23 | M50: =140000 -> 140000 | O50: =E50*10% -> 2761.123 | P50: 20000 | R50: =SUM(E50:Q50) -> 413333.04 | V50: 0 | W50: 58026.609 | X50: =W50+V50+U50+T50+S50 -> 58026.609 | Y50: 355306.43 | Z50: =R50-X50 -> 355306.43
A51: 8 | B51: OFORDEME ADAOBI JULIA | C51: RESEARCH FELLOW 1 | D51: 14(9) | E51: 26732.65 | G51: =E51*300% -> 80197.95 | H51: =E51*7.5% -> 2004.9488 | I51: 0 | J51: =E51*50% -> 13366.325 | K51: =E51*350% -> 93564.275 | L51: =E51*100% -> 26732.65 | M51: =120000+20000 -> 140000 | O51: =E51*10% -> 2673.265 | P51: 15000 | Q51: 0 | R51: =SUM(E51:Q51) -> 400272.06 | W51: 55518.903 | X51: =W51+V51+U51+T51+S51 -> 55518.903 | Y51: 344753.16 | Z51: =R51-X51 -> 344753.16
A52: 9 | B52: DORIS DAKDA AARON | C52: RESEARCH FELLOW II | D52: 13(10) | E52: 25523.45 | G52: =E52*300% -> 76570.35 | H52: =E52*7.5% -> 1914.2587 | J52: =E52*50% -> 12761.725 | K52: =E52*350% -> 89332.075 | L52: =E52*100% -> 25523.45 | M52: =120000 -> 120000 | O52: =E52*10% -> 2552.345 | P52: 15000 | R52: =SUM(E52:Q52) -> 369177.65 | T52: =10000+10000 -> 20000 | V52: 638.08625 | W52: 49548.776 | X52: =W52+V52+U52+T52+S52 -> 70186.862 | Y52: 298990.79 | Z52: =R52-X52 -> 298990.79
A53: 10 | B53: ZAINAB AKINDE | C53: RESEARCH OFFICER | D53: 9(7) | E53: =14736.14 -> 14736.14 | G53: =E53*300% -> 44208.42 | H53: =E53*7.5% -> 1105.2105 | J53: =E53*50% -> 7368.07 | K53: =E53*350% -> 51576.49 | L53: =E53*100% -> 14736.14 | M53: =100000 -> 100000 | O53: =E53*10% -> 1473.614 | P53: 10000 | R53: =SUM(E53:Q53) -> 245204.08 | W53: 28360.953 | X53: =W53+V53+U53+T53 -> 28360.953 | Y53: 216843.13 | Z53: =R53-X53 -> 216843.13
A54: 11 | B54: ABDULLAHI AHMAD USMAN | C54: RESEARCH OFFICER | D54: 9(7) | E54: =14736.14 -> 14736.14 | G54: =E54*300% -> 44208.42 | H54: =E54*7.5% -> 1105.2105 | J54: =E54*50% -> 7368.07 | K54: =E54*350% -> 51576.49 | L54: =E54*100% -> 14736.14 | M54: =100000 -> 100000 | O54: =E54*10% -> 1473.614 | P54: 10000 | R54: =SUM(E54:Q54) -> 245204.08 | W54: 28360.953 | X54: =W54+V54+U54+T54 -> 28360.953 | Y54: 216843.13 | Z54: =R54-X54 -> 216843.13
A55: 12 | B55: GUNAT NANSAK MARK | C55: RESEARCH OFFICER | D55: 9(7) | E55: =14736.14 -> 14736.14 | G55: =E55*300% -> 44208.42 | H55: =E55*7.5% -> 1105.2105 | J55: =E55*50% -> 7368.07 | K55: =E55*350% -> 51576.49 | L55: =E55*100% -> 14736.14 | M55: =100000 -> 100000 | O55: =E55*10% -> 1473.614 | P55: 10001 | R55: =SUM(E55:Q55) -> 245205.08 | W55: 28360.953 | X55: =W55+V55+U55+T55 -> 28360.953 | Y55: 216844.13 | Z55: =R55-X55 -> 216844.13
B56: TOTAL | C56: 12 | E56: =SUM(E44:E55) -> 366212.7 | F56: =SUM(F44:F55) -> 0 | G56: =SUM(G44:G55) -> 1098638.1 | H56: =SUM(H44:H55) -> 27465.953 | I56: =SUM(I44:I55) -> 240733.14 | J56: =SUM(J44:J55) -> 183106.35 | K56: =SUM(K44:K55) -> 1281744.4 | L56: =SUM(L44:L55) -> 366212.7 | ... X56: =SUM(X44:X55) -> 2628315.8 | Y56: 2852419.9 | Z56: =SUM(Z44:Z55) -> 2852419.9
B58: LEGAL SERVICES
A59: 1 | B59: DR SHUIBU DANWANKA | C59: DIRECTOR LEGAL SERVICES | D59: 17(9) | E59: 81740.02 | G59: =E59*300% -> 245220.06 | H59: =E59*7.5% -> 6130.5015 | I59: 80244.38 | J59: =E59*50% -> 40870.01 | K59: =E59*350% -> 286090.07 | L59: =E59*100% -> 81740.02 | M59: =200000 -> 200000 | O59: =E59*10% -> 8174.002 | P59: 20000 | Q59: 0 | R59: =SUM(E59:Q59) -> 1050209.1 | T59: 120000 | V59: 0 | W59: 180306.81 | X59: =W59+V59+U59+T59+S59 -> 300306.81 | Y59: 749902.26 | Z59: =R59-X59 -> 749902.26
A60: 2 | B60: ABDULSALAM BAKO | C60: MANAGER, LEGAL SERVICES | D60: 15 (8) | E60: 32263.2 | G60: 96789.6 | H60: 2419.74 | I60: 40122.19 | J60: 16131.6 | K60: 112921.2 | L60: 32263.2 | N60: 80000 | O60: 3226.32 | P60: 20000 | Q60: 0 | R60: 436137.05 | T60: 50000 | U60: 145000 | V60: 0 | W60: 62404.98 | X60: 257404.98 | Y60: 178732.07 | Z60: 178732.07
B61: TOTAL | C61: 2 | E61: =SUM(E59:E60) -> 114003.22 | G61: =SUM(G59:G60) -> 342009.66 | H61: =SUM(H59:H60) -> 8550.2415 | I61: =SUM(I59:I60) -> 120366.57 | J61: =SUM(J59:J60) -> 57001.61 | K61: =SUM(K59:K60) -> 399011.27 | L61: =SUM(L59:L60) -> 114003.22 | M61: =SUM(M59:M60) -> 200000 | N61: =SUM(N59:N60) -> 80000 | ... X61: =SUM(X59:X60) -> 557711.79 | Y61: 928634.33 | Z61: =SUM(Z59:Z60) -> 928634.33
B63: DEMOCRACY & GOVERNANCE
A64: 1 | B64: DR. ADEWALE ADEREMI | C64: DIRECTOR, DEMOCRATIC STUDIES | D64: 17(9) | E64: 81740.02 | G64: =E64*300% -> 245220.06 | H64: =E64*7.5% -> 6130.5015 | I64: =80244.38 -> 80244.38 | J64: =E64*50% -> 40870.01 | K64: =E64*350% -> 286090.07 | L64: =E64*100% -> 81740.02 | M64: =200000 -> 200000 | O64: =E64*10% -> 8174.002 | P64: 20000 | Q64: 0 | R64: =SUM(E64:Q64) -> 1050209.1 | T64: =100000+100000 -> 200000 | W64: 180306.81 | X64: =W64+V64+U64+T64+S64 -> 380306.81 | Y64: 669902.26 | Z64: =R64-X64 -> 669902.26
A65: 2 | B65: NDANUSA MOHAMMED MANZUMA | C65: SNR RESEARCH FELLOW | D65: 15 (7) | E65: 31018.84 | G65: =E65*300% -> 93056.52 | H65: =E65*7.5% -> 2326.413 | I65: 40122.19 | J65: =E65*50% -> 15509.42 | K65: =E65*350% -> 108565.94 | L65: =E65*100% -> 31018.84 | M65: =160000 -> 160000 | O65: =E65*10% -> 3101.884 | P65: 20000 | Q65: 0 | R65: =SUM(E65:Q65) -> 504720.05 | T65: =100000 -> 100000 | U65: =131250 -> 131250 | W65: 75572.916 | X65: =W65+V65+U65+T65+S65 -> 306822.92 | Y65: 197897.13 | Z65: =R65-X65 -> 197897.13
A66: 3 | B66: EJALONIBU GANIYU LAYI | C66: RESEARCH FELLOW 11 | D66: 13(10) | E66: 25523.45 | G66: =E66*300% -> 76570.35 | H66: =E66*7.5% -> 1914.2587 | J66: =E66*50% -> 12761.725 | K66: =E66*350% -> 89332.075 | L66: =E66*100% -> 25523.45 | M66: =120000 -> 120000 | O66: =E66*10% -> 2552.345 | P66: 15000 | R66: =SUM(E66:Q66) -> 369177.65 | T66: =110000 -> 110000 | W66: 49548.776 | X66: =W66+V66+U66+T66+S66 -> 159548.78 | Y66: 209628.88 | Z66: =R66-X66 -> 209628.88
A67: 4 | B67: LOHNA BONKAT JONATHAN | C67: RESEARCH FELLOW 11 | D67: 13(9) | E67: 24741.26 | G67: =E67*300% -> 74223.78 | H67: =E67*7.5% -> 1855.5945 | I67: 0 | J67: =E67*50% -> 12370.63 | K67: =E67*350% -> 86594.41 | L67: =E67*100% -> 24741.26 | M67: =120000 -> 120000 | O67: =E67*10% -> 2474.126 | P67: 15000 | Q67: 0 | R67: =SUM(E67:Q67) -> 362001.06 | T67: =20000+65000 -> 85000 | U67: 0 | V67: 0 | W67: 48170.87 | X67: =W67+V67+U67+T67+S67 -> 133170.87 | Y67: 228830.19 | Z67: =R67-X67 -> 228830.19
A68: 5 | B68: YUNUSA ABDULLAHI | C68: RESEARCH FELLOW 1 | D68: 14(10) | E68: 27611.23 | G68: =E68*300% -> 82833.69 | H68: =E68*7.5% -> 2070.8422 | J68: =E68*50% -> 13805.615 | K68: =E68*350% -> 96639.305 | L68: =E68*100% -> 27611.23 | M68: =140000 -> 140000 | O68: =E68*10% -> 2761.123 | P68: 20000 | R68: =SUM(E68:Q68) -> 413333.04 | T68: =10000 -> 10000 | U68: =54585.66 -> 54585.66 | W68: 58026.609 | X68: =W68+V68+U68+T68+S68 -> 122612.27 | Y68: 290720.77 | Z68: =R68-X68 -> 290720.77
A69: 6 | B69: EMILY EKHIDE | C69: RESEARCH FELLOW 1 | D69: 14(9) | E69: 26732.65 | G69: 80197.95 | H69: 2004.9488 | I69: 0 | J69: 13366.325 | K69: 93564.275 | L69: 26732.65 | M69: 140000 | O69: 2673.265 | P69: =15000+5000 -> 20000 | Q69: 0 | R69: =SUM(E69:Q69) -> 405272.06 | W69: =56318.07+1598.34 -> 57916.41 | X69: =W69+V69+U69+T69+S69 -> 57916.41 | Y69: 347355.65 | Z69: =R69-X69 -> 347355.65
A70: 7 | B70: UDEFUNA NNADOZIE PATRICK | C70: RESEARCH OFFICER | D70: 12(7) | E70: =20749 -> 20749 | G70: =E70*300% -> 62247 | H70: =E70*7.5% -> 1556.175 | I70: 0 | J70: =E70*50% -> 10374.5 | K70: =E70*350% -> 72621.5 | L70: =E70*100% -> 20749 | M70: =110000 -> 110000 | O70: =E70*10% -> 2074.9 | P70: 15000 | Q70: 0 | R70: =SUM(E70:Q70) -> 315372.08 | T70: =10000 -> 10000 | U70: =65885.83 -> 65885.83 | W70: =40149.18 -> 40149.18 | X70: =W70+V70+U70+T70+S70 -> 116035.01 | Y70: 199337.07 | Z70: =R70-X70 -> 199337.07
A71: 8 | B71: SHAFIU YAHYA MIKAIL | C71: PRINCIPAL RESEARCH OFFICER | D71: 12(7) | E71: 20749 | G71: =E71*300% -> 62247 | H71: =E71*7.5% -> 1556.175 | I71: 0 | J71: =E71*50% -> 10374.5 | K71: =E71*350% -> 72621.5 | L71: =E71*100% -> 20749 | M71: =110000 -> 110000 | O71: =E71*10% -> 2074.9 | P71: 15000 | Q71: 0 | R71: =SUM(E71:Q71) -> 315372.08 | T71: =52000-2000 -> 50000 | W71: 40149.175 | X71: =W71+V71+U71+T71+S71 -> 90149.175 | Y71: 225222.9 | Z71: =R71-X71 -> 225222.9
A72: 9 | B72: HASSAN YERIMA | C72: PRINCIPAL RESEARCH OFFICER | D72: 12(7) | E72: 20749 | G72: =E72*300% -> 62247 | H72: =E72*7.5% -> 1556.175 | I72: 0 | J72: =E72*50% -> 10374.5 | K72: =E72*350% -> 72621.5 | L72: =E72*100% -> 20749 | M72: =110000 -> 110000 | O72: =E72*10% -> 2074.9 | P72: 15000 | Q72: 0 | R72: =SUM(E72:Q72) -> 315372.08 | T72: =67000-2000 -> 65000 | W72: 40149.175 | X72: =W72+V72+U72+T72+S72 -> 105149.18 | Y72: 210222.9 | Z72: =R72-X72 -> 210222.9
A73: 10 | B73: HAUWA PATE SADIQ | C73: PRINCIPAL PROGRAMME OFFICER | D73: 12(8) | E73: 21520.88 | G73: =E73*300% -> 64562.64 | H73: =E73*7.5% -> 1614.066 | J73: =E73*50% -> 10760.44 | K73: =E73*350% -> 75323.08 | L73: =E73*100% -> 21520.88 | M73: =110000 -> 110000 | O73: =E73*10% -> 2152.088 | P73: 15000 | R73: =SUM(E73:Q73) -> 322454.07 | T73: =80000+20000 -> 100000 | W73: 41338.951 | X73: =W73+V73+U73+T73+S73 -> 141338.95 | Y73: 181115.12 | Z73: =R73-X73 -> 181115.12
A74: 11 | B74: ABAYOMI KAYODE QUADRI | C74: RESEARCH OFFICER | D74: 10(8) | E74: 17784.1 | G74: =E74*300% -> 53352.3 | H74: =E74*7.5% -> 1333.8075 | J74: =E74*50% -> 8892.05 | K74: =E74*350% -> 62244.35 | L74: =E74*100% -> 17784.1 | M74: =100000 -> 100000 | O74: =E74*10% -> 1778.41 | P74: 10000 | R74: =SUM(E74:Q74) -> 273169.12 | T74: 0 | U74: 0 | W74: 33059.078 | X74: =W74+V74+U74+T74+S74 -> 33059.078 | Y74: 240110.04 | Z74: =R74-X74 -> 240110.04
A75: 12 | B75: NNANDI LIVINUS ATURE | C75: RESEARCH ASSISTANT | D75: 9(8) | E75: =15188.67 -> 15188.67 | G75: =E75*300% -> 45566.01 | H75: =E75*7.5% -> 1139.1502 | J75: =E75*50% -> 7594.335 | K75: =E75*350% -> 53160.345 | L75: =E75*100% -> 15188.67 | M75: =100000 -> 100000 | O75: =E75*10% -> 1518.867 | P75: 10000 | R75: =SUM(E75:Q75) -> 249356.05 | T75: =10000 -> 10000 | U75: =95833.33 -> 95833.33 | W75: 29058.483 | X75: =W75+V75+U75+T75+S75 -> 134891.81 | Y75: 114464.23 | Z75: =R75-X75 -> 114464.23
A76: 13 | B76: LUCKY AGWOM | C76: RESEARCH ASSISTANT | D76: 8(8) | E76: =12732 -> 12732 | G76: =E76*300% -> 38196 | H76: =E76*7.5% -> 954.9 | J76: =E76*50% -> 6366 | K76: =E76*350% -> 44562 | L76: =E76*100% -> 12732 | M76: =100000 -> 100000 | O76: =E76*10% -> 1273.2 | P76: 10000 | R76: =SUM(E76:Q76) -> 226816.1 | W76: 25271.771 | X76: =W76+V76+U76+T76+S76 -> 25271.771 | Y76: 201544.33 | Z76: =R76-X76 -> 201544.33
B77: TOTAL | C77: 13 | E77: =SUM(E64:E76) -> 346840.1 | F77: =SUM(F64:F76) -> 0 | G77: =SUM(G64:G76) -> 1040520.3 | H77: =SUM(H64:H76) -> 26013.007 | I77: =SUM(I64:I76) -> 120366.57 | J77: =SUM(J64:J76) -> 173420.05 | K77: =SUM(K64:K76) -> 1213940.4 | L77: =SUM(L64:L76) -> 346840.1 | M77: =SUM(M64:M76) -> 1620000 | O77: =SUM(O64:O76) -> 34684.01 | P77: =SUM(P64:P76) -> 200000 | Q77: =SUM(Q64:Q76) -> 0 | R77: =SUM(R64:R76) -> 5122624.5 | T77: =SUM(T64:T76) -> 740000 | U77: =SUM(U64:U76) -> 347554.82 | V77: =SUM(V64:V76) -> 0 | W77: =SUM(W64:W76) -> 718718.2 | X77: =SUM(X64:X76) -> 1806273 | Y77: 3316351.5 | Z77: =SUM(Z64:Z76) -> 3316351.5
B79: DEPARTMENT OF STUDIES
A80: 1 | B80: DR ASIMIYU G. ABIOLA | C80: DIRECTOR POST GRADUATE | D80: 17(9) | E80: 81740.02 | G80: =E80*300% -> 245220.06 | H80: =E80*7.5% -> 6130.5015 | I80: 80244.38 | J80: =E80*50% -> 40870.01 | K80: =E80*350% -> 286090.07 | L80: =E80*100% -> 81740.02 | M80: =200000 -> 200000 | O80: =E80*10% -> 8174.002 | P80: 20000 | Q80: 0 | R80: =SUM(E80:Q80) -> 1050209.1 | T80: 250000 | U80: =0 -> 0 | V80: 0 | W80: 180306.81 | X80: =W80+V80+U80+T80+S80 -> 430306.81 | Y80: 619902.26 | Z80: =R80-X80 -> 619902.26
A81: 2 | B81: USMAN WALI | C81: SENIOR RESEARCH FELLOW | D81: 15 (7) | E81: 31018.84 | G81: =E81*300% -> 93056.52 | H81: =E81*7.5% -> 2326.413 | I81: 40122.19 | J81: =E81*50% -> 15509.42 | K81: =E81*350% -> 108565.94 | L81: =E81*100% -> 31018.84 | M81: =160000 -> 160000 | O81: =E81*10% -> 3101.884 | P81: 20000 | Q81: 0 | R81: =SUM(E81:Q81) -> 504720.05 | V81: 0 | W81: 75572.916 | X81: =W81+V81+U81+T81+S81 -> 75572.916 | Y81: 429147.13 | Z81: =R81-X81 -> 429147.13
A82: 3 | B82: MOSHOOD TOSHO AMUDA | C82: MANAGER, EXAMS & RECORDS | D82: 15 (7) | E82: 31018.84 | G82: =E82*300% -> 93056.52 | H82: =E82*7.5% -> 2326.413 | I82: 40122.19 | J82: =E82*50% -> 15509.42 | K82: =E82*350% -> 108565.94 | L82: =E82*100% -> 31018.84 | M82: =160000 -> 160000 | O82: =E82*10% -> 3101.884 | P82: 20000 | Q82: 0 | R82: =SUM(E82:Q82) -> 504720.05 | V82: 0 | W82: 75572.916 | X82: =W82+V82+U82+T82+S82 -> 75572.916 | Y82: 429147.13 | Z82: =R82-X82 -> 429147.13
A83: 4 | B83: ANTHONY EDET | C83: ASST. MGR M&E | D83: 13(10) | E83: 25523.45 | G83: =E83*300% -> 76570.35 | H83: =E83*7.5% -> 1914.2587 | I83: 0 | J83: =E83*50% -> 12761.725 | K83: =E83*350% -> 89332.075 | L83: =E83*100% -> 25523.45 | M83: =120000 -> 120000 | O83: =E83*10% -> 2552.345 | P83: 15000 | Q83: 0 | R83: =Q83+P83+O83+N83+M83+L83+K83+J83+I83+H83+G83+F83+E83 -> 369177.65 | T83: 20000 | U83: =68750 -> 68750 | V83: 638.08625 | W83: 49548.776 | X83: =W83+V83+U83+T83+S83 -> 138936.86 | Y83: 230240.79 | Z83: =R83-X83 -> 230240.79
A84: 5 | B84: IGWE STACY | C84: PROGRAMME OFFICER | D84: 10(8) | E84: 17784.1 | G84: =E84*300% -> 53352.3 | H84: =E84*7.5% -> 1333.8075 | J84: =E84*50% -> 8892.05 | K84: =E84*350% -> 62244.35 | L84: =E84*100% -> 17784.1 | M84: =100000 -> 100000 | O84: =E84*10% -> 1778.41 | P84: 10000 | R84: =SUM(E84:Q84) -> 273169.12 | T84: =50000 -> 50000 | U84: =50000 -> 50000 | W84: 33059.078 | X84: =W84+V84+U84+T84+S84 -> 133059.08 | Y84: 140110.04 | Z84: =R84-X84 -> 140110.04
B85: TOTAL | C85: 5 | E85: =SUM(E80:E84) -> 187085.25 | G85: =SUM(G80:G84) -> 561255.75 | H85: =SUM(H80:H84) -> 14031.394 | I85: =SUM(I80:I84) -> 160488.76 | J85: =SUM(J80:J84) -> 93542.625 | K85: =SUM(K80:K84) -> 654798.38 | L85: =SUM(L80:L84) -> 187085.25 | M85: =SUM(M80:M84) -> 740000 | O85: =SUM(O80:O84) -> 18708.525 | P85: =SUM(P80:P84) -> 85000 | Q85: =SUM(Q80:Q84) -> 0 | R85: =SUM(R80:R84) -> 2701995.9 | T85: =SUM(T80:T84) -> 320000 | U85: =SUM(U80:U84) -> 118750 | V85: =SUM(V80:V84) -> 638.08625 | W85: =SUM(W80:W84) -> 414060.49 | X85: =SUM(X80:X84) -> 853448.58 | Y85: 1848547.3 | Z85: =SUM(Z80:Z84) -> 1848547.3
B87: ECON. DEV. & SOC. RESEARCH
A88: 1 | B88: TERFA WILLIAMS ABRAHAM | C88: SNR RESEARCH FELLOW | D88: 15(9) | E88: 33507.5 | G88: =E88*300% -> 100522.5 | H88: =E88*7.5% -> 2513.0625 | I88: =40122.19 -> 40122.19 | J88: =E88*50% -> 16753.75 | K88: =E88*350% -> 117276.25 | L88: =E88*100% -> 33507.5 | M88: =160000 -> 160000 | O88: =E88*10% -> 3350.75 | P88: 20000 | Q88: 100000 | R88: =SUM(E88:Q88) -> 627553.5 | W88: 99156.94 | X88: =W88+V88+U88+T88+S88 -> 99156.94 | Y88: 447596.56 | Z88: =R88-X88 -> 528396.56
A89: 2 | B89: DR AUGUSTINE C. OSIGWE | C89: SNR RESEARCH FELLOW | D89: 15(9) | E89: 33507.5 | G89: =E89*300% -> 100522.5 | H89: =E89*7.5% -> 2513.0625 | I89: =40122.19 -> 40122.19 | J89: =E89*50% -> 16753.75 | K89: =E89*350% -> 117276.25 | L89: =E89*100% -> 33507.5 | M89: =160000 -> 160000 | O89: =E89*10% -> 3350.75 | P89: 20000 | R89: =SUM(E89:Q89) -> 527553.5 | T89: =30000 -> 30000 | U89: 98750 | V89: 837.6875 | W89: 79796.103 | X89: =W89+V89+U89+T89+S89 -> 209383.79 | Y89: 318169.71 | Z89: =R89-X89 -> 318169.71
A90: 3 | B90: NGARA CHRISTOPHER OCHANJA | C90: RESEARCH FELLOW 1 | D90: 14(11) | E90: =28489.81 -> 28489.81 | G90: =E90*300% -> 85469.43 | H90: =E90*7.5% -> 2136.7357 | J90: =E90*50% -> 14244.905 | K90: =E90*350% -> 99714.335 | L90: =E90*100% -> 28489.81 | M90: 140000 | O90: =E90*10% -> 2848.981 | P90: 20000 | Q90: 0 | R90: =SUM(E90:Q90) -> 421394.01 | T90: =20000 -> 20000 | U90: =163103.59 -> 163103.59 | V90: 712.24525 | W90: 59441.782 | X90: =W90+V90+U90+T90+S90 -> 243257.62 | Y90: 178136.39 | Z90: =R90-X90 -> 178136.39
A91: 4 | B91: OMOJU OLUWASOLA EMMANUEL | C91: RESEARCH FELLOW I | D91: 14(10) | E91: 27611.23 | G91: =E91*300% -> 82833.69 | H91: =E91*7.5% -> 2070.8422 | J91: =E91*50% -> 13805.615 | K91: =E91*350% -> 96639.305 | L91: =E91*100% -> 27611.23 | M91: 140000 | O91: =E91*10% -> 2761.123 | P91: 20000 | R91: =SUM(E91:Q91) -> 413333.04 | T91: =50000 -> 50000 | U91: =79861.11 -> 79861.11 | W91: 58026.609 | X91: =W91+V91+U91+T91+S91 -> 187887.72 | Y91: 225445.32 | Z91: =R91-X91 -> 225445.32
A92: 5 | B92: IBE EZECHI CYRIACUS | C92: RESEARCH FELLOW II | D92: 13(10) | E92: 25523.45 | G92: =E92*300% -> 76570.35 | H92: =E92*7.5% -> 1914.2587 | I92: 0 | J92: =E92*50% -> 12761.725 | K92: =E92*350% -> 89332.075 | L92: =E92*100% -> 25523.45 | M92: =120000 -> 120000 | O92: =E92*10% -> 2552.345 | P92: 15000 | Q92: 0 | R92: =SUM(E92:Q92) -> 369177.65 | T92: =50000 -> 50000 | U92: 25250 | W92: 49548.776 | X92: =W92+V92+U92+T92+S92 -> 124798.78 | Y92: 244378.88 | Z92: =R92-X92 -> 244378.88
A93: 6 | B93: OSIKHEN LEO IGBANOI | C93: RESEARCH FELLOW 11 | D93: 13(9) | E93: 24741.26 | G93: =E93*300% -> 74223.78 | H93: =E93*7.5% -> 1855.5945 | I93: 0 | J93: =E93*50% -> 12370.63 | K93: =E93*350% -> 86594.41 | L93: =E93*100% -> 24741.26 | M93: =120000 -> 120000 | O93: =E93*10% -> 2474.126 | P93: 15000 | Q93: 0 | R93: =SUM(E93:Q93) -> 362001.06 | W93: 48170.87 | X93: =W93+V93+U93+T93+S93 -> 48170.87 | Y93: 313830.19 | Z93: =R93-X93 -> 313830.19
A94: 7 | B94: OKUNGBOWA OSARETIN GODSPOWER | C94: RESEARCH FELLOW 11 | D94: 13(9) | E94: 24741.26 | G94: =E94*300% -> 74223.78 | H94: =E94*7.5% -> 1855.5945 | I94: 0 | J94: =E94*50% -> 12370.63 | K94: =E94*350% -> 86594.41 | L94: =E94*100% -> 24741.26 | M94: =120000 -> 120000 | O94: =E94*10% -> 2474.126 | P94: 15000 | Q94: 0 | R94: =SUM(E94:Q94) -> 362001.06 | T94: =100000-100000 -> 0 | W94: 48170.87 | X94: =W94+V94+U94+T94+S94 -> 48170.87 | Y94: 313830.19 | Z94: =R94-X94 -> 313830.19
A95: 8 | B95: YUSUF IBRAHIM | C95: PRINCIPAL RESEARCH OFFICER | D95: 12(7) | E95: =20749 -> 20749 | G95: =E95*300% -> 62247 | H95: =E95*7.5% -> 1556.175 | I95: 0 | J95: =E95*50% -> 10374.5 | K95: =E95*350% -> 72621.5 | L95: =E95*100% -> 20749 | M95: =110000 -> 110000 | O95: =E95*10% -> 2074.9 | P95: 15000 | Q95: 0 | R95: =SUM(E95:Q95) -> 315372.08 | T95: =20000 -> 20000 | W95: 40149.175 | X95: =W95+V95+U95+T95+S95 -> 60149.175 | Y95: 255222.9 | Z95: =R95-X95 -> 255222.9
A96: 9 | B96: MARYAM MUSA SADA | C96: ASSIT. RESEARCH OFFICER | D96: 10(7) | E96: 17286.33 | G96: =E96*300% -> 51858.99 | H96: =E96*7.5% -> 1296.4748 | J96: =E96*50% -> 8643.165 | K96: =E96*350% -> 60502.155 | L96: =E96*100% -> 17286.33 | M96: 100000 | O96: =E96*10% -> 1728.633 | P96: 10000 | R96: =SUM(E96:Q96) -> 268602.08 | W96: =32291.82 -> 32291.82 | X96: =W96+V96+U96+T96 -> 32291.82 | Y96: 796310.26 | Z96: =R96-X96 -> 236310.26
A97: 10 | B97: CHARITY EZENWAJIOBI | C97: REASEARCH. ASST. | D97: 8(8) | E97: =12732 -> 12732 | G97: 37055.82 | H97: 926.3955 | J97: 6175.97 | K97: 43231.79 | L97: 12351.94 | M97: =100000 -> 100000 | O97: 1235.194 | P97: 10000 | R97: =SUM(E97:Q97) -> 223709.11 | T97: 50000 | V97: 0 | W97: 24749.797 | X97: =SUM(S97:W97) -> 74749.797 | Y97: 148959.31 | Z97: =R97-X97 -> 148959.31
B98: TOTAL | C98: 10 | E98: =SUM(E88:E97) -> 248889.34 | F98: =SUM(F88:F97) -> 0 | G98: =SUM(G88:G97) -> 745527.84 | H98: =SUM(H88:H97) -> 18638.196 | I98: =SUM(I88:I97) -> 80244.38 | J98: =SUM(J88:J97) -> 124254.64 | K98: =SUM(K88:K97) -> 869782.48 | L98: =SUM(L88:L97) -> 248509.28 | M98: =SUM(M88:M97) -> 1270000 | O98: =SUM(O88:O97) -> 24850.928 | P98: =SUM(P88:P97) -> 160000 | Q98: =SUM(Q88:Q97) -> 100000 | R98: =SUM(R88:R97) -> 3890697.1 | T98: =SUM(T88:T97) -> 220000 | U98: =SUM(U88:U97) -> 366964.7 | V98: =SUM(V88:V97) -> 1549.9327 | W98: =SUM(W88:W97) -> 539502.74 | X98: =SUM(X88:X97) -> 1128017.4 | Y98: 3241879.7 | Z98: =SUM(Z88:Z97) -> 2762679.7
B100: TRAINING & INT''L COOP
A101: 1 | B101: REKIYA IBRAHIM ATTAH | C101: DEPUTY DIRECTOR TRAINING | D101: 16(8) | E101: 41157.69 | G101: =E101*300% -> 123473.07 | H101: =E101*7.5% -> 3086.8268 | I101: 40122.19 | J101: =E101*50% -> 20578.845 | K101: =E101*350% -> 144051.92 | L101: =E101*100% -> 41157.69 | N101: =90000 -> 90000 | O101: =E101*10% -> 4115.769 | P101: 20000 | R101: =SUM(E101:Q101) -> 527744 | T101: =50000 -> 50000 | U101: =91666.67 -> 91666.67 | W101: 79993.514 | X101: =W101+V101+U101+T101+S101 -> 221660.18 | Y101: 306083.81 | Z101: =R101-X101 -> 306083.81
A102: 2 | B102: DR FRANCIS NDUM OJIE | C102: CHIEF TRAINING OFFICER | D102: 14(10) | E102: 27611.23 | G102: =E102*300% -> 82833.69 | H102: =E102*7.5% -> 2070.8422 | J102: =E102*50% -> 13805.615 | K102: =E102*350% -> 96639.305 | L102: =E102*100% -> 27611.23 | N102: =70000 -> 70000 | O102: =E102*10% -> 2761.123 | P102: 20000 | Q102: =100000 -> 100000 | R102: =SUM(E102:Q102) -> 443333.04 | V102: 690.28075 | W102: =63658.29 -> 63658.29 | X102: =W102+V102+U102+T102+S102 -> 64348.571 | Y102: 297908.42 | Z102: =R102-X102 -> 378984.46
A103: 3 | B103: OKECHUKWU UCHENNA HULDA | C103: PRINCIPALTRAINING OFFICER | D103: 12(8) | E103: 21520.88 | G103: =E103*300% -> 64562.64 | H103: =E103*7.5% -> 1614.066 | J103: =E103*50% -> 10760.44 | K103: =E103*350% -> 75323.08 | L103: =E103*100% -> 21520.88 | N103: =60000 -> 60000 | O103: =E103*10% -> 2152.088 | P103: 10000 | R103: =SUM(E103:Q103) -> 267454.07 | T103: =5000 -> 5000 | U103: =64806.29 -> 64806.29 | W103: 32098.951 | X103: =W103+V103+U103+T103+S103 -> 101905.24 | Y103: 165548.83 | Z103: =R103-X103 -> 165548.83
A104: 4 | B104: TASSNEEM IBRAHIM | C104: ASSIST. INFO.OFFICER | D104: 8(10) | E104: 13492.21 | G104: 40476.63 | H104: 1011.9157 | J104: 6746.105 | K104: 47222.735 | L104: 13492.21 | N104: 50000 | O104: 1349.221 | P104: 10000 | R104: 183791.03 | W104: 18102.903 | X104: 18102.903 | Y104: 165688.12 | Z104: 165688.12
B105: TOTAL | C105: 4 | E105: =SUM(E101:E104) -> 103782.01 | F105: =SUM(F101:F104) -> 0 | G105: =SUM(G101:G104) -> 311346.03 | H105: =SUM(H101:H104) -> 7783.6507 | I105: =SUM(I101:I104) -> 40122.19 | J105: =SUM(J101:J104) -> 51891.005 | K105: =SUM(K101:K104) -> 363237.03 | L105: =SUM(L101:L104) -> 103782.01 | ... X105: =SUM(X101:X104) -> 406016.9 | Y105: 935229.18 | Z105: =SUM(Z101:Z104) -> 1016305.2
B107: LIBRARY & DOCUMENTATION
A108: 1 | B108: DR MAIMUNA IZAH | C108: INSITUTE LIBRARIAN | D108: 17(9) | E108: 81740.02 | G108: =E108*300% -> 245220.06 | H108: =E108*7.5% -> 6130.5015 | I108: 80244.38 | J108: =E108*50% -> 40870.01 | K108: =E108*350% -> 286090.07 | L108: =E108*100% -> 81740.02 | M108: =200000 -> 200000 | O108: =E108*10% -> 8174.002 | P108: 20000 | Q108: 0 | R108: =SUM(E108:Q108) -> 1050209.1 | T108: =100000 -> 100000 | U108: 0 | V108: 0 | W108: 180145.97 | X108: =W108+V108+U108+T108+S108 -> 280145.97 | Y108: 770063.09 | Z108: =R108-X108 -> 770063.09
...

Sheet MEMO 1
A2: NATIONAL INSTITUTE FOR LEGISLATIVE AND DEMOCRATIC STUDIES
A3: INTERNAL MEMO
A4: FROM : DEPUTY DIRECTOR, FINANCE AND ACCOUNTS
A5: THRU: DIRECTOR, FINANCE AND ACCOUNTS
A6: TO: DG
A7: 29TH JANUARY , 2021
A9: SUBJECT: PAYROLL FOR THE MONTH OF JANUARY, 2021
A10: Find below the details of NILDS Staff Payroll for the month of January, 2021
A13: TO: | C13: DIRECTOR, GENERAL
A14: THRU: | C14: DIRECTOR, FINANCE AND ACCOUNT
A15: FROM: | C15: ASST. DIRECTOR, FINANCE AND ACCOUNTS
A16: DATE: | C16: 26TH JUNE, 2023
A18: SUBJECT: PAYROLL FOR THE MONTH OF JUNE, 2023
A19: Find below the details of NILDS Staff Payroll for the Month of June 2023: | G19: NGN | H19: NGN
A20: GROSS SALARY FOR JUNE, 2023 | H20: ='JUNE 2023'!R192 -> 51005732
A22: DEDUCTIONS
A23: COOP SOCIETY DEDUCTIONS ( CONTR.& SPEC. SAVINGS) | G23: ='JUNE 2023'!T192 -> 4802500
A24: COOP LOAN RECOVERY | G24: ='JUNE 2023'!U192 -> 7041474.5
A25: PAYE DEDUCTIONS | G25: ='JUNE 2023'!W192 -> 6946057.7
A26: NHF DEDUCTIONS | G26: ='JUNE 2023'!V192 -> 23887.071
A27: TOTAL DEDUCTIONS FOR JUNE, 2023 | H27: =G23+G24+G25+G26 -> 18813919
A28: NET PAY AS PER JUNE, 2023 PAYROLL | H28: =H20-H27 -> 32191813
A29: NET PAY AS PER MAY, 2023 PAYROLL | H29: ='JUNE 2023'!Y192 -> 32708405
A30: NET INCREASE/ (DECREASE) IN PAY FOR JUNE, 2023 | H30: =H28-H29 -> -516592.08
A31: ANALYSED AS FOLLOWS:
A32: Effect of Cooperative adjustment for June 2023 | H32: -20000
A33: Net Effect of Stoppage of Payment to Nasiru Naeem Abdulsalam | H33: =612357.08 -> 612357.08
A34: Effect of Removal of 1st 28 days Allowance of Maryam Musa Sada | H34: =560000 -> 560000
A35: Net Effect of Stoppage of payment to Murtala Lawal due to transfer of Service | H35: =83161.66 -> 83161.66
A36: Net effect of Conversion to Permanent Staff of Munirat Jimoh | H36: =-560000+2949.39 -> -557050.61
A37: Net effect of Legislative Allowance to Terfa Abraham & one other | H37: -161876.05
H38: =SUM(H32:H37) -> 516592.08
E40: MAY, 2023 | G40: JUNE, 2023
E41: No. of Staff | F41: N | G41: No. of Staff | H41: N
A42: 1 | B42: Director General's Office | E42: 33 | F42: ='JUNE 2023'!Y36 -> 8260507.5 | G42: ='JUNE 2023'!C36 -> 29 | H42: ='JUNE 2023'!Z36 -> 7648150.4
A43: 2 | B43: Internal Audit | E43: 2 | F43: ='JUNE 2023'!Y41 -> 650918.62 | G43: 2 | H43: ='JUNE 2023'!Z41 -> 650918.62
A44: 3 | B44: Legis. Support Services | E44: 11 | F44: ='JUNE 2023'!Y56 -> 2852419.9 | G44: ='JUNE 2023'!C56 -> 12 | H44: ='JUNE 2023'!Z56 -> 2852419.9
A45: 4 | B45: Legal Services | E45: 2 | F45: ='JUNE 2023'!Y61 -> 928634.33 | G45: ='JUNE 2023'!C61 -> 2 | H45: ='JUNE 2023'!Z61 -> 928634.33
A46: 5 | B46: Democracy and Governance | E46: 13 | F46: ='JUNE 2023'!Y77 -> 3316351.5 | G46: ='JUNE 2023'!C77 -> 13 | H46: ='JUNE 2023'!Z77 -> 3316351.5
A47: 6 | B47: Studies | E47: 4 | F47: ='JUNE 2023'!Y85 -> 1848547.3 | G47: ='JUNE 2023'!C85 -> 5 | H47: ='JUNE 2023'!Z85 -> 1848547.3
A48: 7 | B48: Economic Dev. & Social Research | E48: 12 | F48: ='JUNE 2023'!Y98 -> 3241879.7 | G48: ='JUNE 2023'!C98 -> 10 | H48: ='JUNE 2023'!Z98 -> 2762679.7
A49: 8 | B49: Training & Int'l Cooperation | E49: 4 | F49: ='JUNE 2023'!Y105 -> 935229.18 | G49: ='JUNE 2023'!C105 -> 4 | H49: ='JUNE 2023'!Z105 -> 1016305.2
A50: 9 | B50: Library & Documentation | E50: 8 | F50: ='JUNE 2023'!Y115 -> 2142429.1 | G50: ='JUNE 2023'!C115 -> 7 | H50: ='JUNE 2023'!Z115 -> 2142429.1
A51: 10 | B51: Leg. Center for Security Analysis | E51: 2 | F51: ='JUNE 2023'!Y120 -> 342292.68 | G51: 2 | H51: ='JUNE 2023'!Z120 -> 342292.68
A52: 11 | B52: Finance and Accounts | E52: 9 | F52: ='JUNE 2023'!Y134 -> 2033147.1 | G52: ='JUNE 2023'!C134 -> 10 | H52: ='JUNE 2023'!Z134 -> 2590197.7
A53: 12 | B53: Admin & Human Resource | E53: 58 | F53: ='JUNE 2023'!Y191 -> 6156048.1 | G53: ='JUNE 2023'!C191 -> 54 | H53: ='JUNE 2023'!Z191 -> 6092886.4
E54: =SUM(E42:E53) -> 158 | F54: =SUM(F42:F53) -> 32708405 | G54: 154 | H54: =SUM(H42:H53) -> 32191813
A56: The Director General is requested to consider and approve payment of N32,191,812.89 to Guaranty Trust Bank being June 2023 Salary, N11,843,974.53 being NILDS Coop Society deductions for June 2023, N6,946,057.67 being PAYE Tax Deductions from Staff Salary for the month of June 2023 and N23,887.07 being NHF deductions from staff for June 2023
A59: RAHILA NURUDEEN HABU
A60: Asst. Director, Finance and Accounts
C164: =10000 -> 10000

Sheet Sallah Welfare April 2023
A1: NATIONAL INSTITUTE FOR LEGISLATIVE AND DEMOCRATIC STUDIES
A2: STAFF WELFARE APRIL, 2023
B4: STAFF NAME | C4: DESIGNATION | D4: GRADE LEVEL | E4: AMOUNT
E5: N
A6: S/N | B6: DG'S OFFICE
A7: 1 | B7: PROF. ABUBAKAR O. SULAIMAN | C7: DIRECTOR GENERAL | D7: CONSOL | E7: 450000
A8: 2 | B8: DR JAKE DABANG DAN AZUMI | C8: DEPUTY DIR. TTECHNICAL | D8: 16(9) | E8: 150000
A9: 3 | B9: DR ABDULSALAM NASIRU NAEEM | C9: SA ACADEMICS | D9: 16(9) | E9: 150000
A10: 4 | B10: RAHEEM USMAN AYIGORO | C10: SA-INFRASTRUCTURE | D10: 16 (9) | E10: 150000
A11: 5 | B11: MARIAM MOHAMMED BELLO | C11: SA- SPECIAL DUTIES | D11: 16(8) | E11: 150000
A12: 6 | B12: AKINSANMI ADEJOKE OLUKEMI | C12: DEPUTY DIR. INFO/PROTOCOL | D12: 16(8) | E12: 150000
A13: 7 | B13: DR IKEME ARTHUR J.O | C13: DEPUTY DIRECTOR, M&E | D13: 16(8) | E13: 150000
A14: 8 | B14: MOSHOOD M. OLALERE | C14: DEPUTY DIR. GENERAL SERVICE | D14: 16(8) | E14: 150000
A15: 9 | B15: ANDRAWUS MUSA | C15: ASST. DIRECTOR, STORES | D15: 15(9) | E15: 105000
A16: 10 | B16: AYOBOLU OLAJIDE OLUFUNSHO | C16: ASST.DIR., INFORMATION | D16: 15 (8) | E16: 105000
A17: 11 | B17: HUSSEIN EGYE MUSA | C17: CHIEF PROTOCOL OFFICER | D17: 14(10) | E17: 75000
A18: 12 | B18: DONALD E. MKPANAM | C18: CHIEF ICT OFFICER | D18: 14(10) | E18: 75000
... A36: 30 | B36: SHOLAGBERU T. SOFIAT | C36: ASST. ACCOUNT. OFFICER | D36: 8(7) | E36: 45000
B37: TOTAL | C37: 30 | E37: =SUM(E7:E36) -> 2790000
B39: INTERNAL AUDIT
A40: 1 | B40: OSANAIYE DAVID AKINYEMI | C40: DIRECTOR INTERNAL AUDIT | D40: 17(9) | E40: 225000
A41: 2 | B41: JAMILA ABDUL | C41: AUDITOR II | D41: 8(7) | E41: 45000
C42: 2 | E42: =SUM(E40:E41) -> 270000
B44: LEG. SUPPORT SEVICES
A45: 1 | B45: PROF. EDOBA BRIGHT OMOREGBE | C45: AG. DLSS | D45: 17(9) | E45: 225000
A46: 2 | B46: DR CLINTON JAJA | C46: SENIOR RESEARCH FELLOW | D46: 15(9) | E46: 105000
A47: 3 | B47: BETHEL UZOMA IHUGBA | C47: SNR RESEARCH FELLOW | D47: 15(9) | E47: 105000
A48: 4 | B48: OGUCHE SAMUEL | C48: SNR RESEARCH FELLOW | D48: 15(9) | E48: 105000
A49: 5 | B49: IBRAHIM USMAN | C49: SNR RESEARCH FELLOW | D49: 15(8) | E49: 105000
A50: 6 | B50: DR MOHAMMED O. AMALI | C50: RESEARCH FELLOW I | D50: 14(10) | E50: 75000
A51: 7 | B51: YAHAYA SHAMSU | C51: RESEARCH FELLOW 1 | D51: 14(10) | E51: 75000
A52: 8 | B52: OFORDEME ADAOBI JULIA | C52: RESEARCH FELLOW 1 | D52: 14(9) | E52: 75000
A53: 9 | B53: DORIS DAKDA AARON | C53: RESEARCH FELLOW II | D53: 13(10) | E53: 75000
A54: 10 | B54: ZAINAB AKINDE | C54: RESEARCH OFFICER | D54: 9(7) | E54: 45000
A55: 11 | B55: ABDULLAHI AHMAD USMAN | C55: RESEARCH OFFICER | D55: 9(7) | E55: 45000
A56: 12 | B56: GUNAT NANSAK MARK | C56: RESEARCH OFFICER | D56: 9(7) | E56: 45000
B57: TOTAL | C57: 12 | E57: =SUM(E45:E56) -> 1080000
B59: LEGAL SERVICES
A60: 1 | B60: DR SHUIBU DANWANKA | C60: DIRECTOR LEGAL SERVICES | D60: 17(9) | E60: 225000
A61: 2 | B61: ABDULSALAM BAKO | C61: MANAGER, LEGAL SERVICES | D61: 15 (8) | E61: 105000
B62: TOTAL | C62: 2 | E62: =SUM(E60:E61) -> 330000
B64: DEMOCRACY & GOVERNANCE
A65: 1 | B65: DR. ADEWALE ADEREMI | C65: DIRECTOR, DEMOCRATIC STUDIES | D65: 17(9) | E65: 225000
A66: 2 | B66: NDANUSA MOHAMMED MANZUMA | C66: SNR RESEARCH FELLOW | D66: 15 (7) | E66: 105000
A67: 3 | B67: EJALONIBU GANIYU LAYI | C67: RESEARCH FELLOW 11 | D67: 13(10) | E67: 75000
A68: 4 | B68: LOHNA BONKAT JONATHAN | C68: RESEARCH FELLOW 11 | D68: 13(9) | E68: 75000
A69: 5 | B69: YUNUSA ABDULLAHI | C69: RESEARCH FELLOW 1 | D69: 14(10) | E69: 75000
A70: 6 | B70: EMILY EKHIDE | C70: RESEARCH FELLOW 1 | D70: 14(9) | E70: 75000
A71: 7 | B71: UDEFUNA NNADOZIE PATRICK | C71: RESEARCH OFFICER | D71: 12(7) | E71: 45000
A72: 8 | B72: OSOLAFIA MUHAMMAD EGYE | C72: PRINCIPAL RESEARCH OFFICER | D72: 12(9) | E72: 45000
A73: 9 | B73: SHAFIU YAHYA MIKAIL | C73: PRINCIPAL RESEARCH OFFICER | D73: 12(7) | E73: 45000
A74: 10 | B74: HASSAN YERIMA | C74: PRINCIPAL RESEARCH OFFICER | D74: 12(7) | E74: 45000
A75: 11 | B75: HAUWA PATE SADIQ | C75: PRINCIPAL PROGRAMME OFFICER | D75: 12(8) | E75: 45000
A76: 12 | B76: ABAYOMI KAYODE QUADRI | C76: RESEARCH OFFICER | D76: 10(8) | E76: 45000
... A78: 14 | B78: LUCKY AGWOM | C78: RESEARCH ASSISTANT | D78: 8(8) | E78: 45000
B79: TOTAL | C79: 14 | E79: =SUM(E65:E78) -> 990000
B81: DEPARTMENT OF STUDIES
A82: 1 | B82: DR ASIMIYU G. ABIOLA | C82: DIRECTOR POST GRADUATE | D82: 17(9) | E82: 225000
A83: 2 | B83: USMAN WALI | C83: SENIOR RESEARCH FELLOW | D83: 15 (7) | E83: 105000
A84: 3 | B84: MOSHOOD TOSHO AMUDA | C84: MANAGER, EXAMS & RECORDS | D84: 15 (7) | E84: 105000
A85: 4 | B85: ANTHONY EDET | C85: ASST. MGR M&E | D85: 13(10) | E85: 75000
A86: 5 | B86: IGWE STACY | C86: PROGRAMME OFFICER | D86: 10(8) | E86: 45000
B87: TOTAL | C87: 5 | E87: =SUM(E82:E86) -> 555000
B89: ECON. DEV. & SOC. RESEARCH
A90: 1 | B90: TERFA WILLIAMS ABRAHAM | C90: SNR RESEARCH FELLOW | D90: 15(9) | E90: 105000
A91: 2 | B91: DR AUGUSTINE C. OSIGWE | C91: SNR RESEARCH FELLOW | D91: 15(9) | E91: 105000
A92: 3 | B92: NGARA CHRISTOPHER OCHANJA | C92: RESEARCH FELLOW 1 | D92: 14(11) | E92: 75000
A93: 4 | B93: OMOJU OLUWASOLA EMMANUEL | C93: RESEARCH FELLOW I | D93: 14(10) | E93: 75000
A94: 5 | B94: IBE EZECHI CYRIACUS | C94: RESEARCH FELLOW II | D94: 13(10) | E94: 75000
A95: 6 | B95: OSIKHEN LEO IGBANOI | C95: RESEARCH FELLOW 11 | D95: 13(9) | E95: 75000
A96: 7 | B96: OKUNGBOWA OSARETIN GODSPOWER | C96: RESEARCH FELLOW 11 | D96: 13(9) | E96: 75000
A97: 8 | B97: YUSUF IBRAHIM | C97: PRINCIPAL RESEARCH OFFICER | D97: 12(7) | E97: 45000
A98: 9 | B98: MARYAM MUSA SADA | C98: ASSIT. RESEARCH OFFICER | D98: 10(7) | E98: 45000
A99: 10 | B99: CHARITY EZENWAJIOBI | C99: REASEARCH. ASST. | D99: 8(8) | E99: 45000
B100: TOTAL | C100: 10 | E100: =SUM(E90:E99) -> 720000
B102: TRAINING & INT''L COOP
A103: 1 | B103: REKIYA IBRAHIM ATTAH | C103: DEPUTY DIRECTOR TRAINING | D103: 16(8) | E103: 150000
A104: 2 | B104: DR FRANCIS NDUM OJIE | C104: CHIEF TRAINING OFFICER | D104: 14(10) | E104: 75000
A105: 3 | B105: OKECHUKWU UCHENNA HULDA | C105: PRINCIPALTRAINING OFFICER | D105: 12(8) | E105: 45000
A106: 4 | B106: TASNEEM IBRAHIM | C106: ASST. INFORMATION OFFICER | D106: 8(10) | E106: 45000
B107: TOTAL | C107: 3 | E107: =SUM(E103:E106) -> 315000
B109: LIBRARY & DOCUMENTATION
A110: 1 | B110: DR MAIMUNA IZAH | C110: INSITUTE LIBRARIAN | D110: 17(9) | E110: 225000
A111: 2 | B111: CATHERINE E. IKOKOH | C111: SNR RESEARCH FELLOW DOCU | D111: 16(8) | E111: 150000
A112: 3 | B112: ALIYU SANNI ABUBAKAR | C112: RESEARCH FELLOW 11 DATA & DOCU | D112: 13(11) | E112: 75000
A113: 4 | B113: CHINAKO N. ASOGWA | C113: RESEARCH FELLOW 11 DATA & DOCU | D113: 13(11) | E113: 75000
A114: 5 | B114: AMOS ABA | C114: LIBRARY ASSISTANT | D114: 8(11) | E114: 45000
A115: 6 | B115: TITILAYO DANIEL MARVELLOUS | C115: LIBRARY ASSISTANT | D115: 8(10) | E115: 45000
A116: 7 | B116: ENENCHE JEREMIAH AGADA | C116: LIBRARY ASSISTANT | D116: 8(8) | E116: 45000
B117: TOTAL | C117: 7 | E117: =SUM(E110:E116) -> 660000
B119: FINANCE & ACCOUNTS
A120: 1 | B120: IBRAHIM M. MSHELIA | C120: DIR. FINANCE & ACCOUNTS | D120: 17(9) | E120: 225000
A121: 2 | B121: RAHILA NURUDEEN HABU | C121: ASST. DIRECTOR, ACCOUNTS | D121: 15(9) | E121: 105000
A122: 3 | B122: TONDO IORWUESE EDWARD | C122: ASST. DIRECTOR, ACCOUNTS | D122: 15(9) | E122: 105000
A123: 4 | B123: ARAOYE GANIYAT TITILOLA | C123: ASST. DIRECTOR, ACCOUNTS | D123: 15(7) | E123: 105000
A124: 5 | B124: SHEHU ABDULLAHI | C124: CHIEF ACCOUNT OFFICER | D124: 14(9) | E124: 75000
A125: 6 | B125: OJOGIWA ABISOLA GANIAT | C125: ASST. CHIEF BUDGET OFFICER | D125: 13(10) | E125: 75000
A126: 7 | B126: RAHILA SALIHU | C126: ASST. CHIEF ACCOUNTOFFICER | D126: 13(10) | E126: 75000
A127: 8 | B127: HUSSAIN HAZEEM | C127: ACCOUNT. OFFICER | D127: 9(8) | E127: 45000
A128: 9 | B128: MUNIRAT JIMOH | C128: ACCOUNT ASSISTANT | D128: 8(8) | E128: 45000
...

Sheet Sallah Welfare June 2023
A1: NATIONAL INSTITUTE FOR LEGISLATIVE AND DEMOCRATIC STUDIES
A2: STAFF WELFARE APRIL, 2023
B4: STAFF NAME | C4: DESIGNATION | D4: GRADE LEVEL | E4: AMOUNT
E5: N
A6: S/N | B6: DG'S OFFICE
A7: 1 | B7: PROF. ABUBAKAR O. SULAIMAN | C7: DIRECTOR GENERAL | D7: CONSOL | E7: 450000
A8: 2 | B8: DR JAKE DABANG DAN AZUMI | C8: DEPUTY DIR. TTECHNICAL | D8: 16(9) | E8: 150000
A9: 3 | B9: DR ABDULSALAM NASIRU NAEEM | C9: SA ACADEMICS | D9: 16(9) | E9: 150000
A10: 4 | B10: RAHEEM USMAN AYIGORO | C10: SA-INFRASTRUCTURE | D10: 16 (9) | E10: 150000
A11: 5 | B11: MARIAM MOHAMMED BELLO | C11: SA- SPECIAL DUTIES | D11: 16(8) | E11: 150000
A12: 6 | B12: AKINSANMI ADEJOKE OLUKEMI | C12: DEPUTY DIR. INFO/PROTOCOL | D12: 16(8) | E12: 150000
A13: 7 | B13: DR IKEME ARTHUR J.O | C13: DEPUTY DIRECTOR, M&E | D13: 16(8) | E13: 150000
A14: 8 | B14: MOSHOOD M. OLALERE | C14: DEPUTY DIR. GENERAL SERVICE | D14: 16(8) | E14: 150000
A15: 9 | B15: ANDRAWUS MUSA | C15: ASST. DIRECTOR, STORES | D15: 15(9) | E15: 105000
A16: 10 | B16: AYOBOLU OLAJIDE OLUFUNSHO | C16: ASST.DIR., INFORMATION | D16: 15 (8) | E16: 105000
A17: 11 | B17: HUSSEIN EGYE MUSA | C17: CHIEF PROTOCOL OFFICER | D17: 14(10) | E17: 75000
A18: 12 | B18: DONALD E. MKPANAM | C18: CHIEF ICT OFFICER | D18: 14(10) | E18: 75000
... A35: 29 | B35: SHOLAGBERU T. SOFIAT | C35: ASST. ACCOUNT. OFFICER | D35: 8(7) | E35: 45000
B36: TOTAL | C36: 29 | E36: =SUM(E7:E35) -> 2745000
B38: INTERNAL AUDIT
A39: 1 | B39: OSANAIYE DAVID AKINYEMI | C39: DIRECTOR INTERNAL AUDIT | D39: 17(9) | E39: 225000
A40: 2 | B40: JAMILA ABDUL | C40: AUDITOR II | D40: 8(7) | E40: 45000
C41: 2 | E41: =SUM(E39:E40) -> 270000
B43: LEG. SUPPORT SEVICES
A44: 1 | B44: PROF. EDOBA BRIGHT OMOREGBE | C44: AG. DLSS | D44: 17(9) | E44: 225000
A45: 2 | B45: DR CLINTON JAJA | C45: SENIOR RESEARCH FELLOW | D45: 15(9) | E45: 105000
A46: 3 | B46: BETHEL UZOMA IHUGBA | C46: SNR RESEARCH FELLOW | D46: 15(9) | E46: 105000
A47: 4 | B47: OGUCHE SAMUEL | C47: SNR RESEARCH FELLOW | D47: 15(9) | E47: 105000
A48: 5 | B48: IBRAHIM USMAN | C48: SNR RESEARCH FELLOW | D48: 15(8) | E48: 105000
A49: 6 | B49: DR MOHAMMED O. AMALI | C49: RESEARCH FELLOW I | D49: 14(10) | E49: 75000
A50: 7 | B50: YAHAYA SHAMSU | C50: RESEARCH FELLOW 1 | D50: 14(10) | E50: 75000
A51: 8 | B51: OFORDEME ADAOBI JULIA | C51: RESEARCH FELLOW 1 | D51: 14(9) | E51: 75000
A52: 9 | B52: DORIS DAKDA AARON | C52: RESEARCH FELLOW II | D52: 13(10) | E52: 75000
A53: 10 | B53: ZAINAB AKINDE | C53: RESEARCH OFFICER | D53: 9(7) | E53: 45000
A54: 11 | B54: ABDULLAHI AHMAD USMAN | C54: RESEARCH OFFICER | D54: 9(7) | E54: 45000
A55: 12 | B55: GUNAT NANSAK MARK | C55: RESEARCH OFFICER | D55: 9(7) | E55: 45000
B56: TOTAL | C56: 12 | E56: =SUM(E44:E55) -> 1080000
B58: LEGAL SERVICES
A59: 1 | B59: DR SHUIBU DANWANKA | C59: DIRECTOR LEGAL SERVICES | D59: 17(9) | E59: 225000
A60: 2 | B60: ABDULSALAM BAKO | C60: MANAGER, LEGAL SERVICES | D60: 15 (8) | E60: 105000
B61: TOTAL | C61: 2 | E61: =SUM(E59:E60) -> 330000
B63: DEMOCRACY & GOVERNANCE
A64: 1 | B64: DR. ADEWALE ADEREMI | C64: DIRECTOR, DEMOCRATIC STUDIES | D64: 17(9) | E64: 225000
A65: 2 | B65: NDANUSA MOHAMMED MANZUMA | C65: SNR RESEARCH FELLOW | D65: 15 (7) | E65: 105000
A66: 3 | B66: EJALONIBU GANIYU LAYI | C66: RESEARCH FELLOW 11 | D66: 13(10) | E66: 75000
A67: 4 | B67: LOHNA BONKAT JONATHAN | C67: RESEARCH FELLOW 11 | D67: 13(9) | E67: 75000
A68: 5 | B68: YUNUSA ABDULLAHI | C68: RESEARCH FELLOW 1 | D68: 14(10) | E68: 75000
A69: 6 | B69: EMILY EKHIDE | C69: RESEARCH FELLOW 1 | D69: 14(9) | E69: 75000
A70: 7 | B70: UDEFUNA NNADOZIE PATRICK | C70: RESEARCH OFFICER | D70: 12(7) | E70: 45000
A71: 8 | B71: SHAFIU YAHYA MIKAIL | C71: PRINCIPAL RESEARCH OFFICER | D71: 12(7) | E71: 45000
A72: 9 | B72: HASSAN YERIMA | C72: PRINCIPAL RESEARCH OFFICER | D72: 12(7) | E72: 45000
A73: 10 | B73: HAUWA PATE SADIQ | C73: PRINCIPAL PROGRAMME OFFICER | D73: 12(8) | E73: 45000
A74: 11 | B74: ABAYOMI KAYODE QUADRI | C74: RESEARCH OFFICER | D74: 10(8) | E74: 45000
A75: 12 | B75: NNANDI LIVINUS ATURE | C75: RESEARCH ASSISTANT | D75: 9(8) | E75: 45000
A76: 13 | B76: LUCKY AGWOM | C76: RESEARCH ASSISTANT | D76: 8(8) | E76: 45000
B77: TOTAL | C77: 13 | E77: =SUM(E64:E76) -> 945000
B79: DEPARTMENT OF STUDIES
A80: 1 | B80: DR ASIMIYU G. ABIOLA | C80: DIRECTOR POST GRADUATE | D80: 17(9) | E80: 225000
A81: 2 | B81: USMAN WALI | C81: SENIOR RESEARCH FELLOW | D81: 15 (7) | E81: 105000
A82: 3 | B82: MOSHOOD TOSHO AMUDA | C82: MANAGER, EXAMS & RECORDS | D82: 15 (7) | E82: 105000
A83: 4 | B83: ANTHONY EDET | C83: ASST. MGR M&E | D83: 13(10) | E83: 75000
A84: 5 | B84: IGWE STACY | C84: PROGRAMME OFFICER | D84: 10(8) | E84: 45000
B85: TOTAL | C85: 5 | E85: =SUM(E80:E84) -> 555000
B87: ECON. DEV. & SOC. RESEARCH
A88: 1 | B88: TERFA WILLIAMS ABRAHAM | C88: SNR RESEARCH FELLOW | D88: 15(9) | E88: 105000
A89: 2 | B89: DR AUGUSTINE C. OSIGWE | C89: SNR RESEARCH FELLOW | D89: 15(9) | E89: 105000
A90: 3 | B90: NGARA CHRISTOPHER OCHANJA | C90: RESEARCH FELLOW 1 | D90: 14(11) | E90: 75000
A91: 4 | B91: OMOJU OLUWASOLA EMMANUEL | C91: RESEARCH FELLOW I | D91: 14(10) | E91: 75000
A92: 5 | B92: IBE EZECHI CYRIACUS | C92: RESEARCH FELLOW II | D92: 13(10) | E92: 75000
A93: 6 | B93: OSIKHEN LEO IGBANOI | C93: RESEARCH FELLOW 11 | D93: 13(9) | E93: 75000
A94: 7 | B94: OKUNGBOWA OSARETIN GODSPOWER | C94: RESEARCH FELLOW 11 | D94: 13(9) | E94: 75000
A95: 8 | B95: YUSUF IBRAHIM | C95: PRINCIPAL RESEARCH OFFICER | D95: 12(7) | E95: 45000
A96: 9 | B96: MARYAM MUSA SADA | C96: ASSIT. RESEARCH OFFICER | D96: 10(7) | E96: 45000
A97: 10 | B97: CHARITY EZENWAJIOBI | C97: REASEARCH. ASST. | D97: 8(8) | E97: 45000
B98: TOTAL | C98: 10 | E98: =SUM(E88:E97) -> 720000
B100: TRAINING & INT''L COOP
A101: 1 | B101: REKIYA IBRAHIM ATTAH | C101: DEPUTY DIRECTOR TRAINING | D101: 16(8) | E101: 150000
A102: 2 | B102: DR FRANCIS NDUM OJIE | C102: CHIEF TRAINING OFFICER | D102: 14(10) | E102: 75000
A103: 3 | B103: OKECHUKWU UCHENNA HULDA | C103: PRINCIPALTRAINING OFFICER | D103: 12(8) | E103: 45000
A104: 4 | B104: TASNEEM IBRAHIM | C104: ASST. INFORMATION OFFICER | D104: 8(10) | E104: 45000
B105: TOTAL | C105: 3 | E105: =SUM(E101:E104) -> 315000
B107: LIBRARY & DOCUMENTATION
A108: 1 | B108: DR MAIMUNA IZAH | C108: INSITUTE LIBRARIAN | D108: 17(9) | E108: 225000
A109: 2 | B109: CATHERINE E. IKOKOH | C109: SNR RESEARCH FELLOW DOCU | D109: 16(8) | E109: 150000
A110: 3 | B110: ALIYU SANNI ABUBAKAR | C110: RESEARCH FELLOW 11 DATA & DOCU | D110: 13(11) | E110: 75000
A111: 4 | B111: CHINAKO N. ASOGWA | C111: RESEARCH FELLOW 11 DATA & DOCU | D111: 13(11) | E111: 75000
A112: 5 | B112: AMOS ABA | C112: LIBRARY ASSISTANT | D112: 8(11) | E112: 45000
A113: 6 | B113: TITILAYO DANIEL MARVELLOUS | C113: LIBRARY ASSISTANT | D113: 8(10) | E113: 45000
A114: 7 | B114: ENENCHE JEREMIAH AGADA | C114: LIBRARY ASSISTANT | D114: 8(8) | E114: 45000
B115: TOTAL | C115: 7 | E115: =SUM(E108:E114) -> 660000
B117: LEG, CTRE FOR SECURITY ANALYSIS
A118: 1 | B118: OSOLAFIA MUHAMMAD EGYE | C118: PRINCIPAL RESEARCH OFFICER | D118: 12(9) | E118: 45000
A119: 2 | B119: EGUATU U. ONYEJELEM | C119: PRINCIPAL M&E OFFICER | D119: 12(8) | E119: 45000
B120: TOTAL | C120: 2 | E120: =SUM(E118:E119) -> 90000
B122: FINANCE & ACCOUNTS
A123: 1 | B123: IBRAHIM M. MSHELIA | C123: DIR. FINANCE & ACCOUNTS | D123: 17(9) | E123: 225000
A124: 2 | B124: RAHILA NURUDEEN HABU | C124: ASST. DIRECTOR, ACCOUNTS | D124: 15(9) | E124: 105000
A125: 3 | B125: TONDO IORWUESE EDWARD | C125: ASST. DIRECTOR, ACCOUNTS | D125: 15(9) | E125: 105000
A126: 4 | B126: ARAOYE GANIYAT TITILOLA | C126: ASST. DIRECTOR, ACCOUNTS | D126: 15(7) | E126: 105000
A127: 5 | B127: SHEHU ABDULLAHI | C127: CHIEF ACCOUNT OFFICER | D127: 14(9) | E127: 75000
...

Sheet Sallah Welfare June 2023 Latest
A1: NATIONAL INSTITUTE FOR LEGISLATIVE AND DEMOCRATIC STUDIES
A2: STAFF WELFARE APRIL, 2023
B4: STAFF NAME | C4: DESIGNATION | D4: GRADE LEVEL | E4: AMOUNT
E5: N
A6: S/N | B6: DG'S OFFICE
A7: 1 | B7: PROF. ABUBAKAR O. SULAIMAN | C7: DIRECTOR GENERAL | D7: CONSOL | E7: 540000
A8: 2 | B8: DR JAKE DABANG DAN AZUMI | C8: DEPUTY DIR. TTECHNICAL | D8: 16(9) | E8: 180000
A9: 3 | B9: RAHEEM USMAN AYIGORO | C9: SA-INFRASTRUCTURE | D9: 16 (9) | E9: 180000
A10: 4 | B10: MARIAM MOHAMMED BELLO | C10: SA- SPECIAL DUTIES | D10: 16(8) | E10: 180000
A11: 5 | B11: AKINSANMI ADEJOKE OLUKEMI | C11: DEPUTY DIR. INFO/PROTOCOL | D11: 16(8) | E11: 180000
A12: 6 | B12: DR IKEME ARTHUR J.O | C12: DEPUTY DIRECTOR, M&E | D12: 16(8) | E12: 180000
A13: 7 | B13: MOSHOOD M. OLALERE | C13: DEPUTY DIR. GENERAL SERVICE | D13: 16(8) | E13: 180000
A14: 8 | B14: ANDRAWUS MUSA | C14: ASST. DIRECTOR, STORES | D14: 15(9) | E14: 126000
A15: 9 | B15: AYOBOLU OLAJIDE OLUFUNSHO | C15: ASST.DIR., INFORMATION | D15: 15 (8) | E15: 126000
A16: 10 | B16: HUSSEIN EGYE MUSA | C16: CHIEF PROTOCOL OFFICER | D16: 14(10) | E16: 90000
A17: 11 | B17: DONALD E. MKPANAM | C17: CHIEF ICT OFFICER | D17: 14(10) | E17: 90000
A18: 12 | B18: JOY HARUNA MAKERI | C18: RESEARCH FELLOW 1 TRAINING | D18: 14(10) | E18: 90000
... A34: 28 | B34: SHOLAGBERU T. SOFIAT | C34: ASST. ACCOUNT. OFFICER | D34: 8(7) | E34: 54000
B35: TOTAL | C35: 28 | E35: =SUM(E7:E34) -> 3114000
B37: INTERNAL AUDIT
A38: 1 | B38: OSANAIYE DAVID AKINYEMI | C38: DIRECTOR INTERNAL AUDIT | D38: 17(9) | E38: 270000
A39: 2 | B39: JAMILA ABDUL | C39: AUDITOR II | D39: 8(7) | E39: 54000
C40: 2 | E40: 324000
B42: LEG. SUPPORT SEVICES
A43: 1 | B43: PROF. EDOBA BRIGHT OMOREGBE | C43: AG. DLSS | D43: 17(9) | E43: 270000
A44: 2 | B44: DR CLINTON JAJA | C44: SENIOR RESEARCH FELLOW | D44: 15(9) | E44: 126000
A45: 3 | B45: BETHEL UZOMA IHUGBA | C45: SNR RESEARCH FELLOW | D45: 15(9) | E45: 126000
A46: 4 | B46: OGUCHE SAMUEL | C46: SNR RESEARCH FELLOW | D46: 15(9) | E46: 126000
A47: 5 | B47: IBRAHIM USMAN | C47: SNR RESEARCH FELLOW | D47: 15(8) | E47: 126000
A48: 6 | B48: DR MOHAMMED O. AMALI | C48: RESEARCH FELLOW I | D48: 14(10) | E48: 90000
A49: 7 | B49: YAHAYA SHAMSU | C49: RESEARCH FELLOW 1 | D49: 14(10) | E49: 90000
A50: 8 | B50: OFORDEME ADAOBI JULIA | C50: RESEARCH FELLOW 1 | D50: 14(9) | E50: 90000
A51: 9 | B51: DORIS DAKDA AARON | C51: RESEARCH FELLOW II | D51: 13(10) | E51: 90000
A52: 10 | B52: ZAINAB AKINDE | C52: RESEARCH OFFICER | D52: 9(7) | E52: 54000
A53: 11 | B53: ABDULLAHI AHMAD USMAN | C53: RESEARCH OFFICER | D53: 9(7) | E53: 54000
A54: 12 | B54: GUNAT NANSAK MARK | C54: RESEARCH OFFICER | D54: 9(7) | E54: 54000
B55: TOTAL | C55: 12 | E55: 1296000
B57: LEGAL SERVICES
A58: 1 | B58: DR SHUIBU DANWANKA | C58: DIRECTOR LEGAL SERVICES | D58: 17(9) | E58: 270000
A59: 2 | B59: ABDULSALAM BAKO | C59: MANAGER, LEGAL SERVICES | D59: 15 (8) | E59: 126000
B60: TOTAL | C60: 2 | E60: 396000
B62: DEMOCRACY & GOVERNANCE
A63: 1 | B63: DR. ADEWALE ADEREMI | C63: DIRECTOR, DEMOCRATIC STUDIES | D63: 17(9) | E63: 270000
A64: 2 | B64: NDANUSA MOHAMMED MANZUMA | C64: SNR RESEARCH FELLOW | D64: 15 (7) | E64: 126000
A65: 3 | B65: EJALONIBU GANIYU LAYI | C65: RESEARCH FELLOW 11 | D65: 13(10) | E65: 90000
A66: 4 | B66: LOHNA BONKAT JONATHAN | C66: RESEARCH FELLOW 11 | D66: 13(9) | E66: 90000
A67: 5 | B67: YUNUSA ABDULLAHI | C67: RESEARCH FELLOW 1 | D67: 14(10) | E67: 90000
A68: 6 | B68: EMILY EKHIDE | C68: RESEARCH FELLOW 1 | D68: 14(9) | E68: 90000
A69: 7 | B69: UDEFUNA NNADOZIE PATRICK | C69: RESEARCH OFFICER | D69: 12(7) | E69: 54000
A70: 8 | B70: SHAFIU YAHYA MIKAIL | C70: PRINCIPAL RESEARCH OFFICER | D70: 12(7) | E70: 54000
A71: 9 | B71: HASSAN YERIMA | C71: PRINCIPAL RESEARCH OFFICER | D71: 12(7) | E71: 54000
A72: 10 | B72: HAUWA PATE SADIQ | C72: PRINCIPAL PROGRAMME OFFICER | D72: 12(8) | E72: 54000
A73: 11 | B73: ABAYOMI KAYODE QUADRI | C73: RESEARCH OFFICER | D73: 10(8) | E73: 54000
A74: 12 | B74: NNANDI LIVINUS ATURE | C74: RESEARCH ASSISTANT | D74: 9(8) | E74: 54000
A75: 13 | B75: LUCKY AGWOM | C75: RESEARCH ASSISTANT | D75: 8(8) | E75: 54000
B76: TOTAL | C76: 13 | E76: 1134000
B78: DEPARTMENT OF STUDIES
A79: 1 | B79: DR ASIMIYU G. ABIOLA | C79: DIRECTOR POST GRADUATE | D79: 17(9) | E79: 270000
A80: 2 | B80: USMAN WALI | C80: SENIOR RESEARCH FELLOW | D80: 15 (7) | E80: 126000
A81: 3 | B81: MOSHOOD TOSHO AMUDA | C81: MANAGER, EXAMS & RECORDS | D81: 15 (7) | E81: 126000
A82: 4 | B82: ANTHONY EDET | C82: ASST. MGR M&E | D82: 13(10) | E82: 90000
A83: 5 | B83: IGWE STACY | C83: PROGRAMME OFFICER | D83: 10(8) | E83: 54000
B84: TOTAL | C84: 5 | E84: 666000
B86: ECON. DEV. & SOC. RESEARCH
A87: 1 | B87: TERFA WILLIAMS ABRAHAM | C87: SNR RESEARCH FELLOW | D87: 15(9) | E87: 126000
A88: 2 | B88: DR AUGUSTINE C. OSIGWE | C88: SNR RESEARCH FELLOW | D88: 15(9) | E88: 126000
A89: 3 | B89: NGARA CHRISTOPHER OCHANJA | C89: RESEARCH FELLOW 1 | D89: 14(11) | E89: 90000
A90: 4 | B90: OMOJU OLUWASOLA EMMANUEL | C90: RESEARCH FELLOW I | D90: 14(10) | E90: 90000
A91: 5 | B91: IBE EZECHI CYRIACUS | C91: RESEARCH FELLOW II | D91: 13(10) | E91: 90000
A92: 6 | B92: OSIKHEN LEO IGBANOI | C92: RESEARCH FELLOW 11 | D92: 13(9) | E92: 90000
A93: 7 | B93: OKUNGBOWA OSARETIN GODSPOWER | C93: RESEARCH FELLOW 11 | D93: 13(9) | E93: 90000
A94: 8 | B94: YUSUF IBRAHIM | C94: PRINCIPAL RESEARCH OFFICER | D94: 12(7) | E94: 54000
A95: 9 | B95: MARYAM MUSA SADA | C95: ASSIT. RESEARCH OFFICER | D95: 10(7) | E95: 54000
A96: 10 | B96: CHARITY EZENWAJIOBI | C96: REASEARCH. ASST. | D96: 8(8) | E96: 54000
B97: TOTAL | C97: 10 | E97: 864000
B99: TRAINING & INT''L COOP
A100: 1 | B100: REKIYA IBRAHIM ATTAH | C100: DEPUTY DIRECTOR TRAINING | D100: 16(8) | E100: 180000
A101: 2 | B101: DR FRANCIS NDUM OJIE | C101: CHIEF TRAINING OFFICER | D101: 14(10) | E101: 90000
A102: 3 | B102: OKECHUKWU UCHENNA HULDA | C102: PRINCIPALTRAINING OFFICER | D102: 12(8) | E102: 54000
A103: 4 | B103: TASNEEM IBRAHIM | C103: ASST. INFORMATION OFFICER | D103: 8(10) | E103: 54000
B104: TOTAL | C104: 3 | E104: 378000
B106: LIBRARY & DOCUMENTATION
A107: 1 | B107: DR MAIMUNA IZAH | C107: INSITUTE LIBRARIAN | D107: 17(9) | E107: 270000
A108: 2 | B108: CATHERINE E. IKOKOH | C108: SNR RESEARCH FELLOW DOCU | D108: 16(8) | E108: 180000
A109: 3 | B109: ALIYU SANNI ABUBAKAR | C109: RESEARCH FELLOW 11 DATA & DOCU | D109: 13(11) | E109: 90000
A110: 4 | B110: CHINAKO N. ASOGWA | C110: RESEARCH FELLOW 11 DATA & DOCU | D110: 13(11) | E110: 90000
A111: 5 | B111: AMOS ABA | C111: LIBRARY ASSISTANT | D111: 8(11) | E111: 54000
A112: 6 | B112: TITILAYO DANIEL MARVELLOUS | C112: LIBRARY ASSISTANT | D112: 8(10) | E112: 54000
A113: 7 | B113: ENENCHE JEREMIAH AGADA | C113: LIBRARY ASSISTANT | D113: 8(8) | E113: 54000
B114: TOTAL | C114: 7 | E114: 792000
B116: LEG, CENTRE FOR SECURITY ANALYSIS
A117: 1 | B117: OSOLAFIA MUHAMMAD EGYE | C117: PRINCIPAL RESEARCH OFFICER | D117: 12(9) | E117: 54000
A118: 2 | B118: EGUATU U. ONYEJELEM | C118: PRINCIPAL M&E OFFICER | D118: 12(8) | E118: 54000
B119: TOTAL | C119: 2 | E119: 108000
B121: FINANCE & ACCOUNTS
A122: 1 | B122: IBRAHIM M. MSHELIA | C122: DIR. FINANCE & ACCOUNTS | D122: 17(9) | E122: 270000
A123: 2 | B123: RAHILA NURUDEEN HABU | C123: ASST. DIRECTOR, ACCOUNTS | D123: 15(9) | E123: 126000
A124: 3 | B124: TONDO IORWUESE EDWARD | C124: ASST. DIRECTOR, ACCOUNTS | D124: 15(9) | E124: 126000
A125: 4 | B125: ARAOYE GANIYAT TITILOLA | C125: ASST. DIRECTOR, ACCOUNTS | D125: 15(7) | E125: 126000
A126: 5 | B126: SHEHU ABDULLAHI | C126: CHIEF ACCOUNT OFFICER | D126: 14(9) | E126: 90000
...

Sheet Sheet1

Sheet January 2023 PAYE
A1: NATIONAL INSTITUTE FOR LEGISLATIVE AND DEMOCRATIC STUDIES
A2: STAFF PAYROLL FOR THE MONTH OF JANUARY 2023
B4: STAFF NAME | C4: DESIGNATION | D4: GRADE LEVEL | E4: OLD PAYE | F4: NEW PAYE | G4: DIFFRENCE
A5: S/N | B5: DG'S OFFICE | E5: N | F5: N | G5: N
A6: 1 | B6: PROF. ABUBAKAR O. SULAIMAN | C6: DIRECTOR GENERAL | D6: CONSOL | E6: =201165.84 -> 201165.84 | F6: 201165.84 | G6: 0
A7: 2 | B7: DR JAKE DABANG DAN AZUMI | C7: DEPUTY DIR. TTECHNICAL | D7: 16(9) | E7: =#REF! -> #REF! | F7: 128510.39 | G7: =F7-E7 -> #REF!
A8: 3 | B8: DR ABDULSALAM NASIRU NAEEM | C8: SA ACADEMICS | D8: 16(9) | E8: =116473.51 -> 116473.51 | F8: 119107.95 | G8: =F8-E8 -> 2634.4414
A9: 4 | B9: RAHEEM USMAN AYIGORO | C9: SA-INFRASTRUCTURE | D9: 16 (9) | E9: =79993.51 -> 79993.51 | F9: 82627.951 | G9: =F9-E9 -> 2634.4414
A10: 5 | B10: MARIAM MOHAMMED BELLO | C10: SA- SPECIAL DUTIES | D10: 16(8) | E10: =107095.69 -> 107095.69 | F10: 109730.05 | G10: =F10-E10 -> 2634.3634
A11: 6 | B11: AKINSANMI ADEJOKE OLUKEMI | C11: DEPUTY DIR. INFO/PROTOCOL | D11: 16(8) | E11: =#REF! -> #REF! | F11: 99032.678 | G11: =F11-E11 -> #REF!
A12: 7 | B12: DR IKEME ARTHUR J.O | C12: DEPUTY DIRECTOR, M&E | D12: 16(8) | E12: =#REF! -> #REF! | F12: 79832.678 | G12: =F12-E12 -> #REF!
A13: 8 | B13: MOSHOOD M. OLALERE | C13: DEPUTY DIR. GENERAL SERVICE | D13: 16(8) | E13: =#REF! -> #REF! | F13: 79832.678 | G13: =F13-E13 -> #REF!
A14: 9 | B14: ANDRAWUS MUSA | C14: ASST. DIRECTOR, STORES | D14: 15(9) | E14: =64436.1 -> 64436.1 | F14: 64436.103 | G14: =F14-E14 -> 0.0031466667
A15: 10 | B15: AYOBOLU OLAJIDE OLUFUNSHO | C15: ASST.DIR., INFORMATION | D15: 15 (8) | E15: =60212.92 -> 60212.92 | F15: 62404.98 | G15: =F15-E15 -> 2192.0603
A16: 11 | B16: HUSSEIN EGYE MUSA | C16: CHIEF PROTOCOL OFFICER | D16: 14(10) | E16: =52638.9 -> 52638.9 | F16: 54186.609 | G16: =F16-E16 -> 1547.7094
A17: 12 | B17: DONALD E. MKPANAM | C17: CHIEF ICT OFFICER | D17: 14(10) | E17: =43380 -> 43380 | F17: 44734.339 | G17: =F17-E17 -> 1354.3394
A18: 13 | B18: JOY HARUNA MAKERI | C18: RESEARCH FELLOW 1 TRAINING | D18: 14(10) | E18: =85278.9 -> 85278.9 | F18: 86826.609 | G18: =F18-E18 -> 1547.7094
A19: 14 | B19: ALI ABDULLAHI | C19: CHIEF ICT OFFICER | D19: 14(10) | E19: =#REF! -> #REF! | F19: 44006.617 | G19: =F19-E19 -> #REF!
A20: 15 | B20: PERCY TERFA GBAHABO | C20: HEAD, NILDS LIAISON OFFICE | D20: 13(9) | E20: =46673.26 -> 46673.26 | F20: 46666.667 | G20: =F20-E20 -> -6.5933333
A21: 16 | B21: HASSANA AHMED IBRAHIM | C21: PA- TO DG | D21: 13 (8) | E21: =63364.81 -> 63364.81 | F21: 64913.264 | G21: =F21-E21 -> 1548.4537
A22: 17 | B22: CHRISTIAN MADUABUCHI ODO | C22: PRINCIPAL ICT OFFICER | D22: 12(9) | E22: =31848.56 -> 31848.56 | F22: 34871.967 | G22: =F22-E22 -> 3023.4074
A23: 18 | B23: ADUGBA RICHARD TERSEER | C23: PRINCIPAL INFO. OFFICER | D23: 12(8) | E23: =#REF! -> #REF! | F23: 32008.563 | G23: =F23-E23 -> #REF!
A24: 19 | B24: EGUATU U. ONYEJELEM | C24: PRINCIPAL M&E OFFICER | D24: 12(8) | E24: =#REF! -> #REF! | F24: 32098.951 | G24: =F24-E24 -> #REF!
A25: 20 | B25: ODEH SUZIE | C25: ADMIN. OFFICER, LIASION OFFICE | D25: 10(10) | E25: =27105.99 -> 27105.99 | F25: 27873.08 | G25: =F25-E25 -> 767.08969
A26: 21 | B26: YAKUB OLUWATOYIN USMAN | C26: ASST. ADMIN. OFFICER | D26: 10(9) | E26: =26339.08 -> 26339.08 | F26: 27105.987 | G26: =F26-E26 -> 766.90656
A27: 22 | B27: ELIZABETH OGECHUKWU ONYEAKU | C27: ICT OFFICER | D27: 9(8) | E27: 21640.95 | F27: 21640.953 | G27: =F27-E27 -> 0.0028626667
A28: 23 | B28: VICTOR ASUKWO | C28: ICT OFFICER | D28: 9(8) | E28: =21640.95 -> 21640.95 | F28: 22338.483 | G28: =F28-E28 -> 697.5326
A29: 24 | B29: IJEOMA NKOLIKWA | C29: STORES OFFICER | D29: 9(8) | E29: 21640.95 | F29: 22338.483 | G29: =F29-E29 -> 697.5326
A30: 25 | B30: ABDULRAHMAN A SULAIMAN | C30: ASSISTANT STORES OFFICER | D30: 8 (10) | E30: =17572.89 -> 17572.89 | F30: 18102.903 | G30: =F30-E30 -> 530.01273
A31: 26 | B31: TASSNEEM IBRAHIM | C31: ASSIST. INFORMATION | D31: 8(10) | E31: =17572.89 -> 17572.89 | F31: 18102.903 | G31: =F31-E31 -> 530.01273
A32: 27 | B32: DARE SHEU MAGBON | C32: ASSIST. PG | D32: 8(10) | E32: =17572.89 -> 17572.89 | F32: 18102.903 | G32: =F32-E32 -> 530.01273
A33: 28 | B33: JIMOH ADEBAYO ZAKA | C33: ASST. OFFICER/COMM | D33: 9(8) | E33: 21640.95 | F33: 22338.483 | G33: =F33-E33 -> 697.5326
A34: 29 | B34: MOHAMMED BELLO | C34: RESEARCH ASSITANT PG | D34: 8(8) | E34: =16512.68 -> 16512.68 | F34: 17042.714 | G34: =F34-E34 -> 530.03387
A35: 30 | B35: SULEIMAN ABUBAKAR SODEEQ | C35: ASST. ADMIN. OFFICER | D35: 8(8) | E35: =16512.68 -> 16512.68 | F35: 17042.866 | G35: =F35-E35 -> 530.18587
A36: 31 | B36: HARUNA JIBRIL A. | C36: ASST. ADMIN. OFFICER | D36: 8(8) | E36: =16512.68 -> 16512.68 | F36: 17043.018 | G36: =F36-E36 -> 530.33787
B37: TOTAL | C37: 31 | E37: =SUM(E6:E36) -> #REF! | F37: =SUM(F6:F36) -> 1716067.7 | G37: =SUM(G6:G36) -> #REF!
B39: INTERNAL AUDIT
A40: 1 | B40: OSANAIYE DAVID AKINYEMI | C40: DIRECTOR INTERNAL AUDIT | D40: 17(9) | E40: =156349.82 -> 156349.82 | F40: 161106.81 | G40: =F40-E40 -> 4756.9869
A41: 2 | B41: JAMILA ABDUL | C41: AUDITOR II | D41: 8(7) | E41: =16512.68 -> 16512.68 | F41: 16512.682 | G41: =F41-E41 -> 0.0021906667
C42: 2 | E42: =SUM(E40:E41) -> 172862.5 | F42: =SUM(F40:F41) -> 177619.49 | G42: =SUM(G40:G41) -> 4756.989
B44: LEG. SUPPORT SEVICES
A45: 1 | B45: PROF. EDOBA BRIGHT OMOREGBE | C45: AG. DLSS | D45: 17(9) | E45: =180306.81 -> 180306.81 | F45: 180306.81 | G45: =F45-E45 -> -0.0031413333
A46: 2 | B46: DR CLINTON JAJA | C46: SENIOR RESEARCH FELLOW | D46: 15(9) | E46: =79956.94 -> 79956.94 | F46: 79956.939 | G46: =F46-E46 -> -0.00085333335
A47: 3 | B47: BETHEL UZOMA IHUGBA | C47: SNR RESEARCH FELLOW | D47: 15(9) | E47: =79956.94 -> 79956.94 | F47: 79956.939 | G47: =F47-E47 -> -0.00085333335
A48: 4 | B48: OGUCHE SAMUEL | C48: SNR RESEARCH FELLOW | D48: 15(9) | E48: =77764.98 -> 77764.98 | F48: 79956.939 | G48: =F48-E48 -> 2191.9591
A49: 5 | B49: IBRAHIM USMAN | C49: SNR RESEARCH FELLOW | D49: 15(8) | E49: =#REF! -> #REF! | F49: 70061.52 | G49: =F49-E49 -> #REF!
A50: 6 | B50: DR MOHAMMED O. AMALI | C50: RESEARCH FELLOW I | D50: 14(10) | E50: =56478.9 -> 56478.9 | F50: 57889.865 | G50: =F50-E50 -> 1410.9648
A51: 7 | B51: YAHAYA SHAMSU | C51: RESEARCH FELLOW 1 | D51: 14(10) | E51: =56478.9 -> 56478.9 | F51: 58026.609 | G51: =F51-E51 -> 1547.7094
A52: 8 | B52: OFORDEME ADAOBI JULIA | C52: RESEARCH FELLOW 1 | D52: 14(9) | E52: =#REF! -> #REF! | F52: 55518.903 | G52: =F52-E52 -> #REF!
A53: 9 | B53: DORIS DAKDA AARON | C53: RESEARCH FELLOW II | D53: 13(10) | E53: =48052.11 -> 48052.11 | F53: 49548.776 | G53: =F53-E53 -> 1496.6662
A54: 10 | B54: ZAINAB AKINDE | C54: RESEARCH OFFICER | D54: 9(7) | E54: =28360.95 -> 28360.95 | F54: 28360.953 | G54: =F54-E54 -> 0.0028626667
A55: 11 | B55: ABDULLAHI AHMAD USMAN | C55: RESEARCH OFFICER | D55: 9(7) | E55: =28360.95 -> 28360.95 | F55: 28360.953 | G55: =F55-E55 -> 0.0028626667
A56: 12 | B56: GUNAT NANSAK MARK | C56: RESEARCH OFFICER | D56: 9(7) | E56: =28360.95 -> 28360.95 | F56: 28360.953 | G56: =F56-E56 -> 0.0028626667
B57: TOTAL | C57: 12 | E57: =SUM(E45:E56) -> #REF! | F57: =SUM(F45:F56) -> 796306.16 | G57: =SUM(G45:G56) -> #REF!
B59: LEGAL SERVICES
A60: 1 | B60: DR SHUIBU DANWANKA | C60: DIRECTOR LEGAL SERVICES | D60: 17(9) | E60: =180306.81 -> 180306.81 | F60: ='[4]August 2022 (2)'!$AA$56 -> 180306.81 | G60: =F60-E60 -> -0.0031413333
B61: TOTAL | C61: 1 | E61: =SUM(E60:E60) -> 180306.81 | F61: =SUM(F60:F60) -> 180306.81 | G61: =F61-E61 -> -0.0031413333
B63: DEMOCRACY & GOVERNANCE
A64: 1 | B64: DR. ADEWALE ADEREMI | C64: DIRECTOR, DEMOCRATIC STUDIES | D64: 17(9) | E64: =180306.81 -> 180306.81 | F64: 180306.81 | G64: =F64-E64 -> -0.0031413333
A65: 2 | B65: NDANUSA MOHAMMED MANZUMA | C65: SNR RESEARCH FELLOW | D65: 15 (7) | E65: 75572.92 | F65: 75572.916 | G65: =F65-E65 -> -0.0043093333
A66: 3 | B66: EJALONIBU GANIYU LAYI | C66: RESEARCH FELLOW 11 | D66: 13(10) | E66: =48170.87 -> 48170.87 | F66: 49548.776 | G66: =F66-E66 -> 1377.9062
A67: 4 | B67: LOHNA BONKAT JONATHAN | C67: RESEARCH FELLOW 11 | D67: 13(9) | E67: =46673.26 -> 46673.26 | F67: 48170.87 | G67: =F67-E67 -> 1497.6103
A68: 5 | B68: YUNUSA ABDULLAHI | C68: RESEARCH FELLOW 1 | D68: 14(10) | E68: 56478.9 | F68: 58026.609 | G68: =F68-E68 -> 1547.7094
A69: 6 | B69: UDEFUNA NNADOZIE PATRICK | C69: RESEARCH OFFICER | D69: 10(14) | E69: 36127.27 | F69: 37661.421 | G69: =F69-E69 -> 1534.1514
A70: 7 | B70: OSOLAFIA MUHAMMAD EGYE | C70: PRINCIPAL RESEARCH OFFICER | D70: 12(9) | E70: 41248.56 | F70: 43278.495 | G70: =F70-E70 -> 2029.9348
A71: 8 | B71: SHAFIU YAHYA MIKAIL | C71: PRINCIPAL RESEARCH OFFICER | D71: 12(7) | E71: =40149.18 -> 40149.18 | F71: 40149.175 | G71: =F71-E71 -> -0.0047333333
A72: 9 | B72: HASSAN YERIMA | C72: PRINCIPAL RESEARCH OFFICER | D72: 12(7) | E72: =40149.18 -> 40149.18 | F72: 40149.175 | G72: =F72-E72 -> -0.0047333333
A73: 10 | B73: HAUWA PATE SADIQ | C73: PRINCIPAL PROGRAMME OFFICER | D73: 12(8) | E73: =#REF! -> #REF! | F73: ='[4]August 2022 (2)'!$Z$69 -> 41338.951 | G73: =F73-E73 -> #REF!
A74: 11 | B74: ABAYOMI KAYODE QUADRI | C74: RESEARCH OFFICER | D74: 10(8) | E74: =32291.82 -> 32291.82 | F74: 33059.078 | G74: =F74-E74 -> 767.25841
A75: 12 | B75: NNANDI LIVINUS ATURE | C75: RESEARCH ASSISTANT | D75: 9(8) | E75: =24685.95 -> 24685.95 | F75: 29058.483 | G75: =F75-E75 -> 4372.5326
A76: 13 | B76: LUCKY AGWOM | C76: RESEARCH ASSISTANT | D76: 8(8) | E76: =24685.95 -> 24685.95 | F76: 25271.771 | G76: =F76-E76 -> 585.82147
B77: TOTAL | C77: 13 | E77: =SUM(E64:E76) -> #REF! | F77: =SUM(F64:F76) -> 701592.53 | G77: =SUM(G64:G76) -> #REF!
B79: DEPARTMENT OF STUDIES
A80: 1 | B80: DR ASIMIYU G. ABIOLA | C80: DIRECTOR POST GRADUATE | D80: 17(9) | E80: =180306.81 -> 180306.81 | F80: 180306.81 | G80: =F80-E80 -> -0.0031413333
A81: 2 | B81: USMAN WALI | C81: SENIOR RESEARCH FELLOW | D81: 15 (7) | E81: =75572.92 -> 75572.92 | F81: 75572.916 | G81: =F81-E81 -> -0.0043093333
A82: 3 | B82: MOSHOOD TOSHO AMUDA | C82: MANAGER, EXAMS & RECORDS | D82: 15 (7) | E82: =75572.92 -> 75572.92 | F82: 75572.916 | G82: =F82-E82 -> -0.0043093333
A83: 4 | B83: ANTHONY EDET | C83: ASST. MGR M&E | D83: 13(10) | E83: 48170.87 | F83: 49548.776 | G83: =F83-E83 -> 1377.9062
A84: 5 | B84: IGWE STACY | C84: PROGRAMME OFFICER | D84: 10(8) | E84: =32291.82 -> 32291.82 | F84: 33059.078 | G84: =F84-E84 -> 767.25841
B85: TOTAL | C85: 5 | E85: =SUM(E80:E84) -> 411915.34 | F85: =SUM(F80:F84) -> 414060.49 | G85: =SUM(G80:G84) -> 2145.1528
B87: ECON. DEV. & SOC. RESEARCH
A88: 1 | B88: ASEMOTA OMOROGBE JOSEPH | C88: Ag. DEPUTY DIRECTOR, ECO & SOC DEV DEPT | D88: 16(9) | E88: =97273.51 -> 97273.51 | F88: 99907.951 | G88: =F88-E88 -> 2634.4414
A89: 2 | B89: TERFA WILLIAMS ABRAHAM | C89: SNR RESEARCH FELLOW | D89: 15(9) | E89: =79956.94 -> 79956.94 | F89: 79956.939 | G89: =F89-E89 -> -0.00085333335
A90: 3 | B90: DR AUGUSTINE C. OSIGWE | C90: SNR RESEARCH FELLOW | D90: 15(9) | E90: =79796.1 -> 79796.1 | F90: 79796.103 | G90: =F90-E90 -> 0.0031466666
A91: 4 | B91: NGARA CHRISTOPHER OCHANJA | C91: RESEARCH FELLOW 1 | D91: 14(11) | E91: =57894.08 -> 57894.08 | F91: 59441.782 | G91: =F91-E91 -> 1547.702
A92: 5 | B92: OMOJU OLUWASOLA EMMANUEL | C92: RESEARCH FELLOW I | D92: 14(10) | E92: =56478.9 -> 56478.9 | F92: 58026.609 | G92: =F92-E92 -> 1547.7094
A93: 6 | B93: IBE EZECHI CYRIACUS | C93: RESEARCH FELLOW II | D93: 13(10) | E93: =48170.87 -> 48170.87 | F93: 49548.776 | G93: =F93-E93 -> 1377.9062
A94: 7 | B94: OSIKHEN LEO IGBANOI | C94: RESEARCH FELLOW 11 | D94: 13(9) | E94: =46673.26 -> 46673.26 | F94: 48170.87 | G94: =F94-E94 -> 1497.6103
A95: 8 | B95: OKUNGBOWA OSARETIN GODSPOWER | C95: RESEARCH FELLOW 11 | D95: 13(9) | E95: =46673.26 -> 46673.26 | F95: 48170.87 | G95: =F95-E95 -> 1497.6103
A96: 9 | B96: YUSUF IBRAHIM | C96: PRINCIPAL RESEARCH OFFICER | D96: 12(7) | E96: =40149.18 -> 40149.18 | F96: 40149.175 | G96: =F96-E96 -> -0.0047333333
A97: 10 | B97: MARYAM MUSA SADA | C97: ASSIT. RESEARCH OFFICER | D97: 10(7) | E97: 0 | F97: 0 | G97: =F97-E97 -> 0
A98: 11 | B98: CHARITY EZENWAJIOBI | C98: REASEARCH. ASST. | D98: 8(8) | E98: =24685.95 -> 24685.95 | F98: 24749.797 | G98: =F98-E98 -> 63.847063
B99: TOTAL | C99: 11 | E99: =SUM(E88:E98) -> 577752.05 | F99: =SUM(F88:F98) -> 587918.87 | G99: =SUM(G88:G98) -> 10166.824
B101: TRAINING & INT''L COOP
A102: 1 | B102: REKIYA IBRAHIM ATTAH | C102: DEPUTY DIRECTOR TRAINING | D102: 16(8) | E102: =79993.51 -> 79993.51 | F102: 79993.514 | G102: =F102-E102 -> 0.0038506667
A103: 2 | B103: DR FRANCIS NDUM OJIE | C103: CHIEF TRAINING OFFICER | D103: 14(10) | E103: =43380.1 -> 43380.1 | F103: 44734.339 | G103: =F103-E103 -> 1354.2394
A104: 3 | B104: ABUBAKAR MOHAMMED BASHIR | C104: ASST. CHIEF TRAINING OFFICER | D104: 13(9) | E104: =38272.44 -> 38272.44 | F104: 39582.845 | G104: =F104-E104 -> 1310.4048
A105: 4 | B105: OKECHUKWU UCHENNA HULDA | C105: PRINCIPALTRAINING OFFICER | D105: 12(8) | E105: =#REF! -> #REF! | F105: 32098.951 | G105: =F105-E105 -> #REF!
B106: TOTAL | C106: 4 | E106: =SUM(E102:E105) -> #REF! | F106: =SUM(F102:F105) -> 196409.65 | G106: =SUM(G102:G105) -> #REF!
B108: LIBRARY & DOCUMENTATION
A109: 1 | B109: DR MAIMUNA IZAH | C109: INSITUTE LIBRARIAN | D109: 17(9) | E109: =180306.81 -> 180306.81 | F109: 180145.97 | G109: =F109-E109 -> -160.83914
...

Sheet January 2023 NHF)
A1: NATIONAL INSTITUTE FOR LEGISLATIVE AND DEMOCRATIC STUDIES
A2: STAFF PAYROLL FOR THE MONTH OF JANUARY 2023
E3: ='[1]FEB 08'!E11/'[1]FEB 08'!M11 -> #REF!
B4: STAFF NAME | C4: DESIGNATION | D4: GRADE LEVEL | E4: BASIC SALARY | F4: NEW NHF DED. | G4: OLD NHF DED. | H4: DIFFERENCE
A5: S/N | B5: DG'S OFFICE | E5: N | F5: N | G5: N | H5: N
A6: 1 | B6: PROF. ABUBAKAR O. SULAIMAN | C6: DIRECTOR GENERAL | D6: CONSOL | E6: 160488.75
A7: 2 | B7: DR JAKE DABANG DAN AZUMI | C7: DEPUTY DIR. TTECHNICAL | D7: 16(9) | E7: =42653.17 -> 42653.17 | F7: =0.025*E7 -> 1066.3293 | G7: ='[5]April 2022'!$H$26 -> 1028.9423 | H7: =F7-G7 -> 37.387
A8: 3 | B8: DR ABDULSALAM NASIRU NAEEM | C8: SA ACADEMICS | D8: 16(9) | E8: =42653.17 -> 42653.17 | H8: =F8-G8 -> 0
A9: 4 | B9: RAHEEM USMAN AYIGORO | C9: SA-INFRASTRUCTURE | D9: 16 (9) | E9: =42653.17 -> 42653.17 | H9: =F9-G9 -> 0
A10: 5 | B10: MARIAM MOHAMMED BELLO | C10: SA- SPECIAL DUTIES | D10: 16(8) | E10: 41157.69 | H10: =F10-G10 -> 0
A11: 6 | B11: AKINSANMI ADEJOKE OLUKEMI | C11: DEPUTY DIR. INFO/PROTOCOL | D11: 16(8) | E11: =41157.69 -> 41157.69 | F11: =0.025*E11 -> 1028.9423 | G11: =G7 -> 1028.9423 | H11: =F11-G11 -> 0
A12: 7 | B12: DR IKEME ARTHUR J.O | C12: DEPUTY DIRECTOR, M&E | D12: 16(8) | E12: =41157.69 -> 41157.69 | F12: =0.025*E12 -> 1028.9423 | G12: =1028.94 -> 1028.94 | H12: =F12-G12 -> 0.00225
A13: 8 | B13: MOSHOOD M. OLALERE | C13: DEPUTY DIR. GENERAL SERVICE | D13: 16(8) | E13: =41157.69 -> 41157.69 | F13: =0.025*E13 -> 1028.9423 | G13: =1028.94 -> 1028.94 | H13: =F13-G13 -> 0.00225
A14: 9 | B14: ANDRAWUS MUSA | C14: ASST. DIRECTOR, STORES | D14: 15(9) | E14: 33507.5 | F14: =0.025*E14 -> 837.6875 | G14: ='[5]April 2022'!$H$28 -> 837.6875 | H14: =F14-G14 -> 0
A15: 10 | B15: AYOBOLU OLAJIDE OLUFUNSHO | C15: ASST.DIR., INFORMATION | D15: 15 (8) | E15: 32263.2 | H15: =F15-G15 -> 0
A16: 11 | B16: HUSSEIN EGYE MUSA | C16: CHIEF PROTOCOL OFFICER | D16: 14(10) | E16: 27611.23 | F16: 0 | G16: 0 | H16: =F16-G16 -> 0
A17: 12 | B17: DONALD E. MKPANAM | C17: CHIEF ICT OFFICER | D17: 14(10) | E17: 27611.23 | F17: =0.025*E17 -> 690.28075 | G17: ='[5]April 2022'!$H$27 -> 668.31625 | H17: =F17-G17 -> 21.9645
A18: 13 | B18: JOY HARUNA MAKERI | C18: RESEARCH FELLOW 1 TRAINING | D18: 14(10) | E18: 27611.23 | H18: =F18-G18 -> 0
A19: 14 | B19: ALI ABDULLAHI | C19: CHIEF ICT OFFICER | D19: 14(10) | E19: 27611.23 | H19: =F19-G19 -> 0
A20: 15 | B20: PERCY TERFA GBAHABO | C20: HEAD, NILDS LIAISON OFFICE | D20: 13(9) | E20: 24741.26 | H20: =F20-G20 -> 0
A21: 16 | B21: HASSANA AHMED IBRAHIM | C21: PA- TO DG | D21: 13 (8) | E21: =23891.12 -> 23891.12 | F21: =0.025*E21 -> 597.278 | G21: ='[5]April 2022'!$H$52 -> 576.87475 | H21: =F21-G21 -> 20.40325
A22: 17 | B22: CHRISTIAN MADUABUCHI ODO | C22: PRINCIPAL ICT OFFICER | D22: 12(9) | E22: =22837.82 -> 22837.82 | F22: =0.025*E22 -> 570.9455 | G22: ='[5]April 2022'!$H$45 -> 538.022 | H22: =F22-G22 -> 32.9235
A23: 18 | B23: ADUGBA RICHARD TERSEER | C23: PRINCIPAL INFO. OFFICER | D23: 12(8) | E23: 21520.88 | H23: =F23-G23 -> 0
A24: 19 | B24: EGUATU U. ONYEJELEM | C24: PRINCIPAL M&E OFFICER | D24: 12(8) | E24: 21520.88 | H24: =F24-G24 -> 0
A25: 20 | B25: ODEH SUZIE | C25: ADMIN. OFFICER, LIASION OFFICE | D25: 10(10) | E25: =18779.3 -> 18779.3 | F25: =0 -> 0 | G25: =0 -> 0 | H25: =F25-G25 -> 0
A26: 21 | B26: YAKUB OLUWATOYIN USMAN | C26: ASST. ADMIN. OFFICER | D26: 10(9) | E26: 18281.64 | H26: =F26-G26 -> 0
A27: 22 | B27: ELIZABETH OGECHUKWU ONYEAKU | C27: ICT OFFICER | D27: 9(8) | E27: 14736.14 | H27: =F27-G27 -> 0
A28: 23 | B28: VICTOR ASUKWO | C28: ICT OFFICER | D28: 9(8) | E28: =15188.67 -> 15188.67 | H28: =F28-G28 -> 0
A29: 24 | B29: IJEOMA NKOLIKWA | C29: STORES OFFICER | D29: 9(8) | E29: =15188.67 -> 15188.67 | H29: =F29-G29 -> 0
A30: 25 | B30: ABDULRAHMAN A SULAIMAN | C30: ASSISTANT STORES OFFICER | D30: 8 (10) | E30: 13492.21 | H30: =F30-G30 -> 0
A31: 26 | B31: TASSNEEM IBRAHIM | C31: ASSIST. INFORMATION | D31: 8(10) | E31: 13492.21 | H31: =F31-G31 -> 0
A32: 27 | B32: DARE SHEU MAGBON | C32: ASSIST. PG | D32: 8(10) | E32: 13492.21 | H32: =F32-G32 -> 0
A33: 28 | B33: JIMOH ADEBAYO ZAKA | C33: ASST. OFFICER/COMM | D33: 9(8) | E33: 15188.67 | F33: =0 -> 0 | G33: =0 -> 0 | H33: =F33-G33 -> 0
A34: 29 | B34: MOHAMMED BELLO | C34: RESEARCH ASSITANT PG | D34: 8(8) | E34: =12732 -> 12732 | H34: =F34-G34 -> 0
A35: 30 | B35: SULEIMAN ABUBAKAR SODEEQ | C35: ASST. ADMIN. OFFICER | D35: 8(8) | E35: =12732 -> 12732 | H35: =F35-G35 -> 0
A36: 31 | B36: HARUNA JIBRIL A. | C36: ASST. ADMIN. OFFICER | D36: 8(8) | E36: =12732 -> 12732 | H36: =F36-G36 -> 0
B37: TOTAL | C37: 31 | E37: =SUM(E6:E36) -> 919842.32 | F37: =SUM(F6:F36) -> 6849.3477 | G37: =SUM(G6:G36) -> 6736.665 | H37: =F37-G37 -> 112.68275
H38: =F38-G38 -> 0
B39: INTERNAL AUDIT | H39: =F39-G39 -> 0
A40: 1 | B40: OSANAIYE DAVID AKINYEMI | C40: DIRECTOR INTERNAL AUDIT | D40: 17(9) | E40: 81740.02 | H40: =F40-G40 -> 0
A41: 2 | B41: JAMILA ABDUL | C41: AUDITOR II | D41: 8(7) | E41: 12351.94 | F41: =0 -> 0 | G41: =0 -> 0 | H41: =F41-G41 -> 0
C42: 2 | E42: =SUM(E40:E41) -> 94091.96 | F42: =SUM(F40:F41) -> 0 | G42: =SUM(G40:G41) -> 0 | H42: =F42-G42 -> 0
H43: =F43-G43 -> 0
B44: LEG. SUPPORT SEVICES | H44: =F44-G44 -> 0
A45: 1 | B45: PROF. EDOBA BRIGHT OMOREGBE | C45: AG. DLSS | D45: 17(9) | E45: 81740.02 | H45: =F45-G45 -> 0
A46: 2 | B46: DR CLINTON JAJA | C46: SENIOR RESEARCH FELLOW | D46: 15(9) | E46: 33507.5 | H46: =F46-G46 -> 0
A47: 3 | B47: BETHEL UZOMA IHUGBA | C47: SNR RESEARCH FELLOW | D47: 15(9) | E47: 33507.5 | H47: =F47-G47 -> 0
A48: 4 | B48: OGUCHE SAMUEL | C48: SNR RESEARCH FELLOW | D48: 15(9) | E48: 33507.5 | H48: =F48-G48 -> 0
A49: 5 | B49: IBRAHIM USMAN | C49: SNR RESEARCH FELLOW | D49: 15(8) | E49: 32263.2 | F49: =0.025*E49 -> 806.58 | G49: =837.69 -> 837.69 | H49: =F49-G49 -> -31.11
A50: 6 | B50: DR MOHAMMED O. AMALI | C50: RESEARCH FELLOW I | D50: 14(10) | E50: 27611.23 | H50: =F50-G50 -> 0
A51: 7 | B51: YAHAYA SHAMSU | C51: RESEARCH FELLOW 1 | D51: 14(10) | E51: 27611.23 | F51: 0 | G51: 0 | H51: =F51-G51 -> 0
A52: 8 | B52: OFORDEME ADAOBI JULIA | C52: RESEARCH FELLOW 1 | D52: 14(9) | E52: 26732.65 | H52: =F52-G52 -> 0
A53: 9 | B53: DORIS DAKDA AARON | C53: RESEARCH FELLOW II | D53: 13(10) | E53: 25523.45 | F53: =0.025*E53 -> 638.08625 | G53: ='[5]April 2022'!$H$46 -> 618.5315 | H53: =F53-G53 -> 19.55475
A54: 10 | B54: ZAINAB AKINDE | C54: RESEARCH OFFICER | D54: 9(7) | E54: =14736.14 -> 14736.14 | H54: =F54-G54 -> 0
A55: 11 | B55: ABDULLAHI AHMAD USMAN | C55: RESEARCH OFFICER | D55: 9(7) | E55: =14736.14 -> 14736.14 | H55: =F55-G55 -> 0
A56: 12 | B56: GUNAT NANSAK MARK | C56: RESEARCH OFFICER | D56: 9(7) | E56: =14736.14 -> 14736.14 | H56: =F56-G56 -> 0
B57: TOTAL | C57: 12 | E57: =SUM(E45:E56) -> 366212.7 | F57: =SUM(F45:F56) -> 1444.6663 | G57: =SUM(G45:G56) -> 1456.2215 | H57: =F57-G57 -> -11.55525
H58: =F58-G58 -> 0
B59: LEGAL SERVICES | H59: =F59-G59 -> 0
A60: 1 | B60: DR SHUIBU DANWANKA | C60: DIRECTOR LEGAL SERVICES | D60: 17(9) | E60: 81740.02 | F60: 0 | G60: 0 | H60: =F60-G60 -> 0
B61: TOTAL | C61: 1 | E61: =SUM(E60:E60) -> 81740.02 | F61: =SUM(F60:F60) -> 0 | G61: =SUM(G60:G60) -> 0 | H61: =F61-G61 -> 0
H62: =F62-G62 -> 0
B63: DEMOCRACY & GOVERNANCE | H63: =F63-G63 -> 0
A64: 1 | B64: DR. ADEWALE ADEREMI | C64: DIRECTOR, DEMOCRATIC STUDIES | D64: 17(9) | E64: 81740.02 | H64: =F64-G64 -> 0
A65: 2 | B65: NDANUSA MOHAMMED MANZUMA | C65: SNR RESEARCH FELLOW | D65: 15 (7) | E65: 31018.84 | H65: =F65-G65 -> 0
A66: 3 | B66: EJALONIBU GANIYU LAYI | C66: RESEARCH FELLOW 11 | D66: 13(10) | E66: 25523.45 | H66: =F66-G66 -> 0
A67: 4 | B67: LOHNA BONKAT JONATHAN | C67: RESEARCH FELLOW 11 | D67: 13(9) | E67: 24741.26 | F67: =0 -> 0 | G67: =0 -> 0 | H67: =F67-G67 -> 0
A68: 5 | B68: YUNUSA ABDULLAHI | C68: RESEARCH FELLOW 1 | D68: 14(10) | E68: 27611.23 | H68: =F68-G68 -> 0
A69: 6 | B69: UDEFUNA NNADOZIE PATRICK | C69: RESEARCH OFFICER | D69: 10(14) | E69: =20769.92 -> 20769.92 | H69: =F69-G69 -> 0
A70: 7 | B70: OSOLAFIA MUHAMMAD EGYE | C70: PRINCIPAL RESEARCH OFFICER | D70: 12(9) | E70: =22837.82 -> 22837.82 | F70: =0.025*E70 -> 570.9455 | G70: ='[5]April 2022'!$H$41 -> 538.022 | H70: =F70-G70 -> 32.9235
A71: 8 | B71: SHAFIU YAHYA MIKAIL | C71: PRINCIPAL RESEARCH OFFICER | D71: 12(7) | E71: 20749 | H71: =F71-G71 -> 0
A72: 9 | B72: HASSAN YERIMA | C72: PRINCIPAL RESEARCH OFFICER | D72: 12(7) | E72: 20749 | H72: =F72-G72 -> 0
A73: 10 | B73: HAUWA PATE SADIQ | C73: PRINCIPAL PROGRAMME OFFICER | D73: 12(8) | E73: 21520.88 | H73: =F73-G73 -> 0
A74: 11 | B74: ABAYOMI KAYODE QUADRI | C74: RESEARCH OFFICER | D74: 10(8) | E74: 17784.1 | H74: =F74-G74 -> 0
A75: 12 | B75: NNANDI LIVINUS ATURE | C75: RESEARCH ASSISTANT | D75: 9(8) | E75: =15188.67 -> 15188.67 | H75: =F75-G75 -> 0
A76: 13 | B76: LUCKY AGWOM | C76: RESEARCH ASSISTANT | D76: 8(8) | E76: =12732 -> 12732 | H76: =F76-G76 -> 0
B77: TOTAL | C77: 13 | E77: =SUM(E64:E76) -> 342966.19 | F77: =SUM(F64:F76) -> 570.9455 | G77: =SUM(G64:G76) -> 538.022 | H77: =F77-G77 -> 32.9235
H78: =F78-G78 -> 0
B79: DEPARTMENT OF STUDIES | H79: =F79-G79 -> 0
A80: 1 | B80: DR ASIMIYU G. ABIOLA | C80: DIRECTOR POST GRADUATE | D80: 17(9) | E80: 81740.02 | F80: 0 | G80: 0 | H80: =F80-G80 -> 0
A81: 2 | B81: USMAN WALI | C81: SENIOR RESEARCH FELLOW | D81: 15 (7) | E81: 31018.84 | F81: 0 | G81: 0 | H81: =F81-G81 -> 0
A82: 3 | B82: MOSHOOD TOSHO AMUDA | C82: MANAGER, EXAMS & RECORDS | D82: 15 (7) | E82: 31018.84 | F82: 0 | G82: 0 | H82: =F82-G82 -> 0
A83: 4 | B83: ANTHONY EDET | C83: ASST. MGR M&E | D83: 13(10) | E83: 25523.45 | F83: =0.025*E83 -> 638.08625 | G83: ='[5]April 2022'!$H$38 -> 618.5315 | H83: =F83-G83 -> 19.55475
A84: 5 | B84: IGWE STACY | C84: PROGRAMME OFFICER | D84: 10(8) | E84: 17784.1 | H84: =F84-G84 -> 0
B85: TOTAL | C85: 5 | E85: =SUM(E80:E84) -> 187085.25 | F85: =SUM(F80:F84) -> 638.08625 | G85: =SUM(G80:G84) -> 618.5315 | H85: =F85-G85 -> 19.55475
H86: =F86-G86 -> 0
B87: ECON. DEV. & SOC. RESEARCH | H87: =F87-G87 -> 0
A88: 1 | B88: ASEMOTA OMOROGBE JOSEPH | C88: Ag. DEPUTY DIRECTOR, ECO & SOC DEV DEPT | D88: 16(9) | E88: 42653.17 | H88: =F88-G88 -> 0
A89: 2 | B89: TERFA WILLIAMS ABRAHAM | C89: SNR RESEARCH FELLOW | D89: 15(9) | E89: 33507.5 | H89: =F89-G89 -> 0
A90: 3 | B90: DR AUGUSTINE C. OSIGWE | C90: SNR RESEARCH FELLOW | D90: 15(9) | E90: 33507.5 | F90: =0.025*E90 -> 837.6875 | G90: ='[5]April 2022'!$H$37 -> 837.6875 | H90: =F90-G90 -> 0
A91: 4 | B91: NGARA CHRISTOPHER OCHANJA | C91: RESEARCH FELLOW 1 | D91: 14(11) | E91: =28489.81 -> 28489.81 | F91: =0.025*E91 -> 712.24525 | G91: ='[5]April 2022'!$H$44 -> 690.28075 | H91: =F91-G91 -> 21.9645
A92: 5 | B92: OMOJU OLUWASOLA EMMANUEL | C92: RESEARCH FELLOW I | D92: 14(10) | E92: 27611.23 | H92: =F92-G92 -> 0
A93: 6 | B93: IBE EZECHI CYRIACUS | C93: RESEARCH FELLOW II | D93: 13(10) | E93: 25523.45 | H93: =F93-G93 -> 0
A94: 7 | B94: OSIKHEN LEO IGBANOI | C94: RESEARCH FELLOW 11 | D94: 13(9) | E94: 24741.26 | H94: =F94-G94 -> 0
A95: 8 | B95: OKUNGBOWA OSARETIN GODSPOWER | C95: RESEARCH FELLOW 11 | D95: 13(9) | E95: 24741.26 | H95: =F95-G95 -> 0
A96: 9 | B96: YUSUF IBRAHIM | C96: PRINCIPAL RESEARCH OFFICER | D96: 12(7) | E96: =20749 -> 20749 | H96: =F96-G96 -> 0
A97: 10 | B97: MARYAM MUSA SADA | C97: ASSIT. RESEARCH OFFICER | D97: 10(7) | E97: 0 | H97: =F97-G97 -> 0
A98: 11 | B98: CHARITY EZENWAJIOBI | C98: REASEARCH. ASST. | D98: 8(8) | E98: =12732 -> 12732 | F98: 0 | G98: 0 | H98: =F98-G98 -> 0
B99: TOTAL | C99: 11 | E99: =SUM(E88:E98) -> 274256.18 | F99: =SUM(F88:F98) -> 1549.9327 | G99: =SUM(G88:G98) -> 1527.9682 | H99: =F99-G99 -> 21.9645
H100: =F100-G100 -> 0
...

Sheet PAYE Computation
A1: NATIONAL INSTITUTE FOR LEGISLATIVE AND DEMOCRATIC STUDIES
A2: NATIONAL ASSEMBLY ABUJA
A3: TAX COMPUTATION FOR 2023
A4: S/NO | B4: NAME | C4: MONTHLY TOTAL SALARY | D4: NO OF MONTHS | E4: ANNUAL SALARY GROSSED UP | F4: NATIONAL HOUSING SCHEME = 2.5% OF BASIC SALARY | G4: PENSION CONTRIBUTION = 8% OF CONSOLIDATED | H4: NHIS | I4: NET SALARY (EXC OF CRA) | M4: CRA=#200,000+(20% 0F NET SALARY (EXC OF CRA) | N4: TOTAL RELIEF | O4: CHARGEABLE INCOME | P4: FIRST N300,000 @ 7% | Q4: NEXT N300,000 @ 11% | R4: NEXT N500,000 @ 15% | S4: NEXT N500,000@ 19% | T4: NEXT N1,600,000 @ 21% | U4: ABOVE N3,200,000 @ 24% | V4: ANNUAL TAX PAYABLE | X4: MONTHLY TAX PAYABLE | Y4: MINIMUM TAX PAYABLE | Z4: NEW ACTUAL TAX PAYABLE | AA4: OLD Tax | AB4: Difference
A5: 1 | B5: PROF. ABUBAKAR O. SULAIMAN | C5: 1158849.8 | D5: 12 | E5: 13906198 | I5: 13906198 | J5: 200000 | K5: 0.2 | L5: 2781239.6 | M5: 2981239.6 | N5: 2981239.6 | O5: 10924958 | P5: 21000 | Q5: 33000 | R5: 75000 | S5: 95000 | T5: 336000 | U5: 1853990 | V5: 2413990 | W5: 12 | X5: 201165.84 | Z5: 201165.84 | AA5: 201165.84 | AB5: -0.0040533334
A6: 3 | B6: DR JAKE DABANG DAN AZUMI | C6: 781465.02 | D6: 12 | E6: 9377580.3 | F6: 12347.31 | I6: 9365233 | J6: 200000 | K6: 0.2 | L6: 1873046.6 | M6: 2073046.6 | N6: 2085393.9 | O6: 7292186.4 | P6: 21000 | Q6: 33000 | R6: 75000 | S6: 95000 | T6: 336000 | U6: 982124.73 | V6: 1542124.7 | W6: 12 | X6: 128510.39 | Z6: 128510.39 | AA6: 128508.39 | AB6: 2.006208
A7: 4 | B7: DR ABDULSALAM NASIRU NAEEM | C7: 731465.02 | D7: 12 | E7: 8777580.3 | I7: 8777580.3 | J7: 200000 | K7: 0.2 | L7: 1755516.1 | M7: 1955516.1 | N7: 1955516.1 | O7: 6822064.2 | P7: 21000 | Q7: 33000 | R7: 75000 | S7: 95000 | T7: 336000 | U7: 869295.42 | V7: 1429295.4 | W7: 12 | X7: 119107.95 | Z7: 119107.95 | AA7: 116473.51 | AB7: 2634.4414
A8: 5 | B8: RAHEEM USMAN AYIGORO | C8: 541465.02 | D8: 12 | E8: 6497580.3 | I8: 6497580.3 | J8: 200000 | K8: 0.2 | L8: 1299516.1 | M8: 1499516.1 | N8: 1499516.1 | O8: 4998064.2 | P8: 21000 | Q8: 33000 | R8: 75000 | S8: 95000 | T8: 336000 | U8: 431535.42 | V8: 991535.42 | W8: 12 | X8: 82627.951 | Z8: 82627.951 | AA8: 79993.51 | AB8: 2634.4414
A9: 6 | B9: MARIAM MOHAMMED BELLO | C9: 682621.81 | D9: 12 | E9: 8191461.7 | I9: 8191461.7 | J9: 200000 | K9: 0.2 | L9: 1638292.3 | M9: 1838292.3 | N9: 1838292.3 | O9: 6353169.3 | P9: 21000 | Q9: 33000 | R9: 75000 | S9: 95000 | T9: 336000 | U9: 756760.64 | V9: 1316760.6 | W9: 12 | X9: 109730.05 | Z9: 109730.05 | AA9: 107095.69 | AB9: 2634.3634
A10: 7 | B10: AKINSANMI ADEJOKE OLUKEMI | C10: 627744 | D10: 12 | E10: 7532927.9 | F10: 10052.25 | I10: 7522875.7 | J10: 200000 | K10: 0.2 | L10: 1504575.1 | M10: 1704575.1 | N10: 1714627.4 | O10: 5818300.6 | P10: 21000 | Q10: 33000 | R10: 75000 | S10: 95000 | T10: 336000 | U10: 628392.13 | V10: 1188392.1 | W10: 12 | X10: 99032.678 | Z10: 99032.678 | AA10: 96398.374 | AB10: 2634.304
A11: 8 | B11: DR IKEME ARTHUR J.O | C11: 527744 | D11: 12 | E11: 6332927.9 | F11: 10052.25 | I11: 6322875.7 | J11: 200000 | K11: 0.2 | L11: 1264575.1 | M11: 1464575.1 | N11: 1474627.4 | O11: 4858300.6 | P11: 21000 | Q11: 33000 | R11: 75000 | S11: 95000 | T11: 336000 | U11: 397992.13 | V11: 957992.13 | W11: 12 | X11: 79832.678 | Z11: 79832.678 | AA11: 77198.374 | AB11: 2634.304
A12: 9 | B12: MOSHOOD M. OLALERE | C12: 527744 | D12: 12 | E12: 6332927.9 | F12: 10052.25 | I12: 6322875.7 | J12: 200000 | K12: 0.2 | L12: 1264575.1 | M12: 1464575.1 | N12: 1474627.4 | O12: 4858300.6 | P12: 21000 | Q12: 33000 | R12: 75000 | S12: 95000 | T12: 336000 | U12: 397992.13 | V12: 957992.13 | W12: 12 | X12: 79832.678 | Z12: 79832.678 | AA12: 77198.374 | AB12: 2634.304
A13: 10 | B13: ANDRAWUS MUSA | C13: 447553.5 | D13: 12 | E13: 5370642 | F13: 10052.25 | I13: 5360589.8 | J13: 200000 | K13: 0.2 | L13: 1072118 | M13: 1272118 | N13: 1282170.2 | O13: 4088471.8 | P13: 21000 | Q13: 33000 | R13: 75000 | S13: 95000 | T13: 336000 | U13: 213233.24 | V13: 773233.24 | W13: 12 | X13: 64436.103 | Z13: 64436.103 | AA13: 64436.1 | AB13: 0.0031466667
A14: 11 | B14: AYOBOLU OLAJIDE OLUFUNSHO | C14: 436137.05 | D14: 12 | E14: 5233644.6 | I14: 5233644.6 | J14: 200000 | K14: 0.2 | L14: 1046728.9 | M14: 1246728.9 | N14: 1246728.9 | O14: 3986915.7 | P14: 21000 | Q14: 33000 | R14: 75000 | S14: 95000 | T14: 336000 | U14: 188859.76 | V14: 748859.76 | W14: 12 | X14: 62404.98 | Z14: 62404.98 | AA14: 60212.92 | AB14: 2192.0603
A15: 12 | B15: HUSSEIN EGYE MUSA | C15: 393333.04 | D15: 12 | E15: 4719996.4 | I15: 4719996.4 | J15: 200000 | K15: 0.2 | L15: 943999.28 | M15: 1143999.3 | N15: 1143999.3 | O15: 3575997.1 | P15: 21000 | Q15: 33000 | R15: 75000 | S15: 95000 | T15: 336000 | U15: 90239.313 | V15: 650239.31 | W15: 12 | X15: 54186.609 | Z15: 54186.609 | AA15: 52638.9 | AB15: 1547.7094
A16: 13 | B16: DONALD E. MKPANAM | C16: 343333.04 | D16: 12 | E16: 4119996.4 | F16: 8019.8 | I16: 4111976.6 | J16: 200000 | K16: 0.2 | L16: 822395.32 | M16: 1022395.3 | N16: 1030415.1 | O16: 3089581.3 | P16: 21000 | Q16: 33000 | R16: 75000 | S16: 95000 | T16: 312812.07 | V16: 536812.07 | W16: 12 | X16: 44734.339 | Z16: 44734.339 | AA16: 43380 | AB16: 1354.3394
A17: 14 | B17: JOY HARUNA MAKERI | C17: 563333.04 | D17: 12 | E17: 6759996.4 | I17: 6759996.4 | J17: 200000 | K17: 0.2 | L17: 1351999.3 | M17: 1551999.3 | N17: 1551999.3 | O17: 5207997.1 | P17: 21000 | Q17: 33000 | R17: 75000 | S17: 95000 | T17: 336000 | U17: 481919.31 | V17: 1041919.3 | W17: 12 | X17: 86826.609 | Z17: 86826.609 | AA17: 85278.9 | AB17: 1547.7094
A18: 15 | B18: ALI ABDULLAHI | C18: 338333.04 | D18: 12 | E18: 4059996.4 | I18: 4059996.4 | J18: 200000 | K18: 0.2 | L18: 811999.28 | M18: 1011999.3 | N18: 1011999.3 | O18: 3047997.1 | P18: 21000 | Q18: 33000 | R18: 75000 | S18: 95000 | T18: 304079.4 | V18: 528079.4 | W18: 12 | X18: 44006.617 | Z18: 44006.617 | AA18: 43492.04 | AB18: 514.5769
A19: 16 | B19: PERCY TERFA GBAHABO | C19: 362001.06 | D19: 12 | E19: 4344012.7 | F19: 7422.38 | I19: 4336590.3 | J19: 200000 | K19: 0.2 | L19: 867318.07 | M19: 1067318.1 | N19: 1074740.4 | O19: 3269272.3 | P19: 21000 | Q19: 33000 | R19: 75000 | S19: 95000 | T19: 336000 | V19: 560000 | W19: 12 | X19: 46666.667 | Z19: 46666.667 | AA19: 46673.26 | AB19: -6.5933333
A20: 17 | B20: HASSANA AHMED IBRAHIM | C20: 449201.03 | D20: 12 | E20: 5390412.3 | I20: 5390412.3 | J20: 200000 | K20: 0.2 | L20: 1078082.5 | M20: 1278082.5 | N20: 1278082.5 | O20: 4112329.8 | P20: 21000 | Q20: 33000 | R20: 75000 | S20: 95000 | T20: 336000 | U20: 218959.16 | V20: 778959.16 | W20: 12 | X20: 64913.264 | Z20: 64913.264 | AA20: 63364.81 | AB20: 1548.4537
A21: 18 | B21: CHRISTIAN MADUABUCHI ODO | C21: 284537 | D21: 12 | E21: 3414444 | F21: 6922.5 | I21: 3407521.5 | J21: 200000 | K21: 0.2 | L21: 681504.3 | M21: 881504.3 | N21: 888426.8 | O21: 2526017.2 | P21: 21000 | Q21: 33000 | R21: 75000 | S21: 95000 | T21: 194463.61 | U21: 0 | V21: 418463.61 | W21: 12 | X21: 34871.967 | Z21: 34871.967 | AA21: 31848.56 | AB21: 3023.4074
A22: 19 | B22: ADUGBA RICHARD TERSEER | C22: 267454.07 | D22: 12 | E22: 3209448.9 | F22: 6456.26 | I22: 3202992.6 | J22: 200000 | K22: 0.2 | L22: 640598.53 | M22: 840598.53 | N22: 847054.79 | O22: 2362394.1 | P22: 21000 | Q22: 33000 | R22: 75000 | S22: 95000 | T22: 160102.76 | V22: 384102.76 | W22: 12 | X22: 32008.563 | Z22: 32008.563 | AA22: 31749.189 | AB22: 259.37433
A23: 20 | B23: EGUATU U. ONYEJELEM | C23: 267454.07 | D23: 12 | E23: 3209448.9 | I23: 3209448.9 | J23: 200000 | K23: 0.2 | L23: 641889.78 | M23: 841889.78 | N23: 841889.78 | O23: 2367559.1 | P23: 21000 | Q23: 33000 | R23: 75000 | S23: 95000 | T23: 161187.41 | V23: 385187.41 | W23: 12 | X23: 32098.951 | Z23: 32098.951 | AA23: 31749.189 | AB23: 349.76197
A24: 21 | B24: ODEH SUZIE | C24: 242300.08 | D24: 12 | E24: 2907600.9 | I24: 2907600.9 | J24: 200000 | K24: 0.2 | L24: 581520.19 | M24: 781520.19 | N24: 781520.19 | O24: 2126080.7 | P24: 21000 | Q24: 33000 | R24: 75000 | S24: 95000 | T24: 110476.96 | V24: 334476.96 | W24: 12 | X24: 27873.08 | Z24: 27873.08 | AA24: 27105.99 | AB24: 767.08969
A25: 22 | B25: YAKUB OLUWATOYIN USMAN | C25: 237734.05 | D25: 12 | E25: 2852808.6 | I25: 2852808.6 | J25: 200000 | K25: 0.2 | L25: 570561.71 | M25: 770561.71 | N25: 770561.71 | O25: 2082246.9 | P25: 21000 | Q25: 33000 | R25: 75000 | S25: 95000 | T25: 101271.84 | V25: 325271.84 | W25: 12 | X25: 27105.987 | Z25: 27105.987 | AA25: 26339.08 | AB25: 766.90656
A26: 23 | B26: ELIZABETH OGECHUKWU ONYEAKU | C26: 205204.08 | D26: 12 | E26: 2462449 | I26: 2462449 | J26: 200000 | K26: 0.2 | L26: 492489.8 | M26: 692489.8 | N26: 692489.8 | O26: 1769959.2 | P26: 21000 | Q26: 33000 | R26: 75000 | S26: 95000 | T26: 35691.434 | V26: 259691.43 | W26: 12 | X26: 21640.953 | Z26: 21640.953 | AA26: 21640.95 | AB26: 0.0028626667
A27: 24 | B27: VICTOR ASUKWO | C27: 209356.05 | D27: 12 | E27: 2512272.6 | I27: 2512272.6 | J27: 200000 | K27: 0.2 | L27: 502454.51 | M27: 702454.51 | N27: 702454.51 | O27: 1809818.1 | P27: 21000 | Q27: 33000 | R27: 75000 | S27: 95000 | T27: 44061.791 | V27: 268061.79 | W27: 12 | X27: 22338.483 | Z27: 22338.483 | AA27: 21640.95 | AB27: 697.5326
A28: 25 | B28: IJEOMA NKOLIKWA | C28: 209356.05 | D28: 12 | E28: 2512272.6 | I28: 2512272.6 | J28: 200000 | K28: 0.2 | L28: 502454.51 | M28: 702454.51 | N28: 702454.51 | O28: 1809818.1 | P28: 21000 | Q28: 33000 | R28: 75000 | S28: 95000 | T28: 44061.791 | V28: 268061.79 | W28: 12 | X28: 22338.483 | Z28: 22338.483 | AA28: 21640.95 | AB28: 697.5326
A29: 26 | B29: ABDULRAHMAN A SULAIMAN | C29: 183791.03 | D29: 12 | E29: 2205492.3 | I29: 2205492.3 | J29: 200000 | K29: 0.2 | L29: 441098.46 | M29: 641098.46 | N29: 641098.46 | O29: 1564393.9 | P29: 21000 | Q29: 33000 | R29: 75000 | S29: 88234.833 | T29: 0 | V29: 217234.83 | W29: 12 | X29: 18102.903 | Z29: 18102.903 | AA29: 17572.89 | AB29: 530.01273
A30: 27 | B30: TASSNEEM IBRAHIM | C30: 183791.03 | D30: 12 | E30: 2205492.3 | I30: 2205492.3 | J30: 200000 | K30: 0.2 | L30: 441098.46 | M30: 641098.46 | N30: 641098.46 | O30: 1564393.9 | P30: 21000 | Q30: 33000 | R30: 75000 | S30: 88234.833 | T30: 0 | V30: 217234.83 | W30: 12 | X30: 18102.903 | Z30: 18102.903 | AA30: 17572.89 | AB30: 530.01273
A31: 28 | B31: DARE SHEU MAGBON | C31: 183791.03 | D31: 12 | E31: 2205492.3 | I31: 2205492.3 | J31: 200000 | K31: 0.2 | L31: 441098.46 | M31: 641098.46 | N31: 641098.46 | O31: 1564393.9 | P31: 21000 | Q31: 33000 | R31: 75000 | S31: 88234.833 | T31: 0 | V31: 217234.83 | W31: 12 | X31: 18102.903 | Z31: 18102.903 | AA31: 17572.89 | AB31: 530.01273
A32: 29 | B32: JIMOH ADEBAYO ZAKA | C32: 209356.05 | D32: 12 | E32: 2512272.6 | I32: 2512272.6 | J32: 200000 | K32: 0.2 | L32: 502454.51 | M32: 702454.51 | N32: 702454.51 | O32: 1809818.1 | P32: 21000 | Q32: 33000 | R32: 75000 | S32: 95000 | T32: 44061.791 | V32: 268061.79 | W32: 12 | X32: 22338.483 | Z32: 22338.483 | AA32: 21640.95 | AB32: 697.5326
A33: 30 | B33: MOHAMMED BELLO | C33: 176816.1 | D33: 12 | E33: 2121793.2 | I33: 2121793.2 | J33: 200000 | K33: 0.2 | L33: 424358.64 | M33: 624358.64 | N33: 624358.64 | O33: 1497434.6 | P33: 21000 | Q33: 33000 | R33: 75000 | S33: 75512.566 | T33: 0 | V33: 204512.57 | W33: 12 | X33: 17042.714 | Z33: 17042.714 | AA33: 16512.68 | AB33: 530.03387
A34: 31 | B34: SULEIMAN ABUBAKAR SODEEQ | C34: 176817.1 | D34: 12 | E34: 2121805.2 | I34: 2121805.2 | J34: 200000 | K34: 0.2 | L34: 424361.04 | M34: 624361.04 | N34: 624361.04 | O34: 1497444.2 | P34: 21000 | Q34: 33000 | R34: 75000 | S34: 75514.39 | T34: 0 | V34: 204514.39 | W34: 12 | X34: 17042.866 | Z34: 17042.866 | AA34: 16512.68 | AB34: 530.18587
A35: 32 | B35: HARUNA JIBRIL A. | C35: 176818.1 | D35: 12 | E35: 2121817.2 | I35: 2121817.2 | J35: 200000 | K35: 0.2 | L35: 424363.44 | M35: 624363.44 | N35: 624363.44 | O35: 1497453.8 | P35: 21000 | Q35: 33000 | R35: 75000 | S35: 75516.214 | T35: 0 | V35: 204516.21 | W35: 12 | X35: 17043.018 | Z35: 17043.018 | AA35: 16512.68 | AB35: 530.33787
C36: 12126899 | G36: 0 | Z36: 1716067.7 | AA36: 1681121.5 | AB36: 34946.156
A38: 33 | B38: OSANAIYE DAVID AKINYEMI | C38: 950209.06 | D38: 12 | E38: 11402509 | I38: 11402509 | J38: 200000 | K38: 0.2 | L38: 2280501.8 | M38: 2480501.8 | N38: 2480501.8 | O38: 8922007 | P38: 21000 | Q38: 33000 | R38: 75000 | S38: 95000 | T38: 336000 | U38: 1373281.7 | V38: 1933281.7 | W38: 12 | X38: 161106.81 | Z38: 161106.81 | AA38: 156349.82 | AB38: 4756.9869
A39: 34 | B39: JAMILA ABDUL | C39: 173329.05 | D39: 12 | E39: 2079948.6 | I39: 2079948.6 | J39: 200000 | K39: 0.2 | L39: 415989.72 | M39: 615989.72 | N39: 615989.72 | O39: 1463958.9 | P39: 21000 | Q39: 33000 | R39: 75000 | S39: 69152.186 | T39: 0 | V39: 198152.19 | W39: 12 | X39: 16512.682 | Z39: 16512.682 | AA39: 16512.68 | AB39: 0.0021906667
A42: 35 | B42: PROF. EDOBA BRIGHT OMOREGBE | C42: 1050209.1 | D42: 12 | E42: 12602509 | I42: 12602509 | J42: 200000 | K42: 0.2 | L42: 2520501.8 | M42: 2720501.8 | N42: 2720501.8 | O42: 9882007 | P42: 21000 | Q42: 33000 | R42: 75000 | S42: 95000 | T42: 336000 | U42: 1603681.7 | V42: 2163681.7 | W42: 12 | X42: 180306.81 | Z42: 180306.81 | AA42: 180306.81 | AB42: -0.0031413333
A43: 36 | B43: DR CLINTON JAJA | C43: 527553.5 | D43: 12 | E43: 6330642 | I43: 6330642 | J43: 200000 | K43: 0.2 | L43: 1266128.4 | M43: 1466128.4 | N43: 1466128.4 | O43: 4864513.6 | P43: 21000 | Q43: 33000 | R43: 75000 | S43: 95000 | T43: 336000 | U43: 399483.27 | V43: 959483.27 | W43: 12 | X43: 79956.939 | Z43: 79956.939 | AA43: 79956.94 | AB43: -0.00085333335
A44: 37 | B44: BETHEL UZOMA IHUGBA | C44: 527553.5 | D44: 12 | E44: 6330642 | I44: 6330642 | J44: 200000 | K44: 0.2 | L44: 1266128.4 | M44: 1466128.4 | N44: 1466128.4 | O44: 4864513.6 | P44: 21000 | Q44: 33000 | R44: 75000 | S44: 95000 | T44: 336000 | U44: 399483.27 | V44: 959483.27 | W44: 12 | X44: 79956.939 | Z44: 79956.939 | AA44: 79956.94 | AB44: -0.00085333335
A45: 38 | B45: OGUCHE SAMUEL | C45: 527553.5 | D45: 12 | E45: 6330642 | I45: 6330642 | J45: 200000 | K45: 0.2 | L45: 1266128.4 | M45: 1466128.4 | N45: 1466128.4 | O45: 4864513.6 | P45: 21000 | Q45: 33000 | R45: 75000 | S45: 95000 | T45: 336000 | U45: 399483.27 | V45: 959483.27 | W45: 12 | X45: 79956.939 | Z45: 79956.939 | AA45: 77764.98 | AB45: 2191.9591
A46: 39 | B46: IBRAHIM USMAN | C46: 476014.86 | D46: 12 | E46: 5712178.3 | I46: 5712178.3 | J46: 200000 | K46: 0.2 | L46: 1142435.7 | M46: 1342435.7 | N46: 1342435.7 | O46: 4369742.7 | P46: 21000 | Q46: 33000 | R46: 75000 | S46: 95000 | T46: 336000 | U46: 280738.24 | V46: 840738.24 | W46: 12 | X46: 70061.52 | Z46: 70061.52 | AA46: 75436.115 | AB46: -5374.5955
A47: 40 | B47: DR MOHAMMED O. AMALI | C47: 413333.04 | D47: 12 | E47: 4959996.4 | F47: 8546.54 | I47: 4951449.9 | J47: 200000 | K47: 0.2 | L47: 990289.98 | M47: 1190290 | N47: 1198836.5 | O47: 3761159.9 | P47: 21000 | Q47: 33000 | R47: 75000 | S47: 95000 | T47: 336000 | U47: 134678.38 | V47: 694678.38 | W47: 12 | X47: 57889.865 | Z47: 57889.865 | AA47: 56478.9 | AB47: 1410.9648
A48: 41 | B48: YAHAYA SHAMSU | C48: 413333.04 | D48: 12 | E48: 4959996.4 | I48: 4959996.4 | J48: 200000 | K48: 0.2 | L48: 991999.28 | M48: 1191999.3 | N48: 1191999.3 | O48: 3767997.1 | P48: 21000 | Q48: 33000 | R48: 75000 | S48: 95000 | T48: 336000 | U48: 136319.31 | V48: 696319.31 | W48: 12 | X48: 58026.609 | Z48: 58026.609 | AA48: 56478.9 | AB48: 1547.7094
A49: 42 | B49: OFORDEME ADAOBI JULIA | C49: 400272.06 | D49: 12 | E49: 4803264.8 | I49: 4803264.8 | J49: 200000 | K49: 0.2 | L49: 960652.95 | M49: 1160653 | N49: 1160653 | O49: 3642611.8 | P49: 21000 | Q49: 33000 | R49: 75000 | S49: 95000 | T49: 336000 | U49: 106226.83 | V49: 666226.83 | W49: 12 | X49: 55518.903 | Z49: 55518.903 | AA49: 54931.4 | AB49: 587.50272
A50: 43 | B50: DORIS DAKDA AARON | C50: 369177.65 | D50: 12 | E50: 4430131.8 | I50: 4430131.8 | J50: 200000 | K50: 0.2 | L50: 886026.37 | M50: 1086026.4 | N50: 1086026.4 | O50: 3344105.5 | P50: 21000 | Q50: 33000 | R50: 75000 | S50: 95000 | T50: 336000 | U50: 34585.314 | V50: 594585.31 | W50: 12 | X50: 49548.776 | Z50: 49548.776 | AA50: 48052.11 | AB50: 1496.6662
A51: 44 | B51: ZAINAB AKINDE | C51: 245204.08 | D51: 12 | E51: 2942449 | F51: 7422.38 | I51: 2935026.6 | J51: 200000 | K51: 0.2 | L51: 587005.33 | M51: 787005.33 | N51: 794427.71 | O51: 2148021.3 | P51: 21000 | Q51: 33000 | R51: 75000 | S51: 95000 | T51: 115084.47 | U51: 0 | V51: 339084.47 | W51: 12 | X51: 28360.953 | Z51: 28360.953 | AA51: 28360.95 | AB51: 0.0028626667
A52: 45 | B52: ABDULLAHI AHMAD USMAN | C52: 245204.08 | D52: 12 | E52: 2942449 | I52: 2942449 | J52: 200000 | K52: 0.2 | L52: 588489.8 | M52: 788489.8 | N52: 788489.8 | O52: 2153959.2 | P52: 21000 | Q52: 33000 | R52: 75000 | S52: 95000 | T52: 116331.43 | V52: 340331.43 | W52: 12 | X52: 28360.953 | Z52: 28360.953 | AA52: 28360.95 | AB52: 0.0028626667
A53: 46 | B53: GUNAT NANSAK MARK | C53: 245205.08 | D53: 12 | E53: 2942461 | I53: 2942461 | J53: 200000 | K53: 0.2 | L53: 588492.2 | M53: 788492.2 | N53: 788492.2 | O53: 2153968.8 | P53: 21000 | Q53: 33000 | R53: 75000 | S53: 95000 | T53: 116333.45 | V53: 340333.45 | W53: 12 | X53: 28360.953 | Z53: 28360.953 | AA53: 28360.95 | AB53: 0.0028626667
A56: 47 | B56: DR SHUIBU DANWANKA | C56: 1050209.1 | D56: 12 | E56: 12602509 | I56: 12602509 | J56: 200000 | K56: 0.2 | L56: 2520501.8 | M56: 2720501.8 | N56: 2720501.8 | O56: 9882007 | P56: 21000 | Q56: 33000 | R56: 75000 | S56: 95000 | T56: 336000 | U56: 1603681.7 | V56: 2163681.7 | W56: 12 | X56: 180306.81 | Z56: 180306.81 | AA56: 180306.81 | AB56: 0
A57: 48 | B57: ABDULSALAM BAKO | C57: 436137.05 | D57: 12 | E57: 5233644.6 | I57: 5233644.6 | J57: 200000 | K57: 0.2 | L57: 1046728.9 | M57: 1246728.9 | N57: 1246728.9 | O57: 3986915.7 | P57: 21000 | Q57: 33000 | R57: 75000 | S57: 95000 | T57: 336000 | U57: 188859.76 | V57: 748859.76 | W57: 12 | X57: 62404.98 | Z57: 62404.98
A60: 49 | B60: DR. ADEWALE ADEREMI | C60: 1050209.1 | D60: 12 | E60: 12602509 | I60: 12602509 | J60: 200000 | K60: 0.2 | L60: 2520501.8 | M60: 2720501.8 | N60: 2720501.8 | O60: 9882007 | P60: 21000 | Q60: 33000 | R60: 75000 | S60: 95000 | T60: 336000 | U60: 1603681.7 | V60: 2163681.7 | W60: 12 | X60: 180306.81 | Z60: 180306.81 | AA60: 180306.81 | AB60: -0.0031413333
A61: 50 | B61: NDANUSA MOHAMMED MANZUMA | C61: 504720.05 | D61: 12 | E61: 6056640.6 | I61: 6056640.6 | J61: 200000 | K61: 0.2 | L61: 1211328.1 | M61: 1411328.1 | N61: 1411328.1 | O61: 4645312.5 | P61: 21000 | Q61: 33000 | R61: 75000 | S61: 95000 | T61: 336000 | U61: 346874.99 | V61: 906874.99 | W61: 12 | X61: 75572.916 | Z61: 75572.916 | AA61: 75572.92 | AB61: -0.0043093333
A62: 51 | B62: EJALONIBU GANIYU LAYI | C62: 369177.65 | D62: 12 | E62: 4430131.8 | I62: 4430131.8 | J62: 200000 | K62: 0.2 | L62: 886026.37 | M62: 1086026.4 | N62: 1086026.4 | O62: 3344105.5 | P62: 21000 | Q62: 33000 | R62: 75000 | S62: 95000 | T62: 336000 | U62: 34585.314 | V62: 594585.31 | W62: 12 | X62: 49548.776 | Z62: 49548.776 | AA62: 48170.87 | AB62: 1377.9062
A63: 52 | B63: LOHNA BONKAT JONATHAN | C63: 362001.06 | D63: 12 | E63: 4344012.7 | I63: 4344012.7 | J63: 200000 | K63: 0.2 | L63: 868802.55 | M63: 1068802.5 | N63: 1068802.5 | O63: 3275210.2 | P63: 21000 | Q63: 33000 | R63: 75000 | S63: 95000 | T63: 336000 | U63: 18050.443 | V63: 578050.44 | W63: 12 | X63: 48170.87 | Z63: 48170.87 | AA63: 46673.26 | AB63: 1497.6103
A64: 53 | B64: YUNUSA ABDULLAHI | C64: 413333.04 | D64: 12 | E64: 4959996.4 | I64: 4959996.4 | J64: 200000 | K64: 0.2 | L64: 991999.28 | M64: 1191999.3 | N64: 1191999.3 | O64: 3767997.1 | P64: 21000 | Q64: 33000 | R64: 75000 | S64: 95000 | T64: 336000 | U64: 136319.31 | V64: 696319.31 | W64: 12 | X64: 58026.609 | Z64: 58026.609 | AA64: 56478.9 | AB64: 1547.7094
A65: 54 | B65: UDEFUNA NNADOZIE PATRICK | C65: 300564.02 | D65: 12 | E65: 3606768.2 | I65: 3606768.2 | J65: 200000 | K65: 0.2 | L65: 721353.64 | M65: 921353.64 | N65: 921353.64 | O65: 2685414.6 | P65: 21000 | Q65: 33000 | R65: 75000 | S65: 95000 | T65: 227937.06 | V65: 451937.06 | W65: 12 | X65: 37661.421 | Z65: 37661.421 | AA65: 36127.27 | AB65: 1534.1514
A66: 55 | B66: OSOLAFIA MUHAMMAD EGYE | C66: 334537 | D66: 12 | E66: 4014444 | F66: 6456.26 | I66: 4007987.7 | J66: 200000 | K66: 0.2 | L66: 801597.54 | M66: 1001597.5 | N66: 1008053.8 | O66: 3006390.2 | P66: 21000 | Q66: 33000 | R66: 75000 | S66: 95000 | T66: 295341.94 | V66: 519341.94 | W66: 12 | X66: 43278.495 | Z66: 43278.495 | AA66: 41248.56 | AB66: 2029.9348
A67: 56 | B67: SHAFIU YAHYA MIKAIL | C67: 315372.08 | D67: 12 | E67: 3784464.9 | I67: 3784464.9 | J67: 200000 | K67: 0.2 | L67: 756892.98 | M67: 956892.98 | N67: 956892.98 | O67: 2827571.9 | P67: 21000 | Q67: 33000 | R67: 75000 | S67: 95000 | T67: 257790.1 | V67: 481790.1 | W67: 12 | X67: 40149.175 | Z67: 40149.175 | AA67: 40149.18 | AB67: -0.0047333333
A68: 57 | B68: HASSAN YERIMA | C68: 315372.08 | D68: 12 | E68: 3784464.9 | I68: 3784464.9 | J68: 200000 | K68: 0.2 | L68: 756892.98 | M68: 956892.98 | N68: 956892.98 | O68: 2827571.9 | P68: 21000 | Q68: 33000 | R68: 75000 | S68: 95000 | T68: 257790.1 | V68: 481790.1 | W68: 12 | X68: 40149.175 | Z68: 40149.175 | AA68: 40149.18 | AB68: -0.0047333333
A69: 58 | B69: HAUWA PATE SADIQ | C69: 322454.07 | D69: 12 | E69: 3869448.9 | I69: 3869448.9 | J69: 200000 | K69: 0.2 | L69: 773889.78 | M69: 973889.78 | N69: 973889.78 | O69: 2895559.1 | P69: 21000 | Q69: 33000 | R69: 75000 | S69: 95000 | T69: 272067.41 | V69: 496067.41 | W69: 12 | X69: 41338.951 | Z69: 41338.951 | AA69: 41829.147 | AB69: -490.19603
A70: 59 | B70: ABAYOMI KAYODE QUADRI | C70: 273169.12 | D70: 12 | E70: 3278029.4 | I70: 3278029.4 | J70: 200000 | K70: 0.2 | L70: 655605.88 | M70: 855605.88 | N70: 855605.88 | O70: 2422423.5 | P70: 21000 | Q70: 33000 | R70: 75000 | S70: 95000 | T70: 172708.94 | V70: 396708.94 | W70: 12 | X70: 33059.078 | Z70: 33059.078 | AA70: 32291.82 | AB70: 767.25841
A71: 60 | B71: NNANDI LIVINUS ATURE | C71: 249356.05 | D71: 12 | E71: 2992272.6 | I71: 2992272.6 | J71: 200000 | K71: 0.2 | L71: 598454.51 | M71: 798454.51 | N71: 798454.51 | O71: 2193818.1 | P71: 21000 | Q71: 33000 | R71: 75000 | S71: 95000 | T71: 124701.79 | V71: 348701.79 | W71: 12 | X71: 29058.483 | Z71: 29058.483 | AA71: 24685.95 | AB71: 4372.5326
A72: 61 | B72: LUCKY AGWOM | C72: 226816.1 | D72: 12 | E72: 2721793.2 | I72: 2721793.2 | J72: 200000 | K72: 0.2 | L72: 544358.64 | M72: 744358.64 | N72: 744358.64 | O72: 1977434.6 | P72: 21000 | Q72: 33000 | R72: 75000 | S72: 95000 | T72: 79261.258 | V72: 303261.26 | W72: 12 | X72: 25271.771 | Z72: 25271.771 | AA72: 24685.95 | AB72: 585.82147
A75: 62 | B75: DR ASIMIYU G. ABIOLA | C75: 1050209.1 | D75: 12 | E75: 12602509 | I75: 12602509 | J75: 200000 | K75: 0.2 | L75: 2520501.8 | M75: 2720501.8 | N75: 2720501.8 | O75: 9882007 | P75: 21000 | Q75: 33000 | R75: 75000 | S75: 95000 | T75: 336000 | U75: 1603681.7 | V75: 2163681.7 | W75: 12 | X75: 180306.81 | Z75: 180306.81 | AA75: 180306.81 | AB75: -0.0031413333
A76: 63 | B76: USMAN WALI | C76: 504720.05 | D76: 12 | E76: 6056640.6 | I76: 6056640.6 | J76: 200000 | K76: 0.2 | L76: 1211328.1 | M76: 1411328.1 | N76: 1411328.1 | O76: 4645312.5 | P76: 21000 | Q76: 33000 | R76: 75000 | S76: 95000 | T76: 336000 | U76: 346874.99 | V76: 906874.99 | W76: 12 | X76: 75572.916 | Z76: 75572.916 | AA76: 75572.92 | AB76: -0.0043093333
A77: 64 | B77: MOSHOOD TOSHO AMUDA | C77: 504720.05 | D77: 12 | E77: 6056640.6 | I77: 6056640.6 | J77: 200000 | K77: 0.2 | L77: 1211328.1 | M77: 1411328.1 | N77: 1411328.1 | O77: 4645312.5 | P77: 21000 | Q77: 33000 | R77: 75000 | S77: 95000 | T77: 336000 | U77: 346874.99 | V77: 906874.99 | W77: 12 | X77: 75572.916 | Z77: 75572.916 | AA77: 75572.92 | AB77: -0.0043093333
A78: 65 | B78: ANTHONY EDET | C78: 369177.65 | D78: 12 | E78: 4430131.8 | I78: 4430131.8 | J78: 200000 | K78: 0.2 | L78: 886026.37 | M78: 1086026.4 | N78: 1086026.4 | O78: 3344105.5 | P78: 21000 | Q78: 33000 | R78: 75000 | S78: 95000 | T78: 336000 | U78: 34585.314 | V78: 594585.31 | W78: 12 | X78: 49548.776 | Z78: 49548.776 | AA78: 48170.87 | AB78: 1377.9062
B79: IGWE STACY | C79: 273169.12 | D79: 12 | E79: 3278029.4 | I79: 3278029.4 | J79: 200000 | K79: 0.2 | L79: 655605.88 | M79: 855605.88 | N79: 855605.88 | O79: 2422423.5 | P79: 21000 | Q79: 33000 | R79: 75000 | S79: 95000 | T79: 172708.94 | U79: 0 | V79: 396708.94 | W79: 12 | X79: 33059.078 | Z79: 33059.078 | AA79: 32291.82 | AB79: 767.25841
A82: 66 | B82: ASEMOTA OMOROGBE JOSEPH | C82: 631465.02 | D82: 12 | E82: 7577580.3 | I82: 7577580.3 | J82: 200000 | K82: 0.2 | L82: 1515516.1 | M82: 1715516.1 | N82: 1715516.1 | O82: 5862064.2 | P82: 21000 | Q82: 33000 | R82: 75000 | S82: 95000 | T82: 336000 | U82: 638895.42 | V82: 1198895.4 | W82: 12 | X82: 99907.951 | Z82: 99907.951 | AA82: 97273.51 | AB82: 2634.4414
A83: 67 | B83: TERFA WILLIAMS ABRAHAM | C83: 527553.5 | D83: 12 | E83: 6330642 | I83: 6330642 | J83: 200000 | K83: 0.2 | L83: 1266128.4 | M83: 1466128.4 | N83: 1466128.4 | O83: 4864513.6 | P83: 21000 | Q83: 33000 | R83: 75000 | S83: 95000 | T83: 336000 | U83: 399483.27 | V83: 959483.27 | W83: 12 | X83: 79956.939 | Z83: 79956.939 | AA83: 79956.94 | AB83: -0.00085333335
A84: 68 | B84: DR AUGUSTINE C. OSIGWE | C84: 527553.5 | D84: 12 | E84: 6330642 | F84: 10052.25 | I84: 6320589.8 | J84: 200000 | K84: 0.2 | L84: 1264118 | M84: 1464118 | N84: 1474170.2 | O84: 4856471.8 | P84: 21000 | Q84: 33000 | R84: 75000 | S84: 95000 | T84: 336000 | U84: 397553.24 | V84: 957553.24 | W84: 12 | X84: 79796.103 | Z84: 79796.103 | AA84: 79796.1 | AB84: 0.0031466666
A85: 69 | B85: NGARA CHRISTOPHER OCHANJA | C85: 421394.01 | D85: 12 | E85: 5056728.1 | F85: 8283.37 | I85: 5048444.7 | J85: 200000 | K85: 0.2 | L85: 1009688.9 | M85: 1209688.9 | N85: 1217972.3 | O85: 3838755.8 | P85: 21000 | Q85: 33000 | R85: 75000 | S85: 95000 | T85: 336000 | U85: 153301.38 | V85: 713301.38 | W85: 12 | X85: 59441.782 | Z85: 59441.782 | AA85: 57894.08 | AB85: 1547.702
A86: 70 | B86: OMOJU OLUWASOLA EMMANUEL | C86: 413333.04 | D86: 12 | E86: 4959996.4 | I86: 4959996.4 | J86: 200000 | K86: 0.2 | L86: 991999.28 | M86: 1191999.3 | N86: 1191999.3 | O86: 3767997.1 | P86: 21000 | Q86: 33000 | R86: 75000 | S86: 95000 | T86: 336000 | U86: 136319.31 | V86: 696319.31 | W86: 12 | X86: 58026.609 | Z86: 58026.609 | AA86: 56478.9 | AB86: 1547.7094
A87: 71 | B87: IBE EZECHI CYRIACUS | C87: 369177.65 | D87: 12 | E87: 4430131.8 | I87: 4430131.8 | J87: 200000 | K87: 0.2 | L87: 886026.37 | M87: 1086026.4 | N87: 1086026.4 | O87: 3344105.5 | P87: 21000 | Q87: 33000 | R87: 75000 | S87: 95000 | T87: 336000 | U87: 34585.314 | V87: 594585.31 | W87: 12 | X87: 49548.776 | Z87: 49548.776 | AA87: 48170.87 | AB87: 1377.9062
A88: 72 | B88: OSIKHEN LEO IGBANOI | C88: 362001.06 | D88: 12 | E88: 4344012.7 | I88: 4344012.7 | J88: 200000 | K88: 0.2 | L88: 868802.55 | M88: 1068802.5 | N88: 1068802.5 | O88: 3275210.2 | P88: 21000 | Q88: 33000 | R88: 75000 | S88: 95000 | T88: 336000 | U88: 18050.443 | V88: 578050.44 | W88: 12 | X88: 48170.87 | Z88: 48170.87 | AA88: 46673.26 | AB88: 1497.6103
A89: 73 | B89: OKUNGBOWA OSARETIN GODSPOWER | C89: 362001.06 | D89: 12 | E89: 4344012.7 | I89: 4344012.7 | J89: 200000 | K89: 0.2 | L89: 868802.55 | M89: 1068802.5 | N89: 1068802.5 | O89: 3275210.2 | P89: 21000 | Q89: 33000 | R89: 75000 | S89: 95000 | T89: 336000 | U89: 18050.443 | V89: 578050.44 | W89: 12 | X89: 48170.87 | Z89: 48170.87 | AA89: 46673.26 | AB89: 1497.6103
A90: 74 | B90: YUSUF IBRAHIM | C90: 315372.08 | D90: 12 | E90: 3784464.9 | I90: 3784464.9 | J90: 200000 | K90: 0.2 | L90: 756892.98 | M90: 956892.98 | N90: 956892.98 | O90: 2827571.9 | P90: 21000 | Q90: 33000 | R90: 75000 | S90: 95000 | T90: 257790.1 | U90: 0 | V90: 481790.1 | W90: 12 | X90: 40149.175 | Z90: 40149.175 | AA90: 40149.18 | AB90: -0.0047333333
A91: 75 | B91: MARYAM MUSA SADA | C91: 0 | D91: 12 | E91: 0 | I91: 0 | J91: 200000 | K91: 0.2 | L91: 0 | M91: 200000 | N91: 200000 | O91: 0 | P91: 0 | Q91: 0 | R91: 0 | S91: 0 | T91: 0 | V91: 0 | W91: 12 | X91: 0 | Z91: 0 | AA91: 0 | AB91: 0
A92: 76 | B92: CHARITY EZENWAJIOBI | C92: 223709.11 | D92: 12 | E92: 2684509.3 | I92: 2684509.3 | J92: 200000 | K92: 0.2 | L92: 536901.86 | M92: 736901.86 | N92: 736901.86 | O92: 1947607.5 | P92: 21000 | Q92: 33000 | R92: 75000 | S92: 95000 | T92: 72997.565 | V92: 296997.56 | W92: 12 | X92: 24749.797 | Z92: 24749.797 | AA92: 24685.95 | AB92: 63.847063
A96: 78 | B96: REKIYA IBRAHIM ATTAH | C96: 527744 | D96: 12 | E96: 6332927.9 | I96: 6332927.9 | J96: 200000 | K96: 0.2 | L96: 1266585.6 | M96: 1466585.6 | N96: 1466585.6 | O96: 4866342.4 | P96: 21000 | Q96: 33000 | R96: 75000 | S96: 95000 | T96: 336000 | U96: 399922.17 | V96: 959922.17 | W96: 12 | X96: 79993.514 | Z96: 79993.514 | AA96: 79993.51 | AB96: 0.0038506667
A97: 79 | B97: DR FRANCIS NDUM OJIE | C97: 343333.04 | D97: 12 | E97: 4119996.4 | F97: 8019.8 | I97: 4111976.6 | J97: 200000 | K97: 0.2 | L97: 822395.32 | M97: 1022395.3 | N97: 1030415.1 | O97: 3089581.3 | P97: 21000 | Q97: 33000 | R97: 75000 | S97: 95000 | T97: 312812.07 | V97: 536812.07 | W97: 12 | X97: 44734.339 | Z97: 44734.339 | AA97: 43380.1 | AB97: 1354.2394
A98: 80 | B98: ABUBAKAR MOHAMMED BASHIR | C98: 312001.06 | D98: 12 | E98: 3744012.7 | I98: 3744012.7 | J98: 200000 | K98: 0.2 | L98: 748802.55 | M98: 948802.55 | N98: 948802.55 | O98: 2795210.2 | P98: 21000 | Q98: 33000 | R98: 75000 | S98: 95000 | T98: 250994.14 | V98: 474994.14 | W98: 12 | X98: 39582.845 | Z98: 39582.845 | AA98: 38272.44 | AB98: 1310.4048
A99: 81 | B99: OKECHUKWU UCHENNA HULDA | C99: 267454.07 | D99: 12 | E99: 3209448.9 | I99: 3209448.9 | J99: 200000 | K99: 0.2 | L99: 641889.78 | M99: 841889.78 | N99: 841889.78 | O99: 2367559.1 | P99: 21000 | Q99: 33000 | R99: 75000 | S99: 95000 | T99: 161187.41 | V99: 385187.41 | W99: 12 | X99: 32098.951 | Z99: 32098.951 | AA99: 31749.137 | AB99: 349.81426
A102: 83 | B102: DR MAIMUNA IZAH | C102: 1050209.1 | D102: 12 | E102: 12602509 | F102: 10052.25 | I102: 12592457 | J102: 200000 | K102: 0.2 | L102: 2518491.3 | M102: 2718491.3 | N102: 2728543.6 | O102: 9873965.2 | P102: 21000 | Q102: 33000 | R102: 75000 | S102: 95000 | T102: 336000 | U102: 1601751.7 | V102: 2161751.7 | W102: 12 | X102: 180145.97 | Z102: 180145.97 | AA102: 180306.81 | AB102: -160.83914
A103: 84 | B103: CATHERINE E. IKOKOH | C103: 617744 | D103: 12 | E103: 7412927.9 | F103: 7901.79 | I103: 7405026.2 | J103: 200000 | K103: 0.2 | L103: 1481005.2 | M103: 1681005.2 | N103: 1688907 | O103: 5724020.9 | P103: 21000 | Q103: 33000 | R103: 75000 | S103: 95000 | T103: 336000 | U103: 605765.02 | V103: 1165765 | W103: 12 | X103: 97147.085 | Z103: 97147.085 | AA103: 94478.374 | AB103: 2668.7113
A104: 85 | B104: ALIYU SANNI ABUBAKAR | C104: 418096.02 | D104: 12 | E104: 5017152.2 | I104: 5017152.2 | J104: 200000 | K104: 0.2 | L104: 1003430.4 | M104: 1203430.4 | N104: 1203430.4 | O104: 3813721.8 | P104: 21000 | Q104: 33000 | R104: 75000 | S104: 95000 | T104: 336000 | U104: 147293.22 | V104: 707293.22 | W104: 12 | X104: 58941.102 | Z104: 58941.102 | AA104: 58814.67 | AB104: 126.43174
A105: 86 | B105: CHINAKO N. ASOGWA | C105: 416483.19 | D105: 12 | E105: 4997798.3 | I105: 4997798.3 | J105: 200000 | K105: 0.2 | L105: 999559.67 | M105: 1199559.7 | N105: 1199559.7 | O105: 3798238.7 | P105: 21000 | Q105: 33000 | R105: 75000 | S105: 95000 | T105: 336000 | U105: 143577.28 | V105: 703577.28 | W105: 12 | X105: 58631.44 | Z105: 58631.44 | AA105: 57194.24 | AB105: 1437.1999
A106: 87 | B106: AMOS ABA | C106: 262612.72 | D106: 12 | E106: 3151352.6 | I106: 3151352.6 | J106: 200000 | K106: 0.2 | L106: 630270.52 | M106: 830270.52 | N106: 830270.52 | O106: 2321082.1 | P106: 21000 | Q106: 33000 | R106: 75000 | S106: 95000 | T106: 151427.24 | V106: 375427.24 | W106: 12 | X106: 31285.603 | Z106: 31285.603 | AA106: 30699.58 | AB106: 586.0232
A107: 88 | B107: TITILAYO DANIEL MARVELLOUS | C107: 258740.8 | D107: 12 | E107: 3104889.6 | I107: 3104889.6 | J107: 200000 | K107: 0.2 | L107: 620977.91 | M107: 820977.91 | N107: 820977.91 | O107: 2283911.7 | P107: 21000 | Q107: 33000 | R107: 75000 | S107: 95000 | T107: 143621.45 | V107: 367621.45 | W107: 12 | X107: 30635.121 | Z107: 30635.121 | AA107: 30049.31 | AB107: 585.81069
A108: 89 | B108: ENENCHE JEREMIAH AGADA | C108: 251382.3 | D108: 12 | E108: 3016587.5 | I108: 2992065.5 | J108: 200000 | K108: 0.2 | L108: 598413.11 | M108: 798413.11 | N108: 822935.12 | O108: 2193652.4 | P108: 21000 | Q108: 33000 | R108: 75000 | S108: 95000 | T108: 124667.01 | U108: 0 | V108: 348667.01 | W108: 12 | X108: 29055.584 | Z108: 29055.584 | AA108: 28813.07 | AB108: 242.51416
O109: 0 | P109: 0 | T109: 0
O110: 0 | P110: 0 | T110: 0
B111: IBRAHIM M. MSHELIA | C111: 1050209.1 | D111: 12 | E111: 12602509 | F111: 24522.01 | I111: 12577987 | J111: 200000 | K111: 0.2 | L111: 2515597.4 | M111: 2715597.4 | N111: 2740119.4 | O111: 9862389.4 | P111: 21000 | Q111: 33000 | R111: 75000 | S111: 95000 | T111: 336000 | U111: 1598973.5 | V111: 2158973.5 | W111: 12 | X111: 179914.45 | Z111: 179914.45 | AA111: 179914.45 | AB111: 0.0046986667
A112: 90 | B112: KABIR MUHAMMAD SULAIMAN | C112: 641465.02 | D112: 12 | E112: 7697580.3 | I112: 7697580.3 | J112: 200000 | K112: 0.2 | L112: 1539516.1 | M112: 1739516.1 | N112: 1739516.1 | O112: 5958064.2 | P112: 21000 | Q112: 33000 | R112: 75000 | S112: 95000 | T112: 336000 | U112: 661935.42 | V112: 1221935.4 | W112: 12 | X112: 101827.95 | Z112: 101827.95 | AA112: 101827.95 | AB112: 0.0014186667
A113: 91 | B113: RAHILA NURUDEEN HABU | C113: 547553.5 | D113: 12 | E113: 6570642 | F113: 10052.25 | I113: 6560589.8 | J113: 200000 | K113: 0.2 | L113: 1312118 | M113: 1512118 | N113: 1522170.2 | O113: 5048471.8 | P113: 21000 | Q113: 33000 | R113: 75000 | S113: 95000 | T113: 336000 | U113: 443633.24 | V113: 1003633.2 | W113: 12 | X113: 83636.103 | Z113: 83636.103 | AA113: 83636.1 | AB113: 0.0031466666
A114: 92 | B114: TONDO IORWUESE EDWARD | C114: 447553.5 | D114: 12 | E114: 5370642 | F114: 10052.25 | I114: 5360589.8 | J114: 200000 | K114: 0.2 | L114: 1072118 | M114: 1272118 | N114: 1282170.2 | O114: 4088471.8 | P114: 21000 | Q114: 33000 | R114: 75000 | S114: 95000 | T114: 336000 | U114: 213233.24 | V114: 773233.24 | W114: 12 | X114: 64436.103 | Z114: 64436.103 | AA114: 64436.1 | AB114: 0.0031466667
A115: 93 | B115: ARAOYE GANIYAT TITILOLA | C115: 424720.05 | D115: 12 | E115: 5096640.6 | I115: 5096640.6 | J115: 200000 | K115: 0.2 | L115: 1019328.1 | M115: 1219328.1 | N115: 1219328.1 | O115: 3877312.5 | P115: 21000 | Q115: 33000 | R115: 75000 | S115: 95000 | T115: 336000 | U115: 162554.99 | V115: 722554.99 | W115: 12 | X115: 60212.916 | Z115: 60212.916 | AA115: 60212.92 | AB115: -0.0043093333
A116: 94 | B116: SHEHU ABDULLAHI | C116: 330272.06 | D116: 12 | E116: 3963264.8 | I116: 3963264.8 | J116: 200000 | K116: 0.2 | L116: 792652.95 | M116: 992652.95 | N116: 992652.95 | O116: 2970611.8 | P116: 21000 | Q116: 33000 | R116: 75000 | S116: 95000 | T116: 287828.48 | V116: 511828.48 | W116: 12 | X116: 42652.373 | Z116: 42652.373 | AA116: 42138.224 | AB116: 514.14888
...

Sheet Tax adj August, 2022
B3: STAFF PAYROLL FOR THE MONTH OF AUGUST 2022
B5: STAFF NAME
C6: DESIGNATION | D6: SALARY
D7: LEVEL | E7: JULY 2022 PAYE | F7: AUGUST 2022 PAYE | G7: DIFFERENCE
A8: S/N | B8: DG'S OFFICE | E8: N | F8: N | G8: N
A9: 1 | B9: PROF. ABUBAKAR O. SULAIMAN | C9: DIRECTOR GENERAL | D9: CONSOL | E9: 113176.97 | F9: =201165.84 -> 201165.84 | G9: =F9-E9 -> 87988.87
A10: 2 | B10: DR ADEYEMI AKEEB FAJINGBESI | C10: DIR. SPECIAL DUTIES, DG OFFICE | D10: 17(9) | E10: 52776.63 | F10: =0 -> 0 | G10: =F10-E10 -> -52776.63
A11: 3 | B11: DR JAKE DABANG DAN AZUMI | C11: DEPUTY DIRECTOR TRAINING | D11: 16(8) | E11: 21618.09 | F11: =125875.96 -> 125875.96 | G11: =F11-E11 -> 104257.87
A12: 4 | B12: DR ABDULSALAM NASIRU NAEEM | C12: SA ACADEMICS | D12: 16(8) | E12: 21618.09 | F12: =116473.51 -> 116473.51 | G12: =F12-E12 -> 94855.42
A13: 5 | B13: RAHEEM USMAN AYIGORO | C13: SA-INFRASTRUCTURE | D13: 16 (8) | E13: 21618.09 | F13: =79993.51 -> 79993.51 | G13: =F13-E13 -> 58375.42
A14: 6 | B14: MARIAM MOHAMMED BELLO | C14: SA- SPECIAL DUTIES | D14: 15 (7) | E14: 21618.09 | F14: =107095.69 -> 107095.69 | G14: =F14-E14 -> 85477.6
A15: 7 | B15: AKINSANMI ADEJOKE OLUKEMI | C15: HEAD INFORMATION/PROTOCOL | D15: 15(9) | E15: 15548.33 | F15: =83636.1 -> 83636.1 | G15: =F15-E15 -> 68087.77
A16: 8 | B16: DR IKEME ARTHUR J.O | C16: SNR RESEARCH FELLOW | D16: 15(9) | E16: 15548.33 | F16: =64436.1 -> 64436.1 | G16: =F16-E16 -> 48887.77
A17: 9 | B17: MOSHOOD M. OLALERE | C17: MANAGER ADMIN DG's OFFICE | D17: 15(9) | E17: 15548.33 | F17: =64436.1 -> 64436.1 | G17: =F17-E17 -> 48887.77
A18: 10 | B18: ANDRAWUS MUSA | C18: ASST. DIRECTOR, STORE | D18: 15(9) | E18: 15548.33 | F18: =64436.1 -> 64436.1 | G18: =F18-E18 -> 48887.77
A19: 11 | B19: AYOBOLU OLAJIDE OLUFUNSHO | C19: ASST.DIR., INFORMATION | D19: 15 (7) | E19: 15548.33 | F19: =60212.92 -> 60212.92 | G19: =F19-E19 -> 44664.59
A20: 12 | B20: HUSSEIN EGYE MUSA | C20: CHIEF PROTOCOL OFFICER | D20: 14(9) | E20: 7709.76 | F20: =52638.9 -> 52638.9 | G20: =F20-E20 -> 44929.14
A21: 13 | B21: DONALD E. MKPANAM | C21: CHIEF ICT OFFICER | D21: 14(9) | E21: 7709.76 | F21: =43380 -> 43380 | G21: =F21-E21 -> 35670.24
A22: 14 | B22: JOY HARUNA MAKERI | C22: RESEARCH FELLOW 1 TRAINING | D22: 14(9) | E22: 7709.76 | F22: =85278.9 -> 85278.9 | G22: =F22-E22 -> 77569.14
A23: 15 | B23: ALI ABDULLAHI | C23: ASST. CHIEF ICT OFFICER | D23: 13(11) | E23: 7709.76 | F23: =42046.06 -> 42046.06 | G23: =F23-E23 -> 34336.3
A24: 16 | B24: ANTHONY EDET | C24: ASST. MGR M&E | D24: 13(9) | E24: 7709.76 | F24: =39478.93 -> 39478.93 | G24: =F24-E24 -> 31769.17
A25: 17 | B25: PERCY TERFA GBAHABO | C25: HEAD, NILDS LIAISON OFFICE | D25: 13(8) | E25: 7709.76 | F25: =46673.26 -> 46673.26 | G25: =F25-E25 -> 38963.5
A26: 18 | B26: HASSANA AHMED IBRAHIM | C26: PA- TO DG | D26: 13 (7) | E26: 7709.76 | F26: =63364.81 -> 63364.81 | G26: =F26-E26 -> 55655.05
A27: 19 | B27: CHRISTIAN MADUABUCHI ODO | C27: PRINCIPAL ICT OFFICER | D27: 12(8) | E27: 3369.51 | F27: =31848.56 -> 31848.56 | G27: =F27-E27 -> 28479.05
A28: 20 | B28: ADUGBA RICHARD TERSEER | C28: INFORMATION OFFICER | D28: 10(10) | E28: 3369.51 | F28: =27873.08 -> 27873.08 | G28: =F28-E28 -> 24503.57
A29: 21 | B29: EGUATU U. ONYEJELEM | C29: OFFICER M&E | D29: 10(10) | E29: 3369.51 | F29: =27873.08 -> 27873.08 | G29: =F29-E29 -> 24503.57
A30: 22 | B30: ODEH SUZIE | C30: ADMIN. OFFICER, LIASION OFFICE | D30: 10(9) | E30: 3369.51 | F30: =27105.99 -> 27105.99 | G30: =F30-E30 -> 23736.48
A31: 23 | B31: YAKUB OLUWATOYIN USMAN | C31: ASST. ADMIN. OFFICER | D31: 10(8) | E31: 1484.37 | F31: =26339.08 -> 26339.08 | G31: =F31-E31 -> 24854.71
A32: 24 | B32: ELIZABETH OGECHUKWU ONYEAKU | C32: ICT OFFICER | D32: 9(7) | E32: 3369.51 | F32: =21640.95 -> 21640.95 | G32: =F32-E32 -> 18271.44
A33: 25 | B33: VICTOR ASUKWO | C33: ICT OFFICER | D33: 8 (10) | E33: 1484.37 | F33: =18102.9 -> 18102.9 | G33: =F33-E33 -> 16618.53
A34: 26 | B34: IJEOMA NKOLIKWA | C34: ASSISTANT STORES OFFICER | D34: 8(10) | E34: 1484.37 | F34: =18102.9 -> 18102.9 | G34: =F34-E34 -> 16618.53
A35: 27 | B35: ABDULRAHMAN A SULAIMAN | C35: ASSISTANT STORES OFFICER | D35: 8 (9) | E35: 1484.37 | F35: =17572.89 -> 17572.89 | G35: =F35-E35 -> 16088.52
A36: 28 | B36: TASSNEEM IBRAHIM | C36: ASSIST. INFORMATION | D36: 8(9) | E36: 1484.37 | F36: =17572.89 -> 17572.89 | G36: =F36-E36 -> 16088.52
A37: 29 | B37: DARE SHEU MAGBON | C37: ASSIST. PG | D37: 8(9) | E37: 1484.37 | F37: =17572.89 -> 17572.89 | G37: =F37-E37 -> 16088.52
A38: 30 | B38: JIMOH ADEBAYO ZAKA | C38: ASST. OFFICER/COMM | D38: 8(7) | E38: 1484.37 | F38: =16512.68 -> 16512.68 | G38: =F38-E38 -> 15028.31
A39: 31 | B39: HABEEBA K MUHAMMAD SALIHU | C39: ASST. OFFICER/COMM | D39: 8(7) | E39: 1484.37 | F39: =16512.68 -> 16512.68 | G39: =F39-E39 -> 15028.31
A40: 32 | B40: MOHAMMED BELLO | C40: RESEARCH ASSITANT PG | D40: 8(7) | E40: 1484.37 | F40: =16512.68 -> 16512.68 | G40: =F40-E40 -> 15028.31
A41: 33 | B41: SULEIMAN ABUBAKAR SODEEQ | C41: ASST. ADMIN. OFFICER | D41: 8(7) | E41: 1484.37 | F41: =16512.68 -> 16512.68 | G41: =F41-E41 -> 15028.31
A42: 34 | B42: HARUNA JIBRIL A. | C42: ASST. ADMIN. OFFICER | D42: 8(7) | E42: 0 | F42: =16512.68 -> 16512.68 | G42: =F42-E42 -> 16512.68
B43: TOTAL | C43: 33 | E43: =SUM(E9:E42) -> 415827.18 | F43: =SUM(F9:F41) -> 1658278.6 | G43: =F43-E43 -> 1242451.4
G44: =F44-E44 -> 0
B45: INTERNAL AUDIT | G45: =F45-E45 -> 0
A46: 1 | B46: OSANAIYE DAVID AKINYEMI | C46: DIRECTOR INTERNAL AUDIT | D46: 17(8) | E46: 52776.63 | F46: =156349.82 -> 156349.82 | G46: =F46-E46 -> 103573.19
A47: 2 | B47: JAMILA ABDUL | C47: AUDITOR II | D47: 8(7) | E47: 1484.37 | F47: =16512.68 -> 16512.68 | G47: =F47-E47 -> 15028.31
C48: 2 | E48: 54261 | F48: =SUM(F46:F47) -> 172862.5 | G48: =F48-E48 -> 118601.5
G49: =F49-E49 -> 0
B50: LEG. SUPPORT SEVICES | G50: =F50-E50 -> 0
A51: 1 | B51: PROF. EDOBA BRIGHT OMOREGBE | C51: AG. DLSS | D51: 17(9) | E51: 52776.63 | F51: =180306.81 -> 180306.81 | G51: =F51-E51 -> 127530.18
A52: 2 | B52: DR CLINTON JAJA | C52: SENIOR RESEARCH FELLOW | D52: 15(9) | E52: 15548.33 | F52: =79956.94 -> 79956.94 | G52: =F52-E52 -> 64408.61
A53: 3 | B53: BETHEL UZOMA IHUGBA | C53: SNR RESEARCH FELLOW | D53: 15(9) | E53: 15548.33 | F53: =79956.94 -> 79956.94 | G53: =F53-E53 -> 64408.61
A54: 4 | B54: OGUCHE SAMUEL | C54: SNR RESEARCH FELLOW | D54: 15(8) | E54: 15548.33 | F54: =77764.98 -> 77764.98 | G54: =F54-E54 -> 62216.65
A55: 5 | B55: IBRAHIM USMAN | C55: RESEARCH FELLOW I | D55: 14(11) | E55: 7709.76 | F55: =59437.57 -> 59437.57 | G55: =F55-E55 -> 51727.81
A56: 6 | B56: DR MOHAMMED O. AMALI | C56: RESEARCH FELLOW I | D56: 14(9) | E56: 7709.76 | F56: =56478.9 -> 56478.9 | G56: =F56-E56 -> 48769.14
A57: 7 | B57: YAHAYA SHAMSU | C57: RESEARCH FELLOW 1 | D57: 14(9) | E57: 7709.76 | F57: =56478.9 -> 56478.9 | G57: =F57-E57 -> 48769.14
A58: 8 | B58: OFORDEME ADAOBI JULIA | C58: RESEARCH FELLOW 11 | D58: 13(10) | E58: 7709.76 | F58: =49548.78 -> 49548.78 | G58: =F58-E58 -> 41839.02
A59: 9 | B59: DORIS DAKDA AARON | C59: RESEARCH FELLOW II | D59: 13(9) | E59: 7709.76 | F59: =48052.11 -> 48052.11 | G59: =F59-E59 -> 40342.35
A60: 10 | B60: ZAINAB AKINDE | C60: RESEARCH OFFICER | D60: 9(7) | E60: 3369.51 | F60: =28360.95 -> 28360.95 | G60: =F60-E60 -> 24991.44
A61: 11 | B61: ABDULLAHI AHMAD USMAN | C61: RESEARCH OFFICER | D61: 9(7) | E61: 3369.51 | F61: =28360.95 -> 28360.95 | G61: =F61-E61 -> 24991.44
A62: 12 | B62: GUNAT NANSAK MARK | C62: RESEARCH OFFICER | D62: 9(7) | E62: 0 | F62: =28360.95*23/31 -> 21041.995 | G62: =F62-E62 -> 21041.995
B63: TOTAL | C63: 11 | E63: =SUM(E51:E62) -> 144709.44 | F63: =SUM(F51:F62) -> 765745.83 | G63: =SUM(G51:G62) -> 621036.39
G64: =F64-E64 -> 0
B65: LEGAL SERVICES | G65: =F65-E65 -> 0
A66: 1 | B66: DR SHUIBU DANWANKA | C66: DIRECTOR LEGAL SERVICES | D66: 17(9) | E66: 52776.63 | F66: =180306.81 -> 180306.81 | G66: =F66-E66 -> 127530.18
A67: 2 | B67: ABDULSALAM BAKO | C67: MANAGER, LEGAL SERVICES | D67: 15 (8) | E67: 15548.33 | F67: =62404.98 -> 62404.98 | G67: =F67-E67 -> 46856.65
B68: TOTAL | C68: 2 | E68: 68324.96 | F68: =SUM(F66:F67) -> 242711.79 | G68: =F68-E68 -> 174386.83
G69: =F69-E69 -> 0
B70: DEMOCRACY AND GOVERNANCE | G70: =F70-E70 -> 0
A71: 1 | B71: DR. ADEWALE ADEREMI | C71: DIRECTOR, DEMOCRATIC STUDIES | D71: 17(9) | E71: 52776.63 | F71: =180306.81 -> 180306.81 | G71: =F71-E71 -> 127530.18
A72: 2 | B72: NDANUSA MOHAMMED MANZUMA | C72: SNR RESEARCH FELLOW | D72: 15 (7) | E72: 15548.33 | F72: 75572.92 | G72: =F72-E72 -> 60024.59
A73: 3 | B73: EJALONIBU GANIYU LAYI | C73: RESEARCH FELLOW 11 | D73: 13(9) | E73: 7709.76 | F73: =48170.87 -> 48170.87 | G73: =F73-E73 -> 40461.11
A74: 4 | B74: LOHNA BONKAT JONATHAN | C74: RESEARCH FELLOW 11 | D74: 13(8) | E74: 7709.76 | F74: =46673.26 -> 46673.26 | G74: =F74-E74 -> 38963.5
A75: 5 | B75: YUNUSA ABDULLAHI | C75: RESEARCH FELLOW 1 | D75: 14(9) | E75: 7709.76 | F75: 56478.9 | G75: =F75-E75 -> 48769.14
A76: 6 | B76: UDEFUNA NNADOZIE PATRICK | C76: RESEARCH OFFICER | D76: 10(13) | E76: 3369.51 | F76: 36127.27 | G76: =F76-E76 -> 32757.76
A77: 7 | B77: OSOLAFIA MUHAMMAD EGYE | C77: PRINCIPAL RESEARCH OFFICER | D77: 12(8) | E77: 3369.51 | F77: 41248.56 | G77: =F77-E77 -> 37879.05
A78: 8 | B78: SHAFIU YAHYA MIKAIL | C78: PRINCIPAL RESEARCH OFFICER | D78: 12(7) | E78: 3369.51 | F78: =40149.18 -> 40149.18 | G78: =F78-E78 -> 36779.67
A79: 9 | B79: HASSAN YERIMA | C79: PRINCIPAL RESEARCH OFFICER | D79: 12(7) | E79: 3369.51 | F79: =40149.18 -> 40149.18 | G79: =F79-E79 -> 36779.67
A80: 10 | B80: HAUWA PATE SADIQ | C80: PROGRAMME OFFICER | D80: 10(10) | E80: 3369.51 | F80: =34593.08 -> 34593.08 | G80: =F80-E80 -> 31223.57
A81: 11 | B81: ABAYOMI KAYODE QUADRI | C81: RESEARCH OFFICER | D81: 10(7) | E81: 3369.51 | F81: =32291.82 -> 32291.82 | G81: =F81-E81 -> 28922.31
A82: 12 | B82: NNANDI LIVINUS ATURE | C82: RESEARCH ASSISTANT | D82: 9(7) | E82: 1484.37 | F82: =24685.95 -> 24685.95 | G82: =F82-E82 -> 23201.58
A83: 13 | B83: LUCKY AGWOM | C83: RESEARCH ASSISTANT | D83: 8(7) | E83: 1484.37 | F83: =24685.95 -> 24685.95 | G83: =F83-E83 -> 23201.58
B84: TOTAL | C84: 13 | E84: 114640.04 | F84: =SUM(F71:F83) -> 681133.75 | G84: =F84-E84 -> 566493.71
G85: =F85-E85 -> 0
B86: STUDIES | G86: =F86-E86 -> 0
A87: 1 | B87: DR ASIMIYU G. ABIOLA | C87: DIRECTOR POST GRADUATE | D87: 17(9) | E87: 52776.63 | F87: =180306.81 -> 180306.81 | G87: =F87-E87 -> 127530.18
A88: 2 | B88: USMAN WALI | C88: SENIOR RESEARCH FELLOW | D88: 15 (7) | E88: 15548.33 | F88: =75572.92 -> 75572.92 | G88: =F88-E88 -> 60024.59
A89: 3 | B89: MOSHOOD TOSHO AMUDA | C89: MANAGER, EXAMS & RECORDS | D89: 15 (7) | E89: 15548.33 | F89: =75572.92 -> 75572.92 | G89: =F89-E89 -> 60024.59
A90: 4 | B90: IGWE STACY | C90: PROGRAMME OFFICER | D90: 10(7) | E90: 3369.51 | F90: =32291.82 -> 32291.82 | G90: =F90-E90 -> 28922.31
B91: TOTAL | C91: 4 | E91: 87242.8 | F91: =SUM(F87:F90) -> 363744.47 | G91: =F91-E91 -> 276501.67
G92: =F92-E92 -> 0
B93: ECONOMIC DEV. AND SOCIAL RESEARCH | G93: =F93-E93 -> 0
A94: 1 | B94: DR ASEMOTA OMOROGBE JOSEPH | C94: Ag. DEPUTY DIRECTOR, ECO & SOC DEV DEPT | D94: 16(8) | E94: 21618.09 | F94: =97273.51 -> 97273.51 | G94: =F94-E94 -> 75655.42
A95: 2 | B95: TERFA WILLIAMS ABRAHAM | C95: SNR RESEARCH FELLOW | D95: 15(9) | E95: 15548.33 | F95: =79956.94 -> 79956.94 | G95: =F95-E95 -> 64408.61
A96: 3 | B96: DR AUGUSTINE C. OSIGWE | C96: SNR RESEARCH FELLOW | D96: 15(9) | E96: 15548.33 | F96: =79796.1 -> 79796.1 | G96: =F96-E96 -> 64247.77
A97: 4 | B97: NGARA CHRISTOPHER OCHANJA | C97: RESEARCH FELLOW 1 | D97: 14(10) | E97: 7709.76 | F97: =57894.08 -> 57894.08 | G97: =F97-E97 -> 50184.32
A98: 5 | B98: OMOJU OLUWASOLA EMMANUEL | C98: RESEARCH FELLOW I | D98: 14(9) | E98: 7709.76 | F98: =56478.9 -> 56478.9 | G98: =F98-E98 -> 48769.14
A99: 6 | B99: FESTUS OSAGU NDIDI | C99: RESEARCH FELLOW I | D99: 14(7) | E99: 7709.76 | F99: =53384.05 -> 53384.05 | G99: =F99-E99 -> 45674.29
A100: 7 | B100: IBE EZECHI CYRIACUS | C100: RESEARCH FELLOW II | D100: 13(9) | E100: 7709.76 | F100: =48170.87 -> 48170.87 | G100: =F100-E100 -> 40461.11
A101: 8 | B101: OSIKHEN LEO IGBANOI | C101: RESEARCH FELLOW 11 | D101: 13(8) | E101: 7709.76 | F101: =46673.26 -> 46673.26 | G101: =F101-E101 -> 38963.5
A102: 9 | B102: OKUNGBOWA OSARETIN GODSPOWER | C102: RESEARCH FELLOW 11 | D102: 13(8) | E102: 7709.76 | F102: =46673.26 -> 46673.26 | G102: =F102-E102 -> 38963.5
A103: 10 | B103: YUSUF IBRAHIM | C103: PRINCIPAL RESEARCH OFFICER | D103: 12(7) | E103: 3369.51 | F103: =40149.18 -> 40149.18 | G103: =F103-E103 -> 36779.67
...

Sheet Annual Increement
B3: STAFF PAYROLL FOR THE MONTH OF DECEMBER, 2021
F4: ='[1]FEB 08'!E8/'[1]FEB 08'!M8 -> 0.22 | I4: ='[1]FEB 08'!F8/'[1]FEB 08'!Q8 -> 0.3
B5: STAFF NAME
D6: DESIGNATION | E6: SALARY | F6: BASIC | M6: MOTOR/ | N6: RESEARCH | O6: HARDSHIP | P6: LEAVE | Q6: OUT FIT | R6: LEGISLATIVE | S6: NEW GROSS | T6: OLD GROSS | U6: DIFFERENCE
E7: LEVEL | F7: SALARY | G7: SALARY/ALLOWCE AREARS | H7: RENT | I7: UTILITY | J7: DOMESTIC | K7: ENTERT. | L7: FURNIT. | M7: FUEL | N7: ALLOWANCE | O7: ALLOWANCE | P7: ALLCE | Q7: ALLCE | R7: DUTY ALLCE | S7: SALARY | T7: SALARY | W7: OLD PAYE | X7: NEW PAYE | Y7: DIFFERENCE
A8: S/N | B8: DG OFFICE | F8: N | I8: N | S8: N | T8: N | U8: N | W8: N | X8: N | Y8: N
A9: 1 | B9: PROF. ABUBAKAR O. SULAIMAN | D9: DIRECTOR GENERAL | E9: CONSOL | F9: 160488.75 | H9: 320977.5 | I9: 48146.63 | J9: 120366.57 | K9: 72219.94 | L9: 0 | M9: 120366.57 | N9: =250000 -> 250000 | P9: 16048.88 | Q9: 25000 | R9: 25235 | S9: =R9+Q9+P9+O9+N9+M9+L9+K9+J9+I9+H9+G9+F9 -> 1158849.8 | T9: 1158849.8 | U9: =S9-T9 -> 0 | W9: 113176.97 | X9: 113176.97 | Y9: =X9-W9 -> 0
A10: 2 | B10: DR ADEYEMI AKEEB FAJINGBESI | D10: DIR. SPECIAL DUTIES, DG OFFICE | E10: 17(9) | F10: 81740.02 | H10: =F10*300% -> 245220.06 | I10: =F10*7.5% -> 6130.5015 | J10: 80244.38 | K10: =F10*50% -> 40870.01 | L10: =F10*350% -> 286090.07 | M10: =F10*100% -> 81740.02 | N10: =200000 -> 200000 | P10: =F10*10% -> 8174.002 | Q10: 20000 | R10: 0 | S10: =R10+Q10+P10+O10+N10+M10+L10+K10+J10+I10+H10+G10+F10 -> 1050209.1 | T10: 1050209.1 | U10: =S10-T10 -> 0 | W10: 52776.63 | X10: 52776.63 | Y10: =X10-W10 -> 0
A11: 3 | B11: SARAFADEEN ALABELEWE | D11: SA- ADMIN | E11: 16(9) | F11: =42653.17 -> 42653.17 | H11: =F11*300% -> 127959.51 | I11: =F11*7.5% -> 3198.9877 | J11: 40122.19 | K11: =F11*50% -> 21326.585 | L11: =F11*350% -> 149286.1 | M11: =F11*100% -> 42653.17 | O11: =90000 -> 90000 | P11: =F11*10% -> 4265.317 | Q11: 20000 | S11: =R11+Q11+P11+O11+N11+M11+L11+K11+J11+I11+H11+G11+F11 -> 541465.02 | T11: 541465.02 | U11: =S11-T11 -> 0 | W11: 21618.09 | X11: 21618.09 | Y11: =X11-W11 -> 0
A12: 4 | B12: DR JAKE DABANG DAN AZUMI | D12: DEPUTY DIRECTOR TRAINING | E12: 16(8) | F12: =41157.69 -> 41157.69 | H12: =F12*300% -> 123473.07 | I12: =F12*7.5% -> 3086.8268 | J12: 40122.19 | K12: =F12*50% -> 20578.845 | L12: =F12*350% -> 144051.92 | M12: =F12*100% -> 41157.69 | N12: =180000 -> 180000 | P12: =F12*10% -> 4115.769 | Q12: 20000 | R12: 150000 | S12: =R12+Q12+P12+O12+N12+M12+L12+K12+J12+I12+H12+G12+F12 -> 767744 | T12: 754023.33 | U12: =S12-T12 -> 13720.662 | W12: =21618.09 -> 21618.09 | X12: 21618.09 | Y12: =X12-W12 -> 0
A13: 5 | B13: DR ABDULSALAM NASIRU NAEEM | D13: SA ACADEMICS | E13: 16(8) | F13: =41157.69 -> 41157.69 | H13: =F13*300% -> 123473.07 | I13: =F13*7.5% -> 3086.8268 | J13: 40122.19 | K13: =F13*50% -> 20578.845 | L13: =F13*350% -> 144051.92 | M13: =F13*100% -> 41157.69 | N13: =180000 -> 180000 | P13: =F13*10% -> 4115.769 | Q13: 20000 | R13: =100000 -> 100000 | S13: =R13+Q13+P13+O13+N13+M13+L13+K13+J13+I13+H13+G13+F13 -> 717744 | T13: 704023.33 | U13: =S13-T13 -> 13720.662 | W13: =21618.09 -> 21618.09 | X13: 21618.09 | Y13: =X13-W13 -> 0
A14: 6 | B14: RAHEEM USMAN AYIGORO | D14: SA-INFRASTRUCTURE | E14: 16 (8) | F14: =41157.69 -> 41157.69 | H14: =F14*300% -> 123473.07 | I14: =F14*7.5% -> 3086.8268 | J14: 40122.19 | K14: =F14*50% -> 20578.845 | L14: =F14*350% -> 144051.92 | M14: =F14*100% -> 41157.69 | O14: =90000 -> 90000 | P14: =F14*10% -> 4115.769 | Q14: 20000 | R14: 0 | S14: =R14+Q14+P14+O14+N14+M14+L14+K14+J14+I14+H14+G14+F14 -> 527744 | T14: 514023.33 | U14: =S14-T14 -> 13720.662 | W14: =21618.09 -> 21618.09 | X14: 21618.09 | Y14: =X14-W14 -> 0
A15: 7 | B15: AKINSANMI ADEJOKE OLUKEMI | D15: HEAD INFORMATION/PROTOCOL | E15: 15(9) | F15: 33507.5 | H15: =F15*300% -> 100522.5 | I15: =F15*7.5% -> 2513.0625 | J15: 40122.19 | K15: =F15*50% -> 16753.75 | L15: =F15*350% -> 117276.25 | M15: =F15*100% -> 33507.5 | O15: =80000 -> 80000 | P15: =F15*10% -> 3350.75 | Q15: 20000 | R15: =100000 -> 100000 | S15: =R15+Q15+P15+O15+N15+M15+L15+K15+J15+I15+H15+G15+F15 -> 547553.5 | T15: 547553.5 | U15: =S15-T15 -> 0 | W15: 15548.33 | X15: 15548.33 | Y15: =X15-W15 -> 0
A16: 8 | B16: DR IKEME ARTHUR J.O | D16: SNR RESEARCH FELLOW | E16: 15(9) | F16: =33507.5 -> 33507.5 | H16: =F16*300% -> 100522.5 | I16: =F16*7.5% -> 2513.0625 | J16: 40122.19 | K16: =F16*50% -> 16753.75 | L16: =F16*350% -> 117276.25 | M16: =F16*100% -> 33507.5 | O16: =80000 -> 80000 | P16: =F16*10% -> 3350.75 | Q16: 20000 | R16: 0 | S16: =R16+Q16+P16+O16+N16+M16+L16+K16+J16+I16+H16+G16+F16 -> 447553.5 | T16: 447553.5 | U16: =S16-T16 -> 0 | W16: 15548.33 | X16: 15548.33 | Y16: =X16-W16 -> 0
A17: 9 | B17: MOSHOOD M. OLALERE | D17: MANAGER ADMIN DG's OFFICE | E17: 15(9) | F17: =33507.5 -> 33507.5 | H17: =F17*300% -> 100522.5 | I17: =F17*7.5% -> 2513.0625 | J17: 40122.19 | K17: =F17*50% -> 16753.75 | L17: =F17*350% -> 117276.25 | M17: =F17*100% -> 33507.5 | O17: =80000 -> 80000 | P17: =F17*10% -> 3350.75 | Q17: 20000 | R17: 0 | S17: =R17+Q17+P17+O17+N17+M17+L17+K17+J17+I17+H17+G17+F17 -> 447553.5 | T17: 447553.5 | U17: =S17-T17 -> 0 | W17: 15548.33 | X17: 15548.33 | Y17: =X17-W17 -> 0
A18: 10 | B18: ANDRAWUS MUSA | D18: ASST. DIRECTOR, STORE | E18: 15(9) | F18: =33507.5 -> 33507.5 | H18: =F18*300% -> 100522.5 | I18: =F18*7.5% -> 2513.0625 | J18: =40122.19 -> 40122.19 | K18: =F18*50% -> 16753.75 | L18: =F18*350% -> 117276.25 | M18: =F18*100% -> 33507.5 | O18: =80000 -> 80000 | P18: =F18*10% -> 3350.75 | Q18: 20000 | R18: 0 | S18: =SUM(F18:R18) -> 447553.5 | T18: 436137.05 | U18: =S18-T18 -> 11416.452 | W18: =15548.33 -> 15548.33 | X18: 15548.33 | Y18: =X18-W18 -> 0
A19: 11 | B19: AYOBOLU OLAJIDE OLUFUNSHO | D19: ASST.DIR., INFORMATION | E19: 15 (7) | F19: 31018.84 | H19: =F19*300% -> 93056.52 | I19: =F19*7.5% -> 2326.413 | J19: 40122.19 | K19: =F19*50% -> 15509.42 | L19: =F19*350% -> 108565.94 | M19: =F19*100% -> 31018.84 | O19: =80000 -> 80000 | P19: =F19*10% -> 3101.884 | Q19: 20000 | R19: 0 | S19: =R19+Q19+P19+O19+N19+M19+L19+K19+J19+I19+H19+G19+F19 -> 424720.05 | T19: 424720.05 | U19: =S19-T19 -> 0 | W19: 15548.33 | X19: 15548.33 | Y19: =X19-W19 -> 0
A20: 12 | B20: HUSSEIN EGYE MUSA | D20: CHIEF PROTOCOL OFFICER | E20: 14(9) | F20: =26732.65 -> 26732.65 | H20: =F20*300% -> 80197.95 | I20: =F20*7.5% -> 2004.9488 | K20: =F20*50% -> 13366.325 | L20: =F20*350% -> 93564.275 | M20: =F20*100% -> 26732.65 | O20: =70000 -> 70000 | P20: =F20*10% -> 2673.265 | Q20: 20000 | R20: 50000 | S20: =R20+Q20+P20+O20+N20+M20+L20+K20+J20+I20+H20+G20+F20 -> 385272.06 | T20: 377211.37 | U20: =S20-T20 -> 8060.6963 | W20: 7709.76 | X20: 7709.76 | Y20: =X20-W20 -> 0
A21: 13 | B21: DONALD E. MKPANAM | D21: CHIEF ICT OFFICER | E21: 14(9) | F21: =26732.65 -> 26732.65 | H21: =F21*300% -> 80197.95 | I21: =F21*7.5% -> 2004.9488 | K21: =F21*50% -> 13366.325 | L21: =F21*350% -> 93564.275 | M21: =F21*100% -> 26732.65 | O21: =70000 -> 70000 | P21: =F21*10% -> 2673.265 | Q21: 20000 | R21: 0 | S21: =R21+Q21+P21+O21+N21+M21+L21+K21+J21+I21+H21+G21+F21 -> 335272.06 | T21: 327211.37 | U21: =S21-T21 -> 8060.6963 | W21: 7709.76 | X21: 7709.76 | Y21: =X21-W21 -> 0
A22: 14 | B22: JOY HARUNA MAKERI | D22: RESEARCH FELLOW 1 TRAINING | E22: 14(9) | F22: =26732.65 -> 26732.65 | H22: =F22*300% -> 80197.95 | I22: =F22*7.5% -> 2004.9488 | K22: =F22*50% -> 13366.325 | L22: =F22*350% -> 93564.275 | M22: =F22*100% -> 26732.65 | N22: =140000 -> 140000 | P22: =F22*10% -> 2673.265 | Q22: 20000 | R22: =50000+100000 -> 150000 | S22: =R22+Q22+P22+O22+N22+M22+L22+K22+J22+I22+H22+G22+F22 -> 555272.06 | T22: 547211.37 | U22: =S22-T22 -> 8060.6963 | W22: =7709.76 -> 7709.76 | X22: 7709.76 | Y22: =X22-W22 -> 0
A23: 15 | B23: ALI ABDULLAHI | D23: ASST. CHIEF ICT OFFICER | E23: 13(11) | F23: =26339.3 -> 26339.3 | H23: =F23*300% -> 79017.9 | I23: =F23*7.5% -> 1975.4475 | J23: 0 | K23: =F23*50% -> 13169.65 | L23: =F23*350% -> 92187.55 | M23: =F23*100% -> 26339.3 | O23: =70000 -> 70000 | P23: =F23*10% -> 2633.93 | Q23: 15000 | R23: =0 -> 0 | S23: =R23+Q23+P23+O23+N23+M23+L23+K23+J23+I23+H23+G23+F23 -> 326663.08 | T23: 326663.08 | U23: =S23-T23 -> 0 | W23: =7709.76 -> 7709.76 | X23: 7709.76 | Y23: =X23-W23 -> 0
A24: 16 | B24: MARIAM MOHAMMED BELLO | D24: PA- SPECIAL DUTIES | E24: 13 (7) | F24: =23074.99 -> 23074.99 | H24: =F24*300% -> 69224.97 | I24: =F24*7.5% -> 1730.6243 | J24: =265272 -> 265272 | K24: =F24*50% -> 11537.495 | L24: =F24*350% -> 80762.465 | M24: =F24*100% -> 23074.99 | O24: =70000 -> 70000 | P24: =F24*10% -> 2307.499 | Q24: 15000 | R24: =100000+100000 -> 200000 | S24: =R24+Q24+P24+O24+N24+M24+L24+K24+J24+I24+H24+G24+F24 -> 761985.03 | T24: 761985.03 | U24: =S24-T24 -> 0 | W24: =7709.76 -> 7709.76 | X24: 7709.76 | Y24: =X24-W24 -> 0
A25: 17 | B25: PERCY TERFA GBAHABO | D25: HEAD, NILDS LIAISON OFFICE | E25: 13(8) | F25: =23891.12 -> 23891.12 | H25: =F25*300% -> 71673.36 | I25: =F25*7.5% -> 1791.834 | J25: 0 | K25: =F25*50% -> 11945.56 | L25: =F25*350% -> 83618.92 | M25: =F25*100% -> 23891.12 | N25: =120000 -> 120000 | P25: =F25*10% -> 2389.112 | Q25: 15000 | R25: 0 | S25: =R25+Q25+P25+O25+N25+M25+L25+K25+J25+I25+H25+G25+F25 -> 354201.03 | T25: 346713.03 | U25: =S25-T25 -> 7487.9928 | W25: =7709.76 -> 7709.76 | X25: 7709.76 | Y25: =X25-W25 -> 0
A26: 18 | B26: ADUGBA RICHARD TERSEER | D26: INFORMATION OFFICER | E26: 10(10) | F26: =18779.3 -> 18779.3 | H26: =F26*300% -> 56337.9 | I26: =F26*7.5% -> 1408.4475 | K26: =F26*50% -> 9389.65 | L26: =F26*350% -> 65727.55 | M26: =F26*100% -> 18779.3 | O26: =60000 -> 60000 | P26: =F26*10% -> 1877.93 | Q26: 10000 | S26: =R26+Q26+P26+O26+N26+M26+L26+K26+J26+I26+H26+G26+F26 -> 242300.08 | T26: 237734.05 | U26: =S26-T26 -> 4566.0305 | W26: 3369.51 | X26: 3369.51 | Y26: =X26-W26 -> 0
A27: 19 | B27: CHRISTIAN MADUABUCHI ODO | D27: PRINCIPAL ICT OFFICER | E27: 12(8) | F27: =21520.88 -> 21520.88 | H27: =F27*300% -> 64562.64 | I27: =F27*7.5% -> 1614.066 | K27: =F27*50% -> 10760.44 | L27: =F27*350% -> 75323.08 | M27: =F27*100% -> 21520.88 | O27: =60000 -> 60000 | P27: =F27*10% -> 2152.088 | Q27: 15000 | S27: =R27+Q27+P27+O27+N27+M27+L27+K27+J27+I27+H27+G27+F27 -> 272454.07 | T27: 265372.07 | U27: =S27-T27 -> 7081.999 | W27: 3369.51 | X27: 3369.51 | Y27: =X27-W27 -> 0
A28: 20 | B28: HASSANA AHMED IBRAHIM | D28: PA- TO DG | E28: 10(9) | F28: =18281.64 -> 18281.64 | H28: =F28*300% -> 54844.92 | I28: =F28*7.5% -> 1371.123 | K28: =F28*50% -> 9140.82 | L28: =F28*350% -> 63985.74 | M28: =F28*100% -> 18281.64 | N28: =100000 -> 100000 | P28: =F28*10% -> 1828.164 | Q28: 10000 | R28: =100000 -> 100000 | S28: =R28+Q28+P28+O28+N28+M28+L28+K28+J28+I28+H28+G28+F28 -> 377734.05 | T28: 373168.2 | U28: =S28-T28 -> 4565.847 | W28: 3369.51 | X28: 3369.51 | Y28: =X28-W28 -> 0
A29: 21 | B29: VICTOR ASUKWO | D29: ICT OFFICER | E29: 8 (10) | F29: =13492.21 -> 13492.21 | H29: =F29*300% -> 40476.63 | I29: =F29*7.5% -> 1011.9157 | K29: =F29*50% -> 6746.105 | L29: =F29*350% -> 47222.735 | M29: =F29*100% -> 13492.21 | O29: =50000 -> 50000 | P29: =F29*10% -> 1349.221 | Q29: 10000 | S29: =R29+Q29+P29+O29+N29+M29+L29+K29+J29+I29+H29+G29+F29 -> 183791.03 | T29: 180304.07 | U29: =S29-T29 -> 3486.9587 | W29: 1484.37 | X29: 1484.37 | Y29: =X29-W29 -> 0
A30: 22 | B30: SULEIMAN ABUBAKAR SODEEQ | D30: ASST. ADMIN. OFFICER | E30: 8(7) | F30: =12351.94 -> 12351.94 | H30: =F30*300% -> 37055.82 | I30: =F30*7.5% -> 926.3955 | K30: =F30*50% -> 6175.97 | L30: =F30*350% -> 43231.79 | M30: =F30*100% -> 12351.94 | O30: =50000 -> 50000 | P30: =F30*10% -> 1235.194 | Q30: 10000 | S30: =R30+Q30+P30+O30+N30+M30+L30+K30+J30+I30+H30+G30+F30 -> 173329.05 | T30: 173329.05 | U30: =S30-T30 -> 0 | W30: =1484.37 -> 1484.37 | X30: 1484.37 | Y30: =X30-W30 -> 0
A31: 23 | B31: YAKUB OLUWATOYIN USMAN | D31: ASST. ADMIN. OFFICER | E31: 10(8) | F31: =17784.1 -> 17784.1 | H31: =F31*300% -> 53352.3 | I31: =F31*7.5% -> 1333.8075 | K31: =F31*50% -> 8892.05 | L31: =F31*350% -> 62244.35 | M31: =F31*100% -> 17784.1 | O31: =60000 -> 60000 | P31: =F31*10% -> 1778.41 | Q31: 10000 | S31: =R31+Q31+P31+O31+N31+M31+L31+K31+J31+I31+H31+G31+F31 -> 233169.12 | T31: 228602.08 | U31: =S31-T31 -> 4567.0397 | W31: =1484.37 -> 1484.37 | X31: 1484.37 | Y31: =X31-W31 -> 0
A32: 24 | B32: ANTHONY EDET | D32: ASST. MGR M&E | E32: 13(9) | F32: =24741.26 -> 24741.26 | H32: =F32*300% -> 74223.78 | I32: =F32*7.5% -> 1855.5945 | J32: 0 | K32: =F32*50% -> 12370.63 | L32: =F32*350% -> 86594.41 | M32: =F32*100% -> 24741.26 | O32: =70000 -> 70000 | P32: =F32*10% -> 2474.126 | Q32: 15000 | R32: 0 | S32: =R32+Q32+P32+O32+N32+M32+L32+K32+J32+I32+H32+G32+F32 -> 312001.06 | T32: 304201.03 | U32: =S32-T32 -> 7800.0345 | W32: =7709.76 -> 7709.76 | X32: 7709.76 | Y32: =X32-W32 -> 0
A33: 25 | B33: EGUATU U. ONYEJELEM | D33: OFFICER M&E | E33: 10(10) | F33: =18779.3 -> 18779.3 | H33: =F33*300% -> 56337.9 | I33: =F33*7.5% -> 1408.4475 | K33: =F33*50% -> 9389.65 | L33: =F33*350% -> 65727.55 | M33: =F33*100% -> 18779.3 | O33: =60000 -> 60000 | P33: =F33*10% -> 1877.93 | Q33: 10000 | S33: =R33+Q33+P33+O33+N33+M33+L33+K33+J33+I33+H33+G33+F33 -> 242300.08 | T33: 237734.05 | U33: =S33-T33 -> 4566.0305 | W33: 3369.51 | X33: 3369.51 | Y33: =X33-W33 -> 0
A34: 26 | B34: ODEH SUZIE | D34: ADMIN. OFFICER, LIASION OFFICE | E34: 10(9) | F34: =18281.64 -> 18281.64 | H34: =F34*300% -> 54844.92 | I34: =F34*7.5% -> 1371.123 | K34: =F34*50% -> 9140.82 | L34: =F34*350% -> 63985.74 | M34: =F34*100% -> 18281.64 | O34: 60000 | P34: =F34*10% -> 1828.164 | Q34: 10000 | S34: =R34+Q34+P34+O34+N34+M34+L34+K34+J34+I34+H34+G34+F34 -> 237734.05 | T34: 233168.2 | U34: =S34-T34 -> 4565.847 | W34: 3369.51 | X34: 3369.51 | Y34: =X34-W34 -> 0
A35: 27 | B35: IJEOMA NKOLIKWA | D35: ASSISTANT STORES OFFICER | E35: 8(10) | F35: =13492.21 -> 13492.21 | H35: =F35*300% -> 40476.63 | I35: =F35*7.5% -> 1011.9157 | K35: =F35*50% -> 6746.105 | L35: =F35*350% -> 47222.735 | M35: =F35*100% -> 13492.21 | O35: =50000 -> 50000 | P35: =F35*10% -> 1349.221 | Q35: 10000 | S35: =SUM(F35:R35) -> 183791.03 | T35: 180304.07 | U35: =S35-T35 -> 3486.9587 | W35: 1484.37 | X35: 1484.37 | Y35: =X35-W35 -> 0
A36: 28 | B36: ABDULRAHMAN A SULAIMAN | D36: ASSISTANT STORES OFFICER | E36: 8 (9) | F36: =13112.16 -> 13112.16 | H36: =F36*300% -> 39336.48 | I36: =F36*7.5% -> 983.412 | K36: =F36*50% -> 6556.08 | L36: =F36*350% -> 45892.56 | M36: =F36*100% -> 13112.16 | O36: =50000 -> 50000 | P36: =F36*10% -> 1311.216 | Q36: 10000 | S36: =SUM(F36:R36) -> 180304.07 | T36: 176816.1 | U36: =S36-T36 -> 3487.968 | W36: =(1484.37) -> 1484.37 | X36: 1484.37 | Y36: =X36-W36 -> 0
A37: 29 | B37: TASSNEEM IBRAHIM | D37: ASSIST. INFORMATION | E37: 8(9) | F37: =13112.16 -> 13112.16 | H37: =F37*300% -> 39336.48 | I37: =F37*7.5% -> 983.412 | K37: =F37*50% -> 6556.08 | L37: =F37*350% -> 45892.56 | M37: =F37*100% -> 13112.16 | O37: =50000 -> 50000 | P37: =F37*10% -> 1311.216 | Q37: 10000 | S37: =R37+Q37+P37+O37+N37+M37+L37+K37+J37+I37+H37+G37+F37 -> 180304.07 | T37: 176816.1 | U37: =S37-T37 -> 3487.968 | W37: =1484.37 -> 1484.37 | X37: 1484.37 | Y37: =X37-W37 -> 0
A38: 30 | B38: JIMOH ADEBAYO ZAKA | D38: ASST. OFFICER/COMM | E38: 8(7) | F38: =12351.94 -> 12351.94 | H38: =F38*300% -> 37055.82 | I38: =F38*7.5% -> 926.3955 | K38: =F38*50% -> 6175.97 | L38: =F38*350% -> 43231.79 | M38: =F38*100% -> 12351.94 | O38: =50000 -> 50000 | P38: =F38*10% -> 1235.194 | Q38: 10000 | S38: =R38+Q38+P38+O38+N38+M38+L38+K38+J38+I38+H38+G38+F38 -> 173329.05 | T38: 173329.05 | U38: =S38-T38 -> 0 | W38: =1484.37 -> 1484.37 | X38: 1484.37 | Y38: =X38-W38 -> 0
B39: TOTAL | D39: 30 | F39: =SUM(F9:F38) -> 942987.95 | G39: =SUM(G9:G38) -> 0 | H39: =SUM(H9:H38) -> 2668475.1 | I39: =SUM(I9:I38) -> 106834.07 | J39: =SUM(J9:J38) -> 826982.66 | K39: =SUM(K9:K38) -> 463469.54 | L39: =SUM(L9:L38) -> 2738747.2 | M39: =SUM(M9:M38) -> 902865.77 | ... S39: =SUM(S9:S38) -> 12789896 | T39: 12388713 | U39: =SUM(U9:U38) -> 135911.2 | W39: =SUM(W9:W38) -> 411374.07 | X39: 411374.07 | Y39: =X39-W39 -> 0
U40: =S40-T40 -> 0 | Y40: =X40-W40 -> 0
B41: INTERNAL AUDIT | U41: =S41-T41 -> 0 | Y41: =X41-W41 -> 0
A42: 1 | B42: OSANAIYE DAVID AKINYEMI | D42: DIRECTOR INTERNAL AUDIT | E42: 17(8) | F42: =79039.64 -> 79039.64 | H42: =F42*300% -> 237118.92 | I42: =F42*7.5% -> 5927.973 | J42: 80244.38 | K42: =F42*50% -> 39519.82 | L42: =F42*350% -> 276638.74 | M42: =F42*100% -> 79039.64 | O42: =100000 -> 100000 | P42: =F42*10% -> 7903.964 | Q42: 20000 | S42: =SUM(F42:R42) -> 925433.08 | T42: 900657.46 | U42: =S42-T42 -> 24775.619 | W42: =(52776.63) -> 52776.63 | X42: 52776.63 | Y42: =X42-W42 -> 0
C43: TOTAL | D43: 1 | F43: =SUM(F42:F42) -> 79039.64 | G43: =SUM(G42:G42) -> 0 | H43: =SUM(H42:H42) -> 237118.92 | I43: =SUM(I42:I42) -> 5927.973 | J43: =SUM(J42:J42) -> 80244.38 | K43: =SUM(K42:K42) -> 39519.82 | L43: =SUM(L42:L42) -> 276638.74 | M43: =SUM(M42:M42) -> 79039.64 | O43: =SUM(O42:O42) -> 100000 | P43: =SUM(P42:P42) -> 7903.964 | Q43: =SUM(Q42:Q42) -> 20000 | R43: =SUM(R42:R42) -> 0 | S43: =SUM(S42:S42) -> 925433.08 | T43: 900657.46 | U43: =S43-T43 -> 24775.619 | W43: =SUM(W42:W42) -> 52776.63 | X43: 52776.63 | Y43: =X43-W43 -> 0
U44: =S44-T44 -> 0 | Y44: =X44-W44 -> 0
B45: LEG. SUPPORT SEVICES | U45: =S45-T45 -> 0 | Y45: =X45-W45 -> 0
A46: 1 | B46: PROF. EDOBA BRIGHT OMOREGBE | D46: AG. DLSS | E46: 17(9) | F46: =81740.02 -> 81740.02 | H46: =F46*300% -> 245220.06 | I46: =F46*7.5% -> 6130.5015 | J46: 80244.38 | K46: =F46*50% -> 40870.01 | L46: =F46*350% -> 286090.07 | M46: =F46*100% -> 81740.02 | N46: =200000 -> 200000 | P46: =F46*10% -> 8174.002 | Q46: 20000 | S46: =SUM(F46:R46) -> 1050209.1 | T46: 1050209.1 | U46: =S46-T46 -> 0 | W46: =52776.63 -> 52776.63 | X46: 52776.63 | Y46: =X46-W46 -> 0
A47: 2 | B47: DR CLINTON JAJA | D47: SENIOR RESEARCH FELLOW | E47: 15(9) | F47: =33507.5 -> 33507.5 | H47: =F47*300% -> 100522.5 | I47: =F47*7.5% -> 2513.0625 | J47: 40122.19 | K47: =F47*50% -> 16753.75 | L47: =F47*350% -> 117276.25 | M47: =F47*100% -> 33507.5 | N47: =160000 -> 160000 | P47: =F47*10% -> 3350.75 | Q47: 20000 | R47: 0 | S47: =SUM(F47:R47) -> 527553.5 | T47: 527553.5 | U47: =S47-T47 -> 0 | W47: 15548.33 | X47: 15548.33 | Y47: =X47-W47 -> 0
A48: 3 | B48: BETHEL UZOMA IHUGBA | D48: SNR RESEARCH FELLOW | E48: 15(9) | F48: =33507.5 -> 33507.5 | H48: =F48*300% -> 100522.5 | I48: =F48*7.5% -> 2513.0625 | J48: 40122.19 | K48: =F48*50% -> 16753.75 | L48: =F48*350% -> 117276.25 | M48: =F48*100% -> 33507.5 | N48: =160000 -> 160000 | P48: =F48*10% -> 3350.75 | Q48: 20000 | S48: =SUM(F48:R48) -> 527553.5 | T48: 527553.5 | U48: =S48-T48 -> 0 | W48: 15548.33 | X48: 15548.33 | Y48: =X48-W48 -> 0
A49: 4 | B49: OGUCHE SAMUEL | D49: SNR RESEARCH FELLOW | E49: 15(8) | F49: =32263.2 -> 32263.2 | H49: =F49*300% -> 96789.6 | I49: =F49*7.5% -> 2419.74 | J49: 40122.19 | K49: =F49*50% -> 16131.6 | L49: =F49*350% -> 112921.2 | M49: =F49*100% -> 32263.2 | N49: =160000 -> 160000 | P49: =F49*10% -> 3226.32 | Q49: 20000 | S49: =SUM(F49:R49) -> 516137.05 | T49: 504720.05 | U49: =S49-T49 -> 11417.003 | W49: =15548.33 -> 15548.33 | X49: 15548.33 | Y49: =X49-W49 -> 0
A50: 5 | B50: IBRAHIM USMAN | D50: RESEARCH FELLOW I | E50: 14(11) | F50: =28489.81 -> 28489.81 | H50: =F50*300% -> 85469.43 | I50: =F50*7.5% -> 2136.7357 | J50: 0 | K50: =F50*50% -> 14244.905 | L50: =F50*350% -> 99714.335 | M50: =F50*100% -> 28489.81 | N50: =140000 -> 140000 | P50: =F50*10% -> 2848.981 | Q50: 20000 | R50: 0 | S50: =SUM(F50:R50) -> 421394.01 | T50: 421394.01 | U50: =S50-T50 -> 0 | W50: 7709.76 | X50: 7709.76 | Y50: =X50-W50 -> 0
A51: 6 | B51: DR MOHAMMED O. AMALI | D51: RESEARCH FELLOW I | E51: 14(9) | F51: =26732.65 -> 26732.65 | H51: =F51*300% -> 80197.95 | I51: =F51*7.5% -> 2004.9488 | K51: =F51*50% -> 13366.325 | L51: =F51*350% -> 93564.275 | M51: =F51*100% -> 26732.65 | N51: =140000 -> 140000 | P51: =F51*10% -> 2673.265 | Q51: 20000 | S51: =SUM(F51:R51) -> 405272.06 | T51: 397211.37 | U51: =S51-T51 -> 8060.6962 | W51: 7709.76 | X51: 7709.76 | Y51: =X51-W51 -> 0
A52: 7 | B52: YAHAYA SHAMSU | D52: RESEARCH FELLOW 1 | E52: 14(9) | F52: =26732.65 -> 26732.65 | H52: =F52*300% -> 80197.95 | I52: =F52*7.5% -> 2004.9488 | K52: =F52*50% -> 13366.325 | L52: =F52*350% -> 93564.275 | M52: =F52*100% -> 26732.65 | N52: =140000 -> 140000 | P52: =F52*10% -> 2673.265 | Q52: 20000 | S52: =SUM(F52:R52) -> 405272.06 | T52: 397211.37 | U52: =S52-T52 -> 8060.6962 | W52: 7709.76 | X52: 7709.76 | Y52: =X52-W52 -> 0
A53: 8 | B53: OFORDEME ADAOBI JULIA | D53: RESEARCH FELLOW 11 | E53: 13(10) | F53: =25523.45 -> 25523.45 | H53: =F53*300% -> 76570.35 | I53: =F53*7.5% -> 1914.2587 | J53: 0 | K53: =F53*50% -> 12761.725 | L53: =F53*350% -> 89332.075 | M53: =F53*100% -> 25523.45 | N53: =120000 -> 120000 | P53: =F53*10% -> 2552.345 | Q53: 15000 | R53: 0 | S53: =SUM(F53:R53) -> 369177.65 | T53: 362001.06 | U53: =S53-T53 -> 7176.5933 | W53: 7709.76 | X53: 7709.76 | Y53: =X53-W53 -> 0
A54: 9 | B54: IKPEAZU CHINEDU ANITA | D54: RESEARCH FELLOW 1 | E54: 14(8) | F54: =25854.1 -> 25854.1 | H54: =F54*300% -> 77562.3 | I54: =F54*7.5% -> 1939.0575 | J54: 0 | K54: =F54*50% -> 12927.05 | L54: =F54*350% -> 90489.35 | M54: =F54*100% -> 25854.1 | N54: 140000 | P54: =F54*10% -> 2585.41 | Q54: 20000 | R54: 0 | S54: =SUM(F54:R54) -> 397211.37 | T54: 397211.37 | U54: =S54-T54 -> 0 | W54: 7709.76 | X54: 7709.76 | Y54: =X54-W54 -> 0
A55: 10 | B55: DORIS DAKDA AARON | D55: RESEARCH FELLOW II | E55: 13(9) | F55: =24741.26 -> 24741.26 | H55: =F55*300% -> 74223.78 | I55: =F55*7.5% -> 1855.5945 | K55: =F55*50% -> 12370.63 | L55: =F55*350% -> 86594.41 | M55: =F55*100% -> 24741.26 | N55: =120000 -> 120000 | P55: =F55*10% -> 2474.126 | Q55: 15000 | S55: =SUM(F55:R55) -> 362001.06 | T55: 354201.03 | U55: =S55-T55 -> 7800.0345 | W55: =7709.76 -> 7709.76 | X55: 7709.76 | Y55: =X55-W55 -> 0
B56: TOTAL | D56: 10 | F56: =SUM(F46:F55) -> 339092.14 | G56: =SUM(G46:G55) -> 0 | H56: =SUM(H46:H55) -> 1017276.4 | I56: =SUM(I46:I55) -> 25431.91 | J56: =SUM(J46:J55) -> 200610.95 | K56: =SUM(K46:K55) -> 169546.07 | L56: =SUM(L46:L55) -> 1186822.5 | M56: =SUM(M46:M55) -> 339092.14 | N56: =SUM(N46:N55) -> 1480000 | P56: =SUM(P46:P55) -> 33909.214 | Q56: =SUM(Q46:Q55) -> 190000 | R56: =SUM(R46:R55) -> 0 | S56: =SUM(S46:S55) -> 4981781.3 | T56: 4939266.3 | U56: =S56-T56 -> 42515.023 | W56: =SUM(W46:W55) -> 145680.18 | X56: 145680.18 | Y56: =X56-W56 -> 0
U57: =S57-T57 -> 0 | Y57: =X57-W57 -> 0
B58: LEGAL SERVICES | U58: =S58-T58 -> 0 | Y58: =X58-W58 -> 0
A59: 1 | B59: DR SHUIBU DANWANKA | D59: DIRECTOR LEGAL SERVICES | E59: 17(9) | F59: =81740.02 -> 81740.02 | H59: =F59*300% -> 245220.06 | I59: =F59*7.5% -> 6130.5015 | J59: 80244.38 | K59: =F59*50% -> 40870.01 | L59: =F59*350% -> 286090.07 | M59: =F59*100% -> 81740.02 | N59: =200000 -> 200000 | P59: =F59*10% -> 8174.002 | Q59: 20000 | R59: 0 | S59: =SUM(F59:R59) -> 1050209.1 | T59: 1050209.1 | U59: =S59-T59 -> 0 | W59: 52776.63 | X59: 52776.63 | Y59: =X59-W59 -> 0
A60: 2 | B60: ABDULSALAM BAKO | D60: MANAGER, LEGAL SERVICES | E60: 15 (8) | F60: =32263.2 -> 32263.2 | H60: =F60*300% -> 96789.6 | I60: =F60*7.5% -> 2419.74 | J60: 40122.19 | K60: =F60*50% -> 16131.6 | L60: =F60*350% -> 112921.2 | M60: =F60*100% -> 32263.2 | O60: =80000 -> 80000 | P60: =F60*10% -> 3226.32 | Q60: 20000 | R60: 0 | S60: =SUM(F60:R60) -> 436137.05 | T60: 424720.05 | U60: =S60-T60 -> 11417.003 | W60: =15548.33 -> 15548.33 | X60: 15548.33 | Y60: =X60-W60 -> 0
B61: TOTAL | D61: 2 | F61: =SUM(F59:F60) -> 114003.22 | H61: =SUM(H59:H60) -> 342009.66 | I61: =SUM(I59:I60) -> 8550.2415 | J61: =SUM(J59:J60) -> 120366.57 | K61: =SUM(K59:K60) -> 57001.61 | L61: =SUM(L59:L60) -> 399011.27 | M61: =SUM(M59:M60) -> 114003.22 | N61: =SUM(N59:N60) -> 200000 | O61: =SUM(O59:O60) -> 80000 | ... S61: =SUM(S59:S60) -> 1486346.1 | T61: 1474929.1 | U61: =S61-T61 -> 11417.003 | W61: =SUM(W59:W60) -> 68324.96 | X61: 68324.96 | Y61: =X61-W61 -> 0
U62: =S62-T62 -> 0 | Y62: =X62-W62 -> 0
B63: DEMOCRACY AND GOVERNANCE | U63: =S63-T63 -> 0 | Y63: =X63-W63 -> 0
A64: 1 | B64: DR. ADEWALE ADEREMI | D64: DIRECTOR, DEMOCRATIC STUDIES | E64: 17(9) | F64: =81740.02 -> 81740.02 | H64: =F64*300% -> 245220.06 | I64: =F64*7.5% -> 6130.5015 | J64: 80244.38 | K64: =F64*50% -> 40870.01 | L64: =F64*350% -> 286090.07 | M64: =F64*100% -> 81740.02 | N64: =200000 -> 200000 | P64: =F64*10% -> 8174.002 | Q64: 20000 | R64: 0 | S64: 1050209.1 | T64: 1025433.1 | U64: =S64-T64 -> 24775.987 | W64: =52776.63 -> 52776.63 | X64: 52776.63 | Y64: =X64-W64 -> 0
A65: 2 | B65: NDANUSA MOHAMMED MANZUMA | D65: SNR RESEARCH FELLOW | E65: 15 (7) | F65: 31018.84 | H65: =F65*300% -> 93056.52 | I65: =F65*7.5% -> 2326.413 | J65: 40122.19 | K65: =F65*50% -> 15509.42 | L65: =F65*350% -> 108565.94 | M65: =F65*100% -> 31018.84 | N65: =160000 -> 160000 | P65: =F65*10% -> 3101.884 | Q65: 20000 | R65: 0 | S65: =SUM(F65:R65) -> 504720.05 | T65: 504720.05 | U65: =S65-T65 -> 0 | W65: =15548.33 -> 15548.33 | X65: 15548.33 | Y65: =X65-W65 -> 0
A66: 3 | B66: EMILY EDOISA IKHIDE | D66: RESEARCH FELLOW II | E66: 13(11) | F66: =26339.3 -> 26339.3 | H66: =F66*300% -> 79017.9 | I66: =F66*7.5% -> 1975.4475 | K66: =F66*50% -> 13169.65 | L66: =F66*350% -> 92187.55 | M66: =F66*100% -> 26339.3 | N66: =120000 -> 120000 | P66: =F66*10% -> 2633.93 | Q66: 15000 | S66: =SUM(F66:R66) -> 376663.08 | T66: 369177.65 | U66: =S66-T66 -> 7485.4237 | W66: 7709.76 | X66: 7709.76 | Y66: =X66-W66 -> 0
A67: 4 | B67: EJALONIBU GANIYU LAYI | D67: RESEARCH FELLOW 11 | E67: 13(9) | F67: =24741.26 -> 24741.26 | H67: =F67*300% -> 74223.78 | I67: =F67*7.5% -> 1855.5945 | K67: =F67*50% -> 12370.63 | L67: =F67*350% -> 86594.41 | M67: =F67*100% -> 24741.26 | N67: =120000 -> 120000 | P67: =F67*10% -> 2474.126 | Q67: 15000 | S67: =SUM(F67:R67) -> 362001.06 | T67: 354201.03 | U67: =S67-T67 -> 7800.0345 | W67: =7709.76 -> 7709.76 | X67: 7709.76 | Y67: =X67-W67 -> 0
A68: 5 | B68: LONA POLIT BONKAT | D68: RESEARCH FELLOW 11 | E68: 13(8) | F68: =23891.12 -> 23891.12 | H68: =F68*300% -> 71673.36 | I68: =F68*7.5% -> 1791.834 | J68: 0 | K68: =F68*50% -> 11945.56 | L68: =F68*350% -> 83618.92 | M68: =F68*100% -> 23891.12 | N68: =120000 -> 120000 | P68: =F68*10% -> 2389.112 | Q68: 15000 | R68: 0 | S68: =SUM(F68:R68) -> 354201.03 | T68: 346713.03 | U68: =S68-T68 -> 7487.9927 | W68: 7709.76 | X68: 7709.76 | Y68: =X68-W68 -> 0
A69: 6 | B69: YUNUSA ABDULLAHI | D69: RESEARCH FELLOW 1 | E69: 14(9) | F69: =26732.65 -> 26732.65 | H69: =F69*300% -> 80197.95 | I69: =F69*7.5% -> 2004.9488 | K69: =F69*50% -> 13366.325 | L69: =F69*350% -> 93564.275 | M69: =F69*100% -> 26732.65 | N69: =140000 -> 140000 | P69: =F69*10% -> 2673.265 | Q69: 20000 | S69: =SUM(F69:R69) -> 405272.06 | T69: 397211.37 | U69: =S69-T69 -> 8060.6962 | W69: =7709.76 -> 7709.76 | X69: 7709.76 | Y69: =X69-W69 -> 0
A70: 7 | B70: UDEFUNA NNADOZIE PATRICK | D70: RESEARCH OFFICER | E70: 10(13) | F70: =19774.62 -> 19774.62 | H70: =F70*300% -> 59323.86 | I70: =F70*7.5% -> 1483.0965 | J70: 0 | K70: =F70*50% -> 9887.31 | L70: =F70*350% -> 69211.17 | M70: =F70*100% -> 19774.62 | N70: =100000 -> 100000 | P70: =F70*10% -> 1977.462 | Q70: 10000 | R70: 0 | S70: =SUM(F70:R70) -> 291432.14 | T70: 291432.14 | U70: =S70-T70 -> 0 | W70: 3369.51 | X70: 3369.51 | Y70: =X70-W70 -> 0
A71: 8 | B71: OSOLAFIA MUHAMMAD EGYE | D71: RESEARCH OFFICER | E71: 12(8) | F71: =21520.88 -> 21520.88 | H71: =F71*300% -> 64562.64 | I71: =F71*7.5% -> 1614.066 | J71: 0 | K71: =F71*50% -> 10760.44 | L71: =F71*350% -> 75323.08 | M71: =F71*100% -> 21520.88 | N71: =110000 -> 110000 | P71: =F71*10% -> 2152.088 | Q71: 15000 | R71: 0 | S71: =SUM(F71:R71) -> 322454.07 | T71: 315372.08 | U71: =S71-T71 -> 7081.999 | W71: =3369.51 -> 3369.51 | X71: 3369.51 | Y71: =X71-W71 -> 0
A72: 9 | B72: HAUWA PATE SADIQ | D72: PROGRAMME OFFICER | E72: 10(10) | F72: =18779.3 -> 18779.3 | H72: =F72*300% -> 56337.9 | I72: =F72*7.5% -> 1408.4475 | K72: =F72*50% -> 9389.65 | L72: =F72*350% -> 65727.55 | M72: =F72*100% -> 18779.3 | N72: =100000 -> 100000 | P72: =F72*10% -> 1877.93 | Q72: 10000 | S72: =SUM(F72:R72) -> 282300.08 | T72: 277734.05 | U72: =S72-T72 -> 4566.0305 | W72: 3369.51 | X72: 3369.51 | Y72: =X72-W72 -> 0
A73: 10 | B73: ABAYOMI KAYODE QUADRI | D73: RESEARCH OFFICER | E73: 10(7) | F73: =17286.33 -> 17286.33 | H73: =F73*300% -> 51858.99 | I73: =F73*7.5% -> 1296.4748 | K73: =F73*50% -> 8643.165 | L73: =F73*350% -> 60502.155 | M73: =F73*100% -> 17286.33 | N73: =100000 -> 100000 | P73: =F73*10% -> 1728.633 | Q73: 10000 | S73: =SUM(F73:R73) -> 268602.08 | T73: 268602.08 | U73: =S73-T73 -> 0 | W73: 3369.51 | X73: 3369.51 | Y73: =X73-W73 -> 0
A74: 11 | B74: NNANDI LIVINUS ATURE | D74: RESEARCH ASSISTANT | E74: 8(7) | F74: =12351.94 -> 12351.94 | H74: =F74*300% -> 37055.82 | I74: =F74*7.5% -> 926.3955 | K74: =F74*50% -> 6175.97 | L74: =F74*350% -> 43231.79 | M74: =F74*100% -> 12351.94 | N74: =100000 -> 100000 | P74: =F74*10% -> 1235.194 | Q74: 10000 | S74: =SUM(F74:R74) -> 223329.05 | T74: 223329.05 | U74: =S74-T74 -> 0 | W74: 1484.37 | X74: 1484.37 | Y74: =X74-W74 -> 0
A75: 12 | B75: LUCKY AGWOM | D75: RESEARCH ASSISTANT | E75: 8(7) | F75: =12351.94 -> 12351.94 | H75: =F75*300% -> 37055.82 | I75: =F75*7.5% -> 926.3955 | K75: =F75*50% -> 6175.97 | L75: =F75*350% -> 43231.79 | M75: =F75*100% -> 12351.94 | N75: =100000 -> 100000 | P75: =F75*10% -> 1235.194 | Q75: 10000 | S75: =SUM(F75:R75) -> 223329.05 | T75: 223329.05 | U75: =S75-T75 -> 0 | W75: 1484.37 | X75: 1484.37 | Y75: =X75-W75 -> 0
B76: TOTAL | D76: 12 | F76: =SUM(F64:F75) -> 316528.2 | G76: =SUM(G64:G75) -> 0 | H76: =SUM(H64:H75) -> 949584.6 | I76: =SUM(I64:I75) -> 23739.615 | J76: =SUM(J64:J75) -> 120366.57 | K76: =SUM(K64:K75) -> 158264.1 | L76: =SUM(L64:L75) -> 1107848.7 | M76: =SUM(M64:M75) -> 316528.2 | N76: =SUM(N64:N75) -> 1470000 | P76: =SUM(P64:P75) -> 31652.82 | Q76: =SUM(Q64:Q75) -> 170000 | R76: =SUM(R64:R75) -> 0 | S76: =SUM(S64:S75) -> 4664512.8 | T76: 4597254.6 | U76: =S76-T76 -> 67258.163 | W76: =SUM(W64:W75) -> 115610.78 | X76: 115610.78 | Y76: =X76-W76 -> 0
U77: =S77-T77 -> 0 | Y77: =X77-W77 -> 0
B78: STUDIES | U78: =S78-T78 -> 0 | Y78: =X78-W78 -> 0
A79: 1 | B79: DR ASIMIYU G. ABIOLA | D79: DIRECTOR POST GRADUATE | E79: 17(9) | F79: =81740.02 -> 81740.02 | H79: =F79*300% -> 245220.06 | I79: =F79*7.5% -> 6130.5015 | J79: 80244.38 | K79: =F79*50% -> 40870.01 | L79: =F79*350% -> 286090.07 | M79: =F79*100% -> 81740.02 | N79: =200000 -> 200000 | P79: =F79*10% -> 8174.002 | Q79: 20000 | R79: 0 | S79: =SUM(F79:R79) -> 1050209.1 | T79: 1050209.1 | U79: =S79-T79 -> 0 | W79: 52776.63 | X79: 52776.63 | Y79: =X79-W79 -> 0
A80: 2 | B80: USMAN WALI | D80: SENIOR RESEARCH FELLOW | E80: 15 (7) | F80: 31018.84 | H80: =F80*300% -> 93056.52 | I80: =F80*7.5% -> 2326.413 | J80: 40122.19 | K80: =F80*50% -> 15509.42 | L80: =F80*350% -> 108565.94 | M80: =F80*100% -> 31018.84 | N80: =160000 -> 160000 | P80: =F80*10% -> 3101.884 | Q80: 20000 | R80: 0 | S80: =SUM(F80:R80) -> 504720.05 | T80: 504720.05 | U80: =S80-T80 -> 0 | W80: =15548.33 -> 15548.33 | X80: 15548.33 | Y80: =X80-W80 -> 0
A81: 3 | B81: MOSHOOD TOSHO AMUDA | D81: MANAGER, EXAMS & RECORDS | E81: 15 (7) | F81: 31018.84 | H81: =F81*300% -> 93056.52 | I81: =F81*7.5% -> 2326.413 | J81: 40122.19 | K81: =F81*50% -> 15509.42 | L81: =F81*350% -> 108565.94 | M81: =F81*100% -> 31018.84 | N81: =160000 -> 160000 | P81: =F81*10% -> 3101.884 | Q81: 20000 | R81: 0 | S81: =SUM(F81:R81) -> 504720.05 | T81: 504720.05 | U81: =S81-T81 -> 0 | W81: =15548.33 -> 15548.33 | X81: 15548.33 | Y81: =X81-W81 -> 0
A82: 4 | B82: UZODINMA EMMANUEL EZENWA | D82: RESEARCH FELLOW II | E82: 13(9) | F82: =24741.26 -> 24741.26 | H82: =F82*300% -> 74223.78 | I82: =F82*7.5% -> 1855.5945 | J82: 0 | K82: =F82*50% -> 12370.63 | L82: =F82*350% -> 86594.41 | M82: =F82*100% -> 24741.26 | N82: =120000 -> 120000 | P82: =F82*10% -> 2474.126 | Q82: 15000 | R82: 0 | S82: =SUM(F82:R82) -> 362001.06 | T82: 354201.03 | U82: =S82-T82 -> 7800.0345 | W82: =7709.76 -> 7709.76 | X82: 7709.76 | Y82: =X82-W82 -> 0
A83: 5 | B83: IGWE STACY | D83: PROGRAMME OFFICER | E83: 10(7) | F83: =17286.33 -> 17286.33 | H83: =F83*300% -> 51858.99 | I83: =F83*7.5% -> 1296.4748 | K83: =F83*50% -> 8643.165 | L83: =F83*350% -> 60502.155 | M83: =F83*100% -> 17286.33 | N83: =100000 -> 100000 | P83: =F83*10% -> 1728.633 | Q83: 10000 | S83: =SUM(F83:R83) -> 268602.08 | T83: 268602.08 | U83: =S83-T83 -> 0 | W83: 3369.51 | X83: 3369.51 | Y83: =X83-W83 -> 0
A84: 6 | B84: DARE SHEU MAGBON | D84: ASSIST. PG | E84: 8(9) | F84: =13112.16 -> 13112.16 | H84: =F84*300% -> 39336.48 | I84: =F84*7.5% -> 983.412 | K84: =F84*50% -> 6556.08 | L84: =F84*350% -> 45892.56 | M84: =F84*100% -> 13112.16 | N84: =100000 -> 100000 | P84: =F84*10% -> 1311.216 | Q84: 10000 | S84: =SUM(F84:R84) -> 230304.07 | T84: 226816.1 | U84: =S84-T84 -> 3487.968 | W84: 1484.37 | X84: 1484.37 | Y84: =X84-W84 -> 0
A85: 7 | B85: MOHAMMED BELLO | D85: RESEARCH ASSITANT PG | E85: 8(7) | F85: =12351.94 -> 12351.94 | H85: =F85*300% -> 37055.82 | I85: =F85*7.5% -> 926.3955 | K85: =F85*50% -> 6175.97 | L85: =F85*350% -> 43231.79 | M85: =F85*100% -> 12351.94 | N85: =100000 -> 100000 | P85: =F85*10% -> 1235.194 | Q85: 10000 | S85: =SUM(F85:R85) -> 223329.05 | T85: 223329.05 | U85: =S85-T85 -> 0 | W85: 1484.37 | X85: 1484.37 | Y85: =X85-W85 -> 0
B86: TOTAL | D86: 7 | F86: =SUM(F79:F85) -> 211269.39 | H86: =SUM(H79:H85) -> 633808.17 | I86: =SUM(I79:I85) -> 15845.204 | J86: =SUM(J79:J85) -> 160488.76 | K86: =SUM(K79:K85) -> 105634.7 | L86: =SUM(L79:L85) -> 739442.86 | M86: =SUM(M79:M85) -> 211269.39 | N86: =SUM(N79:N85) -> 940000 | P86: =SUM(P79:P85) -> 21126.939 | Q86: =SUM(Q79:Q85) -> 105000 | R86: =SUM(R79:R85) -> 0 | S86: =SUM(S79:S85) -> 3143885.4 | T86: 3132597.4 | U86: =S86-T86 -> 11288.002 | W86: =SUM(W79:W85) -> 97921.3 | X86: 97921.3 | Y86: =X86-W86 -> 0
U87: =S87-T87 -> 0 | Y87: =X87-W87 -> 0
B88: ECONOMIC DEV. AND SOCIAL RESEARCH | U88: =S88-T88 -> 0 | Y88: =X88-W88 -> 0
A89: 1 | B89: DR ASEMOTA OMOROGBE JOSEPH | D89: Ag. DEPUTY DIRECTOR, ECO & SOC DEV DEPT | E89: 16(8) | F89: =41157.69 -> 41157.69 | H89: =F89*300% -> 123473.07 | I89: =F89*7.5% -> 3086.8268 | J89: 40122.19 | K89: =F89*50% -> 20578.845 | L89: =F89*350% -> 144051.92 | M89: =F89*100% -> 41157.69 | N89: =180000 -> 180000 | P89: =F89*10% -> 4115.769 | Q89: 20000 | S89: =SUM(F89:R89) -> 617744 | T89: 604023.33 | U89: =S89-T89 -> 13720.662 | W89: =21618.09 -> 21618.09 | X89: 21618.09 | Y89: =X89-W89 -> 0
A90: 2 | B90: TERFA WILLIAMS ABRAHAM | D90: SNR RESEARCH FELLOW | E90: 15(9) | F90: =33507.5 -> 33507.5 | H90: =F90*300% -> 100522.5 | I90: =F90*7.5% -> 2513.0625 | J90: =40122.19 -> 40122.19 | K90: =F90*50% -> 16753.75 | L90: =F90*350% -> 117276.25 | M90: =F90*100% -> 33507.5 | N90: =160000 -> 160000 | P90: =F90*10% -> 3350.75 | Q90: 20000 | S90: =SUM(F90:R90) -> 527553.5 | T90: 516137.05 | U90: =S90-T90 -> 11416.452 | W90: =15548.33 -> 15548.33 | X90: 15548.33 | Y90: =X90-W90 -> 0
A91: 3 | B91: DR AUGUSTINE C. OSIGWE | D91: SNR RESEARCH FELLOW | E91: 15(9) | F91: =33507.5 -> 33507.5 | H91: =F91*300% -> 100522.5 | I91: =F91*7.5% -> 2513.0625 | J91: =40122.19 -> 40122.19 | K91: =F91*50% -> 16753.75 | L91: =F91*350% -> 117276.25 | M91: =F91*100% -> 33507.5 | N91: =160000 -> 160000 | P91: =F91*10% -> 3350.75 | Q91: 20000 | S91: =SUM(F91:R91) -> 527553.5 | T91: 516137.05 | U91: =S91-T91 -> 11416.452 | W91: =15548.33 -> 15548.33 | X91: 15548.33 | Y91: =X91-W91 -> 0
A92: 4 | B92: JUMARE FADILA | D92: RESEARCH FELLOW I | E92: 14(9) | F92: =26732.65 -> 26732.65 | H92: =F92*300% -> 80197.95 | I92: =F92*7.5% -> 2004.9488 | J92: 0 | K92: =F92*50% -> 13366.325 | L92: =F92*350% -> 93564.275 | M92: =F92*100% -> 26732.65 | N92: 140000 | P92: =F92*10% -> 2673.265 | Q92: 20000 | R92: 0 | S92: =SUM(F92:R92) -> 405272.06 | T92: 397211.37 | U92: =S92-T92 -> 8060.6962 | W92: =7709.76 -> 7709.76 | X92: 7709.76 | Y92: =X92-W92 -> 0
A93: 5 | B93: NGARA CHRISTOPHER OCHANJA | D93: RESEARCH FELLOW 1 | E93: 14(10) | F93: =27611.23 -> 27611.23 | H93: =F93*300% -> 82833.69 | I93: =F93*7.5% -> 2070.8422 | K93: =F93*50% -> 13805.615 | L93: =F93*350% -> 96639.305 | M93: =F93*100% -> 27611.23 | N93: 140000 | P93: =F93*10% -> 2761.123 | Q93: 20000 | R93: 0 | S93: =SUM(F93:R93) -> 413333.04 | T93: 405272.06 | U93: =S93-T93 -> 8060.9715 | W93: =7709.76 -> 7709.76 | X93: 7709.76 | Y93: =X93-W93 -> 0
A94: 6 | B94: OMOJU OLUWASOLA EMMANUEL | D94: RESEARCH FELLOW I | E94: 14(9) | F94: =26732.65 -> 26732.65 | H94: =F94*300% -> 80197.95 | I94: =F94*7.5% -> 2004.9488 | K94: =F94*50% -> 13366.325 | L94: =F94*350% -> 93564.275 | M94: =F94*100% -> 26732.65 | N94: 140000 | P94: =F94*10% -> 2673.265 | Q94: 20000 | S94: =SUM(F94:R94) -> 405272.06 | T94: 397211.37 | U94: =S94-T94 -> 8060.6962 | W94: =7709.76 -> 7709.76 | X94: 7709.76 | Y94: =X94-W94 -> 0
A95: 7 | B95: RIFKATU NGHARGBU | D95: RESEARCH FELLOW 1 | E95: 14(8) | F95: =25854.1 -> 25854.1 | H95: =F95*300% -> 77562.3 | I95: =F95*7.5% -> 1939.0575 | J95: 0 | K95: =F95*50% -> 12927.05 | L95: =F95*350% -> 90489.35 | M95: =F95*100% -> 25854.1 | N95: 140000 | P95: =F95*10% -> 2585.41 | Q95: 20000 | R95: `12333 | S95: =SUM(F95:R95) -> 397211.37 | T95: 389153.06 | U95: =S95-T95 -> 8058.3108 | W95: =7709.76 -> 7709.76 | X95: 7709.76 | Y95: =X95-W95 -> 0
A96: 8 | B96: IBE EZECHI CYRIACUS | D96: RESEARCH FELLOW II | E96: 13(9) | F96: =24741.26 -> 24741.26 | H96: =F96*300% -> 74223.78 | I96: =F96*7.5% -> 1855.5945 | J96: 0 | K96: =F96*50% -> 12370.63 | L96: =F96*350% -> 86594.41 | M96: =F96*100% -> 24741.26 | N96: =120000 -> 120000 | P96: =F96*10% -> 2474.126 | Q96: 15000 | R96: 0 | S96: =SUM(F96:R96) -> 362001.06 | T96: 354201.03 | U96: =S96-T96 -> 7800.0345 | W96: =7709.76 -> 7709.76 | X96: 7709.76 | Y96: =X96-W96 -> 0
A97: 9 | B97: OSIKHEN LEO IGBANOI | D97: RESEARCH FELLOW 11 | E97: 13(8) | F97: =23891.12 -> 23891.12 | H97: =F97*300% -> 71673.36 | I97: =F97*7.5% -> 1791.834 | J97: 0 | K97: =F97*50% -> 11945.56 | L97: =F97*350% -> 83618.92 | M97: =F97*100% -> 23891.12 | N97: =120000 -> 120000 | P97: =F97*10% -> 2389.112 | Q97: 15000 | R97: 0 | S97: =SUM(F97:R97) -> 354201.03 | T97: 346713.03 | U97: =S97-T97 -> 7487.9927 | W97: =7709.76 -> 7709.76 | X97: 7709.76 | Y97: =X97-W97 -> 0
A98: 10 | B98: OKUNGBOWA OSARETIN GODSPOWER | D98: RESEARCH FELLOW 11 | E98: 13(8) | F98: =23891.12 -> 23891.12 | H98: =F98*300% -> 71673.36 | I98: =F98*7.5% -> 1791.834 | J98: 0 | K98: =F98*50% -> 11945.56 | L98: =F98*350% -> 83618.92 | M98: =F98*100% -> 23891.12 | N98: =120000 -> 120000 | P98: =F98*10% -> 2389.112 | Q98: 15000 | R98: 0 | S98: =SUM(F98:R98) -> 354201.03 | T98: 346713.03 | U98: =S98-T98 -> 7487.9927 | W98: =7709.76 -> 7709.76 | X98: 7709.76 | Y98: =X98-W98 -> 0
B99: TOTAL | D99: 10 | F99: =SUM(F89:F98) -> 287626.82 | H99: =SUM(H89:H98) -> 862880.46 | I99: =SUM(I89:I98) -> 21572.011 | J99: =SUM(J89:J98) -> 120366.57 | K99: =SUM(K89:K98) -> 143813.41 | L99: =SUM(L89:L98) -> 1006693.9 | M99: =SUM(M89:M98) -> 287626.82 | N99: =SUM(N89:N98) -> 1420000 | P99: =SUM(P89:P98) -> 28762.682 | Q99: =SUM(Q89:Q98) -> 185000 | R99: =SUM(R89:R98) -> 0 | S99: =SUM(S89:S98) -> 4364342.6 | T99: 4272772.4 | U99: =S99-T99 -> 91570.262 | W99: =SUM(W89:W98) -> 106683.07 | X99: 106683.07 | Y99: =X99-W99 -> 0
U100: =S100-T100 -> 0 | Y100: =X100-W100 -> 0
B101: TRAINING AND INTERNATIONAL COOP | U101: =S101-T101 -> 0 | Y101: =X101-W101 -> 0
A102: 1 | B102: REKIYA IBRAHIM ATTAH | D102: DEPUTY DIRECTOR TRAINING | E102: 16(8) | F102: =41157.69 -> 41157.69 | H102: =F102*300% -> 123473.07 | I102: =F102*7.5% -> 3086.8268 | J102: 40122.19 | K102: =F102*50% -> 20578.845 | L102: =F102*350% -> 144051.92 | M102: =F102*100% -> 41157.69 | O102: =90000 -> 90000 | P102: =F102*10% -> 4115.769 | Q102: 20000 | S102: =SUM(F102:R102) -> 527744 | T102: 514023.33 | U102: =S102-T102 -> 13720.662 | W102: =21618.09 -> 21618.09 | X102: 21618.09 | Y102: =X102-W102 -> 0
...

Sheet Enhanced Welfare 2023 (2)
A1: NATIONAL INSTITUTE FOR LEGISLATIVE AND DEMOCRATIC STUDIES
A2: STAFF ENHANCED WELFARE SCHEDULE 2023
B4: STAFF NAME | C4: DESIGNATION | D4: GRADE LEVEL | E4: AMOUNT | F4: Grade Level 01 - 13 | G4: Grade Level 14 - 17
A5: S/N | B5: DG'S OFFICE | E5: N | F5: N | G5: N
A6: 1 | B6: PROF. ABUBAKAR O. SULAIMAN | C6: DIRECTOR GENERAL | D6: CONSOL | E6: 2000000 | F6: 0 | G6: 2000000
A7: 2 | B7: DR JAKE DABANG DAN AZUMI | C7: DEPUTY DIR. TTECHNICAL | D7: 16(9) | E7: 700000 | F7: 0 | G7: 700000
A8: 3 | B8: DR ABDULSALAM NASIRU NAEEM | C8: SA ACADEMICS | D8: 16(8) | E8: =700000/2 -> 350000 | F8: 0 | G8: =700000/2 -> 350000
A9: 4 | B9: RAHEEM USMAN AYIGORO | C9: SA-INFRASTRUCTURE | D9: 16 (8) | E9: =700000/2 -> 350000 | F9: 0 | G9: =700000/2 -> 350000
A10: 5 | B10: MARIAM MOHAMMED BELLO | C10: SA- SPECIAL DUTIES | D10: 16(7) | E10: 700000 | F10: 0 | G10: 700000
A11: 6 | B11: AKINSANMI ADEJOKE OLUKEMI | C11: DEPUTY DIR. INFO/PROTOCOL | D11: 16(7) | E11: 700000 | F11: 0 | G11: 700000
A12: 7 | B12: DR IKEME ARTHUR J.O | C12: DEPUTY DIRECTOR, M&E | D12: 16(7) | E12: 700000 | F12: 0 | G12: 700000
A13: 8 | B13: MOSHOOD M. OLALERE | C13: DEPUTY DIR. GENERAL SERVICE | D13: 16(7) | E13: 700000 | F13: 0 | G13: 700000
A14: 9 | B14: ANDRAWUS MUSA | C14: ASST. DIRECTOR, STORES | D14: 15(9) | E14: 700000 | F14: 0 | G14: 700000
A15: 10 | B15: AYOBOLU OLAJIDE OLUFUNSHO | C15: ASST.DIR., INFORMATION | D15: 15 (7) | E15: 700000 | F15: 0 | G15: 700000
A16: 11 | B16: HUSSEIN EGYE MUSA | C16: CHIEF PROTOCOL OFFICER | D16: 14(9) | E16: 500000 | F16: 0 | G16: 500000
A17: 12 | B17: DONALD E. MKPANAM | C17: CHIEF ICT OFFICER | D17: 14(9) | E17: 500000 | F17: 0 | G17: 500000
A18: 13 | B18: JOY HARUNA MAKERI | C18: RESEARCH FELLOW 1 TRAINING | D18: 14(9) | E18: 500000 | F18: 0 | G18: 500000
A19: 14 | B19: ALI ABDULLAHI | C19: CHIEF ICT OFFICER | D19: 14(9) | E19: 500000 | F19: 0 | G19: 500000
A20: 15 | B20: PERCY TERFA GBAHABO | C20: HEAD, NILDS LIAISON OFFICE | D20: 13(8) | E20: 500000 | F20: 500000 | G20: 0
A21: 16 | B21: HASSANA AHMED IBRAHIM | C21: PA- TO DG | D21: 13 (7) | E21: 500000 | F21: 500000 | G21: 0
... A37: 32 | B37: HARUNA JIBRIL A. | C37: ASST. ADMIN. OFFICER | D37: 8(7) | E37: 300000 | F37: 300000 | G37: 0
B38: TOTAL | C38: 29 | E38: =SUM(E6:E37) -> 15700000 | F38: =SUM(F6:F37) -> 6100000 | G38: =SUM(G6:G37) -> 9600000
B40: INTERNAL AUDIT
A41: 1 | B41: OSANAIYE DAVID AKINYEMI | C41: DIRECTOR INTERNAL AUDIT | D41: 17(8) | E41: 1000000 | F41: 0 | G41: 1000000
A42: 2 | B42: JAMILA ABDUL | C42: AUDITOR II | D42: 8(7) | E42: 300000 | F42: 300000 | G42: 0
C43: 2 | E43: =SUM(E41:E42) -> 1300000 | F43: =SUM(F41:F42) -> 300000 | G43: =SUM(G41:G42) -> 1000000
B45: LEG. SUPPORT SEVICES
A46: 1 | B46: PROF. EDOBA BRIGHT OMOREGBE | C46: AG. DLSS | D46: 17(9) | E46: 1000000 | F46: 0 | G46: 1000000
A47: 2 | B47: DR CLINTON JAJA | C47: SENIOR RESEARCH FELLOW | D47: 15(9) | E47: 700000 | F47: 0 | G47: 700000
A48: 3 | B48: BETHEL UZOMA IHUGBA | C48: SNR RESEARCH FELLOW | D48: 15(9) | E48: 700000 | F48: 0 | G48: 700000
A49: 4 | B49: OGUCHE SAMUEL | C49: SNR RESEARCH FELLOW | D49: 15(8) | E49: 700000 | F49: 0 | G49: 700000
A50: 5 | B50: IBRAHIM USMAN | C50: SNR RESEARCH FELLOW | D50: 15(7) | E50: 700000 | F50: 0 | G50: 700000
A51: 6 | B51: DR MOHAMMED O. AMALI | C51: RESEARCH FELLOW I | D51: 14(9) | E51: 500000 | F51: 0 | G51: 500000
A52: 7 | B52: YAHAYA SHAMSU | C52: RESEARCH FELLOW 1 | D52: 14(9) | E52: 500000 | F52: 0 | G52: 500000
A53: 8 | B53: OFORDEME ADAOBI JULIA | C53: RESEARCH FELLOW 1 | D53: 14(8) | E53: 500000 | F53: 0 | G53: 500000
A54: 9 | B54: DORIS DAKDA AARON | C54: RESEARCH FELLOW II | D54: 13(9) | E54: 500000 | F54: 500000 | G54: 0
A55: 10 | B55: ZAINAB AKINDE | C55: RESEARCH OFFICER | D55: 9(7) | E55: 300000 | F55: 300000 | G55: 0
A56: 11 | B56: ABDULLAHI AHMAD USMAN | C56: RESEARCH OFFICER | D56: 9(7) | E56: 300000 | F56: 300000 | G56: 0
A57: 12 | B57: GUNAT NANSAK MARK | C57: RESEARCH OFFICER | D57: 9(7) | E57: 300000 | F57: 300000 | G57: 0
B58: TOTAL | C58: 11 | E58: =SUM(E46:E57) -> 6700000 | F58: =SUM(F46:F57) -> 1400000 | G58: =SUM(G46:G57) -> 5300000
B60: LEGAL SERVICES
A61: 1 | B61: DR SHUIBU DANWANKA | C61: DIRECTOR LEGAL SERVICES | D61: 17(9) | E61: =1000000/2 -> 500000 | F61: 0 | G61: =1000000/2 -> 500000
B62: TOTAL | C62: 2 | E62: =SUM(E61) -> 500000 | F62: =SUM(F61) -> 0 | G62: =SUM(G61) -> 500000
B64: DEMOCRACY & GOVERNANCE
A65: 1 | B65: DR. ADEWALE ADEREMI | C65: DIRECTOR, DEMOCRATIC STUDIES | D65: 17(9) | E65: =1000000/2 -> 500000 | F65: 0 | G65: =1000000/2 -> 500000
A66: 2 | B66: NDANUSA MOHAMMED MANZUMA | C66: SNR RESEARCH FELLOW | D66: 15 (7) | E66: =700000/2 -> 350000 | F66: 0 | G66: =700000/2 -> 350000
A67: 3 | B67: EJALONIBU GANIYU LAYI | C67: RESEARCH FELLOW 11 | D67: 13(9) | E67: 500000 | F67: 500000 | G67: 0
A68: 4 | B68: LOHNA BONKAT JONATHAN | C68: RESEARCH FELLOW 11 | D68: 13(8) | E68: 500000 | F68: 500000 | G68: 0
A69: 5 | B69: YUNUSA ABDULLAHI | C69: RESEARCH FELLOW 1 | D69: 14(9) | E69: 500000 | F69: 0 | G69: 500000
A70: 6 | B70: UDEFUNA NNADOZIE PATRICK | C70: RESEARCH OFFICER | D70: 10(13) | E70: 300000 | F70: 300000 | G70: 0
A71: 7 | B71: OSOLAFIA MUHAMMAD EGYE | C71: PRINCIPAL RESEARCH OFFICER | D71: 12(8) | E71: 400000 | F71: 400000 | G71: 0
A72: 8 | B72: SHAFIU YAHYA MIKAIL | C72: PRINCIPAL RESEARCH OFFICER | D72: 12(7) | E72: 400000 | F72: 400000 | G72: 0
A73: 9 | B73: HASSAN YERIMA | C73: PRINCIPAL RESEARCH OFFICER | D73: 12(7) | E73: 400000 | F73: 400000 | G73: 0
A74: 10 | B74: HAUWA PATE SADIQ | C74: PRINCIPAL PROGRAMME OFFICER | D74: 12(7) | E74: 400000 | F74: 400000 | G74: 0
A75: 11 | B75: ABAYOMI KAYODE QUADRI | C75: RESEARCH OFFICER | D75: 10(7) | E75: 300000 | F75: 300000 | G75: 0
A76: 12 | B76: NNANDI LIVINUS ATURE | C76: RESEARCH ASSISTANT | D76: 9(7) | E76: 300000 | F76: 300000 | G76: 0
A77: 13 | B77: LUCKY AGWOM | C77: RESEARCH ASSISTANT | D77: 8(7) | E77: 300000 | F77: 300000 | G77: 0
B78: TOTAL | C78: 13 | E78: =SUM(E65:E77) -> 5150000 | F78: =SUM(F65:F77) -> 3800000 | G78: =SUM(G65:G77) -> 1350000
B80: DEPARTMENT OF STUDIES
A81: 1 | B81: DR ASIMIYU G. ABIOLA | C81: DIRECTOR POST GRADUATE | D81: 17(9) | E81: 1000000 | F81: 0 | G81: 1000000
A82: 2 | B82: USMAN WALI | C82: SENIOR RESEARCH FELLOW | D82: 15 (7) | E82: 700000 | F82: 0 | G82: 700000
A83: 3 | B83: MOSHOOD TOSHO AMUDA | C83: MANAGER, EXAMS & RECORDS | D83: 15 (7) | E83: =700000/2 -> 350000 | F83: 0 | G83: =700000/2 -> 350000
A84: 4 | B84: ANTHONY EDET | C84: ASST. MGR M&E | D84: 13(9) | E84: 500000 | F84: 500000 | G84: 0
A85: 5 | B85: IGWE STACY | C85: PROGRAMME OFFICER | D85: 10(7) | E85: 300000 | F85: 300000 | G85: 0
B86: TOTAL | C86: 5 | E86: =SUM(E81:E85) -> 2850000 | F86: =SUM(F81:F85) -> 800000 | G86: =SUM(G81:G85) -> 2050000
B88: ECON. DEV. & SOC. RESEARCH
A89: 1 | B89: DR ASEMOTA OMOROGBE JOSEPH | C89: Ag. DEPUTY DIRECTOR, ECO & SOC DEV DEPT | D89: 16(8) | E89: 700000 | F89: 0 | G89: 700000
A90: 2 | B90: TERFA WILLIAMS ABRAHAM | C90: SNR RESEARCH FELLOW | D90: 15(9) | E90: 700000 | F90: 0 | G90: 700000
A91: 3 | B91: DR AUGUSTINE C. OSIGWE | C91: SNR RESEARCH FELLOW | D91: 15(9) | E91: 700000 | F91: 0 | G91: 700000
A92: 4 | B92: NGARA CHRISTOPHER OCHANJA | C92: RESEARCH FELLOW 1 | D92: 14(10) | E92: 500000 | F92: 0 | G92: 500000
A93: 5 | B93: OMOJU OLUWASOLA EMMANUEL | C93: RESEARCH FELLOW I | D93: 14(9) | E93: 500000 | F93: 0 | G93: 500000
A94: 6 | B94: IBE EZECHI CYRIACUS | C94: RESEARCH FELLOW II | D94: 13(9) | E94: 500000 | F94: 500000 | G94: 0
A95: 7 | B95: OSIKHEN LEO IGBANOI | C95: RESEARCH FELLOW 11 | D95: 13(8) | E95: 500000 | F95: 500000 | G95: 0
A96: 8 | B96: OKUNGBOWA OSARETIN GODSPOWER | C96: RESEARCH FELLOW 11 | D96: 13(8) | E96: =500000/2 -> 250000 | F96: =500000/2 -> 250000 | G96: 0
A97: 9 | B97: YUSUF IBRAHIM | C97: PRINCIPAL RESEARCH OFFICER | D97: 12(7) | E97: 400000 | F97: 400000 | G97: 0
A98: 10 | B98: MARYAM MUSA SADA | C98: ASSIT. RESEARCH OFFICER | D98: 10(7) | E98: 300000 | F98: 300000 | G98: 0
A99: 11 | B99: CHARITY EZENWAJIOBI | C99: REASEARCH. ASST. | D99: 8(7) | E99: 300000 | F99: 300000 | G99: 0
B100: TOTAL | C100: 10 | E100: =SUM(E89:E99) -> 5350000 | F100: =SUM(F89:F99) -> 2250000 | G100: =SUM(G89:G99) -> 3100000
B102: TRAINING & INT'L COOP
A103: 1 | B103: REKIYA IBRAHIM ATTAH | C103: DEPUTY DIRECTOR TRAINING | D103: 16(8) | E103: 700000 | F103: 0 | G103: 700000
A104: 2 | B104: DR FRANCIS NDUM OJIE | C104: CHIEF TRAINING OFFICER | D104: 14(9) | E104: 500000 | F104: 0 | G104: 500000
A105: 3 | B105: ABUBAKAR MOHAMMED BASHIR | C105: ASST. CHIEF TRAINING OFFICER | D105: 13(8) | E105: 500000 | F105: 500000 | G105: 0
A106: 4 | B106: OKECHUKWU UCHENNA HULDA | C106: PRINCIPALTRAINING OFFICER | D106: 12(7) | E106: 400000 | F106: 400000 | G106: 0
B107: TOTAL | C107: 4 | E107: =SUM(E103:E106) -> 2100000 | F107: =SUM(F103:F106) -> 900000 | G107: =SUM(G103:G106) -> 1200000
B109: LIBRARY & DOCUMENTATION
A110: 1 | B110: DR MAIMUNA IZAH | C110: INSITUTE LIBRARIAN | D110: 17(9) | E110: 1000000 | F110: 0 | G110: 1000000
A111: 2 | B111: CATHERINE E. IKOKOH | C111: SNR RESEARCH FELLOW DOCU | D111: 16(7) | E111: 700000 | F111: 0 | G111: 700000
A112: 3 | B112: ALIYU SANNI ABUBAKAR | C112: RESEARCH FELLOW 11 DATA & DOCU | D112: 13(11) | E112: 500000 | F112: 500000 | G112: 0
A113: 4 | B113: CHINAKO N. ASOGWA | C113: RESEARCH FELLOW 11 DATA & DOCU | D113: 13(10) | E113: 500000 | F113: 500000 | G113: 0
A114: 5 | B114: AMOS ABA | C114: LIBRARY ASSISTANT | D114: 8(10) | E114: 300000 | F114: 300000 | G114: 0
A115: 6 | B115: TITILAYO DANIEL MARVELLOUS | C115: LIBRARY ASSISTANT | D115: 8(9) | E115: 300000 | F115: 300000 | G115: 0
A116: 7 | B116: ENENCHE JEREMIAH AGADA | C116: LIBRARY ASSISTANT | D116: 8(7) | E116: 300000 | F116: 300000 | G116: 0
B117: TOTAL | C117: 7 | E117: =SUM(E110:E116) -> 3600000 | F117: =SUM(F110:F116) -> 1900000 | G117: =SUM(G110:G116) -> 1700000
B119: FINANCE & ACCOUNTS
A120: 1 | B120: IBRAHIM M. MSHELIA | C120: DIR. FINANCE & ACCOUNTS | D120: 17(9) | E120: 1000000 | F120: 0 | G120: 1000000
A121: 2 | B121: KABIR MUHAMMAD SULAIMAN | C121: DD FINANCE & ACCOUNTS | D121: 16(9) | E121: 700000 | F121: 0 | G121: 700000
A122: 3 | B122: RAHILA NURUDEEN HABU | C122: ASST. DIRECTOR, ACCOUNTS | D122: 15(9) | E122: 700000 | F122: 0 | G122: 700000
A123: 4 | B123: TONDO IORWUESE EDWARD | C123: ASST. DIRECTOR, ACCOUNTS | D123: 15(9) | E123: 700000 | F123: 0 | G123: 700000
A124: 5 | B124: ARAOYE GANIYAT TITILOLA | C124: ASST. DIRECTOR, ACCOUNTS | D124: 15(7) | E124: 700000 | F124: 0 | G124: 700000
A125: 6 | B125: SHEHU ABDULLAHI | C125: CHIEF ACCOUNT OFFICER | D125: 14(8) | E125: 500000 | F125: 0 | G125: 500000
...

Sheet Enhanced Welfare 2023 (3)
A1: NATIONAL INSTITUTE FOR LEGISLATIVE AND DEMOCRATIC STUDIES
A2: STAFF ENHANCED WELFARE SCHEDULE 2023
B4: STAFF NAME | C4: DESIGNATION | D4: GRADE LEVEL | E4: AMOUNT | F4: Grade Level 01 - 13 | G4: Grade Level 14 - 17
A5: S/N | B5: DG'S OFFICE | E5: N | F5: N | G5: N
A6: 1 | B6: PROF. ABUBAKAR O. SULAIMAN | C6: DIRECTOR GENERAL | D6: CONSOL | E6: 2000000 | F6: 0 | G6: 2000000
A7: 2 | B7: DR JAKE DABANG DAN AZUMI | C7: DEPUTY DIR. TTECHNICAL | D7: 16(9) | E7: 700000 | F7: 0 | G7: 700000
A8: 3 | B8: DR ABDULSALAM NASIRU NAEEM | C8: SA ACADEMICS | D8: 16(8) | E8: =700000/2 -> 350000 | F8: 0 | G8: =700000/2 -> 350000
A9: 4 | B9: RAHEEM USMAN AYIGORO | C9: SA-INFRASTRUCTURE | D9: 16 (8) | E9: =700000/2 -> 350000 | F9: 0 | G9: =700000/2 -> 350000
A10: 5 | B10: MARIAM MOHAMMED BELLO | C10: SA- SPECIAL DUTIES | D10: 16(7) | E10: 700000 | F10: 0 | G10: 700000
A11: 6 | B11: AKINSANMI ADEJOKE OLUKEMI | C11: DEPUTY DIR. INFO/PROTOCOL | D11: 16(7) | E11: 700000 | F11: 0 | G11: 700000
A12: 7 | B12: DR IKEME ARTHUR J.O | C12: DEPUTY DIRECTOR, M&E | D12: 16(7) | E12: 700000 | F12: 0 | G12: 700000
A13: 8 | B13: MOSHOOD M. OLALERE | C13: DEPUTY DIR. GENERAL SERVICE | D13: 16(7) | E13: 700000 | F13: 0 | G13: 700000
A14: 9 | B14: ANDRAWUS MUSA | C14: ASST. DIRECTOR, STORES | D14: 15(9) | E14: 700000 | F14: 0 | G14: 700000
A15: 10 | B15: AYOBOLU OLAJIDE OLUFUNSHO | C15: ASST.DIR., INFORMATION | D15: 15 (7) | E15: 700000 | F15: 0 | G15: 700000
A16: 11 | B16: HUSSEIN EGYE MUSA | C16: CHIEF PROTOCOL OFFICER | D16: 14(9) | E16: 500000 | F16: 0 | G16: 500000
A17: 12 | B17: DONALD E. MKPANAM | C17: CHIEF ICT OFFICER | D17: 14(9) | E17: 500000 | F17: 0 | G17: 500000
A18: 13 | B18: JOY HARUNA MAKERI | C18: RESEARCH FELLOW 1 TRAINING | D18: 14(9) | E18: 500000 | F18: 0 | G18: 500000
A19: 14 | B19: ALI ABDULLAHI | C19: CHIEF ICT OFFICER | D19: 14(9) | E19: 500000 | F19: 0 | G19: 500000
A20: 15 | B20: PERCY TERFA GBAHABO | C20: HEAD, NILDS LIAISON OFFICE | D20: 13(8) | E20: 500000 | F20: 500000 | G20: 0
A21: 16 | B21: HASSANA AHMED IBRAHIM | C21: PA- TO DG | D21: 13 (7) | E21: 500000 | F21: 500000 | G21: 0
... A37: 32 | B37: HARUNA JIBRIL A. | C37: ASST. ADMIN. OFFICER | D37: 8(7) | E37: 300000 | F37: 300000 | G37: 0
B38: TOTAL | C38: 29 | E38: =SUM(E6:E37) -> 15700000 | F38: =SUM(F6:F37) -> 6100000 | G38: =SUM(G6:G37) -> 9600000
B40: INTERNAL AUDIT
A41: 1 | B41: OSANAIYE DAVID AKINYEMI | C41: DIRECTOR INTERNAL AUDIT | D41: 17(8) | E41: 1000000 | F41: 0 | G41: 1000000
A42: 2 | B42: JAMILA ABDUL | C42: AUDITOR II | D42: 8(7) | E42: 300000 | F42: 300000 | G42: 0
C43: 2 | E43: =SUM(E41:E42) -> 1300000 | F43: =SUM(F41:F42) -> 300000 | G43: =SUM(G41:G42) -> 1000000
B45: LEG. SUPPORT SEVICES
A46: 1 | B46: PROF. EDOBA BRIGHT OMOREGBE | C46: AG. DLSS | D46: 17(9) | E46: 1000000 | F46: 0 | G46: 1000000
A47: 2 | B47: DR CLINTON JAJA | C47: SENIOR RESEARCH FELLOW | D47: 15(9) | E47: 700000 | F47: 0 | G47: 700000
A48: 3 | B48: BETHEL UZOMA IHUGBA | C48: SNR RESEARCH FELLOW | D48: 15(9) | E48: 700000 | F48: 0 | G48: 700000
A49: 4 | B49: OGUCHE SAMUEL | C49: SNR RESEARCH FELLOW | D49: 15(8) | E49: 700000 | F49: 0 | G49: 700000
A50: 5 | B50: IBRAHIM USMAN | C50: SNR RESEARCH FELLOW | D50: 15(7) | E50: 700000 | F50: 0 | G50: 700000
A51: 6 | B51: DR MOHAMMED O. AMALI | C51: RESEARCH FELLOW I | D51: 14(9) | E51: 500000 | F51: 0 | G51: 500000
A52: 7 | B52: YAHAYA SHAMSU | C52: RESEARCH FELLOW 1 | D52: 14(9) | E52: 500000 | F52: 0 | G52: 500000
A53: 8 | B53: OFORDEME ADAOBI JULIA | C53: RESEARCH FELLOW 1 | D53: 14(8) | E53: 500000 | F53: 0 | G53: 500000
A54: 9 | B54: DORIS DAKDA AARON | C54: RESEARCH FELLOW II | D54: 13(9) | E54: 500000 | F54: 500000 | G54: 0
A55: 10 | B55: ZAINAB AKINDE | C55: RESEARCH OFFICER | D55: 9(7) | E55: 300000 | F55: 300000 | G55: 0
A56: 11 | B56: ABDULLAHI AHMAD USMAN | C56: RESEARCH OFFICER | D56: 9(7) | E56: 300000 | F56: 300000 | G56: 0
A57: 12 | B57: GUNAT NANSAK MARK | C57: RESEARCH OFFICER | D57: 9(7) | E57: 300000 | F57: 300000 | G57: 0
B58: TOTAL | C58: 11 | E58: =SUM(E46:E57) -> 6700000 | F58: =SUM(F46:F57) -> 1400000 | G58: =SUM(G46:G57) -> 5300000
B60: LEGAL SERVICES
A61: 1 | B61: DR SHUIBU DANWANKA | C61: DIRECTOR LEGAL SERVICES | D61: 17(9) | E61: =1000000/2 -> 500000 | F61: 0 | G61: =1000000/2 -> 500000
B62: TOTAL | C62: 2 | E62: =SUM(E61) -> 500000 | F62: =SUM(F61) -> 0 | G62: =SUM(G61) -> 500000
B64: DEMOCRACY & GOVERNANCE
A65: 1 | B65: DR. ADEWALE ADEREMI | C65: DIRECTOR, DEMOCRATIC STUDIES | D65: 17(9) | E65: =1000000/2 -> 500000 | F65: 0 | G65: =1000000/2 -> 500000
A66: 2 | B66: NDANUSA MOHAMMED MANZUMA | C66: SNR RESEARCH FELLOW | D66: 15 (7) | E66: =700000/2 -> 350000 | F66: 0 | G66: =700000/2 -> 350000
A67: 3 | B67: EJALONIBU GANIYU LAYI | C67: RESEARCH FELLOW 11 | D67: 13(9) | E67: 500000 | F67: 500000 | G67: 0
A68: 4 | B68: LOHNA BONKAT JONATHAN | C68: RESEARCH FELLOW 11 | D68: 13(8) | E68: 500000 | F68: 500000 | G68: 0
A69: 5 | B69: YUNUSA ABDULLAHI | C69: RESEARCH FELLOW 1 | D69: 14(9) | E69: 500000 | F69: 0 | G69: 500000
A70: 6 | B70: UDEFUNA NNADOZIE PATRICK | C70: RESEARCH OFFICER | D70: 10(13) | E70: 300000 | F70: 300000 | G70: 0
A71: 7 | B71: OSOLAFIA MUHAMMAD EGYE | C71: PRINCIPAL RESEARCH OFFICER | D71: 12(8) | E71: 400000 | F71: 400000 | G71: 0
A72: 8 | B72: SHAFIU YAHYA MIKAIL | C72: PRINCIPAL RESEARCH OFFICER | D72: 12(7) | E72: 400000 | F72: 400000 | G72: 0
A73: 9 | B73: HASSAN YERIMA | C73: PRINCIPAL RESEARCH OFFICER | D73: 12(7) | E73: 400000 | F73: 400000 | G73: 0
A74: 10 | B74: HAUWA PATE SADIQ | C74: PRINCIPAL PROGRAMME OFFICER | D74: 12(7) | E74: 400000 | F74: 400000 | G74: 0
A75: 11 | B75: ABAYOMI KAYODE QUADRI | C75: RESEARCH OFFICER | D75: 10(7) | E75: 300000 | F75: 300000 | G75: 0
A76: 12 | B76: NNANDI LIVINUS ATURE | C76: RESEARCH ASSISTANT | D76: 9(7) | E76: 300000 | F76: 300000 | G76: 0
A77: 13 | B77: LUCKY AGWOM | C77: RESEARCH ASSISTANT | D77: 8(7) | E77: 300000 | F77: 300000 | G77: 0
B78: TOTAL | C78: 13 | E78: =SUM(E65:E77) -> 5150000 | F78: =SUM(F65:F77) -> 3800000 | G78: =SUM(G65:G77) -> 1350000
B80: DEPARTMENT OF STUDIES
A81: 1 | B81: DR ASIMIYU G. ABIOLA | C81: DIRECTOR POST GRADUATE | D81: 17(9) | E81: 1000000 | F81: 0 | G81: 1000000
A82: 2 | B82: USMAN WALI | C82: SENIOR RESEARCH FELLOW | D82: 15 (7) | E82: 700000 | F82: 0 | G82: 700000
A83: 3 | B83: MOSHOOD TOSHO AMUDA | C83: MANAGER, EXAMS & RECORDS | D83: 15 (7) | E83: =700000/2 -> 350000 | F83: 0 | G83: =700000/2 -> 350000
A84: 4 | B84: ANTHONY EDET | C84: ASST. MGR M&E | D84: 13(9) | E84: 500000 | F84: 500000 | G84: 0
A85: 5 | B85: IGWE STACY | C85: PROGRAMME OFFICER | D85: 10(7) | E85: 300000 | F85: 300000 | G85: 0
