Workbook

Sheet MAY 2024
A1: NATIONAL INSTITUTE FOR LEGISLATIVE AND DEMOCRATIC STUDIES
A2: STAFF PAYROLL FOR THE MONTH OF MAY, 2024
E3: ='[1]FEB 08'!E11/'[1]FEB 08'!M11 -> #REF!
B4: STAFF NAME | C4: DESIGNATION | D4: GRADE LEVEL | E4: BASIC SALARY | F4: ALLCE/ AREARS | G4: ALLOWANCE | H4: ALLOWANCE | I4: DUTY ALLCE | J4: GROSS SALARY | K4: AUCTION | L4: COOP CONTR/SPEC SAVINGS | M4: COOP. LOAN RECOVERY | N4: NHF DED. | O4: PAYE | P4: EMPLOYEE PENSIONS | Q4: TOTAL DEDUCTION | R4: APRIL, 2024 | S4: MAY, 2024
E5: N | G5: N | H5: N | I5: N | J5: N | K5: N | L5: N | M5: N | N5: N | O5: N | P5: N | Q5: N | R5: N | S5: N
A6: S/N | B6: DG'S OFFICE
A7: 1 | B7: PROF. ABUBAKAR O. SULAIMAN | C7: DIRECTOR GENERAL | D7: CONSOL | E7: 1659751.2 | G7: =250000 -> 250000 | I7: 25235 | J7: =E7+F7+G7+H7+I7 -> 1934986.2 | O7: 350184.01 | Q7: =O7+N7+M7+L7+K7+P7 -> 350184.01 | R7: 1584802.2 | S7: =J7-Q7 -> 1584802.2
A8: 2 | B8: RAHEEM USMAN AYIGORO | C8: SA-INFRASTRUCTURE | D8: 16 (9) | E8: 762373.17 | H8: =90000 -> 90000 | I8: =100000 -> 100000 | J8: =E8+F8+G8+H8+I8 -> 952373.17 | L8: =250000 -> 250000 | O8: ='Additional Leg Duty Allowance'!P7 -> 149812.26 | P8: 60989.853 | Q8: =O8+N8+M8+L8+K8+P8 -> 460802.12 | R8: 641571.05 | S8: =J8-Q8 -> 491571.05
A9: 3 | B9: MARIAM MOHAMMED BELLO | C9: SA- SPECIAL DUTIES | D9: 16 (9) | E9: 762373.17 | H9: =90000 -> 90000 | I9: =200000+100000 -> 300000 | J9: =E9+F9+G9+H9+I9 -> 1152373.2 | O9: ='Additional Leg Duty Allowance'!P8 -> 199922.31 | Q9: =O9+N9+M9+L9+K9+P9 -> 199922.31 | R9: 952450.85 | S9: =J9-Q9 -> 952450.85
A10: 4 | B10: DR IKEME ARTHUR J.O | C10: DEPUTY DIRECTOR, M&E | D10: 16 (9) | E10: 762373.17 | G10: 180000 | I10: 0 | J10: =E10+F10+G10+H10+I10 -> 942373.17 | L10: =50000 -> 50000 | M10: 103000 | N10: 10293.398 | O10: 147687.53 | P10: 60989.853 | Q10: =O10+N10+M10+L10+K10+P10 -> 371970.78 | R10: 570402.39 | S10: =J10-Q10 -> 570402.39
A11: 5 | B11: MOSHOOD M. OLALERE | C11: DEPUTY DIR. GENERAL SERVICE | D11: 16 (9) | E11: 762373.17 | H11: =80000+10000 -> 90000 | I11: =150000+100000 -> 250000 | J11: =E11+F11+G11+H11+I11 -> 1102373.2 | L11: =20000+60000 -> 80000 | M11: ='[2]OCTOBER 2023 '!$D$193 -> 230499.8 | N11: 10293.398 | O11: ='Additional Leg Duty Allowance'!P9 -> 178407.53 | P11: 60989.853 | Q11: =O11+N11+M11+L11+K11+P11 -> 560190.58 | R11: 542182.59 | S11: =J11-Q11 -> 542182.59
A12: 6 | B12: REKIYA IBRAHIM ATTAH | C12: DEPUTY DIRECTOR TRAINING | D12: 16 (9) | E12: 762373.17 | H12: =90000 -> 90000 | I12: =100000+100000 -> 200000 | J12: =E12+F12+G12+H12+I12 -> 1052373.2 | L12: =50000 -> 50000 | M12: =91666.67 -> 91666.67 | O12: ='Additional Leg Duty Allowance'!P10 -> 180722.31 | Q12: =O12+N12+M12+L12+K12+P12 -> 322388.98 | R12: 729984.18 | S12: =J12-Q12 -> 729984.18
A13: 7 | B13: ANDRAWUS MUSA | C13: ASST. DIRECTOR, STORES | D13: 15(9) | E13: 620675.58 | H13: =80000 -> 80000 | I13: 50000 | J13: =E13+F13+G13+H13+I13 -> 750675.58 | L13: =50000-40000 -> 10000 | M13: =90000+110000 -> 200000 | N13: 8380.2271 | O13: 113101.97 | P13: 49654.047 | Q13: =O13+N13+M13+L13+K13+P13 -> 381136.24 | R13: 369539.34 | S13: =J13-Q13 -> 369539.34
A14: 8 | B14: DR FRANCIS NDUM OJIE | C14: AD, TRAINING & IC./SA TO DG | D14: 15(7) | E14: 582118.08 | G14: 160000 | I14: =100000+100000 -> 200000 | J14: =E14+F14+G14+H14+I14 -> 942118.08 | N14: 7859.6313 | O14: ='Additional Leg Duty Allowance'!P12 -> 150463.11 | P14: 46569.447 | Q14: =O14+N14+M14+L14+K14+P14 -> 204892.19 | R14: 737225.9 | S14: =J14-Q14 -> 737225.9
A15: 9 | B15: ALI ABDULLAHI | C15: CHIEF ICT OFFICER | D15: 14(11) | E15: 484373.75 | H15: =70000 -> 70000 | I15: =0 -> 0 | J15: =E15+F15+G15+H15+I15 -> 554373.75 | O15: 77666.446 | P15: 38749.9 | Q15: =O15+N15+M15+L15+K15+P15 -> 116416.35 | R15: 437957.4 | S15: =J15-Q15 -> 437957.4
A16: 10 | B16: EMILY EKHIDE | C16: RESEARCH FELLOW 1 | D16: 14(10) | E16: 470498 | G16: 140000 | I16: =50000+100000 -> 150000 | J16: =E16+F16+G16+H16+I16 -> 760498 | L16: =50000 -> 50000 | O16: 98255.433 | P16: 37639.84 | Q16: =O16+N16+M16+L16+K16+P16 -> 185895.27 | R16: 574602.73 | S16: =J16-Q16 -> 574602.73
A17: 11 | B17: DORIS DAKDA AARON | C17: RESEARCH FELLOW I | D17: 14(8) | E17: 442746.5 | G17: =140000 -> 140000 | I17: =150000+100000 -> 250000 | J17: =E17+F17+G17+H17+I17 -> 832746.5 | L17: 70000 | O17: ='Additional Leg Duty Allowance'!P13 -> 131753.41 | P17: 35419.72 | Q17: =O17+N17+M17+L17+K17+P17 -> 237173.13 | R17: 595573.37 | S17: =J17-Q17 -> 595573.37
A18: 12 | B18: ABDULSALAM S. MUSTAPHA | C18: ASST. MANAGER ICT | D18: 13(11) | E18: 441804.92 | H18: 70000 | J18: =E18+F18+G18+H18+I18 -> 511804.92 | O18: 70147.087 | P18: 35344.393 | Q18: =O18+N18+M18+L18+K18+P18 -> 105491.48 | R18: 406313.44 | S18: =J18-Q18 -> 406313.44
A19: 13 | B19: PERCY TERFA GBAHABO | C19: HEAD, NILDS LIAISON OFFICE | D19: 13(10) | E19: 428915.92 | G19: =120000 -> 120000 | I19: 0 | J19: =E19+F19+G19+H19+I19 -> 548915.92 | L19: =50000 -> 50000 | M19: 105000 | O19: 77470.374 | P19: 34313.273 | Q19: =O19+N19+M19+L19+K19+P19 -> 266783.65 | R19: 282132.27 | S19: =J19-Q19 -> 282132.27
A20: 14 | B20: HASSANA AHMED IBRAHIM | C20: PA- TO DG | D20: 13 (9) | E20: 416026.92 | G20: =120000 -> 120000 | I20: =100000+100000 -> 200000 | J20: =E20+F20+G20+H20+I20 -> 736026.92 | L20: =30000-20000 -> 10000 | M20: =95833.33 -> 95833.33 | N20: 5607.1771 | O20: ='Additional Leg Duty Allowance'!P14 -> 113474.9 | P20: 33282.153 | Q20: =O20+N20+M20+L20+K20+P20 -> 258197.56 | R20: 477829.35 | S20: =J20-Q20 -> 477829.35
A21: 15 | B21: ADUGBA RICHARD TERSEER | C21: PRINCIPAL INFO. OFFICER | D21: 12(9) | E21: 377895.17 | H21: =60000 -> 60000 | I21: 100000 | J21: =E21+F21+G21+H21+I21 -> 537895.17 | L21: =20000+30000 -> 50000 | M21: =111833.33 -> 111833.33 | O21: 76138.069 | P21: 30231.613 | Q21: =O21+N21+M21+L21+K21+P21 -> 268203.01 | R21: 269692.15 | S21: =J21-Q21 -> 269692.15
A22: 16 | B22: LUCKY AGWOM | C22: RESEARCH ASSISTANT | D22: 12(7) | E22: 353512.5 | G22: =100000 -> 100000 | I22: =100000+100000 -> 200000 | J22: =E22+F22+G22+H22+I22 -> 653512.5 | L22: =50000+100000 -> 150000 | O22: ='Additional Leg Duty Allowance'!P15 -> 98711.115 | P22: 28281 | Q22: =O22+N22+M22+L22+K22+P22 -> 276992.11 | R22: 376520.39 | S22: =J22-Q22 -> 376520.39
A23: 17 | B23: IDRIS IBRAHIM | C23: PRINCIPAL RESEARCH OFFICER | D23: 12(7) | E23: 353512.5 | G23: 110000 | I23: 0 | J23: =E23+F23+G23+H23+I23 -> 463512.5 | L23: 0 | O23: 62231.115 | P23: 28281 | Q23: =O23+N23+M23+L23+K23+P23 -> 90512.115 | R23: 373000.39 | S23: =J23-Q23 -> 373000.39
A24: 18 | B24: FARUQ ATOFARATI | C24: PA (SPECIAL DUTIES) TO DG | D24: 10(7) | E24: 293029.67 | H24: =50000+10000 -> 60000 | I24: =100000+100000 -> 200000 | J24: =E24+F24+G24+H24+I24 -> 553029.67 | L24: 130000 | O24: ='Additional Leg Duty Allowance'!P16 -> 80347.427 | P24: 23442.373 | Q24: =O24+N24+M24+L24+K24+P24 -> 233789.8 | R24: 319239.87 | S24: =J24-Q24 -> 319239.87
A25: 19 | B25: ELIZABETH OGECHUKWU ONYEAKU | C25: ICT OFFICER | D25: 9(9) | E25: 270481.67 | H25: =50000+10000 -> 60000 | J25: =E25+F25+G25+H25+I25 -> 330481.67 | L25: 10000 | M25: =20000 -> 20000 | O25: 39052.313 | P25: 21638.533 | Q25: =O25+N25+M25+L25+K25+P25 -> 90690.846 | R25: 239790.82 | S25: =J25-Q25 -> 239790.82
A26: 20 | B26: VICTOR ASUKWO | C26: ICT OFFICER | D26: 9(9) | E26: 270481.67 | H26: =50000+10000 -> 60000 | J26: =E26+F26+G26+H26+I26 -> 330481.67 | O26: 39052.313 | P26: 21638.533 | Q26: =O26+N26+M26+L26+K26+P26 -> 60690.846 | R26: 269790.82 | S26: =J26-Q26 -> 269790.82
A27: 21 | B27: NNANDI LIVINUS ATURE | C27: RESEARCH ASSISTANT | D27: 9(9) | E27: 270481.67 | G27: =100000 -> 100000 | J27: =E27+F27+G27+H27+I27 -> 370481.67 | L27: =10000 -> 10000 | M27: =95833.33 -> 95833.33 | O27: 45772.313 | P27: 21638.533 | Q27: =O27+N27+M27+L27+K27+P27 -> 173244.18 | R27: 197237.49 | S27: =J27-Q27 -> 197237.49
A28: 22 | B28: ABDULRAHMAN A SULAIMAN | C28: STORE OFFICER | D28: 9(8) | E28: 263165.33 | H28: =60000 -> 60000 | J28: =E28+F28+G28+H28+I28 -> 323165.33 | L28: =20000 -> 20000 | M28: =17500 -> 17500 | O28: 37921.501 | P28: 21053.227 | Q28: =O28+N28+M28+L28+K28+P28 -> 96474.727 | R28: 226690.61 | S28: =J28-Q28 -> 226690.61
A29: 23 | B29: DARE SHEU MAGBON | C29: ADMINISTRATION OFFICER | D29: 9(7) | E29: 255849 | H29: =60000 -> 60000 | J29: =E29+F29+G29+H29+I29 -> 315849 | L29: =30000+20000 -> 50000 | M29: 0 | O29: 36790.688 | P29: 20467.92 | Q29: =O29+N29+M29+L29+K29+P29 -> 107258.61 | R29: 208590.39 | S29: =J29-Q29 -> 208590.39
A30: 24 | B30: ABUBAKAR SULAIMAN SODEEQ | C30: ADMINISTRATION OFFICER | D30: 9(7) | E30: 255849 | H30: =60000 -> 60000 | J30: =E30+F30+G30+H30+I30 -> 315849 | M30: 0 | O30: 36790.688 | P30: 20467.92 | Q30: =O30+N30+M30+L30+K30+P30 -> 57258.608 | R30: 258590.39 | S30: =J30-Q30 -> 258590.39
A31: 25 | B31: JIMOH ADEBAYO ZAKA | C31: ASST. OFFICER/COMM | D31: 9(9) | E31: 270481.67 | H31: =60000 -> 60000 | J31: =E31+F31+G31+H31+I31 -> 330481.67 | L31: =50000+50000 -> 100000 | M31: 50000 | O31: 39052.313 | P31: 21638.533 | Q31: =O31+N31+M31+L31+K31+P31 -> 210690.85 | R31: 119790.82 | S31: =J31-Q31 -> 119790.82
A32: 26 | B32: MOHAMMED BELLO | C32: PROTOCOL ASSISTANT | D32: 8(9) | E32: 230631.92 | H32: =50000 -> 50000 | J32: =E32+F32+G32+H32+I32 -> 280631.92 | L32: =0 -> 0 | M32: =26666.67 -> 26666.67 | O32: 31213.136 | P32: 18450.553 | Q32: =O32+N32+M32+L32+K32+P32 -> 76330.359 | R32: 204301.56 | S32: =J32-Q32 -> 204301.56
A33: 27 | B33: HARUNA JIBRIL AMEH | C33: ASST. ADMIN. OFFICER | D33: 8(8) | E33: 224459.75 | H33: 50000 | J33: =E33+F33+G33+H33+I33 -> 274459.75 | L33: 20000 | M33: 0 | O33: 30259.166 | P33: 17956.78 | Q33: =O33+N33+M33+L33+K33+P33 -> 68215.946 | R33: 206243.8 | S33: =J33-Q33 -> 206243.8
B34: TOTAL | C34: 27 | E34: 13048608 | F34: =SUM(F7:F33) -> 0 | G34: =SUM(G7:G33) -> 1420000 | H34: =SUM(H7:H33) -> 1160000 | I34: =SUM(I7:I33) -> 2225235 | J34: =SUM(J7:J33) -> 17853843 | K34: =SUM(K7:K33) -> 0 | L34: =SUM(L7:L33) -> 1160000 | M34: =SUM(M7:M33) -> 1147833.1 | ... Q34: =SUM(Q7:Q33) -> 5831796.7 | R34: 12172047 | S34: =SUM(S7:S33) -> 12022047
B36: INTERNAL AUDIT
A37: 1 | B37: OSANAIYE DAVID AKINYEMI | C37: DIRECTOR INTERNAL AUDIT | D37: 17(9) | E37: 1435720 | H37: =100000 -> 100000 | J37: =SUM(E37:I37) -> 1535720 | K37: ='MAY 2024'!F196 -> 0 | L37: =200000+200000 -> 400000 | M37: 0 | O37: 251472.25 | P37: 114857.6 | Q37: =O37+N37+M37+L37+K37+P37 -> 766329.85 | R37: 769390.15 | S37: =J37-Q37 -> 769390.15
A38: 2 | B38: JAMILA ABDUL | C38: SENIOR INTERNAL AUDITOR | D38: 10(7) | E38: 293029.67 | H38: =60000 -> 60000 | J38: =SUM(E38:I38) -> 353029.67 | L38: =20000 -> 20000 | O38: 42537.332 | P38: 23442.373 | Q38: =O38+N38+M38+L38+K38+P38 -> 85979.705 | R38: 267049.96 | S38: =J38-Q38 -> 267049.96
A39: 3 | B39: IJEOMA EWELUKWA | C39: SENIOR INTERNAL AUDITOR | D39: 10(8) | E39: 300965.58 | H39: =50000+10000 -> 60000 | J39: =SUM(E39:I39) -> 360965.58 | L39: =10000 -> 10000 | O39: 43763.907 | P39: 24077.247 | Q39: =O39+N39+M39+L39+K39+P39 -> 77841.154 | R39: 283124.43 | S39: =J39-Q39 -> 283124.43
C40: 3 | E40: 2029715.2 | F40: =SUM(F37:F39) -> 0 | G40: =SUM(G37:G39) -> 0 | H40: =SUM(H37:H39) -> 220000 | I40: =SUM(I37:I39) -> 0 | J40: =SUM(J37:J39) -> 2249715.2 | K40: =SUM(K37:K39) -> 0 | L40: =SUM(L37:L39) -> 430000 | M40: =SUM(M37:M39) -> 0 | N40: 0 | O40: 337773.49 | P40: =SUM(P37:P39) -> 162377.22 | Q40: =SUM(Q37:Q39) -> 930150.71 | R40: 1319564.5 | S40: =SUM(S37:S39) -> 1319564.5
B42: LEG. SUPPORT SEVICES
A43: 1 | B43: PROF. EDOBA BRIGHT OMOREGBE | C43: AG. DLSS | D43: 17(9) | E43: 1435720 | G43: =200000 -> 200000 | J43: =SUM(E43:I43) -> 1635720 | L43: =400000 -> 400000 | M43: 0 | O43: 270672.25 | P43: 114857.6 | Q43: =O43+N43+M43+L43+K43+P43 -> 785529.85 | R43: 1050190.2 | S43: =J43-Q43 -> 850190.15
A44: 2 | B44: DR CLINTON JAJA | C44: SENIOR RESEARCH FELLOW | D44: 15(9) | E44: 620675.58 | G44: =160000 -> 160000 | I44: 0 | J44: =SUM(E44:I44) -> 780675.58 | L44: =50000 -> 50000 | M44: =385000 -> 385000 | O44: 119022.8 | P44: 49654.047 | Q44: =O44+N44+M44+L44+K44+P44 -> 603676.85 | R44: 176998.73 | S44: =J44-Q44 -> 176998.73
A45: 3 | B45: BETHEL UZOMA IHUGBA | C45: DEPUTY DIRECTOR, LEGAL RESEARCH | D45: 16(8) | E45: 739203.58 | G45: =180000 -> 180000 | J45: =SUM(E45:I45) -> 919203.58 | L45: =80000+23000 -> 103000 | M45: =246905.96 -> 246905.96 | O45: 143799.59 | P45: 59136.287 | Q45: =O45+N45+M45+L45+K45+P45 -> 552841.83 | R45: 366361.75 | S45: =J45-Q45 -> 366361.75
A46: 4 | B46: OGUCHE SAMUEL | C46: SNR RESEARCH FELLOW | D46: 15(9) | E46: 620675.58 | G46: =160000 -> 160000 | J46: =SUM(E46:I46) -> 780675.58 | L46: =30000 -> 30000 | M46: 223059.88 | O46: 119022.8 | P46: 49654.047 | Q46: =O46+N46+M46+L46+K46+P46 -> 421736.73 | R46: 405709.85 | S46: =J46-Q46 -> 358938.85
A47: 5 | B47: IBRAHIM USMAN | C47: SNR RESEARCH FELLOW | D47: 15(9) | E47: 620675.58 | G47: =140000+20000 -> 160000 | I47: 0 | J47: =SUM(E47:I47) -> 780675.58 | N47: ='New NHF Deduction'!G48 -> 8380.2271 | O47: 118861.97 | P47: 49654.047 | Q47: =O47+N47+M47+L47+K47+P47 -> 176896.24 | R47: 603779.34 | S47: =J47-Q47 -> 603779.34
A48: 6 | B48: DR MOHAMMED O. AMALI | C48: SNR RESEARCH FELLOW | D48: 15(7) | E48: 582118.08 | G48: =140000+20000 -> 160000 | J48: =SUM(E48:I48) -> 742118.08 | L48: =15000 -> 15000 | M48: =216666.67 -> 216666.67 | O48: 112212 | P48: 46569.447 | Q48: =O48+N48+M48+L48+K48+P48 -> 390448.12 | R48: 351669.96 | S48: =J48-Q48 -> 351669.96
A49: 7 | B49: YAHAYA SHAMSU | C49: RESEARCH FELLOW 1 | D49: 14(10) | E49: 470498 | G49: =140000 -> 140000 | J49: =SUM(E49:I49) -> 610498 | N49: 0 | O49: 88655.433 | P49: 37639.84 | Q49: =O49+N49+M49+L49+K49+P49 -> 126295.27 | R49: 484202.73 | S49: =J49-Q49 -> 484202.73
A50: 8 | B50: BILKIS S. LAWAL-GAMBARI | C50: RESEARCH OFFICER | D50: 10(8) | E50: 300965.58 | G50: 100000 | J50: =SUM(E50:I50) -> 400965.58 | O50: 51029.227 | P50: 24077.247 | Q50: =O50+N50+M50+L50+K50+P50 -> 75106.474 | R50: 325859.11 | S50: =J50-Q50 -> 325859.11
A51: 9 | B51: ZAINAB AKINDE | C51: RESEARCH OFFICER | D51: 9(8) | E51: 263165.33 | G51: =100000 -> 100000 | J51: =SUM(E51:I51) -> 363165.33 | O51: 44641.501 | P51: 21053.227 | Q51: =O51+N51+M51+L51+K51+P51 -> 65694.727 | R51: 297470.61 | S51: =J51-Q51 -> 297470.61
A52: 10 | B52: ABDULLAHI AHMAD USMAN | C52: RESEARCH OFFICER | D52: 9(8) | E52: 263165.33 | G52: =100000 -> 100000 | J52: =SUM(E52:I52) -> 363165.33 | O52: 44641.501 | P52: 21053.227 | Q52: =O52+N52+M52+L52+K52+P52 -> 65694.727 | R52: 297470.61 | S52: =J52-Q52 -> 297470.61
A53: 11 | B53: GUNAT NANSAK MARK | C53: RESEARCH OFFICER | D53: 9(8) | E53: 263165.33 | G53: =100000 -> 100000 | J53: =SUM(E53:I53) -> 363165.33 | O53: 44641.501 | P53: 21053.227 | Q53: =O53+N53+M53+L53+K53+P53 -> 65694.727 | R53: 297470.61 | S53: =J53-Q53 -> 297470.61
B54: TOTAL | C54: 11 | E54: 6180028 | G54: =SUM(G43:G53) -> 1560000 | H54: =SUM(H43:H53) -> 0 | I54: =SUM(I43:I53) -> 0 | J54: =SUM(J43:J53) -> 7740028 | K54: =SUM(K43:K53) -> 0 | L54: =SUM(L43:L53) -> 598000 | M54: =SUM(M43:M53) -> 1071632.5 | N54: =SUM(N43:N53) -> 8380.2271 | O54: 1157200.6 | P54: 494402.24 | Q54: =SUM(Q43:Q53) -> 3329615.5 | R54: 4657183.5 | S54: =SUM(S43:S53) -> 4410412.5
B56: LEGAL SERVICES
A57: 1 | B57: DR SHUIBU DANWANKA | C57: DIRECTOR LEGAL SERVICES | D57: 17(9) | E57: 1435720 | G57: =200000 -> 200000 | I57: 0 | J57: =SUM(E57:I57) -> 1635720 | L57: 120000 | N57: 0 | O57: 270672.25 | P57: 114857.6 | Q57: =O57+N57+M57+L57+K57+P57 -> 505529.85 | R57: 1130190.2 | S57: =J57-Q57 -> 1130190.2
A58: 2 | B58: ABDULSALAM BAKO | C58: MANAGER, LEGAL SERVICES | D58: 15 (9) | E58: 620675.58 | H58: 80000 | J58: =SUM(E58:I58) -> 700675.58 | L58: 50000 | M58: 145000 | N58: 0 | O58: 103662.8 | P58: 49654.047 | Q58: =O58+N58+M58+L58+K58+P58 -> 348316.85 | R58: 352358.73 | S58: =J58-Q58 -> 352358.73
B59: TOTAL | C59: 2 | E59: 2056395.6 | G59: =SUM(G57:G58) -> 200000 | H59: =SUM(H57:H58) -> 80000 | I59: =SUM(I57:I58) -> 0 | J59: =SUM(J57:J58) -> 2336395.6 | K59: =SUM(K57:K58) -> 0 | L59: =SUM(L57:L58) -> 170000 | M59: =SUM(M57:M58) -> 145000 | N59: 0 | O59: 374335.05 | P59: 164511.65 | Q59: =SUM(Q57:Q58) -> 853846.7 | R59: 1482548.9 | S59: =SUM(S57:S58) -> 1482548.9
B61: DEMOCRACY & GOVERNANCE
A62: 1 | B62: DR. ADEWALE ADEREMI | C62: DIRECTOR, DEMOCRATIC STUDIES | D62: 17(9) | E62: 1435720 | G62: =200000 -> 200000 | I62: 0 | J62: =SUM(E62:I62) -> 1635720 | L62: 100000 | M62: 800000 | O62: 292724.91 | Q62: =O62+N62+M62+L62+K62+P62 -> 1192724.9 | R62: 442995.09 | S62: =J62-Q62 -> 442995.09
A63: 2 | B63: NDANUSA MOHAMMED MANZUMA | C63: SNR RESEARCH FELLOW | D63: 15(8) | E63: 601396.83 | G63: =160000 -> 160000 | I63: 0 | J63: =SUM(E63:I63) -> 761396.83 | L63: =100000 -> 100000 | M63: =131250 -> 131250 | O63: 115617.4 | P63: 48111.747 | Q63: =O63+N63+M63+L63+K63+P63 -> 394979.15 | R63: 366417.68 | S63: =J63-Q63 -> 366417.68
A64: 3 | B64: EJALONIBU GANIYU LAYI | C64: RESEARCH FELLOW 1 | D64: 14(8) | E64: 442746.5 | G64: 140000 | J64: =SUM(E64:I64) -> 582746.5 | L64: =110000+90000 -> 200000 | O64: 83753.408 | P64: 35419.72 | Q64: =O64+N64+M64+L64+K64+P64 -> 319173.13 | R64: 263573.37 | S64: =J64-Q64 -> 263573.37
A65: 4 | B65: LOHNA BONKAT JONATHAN | C65: RESEARCH FELLOW 11 | D65: 13(10) | E65: 428915.92 | G65: =120000 -> 120000 | I65: 0 | J65: =SUM(E65:I65) -> 548915.92 | L65: =20000+65000+65000 -> 150000 | M65: 0 | N65: 0 | O65: 77470.374 | P65: 34313.273 | Q65: =O65+N65+M65+L65+K65+P65 -> 261783.65 | R65: 287132.27 | S65: =J65-Q65 -> 287132.27
A66: 5 | B66: YUNUSA ABDULLAHI | C66: RESEARCH FELLOW 1 | D66: 14(11) | E66: 484373.75 | G66: =140000 -> 140000 | J66: =SUM(E66:I66) -> 624373.75 | L66: =10000+40000 -> 50000 | M66: =54585.66 -> 54585.66 | O66: 91106.446 | P66: 38749.9 | Q66: =O66+N66+M66+L66+K66+P66 -> 234442.01 | R66: 389931.74 | S66: =J66-Q66 -> 389931.74
A67: 7 | B67: UDEFUNA NNADOZIE PATRICK | C67: RESEARCH OFFICER | D67: 12(8) | E67: 365703.83 | G67: =110000 -> 110000 | I67: 0 | J67: =SUM(E67:I67) -> 475703.83 | L67: 50000 | M67: =65885.83 -> 65885.83 | O67: 64384.592 | P67: 29256.307 | Q67: =O67+N67+M67+L67+K67+P67 -> 209526.73 | R67: 266177.1 | S67: =J67-Q67 -> 266177.1
A68: 8 | B68: SHAFIU YAHYA MIKAIL | C68: PRINCIPAL RESEARCH OFFICER | D68: 12(8) | E68: 365703.83 | G68: =110000 -> 110000 | I68: 0 | J68: =SUM(E68:I68) -> 475703.83 | L68: =52000-2000 -> 50000 | O68: 64384.592 | P68: 29256.307 | Q68: =O68+N68+M68+L68+K68+P68 -> 143640.9 | R68: 332062.93 | S68: =J68-Q68 -> 332062.93
A69: 9 | B69: HASSAN YERIMA | C69: PRINCIPAL RESEARCH OFFICER | D69: 12(8) | E69: 365703.83 | G69: =110000 -> 110000 | I69: 0 | J69: =SUM(E69:I69) -> 475703.83 | L69: =67000-2000 -> 65000 | O69: 64384.592 | P69: 29256.307 | Q69: =O69+N69+M69+L69+K69+P69 -> 158640.9 | R69: 317062.93 | S69: =J69-Q69 -> 317062.93
A70: 10 | B70: HAUWA PATE SADIQ | C70: PRINCIPAL PROGRAMME OFFICER | D70: 12(9) | E70: 377895.17 | G70: =110000 -> 110000 | J70: =SUM(E70:I70) -> 487895.17 | L70: =80000+20000 -> 100000 | O70: 66538.069 | P70: 30231.613 | Q70: =O70+N70+M70+L70+K70+P70 -> 196769.68 | R70: 291125.48 | S70: =J70-Q70 -> 291125.48
A71: 11 | B71: KOLAPO Q. ABAYOMI | C71: RESEARCH OFFICER | D71: 10(8) | E71: 300965.58 | G71: 100000 | J71: =SUM(E71:I71) -> 400965.58 | O71: 51029.227 | P71: 24077.247 | Q71: =O71+N71+M71+L71+K71+P71 -> 75106.474 | R71: 325859.11 | S71: =J71-Q71 -> 325859.11
B72: TOTAL | C72: 12 | E72: 5169125.2 | G72: =SUM(G62:G71) -> 1300000 | H72: =SUM(H62:H71) -> 0 | I72: =SUM(I62:I71) -> 0 | J72: =SUM(J62:J71) -> 6469125.2 | K72: =SUM(K62:K71) -> 0 | L72: =SUM(L62:L71) -> 865000 | M72: =SUM(M62:M71) -> 1051721.5 | N72: 0 | O72: 971393.61 | P72: 298672.42 | Q72: =SUM(Q62:Q71) -> 3186787.5 | R72: 3282337.7 | S72: =SUM(S62:S71) -> 3282337.7
B74: DEPARTMENT OF STUDIES
A75: 1 | B75: DR ASIMIYU G. ABIOLA | C75: DIRECTOR POST GRADUATE | D75: 17(9) | E75: 1435720 | G75: =200000 -> 200000 | I75: 0 | J75: =SUM(E75:I75) -> 1635720 | L75: 250000 | M75: =0 -> 0 | N75: 0 | O75: 270672.25 | P75: 114857.6 | Q75: =O75+N75+M75+L75+K75+P75 -> 635529.85 | R75: 1000190.2 | S75: =J75-Q75 -> 1000190.2
A76: 2 | B76: USMAN WALI | C76: SENIOR RESEARCH FELLOW | D76: 15 (8) | E76: 601396.83 | G76: =160000 -> 160000 | I76: 0 | J76: =SUM(E76:I76) -> 761396.83 | N76: 0 | O76: 124854.86 | Q76: =O76+N76+M76+L76+K76+P76 -> 124854.86 | R76: 636541.97 | S76: =J76-Q76 -> 636541.97
A77: 3 | B77: AYOBOLU OLAJIDE OLUFUNSHO | C77: ASST.DIR., INFORMATION | D77: 15 (9) | E77: 620675.58 | G77: 160000 | I77: 0 | J77: =SUM(E77:I77) -> 780675.58 | L77: =50000 -> 50000 | M77: =59583.33 -> 59583.33 | O77: =128556.38 -> 128556.38 | Q77: =O77+N77+M77+L77+K77+P77 -> 238139.71 | R77: 995015.87 | S77: =J77-Q77 -> 542535.87
A78: 4 | B78: ANTHONY EDET | C78: CHIEF PROGRAMMES OFFICER | D78: 14(9) | E78: 456622.25 | G78: =140000 -> 140000 | I78: 0 | J78: =SUM(E78:I78) -> 596622.25 | L78: 20000 | M78: 210785.51 | N78: ='New NHF Deduction'!G79 -> 6154.3229 | O78: 86076.104 | P78: 36529.78 | Q78: =O78+N78+M78+L78+K78+P78 -> 359545.72 | R78: 351197.39 | S78: =J78-Q78 -> 237076.53
A79: 5 | B79: IGWE STACY | C79: PROGRAMME OFFICER | D79: 10(9) | E79: 308901.5 | G79: =100000 -> 100000 | J79: =SUM(E79:I79) -> 408901.5 | L79: =50000 -> 50000 | M79: =50000 -> 50000 | O79: 52431.028 | P79: 24712.12 | Q79: =O79+N79+M79+L79+K79+P79 -> 177143.15 | R79: 231758.35 | S79: =J79-Q79 -> 231758.35
A80: 6 | B80: OLANIYAN TAIWO ABINBOLA | C80: PROGRAMME OFFICER | D80: 9(8) | E80: 263165.33 | G80: 100000 | J80: =SUM(E80:I80) -> 363165.33 | O80: 44641.501 | P80: 21053.227 | Q80: =O80+N80+M80+L80+K80+P80 -> 65694.727 | R80: 297470.61 | S80: =J80-Q80 -> 297470.61
A81: 7 | B81: AMINAT JUMOKE SULAIMON | C81: AST. PROGRAMME OFFICER | D81: 8(8) | E81: 224459.75 | G81: 100000 | H81: 0 | J81: =SUM(E81:I81) -> 324459.75 | L81: 20000 | M81: 0 | N81: 0 | O81: 38659.166 | P81: 17956.78 | Q81: =O81+N81+M81+L81+K81+P81 -> 76615.946 | R81: 247843.8 | S81: =J81-Q81 -> 247843.8
B82: TOTAL | C82: 7 | E82: 3910941.3 | F82: =SUM(F75:F81) -> 0 | G82: =SUM(G75:G81) -> 960000 | H82: =SUM(H75:H81) -> 0 | I82: =SUM(I75:I81) -> 0 | J82: =SUM(J75:J81) -> 4870941.2 | K82: =SUM(K75:K81) -> 0 | L82: =SUM(L75:L81) -> 390000 | M82: =SUM(M75:M81) -> 320368.84 | ... O82: =SUM(O75:O81) -> 745891.28 | P82: 215109.51 | Q82: =SUM(Q75:Q81) -> 1677524 | R82: 3760018.2 | S82: =SUM(S75:S81) -> 3193417.3
B84: ECON. DEV. & SOC. RESEARCH
A85: 1 | B85: TERFA WILLIAMS ABRAHAM | C85: SNR RESEARCH FELLOW | D85: 15(9) | E85: 620675.58 | G85: =160000 -> 160000 | I85: =100000+100000 -> 200000 | J85: =SUM(E85:I85) -> 980675.58 | O85: ='Additional Leg Duty Allowance'!P11 -> 157422.8 | P85: 49654.047 | Q85: =O85+N85+M85+L85+K85+P85 -> 207076.85 | R85: 773598.73 | S85: =J85-Q85 -> 773598.73
A86: 2 | B86: DR AUGUSTINE C. OSIGWE | C86: SNR RESEARCH FELLOW | D86: 15(9) | E86: 620675.58 | G86: =160000 -> 160000 | J86: =SUM(E86:I86) -> 780675.58 | L86: =30000 -> 30000 | M86: 98750 | N86: ='New NHF Deduction'!G87 -> 8380.2271 | O86: 118861.97 | P86: 49654.047 | Q86: =O86+N86+M86+L86+K86+P86 -> 305646.24 | R86: 475029.34 | S86: =J86-Q86 -> 475029.34
A87: 3 | B87: OMOJU OLUWASOLA EMMANUEL | C87: SNR RESEARCH FELLOW | D87: 15(7) | E87: 582118.08 | G87: 160000 | J87: =SUM(E87:I87) -> 742118.08 | L87: =50000 -> 50000 | M87: =79861.11 -> 79861.11 | O87: 112212 | P87: 46569.447 | Q87: =O87+N87+M87+L87+K87+P87 -> 288642.56 | R87: 453475.52 | S87: =J87-Q87 -> 453475.52
A88: 4 | B88: IBE EZECHI CYRIACUS | C88: RESEARCH FELLOW II | D88: 13(11) | E88: 441804.92 | G88: =120000 -> 120000 | I88: 0 | J88: =SUM(E88:I88) -> 561804.92 | L88: =50000 -> 50000 | M88: =77638.89 -> 77638.89 | O88: 79747.087 | P88: 35344.393 | Q88: =O88+N88+M88+L88+K88+P88 -> 242730.37 | R88: 319074.55 | S88: =J88-Q88 -> 319074.55
A89: 5 | B89: OSIKHEN LEO IGBANOI | C89: RESEARCH FELLOW 11 | D89: 13(10) | E89: 428915.92 | G89: =120000 -> 120000 | I89: 0 | J89: =SUM(E89:I89) -> 548915.92 | L89: 50000 | M89: 0 | O89: 77470.374 | P89: 34313.273 | Q89: =O89+N89+M89+L89+K89+P89 -> 161783.65 | R89: 387132.27 | S89: =J89-Q89 -> 387132.27
A90: 6 | B90: OKUNGBOWA OSARETIN GODSPOWER | C90: RESEARCH FELLOW 1 | D90: 14(7) | E90: 428870.75 | G90: =140000 -> 140000 | I90: 0 | J90: =SUM(E90:I90) -> 568870.75 | L90: =100000-100000 -> 0 | O90: 81302.396 | P90: 34309.66 | Q90: =O90+N90+M90+L90+K90+P90 -> 115612.06 | R90: 453258.69 | S90: =J90-Q90 -> 453258.69
A91: 7 | B91: YUSUF IBRAHIM | C91: PRINCIPAL RESEARCH OFFICER | D91: 12(8) | E91: 365703.83 | G91: =110000 -> 110000 | I91: 0 | J91: =SUM(E91:I91) -> 475703.83 | L91: =20000 -> 20000 | M91: 43750 | O91: 64384.592 | P91: 29256.307 | Q91: =O91+N91+M91+L91+K91+P91 -> 157390.9 | R91: 318312.93 | S91: =J91-Q91 -> 318312.93
A92: 8 | B92: MUSTAPHA RAFIU AYOBANJI | C92: RESEARCH FELLOW 11 | D92: 13(7) | E92: 390248.92 | G92: 120000 | I92: 0 | J92: =SUM(E92:I92) -> 510248.92 | L92: 0 | N92: ='New NHF Deduction'!G93 -> 5259.7438 | O92: 70529.475 | P92: 31219.913 | Q92: =O92+N92+M92+L92+K92+P92 -> 107009.13 | R92: 403239.78 | S92: =J92-Q92 -> 403239.78
A93: 9 | B93: MARYAM MUSA SADA | C93: ASSIT. RESEARCH OFFICER | D93: 10(8) | E93: 300965.58 | G93: 100000 | J93: =SUM(E93:I93) -> 400965.58 | O93: 51029.227 | P93: 24077.247 | Q93: =O93+N93+M93+L93+K93+P93 -> 75106.474 | R93: 325859.11 | S93: =J93-Q93 -> 325859.11
A94: 10 | B94: CHARITY EZENWAJIOBI | C94: REASEARCH. ASST. | D94: 8(9) | E94: 230631.92 | G94: =100000 -> 100000 | J94: =SUM(E94:I94) -> 330631.92 | L94: 50000 | N94: 0 | O94: 39613.136 | P94: 18450.553 | Q94: =O94+N94+M94+L94+K94+P94 -> 108063.69 | R94: 222568.23 | S94: =J94-Q94 -> 222568.23
B95: TOTAL | C95: 11 | E95: 4410611.1 | G95: =SUM(G85:G94) -> 1290000 | H95: =SUM(H85:H94) -> 0 | I95: =SUM(I85:I94) -> 200000 | J95: =SUM(J85:J94) -> 5900611.1 | K95: =SUM(K85:K94) -> 0 | L95: =SUM(L85:L94) -> 250000 | M95: =SUM(M85:M94) -> 300000 | N95: =SUM(N85:N94) -> 13639.971 | O95: =SUM(O85:O94) -> 852573.06 | P95: 352848.89 | Q95: =SUM(Q85:Q94) -> 1769061.9 | R95: 4131549.2 | S95: =SUM(S85:S94) -> 4131549.2
B97: TRAINING & INT''L COOP
A98: 1 | B98: AKINSANMI ADEJOKE OLUKEMI | C98: Ag. DIR. TRAINING & IC | D98: 17(7) | E98: ='[3]Annual & Monthly'!$H$44 -> 1352042.7 | H98: =100000 -> 100000 | J98: =E98+F98+G98+H98+I98 -> 1452042.7 | L98: =0 -> 0 | M98: 0 | N98: ='New NHF Deduction'!G99 -> 18254.975 | O98: ='March New PAYE '!Z93 -> 236486.75 | P98: ='Upgrade in March'!P8 -> 114857.6 | Q98: =O98+N98+M98+L98+K98+P98 -> 369599.32 | R98: 1082443.3 | S98: =J98-Q98 -> 1082443.3
A99: 2 | B99: MOHAMMED R. ADAMU | C99: CHIEF TRAINING OFFICER | D99: 14(9) | E99: 456622.25 | H99: 70000 | I99: 0 | J99: =E99+F99+G99+H99+I99 -> 526622.25 | L99: =10000 -> 10000 | M99: 175000 | O99: 72764.421 | P99: 36529.78 | Q99: =O99+N99+M99+L99+K99+P99 -> 294294.2 | R99: 232328.05 | S99: =J99-Q99 -> 232328.05
A100: 3 | B100: OKECHUKWU UCHENNA HULDA | C100: PRINCIPALTRAINING OFFICER | D100: 12(9) | E100: 377895.17 | H100: =60000 -> 60000 | J100: =E100+F100+G100+H100+I100 -> 437895.17 | L100: =5000 -> 5000 | M100: 52500 | O100: 56938.069 | P100: 30231.613 | Q100: =O100+N100+M100+L100+K100+P100 -> 144669.68 | R100: 280919.19 | S100: =J100-Q100 -> 293225.48
A101: 4 | B101: TASSNEEM IBRAHIM | C101: SENIOR PROGRAMME OFFICER | D101: 10(8) | E101: 300965.58 | H101: =60000 -> 60000 | J101: =E101+F101+G101+H101+I101 -> 360965.58 | L101: =10000+80000 -> 90000 | M101: =19583.33 -> 19583.33 | O101: 43763.907 | P101: 24077.247 | Q101: =O101+N101+M101+L101+K101+P101 -> 177424.48 | R101: 183541.1 | S101: =J101-Q101 -> 183541.1
B102: TOTAL | C102: 4 | E102: =SUM(E98:E101) -> 2487525.7 | F102: =SUM(F98:F101) -> 0 | G102: =SUM(G98:G101) -> 0 | H102: =SUM(H98:H101) -> 290000 | I102: =SUM(I98:I101) -> 0 | J102: =SUM(J98:J101) -> 2777525.7 | K102: =SUM(K98:K101) -> 0 | L102: =SUM(L98:L101) -> 105000 | ... Q102: =SUM(Q98:Q101) -> 985987.69 | R102: 1779231.7 | S102: =SUM(S98:S101) -> 1791538
B104: LIBRARY & DOCUMENTATION
A105: 1 | B105: DR MAIMUNA IZAH | C105: INSITUTE LIBRARIAN | D105: 17(9) | E105: 1435720 | G105: =200000 -> 200000 | I105: 0 | J105: =SUM(E105:I105) -> 1635720 | L105: =100000 -> 100000 | M105: 0 | N105: 0 | O105: 270672.25 | P105: 114857.6 | Q105: =O105+N105+M105+L105+K105+P105 -> 485529.85 | R105: 1150190.2 | S105: =J105-Q105 -> 1150190.2
A106: 2 | B106: CATHERINE E. IKOKOH | C106: SNR RESEARCH FELLOW DOCU | D106: 16(9) | E106: 762373.17 | G106: =160000+20000 -> 180000 | I106: 0 | J106: =SUM(E106:I106) -> 942373.17 | L106: 40000 | M106: =238888.89 -> 238888.89 | N106: 10293.398 | O106: 147687.53 | P106: 60989.853 | Q106: =O106+N106+M106+L106+K106+P106 -> 497859.67 | R106: 444513.5 | S106: =J106-Q106 -> 444513.5
A107: 3 | B107: ALIYU SANNI ABUBAKAR | C107: RESEARCH FELLOW 11 DATA & DOCU | D107: 13(11) | E107: 441804.92 | G107: =120000 -> 120000 | I107: 41432.939 | J107: =SUM(E107:I107) -> 603237.86 | L107: 30000 | M107: =61111.11 -> 61111.11 | N107: 5954.6104 | O107: 87575.783 | P107: 35344.393 | Q107: =O107+N107+M107+L107+K107+P107 -> 219985.9 | R107: 383251.96 | S107: =J107-Q107 -> 383251.96
A108: 4 | B108: CHINAKO N. ASOGWA | C108: RESEARCH FELLOW 11 DATA & DOCU | D108: 13(11) | E108: 441804.92 | G108: =120000 -> 120000 | I108: 39820.117 | J108: =SUM(E108:I108) -> 601625.03 | L108: =50000 -> 50000 | M108: 45833.33 | O108: 87392.55 | P108: 35344.393 | Q108: =O108+N108+M108+L108+K108+P108 -> 218570.27 | R108: 428888.09 | S108: =J108-Q108 -> 383054.76
...

Sheet MEMO
A2: NATIONAL INSTITUTE FOR LEGISLATIVE AND DEMOCRATIC STUDIES
A3: INTERNAL MEMO
A4: FROM : DEPUTY DIRECTOR, FINANCE AND ACCOUNTS
A5: THRU: DIRECTOR, FINANCE AND ACCOUNTS
A6: TO: DG
A7: 29TH JANUARY , 2021
A9: SUBJECT: PAYROLL FOR THE MONTH OF JANUARY, 2021
A10: Find below the details of NILDS Staff Payroll for the month of January, 2021
A13: TO: | C13: DIRECTOR, GENERAL
A14: THRU: | C14: DIRECTOR, FINANCE AND ACCOUNT
A15: FROM: | C15: DEPUTY DIRECTOR, FINANCE AND ACCOUNTS
A16: DATE: | C16: 29TH MAY 2024
A18: SUBJECT: PAYROLL FOR THE MONTH OF MAY 2024
A19: Find below the details of NILDS Staff Payroll for the Month of May, 2024: | G19: NGN | H19: NGN
A20: GROSS SALARY FOR MAY, 2024 | H20: ='MAY 2024'!J194 -> 80911797
A22: DEDUCTIONS
A23: COOP SOCIETY DEDUCTIONS ( CONTR.& SPEC. SAVINGS) | G23: ='MAY 2024'!L194 -> 6373500
A24: COOP LOAN RECOVERY | G24: ='MAY 2024'!M194 -> 7974625
A25: NHF DEDUCTIONS | G25: ='MAY 2024'!N194 -> 226658.47
A26: PAYE DEDUCTIONS | G26: ='MAY 2024'!O194 -> 11600740
A27: PENSION DEDUCTIONS | G27: ='MAY 2024'!P194 -> 4618348.5
A28: TOTAL DEDUCTIONS FOR MAY 2024 | H28: =G23+G24+G26+G25+G27 -> 30793872
A29: NET PAY AS PER MAY 2024 PAYROLL | H29: =H20-H28 -> 50117925
A30: NET PAY AS PER APRIL, 2024 PAYROLL | H30: ='MAY 2024'!R194 -> 51163557
A31: NET INCREASE/ (DECREASE) IN PAY FOR MAY, 2024 | H31: =H29-H30 -> -1045631.5
A32: ANALYSED AS FOLLOWS:
A33: Effect of Cooperative Adjustment for May, 2024 | H33: =593151.54 -> 593151.54
A34: Effect of Removal of Arrears of Ayobolu Olufunsho | H34: =452480 -> 452480
H35: =SUM(H33:H34) -> 1045631.5
E37: APRIL, 2024 | G37: MAY, 2024
E38: No. of Staff | F38: N | G38: No. of Staff | H38: N
A39: 1 | B39: Director General's Office | E39: 33 | F39: ='MAY 2024'!R34 -> 12172047 | G39: ='MAY 2024'!C34 -> 27 | H39: ='MAY 2024'!S34 -> 12022047
A40: 2 | B40: Internal Audit | E40: 2 | F40: ='MAY 2024'!R40 -> 1319564.5 | G40: ='MAY 2024'!C40 -> 3 | H40: ='MAY 2024'!S40 -> 1319564.5
A41: 3 | B41: Legis. Support Services | E41: 11 | F41: ='MAY 2024'!R54 -> 4657183.5 | G41: ='MAY 2024'!C54 -> 11 | H41: ='MAY 2024'!S54 -> 4410412.5
A42: 4 | B42: Legal Services | E42: 2 | F42: ='MAY 2024'!R59 -> 1482548.9 | G42: ='MAY 2024'!C59 -> 2 | H42: ='MAY 2024'!S59 -> 1482548.9
A43: 5 | B43: Democracy and Governance | E43: 13 | F43: ='MAY 2024'!R72 -> 3282337.7 | G43: ='MAY 2024'!C72 -> 12 | H43: ='MAY 2024'!S72 -> 3282337.7
A44: 6 | B44: Studies | E44: 4 | F44: ='MAY 2024'!R82 -> 3760018.2 | G44: ='MAY 2024'!C82 -> 7 | H44: ='MAY 2024'!S82 -> 3193417.3
A45: 7 | B45: Economic Dev. & Social Research | E45: 12 | F45: ='MAY 2024'!R95 -> 4131549.2 | G45: ='MAY 2024'!C95 -> 11 | H45: ='MAY 2024'!S95 -> 4131549.2
A46: 8 | B46: Training & Int'l Cooperation | E46: 4 | F46: ='MAY 2024'!R102 -> 1779231.7 | G46: ='MAY 2024'!C102 -> 4 | H46: ='MAY 2024'!S102 -> 1791538
A47: 9 | B47: Library & Documentation | E47: 8 | F47: ='MAY 2024'!R112 -> 3185436 | G47: ='MAY 2024'!C112 -> 7 | H47: ='MAY 2024'!S112 -> 3139602.7
A48: 10 | B48: Leg. Center for Security Analysis | E48: 2 | F48: ='MAY 2024'!R118 -> 1088615.7 | G48: ='MAY 2024'!C118 -> 2 | H48: ='MAY 2024'!S118 -> 1088615.7
A49: 11 | B49: Finance and Accounts | E49: 9 | F49: ='MAY 2024'!R131 -> 3378298.8 | G49: ='MAY 2024'!C131 -> 10 | H49: ='MAY 2024'!S131 -> 3378298.8
A50: 12 | B50: Admin & Human Resource | E50: 58 | F50: ='MAY 2024'!R193 -> 10926726 | G50: ='MAY 2024'!C193 -> 59 | H50: ='MAY 2024'!S193 -> 10877993
E51: =SUM(E39:E50) -> 158 | F51: =SUM(F39:F50) -> 51163557 | G51: 154 | H51: =SUM(H39:H50) -> 50117925
A53: The Director General is requested to consider and approve payment of N50,117,925.08 to Guaranty Trust Bank being May, 2024 Salary, N14,348,125.00 being NILDS Coop Society deductions for May 2024, N11,600,740.35 being PAYE Tax Deductions from Staff Salary for the month of May 2024 and N226,658.47 being NHF deductions from staff for May 2024
A57: RAHILA NURUDEEN HABU
C161: =10000 -> 10000

Sheet Arrears of Res. Allow
D1: OLD PAYE | E1: ADJUSTED PAYE | F1: DIFFERENCE | G1: FOR 7 MONTHS | H1: TOTAL DIFF IN RES ALLOW | I1: NET DIFFERENCE
A2: AYOBOLU OLAJIDE OLUFUNSHO | B2: ASST.DIR., INFORMATION | C2: 15 (9) | D2: =64596.94 -> 64596.94 | E2: =79956.94 -> 79956.94 | F2: =E2-D2 -> 15360 | G2: =F2*7 -> 107520 | H2: 560000 | I2: =H2-G2 -> 452480

Sheet Additional Leg Duty Allowance
A1: NATIONAL INSTITUTE FOR LEGISLATIVE AND DEMOCRATIC STUDIES
A2: STAFF PAYROLL FOR THE MONTH OF MARCH, 2024
E3: ='[1]FEB 08'!E11/'[1]FEB 08'!M11 -> #REF!
B4: STAFF NAME | C4: DESIGNATION | D4: GRADE LEVEL | E4: BASIC SALARY | F4: ALLCE/ AREARS | G4: ALLOWANCE | H4: ALLOWANCE | I4: DUTY ALLCE | J4: GROSS SALARY | K4: AUCTION | L4: COOP CONTR/SPEC SAVINGS | M4: COOP. LOAN RECOVERY | N4: NHF DED. | O4: PAYE | P4: NEW PAYE | Q4: DIFFERENCE | R4: EMPLOYEE PENSIONS | S4: TOTAL DEDUCTION | T4: FEBRUARY, 2024 | U4: MARCH, 2024
E5: N | G5: N | H5: N | I5: N | J5: N | K5: N | L5: N | M5: N | N5: N | O5: N | P5: N | Q5: N | R5: N | S5: N | T5: N | U5: N
A6: S/N | B6: DG'S OFFICE
A7: 1 | B7: RAHEEM USMAN AYIGORO | C7: SA-INFRASTRUCTURE | D7: 16 (9) | E7: 762373.17 | H7: =90000 -> 90000 | I7: 0 | J7: =E7+F7+G7+H7+I7 -> 852373.17 | L7: =100000 -> 100000 | O7: 130612.26 | P7: ='March New PAYE '!Z7 -> 149812.26 | Q7: =P7-O7 -> 19200 | R7: 60989.853 | S7: =O7+N7+M7+L7+K7+R7 -> 291602.12 | T7: 560771.05 | U7: =J7-S7 -> 560771.05
A8: 2 | B8: MARIAM MOHAMMED BELLO | C8: SA- SPECIAL DUTIES | D8: 16 (9) | E8: 762373.17 | H8: =90000 -> 90000 | I8: =100000+100000 -> 200000 | J8: =E8+F8+G8+H8+I8 -> 1052373.2 | O8: 180722.31 | P8: ='March New PAYE '!Z8 -> 199922.31 | Q8: =P8-O8 -> 19200 | S8: =O8+N8+M8+L8+K8+R8 -> 180722.31 | T8: 871650.85 | U8: =J8-S8 -> 871650.85
A9: 3 | B9: MOSHOOD M. OLALERE | C9: DEPUTY DIR. GENERAL SERVICE | D9: 16 (9) | E9: 762373.17 | H9: =80000+10000 -> 90000 | I9: 150000 | J9: =E9+F9+G9+H9+I9 -> 1002373.2 | L9: =20000+60000 -> 80000 | M9: ='[2]OCTOBER 2023 '!$D$193 -> 230499.8 | N9: 1066.3293 | O9: 159207.53 | P9: ='March New PAYE '!Z10 -> 178407.53 | Q9: =P9-O9 -> 19200 | R9: 60989.853 | S9: =O9+N9+M9+L9+K9+R9 -> 531763.51 | T9: 470609.66 | U9: =J9-S9 -> 470609.66
A10: 4 | B10: REKIYA IBRAHIM ATTAH | C10: DEPUTY DIRECTOR TRAINING | D10: 16 (9) | E10: 762373.17 | H10: =90000 -> 90000 | I10: 100000 | J10: =E10+F10+G10+H10+I10 -> 952373.17 | L10: =50000 -> 50000 | M10: =91666.67 -> 91666.67 | O10: 161522.31 | P10: ='March New PAYE '!Z11 -> 180722.31 | Q10: =P10-O10 -> 19200 | S10: =O10+N10+M10+L10+K10+R10 -> 303188.98 | T10: 649184.18 | U10: =J10-S10 -> 649184.18
A11: 5 | B11: TERFA WILLIAMS ABRAHAM | C11: SNR RESEARCH FELLOW | D11: 15(9) | E11: 620675.58 | G11: =160000 -> 160000 | I11: 100000 | J11: =SUM(E11:I11) -> 880675.58 | O11: 138222.8 | P11: ='March New PAYE '!Z80 -> 157422.8 | Q11: =P11-O11 -> 19200 | R11: 49654.047 | S11: =O11+N11+M11+L11+K11+R11 -> 187876.85 | T11: 692798.73 | U11: =J11-S11 -> 692798.73
A12: 6 | B12: DR FRANCIS NDUM OJIE | C12: AD, TRAINING & IC./SA TO DG | D12: 15(7) | E12: 582118.08 | G12: 160000 | I12: =100000 -> 100000 | J12: =E12+F12+G12+H12+I12 -> 842118.08 | N12: 775.496 | O12: 131263.11 | P12: ='March New PAYE '!Z13 -> 150463.11 | Q12: =P12-O12 -> 19200 | R12: 46569.447 | S12: =O12+N12+M12+L12+K12+R12 -> 178608.05 | T12: 663510.03 | U12: =J12-S12 -> 663510.03
A13: 7 | B13: DORIS DAKDA AARON | C13: RESEARCH FELLOW I | D13: 14(8) | E13: 442746.5 | G13: =140000 -> 140000 | I13: 150000 | J13: =E13+F13+G13+H13+I13 -> 732746.5 | L13: 70000 | O13: 112553.41 | P13: ='March New PAYE '!Z16 -> 131753.41 | Q13: =P13-O13 -> 19200 | R13: 35419.72 | S13: =O13+N13+M13+L13+K13+R13 -> 217973.13 | T13: 514773.37 | U13: =J13-S13 -> 514773.37
A14: 8 | B14: HASSANA AHMED IBRAHIM | C14: PA- TO DG | D14: 13 (9) | E14: 416026.92 | G14: =120000 -> 120000 | I14: =100000 -> 100000 | J14: =E14+F14+G14+H14+I14 -> 636026.92 | L14: =30000-20000 -> 10000 | M14: =95833.33 -> 95833.33 | N14: 618.5315 | O14: 94274.903 | P14: ='March New PAYE '!Z19 -> 113474.9 | Q14: =P14-O14 -> 19200 | R14: 33282.153 | S14: =O14+N14+M14+L14+K14+R14 -> 234008.92 | T14: 402018 | U14: =J14-S14 -> 402018
A15: 9 | B15: LUCKY AGWOM | C15: RESEARCH ASSISTANT | D15: 12(7) | E15: 353512.5 | G15: =100000 -> 100000 | I15: 100000 | J15: =E15+F15+G15+H15+I15 -> 553512.5 | L15: 50000 | O15: 79511.115 | P15: ='March New PAYE '!Z21 -> 98711.115 | Q15: =P15-O15 -> 19200 | R15: 28281 | S15: =O15+N15+M15+L15+K15+R15 -> 157792.11 | T15: 395720.39 | U15: =J15-S15 -> 395720.39
A16: 10 | B16: FARUQ ATOFARATI | C16: PA (SPECIAL DUTIES) TO DG | D16: 10(7) | E16: 293029.67 | H16: =50000+10000 -> 60000 | I16: 100000 | J16: =E16+F16+G16+H16+I16 -> 453029.67 | O16: 61147.427 | P16: ='March New PAYE '!Z23 -> 80347.427 | Q16: =P16-O16 -> 19200 | R16: 23442.373 | S16: =O16+N16+M16+L16+K16+R16 -> 84589.8 | T16: 368439.87 | U16: =J16-S16 -> 368439.87
B17: TOTAL | C17: 10 | E17: 14898686 | G17: =SUM(#REF!) -> #REF! | H17: =SUM(#REF!) -> #REF! | I17: =SUM(#REF!) -> #REF! | J17: =SUM(#REF!) -> #REF! | K17: =SUM(#REF!) -> #REF! | L17: =SUM(#REF!) -> #REF! | M17: =SUM(#REF!) -> #REF! | N17: 6347.233 | O17: =SUM(O7:O16) -> 1249037.2 | P17: =SUM(P7:P16) -> 1441037.2 | Q17: =SUM(Q7:Q16) -> 192000 | R17: 1130905.1 | S17: =SUM(#REF!) -> #REF! | T17: 11108681 | U17: =SUM(#REF!) -> #REF!
J19: PREPARED BY: Rahila N. Habu SIGNATURE……………….. DATE: 29TH JANUARY, 2024

Sheet March New PAYE 
A1: NATIONAL INSTITUTE FOR LEGISLATIVE AND DEMOCRATIC STUDIES
A2: NATIONAL ASSEMBLY ABUJA
A3: TAX COMPUTATION FOR 2022
A4: S/NO | B4: NAME | C4: MONTHLY TOTAL SALARY | D4: NO OF MONTHS | E4: ANNUAL SALARY GROSSED UP | F4: NATIONAL HOUSING SCHEME = 2.5% OF BASIC SALARY | G4: PENSION CONTRIBUTION = 8% OF CONSOLIDATED | H4: NHIS | I4: NET SALARY (EXC OF CRA) | M4: CRA=#200,000+(20% 0F NET SALARY (EXC OF CRA) | N4: TOTAL RELIEF | O4: CHARGEABLE INCOME | P4: FIRST N300,000 @ 7% | Q4: NEXT N300,000 @ 11% | R4: NEXT N500,000 @ 15% | S4: NEXT N500,000@ 19% | T4: NEXT N1,600,000 @ 21% | U4: ABOVE N3,200,000 @ 24% | V4: ANNUAL TAX PAYABLE | X4: MONTHLY TAX PAYABLE | Y4: MINIMUM TAX PAYABLE | Z4: NEW ACTUAL TAX PAYABLE | AB4: Difference
A5: 1 | B5: DG'S OFFICE
A6: 3 | B6: PROF. ABUBAKAR O. SULAIMAN | C6: 1934986.2 | D6: 12 | E6: =C6*D6 -> 23219834 | I6: =E6-F6-G6-H6 -> 23219834 | J6: 200000 | K6: 0.2 | L6: =I6*K6 -> 4643966.8 | M6: =J6+L6 -> 4843966.8 | N6: =F6+G6+H6+M6 -> 4843966.8 | O6: =E6-N6 -> 18375867 | P6: =IF(O6<300000,0.07*O6,21000) -> 21000 | Q6: =IF((O6-300000)<0,0,IF((O6-300000)<300000,0.11*(O6-300000),33000)) -> 33000 | R6: =IF((O6-600000)<0,0,IF((O6-600000)<500000,0.15*(O6-600000),75000)) -> 75000 | S6: =IF((O6-1100000)<0,0,IF((O6-1100000)<500000,0.19*(O6-1100000),95000)) -> 95000 | T6: =IF((O6-1600000)<0,0,IF((O6-1600000)<1600000,0.21*(O6-1600000),336000)) -> 336000 | U6: =24%*(O6-3200000) -> 3642208.1 | V6: =P6+Q6+R6+S6+T6+U6 -> 4202208.1 | W6: 12 | X6: =V6/W6 -> 350184.01 | Z6: =X6 -> 350184.01 | AA6: 201165.84 | AB6: =Z6-AA6 -> 149018.17
A7: 4 | B7: RAHEEM USMAN AYIGORO | C7: =852373.166666667+100000 -> 952373.17 | D7: 12 | E7: =C7*D7 -> 11428478 | G7: 731878.24 | I7: =E7-F7-G7-H7 -> 10696600 | J7: 200000 | K7: 0.2 | L7: =I7*K7 -> 2139320 | M7: =J7+L7 -> 2339320 | N7: =F7+G7+H7+M7 -> 3071198.2 | O7: =E7-N7 -> 8357279.8 | P7: =IF(O7<300000,0.07*O7,21000) -> 21000 | Q7: =IF((O7-300000)<0,0,IF((O7-300000)<300000,0.11*(O7-300000),33000)) -> 33000 | R7: =IF((O7-600000)<0,0,IF((O7-600000)<500000,0.15*(O7-600000),75000)) -> 75000 | S7: =IF((O7-1100000)<0,0,IF((O7-1100000)<500000,0.19*(O7-1100000),95000)) -> 95000 | T7: =IF((O7-1600000)<0,0,IF((O7-1600000)<1600000,0.21*(O7-1600000),336000)) -> 336000 | U7: =24%*(O7-3200000) -> 1237747.2 | V7: =P7+Q7+R7+S7+T7+U7 -> 1797747.2 | W7: 12 | X7: =V7/W7 -> 149812.26 | Z7: =X7 -> 149812.26 | AA7: 82627.951 | AB7: =Z7-AA7 -> 67184.311
A8: 5 | B8: MARIAM MOHAMMED BELLO | C8: =1052373.16666667+100000 -> 1152373.2 | D8: 12 | E8: =C8*D8 -> 13828478 | G8: 0 | I8: =E8-F8-G8-H8 -> 13828478 | J8: 200000 | K8: 0.2 | L8: =I8*K8 -> 2765695.6 | M8: =J8+L8 -> 2965695.6 | N8: =F8+G8+H8+M8 -> 2965695.6 | O8: =E8-N8 -> 10862782 | P8: =IF(O8<300000,0.07*O8,21000) -> 21000 | Q8: =IF((O8-300000)<0,0,IF((O8-300000)<300000,0.11*(O8-300000),33000)) -> 33000 | R8: =IF((O8-600000)<0,0,IF((O8-600000)<500000,0.15*(O8-600000),75000)) -> 75000 | S8: =IF((O8-1100000)<0,0,IF((O8-1100000)<500000,0.19*(O8-1100000),95000)) -> 95000 | T8: =IF((O8-1600000)<0,0,IF((O8-1600000)<1600000,0.21*(O8-1600000),336000)) -> 336000 | U8: =24%*(O8-3200000) -> 1839067.8 | V8: =P8+Q8+R8+S8+T8+U8 -> 2399067.8 | W8: 12 | X8: =V8/W8 -> 199922.31 | Z8: =X8 -> 199922.31 | AA8: 121027.95 | AB8: =Z8-AA8 -> 78894.363
A9: 6 | B9: DR IKEME ARTHUR J.O | C9: 942373.17 | D9: 12 | E9: =C9*D9 -> 11308478 | F9: ='[5]JANUARY 2024'!$V$10*12 -> 12795.951 | G9: 731878.24 | I9: =E9-F9-G9-H9 -> 10563804 | J9: 200000 | K9: 0.2 | L9: =I9*K9 -> 2112760.8 | M9: =J9+L9 -> 2312760.8 | N9: =F9+G9+H9+M9 -> 3057435 | O9: =E9-N9 -> 8251043 | P9: =IF(O9<300000,0.07*O9,21000) -> 21000 | Q9: =IF((O9-300000)<0,0,IF((O9-300000)<300000,0.11*(O9-300000),33000)) -> 33000 | R9: =IF((O9-600000)<0,0,IF((O9-600000)<500000,0.15*(O9-600000),75000)) -> 75000 | S9: =IF((O9-1100000)<0,0,IF((O9-1100000)<500000,0.19*(O9-1100000),95000)) -> 95000 | T9: =IF((O9-1600000)<0,0,IF((O9-1600000)<1600000,0.21*(O9-1600000),336000)) -> 336000 | U9: =24%*(O9-3200000) -> 1212250.3 | V9: =P9+Q9+R9+S9+T9+U9 -> 1772250.3 | W9: 12 | X9: =V9/W9 -> 147687.53 | Z9: =X9 -> 147687.53 | AA9: 99703.216 | AB9: =Z9-AA9 -> 47984.311
A10: 7 | B10: MOSHOOD M. OLALERE | C10: =1002373.16666667+100000 -> 1102373.2 | D10: 12 | E10: =C10*D10 -> 13228478 | F10: ='[5]JANUARY 2024'!$V$10*12 -> 12795.951 | G10: 731878.24 | I10: =E10-F10-G10-H10 -> 12483804 | J10: 200000 | K10: 0.2 | L10: =I10*K10 -> 2496760.8 | M10: =J10+L10 -> 2696760.8 | N10: =F10+G10+H10+M10 -> 3441435 | O10: =E10-N10 -> 9787043 | P10: =IF(O10<300000,0.07*O10,21000) -> 21000 | Q10: =IF((O10-300000)<0,0,IF((O10-300000)<300000,0.11*(O10-300000),33000)) -> 33000 | R10: =IF((O10-600000)<0,0,IF((O10-600000)<500000,0.15*(O10-600000),75000)) -> 75000 | S10: =IF((O10-1100000)<0,0,IF((O10-1100000)<500000,0.19*(O10-1100000),95000)) -> 95000 | T10: =IF((O10-1600000)<0,0,IF((O10-1600000)<1600000,0.21*(O10-1600000),336000)) -> 336000 | U10: =24%*(O10-3200000) -> 1580890.3 | V10: =P10+Q10+R10+S10+T10+U10 -> 2140890.3 | W10: 12 | X10: =V10/W10 -> 178407.53 | Z10: =X10 -> 178407.53 | AA10: 111223.22 | AB10: =Z10-AA10 -> 67184.311
A11: 8 | B11: REKIYA IBRAHIM ATTAH | C11: =952373.166666667+100000 -> 1052373.2 | D11: 12 | E11: =C11*D11 -> 12628478 | G11: 0 | I11: =E11-F11-G11-H11 -> 12628478 | J11: 200000 | K11: 0.2 | L11: =I11*K11 -> 2525695.6 | M11: =J11+L11 -> 2725695.6 | N11: =F11+G11+H11+M11 -> 2725695.6 | O11: =E11-N11 -> 9902782.4 | P11: =IF(O11<300000,0.07*O11,21000) -> 21000 | Q11: =IF((O11-300000)<0,0,IF((O11-300000)<300000,0.11*(O11-300000),33000)) -> 33000 | R11: =IF((O11-600000)<0,0,IF((O11-600000)<500000,0.15*(O11-600000),75000)) -> 75000 | S11: =IF((O11-1100000)<0,0,IF((O11-1100000)<500000,0.19*(O11-1100000),95000)) -> 95000 | T11: =IF((O11-1600000)<0,0,IF((O11-1600000)<1600000,0.21*(O11-1600000),336000)) -> 336000 | U11: =24%*(O11-3200000) -> 1608667.8 | V11: =P11+Q11+R11+S11+T11+U11 -> 2168667.8 | W11: 12 | X11: =V11/W11 -> 180722.31 | Z11: =X11 -> 180722.31 | AA11: 101827.95 | AB11: =Z11-AA11 -> 78894.363
A12: 9 | B12: ANDRAWUS MUSA | C12: 750675.58 | D12: 12 | E12: =C12*D12 -> 9008107 | F12: ='[5]JANUARY 2024'!$V$13*12 -> 10052.25 | G12: 595848.56 | I12: =E12-F12-G12-H12 -> 8402206.2 | J12: 200000 | K12: 0.2 | L12: =I12*K12 -> 1680441.2 | M12: =J12+L12 -> 1880441.2 | N12: =F12+G12+H12+M12 -> 2486342 | O12: =E12-N12 -> 6521765 | P12: =IF(O12<300000,0.07*O12,21000) -> 21000 | Q12: =IF((O12-300000)<0,0,IF((O12-300000)<300000,0.11*(O12-300000),33000)) -> 33000 | R12: =IF((O12-600000)<0,0,IF((O12-600000)<500000,0.15*(O12-600000),75000)) -> 75000 | S12: =IF((O12-1100000)<0,0,IF((O12-1100000)<500000,0.19*(O12-1100000),95000)) -> 95000 | T12: =IF((O12-1600000)<0,0,IF((O12-1600000)<1600000,0.21*(O12-1600000),336000)) -> 336000 | U12: =24%*(O12-3200000) -> 797223.59 | V12: =P12+Q12+R12+S12+T12+U12 -> 1357223.6 | W12: 12 | X12: =V12/W12 -> 113101.97 | Z12: =X12 -> 113101.97 | AA12: 74036.103 | AB12: =Z12-AA12 -> 39065.863
A13: 10 | B13: DR FRANCIS NDUM OJIE | C13: =842118.083333333+100000 -> 942118.08 | D13: 12 | E13: =C13*D13 -> 11305417 | F13: ='[5]JANUARY 2024'!$V$14*12 -> 9305.952 | G13: 558833.36 | I13: =E13-F13-G13-H13 -> 10737278 | J13: 200000 | K13: 0.2 | L13: =I13*K13 -> 2147455.5 | M13: =J13+L13 -> 2347455.5 | N13: =F13+G13+H13+M13 -> 2915594.8 | O13: =E13-N13 -> 8389822.2 | P13: =IF(O13<300000,0.07*O13,21000) -> 21000 | Q13: =IF((O13-300000)<0,0,IF((O13-300000)<300000,0.11*(O13-300000),33000)) -> 33000 | R13: =IF((O13-600000)<0,0,IF((O13-600000)<500000,0.15*(O13-600000),75000)) -> 75000 | S13: =IF((O13-1100000)<0,0,IF((O13-1100000)<500000,0.19*(O13-1100000),95000)) -> 95000 | T13: =IF((O13-1600000)<0,0,IF((O13-1600000)<1600000,0.21*(O13-1600000),336000)) -> 336000 | U13: =24%*(O13-3200000) -> 1245557.3 | V13: =P13+Q13+R13+S13+T13+U13 -> 1805557.3 | W13: 12 | X13: =V13/W13 -> 150463.11 | Z13: =X13 -> 150463.11 | AA13: 94625.782 | AB13: =Z13-AA13 -> 55837.328
A14: 11 | B14: ALI ABDULLAHI | C14: 554373.75 | D14: 12 | E14: =C14*D14 -> 6652485 | G14: 464998.8 | I14: =E14-F14-G14-H14 -> 6187486.2 | J14: 200000 | K14: 0.2 | L14: =I14*K14 -> 1237497.2 | M14: =J14+L14 -> 1437497.2 | N14: =F14+G14+H14+M14 -> 1902496 | O14: =E14-N14 -> 4749989 | P14: =IF(O14<300000,0.07*O14,21000) -> 21000 | Q14: =IF((O14-300000)<0,0,IF((O14-300000)<300000,0.11*(O14-300000),33000)) -> 33000 | R14: =IF((O14-600000)<0,0,IF((O14-600000)<500000,0.15*(O14-600000),75000)) -> 75000 | S14: =IF((O14-1100000)<0,0,IF((O14-1100000)<500000,0.19*(O14-1100000),95000)) -> 95000 | T14: =IF((O14-1600000)<0,0,IF((O14-1600000)<1600000,0.21*(O14-1600000),336000)) -> 336000 | U14: =24%*(O14-3200000) -> 371997.35 | V14: =P14+Q14+R14+S14+T14+U14 -> 931997.35 | W14: 12 | X14: =V14/W14 -> 77666.446 | Z14: =X14 -> 77666.446 | AA14: 44846.617 | AB14: =Z14-AA14 -> 32819.829
A15: 12 | B15: EMILY EKHIDE | C15: =660498 -> 660498 | D15: 12 | E15: =C15*D15 -> 7925976 | G15: 451678.08 | I15: =E15-F15-G15-H15 -> 7474297.9 | J15: 200000 | K15: 0.2 | L15: =I15*K15 -> 1494859.6 | M15: =J15+L15 -> 1694859.6 | N15: =F15+G15+H15+M15 -> 2146537.7 | O15: =E15-N15 -> 5779438.3 | P15: =IF(O15<300000,0.07*O15,21000) -> 21000 | Q15: =IF((O15-300000)<0,0,IF((O15-300000)<300000,0.11*(O15-300000),33000)) -> 33000 | R15: =IF((O15-600000)<0,0,IF((O15-600000)<500000,0.15*(O15-600000),75000)) -> 75000 | S15: =IF((O15-1100000)<0,0,IF((O15-1100000)<500000,0.19*(O15-1100000),95000)) -> 95000 | T15: =IF((O15-1600000)<0,0,IF((O15-1600000)<1600000,0.21*(O15-1600000),336000)) -> 336000 | U15: =24%*(O15-3200000) -> 619065.2 | V15: =P15+Q15+R15+S15+T15+U15 -> 1179065.2 | W15: 12 | X15: =V15/W15 -> 98255.433 | Z15: =X15 -> 98255.433 | AA15: 46666.667 | AB15: =Z15-AA15 -> 51588.767
A16: 13 | B16: DORIS DAKDA AARON | C16: =732746.5+100000 -> 832746.5 | D16: 12 | E16: =C16*D16 -> 9992958 | G16: 425036.64 | I16: =E16-F16-G16-H16 -> 9567921.4 | J16: 200000 | K16: 0.2 | L16: =I16*K16 -> 1913584.3 | M16: =J16+L16 -> 2113584.3 | N16: =F16+G16+H16+M16 -> 2538620.9 | O16: =E16-N16 -> 7454337.1 | P16: =IF(O16<300000,0.07*O16,21000) -> 21000 | Q16: =IF((O16-300000)<0,0,IF((O16-300000)<300000,0.11*(O16-300000),33000)) -> 33000 | R16: =IF((O16-600000)<0,0,IF((O16-600000)<500000,0.15*(O16-600000),75000)) -> 75000 | S16: =IF((O16-1100000)<0,0,IF((O16-1100000)<500000,0.19*(O16-1100000),95000)) -> 95000 | T16: =IF((O16-1600000)<0,0,IF((O16-1600000)<1600000,0.21*(O16-1600000),336000)) -> 336000 | U16: =24%*(O16-3200000) -> 1021040.9 | V16: =P16+Q16+R16+S16+T16+U16 -> 1581040.9 | W16: 12 | X16: =V16/W16 -> 131753.41 | Z16: =X16 -> 131753.41 | AA16: 46666.667 | AB16: =Z16-AA16 -> 85086.742
A17: 14 | B17: ABDULSALAM S. MUSTAPHA | C17: 511804.92 | D17: 12 | E17: =C17*D17 -> 6141659 | G17: 424132.72 | I17: =E17-F17-G17-H17 -> 5717526.3 | J17: 200000 | K17: 0.2 | L17: =I17*K17 -> 1143505.3 | M17: =J17+L17 -> 1343505.3 | N17: =F17+G17+H17+M17 -> 1767638 | O17: =E17-N17 -> 4374021 | P17: =IF(O17<300000,0.07*O17,21000) -> 21000 | Q17: =IF((O17-300000)<0,0,IF((O17-300000)<300000,0.11*(O17-300000),33000)) -> 33000 | R17: =IF((O17-600000)<0,0,IF((O17-600000)<500000,0.15*(O17-600000),75000)) -> 75000 | S17: =IF((O17-1100000)<0,0,IF((O17-1100000)<500000,0.19*(O17-1100000),95000)) -> 95000 | T17: =IF((O17-1600000)<0,0,IF((O17-1600000)<1600000,0.21*(O17-1600000),336000)) -> 336000 | U17: =24%*(O17-3200000) -> 281765.05 | V17: =P17+Q17+R17+S17+T17+U17 -> 841765.05 | W17: 12 | X17: =V17/W17 -> 70147.087 | Z17: =X17 -> 70147.087 | AA17: 42046.064 | AB17: =Z17-AA17 -> 28101.023
A18: 15 | B18: PERCY TERFA GBAHABO | C18: 548915.92 | D18: 12 | E18: =C18*D18 -> 6586991 | G18: 411759.28 | I18: =E18-F18-G18-H18 -> 6175231.7 | J18: 200000 | K18: 0.2 | L18: =I18*K18 -> 1235046.3 | M18: =J18+L18 -> 1435046.3 | N18: =F18+G18+H18+M18 -> 1846805.6 | O18: =E18-N18 -> 4740185.4 | P18: =IF(O18<300000,0.07*O18,21000) -> 21000 | Q18: =IF((O18-300000)<0,0,IF((O18-300000)<300000,0.11*(O18-300000),33000)) -> 33000 | R18: =IF((O18-600000)<0,0,IF((O18-600000)<500000,0.15*(O18-600000),75000)) -> 75000 | S18: =IF((O18-1100000)<0,0,IF((O18-1100000)<500000,0.19*(O18-1100000),95000)) -> 95000 | T18: =IF((O18-1600000)<0,0,IF((O18-1600000)<1600000,0.21*(O18-1600000),336000)) -> 336000 | U18: =24%*(O18-3200000) -> 369644.49 | V18: =P18+Q18+R18+S18+T18+U18 -> 929644.49 | W18: 12 | X18: =V18/W18 -> 77470.374 | Z18: =X18 -> 77470.374 | AA18: 46666.667 | AB18: =Z18-AA18 -> 30803.708
A19: 16 | B19: HASSANA AHMED IBRAHIM | C19: =636026.916666667+100000 -> 736026.92 | D19: 12 | E19: =C19*D19 -> 8832323 | F19: =618.53*12 -> 7422.36 | G19: 399385.84 | I19: =E19-F19-G19-H19 -> 8425514.8 | J19: 200000 | K19: 0.2 | L19: =I19*K19 -> 1685103 | M19: =J19+L19 -> 1885103 | N19: =F19+G19+H19+M19 -> 2291911.2 | O19: =E19-N19 -> 6540411.8 | P19: =IF(O19<300000,0.07*O19,21000) -> 21000 | Q19: =IF((O19-300000)<0,0,IF((O19-300000)<300000,0.11*(O19-300000),33000)) -> 33000 | R19: =IF((O19-600000)<0,0,IF((O19-600000)<500000,0.15*(O19-600000),75000)) -> 75000 | S19: =IF((O19-1100000)<0,0,IF((O19-1100000)<500000,0.19*(O19-1100000),95000)) -> 95000 | T19: =IF((O19-1600000)<0,0,IF((O19-1600000)<1600000,0.21*(O19-1600000),336000)) -> 336000 | U19: =24%*(O19-3200000) -> 801698.84 | V19: =P19+Q19+R19+S19+T19+U19 -> 1361698.8 | W19: 12 | X19: =V19/W19 -> 113474.9 | Z19: =X19 -> 113474.9 | AA19: 46666.667 | AB19: =Z19-AA19 -> 66808.237
A20: 17 | B20: ADUGBA RICHARD TERSEER | C20: 537895.17 | D20: 12 | E20: =C20*D20 -> 6454742 | G20: 362779.36 | I20: =E20-F20-G20-H20 -> 6091962.6 | J20: 200000 | K20: 0.2 | L20: =I20*K20 -> 1218392.5 | M20: =J20+L20 -> 1418392.5 | N20: =F20+G20+H20+M20 -> 1781171.9 | O20: =E20-N20 -> 4673570.1 | P20: =IF(O20<300000,0.07*O20,21000) -> 21000 | Q20: =IF((O20-300000)<0,0,IF((O20-300000)<300000,0.11*(O20-300000),33000)) -> 33000 | R20: =IF((O20-600000)<0,0,IF((O20-600000)<500000,0.15*(O20-600000),75000)) -> 75000 | S20: =IF((O20-1100000)<0,0,IF((O20-1100000)<500000,0.19*(O20-1100000),95000)) -> 95000 | T20: =IF((O20-1600000)<0,0,IF((O20-1600000)<1600000,0.21*(O20-1600000),336000)) -> 336000 | U20: =24%*(O20-3200000) -> 353656.83 | V20: =P20+Q20+R20+S20+T20+U20 -> 913656.83 | W20: 12 | X20: =V20/W20 -> 76138.069 | Z20: =X20 -> 76138.069 | AA20: 52497.77 | AB20: =Z20-AA20 -> 23640.299
A21: 18 | B21: LUCKY AGWOM | C21: =553512.5+100000 -> 653512.5 | D21: 12 | E21: =C21*D21 -> 7842150 | G21: 339372 | I21: =E21-F21-G21-H21 -> 7502778 | J21: 200000 | K21: 0.2 | L21: =I21*K21 -> 1500555.6 | M21: =J21+L21 -> 1700555.6 | N21: =F21+G21+H21+M21 -> 2039927.6 | O21: =E21-N21 -> 5802222.4 | P21: =IF(O21<300000,0.07*O21,21000) -> 21000 | Q21: =IF((O21-300000)<0,0,IF((O21-300000)<300000,0.11*(O21-300000),33000)) -> 33000 | R21: =IF((O21-600000)<0,0,IF((O21-600000)<500000,0.15*(O21-600000),75000)) -> 75000 | S21: =IF((O21-1100000)<0,0,IF((O21-1100000)<500000,0.19*(O21-1100000),95000)) -> 95000 | T21: =IF((O21-1600000)<0,0,IF((O21-1600000)<1600000,0.21*(O21-1600000),336000)) -> 336000 | U21: =24%*(O21-3200000) -> 624533.38 | V21: =P21+Q21+R21+S21+T21+U21 -> 1184533.4 | W21: 12 | X21: =V21/W21 -> 98711.115 | Z21: =X21 -> 98711.115 | AA21: 46666.667 | AB21: =Z21-AA21 -> 52044.448
A22: 19 | B22: IDRIS IBRAHIM | C22: 463512.5 | D22: 12 | E22: =C22*D22 -> 5562150 | G22: 339372 | I22: =E22-F22-G22-H22 -> 5222778 | J22: 200000 | K22: 0.2 | L22: =I22*K22 -> 1044555.6 | M22: =J22+L22 -> 1244555.6 | N22: =F22+G22+H22+M22 -> 1583927.6 | O22: =E22-N22 -> 3978222.4 | P22: =IF(O22<300000,0.07*O22,21000) -> 21000 | Q22: =IF((O22-300000)<0,0,IF((O22-300000)<300000,0.11*(O22-300000),33000)) -> 33000 | R22: =IF((O22-600000)<0,0,IF((O22-600000)<500000,0.15*(O22-600000),75000)) -> 75000 | S22: =IF((O22-1100000)<0,0,IF((O22-1100000)<500000,0.19*(O22-1100000),95000)) -> 95000 | T22: =IF((O22-1600000)<0,0,IF((O22-1600000)<1600000,0.21*(O22-1600000),336000)) -> 336000 | U22: =24%*(O22-3200000) -> 186773.38 | V22: =P22+Q22+R22+S22+T22+U22 -> 746773.38 | W22: 12 | X22: =V22/W22 -> 62231.115 | Z22: =X22 -> 62231.115 | AA22: 46666.667 | AB22: =Z22-AA22 -> 15564.448
A23: 20 | B23: FARUQ ATOFARATI | C23: =453029.666666667+100000 -> 553029.67 | D23: 12 | E23: =C23*D23 -> 6636356 | G23: 281308.48 | I23: =E23-F23-G23-H23 -> 6355047.5 | J23: 200000 | K23: 0.2 | L23: =I23*K23 -> 1271009.5 | M23: =J23+L23 -> 1471009.5 | N23: =F23+G23+H23+M23 -> 1752318 | O23: =E23-N23 -> 4884038 | P23: =IF(O23<300000,0.07*O23,21000) -> 21000 | Q23: =IF((O23-300000)<0,0,IF((O23-300000)<300000,0.11*(O23-300000),33000)) -> 33000 | R23: =IF((O23-600000)<0,0,IF((O23-600000)<500000,0.15*(O23-600000),75000)) -> 75000 | S23: =IF((O23-1100000)<0,0,IF((O23-1100000)<500000,0.19*(O23-1100000),95000)) -> 95000 | T23: =IF((O23-1600000)<0,0,IF((O23-1600000)<1600000,0.21*(O23-1600000),336000)) -> 336000 | U23: =24%*(O23-3200000) -> 404169.12 | V23: =P23+Q23+R23+S23+T23+U23 -> 964169.12 | W23: 12 | X23: =V23/W23 -> 80347.427 | Z23: =X23 -> 80347.427 | AA23: 42371.816 | AB23: =Z23-AA23 -> 37975.611
A24: 21 | B24: ELIZABETH OGECHUKWU ONYEAKU | C24: 330481.67 | D24: 12 | E24: =C24*D24 -> 3965780 | G24: 259662.4 | I24: =E24-F24-G24-H24 -> 3706117.6 | J24: 200000 | K24: 0.2 | L24: =I24*K24 -> 741223.52 | M24: =J24+L24 -> 941223.52 | N24: =F24+G24+H24+M24 -> 1200885.9 | O24: =E24-N24 -> 2764894.1 | P24: =IF(O24<300000,0.07*O24,21000) -> 21000 | Q24: =IF((O24-300000)<0,0,IF((O24-300000)<300000,0.11*(O24-300000),33000)) -> 33000 | R24: =IF((O24-600000)<0,0,IF((O24-600000)<500000,0.15*(O24-600000),75000)) -> 75000 | S24: =IF((O24-1100000)<0,0,IF((O24-1100000)<500000,0.19*(O24-1100000),95000)) -> 95000 | T24: =IF((O24-1600000)<0,0,IF((O24-1600000)<1600000,0.21*(O24-1600000),336000)) -> 244627.76 | V24: =P24+Q24+R24+S24+T24+U24 -> 468627.76 | W24: 12 | X24: =V24/W24 -> 39052.313 | Z24: =X24 -> 39052.313 | AA24: 23036.012 | AB24: =Z24-AA24 -> 16016.301
A25: 22 | B25: VICTOR ASUKWO | C25: 330481.67 | D25: 12 | E25: =C25*D25 -> 3965780 | G25: 259662.4 | I25: =E25-F25-G25-H25 -> 3706117.6 | J25: 200000 | K25: 0.2 | L25: =I25*K25 -> 741223.52 | M25: =J25+L25 -> 941223.52 | N25: =F25+G25+H25+M25 -> 1200885.9 | O25: =E25-N25 -> 2764894.1 | P25: =IF(O25<300000,0.07*O25,21000) -> 21000 | Q25: =IF((O25-300000)<0,0,IF((O25-300000)<300000,0.11*(O25-300000),33000)) -> 33000 | R25: =IF((O25-600000)<0,0,IF((O25-600000)<500000,0.15*(O25-600000),75000)) -> 75000 | S25: =IF((O25-1100000)<0,0,IF((O25-1100000)<500000,0.19*(O25-1100000),95000)) -> 95000 | T25: =IF((O25-1600000)<0,0,IF((O25-1600000)<1600000,0.21*(O25-1600000),336000)) -> 244627.76 | V25: =P25+Q25+R25+S25+T25+U25 -> 468627.76 | W25: 12 | X25: =V25/W25 -> 39052.313 | Z25: =X25 -> 39052.313 | AA25: 23036.012 | AB25: =Z25-AA25 -> 16016.301
A26: 23 | B26: NNANDI LIVINUS ATURE | C26: 370481.67 | D26: 12 | E26: =C26*D26 -> 4445780 | G26: 259662.4 | I26: =E26-F26-G26-H26 -> 4186117.6 | J26: 200000 | K26: 0.2 | L26: =I26*K26 -> 837223.52 | M26: =J26+L26 -> 1037223.5 | N26: =F26+G26+H26+M26 -> 1296885.9 | O26: =E26-N26 -> 3148894.1 | P26: =IF(O26<300000,0.07*O26,21000) -> 21000 | Q26: =IF((O26-300000)<0,0,IF((O26-300000)<300000,0.11*(O26-300000),33000)) -> 33000 | R26: =IF((O26-600000)<0,0,IF((O26-600000)<500000,0.15*(O26-600000),75000)) -> 75000 | S26: =IF((O26-1100000)<0,0,IF((O26-1100000)<500000,0.19*(O26-1100000),95000)) -> 95000 | T26: =IF((O26-1600000)<0,0,IF((O26-1600000)<1600000,0.21*(O26-1600000),336000)) -> 325267.76 | V26: =P26+Q26+R26+S26+T26+U26 -> 549267.76 | W26: 12 | X26: =V26/W26 -> 45772.313 | Z26: =X26 -> 45772.313 | AA26: 29756.012 | AB26: =Z26-AA26 -> 16016.301
A27: 24 | B27: ABDULRAHMAN A SULAIMAN | C27: 323165.33 | D27: 12 | E27: =C27*D27 -> 3877984 | G27: 252638.72 | I27: =E27-F27-G27-H27 -> 3625345.3 | J27: 200000 | K27: 0.2 | L27: =I27*K27 -> 725069.06 | M27: =J27+L27 -> 925069.06 | N27: =F27+G27+H27+M27 -> 1177707.8 | O27: =E27-N27 -> 2700276.2 | P27: =IF(O27<300000,0.07*O27,21000) -> 21000 | Q27: =IF((O27-300000)<0,0,IF((O27-300000)<300000,0.11*(O27-300000),33000)) -> 33000 | R27: =IF((O27-600000)<0,0,IF((O27-600000)<500000,0.15*(O27-600000),75000)) -> 75000 | S27: =IF((O27-1100000)<0,0,IF((O27-1100000)<500000,0.19*(O27-1100000),95000)) -> 95000 | T27: =IF((O27-1600000)<0,0,IF((O27-1600000)<1600000,0.21*(O27-1600000),336000)) -> 231058.01 | V27: =P27+Q27+R27+S27+T27+U27 -> 455058.01 | W27: 12 | X27: =V27/W27 -> 37921.501 | Z27: =X27 -> 37921.501 | AA27: 22338.483 | AB27: =Z27-AA27 -> 15583.018
A28: 25 | B28: DARE SHEU MAGBON | C28: 315849 | D28: 12 | E28: =C28*D28 -> 3790188 | G28: 245615.04 | I28: =E28-F28-G28-H28 -> 3544573 | J28: 200000 | K28: 0.2 | L28: =I28*K28 -> 708914.59 | M28: =J28+L28 -> 908914.59 | N28: =F28+G28+H28+M28 -> 1154529.6 | O28: =E28-N28 -> 2635658.4 | P28: =IF(O28<300000,0.07*O28,21000) -> 21000 | Q28: =IF((O28-300000)<0,0,IF((O28-300000)<300000,0.11*(O28-300000),33000)) -> 33000 | R28: =IF((O28-600000)<0,0,IF((O28-600000)<500000,0.15*(O28-600000),75000)) -> 75000 | S28: =IF((O28-1100000)<0,0,IF((O28-1100000)<500000,0.19*(O28-1100000),95000)) -> 95000 | T28: =IF((O28-1600000)<0,0,IF((O28-1600000)<1600000,0.21*(O28-1600000),336000)) -> 217488.26 | V28: =P28+Q28+R28+S28+T28+U28 -> 441488.26 | W28: 12 | X28: =V28/W28 -> 36790.688 | Z28: =X28 -> 36790.688 | AA28: 21640.953 | AB28: =Z28-AA28 -> 15149.735
A29: 26 | B29: ABUBAKAR SULAIMAN SODEEQ | C29: 315849 | D29: 12 | E29: =C29*D29 -> 3790188 | G29: 245615.04 | I29: =E29-F29-G29-H29 -> 3544573 | J29: 200000 | K29: 0.2 | L29: =I29*K29 -> 708914.59 | M29: =J29+L29 -> 908914.59 | N29: =F29+G29+H29+M29 -> 1154529.6 | O29: =E29-N29 -> 2635658.4 | P29: =IF(O29<300000,0.07*O29,21000) -> 21000 | Q29: =IF((O29-300000)<0,0,IF((O29-300000)<300000,0.11*(O29-300000),33000)) -> 33000 | R29: =IF((O29-600000)<0,0,IF((O29-600000)<500000,0.15*(O29-600000),75000)) -> 75000 | S29: =IF((O29-1100000)<0,0,IF((O29-1100000)<500000,0.19*(O29-1100000),95000)) -> 95000 | T29: =IF((O29-1600000)<0,0,IF((O29-1600000)<1600000,0.21*(O29-1600000),336000)) -> 217488.26 | V29: =P29+Q29+R29+S29+T29+U29 -> 441488.26 | W29: 12 | X29: =V29/W29 -> 36790.688 | Z29: =X29 -> 36790.688 | AA29: 21640.953 | AB29: =Z29-AA29 -> 15149.735
A30: 27 | B30: JIMOH ADEBAYO ZAKA | C30: 330481.67 | D30: 12 | E30: =C30*D30 -> 3965780 | G30: 259662.4 | I30: =E30-F30-G30-H30 -> 3706117.6 | J30: 200000 | K30: 0.2 | L30: =I30*K30 -> 741223.52 | M30: =J30+L30 -> 941223.52 | N30: =F30+G30+H30+M30 -> 1200885.9 | O30: =E30-N30 -> 2764894.1 | P30: =IF(O30<300000,0.07*O30,21000) -> 21000 | Q30: =IF((O30-300000)<0,0,IF((O30-300000)<300000,0.11*(O30-300000),33000)) -> 33000 | R30: =IF((O30-600000)<0,0,IF((O30-600000)<500000,0.15*(O30-600000),75000)) -> 75000 | S30: =IF((O30-1100000)<0,0,IF((O30-1100000)<500000,0.19*(O30-1100000),95000)) -> 95000 | T30: =IF((O30-1600000)<0,0,IF((O30-1600000)<1600000,0.21*(O30-1600000),336000)) -> 244627.76 | V30: =P30+Q30+R30+S30+T30+U30 -> 468627.76 | W30: 12 | X30: =V30/W30 -> 39052.313 | Z30: =X30 -> 39052.313 | AA30: 22338.483 | AB30: =Z30-AA30 -> 16713.83
A31: 28 | B31: MOHAMMED BELLO | C31: 280631.92 | D31: 12 | E31: =C31*D31 -> 3367583 | G31: 221406.64 | I31: =E31-F31-G31-H31 -> 3146176.4 | J31: 200000 | K31: 0.2 | L31: =I31*K31 -> 629235.27 | M31: =J31+L31 -> 829235.27 | N31: =F31+G31+H31+M31 -> 1050641.9 | O31: =E31-N31 -> 2316941.1 | P31: =IF(O31<300000,0.07*O31,21000) -> 21000 | Q31: =IF((O31-300000)<0,0,IF((O31-300000)<300000,0.11*(O31-300000),33000)) -> 33000 | R31: =IF((O31-600000)<0,0,IF((O31-600000)<500000,0.15*(O31-600000),75000)) -> 75000 | S31: =IF((O31-1100000)<0,0,IF((O31-1100000)<500000,0.19*(O31-1100000),95000)) -> 95000 | T31: =IF((O31-1600000)<0,0,IF((O31-1600000)<1600000,0.21*(O31-1600000),336000)) -> 150557.63 | V31: =P31+Q31+R31+S31+T31+U31 -> 374557.63 | W31: 12 | X31: =V31/W31 -> 31213.136 | Z31: =X31 -> 31213.136 | AA31: 17572.885 | AB31: =Z31-AA31 -> 13640.251
A32: 29 | B32: HARUNA JIBRIL AMEH | C32: 274459.75 | D32: 12 | E32: =C32*D32 -> 3293517 | G32: =17956.78*12 -> 215481.36 | I32: =E32-F32-G32-H32 -> 3078035.6 | J32: 200000 | K32: 0.2 | L32: =I32*K32 -> 615607.13 | M32: =J32+L32 -> 815607.13 | N32: =F32+G32+H32+M32 -> 1031088.5 | O32: =E32-N32 -> 2262428.5 | P32: =IF(O32<300000,0.07*O32,21000) -> 21000 | Q32: =IF((O32-300000)<0,0,IF((O32-300000)<300000,0.11*(O32-300000),33000)) -> 33000 | R32: =IF((O32-600000)<0,0,IF((O32-600000)<500000,0.15*(O32-600000),75000)) -> 75000 | S32: =IF((O32-1100000)<0,0,IF((O32-1100000)<500000,0.19*(O32-1100000),95000)) -> 95000 | T32: =IF((O32-1600000)<0,0,IF((O32-1600000)<1600000,0.21*(O32-1600000),336000)) -> 139109.99 | V32: =P32+Q32+R32+S32+T32+U32 -> 363109.99 | W32: 12 | X32: =V32/W32 -> 30259.166 | Z32: =X32 -> 30259.166 | AA32: 16512.682 | AB32: =Z32-AA32 -> 13746.483
A33: 31
A34: 32 | B34: INTERNAL AUDIT
B35: OSANAIYE DAVID AKINYEMI | C35: 1535720 | D35: 12 | E35: =C35*D35 -> 18428640 | G35: 1378291.2 | I35: =E35-F35-G35-H35 -> 17050349 | J35: 200000 | K35: 0.2 | L35: =I35*K35 -> 3410069.8 | M35: =J35+L35 -> 3610069.8 | N35: =F35+G35+H35+M35 -> 4988361 | O35: =E35-N35 -> 13440279 | P35: =IF(O35<300000,0.07*O35,21000) -> 21000 | Q35: =IF((O35-300000)<0,0,IF((O35-300000)<300000,0.11*(O35-300000),33000)) -> 33000 | R35: =IF((O35-600000)<0,0,IF((O35-600000)<500000,0.15*(O35-600000),75000)) -> 75000 | S35: =IF((O35-1100000)<0,0,IF((O35-1100000)<500000,0.19*(O35-1100000),95000)) -> 95000 | T35: =IF((O35-1600000)<0,0,IF((O35-1600000)<1600000,0.21*(O35-1600000),336000)) -> 336000 | U35: =24%*(O35-3200000) -> 2457667 | V35: =P35+Q35+R35+S35+T35+U35 -> 3017667 | W35: 12 | X35: =V35/W35 -> 251472.25 | Z35: =X35 -> 251472.25 | AA35: 161106.81 | AB35: =Z35-AA35 -> 90365.441
B36: JAMILA ABDUL | C36: 353029.67 | D36: 12 | E36: =C36*D36 -> 4236356 | G36: 281308.48 | I36: =E36-F36-G36-H36 -> 3955047.5 | J36: 200000 | K36: 0.2 | L36: =I36*K36 -> 791009.5 | M36: =J36+L36 -> 991009.5 | N36: =F36+G36+H36+M36 -> 1272318 | O36: =E36-N36 -> 2964038 | P36: =IF(O36<300000,0.07*O36,21000) -> 21000 | Q36: =IF((O36-300000)<0,0,IF((O36-300000)<300000,0.11*(O36-300000),33000)) -> 33000 | R36: =IF((O36-600000)<0,0,IF((O36-600000)<500000,0.15*(O36-600000),75000)) -> 75000 | S36: =IF((O36-1100000)<0,0,IF((O36-1100000)<500000,0.19*(O36-1100000),95000)) -> 95000 | T36: =IF((O36-1600000)<0,0,IF((O36-1600000)<1600000,0.21*(O36-1600000),336000)) -> 286447.98 | V36: =P36+Q36+R36+S36+T36+U36 -> 510447.98 | W36: 12 | X36: =V36/W36 -> 42537.332 | Z36: =X36 -> 42537.332 | AA36: 17042.714 | AB36: =Z36-AA36 -> 25494.618
A37: 33 | B37: IJEOMA EWELUKWA | C37: 360965.58 | D37: 12 | E37: =C37*D37 -> 4331587 | G37: 288926.96 | I37: =E37-F37-G37-H37 -> 4042660 | J37: 200000 | K37: 0.2 | L37: =I37*K37 -> 808532.01 | M37: =J37+L37 -> 1008532 | N37: =F37+G37+H37+M37 -> 1297459 | O37: =E37-N37 -> 3034128 | P37: =IF(O37<300000,0.07*O37,21000) -> 21000 | Q37: =IF((O37-300000)<0,0,IF((O37-300000)<300000,0.11*(O37-300000),33000)) -> 33000 | R37: =IF((O37-600000)<0,0,IF((O37-600000)<500000,0.15*(O37-600000),75000)) -> 75000 | S37: =IF((O37-1100000)<0,0,IF((O37-1100000)<500000,0.19*(O37-1100000),95000)) -> 95000 | T37: =IF((O37-1600000)<0,0,IF((O37-1600000)<1600000,0.21*(O37-1600000),336000)) -> 301166.89 | V37: =P37+Q37+R37+S37+T37+U37 -> 525166.89 | W37: 12 | X37: =V37/W37 -> 43763.907 | Z37: =X37 -> 43763.907 | AA37: 26339.078 | AB37: =Z37-AA37 -> 17424.829
G38: 0
B39: LEG. SUPPORT SEVICES | G39: 0
A40: 35 | B40: PROF. EDOBA BRIGHT OMOREGBE | C40: 1635720 | D40: 12 | E40: =C40*D40 -> 19628640 | G40: 1378291.2 | I40: =E40-F40-G40-H40 -> 18250349 | J40: 200000 | K40: 0.2 | L40: =I40*K40 -> 3650069.8 | M40: =J40+L40 -> 3850069.8 | N40: =F40+G40+H40+M40 -> 5228361 | O40: =E40-N40 -> 14400279 | P40: =IF(O40<300000,0.07*O40,21000) -> 21000 | Q40: =IF((O40-300000)<0,0,IF((O40-300000)<300000,0.11*(O40-300000),33000)) -> 33000 | R40: =IF((O40-600000)<0,0,IF((O40-600000)<500000,0.15*(O40-600000),75000)) -> 75000 | S40: =IF((O40-1100000)<0,0,IF((O40-1100000)<500000,0.19*(O40-1100000),95000)) -> 95000 | T40: =IF((O40-1600000)<0,0,IF((O40-1600000)<1600000,0.21*(O40-1600000),336000)) -> 336000 | U40: =0.24*(O40-3200000) -> 2688067 | V40: =P40+Q40+R40+S40+T40+U40 -> 3248067 | W40: 12 | X40: =V40/W40 -> 270672.25 | Z40: =X40 -> 270672.25 | AA40: 180306.81 | AB40: =Z40-AA40 -> 90365.441
A41: 36 | B41: DR CLINTON JAJA | C41: 780675.58 | D41: 12 | E41: =C41*D41 -> 9368107 | G41: 595848.56 | I41: =E41-F41-G41-H41 -> 8772258.4 | J41: 200000 | K41: 0.2 | L41: =I41*K41 -> 1754451.7 | M41: =J41+L41 -> 1954451.7 | N41: =F41+G41+H41+M41 -> 2550300.2 | O41: =E41-N41 -> 6817806.8 | P41: =IF(O41<300000,0.07*O41,21000) -> 21000 | Q41: =IF((O41-300000)<0,0,IF((O41-300000)<300000,0.11*(O41-300000),33000)) -> 33000 | R41: =IF((O41-600000)<0,0,IF((O41-600000)<500000,0.15*(O41-600000),75000)) -> 75000 | S41: =IF((O41-1100000)<0,0,IF((O41-1100000)<500000,0.19*(O41-1100000),95000)) -> 95000 | T41: =IF((O41-1600000)<0,0,IF((O41-1600000)<1600000,0.21*(O41-1600000),336000)) -> 336000 | U41: =24%*(O41-3200000) -> 868273.62 | V41: =P41+Q41+R41+S41+T41+U41 -> 1428273.6 | W41: 12 | X41: =V41/W41 -> 119022.8 | Z41: =X41 -> 119022.8 | AA41: 79956.939 | AB41: =Z41-AA41 -> 39065.863
A42: 37 | B42: BETHEL UZOMA IHUGBA | C42: 919203.58 | D42: 12 | E42: =C42*D42 -> 11030443 | G42: 709635.44 | I42: =E42-F42-G42-H42 -> 10320808 | J42: 200000 | K42: 0.2 | L42: =I42*K42 -> 2064161.5 | M42: =J42+L42 -> 2264161.5 | N42: =F42+G42+H42+M42 -> 2973797 | O42: =E42-N42 -> 8056646 | P42: =IF(O42<300000,0.07*O42,21000) -> 21000 | Q42: =IF((O42-300000)<0,0,IF((O42-300000)<300000,0.11*(O42-300000),33000)) -> 33000 | R42: =IF((O42-600000)<0,0,IF((O42-600000)<500000,0.15*(O42-600000),75000)) -> 75000 | S42: =IF((O42-1100000)<0,0,IF((O42-1100000)<500000,0.19*(O42-1100000),95000)) -> 95000 | T42: =IF((O42-1600000)<0,0,IF((O42-1600000)<1600000,0.21*(O42-1600000),336000)) -> 336000 | U42: =24%*(O42-3200000) -> 1165595.1 | V42: =P42+Q42+R42+S42+T42+U42 -> 1725595.1 | W42: 12 | X42: =V42/W42 -> 143799.59 | Z42: =X42 -> 143799.59 | AA42: 97273.514 | AB42: =Z42-AA42 -> 46526.074
A43: 38 | B43: OGUCHE SAMUEL | C43: 780675.58 | D43: 12 | E43: =C43*D43 -> 9368107 | G43: 595848.56 | I43: =E43-F43-G43-H43 -> 8772258.4 | J43: 200000 | K43: 0.2 | L43: =I43*K43 -> 1754451.7 | M43: =J43+L43 -> 1954451.7 | N43: =F43+G43+H43+M43 -> 2550300.2 | O43: =E43-N43 -> 6817806.8 | P43: =IF(O43<300000,0.07*O43,21000) -> 21000 | Q43: =IF((O43-300000)<0,0,IF((O43-300000)<300000,0.11*(O43-300000),33000)) -> 33000 | R43: =IF((O43-600000)<0,0,IF((O43-600000)<500000,0.15*(O43-600000),75000)) -> 75000 | S43: =IF((O43-1100000)<0,0,IF((O43-1100000)<500000,0.19*(O43-1100000),95000)) -> 95000 | T43: =IF((O43-1600000)<0,0,IF((O43-1600000)<1600000,0.21*(O43-1600000),336000)) -> 336000 | U43: =24%*(O43-3200000) -> 868273.62 | V43: =P43+Q43+R43+S43+T43+U43 -> 1428273.6 | W43: 12 | X43: =V43/W43 -> 119022.8 | Z43: =X43 -> 119022.8 | AA43: 79956.939 | AB43: =Z43-AA43 -> 39065.863
A44: 39 | B44: IBRAHIM USMAN | C44: 780675.58 | D44: 12 | E44: =C44*D44 -> 9368107 | F44: ='[5]JANUARY 2024'!$V$47*12 -> 10052.25 | G44: 595848.56 | I44: =E44-F44-G44-H44 -> 8762206.2 | J44: 200000 | K44: 0.2 | L44: =I44*K44 -> 1752441.2 | M44: =J44+L44 -> 1952441.2 | N44: =F44+G44+H44+M44 -> 2558342 | O44: =E44-N44 -> 6809765 | P44: =IF(O44<300000,0.07*O44,21000) -> 21000 | Q44: =IF((O44-300000)<0,0,IF((O44-300000)<300000,0.11*(O44-300000),33000)) -> 33000 | R44: =IF((O44-600000)<0,0,IF((O44-600000)<500000,0.15*(O44-600000),75000)) -> 75000 | S44: =IF((O44-1100000)<0,0,IF((O44-1100000)<500000,0.19*(O44-1100000),95000)) -> 95000 | T44: =IF((O44-1600000)<0,0,IF((O44-1600000)<1600000,0.21*(O44-1600000),336000)) -> 336000 | U44: =24%*(O44-3200000) -> 866343.59 | V44: =P44+Q44+R44+S44+T44+U44 -> 1426343.6 | W44: 12 | X44: =V44/W44 -> 118861.97 | Z44: =X44 -> 118861.97 | AA44: 79796.103 | AB44: =Z44-AA44 -> 39065.863
A45: 40 | B45: DR MOHAMMED O. AMALI | C45: 742118.08 | D45: 12 | E45: =C45*D45 -> 8905417 | G45: 558833.36 | I45: =E45-F45-G45-H45 -> 8346583.6 | J45: 200000 | K45: 0.2 | L45: =I45*K45 -> 1669316.7 | M45: =J45+L45 -> 1869316.7 | N45: =F45+G45+H45+M45 -> 2428150.1 | O45: =E45-N45 -> 6477266.9 | P45: =IF(O45<300000,0.07*O45,21000) -> 21000 | Q45: =IF((O45-300000)<0,0,IF((O45-300000)<300000,0.11*(O45-300000),33000)) -> 33000 | R45: =IF((O45-600000)<0,0,IF((O45-600000)<500000,0.15*(O45-600000),75000)) -> 75000 | S45: =IF((O45-1100000)<0,0,IF((O45-1100000)<500000,0.19*(O45-1100000),95000)) -> 95000 | T45: =IF((O45-1600000)<0,0,IF((O45-1600000)<1600000,0.21*(O45-1600000),336000)) -> 336000 | U45: =24%*(O45-3200000) -> 786544.06 | V45: =P45+Q45+R45+S45+T45+U45 -> 1346544.1 | W45: 12 | X45: =V45/W45 -> 112212 | Z45: =X45 -> 112212 | AA45: 75572.916 | AB45: =Z45-AA45 -> 36639.089
A46: 41 | B46: YAHAYA SHAMSU | C46: 610498 | D46: 12 | E46: =C46*D46 -> 7325976 | G46: 451678.08 | I46: =E46-F46-G46-H46 -> 6874297.9 | J46: 200000 | K46: 0.2 | L46: =I46*K46 -> 1374859.6 | M46: =J46+L46 -> 1574859.6 | N46: =F46+G46+H46+M46 -> 2026537.7 | O46: =E46-N46 -> 5299438.3 | P46: =IF(O46<300000,0.07*O46,21000) -> 21000 | Q46: =IF((O46-300000)<0,0,IF((O46-300000)<300000,0.11*(O46-300000),33000)) -> 33000 | R46: =IF((O46-600000)<0,0,IF((O46-600000)<500000,0.15*(O46-600000),75000)) -> 75000 | S46: =IF((O46-1100000)<0,0,IF((O46-1100000)<500000,0.19*(O46-1100000),95000)) -> 95000 | T46: =IF((O46-1600000)<0,0,IF((O46-1600000)<1600000,0.21*(O46-1600000),336000)) -> 336000 | U46: =24%*(O46-3200000) -> 503865.2 | V46: =P46+Q46+R46+S46+T46+U46 -> 1063865.2 | W46: 12 | X46: =V46/W46 -> 88655.433 | Z46: =X46 -> 88655.433 | AA46: 58026.609 | AB46: =Z46-AA46 -> 30628.824
A47: 42 | B47: BILKIS S. LAWAL-GAMBARI | C47: 400965.58 | D47: 12 | E47: =C47*D47 -> 4811587 | G47: 288926.96 | I47: =E47-F47-G47-H47 -> 4522660 | J47: 200000 | K47: 0.2 | L47: =I47*K47 -> 904532.01 | M47: =J47+L47 -> 1104532 | N47: =F47+G47+H47+M47 -> 1393459 | O47: =E47-N47 -> 3418128 | P47: =IF(O47<300000,0.07*O47,21000) -> 21000 | Q47: =IF((O47-300000)<0,0,IF((O47-300000)<300000,0.11*(O47-300000),33000)) -> 33000 | R47: =IF((O47-600000)<0,0,IF((O47-600000)<500000,0.15*(O47-600000),75000)) -> 75000 | S47: =IF((O47-1100000)<0,0,IF((O47-1100000)<500000,0.19*(O47-1100000),95000)) -> 95000 | T47: =IF((O47-1600000)<0,0,IF((O47-1600000)<1600000,0.21*(O47-1600000),336000)) -> 336000 | U47: =24%*(O47-3200000) -> 52350.728 | V47: =P47+Q47+R47+S47+T47+U47 -> 612350.73 | W47: 12 | X47: =V47/W47 -> 51029.227 | Z47: =X47 -> 51029.227 | AA47: 33059.078 | AB47: =Z47-AA47 -> 17970.149
A48: 43 | B48: ZAINAB AKINDE | C48: 363165.33 | D48: 12 | E48: =C48*D48 -> 4357984 | G48: 252638.72 | I48: =E48-F48-G48-H48 -> 4105345.3 | J48: 200000 | K48: 0.2 | L48: =I48*K48 -> 821069.06 | M48: =J48+L48 -> 1021069.1 | N48: =F48+G48+H48+M48 -> 1273707.8 | O48: =E48-N48 -> 3084276.2 | P48: =IF(O48<300000,0.07*O48,21000) -> 21000 | Q48: =IF((O48-300000)<0,0,IF((O48-300000)<300000,0.11*(O48-300000),33000)) -> 33000 | R48: =IF((O48-600000)<0,0,IF((O48-600000)<500000,0.15*(O48-600000),75000)) -> 75000 | S48: =IF((O48-1100000)<0,0,IF((O48-1100000)<500000,0.19*(O48-1100000),95000)) -> 95000 | T48: =IF((O48-1600000)<0,0,IF((O48-1600000)<1600000,0.21*(O48-1600000),336000)) -> 311698.01 | V48: =P48+Q48+R48+S48+T48+U48 -> 535698.01 | W48: 12 | X48: =V48/W48 -> 44641.501 | Z48: =X48 -> 44641.501 | AA48: 29058.483 | AB48: =Z48-AA48 -> 15583.018
A49: 44 | B49: ABDULLAHI AHMAD USMAN | C49: 363165.33 | D49: 12 | E49: =C49*D49 -> 4357984 | G49: 252638.72 | I49: =E49-F49-G49-H49 -> 4105345.3 | J49: 200000 | K49: 0.2 | L49: =I49*K49 -> 821069.06 | M49: =J49+L49 -> 1021069.1 | N49: =F49+G49+H49+M49 -> 1273707.8 | O49: =E49-N49 -> 3084276.2 | P49: =IF(O49<300000,0.07*O49,21000) -> 21000 | Q49: =IF((O49-300000)<0,0,IF((O49-300000)<300000,0.11*(O49-300000),33000)) -> 33000 | R49: =IF((O49-600000)<0,0,IF((O49-600000)<500000,0.15*(O49-600000),75000)) -> 75000 | S49: =IF((O49-1100000)<0,0,IF((O49-1100000)<500000,0.19*(O49-1100000),95000)) -> 95000 | T49: =IF((O49-1600000)<0,0,IF((O49-1600000)<1600000,0.21*(O49-1600000),336000)) -> 311698.01 | V49: =P49+Q49+R49+S49+T49+U49 -> 535698.01 | W49: 12 | X49: =V49/W49 -> 44641.501 | Z49: =X49 -> 44641.501 | AA49: 28360.953 | AB49: =Z49-AA49 -> 16280.548
A50: 45 | B50: GUNAT NANSAK MARK | C50: 363165.33 | D50: 12 | E50: =C50*D50 -> 4357984 | G50: 252638.72 | I50: =E50-F50-G50-H50 -> 4105345.3 | J50: 200000 | K50: 0.2 | L50: =I50*K50 -> 821069.06 | M50: =J50+L50 -> 1021069.1 | N50: =F50+G50+H50+M50 -> 1273707.8 | O50: =E50-N50 -> 3084276.2 | P50: =IF(O50<300000,0.07*O50,21000) -> 21000 | Q50: =IF((O50-300000)<0,0,IF((O50-300000)<300000,0.11*(O50-300000),33000)) -> 33000 | R50: =IF((O50-600000)<0,0,IF((O50-600000)<500000,0.15*(O50-600000),75000)) -> 75000 | S50: =IF((O50-1100000)<0,0,IF((O50-1100000)<500000,0.19*(O50-1100000),95000)) -> 95000 | T50: =IF((O50-1600000)<0,0,IF((O50-1600000)<1600000,0.21*(O50-1600000),336000)) -> 311698.01 | V50: =P50+Q50+R50+S50+T50+U50 -> 535698.01 | W50: 12 | X50: =V50/W50 -> 44641.501 | Z50: =X50 -> 44641.501 | AA50: 29058.483 | AB50: =Z50-AA50 -> 15583.018
B52: LEGAL SERVICES
A53: 47 | B53: DR SHUAIBU DANWANKA | C53: 1635720 | D53: 12 | E53: =C53*D53 -> 19628640 | G53: 1378291.2 | I53: =E53-F53-G53-H53 -> 18250349 | J53: 200000 | K53: 0.2 | L53: =I53*K53 -> 3650069.8 | M53: =J53+L53 -> 3850069.8 | N53: =F53+G53+H53+M53 -> 5228361 | O53: =E53-N53 -> 14400279 | P53: =IF(O53<300000,0.07*O53,21000) -> 21000 | Q53: =IF((O53-300000)<0,0,IF((O53-300000)<300000,0.11*(O53-300000),33000)) -> 33000 | R53: =IF((O53-600000)<0,0,IF((O53-600000)<500000,0.15*(O53-600000),75000)) -> 75000 | S53: =IF((O53-1100000)<0,0,IF((O53-1100000)<500000,0.19*(O53-1100000),95000)) -> 95000 | T53: =IF((O53-1600000)<0,0,IF((O53-1600000)<1600000,0.21*(O53-1600000),336000)) -> 336000 | U53: =24%*(O53-3200000) -> 2688067 | V53: =P53+Q53+R53+S53+T53+U53 -> 3248067 | W53: 12 | X53: =V53/W53 -> 270672.25 | Z53: =X53 -> 270672.25 | AA53: 180306.81 | AB53: =Z53-AA53 -> 90365.441
A54: 48 | B54: ABDULSALAM BAKO | C54: 700675.58 | D54: 12 | E54: =C54*D54 -> 8408107 | G54: 595848.56 | I54: =E54-F54-G54-H54 -> 7812258.4 | J54: 200000 | K54: 0.2 | L54: =I54*K54 -> 1562451.7 | M54: =J54+L54 -> 1762451.7 | N54: =F54+G54+H54+M54 -> 2358300.2 | O54: =E54-N54 -> 6049806.8 | P54: =IF(O54<300000,0.07*O54,21000) -> 21000 | Q54: =IF((O54-300000)<0,0,IF((O54-300000)<300000,0.11*(O54-300000),33000)) -> 33000 | R54: =IF((O54-600000)<0,0,IF((O54-600000)<500000,0.15*(O54-600000),75000)) -> 75000 | S54: =IF((O54-1100000)<0,0,IF((O54-1100000)<500000,0.19*(O54-1100000),95000)) -> 95000 | T54: =IF((O54-1600000)<0,0,IF((O54-1600000)<1600000,0.21*(O54-1600000),336000)) -> 336000 | U54: =24%*(O54-3200000) -> 683953.62 | V54: =P54+Q54+R54+S54+T54+U54 -> 1243953.6 | W54: 12 | X54: =V54/W54 -> 103662.8 | Z54: =X54 -> 103662.8 | AA54: 64596.939 | AB54: =Z54-AA54 -> 39065.863
G55: 0
A56: 49 | B56: DEMOCRACY & GOVERNANCE | G56: 0
A57: 50 | B57: DR. ADEWALE ADEREMI | C57: 1635720 | D57: 12 | E57: =C57*D57 -> 19628640 | G57: 0 | I57: =E57-F57-G57-H57 -> 19628640 | J57: 200000 | K57: 0.2 | L57: =I57*K57 -> 3925728 | M57: =J57+L57 -> 4125728 | N57: =F57+G57+H57+M57 -> 4125728 | O57: =E57-N57 -> 15502912 | P57: =IF(O57<300000,0.07*O57,21000) -> 21000 | Q57: =IF((O57-300000)<0,0,IF((O57-300000)<300000,0.11*(O57-300000),33000)) -> 33000 | R57: =IF((O57-600000)<0,0,IF((O57-600000)<500000,0.15*(O57-600000),75000)) -> 75000 | S57: =IF((O57-1100000)<0,0,IF((O57-1100000)<500000,0.19*(O57-1100000),95000)) -> 95000 | T57: =IF((O57-1600000)<0,0,IF((O57-1600000)<1600000,0.21*(O57-1600000),336000)) -> 336000 | U57: =24%*(O57-3200000) -> 2952698.9 | V57: =P57+Q57+R57+S57+T57+U57 -> 3512698.9 | W57: 12 | X57: =V57/W57 -> 292724.91 | Z57: =X57 -> 292724.91 | AA57: 180306.81 | AB57: =Z57-AA57 -> 112418.1
A58: 51 | B58: NDANUSA MOHAMMED MANZUMA | C58: 761396.83 | D58: 12 | E58: =C58*D58 -> 9136762 | G58: =48111.7466666667*12 -> 577340.96 | I58: =E58-F58-G58-H58 -> 8559421 | J58: 200000 | K58: 0.2 | L58: =I58*K58 -> 1711884.2 | M58: =J58+L58 -> 1911884.2 | N58: =F58+G58+H58+M58 -> 2489225.2 | O58: =E58-N58 -> 6647536.8 | P58: =IF(O58<300000,0.07*O58,21000) -> 21000 | Q58: =IF((O58-300000)<0,0,IF((O58-300000)<300000,0.11*(O58-300000),33000)) -> 33000 | R58: =IF((O58-600000)<0,0,IF((O58-600000)<500000,0.15*(O58-600000),75000)) -> 75000 | S58: =IF((O58-1100000)<0,0,IF((O58-1100000)<500000,0.19*(O58-1100000),95000)) -> 95000 | T58: =IF((O58-1600000)<0,0,IF((O58-1600000)<1600000,0.21*(O58-1600000),336000)) -> 336000 | U58: =24%*(O58-3200000) -> 827408.84 | V58: =P58+Q58+R58+S58+T58+U58 -> 1387408.8 | W58: 12 | X58: =V58/W58 -> 115617.4 | Z58: =X58 -> 115617.4 | AA58: 77764.98 | AB58: =Z58-AA58 -> 37852.423
A59: 52 | B59: EJALONIBU GANIYU LAYI | C59: 582746.5 | D59: 12 | E59: =C59*D59 -> 6992958 | G59: 425036.64 | I59: =E59-F59-G59-H59 -> 6567921.4 | J59: 200000 | K59: 0.2 | L59: =I59*K59 -> 1313584.3 | M59: =J59+L59 -> 1513584.3 | N59: =F59+G59+H59+M59 -> 1938620.9 | O59: =E59-N59 -> 5054337.1 | P59: =IF(O59<300000,0.07*O59,21000) -> 21000 | Q59: =IF((O59-300000)<0,0,IF((O59-300000)<300000,0.11*(O59-300000),33000)) -> 33000 | R59: =IF((O59-600000)<0,0,IF((O59-600000)<500000,0.15*(O59-600000),75000)) -> 75000 | S59: =IF((O59-1100000)<0,0,IF((O59-1100000)<500000,0.19*(O59-1100000),95000)) -> 95000 | T59: =IF((O59-1600000)<0,0,IF((O59-1600000)<1600000,0.21*(O59-1600000),336000)) -> 336000 | U59: =24%*(O59-3200000) -> 445040.9 | V59: =P59+Q59+R59+S59+T59+U59 -> 1005040.9 | W59: 12 | X59: =V59/W59 -> 83753.408 | Z59: =X59 -> 83753.408 | AA59: 54931.249 | AB59: =Z59-AA59 -> 28822.159
A60: 53 | B60: LOHNA BONKAT JONATHAN | C60: 548915.92 | D60: 12 | E60: =C60*D60 -> 6586991 | G60: 411759.28 | I60: =E60-F60-G60-H60 -> 6175231.7 | J60: 200000 | K60: 0.2 | L60: =I60*K60 -> 1235046.3 | M60: =J60+L60 -> 1435046.3 | N60: =F60+G60+H60+M60 -> 1846805.6 | O60: =E60-N60 -> 4740185.4 | P60: =IF(O60<300000,0.07*O60,21000) -> 21000 | Q60: =IF((O60-300000)<0,0,IF((O60-300000)<300000,0.11*(O60-300000),33000)) -> 33000 | R60: =IF((O60-600000)<0,0,IF((O60-600000)<500000,0.15*(O60-600000),75000)) -> 75000 | S60: =IF((O60-1100000)<0,0,IF((O60-1100000)<500000,0.19*(O60-1100000),95000)) -> 95000 | T60: =IF((O60-1600000)<0,0,IF((O60-1600000)<1600000,0.21*(O60-1600000),336000)) -> 336000 | U60: =24%*(O60-3200000) -> 369644.49 | V60: =P60+Q60+R60+S60+T60+U60 -> 929644.49 | W60: 12 | X60: =V60/W60 -> 77470.374 | Z60: =X60 -> 77470.374 | AA60: 49548.776 | AB60: =Z60-AA60 -> 27921.598
A61: 54 | B61: YUNUSA ABDULLAHI | C61: 624373.75 | D61: 12 | E61: =C61*D61 -> 7492485 | G61: 464998.8 | I61: =E61-F61-G61-H61 -> 7027486.2 | J61: 200000 | K61: 0.2 | L61: =I61*K61 -> 1405497.2 | M61: =J61+L61 -> 1605497.2 | N61: =F61+G61+H61+M61 -> 2070496 | O61: =E61-N61 -> 5421989 | P61: =IF(O61<300000,0.07*O61,21000) -> 21000 | Q61: =IF((O61-300000)<0,0,IF((O61-300000)<300000,0.11*(O61-300000),33000)) -> 33000 | R61: =IF((O61-600000)<0,0,IF((O61-600000)<500000,0.15*(O61-600000),75000)) -> 75000 | S61: =IF((O61-1100000)<0,0,IF((O61-1100000)<500000,0.19*(O61-1100000),95000)) -> 95000 | T61: =IF((O61-1600000)<0,0,IF((O61-1600000)<1600000,0.21*(O61-1600000),336000)) -> 336000 | U61: =24%*(O61-3200000) -> 533277.35 | V61: =P61+Q61+R61+S61+T61+U61 -> 1093277.4 | W61: 12 | X61: =V61/W61 -> 91106.446 | Z61: =X61 -> 91106.446 | AA61: 46666.667 | AB61: =Z61-AA61 -> 44439.779
A62: 55 | B62: UDEFUNA NNADOZIE PATRICK | C62: 475703.83 | D62: 12 | E62: =C62*D62 -> 5708446 | G62: 351075.68 | I62: =E62-F62-G62-H62 -> 5357370.3 | J62: 200000 | K62: 0.2 | L62: =I62*K62 -> 1071474.1 | M62: =J62+L62 -> 1271474.1 | N62: =F62+G62+H62+M62 -> 1622549.7 | O62: =E62-N62 -> 4085896.3 | P62: =IF(O62<300000,0.07*O62,21000) -> 21000 | Q62: =IF((O62-300000)<0,0,IF((O62-300000)<300000,0.11*(O62-300000),33000)) -> 33000 | R62: =IF((O62-600000)<0,0,IF((O62-600000)<500000,0.15*(O62-600000),75000)) -> 75000 | S62: =IF((O62-1100000)<0,0,IF((O62-1100000)<500000,0.19*(O62-1100000),95000)) -> 95000 | T62: =IF((O62-1600000)<0,0,IF((O62-1600000)<1600000,0.21*(O62-1600000),336000)) -> 336000 | U62: =24%*(O62-3200000) -> 212615.1 | V62: =P62+Q62+R62+S62+T62+U62 -> 772615.1 | W62: 12 | X62: =V62/W62 -> 64384.592 | Z62: =X62 -> 64384.592 | AA62: 41338.951 | AB62: =Z62-AA62 -> 23045.641
A63: 56 | B63: SHAFIU YAHYA MIKAIL | C63: 475703.83 | D63: 12 | E63: =C63*D63 -> 5708446 | G63: 351075.68 | I63: =E63-F63-G63-H63 -> 5357370.3 | J63: 200000 | K63: 0.2 | L63: =I63*K63 -> 1071474.1 | M63: =J63+L63 -> 1271474.1 | N63: =F63+G63+H63+M63 -> 1622549.7 | O63: =E63-N63 -> 4085896.3 | P63: =IF(O63<300000,0.07*O63,21000) -> 21000 | Q63: =IF((O63-300000)<0,0,IF((O63-300000)<300000,0.11*(O63-300000),33000)) -> 33000 | R63: =IF((O63-600000)<0,0,IF((O63-600000)<500000,0.15*(O63-600000),75000)) -> 75000 | S63: =IF((O63-1100000)<0,0,IF((O63-1100000)<500000,0.19*(O63-1100000),95000)) -> 95000 | T63: =IF((O63-1600000)<0,0,IF((O63-1600000)<1600000,0.21*(O63-1600000),336000)) -> 336000 | U63: =24%*(O63-3200000) -> 212615.1 | V63: =P63+Q63+R63+S63+T63+U63 -> 772615.1 | W63: 12 | X63: =V63/W63 -> 64384.592 | Z63: =X63 -> 64384.592 | AA63: 41338.951 | AB63: =Z63-AA63 -> 23045.641
A64: 57 | B64: HASSAN YERIMA | C64: 475703.83 | D64: 12 | E64: =C64*D64 -> 5708446 | G64: 351075.68 | I64: =E64-F64-G64-H64 -> 5357370.3 | J64: 200000 | K64: 0.2 | L64: =I64*K64 -> 1071474.1 | M64: =J64+L64 -> 1271474.1 | N64: =F64+G64+H64+M64 -> 1622549.7 | O64: =E64-N64 -> 4085896.3 | P64: =IF(O64<300000,0.07*O64,21000) -> 21000 | Q64: =IF((O64-300000)<0,0,IF((O64-300000)<300000,0.11*(O64-300000),33000)) -> 33000 | R64: =IF((O64-600000)<0,0,IF((O64-600000)<500000,0.15*(O64-600000),75000)) -> 75000 | S64: =IF((O64-1100000)<0,0,IF((O64-1100000)<500000,0.19*(O64-1100000),95000)) -> 95000 | T64: =IF((O64-1600000)<0,0,IF((O64-1600000)<1600000,0.21*(O64-1600000),336000)) -> 336000 | U64: =24%*(O64-3200000) -> 212615.1 | V64: =P64+Q64+R64+S64+T64+U64 -> 772615.1 | W64: 12 | X64: =V64/W64 -> 64384.592 | Z64: =X64 -> 64384.592 | AA64: 41338.951 | AB64: =Z64-AA64 -> 23045.641
A65: 58 | B65: HAUWA PATE SADIQ | C65: 487895.17 | D65: 12 | E65: =C65*D65 -> 5854742 | G65: 362779.36 | I65: =E65-F65-G65-H65 -> 5491962.6 | J65: 200000 | K65: 0.2 | L65: =I65*K65 -> 1098392.5 | M65: =J65+L65 -> 1298392.5 | N65: =F65+G65+H65+M65 -> 1661171.9 | O65: =E65-N65 -> 4193570.1 | P65: =IF(O65<300000,0.07*O65,21000) -> 21000 | Q65: =IF((O65-300000)<0,0,IF((O65-300000)<300000,0.11*(O65-300000),33000)) -> 33000 | R65: =IF((O65-600000)<0,0,IF((O65-600000)<500000,0.15*(O65-600000),75000)) -> 75000 | S65: =IF((O65-1100000)<0,0,IF((O65-1100000)<500000,0.19*(O65-1100000),95000)) -> 95000 | T65: =IF((O65-1600000)<0,0,IF((O65-1600000)<1600000,0.21*(O65-1600000),336000)) -> 336000 | U65: =24%*(O65-3200000) -> 238456.83 | V65: =P65+Q65+R65+S65+T65+U65 -> 798456.83 | W65: 12 | X65: =V65/W65 -> 66538.069 | Z65: =X65 -> 66538.069 | AA65: 43368.882 | AB65: =Z65-AA65 -> 23169.186
A66: 59 | B66: KOLAPO Q. ABAYOMI | C66: 400965.58 | D66: 12 | E66: =C66*D66 -> 4811587 | G66: 288926.96 | I66: =E66-F66-G66-H66 -> 4522660 | J66: 200000 | K66: 0.2 | L66: =I66*K66 -> 904532.01 | M66: =J66+L66 -> 1104532 | N66: =F66+G66+H66+M66 -> 1393459 | O66: =E66-N66 -> 3418128 | P66: =IF(O66<300000,0.07*O66,21000) -> 21000 | Q66: =IF((O66-300000)<0,0,IF((O66-300000)<300000,0.11*(O66-300000),33000)) -> 33000 | R66: =IF((O66-600000)<0,0,IF((O66-600000)<500000,0.15*(O66-600000),75000)) -> 75000 | S66: =IF((O66-1100000)<0,0,IF((O66-1100000)<500000,0.19*(O66-1100000),95000)) -> 95000 | T66: =IF((O66-1600000)<0,0,IF((O66-1600000)<1600000,0.21*(O66-1600000),336000)) -> 336000 | U66: =24%*(O66-3200000) -> 52350.728 | V66: =P66+Q66+R66+S66+T66+U66 -> 612350.73 | W66: 12 | X66: =V66/W66 -> 51029.227 | Z66: =X66 -> 51029.227 | AA66: 33825.987 | AB66: =Z66-AA66 -> 17203.241
A67: 60
A68: 61
B69: DEPARTMENT OF STUDIES
B70: DR ASIMIYU G. ABIOLA | C70: 1635720 | D70: 12 | E70: =C70*D70 -> 19628640 | G70: 1378291.2 | I70: =E70-F70-G70-H70 -> 18250349 | J70: 200000 | K70: 0.2 | L70: =I70*K70 -> 3650069.8 | M70: =J70+L70 -> 3850069.8 | N70: =F70+G70+H70+M70 -> 5228361 | O70: =E70-N70 -> 14400279 | P70: =IF(O70<300000,0.07*O70,21000) -> 21000 | Q70: =IF((O70-300000)<0,0,IF((O70-300000)<300000,0.11*(O70-300000),33000)) -> 33000 | R70: =IF((O70-600000)<0,0,IF((O70-600000)<500000,0.15*(O70-600000),75000)) -> 75000 | S70: =IF((O70-1100000)<0,0,IF((O70-1100000)<500000,0.19*(O70-1100000),95000)) -> 95000 | T70: =IF((O70-1600000)<0,0,IF((O70-1600000)<1600000,0.21*(O70-1600000),336000)) -> 336000 | U70: =24%*(O70-3200000) -> 2688067 | V70: =P70+Q70+R70+S70+T70+U70 -> 3248067 | W70: 12 | X70: =V70/W70 -> 270672.25 | Z70: =X70 -> 270672.25 | AA70: 180306.81 | AB70: =Z70-AA70 -> 90365.441
A71: 62 | B71: USMAN WALI | C71: 761396.83 | D71: 12 | E71: =C71*D71 -> 9136762 | G71: 0 | I71: =E71-F71-G71-H71 -> 9136762 | J71: 200000 | K71: 0.2 | L71: =I71*K71 -> 1827352.4 | M71: =J71+L71 -> 2027352.4 | N71: =F71+G71+H71+M71 -> 2027352.4 | O71: =E71-N71 -> 7109409.6 | P71: =IF(O71<300000,0.07*O71,21000) -> 21000 | Q71: =IF((O71-300000)<0,0,IF((O71-300000)<300000,0.11*(O71-300000),33000)) -> 33000 | R71: =IF((O71-600000)<0,0,IF((O71-600000)<500000,0.15*(O71-600000),75000)) -> 75000 | S71: =IF((O71-1100000)<0,0,IF((O71-1100000)<500000,0.19*(O71-1100000),95000)) -> 95000 | T71: =IF((O71-1600000)<0,0,IF((O71-1600000)<1600000,0.21*(O71-1600000),336000)) -> 336000 | U71: =24%*(O71-3200000) -> 938258.3 | V71: =P71+Q71+R71+S71+T71+U71 -> 1498258.3 | W71: 12 | X71: =V71/W71 -> 124854.86 | Z71: =X71 -> 124854.86 | AA71: 77764.98 | AB71: =Z71-AA71 -> 47089.878
A72: 63 | B72: AYOBOLU OLAJIDE OLUFUNSHO | C72: =700675.583333333+80000 -> 780675.58 | D72: 12 | E72: =C72*D72 -> 9368107 | G72: 0 | I72: =E72-F72-G72-H72 -> 9368107 | J72: 200000 | K72: 0.2 | L72: =I72*K72 -> 1873621.4 | M72: =J72+L72 -> 2073621.4 | N72: =F72+G72+H72+M72 -> 2073621.4 | O72: =E72-N72 -> 7294485.6 | P72: =IF(O72<300000,0.07*O72,21000) -> 21000 | Q72: =IF((O72-300000)<0,0,IF((O72-300000)<300000,0.11*(O72-300000),33000)) -> 33000 | R72: =IF((O72-600000)<0,0,IF((O72-600000)<500000,0.15*(O72-600000),75000)) -> 75000 | S72: =IF((O72-1100000)<0,0,IF((O72-1100000)<500000,0.19*(O72-1100000),95000)) -> 95000 | T72: =IF((O72-1600000)<0,0,IF((O72-1600000)<1600000,0.21*(O72-1600000),336000)) -> 336000 | U72: =24%*(O72-3200000) -> 982676.54 | V72: =P72+Q72+R72+S72+T72+U72 -> 1542676.5 | W72: 12 | X72: =V72/W72 -> 128556.38 | Z72: =X72 -> 128556.38 | AA72: 64596.939 | AB72: =Z72-AA72 -> 63959.44
A73: 64 | B73: ANTHONY EDET | C73: 596622.25 | D73: 12 | E73: =C73*D73 -> 7159467 | F73: ='[5]JANUARY 2024'!$V$78*12 -> 8019.795 | G73: 438357.36 | I73: =E73-F73-G73-H73 -> 6713089.8 | J73: 200000 | K73: 0.2 | L73: =I73*K73 -> 1342618 | M73: =J73+L73 -> 1542618 | N73: =F73+G73+H73+M73 -> 1988995.1 | O73: =E73-N73 -> 5170471.9 | P73: =IF(O73<300000,0.07*O73,21000) -> 21000 | Q73: =IF((O73-300000)<0,0,IF((O73-300000)<300000,0.11*(O73-300000),33000)) -> 33000 | R73: =IF((O73-600000)<0,0,IF((O73-600000)<500000,0.15*(O73-600000),75000)) -> 75000 | S73: =IF((O73-1100000)<0,0,IF((O73-1100000)<500000,0.19*(O73-1100000),95000)) -> 95000 | T73: =IF((O73-1600000)<0,0,IF((O73-1600000)<1600000,0.21*(O73-1600000),336000)) -> 336000 | U73: =24%*(O73-3200000) -> 472913.25 | V73: =P73+Q73+R73+S73+T73+U73 -> 1032913.3 | W73: 12 | X73: =V73/W73 -> 86076.104 | Z73: =X73 -> 86076.104 | AA73: 56350.586 | AB73: =Z73-AA73 -> 29725.518
A74: 65 | B74: IGWE STACY | C74: 408901.5 | D74: 12 | E74: =C74*D74 -> 4906818 | G74: 296545.44 | I74: =E74-F74-G74-H74 -> 4610272.6 | J74: 200000 | K74: 0.2 | L74: =I74*K74 -> 922054.51 | M74: =J74+L74 -> 1122054.5 | N74: =F74+G74+H74+M74 -> 1418600 | O74: =E74-N74 -> 3488218 | P74: =IF(O74<300000,0.07*O74,21000) -> 21000 | Q74: =IF((O74-300000)<0,0,IF((O74-300000)<300000,0.11*(O74-300000),33000)) -> 33000 | R74: =IF((O74-600000)<0,0,IF((O74-600000)<500000,0.15*(O74-600000),75000)) -> 75000 | S74: =IF((O74-1100000)<0,0,IF((O74-1100000)<500000,0.19*(O74-1100000),95000)) -> 95000 | T74: =IF((O74-1600000)<0,0,IF((O74-1600000)<1600000,0.21*(O74-1600000),336000)) -> 336000 | U74: =0.24*(O74-3200000) -> 69172.332 | V74: =P74+Q74+R74+S74+T74+U74 -> 629172.33 | W74: 12 | X74: =V74/W74 -> 52431.028 | Z74: =X74 -> 52431.028 | AA74: 17507.549 | AB74: =Z74-AA74 -> 34923.479
B75: OLANIYAN TAIWO ABINBOLA | C75: 363165.33 | D75: 12 | E75: =C75*D75 -> 4357984 | G75: 252638.72 | I75: =E75-F75-G75-H75 -> 4105345.3 | J75: 200000 | K75: 0.2 | L75: =I75*K75 -> 821069.06 | M75: =J75+L75 -> 1021069.1 | N75: =F75+G75+H75+M75 -> 1273707.8 | O75: =E75-N75 -> 3084276.2 | P75: =IF(O75<300000,0.07*O75,21000) -> 21000 | Q75: =IF((O75-300000)<0,0,IF((O75-300000)<300000,0.11*(O75-300000),33000)) -> 33000 | R75: =IF((O75-600000)<0,0,IF((O75-600000)<500000,0.15*(O75-600000),75000)) -> 75000 | S75: =IF((O75-1100000)<0,0,IF((O75-1100000)<500000,0.19*(O75-1100000),95000)) -> 95000 | T75: =IF((O75-1600000)<0,0,IF((O75-1600000)<1600000,0.21*(O75-1600000),336000)) -> 311698.01 | V75: =P75+Q75+R75+S75+T75+U75 -> 535698.01 | W75: 12 | X75: =V75/W75 -> 44641.501 | Z75: =X75 -> 44641.501 | AA75: 29058.483 | AB75: =Z75-AA75 -> 15583.018
B76: AMINAT JUMOKE SULAIMON | C76: 324459.75 | D76: 12 | E76: =C76*D76 -> 3893517 | G76: 215481.36 | I76: =E76-F76-G76-H76 -> 3678035.6 | J76: 200000 | K76: 0.2 | L76: =I76*K76 -> 735607.13 | M76: =J76+L76 -> 935607.13 | N76: =F76+G76+H76+M76 -> 1151088.5 | O76: =E76-N76 -> 2742428.5 | P76: =IF(O76<300000,0.07*O76,21000) -> 21000 | Q76: =IF((O76-300000)<0,0,IF((O76-300000)<300000,0.11*(O76-300000),33000)) -> 33000 | R76: =IF((O76-600000)<0,0,IF((O76-600000)<500000,0.15*(O76-600000),75000)) -> 75000 | S76: =IF((O76-1100000)<0,0,IF((O76-1100000)<500000,0.19*(O76-1100000),95000)) -> 95000 | T76: =IF((O76-1600000)<0,0,IF((O76-1600000)<1600000,0.21*(O76-1600000),336000)) -> 239909.99 | V76: =P76+Q76+R76+S76+T76+U76 -> 463909.99 | W76: 12 | X76: =V76/W76 -> 38659.166 | Z76: =X76 -> 38659.166 | AA76: 24751.17 | AB76: =Z76-AA76 -> 13907.995
B77: TOTAL
A78: 66
A79: 67 | B79: ECON. DEV. & SOC. RESEARCH | AB79: difference
A80: 68 | B80: TERFA WILLIAMS ABRAHAM | C80: =880675.583333333+100000 -> 980675.58 | D80: 12 | E80: =C80*D80 -> 11768107 | G80: 595848.56 | I80: =E80-F80-G80-H80 -> 11172258 | J80: 200000 | K80: 0.2 | L80: =I80*K80 -> 2234451.7 | M80: =J80+L80 -> 2434451.7 | N80: =F80+G80+H80+M80 -> 3030300.2 | O80: =E80-N80 -> 8737806.8 | P80: =IF(O80<300000,0.07*O80,21000) -> 21000 | Q80: =IF((O80-300000)<0,0,IF((O80-300000)<300000,0.11*(O80-300000),33000)) -> 33000 | R80: =IF((O80-600000)<0,0,IF((O80-600000)<500000,0.15*(O80-600000),75000)) -> 75000 | S80: =IF((O80-1100000)<0,0,IF((O80-1100000)<500000,0.19*(O80-1100000),95000)) -> 95000 | T80: =IF((O80-1600000)<0,0,IF((O80-1600000)<1600000,0.21*(O80-1600000),336000)) -> 336000 | U80: =24%*(O80-3200000) -> 1329073.6 | V80: =P80+Q80+R80+S80+T80+U80 -> 1889073.6 | W80: 12 | X80: =V80/W80 -> 157422.8 | Z80: =X80 -> 157422.8 | AA80: 99156.939 | AB80: =Z80-AA80 -> 58265.863 | AC80: TERFA WILLIAMS ABRAHAM
A81: 69 | B81: DR AUGUSTINE C. OSIGWE | C81: 780675.58 | D81: 12 | E81: =C81*D81 -> 9368107 | F81: ='[5]JANUARY 2024'!$V$86*12 -> 10052.25 | G81: 595848.56 | I81: =E81-F81-G81-H81 -> 8762206.2 | J81: 200000 | K81: 0.2 | L81: =I81*K81 -> 1752441.2 | M81: =J81+L81 -> 1952441.2 | N81: =F81+G81+H81+M81 -> 2558342 | O81: =E81-N81 -> 6809765 | P81: =IF(O81<300000,0.07*O81,21000) -> 21000 | Q81: =IF((O81-300000)<0,0,IF((O81-300000)<300000,0.11*(O81-300000),33000)) -> 33000 | R81: =IF((O81-600000)<0,0,IF((O81-600000)<500000,0.15*(O81-600000),75000)) -> 75000 | S81: =IF((O81-1100000)<0,0,IF((O81-1100000)<500000,0.19*(O81-1100000),95000)) -> 95000 | T81: =IF((O81-1600000)<0,0,IF((O81-1600000)<1600000,0.21*(O81-1600000),336000)) -> 336000 | U81: =24%*(O81-3200000) -> 866343.59 | V81: =P81+Q81+R81+S81+T81+U81 -> 1426343.6 | W81: 12 | X81: =V81/W81 -> 118861.97 | Z81: =X81 -> 118861.97 | AA81: 98996.103 | AB81: =Z81-AA81 -> 19865.863 | AC81: DR AUGUSTINE C. OSIGWE
A82: 70 | B82: OMOJU OLUWASOLA EMMANUEL | C82: 742118.08 | D82: 12 | E82: =C82*D82 -> 8905417 | G82: 558833.36 | I82: =E82-F82-G82-H82 -> 8346583.6 | J82: 200000 | K82: 0.2 | L82: =I82*K82 -> 1669316.7 | M82: =J82+L82 -> 1869316.7 | N82: =F82+G82+H82+M82 -> 2428150.1 | O82: =E82-N82 -> 6477266.9 | P82: =IF(O82<300000,0.07*O82,21000) -> 21000 | Q82: =IF((O82-300000)<0,0,IF((O82-300000)<300000,0.11*(O82-300000),33000)) -> 33000 | R82: =IF((O82-600000)<0,0,IF((O82-600000)<500000,0.15*(O82-600000),75000)) -> 75000 | S82: =IF((O82-1100000)<0,0,IF((O82-1100000)<500000,0.19*(O82-1100000),95000)) -> 95000 | T82: =IF((O82-1600000)<0,0,IF((O82-1600000)<1600000,0.21*(O82-1600000),336000)) -> 336000 | U82: =24%*(O82-3200000) -> 786544.06 | V82: =P82+Q82+R82+S82+T82+U82 -> 1346544.1 | W82: 12 | X82: =V82/W82 -> 112212 | Z82: =X82 -> 112212 | AA82: 79956.939 | AB82: =Z82-AA82 -> 32255.066 | AC82: OMOJU OLUWASOLA EMMANUEL
A83: 71 | B83: IBE EZECHI CYRIACUS | C83: 561804.92 | D83: 12 | E83: =C83*D83 -> 6741659 | G83: 424132.72 | I83: =E83-F83-G83-H83 -> 6317526.3 | J83: 200000 | K83: 0.2 | L83: =I83*K83 -> 1263505.3 | M83: =J83+L83 -> 1463505.3 | N83: =F83+G83+H83+M83 -> 1887638 | O83: =E83-N83 -> 4854021 | P83: =IF(O83<300000,0.07*O83,21000) -> 21000 | Q83: =IF((O83-300000)<0,0,IF((O83-300000)<300000,0.11*(O83-300000),33000)) -> 33000 | R83: =IF((O83-600000)<0,0,IF((O83-600000)<500000,0.15*(O83-600000),75000)) -> 75000 | S83: =IF((O83-1100000)<0,0,IF((O83-1100000)<500000,0.19*(O83-1100000),95000)) -> 95000 | T83: =IF((O83-1600000)<0,0,IF((O83-1600000)<1600000,0.21*(O83-1600000),336000)) -> 336000 | U83: =24%*(O83-3200000) -> 396965.05 | V83: =P83+Q83+R83+S83+T83+U83 -> 956965.05 | W83: 12 | X83: =V83/W83 -> 79747.087 | Z83: =X83 -> 79747.087 | AA83: 75574.677 | AB83: =Z83-AA83 -> 4172.4099 | AC83: IBE EZECHI CYRIACUS
A84: 72 | B84: OSIKHEN LEO IGBANOI | C84: 548915.92 | D84: 12 | E84: =C84*D84 -> 6586991 | G84: 411759.28 | I84: =E84-F84-G84-H84 -> 6175231.7 | J84: 200000 | K84: 0.2 | L84: =I84*K84 -> 1235046.3 | M84: =J84+L84 -> 1435046.3 | N84: =F84+G84+H84+M84 -> 1846805.6 | O84: =E84-N84 -> 4740185.4 | P84: =IF(O84<300000,0.07*O84,21000) -> 21000 | Q84: =IF((O84-300000)<0,0,IF((O84-300000)<300000,0.11*(O84-300000),33000)) -> 33000 | R84: =IF((O84-600000)<0,0,IF((O84-600000)<500000,0.15*(O84-600000),75000)) -> 75000 | S84: =IF((O84-1100000)<0,0,IF((O84-1100000)<500000,0.19*(O84-1100000),95000)) -> 95000 | T84: =IF((O84-1600000)<0,0,IF((O84-1600000)<1600000,0.21*(O84-1600000),336000)) -> 336000 | U84: =24%*(O84-3200000) -> 369644.49 | V84: =P84+Q84+R84+S84+T84+U84 -> 929644.49 | W84: 12 | X84: =V84/W84 -> 77470.374 | Z84: =X84 -> 77470.374 | AA84: 50985.978 | AB84: =Z84-AA84 -> 26484.397 | AC84: OSIKHEN LEO IGBANOI
A85: 73 | B85: OKUNGBOWA OSARETIN GODSPOWER | C85: 568870.75 | D85: 12 | E85: =C85*D85 -> 6826449 | G85: 411715.92 | I85: =E85-F85-G85-H85 -> 6414733.1 | J85: 200000 | K85: 0.2 | L85: =I85*K85 -> 1282946.6 | M85: =J85+L85 -> 1482946.6 | N85: =F85+G85+H85+M85 -> 1894662.5 | O85: =E85-N85 -> 4931786.5 | P85: =IF(O85<300000,0.07*O85,21000) -> 21000 | Q85: =IF((O85-300000)<0,0,IF((O85-300000)<300000,0.11*(O85-300000),33000)) -> 33000 | R85: =IF((O85-600000)<0,0,IF((O85-600000)<500000,0.15*(O85-600000),75000)) -> 75000 | S85: =IF((O85-1100000)<0,0,IF((O85-1100000)<500000,0.19*(O85-1100000),95000)) -> 95000 | T85: =IF((O85-1600000)<0,0,IF((O85-1600000)<1600000,0.21*(O85-1600000),336000)) -> 336000 | U85: =24%*(O85-3200000) -> 415628.75 | V85: =P85+Q85+R85+S85+T85+U85 -> 975628.75 | W85: 12 | X85: =V85/W85 -> 81302.396 | Z85: =X85 -> 81302.396 | AA85: 49548.776 | AB85: =Z85-AA85 -> 31753.62 | AC85: OKUNGBOWA OSARETIN GODSPOWER
A86: 74 | B86: YUSUF IBRAHIM | C86: 475703.83 | D86: 12 | E86: =C86*D86 -> 5708446 | G86: =29256.3066666667*12 -> 351075.68 | I86: =E86-F86-G86-H86 -> 5357370.3 | J86: 200000 | K86: 0.2 | L86: =I86*K86 -> 1071474.1 | M86: =J86+L86 -> 1271474.1 | N86: =F86+G86+H86+M86 -> 1622549.7 | O86: =E86-N86 -> 4085896.3 | P86: =IF(O86<300000,0.07*O86,21000) -> 21000 | Q86: =IF((O86-300000)<0,0,IF((O86-300000)<300000,0.11*(O86-300000),33000)) -> 33000 | R86: =IF((O86-600000)<0,0,IF((O86-600000)<500000,0.15*(O86-600000),75000)) -> 75000 | S86: =IF((O86-1100000)<0,0,IF((O86-1100000)<500000,0.19*(O86-1100000),95000)) -> 95000 | T86: =IF((O86-1600000)<0,0,IF((O86-1600000)<1600000,0.21*(O86-1600000),336000)) -> 336000 | U86: =24%*(O86-3200000) -> 212615.1 | V86: =P86+Q86+R86+S86+T86+U86 -> 772615.1 | W86: 12 | X86: =V86/W86 -> 64384.592 | Z86: =X86 -> 64384.592 | AA86: 53384.054 | AB86: =Z86-AA86 -> 11000.538 | AC86: YUSUF IBRAHIM
A87: 75 | B87: MUSTAPHA RAFIU AYOBANJI | C87: 510248.92 | D87: 12 | E87: =C87*D87 -> 6122987 | F87: ='[5]JANUARY 2024'!$V$92*12 -> 6922.497 | G87: 374638.96 | I87: =E87-F87-G87-H87 -> 5741425.5 | J87: 200000 | K87: 0.2 | L87: =I87*K87 -> 1148285.1 | M87: =J87+L87 -> 1348285.1 | N87: =F87+G87+H87+M87 -> 1729846.6 | O87: =E87-N87 -> 4393140.4 | P87: =IF(O87<300000,0.07*O87,21000) -> 21000 | Q87: =IF((O87-300000)<0,0,IF((O87-300000)<300000,0.11*(O87-300000),33000)) -> 33000 | R87: =IF((O87-600000)<0,0,IF((O87-600000)<500000,0.15*(O87-600000),75000)) -> 75000 | S87: =IF((O87-1100000)<0,0,IF((O87-1100000)<500000,0.19*(O87-1100000),95000)) -> 95000 | T87: =IF((O87-1600000)<0,0,IF((O87-1600000)<1600000,0.21*(O87-1600000),336000)) -> 336000 | U87: =24%*(O87-3200000) -> 286353.7 | V87: =P87+Q87+R87+S87+T87+U87 -> 846353.7 | W87: 12 | X87: =V87/W87 -> 70529.475 | Z87: =X87 -> 70529.475 | AA87: 41242.036 | AB87: =Z87-AA87 -> 29287.439 | AC87: MUSTAPHA RAFIU AYOBANJI
A88: 76 | B88: MARYAM MUSA SADA | C88: 400965.58 | D88: 12 | E88: =C88*D88 -> 4811587 | G88: 288926.96 | I88: =E88-F88-G88-H88 -> 4522660 | J88: 200000 | K88: 0.2 | L88: =I88*K88 -> 904532.01 | M88: =J88+L88 -> 1104532 | N88: =F88+G88+H88+M88 -> 1393459 | O88: =E88-N88 -> 3418128 | P88: =IF(O88<300000,0.07*O88,21000) -> 21000 | Q88: =IF((O88-300000)<0,0,IF((O88-300000)<300000,0.11*(O88-300000),33000)) -> 33000 | R88: =IF((O88-600000)<0,0,IF((O88-600000)<500000,0.15*(O88-600000),75000)) -> 75000 | S88: =IF((O88-1100000)<0,0,IF((O88-1100000)<500000,0.19*(O88-1100000),95000)) -> 95000 | T88: =IF((O88-1600000)<0,0,IF((O88-1600000)<1600000,0.21*(O88-1600000),336000)) -> 336000 | U88: =24%*(O88-3200000) -> 52350.728 | V88: =P88+Q88+R88+S88+T88+U88 -> 612350.73 | W88: 12 | X88: =V88/W88 -> 51029.227 | Z88: =X88 -> 51029.227 | AA88: 45414.456 | AB88: =Z88-AA88 -> 5614.7711 | AC88: MARYAM MUSA SADA
B89: CHARITY EZENWAJIOBI | C89: 330631.92 | D89: 12 | E89: =C89*D89 -> 3967583 | G89: 221406.64 | I89: =E89-F89-G89-H89 -> 3746176.4 | J89: 200000 | K89: 0.2 | L89: =I89*K89 -> 749235.27 | M89: =J89+L89 -> 949235.27 | N89: =F89+G89+H89+M89 -> 1170641.9 | O89: =E89-N89 -> 2796941.1 | P89: =IF(O89<300000,0.07*O89,21000) -> 21000 | Q89: =IF((O89-300000)<0,0,IF((O89-300000)<300000,0.11*(O89-300000),33000)) -> 33000 | R89: =IF((O89-600000)<0,0,IF((O89-600000)<500000,0.15*(O89-600000),75000)) -> 75000 | S89: =IF((O89-1100000)<0,0,IF((O89-1100000)<500000,0.19*(O89-1100000),95000)) -> 95000 | T89: =IF((O89-1600000)<0,0,IF((O89-1600000)<1600000,0.21*(O89-1600000),336000)) -> 251357.63 | V89: =P89+Q89+R89+S89+T89+U89 -> 475357.63 | W89: 12 | X89: =V89/W89 -> 39613.136 | Z89: =X89 -> 39613.136 | AA89: 33825.987 | AB89: =Z89-AA89 -> 5787.1491 | AC89: CHARITY EZENWAJIOBI
A92: 78 | B92: TRAINING & INT''L COOP
A93: 79 | B93: AKINSANMI ADEJOKE OLUKEMI | C93: 1452042.7 | D93: 12 | E93: =C93*D93 -> 17424512 | F93: ='[5]JANUARY 2024'!$V$98*12 -> 12795.951 | G93: =(0.08*1352042.67)*12 -> 1297961 | I93: =E93-F93-G93-H93 -> 16113755 | J93: 200000 | K93: 0.2 | L93: =I93*K93 -> 3222751 | M93: =J93+L93 -> 3422751 | N93: =F93+G93+H93+M93 -> 4733507.9 | O93: =E93-N93 -> 12691004 | P93: =IF(O93<300000,0.07*O93,21000) -> 21000 | Q93: =IF((O93-300000)<0,0,IF((O93-300000)<300000,0.11*(O93-300000),33000)) -> 33000 | R93: =IF((O93-600000)<0,0,IF((O93-600000)<500000,0.15*(O93-600000),75000)) -> 75000 | S93: =IF((O93-1100000)<0,0,IF((O93-1100000)<500000,0.19*(O93-1100000),95000)) -> 95000 | T93: =IF((O93-1600000)<0,0,IF((O93-1600000)<1600000,0.21*(O93-1600000),336000)) -> 336000 | U93: =24%*(O93-3200000) -> 2277841 | V93: =P93+Q93+R93+S93+T93+U93 -> 2837841 | W93: 12 | X93: =V93/W93 -> 236486.75 | Z93: =X93 -> 236486.75 | AA93: 82423.216 | AB93: =Z93-AA93 -> 154063.53 | AC93: AKINSANMI ADEJOKE OLUKEMI
A94: 80 | B94: MOHAMMED R. ADAMU | C94: 526622.25 | D94: 12 | E94: =C94*D94 -> 6319467 | G94: 438357.36 | I94: =E94-F94-G94-H94 -> 5881109.6 | J94: 200000 | K94: 0.2 | L94: =I94*K94 -> 1176221.9 | M94: =J94+L94 -> 1376221.9 | N94: =F94+G94+H94+M94 -> 1814579.3 | O94: =E94-N94 -> 4504887.7 | P94: =IF(O94<300000,0.07*O94,21000) -> 21000 | Q94: =IF((O94-300000)<0,0,IF((O94-300000)<300000,0.11*(O94-300000),33000)) -> 33000 | R94: =IF((O94-600000)<0,0,IF((O94-600000)<500000,0.15*(O94-600000),75000)) -> 75000 | S94: =IF((O94-1100000)<0,0,IF((O94-1100000)<500000,0.19*(O94-1100000),95000)) -> 95000 | T94: =IF((O94-1600000)<0,0,IF((O94-1600000)<1600000,0.21*(O94-1600000),336000)) -> 336000 | U94: =24%*(O94-3200000) -> 313173.05 | V94: =P94+Q94+R94+S94+T94+U94 -> 873173.05 | W94: 12 | X94: =V94/W94 -> 72764.421 | Z94: =X94 -> 72764.421 | AA94: 82627.951 | AB94: =Z94-AA94 -> -9863.5305 | AC94: MOHAMMED R. ADAMU
A95: 81 | B95: OKECHUKWU UCHENNA HULDA | C95: 437895.17 | D95: 12 | E95: =C95*D95 -> 5254742 | G95: 362779.36 | I95: =E95-F95-G95-H95 -> 4891962.6 | J95: 200000 | K95: 0.2 | L95: =I95*K95 -> 978392.53 | M95: =J95+L95 -> 1178392.5 | N95: =F95+G95+H95+M95 -> 1541171.9 | O95: =E95-N95 -> 3713570.1 | P95: =IF(O95<300000,0.07*O95,21000) -> 21000 | Q95: =IF((O95-300000)<0,0,IF((O95-300000)<300000,0.11*(O95-300000),33000)) -> 33000 | R95: =IF((O95-600000)<0,0,IF((O95-600000)<500000,0.15*(O95-600000),75000)) -> 75000 | S95: =IF((O95-1100000)<0,0,IF((O95-1100000)<500000,0.19*(O95-1100000),95000)) -> 95000 | T95: =IF((O95-1600000)<0,0,IF((O95-1600000)<1600000,0.21*(O95-1600000),336000)) -> 336000 | U95: =24%*(O95-3200000) -> 123256.83 | V95: =P95+Q95+R95+S95+T95+U95 -> 683256.83 | W95: 12 | X95: =V95/W95 -> 56938.069 | Z95: =X95 -> 56938.069 | AA95: 43492.373 | AB95: =Z95-AA95 -> 13445.696 | AC95: OKECHUKWU UCHENNA HULDA
B96: TASSNEEM IBRAHIM | C96: 360965.58 | D96: 12 | E96: =C96*D96 -> 4331587 | G96: 288926.96 | I96: =E96-F96-G96-H96 -> 4042660 | J96: 200000 | K96: 0.2 | L96: =I96*K96 -> 808532.01 | M96: =J96+L96 -> 1008532 | N96: =F96+G96+H96+M96 -> 1297459 | O96: =E96-N96 -> 3034128 | P96: =IF(O96<300000,0.07*O96,21000) -> 21000 | Q96: =IF((O96-300000)<0,0,IF((O96-300000)<300000,0.11*(O96-300000),33000)) -> 33000 | R96: =IF((O96-600000)<0,0,IF((O96-600000)<500000,0.15*(O96-600000),75000)) -> 75000 | S96: =IF((O96-1100000)<0,0,IF((O96-1100000)<500000,0.19*(O96-1100000),95000)) -> 95000 | T96: =IF((O96-1600000)<0,0,IF((O96-1600000)<1600000,0.21*(O96-1600000),336000)) -> 301166.89 | V96: =P96+Q96+R96+S96+T96+U96 -> 525166.89 | W96: 12 | X96: =V96/W96 -> 43763.907 | Z96: =X96 -> 43763.907 | AA96: 34968.882 | AB96: =Z96-AA96 -> 8795.0248 | AC96: TASSNEEM IBRAHIM
B97: TOTAL | G97: 0
A98: 83 | G98: 0
A99: 84 | B99: LIBRARY & DOCUMENTATION | G99: 0 | AB99: Difference
A100: 85 | B100: DR MAIMUNA IZAH | C100: 1635720 | D100: 12 | E100: =C100*D100 -> 19628640 | G100: 1378291.2 | I100: =E100-F100-G100-H100 -> 18250349 | J100: 200000 | K100: 0.2 | L100: =I100*K100 -> 3650069.8 | M100: =J100+L100 -> 3850069.8 | N100: =F100+G100+H100+M100 -> 5228361 | O100: =E100-N100 -> 14400279 | P100: =IF(O100<300000,0.07*O100,21000) -> 21000 | Q100: =IF((O100-300000)<0,0,IF((O100-300000)<300000,0.11*(O100-300000),33000)) -> 33000 | R100: =IF((O100-600000)<0,0,IF((O100-600000)<500000,0.15*(O100-600000),75000)) -> 75000 | S100: =IF((O100-1100000)<0,0,IF((O100-1100000)<500000,0.19*(O100-1100000),95000)) -> 95000 | T100: =IF((O100-1600000)<0,0,IF((O100-1600000)<1600000,0.21*(O100-1600000),336000)) -> 336000 | U100: =24%*(O100-3200000) -> 2688067 | V100: =P100+Q100+R100+S100+T100+U100 -> 3248067 | W100: 12 | X100: =V100/W100 -> 270672.25 | Z100: =X100 -> 270672.25 | AA100: 180306.81 | AB100: =Z100-AA100 -> 90365.441 | AC100: DR MAIMUNA IZAH
A101: 86 | B101: CATHERINE E. IKOKOH | C101: 942373.17 | D101: 12 | E101: =C101*D101 -> 11308478 | F101: ='[5]JANUARY 2024'!$V$106*12 -> 12795.951 | G101: 731878.24 | I101: =E101-F101-G101-H101 -> 10563804 | J101: 200000 | K101: 0.2 | L101: =I101*K101 -> 2112760.8 | M101: =J101+L101 -> 2312760.8 | N101: =F101+G101+H101+M101 -> 3057435 | O101: =E101-N101 -> 8251043 | P101: =IF(O101<300000,0.07*O101,21000) -> 21000 | Q101: =IF((O101-300000)<0,0,IF((O101-300000)<300000,0.11*(O101-300000),33000)) -> 33000 | R101: =IF((O101-600000)<0,0,IF((O101-600000)<500000,0.15*(O101-600000),75000)) -> 75000 | S101: =IF((O101-1100000)<0,0,IF((O101-1100000)<500000,0.19*(O101-1100000),95000)) -> 95000 | T101: =IF((O101-1600000)<0,0,IF((O101-1600000)<1600000,0.21*(O101-1600000),336000)) -> 336000 | U101: =24%*(O101-3200000) -> 1212250.3 | V101: =P101+Q101+R101+S101+T101+U101 -> 1772250.3 | W101: 12 | X101: =V101/W101 -> 147687.53 | Z101: =X101 -> 147687.53 | AA101: 99703.216 | AB101: =Z101-AA101 -> 47984.311 | AC101: CATHERINE E. IKOKOH
A102: 87 | B102: ALIYU SANNI ABUBAKAR | C102: 603237.86 | D102: 12 | E102: =C102*D102 -> 7238854.3 | F102: ='[5]JANUARY 2024'!$V$107*12 -> 7901.79 | G102: 424132.72 | I102: =E102-F102-G102-H102 -> 6806819.8 | J102: 200000 | K102: 0.2 | L102: =I102*K102 -> 1361364 | M102: =J102+L102 -> 1561364 | N102: =F102+G102+H102+M102 -> 1993398.5 | O102: =E102-N102 -> 5245455.8 | P102: =IF(O102<300000,0.07*O102,21000) -> 21000 | Q102: =IF((O102-300000)<0,0,IF((O102-300000)<300000,0.11*(O102-300000),33000)) -> 33000 | R102: =IF((O102-600000)<0,0,IF((O102-600000)<500000,0.15*(O102-600000),75000)) -> 75000 | S102: =IF((O102-1100000)<0,0,IF((O102-1100000)<500000,0.19*(O102-1100000),95000)) -> 95000 | T102: =IF((O102-1600000)<0,0,IF((O102-1600000)<1600000,0.21*(O102-1600000),336000)) -> 336000 | U102: =24%*(O102-3200000) -> 490909.39 | V102: =P102+Q102+R102+S102+T102+U102 -> 1050909.4 | W102: 12 | X102: =V102/W102 -> 87575.783 | Z102: =X102 -> 87575.783 | AA102: 180180.38 | AB102: =Z102-AA102 -> -92604.596 | AC102: ALIYU SANNI ABUBAKAR
A103: 88 | B103: CHINAKO N. ASOGWA | C103: 601625.03 | D103: 12 | E103: =C103*D103 -> 7219500.4 | G103: 424132.72 | I103: =E103-F103-G103-H103 -> 6795367.7 | J103: 200000 | K103: 0.2 | L103: =I103*K103 -> 1359073.5 | M103: =J103+L103 -> 1559073.5 | N103: =F103+G103+H103+M103 -> 1983206.3 | O103: =E103-N103 -> 5236294.1 | P103: =IF(O103<300000,0.07*O103,21000) -> 21000 | Q103: =IF((O103-300000)<0,0,IF((O103-300000)<300000,0.11*(O103-300000),33000)) -> 33000 | R103: =IF((O103-600000)<0,0,IF((O103-600000)<500000,0.15*(O103-600000),75000)) -> 75000 | S103: =IF((O103-1100000)<0,0,IF((O103-1100000)<500000,0.19*(O103-1100000),95000)) -> 95000 | T103: =IF((O103-1600000)<0,0,IF((O103-1600000)<1600000,0.21*(O103-1600000),336000)) -> 336000 | U103: =0.24*(O103-3200000) -> 488710.59 | V103: =P103+Q103+R103+S103+T103+U103 -> 1048710.6 | W103: 12 | X103: =V103/W103 -> 87392.55 | Z103: =X103 -> 87392.55 | AA103: 99907.951 | AB103: =Z103-AA103 -> -12515.402 | AC103: CHINAKO N. ASOGWA
...

Sheet Upgrade in March
A1: NATIONAL INSTITUTE FOR LEGISLATIVE AND DEMOCRATIC STUDIES
A2: UPGRADE FROM GL 16(9) TO GL 17(7)
E3: ='[1]FEB 08'!E11/'[1]FEB 08'!M11 -> #REF!
B4: STAFF NAME | C4: DESIGNATION | D4: GRADE LEVEL | E4: BASIC SALARY | F4: ALLCE/ AREARS | G4: ALLOWANCE | H4: ALLOWANCE | I4: DUTY ALLCE | J4: GROSS SALARY | K4: AUCTION | L4: COOP CONTR/SPEC SAVINGS | M4: COOP. LOAN RECOVERY | N4: NHF DED. | O4: PAYE | P4: EMPLOYEE PENSIONS | Q4: TOTAL DEDUCTION | R4: FEBRUARY, 2024 | S4: MARCH, 2024
E5: N | G5: N | H5: N | I5: N | J5: N | K5: N | L5: N | M5: N | N5: N | O5: N | P5: N | Q5: N | R5: N | S5: N
B6: TRAINING & INT''L COOP
A7: 1 | B7: AKINSANMI ADEJOKE OLUKEMI | C7: Ag. DIR. TRAINING & IC | D7: 16(9) | E7: 762373.17 | H7: =80000+10000 -> 90000 | J7: =E7+F7+G7+H7+I7 -> 852373.17 | L7: =0 -> 0 | M7: 0 | N7: 1066.3293 | O7: 130407.53 | P7: 60989.853 | Q7: =O7+N7+M7+L7+K7+P7 -> 192463.71 | R7: 659909.46 | S7: =J7-Q7 -> 659909.46
A8: 1 | B8: AKINSANMI ADEJOKE OLUKEMI | C8: Ag. DIR. TRAINING & IC | D8: 17(7) | E8: ='[3]Annual & Monthly'!$H$44 -> 1352042.7 | H8: =100000 -> 100000 | I8: 0 | J8: =SUM(E8:I8) -> 1452042.7 | N8: 1066.3293 | O8: ='March New PAYE '!Z93 -> 236486.75 | P8: 114857.6 | Q8: =O8+N8+M8+L8+K8+P8 -> 352410.68 | R8: 659909.46 | S8: =J8-Q8 -> 1099632 | T8: =R8-S8 -> -439722.53
B9: DIFFERENCE | C9: =#REF!+#REF!+#REF!+#REF!+#REF!+#REF!+#REF!+#REF!+#REF!+#REF!+#REF! -> #REF! | E9: =E8-E7 -> 589669.5 | F9: =F8-F7 -> 0 | G9: =G8-G7 -> 0 | H9: =H8-H7 -> 10000 | I9: =I8-I7 -> 0 | J9: =J8-J7 -> 599669.5 | K9: =K8-K7 -> 0 | L9: =L8-L7 -> 0 | ... S9: =S8-S7 -> 439722.53

Sheet New NHF Deduction
A1: NATIONAL INSTITUTE FOR LEGISLATIVE AND DEMOCRATIC STUDIES
A2: COMPUTATION OF 2.5% EMPLOYEE NATIONAL HOUSING FUND (NHF)
B5: STAFF NAME | C5: DESIGNATION | D5: GRADE LEVEL | E5: ANNUAL SALARY | F5: MONTHLY SALARY | G5: EMPLOYEE NHF @ 2.25% | H5: OLD EMPLOYEE NHF | I5: DIFFERENCE
E6: N | F6: N | G6: N | H6: N | I6: N
A7: S/N | B7: DG'S OFFICE
A8: 1 | B8: PROF. ABUBAKAR O. SULAIMAN | C8: DIRECTOR GENERAL | D8: CONSOL | F8: =E8/12 -> 0 | G8: =E8*0.025 -> 0 | I8: =G8-H8 -> 0
A9: 2 | B9: RAHEEM USMAN AYIGORO | C9: SA-INFRASTRUCTURE | D9: 16 (9) | F9: =E9/12 -> 0 | G9: =E9*0.025 -> 0 | I9: =G9-H9 -> 0
A10: 3 | B10: MARIAM MOHAMMED BELLO | C10: SA- SPECIAL DUTIES | D10: 16 (9) | F10: =E10/12 -> 0 | G10: =E10*0.025 -> 0 | I10: =G10-H10 -> 0
A11: 4 | B11: DR IKEME ARTHUR J.O | C11: DEPUTY DIRECTOR, M&E | D11: 16 (9) | E11: ='[6]NASS New Structure'!$J$20 -> 4940831 | F11: =E11/12 -> 411735.92 | G11: =F11*0.025 -> 10293.398 | H11: 1066.3293 | I11: =G11-H11 -> 9227.0687
A12: 5 | B12: MOSHOOD M. OLALERE | C12: PPS TO DG | D12: 16 (9) | E12: ='[6]NASS New Structure'!$J$20 -> 4940831 | F12: =E12/12 -> 411735.92 | G12: =F12*0.025 -> 10293.398 | H12: 1066.3293 | I12: =G12-H12 -> 9227.0687
A13: 6 | B13: REKIYA IBRAHIM ATTAH | C13: DEPUTY DIRECTOR TRAINING | D13: 16 (9) | F13: =E13/12 -> 0 | G13: =F13*0.025 -> 0 | I13: =G13-H13 -> 0
A14: 7 | B14: ANDRAWUS MUSA | C14: ASST. DIRECTOR, STORES | D14: 15(9) | E14: ='[6]NASS New Structure'!$J$19 -> 4022509 | F14: =E14/12 -> 335209.08 | G14: =F14*0.025 -> 8380.2271 | H14: 837.6875 | I14: =G14-H14 -> 7542.5396
A15: 8 | B15: DR FRANCIS NDUM OJIE | C15: AD, TRAINING & IC./SA TO DG | D15: 15(7) | E15: ='[6]NASS New Structure'!$H$19 -> 3772623 | F15: =E15/12 -> 314385.25 | G15: =F15*0.025 -> 7859.6313 | H15: 775.496 | I15: =G15-H15 -> 7084.1353
A16: 9 | B16: ALI ABDULLAHI | C16: CHIEF ICT OFFICER | D16: 14(11) | F16: =E16/12 -> 0 | G16: =E16*0.025 -> 0 | I16: =G16-H16 -> 0
A17: 10 | B17: EMILY EKHIDE | C17: RESEARCH FELLOW 1 | D17: 14(10) | F17: =E17/12 -> 0 | G17: =E17*0.025 -> 0 | I17: =G17-H17 -> 0
A18: 11 | B18: DORIS DAKDA AARON | C18: RESEARCH FELLOW I | D18: 14(8) | F18: =E18/12 -> 0 | G18: =E18*0.025 -> 0 | I18: =G18-H18 -> 0
A19: 12 | B19: ABDULSALAM S. MUSTAPHA | C19: ASST. MANAGER ICT | D19: 13(11) | F19: =E19/12 -> 0 | G19: =E19*0.025 -> 0 | I19: =G19-H19 -> 0
A20: 13 | B20: PERCY TERFA GBAHABO | C20: HEAD, NILDS LIAISON OFFICE | D20: 13(10) | F20: =E20/12 -> 0 | G20: =E20*0.025 -> 0 | I20: =G20-H20 -> 0
A21: 14 | B21: HASSANA AHMED IBRAHIM | C21: PA- TRAINING | D21: 13 (9) | E21: ='[6]NASS New Structure'!$J$17 -> 2691445 | F21: =E21/12 -> 224287.08 | G21: =F21*0.025 -> 5607.1771 | H21: 618.5315 | I21: =G21-H21 -> 4988.6456
A22: 15 | B22: ADUGBA RICHARD TERSEER | C22: PRINCIPAL INFO. OFFICER | D22: 12(9) | F22: =E22/12 -> 0 | G22: =E22*0.025 -> 0 | I22: =G22-H22 -> 0
A23: 16 | B23: LUCKY AGWOM | C23: PA-TECHNICAL | D23: 12(7) | F23: =E23/12 -> 0 | G23: =E23*0.025 -> 0 | I23: =G23-H23 -> 0
A24: 17 | B24: IDRIS IBRAHIM | C24: PRINCIPAL RESEARCH OFFICER | D24: 12(7) | F24: =E24/12 -> 0 | G24: =E24*0.025 -> 0 | I24: =G24-H24 -> 0
A25: 18 | B25: FARUQ ATOFARATI | C25: PA (SPECIAL DUTIES) TO DG | D25: 10(7) | F25: =E25/12 -> 0 | G25: =E25*0.025 -> 0 | I25: =G25-H25 -> 0
A26: 19 | B26: ELIZABETH OGECHUKWU ONYEAKU | C26: ICT OFFICER | D26: 9(9) | F26: =E26/12 -> 0 | G26: =E26*0.025 -> 0 | I26: =G26-H26 -> 0
A27: 20 | B27: VICTOR ASUKWO | C27: ICT OFFICER | D27: 9(9) | F27: =E27/12 -> 0 | G27: =E27*0.025 -> 0 | I27: =G27-H27 -> 0
A28: 21 | B28: NNANDI LIVINUS ATURE | C28: RESEARCH ASSISTANT | D28: 9(9) | F28: =E28/12 -> 0 | G28: =E28*0.025 -> 0 | I28: =G28-H28 -> 0
A29: 22 | B29: ABDULRAHMAN A SULAIMAN | C29: STORE OFFICER | D29: 9(8) | F29: =E29/12 -> 0 | G29: =E29*0.025 -> 0 | I29: =G29-H29 -> 0
A30: 23 | B30: DARE SHEU MAGBON | C30: ADMINISTRATION OFFICER | D30: 9(7) | F30: =E30/12 -> 0 | G30: =E30*0.025 -> 0 | I30: =G30-H30 -> 0
A31: 24 | B31: ABUBAKAR SULAIMAN SODEEQ | C31: ADMINISTRATION OFFICER | D31: 9(7) | F31: =E31/12 -> 0 | G31: =E31*0.025 -> 0 | I31: =G31-H31 -> 0
A32: 25 | B32: JIMOH ADEBAYO ZAKA | C32: ASST. OFFICER/COMM | D32: 9(9) | F32: =E32/12 -> 0 | G32: =E32*0.025 -> 0 | I32: =G32-H32 -> 0
A33: 26 | B33: MOHAMMED BELLO | C33: PROTOCOL ASSISTANT | D33: 8(9) | F33: =E33/12 -> 0 | G33: =E33*0.025 -> 0 | I33: =G33-H33 -> 0
A34: 27 | B34: HARUNA JIBRIL AMEH | C34: ASST. ADMIN. OFFICER | D34: 8(8) | F34: =E34/12 -> 0 | G34: =E34*0.025 -> 0 | I34: =G34-H34 -> 0
B35: TOTAL | C35: 27 | E35: =SUM(E8:E34) -> 20368239 | F35: =SUM(F8:F34) -> 1697353.2 | G35: =SUM(G8:G34) -> 42433.831 | H35: =SUM(H8:H34) -> 4364.3735 | I35: =SUM(I8:I34) -> 38069.458
B37: INTERNAL AUDIT
A38: 1 | B38: OSANAIYE DAVID AKINYEMI | C38: DIRECTOR INTERNAL AUDIT | D38: 17(9) | G38: =E38*0.025 -> 0 | H38: =F38*0.025 -> 0 | I38: =G38*0.025 -> 0
A39: 2 | B39: JAMILA ABDUL | C39: SENIOR INTERNAL AUDITOR | D39: 10(7) | G39: =E39*0.025 -> 0 | H39: =F39*0.025 -> 0 | I39: =G39*0.025 -> 0
A40: 3 | B40: IJEOMA EWELUKWA | C40: AUDIT OFFICER | D40: 10(8) | G40: =E40*0.025 -> 0 | H40: =F40*0.025 -> 0 | I40: =G40*0.025 -> 0
C41: 3 | E41: =SUM(E38:E40) -> 0 | G41: =SUM(G38:G40) -> 0 | H41: =SUM(H38:H40) -> 0 | I41: =SUM(I38:I40) -> 0
B43: LEG. SUPPORT SEVICES
A44: 1 | B44: PROF. EDOBA BRIGHT OMOREGBE | C44: AG. DLSS | D44: 17(9) | G44: =E44*0.025 -> 0 | I44: =G44*0.025 -> 0
A45: 2 | B45: DR CLINTON JAJA | C45: SENIOR RESEARCH FELLOW | D45: 15(9) | G45: =E45*0.025 -> 0 | I45: =G45*0.025 -> 0
A46: 3 | B46: BETHEL UZOMA IHUGBA | C46: DEPUTY DIRECTOR, LEGAL RESEARCH | D46: 16(8) | G46: =E46*0.025 -> 0 | I46: =G46*0.025 -> 0
A47: 4 | B47: OGUCHE SAMUEL | C47: SNR RESEARCH FELLOW | D47: 15(9) | G47: =E47*0.025 -> 0 | I47: =G47*0.025 -> 0
A48: 5 | B48: IBRAHIM USMAN | C48: SNR RESEARCH FELLOW | D48: 15(9) | E48: ='[6]NASS New Structure'!$J$19 -> 4022509 | F48: =E48/12 -> 335209.08 | G48: =F48*0.025 -> 8380.2271 | H48: 837.6875 | I48: =G48-H48 -> 7542.5396
A49: 6 | B49: DR MOHAMMED O. AMALI | C49: SNR RESEARCH FELLOW | D49: 15(7) | G49: =E49*0.025 -> 0 | I49: =G49*0.025 -> 0
A50: 7 | B50: YAHAYA SHAMSU | C50: RESEARCH FELLOW 1 | D50: 14(10) | G50: =E50*0.025 -> 0 | H50: 0 | I50: =G50*0.025 -> 0
A51: 8 | B51: BILKIS S. LAWAL-GAMBARI | C51: RESEARCH OFFICER | D51: 10(8) | G51: =E51*0.025 -> 0 | I51: =G51*0.025 -> 0
A52: 9 | B52: ZAINAB AKINDE | C52: RESEARCH OFFICER | D52: 9(8) | G52: =E52*0.025 -> 0 | I52: =G52*0.025 -> 0
A53: 10 | B53: ABDULLAHI AHMAD USMAN | C53: RESEARCH OFFICER | D53: 9(8) | G53: =E53*0.025 -> 0 | I53: =G53*0.025 -> 0
A54: 11 | B54: GUNAT NANSAK MARK | C54: RESEARCH OFFICER | D54: 9(8) | G54: =E54*0.025 -> 0 | I54: =G54*0.025 -> 0
B55: TOTAL | C55: 11 | E55: =SUM(E44:E54) -> 4022509 | F55: =SUM(F44:F54) -> 335209.08 | G55: =SUM(G44:G54) -> 8380.2271 | H55: =SUM(H44:H54) -> 837.6875 | I55: =SUM(I44:I54) -> 7542.5396
B57: LEGAL SERVICES
A58: 1 | B58: DR SHUIBU DANWANKA | C58: DIRECTOR LEGAL SERVICES | D58: 17(9) | G58: =E58*0.025 -> 0 | H58: =F58*0.025 -> 0 | I58: =G58*0.025 -> 0
A59: 2 | B59: ABDULSALAM BAKO | C59: MANAGER, LEGAL SERVICES | D59: 15 (9) | G59: =E59*0.025 -> 0 | H59: =F59*0.025 -> 0 | I59: =G59*0.025 -> 0
B60: TOTAL | C60: 2 | E60: =SUM(E58:E59) -> 0 | G60: =SUM(G58:G59) -> 0 | H60: =SUM(H58:H59) -> 0 | I60: =SUM(I58:I59) -> 0
B62: DEMOCRACY & GOVERNANCE
A63: 1 | B63: DR. ADEWALE ADEREMI | C63: DIRECTOR, DEMOCRATIC STUDIES | D63: 17(9) | G63: =E63*0.025 -> 0 | H63: =F63*0.025 -> 0 | I63: =G63*0.025 -> 0
A64: 2 | B64: NDANUSA MOHAMMED MANZUMA | C64: SNR RESEARCH FELLOW | D64: 15(8) | G64: =E64*0.025 -> 0 | H64: =F64*0.025 -> 0 | I64: =G64*0.025 -> 0
A65: 3 | B65: EJALONIBU GANIYU LAYI | C65: RESEARCH FELLOW 1 | D65: 14(8) | G65: =E65*0.025 -> 0 | H65: =F65*0.025 -> 0 | I65: =G65*0.025 -> 0
A66: 4 | B66: LOHNA BONKAT JONATHAN | C66: RESEARCH FELLOW 11 | D66: 13(10) | G66: =E66*0.025 -> 0 | H66: =F66*0.025 -> 0 | I66: =G66*0.025 -> 0
A67: 5 | B67: YUNUSA ABDULLAHI | C67: RESEARCH FELLOW 1 | D67: 14(11) | G67: =E67*0.025 -> 0 | H67: =F67*0.025 -> 0 | I67: =G67*0.025 -> 0
A68: 7 | B68: UDEFUNA NNADOZIE PATRICK | C68: RESEARCH OFFICER | D68: 12(8) | G68: =E68*0.025 -> 0 | H68: =F68*0.025 -> 0 | I68: =G68*0.025 -> 0
A69: 8 | B69: SHAFIU YAHYA MIKAIL | C69: PRINCIPAL RESEARCH OFFICER | D69: 12(8) | G69: =E69*0.025 -> 0 | H69: =F69*0.025 -> 0 | I69: =G69*0.025 -> 0
A70: 9 | B70: HASSAN YERIMA | C70: PRINCIPAL RESEARCH OFFICER | D70: 12(8) | G70: =E70*0.025 -> 0 | H70: =F70*0.025 -> 0 | I70: =G70*0.025 -> 0
A71: 10 | B71: HAUWA PATE SADIQ | C71: PRINCIPAL PROGRAMME OFFICER | D71: 12(9) | G71: =E71*0.025 -> 0 | H71: =F71*0.025 -> 0 | I71: =G71*0.025 -> 0
A72: 11 | B72: KOLAPO Q. ABAYOMI | C72: RESEARCH OFFICER | D72: 10(8) | G72: =E72*0.025 -> 0 | H72: =F72*0.025 -> 0 | I72: =G72*0.025 -> 0
B73: TOTAL | C73: 12 | E73: =SUM(E63:E72) -> 0 | G73: =SUM(G63:G72) -> 0 | H73: =SUM(H63:H72) -> 0 | I73: =SUM(I63:I72) -> 0
B75: DEPARTMENT OF STUDIES
A76: 1 | B76: DR ASIMIYU G. ABIOLA | C76: DIRECTOR POST GRADUATE | D76: 17(9) | G76: =E76*0.025 -> 0 | H76: =F76*0.025 -> 0 | I76: =G76*0.025 -> 0
A77: 2 | B77: USMAN WALI | C77: SENIOR RESEARCH FELLOW | D77: 15 (8) | G77: =E77*0.025 -> 0 | H77: =F77*0.025 -> 0 | I77: =G77*0.025 -> 0
A78: 3 | B78: AYOBOLU OLAJIDE OLUFUNSHO | C78: ASST.DIR., INFORMATION | D78: 15 (9) | G78: =E78*0.025 -> 0 | H78: =F78*0.025 -> 0 | I78: =G78*0.025 -> 0
A79: 4 | B79: ANTHONY EDET | C79: CHIEF PROGRAMMES OFFICER | D79: 14(9) | E79: ='[6]NASS New Structure'!$J$18 -> 2954075 | F79: =E79/12 -> 246172.92 | G79: =F79*0.025 -> 6154.3229 | H79: 668.31625 | I79: =G79-H79 -> 5486.0067
A80: 5 | B80: IGWE STACY | C80: PROGRAMME OFFICER | D80: 10(9) | G80: =E80*0.025 -> 0 | H80: =F80*0.025 -> 0 | I80: =G80*0.025 -> 0
A81: 6 | B81: OLANIYAN TAIWO ABINBOLA | C81: PROGRAMME OFFICER | D81: 9(8) | G81: =E81*0.025 -> 0 | H81: =F81*0.025 -> 0 | I81: =G81*0.025 -> 0
A82: 7 | B82: AMINAT JUMOKE SULAIMON | C82: AST. PROGRAMME OFFICER | D82: 8(8) | G82: =E82*0.025 -> 0 | H82: =F82*0.025 -> 0 | I82: =G82*0.025 -> 0
B83: TOTAL | C83: 7 | E83: =SUM(E76:E82) -> 2954075 | F83: =SUM(F76:F82) -> 246172.92 | G83: =SUM(G76:G82) -> 6154.3229 | H83: =SUM(H76:H82) -> 668.31625 | I83: =SUM(I76:I82) -> 5486.0067
B85: ECON. DEV. & SOC. RESEARCH
A86: 1 | B86: TERFA WILLIAMS ABRAHAM | C86: SNR RESEARCH FELLOW | D86: 15(9) | G86: =E86*0.025 -> 0 | I86: =G86*0.025 -> 0
A87: 2 | B87: DR AUGUSTINE C. OSIGWE | C87: SNR RESEARCH FELLOW | D87: 15(9) | E87: ='[6]NASS New Structure'!$J$19 -> 4022509 | F87: =E87/12 -> 335209.08 | G87: =F87*0.025 -> 8380.2271 | H87: 837.6875 | I87: =G87-H87 -> 7542.5396
A88: 3 | B88: OMOJU OLUWASOLA EMMANUEL | C88: SNR RESEARCH FELLOW | D88: 15(7) | G88: =E88*0.025 -> 0 | I88: =G88*0.025 -> 0
A89: 4 | B89: IBE EZECHI CYRIACUS | C89: RESEARCH FELLOW II | D89: 13(11) | G89: =E89*0.025 -> 0 | I89: =G89*0.025 -> 0
A90: 5 | B90: OSIKHEN LEO IGBANOI | C90: RESEARCH FELLOW 11 | D90: 13(10) | G90: =E90*0.025 -> 0 | I90: =G90*0.025 -> 0
A91: 6 | B91: OKUNGBOWA OSARETIN GODSPOWER | C91: RESEARCH FELLOW 1 | D91: 14(7) | G91: =E91*0.025 -> 0 | I91: =G91*0.025 -> 0
A92: 7 | B92: YUSUF IBRAHIM | C92: PRINCIPAL RESEARCH OFFICER | D92: 12(8) | G92: =E92*0.025 -> 0 | I92: =G92*0.025 -> 0
A93: 8 | B93: MUSTAPHA RAFIU AYOBANJI | C93: RESEARCH FELLOW 11 | D93: 13(7) | E93: ='[6]NASS New Structure'!$H$17 -> 2524677 | F93: =E93/12 -> 210389.75 | G93: =F93*0.025 -> 5259.7438 | H93: 576.87475 | I93: =G93-H93 -> 4682.869
A94: 9 | B94: MARYAM MUSA SADA | C94: ASSIT. RESEARCH OFFICER | D94: 10(8) | G94: =E94*0.025 -> 0 | I94: =G94*0.025 -> 0
A95: 10 | B95: CHARITY EZENWAJIOBI | C95: REASEARCH. ASST. | D95: 8(9) | G95: =E95*0.025 -> 0 | H95: 0 | I95: =G95*0.025 -> 0
B96: TOTAL | C96: 11 | E96: =SUM(E86:E95) -> 6547186 | F96: =SUM(F86:F95) -> 545598.83 | G96: =SUM(G86:G95) -> 13639.971 | H96: =SUM(H86:H95) -> 1414.5622 | I96: =SUM(I86:I95) -> 12225.409
B98: TRAINING & INT''L COOP
A99: 1 | B99: AKINSANMI ADEJOKE OLUKEMI | C99: Ag. DIR. TRAINING & IC | D99: 16(9) | E99: ='[6]NASS New Structure'!$H$21 -> 8762388 | F99: =E99/12 -> 730199 | G99: =F99*0.025 -> 18254.975 | H99: =H12 -> 1066.3293 | I99: =G99-H99 -> 17188.646
A100: 2 | B100: MOHAMMED R. ADAMU | C100: CHIEF TRAINING OFFICER | D100: 14(9) | G100: =E100*0.025 -> 0 | H100: =F100*0.025 -> 0 | I100: =G100*0.025 -> 0
A101: 3 | B101: OKECHUKWU UCHENNA HULDA | C101: PRINCIPALTRAINING OFFICER | D101: 12(9) | G101: =E101*0.025 -> 0 | H101: =F101*0.025 -> 0 | I101: =G101*0.025 -> 0
A102: 4 | B102: TASSNEEM IBRAHIM | C102: SENIOR PROGRAMME OFFICER | D102: 10(8) | G102: =E102*0.025 -> 0 | H102: =F102*0.025 -> 0 | I102: =G102*0.025 -> 0
B103: TOTAL | C103: 4 | E103: =SUM(E99:E102) -> 8762388 | F103: =SUM(F99:F102) -> 730199 | G103: =SUM(G99:G102) -> 18254.975 | H103: =SUM(H99:H102) -> 1066.3293 | I103: =SUM(I99:I102) -> 17188.646
B105: LIBRARY & DOCUMENTATION
A106: 1 | B106: DR MAIMUNA IZAH | C106: INSITUTE LIBRARIAN | D106: 17(9) | G106: =E106*0.08 -> 0 | H106: =F106*0.08 -> 0 | I106: =G106*0.08 -> 0
A107: 2 | B107: CATHERINE E. IKOKOH | C107: SNR RESEARCH FELLOW DOCU | D107: 16(9) | E107: ='[6]NASS New Structure'!$J$20 -> 4940831 | F107: =E107/12 -> 411735.92 | G107: =F107*0.025 -> 10293.398 | H107: 1066.3293 | I107: =G107-H107 -> 9227.0687
A108: 3 | B108: ALIYU SANNI ABUBAKAR | C108: RESEARCH FELLOW 11 DATA & DOCU | D108: 13(11) | E108: ='[6]NASS New Structure'!$L$17 -> 2858213 | F108: =E108/12 -> 238184.42 | G108: =F108*0.025 -> 5954.6104 | H108: 658.4825 | I108: =G108-H108 -> 5296.1279
A109: 4 | B109: CHINAKO N. ASOGWA | C109: RESEARCH FELLOW 11 DATA & DOCU | D109: 13(11) | G109: =E109*0.08 -> 0 | H109: =F109*0.08 -> 0 | I109: =G109*0.08 -> 0
A110: 5 | B110: AMOS ABA | C110: LIBRARY ASSISTANT | D110: 8(12) | G110: =E110*0.08 -> 0 | H110: =F110*0.08 -> 0 | I110: =G110*0.08 -> 0
...

Sheet Regularisation
D1: Gross | E1: PAYE
A2: HARUNA JIBRIL AMEH | B2: ASST. ADMIN. OFFICER | C2: 8(7) | D2: ='[5]JANUARY 2024'!$R$33 -> 173329.05 | E2: ='[5]JANUARY 2024'!$W$33 -> 16512.682
A3: HARUNA JIBRIL AMEH | B3: ASST. ADMIN. OFFICER | C3: 8(8) | D3: ='[5]JANUARY 2024'!$R$38 -> 176816.1 | E3: ='[5]JANUARY 2024'!$W$38 -> 17042.714
A4: Difference | D4: =D3-D2 -> 3487.0505 | E4: =E3-E2 -> 530.03168 | F4: =D4-E4 -> 2957.0188

Sheet Sallah Welfare, April 2024
A1: NATIONAL INSTITUTE FOR LEGISLATIVE AND DEMOCRATIC STUDIES
A2: STAFF SALLAH WELFARE APRIL 2024
E3: ='[1]FEB 08'!E11/'[1]FEB 08'!M11 -> #REF!
B4: STAFF NAME | C4: DESIGNATION | D4: GRADE LEVEL | E4: AMOUNT
E5: N
A6: S/N | B6: DG'S OFFICE
A7: 1 | B7: PROF. ABUBAKAR O. SULAIMAN | C7: DIRECTOR GENERAL | D7: CONSOL | E7: 540000
A8: 2 | B8: RAHEEM USMAN AYIGORO | C8: SA-INFRASTRUCTURE | D8: 16 (9) | E8: 180000
A9: 3 | B9: MARIAM MOHAMMED BELLO | C9: SA- SPECIAL DUTIES | D9: 16 (9) | E9: 180000
A10: 4 | B10: DR IKEME ARTHUR J.O | C10: DEPUTY DIRECTOR, M&E | D10: 16 (9) | E10: 180000
A11: 5 | B11: MOSHOOD M. OLALERE | C11: DEPUTY DIR. GENERAL SERVICE | D11: 16 (9) | E11: 180000
A12: 6 | B12: REKIYA IBRAHIM ATTAH | C12: DEPUTY DIRECTOR TRAINING | D12: 16 (9) | E12: 180000
A13: 7 | B13: ANDRAWUS MUSA | C13: ASST. DIRECTOR, STORES | D13: 15(9) | E13: 126000
A14: 8 | B14: DR FRANCIS NDUM OJIE | C14: AD, TRAINING & IC./SA TO DG | D14: 15(7) | E14: 126000
A15: 9 | B15: ALI ABDULLAHI | C15: CHIEF ICT OFFICER | D15: 14(11) | E15: 90000
A16: 10 | B16: EMILY EKHIDE | C16: RESEARCH FELLOW 1 | D16: 14(10) | E16: 90000
A17: 11 | B17: DORIS DAKDA AARON | C17: RESEARCH FELLOW I | D17: 14(8) | E17: 90000
A18: 12 | B18: ABDULSALAM S. MUSTAPHA | C18: ASST. MANAGER ICT | D18: 13(11) | E18: 90000
... A33: 27 | B33: HARUNA JIBRIL AMEH | C33: ASST. ADMIN. OFFICER | D33: 8(8) | E33: 54000
B34: TOTAL | C34: 27 | E34: =SUM(E7:E33) -> 2990000
B36: INTERNAL AUDIT
A37: 1 | B37: OSANAIYE DAVID AKINYEMI | C37: DIRECTOR INTERNAL AUDIT | D37: 17(9) | E37: 270000
A38: 2 | B38: JAMILA ABDUL | C38: AUDITOR II | D38: 10(7) | E38: 68000
A39: 3 | B39: IJEOMA EWELUKWA | C39: AUDIT OFFICER | D39: 10(8) | E39: 68000
C40: 3 | E40: =SUM(E37:E39) -> 406000
B42: LEG. SUPPORT SEVICES
A43: 1 | B43: PROF. EDOBA BRIGHT OMOREGBE | C43: AG. DLSS | D43: 17(9) | E43: 270000
A44: 2 | B44: DR CLINTON JAJA | C44: SENIOR RESEARCH FELLOW | D44: 15(9) | E44: 126000
A45: 3 | B45: BETHEL UZOMA IHUGBA | C45: DEPUTY DIRECTOR, LEGAL RESEARCH | D45: 16(8) | E45: 180000
A46: 4 | B46: OGUCHE SAMUEL | C46: SNR RESEARCH FELLOW | D46: 15(9) | E46: 126000
A47: 5 | B47: IBRAHIM USMAN | C47: SNR RESEARCH FELLOW | D47: 15(9) | E47: 126000
A48: 6 | B48: DR MOHAMMED O. AMALI | C48: SNR RESEARCH FELLOW | D48: 15(7) | E48: 126000
A49: 7 | B49: YAHAYA SHAMSU | C49: RESEARCH FELLOW 1 | D49: 14(10) | E49: 90000
A50: 8 | B50: BILKIS S. LAWAL-GAMBARI | C50: RESEARCH OFFICER | D50: 10(8) | E50: 68000
A51: 9 | B51: ZAINAB AKINDE | C51: RESEARCH OFFICER | D51: 9(8) | E51: 54000
A52: 10 | B52: ABDULLAHI AHMAD USMAN | C52: RESEARCH OFFICER | D52: 9(8) | E52: 54000
A53: 11 | B53: GUNAT NANSAK MARK | C53: RESEARCH OFFICER | D53: 9(8) | E53: 54000
B54: TOTAL | C54: 11 | E54: =SUM(E43:E53) -> 1274000
B56: LEGAL SERVICES
A57: 1 | B57: DR SHUIBU DANWANKA | C57: DIRECTOR LEGAL SERVICES | D57: 17(9) | E57: 270000
A58: 2 | B58: ABDULSALAM BAKO | C58: MANAGER, LEGAL SERVICES | D58: 15 (9) | E58: 126000
B59: TOTAL | C59: 2 | E59: =SUM(E57:E58) -> 396000
B61: DEMOCRACY & GOVERNANCE
A62: 1 | B62: DR. ADEWALE ADEREMI | C62: DIRECTOR, DEMOCRATIC STUDIES | D62: 17(9) | E62: 270000
A63: 2 | B63: NDANUSA MOHAMMED MANZUMA | C63: SNR RESEARCH FELLOW | D63: 15(8) | E63: 126000
A64: 3 | B64: EJALONIBU GANIYU LAYI | C64: RESEARCH FELLOW 1 | D64: 14(8) | E64: 90000
A65: 4 | B65: LOHNA BONKAT JONATHAN | C65: RESEARCH FELLOW 11 | D65: 13(10) | E65: 90000
A66: 5 | B66: YUNUSA ABDULLAHI | C66: RESEARCH FELLOW 1 | D66: 14(11) | E66: 90000
A67: 7 | B67: UDEFUNA NNADOZIE PATRICK | C67: RESEARCH OFFICER | D67: 12(8) | E67: 68000
A68: 8 | B68: SHAFIU YAHYA MIKAIL | C68: PRINCIPAL RESEARCH OFFICER | D68: 12(8) | E68: 68000
A69: 9 | B69: HASSAN YERIMA | C69: PRINCIPAL RESEARCH OFFICER | D69: 12(8) | E69: 68000
A70: 10 | B70: HAUWA PATE SADIQ | C70: PRINCIPAL PROGRAMME OFFICER | D70: 12(9) | E70: 68000
A71: 11 | B71: KOLAPO Q. ABAYOMI | C71: RESEARCH OFFICER | D71: 10(8) | E71: 68000
B72: TOTAL | C72: 11 | E72: =SUM(E62:E71) -> 1006000
B74: DEPARTMENT OF STUDIES
A75: 1 | B75: DR ASIMIYU G. ABIOLA | C75: DIRECTOR POST GRADUATE | D75: 17(9) | E75: 270000
A76: 2 | B76: USMAN WALI | C76: SENIOR RESEARCH FELLOW | D76: 15 (8) | E76: 126000
A77: 3 | B77: AYOBOLU OLAJIDE OLUFUNSHO | C77: ASST.DIR., INFORMATION | D77: 15 (9) | E77: 126000
A78: 4 | B78: ANTHONY EDET | C78: CHIEF PROGRAMMES OFFICER | D78: 14(9) | E78: 90000
A79: 5 | B79: IGWE STACY | C79: PROGRAMME OFFICER | D79: 10(9) | E79: 68000
A80: 6 | B80: OLANIYAN TAIWO ABINBOLA | C80: PROGRAMME OFFICER | D80: 9(8) | E80: 54000
A81: 7 | B81: AMINAT JUMOKE SULAIMON | C81: AST. PROGRAMME OFFICER | D81: 8(8) | E81: 54000
B82: TOTAL | C82: 7 | E82: =SUM(E75:E81) -> 788000
B84: ECON. DEV. & SOC. RESEARCH
A85: 1 | B85: TERFA WILLIAMS ABRAHAM | C85: SNR RESEARCH FELLOW | D85: 15(9) | E85: 126000
A86: 2 | B86: DR AUGUSTINE C. OSIGWE | C86: SNR RESEARCH FELLOW | D86: 15(9) | E86: 126000
A87: 3 | B87: OMOJU OLUWASOLA EMMANUEL | C87: SNR RESEARCH FELLOW | D87: 15(7) | E87: 126000
A88: 4 | B88: IBE EZECHI CYRIACUS | C88: RESEARCH FELLOW II | D88: 13(11) | E88: 90000
A89: 5 | B89: OSIKHEN LEO IGBANOI | C89: RESEARCH FELLOW 11 | D89: 13(10) | E89: 90000
A90: 6 | B90: OKUNGBOWA OSARETIN GODSPOWER | C90: RESEARCH FELLOW 1 | D90: 14(7) | E90: 90000
A91: 7 | B91: YUSUF IBRAHIM | C91: PRINCIPAL RESEARCH OFFICER | D91: 12(8) | E91: 68000
A92: 8 | B92: MUSTAPHA RAFIU AYOBANJI | C92: RESEARCH FELLOW 11 | D92: 13(7) | E92: 90000
A93: 9 | B93: MARYAM MUSA SADA | C93: ASSIT. RESEARCH OFFICER | D93: 10(8) | E93: 66000
A94: 10 | B94: CHARITY EZENWAJIOBI | C94: REASEARCH. ASST. | D94: 8(9) | E94: 54000
B95: TOTAL | C95: 10 | E95: =SUM(E85:E94) -> 926000
B97: TRAINING & INT''L COOP
A98: 1 | B98: AKINSANMI ADEJOKE OLUKEMI | C98: Ag. DIR. TRAINING & IC | D98: 17(7) | E98: 270000
A99: 2 | B99: MOHAMMED R. ADAMU | C99: CHIEF TRAINING OFFICER | D99: 14(9) | E99: 90000
A100: 3 | B100: OKECHUKWU UCHENNA HULDA | C100: PRINCIPALTRAINING OFFICER | D100: 12(9) | E100: 68000
A101: 4 | B101: TASSNEEM IBRAHIM | C101: SENIOR PROGRAMME OFFICER | D101: 10(8) | E101: 68000
B102: TOTAL | C102: 4 | E102: =SUM(E98:E101) -> 496000
B104: LIBRARY & DOCUMENTATION
A105: 1 | B105: DR MAIMUNA IZAH | C105: INSITUTE LIBRARIAN | D105: 17(9) | E105: 270000
A106: 2 | B106: CATHERINE E. IKOKOH | C106: SNR RESEARCH FELLOW DOCU | D106: 16(9) | E106: 180000
A107: 3 | B107: ALIYU SANNI ABUBAKAR | C107: RESEARCH FELLOW 11 DATA & DOCU | D107: 13(11) | E107: 90000
A108: 4 | B108: CHINAKO N. ASOGWA | C108: RESEARCH FELLOW 11 DATA & DOCU | D108: 13(11) | E108: 90000
A109: 5 | B109: AMOS ABA | C109: LIBRARY ASSISTANT | D109: 8(12) | E109: 54000
A110: 6 | B110: TITILAYO DANIEL MARVELLOUS | C110: LIBRARY ASSISTANT | D110: 8(11) | E110: 54000
A111: 7 | B111: ENENCHE JEREMIAH AGADA | C111: LIBRARY ASSISTANT | D111: 8(9) | E111: 54000
B112: TOTAL | C112: 7 | E112: =SUM(E105:E111) -> 792000
B114: LEG, CTRE FOR SEC. ANALYSIS
A115: 1 | B115: NGARA CHRISTOPHER OCHANJA | C115: SNR RESEARCH FELLOW | D115: 15(8) | E115: 126000
A116: 2 | B116: EGUATU U. ONYEJELEM | C116: PRINCIPAL M&E OFFICER | D116: 12(9) | E116: 68000
A117: 3 | B117: CHRISTIAN MADUABUCHI ODO | C117: PRINCIPAL ICT OFFICER | D117: 12(10) | E117: 68000
B118: TOTAL | C118: 3 | E118: =SUM(E115:E117) -> 262000
B120: FINANCE & ACCOUNTS
A121: 1 | B121: IBRAHIM M. MSHELIA | C121: DIR. FINANCE & ACCOUNTS | D121: 17(9) | E121: 270000
A122: 2 | B122: RAHILA NURUDEEN HABU | C122: DEP. DIRECTOR, ACCOUNTS | D122: 16(8) | E122: 180000
A123: 3 | B123: TONDO IORWUESE EDWARD | C123: ASST. DIRECTOR, ACCOUNTS | D123: 15(9) | E123: 126000
A124: 4 | B124: ARAOYE GANIYAT TITILOLA | C124: ASST. DIRECTOR, ACCOUNTS | D124: 15(7) | E124: 126000
...

Sheet Sheet4

Sheet January Arrears
A1: NATIONAL INSTITUTE FOR LEGISLATIVE AND DEMOCRATIC STUDIES
A2: COMPUTATION OF JANUARY 2024 ARREARS
E3: ='[1]FEB 08'!E11/'[1]FEB 08'!M11 -> #REF!
B4: STAFF NAME | C4: DESIGNATION | D4: GRADE LEVEL | E4: SALARY | F4: AREARS | G4: RESEARCH ALLOW. | H4: HARDSHIP ALLOW. | I4: DUTY ALLCE | J4: NEW GROSS SALARY | K4: OLD GROSS SALARY | L4: VARIATION IN GROSS SALARY | M4: NEW PAYE TAX | N4: OLD PAYE TAX | O4: VARIATION IN PAYE TAX | Q4: JANUARY 2024 ARREARS
L5: A | O5: B | Q5: (A-B)
A6: S/N | B6: DG'S OFFICE | E6: N | F6: N | G6: N | H6: N | I6: N | J6: N | K6: N | L6: N | M6: N | N6: N | O6: N | Q6: N
A7: 1 | B7: PROF. ABUBAKAR O. SULAIMAN | C7: DIRECTOR GENERAL | D7: CONSOL | E7: 1659751.2 | G7: =250000 -> 250000 | I7: 25235 | J7: =E7+F7+G7+H7+I7 -> 1934986.2 | K7: 1158849.8 | L7: =J7-K7 -> 776136.33 | M7: 350184.01 | N7: 201165.84 | O7: =M7-N7 -> 149018.17 | Q7: =L7-O7 -> 627118.15
A8: 2 | B8: RAHEEM USMAN AYIGORO | C8: SA-INFRASTRUCTURE | D8: 16 (9) | E8: 762373.17 | H8: =90000 -> 90000 | I8: 0 | J8: =E8+F8+G8+H8+I8 -> 852373.17 | K8: 541465.02 | L8: =J8-K8 -> 310908.14 | M8: 130612.26 | N8: 82627.951 | O8: =M8-N8 -> 47984.311 | Q8: =L8-O8 -> 262923.83
A9: 3 | B9: MARIAM MOHAMMED BELLO | C9: SA- SPECIAL DUTIES | D9: 16 (9) | E9: 762373.17 | H9: =90000 -> 90000 | I9: =100000+100000 -> 200000 | J9: =E9+F9+G9+H9+I9 -> 1052373.2 | K9: 741465.02 | L9: =J9-K9 -> 310908.14 | M9: 180722.31 | N9: 121027.95 | O9: =M9-N9 -> 59694.363 | Q9: =L9-O9 -> 251213.78
A10: 4 | B10: DR IKEME ARTHUR J.O | C10: DEPUTY DIRECTOR, M&E | D10: 16 (9) | E10: 762373.17 | G10: 180000 | I10: 0 | J10: =E10+F10+G10+H10+I10 -> 942373.17 | K10: 631465.02 | L10: =J10-K10 -> 310908.14 | M10: 147687.53 | N10: 99703.216 | O10: =M10-N10 -> 47984.311 | Q10: =L10-O10 -> 262923.83
A11: 5 | B11: MOSHOOD M. OLALERE | C11: PPS TO DG | D11: 16 (9) | E11: 762373.17 | H11: =80000+10000 -> 90000 | I11: 150000 | J11: =E11+F11+G11+H11+I11 -> 1002373.2 | K11: 691465.02 | L11: =J11-K11 -> 310908.14 | M11: 159207.53 | N11: 111223.22 | O11: =M11-N11 -> 47984.311 | Q11: =L11-O11 -> 262923.83
A12: 6 | B12: REKIYA IBRAHIM ATTAH | C12: DEPUTY DIRECTOR TRAINING | D12: 16 (9) | E12: 762373.17 | H12: =90000 -> 90000 | I12: 100000 | J12: =E12+F12+G12+H12+I12 -> 952373.17 | K12: 641465.02 | L12: =J12-K12 -> 310908.14 | M12: 161522.31 | N12: 101827.95 | O12: =M12-N12 -> 59694.363 | Q12: =L12-O12 -> 251213.78
A13: 7 | B13: ANDRAWUS MUSA | C13: ASST. DIRECTOR, STORES | D13: 15(9) | E13: 620675.58 | H13: =80000 -> 80000 | I13: 50000 | J13: =E13+F13+G13+H13+I13 -> 750675.58 | K13: 497553.5 | L13: =J13-K13 -> 253122.08 | M13: 113101.97 | N13: 74036.103 | O13: =M13-N13 -> 39065.863 | Q13: =L13-O13 -> 214056.22
A14: 8 | B14: DR FRANCIS NDUM OJIE | C14: AD, TRAINING & IC./SA TO DG | D14: 15(7) | E14: 582118.08 | G14: 160000 | I14: =100000 -> 100000 | J14: =E14+F14+G14+H14+I14 -> 842118.08 | K14: 604729.22 | L14: =J14-K14 -> 237388.86 | M14: 131263.11 | N14: 94625.782 | O14: =M14-N14 -> 36637.328 | Q14: =L14-O14 -> 200751.53
A15: 9 | B15: ALI ABDULLAHI | C15: CHIEF ICT OFFICER | D15: 14(11) | E15: 484373.75 | H15: =70000 -> 70000 | I15: =0 -> 0 | J15: =E15+F15+G15+H15+I15 -> 554373.75 | K15: 343333.04 | L15: =J15-K15 -> 211040.71 | M15: 77666.446 | N15: 44846.617 | O15: =M15-N15 -> 32819.829 | Q15: =L15-O15 -> 178220.89
A16: 10 | B16: EMILY EKHIDE | C16: RESEARCH FELLOW 1 | D16: 14(10) | E16: 470498 | G16: 140000 | I16: 50000 | J16: =E16+F16+G16+H16+I16 -> 660498 | K16: 463333.04 | L16: =J16-K16 -> 197164.96 | M16: 98255.433 | N16: 67626.609 | O16: =M16-N16 -> 30628.824 | Q16: =L16-O16 -> 166536.14
A17: 11 | B17: DORIS DAKDA AARON | C17: RESEARCH FELLOW I | D17: 14(8) | E17: 442746.5 | G17: =140000 -> 140000 | I17: 150000 | J17: =E17+F17+G17+H17+I17 -> 732746.5 | K17: 547211.37 | L17: =J17-K17 -> 185535.13 | M17: 112553.41 | N17: 83731.249 | O17: =M17-N17 -> 28822.159 | Q17: =L17-O17 -> 156712.97
A18: 12 | B18: ABDULSALAM S. MUSTAPHA | C18: ASST. MANAGER ICT | D18: 13(11) | E18: 441804.92 | H18: 70000 | J18: =E18+F18+G18+H18+I18 -> 511804.92 | K18: 326663.08 | L18: =J18-K18 -> 185141.84 | M18: 70147.087 | N18: 42046.064 | O18: =M18-N18 -> 28101.023 | Q18: =L18-O18 -> 157040.82
A19: 13 | B19: PERCY TERFA GBAHABO | C19: HEAD, NILDS LIAISON OFFICE | D19: 13(10) | E19: 428915.92 | G19: =120000 -> 120000 | I19: 0 | J19: =E19+F19+G19+H19+I19 -> 548915.92 | K19: 369177.65 | L19: =J19-K19 -> 179738.26 | M19: 77470.374 | N19: 49548.776 | O19: =M19-N19 -> 27921.598 | Q19: =L19-O19 -> 151816.66
A20: 14 | B20: HASSANA AHMED IBRAHIM | C20: PA- TRAINING | D20: 13 (9) | E20: 416026.92 | G20: =120000 -> 120000 | I20: =100000 -> 100000 | J20: =E20+F20+G20+H20+I20 -> 636026.92 | K20: 462001.06 | L20: =J20-K20 -> 174025.86 | M20: 94274.903 | N20: 67370.87 | O20: =M20-N20 -> 26904.033 | Q20: =L20-O20 -> 147121.82
A21: 15 | B21: ADUGBA RICHARD TERSEER | C21: PRINCIPAL INFO. OFFICER | D21: 12(9) | E21: 377895.17 | H21: =60000 -> 60000 | I21: 100000 | J21: =E21+F21+G21+H21+I21 -> 537895.17 | K21: 384537 | L21: =J21-K21 -> 153358.17 | M21: 76138.069 | N21: 52497.77 | O21: =M21-N21 -> 23640.299 | Q21: =L21-O21 -> 129717.87
A22: 16 | B22: LUCKY AGWOM | C22: PA-TECHNICAL | D22: 12(7) | E22: 353512.5 | G22: =100000 -> 100000 | I22: 100000 | J22: =E22+F22+G22+H22+I22 -> 553512.5 | K22: 400372.08 | L22: =J22-K22 -> 153140.42 | M22: 79511.115 | N22: 55538.105 | O22: =M22-N22 -> 23973.01 | Q22: =L22-O22 -> 129167.42
A23: 17 | B23: IDRIS IBRAHIM | C23: PRINCIPAL RESEARCH OFFICER | D23: 12(7) | E23: 353512.5 | G23: 110000 | I23: 0 | J23: =E23+F23+G23+H23+I23 -> 463512.5 | K23: =1015372.075-700000 -> 315372.07 | L23: =J23-K23 -> 148140.43 | M23: 62231.115 | N23: 40149.175 | O23: =M23-N23 -> 22081.939 | Q23: =L23-O23 -> 126058.49
A24: 18 | B24: FARUQ ATOFARATI | C24: PA (SPECIAL DUTIES) TO DG | D24: 10(7) | E24: 293029.67 | H24: =50000+10000 -> 60000 | I24: 100000 | J24: =E24+F24+G24+H24+I24 -> 453029.67 | K24: 328602.08 | L24: =J24-K24 -> 124427.59 | M24: 61147.427 | N24: 42371.816 | O24: =M24-N24 -> 18775.611 | Q24: =L24-O24 -> 105651.98
A25: 19 | B25: ELIZABETH OGECHUKWU ONYEAKU | C25: ICT OFFICER | D25: 9(9) | E25: 270481.67 | H25: =50000+10000 -> 60000 | J25: =E25+F25+G25+H25+I25 -> 330481.67 | K25: 213508.01 | L25: =J25-K25 -> 116973.66 | M25: 39052.313 | N25: 23036.012 | O25: =M25-N25 -> 16016.301 | Q25: =L25-O25 -> 100957.36
A26: 20 | B26: VICTOR ASUKWO | C26: ICT OFFICER | D26: 9(9) | E26: 270481.67 | H26: =50000+10000 -> 60000 | J26: =E26+F26+G26+H26+I26 -> 330481.67 | K26: 213508.01 | L26: =J26-K26 -> 116973.66 | M26: 39052.313 | N26: 23036.012 | O26: =M26-N26 -> 16016.301 | Q26: =L26-O26 -> 100957.36
A27: 21 | B27: NNANDI LIVINUS ATURE | C27: RESEARCH ASSISTANT | D27: 9(9) | E27: 270481.67 | G27: =100000 -> 100000 | J27: =E27+F27+G27+H27+I27 -> 370481.67 | K27: 253508.01 | L27: =J27-K27 -> 116973.66 | M27: 45772.313 | N27: 29756.012 | O27: =M27-N27 -> 16016.301 | Q27: =L27-O27 -> 100957.36
A28: 22 | B28: ABDULRAHMAN A SULAIMAN | C28: STORE OFFICER | D28: 9(8) | E28: 263165.33 | H28: =60000 -> 60000 | J28: =E28+F28+G28+H28+I28 -> 323165.33 | K28: 209356.05 | L28: =J28-K28 -> 113809.29 | M28: 37921.501 | N28: 22338.483 | O28: =M28-N28 -> 15583.018 | Q28: =L28-O28 -> 98226.268
A29: 23 | B29: DARE SHEU MAGBON | C29: ADMINISTRATION OFFICER | D29: 9(7) | E29: 255849 | H29: =60000 -> 60000 | J29: =E29+F29+G29+H29+I29 -> 315849 | K29: 205204.08 | L29: =J29-K29 -> 110644.92 | M29: 36790.688 | N29: 21640.953 | O29: =M29-N29 -> 15149.735 | Q29: =L29-O29 -> 95495.18
A30: 24 | B30: ABUBAKAR SULAIMAN SODEEQ | C30: ADMINISTRATION OFFICER | D30: 9(7) | E30: 255849 | H30: =60000 -> 60000 | J30: =E30+F30+G30+H30+I30 -> 315849 | K30: 205204.08 | L30: =J30-K30 -> 110644.92 | M30: 36790.688 | N30: 21640.953 | O30: =M30-N30 -> 15149.735 | Q30: =L30-O30 -> 95495.18
A31: 25 | B31: JIMOH ADEBAYO ZAKA | C31: ASST. OFFICER/COMM | D31: 9(9) | E31: 270481.67 | H31: =60000 -> 60000 | J31: =E31+F31+G31+H31+I31 -> 330481.67 | K31: 209356.05 | L31: =J31-K31 -> 121125.62 | M31: 39052.313 | N31: 22338.483 | O31: =M31-N31 -> 16713.83 | Q31: =L31-O31 -> 104411.79
A32: 26 | B32: MOHAMMED BELLO | C32: PROTOCOL ASSISTANT | D32: 8(9) | E32: 230631.92 | H32: =50000 -> 50000 | J32: =E32+F32+G32+H32+I32 -> 280631.92 | K32: 180304.07 | L32: =J32-K32 -> 100327.85 | M32: 31213.136 | N32: 17572.885 | O32: =M32-N32 -> 13640.251 | Q32: =L32-O32 -> 86687.598
A33: 27 | B33: HARUNA JIBRIL AMEH | C33: ASST. ADMIN. OFFICER | D33: 8(8) | E33: 224459.75 | H33: 50000 | J33: =E33+F33+G33+H33+I33 -> 274459.75 | K33: 173329.05 | L33: =J33-K33 -> 101130.7 | M33: 30259.166 | N33: 16512.682 | O33: =M33-N33 -> 13746.483 | Q33: =L33-O33 -> 87384.217
B34: TOTAL | C34: 27 | E34: =SUM(E7:E33) -> 13048608 | F34: =SUM(F7:F33) -> 0 | G34: =SUM(G7:G33) -> 1420000 | H34: =SUM(H7:H33) -> 1160000 | I34: =SUM(I7:I33) -> 1225235 | J34: =SUM(J7:J33) -> 16853843 | K34: =SUM(K7:K33) -> 11312338 | L34: =SUM(L7:L33) -> 5541505.6 | ... O34: =SUM(O7:O33) -> 889763.31 | Q34: =SUM(Q7:Q33) -> 4651742.3
B36: INTERNAL AUDIT
A37: 1 | B37: OSANAIYE DAVID AKINYEMI | C37: DIRECTOR INTERNAL AUDIT | D37: 17(9) | E37: 1435720 | H37: =100000 -> 100000 | J37: =E37+F37+G37+H37+I37 -> 1535720 | K37: 950209.06 | L37: =J37-K37 -> 585510.94 | M37: 251472.25 | N37: 161106.81 | O37: =M37-N37 -> 90365.441 | Q37: =L37-O37 -> 495145.5
A38: 2 | B38: JAMILA ABDUL | C38: SENIOR INTERNAL AUDITOR | D38: 10(7) | E38: 293029.67 | H38: =60000 -> 60000 | J38: =E38+F38+G38+H38+I38 -> 353029.67 | K38: 176816.1 | L38: =J38-K38 -> 176213.57 | M38: 42537.332 | N38: 17042.714 | O38: =M38-N38 -> 25494.618 | Q38: =L38-O38 -> 150718.95
A39: 3 | B39: IJEOMA EWELUKWA | C39: AUDIT OFFICER | D39: 10(8) | E39: 300965.58 | H39: =50000+10000 -> 60000 | J39: =E39+F39+G39+H39+I39 -> 360965.58 | K39: 233169.12 | L39: =J39-K39 -> 127796.47 | M39: 43763.907 | N39: 26339.078 | O39: =M39-N39 -> 17424.829 | Q39: =L39-O39 -> 110371.64
C40: 3 | E40: =SUM(E37:E39) -> 2029715.2 | F40: =SUM(F37:F39) -> 0 | G40: =SUM(G37:G39) -> 0 | H40: =SUM(H37:H39) -> 220000 | I40: =SUM(I37:I39) -> 0 | J40: =SUM(J37:J39) -> 2249715.2 | K40: 1360194.3 | L40: =SUM(L37:L39) -> 889520.97 | M40: =SUM(M37:M39) -> 337773.49 | N40: 204488.6 | O40: =SUM(O37:O39) -> 133284.89 | Q40: =SUM(Q37:Q39) -> 756236.08
B42: LEG. SUPPORT SEVICES
A43: 1 | B43: PROF. EDOBA BRIGHT OMOREGBE | C43: AG. DLSS | D43: 17(9) | E43: 1435720 | G43: =200000 -> 200000 | J43: =E43+F43+G43+H43+I43 -> 1635720 | K43: 1050209.1 | L43: =J43-K43 -> 585510.94 | M43: 270672.25 | N43: 180306.81 | O43: =M43-N43 -> 90365.441 | Q43: =L43-O43 -> 495145.5
A44: 2 | B44: DR CLINTON JAJA | C44: SENIOR RESEARCH FELLOW | D44: 15(9) | E44: 620675.58 | G44: =160000 -> 160000 | I44: 0 | J44: =E44+F44+G44+H44+I44 -> 780675.58 | K44: 527553.5 | L44: =J44-K44 -> 253122.08 | M44: 119022.8 | N44: 79956.939 | O44: =M44-N44 -> 39065.863 | Q44: =L44-O44 -> 214056.22
A45: 3 | B45: BETHEL UZOMA IHUGBA | C45: DEPUTY DIRECTOR, LEGAL RESEARCH | D45: 16(8) | E45: 739203.58 | G45: =180000 -> 180000 | J45: =E45+F45+G45+H45+I45 -> 919203.58 | K45: 617744 | L45: =J45-K45 -> 301459.59 | M45: 143799.59 | N45: 97273.514 | O45: =M45-N45 -> 46526.074 | Q45: =L45-O45 -> 254933.51
A46: 4 | B46: OGUCHE SAMUEL | C46: SNR RESEARCH FELLOW | D46: 15(9) | E46: 620675.58 | G46: =160000 -> 160000 | J46: =E46+F46+G46+H46+I46 -> 780675.58 | K46: 527553.5 | L46: =J46-K46 -> 253122.08 | M46: 119022.8 | N46: 79956.939 | O46: =M46-N46 -> 39065.863 | Q46: =L46-O46 -> 214056.22
A47: 5 | B47: IBRAHIM USMAN | C47: SNR RESEARCH FELLOW | D47: 15(9) | E47: 620675.58 | G47: =140000+20000 -> 160000 | I47: 0 | J47: =E47+F47+G47+H47+I47 -> 780675.58 | K47: 527553.5 | L47: =J47-K47 -> 253122.08 | M47: 118861.97 | N47: 79796.103 | O47: =M47-N47 -> 39065.863 | Q47: =L47-O47 -> 214056.22
A48: 6 | B48: DR MOHAMMED O. AMALI | C48: SNR RESEARCH FELLOW | D48: 15(7) | E48: 582118.08 | G48: =140000+20000 -> 160000 | J48: =E48+F48+G48+H48+I48 -> 742118.08 | K48: 504720.05 | L48: =J48-K48 -> 237398.04 | M48: 112212 | N48: 75572.916 | O48: =M48-N48 -> 36639.089 | Q48: =L48-O48 -> 200758.95
A49: 7 | B49: YAHAYA SHAMSU | C49: RESEARCH FELLOW 1 | D49: 14(10) | E49: 470498 | G49: =140000 -> 140000 | J49: =E49+F49+G49+H49+I49 -> 610498 | K49: 413333.04 | L49: =J49-K49 -> 197164.96 | M49: 88655.433 | N49: 58026.609 | O49: =M49-N49 -> 30628.824 | Q49: =L49-O49 -> 166536.14
A50: 8 | B50: BILKIS S. LAWAL-GAMBARI | C50: RESEARCH OFFICER | D50: 10(8) | E50: 300965.58 | G50: 100000 | J50: =E50+F50+G50+H50+I50 -> 400965.58 | K50: 273169.12 | L50: =J50-K50 -> 127796.47 | M50: 51029.227 | N50: 33059.078 | O50: =M50-N50 -> 17970.149 | Q50: =L50-O50 -> 109826.32
A51: 9 | B51: ZAINAB AKINDE | C51: RESEARCH OFFICER | D51: 9(8) | E51: 263165.33 | G51: =100000 -> 100000 | J51: =E51+F51+G51+H51+I51 -> 363165.33 | K51: 249356.05 | L51: =J51-K51 -> 113809.29 | M51: 44641.501 | N51: 29058.483 | O51: =M51-N51 -> 15583.018 | Q51: =L51-O51 -> 98226.268
A52: 10 | B52: ABDULLAHI AHMAD USMAN | C52: RESEARCH OFFICER | D52: 9(8) | E52: 263165.33 | G52: =100000 -> 100000 | J52: =E52+F52+G52+H52+I52 -> 363165.33 | K52: 249356.05 | L52: =J52-K52 -> 113809.29 | M52: 44641.501 | N52: 28360.953 | O52: =M52-N52 -> 16280.548 | Q52: =L52-O52 -> 97528.738
A53: 11 | B53: GUNAT NANSAK MARK | C53: RESEARCH OFFICER | D53: 9(8) | E53: 263165.33 | G53: =100000 -> 100000 | J53: =E53+F53+G53+H53+I53 -> 363165.33 | K53: 249356.05 | L53: =J53-K53 -> 113809.29 | M53: 44641.501 | N53: 29058.483 | O53: =M53-N53 -> 15583.018 | Q53: =L53-O53 -> 98226.268
B54: TOTAL | C54: 11 | E54: =SUM(E43:E53) -> 6180028 | F54: =SUM(F43:F53) -> 0 | G54: =SUM(G43:G53) -> 1560000 | H54: =SUM(H43:H53) -> 0 | I54: =SUM(I43:I53) -> 0 | J54: =SUM(J43:J53) -> 7740028 | K54: 5189903.9 | L54: =SUM(L43:L53) -> 2550124.1 | M54: =SUM(M43:M53) -> 1157200.6 | N54: 770426.82 | O54: =SUM(O43:O53) -> 386773.75 | Q54: =SUM(Q43:Q53) -> 2163350.3
B56: LEGAL SERVICES
A57: 1 | B57: DR SHUIBU DANWANKA | C57: DIRECTOR LEGAL SERVICES | D57: 17(9) | E57: 1435720 | G57: =200000 -> 200000 | I57: 0 | J57: =E57+F57+G57+H57+I57 -> 1635720 | K57: 1050209.1 | L57: =J57-K57 -> 585510.94 | M57: 270672.25 | N57: 180306.81 | O57: =M57-N57 -> 90365.441 | Q57: =L57-O57 -> 495145.5
A58: 2 | B58: ABDULSALAM BAKO | C58: MANAGER, LEGAL SERVICES | D58: 15 (9) | E58: 620675.58 | H58: 80000 | J58: =E58+F58+G58+H58+I58 -> 700675.58 | K58: 447553.5 | L58: =J58-K58 -> 253122.08 | M58: 103662.8 | N58: 64596.939 | O58: =M58-N58 -> 39065.863 | Q58: =L58-O58 -> 214056.22
B59: TOTAL | C59: 2 | E59: =SUM(E57:E58) -> 2056395.6 | F59: =SUM(F57:F58) -> 0 | G59: =SUM(G57:G58) -> 200000 | H59: =SUM(H57:H58) -> 80000 | I59: =SUM(I57:I58) -> 0 | J59: =SUM(J57:J58) -> 2336395.6 | K59: 1497762.6 | L59: =SUM(L57:L58) -> 838633.02 | M59: =SUM(M57:M58) -> 374335.05 | N59: 244903.75 | O59: =SUM(O57:O58) -> 129431.3 | Q59: =SUM(Q57:Q58) -> 709201.71
B61: DEMOCRACY & GOVERNANCE
A62: 1 | B62: DR. ADEWALE ADEREMI | C62: DIRECTOR, DEMOCRATIC STUDIES | D62: 17(9) | E62: 1435720 | G62: =200000 -> 200000 | I62: 0 | J62: =E62+F62+G62+H62+I62 -> 1635720 | K62: 1050209.1 | L62: =J62-K62 -> 585510.94 | M62: 292724.91 | N62: 180306.81 | O62: =M62-N62 -> 112418.1 | Q62: =L62-O62 -> 473092.84
A63: 2 | B63: NDANUSA MOHAMMED MANZUMA | C63: SNR RESEARCH FELLOW | D63: 15(8) | E63: 601396.83 | G63: =160000 -> 160000 | I63: 0 | J63: =E63+F63+G63+H63+I63 -> 761396.83 | K63: 516137.05 | L63: =J63-K63 -> 245259.78 | M63: 115617.4 | N63: 77764.98 | O63: =M63-N63 -> 37852.423 | Q63: =L63-O63 -> 207407.36
A64: 3 | B64: EJALONIBU GANIYU LAYI | C64: RESEARCH FELLOW 1 | D64: 14(8) | E64: 442746.5 | G64: 140000 | J64: =E64+F64+G64+H64+I64 -> 582746.5 | K64: 397211.37 | L64: =J64-K64 -> 185535.13 | M64: 83753.408 | N64: 54931.249 | O64: =M64-N64 -> 28822.159 | Q64: =L64-O64 -> 156712.97
A65: 4 | B65: LOHNA BONKAT JONATHAN | C65: RESEARCH FELLOW 11 | D65: 13(10) | E65: 428915.92 | G65: =120000 -> 120000 | I65: 0 | J65: =E65+F65+G65+H65+I65 -> 548915.92 | K65: 369177.65 | L65: =J65-K65 -> 179738.26 | M65: 77470.374 | N65: 49548.776 | O65: =M65-N65 -> 27921.598 | Q65: =L65-O65 -> 151816.66
A66: 5 | B66: YUNUSA ABDULLAHI | C66: RESEARCH FELLOW 1 | D66: 14(11) | E66: 484373.75 | G66: =140000 -> 140000 | J66: =E66+F66+G66+H66+I66 -> 624373.75 | K66: 421394.01 | L66: =J66-K66 -> 202979.74 | M66: 91106.446 | N66: 59574.316 | O66: =M66-N66 -> 31532.13 | Q66: =L66-O66 -> 171447.61
A67: 7 | B67: UDEFUNA NNADOZIE PATRICK | C67: RESEARCH OFFICER | D67: 12(8) | E67: 365703.83 | G67: =110000 -> 110000 | I67: 0 | J67: =E67+F67+G67+H67+I67 -> 475703.83 | K67: 322454.07 | L67: =J67-K67 -> 153249.76 | M67: 64384.592 | N67: 41338.951 | O67: =M67-N67 -> 23045.641 | Q67: =L67-O67 -> 130204.12
A68: 8 | B68: SHAFIU YAHYA MIKAIL | C68: PRINCIPAL RESEARCH OFFICER | D68: 12(8) | E68: 365703.83 | G68: =110000 -> 110000 | I68: 0 | J68: =E68+F68+G68+H68+I68 -> 475703.83 | K68: 322454.07 | L68: =J68-K68 -> 153249.76 | M68: 64384.592 | N68: 41338.951 | O68: =M68-N68 -> 23045.641 | Q68: =L68-O68 -> 130204.12
A69: 9 | B69: HASSAN YERIMA | C69: PRINCIPAL RESEARCH OFFICER | D69: 12(8) | E69: 365703.83 | G69: =110000 -> 110000 | I69: 0 | J69: =E69+F69+G69+H69+I69 -> 475703.83 | K69: 322454.07 | L69: =J69-K69 -> 153249.76 | M69: 64384.592 | N69: 41338.951 | O69: =M69-N69 -> 23045.641 | Q69: =L69-O69 -> 130204.12
A70: 10 | B70: HAUWA PATE SADIQ | C70: PRINCIPAL PROGRAMME OFFICER | D70: 12(9) | E70: 377895.17 | G70: =110000 -> 110000 | J70: =E70+F70+G70+H70+I70 -> 487895.17 | K70: 334537 | L70: =J70-K70 -> 153358.17 | M70: 66538.069 | N70: 43368.882 | O70: =M70-N70 -> 23169.186 | Q70: =L70-O70 -> 130188.98
A71: 11 | B71: KOLAPO Q. ABAYOMI | C71: RESEARCH OFFICER | D71: 10(8) | E71: 300965.58 | G71: 100000 | J71: =E71+F71+G71+H71+I71 -> 400965.58 | K71: 277734.05 | L71: =J71-K71 -> 123231.54 | M71: 51029.227 | N71: 33825.987 | O71: =M71-N71 -> 17203.241 | Q71: =L71-O71 -> 106028.3
B72: TOTAL | C72: 12 | E72: =SUM(E62:E71) -> 5169125.2 | F72: =SUM(F62:F71) -> 0 | G72: =SUM(G62:G71) -> 1300000 | H72: =SUM(H62:H71) -> 0 | I72: =SUM(I62:I71) -> 0 | J72: =SUM(J62:J71) -> 6469125.2 | K72: 4333762.4 | L72: =SUM(L62:L71) -> 2135362.8 | M72: =SUM(M62:M71) -> 971393.61 | N72: 623337.85 | O72: =SUM(O62:O71) -> 348055.76 | Q72: =SUM(Q62:Q71) -> 1787307.1
B74: DEPARTMENT OF STUDIES
A75: 1 | B75: DR ASIMIYU G. ABIOLA | C75: DIRECTOR POST GRADUATE | D75: 17(9) | E75: 1435720 | G75: =200000 -> 200000 | I75: 0 | J75: =E75+F75+G75+H75+I75 -> 1635720 | K75: 1050209.1 | L75: =J75-K75 -> 585510.94 | M75: 270672.25 | N75: 180306.81 | O75: =M75-N75 -> 90365.441 | Q75: =L75-O75 -> 495145.5
A76: 2 | B76: USMAN WALI | C76: SENIOR RESEARCH FELLOW | D76: 15 (8) | E76: 601396.83 | G76: =160000 -> 160000 | I76: 0 | J76: =E76+F76+G76+H76+I76 -> 761396.83 | K76: 516137.05 | L76: =J76-K76 -> 245259.78 | M76: 124854.86 | N76: 77764.98 | O76: =M76-N76 -> 47089.878 | Q76: =L76-O76 -> 198169.9
A77: 3 | B77: AYOBOLU OLAJIDE OLUFUNSHO | C77: ASST.DIR., INFORMATION | D77: 15 (9) | E77: 620675.58 | G77: 0 | H77: 80000 | I77: 0 | J77: =E77+F77+G77+H77+I77 -> 700675.58 | K77: 447553.5 | L77: =J77-K77 -> 253122.08 | M77: 113196.38 | N77: 64596.939 | O77: =M77-N77 -> 48599.44 | Q77: =L77-O77 -> 204522.64
A78: 4 | B78: ANTHONY EDET | C78: CHIEF PROGRAMMES OFFICER | D78: 14(9) | E78: 456622.25 | G78: =140000 -> 140000 | I78: 0 | J78: =E78+F78+G78+H78+I78 -> 596622.25 | K78: 405272.06 | L78: =J78-K78 -> 191350.19 | M78: 86076.104 | N78: 56350.586 | O78: =M78-N78 -> 29725.518 | Q78: =L78-O78 -> 161624.67
A79: 5 | B79: IGWE STACY | C79: PROGRAMME OFFICER | D79: 10(9) | E79: 308901.5 | G79: =100000 -> 100000 | J79: =E79+F79+G79+H79+I79 -> 408901.5 | K79: 273169.12 | L79: =J79-K79 -> 135732.38 | M79: 52431.028 | N79: 33059.078 | O79: =M79-N79 -> 19371.949 | Q79: =L79-O79 -> 116360.43
A80: 6 | B80: OLANIYAN TAIWO ABINBOLA | C80: PROGRAMME OFFICER | D80: 9(8) | E80: 263165.33 | G80: 100000 | J80: =E80+F80+G80+H80+I80 -> 363165.33 | K80: 249356.05 | L80: =J80-K80 -> 113809.29 | M80: 44641.501 | N80: 29058.483 | O80: =M80-N80 -> 15583.018 | Q80: =L80-O80 -> 98226.268
A81: 7 | B81: AMINAT JUMOKE SULAIMON | C81: AST. PROGRAMME OFFICER | D81: 8(8) | E81: 224459.75 | G81: 100000 | H81: 0 | J81: =E81+F81+G81+H81+I81 -> 324459.75 | K81: 223717.28 | L81: =J81-K81 -> 100742.47 | M81: 38659.166 | N81: 24751.17 | O81: =M81-N81 -> 13907.995 | Q81: =L81-O81 -> 86834.47
B82: TOTAL | C82: 7 | E82: =SUM(E75:E81) -> 3910941.3 | F82: =SUM(F75:F81) -> 0 | G82: =SUM(G75:G81) -> 800000 | H82: =SUM(H75:H81) -> 80000 | I82: =SUM(I75:I81) -> 0 | J82: =SUM(J75:J81) -> 4790941.2 | K82: 3165414.1 | L82: =SUM(L75:L81) -> 1625527.1 | M82: =SUM(M75:M81) -> 730531.28 | N82: 465888.04 | O82: =SUM(O75:O81) -> 264643.24 | Q82: =SUM(Q75:Q81) -> 1360883.9
B84: ECON. DEV. & SOC. RESEARCH
A85: 1 | B85: TERFA WILLIAMS ABRAHAM | C85: SNR RESEARCH FELLOW | D85: 15(9) | E85: 620675.58 | G85: =160000 -> 160000 | I85: 100000 | J85: =E85+F85+G85+H85+I85 -> 880675.58 | K85: 627553.5 | L85: =J85-K85 -> 253122.08 | M85: 138222.8 | N85: 99156.939 | O85: =M85-N85 -> 39065.863 | Q85: =L85-O85 -> 214056.22
A86: 2 | B86: DR AUGUSTINE C. OSIGWE | C86: SNR RESEARCH FELLOW | D86: 15(9) | E86: 620675.58 | G86: =160000 -> 160000 | J86: =E86+F86+G86+H86+I86 -> 780675.58 | K86: 527553.5 | L86: =J86-K86 -> 253122.08 | M86: 118861.97 | N86: 79796.103 | O86: =M86-N86 -> 39065.863 | Q86: =L86-O86 -> 214056.22
A87: 3 | B87: OMOJU OLUWASOLA EMMANUEL | C87: SNR RESEARCH FELLOW | D87: 15(7) | E87: 582118.08 | G87: 160000 | J87: =E87+F87+G87+H87+I87 -> 742118.08 | K87: 504729.22 | L87: =J87-K87 -> 237388.86 | M87: 112212 | N87: 75574.677 | O87: =M87-N87 -> 36637.328 | Q87: =L87-O87 -> 200751.53
A88: 4 | B88: IBE EZECHI CYRIACUS | C88: RESEARCH FELLOW II | D88: 13(11) | E88: 441804.92 | G88: =120000 -> 120000 | I88: 0 | J88: =E88+F88+G88+H88+I88 -> 561804.92 | K88: 376663.08 | L88: =J88-K88 -> 185141.84 | M88: 79747.087 | N88: 50985.978 | O88: =M88-N88 -> 28761.11 | Q88: =L88-O88 -> 156380.73
A89: 5 | B89: OSIKHEN LEO IGBANOI | C89: RESEARCH FELLOW 11 | D89: 13(10) | E89: 428915.92 | G89: =120000 -> 120000 | I89: 0 | J89: =E89+F89+G89+H89+I89 -> 548915.92 | K89: 369177.65 | L89: =J89-K89 -> 179738.26 | M89: 77470.374 | N89: 49548.776 | O89: =M89-N89 -> 27921.598 | Q89: =L89-O89 -> 151816.66
A90: 6 | B90: OKUNGBOWA OSARETIN GODSPOWER | C90: RESEARCH FELLOW 1 | D90: 14(7) | E90: 428870.75 | G90: =140000 -> 140000 | I90: 0 | J90: =E90+F90+G90+H90+I90 -> 568870.75 | K90: 389153.06 | L90: =J90-K90 -> 179717.69 | M90: 81302.396 | N90: 53384.054 | O90: =M90-N90 -> 27918.342 | Q90: =L90-O90 -> 151799.35
A91: 7 | B91: YUSUF IBRAHIM | C91: PRINCIPAL RESEARCH OFFICER | D91: 12(8) | E91: 365703.83 | G91: =110000 -> 110000 | I91: 0 | J91: =E91+F91+G91+H91+I91 -> 475703.83 | K91: 322454.07 | L91: =J91-K91 -> 153249.76 | M91: 64384.592 | N91: 41338.951 | O91: =M91-N91 -> 23045.641 | Q91: =L91-O91 -> 130204.12
A92: 8 | B92: MUSTAPHA RAFIU AYOBANJI | C92: RESEARCH FELLOW 11 | D92: 13(7) | E92: 390248.92 | G92: 120000 | I92: 0 | J92: =E92+F92+G92+H92+I92 -> 510248.92 | K92: 346713.03 | L92: =J92-K92 -> 163535.88 | M92: 70529.475 | N92: 45317.541 | O92: =M92-N92 -> 25211.934 | Q92: =L92-O92 -> 138323.95
A93: 9 | B93: MARYAM MUSA SADA | C93: ASSIT. RESEARCH OFFICER | D93: 10(8) | E93: 300965.58 | G93: 100000 | J93: =E93+F93+G93+H93+I93 -> 400965.58 | K93: 277734.05 | L93: =J93-K93 -> 123231.54 | M93: 51029.227 | N93: 33825.987 | O93: =M93-N93 -> 17203.241 | Q93: =L93-O93 -> 106028.3
A94: 10 | B94: CHARITY EZENWAJIOBI | C94: REASEARCH. ASST. | D94: 8(9) | E94: 230631.92 | G94: =100000 -> 100000 | J94: =E94+F94+G94+H94+I94 -> 330631.92 | K94: 254870.26 | L94: =J94-K94 -> 75761.653 | M94: 39613.136 | N94: 29984.871 | O94: =M94-N94 -> 9628.2648 | Q94: =L94-O94 -> 66133.388
B95: TOTAL | C95: 11 | E95: =SUM(E85:E94) -> 4410611.1 | F95: =SUM(F85:F94) -> 0 | G95: =SUM(G85:G94) -> 1290000 | H95: =SUM(H85:H94) -> 0 | I95: =SUM(I85:I94) -> 100000 | J95: =SUM(J85:J94) -> 5800611.1 | K95: 3996601.4 | L95: =SUM(L85:L94) -> 1804009.7 | M95: =SUM(M85:M94) -> 833373.06 | N95: 558913.88 | O95: =SUM(O85:O94) -> 274459.18 | Q95: =SUM(Q85:Q94) -> 1529550.5
B97: TRAINING & INT''L COOP
A98: 1 | B98: AKINSANMI ADEJOKE OLUKEMI | C98: Ag. DIR. TRAINING & IC | D98: 16(9) | E98: 762373.17 | H98: =80000+10000 -> 90000 | J98: =E98+F98+G98+H98+I98 -> 852373.17 | K98: 541465.02 | L98: =J98-K98 -> 310908.14 | M98: 130407.53 | N98: 82423.216 | O98: =M98-N98 -> 47984.311 | Q98: =L98-O98 -> 262923.83
A99: 2 | B99: MOHAMMED R. ADAMU | C99: CHIEF TRAINING OFFICER | D99: 14(9) | E99: 456622.25 | H99: 70000 | I99: 0 | J99: =E99+F99+G99+H99+I99 -> 526622.25 | K99: 335272.06 | L99: =J99-K99 -> 191350.19 | M99: 72764.421 | N99: 43492.373 | O99: =M99-N99 -> 29272.048 | Q99: =L99-O99 -> 162078.14
A100: 3 | B100: OKECHUKWU UCHENNA HULDA | C100: PRINCIPALTRAINING OFFICER | D100: 12(9) | E100: 377895.17 | H100: =60000 -> 60000 | J100: =E100+F100+G100+H100+I100 -> 437895.17 | K100: 284537 | L100: =J100-K100 -> 153358.17 | M100: 56938.069 | N100: 34968.882 | O100: =M100-N100 -> 21969.186 | Q100: =L100-O100 -> 131388.98
A101: 4 | B101: TASSNEEM IBRAHIM | C101: SENIOR PROGRAMME OFFICER | D101: 10(8) | E101: 300965.58 | H101: =60000 -> 60000 | J101: =E101+F101+G101+H101+I101 -> 360965.58 | K101: 237734.05 | L101: =J101-K101 -> 123231.54 | M101: 43763.907 | N101: 27105.987 | O101: =M101-N101 -> 16657.921 | Q101: =L101-O101 -> 106573.62
B102: TOTAL | C102: 4 | E102: =SUM(E98:E101) -> 1897856.2 | F102: =SUM(F98:F101) -> 0 | G102: =SUM(G98:G101) -> 0 | H102: =SUM(H98:H101) -> 280000 | I102: =SUM(I98:I101) -> 0 | J102: =SUM(J98:J101) -> 2177856.2 | K102: 1399008.1 | L102: =SUM(L98:L101) -> 778848.03 | M102: =SUM(M98:M101) -> 303873.92 | N102: 187990.46 | O102: =SUM(O98:O101) -> 115883.47 | Q102: =SUM(Q98:Q101) -> 662964.57
B104: LIBRARY & DOCUMENTATION
A105: 1 | B105: DR MAIMUNA IZAH | C105: INSITUTE LIBRARIAN | D105: 17(9) | E105: 1435720 | G105: =200000 -> 200000 | I105: 0 | J105: =E105+F105+G105+H105+I105 -> 1635720 | K105: 1050209.1 | L105: =J105-K105 -> 585510.94 | M105: 270672.25 | N105: 180306.81 | O105: =M105-N105 -> 90365.441 | Q105: =L105-O105 -> 495145.5
A106: 2 | B106: CATHERINE E. IKOKOH | C106: SNR RESEARCH FELLOW DOCU | D106: 16(9) | E106: 762373.17 | G106: =160000+20000 -> 180000 | I106: 0 | J106: =E106+F106+G106+H106+I106 -> 942373.17 | K106: 631465.02 | L106: =J106-K106 -> 310908.14 | M106: 147687.53 | N106: 99703.216 | O106: =M106-N106 -> 47984.311 | Q106: =L106-O106 -> 262923.83
A107: 3 | B107: ALIYU SANNI ABUBAKAR | C107: RESEARCH FELLOW 11 DATA & DOCU | D107: 13(11) | E107: 441804.92 | G107: =120000 -> 120000 | I107: 41432.939 | J107: =E107+F107+G107+H107+I107 -> 603237.86 | K107: 418096.02 | L107: =J107-K107 -> 185141.84 | M107: 87575.783 | N107: 58814.673 | O107: =M107-N107 -> 28761.11 | Q107: =L107-O107 -> 156380.73
A108: 4 | B108: CHINAKO N. ASOGWA | C108: RESEARCH FELLOW 11 DATA & DOCU | D108: 13(11) | E108: 441804.92 | G108: =120000 -> 120000 | I108: 39820.117 | J108: =E108+F108+G108+H108+I108 -> 601625.03 | K108: 416483.19 | L108: =J108-K108 -> 185141.84 | M108: 87392.55 | N108: 58631.44 | O108: =M108-N108 -> 28761.11 | Q108: =L108-O108 -> 156380.73
...

Sheet Tax Reg Sch. 
A1: NATIONAL INSTITUTE FOR LEGISLATIVE AND DEMOCRATIC STUDIES
A2: NATIONAL ASSEMBLY ABUJA
A3: TAX COMPUTATION FOR 2022
A4: S/NO | B4: NAME | C4: MONTHLY TOTAL SALARY | D4: NO OF MONTHS | E4: ANNUAL SALARY GROSSED UP | F4: NATIONAL HOUSING SCHEME = 2.5% OF BASIC SALARY | G4: PENSION CONTRIBUTION = 8% OF CONSOLIDATED | H4: NHIS | I4: NET SALARY (EXC OF CRA) | M4: CRA=#200,000+(20% 0F NET SALARY (EXC OF CRA) | N4: TOTAL RELIEF | O4: CHARGEABLE INCOME | P4: FIRST N300,000 @ 7% | Q4: NEXT N300,000 @ 11% | R4: NEXT N500,000 @ 15% | S4: NEXT N500,000@ 19% | T4: NEXT N1,600,000 @ 21% | U4: ABOVE N3,200,000 @ 24% | V4: ANNUAL TAX PAYABLE | X4: MONTHLY TAX PAYABLE | Y4: MINIMUM TAX PAYABLE | Z4: NEW ACTUAL TAX PAYABLE | AB4: Difference
A5: 1 | B5: DG'S OFFICE
A6: 3 | B6: PROF. ABUBAKAR O. SULAIMAN | C6: 1158849.8 | D6: 12 | E6: =C6*D6 -> 13906198 | I6: =E6-F6-G6-H6 -> 13906198 | J6: 200000 | K6: 0.2 | L6: =I6*K6 -> 2781239.6 | M6: =J6+L6 -> 2981239.6 | N6: =F6+G6+H6+M6 -> 2981239.6 | O6: =E6-N6 -> 10924958 | P6: =IF(O6<300000,0.07*O6,21000) -> 21000 | Q6: =IF((O6-300000)<0,0,IF((O6-300000)<300000,0.11*(O6-300000),33000)) -> 33000 | R6: =IF((O6-600000)<0,0,IF((O6-600000)<500000,0.15*(O6-600000),75000)) -> 75000 | S6: =IF((O6-1100000)<0,0,IF((O6-1100000)<500000,0.19*(O6-1100000),95000)) -> 95000 | T6: =IF((O6-1600000)<0,0,IF((O6-1600000)<1600000,0.21*(O6-1600000),336000)) -> 336000 | U6: =24%*(O6-3200000) -> 1853990 | V6: =P6+Q6+R6+S6+T6+U6 -> 2413990 | W6: 12 | X6: =V6/W6 -> 201165.84 | Z6: =X6 -> 201165.84 | AA6: 201165.84 | AB6: =Z6-AA6 -> 0
A7: 4 | B7: RAHEEM USMAN AYIGORO | C7: 541465.02 | D7: 12 | E7: =C7*D7 -> 6497580.3 | I7: =E7-F7-G7-H7 -> 6497580.3 | J7: 200000 | K7: 0.2 | L7: =I7*K7 -> 1299516.1 | M7: =J7+L7 -> 1499516.1 | N7: =F7+G7+H7+M7 -> 1499516.1 | O7: =E7-N7 -> 4998064.2 | P7: =IF(O7<300000,0.07*O7,21000) -> 21000 | Q7: =IF((O7-300000)<0,0,IF((O7-300000)<300000,0.11*(O7-300000),33000)) -> 33000 | R7: =IF((O7-600000)<0,0,IF((O7-600000)<500000,0.15*(O7-600000),75000)) -> 75000 | S7: =IF((O7-1100000)<0,0,IF((O7-1100000)<500000,0.19*(O7-1100000),95000)) -> 95000 | T7: =IF((O7-1600000)<0,0,IF((O7-1600000)<1600000,0.21*(O7-1600000),336000)) -> 336000 | U7: =24%*(O7-3200000) -> 431535.42 | V7: =P7+Q7+R7+S7+T7+U7 -> 991535.42 | W7: 12 | X7: =V7/W7 -> 82627.951 | Z7: =X7 -> 82627.951 | AA7: 82627.951 | AB7: =Z7-AA7 -> 0
A8: 5 | B8: MARIAM MOHAMMED BELLO | C8: 741465.02 | D8: 12 | E8: =C8*D8 -> 8897580.3 | I8: =E8-F8-G8-H8 -> 8897580.3 | J8: 200000 | K8: 0.2 | L8: =I8*K8 -> 1779516.1 | M8: =J8+L8 -> 1979516.1 | N8: =F8+G8+H8+M8 -> 1979516.1 | O8: =E8-N8 -> 6918064.2 | P8: =IF(O8<300000,0.07*O8,21000) -> 21000 | Q8: =IF((O8-300000)<0,0,IF((O8-300000)<300000,0.11*(O8-300000),33000)) -> 33000 | R8: =IF((O8-600000)<0,0,IF((O8-600000)<500000,0.15*(O8-600000),75000)) -> 75000 | S8: =IF((O8-1100000)<0,0,IF((O8-1100000)<500000,0.19*(O8-1100000),95000)) -> 95000 | T8: =IF((O8-1600000)<0,0,IF((O8-1600000)<1600000,0.21*(O8-1600000),336000)) -> 336000 | U8: =24%*(O8-3200000) -> 892335.42 | V8: =P8+Q8+R8+S8+T8+U8 -> 1452335.4 | W8: 12 | X8: =V8/W8 -> 121027.95 | Z8: =X8 -> 121027.95 | AA8: 121027.95 | AB8: =Z8-AA8 -> 0
A9: 6 | B9: DR IKEME ARTHUR J.O | C9: 631465.02 | D9: 12 | E9: =C9*D9 -> 7577580.3 | F9: ='[5]JANUARY 2024'!$V$10*12 -> 12795.951 | I9: =E9-F9-G9-H9 -> 7564784.3 | J9: 200000 | K9: 0.2 | L9: =I9*K9 -> 1512956.9 | M9: =J9+L9 -> 1712956.9 | N9: =F9+G9+H9+M9 -> 1725752.8 | O9: =E9-N9 -> 5851827.5 | P9: =IF(O9<300000,0.07*O9,21000) -> 21000 | Q9: =IF((O9-300000)<0,0,IF((O9-300000)<300000,0.11*(O9-300000),33000)) -> 33000 | R9: =IF((O9-600000)<0,0,IF((O9-600000)<500000,0.15*(O9-600000),75000)) -> 75000 | S9: =IF((O9-1100000)<0,0,IF((O9-1100000)<500000,0.19*(O9-1100000),95000)) -> 95000 | T9: =IF((O9-1600000)<0,0,IF((O9-1600000)<1600000,0.21*(O9-1600000),336000)) -> 336000 | U9: =24%*(O9-3200000) -> 636438.59 | V9: =P9+Q9+R9+S9+T9+U9 -> 1196438.6 | W9: 12 | X9: =V9/W9 -> 99703.216 | Z9: =X9 -> 99703.216 | AA9: 99703.216 | AB9: =Z9-AA9 -> 0
A10: 7 | B10: MOSHOOD M. OLALERE | C10: 691465.02 | D10: 12 | E10: =C10*D10 -> 8297580.3 | F10: ='[5]JANUARY 2024'!$V$10*12 -> 12795.951 | I10: =E10-F10-G10-H10 -> 8284784.3 | J10: 200000 | K10: 0.2 | L10: =I10*K10 -> 1656956.9 | M10: =J10+L10 -> 1856956.9 | N10: =F10+G10+H10+M10 -> 1869752.8 | O10: =E10-N10 -> 6427827.5 | P10: =IF(O10<300000,0.07*O10,21000) -> 21000 | Q10: =IF((O10-300000)<0,0,IF((O10-300000)<300000,0.11*(O10-300000),33000)) -> 33000 | R10: =IF((O10-600000)<0,0,IF((O10-600000)<500000,0.15*(O10-600000),75000)) -> 75000 | S10: =IF((O10-1100000)<0,0,IF((O10-1100000)<500000,0.19*(O10-1100000),95000)) -> 95000 | T10: =IF((O10-1600000)<0,0,IF((O10-1600000)<1600000,0.21*(O10-1600000),336000)) -> 336000 | U10: =24%*(O10-3200000) -> 774678.59 | V10: =P10+Q10+R10+S10+T10+U10 -> 1334678.6 | W10: 12 | X10: =V10/W10 -> 111223.22 | Z10: =X10 -> 111223.22 | AA10: 111223.22 | AB10: =Z10-AA10 -> 0
A11: 8 | B11: REKIYA IBRAHIM ATTAH | C11: 641465.02 | D11: 12 | E11: =C11*D11 -> 7697580.3 | I11: =E11-F11-G11-H11 -> 7697580.3 | J11: 200000 | K11: 0.2 | L11: =I11*K11 -> 1539516.1 | M11: =J11+L11 -> 1739516.1 | N11: =F11+G11+H11+M11 -> 1739516.1 | O11: =E11-N11 -> 5958064.2 | P11: =IF(O11<300000,0.07*O11,21000) -> 21000 | Q11: =IF((O11-300000)<0,0,IF((O11-300000)<300000,0.11*(O11-300000),33000)) -> 33000 | R11: =IF((O11-600000)<0,0,IF((O11-600000)<500000,0.15*(O11-600000),75000)) -> 75000 | S11: =IF((O11-1100000)<0,0,IF((O11-1100000)<500000,0.19*(O11-1100000),95000)) -> 95000 | T11: =IF((O11-1600000)<0,0,IF((O11-1600000)<1600000,0.21*(O11-1600000),336000)) -> 336000 | U11: =24%*(O11-3200000) -> 661935.42 | V11: =P11+Q11+R11+S11+T11+U11 -> 1221935.4 | W11: 12 | X11: =V11/W11 -> 101827.95 | Z11: =X11 -> 101827.95 | AA11: 101827.95 | AB11: =Z11-AA11 -> 0
A12: 9 | B12: ANDRAWUS MUSA | C12: 497553.5 | D12: 12 | E12: =C12*D12 -> 5970642 | F12: ='[5]JANUARY 2024'!$V$13*12 -> 10052.25 | I12: =E12-F12-G12-H12 -> 5960589.8 | J12: 200000 | K12: 0.2 | L12: =I12*K12 -> 1192118 | M12: =J12+L12 -> 1392118 | N12: =F12+G12+H12+M12 -> 1402170.2 | O12: =E12-N12 -> 4568471.8 | P12: =IF(O12<300000,0.07*O12,21000) -> 21000 | Q12: =IF((O12-300000)<0,0,IF((O12-300000)<300000,0.11*(O12-300000),33000)) -> 33000 | R12: =IF((O12-600000)<0,0,IF((O12-600000)<500000,0.15*(O12-600000),75000)) -> 75000 | S12: =IF((O12-1100000)<0,0,IF((O12-1100000)<500000,0.19*(O12-1100000),95000)) -> 95000 | T12: =IF((O12-1600000)<0,0,IF((O12-1600000)<1600000,0.21*(O12-1600000),336000)) -> 336000 | U12: =24%*(O12-3200000) -> 328433.24 | V12: =P12+Q12+R12+S12+T12+U12 -> 888433.24 | W12: 12 | X12: =V12/W12 -> 74036.103 | Z12: =X12 -> 74036.103 | AA12: 74036.103 | AB12: =Z12-AA12 -> 0
A13: 10 | B13: DR FRANCIS NDUM OJIE | C13: 604729.22 | D13: 12 | E13: =C13*D13 -> 7256750.7 | F13: ='[5]JANUARY 2024'!$V$14*12 -> 9305.952 | I13: =E13-F13-G13-H13 -> 7247444.7 | J13: 200000 | K13: 0.2 | L13: =I13*K13 -> 1449488.9 | M13: =J13+L13 -> 1649488.9 | N13: =F13+G13+H13+M13 -> 1658794.9 | O13: =E13-N13 -> 5597955.8 | P13: =IF(O13<300000,0.07*O13,21000) -> 21000 | Q13: =IF((O13-300000)<0,0,IF((O13-300000)<300000,0.11*(O13-300000),33000)) -> 33000 | R13: =IF((O13-600000)<0,0,IF((O13-600000)<500000,0.15*(O13-600000),75000)) -> 75000 | S13: =IF((O13-1100000)<0,0,IF((O13-1100000)<500000,0.19*(O13-1100000),95000)) -> 95000 | T13: =IF((O13-1600000)<0,0,IF((O13-1600000)<1600000,0.21*(O13-1600000),336000)) -> 336000 | U13: =24%*(O13-3200000) -> 575509.38 | V13: =P13+Q13+R13+S13+T13+U13 -> 1135509.4 | W13: 12 | X13: =V13/W13 -> 94625.782 | Z13: =X13 -> 94625.782 | AA13: 94625.782 | AB13: =Z13-AA13 -> 0
A14: 11 | B14: ALI ABDULLAHI | C14: 343333.04 | D14: 12 | E14: =C14*D14 -> 4119996.4 | I14: =E14-F14-G14-H14 -> 4119996.4 | J14: 200000 | K14: 0.2 | L14: =I14*K14 -> 823999.28 | M14: =J14+L14 -> 1023999.3 | N14: =F14+G14+H14+M14 -> 1023999.3 | O14: =E14-N14 -> 3095997.1 | P14: =IF(O14<300000,0.07*O14,21000) -> 21000 | Q14: =IF((O14-300000)<0,0,IF((O14-300000)<300000,0.11*(O14-300000),33000)) -> 33000 | R14: =IF((O14-600000)<0,0,IF((O14-600000)<500000,0.15*(O14-600000),75000)) -> 75000 | S14: =IF((O14-1100000)<0,0,IF((O14-1100000)<500000,0.19*(O14-1100000),95000)) -> 95000 | T14: =IF((O14-1600000)<0,0,IF((O14-1600000)<1600000,0.21*(O14-1600000),336000)) -> 314159.4 | V14: =P14+Q14+R14+S14+T14+U14 -> 538159.4 | W14: 12 | X14: =V14/W14 -> 44846.617 | Z14: =X14 -> 44846.617 | AA14: 44846.617 | AB14: =Z14-AA14 -> 0
A15: 12 | B15: EMILY EKHIDE | C15: 463333.04 | D15: 12 | E15: =C15*D15 -> 5559996.4 | I15: =E15-F15-G15-H15 -> 5559996.4 | J15: 200000 | K15: 0.2 | L15: =I15*K15 -> 1111999.3 | M15: =J15+L15 -> 1311999.3 | N15: =F15+G15+H15+M15 -> 1311999.3 | O15: =E15-N15 -> 4247997.1 | P15: =IF(O15<300000,0.07*O15,21000) -> 21000 | Q15: =IF((O15-300000)<0,0,IF((O15-300000)<300000,0.11*(O15-300000),33000)) -> 33000 | R15: =IF((O15-600000)<0,0,IF((O15-600000)<500000,0.15*(O15-600000),75000)) -> 75000 | S15: =IF((O15-1100000)<0,0,IF((O15-1100000)<500000,0.19*(O15-1100000),95000)) -> 95000 | T15: =IF((O15-1600000)<0,0,IF((O15-1600000)<1600000,0.21*(O15-1600000),336000)) -> 336000 | U15: =24%*(O15-3200000) -> 251519.31 | V15: =P15+Q15+R15+S15+T15+U15 -> 811519.31 | W15: 12 | X15: =V15/W15 -> 67626.609 | Z15: =X15 -> 67626.609 | AA15: 46666.667 | AB15: =Z15-AA15 -> 20959.943
A16: 13 | B16: DORIS DAKDA AARON | C16: 547211.37 | D16: 12 | E16: =C16*D16 -> 6566536.4 | I16: =E16-F16-G16-H16 -> 6566536.4 | J16: 200000 | K16: 0.2 | L16: =I16*K16 -> 1313307.3 | M16: =J16+L16 -> 1513307.3 | N16: =F16+G16+H16+M16 -> 1513307.3 | O16: =E16-N16 -> 5053229.1 | P16: =IF(O16<300000,0.07*O16,21000) -> 21000 | Q16: =IF((O16-300000)<0,0,IF((O16-300000)<300000,0.11*(O16-300000),33000)) -> 33000 | R16: =IF((O16-600000)<0,0,IF((O16-600000)<500000,0.15*(O16-600000),75000)) -> 75000 | S16: =IF((O16-1100000)<0,0,IF((O16-1100000)<500000,0.19*(O16-1100000),95000)) -> 95000 | T16: =IF((O16-1600000)<0,0,IF((O16-1600000)<1600000,0.21*(O16-1600000),336000)) -> 336000 | U16: =24%*(O16-3200000) -> 444774.99 | V16: =P16+Q16+R16+S16+T16+U16 -> 1004775 | W16: 12 | X16: =V16/W16 -> 83731.249 | Z16: =X16 -> 83731.249 | AA16: 46666.667 | AB16: =Z16-AA16 -> 37064.583
A17: 14 | B17: ABDULSALAM S. MUSTAPHA | C17: 326663.08 | D17: 12 | E17: =C17*D17 -> 3919956.9 | I17: =E17-F17-G17-H17 -> 3919956.9 | J17: 200000 | K17: 0.2 | L17: =I17*K17 -> 783991.39 | M17: =J17+L17 -> 983991.39 | N17: =F17+G17+H17+M17 -> 983991.39 | O17: =E17-N17 -> 2935965.5 | P17: =IF(O17<300000,0.07*O17,21000) -> 21000 | Q17: =IF((O17-300000)<0,0,IF((O17-300000)<300000,0.11*(O17-300000),33000)) -> 33000 | R17: =IF((O17-600000)<0,0,IF((O17-600000)<500000,0.15*(O17-600000),75000)) -> 75000 | S17: =IF((O17-1100000)<0,0,IF((O17-1100000)<500000,0.19*(O17-1100000),95000)) -> 95000 | T17: =IF((O17-1600000)<0,0,IF((O17-1600000)<1600000,0.21*(O17-1600000),336000)) -> 280552.76 | V17: =P17+Q17+R17+S17+T17+U17 -> 504552.76 | W17: 12 | X17: =V17/W17 -> 42046.064 | Z17: =X17 -> 42046.064 | AA17: 42046.064 | AB17: =Z17-AA17 -> 0
A18: 15 | B18: PERCY TERFA GBAHABO | C18: 369177.65 | D18: 12 | E18: =C18*D18 -> 4430131.8 | I18: =E18-F18-G18-H18 -> 4430131.8 | J18: 200000 | K18: 0.2 | L18: =I18*K18 -> 886026.37 | M18: =J18+L18 -> 1086026.4 | N18: =F18+G18+H18+M18 -> 1086026.4 | O18: =E18-N18 -> 3344105.5 | P18: =IF(O18<300000,0.07*O18,21000) -> 21000 | Q18: =IF((O18-300000)<0,0,IF((O18-300000)<300000,0.11*(O18-300000),33000)) -> 33000 | R18: =IF((O18-600000)<0,0,IF((O18-600000)<500000,0.15*(O18-600000),75000)) -> 75000 | S18: =IF((O18-1100000)<0,0,IF((O18-1100000)<500000,0.19*(O18-1100000),95000)) -> 95000 | T18: =IF((O18-1600000)<0,0,IF((O18-1600000)<1600000,0.21*(O18-1600000),336000)) -> 336000 | U18: =24%*(O18-3200000) -> 34585.314 | V18: =P18+Q18+R18+S18+T18+U18 -> 594585.31 | W18: 12 | X18: =V18/W18 -> 49548.776 | Z18: =X18 -> 49548.776 | AA18: 46666.667 | AB18: =Z18-AA18 -> 2882.1095
A19: 16 | B19: HASSANA AHMED IBRAHIM | C19: 462001.06 | D19: 12 | E19: =C19*D19 -> 5544012.7 | I19: =E19-F19-G19-H19 -> 5544012.7 | J19: 200000 | K19: 0.2 | L19: =I19*K19 -> 1108802.5 | M19: =J19+L19 -> 1308802.5 | N19: =F19+G19+H19+M19 -> 1308802.5 | O19: =E19-N19 -> 4235210.2 | P19: =IF(O19<300000,0.07*O19,21000) -> 21000 | Q19: =IF((O19-300000)<0,0,IF((O19-300000)<300000,0.11*(O19-300000),33000)) -> 33000 | R19: =IF((O19-600000)<0,0,IF((O19-600000)<500000,0.15*(O19-600000),75000)) -> 75000 | S19: =IF((O19-1100000)<0,0,IF((O19-1100000)<500000,0.19*(O19-1100000),95000)) -> 95000 | T19: =IF((O19-1600000)<0,0,IF((O19-1600000)<1600000,0.21*(O19-1600000),336000)) -> 336000 | U19: =24%*(O19-3200000) -> 248450.44 | V19: =P19+Q19+R19+S19+T19+U19 -> 808450.44 | W19: 12 | X19: =V19/W19 -> 67370.87 | Z19: =X19 -> 67370.87 | AA19: 46666.667 | AB19: =Z19-AA19 -> 20704.204
A20: 17 | B20: ADUGBA RICHARD TERSEER | C20: 384537 | D20: 12 | E20: =C20*D20 -> 4614444 | I20: =E20-F20-G20-H20 -> 4614444 | J20: 200000 | K20: 0.2 | L20: =I20*K20 -> 922888.8 | M20: =J20+L20 -> 1122888.8 | N20: =F20+G20+H20+M20 -> 1122888.8 | O20: =E20-N20 -> 3491555.2 | P20: =IF(O20<300000,0.07*O20,21000) -> 21000 | Q20: =IF((O20-300000)<0,0,IF((O20-300000)<300000,0.11*(O20-300000),33000)) -> 33000 | R20: =IF((O20-600000)<0,0,IF((O20-600000)<500000,0.15*(O20-600000),75000)) -> 75000 | S20: =IF((O20-1100000)<0,0,IF((O20-1100000)<500000,0.19*(O20-1100000),95000)) -> 95000 | T20: =IF((O20-1600000)<0,0,IF((O20-1600000)<1600000,0.21*(O20-1600000),336000)) -> 336000 | U20: =24%*(O20-3200000) -> 69973.245 | V20: =P20+Q20+R20+S20+T20+U20 -> 629973.24 | W20: 12 | X20: =V20/W20 -> 52497.77 | Z20: =X20 -> 52497.77 | AA20: 52497.77 | AB20: =Z20-AA20 -> 0
A21: 18 | B21: LUCKY AGWOM | C21: 400372.08 | D21: 12 | E21: =C21*D21 -> 4804464.9 | I21: =E21-F21-G21-H21 -> 4804464.9 | J21: 200000 | K21: 0.2 | L21: =I21*K21 -> 960892.98 | M21: =J21+L21 -> 1160893 | N21: =F21+G21+H21+M21 -> 1160893 | O21: =E21-N21 -> 3643571.9 | P21: =IF(O21<300000,0.07*O21,21000) -> 21000 | Q21: =IF((O21-300000)<0,0,IF((O21-300000)<300000,0.11*(O21-300000),33000)) -> 33000 | R21: =IF((O21-600000)<0,0,IF((O21-600000)<500000,0.15*(O21-600000),75000)) -> 75000 | S21: =IF((O21-1100000)<0,0,IF((O21-1100000)<500000,0.19*(O21-1100000),95000)) -> 95000 | T21: =IF((O21-1600000)<0,0,IF((O21-1600000)<1600000,0.21*(O21-1600000),336000)) -> 336000 | U21: =24%*(O21-3200000) -> 106457.26 | V21: =P21+Q21+R21+S21+T21+U21 -> 666457.26 | W21: 12 | X21: =V21/W21 -> 55538.105 | Z21: =X21 -> 55538.105 | AA21: 46666.667 | AB21: =Z21-AA21 -> 8871.4384
A22: 19 | B22: IDRIS IBRAHIM | C22: =1015372.075-700000 -> 315372.07 | D22: 12 | E22: =C22*D22 -> 3784464.9 | I22: =E22-F22-G22-H22 -> 3784464.9 | J22: 200000 | K22: 0.2 | L22: =I22*K22 -> 756892.98 | M22: =J22+L22 -> 956892.98 | N22: =F22+G22+H22+M22 -> 956892.98 | O22: =E22-N22 -> 2827571.9 | P22: =IF(O22<300000,0.07*O22,21000) -> 21000 | Q22: =IF((O22-300000)<0,0,IF((O22-300000)<300000,0.11*(O22-300000),33000)) -> 33000 | R22: =IF((O22-600000)<0,0,IF((O22-600000)<500000,0.15*(O22-600000),75000)) -> 75000 | S22: =IF((O22-1100000)<0,0,IF((O22-1100000)<500000,0.19*(O22-1100000),95000)) -> 95000 | T22: =IF((O22-1600000)<0,0,IF((O22-1600000)<1600000,0.21*(O22-1600000),336000)) -> 257790.1 | V22: =P22+Q22+R22+S22+T22+U22 -> 481790.1 | W22: 12 | X22: =V22/W22 -> 40149.175 | Z22: =X22 -> 40149.175 | AA22: 46666.667 | AB22: =Z22-AA22 -> -6517.4914 | AC22: to be paid in February
A23: 20 | B23: FARUQ ATOFARATI | C23: 328602.08 | D23: 12 | E23: =C23*D23 -> 3943224.9 | I23: =E23-F23-G23-H23 -> 3943224.9 | J23: 200000 | K23: 0.2 | L23: =I23*K23 -> 788644.99 | M23: =J23+L23 -> 988644.99 | N23: =F23+G23+H23+M23 -> 988644.99 | O23: =E23-N23 -> 2954579.9 | P23: =IF(O23<300000,0.07*O23,21000) -> 21000 | Q23: =IF((O23-300000)<0,0,IF((O23-300000)<300000,0.11*(O23-300000),33000)) -> 33000 | R23: =IF((O23-600000)<0,0,IF((O23-600000)<500000,0.15*(O23-600000),75000)) -> 75000 | S23: =IF((O23-1100000)<0,0,IF((O23-1100000)<500000,0.19*(O23-1100000),95000)) -> 95000 | T23: =IF((O23-1600000)<0,0,IF((O23-1600000)<1600000,0.21*(O23-1600000),336000)) -> 284461.79 | V23: =P23+Q23+R23+S23+T23+U23 -> 508461.79 | W23: 12 | X23: =V23/W23 -> 42371.816 | Z23: =X23 -> 42371.816 | AA23: 42371.816 | AB23: =Z23-AA23 -> 0
A24: 21 | B24: ELIZABETH OGECHUKWU ONYEAKU | C24: 213508.01 | D24: 12 | E24: =C24*D24 -> 2562096.1 | I24: =E24-F24-G24-H24 -> 2562096.1 | J24: 200000 | K24: 0.2 | L24: =I24*K24 -> 512419.22 | M24: =J24+L24 -> 712419.22 | N24: =F24+G24+H24+M24 -> 712419.22 | O24: =E24-N24 -> 1849676.9 | P24: =IF(O24<300000,0.07*O24,21000) -> 21000 | Q24: =IF((O24-300000)<0,0,IF((O24-300000)<300000,0.11*(O24-300000),33000)) -> 33000 | R24: =IF((O24-600000)<0,0,IF((O24-600000)<500000,0.15*(O24-600000),75000)) -> 75000 | S24: =IF((O24-1100000)<0,0,IF((O24-1100000)<500000,0.19*(O24-1100000),95000)) -> 95000 | T24: =IF((O24-1600000)<0,0,IF((O24-1600000)<1600000,0.21*(O24-1600000),336000)) -> 52432.148 | V24: =P24+Q24+R24+S24+T24+U24 -> 276432.15 | W24: 12 | X24: =V24/W24 -> 23036.012 | Z24: =X24 -> 23036.012 | AA24: 23036.012 | AB24: =Z24-AA24 -> 0
A25: 22 | B25: VICTOR ASUKWO | C25: 213508.01 | D25: 12 | E25: =C25*D25 -> 2562096.1 | I25: =E25-F25-G25-H25 -> 2562096.1 | J25: 200000 | K25: 0.2 | L25: =I25*K25 -> 512419.22 | M25: =J25+L25 -> 712419.22 | N25: =F25+G25+H25+M25 -> 712419.22 | O25: =E25-N25 -> 1849676.9 | P25: =IF(O25<300000,0.07*O25,21000) -> 21000 | Q25: =IF((O25-300000)<0,0,IF((O25-300000)<300000,0.11*(O25-300000),33000)) -> 33000 | R25: =IF((O25-600000)<0,0,IF((O25-600000)<500000,0.15*(O25-600000),75000)) -> 75000 | S25: =IF((O25-1100000)<0,0,IF((O25-1100000)<500000,0.19*(O25-1100000),95000)) -> 95000 | T25: =IF((O25-1600000)<0,0,IF((O25-1600000)<1600000,0.21*(O25-1600000),336000)) -> 52432.148 | V25: =P25+Q25+R25+S25+T25+U25 -> 276432.15 | W25: 12 | X25: =V25/W25 -> 23036.012 | Z25: =X25 -> 23036.012 | AA25: 23036.012 | AB25: =Z25-AA25 -> 0
A26: 23 | B26: NNANDI LIVINUS ATURE | C26: 253508.01 | D26: 12 | E26: =C26*D26 -> 3042096.1 | I26: =E26-F26-G26-H26 -> 3042096.1 | J26: 200000 | K26: 0.2 | L26: =I26*K26 -> 608419.22 | M26: =J26+L26 -> 808419.22 | N26: =F26+G26+H26+M26 -> 808419.22 | O26: =E26-N26 -> 2233676.9 | P26: =IF(O26<300000,0.07*O26,21000) -> 21000 | Q26: =IF((O26-300000)<0,0,IF((O26-300000)<300000,0.11*(O26-300000),33000)) -> 33000 | R26: =IF((O26-600000)<0,0,IF((O26-600000)<500000,0.15*(O26-600000),75000)) -> 75000 | S26: =IF((O26-1100000)<0,0,IF((O26-1100000)<500000,0.19*(O26-1100000),95000)) -> 95000 | T26: =IF((O26-1600000)<0,0,IF((O26-1600000)<1600000,0.21*(O26-1600000),336000)) -> 133072.15 | V26: =P26+Q26+R26+S26+T26+U26 -> 357072.15 | W26: 12 | X26: =V26/W26 -> 29756.012 | Z26: =X26 -> 29756.012 | AA26: 29756.012 | AB26: =Z26-AA26 -> 0
A27: 24 | B27: ABDULRAHMAN A SULAIMAN | C27: 209356.05 | D27: 12 | E27: =C27*D27 -> 2512272.6 | I27: =E27-F27-G27-H27 -> 2512272.6 | J27: 200000 | K27: 0.2 | L27: =I27*K27 -> 502454.51 | M27: =J27+L27 -> 702454.51 | N27: =F27+G27+H27+M27 -> 702454.51 | O27: =E27-N27 -> 1809818.1 | P27: =IF(O27<300000,0.07*O27,21000) -> 21000 | Q27: =IF((O27-300000)<0,0,IF((O27-300000)<300000,0.11*(O27-300000),33000)) -> 33000 | R27: =IF((O27-600000)<0,0,IF((O27-600000)<500000,0.15*(O27-600000),75000)) -> 75000 | S27: =IF((O27-1100000)<0,0,IF((O27-1100000)<500000,0.19*(O27-1100000),95000)) -> 95000 | T27: =IF((O27-1600000)<0,0,IF((O27-1600000)<1600000,0.21*(O27-1600000),336000)) -> 44061.791 | V27: =P27+Q27+R27+S27+T27+U27 -> 268061.79 | W27: 12 | X27: =V27/W27 -> 22338.483 | Z27: =X27 -> 22338.483 | AA27: 22338.483 | AB27: =Z27-AA27 -> 0
A28: 25 | B28: DARE SHEU MAGBON | C28: 205204.08 | D28: 12 | E28: =C28*D28 -> 2462449 | I28: =E28-F28-G28-H28 -> 2462449 | J28: 200000 | K28: 0.2 | L28: =I28*K28 -> 492489.8 | M28: =J28+L28 -> 692489.8 | N28: =F28+G28+H28+M28 -> 692489.8 | O28: =E28-N28 -> 1769959.2 | P28: =IF(O28<300000,0.07*O28,21000) -> 21000 | Q28: =IF((O28-300000)<0,0,IF((O28-300000)<300000,0.11*(O28-300000),33000)) -> 33000 | R28: =IF((O28-600000)<0,0,IF((O28-600000)<500000,0.15*(O28-600000),75000)) -> 75000 | S28: =IF((O28-1100000)<0,0,IF((O28-1100000)<500000,0.19*(O28-1100000),95000)) -> 95000 | T28: =IF((O28-1600000)<0,0,IF((O28-1600000)<1600000,0.21*(O28-1600000),336000)) -> 35691.434 | V28: =P28+Q28+R28+S28+T28+U28 -> 259691.43 | W28: 12 | X28: =V28/W28 -> 21640.953 | Z28: =X28 -> 21640.953 | AA28: 21640.953 | AB28: =Z28-AA28 -> 0
A29: 26 | B29: ABUBAKAR SULAIMAN SODEEQ | C29: 205204.08 | D29: 12 | E29: =C29*D29 -> 2462449 | I29: =E29-F29-G29-H29 -> 2462449 | J29: 200000 | K29: 0.2 | L29: =I29*K29 -> 492489.8 | M29: =J29+L29 -> 692489.8 | N29: =F29+G29+H29+M29 -> 692489.8 | O29: =E29-N29 -> 1769959.2 | P29: =IF(O29<300000,0.07*O29,21000) -> 21000 | Q29: =IF((O29-300000)<0,0,IF((O29-300000)<300000,0.11*(O29-300000),33000)) -> 33000 | R29: =IF((O29-600000)<0,0,IF((O29-600000)<500000,0.15*(O29-600000),75000)) -> 75000 | S29: =IF((O29-1100000)<0,0,IF((O29-1100000)<500000,0.19*(O29-1100000),95000)) -> 95000 | T29: =IF((O29-1600000)<0,0,IF((O29-1600000)<1600000,0.21*(O29-1600000),336000)) -> 35691.434 | V29: =P29+Q29+R29+S29+T29+U29 -> 259691.43 | W29: 12 | X29: =V29/W29 -> 21640.953 | Z29: =X29 -> 21640.953 | AA29: 21640.953 | AB29: =Z29-AA29 -> 0
A30: 27 | B30: JIMOH ADEBAYO ZAKA | C30: 209356.05 | D30: 12 | E30: =C30*D30 -> 2512272.6 | I30: =E30-F30-G30-H30 -> 2512272.6 | J30: 200000 | K30: 0.2 | L30: =I30*K30 -> 502454.51 | M30: =J30+L30 -> 702454.51 | N30: =F30+G30+H30+M30 -> 702454.51 | O30: =E30-N30 -> 1809818.1 | P30: =IF(O30<300000,0.07*O30,21000) -> 21000 | Q30: =IF((O30-300000)<0,0,IF((O30-300000)<300000,0.11*(O30-300000),33000)) -> 33000 | R30: =IF((O30-600000)<0,0,IF((O30-600000)<500000,0.15*(O30-600000),75000)) -> 75000 | S30: =IF((O30-1100000)<0,0,IF((O30-1100000)<500000,0.19*(O30-1100000),95000)) -> 95000 | T30: =IF((O30-1600000)<0,0,IF((O30-1600000)<1600000,0.21*(O30-1600000),336000)) -> 44061.791 | V30: =P30+Q30+R30+S30+T30+U30 -> 268061.79 | W30: 12 | X30: =V30/W30 -> 22338.483 | Z30: =X30 -> 22338.483 | AA30: 22338.483 | AB30: =Z30-AA30 -> 0
A31: 28 | B31: MOHAMMED BELLO | C31: 180304.07 | D31: 12 | E31: =C31*D31 -> 2163648.8 | I31: =E31-F31-G31-H31 -> 2163648.8 | J31: 200000 | K31: 0.2 | L31: =I31*K31 -> 432729.76 | M31: =J31+L31 -> 632729.76 | N31: =F31+G31+H31+M31 -> 632729.76 | O31: =E31-N31 -> 1530919.1 | P31: =IF(O31<300000,0.07*O31,21000) -> 21000 | Q31: =IF((O31-300000)<0,0,IF((O31-300000)<300000,0.11*(O31-300000),33000)) -> 33000 | R31: =IF((O31-600000)<0,0,IF((O31-600000)<500000,0.15*(O31-600000),75000)) -> 75000 | S31: =IF((O31-1100000)<0,0,IF((O31-1100000)<500000,0.19*(O31-1100000),95000)) -> 81874.62 | T31: =IF((O31-1600000)<0,0,IF((O31-1600000)<1600000,0.21*(O31-1600000),336000)) -> 0 | V31: =P31+Q31+R31+S31+T31+U31 -> 210874.62 | W31: 12 | X31: =V31/W31 -> 17572.885 | Z31: =X31 -> 17572.885 | AA31: 17572.885 | AB31: =Z31-AA31 -> 0
A32: 29 | B32: HARUNA JIBRIL AMEH | C32: 173329.05 | D32: 12 | E32: =C32*D32 -> 2079948.6 | I32: =E32-F32-G32-H32 -> 2079948.6 | J32: 200000 | K32: 0.2 | L32: =I32*K32 -> 415989.72 | M32: =J32+L32 -> 615989.72 | N32: =F32+G32+H32+M32 -> 615989.72 | O32: =E32-N32 -> 1463958.9 | P32: =IF(O32<300000,0.07*O32,21000) -> 21000 | Q32: =IF((O32-300000)<0,0,IF((O32-300000)<300000,0.11*(O32-300000),33000)) -> 33000 | R32: =IF((O32-600000)<0,0,IF((O32-600000)<500000,0.15*(O32-600000),75000)) -> 75000 | S32: =IF((O32-1100000)<0,0,IF((O32-1100000)<500000,0.19*(O32-1100000),95000)) -> 69152.186 | T32: =IF((O32-1600000)<0,0,IF((O32-1600000)<1600000,0.21*(O32-1600000),336000)) -> 0 | V32: =P32+Q32+R32+S32+T32+U32 -> 198152.19 | W32: 12 | X32: =V32/W32 -> 16512.682 | Z32: =X32 -> 16512.682 | AA32: 16512.682 | AB32: =Z32-AA32 -> 0
A33: 31 | AB33: =SUM(AB6:AB32) -> 83964.785
A34: 32 | B34: INTERNAL AUDIT
B35: OSANAIYE DAVID AKINYEMI | C35: 950209.06 | D35: 12 | E35: =C35*D35 -> 11402509 | G35: =SUM(G5:G34) -> 0 | I35: =E35-F35-G35-H35 -> 11402509 | J35: 200000 | K35: 0.2 | L35: =I35*K35 -> 2280501.8 | M35: =J35+L35 -> 2480501.8 | N35: =F35+G35+H35+M35 -> 2480501.8 | O35: =E35-N35 -> 8922007 | P35: =IF(O35<300000,0.07*O35,21000) -> 21000 | Q35: =IF((O35-300000)<0,0,IF((O35-300000)<300000,0.11*(O35-300000),33000)) -> 33000 | R35: =IF((O35-600000)<0,0,IF((O35-600000)<500000,0.15*(O35-600000),75000)) -> 75000 | S35: =IF((O35-1100000)<0,0,IF((O35-1100000)<500000,0.19*(O35-1100000),95000)) -> 95000 | T35: =IF((O35-1600000)<0,0,IF((O35-1600000)<1600000,0.21*(O35-1600000),336000)) -> 336000 | U35: =24%*(O35-3200000) -> 1373281.7 | V35: =P35+Q35+R35+S35+T35+U35 -> 1933281.7 | W35: 12 | X35: =V35/W35 -> 161106.81 | Z35: =X35 -> 161106.81 | AA35: 161106.81 | AB35: =Z35-AA35 -> 0
B36: JAMILA ABDUL | C36: 176816.1 | D36: 12 | E36: =C36*D36 -> 2121793.2 | G36: =SUM(G6:G35) -> 0 | I36: =E36-F36-G36-H36 -> 2121793.2 | J36: 200000 | K36: 0.2 | L36: =I36*K36 -> 424358.64 | M36: =J36+L36 -> 624358.64 | N36: =F36+G36+H36+M36 -> 624358.64 | O36: =E36-N36 -> 1497434.6 | P36: =IF(O36<300000,0.07*O36,21000) -> 21000 | Q36: =IF((O36-300000)<0,0,IF((O36-300000)<300000,0.11*(O36-300000),33000)) -> 33000 | R36: =IF((O36-600000)<0,0,IF((O36-600000)<500000,0.15*(O36-600000),75000)) -> 75000 | S36: =IF((O36-1100000)<0,0,IF((O36-1100000)<500000,0.19*(O36-1100000),95000)) -> 75512.566 | T36: =IF((O36-1600000)<0,0,IF((O36-1600000)<1600000,0.21*(O36-1600000),336000)) -> 0 | V36: =P36+Q36+R36+S36+T36+U36 -> 204512.57 | W36: 12 | X36: =V36/W36 -> 17042.714 | Z36: =X36 -> 17042.714 | AA36: 17042.714 | AB36: =Z36-AA36 -> 0
A37: 33 | B37: IJEOMA EWELUKWA | C37: 233169.12 | D37: 12 | E37: =C37*D37 -> 2798029.4 | G37: =SUM(G7:G36) -> 0 | I37: =E37-F37-G37-H37 -> 2798029.4 | J37: 200000 | K37: 0.2 | L37: =I37*K37 -> 559605.88 | M37: =J37+L37 -> 759605.88 | N37: =F37+G37+H37+M37 -> 759605.88 | O37: =E37-N37 -> 2038423.5 | P37: =IF(O37<300000,0.07*O37,21000) -> 21000 | Q37: =IF((O37-300000)<0,0,IF((O37-300000)<300000,0.11*(O37-300000),33000)) -> 33000 | R37: =IF((O37-600000)<0,0,IF((O37-600000)<500000,0.15*(O37-600000),75000)) -> 75000 | S37: =IF((O37-1100000)<0,0,IF((O37-1100000)<500000,0.19*(O37-1100000),95000)) -> 95000 | T37: =IF((O37-1600000)<0,0,IF((O37-1600000)<1600000,0.21*(O37-1600000),336000)) -> 92068.941 | V37: =P37+Q37+R37+S37+T37+U37 -> 316068.94 | W37: 12 | X37: =V37/W37 -> 26339.078 | Z37: =X37 -> 26339.078 | AA37: 26339.078 | AB37: =Z37-AA37 -> 0
B39: LEG. SUPPORT SEVICES
A40: 35 | B40: PROF. EDOBA BRIGHT OMOREGBE | C40: 1050209.1 | D40: 12 | E40: =C40*D40 -> 12602509 | I40: =E40-F40-G40-H40 -> 12602509 | J40: 200000 | K40: 0.2 | L40: =I40*K40 -> 2520501.8 | M40: =J40+L40 -> 2720501.8 | N40: =F40+G40+H40+M40 -> 2720501.8 | O40: =E40-N40 -> 9882007 | P40: =IF(O40<300000,0.07*O40,21000) -> 21000 | Q40: =IF((O40-300000)<0,0,IF((O40-300000)<300000,0.11*(O40-300000),33000)) -> 33000 | R40: =IF((O40-600000)<0,0,IF((O40-600000)<500000,0.15*(O40-600000),75000)) -> 75000 | S40: =IF((O40-1100000)<0,0,IF((O40-1100000)<500000,0.19*(O40-1100000),95000)) -> 95000 | T40: =IF((O40-1600000)<0,0,IF((O40-1600000)<1600000,0.21*(O40-1600000),336000)) -> 336000 | U40: =0.24*(O40-3200000) -> 1603681.7 | V40: =P40+Q40+R40+S40+T40+U40 -> 2163681.7 | W40: 12 | X40: =V40/W40 -> 180306.81 | Z40: =X40 -> 180306.81 | AA40: 180306.81 | AB40: =Z40-AA40 -> 0
A41: 36 | B41: DR CLINTON JAJA | C41: 527553.5 | D41: 12 | E41: =C41*D41 -> 6330642 | I41: =E41-F41-G41-H41 -> 6330642 | J41: 200000 | K41: 0.2 | L41: =I41*K41 -> 1266128.4 | M41: =J41+L41 -> 1466128.4 | N41: =F41+G41+H41+M41 -> 1466128.4 | O41: =E41-N41 -> 4864513.6 | P41: =IF(O41<300000,0.07*O41,21000) -> 21000 | Q41: =IF((O41-300000)<0,0,IF((O41-300000)<300000,0.11*(O41-300000),33000)) -> 33000 | R41: =IF((O41-600000)<0,0,IF((O41-600000)<500000,0.15*(O41-600000),75000)) -> 75000 | S41: =IF((O41-1100000)<0,0,IF((O41-1100000)<500000,0.19*(O41-1100000),95000)) -> 95000 | T41: =IF((O41-1600000)<0,0,IF((O41-1600000)<1600000,0.21*(O41-1600000),336000)) -> 336000 | U41: =24%*(O41-3200000) -> 399483.27 | V41: =P41+Q41+R41+S41+T41+U41 -> 959483.27 | W41: 12 | X41: =V41/W41 -> 79956.939 | Z41: =X41 -> 79956.939 | AA41: 79956.939 | AB41: =Z41-AA41 -> 0
A42: 37 | B42: BETHEL UZOMA IHUGBA | C42: 617744 | D42: 12 | E42: =C42*D42 -> 7412927.9 | I42: =E42-F42-G42-H42 -> 7412927.9 | J42: 200000 | K42: 0.2 | L42: =I42*K42 -> 1482585.6 | M42: =J42+L42 -> 1682585.6 | N42: =F42+G42+H42+M42 -> 1682585.6 | O42: =E42-N42 -> 5730342.4 | P42: =IF(O42<300000,0.07*O42,21000) -> 21000 | Q42: =IF((O42-300000)<0,0,IF((O42-300000)<300000,0.11*(O42-300000),33000)) -> 33000 | R42: =IF((O42-600000)<0,0,IF((O42-600000)<500000,0.15*(O42-600000),75000)) -> 75000 | S42: =IF((O42-1100000)<0,0,IF((O42-1100000)<500000,0.19*(O42-1100000),95000)) -> 95000 | T42: =IF((O42-1600000)<0,0,IF((O42-1600000)<1600000,0.21*(O42-1600000),336000)) -> 336000 | U42: =24%*(O42-3200000) -> 607282.17 | V42: =P42+Q42+R42+S42+T42+U42 -> 1167282.2 | W42: 12 | X42: =V42/W42 -> 97273.514 | Z42: =X42 -> 97273.514 | AA42: 97273.514 | AB42: =Z42-AA42 -> 0
A43: 38 | B43: OGUCHE SAMUEL | C43: 527553.5 | D43: 12 | E43: =C43*D43 -> 6330642 | I43: =E43-F43-G43-H43 -> 6330642 | J43: 200000 | K43: 0.2 | L43: =I43*K43 -> 1266128.4 | M43: =J43+L43 -> 1466128.4 | N43: =F43+G43+H43+M43 -> 1466128.4 | O43: =E43-N43 -> 4864513.6 | P43: =IF(O43<300000,0.07*O43,21000) -> 21000 | Q43: =IF((O43-300000)<0,0,IF((O43-300000)<300000,0.11*(O43-300000),33000)) -> 33000 | R43: =IF((O43-600000)<0,0,IF((O43-600000)<500000,0.15*(O43-600000),75000)) -> 75000 | S43: =IF((O43-1100000)<0,0,IF((O43-1100000)<500000,0.19*(O43-1100000),95000)) -> 95000 | T43: =IF((O43-1600000)<0,0,IF((O43-1600000)<1600000,0.21*(O43-1600000),336000)) -> 336000 | U43: =24%*(O43-3200000) -> 399483.27 | V43: =P43+Q43+R43+S43+T43+U43 -> 959483.27 | W43: 12 | X43: =V43/W43 -> 79956.939 | Z43: =X43 -> 79956.939 | AA43: 79956.939 | AB43: =Z43-AA43 -> 0
A44: 39 | B44: IBRAHIM USMAN | C44: 527553.5 | D44: 12 | E44: =C44*D44 -> 6330642 | F44: ='[5]JANUARY 2024'!$V$47*12 -> 10052.25 | I44: =E44-F44-G44-H44 -> 6320589.8 | J44: 200000 | K44: 0.2 | L44: =I44*K44 -> 1264118 | M44: =J44+L44 -> 1464118 | N44: =F44+G44+H44+M44 -> 1474170.2 | O44: =E44-N44 -> 4856471.8 | P44: =IF(O44<300000,0.07*O44,21000) -> 21000 | Q44: =IF((O44-300000)<0,0,IF((O44-300000)<300000,0.11*(O44-300000),33000)) -> 33000 | R44: =IF((O44-600000)<0,0,IF((O44-600000)<500000,0.15*(O44-600000),75000)) -> 75000 | S44: =IF((O44-1100000)<0,0,IF((O44-1100000)<500000,0.19*(O44-1100000),95000)) -> 95000 | T44: =IF((O44-1600000)<0,0,IF((O44-1600000)<1600000,0.21*(O44-1600000),336000)) -> 336000 | U44: =24%*(O44-3200000) -> 397553.24 | V44: =P44+Q44+R44+S44+T44+U44 -> 957553.24 | W44: 12 | X44: =V44/W44 -> 79796.103 | Z44: =X44 -> 79796.103 | AA44: 79796.103 | AB44: =Z44-AA44 -> 0
A45: 40 | B45: DR MOHAMMED O. AMALI | C45: 504720.05 | D45: 12 | E45: =C45*D45 -> 6056640.6 | I45: =E45-F45-G45-H45 -> 6056640.6 | J45: 200000 | K45: 0.2 | L45: =I45*K45 -> 1211328.1 | M45: =J45+L45 -> 1411328.1 | N45: =F45+G45+H45+M45 -> 1411328.1 | O45: =E45-N45 -> 4645312.5 | P45: =IF(O45<300000,0.07*O45,21000) -> 21000 | Q45: =IF((O45-300000)<0,0,IF((O45-300000)<300000,0.11*(O45-300000),33000)) -> 33000 | R45: =IF((O45-600000)<0,0,IF((O45-600000)<500000,0.15*(O45-600000),75000)) -> 75000 | S45: =IF((O45-1100000)<0,0,IF((O45-1100000)<500000,0.19*(O45-1100000),95000)) -> 95000 | T45: =IF((O45-1600000)<0,0,IF((O45-1600000)<1600000,0.21*(O45-1600000),336000)) -> 336000 | U45: =24%*(O45-3200000) -> 346874.99 | V45: =P45+Q45+R45+S45+T45+U45 -> 906874.99 | W45: 12 | X45: =V45/W45 -> 75572.916 | Z45: =X45 -> 75572.916 | AA45: 75572.916 | AB45: =Z45-AA45 -> 0
A46: 41 | B46: YAHAYA SHAMSU | C46: 413333.04 | D46: 12 | E46: =C46*D46 -> 4959996.4 | I46: =E46-F46-G46-H46 -> 4959996.4 | J46: 200000 | K46: 0.2 | L46: =I46*K46 -> 991999.28 | M46: =J46+L46 -> 1191999.3 | N46: =F46+G46+H46+M46 -> 1191999.3 | O46: =E46-N46 -> 3767997.1 | P46: =IF(O46<300000,0.07*O46,21000) -> 21000 | Q46: =IF((O46-300000)<0,0,IF((O46-300000)<300000,0.11*(O46-300000),33000)) -> 33000 | R46: =IF((O46-600000)<0,0,IF((O46-600000)<500000,0.15*(O46-600000),75000)) -> 75000 | S46: =IF((O46-1100000)<0,0,IF((O46-1100000)<500000,0.19*(O46-1100000),95000)) -> 95000 | T46: =IF((O46-1600000)<0,0,IF((O46-1600000)<1600000,0.21*(O46-1600000),336000)) -> 336000 | U46: =24%*(O46-3200000) -> 136319.31 | V46: =P46+Q46+R46+S46+T46+U46 -> 696319.31 | W46: 12 | X46: =V46/W46 -> 58026.609 | Z46: =X46 -> 58026.609 | AA46: 58026.609 | AB46: =Z46-AA46 -> 0
A47: 42 | B47: BILKIS S. LAWAL-GAMBARI | C47: 273169.12 | D47: 12 | E47: =C47*D47 -> 3278029.4 | I47: =E47-F47-G47-H47 -> 3278029.4 | J47: 200000 | K47: 0.2 | L47: =I47*K47 -> 655605.88 | M47: =J47+L47 -> 855605.88 | N47: =F47+G47+H47+M47 -> 855605.88 | O47: =E47-N47 -> 2422423.5 | P47: =IF(O47<300000,0.07*O47,21000) -> 21000 | Q47: =IF((O47-300000)<0,0,IF((O47-300000)<300000,0.11*(O47-300000),33000)) -> 33000 | R47: =IF((O47-600000)<0,0,IF((O47-600000)<500000,0.15*(O47-600000),75000)) -> 75000 | S47: =IF((O47-1100000)<0,0,IF((O47-1100000)<500000,0.19*(O47-1100000),95000)) -> 95000 | T47: =IF((O47-1600000)<0,0,IF((O47-1600000)<1600000,0.21*(O47-1600000),336000)) -> 172708.94 | V47: =P47+Q47+R47+S47+T47+U47 -> 396708.94 | W47: 12 | X47: =V47/W47 -> 33059.078 | Z47: =X47 -> 33059.078 | AA47: 33059.078 | AB47: =Z47-AA47 -> 0
A48: 43 | B48: ZAINAB AKINDE | C48: 249356.05 | D48: 12 | E48: =C48*D48 -> 2992272.6 | I48: =E48-F48-G48-H48 -> 2992272.6 | J48: 200000 | K48: 0.2 | L48: =I48*K48 -> 598454.51 | M48: =J48+L48 -> 798454.51 | N48: =F48+G48+H48+M48 -> 798454.51 | O48: =E48-N48 -> 2193818.1 | P48: =IF(O48<300000,0.07*O48,21000) -> 21000 | Q48: =IF((O48-300000)<0,0,IF((O48-300000)<300000,0.11*(O48-300000),33000)) -> 33000 | R48: =IF((O48-600000)<0,0,IF((O48-600000)<500000,0.15*(O48-600000),75000)) -> 75000 | S48: =IF((O48-1100000)<0,0,IF((O48-1100000)<500000,0.19*(O48-1100000),95000)) -> 95000 | T48: =IF((O48-1600000)<0,0,IF((O48-1600000)<1600000,0.21*(O48-1600000),336000)) -> 124701.79 | V48: =P48+Q48+R48+S48+T48+U48 -> 348701.79 | W48: 12 | X48: =V48/W48 -> 29058.483 | Z48: =X48 -> 29058.483 | AA48: 29058.483 | AB48: =Z48-AA48 -> 0
A49: 44 | B49: ABDULLAHI AHMAD USMAN | C49: 249356.05 | D49: 12 | E49: =C49*D49 -> 2992272.6 | I49: =E49-F49-G49-H49 -> 2992272.6 | J49: 200000 | K49: 0.2 | L49: =I49*K49 -> 598454.51 | M49: =J49+L49 -> 798454.51 | N49: =F49+G49+H49+M49 -> 798454.51 | O49: =E49-N49 -> 2193818.1 | P49: =IF(O49<300000,0.07*O49,21000) -> 21000 | Q49: =IF((O49-300000)<0,0,IF((O49-300000)<300000,0.11*(O49-300000),33000)) -> 33000 | R49: =IF((O49-600000)<0,0,IF((O49-600000)<500000,0.15*(O49-600000),75000)) -> 75000 | S49: =IF((O49-1100000)<0,0,IF((O49-1100000)<500000,0.19*(O49-1100000),95000)) -> 95000 | T49: =IF((O49-1600000)<0,0,IF((O49-1600000)<1600000,0.21*(O49-1600000),336000)) -> 124701.79 | V49: =P49+Q49+R49+S49+T49+U49 -> 348701.79 | W49: 12 | X49: 28360.953 | Z49: =X49 -> 28360.953 | AA49: 28360.953 | AB49: =Z49-AA49 -> 0
A50: 45 | B50: GUNAT NANSAK MARK | C50: 249356.05 | D50: 12 | E50: =C50*D50 -> 2992272.6 | I50: =E50-F50-G50-H50 -> 2992272.6 | J50: 200000 | K50: 0.2 | L50: =I50*K50 -> 598454.51 | M50: =J50+L50 -> 798454.51 | N50: =F50+G50+H50+M50 -> 798454.51 | O50: =E50-N50 -> 2193818.1 | P50: =IF(O50<300000,0.07*O50,21000) -> 21000 | Q50: =IF((O50-300000)<0,0,IF((O50-300000)<300000,0.11*(O50-300000),33000)) -> 33000 | R50: =IF((O50-600000)<0,0,IF((O50-600000)<500000,0.15*(O50-600000),75000)) -> 75000 | S50: =IF((O50-1100000)<0,0,IF((O50-1100000)<500000,0.19*(O50-1100000),95000)) -> 95000 | T50: =IF((O50-1600000)<0,0,IF((O50-1600000)<1600000,0.21*(O50-1600000),336000)) -> 124701.79 | V50: =P50+Q50+R50+S50+T50+U50 -> 348701.79 | W50: 12 | X50: =V50/W50 -> 29058.483 | Z50: =X50 -> 29058.483 | AA50: 29058.483 | AB50: =Z50-AA50 -> 0
B52: LEGAL SERVICES
A53: 47 | B53: DR SHUIBU DANWANKA | C53: 1050209.1 | D53: 12 | E53: =C53*D53 -> 12602509 | I53: =E53-F53-G53-H53 -> 12602509 | J53: 200000 | K53: 0.2 | L53: =I53*K53 -> 2520501.8 | M53: =J53+L53 -> 2720501.8 | N53: =F53+G53+H53+M53 -> 2720501.8 | O53: =E53-N53 -> 9882007 | P53: =IF(O53<300000,0.07*O53,21000) -> 21000 | Q53: =IF((O53-300000)<0,0,IF((O53-300000)<300000,0.11*(O53-300000),33000)) -> 33000 | R53: =IF((O53-600000)<0,0,IF((O53-600000)<500000,0.15*(O53-600000),75000)) -> 75000 | S53: =IF((O53-1100000)<0,0,IF((O53-1100000)<500000,0.19*(O53-1100000),95000)) -> 95000 | T53: =IF((O53-1600000)<0,0,IF((O53-1600000)<1600000,0.21*(O53-1600000),336000)) -> 336000 | U53: =24%*(O53-3200000) -> 1603681.7 | V53: =P53+Q53+R53+S53+T53+U53 -> 2163681.7 | W53: 12 | X53: =V53/W53 -> 180306.81 | Z53: =X53 -> 180306.81 | AA53: 180306.81 | AB53: =Z53-AA53 -> 0
A54: 48 | B54: ABDULSALAM BAKO | C54: 447553.5 | D54: 12 | E54: =C54*D54 -> 5370642 | I54: =E54-F54-G54-H54 -> 5370642 | J54: 200000 | K54: 0.2 | L54: =I54*K54 -> 1074128.4 | M54: =J54+L54 -> 1274128.4 | N54: =F54+G54+H54+M54 -> 1274128.4 | O54: =E54-N54 -> 4096513.6 | P54: =IF(O54<300000,0.07*O54,21000) -> 21000 | Q54: =IF((O54-300000)<0,0,IF((O54-300000)<300000,0.11*(O54-300000),33000)) -> 33000 | R54: =IF((O54-600000)<0,0,IF((O54-600000)<500000,0.15*(O54-600000),75000)) -> 75000 | S54: =IF((O54-1100000)<0,0,IF((O54-1100000)<500000,0.19*(O54-1100000),95000)) -> 95000 | T54: =IF((O54-1600000)<0,0,IF((O54-1600000)<1600000,0.21*(O54-1600000),336000)) -> 336000 | U54: =24%*(O54-3200000) -> 215163.27 | V54: =P54+Q54+R54+S54+T54+U54 -> 775163.27 | W54: 12 | X54: =V54/W54 -> 64596.939 | Z54: =X54 -> 64596.939 | AA54: 64596.939 | AB54: =Z54-AA54 -> 0
A56: 49 | B56: DEMOCRACY & GOVERNANCE
A57: 50 | B57: DR. ADEWALE ADEREMI | C57: 1050209.1 | D57: 12 | E57: =C57*D57 -> 12602509 | I57: =E57-F57-G57-H57 -> 12602509 | J57: 200000 | K57: 0.2 | L57: =I57*K57 -> 2520501.8 | M57: =J57+L57 -> 2720501.8 | N57: =F57+G57+H57+M57 -> 2720501.8 | O57: =E57-N57 -> 9882007 | P57: =IF(O57<300000,0.07*O57,21000) -> 21000 | Q57: =IF((O57-300000)<0,0,IF((O57-300000)<300000,0.11*(O57-300000),33000)) -> 33000 | R57: =IF((O57-600000)<0,0,IF((O57-600000)<500000,0.15*(O57-600000),75000)) -> 75000 | S57: =IF((O57-1100000)<0,0,IF((O57-1100000)<500000,0.19*(O57-1100000),95000)) -> 95000 | T57: =IF((O57-1600000)<0,0,IF((O57-1600000)<1600000,0.21*(O57-1600000),336000)) -> 336000 | U57: =24%*(O57-3200000) -> 1603681.7 | V57: =P57+Q57+R57+S57+T57+U57 -> 2163681.7 | W57: 12 | X57: =V57/W57 -> 180306.81 | Z57: =X57 -> 180306.81 | AA57: 180306.81 | AB57: =Z57-AA57 -> 0
A58: 51 | B58: NDANUSA MOHAMMED MANZUMA | C58: 516137.05 | D58: 12 | E58: =C58*D58 -> 6193644.6 | I58: =E58-F58-G58-H58 -> 6193644.6 | J58: 200000 | K58: 0.2 | L58: =I58*K58 -> 1238728.9 | M58: =J58+L58 -> 1438728.9 | N58: =F58+G58+H58+M58 -> 1438728.9 | O58: =E58-N58 -> 4754915.7 | P58: =IF(O58<300000,0.07*O58,21000) -> 21000 | Q58: =IF((O58-300000)<0,0,IF((O58-300000)<300000,0.11*(O58-300000),33000)) -> 33000 | R58: =IF((O58-600000)<0,0,IF((O58-600000)<500000,0.15*(O58-600000),75000)) -> 75000 | S58: =IF((O58-1100000)<0,0,IF((O58-1100000)<500000,0.19*(O58-1100000),95000)) -> 95000 | T58: =IF((O58-1600000)<0,0,IF((O58-1600000)<1600000,0.21*(O58-1600000),336000)) -> 336000 | U58: =24%*(O58-3200000) -> 373179.76 | V58: =P58+Q58+R58+S58+T58+U58 -> 933179.76 | W58: 12 | X58: =V58/W58 -> 77764.98 | Z58: =X58 -> 77764.98 | AA58: 77764.98 | AB58: =Z58-AA58 -> 0
