Workbook

Sheet NOVEMBER 2024
A1: NATIONAL INSTITUTE FOR LEGISLATIVE AND DEMOCRATIC STUDIES
A2: STAFF PAYROLL FOR THE MONTH OF NOVEMBER, 2024
E3: ='[1]FEB 08'!E11/'[1]FEB 08'!M11 -> #REF!
B4: STAFF NAME | C4: DESIGNATION | D4: GRADE LEVEL | E4: BASIC SALARY | F4: ALLCE/ AREARS | G4: ALLOWANCE | H4: ALLOWANCE | I4: DUTY ALLCE | J4: GROSS SALARY | K4: AUCTION | L4: COOP CONTR/SPEC SAVINGS | M4: COOP. LOAN RECOVERY | N4: NHF DED. | O4: PAYE | P4: EMPLOYEE PENSIONS | Q4: TOTAL DEDUCTION | R4: OCTOBER, 2024 | S4: NOVEMBER, 2024
E5: N | F5: N | G5: N | H5: N | I5: N | J5: N | K5: N | L5: N | M5: N | N5: N | O5: N | P5: N | Q5: N | R5: N | S5: N
A6: S/N | B6: DG'S OFFICE
A7: 1 | B7: PROF. ABUBAKAR O. SULAIMAN | C7: DIRECTOR GENERAL | D7: CONSOL | E7: 1659751.2 | G7: =250000 -> 250000 | I7: 25235 | J7: =E7+F7+G7+H7+I7 -> 1934986.2 | O7: 350184.01 | Q7: =O7+N7+M7+L7+K7+P7 -> 350184.01 | R7: 1584802.2 | S7: =J7-Q7 -> 1584802.2
A8: 2 | B8: RAHEEM USMAN AYIGORO | C8: SA-INFRASTRUCTURE | D8: 16 (9) | E8: 762373.17 | H8: =90000 -> 90000 | I8: =100000 -> 100000 | J8: =E8+F8+G8+H8+I8 -> 952373.17 | L8: =250000 -> 250000 | O8: ='Additional Leg Duty Allowance'!P7 -> 149812.26 | P8: 60989.853 | Q8: =O8+N8+M8+L8+K8+P8 -> 460802.12 | R8: 491571.05 | S8: =J8-Q8 -> 491571.05
A9: 3 | B9: MARIAM MOHAMMED BELLO | C9: SA- SPECIAL DUTIES | D9: 16 (9) | E9: 762373.17 | H9: =90000 -> 90000 | I9: =200000+100000 -> 300000 | J9: =E9+F9+G9+H9+I9 -> 1152373.2 | O9: ='Additional Leg Duty Allowance'!P8 -> 199922.31 | Q9: =O9+N9+M9+L9+K9+P9 -> 199922.31 | R9: 952450.85 | S9: =J9-Q9 -> 952450.85
A10: 4 | B10: DR IKEME ARTHUR J.O | C10: DEPUTY DIRECTOR, M&E | D10: 16 (9) | E10: 762373.17 | G10: 180000 | I10: 0 | J10: =E10+F10+G10+H10+I10 -> 942373.17 | L10: =50000 -> 50000 | M10: 0 | N10: 10293.398 | O10: 147687.53 | P10: 60989.853 | Q10: =O10+N10+M10+L10+K10+P10 -> 268970.78 | R10: 673402.39 | S10: =J10-Q10 -> 673402.39
A11: 5 | B11: MOSHOOD M. OLALERE | C11: DEPUTY DIR. GENERAL SERVICE | D11: 16 (9) | E11: 762373.17 | H11: =80000+10000 -> 90000 | I11: =150000+100000 -> 250000 | J11: =E11+F11+G11+H11+I11 -> 1102373.2 | L11: =20000+60000 -> 80000 | M11: ='[2]OCTOBER 2023 '!$D$193 -> 230499.8 | N11: 10293.398 | O11: ='Additional Leg Duty Allowance'!P9 -> 178407.53 | P11: 60989.853 | Q11: =O11+N11+M11+L11+K11+P11 -> 560190.58 | R11: 542182.59 | S11: =J11-Q11 -> 542182.59
A12: 6 | B12: ANDRAWUS MUSA | C12: ASST. DIRECTOR, STORES | D12: 15(9) | E12: 620675.58 | H12: =80000 -> 80000 | I12: 50000 | J12: =E12+F12+G12+H12+I12 -> 750675.58 | L12: =50000-40000 -> 10000 | M12: =90000+110000 -> 200000 | N12: 8380.2271 | O12: 113101.97 | P12: 49654.047 | Q12: =O12+N12+M12+L12+K12+P12 -> 381136.24 | R12: 369539.34 | S12: =J12-Q12 -> 369539.34
A13: 7 | B13: DR FRANCIS NDUM OJIE | C13: AD, TRAINING & IC./SA TO DG | D13: 15(7) | E13: 582118.08 | G13: 160000 | I13: =100000+100000 -> 200000 | J13: =E13+F13+G13+H13+I13 -> 942118.08 | N13: 7859.6313 | O13: ='Additional Leg Duty Allowance'!P12 -> 150463.11 | P13: 46569.447 | Q13: =O13+N13+M13+L13+K13+P13 -> 204892.19 | R13: 737225.9 | S13: =J13-Q13 -> 737225.9
A14: 8 | B14: ALI ABDULLAHI | C14: CHIEF ICT OFFICER | D14: 14(11) | E14: 484373.75 | H14: =70000 -> 70000 | I14: =0 -> 0 | J14: =E14+F14+G14+H14+I14 -> 554373.75 | O14: 77666.446 | P14: 38749.9 | Q14: =O14+N14+M14+L14+K14+P14 -> 116416.35 | R14: 437957.4 | S14: =J14-Q14 -> 437957.4
A15: 9 | B15: EMILY EKHIDE | C15: SENIOR RESEARCH FELLOW | D15: 15(7) | E15: 582118.08 | F15: ='2024 Promotion Arrears'!J7 -> 526480 | G15: 160000 | I15: =50000+100000 -> 150000 | J15: =E15+F15+G15+H15+I15 -> 1418598.1 | L15: =50000 -> 50000 | O15: =' New Grade PAYE '!AB6 -> 211821.48 | P15: =46569.45 -> 46569.45 | Q15: =O15+N15+M15+L15+K15+P15 -> 308390.93 | R15: 574602.73 | S15: =J15-Q15 -> 1110207.2
A16: 10 | B16: DORIS DAKDA AARON | C16: RESEARCH FELLOW I | D16: 14(8) | E16: 442746.5 | G16: =140000 -> 140000 | I16: =150000+100000 -> 250000 | J16: =E16+F16+G16+H16+I16 -> 832746.5 | L16: 70000 | M16: 175000 | O16: ='Additional Leg Duty Allowance'!P13 -> 131753.41 | P16: 35419.72 | Q16: =O16+N16+M16+L16+K16+P16 -> 412173.13 | R16: 420573.37 | S16: =J16-Q16 -> 420573.37
A17: 11 | B17: ABDULSALAM S. MUSTAPHA | C17: ASST. DIRECTOR ICT | D17: 15(7) | E17: 582118.08 | F17: ='2024 Promotion Arrears'!J6 -> 150313.08 | H17: 80000 | J17: =E17+F17+G17+H17+I17 -> 812431.16 | O17: =' New Grade PAYE '!AB5 -> 103801.22 | P17: =46569.45 -> 46569.45 | Q17: =O17+N17+M17+L17+K17+P17 -> 150370.67 | R17: 406313.44 | S17: =J17-Q17 -> 662060.49
A18: 12 | B18: PERCY TERFA GBAHABO | C18: HEAD, NILDS LIAISON OFFICE | D18: 13(10) | E18: 428915.92 | G18: =120000 -> 120000 | I18: 0 | J18: =E18+F18+G18+H18+I18 -> 548915.92 | L18: =50000 -> 50000 | M18: 105000 | O18: 77470.374 | P18: 34313.273 | Q18: =O18+N18+M18+L18+K18+P18 -> 266783.65 | R18: 282132.27 | S18: =J18-Q18 -> 282132.27
A19: 13 | B19: HASSANA AHMED IBRAHIM | C19: PA- TO DG | D19: 13 (9) | E19: 416026.92 | G19: =120000 -> 120000 | I19: =100000+100000 -> 200000 | J19: =E19+F19+G19+H19+I19 -> 736026.92 | L19: =30000-20000 -> 10000 | M19: =95833.33 -> 95833.33 | N19: 5607.1771 | O19: ='Additional Leg Duty Allowance'!P14 -> 113474.9 | P19: 33282.153 | Q19: =O19+N19+M19+L19+K19+P19 -> 258197.56 | R19: 477829.35 | S19: =J19-Q19 -> 477829.35
A20: 14 | B20: IKIP LEBO | C20: ASST CHIEF PROC. OFFICER | D20: 13 (7) | E20: ='[3]Annual & Monthly'!$H$40 -> 390248.92 | H20: 70000 | J20: =E20+F20+G20+H20+I20 -> 460248.92 | L20: 50000 | O20: =61040.2353066666 -> 61040.235 | P20: =390248.916666667*0.08 -> 31219.913 | Q20: =O20+N20+M20+L20+K20+P20 -> 142260.15 | R20: 317988.77 | S20: =J20-Q20 -> 317988.77
A21: 15 | B21: ALABI ADESINA MUHYDEEN | C21: HEAD, NILDS LIAISON OFFICE | D21: 13 (7) | E21: 390248.92 | G21: 120000 | J21: =E21+F21+G21+H21+I21 -> 510248.92 | O21: =70640.2353066667 -> 70640.235 | P21: 31219.913 | Q21: =O21+N21+M21+L21+K21+P21 -> 101860.15 | R21: 408388.77 | S21: =J21-Q21 -> 408388.77
A22: 16 | B22: ADUGBA RICHARD TERSEER | C22: PRINCIPAL INFO. OFFICER | D22: 12(9) | E22: 377895.17 | H22: =60000 -> 60000 | I22: =100000+50000 -> 150000 | J22: =E22+F22+G22+H22+I22 -> 587895.17 | L22: =20000+30000 -> 50000 | M22: =111833.33 -> 111833.33 | O22: 82601.205 | P22: 30231.613 | Q22: =O22+N22+M22+L22+K22+P22 -> 274666.15 | R22: 313229.02 | S22: =J22-Q22 -> 313229.02
A23: 17 | B23: LUCKY AGWOM | C23: RESEARCH ASSISTANT | D23: 12(7) | E23: 353512.5 | G23: =100000 -> 100000 | I23: =100000+100000 -> 200000 | J23: =E23+F23+G23+H23+I23 -> 653512.5 | L23: =50000+100000 -> 150000 | O23: ='Additional Leg Duty Allowance'!P15 -> 98711.115 | P23: 28281 | Q23: =O23+N23+M23+L23+K23+P23 -> 276992.11 | R23: 376520.39 | S23: =J23-Q23 -> 376520.39
A24: 18 | B24: IDRIS IBRAHIM | C24: PRINCIPAL RESEARCH OFFICER | D24: 12(7) | E24: 353512.5 | G24: 110000 | I24: 0 | J24: =E24+F24+G24+H24+I24 -> 463512.5 | L24: 0 | O24: 62231.115 | P24: 28281 | Q24: =O24+N24+M24+L24+K24+P24 -> 90512.115 | R24: 373000.39 | S24: =J24-Q24 -> 373000.39
A25: 19 | B25: FARUQ ATOFARATI | C25: PA (SPECIAL DUTIES) TO DG | D25: 10(7) | E25: 293029.67 | H25: =50000+10000 -> 60000 | I25: =100000+100000 -> 200000 | J25: =E25+F25+G25+H25+I25 -> 553029.67 | L25: 130000 | O25: ='Additional Leg Duty Allowance'!P16 -> 80347.427 | P25: 23442.373 | Q25: =O25+N25+M25+L25+K25+P25 -> 233789.8 | R25: 319239.87 | S25: =J25-Q25 -> 319239.87
A26: 20 | B26: RASHEEDAT DAIBU | C26: SENIOR INFO. OFFICER | D26: 10(7) | E26: 293029.67 | H26: 60000 | J26: =E26+F26+G26+H26+I26 -> 353029.67 | L26: 40000 | O26: =42537.3319466667 -> 42537.332 | P26: 23442.373 | Q26: =O26+N26+M26+L26+K26+P26 -> 105979.71 | R26: 247049.96 | S26: =J26-Q26 -> 247049.96
A27: 21 | B27: ELIZABETH OGECHUKWU ONYEAKU | C27: ICT OFFICER | D27: 9(9) | E27: 270481.67 | H27: =50000+10000 -> 60000 | J27: =E27+F27+G27+H27+I27 -> 330481.67 | L27: 10000 | O27: 39052.313 | P27: 21638.533 | Q27: =O27+N27+M27+L27+K27+P27 -> 70690.846 | R27: 259790.82 | S27: =J27-Q27 -> 259790.82
A28: 22 | B28: VICTOR ASUKWO | C28: ICT OFFICER | D28: 9(9) | E28: 270481.67 | H28: =50000+10000 -> 60000 | J28: =E28+F28+G28+H28+I28 -> 330481.67 | O28: 39052.313 | P28: 21638.533 | Q28: =O28+N28+M28+L28+K28+P28 -> 60690.846 | R28: 269790.82 | S28: =J28-Q28 -> 269790.82
A29: 23 | B29: NNANDI LIVINUS ATURE | C29: RESEARCH ASSISTANT | D29: 9(9) | E29: 270481.67 | G29: =100000 -> 100000 | J29: =E29+F29+G29+H29+I29 -> 370481.67 | L29: =10000 -> 10000 | M29: =95833.33 -> 95833.33 | O29: 45772.313 | P29: 21638.533 | Q29: =O29+N29+M29+L29+K29+P29 -> 173244.18 | R29: 197237.49 | S29: =J29-Q29 -> 197237.49
A30: 24 | B30: ABDULRAHMAN A SULAIMAN | C30: STORE OFFICER | D30: 9(8) | E30: 263165.33 | H30: =60000 -> 60000 | J30: =E30+F30+G30+H30+I30 -> 323165.33 | L30: =20000 -> 20000 | M30: =17500 -> 17500 | O30: 37921.501 | P30: 21053.227 | Q30: =O30+N30+M30+L30+K30+P30 -> 96474.727 | R30: 226690.61 | S30: =J30-Q30 -> 226690.61
A31: 25 | B31: DARE SHEU MAGBON | C31: ADMINISTRATION OFFICER | D31: 9(7) | E31: 255849 | H31: =60000 -> 60000 | J31: =E31+F31+G31+H31+I31 -> 315849 | L31: =30000+20000 -> 50000 | M31: 0 | O31: 36790.688 | P31: 20467.92 | Q31: =O31+N31+M31+L31+K31+P31 -> 107258.61 | R31: 208590.39 | S31: =J31-Q31 -> 208590.39
A32: 26 | B32: ABUBAKAR SULAIMAN SODEEQ | C32: ADMINISTRATION OFFICER | D32: 9(7) | E32: 255849 | H32: =60000 -> 60000 | J32: =E32+F32+G32+H32+I32 -> 315849 | M32: 0 | O32: 36790.688 | P32: 20467.92 | Q32: =O32+N32+M32+L32+K32+P32 -> 57258.608 | R32: 258590.39 | S32: =J32-Q32 -> 258590.39
A33: 27 | B33: JIMOH ADEBAYO ZAKA | C33: ASST. OFFICER/COMM | D33: 9(9) | E33: 270481.67 | H33: =60000 -> 60000 | J33: =E33+F33+G33+H33+I33 -> 330481.67 | L33: =10000 -> 10000 | M33: 161429.76 | N33: =3653.5 -> 3653.5 | O33: 39052.313 | P33: 21638.533 | Q33: =O33+N33+M33+L33+K33+P33 -> 235774.11 | R33: 94707.56 | S33: =J33-Q33 -> 94707.56
A34: 28 | B34: ABDULMUSHIN TAWFIQ LADAN | C34: ICT OFFICER | D34: 9(7) | E34: 255849 | H34: =60000 -> 60000 | J34: =E34+F34+G34+H34+I34 -> 315849 | M34: 0 | O34: =36790.6881066667 -> 36790.688 | P34: 20467.92 | Q34: =O34+N34+M34+L34+K34+P34 -> 57258.608 | R34: 258590.39 | S34: =J34-Q34 -> 258590.39
A35: 29 | B35: MOHAMMED BELLO | C35: PROTOCOL ASSISTANT | D35: 9(7) | E35: 255849 | H35: =60000 -> 60000 | J35: =E35+F35+G35+H35+I35 -> 315849 | L35: =0 -> 0 | O35: 36790.688 | P35: 20467.92 | Q35: =O35+N35+M35+L35+K35+P35 -> 57258.608 | R35: 614264.76 | S35: =J35-Q35 -> 258590.39
A36: 30 | B36: HARUNA JIBRIL AMEH | C36: ASST. ADMIN. OFFICER | D36: 8(8) | E36: 224459.75 | H36: 50000 | J36: =E36+F36+G36+H36+I36 -> 274459.75 | L36: 20000 | M36: 0 | O36: 30259.166 | P36: 17956.78 | Q36: =O36+N36+M36+L36+K36+P36 -> 68215.946 | R36: 206243.8 | S36: =J36-Q36 -> 206243.8
A37: 31 | B37: RAMATU IBRAHIM ABDULRAHEEM | C37: INFORMATION OFFICER | D37: 8(7) | E37: 218287.58 | H37: 50000 | J37: =E37+F37+G37+H37+I37 -> 268287.58 | L37: 50000 | M37: 45833.33 | O37: =29305.1955466667 -> 29305.196 | P37: =218287.583333333*0.08 -> 17463.007 | Q37: =O37+N37+M37+L37+K37+P37 -> 142601.53 | R37: 125686.05 | S37: =J37-Q37 -> 125686.05
B38: TOTAL | C38: 31 | E38: =SUM(E7:E37) -> 14111049 | F38: =SUM(F7:F37) -> 676793.08 | G38: =SUM(G7:G37) -> 1560000 | H38: =SUM(H7:H37) -> 1330000 | I38: =SUM(I7:I37) -> 2075235 | J38: =SUM(J7:J37) -> 19753077 | K38: =SUM(K7:K37) -> 0 | L38: =SUM(L7:L37) -> 1160000 | ... Q38: =SUM(Q7:Q37) -> 6291217.3 | R38: 13026183 | S38: =SUM(S7:S37) -> 13461860
B40: INTERNAL AUDIT
A41: 1 | B41: OSANAIYE DAVID AKINYEMI | C41: DIRECTOR INTERNAL AUDIT | D41: 17(9) | E41: 1435720 | H41: =100000 -> 100000 | J41: =SUM(E41:I41) -> 1535720 | K41: ='NOVEMBER 2024'!F207 -> 0 | L41: =200000+200000 -> 400000 | M41: 0 | O41: 251472.25 | P41: 114857.6 | Q41: =O41+N41+M41+L41+K41+P41 -> 766329.85 | R41: 769390.15 | S41: =J41-Q41 -> 769390.15
A42: 2 | B42: JAMILA ABDUL | C42: SENIOR INTERNAL AUDITOR | D42: 10(7) | E42: 293029.67 | H42: =60000 -> 60000 | J42: =SUM(E42:I42) -> 353029.67 | L42: =20000 -> 20000 | M42: 45833.33 | O42: 42537.332 | P42: 23442.373 | Q42: =O42+N42+M42+L42+K42+P42 -> 131813.04 | R42: 221216.63 | S42: =J42-Q42 -> 221216.63
A43: 3 | B43: IJEOMA EWELUKWA | C43: SENIOR INTERNAL AUDITOR | D43: 10(8) | E43: 300965.58 | H43: =50000+10000 -> 60000 | J43: =SUM(E43:I43) -> 360965.58 | L43: =10000 -> 10000 | O43: 43763.907 | P43: 24077.247 | Q43: =O43+N43+M43+L43+K43+P43 -> 77841.154 | R43: 283124.43 | S43: =J43-Q43 -> 283124.43
A44: 4 | B44: YUSUF YUSUF DAYYABU | C44: INERNAL AUDIT OFFICER | D44: 9(7) | E44: ='[3]Annual & Monthly'!$H$37 -> 255849 | H44: 60000 | J44: =SUM(E44:I44) -> 315849 | L44: 20000 | O44: =36790.6881066667 -> 36790.688 | P44: =255849*0.08 -> 20467.92 | Q44: =O44+N44+M44+L44+K44+P44 -> 77258.608 | R44: 238590.39 | S44: =J44-Q44 -> 238590.39
C45: 4 | E45: =SUM(E41:E44) -> 2285564.2 | F45: =SUM(F41:F44) -> 0 | G45: =SUM(G41:G44) -> 0 | H45: =SUM(H41:H44) -> 280000 | I45: =SUM(I41:I44) -> 0 | J45: =SUM(J41:J44) -> 2565564.2 | K45: =SUM(K41:K44) -> 0 | L45: =SUM(L41:L44) -> 450000 | ... Q45: =SUM(Q41:Q44) -> 1053242.6 | R45: 1512321.6 | S45: =SUM(S41:S44) -> 1512321.6
B47: LEG. SUPPORT SEVICES
A48: 1 | B48: PROF. EDOBA BRIGHT OMOREGBE | C48: AG. DLSS | D48: 17(9) | E48: 1435720 | G48: =200000 -> 200000 | J48: =SUM(E48:I48) -> 1635720 | L48: =400000 -> 400000 | M48: 0 | O48: 270672.25 | P48: 114857.6 | Q48: =O48+N48+M48+L48+K48+P48 -> 785529.85 | R48: 850190.15 | S48: =J48-Q48 -> 850190.15
A49: 2 | B49: DR CLINTON JAJA | C49: SENIOR RESEARCH FELLOW | D49: 15(9) | E49: 620675.58 | G49: =160000 -> 160000 | I49: 0 | J49: 0 | Q49: =O49+N49+M49+L49+K49+P49 -> 0 | R49: 176998.73 | S49: =J49-Q49 -> 0
A50: 3 | B50: BETHEL UZOMA IHUGBA | C50: DEPUTY DIRECTOR, LEGAL RESEARCH | D50: 16(8) | E50: 739203.58 | G50: =180000 -> 180000 | J50: =SUM(E50:I50) -> 919203.58 | L50: =80000+23000 -> 103000 | M50: =246905.96 -> 246905.96 | O50: 143799.59 | P50: 59136.287 | Q50: =O50+N50+M50+L50+K50+P50 -> 552841.83 | R50: 366361.75 | S50: =J50-Q50 -> 366361.75
A51: 4 | B51: OGUCHE SAMUEL | C51: SNR RESEARCH FELLOW | D51: 15(9) | E51: 620675.58 | G51: =160000 -> 160000 | J51: =SUM(E51:I51) -> 780675.58 | L51: =30000 -> 30000 | M51: 223059.88 | O51: 119022.8 | P51: 49654.047 | Q51: =O51+N51+M51+L51+K51+P51 -> 421736.73 | R51: 358938.85 | S51: =J51-Q51 -> 358938.85
A52: 5 | B52: IBRAHIM USMAN | C52: SNR RESEARCH FELLOW | D52: 15(9) | E52: 620675.58 | G52: =140000+20000 -> 160000 | I52: 0 | J52: =SUM(E52:I52) -> 780675.58 | N52: ='New NHF Deduction'!G48 -> 8380.2271 | O52: 118861.97 | P52: 49654.047 | Q52: =O52+N52+M52+L52+K52+P52 -> 176896.24 | R52: 603779.34 | S52: =J52-Q52 -> 603779.34
A53: 6 | B53: DR MOHAMMED O. AMALI | C53: SNR RESEARCH FELLOW | D53: 15(7) | E53: 582118.08 | G53: =140000+20000 -> 160000 | J53: =SUM(E53:I53) -> 742118.08 | L53: =15000 -> 15000 | M53: 99000 | O53: 112212 | P53: 46569.447 | Q53: =O53+N53+M53+L53+K53+P53 -> 272781.45 | R53: 469336.63 | S53: =J53-Q53 -> 469336.63
A54: 7 | B54: YAHAYA SHAMSU | C54: SNR RESEARCH FELLOW | D54: 15(7) | E54: 582118.08 | F54: ='2024 Promotion Arrears'!J16 -> 394860 | G54: =160000 -> 160000 | J54: =SUM(E54:I54) -> 1136978.1 | N54: 0 | O54: =' New Grade PAYE '!AB15 -> 157891.47 | P54: =46569.45 -> 46569.45 | Q54: =O54+N54+M54+L54+K54+P54 -> 204460.92 | R54: 484202.73 | S54: =J54-Q54 -> 932517.16
A55: 8 | B55: BILKIS S. LAWAL-GAMBARI | C55: RESEARCH OFFICER | D55: 10(8) | E55: 300965.58 | G55: 100000 | J55: =SUM(E55:I55) -> 400965.58 | O55: 51029.227 | P55: 24077.247 | Q55: =O55+N55+M55+L55+K55+P55 -> 75106.474 | R55: 325859.11 | S55: =J55-Q55 -> 325859.11
A56: 9 | B56: ZAINAB AKINDE | C56: RESEARCH OFFICER | D56: 9(8) | E56: 263165.33 | G56: =100000 -> 100000 | J56: =SUM(E56:I56) -> 363165.33 | O56: 44641.501 | P56: 21053.227 | Q56: =O56+N56+M56+L56+K56+P56 -> 65694.727 | R56: 297470.61 | S56: =J56-Q56 -> 297470.61
A57: 10 | B57: GUNAT NANSAK MARK | C57: RESEARCH OFFICER | D57: 9(8) | E57: 263165.33 | G57: =100000 -> 100000 | J57: =SUM(E57:I57) -> 363165.33 | O57: 44641.501 | P57: 21053.227 | Q57: =O57+N57+M57+L57+K57+P57 -> 65694.727 | R57: 297470.61 | S57: =J57-Q57 -> 297470.61
B58: TOTAL | C58: 10 | E58: =SUM(E48:E57) -> 6028482.7 | F58: =SUM(F48:F57) -> 394860 | G58: =SUM(G48:G57) -> 1480000 | H58: =SUM(H48:H57) -> 0 | I58: =SUM(I48:I57) -> 0 | J58: =SUM(J48:J57) -> 7122667.2 | K58: =SUM(K48:K57) -> 0 | L58: =SUM(L48:L57) -> 548000 | ... Q58: =SUM(Q48:Q57) -> 2620742.9 | R58: 4230608.5 | S58: =SUM(S48:S57) -> 4501924.2
B60: LEGAL SERVICES
A61: 1 | B61: DR SHUIBU DANWANKA | C61: DIRECTOR LEGAL SERVICES | D61: 17(9) | E61: 1435720 | G61: =200000 -> 200000 | I61: 0 | J61: 0 | N61: 0 | Q61: =O61+N61+M61+L61+K61+P61 -> 0 | R61: 1130190.2 | S61: =J61-Q61 -> 0
A62: 2 | B62: ABDULSALAM BAKO | C62: MANAGER, LEGAL SERVICES | D62: 15 (9) | E62: 620675.58 | H62: 80000 | J62: =SUM(E62:I62) -> 700675.58 | L62: 50000 | M62: 145000 | N62: 0 | O62: 103662.8 | P62: 49654.047 | Q62: =O62+N62+M62+L62+K62+P62 -> 348316.85 | R62: 352358.73 | S62: =J62-Q62 -> 352358.73
B63: TOTAL | C63: 2 | E63: =SUM(E61:E62) -> 2056395.6 | F63: =SUM(F61:F62) -> 0 | G63: =SUM(G61:G62) -> 200000 | H63: =SUM(H61:H62) -> 80000 | I63: =SUM(I61:I62) -> 0 | J63: =SUM(J61:J62) -> 700675.58 | K63: =SUM(K61:K62) -> 0 | L63: =SUM(L61:L62) -> 50000 | ... Q63: =SUM(Q61:Q62) -> 348316.85 | R63: 1482548.9 | S63: =SUM(S61:S62) -> 352358.73
B65: DEMOCRACY & GOVERNANCE
A66: 1 | B66: DR. ADEWALE ADEREMI | C66: DIRECTOR, DEMOCRATIC STUDIES | D66: 17(9) | E66: 1435720 | G66: =200000 -> 200000 | I66: 0 | J66: =SUM(E66:I66) -> 1635720 | L66: 100000 | M66: 800000 | O66: 292724.91 | Q66: =O66+N66+M66+L66+K66+P66 -> 1192724.9 | R66: 442995.09 | S66: =J66-Q66 -> 442995.09
A67: 2 | B67: NDANUSA MOHAMMED MANZUMA | C67: SNR RESEARCH FELLOW | D67: 15(8) | E67: 601396.83 | G67: =160000 -> 160000 | I67: 0 | J67: =SUM(E67:I67) -> 761396.83 | L67: =100000 -> 100000 | M67: =230527.74 -> 230527.74 | O67: 115617.4 | P67: 48111.747 | Q67: =O67+N67+M67+L67+K67+P67 -> 494256.89 | R67: 267139.94 | S67: =J67-Q67 -> 267139.94
A68: 3 | B68: EJALONIBU GANIYU LAYI | C68: RESEARCH FELLOW 1 | D68: 14(8) | E68: 442746.5 | G68: 140000 | J68: =SUM(E68:I68) -> 582746.5 | L68: =110000+90000 -> 200000 | O68: 83753.408 | P68: 35419.72 | Q68: =O68+N68+M68+L68+K68+P68 -> 319173.13 | R68: 263573.37 | S68: =J68-Q68 -> 263573.37
A69: 4 | B69: LOHNA BONKAT JONATHAN | C69: RESEARCH FELLOW 11 | D69: 13(10) | E69: 428915.92 | F69: 0 | G69: =120000 -> 120000 | I69: 0 | J69: 0 | M69: 0 | N69: 0 | Q69: =O69+N69+M69+L69+K69+P69 -> 0 | R69: 287132.27 | S69: =J69-Q69 -> 0
A70: 7 | B70: UDEFUNA NNADOZIE PATRICK | C70: RESEARCH OFFICER | D70: 12(8) | E70: 365703.83 | G70: =110000 -> 110000 | I70: 0 | J70: =SUM(E70:I70) -> 475703.83 | L70: 10000 | M70: =163196.67 -> 163196.67 | O70: 64384.592 | P70: 29256.307 | Q70: =O70+N70+M70+L70+K70+P70 -> 266837.57 | R70: 208866.26 | S70: =J70-Q70 -> 208866.26
A71: 8 | B71: SHAFIU YAHYA MIKAIL | C71: PRINCIPAL RESEARCH OFFICER | D71: 12(8) | E71: 365703.83 | G71: =110000 -> 110000 | I71: 0 | J71: =SUM(E71:I71) -> 475703.83 | L71: =52000-2000 -> 50000 | O71: 64384.592 | P71: 29256.307 | Q71: =O71+N71+M71+L71+K71+P71 -> 143640.9 | R71: 332062.93 | S71: =J71-Q71 -> 332062.93
A72: 9 | B72: HASSAN YERIMA | C72: PRINCIPAL RESEARCH OFFICER | D72: 12(8) | E72: 365703.83 | G72: =110000 -> 110000 | I72: 0 | J72: =SUM(E72:I72) -> 475703.83 | L72: =67000-2000 -> 65000 | O72: 64384.592 | P72: 29256.307 | Q72: =O72+N72+M72+L72+K72+P72 -> 158640.9 | R72: 317062.93 | S72: =J72-Q72 -> 317062.93
A73: 10 | B73: HAUWA PATE SADIQ | C73: PRINCIPAL PROGRAMME OFFICER | D73: 12(9) | E73: 377895.17 | G73: =110000 -> 110000 | J73: =SUM(E73:I73) -> 487895.17 | L73: =80000+20000 -> 100000 | O73: 66538.069 | P73: 30231.613 | Q73: =O73+N73+M73+L73+K73+P73 -> 196769.68 | R73: 291125.48 | S73: =J73-Q73 -> 291125.48
A74: 11 | B74: KOLAPO Q. ABAYOMI | C74: RESEARCH OFFICER | D74: 10(8) | E74: 300965.58 | G74: 100000 | J74: =SUM(E74:I74) -> 400965.58 | O74: 51029.227 | P74: 24077.247 | Q74: =O74+N74+M74+L74+K74+P74 -> 75106.474 | R74: 325859.11 | S74: =J74-Q74 -> 325859.11
B75: TOTAL | C75: 11 | E75: =SUM(E66:E74) -> 4684751.5 | F75: =SUM(F66:F74) -> 0 | G75: =SUM(G66:G74) -> 1160000 | H75: =SUM(H66:H74) -> 0 | I75: =SUM(I66:I74) -> 0 | J75: =SUM(J66:J74) -> 5295835.6 | K75: =SUM(K66:K74) -> 0 | L75: =SUM(L66:L74) -> 625000 | ... Q75: =SUM(Q66:Q74) -> 2847150.4 | R75: 2735817.4 | S75: =SUM(S66:S74) -> 2448685.1
B77: DEPARTMENT OF STUDIES
A78: 1 | B78: DR ASIMIYU G. ABIOLA | C78: DIRECTOR POST GRADUATE | D78: 17(9) | E78: 1435720 | G78: =200000 -> 200000 | I78: 0 | J78: =SUM(E78:I78) -> 1635720 | L78: 350000 | M78: =0 -> 0 | N78: 0 | O78: 270672.25 | P78: 114857.6 | Q78: =O78+N78+M78+L78+K78+P78 -> 735529.85 | R78: 900190.15 | S78: =J78-Q78 -> 900190.15
A79: 2 | B79: DR. HADIZA SAIDU | C79: ASSISTANT DIRECTOR | D79: 15(7) | E79: 582118.08 | G79: 160000 | J79: =SUM(E79:I79) -> 742118.08 | O79: 112212 | P79: 46569.447 | Q79: =O79+N79+M79+L79+K79+P79 -> 158781.45 | R79: 583336.63 | S79: =J79-Q79 -> 583336.63
A80: 3 | B80: ANTHONY EDET | C80: CHIEF PROGRAMMES OFFICER | D80: 14(9) | E80: 456622.25 | G80: =140000 -> 140000 | I80: 0 | J80: =SUM(E80:I80) -> 596622.25 | L80: 20000 | M80: 210785.51 | N80: ='New NHF Deduction'!G79 -> 6154.3229 | O80: 86076.104 | P80: 36529.78 | Q80: =O80+N80+M80+L80+K80+P80 -> 359545.72 | R80: 237076.53 | S80: =J80-Q80 -> 237076.53
A81: 4 | B81: IGWE STACY | C81: PRINC. PROGRAMME OFFICER | D81: 12(7) | E81: 353512.5 | F81: ='2024 Promotion Arrears'!J21 -> 218444 | G81: =110000 -> 110000 | J81: =SUM(E81:I81) -> 681956.5 | L81: =50000 -> 50000 | M81: =50000 -> 50000 | O81: =' New Grade PAYE '!AB20 -> 81345.165 | P81: =28281 -> 28281 | Q81: =O81+N81+M81+L81+K81+P81 -> 209626.17 | R81: 231758.35 | S81: =J81-Q81 -> 472330.33
A82: 5 | B82: OLANIYAN TAIWO ABINBOLA | C82: PROGRAMME OFFICER | D82: 9(8) | E82: 263165.33 | G82: 100000 | J82: =SUM(E82:I82) -> 363165.33 | O82: 44641.501 | P82: 21053.227 | Q82: =O82+N82+M82+L82+K82+P82 -> 65694.727 | R82: 297470.61 | S82: =J82-Q82 -> 297470.61
A83: 6 | B83: AMINAT JUMOKE SULAIMON | C83: AST. PROGRAMME OFFICER | D83: 8(8) | E83: 224459.75 | G83: 100000 | H83: 0 | J83: =SUM(E83:I83) -> 324459.75 | L83: 20000 | M83: 0 | N83: 0 | O83: 38659.166 | P83: 17956.78 | Q83: =O83+N83+M83+L83+K83+P83 -> 76615.946 | R83: 247843.8 | S83: =J83-Q83 -> 247843.8
B84: TOTAL | C84: 6 | E84: =SUM(E78:E83) -> 3315597.9 | F84: =SUM(F78:F83) -> 218444 | G84: =SUM(G78:G83) -> 810000 | H84: =SUM(H78:H83) -> 0 | I84: =SUM(I78:I83) -> 0 | J84: =SUM(J78:J83) -> 4344041.9 | K84: =SUM(K78:K83) -> 0 | L84: =SUM(L78:L83) -> 440000 | ... Q84: =SUM(Q78:Q83) -> 1605793.9 | R84: 2497676.1 | S84: =SUM(S78:S83) -> 2738248.1
B86: ECON. DEV. & SOC. RESEARCH
A87: 1 | B87: TERFA WILLIAMS ABRAHAM | C87: SNR RESEARCH FELLOW | D87: 15(9) | E87: 620675.58 | G87: =160000 -> 160000 | I87: =100000+100000 -> 200000 | J87: =SUM(E87:I87) -> 980675.58 | O87: ='Additional Leg Duty Allowance'!P11 -> 157422.8 | P87: 49654.047 | Q87: =O87+N87+M87+L87+K87+P87 -> 207076.85 | R87: 773598.73 | S87: =J87-Q87 -> 773598.73
A88: 2 | B88: DR AUGUSTINE C. OSIGWE | C88: SNR RESEARCH FELLOW | D88: 15(9) | E88: 620675.58 | G88: =160000 -> 160000 | J88: =SUM(E88:I88) -> 780675.58 | L88: =30000 -> 30000 | M88: 98750 | N88: ='New NHF Deduction'!G87 -> 8380.2271 | O88: 118861.97 | P88: 49654.047 | Q88: =O88+N88+M88+L88+K88+P88 -> 305646.24 | R88: 475029.34 | S88: =J88-Q88 -> 475029.34
A89: 3 | B89: OMOJU OLUWASOLA EMMANUEL | C89: SNR RESEARCH FELLOW | D89: 15(7) | E89: 582118.08 | G89: 160000 | J89: =SUM(E89:I89) -> 742118.08 | L89: =50000 -> 50000 | M89: =79861.11 -> 79861.11 | O89: 112212 | P89: 46569.447 | Q89: =O89+N89+M89+L89+K89+P89 -> 288642.56 | R89: 453475.52 | S89: =J89-Q89 -> 453475.52
A90: 4 | B90: IBE EZECHI CYRIACUS | C90: RESEARCH FELLOW 1 | D90: 14(8) | E90: 442746.5 | F90: ='Promotion in Sept'!V8 -> 76989.642 | G90: =140000 -> 140000 | I90: 0 | J90: =SUM(E90:I90) -> 659736.14 | L90: =50000 -> 50000 | M90: =77638.89 -> 77638.89 | O90: 83767.87 | P90: 35344.393 | Q90: =O90+N90+M90+L90+K90+P90 -> 246751.15 | R90: 335995.35 | S90: =J90-Q90 -> 412984.99
A91: 5 | B91: OSIKHEN LEO IGBANOI | C91: RESEARCH FELLOW 1 | D91: 14(8) | E91: 442746.5 | F91: ='2024 Promotion Arrears'!J19 -> 676611.67 | G91: =120000 -> 120000 | I91: 0 | J91: =SUM(E91:I91) -> 1239358.2 | L91: 50000 | M91: 0 | O91: =' New Grade PAYE '!AB18 -> 185528.93 | P91: =35419.72 -> 35419.72 | Q91: =O91+N91+M91+L91+K91+P91 -> 270948.65 | R91: 387132.27 | S91: =J91-Q91 -> 968409.52
A92: 6 | B92: OKUNGBOWA OSARETIN GODSPOWER | C92: RESEARCH FELLOW 1 | D92: 14(7) | E92: 428870.75 | G92: =140000 -> 140000 | I92: 0 | J92: =SUM(E92:I92) -> 568870.75 | L92: =100000-100000 -> 0 | O92: 81302.396 | P92: 34309.66 | Q92: =O92+N92+M92+L92+K92+P92 -> 115612.06 | R92: 453258.69 | S92: =J92-Q92 -> 453258.69
A93: 7 | B93: YUSUF IBRAHIM | C93: PRINCIPAL RESEARCH OFFICER | D93: 12(8) | E93: 365703.83 | G93: =110000 -> 110000 | I93: 0 | J93: =SUM(E93:I93) -> 475703.83 | L93: =20000 -> 20000 | M93: 43750 | O93: 64384.592 | P93: 29256.307 | Q93: =O93+N93+M93+L93+K93+P93 -> 157390.9 | R93: 318312.93 | S93: =J93-Q93 -> 318312.93
A94: 8 | B94: MUSTAPHA RAFIU AYOBANJI | C94: RESEARCH FELLOW 11 | D94: 13(7) | E94: 390248.92 | G94: 120000 | I94: 0 | J94: =SUM(E94:I94) -> 510248.92 | L94: 0 | N94: ='New NHF Deduction'!G93 -> 5259.7438 | O94: 70529.475 | P94: 31219.913 | Q94: =O94+N94+M94+L94+K94+P94 -> 107009.13 | R94: 403239.78 | S94: =J94-Q94 -> 403239.78
A95: 9 | B95: MARYAM MUSA SADA | C95: ASSIT. RESEARCH OFFICER | D95: 10(8) | E95: 300965.58 | G95: 100000 | J95: =SUM(E95:I95) -> 400965.58 | O95: 51029.227 | P95: 24077.247 | Q95: =O95+N95+M95+L95+K95+P95 -> 75106.474 | R95: 325859.11 | S95: =J95-Q95 -> 325859.11
A96: 10 | B96: CHARITY EZENWAJIOBI | C96: REASEARCH. ASST. | D96: 8(9) | E96: 230631.92 | G96: =100000 -> 100000 | J96: =SUM(E96:I96) -> 330631.92 | L96: 50000 | N96: 0 | O96: 39613.136 | P96: 18450.553 | Q96: =O96+N96+M96+L96+K96+P96 -> 108063.69 | R96: 222568.23 | S96: =J96-Q96 -> 222568.23
B97: TOTAL | C97: 10 | E97: =SUM(E87:E96) -> 4425383.2 | F97: =SUM(F87:F96) -> 753601.31 | G97: =SUM(G87:G96) -> 1310000 | H97: =SUM(H87:H96) -> 0 | I97: =SUM(I87:I96) -> 200000 | J97: =SUM(J87:J96) -> 6688984.6 | K97: =SUM(K87:K96) -> 0 | L97: =SUM(L87:L96) -> 250000 | ... Q97: =SUM(Q87:Q96) -> 1882247.7 | R97: 4148470 | S97: =SUM(S87:S96) -> 4806736.9
B99: TRAINING & INT''L COOP
A100: 1 | B100: AKINSANMI ADEJOKE OLUKEMI | C100: Ag. DIR. TRAINING & IC | D100: 17(7) | E100: ='[3]Annual & Monthly'!$H$44 -> 1352042.7 | H100: =100000 -> 100000 | J100: =E100+F100+G100+H100+I100 -> 1452042.7 | L100: 500000 | M100: 0 | N100: ='New NHF Deduction'!G99 -> 18254.975 | O100: ='March New PAYE '!Z93 -> 236486.75 | P100: ='Upgrade in March'!P8 -> 114857.6 | Q100: =O100+N100+M100+L100+K100+P100 -> 869599.32 | R100: 582443.34 | S100: =J100-Q100 -> 582443.34
A101: 2 | B101: MOHAMMED R. ADAMU | C101: CHIEF TRAINING OFFICER | D101: 14(9) | E101: 456622.25 | H101: 70000 | I101: 0 | J101: =E101+F101+G101+H101+I101 -> 526622.25 | L101: =10000 -> 10000 | M101: 175000 | O101: 72764.421 | P101: 36529.78 | Q101: =O101+N101+M101+L101+K101+P101 -> 294294.2 | R101: 232328.05 | S101: =J101-Q101 -> 232328.05
A102: 3 | B102: OKECHUKWU UCHENNA HULDA | C102: PRINCIPALTRAINING OFFICER | D102: 12(9) | E102: 377895.17 | H102: =60000 -> 60000 | J102: =E102+F102+G102+H102+I102 -> 437895.17 | L102: =5000 -> 5000 | M102: 52500 | O102: 56938.069 | P102: 30231.613 | Q102: =O102+N102+M102+L102+K102+P102 -> 144669.68 | R102: 293225.48 | S102: =J102-Q102 -> 293225.48
A103: 4 | B103: TASSNEEM IBRAHIM | C103: SENIOR PROGRAMME OFFICER | D103: 10(8) | E103: 300965.58 | H103: =60000 -> 60000 | J103: =E103+F103+G103+H103+I103 -> 360965.58 | L103: =10000+80000 -> 90000 | M103: =19583.33 -> 19583.33 | O103: 43763.907 | P103: 24077.247 | Q103: =O103+N103+M103+L103+K103+P103 -> 177424.48 | R103: 183541.1 | S103: =J103-Q103 -> 183541.1
B104: TOTAL | C104: 4 | E104: =SUM(E100:E103) -> 2487525.7 | F104: =SUM(F100:F103) -> 0 | G104: =SUM(G100:G103) -> 0 | H104: =SUM(H100:H103) -> 290000 | I104: =SUM(I100:I103) -> 0 | J104: =SUM(J100:J103) -> 2777525.7 | K104: =SUM(K100:K103) -> 0 | L104: =SUM(L100:L103) -> 605000 | ... Q104: =SUM(Q100:Q103) -> 1485987.7 | R104: 1291538 | S104: =SUM(S100:S103) -> 1291538
B106: LIBRARY & DOCUMENTATION
A107: 1 | B107: DR MAIMUNA IZAH | C107: INSITUTE LIBRARIAN | D107: 17(9) | E107: 1435720 | G107: =200000 -> 200000 | I107: 0 | J107: =SUM(E107:I107) -> 1635720 | L107: =100000 -> 100000 | M107: 0 | N107: 0 | O107: 270672.25 | P107: 114857.6 | Q107: =O107+N107+M107+L107+K107+P107 -> 485529.85 | R107: 1150190.2 | S107: =J107-Q107 -> 1150190.2
A108: 2 | B108: CATHERINE E. IKOKOH | C108: SNR RESEARCH FELLOW DOCU | D108: 16(9) | E108: 762373.17 | G108: =160000+20000 -> 180000 | I108: 0 | J108: =SUM(E108:I108) -> 942373.17 | L108: 40000 | N108: 10293.398 | O108: 147687.53 | P108: 60989.853 | Q108: =O108+N108+M108+L108+K108+P108 -> 258970.78 | R108: 444513.5 | S108: =J108-Q108 -> 683402.39
...

Sheet MEMO
A2: NATIONAL INSTITUTE FOR LEGISLATIVE AND DEMOCRATIC STUDIES
A3: INTERNAL MEMO
A4: FROM : DEPUTY DIRECTOR, FINANCE AND ACCOUNTS
A5: THRU: DIRECTOR, FINANCE AND ACCOUNTS
A6: TO: DG
A7: 29TH JANUARY , 2021
A9: SUBJECT: PAYROLL FOR THE MONTH OF JANUARY, 2021
A10: Find below the details of NILDS Staff Payroll for the month of January, 2021
A13: TO: | C13: DIRECTOR, GENERAL
A14: THRU: | C14: DIRECTOR, FINANCE AND ACCOUNT
A15: FROM: | C15: DEPUTY DIRECTOR, FINANCE AND ACCOUNTS
A16: DATE: | C16: 30TH NOVEMBER 2024
A18: SUBJECT: PAYROLL FOR THE MONTH OF NOVEMBER 2024
A19: Find below the details of NILDS Staff Payroll for the Month of November, 2024: | G19: NGN | H19: NGN
A20: GROSS SALARY FOR NOVEMBER, 2024 | H20: ='NOVEMBER 2024'!J205 -> 85506402
A22: DEDUCTIONS
A23: COOP SOCIETY DEDUCTIONS ( CONTR.& SPEC. SAVINGS) | G23: ='NOVEMBER 2024'!L205 -> 6278500
A24: COOP LOAN RECOVERY | G24: ='NOVEMBER 2024'!M205 -> 7820349.2
A25: NHF DEDUCTIONS | G25: ='NOVEMBER 2024'!N205 -> 237989.65
A26: PAYE DEDUCTIONS | G26: ='NOVEMBER 2024'!O205 -> 11965920
A27: PENSION DEDUCTIONS | G27: ='NOVEMBER 2024'!P205 -> 4754985.8
A28: TOTAL DEDUCTIONS FOR NOVEMBER 2024 | H28: =G23+G24+G26+G25+G27 -> 31057744
A29: NET PAY AS PER NOVEMBER 2024 PAYROLL | H29: =H20-H28 -> 54448658
A30: NET PAY AS PER OCTOBER, 2024 PAYROLL | H30: ='NOVEMBER 2024'!R205 -> 49732867
A31: NET INCREASE/ (DECREASE) IN PAY FOR NOVEMBER, 2024 | H31: =H29-H30 -> 4715790.2
A32: ANALYSED AS FOLLOWS:
A33: Effect of Cooperative Adjustment for November, 2024 | H33: =-153888.89 -> -153888.89
A34: Effect of Promotion for Abdulsalam Mustapha & 17 Others | H34: =-1104397.42 -> -1104397.4
A35: Effect of Promotion Arrears for Abdulsalam Mustapha & 16 Others | H35: =-6154690.14 -> -6154690.1
A36: Effect of Changes in PAYE & Pensions for Abdulsalam Mustapha & 17 Others due to Promotions | H36: =1075093.09 -> 1075093.1
A37: Effect of Conversion of Saratu Atajiri from Casual to Permanent Staff | H37: =-258590.39 -> -258590.39
A38: Effect of Increase in NHF of Simon Wakawa & 5 others due to Promotions | H38: =7677.68 -> 7677.68
A39: Net Effect of Stoppage of Payment to Dr. Shuaibu Danwanka & 2 Others | H39: =1594321.16 -> 1594321.2
A40: Effect for removal of regularization arrears of Mohammed Bello | H40: =355674.37 -> 355674.37
A41: Effect of Promotion Arrears for Ibeh | H41: =-76989.64 -> -76989.64
H42: =SUM(H33:H41) -> -4715790.2
E45: OCTOBER, 2024 | G45: NOVEMBER, 2024
E46: No. of Staff | F46: N | G46: No. of Staff | H46: N
A47: 1 | B47: Director General's Office | E47: 32 | F47: ='NOVEMBER 2024'!R38 -> 13026183 | G47: ='NOVEMBER 2024'!C38 -> 31 | H47: ='NOVEMBER 2024'!S38 -> 13461860
A48: 2 | B48: Internal Audit | E48: 3 | F48: ='NOVEMBER 2024'!R45 -> 1512321.6 | G48: ='NOVEMBER 2024'!C45 -> 4 | H48: ='NOVEMBER 2024'!S45 -> 1512321.6
A49: 3 | B49: Legis. Support Services | E49: 11 | F49: ='NOVEMBER 2024'!R58 -> 4230608.5 | G49: ='NOVEMBER 2024'!C58 -> 10 | H49: ='NOVEMBER 2024'!S58 -> 4501924.2
A50: 4 | B50: Legal Services | E50: 2 | F50: ='NOVEMBER 2024'!R63 -> 1482548.9 | G50: ='NOVEMBER 2024'!C63 -> 2 | H50: ='NOVEMBER 2024'!S63 -> 352358.73
A51: 5 | B51: Democracy and Governance | E51: 12 | F51: ='NOVEMBER 2024'!R75 -> 2735817.4 | G51: ='NOVEMBER 2024'!C75 -> 11 | H51: ='NOVEMBER 2024'!S75 -> 2448685.1
A52: 6 | B52: Studies | E52: 6 | F52: ='NOVEMBER 2024'!R84 -> 2497676.1 | G52: ='NOVEMBER 2024'!C84 -> 6 | H52: ='NOVEMBER 2024'!S84 -> 2738248.1
A53: 7 | B53: Economic Dev. & Social Research | E53: 11 | F53: ='NOVEMBER 2024'!R97 -> 4148470 | G53: ='NOVEMBER 2024'!C97 -> 10 | H53: ='NOVEMBER 2024'!S97 -> 4806736.9
A54: 8 | B54: Training & Int'l Cooperation | E54: 4 | F54: ='NOVEMBER 2024'!R104 -> 1291538 | G54: ='NOVEMBER 2024'!C104 -> 4 | H54: ='NOVEMBER 2024'!S104 -> 1291538
A55: 9 | B55: Library & Documentation | E55: 7 | F55: ='NOVEMBER 2024'!R114 -> 3139602.7 | G55: ='NOVEMBER 2024'!C114 -> 7 | H55: ='NOVEMBER 2024'!S114 -> 3378491.6
A56: 10 | B56: Leg. Center for Security Analysis | E56: 2 | F56: ='NOVEMBER 2024'!R120 -> 990230.27 | G56: ='NOVEMBER 2024'!C120 -> 2 | H56: ='NOVEMBER 2024'!S120 -> 1158023.8
A57: 11 | B57: Democracy Radio 104.9 | E57: 3 | F57: ='NOVEMBER 2024'!R126 -> 664558.14 | G57: 3 | H57: ='NOVEMBER 2024'!S126 -> 664558.14
A58: 12 | B58: Finance and Accounts | E58: 10 | F58: ='NOVEMBER 2024'!R139 -> 3206493.4 | G58: ='NOVEMBER 2024'!C139 -> 10 | H58: ='NOVEMBER 2024'!S139 -> 3206493.4
A59: 13 | B59: Admin & Human Resource | E59: 61 | F59: ='NOVEMBER 2024'!R204 -> 10806819 | G59: ='NOVEMBER 2024'!C204 -> 62 | H59: ='NOVEMBER 2024'!S204 -> 14927418
E60: =SUM(E47:E59) -> 164 | F60: =SUM(F47:F59) -> 49732867 | G60: 163 | H60: =SUM(H47:H59) -> 54448658
A62: The Director General is requested to consider and approve payment of N54,448,657.50 to Guaranty Trust Bank being November, 2024 Salary, N14,098,849.21 being NILDS Coop Society deductions for November 2024, N11,965,919.65 being PAYE Tax Deductions from Staff Salary for the month of November 2024 and N237,989.65 being NHF deductions from staff for November 2024
A66: RAHILA NURUDEEN HABU
C170: =10000 -> 10000

Sheet 2024 Promotion Arrears
A1: NATIONAL INSTITUTE FOR LEGISLATIVE & DEMOCRATIC STUDIES
A2: 2024 ANALYSIS OF STAFF PROMOTION ARREARS
A4: SN | B4: Name of Employee | C4: Department | D4: Present Grade Level | E4: New Grade Level | F4: Consolidated Salary of Present Position | G4: Consolidated Salary of New Position | H4: Diference/Arrears | I4: No of Months | J4: Total Amount of Arrears (Gross)
F5: N | G5: N | H5: N | J5: N
A6: 1 | B6: ABDULSALAM MUSTAPHA | C6: DG's Office | D6: 13/11 | E6: 15/7 | F6: =511804.92 -> 511804.92 | G6: =582118+80000 -> 662118 | H6: =G6-F6 -> 150313.08 | I6: 1 | J6: =H6*I6 -> 150313.08
A7: 2 | B7: EMILY EDIOSA IKHIDE | C7: DG's Office | D7: 014/10 | E7: 015/7 | F7: 610498 | G7: =582118+160000 -> 742118 | H7: =G7-F7 -> 131620 | I7: 4 | J7: =H7*I7 -> 526480
A8: 3 | B8: SIMON WAKAWA | C8: DG's Office | D8: 014/11 | E8: 015/7 | F8: 554373.75 | G8: =582118+80000 -> 662118 | H8: =G8-F8 -> 107744.25 | I8: =2.71 -> 2.71 | J8: =H8*I8 -> 291986.92
A9: 4 | B9: WAZIRI USMAN | C9: Admin. & HR | D9: 014/11 | E9: 015/7 | F9: 554374.75 | G9: =582118+80000 -> 662118 | H9: =G9-F9 -> 107743.25 | I9: =2.71 -> 2.71 | J9: =H9*I9 -> 291984.21
A10: 5 | B10: TAIWO I. OYINLOLA | C10: Admin. & HR | D10: 05/9 | E10: 07/3 | F10: 121145.75 | G10: 189814.17 | H10: =G10-F10 -> 68668.417 | I10: 0 | J10: =H10*I10 -> 0 | K10: Effective in Dec
A11: 6 | B11: SARATU ATAJIRI | C11: Admin. & HR | D11: N/A | E11: 09/7 | F11: 120000 | G11: =255849+60000 -> 315849 | H11: =G11-F11 -> 195849 | I11: 8 | J11: =H11*I11 -> 1566792
A12: 7 | B12: YUSIF SANI SADIQ | C12: Admin. & HR | D12: 10/9 | E12: 12/7 | F12: 368901.5 | G12: 413512.5 | H12: =G12-F12 -> 44611 | I12: 2.71 | J12: =H12*I12 -> 120895.81
A13: 8 | B13: STELLA NGOZI PAUL | C13: Admin. & HR | D13: 10/10 | E13: 12/7 | F13: 376837.42 | G13: 413512.5 | H13: =G13-F13 -> 36675.083 | I13: 2.71 | J13: =H13*I13 -> 99389.476
A14: 9 | B14: OMONIGHO EROMOSELE-WESEY | C14: Admin. & HR | D14: 12/10 | E14: 13/7 | F14: 450086.5 | G14: 510248.92 | H14: =G14-F14 -> 60162.417 | I14: 8 | J14: =H14*I14 -> 481299.33
A15: 10 | B15: QUEEN ONYEKESON | C15: Admin. & HR | D15: 12/10 | E15: 13/7 | F15: 450086.5 | G15: 510248.92 | H15: =G15-F15 -> 60162.417 | I15: 2.71 | J15: =H15*I15 -> 163040.15
A16: 11 | B16: SHAMSUDEEN YAHAYA | C16: LSS | D16: 014/10 | E16: 015/7 | F16: 610498 | G16: 742118 | H16: =G16-F16 -> 131620 | I16: 3 | J16: =H16*I16 -> 394860
A17: 12 | B17: SALAMATU YAKUBU | C17: LSS | D17: 014/11 | E17: 015/7 | F17: 554373.75 | G17: 662118 | H17: =G17-F17 -> 107744.25 | I17: 3 | J17: =H17*I17 -> 323232.75
A18: 13 | B18: ROTIMI OGUNYOMI | C18: LSS | D18: 12/10 | E18: 13/7 | F18: 450086.5 | G18: 510248.92 | H18: =G18-F18 -> 60162.417 | I18: 3 | J18: =H18*I18 -> 180487.25
A19: 14 | B19: LEO IGBANOI | C19: Dem. & Gov. | D19: 13/10 | E19: 14/8 | F19: 548915.92 | G19: 582746.5 | H19: =G19-F19 -> 33830.583 | I19: 20 | J19: =H19*I19 -> 676611.67
A20: 15 | B20: TOSIN OWOEYE | C20: Dem. & Gov. | D20: 10/9 | E20: 12/7 | F20: 368901.5 | G20: 413512.5 | H20: =G20-F20 -> 44611 | I20: 9 | J20: =H20*I20 -> 401499
A21: 16 | B21: STACY CHINYERE IGWE | C21: DOS | D21: 10/9 | E21: 12/7 | F21: 408901.5 | G21: =353512.5+110000 -> 463512.5 | H21: =G21-F21 -> 54611 | I21: 4 | J21: =H21*I21 -> 218444
A22: 17 | B22: TANIMU M. LAWAL | C22: Econ/ & Social Res. | D22: 04/10 | E22: 07/3 | F22: 102926.92 | G22: 189814.17 | H22: =G22-F22 -> 86887.25 | I22: 1 | J22: =H22*I22 -> 86887.25
A23: 18 | B23: CHRISTIAN MADUABUCHI ODO | C23: Finance & Accts | D23: 12/10 | E23: 13/7 | F23: 450086.5 | G23: 510248.92 | H23: =G23-F23 -> 60162.417 | I23: 3 | J23: =H23*I23 -> 180487.25
B24: TOTAL | J24: =SUM(J6:J23) -> 6154690.1

Sheet Promotion in Sept
A1: NATIONAL INSTITUTE FOR LEGISLATIVE AND DEMOCRATIC STUDIES | G1: ='[1]FEB 08'!F8/'[1]FEB 08'!Q8 -> 0.3
A2: STAFF PAYROLL FOR THE MONTH OF NOVEMBER 2024
E3: ='[1]FEB 08'!E11/'[1]FEB 08'!M11 -> #REF! | G3: ='[1]FEB 08'!F11/'[1]FEB 08'!Q11 -> #REF!
B4: STAFF NAME | C4: DESIGNATION | D4: GRADE LEVEL | E4: BASIC SALARY | F4: ALLCE/ AREARS | G4: ALLOWANCE | H4: ALLOWANCE | I4: DUTY ALLCE | J4: CURRENT GROSS SALARY | K4: NEW GRADE LEVEL | L4: NEW GROSS SALARY | M4: INCREMENT IN GROSS SALARY | N4: CURRENT NHF | O4: NEW NHF | P4: CURRENT PAYE | Q4: NEW PAYE | S4: INCREMENT IN PAYE | T4: NET SALARY INCREMENT | U4: NO OF MONTHS | V4: ARREARS
E5: N | F5: N | G5: N | H5: N | I5: N | J5: N | L5: N | N5: N | P5: N
A7: 1 | B7: IBE EZECHI CYRIACUS | C7: RESEARCH FELLOW II | D7: 13(11) | E7: 441804.92 | G7: =120000 -> 120000 | I7: 0 | J7: =SUM(E7:I7) -> 561804.92 | K7: 14(7) | L7: =442746.5+140000 -> 582746.5 | M7: =L7-J7 -> 20941.583 | P7: 79747.087 | Q7: =83767.87 -> 83767.87 | S7: =Q7-P7 -> 4020.7829 | T7: =M7-S7 -> 16920.8 | U7: 4.55 | V7: =T7*U7 -> 76989.642
B8: TOTAL | E8: =SUM(E7:E7) -> 441804.92 | F8: =SUM(F7:F7) -> 0 | G8: =SUM(G7:G7) -> 120000 | H8: =SUM(H7:H7) -> 0 | I8: =SUM(I7:I7) -> 0 | J8: =SUM(J7:J7) -> 561804.92 | L8: =SUM(L7:L7) -> 582746.5 | M8: =SUM(M7:M7) -> 20941.583 | N8: =SUM(N7:N7) -> 0 | O8: =SUM(O7:O7) -> 0 | P8: =SUM(P7:P7) -> 79747.087 | Q8: =SUM(Q7:Q7) -> 83767.87 | S8: =SUM(S7:S7) -> 4020.7829 | T8: =SUM(T7:T7) -> 16920.8 | V8: =SUM(V7:V7) -> 76989.642

Sheet  New Grade PAYE 
A1: NATIONAL INSTITUTE FOR LEGISLATIVE AND DEMOCRATIC STUDIES
A2: NATIONAL ASSEMBLY ABUJA
A3: TAX COMPUTATION FOR 2022
A4: S/NO | B4: NAME | C4: MONTHLY TOTAL SALARY | D4: NO OF MONTHS | E4: ANNUAL SALARY GROSSED UP | F4: NATIONAL HOUSING SCHEME = 2.5% OF BASIC SALARY | G4: PENSION CONTRIBUTION = 8% OF CONSOLIDATED | H4: NHIS | I4: NET SALARY (EXC OF CRA) | M4: CRA=#200,000+(20% 0F NET SALARY (EXC OF CRA) | N4: TOTAL RELIEF | O4: CHARGEABLE INCOME | P4: FIRST N300,000 @ 7% | Q4: NEXT N300,000 @ 11% | R4: NEXT N500,000 @ 15% | S4: NEXT N500,000@ 19% | T4: NEXT N1,600,000 @ 21% | U4: ABOVE N3,200,000 @ 24% | V4: ANNUAL TAX PAYABLE | X4: MONTHLY TAX PAYABLE | Y4: MINIMUM TAX PAYABLE | Z4: NEW ACTUAL TAX PAYABLE | AA4: TAX PAYABLE ON ARREARS | AB4: TOTAL TAX PAYABLE IN NOVEMBER
A5: 1 | B5: ABDULSALAM MUSTAPHA | C5: =582118+80000 -> 662118 | D5: 12 | E5: =C5*D5 -> 7945416 | G5: 558833.36 | I5: =E5-F5-G5-H5 -> 7386582.6 | J5: 200000 | K5: 0.2 | L5: =I5*K5 -> 1477316.5 | M5: =J5+L5 -> 1677316.5 | N5: =F5+G5+H5+M5 -> 2236149.9 | O5: =E5-N5 -> 5709266.1 | P5: =IF(O5<300000,0.07*O5,21000) -> 21000 | Q5: =IF((O5-300000)<0,0,IF((O5-300000)<300000,0.11*(O5-300000),33000)) -> 33000 | R5: =IF((O5-600000)<0,0,IF((O5-600000)<500000,0.15*(O5-600000),75000)) -> 75000 | S5: =IF((O5-1100000)<0,0,IF((O5-1100000)<500000,0.19*(O5-1100000),95000)) -> 95000 | T5: =IF((O5-1600000)<0,0,IF((O5-1600000)<1600000,0.21*(O5-1600000),336000)) -> 336000 | U5: =24%*(O5-3200000) -> 602223.87 | V5: =P5+Q5+R5+S5+T5+U5 -> 1162223.9 | W5: 12 | X5: =V5/W5 -> 96851.989 | Z5: =X5 -> 96851.989 | AA5: 6949.236 | AB5: =Z5+AA5 -> 103801.22 | AC5: ABDULSALAM MUSTAPHA
A6: 2 | B6: EMILY EDIOSA IKHIDE | C6: =582118+160000+150000 -> 892118 | D6: 12 | E6: =C6*D6 -> 10705416 | G6: 558833.36 | I6: =E6-F6-G6-H6 -> 10146583 | J6: 200000 | K6: 0.2 | L6: =I6*K6 -> 2029316.5 | M6: =J6+L6 -> 2229316.5 | N6: =F6+G6+H6+M6 -> 2788149.9 | O6: =E6-N6 -> 7917266.1 | P6: =IF(O6<300000,0.07*O6,21000) -> 21000 | Q6: =IF((O6-300000)<0,0,IF((O6-300000)<300000,0.11*(O6-300000),33000)) -> 33000 | R6: =IF((O6-600000)<0,0,IF((O6-600000)<500000,0.15*(O6-600000),75000)) -> 75000 | S6: =IF((O6-1100000)<0,0,IF((O6-1100000)<500000,0.19*(O6-1100000),95000)) -> 95000 | T6: =IF((O6-1600000)<0,0,IF((O6-1600000)<1600000,0.21*(O6-1600000),336000)) -> 336000 | U6: =24%*(O6-3200000) -> 1132143.9 | V6: =P6+Q6+R6+S6+T6+U6 -> 1692143.9 | W6: 12 | X6: =V6/W6 -> 141011.99 | Z6: =X6 -> 141011.99 | AA6: 70809.493 | AB6: =Z6+AA6 -> 211821.48 | AC6: EMILY EDIOSA IKHIDE
A7: 3 | B7: SIMON WAKAWA | C7: =582118+80000 -> 662118 | D7: 12 | E7: =C7*D7 -> 7945416 | F7: =8019.8*12 -> 96237.6 | G7: 558833.36 | I7: =E7-F7-G7-H7 -> 7290345 | J7: 200000 | K7: 0.2 | L7: =I7*K7 -> 1458069 | M7: =J7+L7 -> 1658069 | N7: =F7+G7+H7+M7 -> 2313140 | O7: =E7-N7 -> 5632276 | P7: =IF(O7<300000,0.07*O7,21000) -> 21000 | Q7: =IF((O7-300000)<0,0,IF((O7-300000)<300000,0.11*(O7-300000),33000)) -> 33000 | R7: =IF((O7-600000)<0,0,IF((O7-600000)<500000,0.15*(O7-600000),75000)) -> 75000 | S7: =IF((O7-1100000)<0,0,IF((O7-1100000)<500000,0.19*(O7-1100000),95000)) -> 95000 | T7: =IF((O7-1600000)<0,0,IF((O7-1600000)<1600000,0.21*(O7-1600000),336000)) -> 336000 | U7: =24%*(O7-3200000) -> 583746.25 | V7: =P7+Q7+R7+S7+T7+U7 -> 1143746.2 | W7: 12 | X7: =V7/W7 -> 95312.187 | Z7: =X7 -> 95312.187 | AA7: 27049.475 | AB7: =Z7+AA7 -> 122361.66 | AC7: SIMON WAKAWA
A8: 4 | B8: WAZIRI USMAN | C8: =582118+80000 -> 662118 | D8: 12 | E8: =C8*D8 -> 7945416 | F8: =8019.8*12 -> 96237.6 | G8: 558833.36 | I8: =E8-F8-G8-H8 -> 7290345 | J8: 200000 | K8: 0.2 | L8: =I8*K8 -> 1458069 | M8: =J8+L8 -> 1658069 | N8: =F8+G8+H8+M8 -> 2313140 | O8: =E8-N8 -> 5632276 | P8: =IF(O8<300000,0.07*O8,21000) -> 21000 | Q8: =IF((O8-300000)<0,0,IF((O8-300000)<300000,0.11*(O8-300000),33000)) -> 33000 | R8: =IF((O8-600000)<0,0,IF((O8-600000)<500000,0.15*(O8-600000),75000)) -> 75000 | S8: =IF((O8-1100000)<0,0,IF((O8-1100000)<500000,0.19*(O8-1100000),95000)) -> 95000 | T8: =IF((O8-1600000)<0,0,IF((O8-1600000)<1600000,0.21*(O8-1600000),336000)) -> 336000 | U8: =24%*(O8-3200000) -> 583746.25 | V8: =P8+Q8+R8+S8+T8+U8 -> 1143746.2 | W8: 12 | X8: =V8/W8 -> 95312.187 | Z8: =X8 -> 95312.187 | AA8: 27049.02 | AB8: =Z8+AA8 -> 122361.21 | AC8: WAZIRI USMAN
A9: 5 | B9: TAIWO I. OYINLOLA | C9: 189814.17 | D9: 12 | E9: =C9*D9 -> 2277770 | G9: 146701.6 | I9: =E9-F9-G9-H9 -> 2131068.4 | J9: 200000 | K9: 0.2 | L9: =I9*K9 -> 426213.68 | M9: =J9+L9 -> 626213.68 | N9: =F9+G9+H9+M9 -> 772915.28 | O9: =E9-N9 -> 1504854.7 | P9: =IF(O9<300000,0.07*O9,21000) -> 21000 | Q9: =IF((O9-300000)<0,0,IF((O9-300000)<300000,0.11*(O9-300000),33000)) -> 33000 | R9: =IF((O9-600000)<0,0,IF((O9-600000)<500000,0.15*(O9-600000),75000)) -> 75000 | S9: =IF((O9-1100000)<0,0,IF((O9-1100000)<500000,0.19*(O9-1100000),95000)) -> 76922.396 | T9: =IF((O9-1600000)<0,0,IF((O9-1600000)<1600000,0.21*(O9-1600000),336000)) -> 0 | V9: =P9+Q9+R9+S9+T9+U9 -> 205922.4 | W9: 12 | X9: =V9/W9 -> 17160.2 | Z9: =X9 -> 17160.2 | AA9: 0 | AB9: =Z9+AA9 -> 17160.2 | AC9: TAIWO I. OYINLOLA
A10: 6 | B10: SARATU ATAJIRI | C10: =255849+50000 -> 305849 | D10: 12 | E10: =C10*D10 -> 3670188 | G10: 245615.04 | I10: =E10-F10-G10-H10 -> 3424573 | J10: 200000 | K10: 0.2 | L10: =I10*K10 -> 684914.59 | M10: =J10+L10 -> 884914.59 | N10: =F10+G10+H10+M10 -> 1130529.6 | O10: =E10-N10 -> 2539658.4 | P10: =IF(O10<300000,0.07*O10,21000) -> 21000 | Q10: =IF((O10-300000)<0,0,IF((O10-300000)<300000,0.11*(O10-300000),33000)) -> 33000 | R10: =IF((O10-600000)<0,0,IF((O10-600000)<500000,0.15*(O10-600000),75000)) -> 75000 | S10: =IF((O10-1100000)<0,0,IF((O10-1100000)<500000,0.19*(O10-1100000),95000)) -> 95000 | T10: =IF((O10-1600000)<0,0,IF((O10-1600000)<1600000,0.21*(O10-1600000),336000)) -> 197328.26 | V10: =P10+Q10+R10+S10+T10+U10 -> 421328.26 | W10: 12 | X10: =V10/W10 -> 35110.688 | Z10: =X10 -> 35110.688 | AA10: 260200.89 | AB10: =Z10+AA10 -> 295311.58 | AC10: SARATU ATAJIRI
A11: 7 | B11: YUSIF SANI SADIQ | C11: 413512.5 | D11: 12 | E11: =C11*D11 -> 4962150 | G11: 339372 | I11: =E11-F11-G11-H11 -> 4622778 | J11: 200000 | K11: 0.2 | L11: =I11*K11 -> 924555.6 | M11: =J11+L11 -> 1124555.6 | N11: =F11+G11+H11+M11 -> 1463927.6 | O11: =E11-N11 -> 3498222.4 | P11: =IF(O11<300000,0.07*O11,21000) -> 21000 | Q11: =IF((O11-300000)<0,0,IF((O11-300000)<300000,0.11*(O11-300000),33000)) -> 33000 | R11: =IF((O11-600000)<0,0,IF((O11-600000)<500000,0.15*(O11-600000),75000)) -> 75000 | S11: =IF((O11-1100000)<0,0,IF((O11-1100000)<500000,0.19*(O11-1100000),95000)) -> 95000 | T11: =IF((O11-1600000)<0,0,IF((O11-1600000)<1600000,0.21*(O11-1600000),336000)) -> 336000 | U11: =24%*(O11-3200000) -> 71573.376 | V11: =P11+Q11+R11+S11+T11+U11 -> 631573.38 | W11: 12 | X11: =V11/W11 -> 52631.115 | Z11: =X11 -> 52631.115 | AA11: 5613.7772 | AB11: =Z11+AA11 -> 58244.892 | AC11: YUSIF SANI SADIQ
A12: 8 | B12: STELLA NGOZI PAUL | C12: 413512.5 | D12: 12 | E12: =C12*D12 -> 4962150 | G12: 339372 | I12: =E12-F12-G12-H12 -> 4622778 | J12: 200000 | K12: 0.2 | L12: =I12*K12 -> 924555.6 | M12: =J12+L12 -> 1124555.6 | N12: =F12+G12+H12+M12 -> 1463927.6 | O12: =E12-N12 -> 3498222.4 | P12: =IF(O12<300000,0.07*O12,21000) -> 21000 | Q12: =IF((O12-300000)<0,0,IF((O12-300000)<300000,0.11*(O12-300000),33000)) -> 33000 | R12: =IF((O12-600000)<0,0,IF((O12-600000)<500000,0.15*(O12-600000),75000)) -> 75000 | S12: =IF((O12-1100000)<0,0,IF((O12-1100000)<500000,0.19*(O12-1100000),95000)) -> 95000 | T12: =IF((O12-1600000)<0,0,IF((O12-1600000)<1600000,0.21*(O12-1600000),336000)) -> 336000 | U12: =24%*(O12-3200000) -> 71573.376 | V12: =P12+Q12+R12+S12+T12+U12 -> 631573.38 | W12: 12 | X12: =V12/W12 -> 52631.115 | Z12: =X12 -> 52631.115 | AA12: 3424.2125 | AB12: =Z12+AA12 -> 56055.327 | AC12: STELLA NGOZI PAUL
A13: 9 | B13: OMONIGHO EROMOSELE-WESEY | C13: 510248.92 | D13: 12 | E13: =C13*D13 -> 6122987 | F13: =6922.5*12 -> 83070 | G13: 374638.96 | I13: =E13-F13-G13-H13 -> 5665278 | J13: 200000 | K13: 0.2 | L13: =I13*K13 -> 1133055.6 | M13: =J13+L13 -> 1333055.6 | N13: =F13+G13+H13+M13 -> 1790764.6 | O13: =E13-N13 -> 4332222.4 | P13: =IF(O13<300000,0.07*O13,21000) -> 21000 | Q13: =IF((O13-300000)<0,0,IF((O13-300000)<300000,0.11*(O13-300000),33000)) -> 33000 | R13: =IF((O13-600000)<0,0,IF((O13-600000)<500000,0.15*(O13-600000),75000)) -> 75000 | S13: =IF((O13-1100000)<0,0,IF((O13-1100000)<500000,0.19*(O13-1100000),95000)) -> 95000 | T13: =IF((O13-1600000)<0,0,IF((O13-1600000)<1600000,0.21*(O13-1600000),336000)) -> 336000 | U13: =24%*(O13-3200000) -> 271733.38 | V13: =P13+Q13+R13+S13+T13+U13 -> 831733.38 | W13: 12 | X13: =V13/W13 -> 69311.115 | Z13: =X13 -> 69311.115 | AA13: 63752.795 | AB13: =Z13+AA13 -> 133063.91 | AC13: OMONIGHO EROMOSELE-WESEY
A14: 10 | B14: QUEEN ONYEKESON | C14: 510248.92 | D14: 12 | E14: =C14*D14 -> 6122987 | G14: 374638.96 | I14: =E14-F14-G14-H14 -> 5748348 | J14: 200000 | K14: 0.2 | L14: =I14*K14 -> 1149669.6 | M14: =J14+L14 -> 1349669.6 | N14: =F14+G14+H14+M14 -> 1724308.6 | O14: =E14-N14 -> 4398678.4 | P14: =IF(O14<300000,0.07*O14,21000) -> 21000 | Q14: =IF((O14-300000)<0,0,IF((O14-300000)<300000,0.11*(O14-300000),33000)) -> 33000 | R14: =IF((O14-600000)<0,0,IF((O14-600000)<500000,0.15*(O14-600000),75000)) -> 75000 | S14: =IF((O14-1100000)<0,0,IF((O14-1100000)<500000,0.19*(O14-1100000),95000)) -> 95000 | T14: =IF((O14-1600000)<0,0,IF((O14-1600000)<1600000,0.21*(O14-1600000),336000)) -> 336000 | U14: =24%*(O14-3200000) -> 287682.82 | V14: =P14+Q14+R14+S14+T14+U14 -> 847682.82 | W14: 12 | X14: =V14/W14 -> 70640.235 | Z14: =X14 -> 70640.235 | AA14: 10318.428 | AB14: =Z14+AA14 -> 80958.664 | AC14: QUEEN ONYEKESON
A15: 11 | B15: SHAMSUDEEN YAHAYA | C15: 742118 | D15: 12 | E15: =C15*D15 -> 8905416 | G15: 558833.36 | I15: =E15-F15-G15-H15 -> 8346582.6 | J15: 200000 | K15: 0.2 | L15: =I15*K15 -> 1669316.5 | M15: =J15+L15 -> 1869316.5 | N15: =F15+G15+H15+M15 -> 2428149.9 | O15: =E15-N15 -> 6477266.1 | P15: =IF(O15<300000,0.07*O15,21000) -> 21000 | Q15: =IF((O15-300000)<0,0,IF((O15-300000)<300000,0.11*(O15-300000),33000)) -> 33000 | R15: =IF((O15-600000)<0,0,IF((O15-600000)<500000,0.15*(O15-600000),75000)) -> 75000 | S15: =IF((O15-1100000)<0,0,IF((O15-1100000)<500000,0.19*(O15-1100000),95000)) -> 95000 | T15: =IF((O15-1600000)<0,0,IF((O15-1600000)<1600000,0.21*(O15-1600000),336000)) -> 336000 | U15: =24%*(O15-3200000) -> 786543.87 | V15: =P15+Q15+R15+S15+T15+U15 -> 1346543.9 | W15: 12 | X15: =V15/W15 -> 112211.99 | Z15: =X15 -> 112211.99 | AA15: 45679.48 | AB15: =Z15+AA15 -> 157891.47 | AC15: SHAMSUDEEN YAHAYA
A16: 12 | B16: SALAMATU YAKUBU | C16: 662118 | D16: 12 | E16: =C16*D16 -> 7945416 | F16: =8019.8*12 -> 96237.6 | G16: 558833.36 | I16: =E16-F16-G16-H16 -> 7290345 | J16: 200000 | K16: 0.2 | L16: =I16*K16 -> 1458069 | M16: =J16+L16 -> 1658069 | N16: =F16+G16+H16+M16 -> 2313140 | O16: =E16-N16 -> 5632276 | P16: =IF(O16<300000,0.07*O16,21000) -> 21000 | Q16: =IF((O16-300000)<0,0,IF((O16-300000)<300000,0.11*(O16-300000),33000)) -> 33000 | R16: =IF((O16-600000)<0,0,IF((O16-600000)<500000,0.15*(O16-600000),75000)) -> 75000 | S16: =IF((O16-1100000)<0,0,IF((O16-1100000)<500000,0.19*(O16-1100000),95000)) -> 95000 | T16: =IF((O16-1600000)<0,0,IF((O16-1600000)<1600000,0.21*(O16-1600000),336000)) -> 336000 | U16: =24%*(O16-3200000) -> 583746.25 | V16: =P16+Q16+R16+S16+T16+U16 -> 1143746.2 | W16: 12 | X16: =V16/W16 -> 95312.187 | Z16: =X16 -> 95312.187 | AA16: 32298.775 | AB16: =Z16+AA16 -> 127610.96 | AC16: SALAMATU YAKUBU
A17: 13 | B17: ROTIMI OGUNYOMI | C17: 510248.92 | D17: 12 | E17: =C17*D17 -> 6122987 | G17: 374638.96 | I17: =E17-F17-G17-H17 -> 5748348 | J17: 200000 | K17: 0.2 | L17: =I17*K17 -> 1149669.6 | M17: =J17+L17 -> 1349669.6 | N17: =F17+G17+H17+M17 -> 1724308.6 | O17: =E17-N17 -> 4398678.4 | P17: =IF(O17<300000,0.07*O17,21000) -> 21000 | Q17: =IF((O17-300000)<0,0,IF((O17-300000)<300000,0.11*(O17-300000),33000)) -> 33000 | R17: =IF((O17-600000)<0,0,IF((O17-600000)<500000,0.15*(O17-600000),75000)) -> 75000 | S17: =IF((O17-1100000)<0,0,IF((O17-1100000)<500000,0.19*(O17-1100000),95000)) -> 95000 | T17: =IF((O17-1600000)<0,0,IF((O17-1600000)<1600000,0.21*(O17-1600000),336000)) -> 336000 | U17: =24%*(O17-3200000) -> 287682.82 | V17: =P17+Q17+R17+S17+T17+U17 -> 847682.82 | W17: 12 | X17: =V17/W17 -> 70640.235 | Z17: =X17 -> 70640.235 | AA17: 12855.302 | AB17: =Z17+AA17 -> 83495.537 | AC17: ROTIMI OGUNYOMI
A18: 14 | B18: LEO IGBANOI | C18: 582746.5 | D18: 12 | E18: =C18*D18 -> 6992958 | G18: 425036.64 | I18: =E18-F18-G18-H18 -> 6567921.4 | J18: 200000 | K18: 0.2 | L18: =I18*K18 -> 1313584.3 | M18: =J18+L18 -> 1513584.3 | N18: =F18+G18+H18+M18 -> 1938620.9 | O18: =E18-N18 -> 5054337.1 | P18: =IF(O18<300000,0.07*O18,21000) -> 21000 | Q18: =IF((O18-300000)<0,0,IF((O18-300000)<300000,0.11*(O18-300000),33000)) -> 33000 | R18: =IF((O18-600000)<0,0,IF((O18-600000)<500000,0.15*(O18-600000),75000)) -> 75000 | S18: =IF((O18-1100000)<0,0,IF((O18-1100000)<500000,0.19*(O18-1100000),95000)) -> 95000 | T18: =IF((O18-1600000)<0,0,IF((O18-1600000)<1600000,0.21*(O18-1600000),336000)) -> 336000 | U18: =24%*(O18-3200000) -> 445040.9 | V18: =P18+Q18+R18+S18+T18+U18 -> 1005040.9 | W18: 12 | X18: =V18/W18 -> 83753.408 | Z18: =X18 -> 83753.408 | AA18: 101775.52 | AB18: =Z18+AA18 -> 185528.93 | AC18: LEO IGBANOI
A19: 15 | B19: TOSIN OWOEYE | C19: 413512.5 | D19: 12 | E19: =C19*D19 -> 4962150 | G19: 339372 | I19: =E19-F19-G19-H19 -> 4622778 | J19: 200000 | K19: 0.2 | L19: =I19*K19 -> 924555.6 | M19: =J19+L19 -> 1124555.6 | N19: =F19+G19+H19+M19 -> 1463927.6 | O19: =E19-N19 -> 3498222.4 | P19: =IF(O19<300000,0.07*O19,21000) -> 21000 | Q19: =IF((O19-300000)<0,0,IF((O19-300000)<300000,0.11*(O19-300000),33000)) -> 33000 | R19: =IF((O19-600000)<0,0,IF((O19-600000)<500000,0.15*(O19-600000),75000)) -> 75000 | S19: =IF((O19-1100000)<0,0,IF((O19-1100000)<500000,0.19*(O19-1100000),95000)) -> 95000 | T19: =IF((O19-1600000)<0,0,IF((O19-1600000)<1600000,0.21*(O19-1600000),336000)) -> 336000 | U19: =24%*(O19-3200000) -> 71573.376 | V19: =P19+Q19+R19+S19+T19+U19 -> 631573.38 | W19: 12 | X19: =V19/W19 -> 52631.115 | Z19: =X19 -> 52631.115 | AA19: 50324.523 | AB19: =Z19+AA19 -> 102955.64 | AC19: TOSIN OWOEYE
A20: 16 | B20: STACY CHINYERE IGWE | C20: =353512.5+110000 -> 463512.5 | D20: 12 | E20: =C20*D20 -> 5562150 | G20: 339372 | I20: =E20-F20-G20-H20 -> 5222778 | J20: 200000 | K20: 0.2 | L20: =I20*K20 -> 1044555.6 | M20: =J20+L20 -> 1244555.6 | N20: =F20+G20+H20+M20 -> 1583927.6 | O20: =E20-N20 -> 3978222.4 | P20: =IF(O20<300000,0.07*O20,21000) -> 21000 | Q20: =IF((O20-300000)<0,0,IF((O20-300000)<300000,0.11*(O20-300000),33000)) -> 33000 | R20: =IF((O20-600000)<0,0,IF((O20-600000)<500000,0.15*(O20-600000),75000)) -> 75000 | S20: =IF((O20-1100000)<0,0,IF((O20-1100000)<500000,0.19*(O20-1100000),95000)) -> 95000 | T20: =IF((O20-1600000)<0,0,IF((O20-1600000)<1600000,0.21*(O20-1600000),336000)) -> 336000 | U20: =24%*(O20-3200000) -> 186773.38 | V20: =P20+Q20+R20+S20+T20+U20 -> 746773.38 | W20: 12 | X20: =V20/W20 -> 62231.115 | Z20: =X20 -> 62231.115 | AA20: 19114.051 | AB20: =Z20+AA20 -> 81345.165 | AC20: STACY CHINYERE IGWE
A21: 17 | B21: TANIMU M. LAWAL | C21: 189814.17 | D21: 12 | E21: =C21*D21 -> 2277770 | G21: 146701.6 | I21: =E21-F21-G21-H21 -> 2131068.4 | J21: 200000 | K21: 0.2 | L21: =I21*K21 -> 426213.68 | M21: =J21+L21 -> 626213.68 | N21: =F21+G21+H21+M21 -> 772915.28 | O21: =E21-N21 -> 1504854.7 | P21: =IF(O21<300000,0.07*O21,21000) -> 21000 | Q21: =IF((O21-300000)<0,0,IF((O21-300000)<300000,0.11*(O21-300000),33000)) -> 33000 | R21: =IF((O21-600000)<0,0,IF((O21-600000)<500000,0.15*(O21-600000),75000)) -> 75000 | S21: =IF((O21-1100000)<0,0,IF((O21-1100000)<500000,0.19*(O21-1100000),95000)) -> 76922.396 | T21: =IF((O21-1600000)<0,0,IF((O21-1600000)<1600000,0.21*(O21-1600000),336000)) -> 0 | V21: =P21+Q21+R21+S21+T21+U21 -> 205922.4 | W21: 12 | X21: =V21/W21 -> 17160.2 | Z21: =X21 -> 17160.2 | AA21: 3736.9329 | AB21: =Z21+AA21 -> 20897.133 | AC21: TANIMU M. LAWAL
A22: 18 | B22: CHRISTIAN MADUABUCHI ODO | C22: 510248.92 | D22: 12 | E22: =C22*D22 -> 6122987 | F22: =6922.5*12 -> 83070 | G22: 374638.96 | I22: =E22-F22-G22-H22 -> 5665278 | J22: 200000 | K22: 0.2 | L22: =I22*K22 -> 1133055.6 | M22: =J22+L22 -> 1333055.6 | N22: =F22+G22+H22+M22 -> 1790764.6 | O22: =E22-N22 -> 4332222.4 | P22: =IF(O22<300000,0.07*O22,21000) -> 21000 | Q22: =IF((O22-300000)<0,0,IF((O22-300000)<300000,0.11*(O22-300000),33000)) -> 33000 | R22: =IF((O22-600000)<0,0,IF((O22-600000)<500000,0.15*(O22-600000),75000)) -> 75000 | S22: =IF((O22-1100000)<0,0,IF((O22-1100000)<500000,0.19*(O22-1100000),95000)) -> 95000 | T22: =IF((O22-1600000)<0,0,IF((O22-1600000)<1600000,0.21*(O22-1600000),336000)) -> 336000 | U22: =24%*(O22-3200000) -> 271733.38 | V22: =P22+Q22+R22+S22+T22+U22 -> 831733.38 | W22: 12 | X22: =V22/W22 -> 69311.115 | Z22: =X22 -> 69311.115 | AA22: 11803.082 | AB22: =Z22+AA22 -> 81114.197 | AC22: CHRISTIAN MADUABUCHI ODO
B23: TOTAL - ANNUAL | C23: =SUM(C5:C22) -> 9295977.5 | F23: =SUM(F5:F22) -> 454852.8 | G23: =SUM(G5:G22) -> 7173098.9 | V23: =SUM(V5:V22) -> 15470690 | X23: =SUM(X5:X22) -> 1289224.2 | Z23: =SUM(Z5:Z22) -> 1289224.2
B24: TOTAL - MONTHLY | F24: =F23/12 -> 37904.4 | G24: =G23/12 -> 597758.24 | V24: =V23/12 -> 1289224.2
Z26: 11287301

Sheet Tax on Arrears
A1: NATIONAL INSTITUTE FOR LEGISLATIVE AND DEMOCRATIC STUDIES
A2: NATIONAL ASSEMBLY ABUJA
A3: TAX COMPUTATION FOR 2022
A4: S/NO | B4: NAME | C4: ARREARS OF PROMOTION | D4: NO OF MONTHS | E4: ANNUAL SALARY GROSSED UP | F4: NATIONAL HOUSING SCHEME = 2.5% OF BASIC SALARY | G4: PENSION CONTRIBUTION = 8% OF CONSOLIDATED | H4: NHIS | I4: NET SALARY (EXC OF CRA) | M4: CRA=#200,000+(20% 0F NET SALARY (EXC OF CRA) | N4: TOTAL RELIEF | O4: CHARGEABLE INCOME | P4: FIRST N300,000 @ 7% | Q4: NEXT N300,000 @ 11% | R4: NEXT N500,000 @ 15% | S4: NEXT N500,000@ 19% | T4: NEXT N1,600,000 @ 21% | U4: ABOVE N3,200,000 @ 24% | V4: ANNUAL TAX PAYABLE | X4: MONTHLY TAX PAYABLE | Y4: MINIMUM TAX PAYABLE | Z4: TAX PAYABLE ON ARREARS
A5: 1 | B5: ABDULSALAM MUSTAPHA | C5: 150313.08 | D5: 12 | E5: =C5*D5 -> 1803757 | G5: 558833.36 | I5: =E5-F5-G5-H5 -> 1244923.6 | J5: 200000 | K5: 0.2 | L5: =I5*K5 -> 248984.72 | M5: =J5+L5 -> 448984.72 | N5: =F5+G5+H5+M5 -> 1007818.1 | O5: =E5-N5 -> 795938.88 | P5: =IF(O5<300000,0.07*O5,21000) -> 21000 | Q5: =IF((O5-300000)<0,0,IF((O5-300000)<300000,0.11*(O5-300000),33000)) -> 33000 | R5: =IF((O5-600000)<0,0,IF((O5-600000)<500000,0.15*(O5-600000),75000)) -> 29390.832 | S5: =IF((O5-1100000)<0,0,IF((O5-1100000)<500000,0.19*(O5-1100000),95000)) -> 0 | T5: =IF((O5-1600000)<0,0,IF((O5-1600000)<1600000,0.21*(O5-1600000),336000)) -> 0 | U5: 0 | V5: =P5+Q5+R5+S5+T5+U5 -> 83390.832 | W5: 12 | X5: =V5/W5 -> 6949.236 | Z5: =X5 -> 6949.236
A6: 2 | B6: EMILY EDIOSA IKHIDE | C6: 526480 | D6: 12 | E6: =C6*D6 -> 6317760 | G6: 558833.36 | I6: =E6-F6-G6-H6 -> 5758926.6 | J6: 200000 | K6: 0.2 | L6: =I6*K6 -> 1151785.3 | M6: =J6+L6 -> 1351785.3 | N6: =F6+G6+H6+M6 -> 1910618.7 | O6: =E6-N6 -> 4407141.3 | P6: =IF(O6<300000,0.07*O6,21000) -> 21000 | Q6: =IF((O6-300000)<0,0,IF((O6-300000)<300000,0.11*(O6-300000),33000)) -> 33000 | R6: =IF((O6-600000)<0,0,IF((O6-600000)<500000,0.15*(O6-600000),75000)) -> 75000 | S6: =IF((O6-1100000)<0,0,IF((O6-1100000)<500000,0.19*(O6-1100000),95000)) -> 95000 | T6: =IF((O6-1600000)<0,0,IF((O6-1600000)<1600000,0.21*(O6-1600000),336000)) -> 336000 | U6: =24%*(O6-3200000) -> 289713.92 | V6: =P6+Q6+R6+S6+T6+U6 -> 849713.92 | W6: 12 | X6: =V6/W6 -> 70809.493 | Z6: =X6 -> 70809.493
A7: 3 | B7: SIMON WAKAWA | C7: 291986.92 | D7: 12 | E7: =C7*D7 -> 3503843 | F7: =8019.8*12 -> 96237.6 | G7: 558833.36 | I7: =E7-F7-G7-H7 -> 2848772.1 | J7: 200000 | K7: 0.2 | L7: =I7*K7 -> 569754.41 | M7: =J7+L7 -> 769754.41 | N7: =F7+G7+H7+M7 -> 1424825.4 | O7: =E7-N7 -> 2079017.6 | P7: =IF(O7<300000,0.07*O7,21000) -> 21000 | Q7: =IF((O7-300000)<0,0,IF((O7-300000)<300000,0.11*(O7-300000),33000)) -> 33000 | R7: =IF((O7-600000)<0,0,IF((O7-600000)<500000,0.15*(O7-600000),75000)) -> 75000 | S7: =IF((O7-1100000)<0,0,IF((O7-1100000)<500000,0.19*(O7-1100000),95000)) -> 95000 | T7: =IF((O7-1600000)<0,0,IF((O7-1600000)<1600000,0.21*(O7-1600000),336000)) -> 100593.7 | V7: =P7+Q7+R7+S7+T7+U7 -> 324593.7 | W7: 12 | X7: =V7/W7 -> 27049.475 | Z7: =X7 -> 27049.475
A8: 4 | B8: WAZIRI USMAN | C8: 291984.21 | D8: 12 | E8: =C8*D8 -> 3503810.5 | F8: =8019.8*12 -> 96237.6 | G8: 558833.36 | I8: =E8-F8-G8-H8 -> 2848739.5 | J8: 200000 | K8: 0.2 | L8: =I8*K8 -> 569747.91 | M8: =J8+L8 -> 769747.91 | N8: =F8+G8+H8+M8 -> 1424818.9 | O8: =E8-N8 -> 2078991.6 | P8: =IF(O8<300000,0.07*O8,21000) -> 21000 | Q8: =IF((O8-300000)<0,0,IF((O8-300000)<300000,0.11*(O8-300000),33000)) -> 33000 | R8: =IF((O8-600000)<0,0,IF((O8-600000)<500000,0.15*(O8-600000),75000)) -> 75000 | S8: =IF((O8-1100000)<0,0,IF((O8-1100000)<500000,0.19*(O8-1100000),95000)) -> 95000 | T8: =IF((O8-1600000)<0,0,IF((O8-1600000)<1600000,0.21*(O8-1600000),336000)) -> 100588.24 | V8: =P8+Q8+R8+S8+T8+U8 -> 324588.24 | W8: 12 | X8: =V8/W8 -> 27049.02 | Z8: =X8 -> 27049.02
A9: 5 | B9: TAIWO I. OYINLOLA | C9: 0 | D9: 0 | E9: =C9*D9 -> 0 | G9: 0 | I9: =E9-F9-G9-H9 -> 0 | J9: 0 | K9: 0.2 | L9: =I9*K9 -> 0 | M9: =J9+L9 -> 0 | N9: =F9+G9+H9+M9 -> 0 | O9: =E9-N9 -> 0 | P9: =IF(O9<300000,0.07*O9,21000) -> 0 | Q9: =IF((O9-300000)<0,0,IF((O9-300000)<300000,0.11*(O9-300000),33000)) -> 0 | R9: =IF((O9-600000)<0,0,IF((O9-600000)<500000,0.15*(O9-600000),75000)) -> 0 | S9: =IF((O9-1100000)<0,0,IF((O9-1100000)<500000,0.19*(O9-1100000),95000)) -> 0 | T9: =IF((O9-1600000)<0,0,IF((O9-1600000)<1600000,0.21*(O9-1600000),336000)) -> 0 | V9: =P9+Q9+R9+S9+T9+U9 -> 0 | W9: 12 | X9: =V9/W9 -> 0 | Z9: =X9 -> 0
A10: 6 | B10: SARATU ATAJIRI | C10: 1486792 | D10: 12 | E10: =C10*D10 -> 17841504 | G10: 245615.04 | I10: =E10-F10-G10-H10 -> 17595889 | J10: 200000 | K10: 0.2 | L10: =I10*K10 -> 3519177.8 | M10: =J10+L10 -> 3719177.8 | N10: =F10+G10+H10+M10 -> 3964792.8 | O10: =E10-N10 -> 13876711 | P10: =IF(O10<300000,0.07*O10,21000) -> 21000 | Q10: =IF((O10-300000)<0,0,IF((O10-300000)<300000,0.11*(O10-300000),33000)) -> 33000 | R10: =IF((O10-600000)<0,0,IF((O10-600000)<500000,0.15*(O10-600000),75000)) -> 75000 | S10: =IF((O10-1100000)<0,0,IF((O10-1100000)<500000,0.19*(O10-1100000),95000)) -> 95000 | T10: =IF((O10-1600000)<0,0,IF((O10-1600000)<1600000,0.21*(O10-1600000),336000)) -> 336000 | U10: =24%*(O10-3200000) -> 2562410.7 | V10: =P10+Q10+R10+S10+T10+U10 -> 3122410.7 | W10: 12 | X10: =V10/W10 -> 260200.89 | Z10: =X10 -> 260200.89
A11: 7 | B11: YUSIF SANI SADIQ | C11: 120895.81 | D11: 12 | E11: =C11*D11 -> 1450749.7 | G11: 339372 | I11: =E11-F11-G11-H11 -> 1111377.7 | J11: 200000 | K11: 0.2 | L11: =I11*K11 -> 222275.54 | M11: =J11+L11 -> 422275.54 | N11: =F11+G11+H11+M11 -> 761647.54 | O11: =E11-N11 -> 689102.18 | P11: =IF(O11<300000,0.07*O11,21000) -> 21000 | Q11: =IF((O11-300000)<0,0,IF((O11-300000)<300000,0.11*(O11-300000),33000)) -> 33000 | R11: =IF((O11-600000)<0,0,IF((O11-600000)<500000,0.15*(O11-600000),75000)) -> 13365.326 | S11: =IF((O11-1100000)<0,0,IF((O11-1100000)<500000,0.19*(O11-1100000),95000)) -> 0 | T11: =IF((O11-1600000)<0,0,IF((O11-1600000)<1600000,0.21*(O11-1600000),336000)) -> 0 | V11: =P11+Q11+R11+S11+T11+U11 -> 67365.326 | W11: 12 | X11: =V11/W11 -> 5613.7772 | Z11: =X11 -> 5613.7772
A12: 8 | B12: STELLA NGOZI PAUL | C12: 99389.476 | D12: 12 | E12: =C12*D12 -> 1192673.7 | G12: 339372 | I12: =E12-F12-G12-H12 -> 853301.71 | J12: 200000 | K12: 0.2 | L12: =I12*K12 -> 170660.34 | M12: =J12+L12 -> 370660.34 | N12: =F12+G12+H12+M12 -> 710032.34 | O12: =E12-N12 -> 482641.37 | P12: =IF(O12<300000,0.07*O12,21000) -> 21000 | Q12: =IF((O12-300000)<0,0,IF((O12-300000)<300000,0.11*(O12-300000),33000)) -> 20090.55 | R12: =IF((O12-600000)<0,0,IF((O12-600000)<500000,0.15*(O12-600000),75000)) -> 0 | S12: =IF((O12-1100000)<0,0,IF((O12-1100000)<500000,0.19*(O12-1100000),95000)) -> 0 | T12: =IF((O12-1600000)<0,0,IF((O12-1600000)<1600000,0.21*(O12-1600000),336000)) -> 0 | V12: =P12+Q12+R12+S12+T12+U12 -> 41090.55 | W12: 12 | X12: =V12/W12 -> 3424.2125 | Z12: =X12 -> 3424.2125
A13: 9 | B13: OMONIGHO EROMOSELE-WESEY | C13: 481299.33 | D13: 12 | E13: =C13*D13 -> 5775592 | F13: =6922.5*12 -> 83070 | G13: 374638.96 | I13: =E13-F13-G13-H13 -> 5317883 | J13: 200000 | K13: 0.2 | L13: =I13*K13 -> 1063576.6 | M13: =J13+L13 -> 1263576.6 | N13: =F13+G13+H13+M13 -> 1721285.6 | O13: =E13-N13 -> 4054306.4 | P13: =IF(O13<300000,0.07*O13,21000) -> 21000 | Q13: =IF((O13-300000)<0,0,IF((O13-300000)<300000,0.11*(O13-300000),33000)) -> 33000 | R13: =IF((O13-600000)<0,0,IF((O13-600000)<500000,0.15*(O13-600000),75000)) -> 75000 | S13: =IF((O13-1100000)<0,0,IF((O13-1100000)<500000,0.19*(O13-1100000),95000)) -> 95000 | T13: =IF((O13-1600000)<0,0,IF((O13-1600000)<1600000,0.21*(O13-1600000),336000)) -> 336000 | U13: =24%*(O13-3200000) -> 205033.54 | V13: =P13+Q13+R13+S13+T13+U13 -> 765033.54 | W13: 12 | X13: =V13/W13 -> 63752.795 | Z13: =X13 -> 63752.795
A14: 10 | B14: QUEEN ONYEKESON | C14: 163040.15 | D14: 12 | E14: =C14*D14 -> 1956481.8 | G14: 374638.96 | I14: =E14-F14-G14-H14 -> 1581842.8 | J14: 200000 | K14: 0.2 | L14: =I14*K14 -> 316368.57 | M14: =J14+L14 -> 516368.57 | N14: =F14+G14+H14+M14 -> 891007.53 | O14: =E14-N14 -> 1065474.3 | P14: =IF(O14<300000,0.07*O14,21000) -> 21000 | Q14: =IF((O14-300000)<0,0,IF((O14-300000)<300000,0.11*(O14-300000),33000)) -> 33000 | R14: =IF((O14-600000)<0,0,IF((O14-600000)<500000,0.15*(O14-600000),75000)) -> 69821.139 | S14: =IF((O14-1100000)<0,0,IF((O14-1100000)<500000,0.19*(O14-1100000),95000)) -> 0 | T14: =IF((O14-1600000)<0,0,IF((O14-1600000)<1600000,0.21*(O14-1600000),336000)) -> 0 | V14: =P14+Q14+R14+S14+T14+U14 -> 123821.14 | W14: 12 | X14: =V14/W14 -> 10318.428 | Z14: =X14 -> 10318.428
A15: 11 | B15: SHAMSUDEEN YAHAYA | C15: 394860 | D15: 12 | E15: =C15*D15 -> 4738320 | G15: 558833.36 | I15: =E15-F15-G15-H15 -> 4179486.6 | J15: 200000 | K15: 0.2 | L15: =I15*K15 -> 835897.33 | M15: =J15+L15 -> 1035897.3 | N15: =F15+G15+H15+M15 -> 1594730.7 | O15: =E15-N15 -> 3143589.3 | P15: =IF(O15<300000,0.07*O15,21000) -> 21000 | Q15: =IF((O15-300000)<0,0,IF((O15-300000)<300000,0.11*(O15-300000),33000)) -> 33000 | R15: =IF((O15-600000)<0,0,IF((O15-600000)<500000,0.15*(O15-600000),75000)) -> 75000 | S15: =IF((O15-1100000)<0,0,IF((O15-1100000)<500000,0.19*(O15-1100000),95000)) -> 95000 | T15: =IF((O15-1600000)<0,0,IF((O15-1600000)<1600000,0.21*(O15-1600000),336000)) -> 324153.76 | V15: =P15+Q15+R15+S15+T15+U15 -> 548153.76 | W15: 12 | X15: =V15/W15 -> 45679.48 | Z15: =X15 -> 45679.48
A16: 12 | B16: SALAMATU YAKUBU | C16: 323232.75 | D16: 12 | E16: =C16*D16 -> 3878793 | F16: =8019.8*12 -> 96237.6 | G16: 558833.36 | I16: =E16-F16-G16-H16 -> 3223722 | J16: 200000 | K16: 0.2 | L16: =I16*K16 -> 644744.41 | M16: =J16+L16 -> 844744.41 | N16: =F16+G16+H16+M16 -> 1499815.4 | O16: =E16-N16 -> 2378977.6 | P16: =IF(O16<300000,0.07*O16,21000) -> 21000 | Q16: =IF((O16-300000)<0,0,IF((O16-300000)<300000,0.11*(O16-300000),33000)) -> 33000 | R16: =IF((O16-600000)<0,0,IF((O16-600000)<500000,0.15*(O16-600000),75000)) -> 75000 | S16: =IF((O16-1100000)<0,0,IF((O16-1100000)<500000,0.19*(O16-1100000),95000)) -> 95000 | T16: =IF((O16-1600000)<0,0,IF((O16-1600000)<1600000,0.21*(O16-1600000),336000)) -> 163585.3 | V16: =P16+Q16+R16+S16+T16+U16 -> 387585.3 | W16: 12 | X16: =V16/W16 -> 32298.775 | Z16: =X16 -> 32298.775
A17: 13 | B17: ROTIMI OGUNYOMI | C17: 180487.25 | D17: 12 | E17: =C17*D17 -> 2165847 | G17: 374638.96 | I17: =E17-F17-G17-H17 -> 1791208 | J17: 200000 | K17: 0.2 | L17: =I17*K17 -> 358241.61 | M17: =J17+L17 -> 558241.61 | N17: =F17+G17+H17+M17 -> 932880.57 | O17: =E17-N17 -> 1232966.4 | P17: =IF(O17<300000,0.07*O17,21000) -> 21000 | Q17: =IF((O17-300000)<0,0,IF((O17-300000)<300000,0.11*(O17-300000),33000)) -> 33000 | R17: =IF((O17-600000)<0,0,IF((O17-600000)<500000,0.15*(O17-600000),75000)) -> 75000 | S17: =IF((O17-1100000)<0,0,IF((O17-1100000)<500000,0.19*(O17-1100000),95000)) -> 25263.622 | T17: =IF((O17-1600000)<0,0,IF((O17-1600000)<1600000,0.21*(O17-1600000),336000)) -> 0 | V17: =P17+Q17+R17+S17+T17+U17 -> 154263.62 | W17: 12 | X17: =V17/W17 -> 12855.302 | Z17: =X17 -> 12855.302
A18: 14 | B18: LEO IGBANOI | C18: 676611.67 | D18: 12 | E18: =C18*D18 -> 8119340 | G18: 425036.64 | I18: =E18-F18-G18-H18 -> 7694303.4 | J18: 200000 | K18: 0.2 | L18: =I18*K18 -> 1538860.7 | M18: =J18+L18 -> 1738860.7 | N18: =F18+G18+H18+M18 -> 2163897.3 | O18: =E18-N18 -> 5955442.7 | P18: =IF(O18<300000,0.07*O18,21000) -> 21000 | Q18: =IF((O18-300000)<0,0,IF((O18-300000)<300000,0.11*(O18-300000),33000)) -> 33000 | R18: =IF((O18-600000)<0,0,IF((O18-600000)<500000,0.15*(O18-600000),75000)) -> 75000 | S18: =IF((O18-1100000)<0,0,IF((O18-1100000)<500000,0.19*(O18-1100000),95000)) -> 95000 | T18: =IF((O18-1600000)<0,0,IF((O18-1600000)<1600000,0.21*(O18-1600000),336000)) -> 336000 | U18: =24%*(O18-3200000) -> 661306.25 | V18: =P18+Q18+R18+S18+T18+U18 -> 1221306.2 | W18: 12 | X18: =V18/W18 -> 101775.52 | Z18: =X18 -> 101775.52
A19: 15 | B19: LOHNA BONKAT JONATHAN | C19: 575119.92 | D19: 12 | E19: =C19*D19 -> 6901439 | G19: 425036.64 | I19: =E19-F19-G19-H19 -> 6476402.4 | J19: 200000 | K19: 0.2 | L19: =I19*K19 -> 1295280.5 | M19: =J19+L19 -> 1495280.5 | N19: =F19+G19+H19+M19 -> 1920317.1 | O19: =E19-N19 -> 4981121.9 | P19: =IF(O19<300000,0.07*O19,21000) -> 21000 | Q19: =IF((O19-300000)<0,0,IF((O19-300000)<300000,0.11*(O19-300000),33000)) -> 33000 | R19: =IF((O19-600000)<0,0,IF((O19-600000)<500000,0.15*(O19-600000),75000)) -> 75000 | S19: =IF((O19-1100000)<0,0,IF((O19-1100000)<500000,0.19*(O19-1100000),95000)) -> 95000 | T19: =IF((O19-1600000)<0,0,IF((O19-1600000)<1600000,0.21*(O19-1600000),336000)) -> 336000 | U19: =24%*(O19-3200000) -> 427469.25 | V19: =P19+Q19+R19+S19+T19+U19 -> 987469.25 | W19: 12 | X19: =V19/W19 -> 82289.104 | Z19: =X19 -> 82289.104
A20: 16 | B20: TOSIN OWOEYE | C20: 401499 | D20: 12 | E20: =C20*D20 -> 4817988 | G20: 339372 | I20: =E20-F20-G20-H20 -> 4478616 | J20: 200000 | K20: 0.2 | L20: =I20*K20 -> 895723.2 | M20: =J20+L20 -> 1095723.2 | N20: =F20+G20+H20+M20 -> 1435095.2 | O20: =E20-N20 -> 3382892.8 | P20: =IF(O20<300000,0.07*O20,21000) -> 21000 | Q20: =IF((O20-300000)<0,0,IF((O20-300000)<300000,0.11*(O20-300000),33000)) -> 33000 | R20: =IF((O20-600000)<0,0,IF((O20-600000)<500000,0.15*(O20-600000),75000)) -> 75000 | S20: =IF((O20-1100000)<0,0,IF((O20-1100000)<500000,0.19*(O20-1100000),95000)) -> 95000 | T20: =IF((O20-1600000)<0,0,IF((O20-1600000)<1600000,0.21*(O20-1600000),336000)) -> 336000 | U20: =24%*(O20-3200000) -> 43894.272 | V20: =P20+Q20+R20+S20+T20+U20 -> 603894.27 | W20: 12 | X20: =V20/W20 -> 50324.523 | Z20: =X20 -> 50324.523
A21: 17 | B21: STACY CHINYERE IGWE | C21: 218444 | D21: 12 | E21: =C21*D21 -> 2621328 | G21: 339372 | I21: =E21-F21-G21-H21 -> 2281956 | J21: 200000 | K21: 0.2 | L21: =I21*K21 -> 456391.2 | M21: =J21+L21 -> 656391.2 | N21: =F21+G21+H21+M21 -> 995763.2 | O21: =E21-N21 -> 1625564.8 | P21: =IF(O21<300000,0.07*O21,21000) -> 21000 | Q21: =IF((O21-300000)<0,0,IF((O21-300000)<300000,0.11*(O21-300000),33000)) -> 33000 | R21: =IF((O21-600000)<0,0,IF((O21-600000)<500000,0.15*(O21-600000),75000)) -> 75000 | S21: =IF((O21-1100000)<0,0,IF((O21-1100000)<500000,0.19*(O21-1100000),95000)) -> 95000 | T21: =IF((O21-1600000)<0,0,IF((O21-1600000)<1600000,0.21*(O21-1600000),336000)) -> 5368.608 | V21: =P21+Q21+R21+S21+T21+U21 -> 229368.61 | W21: 12 | X21: =V21/W21 -> 19114.051 | Z21: =X21 -> 19114.051
A22: 18 | B22: TITILAYO MARVELOUS DANIEL | C22: 176519 | D22: 12 | E22: =C22*D22 -> 2118228 | G22: 245615.04 | I22: =E22-F22-G22-H22 -> 1872613 | J22: 200000 | K22: 0.2 | L22: =I22*K22 -> 374522.59 | M22: =J22+L22 -> 574522.59 | N22: =F22+G22+H22+M22 -> 820137.63 | O22: =E22-N22 -> 1298090.4 | P22: =IF(O22<300000,0.07*O22,21000) -> 21000 | Q22: =IF((O22-300000)<0,0,IF((O22-300000)<300000,0.11*(O22-300000),33000)) -> 33000 | R22: =IF((O22-600000)<0,0,IF((O22-600000)<500000,0.15*(O22-600000),75000)) -> 75000 | S22: =IF((O22-1100000)<0,0,IF((O22-1100000)<500000,0.19*(O22-1100000),95000)) -> 37637.17 | T22: =IF((O22-1600000)<0,0,IF((O22-1600000)<1600000,0.21*(O22-1600000),336000)) -> 0 | V22: =P22+Q22+R22+S22+T22+U22 -> 166637.17 | W22: 12 | X22: =V22/W22 -> 13886.431 | Z22: =X22 -> 13886.431
A23: 19 | B23: TANIMU M. LAWAL | C23: 86887.25 | D23: 12 | E23: =C23*D23 -> 1042647 | G23: 146701.6 | I23: =E23-F23-G23-H23 -> 895945.4 | J23: 200000 | K23: 0.2 | L23: =I23*K23 -> 179189.08 | M23: =J23+L23 -> 379189.08 | N23: =F23+G23+H23+M23 -> 525890.68 | O23: =E23-N23 -> 516756.32 | P23: =IF(O23<300000,0.07*O23,21000) -> 21000 | Q23: =IF((O23-300000)<0,0,IF((O23-300000)<300000,0.11*(O23-300000),33000)) -> 23843.195 | R23: =IF((O23-600000)<0,0,IF((O23-600000)<500000,0.15*(O23-600000),75000)) -> 0 | S23: =IF((O23-1100000)<0,0,IF((O23-1100000)<500000,0.19*(O23-1100000),95000)) -> 0 | T23: =IF((O23-1600000)<0,0,IF((O23-1600000)<1600000,0.21*(O23-1600000),336000)) -> 0 | V23: =P23+Q23+R23+S23+T23+U23 -> 44843.195 | W23: 12 | X23: =V23/W23 -> 3736.9329 | Z23: =X23 -> 3736.9329
A24: 20 | B24: CHRISTIAN MADUABUCHI ODO | C24: 180487.25 | D24: 12 | E24: =C24*D24 -> 2165847 | F24: =6922.5*12 -> 83070 | G24: 374638.96 | I24: =E24-F24-G24-H24 -> 1708138 | J24: 200000 | K24: 0.2 | L24: =I24*K24 -> 341627.61 | M24: =J24+L24 -> 541627.61 | N24: =F24+G24+H24+M24 -> 999336.57 | O24: =E24-N24 -> 1166510.4 | P24: =IF(O24<300000,0.07*O24,21000) -> 21000 | Q24: =IF((O24-300000)<0,0,IF((O24-300000)<300000,0.11*(O24-300000),33000)) -> 33000 | R24: =IF((O24-600000)<0,0,IF((O24-600000)<500000,0.15*(O24-600000),75000)) -> 75000 | S24: =IF((O24-1100000)<0,0,IF((O24-1100000)<500000,0.19*(O24-1100000),95000)) -> 12636.982 | T24: =IF((O24-1600000)<0,0,IF((O24-1600000)<1600000,0.21*(O24-1600000),336000)) -> 0 | V24: =P24+Q24+R24+S24+T24+U24 -> 141636.98 | W24: 12 | X24: =V24/W24 -> 11803.082 | Z24: =X24 -> 11803.082
B25: TOTAL - ANNUAL | C25: =SUM(C5:C24) -> 6826329.1 | F25: =SUM(F5:F24) -> 454852.8 | G25: =SUM(G5:G24) -> 7697049 | V25: =SUM(V5:V24) -> 10187166 | X25: =SUM(X5:X24) -> 848930.53 | Z25: =SUM(Z5:Z24) -> 848930.53
B26: TOTAL - MONTHLY | F26: =F25/12 -> 37904.4 | G26: =G25/12 -> 641420.75 | V26: =V25/12 -> 848930.53
Z28: 11287301

Sheet Stoppage of Salary
A1: NATIONAL INSTITUTE FOR LEGISLATIVE AND DEMOCRATIC STUDIES
A2: STAFF PAYROLL FOR THE MONTH OF NOVEMBER, 2024
E3: ='[1]FEB 08'!E11/'[1]FEB 08'!M11 -> #REF!
B4: STAFF NAME | C4: DESIGNATION | D4: GRADE LEVEL | E4: BASIC SALARY | F4: ALLCE/ AREARS | G4: ALLOWANCE | H4: ALLOWANCE | I4: DUTY ALLCE | J4: GROSS SALARY | K4: AUCTION | L4: COOP CONTR/SPEC SAVINGS | M4: COOP. LOAN RECOVERY | N4: NHF DED. | O4: PAYE | P4: EMPLOYEE PENSIONS | Q4: TOTAL DEDUCTION | R4: OCTOBER, 2024 | S4: NOVEMBER, 2024
E5: N | F5: N | G5: N | H5: N | I5: N | J5: N | K5: N | L5: N | M5: N | N5: N | O5: N | P5: N | Q5: N | R5: N | S5: N
A6: S/N | B6: DG'S OFFICE
A7: 1 | B7: DR SHUIBU DANWANKA | C7: DIRECTOR LEGAL SERVICES | D7: 17(9) | E7: 1435720 | G7: =200000 -> 200000 | I7: 0 | J7: =SUM(E7:I7) -> 1635720 | L7: 120000 | N7: 0 | O7: 270672.25 | P7: 114857.6 | Q7: =O7+N7+M7+L7+K7+P7 -> 505529.85 | R7: 1130190.2 | S7: =J7-Q7 -> 1130190.2
A8: 2 | B8: DR CLINTON JAJA | C8: SENIOR RESEARCH FELLOW | D8: 15(9) | E8: 620675.58 | G8: =160000 -> 160000 | I8: 0 | J8: =SUM(E8:I8) -> 780675.58 | L8: =50000 -> 50000 | M8: =385000 -> 385000 | O8: 119022.8 | P8: 49654.047 | Q8: =O8+N8+M8+L8+K8+P8 -> 603676.85 | R8: 176998.73 | S8: =J8-Q8 -> 176998.73
A9: 3 | B9: LOHNA BONKAT JONATHAN | C9: RESEARCH FELLOW 11 | D9: 13(10) | E9: 428915.92 | F9: 0 | G9: =120000 -> 120000 | I9: 0 | J9: =SUM(E9:I9) -> 548915.92 | L9: =20000+65000+65000 -> 150000 | M9: 0 | N9: 0 | O9: 77470.374 | P9: 34313.273 | Q9: =O9+N9+M9+L9+K9+P9 -> 261783.65 | R9: 287132.27 | S9: =J9-Q9 -> 287132.27
B10: TOTAL | C10: 31 | E10: =SUM(E7:E9) -> 2485311.5 | F10: =SUM(F7:F9) -> 0 | G10: =SUM(G7:G9) -> 480000 | H10: =SUM(H7:H9) -> 0 | I10: =SUM(I7:I9) -> 0 | J10: =SUM(J7:J9) -> 2965311.5 | K10: =SUM(K7:K9) -> 0 | L10: =SUM(L7:L9) -> 320000 | ... Q10: =SUM(Q7:Q9) -> 1370990.3 | R10: 13026183 | S10: =SUM(S7:S9) -> 1594321.2

Sheet New PAYE

Sheet New Pensions Promotion
A1: NATIONAL INSTITUTE FOR LEGISLATIVE & DEMOCRATIC STUDIES
A2: 2024 ANALYSIS OF STAFF PROMOTION ARREARS
A4: SN | B4: Name of Employee | C4: Department | D4: New Grade Level | E4: Annual Consolidated Salary of New Position(Less Res/Harsh Allow | F4: Monthly Consolidated Salary of New Position(Less Res/Harsh Allow | G4: 8% Employee Contr | H4: Annual 8% Employee Contr
F5: N | G5: N | H5: N
A6: 1 | B6: ABDULSALAM MUSTAPHA | C6: DG's Office | D6: 15/7 | E6: =F6*12 -> 6985417 | F6: =582118.08 -> 582118.08 | G6: =F6*0.08 -> 46569.446 | H6: =G6*12 -> 558833.36
A7: 2 | B7: EMILY EDIOSA IKHIDE | C7: DG's Office | D7: 015/7 | E7: =F7*12 -> 6985417 | F7: =582118.08 -> 582118.08 | G7: =F7*0.08 -> 46569.446 | H7: =G7*12 -> 558833.36
A8: 3 | B8: SIMON WAKAWA | C8: DG's Office | D8: 015/7 | E8: =F8*12 -> 6985417 | F8: =582118.08 -> 582118.08 | G8: =F8*0.08 -> 46569.446 | H8: =G8*12 -> 558833.36
A9: 4 | B9: WAZIRI USMAN | C9: DG's Office | D9: 015/7 | E9: =F9*12 -> 6985417 | F9: =582118.08 -> 582118.08 | G9: =F9*0.08 -> 46569.446 | H9: =G9*12 -> 558833.36
A10: 5 | B10: TAIWO I. OYINLOLA | C10: Admin. & HR | D10: 07/3 | E10: =F10*12 -> 1833770 | F10: =152814.17 -> 152814.17 | G10: =F10*0.08 -> 12225.134 | H10: =G10*12 -> 146701.6
A11: 6 | B11: SARATU ATAJIRI | C11: Admin. & HR | D11: 09/7 | E11: =F11*12 -> 3070188 | F11: =255849 -> 255849 | G11: =F11*0.08 -> 20467.92 | H11: =G11*12 -> 245615.04
A12: 7 | B12: YUSIF SANI SADIQ | C12: Admin. & HR | D12: 12/7 | E12: =F12*12 -> 4242150 | F12: =353512.5 -> 353512.5 | G12: =F12*0.08 -> 28281 | H12: =G12*12 -> 339372
A13: 8 | B13: STELLA NGOZI PAUL | C13: Admin. & HR | D13: 12/7 | E13: =F13*12 -> 4242150 | F13: =353512.5 -> 353512.5 | G13: =F13*0.08 -> 28281 | H13: =G13*12 -> 339372
A14: 9 | B14: OMONIGHO EROMOSELE-WESEY | C14: Admin. & HR | D14: 13/7 | E14: =F14*12 -> 4682987 | F14: =390248.92 -> 390248.92 | G14: =F14*0.08 -> 31219.914 | H14: =G14*12 -> 374638.96
A15: 10 | B15: QUEEN ONYEKESON | C15: Admin. & HR | D15: 13/7 | E15: =F15*12 -> 4682987 | F15: =390248.92 -> 390248.92 | G15: =F15*0.08 -> 31219.914 | H15: =G15*12 -> 374638.96
A16: 11 | B16: SHAMSUDEEN YAHAYA | C16: LSS | D16: 015/7 | E16: =F16*12 -> 6985417 | F16: 582118.08 | G16: =F16*0.08 -> 46569.446 | H16: =G16*12 -> 558833.36
A17: 12 | B17: SALAMATU YAKUBU | C17: LSS | D17: 015/7 | E17: =F17*12 -> 6985417 | F17: 582118.08 | G17: =F17*0.08 -> 46569.446 | H17: =G17*12 -> 558833.36
A18: 13 | B18: ROTIMI OGUNYOMI | C18: LSS | D18: 13/7 | E18: =F18*12 -> 4682987 | F18: 390248.92 | G18: =F18*0.08 -> 31219.914 | H18: =G18*12 -> 374638.96
A19: 14 | B19: LEO IGBANOI | C19: Dem. & Gov. | D19: 14/8 | E19: =F19*12 -> 5312958 | F19: =442746.5 -> 442746.5 | G19: =F19*0.08 -> 35419.72 | H19: =G19*12 -> 425036.64
A20: 15 | B20: LOHNA BONKAT JONATHAN | C20: Dem. & Gov. | D20: 14/8 | E20: =F20*12 -> 5312958 | F20: =442746.5 -> 442746.5 | G20: =F20*0.08 -> 35419.72 | H20: =G20*12 -> 425036.64
A21: 16 | B21: TOSIN OWOEYE | C21: Dem. & Gov. | D21: 12/7 | E21: =F21*12 -> 4242150 | F21: 353512.5 | G21: =F21*0.08 -> 28281 | H21: =G21*12 -> 339372
A22: 17 | B22: STACY CHINYERE IGWE | C22: DOS | D22: 12/7 | E22: =F22*12 -> 4242150 | F22: 353512.5 | G22: =F22*0.08 -> 28281 | H22: =G22*12 -> 339372
A23: 18 | B23: TITILAYO MARVELOUS DANIEL | C23: Library | D23: 09/7 | E23: =F23*12 -> 3070188 | F23: 255849 | G23: =F23*0.08 -> 20467.92 | H23: =G23*12 -> 245615.04
A24: 19 | B24: TANIMU M. LAWAL | C24: Econ/ & Social Res. | D24: 07/3 | E24: =F24*12 -> 1833770 | F24: 152814.17 | G24: =F24*0.08 -> 12225.134 | H24: =G24*12 -> 146701.6
A25: 20 | B25: CHRISTIAN MADUABUCHI ODO | C25: Finance & Accts | D25: 13/7 | E25: =F25*12 -> 4682987 | F25: 390248.92 | G25: =F25*0.08 -> 31219.914 | H25: =G25*12 -> 374638.96
B26: TOTAL

Sheet Conversion in Nov
A1: NATIONAL INSTITUTE FOR LEGISLATIVE AND DEMOCRATIC STUDIES
A2: STAFF PAYROLL FOR THE MONTH OF NOVEMBER, 2024
E3: ='[1]FEB 08'!E11/'[1]FEB 08'!M11 -> #REF!
B4: STAFF NAME | C4: DESIGNATION | D4: GRADE LEVEL | E4: BASIC SALARY | F4: ALLCE/ AREARS | G4: ALLOWANCE | H4: ALLOWANCE | I4: DUTY ALLCE | J4: GROSS SALARY | K4: AUCTION | L4: COOP CONTR/SPEC SAVINGS | M4: COOP. LOAN RECOVERY | N4: NHF DED. | O4: PAYE | P4: EMPLOYEE PENSIONS | Q4: TOTAL DEDUCTION | R4: OCTOBER, 2024 | S4: NOVEMBER, 2024
E5: N | F5: N | G5: N | H5: N | I5: N | J5: N | K5: N | L5: N | M5: N | N5: N | O5: N | P5: N | Q5: N | R5: N | S5: N
A6: S/N | B6: DG'S OFFICE
A7: 25 | B7: SARATU ATAJIRI | C7: ADMINI OFFICER | D7: 9(7) | E7: 255849 | H7: =60000 -> 60000 | J7: =E7+F7+G7+H7+I7 -> 315849 | O7: 36790.688 | P7: 20467.92 | Q7: =O7+N7+M7+L7+K7+P7 -> 57258.608 | S7: =J7-Q7 -> 258590.39

Sheet New Enrolmt
B4: STAFF NAME | C4: DESIGNATION | D4: GRADE LEVEL | E4: BASIC SALARY | F4: ALLOWANCE | G4: DUTY ALLCE | H4: GROSS SALARY | I4: PAYE | J4: EMPLOYEE PENSIONS | K4: TOTAL DEDUCTION | L4: AUGUST, 2024
A5: 1 | B5: JOSEPH GWATANA | C5: SENIOR MOTOR DRIVER MECH. | D5: 5(7) | E5: 83955 | F5: =20000 -> 20000 | G5: =4000+3000 -> 7000 | H5: =SUM(E5:G5) -> 110955 | I5: 5719.04 | K5: 5719.04 | L5: =H5-K5 -> 105235.96
B6: PRORATED FOR 12 DAYS | E6: 83955 | F6: =20000 -> 20000 | G6: =4000+3000 -> 7000 | H6: =SUM(E6:G6)*(12/31) -> 42950.323 | I6: 3127.74 | J6: 0 | K6: 3127.74 | L6: =H6-K6 -> 39822.583
A7: 2 | B7: ABDULMUSHIN TAWFIQ LADAN | C7: ICT OFFICER | D7: 95(7) | E7: 255849 | F7: 60000 | H7: =SUM(E7:G7) -> 315849 | I7: =36790.6881 -> 36790.688 | J7: ='NOVEMBER 2024'!P34 -> 20467.92 | K7: =I7+J7 -> 57258.608 | L7: =H7-K7 -> 258590.39
B8: TOTAL | L8: =SUM(L6:L7) -> 298412.97

Sheet 1ST 28 DAYS
A1: SCHEDULE OF 1ST 28 DAY TO THE NEWLY CONVERTED STAFF
A2: S/N | B2: NAME | C2: GRADE LEVEL | D2: AMOUNT (NGN) | E2: PAYE (NGN) | F2: NET AMOUNT (NGN)
A3: 1 | B3: Alabi Adesina Muhydeen | C3: 13 | D3: =25000*28 -> 700000 | E3: 104125.33 | F3: =D3-E3 -> 595874.67
A4: 2 | B4: Ikip Lebo | C4: 13 | D4: =25000*28 -> 700000 | E4: 104125.33 | F4: =D4-E4 -> 595874.67
A5: 3 | B5: Rasheedat Daibu | C5: 10 | D5: =20000*28 -> 560000 | E5: =86186.67 -> 86186.67 | F5: =D5-E5 -> 473813.33
A6: 4 | B6: Yussuf Yussuf Dayyabu | C6: 09 | D6: =20000*28 -> 560000 | E6: =86186.67 -> 86186.67 | F6: =D6-E6 -> 473813.33
A7: 5 | B7: Rahimat Onize Suberu | C7: 08 | D7: =20000*28 -> 560000 | E7: =86186.67 -> 86186.67 | F7: =D7-E7 -> 473813.33
A8: 6 | B8: Ramatu Ibrahim Abdulraheem | C8: 08 | D8: =20000*28 -> 560000 | E8: =86186.67 -> 86186.67 | F8: =D8-E8 -> 473813.33
A9: 7 | B9: Katman Emmanuel | C9: 08 | D9: =20000*28 -> 560000 | E9: =86186.67 -> 86186.67 | F9: =D9-E9 -> 473813.33
A10: 8 | B10: Usman Muhammed Gidado | C10: 08 | D10: =20000*28 -> 560000 | E10: =86186.67 -> 86186.67 | F10: =D10-E10 -> 473813.33
B11: TOTAL | D11: =SUM(D3:D10) -> 4760000 | E11: =SUM(E3:E10) -> 725370.68 | F11: =SUM(F3:F10) -> 4034629.3
A14: S/N | B14: NAME | C14: GRADE LEVEL | D14: AMOUNT (NGN) | E14: PAYE (NGN) | F14: NET AMOUNT (NGN)
B15: Abdulmushin Tawfiq Ladan | C15: 09 | D15: =20000*28 -> 560000 | E15: =86186.67 -> 86186.67 | F15: =D15-E15 -> 473813.33
B16: Joseph Gwatana | C16: 05 | D16: =10000*28 -> 280000 | E16: 31272.88 | F16: =D16-E16 -> 248727.12
B17: TOTAL | D17: =SUM(D15:D16) -> 840000 | E17: =SUM(E15:E16) -> 117459.55 | F17: =SUM(F15:F16) -> 722540.45

Sheet Conversion in Sept
A1: S/N | B1: STAFF NAME | C1: DESIGNATION | D1: GRADE LEVEL | E1: SALARY | F1: RESEARCH/HARDSHIP | G1: ARREARS | H1: GROSS SALARY | I1: DEDUCTIONS | N1: JULY 2024 NET SALARY
I2: COOP CONTR/SPEC. SAVINGS | J2: COOP LOAN REC. | K2: PAYE TAX | L2: PENSION DEDUCTION | M2: TOTAL DEDUCTION
E4: N | F4: N | G4: N | H4: N | I4: N | J4: N | K4: N | L4: N | M4: N | N4: N
A5: 1 | B5: Mugisat Abdulganiyu | C5: Presenter/Announcer | D5: 8(7) | E5: ='[3]Annual & Monthly'!$H$36 -> 218287.58 | F5: 50000 | H5: =E5+F5+G5 -> 268287.58 | K5: 29305.196 | L5: 17463.007 | M5: =I5+J5+K5+L5 -> 46768.202 | N5: =H5-M5 -> 221519.38
A6: 2 | B6: Zainab Bakari | C6: News Caster | D6: 8(7) | E6: ='[3]Annual & Monthly'!$H$36 -> 218287.58 | F6: 50000 | H6: =E6+F6+G6 -> 268287.58 | K6: 29305.196 | L6: =218287.583333333*0.08 -> 17463.007 | M6: =I6+J6+K6+L6 -> 46768.202 | N6: =H6-M6 -> 221519.38
A7: 3 | B7: Shugge Ngalabak | C7: Digital Producer/Marketer | D7: 8(7) | E7: ='[3]Annual & Monthly'!$H$36 -> 218287.58 | F7: 50000 | H7: =E7+F7+G7 -> 268287.58 | K7: 29305.196 | L7: =218287.583333333*0.08 -> 17463.007 | M7: =I7+J7+K7+L7 -> 46768.202 | N7: =H7-M7 -> 221519.38
A8: 5 | B8: Dr. Hadiza Saidu | C8: Assistant Director | D8: 15(7) | E8: 582118.08 | F8: 160000 | H8: =E8+F8+G8 -> 742118.08 | K8: 112212 | L8: 46569.447 | M8: =I8+J8+K8+L8 -> 158781.45 | N8: =H8-M8 -> 583336.63
B9: TOTAL | E9: =SUM(E5:E8) -> 1236980.8 | F9: =SUM(F5:F8) -> 310000 | G9: =SUM(G5:G8) -> 0 | H9: =SUM(H5:H8) -> 1546980.8 | I9: =SUM(I5:I8) -> 0 | J9: =SUM(J5:J8) -> 0 | K9: =SUM(K5:K8) -> 200127.59 | L9: =SUM(L5:L8) -> 98958.467 | ... N9: =SUM(N5:N8) -> 1247894.8

Sheet Conversion & Enrol Effect
A1: S/N | B1: STAFF NAME | C1: DESIGNATION | D1: GRADE LEVEL | E1: SALARY | F1: RESEARCH/HARDSHIP | G1: ARREARS | H1: GROSS SALARY | I1: DEDUCTIONS | N1: JULY 2024 NET SALARY
I2: COOP CONTR/SPEC. SAVINGS | J2: COOP LOAN REC. | K2: PAYE TAX | L2: PENSION DEDUCTION | M2: TOTAL DEDUCTION
E4: N | F4: N | G4: N | H4: N | I4: N | J4: N | K4: N | L4: N | M4: N | N4: N
A5: 1 | B5: Mugisat Abdulganiyu | C5: Presenter/Announcer | D5: 8(7) | E5: ='[3]Annual & Monthly'!$H$36 -> 218287.58 | F5: 50000 | H5: =E5+F5+G5 -> 268287.58 | K5: 29305.196 | L5: 17463.007 | M5: =I5+J5+K5+L5 -> 46768.202 | N5: =H5-M5 -> 221519.38
A6: 2 | B6: Zainab Bakari | C6: News Caster | D6: 8(7) | E6: ='[3]Annual & Monthly'!$H$36 -> 218287.58 | F6: 50000 | H6: =E6+F6+G6 -> 268287.58 | K6: 29305.196 | L6: =218287.583333333*0.08 -> 17463.007 | M6: =I6+J6+K6+L6 -> 46768.202 | N6: =H6-M6 -> 221519.38
A7: 3 | B7: Shugge Ngalabak | C7: Digital Producer/Marketer | D7: 8(7) | E7: ='[3]Annual & Monthly'!$H$36 -> 218287.58 | F7: 50000 | H7: =E7+F7+G7 -> 268287.58 | K7: 29305.196 | L7: =218287.583333333*0.08 -> 17463.007 | M7: =I7+J7+K7+L7 -> 46768.202 | N7: =H7-M7 -> 221519.38
A8: 4 | B8: Olufemi E. Oyegoke | C8: Marketer | D8: 8(7) | E8: ='[3]Annual & Monthly'!$H$36 -> 218287.58 | F8: 50000 | H8: =E8+F8+G8 -> 268287.58 | K8: 29305.196 | L8: =218287.583333333*0.08 -> 17463.007 | M8: =I8+J8+K8+L8 -> 46768.202 | N8: =H8-M8 -> 221519.38
A9: 5 | B9: Dr. Hadiza Saidu | C9: Assistant Director | D9: 15(7) | E9: 582118.08 | F9: 160000 | H9: =E9+F9+G9 -> 742118.08 | K9: 112212 | L9: 46569.447 | M9: =I9+J9+K9+L9 -> 158781.45 | N9: =H9-M9 -> 583336.63
B10: TOTAL | E10: =SUM(E5:E9) -> 1455268.4 | F10: =SUM(F5:F9) -> 360000 | G10: =SUM(G5:G9) -> 0 | H10: =SUM(H5:H9) -> 1815268.4 | I10: =SUM(I5:I9) -> 0 | J10: =SUM(J5:J9) -> 0 | K10: =SUM(K5:K9) -> 229432.79 | L10: =SUM(L5:L9) -> 116421.47 | ... N10: =SUM(N5:N9) -> 1469414.2

Sheet Converted Staff PAYE
A1: NATIONAL INSTITUTE FOR LEGISLATIVE AND DEMOCRATIC STUDIES
A2: NATIONAL ASSEMBLY ABUJA
A3: TAX COMPUTATION FOR 2022
A4: S/NO | B4: NAME | C4: MONTHLY TOTAL SALARY | D4: NO OF MONTHS | E4: ANNUAL SALARY GROSSED UP | F4: NATIONAL HOUSING SCHEME = 2.5% OF BASIC SALARY | G4: PENSION CONTRIBUTION = 8% OF CONSOLIDATED | H4: NHIS | I4: NET SALARY (EXC OF CRA) | M4: CRA=#200,000+(20% 0F NET SALARY (EXC OF CRA) | N4: TOTAL RELIEF | O4: CHARGEABLE INCOME | P4: FIRST N300,000 @ 7% | Q4: NEXT N300,000 @ 11% | R4: NEXT N500,000 @ 15% | S4: NEXT N500,000@ 19% | T4: NEXT N1,600,000 @ 21% | U4: ABOVE N3,200,000 @ 24% | V4: ANNUAL TAX PAYABLE | X4: MONTHLY TAX PAYABLE | Y4: MINIMUM TAX PAYABLE | Z4: NEW ACTUAL TAX PAYABLE
A5: 1
A6: 3 | B6: Rahimat Suberu Onize | C6: 268287.58 | D6: 12 | E6: =C6*D6 -> 3219451 | G6: 209556.08 | I6: =E6-F6-G6-H6 -> 3009894.9 | J6: 200000 | K6: 0.2 | L6: =I6*K6 -> 601978.98 | M6: =J6+L6 -> 801978.98 | N6: =F6+G6+H6+M6 -> 1011535.1 | O6: =E6-N6 -> 2207915.9 | P6: =IF(O6<300000,0.07*O6,21000) -> 21000 | Q6: =IF((O6-300000)<0,0,IF((O6-300000)<300000,0.11*(O6-300000),33000)) -> 33000 | R6: =IF((O6-600000)<0,0,IF((O6-600000)<500000,0.15*(O6-600000),75000)) -> 75000 | S6: =IF((O6-1100000)<0,0,IF((O6-1100000)<500000,0.19*(O6-1100000),95000)) -> 95000 | T6: =IF((O6-1600000)<0,0,IF((O6-1600000)<1600000,0.21*(O6-1600000),336000)) -> 127662.35 | V6: =P6+Q6+R6+S6+T6+U6 -> 351662.35 | W6: 12 | X6: =V6/W6 -> 29305.196 | Z6: =X6 -> 29305.196
A7: 4 | B7: Ikip Lebo | C7: 460248.92 | D7: 12 | E7: =C7*D7 -> 5522987 | G7: 374638.96 | I7: =E7-F7-G7-H7 -> 5148348 | J7: 200000 | K7: 0.2 | L7: =I7*K7 -> 1029669.6 | M7: =J7+L7 -> 1229669.6 | N7: =F7+G7+H7+M7 -> 1604308.6 | O7: =E7-N7 -> 3918678.4 | P7: =IF(O7<300000,0.07*O7,21000) -> 21000 | Q7: =IF((O7-300000)<0,0,IF((O7-300000)<300000,0.11*(O7-300000),33000)) -> 33000 | R7: =IF((O7-600000)<0,0,IF((O7-600000)<500000,0.15*(O7-600000),75000)) -> 75000 | S7: =IF((O7-1100000)<0,0,IF((O7-1100000)<500000,0.19*(O7-1100000),95000)) -> 95000 | T7: =IF((O7-1600000)<0,0,IF((O7-1600000)<1600000,0.21*(O7-1600000),336000)) -> 336000 | U7: =24%*(O7-3200000) -> 172482.82 | V7: =P7+Q7+R7+S7+T7+U7 -> 732482.82 | W7: 12 | X7: =V7/W7 -> 61040.235 | Z7: =X7 -> 61040.235
A8: 5 | B8: Yusuf Yusuf Dayyabu | C8: 315849 | D8: 12 | E8: =C8*D8 -> 3790188 | G8: 245615.04 | I8: =E8-F8-G8-H8 -> 3544573 | J8: 200000 | K8: 0.2 | L8: =I8*K8 -> 708914.59 | M8: =J8+L8 -> 908914.59 | N8: =F8+G8+H8+M8 -> 1154529.6 | O8: =E8-N8 -> 2635658.4 | P8: =IF(O8<300000,0.07*O8,21000) -> 21000 | Q8: =IF((O8-300000)<0,0,IF((O8-300000)<300000,0.11*(O8-300000),33000)) -> 33000 | R8: =IF((O8-600000)<0,0,IF((O8-600000)<500000,0.15*(O8-600000),75000)) -> 75000 | S8: =IF((O8-1100000)<0,0,IF((O8-1100000)<500000,0.19*(O8-1100000),95000)) -> 95000 | T8: =IF((O8-1600000)<0,0,IF((O8-1600000)<1600000,0.21*(O8-1600000),336000)) -> 217488.26 | V8: =P8+Q8+R8+S8+T8+U8 -> 441488.26 | W8: 12 | X8: =V8/W8 -> 36790.688 | Z8: =X8 -> 36790.688
A9: 6 | B9: Ramatu Ibrahim Abdulrahim | C9: 268287.58 | D9: 12 | E9: =C9*D9 -> 3219451 | G9: 209556.08 | I9: =E9-F9-G9-H9 -> 3009894.9 | J9: 200000 | K9: 0.2 | L9: =I9*K9 -> 601978.98 | M9: =J9+L9 -> 801978.98 | N9: =F9+G9+H9+M9 -> 1011535.1 | O9: =E9-N9 -> 2207915.9 | P9: =IF(O9<300000,0.07*O9,21000) -> 21000 | Q9: =IF((O9-300000)<0,0,IF((O9-300000)<300000,0.11*(O9-300000),33000)) -> 33000 | R9: =IF((O9-600000)<0,0,IF((O9-600000)<500000,0.15*(O9-600000),75000)) -> 75000 | S9: =IF((O9-1100000)<0,0,IF((O9-1100000)<500000,0.19*(O9-1100000),95000)) -> 95000 | T9: =IF((O9-1600000)<0,0,IF((O9-1600000)<1600000,0.21*(O9-1600000),336000)) -> 127662.35 | V9: =P9+Q9+R9+S9+T9+U9 -> 351662.35 | W9: 12 | X9: =V9/W9 -> 29305.196 | Z9: =X9 -> 29305.196
A10: 7 | B10: Rasheedat Daibu | C10: 353029.67 | D10: 12 | E10: =C10*D10 -> 4236356 | G10: 281308.48 | I10: =E10-F10-G10-H10 -> 3955047.5 | J10: 200000 | K10: 0.2 | L10: =I10*K10 -> 791009.5 | M10: =J10+L10 -> 991009.5 | N10: =F10+G10+H10+M10 -> 1272318 | O10: =E10-N10 -> 2964038 | P10: =IF(O10<300000,0.07*O10,21000) -> 21000 | Q10: =IF((O10-300000)<0,0,IF((O10-300000)<300000,0.11*(O10-300000),33000)) -> 33000 | R10: =IF((O10-600000)<0,0,IF((O10-600000)<500000,0.15*(O10-600000),75000)) -> 75000 | S10: =IF((O10-1100000)<0,0,IF((O10-1100000)<500000,0.19*(O10-1100000),95000)) -> 95000 | T10: =IF((O10-1600000)<0,0,IF((O10-1600000)<1600000,0.21*(O10-1600000),336000)) -> 286447.98 | V10: =P10+Q10+R10+S10+T10+U10 -> 510447.98 | W10: 12 | X10: =V10/W10 -> 42537.332 | Z10: =X10 -> 42537.332
A11: 8 | B11: Dr. Alabi Adesina Muhydeen | C11: 510248.92 | D11: 12 | E11: =C11*D11 -> 6122987 | G11: 374638.96 | I11: =E11-F11-G11-H11 -> 5748348 | J11: 200000 | K11: 0.2 | L11: =I11*K11 -> 1149669.6 | M11: =J11+L11 -> 1349669.6 | N11: =F11+G11+H11+M11 -> 1724308.6 | O11: =E11-N11 -> 4398678.4 | P11: =IF(O11<300000,0.07*O11,21000) -> 21000 | Q11: =IF((O11-300000)<0,0,IF((O11-300000)<300000,0.11*(O11-300000),33000)) -> 33000 | R11: =IF((O11-600000)<0,0,IF((O11-600000)<500000,0.15*(O11-600000),75000)) -> 75000 | S11: =IF((O11-1100000)<0,0,IF((O11-1100000)<500000,0.19*(O11-1100000),95000)) -> 95000 | T11: =IF((O11-1600000)<0,0,IF((O11-1600000)<1600000,0.21*(O11-1600000),336000)) -> 336000 | U11: =24%*(O11-3200000) -> 287682.82 | V11: =P11+Q11+R11+S11+T11+U11 -> 847682.82 | W11: 12 | X11: =V11/W11 -> 70640.235 | Z11: =X11 -> 70640.235
A12: 9 | B12: Katman Emmanuel | C12: 268287.58 | D12: 12 | E12: =C12*D12 -> 3219451 | G12: 209556.08 | I12: =E12-F12-G12-H12 -> 3009894.9 | J12: 200000 | K12: 0.2 | L12: =I12*K12 -> 601978.98 | M12: =J12+L12 -> 801978.98 | N12: =F12+G12+H12+M12 -> 1011535.1 | O12: =E12-N12 -> 2207915.9 | P12: =IF(O12<300000,0.07*O12,21000) -> 21000 | Q12: =IF((O12-300000)<0,0,IF((O12-300000)<300000,0.11*(O12-300000),33000)) -> 33000 | R12: =IF((O12-600000)<0,0,IF((O12-600000)<500000,0.15*(O12-600000),75000)) -> 75000 | S12: =IF((O12-1100000)<0,0,IF((O12-1100000)<500000,0.19*(O12-1100000),95000)) -> 95000 | T12: =IF((O12-1600000)<0,0,IF((O12-1600000)<1600000,0.21*(O12-1600000),336000)) -> 127662.35 | V12: =P12+Q12+R12+S12+T12+U12 -> 351662.35 | W12: 12 | X12: =V12/W12 -> 29305.196 | Z12: =X12 -> 29305.196
A13: 10 | B13: Usman Muhammed Gidado | C13: 268287.58 | D13: 12 | E13: =C13*D13 -> 3219451 | G13: 209556.08 | I13: =E13-F13-G13-H13 -> 3009894.9 | J13: 200000 | K13: 0.2 | L13: =I13*K13 -> 601978.98 | M13: =J13+L13 -> 801978.98 | N13: =F13+G13+H13+M13 -> 1011535.1 | O13: =E13-N13 -> 2207915.9 | P13: =IF(O13<300000,0.07*O13,21000) -> 21000 | Q13: =IF((O13-300000)<0,0,IF((O13-300000)<300000,0.11*(O13-300000),33000)) -> 33000 | R13: =IF((O13-600000)<0,0,IF((O13-600000)<500000,0.15*(O13-600000),75000)) -> 75000 | S13: =IF((O13-1100000)<0,0,IF((O13-1100000)<500000,0.19*(O13-1100000),95000)) -> 95000 | T13: =IF((O13-1600000)<0,0,IF((O13-1600000)<1600000,0.21*(O13-1600000),336000)) -> 127662.35 | V13: =P13+Q13+R13+S13+T13+U13 -> 351662.35 | W13: 12 | X13: =V13/W13 -> 29305.196 | Z13: =X13 -> 29305.196
B14: TOTAL - MONTHLY | Z14: =SUM(Z6:Z13) -> 328229.27
C16: MONTHLY PENSIONS | D16: 12 | E16: ANNUAL PENSIONS
B17: Rahimat Suberu Onize | C17: =218287.583333333*0.08 -> 17463.007 | D17: 12 | E17: =C17*D17 -> 209556.08
B18: Ikip Lebo | C18: =390248.916666667*0.08 -> 31219.913 | D18: 12 | E18: =C18*D18 -> 374638.96
B19: Yusuf Yusuf Dayyabu | C19: =255849*0.08 -> 20467.92 | D19: 12 | E19: =C19*D19 -> 245615.04
B20: Ramatu Ibrahim Abdulrahim | C20: =218287.583333333*0.08 -> 17463.007 | D20: 12 | E20: =C20*D20 -> 209556.08
B21: Rasheedat Daibu | C21: =293029.666666667*0.08 -> 23442.373 | D21: 12 | E21: =C21*D21 -> 281308.48
B22: Dr. Alabi Adesina Muhydeen | C22: =390248.916666667*0.08 -> 31219.913 | D22: 12 | E22: =C22*D22 -> 374638.96
B23: Katman Emmanuel | C23: =218287.583333333*0.08 -> 17463.007 | D23: 12 | E23: =C23*D23 -> 209556.08
B24: Usman Muhammed Gidado | C24: =218287.583333333*0.08 -> 17463.007 | D24: 12 | E24: =C24*D24 -> 209556.08

Sheet Movt to Contract
B3: STAFF NAME | C3: DESIGNATION | D3: GRADE LEVEL | E3: BASIC SALARY | F3: ALLCE/ AREARS | G3: ALLOWANCE | H3: ALLOWANCE | I3: DUTY ALLCE | J3: GROSS SALARY | K3: AUCTION | L3: COOP CONTR/SPEC SAVINGS | M3: COOP. LOAN RECOVERY | N3: NHF DED. | O3: PAYE | P3: EMPLOYEE PENSIONS | Q3: TOTAL DEDUCTION | R3: JUNE, 2024 | S3: JULY, 2024
E4: N | F4: N | G4: N | H4: N | I4: N | J4: N | K4: N | L4: N | M4: N | N4: N | O4: N | P4: N | Q4: N | R4: N | S4: N
A5: 1 | B5: USMAN WALI | C5: SENIOR RESEARCH FELLOW | D5: 15 (8) | E5: 601396.83 | G5: =160000 -> 160000 | I5: 0 | J5: =SUM(E5:I5) -> 761396.83 | N5: 0 | O5: 124854.86 | Q5: =O5+N5+M5+L5+K5+P5 -> 124854.86 | R5: 636541.97 | S5: =J5-Q5 -> 636541.97
A6: 2 | B6: AYOBOLU OLAJIDE OLUFUNSHO | C6: ASST.DIR., INFORMATION | D6: 15 (9) | E6: 620675.58 | G6: 160000 | I6: 0 | J6: =SUM(E6:I6) -> 780675.58 | L6: =50000 -> 50000 | M6: =59583.33 -> 59583.33 | O6: =128556.38 -> 128556.38 | Q6: =O6+N6+M6+L6+K6+P6 -> 238139.71 | R6: 542535.87 | S6: =J6-Q6 -> 542535.87
A7: 3 | B7: ARAOYE GANIYAT TITILOLA | C7: ASST. DIRECTOR, ACCOUNTS | D7: 15(7) | E7: 582118.08 | H7: =80000 -> 80000 | I7: 0 | J7: =SUM(E7:I7) -> 662118.08 | L7: =100000 -> 100000 | M7: =103000 -> 103000 | N7: 0 | O7: 105793.34 | Q7: =O7+N7+M7+L7+K7+P7 -> 308793.34 | R7: 353324.74 | S7: =J7-Q7 -> 353324.74
A8: 4 | B8: MAGAJI BALA | C8: DD ADMIN | D8: 16(9) | E8: 762373.17 | H8: 90000 | J8: =SUM(E8:I8) -> 852373.17 | L8: 50000 | M8: 200000 | O8: 142322.31 | Q8: =O8+N8+M8+L8+K8+P8 -> 392322.31 | R8: 460050.85 | S8: =J8-Q8 -> 460050.85
E9: =SUM(E5:E8) -> 2566563.7 | F9: =SUM(F5:F8) -> 0 | G9: =SUM(G5:G8) -> 320000 | H9: =SUM(H5:H8) -> 170000 | I9: =SUM(I5:I8) -> 0 | J9: =SUM(J5:J8) -> 3056563.7 | K9: =SUM(K5:K8) -> 0 | L9: =SUM(L5:L8) -> 200000 | ... S9: =SUM(S5:S8) -> 1992453.4

Sheet Sheet10

Sheet Sheet8
B3: STAFF NAME | C3: DESIGNATION | D3: GRADE LEVEL | E3: BASIC SALARY | F3: ALLCE/ AREARS | G3: ALLOWANCE | H3: ALLOWANCE | I3: DUTY ALLCE | J3: GROSS SALARY | K3: AUCTION | L3: COOP CONTR/SPEC SAVINGS | M3: COOP. LOAN RECOVERY | N3: NHF DED. | O3: PAYE | P3: EMPLOYEE PENSIONS | Q3: TOTAL DEDUCTION | R3: JUNE, 2024 | S3: JULY, 2024
E4: N | F4: N | G4: N | H4: N | I4: N | J4: N | K4: N | L4: N | M4: N | N4: N | O4: N | P4: N | Q4: N | R4: N | S4: N
A5: 6 | B5: REKIYA IBRAHIM ATTAH | C5: DEPUTY DIRECTOR TRAINING | D5: 16 (9) | E5: 762373.17 | H5: =90000 -> 90000 | I5: =100000+100000 -> 200000 | J5: =E5+F5+G5+H5+I5 -> 1052373.2 | L5: =50000 -> 50000 | M5: =91666.67 -> 91666.67 | O5: ='Additional Leg Duty Allowance'!P3 -> 0 | Q5: =O5+N5+M5+L5+K5+P5 -> 141666.67 | R5: 729984.18 | S5: =J5-Q5 -> 910706.5

Sheet Welfare June
A1: NATIONAL INSTITUTE FOR LEGISLATIVE AND DEMOCRATIC STUDIES
A2: STAFF SALLAH WELFARE JUNE, 2024
B4: STAFF NAME | C4: DESIGNATION | D4: GRADE LEVEL | E4: AMOUNT
E5: N
A6: S/N | B6: DG'S OFFICE
A7: 1 | B7: PROF. ABUBAKAR O. SULAIMAN | C7: DIRECTOR GENERAL | D7: CONSOL | E7: 540000
A8: 2 | B8: RAHEEM USMAN AYIGORO | C8: SA-INFRASTRUCTURE | D8: 16 (9) | E8: 180000
A9: 3 | B9: MARIAM MOHAMMED BELLO | C9: SA- SPECIAL DUTIES | D9: 16 (9) | E9: 180000
A10: 4 | B10: DR IKEME ARTHUR J.O | C10: DEPUTY DIRECTOR, M&E | D10: 16 (9) | E10: 180000
A11: 5 | B11: MOSHOOD M. OLALERE | C11: DEPUTY DIR. GENERAL SERVICE | D11: 16 (9) | E11: 180000
A12: 6 | B12: REKIYA IBRAHIM ATTAH | C12: DEPUTY DIRECTOR TRAINING | D12: 16 (9) | E12: 180000
A13: 7 | B13: ANDRAWUS MUSA | C13: ASST. DIRECTOR, STORES | D13: 15(9) | E13: 126000
A14: 8 | B14: DR FRANCIS NDUM OJIE | C14: AD, TRAINING & IC./SA TO DG | D14: 15(7) | E14: 126000
A15: 9 | B15: ALI ABDULLAHI | C15: CHIEF ICT OFFICER | D15: 14(11) | E15: 90000
A16: 10 | B16: EMILY EKHIDE | C16: RESEARCH FELLOW 1 | D16: 14(10) | E16: 90000
A17: 11 | B17: DORIS DAKDA AARON | C17: RESEARCH FELLOW I | D17: 14(8) | E17: 90000
A18: 12 | B18: ABDULSALAM S. MUSTAPHA | C18: ASST. MANAGER ICT | D18: 13(11) | E18: 90000
... A33: 27 | B33: HARUNA JIBRIL AMEH | C33: ASST. ADMIN. OFFICER | D33: 8(8) | E33: 54000
B34: TOTAL | C34: 27 | E34: =SUM(E7:E33) -> 2990000
B36: INTERNAL AUDIT
A37: 1 | B37: OSANAIYE DAVID AKINYEMI | C37: DIRECTOR INTERNAL AUDIT | D37: 17(9) | E37: 270000
A38: 2 | B38: JAMILA ABDUL | C38: SENIOR INTERNAL AUDITOR | D38: 10(7) | E38: 68000
A39: 3 | B39: IJEOMA EWELUKWA | C39: SENIOR INTERNAL AUDITOR | D39: 10(8) | E39: 68000
C40: 3 | E40: =SUM(E37:E39) -> 406000
B42: LEG. SUPPORT SEVICES
A43: 1 | B43: PROF. EDOBA BRIGHT OMOREGBE | C43: AG. DLSS | D43: 17(9) | E43: 270000
A44: 2 | B44: DR CLINTON JAJA | C44: SENIOR RESEARCH FELLOW | D44: 15(9) | E44: 126000
A45: 3 | B45: BETHEL UZOMA IHUGBA | C45: DEPUTY DIRECTOR, LEGAL RESEARCH | D45: 16(8) | E45: 180000
A46: 4 | B46: OGUCHE SAMUEL | C46: SNR RESEARCH FELLOW | D46: 15(9) | E46: 126000
A47: 5 | B47: IBRAHIM USMAN | C47: SNR RESEARCH FELLOW | D47: 15(9) | E47: 126000
A48: 6 | B48: DR MOHAMMED O. AMALI | C48: SNR RESEARCH FELLOW | D48: 15(7) | E48: 126000
A49: 7 | B49: YAHAYA SHAMSU | C49: RESEARCH FELLOW 1 | D49: 14(10) | E49: 90000
A50: 8 | B50: BILKIS S. LAWAL-GAMBARI | C50: RESEARCH OFFICER | D50: 10(8) | E50: 68000
A51: 9 | B51: ZAINAB AKINDE | C51: RESEARCH OFFICER | D51: 9(8) | E51: 54000
A52: 10 | B52: ABDULLAHI AHMAD USMAN | C52: RESEARCH OFFICER | D52: 9(8) | E52: 54000
A53: 11 | B53: GUNAT NANSAK MARK | C53: RESEARCH OFFICER | D53: 9(8) | E53: 54000
B54: TOTAL | C54: 11 | E54: =SUM(E43:E53) -> 1274000
B56: LEGAL SERVICES
A57: 1 | B57: DR SHUIBU DANWANKA | C57: DIRECTOR LEGAL SERVICES | D57: 17(9) | E57: 270000
A58: 2 | B58: ABDULSALAM BAKO | C58: MANAGER, LEGAL SERVICES | D58: 15 (9) | E58: 126000
B59: TOTAL | C59: 2 | E59: =SUM(E57:E58) -> 396000
B61: DEMOCRACY & GOVERNANCE
A62: 1 | B62: DR. ADEWALE ADEREMI | C62: DIRECTOR, DEMOCRATIC STUDIES | D62: 17(9) | E62: 270000
A63: 2 | B63: NDANUSA MOHAMMED MANZUMA | C63: SNR RESEARCH FELLOW | D63: 15(8) | E63: 126000
A64: 3 | B64: EJALONIBU GANIYU LAYI | C64: RESEARCH FELLOW 1 | D64: 14(8) | E64: 90000
A65: 4 | B65: LOHNA BONKAT JONATHAN | C65: RESEARCH FELLOW 11 | D65: 13(10) | E65: 90000
A66: 5 | B66: YUNUSA ABDULLAHI | C66: RESEARCH FELLOW 1 | D66: 14(11) | E66: 90000
A67: 7 | B67: UDEFUNA NNADOZIE PATRICK | C67: RESEARCH OFFICER | D67: 12(8) | E67: 68000
A68: 8 | B68: SHAFIU YAHYA MIKAIL | C68: PRINCIPAL RESEARCH OFFICER | D68: 12(8) | E68: 68000
A69: 9 | B69: HASSAN YERIMA | C69: PRINCIPAL RESEARCH OFFICER | D69: 12(8) | E69: 68000
A70: 10 | B70: HAUWA PATE SADIQ | C70: PRINCIPAL PROGRAMME OFFICER | D70: 12(9) | E70: 68000
A71: 11 | B71: KOLAPO Q. ABAYOMI | C71: RESEARCH OFFICER | D71: 10(8) | E71: 68000
B72: TOTAL | C72: 12 | E72: =SUM(E62:E71) -> 1006000
B74: DEPARTMENT OF STUDIES
A75: 1 | B75: DR ASIMIYU G. ABIOLA | C75: DIRECTOR POST GRADUATE | D75: 17(9) | E75: 270000
A76: 2 | B76: USMAN WALI | C76: SENIOR RESEARCH FELLOW | D76: 15 (8) | E76: 126000
A77: 3 | B77: AYOBOLU OLAJIDE OLUFUNSHO | C77: ASST.DIR., INFORMATION | D77: 15 (9) | E77: 126000
A78: 4 | B78: ANTHONY EDET | C78: CHIEF PROGRAMMES OFFICER | D78: 14(9) | E78: 90000
A79: 5 | B79: IGWE STACY | C79: PROGRAMME OFFICER | D79: 10(9) | E79: 68000
A80: 6 | B80: OLANIYAN TAIWO ABINBOLA | C80: PROGRAMME OFFICER | D80: 9(8) | E80: 54000
A81: 7 | B81: AMINAT JUMOKE SULAIMON | C81: AST. PROGRAMME OFFICER | D81: 8(8) | E81: 54000
B82: TOTAL | C82: 7 | E82: =SUM(E75:E81) -> 788000
B84: ECON. DEV. & SOC. RESEARCH
A85: 1 | B85: TERFA WILLIAMS ABRAHAM | C85: SNR RESEARCH FELLOW | D85: 15(9) | E85: 126000
A86: 2 | B86: DR AUGUSTINE C. OSIGWE | C86: SNR RESEARCH FELLOW | D86: 15(9) | E86: 126000
A87: 3 | B87: OMOJU OLUWASOLA EMMANUEL | C87: SNR RESEARCH FELLOW | D87: 15(7) | E87: 126000
A88: 4 | B88: IBE EZECHI CYRIACUS | C88: RESEARCH FELLOW II | D88: 13(11) | E88: 90000
A89: 5 | B89: OSIKHEN LEO IGBANOI | C89: RESEARCH FELLOW 11 | D89: 13(10) | E89: 90000
A90: 6 | B90: OKUNGBOWA OSARETIN GODSPOWER | C90: RESEARCH FELLOW 1 | D90: 14(7) | E90: 90000
A91: 7 | B91: YUSUF IBRAHIM | C91: PRINCIPAL RESEARCH OFFICER | D91: 12(8) | E91: 68000
A92: 8 | B92: MUSTAPHA RAFIU AYOBANJI | C92: RESEARCH FELLOW 11 | D92: 13(7) | E92: 90000
A93: 9 | B93: MARYAM MUSA SADA | C93: ASSIT. RESEARCH OFFICER | D93: 10(8) | E93: 68000
A94: 10 | B94: CHARITY EZENWAJIOBI | C94: REASEARCH. ASST. | D94: 8(9) | E94: 54000
B95: TOTAL | C95: 11 | E95: =SUM(E85:E94) -> 928000
B97: TRAINING & INT''L COOP
A98: 1 | B98: AKINSANMI ADEJOKE OLUKEMI | C98: Ag. DIR. TRAINING & IC | D98: 17(7) | E98: 270000
A99: 2 | B99: MOHAMMED R. ADAMU | C99: CHIEF TRAINING OFFICER | D99: 14(9) | E99: 90000
A100: 3 | B100: OKECHUKWU UCHENNA HULDA | C100: PRINCIPALTRAINING OFFICER | D100: 12(9) | E100: 68000
A101: 4 | B101: TASSNEEM IBRAHIM | C101: SENIOR PROGRAMME OFFICER | D101: 10(8) | E101: 68000
B102: TOTAL | C102: 4 | E102: =SUM(E98:E101) -> 496000
B104: LIBRARY & DOCUMENTATION
A105: 1 | B105: DR MAIMUNA IZAH | C105: INSITUTE LIBRARIAN | D105: 17(9) | E105: 270000
A106: 2 | B106: CATHERINE E. IKOKOH | C106: SNR RESEARCH FELLOW DOCU | D106: 16(9) | E106: 180000
A107: 3 | B107: ALIYU SANNI ABUBAKAR | C107: RESEARCH FELLOW 11 DATA & DOCU | D107: 13(11) | E107: 90000
A108: 4 | B108: CHINAKO N. ASOGWA | C108: RESEARCH FELLOW 11 DATA & DOCU | D108: 13(11) | E108: 90000
A109: 5 | B109: AMOS ABA | C109: LIBRARY ASSISTANT | D109: 8(12) | E109: 54000
A110: 6 | B110: TITILAYO DANIEL MARVELLOUS | C110: LIBRARY ASSISTANT | D110: 8(11) | E110: 54000
A111: 7 | B111: ENENCHE JEREMIAH AGADA | C111: LIBRARY ASSISTANT | D111: 8(9) | E111: 54000
B112: TOTAL | C112: 7 | E112: =SUM(E105:E111) -> 792000
B114: LEG, CTRE FOR SEC. ANALYSIS
A115: 1 | B115: NGARA CHRISTOPHER OCHANJA | C115: SNR RESEARCH FELLOW | D115: 15(8) | E115: 126000
A116: 2 | B116: EGUATU U. ONYEJELEM | C116: PRINCIPAL M&E OFFICER | D116: 12(9) | E116: 68000
A117: 3 | B117: CHRISTIAN MADUABUCHI ODO | C117: PRINCIPAL ICT OFFICER | D117: 12(10) | E117: 68000
B118: TOTAL | C118: 2 | E118: =SUM(E115:E117) -> 262000
B120: FINANCE & ACCOUNTS
A121: 1 | B121: IBRAHIM M. MSHELIA | C121: DIR. FINANCE & ACCOUNTS | D121: 17(9) | E121: 270000
A122: 2 | B122: RAHILA NURUDEEN HABU | C122: DEP. DIRECTOR, ACCOUNTS | D122: 16(8) | E122: 180000
A123: 3 | B123: TONDO IORWUESE EDWARD | C123: ASST. DIRECTOR, ACCOUNTS | D123: 15(9) | E123: 126000
A124: 4 | B124: ARAOYE GANIYAT TITILOLA | C124: ASST. DIRECTOR, ACCOUNTS | D124: 15(7) | E124: 126000
A125: 5 | B125: SHEHU ABDULLAHI | C125: CHIEF ACCOUNT OFFICER | D125: 14(10) | E125: 90000
...

Sheet Welfare Summary
A2: 1 | B2: Permanent Staff | C2: ='Welfare June'!E194 -> 13858000
A3: 2 | B3: Contract Staff | C3: ='[4]CONTRACT Welfare'!$E$26 -> 1688000
A4: 3 | B4: Casual, Sabbatical & NYSC | C4: ='[4]CAS. SABB. NYSC Welfare'!$D$58 -> 1791000
A5: 4 | B5: Consultants | C5: ='[4]CONSULTANCY Welfare'!$D$31 -> 1746000
A6: 5 | B6: Cleaners & Securities | C6: ='[4]Welfare Others'!$C$92 -> 1225000
C7: =SUM(C2:C6) -> 20308000

Sheet Arrears of Res. Allow
D1: OLD PAYE | E1: ADJUSTED PAYE | F1: DIFFERENCE | G1: FOR 7 MONTHS | H1: TOTAL DIFF IN RES ALLOW | I1: NET DIFFERENCE
A2: AYOBOLU OLAJIDE OLUFUNSHO | B2: ASST.DIR., INFORMATION | C2: 15 (9) | D2: =64596.94 -> 64596.94 | E2: =79956.94 -> 79956.94 | F2: =E2-D2 -> 15360 | G2: =F2*7 -> 107520 | H2: 560000 | I2: =H2-G2 -> 452480

Sheet Additional Leg Duty Allowance
A1: NATIONAL INSTITUTE FOR LEGISLATIVE AND DEMOCRATIC STUDIES
A2: STAFF PAYROLL FOR THE MONTH OF MARCH, 2024
E3: ='[1]FEB 08'!E11/'[1]FEB 08'!M11 -> #REF!
B4: STAFF NAME | C4: DESIGNATION | D4: GRADE LEVEL | E4: BASIC SALARY | F4: ALLCE/ AREARS | G4: ALLOWANCE | H4: ALLOWANCE | I4: DUTY ALLCE | J4: GROSS SALARY | K4: AUCTION | L4: COOP CONTR/SPEC SAVINGS | M4: COOP. LOAN RECOVERY | N4: NHF DED. | O4: PAYE | P4: NEW PAYE | Q4: DIFFERENCE | R4: EMPLOYEE PENSIONS | S4: TOTAL DEDUCTION | T4: FEBRUARY, 2024 | U4: MARCH, 2024
E5: N | G5: N | H5: N | I5: N | J5: N | K5: N | L5: N | M5: N | N5: N | O5: N | P5: N | Q5: N | R5: N | S5: N | T5: N | U5: N
A6: S/N | B6: DG'S OFFICE
A7: 1 | B7: RAHEEM USMAN AYIGORO | C7: SA-INFRASTRUCTURE | D7: 16 (9) | E7: 762373.17 | H7: =90000 -> 90000 | I7: 0 | J7: =E7+F7+G7+H7+I7 -> 852373.17 | L7: =100000 -> 100000 | O7: 130612.26 | P7: ='March New PAYE '!Z7 -> 149812.26 | Q7: =P7-O7 -> 19200 | R7: 60989.853 | S7: =O7+N7+M7+L7+K7+R7 -> 291602.12 | T7: 560771.05 | U7: =J7-S7 -> 560771.05
A8: 2 | B8: MARIAM MOHAMMED BELLO | C8: SA- SPECIAL DUTIES | D8: 16 (9) | E8: 762373.17 | H8: =90000 -> 90000 | I8: =100000+100000 -> 200000 | J8: =E8+F8+G8+H8+I8 -> 1052373.2 | O8: 180722.31 | P8: ='March New PAYE '!Z8 -> 199922.31 | Q8: =P8-O8 -> 19200 | S8: =O8+N8+M8+L8+K8+R8 -> 180722.31 | T8: 871650.85 | U8: =J8-S8 -> 871650.85
A9: 3 | B9: MOSHOOD M. OLALERE | C9: DEPUTY DIR. GENERAL SERVICE | D9: 16 (9) | E9: 762373.17 | H9: =80000+10000 -> 90000 | I9: 150000 | J9: =E9+F9+G9+H9+I9 -> 1002373.2 | L9: =20000+60000 -> 80000 | M9: ='[2]OCTOBER 2023 '!$D$193 -> 230499.8 | N9: 1066.3293 | O9: 159207.53 | P9: ='March New PAYE '!Z10 -> 178407.53 | Q9: =P9-O9 -> 19200 | R9: 60989.853 | S9: =O9+N9+M9+L9+K9+R9 -> 531763.51 | T9: 470609.66 | U9: =J9-S9 -> 470609.66
A10: 4 | B10: REKIYA IBRAHIM ATTAH | C10: DEPUTY DIRECTOR TRAINING | D10: 16 (9) | E10: 762373.17 | H10: =90000 -> 90000 | I10: 100000 | J10: =E10+F10+G10+H10+I10 -> 952373.17 | L10: =50000 -> 50000 | M10: =91666.67 -> 91666.67 | O10: 161522.31 | P10: ='March New PAYE '!Z11 -> 180722.31 | Q10: =P10-O10 -> 19200 | S10: =O10+N10+M10+L10+K10+R10 -> 303188.98 | T10: 649184.18 | U10: =J10-S10 -> 649184.18
A11: 5 | B11: TERFA WILLIAMS ABRAHAM | C11: SNR RESEARCH FELLOW | D11: 15(9) | E11: 620675.58 | G11: =160000 -> 160000 | I11: 100000 | J11: =SUM(E11:I11) -> 880675.58 | O11: 138222.8 | P11: ='March New PAYE '!Z80 -> 157422.8 | Q11: =P11-O11 -> 19200 | R11: 49654.047 | S11: =O11+N11+M11+L11+K11+R11 -> 187876.85 | T11: 692798.73 | U11: =J11-S11 -> 692798.73
A12: 6 | B12: DR FRANCIS NDUM OJIE | C12: AD, TRAINING & IC./SA TO DG | D12: 15(7) | E12: 582118.08 | G12: 160000 | I12: =100000 -> 100000 | J12: =E12+F12+G12+H12+I12 -> 842118.08 | N12: 775.496 | O12: 131263.11 | P12: ='March New PAYE '!Z13 -> 150463.11 | Q12: =P12-O12 -> 19200 | R12: 46569.447 | S12: =O12+N12+M12+L12+K12+R12 -> 178608.05 | T12: 663510.03 | U12: =J12-S12 -> 663510.03
A13: 7 | B13: DORIS DAKDA AARON | C13: RESEARCH FELLOW I | D13: 14(8) | E13: 442746.5 | G13: =140000 -> 140000 | I13: 150000 | J13: =E13+F13+G13+H13+I13 -> 732746.5 | L13: 70000 | O13: 112553.41 | P13: ='March New PAYE '!Z16 -> 131753.41 | Q13: =P13-O13 -> 19200 | R13: 35419.72 | S13: =O13+N13+M13+L13+K13+R13 -> 217973.13 | T13: 514773.37 | U13: =J13-S13 -> 514773.37
A14: 8 | B14: HASSANA AHMED IBRAHIM | C14: PA- TO DG | D14: 13 (9) | E14: 416026.92 | G14: =120000 -> 120000 | I14: =100000 -> 100000 | J14: =E14+F14+G14+H14+I14 -> 636026.92 | L14: =30000-20000 -> 10000 | M14: =95833.33 -> 95833.33 | N14: 618.5315 | O14: 94274.903 | P14: ='March New PAYE '!Z19 -> 113474.9 | Q14: =P14-O14 -> 19200 | R14: 33282.153 | S14: =O14+N14+M14+L14+K14+R14 -> 234008.92 | T14: 402018 | U14: =J14-S14 -> 402018
A15: 9 | B15: LUCKY AGWOM | C15: RESEARCH ASSISTANT | D15: 12(7) | E15: 353512.5 | G15: =100000 -> 100000 | I15: 100000 | J15: =E15+F15+G15+H15+I15 -> 553512.5 | L15: 50000 | O15: 79511.115 | P15: ='March New PAYE '!Z21 -> 98711.115 | Q15: =P15-O15 -> 19200 | R15: 28281 | S15: =O15+N15+M15+L15+K15+R15 -> 157792.11 | T15: 395720.39 | U15: =J15-S15 -> 395720.39
A16: 10 | B16: FARUQ ATOFARATI | C16: PA (SPECIAL DUTIES) TO DG | D16: 10(7) | E16: 293029.67 | H16: =50000+10000 -> 60000 | I16: 100000 | J16: =E16+F16+G16+H16+I16 -> 453029.67 | O16: 61147.427 | P16: ='March New PAYE '!Z23 -> 80347.427 | Q16: =P16-O16 -> 19200 | R16: 23442.373 | S16: =O16+N16+M16+L16+K16+R16 -> 84589.8 | T16: 368439.87 | U16: =J16-S16 -> 368439.87
B17: TOTAL | C17: 10 | E17: 14898686 | G17: =SUM(#REF!) -> #REF! | H17: =SUM(#REF!) -> #REF! | I17: =SUM(#REF!) -> #REF! | J17: =SUM(#REF!) -> #REF! | K17: =SUM(#REF!) -> #REF! | L17: =SUM(#REF!) -> #REF! | M17: =SUM(#REF!) -> #REF! | N17: 6347.233 | O17: =SUM(O7:O16) -> 1249037.2 | P17: =SUM(P7:P16) -> 1441037.2 | Q17: =SUM(Q7:Q16) -> 192000 | R17: 1130905.1 | S17: =SUM(#REF!) -> #REF! | T17: 11108681 | U17: =SUM(#REF!) -> #REF!
J19: PREPARED BY: Rahila N. Habu SIGNATURE……………….. DATE: 29TH JANUARY, 2024

Sheet March New PAYE 
A1: NATIONAL INSTITUTE FOR LEGISLATIVE AND DEMOCRATIC STUDIES
A2: NATIONAL ASSEMBLY ABUJA
A3: TAX COMPUTATION FOR 2022
A4: S/NO | B4: NAME | C4: MONTHLY TOTAL SALARY | D4: NO OF MONTHS | E4: ANNUAL SALARY GROSSED UP | F4: NATIONAL HOUSING SCHEME = 2.5% OF BASIC SALARY | G4: PENSION CONTRIBUTION = 8% OF CONSOLIDATED | H4: NHIS | I4: NET SALARY (EXC OF CRA) | M4: CRA=#200,000+(20% 0F NET SALARY (EXC OF CRA) | N4: TOTAL RELIEF | O4: CHARGEABLE INCOME | P4: FIRST N300,000 @ 7% | Q4: NEXT N300,000 @ 11% | R4: NEXT N500,000 @ 15% | S4: NEXT N500,000@ 19% | T4: NEXT N1,600,000 @ 21% | U4: ABOVE N3,200,000 @ 24% | V4: ANNUAL TAX PAYABLE | X4: MONTHLY TAX PAYABLE | Y4: MINIMUM TAX PAYABLE | Z4: NEW ACTUAL TAX PAYABLE | AB4: Difference
A5: 1 | B5: DG'S OFFICE
A6: 3 | B6: PROF. ABUBAKAR O. SULAIMAN | C6: 1934986.2 | D6: 12 | E6: =C6*D6 -> 23219834 | I6: =E6-F6-G6-H6 -> 23219834 | J6: 200000 | K6: 0.2 | L6: =I6*K6 -> 4643966.8 | M6: =J6+L6 -> 4843966.8 | N6: =F6+G6+H6+M6 -> 4843966.8 | O6: =E6-N6 -> 18375867 | P6: =IF(O6<300000,0.07*O6,21000) -> 21000 | Q6: =IF((O6-300000)<0,0,IF((O6-300000)<300000,0.11*(O6-300000),33000)) -> 33000 | R6: =IF((O6-600000)<0,0,IF((O6-600000)<500000,0.15*(O6-600000),75000)) -> 75000 | S6: =IF((O6-1100000)<0,0,IF((O6-1100000)<500000,0.19*(O6-1100000),95000)) -> 95000 | T6: =IF((O6-1600000)<0,0,IF((O6-1600000)<1600000,0.21*(O6-1600000),336000)) -> 336000 | U6: =24%*(O6-3200000) -> 3642208.1 | V6: =P6+Q6+R6+S6+T6+U6 -> 4202208.1 | W6: 12 | X6: =V6/W6 -> 350184.01 | Z6: =X6 -> 350184.01 | AA6: 201165.84 | AB6: =Z6-AA6 -> 149018.17
A7: 4 | B7: RAHEEM USMAN AYIGORO | C7: =852373.166666667+100000 -> 952373.17 | D7: 12 | E7: =C7*D7 -> 11428478 | G7: 731878.24 | I7: =E7-F7-G7-H7 -> 10696600 | J7: 200000 | K7: 0.2 | L7: =I7*K7 -> 2139320 | M7: =J7+L7 -> 2339320 | N7: =F7+G7+H7+M7 -> 3071198.2 | O7: =E7-N7 -> 8357279.8 | P7: =IF(O7<300000,0.07*O7,21000) -> 21000 | Q7: =IF((O7-300000)<0,0,IF((O7-300000)<300000,0.11*(O7-300000),33000)) -> 33000 | R7: =IF((O7-600000)<0,0,IF((O7-600000)<500000,0.15*(O7-600000),75000)) -> 75000 | S7: =IF((O7-1100000)<0,0,IF((O7-1100000)<500000,0.19*(O7-1100000),95000)) -> 95000 | T7: =IF((O7-1600000)<0,0,IF((O7-1600000)<1600000,0.21*(O7-1600000),336000)) -> 336000 | U7: =24%*(O7-3200000) -> 1237747.2 | V7: =P7+Q7+R7+S7+T7+U7 -> 1797747.2 | W7: 12 | X7: =V7/W7 -> 149812.26 | Z7: =X7 -> 149812.26 | AA7: 82627.951 | AB7: =Z7-AA7 -> 67184.311
A8: 5 | B8: MARIAM MOHAMMED BELLO | C8: =1052373.16666667+100000 -> 1152373.2 | D8: 12 | E8: =C8*D8 -> 13828478 | G8: 0 | I8: =E8-F8-G8-H8 -> 13828478 | J8: 200000 | K8: 0.2 | L8: =I8*K8 -> 2765695.6 | M8: =J8+L8 -> 2965695.6 | N8: =F8+G8+H8+M8 -> 2965695.6 | O8: =E8-N8 -> 10862782 | P8: =IF(O8<300000,0.07*O8,21000) -> 21000 | Q8: =IF((O8-300000)<0,0,IF((O8-300000)<300000,0.11*(O8-300000),33000)) -> 33000 | R8: =IF((O8-600000)<0,0,IF((O8-600000)<500000,0.15*(O8-600000),75000)) -> 75000 | S8: =IF((O8-1100000)<0,0,IF((O8-1100000)<500000,0.19*(O8-1100000),95000)) -> 95000 | T8: =IF((O8-1600000)<0,0,IF((O8-1600000)<1600000,0.21*(O8-1600000),336000)) -> 336000 | U8: =24%*(O8-3200000) -> 1839067.8 | V8: =P8+Q8+R8+S8+T8+U8 -> 2399067.8 | W8: 12 | X8: =V8/W8 -> 199922.31 | Z8: =X8 -> 199922.31 | AA8: 121027.95 | AB8: =Z8-AA8 -> 78894.363
A9: 6 | B9: DR IKEME ARTHUR J.O | C9: 942373.17 | D9: 12 | E9: =C9*D9 -> 11308478 | F9: ='[5]JANUARY 2024'!$V$10*12 -> 12795.951 | G9: 731878.24 | I9: =E9-F9-G9-H9 -> 10563804 | J9: 200000 | K9: 0.2 | L9: =I9*K9 -> 2112760.8 | M9: =J9+L9 -> 2312760.8 | N9: =F9+G9+H9+M9 -> 3057435 | O9: =E9-N9 -> 8251043 | P9: =IF(O9<300000,0.07*O9,21000) -> 21000 | Q9: =IF((O9-300000)<0,0,IF((O9-300000)<300000,0.11*(O9-300000),33000)) -> 33000 | R9: =IF((O9-600000)<0,0,IF((O9-600000)<500000,0.15*(O9-600000),75000)) -> 75000 | S9: =IF((O9-1100000)<0,0,IF((O9-1100000)<500000,0.19*(O9-1100000),95000)) -> 95000 | T9: =IF((O9-1600000)<0,0,IF((O9-1600000)<1600000,0.21*(O9-1600000),336000)) -> 336000 | U9: =24%*(O9-3200000) -> 1212250.3 | V9: =P9+Q9+R9+S9+T9+U9 -> 1772250.3 | W9: 12 | X9: =V9/W9 -> 147687.53 | Z9: =X9 -> 147687.53 | AA9: 99703.216 | AB9: =Z9-AA9 -> 47984.311
A10: 7 | B10: MOSHOOD M. OLALERE | C10: =1002373.16666667+100000 -> 1102373.2 | D10: 12 | E10: =C10*D10 -> 13228478 | F10: ='[5]JANUARY 2024'!$V$10*12 -> 12795.951 | G10: 731878.24 | I10: =E10-F10-G10-H10 -> 12483804 | J10: 200000 | K10: 0.2 | L10: =I10*K10 -> 2496760.8 | M10: =J10+L10 -> 2696760.8 | N10: =F10+G10+H10+M10 -> 3441435 | O10: =E10-N10 -> 9787043 | P10: =IF(O10<300000,0.07*O10,21000) -> 21000 | Q10: =IF((O10-300000)<0,0,IF((O10-300000)<300000,0.11*(O10-300000),33000)) -> 33000 | R10: =IF((O10-600000)<0,0,IF((O10-600000)<500000,0.15*(O10-600000),75000)) -> 75000 | S10: =IF((O10-1100000)<0,0,IF((O10-1100000)<500000,0.19*(O10-1100000),95000)) -> 95000 | T10: =IF((O10-1600000)<0,0,IF((O10-1600000)<1600000,0.21*(O10-1600000),336000)) -> 336000 | U10: =24%*(O10-3200000) -> 1580890.3 | V10: =P10+Q10+R10+S10+T10+U10 -> 2140890.3 | W10: 12 | X10: =V10/W10 -> 178407.53 | Z10: =X10 -> 178407.53 | AA10: 111223.22 | AB10: =Z10-AA10 -> 67184.311
A11: 8 | B11: REKIYA IBRAHIM ATTAH | C11: =952373.166666667+100000 -> 1052373.2 | D11: 12 | E11: =C11*D11 -> 12628478 | G11: 0 | I11: =E11-F11-G11-H11 -> 12628478 | J11: 200000 | K11: 0.2 | L11: =I11*K11 -> 2525695.6 | M11: =J11+L11 -> 2725695.6 | N11: =F11+G11+H11+M11 -> 2725695.6 | O11: =E11-N11 -> 9902782.4 | P11: =IF(O11<300000,0.07*O11,21000) -> 21000 | Q11: =IF((O11-300000)<0,0,IF((O11-300000)<300000,0.11*(O11-300000),33000)) -> 33000 | R11: =IF((O11-600000)<0,0,IF((O11-600000)<500000,0.15*(O11-600000),75000)) -> 75000 | S11: =IF((O11-1100000)<0,0,IF((O11-1100000)<500000,0.19*(O11-1100000),95000)) -> 95000 | T11: =IF((O11-1600000)<0,0,IF((O11-1600000)<1600000,0.21*(O11-1600000),336000)) -> 336000 | U11: =24%*(O11-3200000) -> 1608667.8 | V11: =P11+Q11+R11+S11+T11+U11 -> 2168667.8 | W11: 12 | X11: =V11/W11 -> 180722.31 | Z11: =X11 -> 180722.31 | AA11: 101827.95 | AB11: =Z11-AA11 -> 78894.363
A12: 9 | B12: ANDRAWUS MUSA | C12: 750675.58 | D12: 12 | E12: =C12*D12 -> 9008107 | F12: ='[5]JANUARY 2024'!$V$13*12 -> 10052.25 | G12: 595848.56 | I12: =E12-F12-G12-H12 -> 8402206.2 | J12: 200000 | K12: 0.2 | L12: =I12*K12 -> 1680441.2 | M12: =J12+L12 -> 1880441.2 | N12: =F12+G12+H12+M12 -> 2486342 | O12: =E12-N12 -> 6521765 | P12: =IF(O12<300000,0.07*O12,21000) -> 21000 | Q12: =IF((O12-300000)<0,0,IF((O12-300000)<300000,0.11*(O12-300000),33000)) -> 33000 | R12: =IF((O12-600000)<0,0,IF((O12-600000)<500000,0.15*(O12-600000),75000)) -> 75000 | S12: =IF((O12-1100000)<0,0,IF((O12-1100000)<500000,0.19*(O12-1100000),95000)) -> 95000 | T12: =IF((O12-1600000)<0,0,IF((O12-1600000)<1600000,0.21*(O12-1600000),336000)) -> 336000 | U12: =24%*(O12-3200000) -> 797223.59 | V12: =P12+Q12+R12+S12+T12+U12 -> 1357223.6 | W12: 12 | X12: =V12/W12 -> 113101.97 | Z12: =X12 -> 113101.97 | AA12: 74036.103 | AB12: =Z12-AA12 -> 39065.863
A13: 10 | B13: DR FRANCIS NDUM OJIE | C13: =842118.083333333+100000 -> 942118.08 | D13: 12 | E13: =C13*D13 -> 11305417 | F13: ='[5]JANUARY 2024'!$V$14*12 -> 9305.952 | G13: 558833.36 | I13: =E13-F13-G13-H13 -> 10737278 | J13: 200000 | K13: 0.2 | L13: =I13*K13 -> 2147455.5 | M13: =J13+L13 -> 2347455.5 | N13: =F13+G13+H13+M13 -> 2915594.8 | O13: =E13-N13 -> 8389822.2 | P13: =IF(O13<300000,0.07*O13,21000) -> 21000 | Q13: =IF((O13-300000)<0,0,IF((O13-300000)<300000,0.11*(O13-300000),33000)) -> 33000 | R13: =IF((O13-600000)<0,0,IF((O13-600000)<500000,0.15*(O13-600000),75000)) -> 75000 | S13: =IF((O13-1100000)<0,0,IF((O13-1100000)<500000,0.19*(O13-1100000),95000)) -> 95000 | T13: =IF((O13-1600000)<0,0,IF((O13-1600000)<1600000,0.21*(O13-1600000),336000)) -> 336000 | U13: =24%*(O13-3200000) -> 1245557.3 | V13: =P13+Q13+R13+S13+T13+U13 -> 1805557.3 | W13: 12 | X13: =V13/W13 -> 150463.11 | Z13: =X13 -> 150463.11 | AA13: 94625.782 | AB13: =Z13-AA13 -> 55837.328
A14: 11 | B14: ALI ABDULLAHI | C14: 554373.75 | D14: 12 | E14: =C14*D14 -> 6652485 | G14: 464998.8 | I14: =E14-F14-G14-H14 -> 6187486.2 | J14: 200000 | K14: 0.2 | L14: =I14*K14 -> 1237497.2 | M14: =J14+L14 -> 1437497.2 | N14: =F14+G14+H14+M14 -> 1902496 | O14: =E14-N14 -> 4749989 | P14: =IF(O14<300000,0.07*O14,21000) -> 21000 | Q14: =IF((O14-300000)<0,0,IF((O14-300000)<300000,0.11*(O14-300000),33000)) -> 33000 | R14: =IF((O14-600000)<0,0,IF((O14-600000)<500000,0.15*(O14-600000),75000)) -> 75000 | S14: =IF((O14-1100000)<0,0,IF((O14-1100000)<500000,0.19*(O14-1100000),95000)) -> 95000 | T14: =IF((O14-1600000)<0,0,IF((O14-1600000)<1600000,0.21*(O14-1600000),336000)) -> 336000 | U14: =24%*(O14-3200000) -> 371997.35 | V14: =P14+Q14+R14+S14+T14+U14 -> 931997.35 | W14: 12 | X14: =V14/W14 -> 77666.446 | Z14: =X14 -> 77666.446 | AA14: 44846.617 | AB14: =Z14-AA14 -> 32819.829
A15: 12 | B15: EMILY EKHIDE | C15: =660498 -> 660498 | D15: 12 | E15: =C15*D15 -> 7925976 | G15: 451678.08 | I15: =E15-F15-G15-H15 -> 7474297.9 | J15: 200000 | K15: 0.2 | L15: =I15*K15 -> 1494859.6 | M15: =J15+L15 -> 1694859.6 | N15: =F15+G15+H15+M15 -> 2146537.7 | O15: =E15-N15 -> 5779438.3 | P15: =IF(O15<300000,0.07*O15,21000) -> 21000 | Q15: =IF((O15-300000)<0,0,IF((O15-300000)<300000,0.11*(O15-300000),33000)) -> 33000 | R15: =IF((O15-600000)<0,0,IF((O15-600000)<500000,0.15*(O15-600000),75000)) -> 75000 | S15: =IF((O15-1100000)<0,0,IF((O15-1100000)<500000,0.19*(O15-1100000),95000)) -> 95000 | T15: =IF((O15-1600000)<0,0,IF((O15-1600000)<1600000,0.21*(O15-1600000),336000)) -> 336000 | U15: =24%*(O15-3200000) -> 619065.2 | V15: =P15+Q15+R15+S15+T15+U15 -> 1179065.2 | W15: 12 | X15: =V15/W15 -> 98255.433 | Z15: =X15 -> 98255.433 | AA15: 46666.667 | AB15: =Z15-AA15 -> 51588.767
A16: 13 | B16: DORIS DAKDA AARON | C16: =732746.5+100000 -> 832746.5 | D16: 12 | E16: =C16*D16 -> 9992958 | G16: 425036.64 | I16: =E16-F16-G16-H16 -> 9567921.4 | J16: 200000 | K16: 0.2 | L16: =I16*K16 -> 1913584.3 | M16: =J16+L16 -> 2113584.3 | N16: =F16+G16+H16+M16 -> 2538620.9 | O16: =E16-N16 -> 7454337.1 | P16: =IF(O16<300000,0.07*O16,21000) -> 21000 | Q16: =IF((O16-300000)<0,0,IF((O16-300000)<300000,0.11*(O16-300000),33000)) -> 33000 | R16: =IF((O16-600000)<0,0,IF((O16-600000)<500000,0.15*(O16-600000),75000)) -> 75000 | S16: =IF((O16-1100000)<0,0,IF((O16-1100000)<500000,0.19*(O16-1100000),95000)) -> 95000 | T16: =IF((O16-1600000)<0,0,IF((O16-1600000)<1600000,0.21*(O16-1600000),336000)) -> 336000 | U16: =24%*(O16-3200000) -> 1021040.9 | V16: =P16+Q16+R16+S16+T16+U16 -> 1581040.9 | W16: 12 | X16: =V16/W16 -> 131753.41 | Z16: =X16 -> 131753.41 | AA16: 46666.667 | AB16: =Z16-AA16 -> 85086.742
A17: 14 | B17: ABDULSALAM S. MUSTAPHA | C17: 511804.92 | D17: 12 | E17: =C17*D17 -> 6141659 | G17: 424132.72 | I17: =E17-F17-G17-H17 -> 5717526.3 | J17: 200000 | K17: 0.2 | L17: =I17*K17 -> 1143505.3 | M17: =J17+L17 -> 1343505.3 | N17: =F17+G17+H17+M17 -> 1767638 | O17: =E17-N17 -> 4374021 | P17: =IF(O17<300000,0.07*O17,21000) -> 21000 | Q17: =IF((O17-300000)<0,0,IF((O17-300000)<300000,0.11*(O17-300000),33000)) -> 33000 | R17: =IF((O17-600000)<0,0,IF((O17-600000)<500000,0.15*(O17-600000),75000)) -> 75000 | S17: =IF((O17-1100000)<0,0,IF((O17-1100000)<500000,0.19*(O17-1100000),95000)) -> 95000 | T17: =IF((O17-1600000)<0,0,IF((O17-1600000)<1600000,0.21*(O17-1600000),336000)) -> 336000 | U17: =24%*(O17-3200000) -> 281765.05 | V17: =P17+Q17+R17+S17+T17+U17 -> 841765.05 | W17: 12 | X17: =V17/W17 -> 70147.087 | Z17: =X17 -> 70147.087 | AA17: 42046.064 | AB17: =Z17-AA17 -> 28101.023
A18: 15 | B18: PERCY TERFA GBAHABO | C18: 548915.92 | D18: 12 | E18: =C18*D18 -> 6586991 | G18: 411759.28 | I18: =E18-F18-G18-H18 -> 6175231.7 | J18: 200000 | K18: 0.2 | L18: =I18*K18 -> 1235046.3 | M18: =J18+L18 -> 1435046.3 | N18: =F18+G18+H18+M18 -> 1846805.6 | O18: =E18-N18 -> 4740185.4 | P18: =IF(O18<300000,0.07*O18,21000) -> 21000 | Q18: =IF((O18-300000)<0,0,IF((O18-300000)<300000,0.11*(O18-300000),33000)) -> 33000 | R18: =IF((O18-600000)<0,0,IF((O18-600000)<500000,0.15*(O18-600000),75000)) -> 75000 | S18: =IF((O18-1100000)<0,0,IF((O18-1100000)<500000,0.19*(O18-1100000),95000)) -> 95000 | T18: =IF((O18-1600000)<0,0,IF((O18-1600000)<1600000,0.21*(O18-1600000),336000)) -> 336000 | U18: =24%*(O18-3200000) -> 369644.49 | V18: =P18+Q18+R18+S18+T18+U18 -> 929644.49 | W18: 12 | X18: =V18/W18 -> 77470.374 | Z18: =X18 -> 77470.374 | AA18: 46666.667 | AB18: =Z18-AA18 -> 30803.708
A19: 16 | B19: HASSANA AHMED IBRAHIM | C19: =636026.916666667+100000 -> 736026.92 | D19: 12 | E19: =C19*D19 -> 8832323 | F19: =618.53*12 -> 7422.36 | G19: 399385.84 | I19: =E19-F19-G19-H19 -> 8425514.8 | J19: 200000 | K19: 0.2 | L19: =I19*K19 -> 1685103 | M19: =J19+L19 -> 1885103 | N19: =F19+G19+H19+M19 -> 2291911.2 | O19: =E19-N19 -> 6540411.8 | P19: =IF(O19<300000,0.07*O19,21000) -> 21000 | Q19: =IF((O19-300000)<0,0,IF((O19-300000)<300000,0.11*(O19-300000),33000)) -> 33000 | R19: =IF((O19-600000)<0,0,IF((O19-600000)<500000,0.15*(O19-600000),75000)) -> 75000 | S19: =IF((O19-1100000)<0,0,IF((O19-1100000)<500000,0.19*(O19-1100000),95000)) -> 95000 | T19: =IF((O19-1600000)<0,0,IF((O19-1600000)<1600000,0.21*(O19-1600000),336000)) -> 336000 | U19: =24%*(O19-3200000) -> 801698.84 | V19: =P19+Q19+R19+S19+T19+U19 -> 1361698.8 | W19: 12 | X19: =V19/W19 -> 113474.9 | Z19: =X19 -> 113474.9 | AA19: 46666.667 | AB19: =Z19-AA19 -> 66808.237
A20: 17 | B20: ADUGBA RICHARD TERSEER | C20: 537895.17 | D20: 12 | E20: =C20*D20 -> 6454742 | G20: 362779.36 | I20: =E20-F20-G20-H20 -> 6091962.6 | J20: 200000 | K20: 0.2 | L20: =I20*K20 -> 1218392.5 | M20: =J20+L20 -> 1418392.5 | N20: =F20+G20+H20+M20 -> 1781171.9 | O20: =E20-N20 -> 4673570.1 | P20: =IF(O20<300000,0.07*O20,21000) -> 21000 | Q20: =IF((O20-300000)<0,0,IF((O20-300000)<300000,0.11*(O20-300000),33000)) -> 33000 | R20: =IF((O20-600000)<0,0,IF((O20-600000)<500000,0.15*(O20-600000),75000)) -> 75000 | S20: =IF((O20-1100000)<0,0,IF((O20-1100000)<500000,0.19*(O20-1100000),95000)) -> 95000 | T20: =IF((O20-1600000)<0,0,IF((O20-1600000)<1600000,0.21*(O20-1600000),336000)) -> 336000 | U20: =24%*(O20-3200000) -> 353656.83 | V20: =P20+Q20+R20+S20+T20+U20 -> 913656.83 | W20: 12 | X20: =V20/W20 -> 76138.069 | Z20: =X20 -> 76138.069 | AA20: 52497.77 | AB20: =Z20-AA20 -> 23640.299
A21: 18 | B21: LUCKY AGWOM | C21: =553512.5+100000 -> 653512.5 | D21: 12 | E21: =C21*D21 -> 7842150 | G21: 339372 | I21: =E21-F21-G21-H21 -> 7502778 | J21: 200000 | K21: 0.2 | L21: =I21*K21 -> 1500555.6 | M21: =J21+L21 -> 1700555.6 | N21: =F21+G21+H21+M21 -> 2039927.6 | O21: =E21-N21 -> 5802222.4 | P21: =IF(O21<300000,0.07*O21,21000) -> 21000 | Q21: =IF((O21-300000)<0,0,IF((O21-300000)<300000,0.11*(O21-300000),33000)) -> 33000 | R21: =IF((O21-600000)<0,0,IF((O21-600000)<500000,0.15*(O21-600000),75000)) -> 75000 | S21: =IF((O21-1100000)<0,0,IF((O21-1100000)<500000,0.19*(O21-1100000),95000)) -> 95000 | T21: =IF((O21-1600000)<0,0,IF((O21-1600000)<1600000,0.21*(O21-1600000),336000)) -> 336000 | U21: =24%*(O21-3200000) -> 624533.38 | V21: =P21+Q21+R21+S21+T21+U21 -> 1184533.4 | W21: 12 | X21: =V21/W21 -> 98711.115 | Z21: =X21 -> 98711.115 | AA21: 46666.667 | AB21: =Z21-AA21 -> 52044.448
A22: 19 | B22: IDRIS IBRAHIM | C22: 463512.5 | D22: 12 | E22: =C22*D22 -> 5562150 | G22: 339372 | I22: =E22-F22-G22-H22 -> 5222778 | J22: 200000 | K22: 0.2 | L22: =I22*K22 -> 1044555.6 | M22: =J22+L22 -> 1244555.6 | N22: =F22+G22+H22+M22 -> 1583927.6 | O22: =E22-N22 -> 3978222.4 | P22: =IF(O22<300000,0.07*O22,21000) -> 21000 | Q22: =IF((O22-300000)<0,0,IF((O22-300000)<300000,0.11*(O22-300000),33000)) -> 33000 | R22: =IF((O22-600000)<0,0,IF((O22-600000)<500000,0.15*(O22-600000),75000)) -> 75000 | S22: =IF((O22-1100000)<0,0,IF((O22-1100000)<500000,0.19*(O22-1100000),95000)) -> 95000 | T22: =IF((O22-1600000)<0,0,IF((O22-1600000)<1600000,0.21*(O22-1600000),336000)) -> 336000 | U22: =24%*(O22-3200000) -> 186773.38 | V22: =P22+Q22+R22+S22+T22+U22 -> 746773.38 | W22: 12 | X22: =V22/W22 -> 62231.115 | Z22: =X22 -> 62231.115 | AA22: 46666.667 | AB22: =Z22-AA22 -> 15564.448
A23: 20 | B23: FARUQ ATOFARATI | C23: =453029.666666667+100000 -> 553029.67 | D23: 12 | E23: =C23*D23 -> 6636356 | G23: 281308.48 | I23: =E23-F23-G23-H23 -> 6355047.5 | J23: 200000 | K23: 0.2 | L23: =I23*K23 -> 1271009.5 | M23: =J23+L23 -> 1471009.5 | N23: =F23+G23+H23+M23 -> 1752318 | O23: =E23-N23 -> 4884038 | P23: =IF(O23<300000,0.07*O23,21000) -> 21000 | Q23: =IF((O23-300000)<0,0,IF((O23-300000)<300000,0.11*(O23-300000),33000)) -> 33000 | R23: =IF((O23-600000)<0,0,IF((O23-600000)<500000,0.15*(O23-600000),75000)) -> 75000 | S23: =IF((O23-1100000)<0,0,IF((O23-1100000)<500000,0.19*(O23-1100000),95000)) -> 95000 | T23: =IF((O23-1600000)<0,0,IF((O23-1600000)<1600000,0.21*(O23-1600000),336000)) -> 336000 | U23: =24%*(O23-3200000) -> 404169.12 | V23: =P23+Q23+R23+S23+T23+U23 -> 964169.12 | W23: 12 | X23: =V23/W23 -> 80347.427 | Z23: =X23 -> 80347.427 | AA23: 42371.816 | AB23: =Z23-AA23 -> 37975.611
A24: 21 | B24: ELIZABETH OGECHUKWU ONYEAKU | C24: 330481.67 | D24: 12 | E24: =C24*D24 -> 3965780 | G24: 259662.4 | I24: =E24-F24-G24-H24 -> 3706117.6 | J24: 200000 | K24: 0.2 | L24: =I24*K24 -> 741223.52 | M24: =J24+L24 -> 941223.52 | N24: =F24+G24+H24+M24 -> 1200885.9 | O24: =E24-N24 -> 2764894.1 | P24: =IF(O24<300000,0.07*O24,21000) -> 21000 | Q24: =IF((O24-300000)<0,0,IF((O24-300000)<300000,0.11*(O24-300000),33000)) -> 33000 | R24: =IF((O24-600000)<0,0,IF((O24-600000)<500000,0.15*(O24-600000),75000)) -> 75000 | S24: =IF((O24-1100000)<0,0,IF((O24-1100000)<500000,0.19*(O24-1100000),95000)) -> 95000 | T24: =IF((O24-1600000)<0,0,IF((O24-1600000)<1600000,0.21*(O24-1600000),336000)) -> 244627.76 | V24: =P24+Q24+R24+S24+T24+U24 -> 468627.76 | W24: 12 | X24: =V24/W24 -> 39052.313 | Z24: =X24 -> 39052.313 | AA24: 23036.012 | AB24: =Z24-AA24 -> 16016.301
A25: 22 | B25: VICTOR ASUKWO | C25: 330481.67 | D25: 12 | E25: =C25*D25 -> 3965780 | G25: 259662.4 | I25: =E25-F25-G25-H25 -> 3706117.6 | J25: 200000 | K25: 0.2 | L25: =I25*K25 -> 741223.52 | M25: =J25+L25 -> 941223.52 | N25: =F25+G25+H25+M25 -> 1200885.9 | O25: =E25-N25 -> 2764894.1 | P25: =IF(O25<300000,0.07*O25,21000) -> 21000 | Q25: =IF((O25-300000)<0,0,IF((O25-300000)<300000,0.11*(O25-300000),33000)) -> 33000 | R25: =IF((O25-600000)<0,0,IF((O25-600000)<500000,0.15*(O25-600000),75000)) -> 75000 | S25: =IF((O25-1100000)<0,0,IF((O25-1100000)<500000,0.19*(O25-1100000),95000)) -> 95000 | T25: =IF((O25-1600000)<0,0,IF((O25-1600000)<1600000,0.21*(O25-1600000),336000)) -> 244627.76 | V25: =P25+Q25+R25+S25+T25+U25 -> 468627.76 | W25: 12 | X25: =V25/W25 -> 39052.313 | Z25: =X25 -> 39052.313 | AA25: 23036.012 | AB25: =Z25-AA25 -> 16016.301
A26: 23 | B26: NNANDI LIVINUS ATURE | C26: 370481.67 | D26: 12 | E26: =C26*D26 -> 4445780 | G26: 259662.4 | I26: =E26-F26-G26-H26 -> 4186117.6 | J26: 200000 | K26: 0.2 | L26: =I26*K26 -> 837223.52 | M26: =J26+L26 -> 1037223.5 | N26: =F26+G26+H26+M26 -> 1296885.9 | O26: =E26-N26 -> 3148894.1 | P26: =IF(O26<300000,0.07*O26,21000) -> 21000 | Q26: =IF((O26-300000)<0,0,IF((O26-300000)<300000,0.11*(O26-300000),33000)) -> 33000 | R26: =IF((O26-600000)<0,0,IF((O26-600000)<500000,0.15*(O26-600000),75000)) -> 75000 | S26: =IF((O26-1100000)<0,0,IF((O26-1100000)<500000,0.19*(O26-1100000),95000)) -> 95000 | T26: =IF((O26-1600000)<0,0,IF((O26-1600000)<1600000,0.21*(O26-1600000),336000)) -> 325267.76 | V26: =P26+Q26+R26+S26+T26+U26 -> 549267.76 | W26: 12 | X26: =V26/W26 -> 45772.313 | Z26: =X26 -> 45772.313 | AA26: 29756.012 | AB26: =Z26-AA26 -> 16016.301
A27: 24 | B27: ABDULRAHMAN A SULAIMAN | C27: 323165.33 | D27: 12 | E27: =C27*D27 -> 3877984 | G27: 252638.72 | I27: =E27-F27-G27-H27 -> 3625345.3 | J27: 200000 | K27: 0.2 | L27: =I27*K27 -> 725069.06 | M27: =J27+L27 -> 925069.06 | N27: =F27+G27+H27+M27 -> 1177707.8 | O27: =E27-N27 -> 2700276.2 | P27: =IF(O27<300000,0.07*O27,21000) -> 21000 | Q27: =IF((O27-300000)<0,0,IF((O27-300000)<300000,0.11*(O27-300000),33000)) -> 33000 | R27: =IF((O27-600000)<0,0,IF((O27-600000)<500000,0.15*(O27-600000),75000)) -> 75000 | S27: =IF((O27-1100000)<0,0,IF((O27-1100000)<500000,0.19*(O27-1100000),95000)) -> 95000 | T27: =IF((O27-1600000)<0,0,IF((O27-1600000)<1600000,0.21*(O27-1600000),336000)) -> 231058.01 | V27: =P27+Q27+R27+S27+T27+U27 -> 455058.01 | W27: 12 | X27: =V27/W27 -> 37921.501 | Z27: =X27 -> 37921.501 | AA27: 22338.483 | AB27: =Z27-AA27 -> 15583.018
A28: 25 | B28: DARE SHEU MAGBON | C28: 315849 | D28: 12 | E28: =C28*D28 -> 3790188 | G28: 245615.04 | I28: =E28-F28-G28-H28 -> 3544573 | J28: 200000 | K28: 0.2 | L28: =I28*K28 -> 708914.59 | M28: =J28+L28 -> 908914.59 | N28: =F28+G28+H28+M28 -> 1154529.6 | O28: =E28-N28 -> 2635658.4 | P28: =IF(O28<300000,0.07*O28,21000) -> 21000 | Q28: =IF((O28-300000)<0,0,IF((O28-300000)<300000,0.11*(O28-300000),33000)) -> 33000 | R28: =IF((O28-600000)<0,0,IF((O28-600000)<500000,0.15*(O28-600000),75000)) -> 75000 | S28: =IF((O28-1100000)<0,0,IF((O28-1100000)<500000,0.19*(O28-1100000),95000)) -> 95000 | T28: =IF((O28-1600000)<0,0,IF((O28-1600000)<1600000,0.21*(O28-1600000),336000)) -> 217488.26 | V28: =P28+Q28+R28+S28+T28+U28 -> 441488.26 | W28: 12 | X28: =V28/W28 -> 36790.688 | Z28: =X28 -> 36790.688 | AA28: 21640.953 | AB28: =Z28-AA28 -> 15149.735
A29: 26 | B29: ABUBAKAR SULAIMAN SODEEQ | C29: 315849 | D29: 12 | E29: =C29*D29 -> 3790188 | G29: 245615.04 | I29: =E29-F29-G29-H29 -> 3544573 | J29: 200000 | K29: 0.2 | L29: =I29*K29 -> 708914.59 | M29: =J29+L29 -> 908914.59 | N29: =F29+G29+H29+M29 -> 1154529.6 | O29: =E29-N29 -> 2635658.4 | P29: =IF(O29<300000,0.07*O29,21000) -> 21000 | Q29: =IF((O29-300000)<0,0,IF((O29-300000)<300000,0.11*(O29-300000),33000)) -> 33000 | R29: =IF((O29-600000)<0,0,IF((O29-600000)<500000,0.15*(O29-600000),75000)) -> 75000 | S29: =IF((O29-1100000)<0,0,IF((O29-1100000)<500000,0.19*(O29-1100000),95000)) -> 95000 | T29: =IF((O29-1600000)<0,0,IF((O29-1600000)<1600000,0.21*(O29-1600000),336000)) -> 217488.26 | V29: =P29+Q29+R29+S29+T29+U29 -> 441488.26 | W29: 12 | X29: =V29/W29 -> 36790.688 | Z29: =X29 -> 36790.688 | AA29: 21640.953 | AB29: =Z29-AA29 -> 15149.735
A30: 27 | B30: JIMOH ADEBAYO ZAKA | C30: 330481.67 | D30: 12 | E30: =C30*D30 -> 3965780 | G30: 259662.4 | I30: =E30-F30-G30-H30 -> 3706117.6 | J30: 200000 | K30: 0.2 | L30: =I30*K30 -> 741223.52 | M30: =J30+L30 -> 941223.52 | N30: =F30+G30+H30+M30 -> 1200885.9 | O30: =E30-N30 -> 2764894.1 | P30: =IF(O30<300000,0.07*O30,21000) -> 21000 | Q30: =IF((O30-300000)<0,0,IF((O30-300000)<300000,0.11*(O30-300000),33000)) -> 33000 | R30: =IF((O30-600000)<0,0,IF((O30-600000)<500000,0.15*(O30-600000),75000)) -> 75000 | S30: =IF((O30-1100000)<0,0,IF((O30-1100000)<500000,0.19*(O30-1100000),95000)) -> 95000 | T30: =IF((O30-1600000)<0,0,IF((O30-1600000)<1600000,0.21*(O30-1600000),336000)) -> 244627.76 | V30: =P30+Q30+R30+S30+T30+U30 -> 468627.76 | W30: 12 | X30: =V30/W30 -> 39052.313 | Z30: =X30 -> 39052.313 | AA30: 22338.483 | AB30: =Z30-AA30 -> 16713.83
A31: 28 | B31: MOHAMMED BELLO | C31: 280631.92 | D31: 12 | E31: =C31*D31 -> 3367583 | G31: 221406.64 | I31: =E31-F31-G31-H31 -> 3146176.4 | J31: 200000 | K31: 0.2 | L31: =I31*K31 -> 629235.27 | M31: =J31+L31 -> 829235.27 | N31: =F31+G31+H31+M31 -> 1050641.9 | O31: =E31-N31 -> 2316941.1 | P31: =IF(O31<300000,0.07*O31,21000) -> 21000 | Q31: =IF((O31-300000)<0,0,IF((O31-300000)<300000,0.11*(O31-300000),33000)) -> 33000 | R31: =IF((O31-600000)<0,0,IF((O31-600000)<500000,0.15*(O31-600000),75000)) -> 75000 | S31: =IF((O31-1100000)<0,0,IF((O31-1100000)<500000,0.19*(O31-1100000),95000)) -> 95000 | T31: =IF((O31-1600000)<0,0,IF((O31-1600000)<1600000,0.21*(O31-1600000),336000)) -> 150557.63 | V31: =P31+Q31+R31+S31+T31+U31 -> 374557.63 | W31: 12 | X31: =V31/W31 -> 31213.136 | Z31: =X31 -> 31213.136 | AA31: 17572.885 | AB31: =Z31-AA31 -> 13640.251
A32: 29 | B32: HARUNA JIBRIL AMEH | C32: 274459.75 | D32: 12 | E32: =C32*D32 -> 3293517 | G32: =17956.78*12 -> 215481.36 | I32: =E32-F32-G32-H32 -> 3078035.6 | J32: 200000 | K32: 0.2 | L32: =I32*K32 -> 615607.13 | M32: =J32+L32 -> 815607.13 | N32: =F32+G32+H32+M32 -> 1031088.5 | O32: =E32-N32 -> 2262428.5 | P32: =IF(O32<300000,0.07*O32,21000) -> 21000 | Q32: =IF((O32-300000)<0,0,IF((O32-300000)<300000,0.11*(O32-300000),33000)) -> 33000 | R32: =IF((O32-600000)<0,0,IF((O32-600000)<500000,0.15*(O32-600000),75000)) -> 75000 | S32: =IF((O32-1100000)<0,0,IF((O32-1100000)<500000,0.19*(O32-1100000),95000)) -> 95000 | T32: =IF((O32-1600000)<0,0,IF((O32-1600000)<1600000,0.21*(O32-1600000),336000)) -> 139109.99 | V32: =P32+Q32+R32+S32+T32+U32 -> 363109.99 | W32: 12 | X32: =V32/W32 -> 30259.166 | Z32: =X32 -> 30259.166 | AA32: 16512.682 | AB32: =Z32-AA32 -> 13746.483
A33: 31
A34: 32 | B34: INTERNAL AUDIT
B35: OSANAIYE DAVID AKINYEMI | C35: 1535720 | D35: 12 | E35: =C35*D35 -> 18428640 | G35: 1378291.2 | I35: =E35-F35-G35-H35 -> 17050349 | J35: 200000 | K35: 0.2 | L35: =I35*K35 -> 3410069.8 | M35: =J35+L35 -> 3610069.8 | N35: =F35+G35+H35+M35 -> 4988361 | O35: =E35-N35 -> 13440279 | P35: =IF(O35<300000,0.07*O35,21000) -> 21000 | Q35: =IF((O35-300000)<0,0,IF((O35-300000)<300000,0.11*(O35-300000),33000)) -> 33000 | R35: =IF((O35-600000)<0,0,IF((O35-600000)<500000,0.15*(O35-600000),75000)) -> 75000 | S35: =IF((O35-1100000)<0,0,IF((O35-1100000)<500000,0.19*(O35-1100000),95000)) -> 95000 | T35: =IF((O35-1600000)<0,0,IF((O35-1600000)<1600000,0.21*(O35-1600000),336000)) -> 336000 | U35: =24%*(O35-3200000) -> 2457667 | V35: =P35+Q35+R35+S35+T35+U35 -> 3017667 | W35: 12 | X35: =V35/W35 -> 251472.25 | Z35: =X35 -> 251472.25 | AA35: 161106.81 | AB35: =Z35-AA35 -> 90365.441
B36: JAMILA ABDUL | C36: 353029.67 | D36: 12 | E36: =C36*D36 -> 4236356 | G36: 281308.48 | I36: =E36-F36-G36-H36 -> 3955047.5 | J36: 200000 | K36: 0.2 | L36: =I36*K36 -> 791009.5 | M36: =J36+L36 -> 991009.5 | N36: =F36+G36+H36+M36 -> 1272318 | O36: =E36-N36 -> 2964038 | P36: =IF(O36<300000,0.07*O36,21000) -> 21000 | Q36: =IF((O36-300000)<0,0,IF((O36-300000)<300000,0.11*(O36-300000),33000)) -> 33000 | R36: =IF((O36-600000)<0,0,IF((O36-600000)<500000,0.15*(O36-600000),75000)) -> 75000 | S36: =IF((O36-1100000)<0,0,IF((O36-1100000)<500000,0.19*(O36-1100000),95000)) -> 95000 | T36: =IF((O36-1600000)<0,0,IF((O36-1600000)<1600000,0.21*(O36-1600000),336000)) -> 286447.98 | V36: =P36+Q36+R36+S36+T36+U36 -> 510447.98 | W36: 12 | X36: =V36/W36 -> 42537.332 | Z36: =X36 -> 42537.332 | AA36: 17042.714 | AB36: =Z36-AA36 -> 25494.618
A37: 33 | B37: IJEOMA EWELUKWA | C37: 360965.58 | D37: 12 | E37: =C37*D37 -> 4331587 | G37: 288926.96 | I37: =E37-F37-G37-H37 -> 4042660 | J37: 200000 | K37: 0.2 | L37: =I37*K37 -> 808532.01 | M37: =J37+L37 -> 1008532 | N37: =F37+G37+H37+M37 -> 1297459 | O37: =E37-N37 -> 3034128 | P37: =IF(O37<300000,0.07*O37,21000) -> 21000 | Q37: =IF((O37-300000)<0,0,IF((O37-300000)<300000,0.11*(O37-300000),33000)) -> 33000 | R37: =IF((O37-600000)<0,0,IF((O37-600000)<500000,0.15*(O37-600000),75000)) -> 75000 | S37: =IF((O37-1100000)<0,0,IF((O37-1100000)<500000,0.19*(O37-1100000),95000)) -> 95000 | T37: =IF((O37-1600000)<0,0,IF((O37-1600000)<1600000,0.21*(O37-1600000),336000)) -> 301166.89 | V37: =P37+Q37+R37+S37+T37+U37 -> 525166.89 | W37: 12 | X37: =V37/W37 -> 43763.907 | Z37: =X37 -> 43763.907 | AA37: 26339.078 | AB37: =Z37-AA37 -> 17424.829
G38: 0
B39: LEG. SUPPORT SEVICES | G39: 0
A40: 35 | B40: PROF. EDOBA BRIGHT OMOREGBE | C40: 1635720 | D40: 12 | E40: =C40*D40 -> 19628640 | G40: 1378291.2 | I40: =E40-F40-G40-H40 -> 18250349 | J40: 200000 | K40: 0.2 | L40: =I40*K40 -> 3650069.8 | M40: =J40+L40 -> 3850069.8 | N40: =F40+G40+H40+M40 -> 5228361 | O40: =E40-N40 -> 14400279 | P40: =IF(O40<300000,0.07*O40,21000) -> 21000 | Q40: =IF((O40-300000)<0,0,IF((O40-300000)<300000,0.11*(O40-300000),33000)) -> 33000 | R40: =IF((O40-600000)<0,0,IF((O40-600000)<500000,0.15*(O40-600000),75000)) -> 75000 | S40: =IF((O40-1100000)<0,0,IF((O40-1100000)<500000,0.19*(O40-1100000),95000)) -> 95000 | T40: =IF((O40-1600000)<0,0,IF((O40-1600000)<1600000,0.21*(O40-1600000),336000)) -> 336000 | U40: =0.24*(O40-3200000) -> 2688067 | V40: =P40+Q40+R40+S40+T40+U40 -> 3248067 | W40: 12 | X40: =V40/W40 -> 270672.25 | Z40: =X40 -> 270672.25 | AA40: 180306.81 | AB40: =Z40-AA40 -> 90365.441
A41: 36 | B41: DR CLINTON JAJA | C41: 780675.58 | D41: 12 | E41: =C41*D41 -> 9368107 | G41: 595848.56 | I41: =E41-F41-G41-H41 -> 8772258.4 | J41: 200000 | K41: 0.2 | L41: =I41*K41 -> 1754451.7 | M41: =J41+L41 -> 1954451.7 | N41: =F41+G41+H41+M41 -> 2550300.2 | O41: =E41-N41 -> 6817806.8 | P41: =IF(O41<300000,0.07*O41,21000) -> 21000 | Q41: =IF((O41-300000)<0,0,IF((O41-300000)<300000,0.11*(O41-300000),33000)) -> 33000 | R41: =IF((O41-600000)<0,0,IF((O41-600000)<500000,0.15*(O41-600000),75000)) -> 75000 | S41: =IF((O41-1100000)<0,0,IF((O41-1100000)<500000,0.19*(O41-1100000),95000)) -> 95000 | T41: =IF((O41-1600000)<0,0,IF((O41-1600000)<1600000,0.21*(O41-1600000),336000)) -> 336000 | U41: =24%*(O41-3200000) -> 868273.62 | V41: =P41+Q41+R41+S41+T41+U41 -> 1428273.6 | W41: 12 | X41: =V41/W41 -> 119022.8 | Z41: =X41 -> 119022.8 | AA41: 79956.939 | AB41: =Z41-AA41 -> 39065.863
A42: 37 | B42: BETHEL UZOMA IHUGBA | C42: 919203.58 | D42: 12 | E42: =C42*D42 -> 11030443 | G42: 709635.44 | I42: =E42-F42-G42-H42 -> 10320808 | J42: 200000 | K42: 0.2 | L42: =I42*K42 -> 2064161.5 | M42: =J42+L42 -> 2264161.5 | N42: =F42+G42+H42+M42 -> 2973797 | O42: =E42-N42 -> 8056646 | P42: =IF(O42<300000,0.07*O42,21000) -> 21000 | Q42: =IF((O42-300000)<0,0,IF((O42-300000)<300000,0.11*(O42-300000),33000)) -> 33000 | R42: =IF((O42-600000)<0,0,IF((O42-600000)<500000,0.15*(O42-600000),75000)) -> 75000 | S42: =IF((O42-1100000)<0,0,IF((O42-1100000)<500000,0.19*(O42-1100000),95000)) -> 95000 | T42: =IF((O42-1600000)<0,0,IF((O42-1600000)<1600000,0.21*(O42-1600000),336000)) -> 336000 | U42: =24%*(O42-3200000) -> 1165595.1 | V42: =P42+Q42+R42+S42+T42+U42 -> 1725595.1 | W42: 12 | X42: =V42/W42 -> 143799.59 | Z42: =X42 -> 143799.59 | AA42: 97273.514 | AB42: =Z42-AA42 -> 46526.074
A43: 38 | B43: OGUCHE SAMUEL | C43: 780675.58 | D43: 12 | E43: =C43*D43 -> 9368107 | G43: 595848.56 | I43: =E43-F43-G43-H43 -> 8772258.4 | J43: 200000 | K43: 0.2 | L43: =I43*K43 -> 1754451.7 | M43: =J43+L43 -> 1954451.7 | N43: =F43+G43+H43+M43 -> 2550300.2 | O43: =E43-N43 -> 6817806.8 | P43: =IF(O43<300000,0.07*O43,21000) -> 21000 | Q43: =IF((O43-300000)<0,0,IF((O43-300000)<300000,0.11*(O43-300000),33000)) -> 33000 | R43: =IF((O43-600000)<0,0,IF((O43-600000)<500000,0.15*(O43-600000),75000)) -> 75000 | S43: =IF((O43-1100000)<0,0,IF((O43-1100000)<500000,0.19*(O43-1100000),95000)) -> 95000 | T43: =IF((O43-1600000)<0,0,IF((O43-1600000)<1600000,0.21*(O43-1600000),336000)) -> 336000 | U43: =24%*(O43-3200000) -> 868273.62 | V43: =P43+Q43+R43+S43+T43+U43 -> 1428273.6 | W43: 12 | X43: =V43/W43 -> 119022.8 | Z43: =X43 -> 119022.8 | AA43: 79956.939 | AB43: =Z43-AA43 -> 39065.863
A44: 39 | B44: IBRAHIM USMAN | C44: 780675.58 | D44: 12 | E44: =C44*D44 -> 9368107 | F44: ='[5]JANUARY 2024'!$V$47*12 -> 10052.25 | G44: 595848.56 | I44: =E44-F44-G44-H44 -> 8762206.2 | J44: 200000 | K44: 0.2 | L44: =I44*K44 -> 1752441.2 | M44: =J44+L44 -> 1952441.2 | N44: =F44+G44+H44+M44 -> 2558342 | O44: =E44-N44 -> 6809765 | P44: =IF(O44<300000,0.07*O44,21000) -> 21000 | Q44: =IF((O44-300000)<0,0,IF((O44-300000)<300000,0.11*(O44-300000),33000)) -> 33000 | R44: =IF((O44-600000)<0,0,IF((O44-600000)<500000,0.15*(O44-600000),75000)) -> 75000 | S44: =IF((O44-1100000)<0,0,IF((O44-1100000)<500000,0.19*(O44-1100000),95000)) -> 95000 | T44: =IF((O44-1600000)<0,0,IF((O44-1600000)<1600000,0.21*(O44-1600000),336000)) -> 336000 | U44: =24%*(O44-3200000) -> 866343.59 | V44: =P44+Q44+R44+S44+T44+U44 -> 1426343.6 | W44: 12 | X44: =V44/W44 -> 118861.97 | Z44: =X44 -> 118861.97 | AA44: 79796.103 | AB44: =Z44-AA44 -> 39065.863
A45: 40 | B45: DR MOHAMMED O. AMALI | C45: 742118.08 | D45: 12 | E45: =C45*D45 -> 8905417 | G45: 558833.36 | I45: =E45-F45-G45-H45 -> 8346583.6 | J45: 200000 | K45: 0.2 | L45: =I45*K45 -> 1669316.7 | M45: =J45+L45 -> 1869316.7 | N45: =F45+G45+H45+M45 -> 2428150.1 | O45: =E45-N45 -> 6477266.9 | P45: =IF(O45<300000,0.07*O45,21000) -> 21000 | Q45: =IF((O45-300000)<0,0,IF((O45-300000)<300000,0.11*(O45-300000),33000)) -> 33000 | R45: =IF((O45-600000)<0,0,IF((O45-600000)<500000,0.15*(O45-600000),75000)) -> 75000 | S45: =IF((O45-1100000)<0,0,IF((O45-1100000)<500000,0.19*(O45-1100000),95000)) -> 95000 | T45: =IF((O45-1600000)<0,0,IF((O45-1600000)<1600000,0.21*(O45-1600000),336000)) -> 336000 | U45: =24%*(O45-3200000) -> 786544.06 | V45: =P45+Q45+R45+S45+T45+U45 -> 1346544.1 | W45: 12 | X45: =V45/W45 -> 112212 | Z45: =X45 -> 112212 | AA45: 75572.916 | AB45: =Z45-AA45 -> 36639.089
A46: 41 | B46: YAHAYA SHAMSU | C46: 610498 | D46: 12 | E46: =C46*D46 -> 7325976 | G46: 451678.08 | I46: =E46-F46-G46-H46 -> 6874297.9 | J46: 200000 | K46: 0.2 | L46: =I46*K46 -> 1374859.6 | M46: =J46+L46 -> 1574859.6 | N46: =F46+G46+H46+M46 -> 2026537.7 | O46: =E46-N46 -> 5299438.3 | P46: =IF(O46<300000,0.07*O46,21000) -> 21000 | Q46: =IF((O46-300000)<0,0,IF((O46-300000)<300000,0.11*(O46-300000),33000)) -> 33000 | R46: =IF((O46-600000)<0,0,IF((O46-600000)<500000,0.15*(O46-600000),75000)) -> 75000 | S46: =IF((O46-1100000)<0,0,IF((O46-1100000)<500000,0.19*(O46-1100000),95000)) -> 95000 | T46: =IF((O46-1600000)<0,0,IF((O46-1600000)<1600000,0.21*(O46-1600000),336000)) -> 336000 | U46: =24%*(O46-3200000) -> 503865.2 | V46: =P46+Q46+R46+S46+T46+U46 -> 1063865.2 | W46: 12 | X46: =V46/W46 -> 88655.433 | Z46: =X46 -> 88655.433 | AA46: 58026.609 | AB46: =Z46-AA46 -> 30628.824
A47: 42 | B47: BILKIS S. LAWAL-GAMBARI | C47: 400965.58 | D47: 12 | E47: =C47*D47 -> 4811587 | G47: 288926.96 | I47: =E47-F47-G47-H47 -> 4522660 | J47: 200000 | K47: 0.2 | L47: =I47*K47 -> 904532.01 | M47: =J47+L47 -> 1104532 | N47: =F47+G47+H47+M47 -> 1393459 | O47: =E47-N47 -> 3418128 | P47: =IF(O47<300000,0.07*O47,21000) -> 21000 | Q47: =IF((O47-300000)<0,0,IF((O47-300000)<300000,0.11*(O47-300000),33000)) -> 33000 | R47: =IF((O47-600000)<0,0,IF((O47-600000)<500000,0.15*(O47-600000),75000)) -> 75000 | S47: =IF((O47-1100000)<0,0,IF((O47-1100000)<500000,0.19*(O47-1100000),95000)) -> 95000 | T47: =IF((O47-1600000)<0,0,IF((O47-1600000)<1600000,0.21*(O47-1600000),336000)) -> 336000 | U47: =24%*(O47-3200000) -> 52350.728 | V47: =P47+Q47+R47+S47+T47+U47 -> 612350.73 | W47: 12 | X47: =V47/W47 -> 51029.227 | Z47: =X47 -> 51029.227 | AA47: 33059.078 | AB47: =Z47-AA47 -> 17970.149
A48: 43 | B48: ZAINAB AKINDE | C48: 363165.33 | D48: 12 | E48: =C48*D48 -> 4357984 | G48: 252638.72 | I48: =E48-F48-G48-H48 -> 4105345.3 | J48: 200000 | K48: 0.2 | L48: =I48*K48 -> 821069.06 | M48: =J48+L48 -> 1021069.1 | N48: =F48+G48+H48+M48 -> 1273707.8 | O48: =E48-N48 -> 3084276.2 | P48: =IF(O48<300000,0.07*O48,21000) -> 21000 | Q48: =IF((O48-300000)<0,0,IF((O48-300000)<300000,0.11*(O48-300000),33000)) -> 33000 | R48: =IF((O48-600000)<0,0,IF((O48-600000)<500000,0.15*(O48-600000),75000)) -> 75000 | S48: =IF((O48-1100000)<0,0,IF((O48-1100000)<500000,0.19*(O48-1100000),95000)) -> 95000 | T48: =IF((O48-1600000)<0,0,IF((O48-1600000)<1600000,0.21*(O48-1600000),336000)) -> 311698.01 | V48: =P48+Q48+R48+S48+T48+U48 -> 535698.01 | W48: 12 | X48: =V48/W48 -> 44641.501 | Z48: =X48 -> 44641.501 | AA48: 29058.483 | AB48: =Z48-AA48 -> 15583.018
A49: 44 | B49: ABDULLAHI AHMAD USMAN | C49: 363165.33 | D49: 12 | E49: =C49*D49 -> 4357984 | G49: 252638.72 | I49: =E49-F49-G49-H49 -> 4105345.3 | J49: 200000 | K49: 0.2 | L49: =I49*K49 -> 821069.06 | M49: =J49+L49 -> 1021069.1 | N49: =F49+G49+H49+M49 -> 1273707.8 | O49: =E49-N49 -> 3084276.2 | P49: =IF(O49<300000,0.07*O49,21000) -> 21000 | Q49: =IF((O49-300000)<0,0,IF((O49-300000)<300000,0.11*(O49-300000),33000)) -> 33000 | R49: =IF((O49-600000)<0,0,IF((O49-600000)<500000,0.15*(O49-600000),75000)) -> 75000 | S49: =IF((O49-1100000)<0,0,IF((O49-1100000)<500000,0.19*(O49-1100000),95000)) -> 95000 | T49: =IF((O49-1600000)<0,0,IF((O49-1600000)<1600000,0.21*(O49-1600000),336000)) -> 311698.01 | V49: =P49+Q49+R49+S49+T49+U49 -> 535698.01 | W49: 12 | X49: =V49/W49 -> 44641.501 | Z49: =X49 -> 44641.501 | AA49: 28360.953 | AB49: =Z49-AA49 -> 16280.548
A50: 45 | B50: GUNAT NANSAK MARK | C50: 363165.33 | D50: 12 | E50: =C50*D50 -> 4357984 | G50: 252638.72 | I50: =E50-F50-G50-H50 -> 4105345.3 | J50: 200000 | K50: 0.2 | L50: =I50*K50 -> 821069.06 | M50: =J50+L50 -> 1021069.1 | N50: =F50+G50+H50+M50 -> 1273707.8 | O50: =E50-N50 -> 3084276.2 | P50: =IF(O50<300000,0.07*O50,21000) -> 21000 | Q50: =IF((O50-300000)<0,0,IF((O50-300000)<300000,0.11*(O50-300000),33000)) -> 33000 | R50: =IF((O50-600000)<0,0,IF((O50-600000)<500000,0.15*(O50-600000),75000)) -> 75000 | S50: =IF((O50-1100000)<0,0,IF((O50-1100000)<500000,0.19*(O50-1100000),95000)) -> 95000 | T50: =IF((O50-1600000)<0,0,IF((O50-1600000)<1600000,0.21*(O50-1600000),336000)) -> 311698.01 | V50: =P50+Q50+R50+S50+T50+U50 -> 535698.01 | W50: 12 | X50: =V50/W50 -> 44641.501 | Z50: =X50 -> 44641.501 | AA50: 29058.483 | AB50: =Z50-AA50 -> 15583.018
B52: LEGAL SERVICES
A53: 47 | B53: DR SHUAIBU DANWANKA | C53: 1635720 | D53: 12 | E53: =C53*D53 -> 19628640 | G53: 1378291.2 | I53: =E53-F53-G53-H53 -> 18250349 | J53: 200000 | K53: 0.2 | L53: =I53*K53 -> 3650069.8 | M53: =J53+L53 -> 3850069.8 | N53: =F53+G53+H53+M53 -> 5228361 | O53: =E53-N53 -> 14400279 | P53: =IF(O53<300000,0.07*O53,21000) -> 21000 | Q53: =IF((O53-300000)<0,0,IF((O53-300000)<300000,0.11*(O53-300000),33000)) -> 33000 | R53: =IF((O53-600000)<0,0,IF((O53-600000)<500000,0.15*(O53-600000),75000)) -> 75000 | S53: =IF((O53-1100000)<0,0,IF((O53-1100000)<500000,0.19*(O53-1100000),95000)) -> 95000 | T53: =IF((O53-1600000)<0,0,IF((O53-1600000)<1600000,0.21*(O53-1600000),336000)) -> 336000 | U53: =24%*(O53-3200000) -> 2688067 | V53: =P53+Q53+R53+S53+T53+U53 -> 3248067 | W53: 12 | X53: =V53/W53 -> 270672.25 | Z53: =X53 -> 270672.25 | AA53: 180306.81 | AB53: =Z53-AA53 -> 90365.441
A54: 48 | B54: ABDULSALAM BAKO | C54: 700675.58 | D54: 12 | E54: =C54*D54 -> 8408107 | G54: 595848.56 | I54: =E54-F54-G54-H54 -> 7812258.4 | J54: 200000 | K54: 0.2 | L54: =I54*K54 -> 1562451.7 | M54: =J54+L54 -> 1762451.7 | N54: =F54+G54+H54+M54 -> 2358300.2 | O54: =E54-N54 -> 6049806.8 | P54: =IF(O54<300000,0.07*O54,21000) -> 21000 | Q54: =IF((O54-300000)<0,0,IF((O54-300000)<300000,0.11*(O54-300000),33000)) -> 33000 | R54: =IF((O54-600000)<0,0,IF((O54-600000)<500000,0.15*(O54-600000),75000)) -> 75000 | S54: =IF((O54-1100000)<0,0,IF((O54-1100000)<500000,0.19*(O54-1100000),95000)) -> 95000 | T54: =IF((O54-1600000)<0,0,IF((O54-1600000)<1600000,0.21*(O54-1600000),336000)) -> 336000 | U54: =24%*(O54-3200000) -> 683953.62 | V54: =P54+Q54+R54+S54+T54+U54 -> 1243953.6 | W54: 12 | X54: =V54/W54 -> 103662.8 | Z54: =X54 -> 103662.8 | AA54: 64596.939 | AB54: =Z54-AA54 -> 39065.863
G55: 0
A56: 49 | B56: DEMOCRACY & GOVERNANCE | G56: 0
A57: 50 | B57: DR. ADEWALE ADEREMI | C57: 1635720 | D57: 12 | E57: =C57*D57 -> 19628640 | G57: 0 | I57: =E57-F57-G57-H57 -> 19628640 | J57: 200000 | K57: 0.2 | L57: =I57*K57 -> 3925728 | M57: =J57+L57 -> 4125728 | N57: =F57+G57+H57+M57 -> 4125728 | O57: =E57-N57 -> 15502912 | P57: =IF(O57<300000,0.07*O57,21000) -> 21000 | Q57: =IF((O57-300000)<0,0,IF((O57-300000)<300000,0.11*(O57-300000),33000)) -> 33000 | R57: =IF((O57-600000)<0,0,IF((O57-600000)<500000,0.15*(O57-600000),75000)) -> 75000 | S57: =IF((O57-1100000)<0,0,IF((O57-1100000)<500000,0.19*(O57-1100000),95000)) -> 95000 | T57: =IF((O57-1600000)<0,0,IF((O57-1600000)<1600000,0.21*(O57-1600000),336000)) -> 336000 | U57: =24%*(O57-3200000) -> 2952698.9 | V57: =P57+Q57+R57+S57+T57+U57 -> 3512698.9 | W57: 12 | X57: =V57/W57 -> 292724.91 | Z57: =X57 -> 292724.91 | AA57: 180306.81 | AB57: =Z57-AA57 -> 112418.1
A58: 51 | B58: NDANUSA MOHAMMED MANZUMA | C58: 761396.83 | D58: 12 | E58: =C58*D58 -> 9136762 | G58: =48111.7466666667*12 -> 577340.96 | I58: =E58-F58-G58-H58 -> 8559421 | J58: 200000 | K58: 0.2 | L58: =I58*K58 -> 1711884.2 | M58: =J58+L58 -> 1911884.2 | N58: =F58+G58+H58+M58 -> 2489225.2 | O58: =E58-N58 -> 6647536.8 | P58: =IF(O58<300000,0.07*O58,21000) -> 21000 | Q58: =IF((O58-300000)<0,0,IF((O58-300000)<300000,0.11*(O58-300000),33000)) -> 33000 | R58: =IF((O58-600000)<0,0,IF((O58-600000)<500000,0.15*(O58-600000),75000)) -> 75000 | S58: =IF((O58-1100000)<0,0,IF((O58-1100000)<500000,0.19*(O58-1100000),95000)) -> 95000 | T58: =IF((O58-1600000)<0,0,IF((O58-1600000)<1600000,0.21*(O58-1600000),336000)) -> 336000 | U58: =24%*(O58-3200000) -> 827408.84 | V58: =P58+Q58+R58+S58+T58+U58 -> 1387408.8 | W58: 12 | X58: =V58/W58 -> 115617.4 | Z58: =X58 -> 115617.4 | AA58: 77764.98 | AB58: =Z58-AA58 -> 37852.423
A59: 52 | B59: EJALONIBU GANIYU LAYI | C59: 582746.5 | D59: 12 | E59: =C59*D59 -> 6992958 | G59: 425036.64 | I59: =E59-F59-G59-H59 -> 6567921.4 | J59: 200000 | K59: 0.2 | L59: =I59*K59 -> 1313584.3 | M59: =J59+L59 -> 1513584.3 | N59: =F59+G59+H59+M59 -> 1938620.9 | O59: =E59-N59 -> 5054337.1 | P59: =IF(O59<300000,0.07*O59,21000) -> 21000 | Q59: =IF((O59-300000)<0,0,IF((O59-300000)<300000,0.11*(O59-300000),33000)) -> 33000 | R59: =IF((O59-600000)<0,0,IF((O59-600000)<500000,0.15*(O59-600000),75000)) -> 75000 | S59: =IF((O59-1100000)<0,0,IF((O59-1100000)<500000,0.19*(O59-1100000),95000)) -> 95000 | T59: =IF((O59-1600000)<0,0,IF((O59-1600000)<1600000,0.21*(O59-1600000),336000)) -> 336000 | U59: =24%*(O59-3200000) -> 445040.9 | V59: =P59+Q59+R59+S59+T59+U59 -> 1005040.9 | W59: 12 | X59: =V59/W59 -> 83753.408 | Z59: =X59 -> 83753.408 | AA59: 54931.249 | AB59: =Z59-AA59 -> 28822.159
A60: 53 | B60: LOHNA BONKAT JONATHAN | C60: 548915.92 | D60: 12 | E60: =C60*D60 -> 6586991 | G60: 411759.28 | I60: =E60-F60-G60-H60 -> 6175231.7 | J60: 200000 | K60: 0.2 | L60: =I60*K60 -> 1235046.3 | M60: =J60+L60 -> 1435046.3 | N60: =F60+G60+H60+M60 -> 1846805.6 | O60: =E60-N60 -> 4740185.4 | P60: =IF(O60<300000,0.07*O60,21000) -> 21000 | Q60: =IF((O60-300000)<0,0,IF((O60-300000)<300000,0.11*(O60-300000),33000)) -> 33000 | R60: =IF((O60-600000)<0,0,IF((O60-600000)<500000,0.15*(O60-600000),75000)) -> 75000 | S60: =IF((O60-1100000)<0,0,IF((O60-1100000)<500000,0.19*(O60-1100000),95000)) -> 95000 | T60: =IF((O60-1600000)<0,0,IF((O60-1600000)<1600000,0.21*(O60-1600000),336000)) -> 336000 | U60: =24%*(O60-3200000) -> 369644.49 | V60: =P60+Q60+R60+S60+T60+U60 -> 929644.49 | W60: 12 | X60: =V60/W60 -> 77470.374 | Z60: =X60 -> 77470.374 | AA60: 49548.776 | AB60: =Z60-AA60 -> 27921.598
A61: 54 | B61: YUNUSA ABDULLAHI | C61: 624373.75 | D61: 12 | E61: =C61*D61 -> 7492485 | G61: 464998.8 | I61: =E61-F61-G61-H61 -> 7027486.2 | J61: 200000 | K61: 0.2 | L61: =I61*K61 -> 1405497.2 | M61: =J61+L61 -> 1605497.2 | N61: =F61+G61+H61+M61 -> 2070496 | O61: =E61-N61 -> 5421989 | P61: =IF(O61<300000,0.07*O61,21000) -> 21000 | Q61: =IF((O61-300000)<0,0,IF((O61-300000)<300000,0.11*(O61-300000),33000)) -> 33000 | R61: =IF((O61-600000)<0,0,IF((O61-600000)<500000,0.15*(O61-600000),75000)) -> 75000 | S61: =IF((O61-1100000)<0,0,IF((O61-1100000)<500000,0.19*(O61-1100000),95000)) -> 95000 | T61: =IF((O61-1600000)<0,0,IF((O61-1600000)<1600000,0.21*(O61-1600000),336000)) -> 336000 | U61: =24%*(O61-3200000) -> 533277.35 | V61: =P61+Q61+R61+S61+T61+U61 -> 1093277.4 | W61: 12 | X61: =V61/W61 -> 91106.446 | Z61: =X61 -> 91106.446 | AA61: 46666.667 | AB61: =Z61-AA61 -> 44439.779
A62: 55 | B62: UDEFUNA NNADOZIE PATRICK | C62: 475703.83 | D62: 12 | E62: =C62*D62 -> 5708446 | G62: 351075.68 | I62: =E62-F62-G62-H62 -> 5357370.3 | J62: 200000 | K62: 0.2 | L62: =I62*K62 -> 1071474.1 | M62: =J62+L62 -> 1271474.1 | N62: =F62+G62+H62+M62 -> 1622549.7 | O62: =E62-N62 -> 4085896.3 | P62: =IF(O62<300000,0.07*O62,21000) -> 21000 | Q62: =IF((O62-300000)<0,0,IF((O62-300000)<300000,0.11*(O62-300000),33000)) -> 33000 | R62: =IF((O62-600000)<0,0,IF((O62-600000)<500000,0.15*(O62-600000),75000)) -> 75000 | S62: =IF((O62-1100000)<0,0,IF((O62-1100000)<500000,0.19*(O62-1100000),95000)) -> 95000 | T62: =IF((O62-1600000)<0,0,IF((O62-1600000)<1600000,0.21*(O62-1600000),336000)) -> 336000 | U62: =24%*(O62-3200000) -> 212615.1 | V62: =P62+Q62+R62+S62+T62+U62 -> 772615.1 | W62: 12 | X62: =V62/W62 -> 64384.592 | Z62: =X62 -> 64384.592 | AA62: 41338.951 | AB62: =Z62-AA62 -> 23045.641
A63: 56 | B63: SHAFIU YAHYA MIKAIL | C63: 475703.83 | D63: 12 | E63: =C63*D63 -> 5708446 | G63: 351075.68 | I63: =E63-F63-G63-H63 -> 5357370.3 | J63: 200000 | K63: 0.2 | L63: =I63*K63 -> 1071474.1 | M63: =J63+L63 -> 1271474.1 | N63: =F63+G63+H63+M63 -> 1622549.7 | O63: =E63-N63 -> 4085896.3 | P63: =IF(O63<300000,0.07*O63,21000) -> 21000 | Q63: =IF((O63-300000)<0,0,IF((O63-300000)<300000,0.11*(O63-300000),33000)) -> 33000 | R63: =IF((O63-600000)<0,0,IF((O63-600000)<500000,0.15*(O63-600000),75000)) -> 75000 | S63: =IF((O63-1100000)<0,0,IF((O63-1100000)<500000,0.19*(O63-1100000),95000)) -> 95000 | T63: =IF((O63-1600000)<0,0,IF((O63-1600000)<1600000,0.21*(O63-1600000),336000)) -> 336000 | U63: =24%*(O63-3200000) -> 212615.1 | V63: =P63+Q63+R63+S63+T63+U63 -> 772615.1 | W63: 12 | X63: =V63/W63 -> 64384.592 | Z63: =X63 -> 64384.592 | AA63: 41338.951 | AB63: =Z63-AA63 -> 23045.641
A64: 57 | B64: HASSAN YERIMA | C64: 475703.83 | D64: 12 | E64: =C64*D64 -> 5708446 | G64: 351075.68 | I64: =E64-F64-G64-H64 -> 5357370.3 | J64: 200000 | K64: 0.2 | L64: =I64*K64 -> 1071474.1 | M64: =J64+L64 -> 1271474.1 | N64: =F64+G64+H64+M64 -> 1622549.7 | O64: =E64-N64 -> 4085896.3 | P64: =IF(O64<300000,0.07*O64,21000) -> 21000 | Q64: =IF((O64-300000)<0,0,IF((O64-300000)<300000,0.11*(O64-300000),33000)) -> 33000 | R64: =IF((O64-600000)<0,0,IF((O64-600000)<500000,0.15*(O64-600000),75000)) -> 75000 | S64: =IF((O64-1100000)<0,0,IF((O64-1100000)<500000,0.19*(O64-1100000),95000)) -> 95000 | T64: =IF((O64-1600000)<0,0,IF((O64-1600000)<1600000,0.21*(O64-1600000),336000)) -> 336000 | U64: =24%*(O64-3200000) -> 212615.1 | V64: =P64+Q64+R64+S64+T64+U64 -> 772615.1 | W64: 12 | X64: =V64/W64 -> 64384.592 | Z64: =X64 -> 64384.592 | AA64: 41338.951 | AB64: =Z64-AA64 -> 23045.641
A65: 58 | B65: HAUWA PATE SADIQ | C65: 487895.17 | D65: 12 | E65: =C65*D65 -> 5854742 | G65: 362779.36 | I65: =E65-F65-G65-H65 -> 5491962.6 | J65: 200000 | K65: 0.2 | L65: =I65*K65 -> 1098392.5 | M65: =J65+L65 -> 1298392.5 | N65: =F65+G65+H65+M65 -> 1661171.9 | O65: =E65-N65 -> 4193570.1 | P65: =IF(O65<300000,0.07*O65,21000) -> 21000 | Q65: =IF((O65-300000)<0,0,IF((O65-300000)<300000,0.11*(O65-300000),33000)) -> 33000 | R65: =IF((O65-600000)<0,0,IF((O65-600000)<500000,0.15*(O65-600000),75000)) -> 75000 | S65: =IF((O65-1100000)<0,0,IF((O65-1100000)<500000,0.19*(O65-1100000),95000)) -> 95000 | T65: =IF((O65-1600000)<0,0,IF((O65-1600000)<1600000,0.21*(O65-1600000),336000)) -> 336000 | U65: =24%*(O65-3200000) -> 238456.83 | V65: =P65+Q65+R65+S65+T65+U65 -> 798456.83 | W65: 12 | X65: =V65/W65 -> 66538.069 | Z65: =X65 -> 66538.069 | AA65: 43368.882 | AB65: =Z65-AA65 -> 23169.186
A66: 59 | B66: KOLAPO Q. ABAYOMI | C66: 400965.58 | D66: 12 | E66: =C66*D66 -> 4811587 | G66: 288926.96 | I66: =E66-F66-G66-H66 -> 4522660 | J66: 200000 | K66: 0.2 | L66: =I66*K66 -> 904532.01 | M66: =J66+L66 -> 1104532 | N66: =F66+G66+H66+M66 -> 1393459 | O66: =E66-N66 -> 3418128 | P66: =IF(O66<300000,0.07*O66,21000) -> 21000 | Q66: =IF((O66-300000)<0,0,IF((O66-300000)<300000,0.11*(O66-300000),33000)) -> 33000 | R66: =IF((O66-600000)<0,0,IF((O66-600000)<500000,0.15*(O66-600000),75000)) -> 75000 | S66: =IF((O66-1100000)<0,0,IF((O66-1100000)<500000,0.19*(O66-1100000),95000)) -> 95000 | T66: =IF((O66-1600000)<0,0,IF((O66-1600000)<1600000,0.21*(O66-1600000),336000)) -> 336000 | U66: =24%*(O66-3200000) -> 52350.728 | V66: =P66+Q66+R66+S66+T66+U66 -> 612350.73 | W66: 12 | X66: =V66/W66 -> 51029.227 | Z66: =X66 -> 51029.227 | AA66: 33825.987 | AB66: =Z66-AA66 -> 17203.241
A67: 60
A68: 61
B69: DEPARTMENT OF STUDIES
B70: DR ASIMIYU G. ABIOLA | C70: 1635720 | D70: 12 | E70: =C70*D70 -> 19628640 | G70: 1378291.2 | I70: =E70-F70-G70-H70 -> 18250349 | J70: 200000 | K70: 0.2 | L70: =I70*K70 -> 3650069.8 | M70: =J70+L70 -> 3850069.8 | N70: =F70+G70+H70+M70 -> 5228361 | O70: =E70-N70 -> 14400279 | P70: =IF(O70<300000,0.07*O70,21000) -> 21000 | Q70: =IF((O70-300000)<0,0,IF((O70-300000)<300000,0.11*(O70-300000),33000)) -> 33000 | R70: =IF((O70-600000)<0,0,IF((O70-600000)<500000,0.15*(O70-600000),75000)) -> 75000 | S70: =IF((O70-1100000)<0,0,IF((O70-1100000)<500000,0.19*(O70-1100000),95000)) -> 95000 | T70: =IF((O70-1600000)<0,0,IF((O70-1600000)<1600000,0.21*(O70-1600000),336000)) -> 336000 | U70: =24%*(O70-3200000) -> 2688067 | V70: =P70+Q70+R70+S70+T70+U70 -> 3248067 | W70: 12 | X70: =V70/W70 -> 270672.25 | Z70: =X70 -> 270672.25 | AA70: 180306.81 | AB70: =Z70-AA70 -> 90365.441
A71: 62 | B71: USMAN WALI | C71: 761396.83 | D71: 12 | E71: =C71*D71 -> 9136762 | G71: 0 | I71: =E71-F71-G71-H71 -> 9136762 | J71: 200000 | K71: 0.2 | L71: =I71*K71 -> 1827352.4 | M71: =J71+L71 -> 2027352.4 | N71: =F71+G71+H71+M71 -> 2027352.4 | O71: =E71-N71 -> 7109409.6 | P71: =IF(O71<300000,0.07*O71,21000) -> 21000 | Q71: =IF((O71-300000)<0,0,IF((O71-300000)<300000,0.11*(O71-300000),33000)) -> 33000 | R71: =IF((O71-600000)<0,0,IF((O71-600000)<500000,0.15*(O71-600000),75000)) -> 75000 | S71: =IF((O71-1100000)<0,0,IF((O71-1100000)<500000,0.19*(O71-1100000),95000)) -> 95000 | T71: =IF((O71-1600000)<0,0,IF((O71-1600000)<1600000,0.21*(O71-1600000),336000)) -> 336000 | U71: =24%*(O71-3200000) -> 938258.3 | V71: =P71+Q71+R71+S71+T71+U71 -> 1498258.3 | W71: 12 | X71: =V71/W71 -> 124854.86 | Z71: =X71 -> 124854.86 | AA71: 77764.98 | AB71: =Z71-AA71 -> 47089.878
A72: 63 | B72: AYOBOLU OLAJIDE OLUFUNSHO | C72: =700675.583333333+80000 -> 780675.58 | D72: 12 | E72: =C72*D72 -> 9368107 | G72: 0 | I72: =E72-F72-G72-H72 -> 9368107 | J72: 200000 | K72: 0.2 | L72: =I72*K72 -> 1873621.4 | M72: =J72+L72 -> 2073621.4 | N72: =F72+G72+H72+M72 -> 2073621.4 | O72: =E72-N72 -> 7294485.6 | P72: =IF(O72<300000,0.07*O72,21000) -> 21000 | Q72: =IF((O72-300000)<0,0,IF((O72-300000)<300000,0.11*(O72-300000),33000)) -> 33000 | R72: =IF((O72-600000)<0,0,IF((O72-600000)<500000,0.15*(O72-600000),75000)) -> 75000 | S72: =IF((O72-1100000)<0,0,IF((O72-1100000)<500000,0.19*(O72-1100000),95000)) -> 95000 | T72: =IF((O72-1600000)<0,0,IF((O72-1600000)<1600000,0.21*(O72-1600000),336000)) -> 336000 | U72: =24%*(O72-3200000) -> 982676.54 | V72: =P72+Q72+R72+S72+T72+U72 -> 1542676.5 | W72: 12 | X72: =V72/W72 -> 128556.38 | Z72: =X72 -> 128556.38 | AA72: 64596.939 | AB72: =Z72-AA72 -> 63959.44
A73: 64 | B73: ANTHONY EDET | C73: 596622.25 | D73: 12 | E73: =C73*D73 -> 7159467 | F73: ='[5]JANUARY 2024'!$V$78*12 -> 8019.795 | G73: 438357.36 | I73: =E73-F73-G73-H73 -> 6713089.8 | J73: 200000 | K73: 0.2 | L73: =I73*K73 -> 1342618 | M73: =J73+L73 -> 1542618 | N73: =F73+G73+H73+M73 -> 1988995.1 | O73: =E73-N73 -> 5170471.9 | P73: =IF(O73<300000,0.07*O73,21000) -> 21000 | Q73: =IF((O73-300000)<0,0,IF((O73-300000)<300000,0.11*(O73-300000),33000)) -> 33000 | R73: =IF((O73-600000)<0,0,IF((O73-600000)<500000,0.15*(O73-600000),75000)) -> 75000 | S73: =IF((O73-1100000)<0,0,IF((O73-1100000)<500000,0.19*(O73-1100000),95000)) -> 95000 | T73: =IF((O73-1600000)<0,0,IF((O73-1600000)<1600000,0.21*(O73-1600000),336000)) -> 336000 | U73: =24%*(O73-3200000) -> 472913.25 | V73: =P73+Q73+R73+S73+T73+U73 -> 1032913.3 | W73: 12 | X73: =V73/W73 -> 86076.104 | Z73: =X73 -> 86076.104 | AA73: 56350.586 | AB73: =Z73-AA73 -> 29725.518
A74: 65 | B74: IGWE STACY | C74: 408901.5 | D74: 12 | E74: =C74*D74 -> 4906818 | G74: 296545.44 | I74: =E74-F74-G74-H74 -> 4610272.6 | J74: 200000 | K74: 0.2 | L74: =I74*K74 -> 922054.51 | M74: =J74+L74 -> 1122054.5 | N74: =F74+G74+H74+M74 -> 1418600 | O74: =E74-N74 -> 3488218 | P74: =IF(O74<300000,0.07*O74,21000) -> 21000 | Q74: =IF((O74-300000)<0,0,IF((O74-300000)<300000,0.11*(O74-300000),33000)) -> 33000 | R74: =IF((O74-600000)<0,0,IF((O74-600000)<500000,0.15*(O74-600000),75000)) -> 75000 | S74: =IF((O74-1100000)<0,0,IF((O74-1100000)<500000,0.19*(O74-1100000),95000)) -> 95000 | T74: =IF((O74-1600000)<0,0,IF((O74-1600000)<1600000,0.21*(O74-1600000),336000)) -> 336000 | U74: =0.24*(O74-3200000) -> 69172.332 | V74: =P74+Q74+R74+S74+T74+U74 -> 629172.33 | W74: 12 | X74: =V74/W74 -> 52431.028 | Z74: =X74 -> 52431.028 | AA74: 17507.549 | AB74: =Z74-AA74 -> 34923.479
B75: OLANIYAN TAIWO ABINBOLA | C75: 363165.33 | D75: 12 | E75: =C75*D75 -> 4357984 | G75: 252638.72 | I75: =E75-F75-G75-H75 -> 4105345.3 | J75: 200000 | K75: 0.2 | L75: =I75*K75 -> 821069.06 | M75: =J75+L75 -> 1021069.1 | N75: =F75+G75+H75+M75 -> 1273707.8 | O75: =E75-N75 -> 3084276.2 | P75: =IF(O75<300000,0.07*O75,21000) -> 21000 | Q75: =IF((O75-300000)<0,0,IF((O75-300000)<300000,0.11*(O75-300000),33000)) -> 33000 | R75: =IF((O75-600000)<0,0,IF((O75-600000)<500000,0.15*(O75-600000),75000)) -> 75000 | S75: =IF((O75-1100000)<0,0,IF((O75-1100000)<500000,0.19*(O75-1100000),95000)) -> 95000 | T75: =IF((O75-1600000)<0,0,IF((O75-1600000)<1600000,0.21*(O75-1600000),336000)) -> 311698.01 | V75: =P75+Q75+R75+S75+T75+U75 -> 535698.01 | W75: 12 | X75: =V75/W75 -> 44641.501 | Z75: =X75 -> 44641.501 | AA75: 29058.483 | AB75: =Z75-AA75 -> 15583.018
B76: AMINAT JUMOKE SULAIMON | C76: 324459.75 | D76: 12 | E76: =C76*D76 -> 3893517 | G76: 215481.36 | I76: =E76-F76-G76-H76 -> 3678035.6 | J76: 200000 | K76: 0.2 | L76: =I76*K76 -> 735607.13 | M76: =J76+L76 -> 935607.13 | N76: =F76+G76+H76+M76 -> 1151088.5 | O76: =E76-N76 -> 2742428.5 | P76: =IF(O76<300000,0.07*O76,21000) -> 21000 | Q76: =IF((O76-300000)<0,0,IF((O76-300000)<300000,0.11*(O76-300000),33000)) -> 33000 | R76: =IF((O76-600000)<0,0,IF((O76-600000)<500000,0.15*(O76-600000),75000)) -> 75000 | S76: =IF((O76-1100000)<0,0,IF((O76-1100000)<500000,0.19*(O76-1100000),95000)) -> 95000 | T76: =IF((O76-1600000)<0,0,IF((O76-1600000)<1600000,0.21*(O76-1600000),336000)) -> 239909.99 | V76: =P76+Q76+R76+S76+T76+U76 -> 463909.99 | W76: 12 | X76: =V76/W76 -> 38659.166 | Z76: =X76 -> 38659.166 | AA76: 24751.17 | AB76: =Z76-AA76 -> 13907.995
B77: TOTAL
A78: 66
A79: 67 | B79: ECON. DEV. & SOC. RESEARCH | AB79: difference
A80: 68 | B80: TERFA WILLIAMS ABRAHAM | C80: =880675.583333333+100000 -> 980675.58 | D80: 12 | E80: =C80*D80 -> 11768107 | G80: 595848.56 | I80: =E80-F80-G80-H80 -> 11172258 | J80: 200000 | K80: 0.2 | L80: =I80*K80 -> 2234451.7 | M80: =J80+L80 -> 2434451.7 | N80: =F80+G80+H80+M80 -> 3030300.2 | O80: =E80-N80 -> 8737806.8 | P80: =IF(O80<300000,0.07*O80,21000) -> 21000 | Q80: =IF((O80-300000)<0,0,IF((O80-300000)<300000,0.11*(O80-300000),33000)) -> 33000 | R80: =IF((O80-600000)<0,0,IF((O80-600000)<500000,0.15*(O80-600000),75000)) -> 75000 | S80: =IF((O80-1100000)<0,0,IF((O80-1100000)<500000,0.19*(O80-1100000),95000)) -> 95000 | T80: =IF((O80-1600000)<0,0,IF((O80-1600000)<1600000,0.21*(O80-1600000),336000)) -> 336000 | U80: =24%*(O80-3200000) -> 1329073.6 | V80: =P80+Q80+R80+S80+T80+U80 -> 1889073.6 | W80: 12 | X80: =V80/W80 -> 157422.8 | Z80: =X80 -> 157422.8 | AA80: 99156.939 | AB80: =Z80-AA80 -> 58265.863 | AC80: TERFA WILLIAMS ABRAHAM
A81: 69 | B81: DR AUGUSTINE C. OSIGWE | C81: 780675.58 | D81: 12 | E81: =C81*D81 -> 9368107 | F81: ='[5]JANUARY 2024'!$V$86*12 -> 10052.25 | G81: 595848.56 | I81: =E81-F81-G81-H81 -> 8762206.2 | J81: 200000 | K81: 0.2 | L81: =I81*K81 -> 1752441.2 | M81: =J81+L81 -> 1952441.2 | N81: =F81+G81+H81+M81 -> 2558342 | O81: =E81-N81 -> 6809765 | P81: =IF(O81<300000,0.07*O81,21000) -> 21000 | Q81: =IF((O81-300000)<0,0,IF((O81-300000)<300000,0.11*(O81-300000),33000)) -> 33000 | R81: =IF((O81-600000)<0,0,IF((O81-600000)<500000,0.15*(O81-600000),75000)) -> 75000 | S81: =IF((O81-1100000)<0,0,IF((O81-1100000)<500000,0.19*(O81-1100000),95000)) -> 95000 | T81: =IF((O81-1600000)<0,0,IF((O81-1600000)<1600000,0.21*(O81-1600000),336000)) -> 336000 | U81: =24%*(O81-3200000) -> 866343.59 | V81: =P81+Q81+R81+S81+T81+U81 -> 1426343.6 | W81: 12 | X81: =V81/W81 -> 118861.97 | Z81: =X81 -> 118861.97 | AA81: 98996.103 | AB81: =Z81-AA81 -> 19865.863 | AC81: DR AUGUSTINE C. OSIGWE
A82: 70 | B82: OMOJU OLUWASOLA EMMANUEL | C82: 587895.17 | D82: 12 | E82: =C82*D82 -> 7054742 | G82: 558833.36 | I82: =E82-F82-G82-H82 -> 6495908.6 | J82: 200000 | K82: 0.2 | L82: =I82*K82 -> 1299181.7 | M82: =J82+L82 -> 1499181.7 | N82: =F82+G82+H82+M82 -> 2058015.1 | O82: =E82-N82 -> 4996726.9 | P82: =IF(O82<300000,0.07*O82,21000) -> 21000 | Q82: =IF((O82-300000)<0,0,IF((O82-300000)<300000,0.11*(O82-300000),33000)) -> 33000 | R82: =IF((O82-600000)<0,0,IF((O82-600000)<500000,0.15*(O82-600000),75000)) -> 75000 | S82: =IF((O82-1100000)<0,0,IF((O82-1100000)<500000,0.19*(O82-1100000),95000)) -> 95000 | T82: =IF((O82-1600000)<0,0,IF((O82-1600000)<1600000,0.21*(O82-1600000),336000)) -> 336000 | U82: =24%*(O82-3200000) -> 431214.46 | V82: =P82+Q82+R82+S82+T82+U82 -> 991214.46 | W82: 12 | X82: =V82/W82 -> 82601.205 | Z82: =X82 -> 82601.205 | AA82: 79956.939 | AB82: =Z82-AA82 -> 2644.2658 | AC82: OMOJU OLUWASOLA EMMANUEL
A83: 71 | B83: IBE EZECHI CYRIACUS | C83: 582746.5 | D83: 12 | E83: =C83*D83 -> 6992958 | G83: 424132.72 | I83: =E83-F83-G83-H83 -> 6568825.3 | J83: 200000 | K83: 0.2 | L83: =I83*K83 -> 1313765.1 | M83: =J83+L83 -> 1513765.1 | N83: =F83+G83+H83+M83 -> 1937897.8 | O83: =E83-N83 -> 5055060.2 | P83: =IF(O83<300000,0.07*O83,21000) -> 21000 | Q83: =IF((O83-300000)<0,0,IF((O83-300000)<300000,0.11*(O83-300000),33000)) -> 33000 | R83: =IF((O83-600000)<0,0,IF((O83-600000)<500000,0.15*(O83-600000),75000)) -> 75000 | S83: =IF((O83-1100000)<0,0,IF((O83-1100000)<500000,0.19*(O83-1100000),95000)) -> 95000 | T83: =IF((O83-1600000)<0,0,IF((O83-1600000)<1600000,0.21*(O83-1600000),336000)) -> 336000 | U83: =24%*(O83-3200000) -> 445214.45 | V83: =P83+Q83+R83+S83+T83+U83 -> 1005214.5 | W83: 12 | X83: =V83/W83 -> 83767.871 | Z83: =X83 -> 83767.871 | AA83: 75574.677 | AB83: =Z83-AA83 -> 8193.1939 | AC83: IBE EZECHI CYRIACUS
A84: 72 | B84: OSIKHEN LEO IGBANOI | C84: 548915.92 | D84: 12 | E84: =C84*D84 -> 6586991 | G84: 411759.28 | I84: =E84-F84-G84-H84 -> 6175231.7 | J84: 200000 | K84: 0.2 | L84: =I84*K84 -> 1235046.3 | M84: =J84+L84 -> 1435046.3 | N84: =F84+G84+H84+M84 -> 1846805.6 | O84: =E84-N84 -> 4740185.4 | P84: =IF(O84<300000,0.07*O84,21000) -> 21000 | Q84: =IF((O84-300000)<0,0,IF((O84-300000)<300000,0.11*(O84-300000),33000)) -> 33000 | R84: =IF((O84-600000)<0,0,IF((O84-600000)<500000,0.15*(O84-600000),75000)) -> 75000 | S84: =IF((O84-1100000)<0,0,IF((O84-1100000)<500000,0.19*(O84-1100000),95000)) -> 95000 | T84: =IF((O84-1600000)<0,0,IF((O84-1600000)<1600000,0.21*(O84-1600000),336000)) -> 336000 | U84: =24%*(O84-3200000) -> 369644.49 | V84: =P84+Q84+R84+S84+T84+U84 -> 929644.49 | W84: 12 | X84: =V84/W84 -> 77470.374 | Z84: =X84 -> 77470.374 | AA84: 50985.978 | AB84: =Z84-AA84 -> 26484.397 | AC84: OSIKHEN LEO IGBANOI
A85: 73 | B85: OKUNGBOWA OSARETIN GODSPOWER | C85: 568870.75 | D85: 12 | E85: =C85*D85 -> 6826449 | G85: 411715.92 | I85: =E85-F85-G85-H85 -> 6414733.1 | J85: 200000 | K85: 0.2 | L85: =I85*K85 -> 1282946.6 | M85: =J85+L85 -> 1482946.6 | N85: =F85+G85+H85+M85 -> 1894662.5 | O85: =E85-N85 -> 4931786.5 | P85: =IF(O85<300000,0.07*O85,21000) -> 21000 | Q85: =IF((O85-300000)<0,0,IF((O85-300000)<300000,0.11*(O85-300000),33000)) -> 33000 | R85: =IF((O85-600000)<0,0,IF((O85-600000)<500000,0.15*(O85-600000),75000)) -> 75000 | S85: =IF((O85-1100000)<0,0,IF((O85-1100000)<500000,0.19*(O85-1100000),95000)) -> 95000 | T85: =IF((O85-1600000)<0,0,IF((O85-1600000)<1600000,0.21*(O85-1600000),336000)) -> 336000 | U85: =24%*(O85-3200000) -> 415628.75 | V85: =P85+Q85+R85+S85+T85+U85 -> 975628.75 | W85: 12 | X85: =V85/W85 -> 81302.396 | Z85: =X85 -> 81302.396 | AA85: 49548.776 | AB85: =Z85-AA85 -> 31753.62 | AC85: OKUNGBOWA OSARETIN GODSPOWER
A86: 74 | B86: YUSUF IBRAHIM | C86: 475703.83 | D86: 12 | E86: =C86*D86 -> 5708446 | G86: =29256.3066666667*12 -> 351075.68 | I86: =E86-F86-G86-H86 -> 5357370.3 | J86: 200000 | K86: 0.2 | L86: =I86*K86 -> 1071474.1 | M86: =J86+L86 -> 1271474.1 | N86: =F86+G86+H86+M86 -> 1622549.7 | O86: =E86-N86 -> 4085896.3 | P86: =IF(O86<300000,0.07*O86,21000) -> 21000 | Q86: =IF((O86-300000)<0,0,IF((O86-300000)<300000,0.11*(O86-300000),33000)) -> 33000 | R86: =IF((O86-600000)<0,0,IF((O86-600000)<500000,0.15*(O86-600000),75000)) -> 75000 | S86: =IF((O86-1100000)<0,0,IF((O86-1100000)<500000,0.19*(O86-1100000),95000)) -> 95000 | T86: =IF((O86-1600000)<0,0,IF((O86-1600000)<1600000,0.21*(O86-1600000),336000)) -> 336000 | U86: =24%*(O86-3200000) -> 212615.1 | V86: =P86+Q86+R86+S86+T86+U86 -> 772615.1 | W86: 12 | X86: =V86/W86 -> 64384.592 | Z86: =X86 -> 64384.592 | AA86: 53384.054 | AB86: =Z86-AA86 -> 11000.538 | AC86: YUSUF IBRAHIM
A87: 75 | B87: MUSTAPHA RAFIU AYOBANJI | C87: 510248.92 | D87: 12 | E87: =C87*D87 -> 6122987 | F87: ='[5]JANUARY 2024'!$V$92*12 -> 6922.497 | G87: 374638.96 | I87: =E87-F87-G87-H87 -> 5741425.5 | J87: 200000 | K87: 0.2 | L87: =I87*K87 -> 1148285.1 | M87: =J87+L87 -> 1348285.1 | N87: =F87+G87+H87+M87 -> 1729846.6 | O87: =E87-N87 -> 4393140.4 | P87: =IF(O87<300000,0.07*O87,21000) -> 21000 | Q87: =IF((O87-300000)<0,0,IF((O87-300000)<300000,0.11*(O87-300000),33000)) -> 33000 | R87: =IF((O87-600000)<0,0,IF((O87-600000)<500000,0.15*(O87-600000),75000)) -> 75000 | S87: =IF((O87-1100000)<0,0,IF((O87-1100000)<500000,0.19*(O87-1100000),95000)) -> 95000 | T87: =IF((O87-1600000)<0,0,IF((O87-1600000)<1600000,0.21*(O87-1600000),336000)) -> 336000 | U87: =24%*(O87-3200000) -> 286353.7 | V87: =P87+Q87+R87+S87+T87+U87 -> 846353.7 | W87: 12 | X87: =V87/W87 -> 70529.475 | Z87: =X87 -> 70529.475 | AA87: 41242.036 | AB87: =Z87-AA87 -> 29287.439 | AC87: MUSTAPHA RAFIU AYOBANJI
A88: 76 | B88: MARYAM MUSA SADA | C88: 400965.58 | D88: 12 | E88: =C88*D88 -> 4811587 | G88: 288926.96 | I88: =E88-F88-G88-H88 -> 4522660 | J88: 200000 | K88: 0.2 | L88: =I88*K88 -> 904532.01 | M88: =J88+L88 -> 1104532 | N88: =F88+G88+H88+M88 -> 1393459 | O88: =E88-N88 -> 3418128 | P88: =IF(O88<300000,0.07*O88,21000) -> 21000 | Q88: =IF((O88-300000)<0,0,IF((O88-300000)<300000,0.11*(O88-300000),33000)) -> 33000 | R88: =IF((O88-600000)<0,0,IF((O88-600000)<500000,0.15*(O88-600000),75000)) -> 75000 | S88: =IF((O88-1100000)<0,0,IF((O88-1100000)<500000,0.19*(O88-1100000),95000)) -> 95000 | T88: =IF((O88-1600000)<0,0,IF((O88-1600000)<1600000,0.21*(O88-1600000),336000)) -> 336000 | U88: =24%*(O88-3200000) -> 52350.728 | V88: =P88+Q88+R88+S88+T88+U88 -> 612350.73 | W88: 12 | X88: =V88/W88 -> 51029.227 | Z88: =X88 -> 51029.227 | AA88: 45414.456 | AB88: =Z88-AA88 -> 5614.7711 | AC88: MARYAM MUSA SADA
B89: CHARITY EZENWAJIOBI | C89: 330631.92 | D89: 12 | E89: =C89*D89 -> 3967583 | G89: 221406.64 | I89: =E89-F89-G89-H89 -> 3746176.4 | J89: 200000 | K89: 0.2 | L89: =I89*K89 -> 749235.27 | M89: =J89+L89 -> 949235.27 | N89: =F89+G89+H89+M89 -> 1170641.9 | O89: =E89-N89 -> 2796941.1 | P89: =IF(O89<300000,0.07*O89,21000) -> 21000 | Q89: =IF((O89-300000)<0,0,IF((O89-300000)<300000,0.11*(O89-300000),33000)) -> 33000 | R89: =IF((O89-600000)<0,0,IF((O89-600000)<500000,0.15*(O89-600000),75000)) -> 75000 | S89: =IF((O89-1100000)<0,0,IF((O89-1100000)<500000,0.19*(O89-1100000),95000)) -> 95000 | T89: =IF((O89-1600000)<0,0,IF((O89-1600000)<1600000,0.21*(O89-1600000),336000)) -> 251357.63 | V89: =P89+Q89+R89+S89+T89+U89 -> 475357.63 | W89: 12 | X89: =V89/W89 -> 39613.136 | Z89: =X89 -> 39613.136 | AA89: 33825.987 | AB89: =Z89-AA89 -> 5787.1491 | AC89: CHARITY EZENWAJIOBI
A92: 78 | B92: TRAINING & INT''L COOP
A93: 79 | B93: AKINSANMI ADEJOKE OLUKEMI | C93: 1452042.7 | D93: 12 | E93: =C93*D93 -> 17424512 | F93: ='[5]JANUARY 2024'!$V$98*12 -> 12795.951 | G93: =(0.08*1352042.67)*12 -> 1297961 | I93: =E93-F93-G93-H93 -> 16113755 | J93: 200000 | K93: 0.2 | L93: =I93*K93 -> 3222751 | M93: =J93+L93 -> 3422751 | N93: =F93+G93+H93+M93 -> 4733507.9 | O93: =E93-N93 -> 12691004 | P93: =IF(O93<300000,0.07*O93,21000) -> 21000 | Q93: =IF((O93-300000)<0,0,IF((O93-300000)<300000,0.11*(O93-300000),33000)) -> 33000 | R93: =IF((O93-600000)<0,0,IF((O93-600000)<500000,0.15*(O93-600000),75000)) -> 75000 | S93: =IF((O93-1100000)<0,0,IF((O93-1100000)<500000,0.19*(O93-1100000),95000)) -> 95000 | T93: =IF((O93-1600000)<0,0,IF((O93-1600000)<1600000,0.21*(O93-1600000),336000)) -> 336000 | U93: =24%*(O93-3200000) -> 2277841 | V93: =P93+Q93+R93+S93+T93+U93 -> 2837841 | W93: 12 | X93: =V93/W93 -> 236486.75 | Z93: =X93 -> 236486.75 | AA93: 82423.216 | AB93: =Z93-AA93 -> 154063.53 | AC93: AKINSANMI ADEJOKE OLUKEMI
A94: 80 | B94: MOHAMMED R. ADAMU | C94: 526622.25 | D94: 12 | E94: =C94*D94 -> 6319467 | G94: 438357.36 | I94: =E94-F94-G94-H94 -> 5881109.6 | J94: 200000 | K94: 0.2 | L94: =I94*K94 -> 1176221.9 | M94: =J94+L94 -> 1376221.9 | N94: =F94+G94+H94+M94 -> 1814579.3 | O94: =E94-N94 -> 4504887.7 | P94: =IF(O94<300000,0.07*O94,21000) -> 21000 | Q94: =IF((O94-300000)<0,0,IF((O94-300000)<300000,0.11*(O94-300000),33000)) -> 33000 | R94: =IF((O94-600000)<0,0,IF((O94-600000)<500000,0.15*(O94-600000),75000)) -> 75000 | S94: =IF((O94-1100000)<0,0,IF((O94-1100000)<500000,0.19*(O94-1100000),95000)) -> 95000 | T94: =IF((O94-1600000)<0,0,IF((O94-1600000)<1600000,0.21*(O94-1600000),336000)) -> 336000 | U94: =24%*(O94-3200000) -> 313173.05 | V94: =P94+Q94+R94+S94+T94+U94 -> 873173.05 | W94: 12 | X94: =V94/W94 -> 72764.421 | Z94: =X94 -> 72764.421 | AA94: 82627.951 | AB94: =Z94-AA94 -> -9863.5305 | AC94: MOHAMMED R. ADAMU
A95: 81 | B95: OKECHUKWU UCHENNA HULDA | C95: 437895.17 | D95: 12 | E95: =C95*D95 -> 5254742 | G95: 362779.36 | I95: =E95-F95-G95-H95 -> 4891962.6 | J95: 200000 | K95: 0.2 | L95: =I95*K95 -> 978392.53 | M95: =J95+L95 -> 1178392.5 | N95: =F95+G95+H95+M95 -> 1541171.9 | O95: =E95-N95 -> 3713570.1 | P95: =IF(O95<300000,0.07*O95,21000) -> 21000 | Q95: =IF((O95-300000)<0,0,IF((O95-300000)<300000,0.11*(O95-300000),33000)) -> 33000 | R95: =IF((O95-600000)<0,0,IF((O95-600000)<500000,0.15*(O95-600000),75000)) -> 75000 | S95: =IF((O95-1100000)<0,0,IF((O95-1100000)<500000,0.19*(O95-1100000),95000)) -> 95000 | T95: =IF((O95-1600000)<0,0,IF((O95-1600000)<1600000,0.21*(O95-1600000),336000)) -> 336000 | U95: =24%*(O95-3200000) -> 123256.83 | V95: =P95+Q95+R95+S95+T95+U95 -> 683256.83 | W95: 12 | X95: =V95/W95 -> 56938.069 | Z95: =X95 -> 56938.069 | AA95: 43492.373 | AB95: =Z95-AA95 -> 13445.696 | AC95: OKECHUKWU UCHENNA HULDA
B96: TASSNEEM IBRAHIM | C96: 360965.58 | D96: 12 | E96: =C96*D96 -> 4331587 | G96: 288926.96 | I96: =E96-F96-G96-H96 -> 4042660 | J96: 200000 | K96: 0.2 | L96: =I96*K96 -> 808532.01 | M96: =J96+L96 -> 1008532 | N96: =F96+G96+H96+M96 -> 1297459 | O96: =E96-N96 -> 3034128 | P96: =IF(O96<300000,0.07*O96,21000) -> 21000 | Q96: =IF((O96-300000)<0,0,IF((O96-300000)<300000,0.11*(O96-300000),33000)) -> 33000 | R96: =IF((O96-600000)<0,0,IF((O96-600000)<500000,0.15*(O96-600000),75000)) -> 75000 | S96: =IF((O96-1100000)<0,0,IF((O96-1100000)<500000,0.19*(O96-1100000),95000)) -> 95000 | T96: =IF((O96-1600000)<0,0,IF((O96-1600000)<1600000,0.21*(O96-1600000),336000)) -> 301166.89 | V96: =P96+Q96+R96+S96+T96+U96 -> 525166.89 | W96: 12 | X96: =V96/W96 -> 43763.907 | Z96: =X96 -> 43763.907 | AA96: 34968.882 | AB96: =Z96-AA96 -> 8795.0248 | AC96: TASSNEEM IBRAHIM
B97: TOTAL | G97: 0
A98: 83 | G98: 0
A99: 84 | B99: LIBRARY & DOCUMENTATION | G99: 0 | AB99: Difference
A100: 85 | B100: DR MAIMUNA IZAH | C100: 1635720 | D100: 12 | E100: =C100*D100 -> 19628640 | G100: 1378291.2 | I100: =E100-F100-G100-H100 -> 18250349 | J100: 200000 | K100: 0.2 | L100: =I100*K100 -> 3650069.8 | M100: =J100+L100 -> 3850069.8 | N100: =F100+G100+H100+M100 -> 5228361 | O100: =E100-N100 -> 14400279 | P100: =IF(O100<300000,0.07*O100,21000) -> 21000 | Q100: =IF((O100-300000)<0,0,IF((O100-300000)<300000,0.11*(O100-300000),33000)) -> 33000 | R100: =IF((O100-600000)<0,0,IF((O100-600000)<500000,0.15*(O100-600000),75000)) -> 75000 | S100: =IF((O100-1100000)<0,0,IF((O100-1100000)<500000,0.19*(O100-1100000),95000)) -> 95000 | T100: =IF((O100-1600000)<0,0,IF((O100-1600000)<1600000,0.21*(O100-1600000),336000)) -> 336000 | U100: =24%*(O100-3200000) -> 2688067 | V100: =P100+Q100+R100+S100+T100+U100 -> 3248067 | W100: 12 | X100: =V100/W100 -> 270672.25 | Z100: =X100 -> 270672.25 | AA100: 180306.81 | AB100: =Z100-AA100 -> 90365.441 | AC100: DR MAIMUNA IZAH
A101: 86 | B101: CATHERINE E. IKOKOH | C101: 942373.17 | D101: 12 | E101: =C101*D101 -> 11308478 | F101: ='[5]JANUARY 2024'!$V$106*12 -> 12795.951 | G101: 731878.24 | I101: =E101-F101-G101-H101 -> 10563804 | J101: 200000 | K101: 0.2 | L101: =I101*K101 -> 2112760.8 | M101: =J101+L101 -> 2312760.8 | N101: =F101+G101+H101+M101 -> 3057435 | O101: =E101-N101 -> 8251043 | P101: =IF(O101<300000,0.07*O101,21000) -> 21000 | Q101: =IF((O101-300000)<0,0,IF((O101-300000)<300000,0.11*(O101-300000),33000)) -> 33000 | R101: =IF((O101-600000)<0,0,IF((O101-600000)<500000,0.15*(O101-600000),75000)) -> 75000 | S101: =IF((O101-1100000)<0,0,IF((O101-1100000)<500000,0.19*(O101-1100000),95000)) -> 95000 | T101: =IF((O101-1600000)<0,0,IF((O101-1600000)<1600000,0.21*(O101-1600000),336000)) -> 336000 | U101: =24%*(O101-3200000) -> 1212250.3 | V101: =P101+Q101+R101+S101+T101+U101 -> 1772250.3 | W101: 12 | X101: =V101/W101 -> 147687.53 | Z101: =X101 -> 147687.53 | AA101: 99703.216 | AB101: =Z101-AA101 -> 47984.311 | AC101: CATHERINE E. IKOKOH
A102: 87 | B102: ALIYU SANNI ABUBAKAR | C102: 603237.86 | D102: 12 | E102: =C102*D102 -> 7238854.3 | F102: ='[5]JANUARY 2024'!$V$107*12 -> 7901.79 | G102: 424132.72 | I102: =E102-F102-G102-H102 -> 6806819.8 | J102: 200000 | K102: 0.2 | L102: =I102*K102 -> 1361364 | M102: =J102+L102 -> 1561364 | N102: =F102+G102+H102+M102 -> 1993398.5 | O102: =E102-N102 -> 5245455.8 | P102: =IF(O102<300000,0.07*O102,21000) -> 21000 | Q102: =IF((O102-300000)<0,0,IF((O102-300000)<300000,0.11*(O102-300000),33000)) -> 33000 | R102: =IF((O102-600000)<0,0,IF((O102-600000)<500000,0.15*(O102-600000),75000)) -> 75000 | S102: =IF((O102-1100000)<0,0,IF((O102-1100000)<500000,0.19*(O102-1100000),95000)) -> 95000 | T102: =IF((O102-1600000)<0,0,IF((O102-1600000)<1600000,0.21*(O102-1600000),336000)) -> 336000 | U102: =24%*(O102-3200000) -> 490909.39 | V102: =P102+Q102+R102+S102+T102+U102 -> 1050909.4 | W102: 12 | X102: =V102/W102 -> 87575.783 | Z102: =X102 -> 87575.783 | AA102: 180180.38 | AB102: =Z102-AA102 -> -92604.596 | AC102: ALIYU SANNI ABUBAKAR
A103: 88 | B103: CHINAKO N. ASOGWA | C103: 601625.03 | D103: 12 | E103: =C103*D103 -> 7219500.4 | G103: 424132.72 | I103: =E103-F103-G103-H103 -> 6795367.7 | J103: 200000 | K103: 0.2 | L103: =I103*K103 -> 1359073.5 | M103: =J103+L103 -> 1559073.5 | N103: =F103+G103+H103+M103 -> 1983206.3 | O103: =E103-N103 -> 5236294.1 | P103: =IF(O103<300000,0.07*O103,21000) -> 21000 | Q103: =IF((O103-300000)<0,0,IF((O103-300000)<300000,0.11*(O103-300000),33000)) -> 33000 | R103: =IF((O103-600000)<0,0,IF((O103-600000)<500000,0.15*(O103-600000),75000)) -> 75000 | S103: =IF((O103-1100000)<0,0,IF((O103-1100000)<500000,0.19*(O103-1100000),95000)) -> 95000 | T103: =IF((O103-1600000)<0,0,IF((O103-1600000)<1600000,0.21*(O103-1600000),336000)) -> 336000 | U103: =0.24*(O103-3200000) -> 488710.59 | V103: =P103+Q103+R103+S103+T103+U103 -> 1048710.6 | W103: 12 | X103: =V103/W103 -> 87392.55 | Z103: =X103 -> 87392.55 | AA103: 99907.951 | AB103: =Z103-AA103 -> -12515.402 | AC103: CHINAKO N. ASOGWA
...

Sheet Upgrade in March
A1: NATIONAL INSTITUTE FOR LEGISLATIVE AND DEMOCRATIC STUDIES
A2: UPGRADE FROM GL 16(9) TO GL 17(7)
E3: ='[1]FEB 08'!E11/'[1]FEB 08'!M11 -> #REF!
B4: STAFF NAME | C4: DESIGNATION | D4: GRADE LEVEL | E4: BASIC SALARY | F4: ALLCE/ AREARS | G4: ALLOWANCE | H4: ALLOWANCE | I4: DUTY ALLCE | J4: GROSS SALARY | K4: AUCTION | L4: COOP CONTR/SPEC SAVINGS | M4: COOP. LOAN RECOVERY | N4: NHF DED. | O4: PAYE | P4: EMPLOYEE PENSIONS | Q4: TOTAL DEDUCTION | R4: FEBRUARY, 2024 | S4: MARCH, 2024
E5: N | G5: N | H5: N | I5: N | J5: N | K5: N | L5: N | M5: N | N5: N | O5: N | P5: N | Q5: N | R5: N | S5: N
B6: TRAINING & INT''L COOP
A7: 1 | B7: AKINSANMI ADEJOKE OLUKEMI | C7: Ag. DIR. TRAINING & IC | D7: 16(9) | E7: 762373.17 | H7: =80000+10000 -> 90000 | J7: =E7+F7+G7+H7+I7 -> 852373.17 | L7: =0 -> 0 | M7: 0 | N7: 1066.3293 | O7: 130407.53 | P7: 60989.853 | Q7: =O7+N7+M7+L7+K7+P7 -> 192463.71 | R7: 659909.46 | S7: =J7-Q7 -> 659909.46
A8: 1 | B8: AKINSANMI ADEJOKE OLUKEMI | C8: Ag. DIR. TRAINING & IC | D8: 17(7) | E8: ='[3]Annual & Monthly'!$H$44 -> 1352042.7 | H8: =100000 -> 100000 | I8: 0 | J8: =SUM(E8:I8) -> 1452042.7 | N8: 1066.3293 | O8: ='March New PAYE '!Z93 -> 236486.75 | P8: 114857.6 | Q8: =O8+N8+M8+L8+K8+P8 -> 352410.68 | R8: 659909.46 | S8: =J8-Q8 -> 1099632 | T8: =R8-S8 -> -439722.53
B9: DIFFERENCE | C9: =#REF!+#REF!+#REF!+#REF!+#REF!+#REF!+#REF!+#REF!+#REF!+#REF!+#REF! -> #REF! | E9: =E8-E7 -> 589669.5 | F9: =F8-F7 -> 0 | G9: =G8-G7 -> 0 | H9: =H8-H7 -> 10000 | I9: =I8-I7 -> 0 | J9: =J8-J7 -> 599669.5 | K9: =K8-K7 -> 0 | L9: =L8-L7 -> 0 | ... S9: =S8-S7 -> 439722.53

Sheet New NHF Deduction
A1: NATIONAL INSTITUTE FOR LEGISLATIVE AND DEMOCRATIC STUDIES
A2: COMPUTATION OF 2.5% EMPLOYEE NATIONAL HOUSING FUND (NHF)
B5: STAFF NAME | C5: DESIGNATION | D5: GRADE LEVEL | E5: ANNUAL SALARY | F5: MONTHLY SALARY | G5: EMPLOYEE NHF @ 2.5% | H5: OLD EMPLOYEE NHF | I5: DIFFERENCE
E6: N | F6: N | G6: N | H6: N | I6: N
A7: S/N | B7: DG'S OFFICE
A8: 1 | B8: PROF. ABUBAKAR O. SULAIMAN | C8: DIRECTOR GENERAL | D8: CONSOL | F8: =E8/12 -> 0 | G8: =E8*0.025 -> 0 | I8: =G8-H8 -> 0
A9: 2 | B9: RAHEEM USMAN AYIGORO | C9: SA-INFRASTRUCTURE | D9: 16 (9) | F9: =E9/12 -> 0 | G9: =E9*0.025 -> 0 | I9: =G9-H9 -> 0
A10: 3 | B10: MARIAM MOHAMMED BELLO | C10: SA- SPECIAL DUTIES | D10: 16 (9) | F10: =E10/12 -> 0 | G10: =E10*0.025 -> 0 | I10: =G10-H10 -> 0
A11: 4 | B11: DR IKEME ARTHUR J.O | C11: DEPUTY DIRECTOR, M&E | D11: 16 (9) | E11: ='[6]NASS New Structure'!$J$20 -> 4940831 | F11: =E11/12 -> 411735.92 | G11: =F11*0.025 -> 10293.398 | H11: 1066.3293 | I11: =G11-H11 -> 9227.0687
A12: 5 | B12: MOSHOOD M. OLALERE | C12: PPS TO DG | D12: 16 (9) | E12: ='[6]NASS New Structure'!$J$20 -> 4940831 | F12: =E12/12 -> 411735.92 | G12: =F12*0.025 -> 10293.398 | H12: 1066.3293 | I12: =G12-H12 -> 9227.0687
A13: 6 | B13: REKIYA IBRAHIM ATTAH | C13: DEPUTY DIRECTOR TRAINING | D13: 16 (9) | F13: =E13/12 -> 0 | G13: =F13*0.025 -> 0 | I13: =G13-H13 -> 0
A14: 7 | B14: ANDRAWUS MUSA | C14: ASST. DIRECTOR, STORES | D14: 15(9) | E14: ='[6]NASS New Structure'!$J$19 -> 4022509 | F14: =E14/12 -> 335209.08 | G14: =F14*0.025 -> 8380.2271 | H14: 837.6875 | I14: =G14-H14 -> 7542.5396
A15: 8 | B15: DR FRANCIS NDUM OJIE | C15: AD, TRAINING & IC./SA TO DG | D15: 15(7) | E15: ='[6]NASS New Structure'!$H$19 -> 3772623 | F15: =E15/12 -> 314385.25 | G15: =F15*0.025 -> 7859.6313 | H15: 775.496 | I15: =G15-H15 -> 7084.1353
A16: 9 | B16: ALI ABDULLAHI | C16: CHIEF ICT OFFICER | D16: 14(11) | F16: =E16/12 -> 0 | G16: =E16*0.025 -> 0 | I16: =G16-H16 -> 0
A17: 10 | B17: EMILY EKHIDE | C17: RESEARCH FELLOW 1 | D17: 14(10) | F17: =E17/12 -> 0 | G17: =E17*0.025 -> 0 | I17: =G17-H17 -> 0
A18: 11 | B18: DORIS DAKDA AARON | C18: RESEARCH FELLOW I | D18: 14(8) | F18: =E18/12 -> 0 | G18: =E18*0.025 -> 0 | I18: =G18-H18 -> 0
A19: 12 | B19: ABDULSALAM S. MUSTAPHA | C19: ASST. MANAGER ICT | D19: 13(11) | F19: =E19/12 -> 0 | G19: =E19*0.025 -> 0 | I19: =G19-H19 -> 0
A20: 13 | B20: PERCY TERFA GBAHABO | C20: HEAD, NILDS LIAISON OFFICE | D20: 13(10) | F20: =E20/12 -> 0 | G20: =E20*0.025 -> 0 | I20: =G20-H20 -> 0
A21: 14 | B21: HASSANA AHMED IBRAHIM | C21: PA- TRAINING | D21: 13 (9) | E21: ='[6]NASS New Structure'!$J$17 -> 2691445 | F21: =E21/12 -> 224287.08 | G21: =F21*0.025 -> 5607.1771 | H21: 618.5315 | I21: =G21-H21 -> 4988.6456
A22: 15 | B22: ADUGBA RICHARD TERSEER | C22: PRINCIPAL INFO. OFFICER | D22: 12(9) | F22: =E22/12 -> 0 | G22: =E22*0.025 -> 0 | I22: =G22-H22 -> 0
A23: 16 | B23: LUCKY AGWOM | C23: PA-TECHNICAL | D23: 12(7) | F23: =E23/12 -> 0 | G23: =E23*0.025 -> 0 | I23: =G23-H23 -> 0
A24: 17 | B24: IDRIS IBRAHIM | C24: PRINCIPAL RESEARCH OFFICER | D24: 12(7) | F24: =E24/12 -> 0 | G24: =E24*0.025 -> 0 | I24: =G24-H24 -> 0
A25: 18 | B25: FARUQ ATOFARATI | C25: PA (SPECIAL DUTIES) TO DG | D25: 10(7) | F25: =E25/12 -> 0 | G25: =E25*0.025 -> 0 | I25: =G25-H25 -> 0
A26: 19 | B26: ELIZABETH OGECHUKWU ONYEAKU | C26: ICT OFFICER | D26: 9(9) | F26: =E26/12 -> 0 | G26: =E26*0.025 -> 0 | I26: =G26-H26 -> 0
A27: 20 | B27: VICTOR ASUKWO | C27: ICT OFFICER | D27: 9(9) | F27: =E27/12 -> 0 | G27: =E27*0.025 -> 0 | I27: =G27-H27 -> 0
A28: 21 | B28: NNANDI LIVINUS ATURE | C28: RESEARCH ASSISTANT | D28: 9(9) | F28: =E28/12 -> 0 | G28: =E28*0.025 -> 0 | I28: =G28-H28 -> 0
A29: 22 | B29: ABDULRAHMAN A SULAIMAN | C29: STORE OFFICER | D29: 9(8) | F29: =E29/12 -> 0 | G29: =E29*0.025 -> 0 | I29: =G29-H29 -> 0
A30: 23 | B30: DARE SHEU MAGBON | C30: ADMINISTRATION OFFICER | D30: 9(7) | F30: =E30/12 -> 0 | G30: =E30*0.025 -> 0 | I30: =G30-H30 -> 0
A31: 24 | B31: ABUBAKAR SULAIMAN SODEEQ | C31: ADMINISTRATION OFFICER | D31: 9(7) | F31: =E31/12 -> 0 | G31: =E31*0.025 -> 0 | I31: =G31-H31 -> 0
A32: 25 | B32: JIMOH ADEBAYO ZAKA | C32: ASST. OFFICER/COMM | D32: 9(9) | E32: ='[7]NASS New Structure'!$J$14 -> 1753681 | F32: =E32/12 -> 146140.08 | G32: =F32*0.025 -> 3653.5021 | I32: =G32-H32 -> 3653.5021
A33: 26 | B33: MOHAMMED BELLO | C33: PROTOCOL ASSISTANT | D33: 8(9) | F33: =E33/12 -> 0 | G33: =E33*0.025 -> 0 | I33: =G33-H33 -> 0
A34: 27 | B34: HARUNA JIBRIL AMEH | C34: ASST. ADMIN. OFFICER | D34: 8(8) | F34: =E34/12 -> 0 | G34: =E34*0.025 -> 0 | I34: =G34-H34 -> 0
B35: TOTAL | C35: 27 | E35: =SUM(E8:E34) -> 22121920 | F35: =SUM(F8:F34) -> 1843493.3 | G35: =SUM(G8:G34) -> 46087.333 | H35: =SUM(H8:H34) -> 4364.3735 | I35: =SUM(I8:I34) -> 41722.96
B37: INTERNAL AUDIT
A38: 1 | B38: OSANAIYE DAVID AKINYEMI | C38: DIRECTOR INTERNAL AUDIT | D38: 17(9) | G38: =E38*0.025 -> 0 | H38: =F38*0.025 -> 0 | I38: =G38*0.025 -> 0
A39: 2 | B39: JAMILA ABDUL | C39: SENIOR INTERNAL AUDITOR | D39: 10(7) | G39: =E39*0.025 -> 0 | H39: =F39*0.025 -> 0 | I39: =G39*0.025 -> 0
A40: 3 | B40: IJEOMA EWELUKWA | C40: AUDIT OFFICER | D40: 10(8) | G40: =E40*0.025 -> 0 | H40: =F40*0.025 -> 0 | I40: =G40*0.025 -> 0
C41: 3 | E41: =SUM(E38:E40) -> 0 | G41: =SUM(G38:G40) -> 0 | H41: =SUM(H38:H40) -> 0 | I41: =SUM(I38:I40) -> 0
B43: LEG. SUPPORT SEVICES
A44: 1 | B44: PROF. EDOBA BRIGHT OMOREGBE | C44: AG. DLSS | D44: 17(9) | G44: =E44*0.025 -> 0 | I44: =G44*0.025 -> 0
A45: 2 | B45: DR CLINTON JAJA | C45: SENIOR RESEARCH FELLOW | D45: 15(9) | G45: =E45*0.025 -> 0 | I45: =G45*0.025 -> 0
A46: 3 | B46: BETHEL UZOMA IHUGBA | C46: DEPUTY DIRECTOR, LEGAL RESEARCH | D46: 16(8) | G46: =E46*0.025 -> 0 | I46: =G46*0.025 -> 0
A47: 4 | B47: OGUCHE SAMUEL | C47: SNR RESEARCH FELLOW | D47: 15(9) | G47: =E47*0.025 -> 0 | I47: =G47*0.025 -> 0
A48: 5 | B48: IBRAHIM USMAN | C48: SNR RESEARCH FELLOW | D48: 15(9) | E48: ='[6]NASS New Structure'!$J$19 -> 4022509 | F48: =E48/12 -> 335209.08 | G48: =F48*0.025 -> 8380.2271 | H48: 837.6875 | I48: =G48-H48 -> 7542.5396
A49: 6 | B49: DR MOHAMMED O. AMALI | C49: SNR RESEARCH FELLOW | D49: 15(7) | G49: =E49*0.025 -> 0 | I49: =G49*0.025 -> 0
A50: 7 | B50: YAHAYA SHAMSU | C50: RESEARCH FELLOW 1 | D50: 14(10) | G50: =E50*0.025 -> 0 | H50: 0 | I50: =G50*0.025 -> 0
A51: 8 | B51: BILKIS S. LAWAL-GAMBARI | C51: RESEARCH OFFICER | D51: 10(8) | G51: =E51*0.025 -> 0 | I51: =G51*0.025 -> 0
A52: 9 | B52: ZAINAB AKINDE | C52: RESEARCH OFFICER | D52: 9(8) | G52: =E52*0.025 -> 0 | I52: =G52*0.025 -> 0
A53: 10 | B53: ABDULLAHI AHMAD USMAN | C53: RESEARCH OFFICER | D53: 9(8) | G53: =E53*0.025 -> 0 | I53: =G53*0.025 -> 0
A54: 11 | B54: GUNAT NANSAK MARK | C54: RESEARCH OFFICER | D54: 9(8) | G54: =E54*0.025 -> 0 | I54: =G54*0.025 -> 0
B55: TOTAL | C55: 11 | E55: =SUM(E44:E54) -> 4022509 | F55: =SUM(F44:F54) -> 335209.08 | G55: =SUM(G44:G54) -> 8380.2271 | H55: =SUM(H44:H54) -> 837.6875 | I55: =SUM(I44:I54) -> 7542.5396
B57: LEGAL SERVICES
A58: 1 | B58: DR SHUIBU DANWANKA | C58: DIRECTOR LEGAL SERVICES | D58: 17(9) | G58: =E58*0.025 -> 0 | H58: =F58*0.025 -> 0 | I58: =G58*0.025 -> 0
A59: 2 | B59: ABDULSALAM BAKO | C59: MANAGER, LEGAL SERVICES | D59: 15 (9) | G59: =E59*0.025 -> 0 | H59: =F59*0.025 -> 0 | I59: =G59*0.025 -> 0
B60: TOTAL | C60: 2 | E60: =SUM(E58:E59) -> 0 | G60: =SUM(G58:G59) -> 0 | H60: =SUM(H58:H59) -> 0 | I60: =SUM(I58:I59) -> 0
B62: DEMOCRACY & GOVERNANCE
A63: 1 | B63: DR. ADEWALE ADEREMI | C63: DIRECTOR, DEMOCRATIC STUDIES | D63: 17(9) | G63: =E63*0.025 -> 0 | H63: =F63*0.025 -> 0 | I63: =G63*0.025 -> 0
A64: 2 | B64: NDANUSA MOHAMMED MANZUMA | C64: SNR RESEARCH FELLOW | D64: 15(8) | G64: =E64*0.025 -> 0 | H64: =F64*0.025 -> 0 | I64: =G64*0.025 -> 0
A65: 3 | B65: EJALONIBU GANIYU LAYI | C65: RESEARCH FELLOW 1 | D65: 14(8) | G65: =E65*0.025 -> 0 | H65: =F65*0.025 -> 0 | I65: =G65*0.025 -> 0
A66: 4 | B66: LOHNA BONKAT JONATHAN | C66: RESEARCH FELLOW 11 | D66: 13(10) | G66: =E66*0.025 -> 0 | H66: =F66*0.025 -> 0 | I66: =G66*0.025 -> 0
A67: 5 | B67: YUNUSA ABDULLAHI | C67: RESEARCH FELLOW 1 | D67: 14(11) | G67: =E67*0.025 -> 0 | H67: =F67*0.025 -> 0 | I67: =G67*0.025 -> 0
A68: 7 | B68: UDEFUNA NNADOZIE PATRICK | C68: RESEARCH OFFICER | D68: 12(8) | G68: =E68*0.025 -> 0 | H68: =F68*0.025 -> 0 | I68: =G68*0.025 -> 0
A69: 8 | B69: SHAFIU YAHYA MIKAIL | C69: PRINCIPAL RESEARCH OFFICER | D69: 12(8) | G69: =E69*0.025 -> 0 | H69: =F69*0.025 -> 0 | I69: =G69*0.025 -> 0
A70: 9 | B70: HASSAN YERIMA | C70: PRINCIPAL RESEARCH OFFICER | D70: 12(8) | G70: =E70*0.025 -> 0 | H70: =F70*0.025 -> 0 | I70: =G70*0.025 -> 0
A71: 10 | B71: HAUWA PATE SADIQ | C71: PRINCIPAL PROGRAMME OFFICER | D71: 12(9) | G71: =E71*0.025 -> 0 | H71: =F71*0.025 -> 0 | I71: =G71*0.025 -> 0
A72: 11 | B72: KOLAPO Q. ABAYOMI | C72: RESEARCH OFFICER | D72: 10(8) | G72: =E72*0.025 -> 0 | H72: =F72*0.025 -> 0 | I72: =G72*0.025 -> 0
B73: TOTAL | C73: 12 | E73: =SUM(E63:E72) -> 0 | G73: =SUM(G63:G72) -> 0 | H73: =SUM(H63:H72) -> 0 | I73: =SUM(I63:I72) -> 0
B75: DEPARTMENT OF STUDIES
A76: 1 | B76: DR ASIMIYU G. ABIOLA | C76: DIRECTOR POST GRADUATE | D76: 17(9) | G76: =E76*0.025 -> 0 | H76: =F76*0.025 -> 0 | I76: =G76*0.025 -> 0
A77: 2 | B77: USMAN WALI | C77: SENIOR RESEARCH FELLOW | D77: 15 (8) | G77: =E77*0.025 -> 0 | H77: =F77*0.025 -> 0 | I77: =G77*0.025 -> 0
A78: 3 | B78: AYOBOLU OLAJIDE OLUFUNSHO | C78: ASST.DIR., INFORMATION | D78: 15 (9) | G78: =E78*0.025 -> 0 | H78: =F78*0.025 -> 0 | I78: =G78*0.025 -> 0
A79: 4 | B79: ANTHONY EDET | C79: CHIEF PROGRAMMES OFFICER | D79: 14(9) | E79: ='[6]NASS New Structure'!$J$18 -> 2954075 | F79: =E79/12 -> 246172.92 | G79: =F79*0.025 -> 6154.3229 | H79: 668.31625 | I79: =G79-H79 -> 5486.0067
A80: 5 | B80: IGWE STACY | C80: PROGRAMME OFFICER | D80: 10(9) | G80: =E80*0.025 -> 0 | H80: =F80*0.025 -> 0 | I80: =G80*0.025 -> 0
A81: 6 | B81: OLANIYAN TAIWO ABINBOLA | C81: PROGRAMME OFFICER | D81: 9(8) | G81: =E81*0.025 -> 0 | H81: =F81*0.025 -> 0 | I81: =G81*0.025 -> 0
A82: 7 | B82: AMINAT JUMOKE SULAIMON | C82: AST. PROGRAMME OFFICER | D82: 8(8) | G82: =E82*0.025 -> 0 | H82: =F82*0.025 -> 0 | I82: =G82*0.025 -> 0
B83: TOTAL | C83: 7 | E83: =SUM(E76:E82) -> 2954075 | F83: =SUM(F76:F82) -> 246172.92 | G83: =SUM(G76:G82) -> 6154.3229 | H83: =SUM(H76:H82) -> 668.31625 | I83: =SUM(I76:I82) -> 5486.0067
B85: ECON. DEV. & SOC. RESEARCH
A86: 1 | B86: TERFA WILLIAMS ABRAHAM | C86: SNR RESEARCH FELLOW | D86: 15(9) | G86: =E86*0.025 -> 0 | I86: =G86*0.025 -> 0
A87: 2 | B87: DR AUGUSTINE C. OSIGWE | C87: SNR RESEARCH FELLOW | D87: 15(9) | E87: ='[6]NASS New Structure'!$J$19 -> 4022509 | F87: =E87/12 -> 335209.08 | G87: =F87*0.025 -> 8380.2271 | H87: 837.6875 | I87: =G87-H87 -> 7542.5396
A88: 3 | B88: OMOJU OLUWASOLA EMMANUEL | C88: SNR RESEARCH FELLOW | D88: 15(7) | G88: =E88*0.025 -> 0 | I88: =G88*0.025 -> 0
A89: 4 | B89: IBE EZECHI CYRIACUS | C89: RESEARCH FELLOW II | D89: 13(11) | G89: =E89*0.025 -> 0 | I89: =G89*0.025 -> 0
A90: 5 | B90: OSIKHEN LEO IGBANOI | C90: RESEARCH FELLOW 11 | D90: 13(10) | G90: =E90*0.025 -> 0 | I90: =G90*0.025 -> 0
A91: 6 | B91: OKUNGBOWA OSARETIN GODSPOWER | C91: RESEARCH FELLOW 1 | D91: 14(7) | G91: =E91*0.025 -> 0 | I91: =G91*0.025 -> 0
A92: 7 | B92: YUSUF IBRAHIM | C92: PRINCIPAL RESEARCH OFFICER | D92: 12(8) | G92: =E92*0.025 -> 0 | I92: =G92*0.025 -> 0
A93: 8 | B93: MUSTAPHA RAFIU AYOBANJI | C93: RESEARCH FELLOW 11 | D93: 13(7) | E93: ='[6]NASS New Structure'!$H$17 -> 2524677 | F93: =E93/12 -> 210389.75 | G93: =F93*0.025 -> 5259.7438 | H93: 576.87475 | I93: =G93-H93 -> 4682.869
A94: 9 | B94: MARYAM MUSA SADA | C94: ASSIT. RESEARCH OFFICER | D94: 10(8) | G94: =E94*0.025 -> 0 | I94: =G94*0.025 -> 0
A95: 10 | B95: CHARITY EZENWAJIOBI | C95: REASEARCH. ASST. | D95: 8(9) | G95: =E95*0.025 -> 0 | H95: 0 | I95: =G95*0.025 -> 0
B96: TOTAL | C96: 11 | E96: =SUM(E86:E95) -> 6547186 | F96: =SUM(F86:F95) -> 545598.83 | G96: =SUM(G86:G95) -> 13639.971 | H96: =SUM(H86:H95) -> 1414.5622 | I96: =SUM(I86:I95) -> 12225.409
B98: TRAINING & INT''L COOP
A99: 1 | B99: AKINSANMI ADEJOKE OLUKEMI | C99: Ag. DIR. TRAINING & IC | D99: 16(9) | E99: ='[6]NASS New Structure'!$H$21 -> 8762388 | F99: =E99/12 -> 730199 | G99: =F99*0.025 -> 18254.975 | H99: =H12 -> 1066.3293 | I99: =G99-H99 -> 17188.646
A100: 2 | B100: MOHAMMED R. ADAMU | C100: CHIEF TRAINING OFFICER | D100: 14(9) | G100: =E100*0.025 -> 0 | H100: =F100*0.025 -> 0 | I100: =G100*0.025 -> 0
A101: 3 | B101: OKECHUKWU UCHENNA HULDA | C101: PRINCIPALTRAINING OFFICER | D101: 12(9) | G101: =E101*0.025 -> 0 | H101: =F101*0.025 -> 0 | I101: =G101*0.025 -> 0
A102: 4 | B102: TASSNEEM IBRAHIM | C102: SENIOR PROGRAMME OFFICER | D102: 10(8) | G102: =E102*0.025 -> 0 | H102: =F102*0.025 -> 0 | I102: =G102*0.025 -> 0
B103: TOTAL | C103: 4 | E103: =SUM(E99:E102) -> 8762388 | F103: =SUM(F99:F102) -> 730199 | G103: =SUM(G99:G102) -> 18254.975 | H103: =SUM(H99:H102) -> 1066.3293 | I103: =SUM(I99:I102) -> 17188.646
B105: LIBRARY & DOCUMENTATION
A106: 1 | B106: DR MAIMUNA IZAH | C106: INSITUTE LIBRARIAN | D106: 17(9) | G106: =E106*0.08 -> 0 | H106: =F106*0.08 -> 0 | I106: =G106*0.08 -> 0
A107: 2 | B107: CATHERINE E. IKOKOH | C107: SNR RESEARCH FELLOW DOCU | D107: 16(9) | E107: ='[6]NASS New Structure'!$J$20 -> 4940831 | F107: =E107/12 -> 411735.92 | G107: =F107*0.025 -> 10293.398 | H107: 1066.3293 | I107: =G107-H107 -> 9227.0687
A108: 3 | B108: ALIYU SANNI ABUBAKAR | C108: RESEARCH FELLOW 11 DATA & DOCU | D108: 13(11) | E108: ='[6]NASS New Structure'!$L$17 -> 2858213 | F108: =E108/12 -> 238184.42 | G108: =F108*0.025 -> 5954.6104 | H108: 658.4825 | I108: =G108-H108 -> 5296.1279
A109: 4 | B109: CHINAKO N. ASOGWA | C109: RESEARCH FELLOW 11 DATA & DOCU | D109: 13(11) | G109: =E109*0.08 -> 0 | H109: =F109*0.08 -> 0 | I109: =G109*0.08 -> 0
A110: 5 | B110: AMOS ABA | C110: LIBRARY ASSISTANT | D110: 8(12) | G110: =E110*0.08 -> 0 | H110: =F110*0.08 -> 0 | I110: =G110*0.08 -> 0
...

Sheet Regularisation
D1: Gross | E1: PAYE
A2: HARUNA JIBRIL AMEH | B2: ASST. ADMIN. OFFICER | C2: 8(7) | D2: ='[5]JANUARY 2024'!$R$33 -> 173329.05 | E2: ='[5]JANUARY 2024'!$W$33 -> 16512.682
A3: HARUNA JIBRIL AMEH | B3: ASST. ADMIN. OFFICER | C3: 8(8) | D3: ='[5]JANUARY 2024'!$R$38 -> 176816.1 | E3: ='[5]JANUARY 2024'!$W$38 -> 17042.714
A4: Difference | D4: =D3-D2 -> 3487.0505 | E4: =E3-E2 -> 530.03168 | F4: =D4-E4 -> 2957.0188

Sheet Sallah Welfare, April 2024
A1: NATIONAL INSTITUTE FOR LEGISLATIVE AND DEMOCRATIC STUDIES
A2: STAFF SALLAH WELFARE APRIL 2024
E3: ='[1]FEB 08'!E11/'[1]FEB 08'!M11 -> #REF!
B4: STAFF NAME | C4: DESIGNATION | D4: GRADE LEVEL | E4: AMOUNT
E5: N
A6: S/N | B6: DG'S OFFICE
A7: 1 | B7: PROF. ABUBAKAR O. SULAIMAN | C7: DIRECTOR GENERAL | D7: CONSOL | E7: 540000
A8: 2 | B8: RAHEEM USMAN AYIGORO | C8: SA-INFRASTRUCTURE | D8: 16 (9) | E8: 180000
A9: 3 | B9: MARIAM MOHAMMED BELLO | C9: SA- SPECIAL DUTIES | D9: 16 (9) | E9: 180000
A10: 4 | B10: DR IKEME ARTHUR J.O | C10: DEPUTY DIRECTOR, M&E | D10: 16 (9) | E10: 180000
A11: 5 | B11: MOSHOOD M. OLALERE | C11: DEPUTY DIR. GENERAL SERVICE | D11: 16 (9) | E11: 180000
A12: 6 | B12: REKIYA IBRAHIM ATTAH | C12: DEPUTY DIRECTOR TRAINING | D12: 16 (9) | E12: 180000
A13: 7 | B13: ANDRAWUS MUSA | C13: ASST. DIRECTOR, STORES | D13: 15(9) | E13: 126000
A14: 8 | B14: DR FRANCIS NDUM OJIE | C14: AD, TRAINING & IC./SA TO DG | D14: 15(7) | E14: 126000
A15: 9 | B15: ALI ABDULLAHI | C15: CHIEF ICT OFFICER | D15: 14(11) | E15: 90000
A16: 10 | B16: EMILY EKHIDE | C16: RESEARCH FELLOW 1 | D16: 14(10) | E16: 90000
A17: 11 | B17: DORIS DAKDA AARON | C17: RESEARCH FELLOW I | D17: 14(8) | E17: 90000
A18: 12 | B18: ABDULSALAM S. MUSTAPHA | C18: ASST. MANAGER ICT | D18: 13(11) | E18: 90000
... A33: 27 | B33: HARUNA JIBRIL AMEH | C33: ASST. ADMIN. OFFICER | D33: 8(8) | E33: 54000
B34: TOTAL | C34: 27 | E34: =SUM(E7:E33) -> 2990000
B36: INTERNAL AUDIT
A37: 1 | B37: OSANAIYE DAVID AKINYEMI | C37: DIRECTOR INTERNAL AUDIT | D37: 17(9) | E37: 270000
A38: 2 | B38: JAMILA ABDUL | C38: AUDITOR II | D38: 10(7) | E38: 68000
A39: 3 | B39: IJEOMA EWELUKWA | C39: AUDIT OFFICER | D39: 10(8) | E39: 68000
C40: 3 | E40: =SUM(E37:E39) -> 406000
B42: LEG. SUPPORT SEVICES
A43: 1 | B43: PROF. EDOBA BRIGHT OMOREGBE | C43: AG. DLSS | D43: 17(9) | E43: 270000
A44: 2 | B44: DR CLINTON JAJA | C44: SENIOR RESEARCH FELLOW | D44: 15(9) | E44: 126000
A45: 3 | B45: BETHEL UZOMA IHUGBA | C45: DEPUTY DIRECTOR, LEGAL RESEARCH | D45: 16(8) | E45: 180000
A46: 4 | B46: OGUCHE SAMUEL | C46: SNR RESEARCH FELLOW | D46: 15(9) | E46: 126000
A47: 5 | B47: IBRAHIM USMAN | C47: SNR RESEARCH FELLOW | D47: 15(9) | E47: 126000
A48: 6 | B48: DR MOHAMMED O. AMALI | C48: SNR RESEARCH FELLOW | D48: 15(7) | E48: 126000
A49: 7 | B49: YAHAYA SHAMSU | C49: RESEARCH FELLOW 1 | D49: 14(10) | E49: 90000
A50: 8 | B50: BILKIS S. LAWAL-GAMBARI | C50: RESEARCH OFFICER | D50: 10(8) | E50: 68000
A51: 9 | B51: ZAINAB AKINDE | C51: RESEARCH OFFICER | D51: 9(8) | E51: 54000
A52: 10 | B52: ABDULLAHI AHMAD USMAN | C52: RESEARCH OFFICER | D52: 9(8) | E52: 54000
A53: 11 | B53: GUNAT NANSAK MARK | C53: RESEARCH OFFICER | D53: 9(8) | E53: 54000
